Workbook

Sheet Curr
C1: NOK
B2: EUR | C2: 10.8
B3: SEK | C3: 1.02
B4: DKK | C4: 1.5
B5: ISK | C5: 0.075
B6: NOK | C6: 1
B7: USD | C7: 10.6

Sheet Kalk
B2: Dates: 27.06.2026
B3: Pax: 4
B4: Rooming: 2 x double
B6: ID | C6: Day | D6: Type | E6: From date | F6: To date | G6: From time | H6: To time | I6: Supplier | J6: Travel element | K6: Manual booking? | L6: Status | M6: Comments | N6: Non-refundable | O6: Refundable | P6: URL | Q6: Gross P per unit | R6: Units | S6: Gross P | T6: Supp Comm | U6: Net P | V6: Supp curr | W6: X-rate | X6: Net P NOK | Y6: Sales P per unit | Z6: Price | AA6: Sales curr | AB6: X-rate | AC6: Sales P NOK tot | AD6: GP NOK | AE6: GP % | AF6: VAT25 | AG6: VAT15 | AH6: VAT12 | AI6: VAT0-D | AJ6: VAT0-I
C7: Day 1 | D7: Arrival | E7: 27.06.2026 | J7: Keflavik: Welcome to Iceland | Q7: 0 | R7: 0 | S7: =+Q7*R7 -> 0 | T7: 0 | U7: =S7*(1-T7) -> 0 | V7: EUR | W7: =IFERROR(VLOOKUP(V7,Curr!$B$2:$C$13,2,FALSE),0) -> 10.8 | X7: =U7*W7 -> 0 | Y7: =Q7 -> 0 | Z7: =+Y7*R7 -> 0 | AA7: EUR | AB7: =IFERROR(VLOOKUP(AA7,Curr!$B$2:$C$13,2,FALSE),0) -> 10.8 | AC7: =+Y7*AB7*R7 -> 0 | AD7: =+AC7-X7 -> 0 | AE7: =IFERROR(AD7/AC7,0) -> 0
C8: Day 1 | D8: Car | E8: 27.06.2026 | J8: Keflavik: Pick up your rental car at Keflavik Airport Car rental office | Q8: 0 | R8: 0 | S8: =+Q8*R8 -> 0 | T8: 0 | U8: =S8*(1-T8) -> 0 | V8: EUR | W8: =IFERROR(VLOOKUP(V8,Curr!$B$2:$C$13,2,FALSE),0) -> 10.8 | X8: =U8*W8 -> 0 | Y8: =Q8 -> 0 | Z8: =+Y8*R8 -> 0 | AA8: EUR | AB8: =IFERROR(VLOOKUP(AA8,Curr!$B$2:$C$13,2,FALSE),0) -> 10.8 | AC8: =+Y8*AB8*R8 -> 0 | AD8: =+AC8-X8 -> 0 | AE8: =IFERROR(AD8/AC8,0) -> 0
C9: Day 1 | D9: Drive | E9: 27.06.2026 | J9: Keflavik: Drive to your accommodaiton | Q9: 0 | R9: 0 | S9: =+Q9*R9 -> 0 | T9: 0 | U9: =S9*(1-T9) -> 0 | V9: EUR | W9: =IFERROR(VLOOKUP(V9,Curr!$B$2:$C$13,2,FALSE),0) -> 10.8 | X9: =U9*W9 -> 0 | Y9: =Q9 -> 0 | Z9: =+Y9*R9 -> 0 | AA9: EUR | AB9: =IFERROR(VLOOKUP(AA9,Curr!$B$2:$C$13,2,FALSE),0) -> 10.8 | AC9: =+Y9*AB9*R9 -> 0 | AD9: =+AC9-X9 -> 0 | AE9: =IFERROR(AD9/AC9,0) -> 0
C10: Day 1 | D10: Hotel | E10: 27.06.2026 | F10: 29.06.2026 | J10: Vik: Check in to your accommodation for a 2 night stay - - 2 x double room - breakfast included | Q10: 0 | R10: 0 | S10: =+Q10*R10 -> 0 | T10: 0 | U10: =S10*(1-T10) -> 0 | V10: EUR | W10: =IFERROR(VLOOKUP(V10,Curr!$B$2:$C$13,2,FALSE),0) -> 10.8 | X10: =U10*W10 -> 0 | Y10: =Q10 -> 0 | Z10: =+Y10*R10 -> 0 | AA10: EUR | AB10: =IFERROR(VLOOKUP(AA10,Curr!$B$2:$C$13,2,FALSE),0) -> 10.8 | AC10: =+Y10*AB10*R10 -> 0 | AD10: =+AC10-X10 -> 0 | AE10: =IFERROR(AD10/AC10,0) -> 0
C11: Day 1 | D11: Leisure | E11: 27.06.2026 | J11: Vik: Spend time at leisure | Q11: 0 | R11: 0 | S11: =+Q11*R11 -> 0 | T11: 0 | U11: =S11*(1-T11) -> 0 | V11: EUR | W11: =IFERROR(VLOOKUP(V11,Curr!$B$2:$C$13,2,FALSE),0) -> 10.8 | X11: =U11*W11 -> 0 | Y11: =Q11 -> 0 | Z11: =+Y11*R11 -> 0 | AA11: EUR | AB11: =IFERROR(VLOOKUP(AA11,Curr!$B$2:$C$13,2,FALSE),0) -> 10.8 | AC11: =+Y11*AB11*R11 -> 0 | AD11: =+AC11-X11 -> 0 | AE11: =IFERROR(AD11/AC11,0) -> 0
S12: =+Q12*R12 -> 0 | T12: 0 | U12: =S12*(1-T12) -> 0 | V12: EUR | W12: =IFERROR(VLOOKUP(V12,Curr!$B$2:$C$13,2,FALSE),0) -> 10.8 | X12: =U12*W12 -> 0 | Y12: =Q12 -> 0 | Z12: =+Y12*R12 -> 0 | AA12: EUR | AB12: =IFERROR(VLOOKUP(AA12,Curr!$B$2:$C$13,2,FALSE),0) -> 10.8 | AC12: =+Y12*AB12*R12 -> 0 | AD12: =+AC12-X12 -> 0 | AE12: =IFERROR(AD12/AC12,0) -> 0
C13: Day 2 | D13: Activity | E13: 28.06.2026 | J13: Lava | Q13: 0 | R13: 0 | S13: =+Q13*R13 -> 0 | T13: 0 | U13: =S13*(1-T13) -> 0 | V13: EUR | W13: =IFERROR(VLOOKUP(V13,Curr!$B$2:$C$13,2,FALSE),0) -> 10.8 | X13: =U13*W13 -> 0 | Y13: =Q13 -> 0 | Z13: =+Y13*R13 -> 0 | AA13: EUR | AB13: =IFERROR(VLOOKUP(AA13,Curr!$B$2:$C$13,2,FALSE),0) -> 10.8 | AC13: =+Y13*AB13*R13 -> 0 | AD13: =+AC13-X13 -> 0 | AE13: =IFERROR(AD13/AC13,0) -> 0
C14: Day 2 | D14: Leisure | E14: 28.06.2026 | J14: Vik: Spend time at leisure | Q14: 0 | R14: 0 | S14: =+Q14*R14 -> 0 | T14: 0 | U14: =S14*(1-T14) -> 0 | V14: EUR | W14: =IFERROR(VLOOKUP(V14,Curr!$B$2:$C$13,2,FALSE),0) -> 10.8 | X14: =U14*W14 -> 0 | Y14: =Q14 -> 0 | Z14: =+Y14*R14 -> 0 | AA14: EUR | AB14: =IFERROR(VLOOKUP(AA14,Curr!$B$2:$C$13,2,FALSE),0) -> 10.8 | AC14: =+Y14*AB14*R14 -> 0 | AD14: =+AC14-X14 -> 0 | AE14: =IFERROR(AD14/AC14,0) -> 0
C15: Day 2 | D15: Activity | E15: 28.06.2026 | J15: Ice Cave | Q15: 0 | R15: 0 | S15: =+Q15*R15 -> 0 | T15: 0 | U15: =S15*(1-T15) -> 0 | V15: EUR | W15: =IFERROR(VLOOKUP(V15,Curr!$B$2:$C$13,2,FALSE),0) -> 10.8 | X15: =U15*W15 -> 0 | Y15: =Q15 -> 0 | Z15: =+Y15*R15 -> 0 | AA15: EUR | AB15: =IFERROR(VLOOKUP(AA15,Curr!$B$2:$C$13,2,FALSE),0) -> 10.8 | AC15: =+Y15*AB15*R15 -> 0 | AD15: =+AC15-X15 -> 0 | AE15: =IFERROR(AD15/AC15,0) -> 0
S16: =+Q16*R16 -> 0 | T16: 0 | U16: =S16*(1-T16) -> 0 | V16: EUR | W16: =IFERROR(VLOOKUP(V16,Curr!$B$2:$C$13,2,FALSE),0) -> 10.8 | X16: =U16*W16 -> 0 | Y16: =Q16 -> 0 | Z16: =+Y16*R16 -> 0 | AA16: EUR | AB16: =IFERROR(VLOOKUP(AA16,Curr!$B$2:$C$13,2,FALSE),0) -> 10.8 | AC16: =+Y16*AB16*R16 -> 0 | AD16: =+AC16-X16 -> 0 | AE16: =IFERROR(AD16/AC16,0) -> 0
C17: Day 3 | D17: Drive | E17: 29.06.2026 | J17: Vik: Drive to Selfoss, then embark on the Golden Circle - Driving time: 4hrs 40 minutes (without stops) - Things to see: Kerið Crater Lake, Fridheimar Tomato Farm, Gullfoss Waterfall, Geysir Hot Spring, Efstidalur Dairy Farm, Öxarárfoss Waterfall, Thingvellir National Park | P17: https://www.google.no/maps/dir/V%C3%ADk+%C3%AD+M%C3%BDrdal,+870,+Island/Keri%C3%B0,+805+Klausturholar,+Island/Fri%C3%B0heimar,+5HH4%2B225,+Fri%C3%B0heimar,+806+Reykholt,+Island/Gullfoss+Waterfall+Lookout,+above,+Gullfoss+Parking,+Island/Geysir+Hot+Springs,+333,+806,+Island/%C3%96xar%C3%A1rfoss,+7V8J%2B8RH,+806+Thingvellir,+Island/Reykjav%C3%ADk,+Island/@64.0776152,-20.5649188,170091m/data=!3m1!1e3!4m44!4m43!1m5!1m1!1s0x48d74a424936b0d1:0xbe83531b006d778d!2m2!1d-18.9974396!2d63.4176505!1m5!1m1!1s0x48d68bb755f6f257:0x515a44e0c12ed907!2m2!1d-20.8851466!2d64.0412785!1m5!1m1!1s0x48d696fbe383f7bb:0xdee6f1f7177295af!2m2!1d-20.4448859!2d64.177503!1m5!1m1!1s0x48d6a5f34f4c88b1:0xd3558f2a84b426ba!2m2!1d-20.1244323!2d64.326181!1m5!1m1!1s0x48d6a3ec33d9dc1f:0xda8b28dafde977e5!2m2!1d-20.299508!2d64.3137795!1m5!1m1!1s0x48d6811eadf0fd95:0x48dd72aa97e36e57!2m2!1d-21.117885!2d64.2658062!1m5!1m1!1s0x48d674b9eedcedc3:0xec912ca230d26071!2m2!1d-21.9407552!2d64.1469868!3e0?entry=ttu&g_ep=EgoyMDI2MDQwNy4wIKXMDSoASAFQAw%3D%3D | Q17: 0 | R17: 0 | S17: =+Q17*R17 -> 0 | T17: 0 | U17: =S17*(1-T17) -> 0 | V17: EUR | W17: =IFERROR(VLOOKUP(V17,Curr!$B$2:$C$13,2,FALSE),0) -> 10.8 | X17: =U17*W17 -> 0 | Y17: =Q17 -> 0 | Z17: =+Y17*R17 -> 0 | AA17: EUR | AB17: =IFERROR(VLOOKUP(AA17,Curr!$B$2:$C$13,2,FALSE),0) -> 10.8 | AC17: =+Y17*AB17*R17 -> 0 | AD17: =+AC17-X17 -> 0 | AE17: =IFERROR(AD17/AC17,0) -> 0
C18: Day 3 | D18: Hotel | E18: 29.06.2026 | F18: 03.07.2026 | J18: Reykjavik: Check in to your accommodation for a 4 night stay - - 2 x double room - breakfast included | Q18: 0 | R18: 0 | S18: =+Q18*R18 -> 0 | T18: 0 | U18: =S18*(1-T18) -> 0 | V18: EUR | W18: =IFERROR(VLOOKUP(V18,Curr!$B$2:$C$13,2,FALSE),0) -> 10.8 | X18: =U18*W18 -> 0 | Y18: =Q18 -> 0 | Z18: =+Y18*R18 -> 0 | AA18: EUR | AB18: =IFERROR(VLOOKUP(AA18,Curr!$B$2:$C$13,2,FALSE),0) -> 10.8 | AC18: =+Y18*AB18*R18 -> 0 | AD18: =+AC18-X18 -> 0 | AE18: =IFERROR(AD18/AC18,0) -> 0
C19: Day 3 | D19: Leisure | E19: 29.06.2026 | J19: Reykjavik: Spend time at leisure | Q19: 0 | R19: 0 | S19: =+Q19*R19 -> 0 | T19: 0 | U19: =S19*(1-T19) -> 0 | V19: EUR | W19: =IFERROR(VLOOKUP(V19,Curr!$B$2:$C$13,2,FALSE),0) -> 10.8 | X19: =U19*W19 -> 0 | Y19: =Q19 -> 0 | Z19: =+Y19*R19 -> 0 | AA19: EUR | AB19: =IFERROR(VLOOKUP(AA19,Curr!$B$2:$C$13,2,FALSE),0) -> 10.8 | AC19: =+Y19*AB19*R19 -> 0 | AD19: =+AC19-X19 -> 0 | AE19: =IFERROR(AD19/AC19,0) -> 0
S20: =+Q20*R20 -> 0 | T20: 0 | U20: =S20*(1-T20) -> 0 | V20: EUR | W20: =IFERROR(VLOOKUP(V20,Curr!$B$2:$C$13,2,FALSE),0) -> 10.8 | X20: =U20*W20 -> 0 | Y20: =Q20 -> 0 | Z20: =+Y20*R20 -> 0 | AA20: EUR | AB20: =IFERROR(VLOOKUP(AA20,Curr!$B$2:$C$13,2,FALSE),0) -> 10.8 | AC20: =+Y20*AB20*R20 -> 0 | AD20: =+AC20-X20 -> 0 | AE20: =IFERROR(AD20/AC20,0) -> 0
C21: Day 4 | D21: Activity | E21: 30.06.2026 | J21: Fly oVer | Q21: 0 | R21: 0 | S21: =+Q21*R21 -> 0 | T21: 0 | U21: =S21*(1-T21) -> 0 | V21: EUR | W21: =IFERROR(VLOOKUP(V21,Curr!$B$2:$C$13,2,FALSE),0) -> 10.8 | X21: =U21*W21 -> 0 | Y21: =Q21 -> 0 | Z21: =+Y21*R21 -> 0 | AA21: EUR | AB21: =IFERROR(VLOOKUP(AA21,Curr!$B$2:$C$13,2,FALSE),0) -> 10.8 | AC21: =+Y21*AB21*R21 -> 0 | AD21: =+AC21-X21 -> 0 | AE21: =IFERROR(AD21/AC21,0) -> 0
C22: Day 4 | D22: Leisure | E22: 30.06.2026 | J22: Reykjavik: Spend time at leisure | Q22: 0 | R22: 0 | S22: =+Q22*R22 -> 0 | T22: 0 | U22: =S22*(1-T22) -> 0 | V22: EUR | W22: =IFERROR(VLOOKUP(V22,Curr!$B$2:$C$13,2,FALSE),0) -> 10.8 | X22: =U22*W22 -> 0 | Y22: =Q22 -> 0 | Z22: =+Y22*R22 -> 0 | AA22: EUR | AB22: =IFERROR(VLOOKUP(AA22,Curr!$B$2:$C$13,2,FALSE),0) -> 10.8 | AC22: =+Y22*AB22*R22 -> 0 | AD22: =+AC22-X22 -> 0 | AE22: =IFERROR(AD22/AC22,0) -> 0
C23: Day 4 | D23: Activity | E23: 30.06.2026 | J23: Whale MidNightsun | Q23: 0 | R23: 0 | S23: =+Q23*R23 -> 0 | T23: 0 | U23: =S23*(1-T23) -> 0 | V23: EUR | W23: =IFERROR(VLOOKUP(V23,Curr!$B$2:$C$13,2,FALSE),0) -> 10.8 | X23: =U23*W23 -> 0 | Y23: =Q23 -> 0 | Z23: =+Y23*R23 -> 0 | AA23: EUR | AB23: =IFERROR(VLOOKUP(AA23,Curr!$B$2:$C$13,2,FALSE),0) -> 10.8 | AC23: =+Y23*AB23*R23 -> 0 | AD23: =+AC23-X23 -> 0 | AE23: =IFERROR(AD23/AC23,0) -> 0
S24: =+Q24*R24 -> 0 | T24: 0 | U24: =S24*(1-T24) -> 0 | V24: EUR | W24: =IFERROR(VLOOKUP(V24,Curr!$B$2:$C$13,2,FALSE),0) -> 10.8 | X24: =U24*W24 -> 0 | Y24: =Q24 -> 0 | Z24: =+Y24*R24 -> 0 | AA24: EUR | AB24: =IFERROR(VLOOKUP(AA24,Curr!$B$2:$C$13,2,FALSE),0) -> 10.8 | AC24: =+Y24*AB24*R24 -> 0 | AD24: =+AC24-X24 -> 0 | AE24: =IFERROR(AD24/AC24,0) -> 0
C25: Day 5 | D25: Optional | E25: 01.07.2026 | J25: Reykjavik: Self guided roadtrip to Snæfellnes - | Q25: 0 | R25: 0 | S25: =+Q25*R25 -> 0 | T25: 0 | U25: =S25*(1-T25) -> 0 | V25: EUR | W25: =IFERROR(VLOOKUP(V25,Curr!$B$2:$C$13,2,FALSE),0) -> 10.8 | X25: =U25*W25 -> 0 | Y25: =Q25 -> 0 | Z25: =+Y25*R25 -> 0 | AA25: EUR | AB25: =IFERROR(VLOOKUP(AA25,Curr!$B$2:$C$13,2,FALSE),0) -> 10.8 | AC25: =+Y25*AB25*R25 -> 0 | AD25: =+AC25-X25 -> 0 | AE25: =IFERROR(AD25/AC25,0) -> 0
C26: Day 5 | D26: Leisure | E26: 01.07.2026 | J26: Reykjavik: Spend time at leisure | Q26: 0 | R26: 0 | S26: =+Q26*R26 -> 0 | T26: 0 | U26: =S26*(1-T26) -> 0 | V26: EUR | W26: =IFERROR(VLOOKUP(V26,Curr!$B$2:$C$13,2,FALSE),0) -> 10.8 | X26: =U26*W26 -> 0 | Y26: =Q26 -> 0 | Z26: =+Y26*R26 -> 0 | AA26: EUR | AB26: =IFERROR(VLOOKUP(AA26,Curr!$B$2:$C$13,2,FALSE),0) -> 10.8 | AC26: =+Y26*AB26*R26 -> 0 | AD26: =+AC26-X26 -> 0 | AE26: =IFERROR(AD26/AC26,0) -> 0
S27: =+Q27*R27 -> 0 | T27: 0 | U27: =S27*(1-T27) -> 0 | V27: EUR | W27: =IFERROR(VLOOKUP(V27,Curr!$B$2:$C$13,2,FALSE),0) -> 10.8 | X27: =U27*W27 -> 0 | Y27: =Q27 -> 0 | Z27: =+Y27*R27 -> 0 | AA27: EUR | AB27: =IFERROR(VLOOKUP(AA27,Curr!$B$2:$C$13,2,FALSE),0) -> 10.8 | AC27: =+Y27*AB27*R27 -> 0 | AD27: =+AC27-X27 -> 0 | AE27: =IFERROR(AD27/AC27,0) -> 0
C28: Day 6 | D28: Activity | E28: 02.07.2026 | J28: Sky Lagoon | Q28: 0 | R28: 0 | S28: =+Q28*R28 -> 0 | T28: 0 | U28: =S28*(1-T28) -> 0 | V28: EUR | W28: =IFERROR(VLOOKUP(V28,Curr!$B$2:$C$13,2,FALSE),0) -> 10.8 | X28: =U28*W28 -> 0 | Y28: =Q28 -> 0 | Z28: =+Y28*R28 -> 0 | AA28: EUR | AB28: =IFERROR(VLOOKUP(AA28,Curr!$B$2:$C$13,2,FALSE),0) -> 10.8 | AC28: =+Y28*AB28*R28 -> 0 | AD28: =+AC28-X28 -> 0 | AE28: =IFERROR(AD28/AC28,0) -> 0
C29: Day 6 | D29: Leisure | E29: 02.07.2026 | J29: Reykjavik: Spend time at leisure | Q29: 0 | R29: 0 | S29: =+Q29*R29 -> 0 | T29: 0 | U29: =S29*(1-T29) -> 0 | V29: EUR | W29: =IFERROR(VLOOKUP(V29,Curr!$B$2:$C$13,2,FALSE),0) -> 10.8 | X29: =U29*W29 -> 0 | Y29: =Q29 -> 0 | Z29: =+Y29*R29 -> 0 | AA29: EUR | AB29: =IFERROR(VLOOKUP(AA29,Curr!$B$2:$C$13,2,FALSE),0) -> 10.8 | AC29: =+Y29*AB29*R29 -> 0 | AD29: =+AC29-X29 -> 0 | AE29: =IFERROR(AD29/AC29,0) -> 0
S30: =+Q30*R30 -> 0 | T30: 0 | U30: =S30*(1-T30) -> 0 | V30: EUR | W30: =IFERROR(VLOOKUP(V30,Curr!$B$2:$C$13,2,FALSE),0) -> 10.8 | X30: =U30*W30 -> 0 | Y30: =Q30 -> 0 | Z30: =+Y30*R30 -> 0 | AA30: EUR | AB30: =IFERROR(VLOOKUP(AA30,Curr!$B$2:$C$13,2,FALSE),0) -> 10.8 | AC30: =+Y30*AB30*R30 -> 0 | AD30: =+AC30-X30 -> 0 | AE30: =IFERROR(AD30/AC30,0) -> 0
C31: Day 7 | D31: Drive | E31: 03.07.2026 | J31: Reykjavik: Drive to Keflavik Airport | Q31: 0 | R31: 0 | S31: =+Q31*R31 -> 0 | T31: 0 | U31: =S31*(1-T31) -> 0 | V31: EUR | W31: =IFERROR(VLOOKUP(V31,Curr!$B$2:$C$13,2,FALSE),0) -> 10.8 | X31: =U31*W31 -> 0 | Y31: =Q31 -> 0 | Z31: =+Y31*R31 -> 0 | AA31: EUR | AB31: =IFERROR(VLOOKUP(AA31,Curr!$B$2:$C$13,2,FALSE),0) -> 10.8 | AC31: =+Y31*AB31*R31 -> 0 | AD31: =+AC31-X31 -> 0 | AE31: =IFERROR(AD31/AC31,0) -> 0
C32: Day 7 | D32: Car | E32: 03.07.2026 | J32: Keflavik: Deliver your rental car at the airport car rental office | Q32: 0 | R32: 0 | S32: =+Q32*R32 -> 0 | T32: 0 | U32: =S32*(1-T32) -> 0 | V32: EUR | W32: =IFERROR(VLOOKUP(V32,Curr!$B$2:$C$13,2,FALSE),0) -> 10.8 | X32: =U32*W32 -> 0 | Y32: =Q32 -> 0 | Z32: =+Y32*R32 -> 0 | AA32: EUR | AB32: =IFERROR(VLOOKUP(AA32,Curr!$B$2:$C$13,2,FALSE),0) -> 10.8 | AC32: =+Y32*AB32*R32 -> 0 | AD32: =+AC32-X32 -> 0 | AE32: =IFERROR(AD32/AC32,0) -> 0
C33: Day 7 | D33: Flight | E33: 03.07.2026 | J33: Keflavik: Flight to Oslo - Time: - Luggage included: 1 x 23 kg check in and 1 x 8 kg carry on per person | Q33: 0 | R33: 0 | S33: =+Q33*R33 -> 0 | T33: 0 | U33: =S33*(1-T33) -> 0 | V33: EUR | W33: =IFERROR(VLOOKUP(V33,Curr!$B$2:$C$13,2,FALSE),0) -> 10.8 | X33: =U33*W33 -> 0 | Y33: =Q33 -> 0 | Z33: =+Y33*R33 -> 0 | AA33: EUR | AB33: =IFERROR(VLOOKUP(AA33,Curr!$B$2:$C$13,2,FALSE),0) -> 10.8 | AC33: =+Y33*AB33*R33 -> 0 | AD33: =+AC33-X33 -> 0 | AE33: =IFERROR(AD33/AC33,0) -> 0
C34: Day 7 | D34: Transfer | E34: 03.07.2026 | J34: Oslo: Private transfer to your accommodation | Q34: 0 | R34: 0 | S34: =+Q34*R34 -> 0 | T34: 0 | U34: =S34*(1-T34) -> 0 | V34: EUR | W34: =IFERROR(VLOOKUP(V34,Curr!$B$2:$C$13,2,FALSE),0) -> 10.8 | X34: =U34*W34 -> 0 | Y34: =Q34 -> 0 | Z34: =+Y34*R34 -> 0 | AA34: EUR | AB34: =IFERROR(VLOOKUP(AA34,Curr!$B$2:$C$13,2,FALSE),0) -> 10.8 | AC34: =+Y34*AB34*R34 -> 0 | AD34: =+AC34-X34 -> 0 | AE34: =IFERROR(AD34/AC34,0) -> 0
C35: Day 7 | D35: Hotel | E35: 03.07.2026 | F35: 05.07.2026 | J35: Oslo: Check in to your accommodation for a X night stay - 2 x double room - breakfast included | Q35: 0 | R35: 0 | S35: =+Q35*R35 -> 0 | T35: 0 | U35: =S35*(1-T35) -> 0 | V35: EUR | W35: =IFERROR(VLOOKUP(V35,Curr!$B$2:$C$13,2,FALSE),0) -> 10.8 | X35: =U35*W35 -> 0 | Y35: =Q35 -> 0 | Z35: =+Y35*R35 -> 0 | AA35: EUR | AB35: =IFERROR(VLOOKUP(AA35,Curr!$B$2:$C$13,2,FALSE),0) -> 10.8 | AC35: =+Y35*AB35*R35 -> 0 | AD35: =+AC35-X35 -> 0 | AE35: =IFERROR(AD35/AC35,0) -> 0
C36: Day 7 | D36: Leisure | E36: 03.07.2026 | J36: Oslo: Spend time at leisure | Q36: 0 | R36: 0 | S36: =+Q36*R36 -> 0 | T36: 0 | U36: =S36*(1-T36) -> 0 | V36: EUR | W36: =IFERROR(VLOOKUP(V36,Curr!$B$2:$C$13,2,FALSE),0) -> 10.8 | X36: =U36*W36 -> 0 | Y36: =Q36 -> 0 | Z36: =+Y36*R36 -> 0 | AA36: EUR | AB36: =IFERROR(VLOOKUP(AA36,Curr!$B$2:$C$13,2,FALSE),0) -> 10.8 | AC36: =+Y36*AB36*R36 -> 0 | AD36: =+AC36-X36 -> 0 | AE36: =IFERROR(AD36/AC36,0) -> 0
S37: =+Q37*R37 -> 0 | T37: 0 | U37: =S37*(1-T37) -> 0 | V37: EUR | W37: =IFERROR(VLOOKUP(V37,Curr!$B$2:$C$13,2,FALSE),0) -> 10.8 | X37: =U37*W37 -> 0 | Y37: =Q37 -> 0 | Z37: =+Y37*R37 -> 0 | AA37: EUR | AB37: =IFERROR(VLOOKUP(AA37,Curr!$B$2:$C$13,2,FALSE),0) -> 10.8 | AC37: =+Y37*AB37*R37 -> 0 | AD37: =+AC37-X37 -> 0 | AE37: =IFERROR(AD37/AC37,0) -> 0
C38: Day 8 | D38: Activity | E38: 04.07.2026 | Q38: 0 | R38: 0 | S38: =+Q38*R38 -> 0 | T38: 0 | U38: =S38*(1-T38) -> 0 | V38: EUR | W38: =IFERROR(VLOOKUP(V38,Curr!$B$2:$C$13,2,FALSE),0) -> 10.8 | X38: =U38*W38 -> 0 | Y38: =Q38 -> 0 | Z38: =+Y38*R38 -> 0 | AA38: EUR | AB38: =IFERROR(VLOOKUP(AA38,Curr!$B$2:$C$13,2,FALSE),0) -> 10.8 | AC38: =+Y38*AB38*R38 -> 0 | AD38: =+AC38-X38 -> 0 | AE38: =IFERROR(AD38/AC38,0) -> 0
C39: Day 8 | D39: Leisure | E39: 04.07.2026 | J39: Oslo: Spend time at leisure | Q39: 0 | R39: 0 | S39: =+Q39*R39 -> 0 | T39: 0 | U39: =S39*(1-T39) -> 0 | V39: EUR | W39: =IFERROR(VLOOKUP(V39,Curr!$B$2:$C$13,2,FALSE),0) -> 10.8 | X39: =U39*W39 -> 0 | Y39: =Q39 -> 0 | Z39: =+Y39*R39 -> 0 | AA39: EUR | AB39: =IFERROR(VLOOKUP(AA39,Curr!$B$2:$C$13,2,FALSE),0) -> 10.8 | AC39: =+Y39*AB39*R39 -> 0 | AD39: =+AC39-X39 -> 0 | AE39: =IFERROR(AD39/AC39,0) -> 0
S40: =+Q40*R40 -> 0 | T40: 0 | U40: =S40*(1-T40) -> 0 | V40: EUR | W40: =IFERROR(VLOOKUP(V40,Curr!$B$2:$C$13,2,FALSE),0) -> 10.8 | X40: =U40*W40 -> 0 | Y40: =Q40 -> 0 | Z40: =+Y40*R40 -> 0 | AA40: EUR | AB40: =IFERROR(VLOOKUP(AA40,Curr!$B$2:$C$13,2,FALSE),0) -> 10.8 | AC40: =+Y40*AB40*R40 -> 0 | AD40: =+AC40-X40 -> 0 | AE40: =IFERROR(AD40/AC40,0) -> 0
C41: Day 9 | D41: Transfer | E41: 05.07.2026 | J41: Oslo: Self transfer to Oslo Central Station | Q41: 0 | R41: 0 | S41: =+Q41*R41 -> 0 | T41: 0 | U41: =S41*(1-T41) -> 0 | V41: EUR | W41: =IFERROR(VLOOKUP(V41,Curr!$B$2:$C$13,2,FALSE),0) -> 10.8 | X41: =U41*W41 -> 0 | Y41: =Q41 -> 0 | Z41: =+Y41*R41 -> 0 | AA41: EUR | AB41: =IFERROR(VLOOKUP(AA41,Curr!$B$2:$C$13,2,FALSE),0) -> 10.8 | AC41: =+Y41*AB41*R41 -> 0 | AD41: =+AC41-X41 -> 0 | AE41: =IFERROR(AD41/AC41,0) -> 0
C42: Day 9 | D42: Activity | E42: 05.07.2026 | J42: NIAN | Q42: 0 | R42: 0 | S42: =+Q42*R42 -> 0 | T42: 0 | U42: =S42*(1-T42) -> 0 | V42: EUR | W42: =IFERROR(VLOOKUP(V42,Curr!$B$2:$C$13,2,FALSE),0) -> 10.8 | X42: =U42*W42 -> 0 | Y42: =Q42 -> 0 | Z42: =+Y42*R42 -> 0 | AA42: EUR | AB42: =IFERROR(VLOOKUP(AA42,Curr!$B$2:$C$13,2,FALSE),0) -> 10.8 | AC42: =+Y42*AB42*R42 -> 0 | AD42: =+AC42-X42 -> 0 | AE42: =IFERROR(AD42/AC42,0) -> 0
C43: Day 9 | D43: Transfer | E43: 05.07.2026 | J43: Gudvangen: Self transfer to your accommodation | Q43: 0 | R43: 0 | S43: =+Q43*R43 -> 0 | T43: 0 | U43: =S43*(1-T43) -> 0 | V43: EUR | W43: =IFERROR(VLOOKUP(V43,Curr!$B$2:$C$13,2,FALSE),0) -> 10.8 | X43: =U43*W43 -> 0 | Y43: =Q43 -> 0 | Z43: =+Y43*R43 -> 0 | AA43: EUR | AB43: =IFERROR(VLOOKUP(AA43,Curr!$B$2:$C$13,2,FALSE),0) -> 10.8 | AC43: =+Y43*AB43*R43 -> 0 | AD43: =+AC43-X43 -> 0 | AE43: =IFERROR(AD43/AC43,0) -> 0
C44: Day 9 | D44: Hotel | E44: 05.07.2026 | F44: 06.07.2026 | J44: Gudvangen: Check in to your accommodation for a 1 night stay - Gudvangen Fjordtell - 2 x double room - breakfast included | P44: https://app.hotelbeds.com/factsheet/stay/1087626?check_in=05-07-2026&check_out=06-07-2026&occupancy=2~0_2~0&packaging=true | Q44: 1014 | R44: 1 | S44: =+Q44*R44 -> 1014 | T44: 0 | U44: =S44*(1-T44) -> 1014 | V44: EUR | W44: =IFERROR(VLOOKUP(V44,Curr!$B$2:$C$13,2,FALSE),0) -> 10.8 | X44: =U44*W44 -> 10951.2 | Y44: =Q44/0.85 -> 1192.9412 | Z44: =+Y44*R44 -> 1192.9412 | AA44: EUR | AB44: =IFERROR(VLOOKUP(AA44,Curr!$B$2:$C$13,2,FALSE),0) -> 10.8 | AC44: =+Y44*AB44*R44 -> 12883.765 | AD44: =+AC44-X44 -> 1932.5647 | AE44: =IFERROR(AD44/AC44,0) -> 0.15
C45: Day 9 | D45: Leisure | E45: 05.07.2026 | J45: Gudvangen: Spend time at leisure | Q45: 0 | R45: 0 | S45: =+Q45*R45 -> 0 | T45: 0 | U45: =S45*(1-T45) -> 0 | V45: EUR | W45: =IFERROR(VLOOKUP(V45,Curr!$B$2:$C$13,2,FALSE),0) -> 10.8 | X45: =U45*W45 -> 0 | Y45: =Q45 -> 0 | Z45: =+Y45*R45 -> 0 | AA45: EUR | AB45: =IFERROR(VLOOKUP(AA45,Curr!$B$2:$C$13,2,FALSE),0) -> 10.8 | AC45: =+Y45*AB45*R45 -> 0 | AD45: =+AC45-X45 -> 0 | AE45: =IFERROR(AD45/AC45,0) -> 0
S46: =+Q46*R46 -> 0 | T46: 0 | U46: =S46*(1-T46) -> 0 | V46: EUR | W46: =IFERROR(VLOOKUP(V46,Curr!$B$2:$C$13,2,FALSE),0) -> 10.8 | X46: =U46*W46 -> 0 | Y46: =Q46 -> 0 | Z46: =+Y46*R46 -> 0 | AA46: EUR | AB46: =IFERROR(VLOOKUP(AA46,Curr!$B$2:$C$13,2,FALSE),0) -> 10.8 | AC46: =+Y46*AB46*R46 -> 0 | AD46: =+AC46-X46 -> 0 | AE46: =IFERROR(AD46/AC46,0) -> 0
C47: Day 10 | D47: Transfer | E47: 06.07.2026 | J47: Gudvangen: Self transfer to XXX | Q47: 0 | R47: 0 | S47: =+Q47*R47 -> 0 | T47: 0 | U47: =S47*(1-T47) -> 0 | V47: EUR | W47: =IFERROR(VLOOKUP(V47,Curr!$B$2:$C$13,2,FALSE),0) -> 10.8 | X47: =U47*W47 -> 0 | Y47: =Q47 -> 0 | Z47: =+Y47*R47 -> 0 | AA47: EUR | AB47: =IFERROR(VLOOKUP(AA47,Curr!$B$2:$C$13,2,FALSE),0) -> 10.8 | AC47: =+Y47*AB47*R47 -> 0 | AD47: =+AC47-X47 -> 0 | AE47: =IFERROR(AD47/AC47,0) -> 0
C48: Day 10 | D48: Activity | E48: 06.07.2026 | J48: Gudvangen: NINA | Q48: 0 | R48: 0 | S48: =+Q48*R48 -> 0 | T48: 0 | U48: =S48*(1-T48) -> 0 | V48: EUR | W48: =IFERROR(VLOOKUP(V48,Curr!$B$2:$C$13,2,FALSE),0) -> 10.8 | X48: =U48*W48 -> 0 | Y48: =Q48 -> 0 | Z48: =+Y48*R48 -> 0 | AA48: EUR | AB48: =IFERROR(VLOOKUP(AA48,Curr!$B$2:$C$13,2,FALSE),0) -> 10.8 | AC48: =+Y48*AB48*R48 -> 0 | AD48: =+AC48-X48 -> 0 | AE48: =IFERROR(AD48/AC48,0) -> 0
C49: Day 10 | D49: Transfer | E49: 06.07.2026 | J49: Bergen: Private transfer to your accommodation | Q49: 0 | R49: 0 | S49: =+Q49*R49 -> 0 | T49: 0 | U49: =S49*(1-T49) -> 0 | V49: EUR | W49: =IFERROR(VLOOKUP(V49,Curr!$B$2:$C$13,2,FALSE),0) -> 10.8 | X49: =U49*W49 -> 0 | Y49: =Q49 -> 0 | Z49: =+Y49*R49 -> 0 | AA49: EUR | AB49: =IFERROR(VLOOKUP(AA49,Curr!$B$2:$C$13,2,FALSE),0) -> 10.8 | AC49: =+Y49*AB49*R49 -> 0 | AD49: =+AC49-X49 -> 0 | AE49: =IFERROR(AD49/AC49,0) -> 0
C50: Day 10 | D50: Hotel | E50: 06.07.2026 | F50: 08.07.2026 | J50: Bergen: Check in to your accommodation for a 2 night stay - 2 x double room - breakfast included | Q50: 0 | R50: 0 | S50: =+Q50*R50 -> 0 | T50: 0 | U50: =S50*(1-T50) -> 0 | V50: EUR | W50: =IFERROR(VLOOKUP(V50,Curr!$B$2:$C$13,2,FALSE),0) -> 10.8 | X50: =U50*W50 -> 0 | Y50: =Q50 -> 0 | Z50: =+Y50*R50 -> 0 | AA50: EUR | AB50: =IFERROR(VLOOKUP(AA50,Curr!$B$2:$C$13,2,FALSE),0) -> 10.8 | AC50: =+Y50*AB50*R50 -> 0 | AD50: =+AC50-X50 -> 0 | AE50: =IFERROR(AD50/AC50,0) -> 0
C51: Day 10 | D51: Leisure | E51: 06.07.2026 | Q51: 0 | R51: 0 | S51: =+Q51*R51 -> 0 | T51: 0 | U51: =S51*(1-T51) -> 0 | V51: EUR | W51: =IFERROR(VLOOKUP(V51,Curr!$B$2:$C$13,2,FALSE),0) -> 10.8 | X51: =U51*W51 -> 0 | Y51: =Q51 -> 0 | Z51: =+Y51*R51 -> 0 | AA51: EUR | AB51: =IFERROR(VLOOKUP(AA51,Curr!$B$2:$C$13,2,FALSE),0) -> 10.8 | AC51: =+Y51*AB51*R51 -> 0 | AD51: =+AC51-X51 -> 0 | AE51: =IFERROR(AD51/AC51,0) -> 0
S52: =+Q52*R52 -> 0 | T52: 0 | U52: =S52*(1-T52) -> 0 | V52: EUR | W52: =IFERROR(VLOOKUP(V52,Curr!$B$2:$C$13,2,FALSE),0) -> 10.8 | X52: =U52*W52 -> 0 | Y52: =Q52 -> 0 | Z52: =+Y52*R52 -> 0 | AA52: EUR | AB52: =IFERROR(VLOOKUP(AA52,Curr!$B$2:$C$13,2,FALSE),0) -> 10.8 | AC52: =+Y52*AB52*R52 -> 0 | AD52: =+AC52-X52 -> 0 | AE52: =IFERROR(AD52/AC52,0) -> 0
C53: Day 11 | D53: Activity | E53: 07.07.2026 | J53: Mostarumen | Q53: 0 | R53: 0 | S53: =+Q53*R53 -> 0 | T53: 0 | U53: =S53*(1-T53) -> 0 | V53: EUR | W53: =IFERROR(VLOOKUP(V53,Curr!$B$2:$C$13,2,FALSE),0) -> 10.8 | X53: =U53*W53 -> 0 | Y53: =Q53 -> 0 | Z53: =+Y53*R53 -> 0 | AA53: EUR | AB53: =IFERROR(VLOOKUP(AA53,Curr!$B$2:$C$13,2,FALSE),0) -> 10.8 | AC53: =+Y53*AB53*R53 -> 0 | AD53: =+AC53-X53 -> 0 | AE53: =IFERROR(AD53/AC53,0) -> 0
C54: Day 11 | D54: Leisure | E54: 07.07.2026 | J54: Bergen: Spend time at leisure | Q54: 0 | R54: 0 | S54: =+Q54*R54 -> 0 | T54: 0 | U54: =S54*(1-T54) -> 0 | V54: EUR | W54: =IFERROR(VLOOKUP(V54,Curr!$B$2:$C$13,2,FALSE),0) -> 10.8 | X54: =U54*W54 -> 0 | Y54: =Q54 -> 0 | Z54: =+Y54*R54 -> 0 | AA54: EUR | AB54: =IFERROR(VLOOKUP(AA54,Curr!$B$2:$C$13,2,FALSE),0) -> 10.8 | AC54: =+Y54*AB54*R54 -> 0 | AD54: =+AC54-X54 -> 0 | AE54: =IFERROR(AD54/AC54,0) -> 0
C55: Day 11 | D55: Activity | E55: 07.07.2026 | J55: Fløy | S55: =+Q55*R55 -> 0 | T55: 0 | U55: =S55*(1-T55) -> 0 | V55: EUR | W55: =IFERROR(VLOOKUP(V55,Curr!$B$2:$C$13,2,FALSE),0) -> 10.8 | X55: =U55*W55 -> 0 | Y55: =Q55 -> 0 | Z55: =+Y55*R55 -> 0 | AA55: EUR | AB55: =IFERROR(VLOOKUP(AA55,Curr!$B$2:$C$13,2,FALSE),0) -> 10.8 | AC55: =+Y55*AB55*R55 -> 0 | AD55: =+AC55-X55 -> 0 | AE55: =IFERROR(AD55/AC55,0) -> 0
Q56: 0 | R56: 0 | S56: =+Q56*R56 -> 0 | T56: 0 | U56: =S56*(1-T56) -> 0 | V56: EUR | W56: =IFERROR(VLOOKUP(V56,Curr!$B$2:$C$13,2,FALSE),0) -> 10.8 | X56: =U56*W56 -> 0 | Y56: =Q56 -> 0 | Z56: =+Y56*R56 -> 0 | AA56: EUR | AB56: =IFERROR(VLOOKUP(AA56,Curr!$B$2:$C$13,2,FALSE),0) -> 10.8 | AC56: =+Y56*AB56*R56 -> 0 | AD56: =+AC56-X56 -> 0 | AE56: =IFERROR(AD56/AC56,0) -> 0
C57: Day 12 | D57: Transfer | E57: 08.07.2026 | J57: Bergen: Private transfer to Bergen Airport | Q57: 0 | R57: 0 | S57: =+Q57*R57 -> 0 | T57: 0 | U57: =S57*(1-T57) -> 0 | V57: EUR | W57: =IFERROR(VLOOKUP(V57,Curr!$B$2:$C$13,2,FALSE),0) -> 10.8 | X57: =U57*W57 -> 0 | Y57: =Q57 -> 0 | Z57: =+Y57*R57 -> 0 | AA57: EUR | AB57: =IFERROR(VLOOKUP(AA57,Curr!$B$2:$C$13,2,FALSE),0) -> 10.8 | AC57: =+Y57*AB57*R57 -> 0 | AD57: =+AC57-X57 -> 0 | AE57: =IFERROR(AD57/AC57,0) -> 0
C58: Day 12 | D58: Flight | E58: 08.07.2026 | J58: Bergen: Flight to Ålesund - Time: - Luggage included: 1 x 23 kg check in and 1 x 8 kg carry on per person | S58: =+Q58*R58 -> 0 | T58: 0 | U58: =S58*(1-T58) -> 0 | V58: EUR | W58: =IFERROR(VLOOKUP(V58,Curr!$B$2:$C$13,2,FALSE),0) -> 10.8 | X58: =U58*W58 -> 0 | Y58: =Q58 -> 0 | Z58: =+Y58*R58 -> 0 | AA58: EUR | AB58: =IFERROR(VLOOKUP(AA58,Curr!$B$2:$C$13,2,FALSE),0) -> 10.8 | AC58: =+Y58*AB58*R58 -> 0 | AD58: =+AC58-X58 -> 0 | AE58: =IFERROR(AD58/AC58,0) -> 0
C59: Day 12 | D59: Transfer | E59: 08.07.2026 | J59: Ålesund: | Q59: 0 | R59: 0 | S59: =+Q59*R59 -> 0 | T59: 0 | U59: =S59*(1-T59) -> 0 | V59: EUR | W59: =IFERROR(VLOOKUP(V59,Curr!$B$2:$C$13,2,FALSE),0) -> 10.8 | X59: =U59*W59 -> 0 | Y59: =Q59 -> 0 | Z59: =+Y59*R59 -> 0 | AA59: EUR | AB59: =IFERROR(VLOOKUP(AA59,Curr!$B$2:$C$13,2,FALSE),0) -> 10.8 | AC59: =+Y59*AB59*R59 -> 0 | AD59: =+AC59-X59 -> 0 | AE59: =IFERROR(AD59/AC59,0) -> 0
C60: Day 12 | D60: Hotel | E60: 08.07.2026 | J60: Ålesund: Check in to your accommodation for a 2 night stay - 2 x double room - breakfast included | Q60: 0 | R60: 0 | S60: =+Q60*R60 -> 0 | T60: 0 | U60: =S60*(1-T60) -> 0 | V60: EUR | W60: =IFERROR(VLOOKUP(V60,Curr!$B$2:$C$13,2,FALSE),0) -> 10.8 | X60: =U60*W60 -> 0 | Y60: =Q60 -> 0 | Z60: =+Y60*R60 -> 0 | AA60: EUR | AB60: =IFERROR(VLOOKUP(AA60,Curr!$B$2:$C$13,2,FALSE),0) -> 10.8 | AC60: =+Y60*AB60*R60 -> 0 | AD60: =+AC60-X60 -> 0 | AE60: =IFERROR(AD60/AC60,0) -> 0
C61: Day 12 | D61: Leisure | E61: 08.07.2026 | J61: Ålesund: Spend time at leisure | Q61: 0 | R61: 0 | S61: =+Q61*R61 -> 0 | T61: 0 | U61: =S61*(1-T61) -> 0 | V61: EUR | W61: =IFERROR(VLOOKUP(V61,Curr!$B$2:$C$13,2,FALSE),0) -> 10.8 | X61: =U61*W61 -> 0 | Y61: =Q61 -> 0 | Z61: =+Y61*R61 -> 0 | AA61: EUR | AB61: =IFERROR(VLOOKUP(AA61,Curr!$B$2:$C$13,2,FALSE),0) -> 10.8 | AC61: =+Y61*AB61*R61 -> 0 | AD61: =+AC61-X61 -> 0 | AE61: =IFERROR(AD61/AC61,0) -> 0
Q62: 0 | R62: 0 | S62: =+Q62*R62 -> 0 | T62: 0 | U62: =S62*(1-T62) -> 0 | V62: EUR | W62: =IFERROR(VLOOKUP(V62,Curr!$B$2:$C$13,2,FALSE),0) -> 10.8 | X62: =U62*W62 -> 0 | Y62: =Q62 -> 0 | Z62: =+Y62*R62 -> 0 | AA62: EUR | AB62: =IFERROR(VLOOKUP(AA62,Curr!$B$2:$C$13,2,FALSE),0) -> 10.8 | AC62: =+Y62*AB62*R62 -> 0 | AD62: =+AC62-X62 -> 0 | AE62: =IFERROR(AD62/AC62,0) -> 0
C63: Day 13 | D63: Activity | E63: 09.07.2026 | J63: Geiranger | Q63: 0 | R63: 0 | S63: =+Q63*R63 -> 0 | T63: 0 | U63: =S63*(1-T63) -> 0 | V63: EUR | W63: =IFERROR(VLOOKUP(V63,Curr!$B$2:$C$13,2,FALSE),0) -> 10.8 | X63: =U63*W63 -> 0 | Y63: =Q63 -> 0 | Z63: =+Y63*R63 -> 0 | AA63: EUR | AB63: =IFERROR(VLOOKUP(AA63,Curr!$B$2:$C$13,2,FALSE),0) -> 10.8 | AC63: =+Y63*AB63*R63 -> 0 | AD63: =+AC63-X63 -> 0 | AE63: =IFERROR(AD63/AC63,0) -> 0
C64: Day 13 | D64: Leisure | E64: 09.07.2026 | J64: Ålesund: Spend time at leisure | Q64: 0 | R64: 0 | S64: =+Q64*R64 -> 0 | T64: 0 | U64: =S64*(1-T64) -> 0 | V64: EUR | W64: =IFERROR(VLOOKUP(V64,Curr!$B$2:$C$13,2,FALSE),0) -> 10.8 | X64: =U64*W64 -> 0 | Y64: =Q64 -> 0 | Z64: =+Y64*R64 -> 0 | AA64: EUR | AB64: =IFERROR(VLOOKUP(AA64,Curr!$B$2:$C$13,2,FALSE),0) -> 10.8 | AC64: =+Y64*AB64*R64 -> 0 | AD64: =+AC64-X64 -> 0 | AE64: =IFERROR(AD64/AC64,0) -> 0
S65: =+Q65*R65 -> 0 | T65: 0 | U65: =S65*(1-T65) -> 0 | V65: EUR | W65: =IFERROR(VLOOKUP(V65,Curr!$B$2:$C$13,2,FALSE),0) -> 10.8 | X65: =U65*W65 -> 0 | Y65: =Q65 -> 0 | Z65: =+Y65*R65 -> 0 | AA65: EUR | AB65: =IFERROR(VLOOKUP(AA65,Curr!$B$2:$C$13,2,FALSE),0) -> 10.8 | AC65: =+Y65*AB65*R65 -> 0 | AD65: =+AC65-X65 -> 0 | AE65: =IFERROR(AD65/AC65,0) -> 0
C66: Day 14 | D66: Transfer | E66: 10.07.2026 | J66: Ålesund: Private transfer to Ålesund Airport | Q66: 0 | R66: 0 | S66: =+Q66*R66 -> 0 | T66: 0 | U66: =S66*(1-T66) -> 0 | V66: EUR | W66: =IFERROR(VLOOKUP(V66,Curr!$B$2:$C$13,2,FALSE),0) -> 10.8 | X66: =U66*W66 -> 0 | Y66: =Q66 -> 0 | Z66: =+Y66*R66 -> 0 | AA66: EUR | AB66: =IFERROR(VLOOKUP(AA66,Curr!$B$2:$C$13,2,FALSE),0) -> 10.8 | AC66: =+Y66*AB66*R66 -> 0 | AD66: =+AC66-X66 -> 0 | AE66: =IFERROR(AD66/AC66,0) -> 0
C67: Day 14 | D67: Flight | E67: 10.07.2026 | J67: Ålesund: Flight to Oslo - Time: - Luggage included: 1 x 23 kg check in and 1 x 8 kg carry on per person | Q67: 0 | R67: 0 | S67: =+Q67*R67 -> 0 | T67: 0 | U67: =S67*(1-T67) -> 0 | V67: EUR | W67: =IFERROR(VLOOKUP(V67,Curr!$B$2:$C$13,2,FALSE),0) -> 10.8 | X67: =U67*W67 -> 0 | Y67: =Q67 -> 0 | Z67: =+Y67*R67 -> 0 | AA67: EUR | AB67: =IFERROR(VLOOKUP(AA67,Curr!$B$2:$C$13,2,FALSE),0) -> 10.8 | AC67: =+Y67*AB67*R67 -> 0 | AD67: =+AC67-X67 -> 0 | AE67: =IFERROR(AD67/AC67,0) -> 0
C68: Day 14 | D68: Transfer | E68: 10.07.2026 | J68: Oslo: Private transfer to your accommodation | Q68: 0 | R68: 0 | S68: =+Q68*R68 -> 0 | T68: 0 | U68: =S68*(1-T68) -> 0 | V68: EUR | W68: =IFERROR(VLOOKUP(V68,Curr!$B$2:$C$13,2,FALSE),0) -> 10.8 | X68: =U68*W68 -> 0 | Y68: =Q68 -> 0 | Z68: =+Y68*R68 -> 0 | AA68: EUR | AB68: =IFERROR(VLOOKUP(AA68,Curr!$B$2:$C$13,2,FALSE),0) -> 10.8 | AC68: =+Y68*AB68*R68 -> 0 | AD68: =+AC68-X68 -> 0 | AE68: =IFERROR(AD68/AC68,0) -> 0
C69: Day 14 | D69: Hotel | E69: 10.07.2026 | J69: Oslo: Check in to your accommodation for a 1 night stay - 2 x double room - breakfast included | Q69: 0 | R69: 0 | S69: =+Q69*R69 -> 0 | T69: 0 | U69: =S69*(1-T69) -> 0 | V69: EUR | W69: =IFERROR(VLOOKUP(V69,Curr!$B$2:$C$13,2,FALSE),0) -> 10.8 | X69: =U69*W69 -> 0 | Y69: =Q69 -> 0 | Z69: =+Y69*R69 -> 0 | AA69: EUR | AB69: =IFERROR(VLOOKUP(AA69,Curr!$B$2:$C$13,2,FALSE),0) -> 10.8 | AC69: =+Y69*AB69*R69 -> 0 | AD69: =+AC69-X69 -> 0 | AE69: =IFERROR(AD69/AC69,0) -> 0
C70: Day 14 | D70: Leisure | E70: 10.07.2026 | J70: Oslo: Spend time at leisure | Q70: 0 | R70: 0 | S70: =+Q70*R70 -> 0 | T70: 0 | U70: =S70*(1-T70) -> 0 | V70: EUR | W70: =IFERROR(VLOOKUP(V70,Curr!$B$2:$C$13,2,FALSE),0) -> 10.8 | X70: =U70*W70 -> 0 | Y70: =Q70 -> 0 | Z70: =+Y70*R70 -> 0 | AA70: EUR | AB70: =IFERROR(VLOOKUP(AA70,Curr!$B$2:$C$13,2,FALSE),0) -> 10.8 | AC70: =+Y70*AB70*R70 -> 0 | AD70: =+AC70-X70 -> 0 | AE70: =IFERROR(AD70/AC70,0) -> 0
S71: =+Q71*R71 -> 0 | T71: 0 | U71: =S71*(1-T71) -> 0 | V71: EUR | W71: =IFERROR(VLOOKUP(V71,Curr!$B$2:$C$13,2,FALSE),0) -> 10.8 | X71: =U71*W71 -> 0 | Y71: =Q71 -> 0 | Z71: =+Y71*R71 -> 0 | AA71: EUR | AB71: =IFERROR(VLOOKUP(AA71,Curr!$B$2:$C$13,2,FALSE),0) -> 10.8 | AC71: =+Y71*AB71*R71 -> 0 | AD71: =+AC71-X71 -> 0 | AE71: =IFERROR(AD71/AC71,0) -> 0
C72: Day 15 | D72: Transfer | E72: 11.07.2026 | J72: Oslo: Private transfer to Oslo Airport | Q72: 0 | R72: 0 | S72: =+Q72*R72 -> 0 | T72: 0 | U72: =S72*(1-T72) -> 0 | V72: EUR | W72: =IFERROR(VLOOKUP(V72,Curr!$B$2:$C$13,2,FALSE),0) -> 10.8 | X72: =U72*W72 -> 0 | Y72: =Q72 -> 0 | Z72: =+Y72*R72 -> 0 | AA72: EUR | AB72: =IFERROR(VLOOKUP(AA72,Curr!$B$2:$C$13,2,FALSE),0) -> 10.8 | AC72: =+Y72*AB72*R72 -> 0 | AD72: =+AC72-X72 -> 0 | AE72: =IFERROR(AD72/AC72,0) -> 0
C73: Day 15 | D73: Departure | E73: 11.07.2026 | J73: Oslo: Departure home | Q73: 0 | R73: 0 | S73: =+Q73*R73 -> 0 | T73: 0 | U73: =S73*(1-T73) -> 0 | V73: EUR | W73: =IFERROR(VLOOKUP(V73,Curr!$B$2:$C$13,2,FALSE),0) -> 10.8 | X73: =U73*W73 -> 0 | Y73: =Q73 -> 0 | Z73: =+Y73*R73 -> 0 | AA73: EUR | AB73: =IFERROR(VLOOKUP(AA73,Curr!$B$2:$C$13,2,FALSE),0) -> 10.8 | AC73: =+Y73*AB73*R73 -> 0 | AD73: =+AC73-X73 -> 0 | AE73: =IFERROR(AD73/AC73,0) -> 0
S74: =+Q74*R74 -> 0 | T74: 0 | U74: =S74*(1-T74) -> 0 | V74: EUR | W74: =IFERROR(VLOOKUP(V74,Curr!$B$2:$C$13,2,FALSE),0) -> 10.8 | X74: =U74*W74 -> 0 | Y74: =Q74 -> 0 | Z74: =+Y74*R74 -> 0 | AA74: EUR | AB74: =IFERROR(VLOOKUP(AA74,Curr!$B$2:$C$13,2,FALSE),0) -> 10.8 | AC74: =+Y74*AB74*R74 -> 0 | AD74: =+AC74-X74 -> 0 | AE74: =IFERROR(AD74/AC74,0) -> 0
S75: =+Q75*R75 -> 0 | T75: 0 | U75: =S75*(1-T75) -> 0 | V75: EUR | W75: =IFERROR(VLOOKUP(V75,Curr!$B$2:$C$13,2,FALSE),0) -> 10.8 | X75: =U75*W75 -> 0 | Y75: =Q75 -> 0 | Z75: =+Y75*R75 -> 0 | AA75: EUR | AB75: =IFERROR(VLOOKUP(AA75,Curr!$B$2:$C$13,2,FALSE),0) -> 10.8 | AC75: =+Y75*AB75*R75 -> 0 | AD75: =+AC75-X75 -> 0 | AE75: =IFERROR(AD75/AC75,0) -> 0
S76: =+Q76*R76 -> 0 | T76: 0 | U76: =S76*(1-T76) -> 0 | V76: EUR | W76: =IFERROR(VLOOKUP(V76,Curr!$B$2:$C$13,2,FALSE),0) -> 10.8 | X76: =U76*W76 -> 0 | Y76: =Q76 -> 0 | Z76: =+Y76*R76 -> 0 | AA76: EUR | AB76: =IFERROR(VLOOKUP(AA76,Curr!$B$2:$C$13,2,FALSE),0) -> 10.8 | AC76: =+Y76*AB76*R76 -> 0 | AD76: =+AC76-X76 -> 0 | AE76: =IFERROR(AD76/AC76,0) -> 0
S77: =+Q77*R77 -> 0 | T77: 0 | U77: =S77*(1-T77) -> 0 | V77: EUR | W77: =IFERROR(VLOOKUP(V77,Curr!$B$2:$C$13,2,FALSE),0) -> 10.8 | X77: =U77*W77 -> 0 | Y77: =Q77 -> 0 | Z77: =+Y77*R77 -> 0 | AA77: EUR | AB77: =IFERROR(VLOOKUP(AA77,Curr!$B$2:$C$13,2,FALSE),0) -> 10.8 | AC77: =+Y77*AB77*R77 -> 0 | AD77: =+AC77-X77 -> 0 | AE77: =IFERROR(AD77/AC77,0) -> 0
S78: =+Q78*R78 -> 0 | T78: 0 | U78: =S78*(1-T78) -> 0 | V78: EUR | W78: =IFERROR(VLOOKUP(V78,Curr!$B$2:$C$13,2,FALSE),0) -> 10.8 | X78: =U78*W78 -> 0 | Y78: =Q78 -> 0 | Z78: =+Y78*R78 -> 0 | AA78: EUR | AB78: =IFERROR(VLOOKUP(AA78,Curr!$B$2:$C$13,2,FALSE),0) -> 10.8 | AC78: =+Y78*AB78*R78 -> 0 | AD78: =+AC78-X78 -> 0 | AE78: =IFERROR(AD78/AC78,0) -> 0
S79: =+Q79*R79 -> 0 | T79: 0 | U79: =S79*(1-T79) -> 0 | V79: EUR | W79: =IFERROR(VLOOKUP(V79,Curr!$B$2:$C$13,2,FALSE),0) -> 10.8 | X79: =U79*W79 -> 0 | Y79: =Q79 -> 0 | Z79: =+Y79*R79 -> 0 | AA79: EUR | AB79: =IFERROR(VLOOKUP(AA79,Curr!$B$2:$C$13,2,FALSE),0) -> 10.8 | AC79: =+Y79*AB79*R79 -> 0 | AD79: =+AC79-X79 -> 0 | AE79: =IFERROR(AD79/AC79,0) -> 0
S80: =+Q80*R80 -> 0 | T80: 0 | U80: =S80*(1-T80) -> 0 | V80: EUR | W80: =IFERROR(VLOOKUP(V80,Curr!$B$2:$C$13,2,FALSE),0) -> 10.8 | X80: =U80*W80 -> 0 | Y80: =Q80 -> 0 | Z80: =+Y80*R80 -> 0 | AA80: EUR | AB80: =IFERROR(VLOOKUP(AA80,Curr!$B$2:$C$13,2,FALSE),0) -> 10.8 | AC80: =+Y80*AB80*R80 -> 0 | AD80: =+AC80-X80 -> 0 | AE80: =IFERROR(AD80/AC80,0) -> 0
S81: =+Q81*R81 -> 0 | T81: 0 | U81: =S81*(1-T81) -> 0 | V81: EUR | W81: =IFERROR(VLOOKUP(V81,Curr!$B$2:$C$13,2,FALSE),0) -> 10.8 | X81: =U81*W81 -> 0 | Y81: =Q81 -> 0 | Z81: =+Y81*R81 -> 0 | AA81: EUR | AB81: =IFERROR(VLOOKUP(AA81,Curr!$B$2:$C$13,2,FALSE),0) -> 10.8 | AC81: =+Y81*AB81*R81 -> 0 | AD81: =+AC81-X81 -> 0 | AE81: =IFERROR(AD81/AC81,0) -> 0
B83: Totals | D83: x | E83: x | F83: x | G83: x | H83: x | I83: x | J83: x | K83: x | L83: x | M83: x | N83: x | O83: x | P83: x | Q83: x | R83: x | S83: x | T83: x | U83: x | V83: x | W83: x | X83: x | Y83: x | Z83: =SUM(Z7:Z81) -> 1192.9412 | AC83: =SUM(AC7:AC81) -> 12883.765 | AD83: =SUM(AD7:AD81) -> 1932.5647 | AE83: =IFERROR(AD83/AC83,0) -> 0.15 | AF83: =SUM(AF8:AF82) -> 0 | AG83: =SUM(AG8:AG82) -> 0 | AH83: =SUM(AH8:AH82) -> 0 | AI83: =SUM(AI8:AI82) -> 0 | AJ83: =SUM(AJ8:AJ82) -> 0
Y85: Quote | Z85: 8920
Y86: PP | Z86: =Z85/4 -> 2230
Y88: USD | Z88: 10440
Y89: PP | Z89: =Z88/4 -> 2610

Sheet Kalk 2
B2: Dates: 27.06.2026
B3: Pax: 4
B4: Rooming: 2 x double
B6: ID | C6: Day | D6: Type | E6: From date | F6: To date | G6: From time | H6: To time | I6: Supplier | J6: Travel element | K6: Manual booking? | L6: Status | M6: Comments | N6: Non-refundable | O6: Refundable | P6: URL | Q6: Gross P per unit | R6: Units | S6: Gross P | T6: Supp Comm | U6: Net P | V6: Supp curr | W6: X-rate | X6: Net P NOK | Y6: Sales P per unit | Z6: Price | AA6: Sales curr | AB6: X-rate | AC6: Sales P NOK tot | AD6: GP NOK | AE6: GP % | AF6: VAT25 | AG6: VAT15 | AH6: VAT12 | AI6: VAT0-D | AJ6: VAT0-I
C7: Day 1 | D7: Arrival | E7: 27.06.2026 | J7: Keflavik: Welcome to Iceland | Q7: 0 | R7: 0 | S7: =+Q7*R7 -> 0 | T7: 0 | U7: =S7*(1-T7) -> 0 | V7: EUR | W7: =IFERROR(VLOOKUP(V7,Curr!$B$2:$C$13,2,FALSE),0) -> 10.8 | X7: =U7*W7 -> 0 | Y7: =Q7 -> 0 | Z7: =+Y7*R7 -> 0 | AA7: EUR | AB7: =IFERROR(VLOOKUP(AA7,Curr!$B$2:$C$13,2,FALSE),0) -> 10.8 | AC7: =+Y7*AB7*R7 -> 0 | AD7: =+AC7-X7 -> 0 | AE7: =IFERROR(AD7/AC7,0) -> 0
C8: Day 1 | D8: Car | E8: 27.06.2026 | F8: 03.07.2026 | J8: Keflavik: Pick up your rental car at Keflavik Airport Car rental office - Car: Ford Kuga 4x4 - Automatic or similar - Includes: Unlimited milage, Airport service charge, Other taxes and service charges, Supplementary liability insurance, Collision damage waiver, Fuel information, Third party coverage, Theft protection, Vat | Q8: 535 | R8: 1 | S8: =+Q8*R8 -> 535 | T8: 0 | U8: =S8*(1-T8) -> 535 | V8: EUR | W8: =IFERROR(VLOOKUP(V8,Curr!$B$2:$C$13,2,FALSE),0) -> 10.8 | X8: =U8*W8 -> 5778 | Y8: =Q8/0.8 -> 668.75 | Z8: =+Y8*R8 -> 668.75 | AA8: EUR | AB8: =IFERROR(VLOOKUP(AA8,Curr!$B$2:$C$13,2,FALSE),0) -> 10.8 | AC8: =+Y8*AB8*R8 -> 7222.5 | AD8: =+AC8-X8 -> 1444.5 | AE8: =IFERROR(AD8/AC8,0) -> 0.2
C9: Day 1 | D9: Drive | E9: 27.06.2026 | J9: Keflavik: Drive to your accommodaiton | Q9: 0 | R9: 0 | S9: =+Q9*R9 -> 0 | T9: 0 | U9: =S9*(1-T9) -> 0 | V9: EUR | W9: =IFERROR(VLOOKUP(V9,Curr!$B$2:$C$13,2,FALSE),0) -> 10.8 | X9: =U9*W9 -> 0 | Y9: =Q9 -> 0 | Z9: =+Y9*R9 -> 0 | AA9: EUR | AB9: =IFERROR(VLOOKUP(AA9,Curr!$B$2:$C$13,2,FALSE),0) -> 10.8 | AC9: =+Y9*AB9*R9 -> 0 | AD9: =+AC9-X9 -> 0 | AE9: =IFERROR(AD9/AC9,0) -> 0
C10: Day 1 | D10: Hotel | E10: 27.06.2026 | F10: 28.07.2026 | J10: Reykjavik: Check in to your accommodation for a 1 night stay - Grandi by Center Hotels - 2 x Standard twin/double - breakfast included | P10: https://app.hotelbeds.com/factsheet/stay/749447?check_in=27-06-2026&check_out=28-06-2026&occupancy=2~0_2~0&packaging=true | Q10: 574 | R10: 1 | S10: =+Q10*R10 -> 574 | T10: 0 | U10: =S10*(1-T10) -> 574 | V10: EUR | W10: =IFERROR(VLOOKUP(V10,Curr!$B$2:$C$13,2,FALSE),0) -> 10.8 | X10: =U10*W10 -> 6199.2 | Y10: =Q10/0.85 -> 675.29412 | Z10: =+Y10*R10 -> 675.29412 | AA10: EUR | AB10: =IFERROR(VLOOKUP(AA10,Curr!$B$2:$C$13,2,FALSE),0) -> 10.8 | AC10: =+Y10*AB10*R10 -> 7293.1765 | AD10: =+AC10-X10 -> 1093.9765 | AE10: =IFERROR(AD10/AC10,0) -> 0.15
C11: Day 1 | D11: Leisure | E11: 27.06.2026 | J11: Vik: Spend time at leisure | Q11: 0 | R11: 0 | S11: =+Q11*R11 -> 0 | T11: 0 | U11: =S11*(1-T11) -> 0 | V11: EUR | W11: =IFERROR(VLOOKUP(V11,Curr!$B$2:$C$13,2,FALSE),0) -> 10.8 | X11: =U11*W11 -> 0 | Y11: =Q11 -> 0 | Z11: =+Y11*R11 -> 0 | AA11: EUR | AB11: =IFERROR(VLOOKUP(AA11,Curr!$B$2:$C$13,2,FALSE),0) -> 10.8 | AC11: =+Y11*AB11*R11 -> 0 | AD11: =+AC11-X11 -> 0 | AE11: =IFERROR(AD11/AC11,0) -> 0
S12: =+Q12*R12 -> 0 | T12: 0 | U12: =S12*(1-T12) -> 0 | V12: EUR | W12: =IFERROR(VLOOKUP(V12,Curr!$B$2:$C$13,2,FALSE),0) -> 10.8 | X12: =U12*W12 -> 0 | Y12: =Q12 -> 0 | Z12: =+Y12*R12 -> 0 | AA12: EUR | AB12: =IFERROR(VLOOKUP(AA12,Curr!$B$2:$C$13,2,FALSE),0) -> 10.8 | AC12: =+Y12*AB12*R12 -> 0 | AD12: =+AC12-X12 -> 0 | AE12: =IFERROR(AD12/AC12,0) -> 0
C13: Day 2 | D13: Drive | E13: 28.07.2026 | J13: Reykjavik: Drive to Vik - Drivign time: | Q13: 0 | R13: 0 | S13: =+Q13*R13 -> 0 | T13: 0 | U13: =S13*(1-T13) -> 0 | V13: EUR | W13: =IFERROR(VLOOKUP(V13,Curr!$B$2:$C$13,2,FALSE),0) -> 10.8 | X13: =U13*W13 -> 0 | Y13: =Q13 -> 0 | Z13: =+Y13*R13 -> 0 | AA13: EUR | AB13: =IFERROR(VLOOKUP(AA13,Curr!$B$2:$C$13,2,FALSE),0) -> 10.8 | AC13: =+Y13*AB13*R13 -> 0 | AD13: =+AC13-X13 -> 0 | AE13: =IFERROR(AD13/AC13,0) -> 0
C14: Day 2 | D14: Hotel | E14: 28.07.2026 | F14: 30.06.2026 | J14: Vik: Check in to your accommodation for a 2 night stay - Hotel Katla by Keahotels - 2 x Superior Double room - breakfast included | P14: https://www.ratehawk.com/hotel/iceland/vik_i_myrdal/mid7524341/hotel_hofdabrekka_country_hotel/?q=6130429&dates=28.06.2026-30.06.2026&guests=2-2&payment=freecancellation&price=one&sid=22ec769a-b117-452f-befc-9c97bff50e0a | Q14: 2130 | R14: 1 | S14: =+Q14*R14 -> 2130 | T14: 0 | U14: =S14*(1-T14) -> 2130 | V14: EUR | W14: =IFERROR(VLOOKUP(V14,Curr!$B$2:$C$13,2,FALSE),0) -> 10.8 | X14: =U14*W14 -> 23004 | Y14: =Q14/0.85 -> 2505.8824 | Z14: =+Y14*R14 -> 2505.8824 | AA14: EUR | AB14: =IFERROR(VLOOKUP(AA14,Curr!$B$2:$C$13,2,FALSE),0) -> 10.8 | AC14: =+Y14*AB14*R14 -> 27063.529 | AD14: =+AC14-X14 -> 4059.5294 | AE14: =IFERROR(AD14/AC14,0) -> 0.15
C15: Day 2 | D15: Leisure | E15: 28.07.2026 | J15: Vik: Spend time at leisure | Q15: 0 | R15: 0 | S15: =+Q15*R15 -> 0 | T15: 0 | U15: =S15*(1-T15) -> 0 | V15: EUR | W15: =IFERROR(VLOOKUP(V15,Curr!$B$2:$C$13,2,FALSE),0) -> 10.8 | X15: =U15*W15 -> 0 | Y15: =Q15 -> 0 | Z15: =+Y15*R15 -> 0 | AA15: EUR | AB15: =IFERROR(VLOOKUP(AA15,Curr!$B$2:$C$13,2,FALSE),0) -> 10.8 | AC15: =+Y15*AB15*R15 -> 0 | AD15: =+AC15-X15 -> 0 | AE15: =IFERROR(AD15/AC15,0) -> 0
S16: =+Q16*R16 -> 0 | T16: 0 | U16: =S16*(1-T16) -> 0 | V16: EUR | W16: =IFERROR(VLOOKUP(V16,Curr!$B$2:$C$13,2,FALSE),0) -> 10.8 | X16: =U16*W16 -> 0 | Y16: =Q16 -> 0 | Z16: =+Y16*R16 -> 0 | AA16: EUR | AB16: =IFERROR(VLOOKUP(AA16,Curr!$B$2:$C$13,2,FALSE),0) -> 10.8 | AC16: =+Y16*AB16*R16 -> 0 | AD16: =+AC16-X16 -> 0 | AE16: =IFERROR(AD16/AC16,0) -> 0
C17: Day 3 | D17: Activity | E17: 29.06.2026 | J17: Vik: Lava Show Vík - Time: 11:00 am - 12:00 pm - Meeeting point: Icelandic Lava Show, Víkurbraut 5 - Includes: A chance to get up close to real flowing lava, The only live lava show in the world, Security goggles, A live host makes the show fun and personal, A short educational video about Icelandic volcanism, A true story from the 1918 Katla eruption, A sensory loaded experience - you feel the heat from the lava, A Q&A session at the end of the show, A unique once-in-a-lifetime experience | P17: https://booknordics.com/iceland/southern-iceland/vik/lava-show-vik-the-original | Q17: 46 | R17: 4 | S17: =+Q17*R17 -> 184 | T17: 0.2 | U17: =S17*(1-T17) -> 147.2 | V17: EUR | W17: =IFERROR(VLOOKUP(V17,Curr!$B$2:$C$13,2,FALSE),0) -> 10.8 | X17: =U17*W17 -> 1589.76 | Y17: =Q17 -> 46 | Z17: =+Y17*R17 -> 184 | AA17: EUR | AB17: =IFERROR(VLOOKUP(AA17,Curr!$B$2:$C$13,2,FALSE),0) -> 10.8 | AC17: =+Y17*AB17*R17 -> 1987.2 | AD17: =+AC17-X17 -> 397.44 | AE17: =IFERROR(AD17/AC17,0) -> 0.2
C18: Day 3 | D18: Leisure | E18: 29.06.2026 | J18: Vik: Spend time at leisure | Q18: 0 | R18: 0 | S18: =+Q18*R18 -> 0 | T18: 0 | U18: =S18*(1-T18) -> 0 | V18: EUR | W18: =IFERROR(VLOOKUP(V18,Curr!$B$2:$C$13,2,FALSE),0) -> 10.8 | X18: =U18*W18 -> 0 | Y18: =Q18 -> 0 | Z18: =+Y18*R18 -> 0 | AA18: EUR | AB18: =IFERROR(VLOOKUP(AA18,Curr!$B$2:$C$13,2,FALSE),0) -> 10.8 | AC18: =+Y18*AB18*R18 -> 0 | AD18: =+AC18-X18 -> 0 | AE18: =IFERROR(AD18/AC18,0) -> 0
C19: Day 3 | D19: Activity | E19: 29.06.2026 | J19: Vik: Ice Cave Underneath Katla Volcano Super Jeep Tour - Time: 6:00 pm - 9:00 pm - Meeting point: Tröll Expeditions Katla Ice Cave, Víkubraut 26 - Includes: Stunning ride on a super jeep, Certified glacier guide, Visit to a natural ice cave, All safety ice cave equipment, Scenic landscapes viewing | P19: https://booknordics.com/iceland/southern-iceland/vik/katla-ice-cave-super-jeep-from-vik | Q19: 204 | R19: 4 | S19: =+Q19*R19 -> 816 | T19: 0.25 | U19: =S19*(1-T19) -> 612 | V19: EUR | W19: =IFERROR(VLOOKUP(V19,Curr!$B$2:$C$13,2,FALSE),0) -> 10.8 | X19: =U19*W19 -> 6609.6 | Y19: =Q19 -> 204 | Z19: =+Y19*R19 -> 816 | AA19: EUR | AB19: =IFERROR(VLOOKUP(AA19,Curr!$B$2:$C$13,2,FALSE),0) -> 10.8 | AC19: =+Y19*AB19*R19 -> 8812.8 | AD19: =+AC19-X19 -> 2203.2 | AE19: =IFERROR(AD19/AC19,0) -> 0.25
S20: =+Q20*R20 -> 0 | T20: 0 | U20: =S20*(1-T20) -> 0 | V20: EUR | W20: =IFERROR(VLOOKUP(V20,Curr!$B$2:$C$13,2,FALSE),0) -> 10.8 | X20: =U20*W20 -> 0 | Y20: =Q20 -> 0 | Z20: =+Y20*R20 -> 0 | AA20: EUR | AB20: =IFERROR(VLOOKUP(AA20,Curr!$B$2:$C$13,2,FALSE),0) -> 10.8 | AC20: =+Y20*AB20*R20 -> 0 | AD20: =+AC20-X20 -> 0 | AE20: =IFERROR(AD20/AC20,0) -> 0
C21: Day 4 | D21: Drive | E21: 30.06.2026 | J21: Vik: Drive to Selfoss, then embark on the Golden Circle - Driving time: 4hrs 40 minutes (without stops) - Things to see: Kerið Crater Lake, Fridheimar Tomato Farm, Gullfoss Waterfall, Geysir Hot Spring, Efstidalur Dairy Farm, Öxarárfoss Waterfall, Thingvellir National Park | Q21: 0 | R21: 0 | S21: =+Q21*R21 -> 0 | T21: 0 | U21: =S21*(1-T21) -> 0 | V21: EUR | W21: =IFERROR(VLOOKUP(V21,Curr!$B$2:$C$13,2,FALSE),0) -> 10.8 | X21: =U21*W21 -> 0 | Y21: =Q21 -> 0 | Z21: =+Y21*R21 -> 0 | AA21: EUR | AB21: =IFERROR(VLOOKUP(AA21,Curr!$B$2:$C$13,2,FALSE),0) -> 10.8 | AC21: =+Y21*AB21*R21 -> 0 | AD21: =+AC21-X21 -> 0 | AE21: =IFERROR(AD21/AC21,0) -> 0
C22: Day 4 | D22: Hotel | E22: 30.06.2026 | F22: 03.07.2026 | J22: Reykjavik: Check in to your accommodation for a 3 night stay - Grandi by Center Hotels - 2 x Standard twin/double - breakfast included | P22: https://app.hotelbeds.com/factsheet/stay/749447?check_in=30-06-2026&check_out=03-07-2026&occupancy=2~0_2~0&packaging=true | Q22: 1634 | R22: 1 | S22: =+Q22*R22 -> 1634 | T22: 0 | U22: =S22*(1-T22) -> 1634 | V22: EUR | W22: =IFERROR(VLOOKUP(V22,Curr!$B$2:$C$13,2,FALSE),0) -> 10.8 | X22: =U22*W22 -> 17647.2 | Y22: =Q22/0.85 -> 1922.3529 | Z22: =+Y22*R22 -> 1922.3529 | AA22: EUR | AB22: =IFERROR(VLOOKUP(AA22,Curr!$B$2:$C$13,2,FALSE),0) -> 10.8 | AC22: =+Y22*AB22*R22 -> 20761.412 | AD22: =+AC22-X22 -> 3114.2118 | AE22: =IFERROR(AD22/AC22,0) -> 0.15
C23: Day 4 | D23: Leisure | E23: 30.06.2026 | J23: Reykjavik: Spend time at leisure | Q23: 0 | R23: 0 | S23: =+Q23*R23 -> 0 | T23: 0 | U23: =S23*(1-T23) -> 0 | V23: EUR | W23: =IFERROR(VLOOKUP(V23,Curr!$B$2:$C$13,2,FALSE),0) -> 10.8 | X23: =U23*W23 -> 0 | Y23: =Q23 -> 0 | Z23: =+Y23*R23 -> 0 | AA23: EUR | AB23: =IFERROR(VLOOKUP(AA23,Curr!$B$2:$C$13,2,FALSE),0) -> 10.8 | AC23: =+Y23*AB23*R23 -> 0 | AD23: =+AC23-X23 -> 0 | AE23: =IFERROR(AD23/AC23,0) -> 0
S24: =+Q24*R24 -> 0 | T24: 0 | U24: =S24*(1-T24) -> 0 | V24: EUR | W24: =IFERROR(VLOOKUP(V24,Curr!$B$2:$C$13,2,FALSE),0) -> 10.8 | X24: =U24*W24 -> 0 | Y24: =Q24 -> 0 | Z24: =+Y24*R24 -> 0 | AA24: EUR | AB24: =IFERROR(VLOOKUP(AA24,Curr!$B$2:$C$13,2,FALSE),0) -> 10.8 | AC24: =+Y24*AB24*R24 -> 0 | AD24: =+AC24-X24 -> 0 | AE24: =IFERROR(AD24/AC24,0) -> 0
C25: Day 5 | D25: Activity | E25: 01.07.2026 | J25: Reykjavik: FlyOver Iceland - Time: 12:30 pm - 1:30 pm - Meeting point: Fiskislóð 43 - Includes: Entry or admission fee, FlyOver Iceland Pursuit | P25: https://booknordics.com/iceland/western-iceland/reykjavik/flyover-iceland | Q25: 35 | R25: 4 | S25: =+Q25*R25 -> 140 | T25: 0.2 | U25: =S25*(1-T25) -> 112 | V25: EUR | W25: =IFERROR(VLOOKUP(V25,Curr!$B$2:$C$13,2,FALSE),0) -> 10.8 | X25: =U25*W25 -> 1209.6 | Y25: =Q25 -> 35 | Z25: =+Y25*R25 -> 140 | AA25: EUR | AB25: =IFERROR(VLOOKUP(AA25,Curr!$B$2:$C$13,2,FALSE),0) -> 10.8 | AC25: =+Y25*AB25*R25 -> 1512 | AD25: =+AC25-X25 -> 302.4 | AE25: =IFERROR(AD25/AC25,0) -> 0.2
C26: Day 5 | D26: Leisure | E26: 01.07.2026 | J26: Reykjavik: Spend time at leisure | Q26: 0 | R26: 0 | S26: =+Q26*R26 -> 0 | T26: 0 | U26: =S26*(1-T26) -> 0 | V26: EUR | W26: =IFERROR(VLOOKUP(V26,Curr!$B$2:$C$13,2,FALSE),0) -> 10.8 | X26: =U26*W26 -> 0 | Y26: =Q26 -> 0 | Z26: =+Y26*R26 -> 0 | AA26: EUR | AB26: =IFERROR(VLOOKUP(AA26,Curr!$B$2:$C$13,2,FALSE),0) -> 10.8 | AC26: =+Y26*AB26*R26 -> 0 | AD26: =+AC26-X26 -> 0 | AE26: =IFERROR(AD26/AC26,0) -> 0
C27: Day 5 | D27: Activity | E27: 01.07.2026 | J27: Reykjavík: Classic Whale Watching under the Midnight Sun - Time: 8:30 pm - 11:30 pm - Meeting point: Elding ticket office, Ægisgarður 5c -Includes: 2-3,5 hours whale watching tour, Access to our Wildlife Exhibition, Excellent live commentary in English, Use of warm overalls & mellow music | P27: https://booknordics.com/iceland/western-iceland/reykjavik/reykjavik-classic-whales-in-the-midnight-sun | Q27: 127 | R27: 4 | S27: =+Q27*R27 -> 508 | T27: 0.25 | U27: =S27*(1-T27) -> 381 | V27: EUR | W27: =IFERROR(VLOOKUP(V27,Curr!$B$2:$C$13,2,FALSE),0) -> 10.8 | X27: =U27*W27 -> 4114.8 | Y27: =Q27 -> 127 | Z27: =+Y27*R27 -> 508 | AA27: EUR | AB27: =IFERROR(VLOOKUP(AA27,Curr!$B$2:$C$13,2,FALSE),0) -> 10.8 | AC27: =+Y27*AB27*R27 -> 5486.4 | AD27: =+AC27-X27 -> 1371.6 | AE27: =IFERROR(AD27/AC27,0) -> 0.25
S28: =+Q28*R28 -> 0 | T28: 0 | U28: =S28*(1-T28) -> 0 | V28: EUR | W28: =IFERROR(VLOOKUP(V28,Curr!$B$2:$C$13,2,FALSE),0) -> 10.8 | X28: =U28*W28 -> 0 | Y28: =Q28 -> 0 | Z28: =+Y28*R28 -> 0 | AA28: EUR | AB28: =IFERROR(VLOOKUP(AA28,Curr!$B$2:$C$13,2,FALSE),0) -> 10.8 | AC28: =+Y28*AB28*R28 -> 0 | AD28: =+AC28-X28 -> 0 | AE28: =IFERROR(AD28/AC28,0) -> 0
C29: Day 6 | D29: Activity | E29: 02.07.2026 | J29: Reykjavik: Sky Lagoon Sér Pass with Transfer - Time: 2:00 pm - 4:30 pm - Meeting point: Hotel Pick up - Includes: Bus fare, Sky Lagoon Sér Admission, Complete Seven-step Ritual, Private Changing Facilities, Towel | P29: https://booknordics.com/iceland/western-iceland/reykjavik/sky-lagoon-sky-pass-with-transfer | Q29: 167 | R29: 4 | S29: =+Q29*R29 -> 668 | T29: 0.2 | U29: =S29*(1-T29) -> 534.4 | V29: EUR | W29: =IFERROR(VLOOKUP(V29,Curr!$B$2:$C$13,2,FALSE),0) -> 10.8 | X29: =U29*W29 -> 5771.52 | Y29: =Q29 -> 167 | Z29: =+Y29*R29 -> 668 | AA29: EUR | AB29: =IFERROR(VLOOKUP(AA29,Curr!$B$2:$C$13,2,FALSE),0) -> 10.8 | AC29: =+Y29*AB29*R29 -> 7214.4 | AD29: =+AC29-X29 -> 1442.88 | AE29: =IFERROR(AD29/AC29,0) -> 0.2
C30: Day 6 | D30: Leisure | E30: 02.07.2026 | J30: Reykjavik: Spend time at leisure | Q30: 0 | R30: 0 | S30: =+Q30*R30 -> 0 | T30: 0 | U30: =S30*(1-T30) -> 0 | V30: EUR | W30: =IFERROR(VLOOKUP(V30,Curr!$B$2:$C$13,2,FALSE),0) -> 10.8 | X30: =U30*W30 -> 0 | Y30: =Q30 -> 0 | Z30: =+Y30*R30 -> 0 | AA30: EUR | AB30: =IFERROR(VLOOKUP(AA30,Curr!$B$2:$C$13,2,FALSE),0) -> 10.8 | AC30: =+Y30*AB30*R30 -> 0 | AD30: =+AC30-X30 -> 0 | AE30: =IFERROR(AD30/AC30,0) -> 0
S31: =+Q31*R31 -> 0 | T31: 0 | U31: =S31*(1-T31) -> 0 | V31: EUR | W31: =IFERROR(VLOOKUP(V31,Curr!$B$2:$C$13,2,FALSE),0) -> 10.8 | X31: =U31*W31 -> 0 | Y31: =Q31 -> 0 | Z31: =+Y31*R31 -> 0 | AA31: EUR | AB31: =IFERROR(VLOOKUP(AA31,Curr!$B$2:$C$13,2,FALSE),0) -> 10.8 | AC31: =+Y31*AB31*R31 -> 0 | AD31: =+AC31-X31 -> 0 | AE31: =IFERROR(AD31/AC31,0) -> 0
C32: Day 7 | D32: Drive | E32: 03.07.2026 | J32: Reykjavik: Drive to Keflavik Airport | Q32: 0 | R32: 0 | S32: =+Q32*R32 -> 0 | T32: 0 | U32: =S32*(1-T32) -> 0 | V32: EUR | W32: =IFERROR(VLOOKUP(V32,Curr!$B$2:$C$13,2,FALSE),0) -> 10.8 | X32: =U32*W32 -> 0 | Y32: =Q32 -> 0 | Z32: =+Y32*R32 -> 0 | AA32: EUR | AB32: =IFERROR(VLOOKUP(AA32,Curr!$B$2:$C$13,2,FALSE),0) -> 10.8 | AC32: =+Y32*AB32*R32 -> 0 | AD32: =+AC32-X32 -> 0 | AE32: =IFERROR(AD32/AC32,0) -> 0
C33: Day 7 | D33: Car | E33: 03.07.2026 | J33: Keflavik: Deliver your rental car at the airport car rental office | Q33: 0 | R33: 0 | S33: =+Q33*R33 -> 0 | T33: 0 | U33: =S33*(1-T33) -> 0 | V33: EUR | W33: =IFERROR(VLOOKUP(V33,Curr!$B$2:$C$13,2,FALSE),0) -> 10.8 | X33: =U33*W33 -> 0 | Y33: =Q33 -> 0 | Z33: =+Y33*R33 -> 0 | AA33: EUR | AB33: =IFERROR(VLOOKUP(AA33,Curr!$B$2:$C$13,2,FALSE),0) -> 10.8 | AC33: =+Y33*AB33*R33 -> 0 | AD33: =+AC33-X33 -> 0 | AE33: =IFERROR(AD33/AC33,0) -> 0
C34: Day 7 | D34: Flight | E34: 03.07.2026 | J34: Keflavik: Flight to Oslo - Time: 09:10 am - 1:50 pm - Luggage included: 1 x 23 kg check in and 1 x 8 kg carry on per person | P34: https://www.sas.no/book/flights/?search=OW_KEF-OSL-20260703_a4c0i0y0&view=upsell&bookingFlow=revenue&out_flight_number=SK4788&skyscanner_redirectid=RhZvBkUmTrSXl9DScsN5CA&utm_source=skyscanner&utm_medium=metasearch&utm_campaign=skyscanner_metasearch&sortBy=rec&out_class=ECONOMY&out_sub_class=FLEX | Q34: 3747 | R34: 4 | S34: =+Q34*R34 -> 14988 | T34: 0 | U34: =S34*(1-T34) -> 14988 | V34: NOK | W34: =IFERROR(VLOOKUP(V34,Curr!$B$2:$C$13,2,FALSE),0) -> 1 | X34: =U34*W34 -> 14988 | Y34: =Q34/11/0.8 -> 425.79545 | Z34: =+Y34*R34 -> 1703.1818 | AA34: EUR | AB34: =IFERROR(VLOOKUP(AA34,Curr!$B$2:$C$13,2,FALSE),0) -> 10.8 | AC34: =+Y34*AB34*R34 -> 18394.364 | AD34: =+AC34-X34 -> 3406.3636 | AE34: =IFERROR(AD34/AC34,0) -> 0.18518519
C35: Day 7 | D35: Transfer | E35: 03.07.2026 | J35: Oslo: Private transfer to your accommodation | Q35: 1900 | R35: 1 | S35: =+Q35*R35 -> 1900 | T35: 0 | U35: =S35*(1-T35) -> 1900 | V35: NOK | W35: =IFERROR(VLOOKUP(V35,Curr!$B$2:$C$13,2,FALSE),0) -> 1 | X35: =U35*W35 -> 1900 | Y35: =Q35/11/0.8 -> 215.90909 | Z35: =+Y35*R35 -> 215.90909 | AA35: EUR | AB35: =IFERROR(VLOOKUP(AA35,Curr!$B$2:$C$13,2,FALSE),0) -> 10.8 | AC35: =+Y35*AB35*R35 -> 2331.8182 | AD35: =+AC35-X35 -> 431.81818 | AE35: =IFERROR(AD35/AC35,0) -> 0.18518519
C36: Day 7 | D36: Hotel | E36: 03.07.2026 | F36: 05.07.2026 | J36: Oslo: Check in to your accommodation for a 2 night stay - Clarion Hotel The Hub - 2 x double room - breakfast included | P36: https://app.hotelbeds.com/factsheet/stay/7398?check_in=03-07-2026&check_out=05-07-2026&occupancy=2~0_2~0&packaging=true | Q36: 1336 | R36: 1 | S36: =+Q36*R36 -> 1336 | T36: 0 | U36: =S36*(1-T36) -> 1336 | V36: EUR | W36: =IFERROR(VLOOKUP(V36,Curr!$B$2:$C$13,2,FALSE),0) -> 10.8 | X36: =U36*W36 -> 14428.8 | Y36: =Q36/0.85 -> 1571.7647 | Z36: =+Y36*R36 -> 1571.7647 | AA36: EUR | AB36: =IFERROR(VLOOKUP(AA36,Curr!$B$2:$C$13,2,FALSE),0) -> 10.8 | AC36: =+Y36*AB36*R36 -> 16975.059 | AD36: =+AC36-X36 -> 2546.2588 | AE36: =IFERROR(AD36/AC36,0) -> 0.15
C37: Day 7 | D37: Leisure | E37: 03.07.2026 | J37: Oslo: Spend time at leisure | Q37: 0 | R37: 0 | S37: =+Q37*R37 -> 0 | T37: 0 | U37: =S37*(1-T37) -> 0 | V37: EUR | W37: =IFERROR(VLOOKUP(V37,Curr!$B$2:$C$13,2,FALSE),0) -> 10.8 | X37: =U37*W37 -> 0 | Y37: =Q37 -> 0 | Z37: =+Y37*R37 -> 0 | AA37: EUR | AB37: =IFERROR(VLOOKUP(AA37,Curr!$B$2:$C$13,2,FALSE),0) -> 10.8 | AC37: =+Y37*AB37*R37 -> 0 | AD37: =+AC37-X37 -> 0 | AE37: =IFERROR(AD37/AC37,0) -> 0
S38: =+Q38*R38 -> 0 | T38: 0 | U38: =S38*(1-T38) -> 0 | V38: EUR | W38: =IFERROR(VLOOKUP(V38,Curr!$B$2:$C$13,2,FALSE),0) -> 10.8 | X38: =U38*W38 -> 0 | Y38: =Q38 -> 0 | Z38: =+Y38*R38 -> 0 | AA38: EUR | AB38: =IFERROR(VLOOKUP(AA38,Curr!$B$2:$C$13,2,FALSE),0) -> 10.8 | AC38: =+Y38*AB38*R38 -> 0 | AD38: =+AC38-X38 -> 0 | AE38: =IFERROR(AD38/AC38,0) -> 0
C39: Day 8 | D39: Activity | E39: 04.07.2026 | J39: Oslo: Fjord Sightseeing Cruise by 100% Electric Boat - Time: 1:30 pm - 3:30 pm - Meeting point: Rådhusbrygge 4, Platform E - Includes: Oslo Fjord archipelago cruise by electric boat, Cafeteria with snacks and drinks for purchase, "Voice of Norway" Audio guide for download, Stop at the Bygdøy peninsula near to museums | P39: https://booknordics.com/norway/eastern-norway/oslo/oslofjord-sightseeing-cruise | Q39: 40 | R39: 4 | S39: =+Q39*R39 -> 160 | T39: 0.2 | U39: =S39*(1-T39) -> 128 | V39: EUR | W39: =IFERROR(VLOOKUP(V39,Curr!$B$2:$C$13,2,FALSE),0) -> 10.8 | X39: =U39*W39 -> 1382.4 | Y39: =Q39 -> 40 | Z39: =+Y39*R39 -> 160 | AA39: EUR | AB39: =IFERROR(VLOOKUP(AA39,Curr!$B$2:$C$13,2,FALSE),0) -> 10.8 | AC39: =+Y39*AB39*R39 -> 1728 | AD39: =+AC39-X39 -> 345.6 | AE39: =IFERROR(AD39/AC39,0) -> 0.2
C40: Day 8 | D40: Leisure | E40: 04.07.2026 | J40: Oslo: Spend time at leisure | Q40: 0 | R40: 0 | S40: =+Q40*R40 -> 0 | T40: 0 | U40: =S40*(1-T40) -> 0 | V40: EUR | W40: =IFERROR(VLOOKUP(V40,Curr!$B$2:$C$13,2,FALSE),0) -> 10.8 | X40: =U40*W40 -> 0 | Y40: =Q40 -> 0 | Z40: =+Y40*R40 -> 0 | AA40: EUR | AB40: =IFERROR(VLOOKUP(AA40,Curr!$B$2:$C$13,2,FALSE),0) -> 10.8 | AC40: =+Y40*AB40*R40 -> 0 | AD40: =+AC40-X40 -> 0 | AE40: =IFERROR(AD40/AC40,0) -> 0
S41: =+Q41*R41 -> 0 | T41: 0 | U41: =S41*(1-T41) -> 0 | V41: EUR | W41: =IFERROR(VLOOKUP(V41,Curr!$B$2:$C$13,2,FALSE),0) -> 10.8 | X41: =U41*W41 -> 0 | Y41: =Q41 -> 0 | Z41: =+Y41*R41 -> 0 | AA41: EUR | AB41: =IFERROR(VLOOKUP(AA41,Curr!$B$2:$C$13,2,FALSE),0) -> 10.8 | AC41: =+Y41*AB41*R41 -> 0 | AD41: =+AC41-X41 -> 0 | AE41: =IFERROR(AD41/AC41,0) -> 0
C42: Day 9 | D42: Transfer | E42: 05.07.2026 | J42: Oslo: Self transfer to Oslo Central Station | Q42: 0 | R42: 0 | S42: =+Q42*R42 -> 0 | T42: 0 | U42: =S42*(1-T42) -> 0 | V42: EUR | W42: =IFERROR(VLOOKUP(V42,Curr!$B$2:$C$13,2,FALSE),0) -> 10.8 | X42: =U42*W42 -> 0 | Y42: =Q42 -> 0 | Z42: =+Y42*R42 -> 0 | AA42: EUR | AB42: =IFERROR(VLOOKUP(AA42,Curr!$B$2:$C$13,2,FALSE),0) -> 10.8 | AC42: =+Y42*AB42*R42 -> 0 | AD42: =+AC42-X42 -> 0 | AE42: =IFERROR(AD42/AC42,0) -> 0
C43: Day 9 | D43: Activity | E43: 05.07.2026 | J43: Oslo: Norway in a Nutshell tour to Bergen, with a 1 night stay in Gudvangen - Time: 08:23 am - 5:00 pm - Includes: Train tickets Oslo to Bergen, Train tickets Flåm to Myrdal, Fjord Cruisee Flåm to Gudvangen | P43: https://www.fjordtours.com/en/norway/booking/tour/norway-in-a-nutshell/b1205fbc-1045-45fb-a099-1d3be8f4aa58/5c582628-ae09-482f-93bf-e41e16e39ac0 | Q43: 3474 | R43: 4 | S43: =+Q43*R43 -> 13896 | T43: 0.12 | U43: =S43*(1-T43) -> 12228.48 | V43: NOK | W43: =IFERROR(VLOOKUP(V43,Curr!$B$2:$C$13,2,FALSE),0) -> 1 | X43: =U43*W43 -> 12228.48 | Y43: =Q43/11/0.9 -> 350.90909 | Z43: =+Y43*R43 -> 1403.6364 | AA43: EUR | AB43: =IFERROR(VLOOKUP(AA43,Curr!$B$2:$C$13,2,FALSE),0) -> 10.8 | AC43: =+Y43*AB43*R43 -> 15159.273 | AD43: =+AC43-X43 -> 2930.7927 | AE43: =IFERROR(AD43/AC43,0) -> 0.19333333
C44: Day 9 | D44: Transfer | E44: 05.07.2026 | J44: Gudvangen: Self transfer to your accommodation | Q44: 0 | R44: 0 | S44: =+Q44*R44 -> 0 | T44: 0 | U44: =S44*(1-T44) -> 0 | V44: EUR | W44: =IFERROR(VLOOKUP(V44,Curr!$B$2:$C$13,2,FALSE),0) -> 10.8 | X44: =U44*W44 -> 0 | Y44: =Q44 -> 0 | Z44: =+Y44*R44 -> 0 | AA44: EUR | AB44: =IFERROR(VLOOKUP(AA44,Curr!$B$2:$C$13,2,FALSE),0) -> 10.8 | AC44: =+Y44*AB44*R44 -> 0 | AD44: =+AC44-X44 -> 0 | AE44: =IFERROR(AD44/AC44,0) -> 0
C45: Day 9 | D45: Hotel | E45: 05.07.2026 | F45: 06.07.2026 | J45: Gudvangen: Check in to your accommodation for a 1 night stay - Gudvangen Fjordtell - 2 x double room - breakfast included | P45: https://app.hotelbeds.com/factsheet/stay/1087626?check_in=05-07-2026&check_out=06-07-2026&occupancy=2~0_2~0&packaging=true | Q45: 1014 | R45: 1 | S45: =+Q45*R45 -> 1014 | T45: 0 | U45: =S45*(1-T45) -> 1014 | V45: EUR | W45: =IFERROR(VLOOKUP(V45,Curr!$B$2:$C$13,2,FALSE),0) -> 10.8 | X45: =U45*W45 -> 10951.2 | Y45: =Q45/0.85 -> 1192.9412 | Z45: =+Y45*R45 -> 1192.9412 | AA45: EUR | AB45: =IFERROR(VLOOKUP(AA45,Curr!$B$2:$C$13,2,FALSE),0) -> 10.8 | AC45: =+Y45*AB45*R45 -> 12883.765 | AD45: =+AC45-X45 -> 1932.5647 | AE45: =IFERROR(AD45/AC45,0) -> 0.15
C46: Day 9 | D46: Leisure | E46: 05.07.2026 | J46: Gudvangen: Spend time at leisure | Q46: 0 | R46: 0 | S46: =+Q46*R46 -> 0 | T46: 0 | U46: =S46*(1-T46) -> 0 | V46: EUR | W46: =IFERROR(VLOOKUP(V46,Curr!$B$2:$C$13,2,FALSE),0) -> 10.8 | X46: =U46*W46 -> 0 | Y46: =Q46 -> 0 | Z46: =+Y46*R46 -> 0 | AA46: EUR | AB46: =IFERROR(VLOOKUP(AA46,Curr!$B$2:$C$13,2,FALSE),0) -> 10.8 | AC46: =+Y46*AB46*R46 -> 0 | AD46: =+AC46-X46 -> 0 | AE46: =IFERROR(AD46/AC46,0) -> 0
S47: =+Q47*R47 -> 0 | T47: 0 | U47: =S47*(1-T47) -> 0 | V47: EUR | W47: =IFERROR(VLOOKUP(V47,Curr!$B$2:$C$13,2,FALSE),0) -> 10.8 | X47: =U47*W47 -> 0 | Y47: =Q47 -> 0 | Z47: =+Y47*R47 -> 0 | AA47: EUR | AB47: =IFERROR(VLOOKUP(AA47,Curr!$B$2:$C$13,2,FALSE),0) -> 10.8 | AC47: =+Y47*AB47*R47 -> 0 | AD47: =+AC47-X47 -> 0 | AE47: =IFERROR(AD47/AC47,0) -> 0
C48: Day 10 | D48: Transfer | E48: 06.07.2026 | J48: Gudvangen: Self transfer to Gudvangen Bus Stop | Q48: 0 | R48: 0 | S48: =+Q48*R48 -> 0 | T48: 0 | U48: =S48*(1-T48) -> 0 | V48: EUR | W48: =IFERROR(VLOOKUP(V48,Curr!$B$2:$C$13,2,FALSE),0) -> 10.8 | X48: =U48*W48 -> 0 | Y48: =Q48 -> 0 | Z48: =+Y48*R48 -> 0 | AA48: EUR | AB48: =IFERROR(VLOOKUP(AA48,Curr!$B$2:$C$13,2,FALSE),0) -> 10.8 | AC48: =+Y48*AB48*R48 -> 0 | AD48: =+AC48-X48 -> 0 | AE48: =IFERROR(AD48/AC48,0) -> 0
C49: Day 10 | D49: Activity | E49: 06.07.2026 | J49: Gudvangen: Norway in a Nutshell to Bergen - Time: 11:40 am - 2:15 pm - Includes: Bus Tickets Gudvangen to Voss, Train tickets Voss to Bergen | Q49: 0 | R49: 0 | S49: =+Q49*R49 -> 0 | T49: 0 | U49: =S49*(1-T49) -> 0 | V49: EUR | W49: =IFERROR(VLOOKUP(V49,Curr!$B$2:$C$13,2,FALSE),0) -> 10.8 | X49: =U49*W49 -> 0 | Y49: =Q49 -> 0 | Z49: =+Y49*R49 -> 0 | AA49: EUR | AB49: =IFERROR(VLOOKUP(AA49,Curr!$B$2:$C$13,2,FALSE),0) -> 10.8 | AC49: =+Y49*AB49*R49 -> 0 | AD49: =+AC49-X49 -> 0 | AE49: =IFERROR(AD49/AC49,0) -> 0
C50: Day 10 | D50: Transfer | E50: 06.07.2026 | J50: Bergen: Private transfer to your accommodation | P50: https://www.btservice.no/private-cruiseport-transfer | Q50: 1690 | R50: 1 | S50: =+Q50*R50 -> 1690 | T50: 0.15 | U50: =S50*(1-T50) -> 1436.5 | V50: NOK | W50: =IFERROR(VLOOKUP(V50,Curr!$B$2:$C$13,2,FALSE),0) -> 1 | X50: =U50*W50 -> 1436.5 | Y50: =Q50/11/0.9 -> 170.70707 | Z50: =+Y50*R50 -> 170.70707 | AA50: EUR | AB50: =IFERROR(VLOOKUP(AA50,Curr!$B$2:$C$13,2,FALSE),0) -> 10.8 | AC50: =+Y50*AB50*R50 -> 1843.6364 | AD50: =+AC50-X50 -> 407.13636 | AE50: =IFERROR(AD50/AC50,0) -> 0.22083333
C51: Day 10 | D51: Hotel | E51: 06.07.2026 | F51: 08.07.2026 | J51: Bergen: Check in to your accommodation for a 2 night stay - Clarion Hotel Admiral - 2 x double room - breakfast included | P51: https://app.hotelbeds.com/factsheet/stay/70255?check_in=06-07-2026&check_out=08-07-2026&occupancy=2~0_2~0&packaging=true | Q51: 1174 | R51: 1 | S51: =+Q51*R51 -> 1174 | T51: 0 | U51: =S51*(1-T51) -> 1174 | V51: EUR | W51: =IFERROR(VLOOKUP(V51,Curr!$B$2:$C$13,2,FALSE),0) -> 10.8 | X51: =U51*W51 -> 12679.2 | Y51: =Q51/0.85 -> 1381.1765 | Z51: =+Y51*R51 -> 1381.1765 | AA51: EUR | AB51: =IFERROR(VLOOKUP(AA51,Curr!$B$2:$C$13,2,FALSE),0) -> 10.8 | AC51: =+Y51*AB51*R51 -> 14916.706 | AD51: =+AC51-X51 -> 2237.5059 | AE51: =IFERROR(AD51/AC51,0) -> 0.15
C52: Day 10 | D52: Leisure | E52: 06.07.2026 | J52: Bergen: Spend time at leisure | Q52: 0 | R52: 0 | S52: =+Q52*R52 -> 0 | T52: 0 | U52: =S52*(1-T52) -> 0 | V52: EUR | W52: =IFERROR(VLOOKUP(V52,Curr!$B$2:$C$13,2,FALSE),0) -> 10.8 | X52: =U52*W52 -> 0 | Y52: =Q52 -> 0 | Z52: =+Y52*R52 -> 0 | AA52: EUR | AB52: =IFERROR(VLOOKUP(AA52,Curr!$B$2:$C$13,2,FALSE),0) -> 10.8 | AC52: =+Y52*AB52*R52 -> 0 | AD52: =+AC52-X52 -> 0 | AE52: =IFERROR(AD52/AC52,0) -> 0
S53: =+Q53*R53 -> 0 | T53: 0 | U53: =S53*(1-T53) -> 0 | V53: EUR | W53: =IFERROR(VLOOKUP(V53,Curr!$B$2:$C$13,2,FALSE),0) -> 10.8 | X53: =U53*W53 -> 0 | Y53: =Q53 -> 0 | Z53: =+Y53*R53 -> 0 | AA53: EUR | AB53: =IFERROR(VLOOKUP(AA53,Curr!$B$2:$C$13,2,FALSE),0) -> 10.8 | AC53: =+Y53*AB53*R53 -> 0 | AD53: =+AC53-X53 -> 0 | AE53: =IFERROR(AD53/AC53,0) -> 0
C54: Day 11 | D54: Activity | E54: 07.07.2026 | J54: Bergen: Fløybanen Funicular Tickets - Time: Flexible - Meeting point: Fløybanen | P54: https://www.floyen.no/floibanen/kjop-billetter | Q54: 200 | R54: 4 | S54: =+Q54*R54 -> 800 | T54: 0 | U54: =S54*(1-T54) -> 800 | V54: NOK | W54: =IFERROR(VLOOKUP(V54,Curr!$B$2:$C$13,2,FALSE),0) -> 1 | X54: =U54*W54 -> 800 | Y54: =Q54/11/0.8 -> 22.727273 | Z54: =+Y54*R54 -> 90.909091 | AA54: EUR | AB54: =IFERROR(VLOOKUP(AA54,Curr!$B$2:$C$13,2,FALSE),0) -> 10.8 | AC54: =+Y54*AB54*R54 -> 981.81818 | AD54: =+AC54-X54 -> 181.81818 | AE54: =IFERROR(AD54/AC54,0) -> 0.18518519
C55: Day 11 | D55: Leisure | E55: 07.07.2026 | J55: Bergen: Spend time at leisure | Q55: 0 | R55: 0 | S55: =+Q55*R55 -> 0 | T55: 0 | U55: =S55*(1-T55) -> 0 | V55: EUR | W55: =IFERROR(VLOOKUP(V55,Curr!$B$2:$C$13,2,FALSE),0) -> 10.8 | X55: =U55*W55 -> 0 | Y55: =Q55 -> 0 | Z55: =+Y55*R55 -> 0 | AA55: EUR | AB55: =IFERROR(VLOOKUP(AA55,Curr!$B$2:$C$13,2,FALSE),0) -> 10.8 | AC55: =+Y55*AB55*R55 -> 0 | AD55: =+AC55-X55 -> 0 | AE55: =IFERROR(AD55/AC55,0) -> 0
C56: Day 11 | D56: Activity | E56: 07.07.2026 | J56: Bergen: Mostraumen Majestic Fjord & Waterfall Cruise - Time: 5:00 pm - 7:00 pm - Meeting point: Börshopen Pier, Strandkaien 13 - Round-trip criose Bergen to Mostraumen to Bergen | P56: https://booknordics.com/norway/western-fjord-norway/bergen-and-hardanger/mostraumen-fjord-waterfall-cruise | Q56: 75 | R56: 4 | S56: =+Q56*R56 -> 300 | T56: 0.2 | U56: =S56*(1-T56) -> 240 | V56: EUR | W56: =IFERROR(VLOOKUP(V56,Curr!$B$2:$C$13,2,FALSE),0) -> 10.8 | X56: =U56*W56 -> 2592 | Y56: =Q56 -> 75 | Z56: =+Y56*R56 -> 300 | AA56: EUR | AB56: =IFERROR(VLOOKUP(AA56,Curr!$B$2:$C$13,2,FALSE),0) -> 10.8 | AC56: =+Y56*AB56*R56 -> 3240 | AD56: =+AC56-X56 -> 648 | AE56: =IFERROR(AD56/AC56,0) -> 0.2
S57: =+Q57*R57 -> 0 | T57: 0 | U57: =S57*(1-T57) -> 0 | V57: EUR | W57: =IFERROR(VLOOKUP(V57,Curr!$B$2:$C$13,2,FALSE),0) -> 10.8 | X57: =U57*W57 -> 0 | Y57: =Q57 -> 0 | Z57: =+Y57*R57 -> 0 | AA57: EUR | AB57: =IFERROR(VLOOKUP(AA57,Curr!$B$2:$C$13,2,FALSE),0) -> 10.8 | AC57: =+Y57*AB57*R57 -> 0 | AD57: =+AC57-X57 -> 0 | AE57: =IFERROR(AD57/AC57,0) -> 0
C58: Day 12 | D58: Transfer | E58: 08.07.2026 | J58: Bergen: Private transfer to Bergen Airport | P58: https://www.btservice.no/private-cruiseport-transfer | Q58: 2290 | R58: 1 | S58: =+Q58*R58 -> 2290 | T58: 0.15 | U58: =S58*(1-T58) -> 1946.5 | V58: NOK | W58: =IFERROR(VLOOKUP(V58,Curr!$B$2:$C$13,2,FALSE),0) -> 1 | X58: =U58*W58 -> 1946.5 | Y58: =Q58/11/0.9 -> 231.31313 | Z58: =+Y58*R58 -> 231.31313 | AA58: EUR | AB58: =IFERROR(VLOOKUP(AA58,Curr!$B$2:$C$13,2,FALSE),0) -> 10.8 | AC58: =+Y58*AB58*R58 -> 2498.1818 | AD58: =+AC58-X58 -> 551.68182 | AE58: =IFERROR(AD58/AC58,0) -> 0.22083333
C59: Day 12 | D59: Flight | E59: 08.07.2026 | J59: Bergen: Flight to Ålesund - Time: 11:00 am - 11:50 am - Luggage included: 1 x 23 kg check in and 1 x 8 kg carry on per person | P59: https://www.wideroe.no/booking/booking#/select-flight | Q59: 849 | R59: 4 | S59: =+Q59*R59 -> 3396 | T59: 0 | U59: =S59*(1-T59) -> 3396 | V59: NOK | W59: =IFERROR(VLOOKUP(V59,Curr!$B$2:$C$13,2,FALSE),0) -> 1 | X59: =U59*W59 -> 3396 | Y59: =Q59/11/0.8 -> 96.477273 | Z59: =+Y59*R59 -> 385.90909 | AA59: EUR | AB59: =IFERROR(VLOOKUP(AA59,Curr!$B$2:$C$13,2,FALSE),0) -> 10.8 | AC59: =+Y59*AB59*R59 -> 4167.8182 | AD59: =+AC59-X59 -> 771.81818 | AE59: =IFERROR(AD59/AC59,0) -> 0.18518519
C60: Day 12 | D60: Transfer | E60: 08.07.2026 | J60: Ålesund: Private transfer to your accommodation | Q60: 2290 | R60: 1 | S60: =+Q60*R60 -> 2290 | T60: 0 | U60: =S60*(1-T60) -> 2290 | V60: NOK | W60: =IFERROR(VLOOKUP(V60,Curr!$B$2:$C$13,2,FALSE),0) -> 1 | X60: =U60*W60 -> 2290 | Y60: =Q60/11/0.8 -> 260.22727 | Z60: =+Y60*R60 -> 260.22727 | AA60: EUR | AB60: =IFERROR(VLOOKUP(AA60,Curr!$B$2:$C$13,2,FALSE),0) -> 10.8 | AC60: =+Y60*AB60*R60 -> 2810.4545 | AD60: =+AC60-X60 -> 520.45455 | AE60: =IFERROR(AD60/AC60,0) -> 0.18518519
C61: Day 12 | D61: Hotel | E61: 08.07.2026 | J61: Ålesund: Check in to your accommodation for a 2 night stay - Quality Hotel Waterfront - 2 x double room - breakfast included | P61: https://app.hotelbeds.com/factsheet/stay/189134?check_in=08-07-2026&check_out=10-07-2026&occupancy=2~0_2~0&packaging=true | Q61: 890 | R61: 1 | S61: =+Q61*R61 -> 890 | T61: 0 | U61: =S61*(1-T61) -> 890 | V61: EUR | W61: =IFERROR(VLOOKUP(V61,Curr!$B$2:$C$13,2,FALSE),0) -> 10.8 | X61: =U61*W61 -> 9612 | Y61: =Q61/0.85 -> 1047.0588 | Z61: =+Y61*R61 -> 1047.0588 | AA61: EUR | AB61: =IFERROR(VLOOKUP(AA61,Curr!$B$2:$C$13,2,FALSE),0) -> 10.8 | AC61: =+Y61*AB61*R61 -> 11308.235 | AD61: =+AC61-X61 -> 1696.2353 | AE61: =IFERROR(AD61/AC61,0) -> 0.15
C62: Day 12 | D62: Leisure | E62: 08.07.2026 | J62: Ålesund: Spend time at leisure | Q62: 0 | R62: 0 | S62: =+Q62*R62 -> 0 | T62: 0 | U62: =S62*(1-T62) -> 0 | V62: EUR | W62: =IFERROR(VLOOKUP(V62,Curr!$B$2:$C$13,2,FALSE),0) -> 10.8 | X62: =U62*W62 -> 0 | Y62: =Q62 -> 0 | Z62: =+Y62*R62 -> 0 | AA62: EUR | AB62: =IFERROR(VLOOKUP(AA62,Curr!$B$2:$C$13,2,FALSE),0) -> 10.8 | AC62: =+Y62*AB62*R62 -> 0 | AD62: =+AC62-X62 -> 0 | AE62: =IFERROR(AD62/AC62,0) -> 0
Q63: 0 | R63: 0 | S63: =+Q63*R63 -> 0 | T63: 0 | U63: =S63*(1-T63) -> 0 | V63: EUR | W63: =IFERROR(VLOOKUP(V63,Curr!$B$2:$C$13,2,FALSE),0) -> 10.8 | X63: =U63*W63 -> 0 | Y63: =Q63 -> 0 | Z63: =+Y63*R63 -> 0 | AA63: EUR | AB63: =IFERROR(VLOOKUP(AA63,Curr!$B$2:$C$13,2,FALSE),0) -> 10.8 | AC63: =+Y63*AB63*R63 -> 0 | AD63: =+AC63-X63 -> 0 | AE63: =IFERROR(AD63/AC63,0) -> 0
C64: Day 13 | D64: Activity | E64: 09.07.2026 | J64: Ålesund: Round Trip Fjord Cruise to Geiranger - Time: 08:30 am - 6:00 pm - Departure Ålesund: 08:30 am - Meeting point: Skutvika, Nedre Strandgate 53 - Arrival Geiranger: 11:30 am - Departure Geiranger: 3:00 pm - Arrival Ålesund: 6:00 pm - Includes: Return tickets Ålesund - Geiranger - Ålesund, scenic fjord cruise | P64: https://www.geirangerfjord.no/ | Q64: 2139 | R64: 4 | S64: =+Q64*R64 -> 8556 | T64: 0 | U64: =S64*(1-T64) -> 8556 | V64: NOK | W64: =IFERROR(VLOOKUP(V64,Curr!$B$2:$C$13,2,FALSE),0) -> 1 | X64: =U64*W64 -> 8556 | Y64: =Q64/11/0.8 -> 243.06818 | Z64: =+Y64*R64 -> 972.27273 | AA64: EUR | AB64: =IFERROR(VLOOKUP(AA64,Curr!$B$2:$C$13,2,FALSE),0) -> 10.8 | AC64: =+Y64*AB64*R64 -> 10500.545 | AD64: =+AC64-X64 -> 1944.5455 | AE64: =IFERROR(AD64/AC64,0) -> 0.18518519
C65: Day 13 | D65: Leisure | E65: 09.07.2026 | J65: Ålesund: Spend time at leisure | Q65: 0 | R65: 0 | S65: =+Q65*R65 -> 0 | T65: 0 | U65: =S65*(1-T65) -> 0 | V65: EUR | W65: =IFERROR(VLOOKUP(V65,Curr!$B$2:$C$13,2,FALSE),0) -> 10.8 | X65: =U65*W65 -> 0 | Y65: =Q65 -> 0 | Z65: =+Y65*R65 -> 0 | AA65: EUR | AB65: =IFERROR(VLOOKUP(AA65,Curr!$B$2:$C$13,2,FALSE),0) -> 10.8 | AC65: =+Y65*AB65*R65 -> 0 | AD65: =+AC65-X65 -> 0 | AE65: =IFERROR(AD65/AC65,0) -> 0
S66: =+Q66*R66 -> 0 | T66: 0 | U66: =S66*(1-T66) -> 0 | V66: EUR | W66: =IFERROR(VLOOKUP(V66,Curr!$B$2:$C$13,2,FALSE),0) -> 10.8 | X66: =U66*W66 -> 0 | Y66: =Q66 -> 0 | Z66: =+Y66*R66 -> 0 | AA66: EUR | AB66: =IFERROR(VLOOKUP(AA66,Curr!$B$2:$C$13,2,FALSE),0) -> 10.8 | AC66: =+Y66*AB66*R66 -> 0 | AD66: =+AC66-X66 -> 0 | AE66: =IFERROR(AD66/AC66,0) -> 0
C67: Day 14 | D67: Transfer | E67: 10.07.2026 | J67: Ålesund: Private transfer to Ålesund Airport | Q67: 2290 | R67: 1 | S67: =+Q67*R67 -> 2290 | T67: 0 | U67: =S67*(1-T67) -> 2290 | V67: NOK | W67: =IFERROR(VLOOKUP(V67,Curr!$B$2:$C$13,2,FALSE),0) -> 1 | X67: =U67*W67 -> 2290 | Y67: =Q67/11/0.8 -> 260.22727 | Z67: =+Y67*R67 -> 260.22727 | AA67: EUR | AB67: =IFERROR(VLOOKUP(AA67,Curr!$B$2:$C$13,2,FALSE),0) -> 10.8 | AC67: =+Y67*AB67*R67 -> 2810.4545 | AD67: =+AC67-X67 -> 520.45455 | AE67: =IFERROR(AD67/AC67,0) -> 0.18518519
C68: Day 14 | D68: Flight | E68: 10.07.2026 | J68: Ålesund: Flight to Oslo - Time: 4:15 pm - 5:10 pm - Luggage included: 1 x 23 kg check in and 1 x 8 kg carry on per person | P68: https://www.wideroe.no/booking/booking#/select-flight | Q68: 1900 | R68: 0 | S68: =+Q68*R68 -> 0 | T68: 0 | U68: =S68*(1-T68) -> 0 | V68: EUR | W68: =IFERROR(VLOOKUP(V68,Curr!$B$2:$C$13,2,FALSE),0) -> 10.8 | X68: =U68*W68 -> 0 | Y68: =Q68 -> 1900 | Z68: =+Y68*R68 -> 0 | AA68: EUR | AB68: =IFERROR(VLOOKUP(AA68,Curr!$B$2:$C$13,2,FALSE),0) -> 10.8 | AC68: =+Y68*AB68*R68 -> 0 | AD68: =+AC68-X68 -> 0 | AE68: =IFERROR(AD68/AC68,0) -> 0
C69: Day 14 | D69: Transfer | E69: 10.07.2026 | J69: Oslo: Self transfer to your accommodation | Q69: 0 | R69: 0 | S69: =+Q69*R69 -> 0 | T69: 0 | U69: =S69*(1-T69) -> 0 | V69: EUR | W69: =IFERROR(VLOOKUP(V69,Curr!$B$2:$C$13,2,FALSE),0) -> 10.8 | X69: =U69*W69 -> 0 | Y69: =Q69 -> 0 | Z69: =+Y69*R69 -> 0 | AA69: EUR | AB69: =IFERROR(VLOOKUP(AA69,Curr!$B$2:$C$13,2,FALSE),0) -> 10.8 | AC69: =+Y69*AB69*R69 -> 0 | AD69: =+AC69-X69 -> 0 | AE69: =IFERROR(AD69/AC69,0) -> 0
C70: Day 14 | D70: Hotel | E70: 10.07.2026 | J70: Oslo: Check in to your accommodation for a 1 night stay -Clarion Hotel Oslo Airport - 2 x double room - breakfast included | P70: https://app.hotelbeds.com/factsheet/stay/107785?check_in=10-07-2026&check_out=11-07-2026&occupancy=2~0_2~0&packaging=true | Q70: 226 | R70: 1 | S70: =+Q70*R70 -> 226 | T70: 0 | U70: =S70*(1-T70) -> 226 | V70: EUR | W70: =IFERROR(VLOOKUP(V70,Curr!$B$2:$C$13,2,FALSE),0) -> 10.8 | X70: =U70*W70 -> 2440.8 | Y70: =Q70/0.85 -> 265.88235 | Z70: =+Y70*R70 -> 265.88235 | AA70: EUR | AB70: =IFERROR(VLOOKUP(AA70,Curr!$B$2:$C$13,2,FALSE),0) -> 10.8 | AC70: =+Y70*AB70*R70 -> 2871.5294 | AD70: =+AC70-X70 -> 430.72941 | AE70: =IFERROR(AD70/AC70,0) -> 0.15
C71: Day 14 | D71: Leisure | E71: 10.07.2026 | J71: Oslo: Spend time at leisure | Q71: 0 | R71: 0 | S71: =+Q71*R71 -> 0 | T71: 0 | U71: =S71*(1-T71) -> 0 | V71: EUR | W71: =IFERROR(VLOOKUP(V71,Curr!$B$2:$C$13,2,FALSE),0) -> 10.8 | X71: =U71*W71 -> 0 | Y71: =Q71 -> 0 | Z71: =+Y71*R71 -> 0 | AA71: EUR | AB71: =IFERROR(VLOOKUP(AA71,Curr!$B$2:$C$13,2,FALSE),0) -> 10.8 | AC71: =+Y71*AB71*R71 -> 0 | AD71: =+AC71-X71 -> 0 | AE71: =IFERROR(AD71/AC71,0) -> 0
S72: =+Q72*R72 -> 0 | T72: 0 | U72: =S72*(1-T72) -> 0 | V72: EUR | W72: =IFERROR(VLOOKUP(V72,Curr!$B$2:$C$13,2,FALSE),0) -> 10.8 | X72: =U72*W72 -> 0 | Y72: =Q72 -> 0 | Z72: =+Y72*R72 -> 0 | AA72: EUR | AB72: =IFERROR(VLOOKUP(AA72,Curr!$B$2:$C$13,2,FALSE),0) -> 10.8 | AC72: =+Y72*AB72*R72 -> 0 | AD72: =+AC72-X72 -> 0 | AE72: =IFERROR(AD72/AC72,0) -> 0
C73: Day 15 | D73: Transfer | E73: 11.07.2026 | J73: Oslo: Self transfer to Oslo Airport | Q73: 0 | R73: 0 | S73: =+Q73*R73 -> 0 | T73: 0 | U73: =S73*(1-T73) -> 0 | V73: EUR | W73: =IFERROR(VLOOKUP(V73,Curr!$B$2:$C$13,2,FALSE),0) -> 10.8 | X73: =U73*W73 -> 0 | Y73: =Q73 -> 0 | Z73: =+Y73*R73 -> 0 | AA73: EUR | AB73: =IFERROR(VLOOKUP(AA73,Curr!$B$2:$C$13,2,FALSE),0) -> 10.8 | AC73: =+Y73*AB73*R73 -> 0 | AD73: =+AC73-X73 -> 0 | AE73: =IFERROR(AD73/AC73,0) -> 0
C74: Day 15 | D74: Departure | E74: 11.07.2026 | J74: Oslo: Departure home | Q74: 0 | R74: 0 | S74: =+Q74*R74 -> 0 | T74: 0 | U74: =S74*(1-T74) -> 0 | V74: EUR | W74: =IFERROR(VLOOKUP(V74,Curr!$B$2:$C$13,2,FALSE),0) -> 10.8 | X74: =U74*W74 -> 0 | Y74: =Q74 -> 0 | Z74: =+Y74*R74 -> 0 | AA74: EUR | AB74: =IFERROR(VLOOKUP(AA74,Curr!$B$2:$C$13,2,FALSE),0) -> 10.8 | AC74: =+Y74*AB74*R74 -> 0 | AD74: =+AC74-X74 -> 0 | AE74: =IFERROR(AD74/AC74,0) -> 0
S75: =+Q75*R75 -> 0 | T75: 0 | U75: =S75*(1-T75) -> 0 | V75: EUR | W75: =IFERROR(VLOOKUP(V75,Curr!$B$2:$C$13,2,FALSE),0) -> 10.8 | X75: =U75*W75 -> 0 | Y75: =Q75 -> 0 | Z75: =+Y75*R75 -> 0 | AA75: EUR | AB75: =IFERROR(VLOOKUP(AA75,Curr!$B$2:$C$13,2,FALSE),0) -> 10.8 | AC75: =+Y75*AB75*R75 -> 0 | AD75: =+AC75-X75 -> 0 | AE75: =IFERROR(AD75/AC75,0) -> 0
S76: =+Q76*R76 -> 0 | T76: 0 | U76: =S76*(1-T76) -> 0 | V76: EUR | W76: =IFERROR(VLOOKUP(V76,Curr!$B$2:$C$13,2,FALSE),0) -> 10.8 | X76: =U76*W76 -> 0 | Y76: =Q76 -> 0 | Z76: =+Y76*R76 -> 0 | AA76: EUR | AB76: =IFERROR(VLOOKUP(AA76,Curr!$B$2:$C$13,2,FALSE),0) -> 10.8 | AC76: =+Y76*AB76*R76 -> 0 | AD76: =+AC76-X76 -> 0 | AE76: =IFERROR(AD76/AC76,0) -> 0
S77: =+Q77*R77 -> 0 | T77: 0 | U77: =S77*(1-T77) -> 0 | V77: EUR | W77: =IFERROR(VLOOKUP(V77,Curr!$B$2:$C$13,2,FALSE),0) -> 10.8 | X77: =U77*W77 -> 0 | Y77: =Q77 -> 0 | Z77: =+Y77*R77 -> 0 | AA77: EUR | AB77: =IFERROR(VLOOKUP(AA77,Curr!$B$2:$C$13,2,FALSE),0) -> 10.8 | AC77: =+Y77*AB77*R77 -> 0 | AD77: =+AC77-X77 -> 0 | AE77: =IFERROR(AD77/AC77,0) -> 0
S78: =+Q78*R78 -> 0 | T78: 0 | U78: =S78*(1-T78) -> 0 | V78: EUR | W78: =IFERROR(VLOOKUP(V78,Curr!$B$2:$C$13,2,FALSE),0) -> 10.8 | X78: =U78*W78 -> 0 | Y78: =Q78 -> 0 | Z78: =+Y78*R78 -> 0 | AA78: EUR | AB78: =IFERROR(VLOOKUP(AA78,Curr!$B$2:$C$13,2,FALSE),0) -> 10.8 | AC78: =+Y78*AB78*R78 -> 0 | AD78: =+AC78-X78 -> 0 | AE78: =IFERROR(AD78/AC78,0) -> 0
S79: =+Q79*R79 -> 0 | T79: 0 | U79: =S79*(1-T79) -> 0 | V79: EUR | W79: =IFERROR(VLOOKUP(V79,Curr!$B$2:$C$13,2,FALSE),0) -> 10.8 | X79: =U79*W79 -> 0 | Y79: =Q79 -> 0 | Z79: =+Y79*R79 -> 0 | AA79: EUR | AB79: =IFERROR(VLOOKUP(AA79,Curr!$B$2:$C$13,2,FALSE),0) -> 10.8 | AC79: =+Y79*AB79*R79 -> 0 | AD79: =+AC79-X79 -> 0 | AE79: =IFERROR(AD79/AC79,0) -> 0
S80: =+Q80*R80 -> 0 | T80: 0 | U80: =S80*(1-T80) -> 0 | V80: EUR | W80: =IFERROR(VLOOKUP(V80,Curr!$B$2:$C$13,2,FALSE),0) -> 10.8 | X80: =U80*W80 -> 0 | Y80: =Q80 -> 0 | Z80: =+Y80*R80 -> 0 | AA80: EUR | AB80: =IFERROR(VLOOKUP(AA80,Curr!$B$2:$C$13,2,FALSE),0) -> 10.8 | AC80: =+Y80*AB80*R80 -> 0 | AD80: =+AC80-X80 -> 0 | AE80: =IFERROR(AD80/AC80,0) -> 0
S81: =+Q81*R81 -> 0 | T81: 0 | U81: =S81*(1-T81) -> 0 | V81: EUR | W81: =IFERROR(VLOOKUP(V81,Curr!$B$2:$C$13,2,FALSE),0) -> 10.8 | X81: =U81*W81 -> 0 | Y81: =Q81 -> 0 | Z81: =+Y81*R81 -> 0 | AA81: EUR | AB81: =IFERROR(VLOOKUP(AA81,Curr!$B$2:$C$13,2,FALSE),0) -> 10.8 | AC81: =+Y81*AB81*R81 -> 0 | AD81: =+AC81-X81 -> 0 | AE81: =IFERROR(AD81/AC81,0) -> 0
S82: =+Q82*R82 -> 0 | T82: 0 | U82: =S82*(1-T82) -> 0 | V82: EUR | W82: =IFERROR(VLOOKUP(V82,Curr!$B$2:$C$13,2,FALSE),0) -> 10.8 | X82: =U82*W82 -> 0 | Y82: =Q82 -> 0 | Z82: =+Y82*R82 -> 0 | AA82: EUR | AB82: =IFERROR(VLOOKUP(AA82,Curr!$B$2:$C$13,2,FALSE),0) -> 10.8 | AC82: =+Y82*AB82*R82 -> 0 | AD82: =+AC82-X82 -> 0 | AE82: =IFERROR(AD82/AC82,0) -> 0
B84: Totals | D84: x | E84: x | F84: x | G84: x | H84: x | I84: x | J84: x | K84: x | L84: x | M84: x | N84: x | O84: x | P84: x | Q84: x | R84: x | S84: x | T84: x | U84: x | V84: x | W84: x | X84: x | Y84: x | Z84: =SUM(Z7:Z82) -> 19701.396 | AC84: =SUM(AC7:AC82) -> 212775.08 | AD84: =SUM(AD7:AD82) -> 36933.515 | AE84: =IFERROR(AD84/AC84,0) -> 0.17358008 | AF84: =SUM(AF8:AF83) -> 0 | AG84: =SUM(AG8:AG83) -> 0 | AH84: =SUM(AH8:AH83) -> 0 | AI84: =SUM(AI8:AI83) -> 0 | AJ84: =SUM(AJ8:AJ83) -> 0
Y86: Quote | Z86: 19700
Y87: PP | Z87: =Z86/4 -> 4925
Y89: USD | Z89: 23000
Y90: PP | Z90: =Z89/4 -> 5750

Sheet Kalk 3
B2: Dates: 27.06.2026
B3: Pax: 4
B4: Rooming: 2 x double
B6: ID | C6: Day | D6: Type | E6: From date | F6: To date | G6: From time | H6: To time | I6: Supplier | J6: Travel element | K6: Manual booking? | L6: Status | M6: Comments | N6: Non-refundable | O6: Refundable | P6: URL | Q6: Gross P per unit | R6: Units | S6: Gross P | T6: Supp Comm | U6: Net P | V6: Supp curr | W6: X-rate | X6: Net P NOK | Y6: Sales P per unit | Z6: Price | AA6: Sales curr | AB6: X-rate | AC6: Sales P NOK tot | AD6: GP NOK | AE6: GP % | AF6: VAT25 | AG6: VAT15 | AH6: VAT12 | AI6: VAT0-D | AJ6: VAT0-I
C7: Day 1 | D7: Arrival | E7: 27.06.2026 | J7: Keflavik: Welcome to Iceland | Q7: 0 | R7: 0 | S7: =+Q7*R7 -> 0 | T7: 0 | U7: =S7*(1-T7) -> 0 | V7: EUR | W7: =IFERROR(VLOOKUP(V7,Curr!$B$2:$C$13,2,FALSE),0) -> 10.8 | X7: =U7*W7 -> 0 | Y7: =Q7 -> 0 | Z7: =+Y7*R7 -> 0 | AA7: EUR | AB7: =IFERROR(VLOOKUP(AA7,Curr!$B$2:$C$13,2,FALSE),0) -> 10.8 | AC7: =+Y7*AB7*R7 -> 0 | AD7: =+AC7-X7 -> 0 | AE7: =IFERROR(AD7/AC7,0) -> 0
C8: Day 1 | D8: Tranfser | E8: 27.06.2026 | J8: Keflavik: Private transfer to your accommodation | Q8: 160 | R8: 1 | S8: =+Q8*R8 -> 160 | T8: 0.2 | U8: =S8*(1-T8) -> 128 | V8: EUR | W8: =IFERROR(VLOOKUP(V8,Curr!$B$2:$C$13,2,FALSE),0) -> 10.8 | X8: =U8*W8 -> 1382.4 | Y8: =Q8 -> 160 | Z8: =+Y8*R8 -> 160 | AA8: EUR | AB8: =IFERROR(VLOOKUP(AA8,Curr!$B$2:$C$13,2,FALSE),0) -> 10.8 | AC8: =+Y8*AB8*R8 -> 1728 | AD8: =+AC8-X8 -> 345.6 | AE8: =IFERROR(AD8/AC8,0) -> 0.2
C9: Day 1 | D9: Hotel | E9: 27.06.2026 | F9: 28.06.2026 | J9: Reykjavik: Check in to your accommodation for a 1 night stay - Grandi by Center Hotels - 2 x Double deluxe - breakfast included | P9: https://app.hotelbeds.com/factsheet/stay/749447?check_in=27-06-2026&check_out=28-06-2026&occupancy=2~0_2~0&packaging=true | Q9: 811 | R9: 1 | S9: =+Q9*R9 -> 811 | T9: 0 | U9: =S9*(1-T9) -> 811 | V9: EUR | W9: =IFERROR(VLOOKUP(V9,Curr!$B$2:$C$13,2,FALSE),0) -> 10.8 | X9: =U9*W9 -> 8758.8 | Y9: =Q9/0.8 -> 1013.75 | Z9: =+Y9*R9 -> 1013.75 | AA9: EUR | AB9: =IFERROR(VLOOKUP(AA9,Curr!$B$2:$C$13,2,FALSE),0) -> 10.8 | AC9: =+Y9*AB9*R9 -> 10948.5 | AD9: =+AC9-X9 -> 2189.7 | AE9: =IFERROR(AD9/AC9,0) -> 0.2
C10: Day 1 | D10: Leisure | E10: 27.06.2026 | J10: Reykjavik: Spend time at leisure | Q10: 0 | R10: 0 | S10: =+Q10*R10 -> 0 | T10: 0 | U10: =S10*(1-T10) -> 0 | V10: EUR | W10: =IFERROR(VLOOKUP(V10,Curr!$B$2:$C$13,2,FALSE),0) -> 10.8 | X10: =U10*W10 -> 0 | Y10: =Q10 -> 0 | Z10: =+Y10*R10 -> 0 | AA10: EUR | AB10: =IFERROR(VLOOKUP(AA10,Curr!$B$2:$C$13,2,FALSE),0) -> 10.8 | AC10: =+Y10*AB10*R10 -> 0 | AD10: =+AC10-X10 -> 0 | AE10: =IFERROR(AD10/AC10,0) -> 0
S11: =+Q11*R11 -> 0 | T11: 0 | U11: =S11*(1-T11) -> 0 | V11: EUR | W11: =IFERROR(VLOOKUP(V11,Curr!$B$2:$C$13,2,FALSE),0) -> 10.8 | X11: =U11*W11 -> 0 | Y11: =Q11 -> 0 | Z11: =+Y11*R11 -> 0 | AA11: EUR | AB11: =IFERROR(VLOOKUP(AA11,Curr!$B$2:$C$13,2,FALSE),0) -> 10.8 | AC11: =+Y11*AB11*R11 -> 0 | AD11: =+AC11-X11 -> 0 | AE11: =IFERROR(AD11/AC11,0) -> 0
C12: Day 2 | D12: Transfer | E12: 28.06.2026 | J12: Reykjavik: Self transfer by Uber to the car rental office | Q12: 0 | R12: 0 | S12: =+Q12*R12 -> 0 | T12: 0 | U12: =S12*(1-T12) -> 0 | V12: EUR | W12: =IFERROR(VLOOKUP(V12,Curr!$B$2:$C$13,2,FALSE),0) -> 10.8 | X12: =U12*W12 -> 0 | Y12: =Q12 -> 0 | Z12: =+Y12*R12 -> 0 | AA12: EUR | AB12: =IFERROR(VLOOKUP(AA12,Curr!$B$2:$C$13,2,FALSE),0) -> 10.8 | AC12: =+Y12*AB12*R12 -> 0 | AD12: =+AC12-X12 -> 0 | AE12: =IFERROR(AD12/AC12,0) -> 0
C13: Day 2 | D13: Car | E13: 28.06.2026 | J13: Reykjavik: Pick up your rental car at the car rental office - Car: TOYOTA RAV4 2.0 4WD AUTOMATIC or similar - Office Location: Njardargata Fluggardar - Includes: Collision damage waiver, Fuel information, Unlimited mileage, Theft protection, Vat, Personal accident insurance, Cancellation fee - Excludes: 1 way fee, road tax | Q13: 691 | R13: 1 | S13: =+Q13*R13 -> 691 | T13: 0 | U13: =S13*(1-T13) -> 691 | V13: EUR | W13: =IFERROR(VLOOKUP(V13,Curr!$B$2:$C$13,2,FALSE),0) -> 10.8 | X13: =U13*W13 -> 7462.8 | Y13: =Q13/0.8 -> 863.75 | Z13: =+Y13*R13 -> 863.75 | AA13: EUR | AB13: =IFERROR(VLOOKUP(AA13,Curr!$B$2:$C$13,2,FALSE),0) -> 10.8 | AC13: =+Y13*AB13*R13 -> 9328.5 | AD13: =+AC13-X13 -> 1865.7 | AE13: =IFERROR(AD13/AC13,0) -> 0.2
C14: Day 2 | D14: Drive | E14: 28.06.2026 | J14: Reykjavik: Drive to Vik - Driving time: 2hrs 40 minutes | Q14: 0 | R14: 0 | S14: =+Q14*R14 -> 0 | T14: 0 | U14: =S14*(1-T14) -> 0 | V14: EUR | W14: =IFERROR(VLOOKUP(V14,Curr!$B$2:$C$13,2,FALSE),0) -> 10.8 | X14: =U14*W14 -> 0 | Y14: =Q14 -> 0 | Z14: =+Y14*R14 -> 0 | AA14: EUR | AB14: =IFERROR(VLOOKUP(AA14,Curr!$B$2:$C$13,2,FALSE),0) -> 10.8 | AC14: =+Y14*AB14*R14 -> 0 | AD14: =+AC14-X14 -> 0 | AE14: =IFERROR(AD14/AC14,0) -> 0
C15: Day 2 | D15: Hotel | E15: 28.06.2026 | F15: 30.06.2026 | J15: Vik: Check in to your accommodation for a 2 night stay - Hotel Katla by Keahotels - 2 x Superior Double room - breakfast included | P15: https://www.ratehawk.com/hotel/iceland/vik_i_myrdal/mid7524341/hotel_hofdabrekka_country_hotel/?q=6130429&dates=28.06.2026-30.06.2026&guests=2-2&payment=freecancellation&price=one&sid=22ec769a-b117-452f-befc-9c97bff50e0a | Q15: 2232 | R15: 1 | S15: =+Q15*R15 -> 2232 | T15: 0 | U15: =S15*(1-T15) -> 2232 | V15: EUR | W15: =IFERROR(VLOOKUP(V15,Curr!$B$2:$C$13,2,FALSE),0) -> 10.8 | X15: =U15*W15 -> 24105.6 | Y15: =Q15/0.85 -> 2625.8824 | Z15: =+Y15*R15 -> 2625.8824 | AA15: EUR | AB15: =IFERROR(VLOOKUP(AA15,Curr!$B$2:$C$13,2,FALSE),0) -> 10.8 | AC15: =+Y15*AB15*R15 -> 28359.529 | AD15: =+AC15-X15 -> 4253.9294 | AE15: =IFERROR(AD15/AC15,0) -> 0.15
C16: Day 2 | D16: Leisure | E16: 28.06.2026 | J16: Vik: Spend time at leisure | Q16: 0 | R16: 0 | S16: =+Q16*R16 -> 0 | T16: 0 | U16: =S16*(1-T16) -> 0 | V16: EUR | W16: =IFERROR(VLOOKUP(V16,Curr!$B$2:$C$13,2,FALSE),0) -> 10.8 | X16: =U16*W16 -> 0 | Y16: =Q16 -> 0 | Z16: =+Y16*R16 -> 0 | AA16: EUR | AB16: =IFERROR(VLOOKUP(AA16,Curr!$B$2:$C$13,2,FALSE),0) -> 10.8 | AC16: =+Y16*AB16*R16 -> 0 | AD16: =+AC16-X16 -> 0 | AE16: =IFERROR(AD16/AC16,0) -> 0
S17: =+Q17*R17 -> 0 | T17: 0 | U17: =S17*(1-T17) -> 0 | V17: EUR | W17: =IFERROR(VLOOKUP(V17,Curr!$B$2:$C$13,2,FALSE),0) -> 10.8 | X17: =U17*W17 -> 0 | Y17: =Q17 -> 0 | Z17: =+Y17*R17 -> 0 | AA17: EUR | AB17: =IFERROR(VLOOKUP(AA17,Curr!$B$2:$C$13,2,FALSE),0) -> 10.8 | AC17: =+Y17*AB17*R17 -> 0 | AD17: =+AC17-X17 -> 0 | AE17: =IFERROR(AD17/AC17,0) -> 0
C18: Day 3 | D18: Activity | E18: 29.06.2026 | J18: Vik: Lava Show Vík - Time: 11:00 am - 12:00 pm - Meeeting point: Icelandic Lava Show, Víkurbraut 5 - Includes: A chance to get up close to real flowing lava, The only live lava show in the world, Security goggles, A live host makes the show fun and personal, A short educational video about Icelandic volcanism, A true story from the 1918 Katla eruption, A sensory loaded experience - you feel the heat from the lava, A Q&A session at the end of the show, A unique once-in-a-lifetime experience | P18: https://booknordics.com/iceland/southern-iceland/vik/lava-show-vik-the-original | Q18: 46 | R18: 4 | S18: =+Q18*R18 -> 184 | T18: 0.2 | U18: =S18*(1-T18) -> 147.2 | V18: EUR | W18: =IFERROR(VLOOKUP(V18,Curr!$B$2:$C$13,2,FALSE),0) -> 10.8 | X18: =U18*W18 -> 1589.76 | Y18: =Q18 -> 46 | Z18: =+Y18*R18 -> 184 | AA18: EUR | AB18: =IFERROR(VLOOKUP(AA18,Curr!$B$2:$C$13,2,FALSE),0) -> 10.8 | AC18: =+Y18*AB18*R18 -> 1987.2 | AD18: =+AC18-X18 -> 397.44 | AE18: =IFERROR(AD18/AC18,0) -> 0.2
C19: Day 3 | D19: Leisure | E19: 29.06.2026 | J19: Vik: Spend time at leisure | Q19: 0 | R19: 0 | S19: =+Q19*R19 -> 0 | T19: 0 | U19: =S19*(1-T19) -> 0 | V19: EUR | W19: =IFERROR(VLOOKUP(V19,Curr!$B$2:$C$13,2,FALSE),0) -> 10.8 | X19: =U19*W19 -> 0 | Y19: =Q19 -> 0 | Z19: =+Y19*R19 -> 0 | AA19: EUR | AB19: =IFERROR(VLOOKUP(AA19,Curr!$B$2:$C$13,2,FALSE),0) -> 10.8 | AC19: =+Y19*AB19*R19 -> 0 | AD19: =+AC19-X19 -> 0 | AE19: =IFERROR(AD19/AC19,0) -> 0
C20: Day 3 | D20: Activity | E20: 29.06.2026 | J20: Vik: Ice Cave Underneath Katla Volcano Super Jeep Tour - Time: 6:00 pm - 9:00 pm - Meeting point: Tröll Expeditions Katla Ice Cave, Víkubraut 26 - Includes: Stunning ride on a super jeep, Certified glacier guide, Visit to a natural ice cave, All safety ice cave equipment, Scenic landscapes viewing | P20: https://booknordics.com/iceland/southern-iceland/vik/katla-ice-cave-super-jeep-from-vik | Q20: 204 | R20: 4 | S20: =+Q20*R20 -> 816 | T20: 0.25 | U20: =S20*(1-T20) -> 612 | V20: EUR | W20: =IFERROR(VLOOKUP(V20,Curr!$B$2:$C$13,2,FALSE),0) -> 10.8 | X20: =U20*W20 -> 6609.6 | Y20: =Q20 -> 204 | Z20: =+Y20*R20 -> 816 | AA20: EUR | AB20: =IFERROR(VLOOKUP(AA20,Curr!$B$2:$C$13,2,FALSE),0) -> 10.8 | AC20: =+Y20*AB20*R20 -> 8812.8 | AD20: =+AC20-X20 -> 2203.2 | AE20: =IFERROR(AD20/AC20,0) -> 0.25
S21: =+Q21*R21 -> 0 | T21: 0 | U21: =S21*(1-T21) -> 0 | V21: EUR | W21: =IFERROR(VLOOKUP(V21,Curr!$B$2:$C$13,2,FALSE),0) -> 10.8 | X21: =U21*W21 -> 0 | Y21: =Q21 -> 0 | Z21: =+Y21*R21 -> 0 | AA21: EUR | AB21: =IFERROR(VLOOKUP(AA21,Curr!$B$2:$C$13,2,FALSE),0) -> 10.8 | AC21: =+Y21*AB21*R21 -> 0 | AD21: =+AC21-X21 -> 0 | AE21: =IFERROR(AD21/AC21,0) -> 0
C22: Day 4 | D22: Drive | E22: 30.06.2026 | J22: Vik: Drive to Asborgir - Things to see: Hella, Seashells beach, Black Sand Dunes, Selfoss | Q22: 0 | R22: 0 | S22: =+Q22*R22 -> 0 | T22: 0 | U22: =S22*(1-T22) -> 0 | V22: EUR | W22: =IFERROR(VLOOKUP(V22,Curr!$B$2:$C$13,2,FALSE),0) -> 10.8 | X22: =U22*W22 -> 0 | Y22: =Q22 -> 0 | Z22: =+Y22*R22 -> 0 | AA22: EUR | AB22: =IFERROR(VLOOKUP(AA22,Curr!$B$2:$C$13,2,FALSE),0) -> 10.8 | AC22: =+Y22*AB22*R22 -> 0 | AD22: =+AC22-X22 -> 0 | AE22: =IFERROR(AD22/AC22,0) -> 0
C23: Day 4 | D23: Hotel | E23: 30.06.2026 | F23: 01.07.2026 | J23: Asborgir: Check in to your accommodaiton for a 1 night stay - Hotel Grimsborgir by Keahotels - 2 x Double deluxe - Breakfast included | P23: https://app.hotelbeds.com/factsheet/stay/257043?check_in=30-06-2026&check_out=01-07-2026&occupancy=2~0_2~0&packaging=true | Q23: 694 | R23: 1 | S23: =+Q23*R23 -> 694 | T23: 0 | U23: =S23*(1-T23) -> 694 | V23: EUR | W23: =IFERROR(VLOOKUP(V23,Curr!$B$2:$C$13,2,FALSE),0) -> 10.8 | X23: =U23*W23 -> 7495.2 | Y23: =Q23/0.85 -> 816.47059 | Z23: =+Y23*R23 -> 816.47059 | AA23: EUR | AB23: =IFERROR(VLOOKUP(AA23,Curr!$B$2:$C$13,2,FALSE),0) -> 10.8 | AC23: =+Y23*AB23*R23 -> 8817.8824 | AD23: =+AC23-X23 -> 1322.6824 | AE23: =IFERROR(AD23/AC23,0) -> 0.15
C24: Day 4 | D24: Leisure | E24: 30.06.2026 | J24: Asborgir: Spend time at leisure | Q24: 0 | R24: 0 | S24: =+Q24*R24 -> 0 | T24: 0 | U24: =S24*(1-T24) -> 0 | V24: EUR | W24: =IFERROR(VLOOKUP(V24,Curr!$B$2:$C$13,2,FALSE),0) -> 10.8 | X24: =U24*W24 -> 0 | Y24: =Q24 -> 0 | Z24: =+Y24*R24 -> 0 | AA24: EUR | AB24: =IFERROR(VLOOKUP(AA24,Curr!$B$2:$C$13,2,FALSE),0) -> 10.8 | AC24: =+Y24*AB24*R24 -> 0 | AD24: =+AC24-X24 -> 0 | AE24: =IFERROR(AD24/AC24,0) -> 0
S25: =+Q25*R25 -> 0 | T25: 0 | U25: =S25*(1-T25) -> 0 | V25: EUR | W25: =IFERROR(VLOOKUP(V25,Curr!$B$2:$C$13,2,FALSE),0) -> 10.8 | X25: =U25*W25 -> 0 | Y25: =Q25 -> 0 | Z25: =+Y25*R25 -> 0 | AA25: EUR | AB25: =IFERROR(VLOOKUP(AA25,Curr!$B$2:$C$13,2,FALSE),0) -> 10.8 | AC25: =+Y25*AB25*R25 -> 0 | AD25: =+AC25-X25 -> 0 | AE25: =IFERROR(AD25/AC25,0) -> 0
C26: Day 5 | D26: Drive | E26: 01.07.2026 | J26: Asborgir: Drive to Reykjavik via the Golden Circle - Driving time: 3 hrs (without stops) - Things to see: Kerið Crater Lake, Fridheimar Tomato Farm (perfect stop for lunch), Gullfoss Waterfall, Geysir Hot Spring, Efstidalur Dairy Farm, Öxarárfoss Waterfall, Thingvellir National Park | P26: https://www.google.no/maps/dir/Gr%C3%ADmsborgir+-+Restaurant+and+Bar,+805+Selfoss,+Island/Keri%C3%B0,+805+Klausturholar,+Island/Fri%C3%B0heimar,+5HH4%2B225,+Fri%C3%B0heimar,+806+Reykholt,+Island/Gullfoss+Waterfall+Lookout,+above,+Gullfoss+Parking,+Island/Geysir+Hot+Springs,+333,+806,+Island/Efstidalur+II,+Bl%C3%A1sk%C3%B3gabygg%C3%B0,+801+Laugarvatn,+Island/%C3%96xar%C3%A1rfoss,+7V8J%2B8RH,+806+Thingvellir,+Island/Reykjav%C3%ADk,+Island/@64.1688511,-21.6918568,121628m/data=!3m1!1e3!4m50!4m49!1m5!1m1!1s0x48d68b942e2bd0e5:0x5a7a846e86721d79!2m2!1d-20.9667166!2d64.0521039!1m5!1m1!1s0x48d68bb755f6f257:0x515a44e0c12ed907!2m2!1d-20.8851466!2d64.0412785!1m5!1m1!1s0x48d696fbe383f7bb:0xdee6f1f7177295af!2m2!1d-20.4448859!2d64.177503!1m5!1m1!1s0x48d6a5f34f4c88b1:0xd3558f2a84b426ba!2m2!1d-20.1244323!2d64.326181!1m5!1m1!1s0x48d6a3ec33d9dc1f:0xda8b28dafde977e5!2m2!1d-20.299508!2d64.3137795!1m5!1m1!1s0x48d699ea8baff6ab:0x27379b3ab3273542!2m2!1d-20.5516435!2d64.2424477!1m5!1m1!1s0x48d6811eadf0fd95:0x48dd72aa97e36e57!2m2!1d-21.117885!2d64.2658062!1m5!1m1!1s0x48d674b9eedcedc3:0xec912ca230d26071!2m2!1d-21.9407552!2d64.1469868!3e0?entry=ttu&g_ep=EgoyMDI2MDQwOC4wIKXMDSoASAFQAw%3D%3D | Q26: 0 | R26: 0 | S26: =+Q26*R26 -> 0 | T26: 0 | U26: =S26*(1-T26) -> 0 | V26: EUR | W26: =IFERROR(VLOOKUP(V26,Curr!$B$2:$C$13,2,FALSE),0) -> 10.8 | X26: =U26*W26 -> 0 | Y26: =Q26 -> 0 | Z26: =+Y26*R26 -> 0 | AA26: EUR | AB26: =IFERROR(VLOOKUP(AA26,Curr!$B$2:$C$13,2,FALSE),0) -> 10.8 | AC26: =+Y26*AB26*R26 -> 0 | AD26: =+AC26-X26 -> 0 | AE26: =IFERROR(AD26/AC26,0) -> 0
C27: Day 5 | D27: Hotel | E27: 01.07.2026 | F27: 03.07.2026 | J27: Reykjavik: Check in to your accommodation for a 2 night stay - Borg by Keahotels - 2 x Deluxe room - breakfast included | P27: https://app.hotelbeds.com/factsheet/stay/90467?check_in=01-07-2026&check_out=03-07-2026&occupancy=2~0_2~0&packaging=true | Q27: 2170 | R27: 1 | S27: =+Q27*R27 -> 2170 | T27: 0 | U27: =S27*(1-T27) -> 2170 | V27: EUR | W27: =IFERROR(VLOOKUP(V27,Curr!$B$2:$C$13,2,FALSE),0) -> 10.8 | X27: =U27*W27 -> 23436 | Y27: =Q27/0.85 -> 2552.9412 | Z27: =+Y27*R27 -> 2552.9412 | AA27: EUR | AB27: =IFERROR(VLOOKUP(AA27,Curr!$B$2:$C$13,2,FALSE),0) -> 10.8 | AC27: =+Y27*AB27*R27 -> 27571.765 | AD27: =+AC27-X27 -> 4135.7647 | AE27: =IFERROR(AD27/AC27,0) -> 0.15
C28: Day 5 | D28: Leisure | E28: 01.07.2026 | J28: Reykjavik: Spend time at leisure | Q28: 0 | R28: 0 | S28: =+Q28*R28 -> 0 | T28: 0 | U28: =S28*(1-T28) -> 0 | V28: EUR | W28: =IFERROR(VLOOKUP(V28,Curr!$B$2:$C$13,2,FALSE),0) -> 10.8 | X28: =U28*W28 -> 0 | Y28: =Q28 -> 0 | Z28: =+Y28*R28 -> 0 | AA28: EUR | AB28: =IFERROR(VLOOKUP(AA28,Curr!$B$2:$C$13,2,FALSE),0) -> 10.8 | AC28: =+Y28*AB28*R28 -> 0 | AD28: =+AC28-X28 -> 0 | AE28: =IFERROR(AD28/AC28,0) -> 0
C29: Day 5 | D29: Activity | E29: 01.07.2026 | J29: Reykjavík: Classic Whale Watching under the Midnight Sun - Time: 8:30 pm - 11:30 pm - Meeting point: Elding ticket office, Ægisgarður 5c -Includes: 2-3,5 hours whale watching tour, Access to our Wildlife Exhibition, Excellent live commentary in English, Use of warm overalls & mellow music | P29: https://booknordics.com/iceland/western-iceland/reykjavik/reykjavik-classic-whales-in-the-midnight-sun | Q29: 127 | R29: 4 | S29: =+Q29*R29 -> 508 | T29: 0.25 | U29: =S29*(1-T29) -> 381 | V29: EUR | W29: =IFERROR(VLOOKUP(V29,Curr!$B$2:$C$13,2,FALSE),0) -> 10.8 | X29: =U29*W29 -> 4114.8 | Y29: =Q29 -> 127 | Z29: =+Y29*R29 -> 508 | AA29: EUR | AB29: =IFERROR(VLOOKUP(AA29,Curr!$B$2:$C$13,2,FALSE),0) -> 10.8 | AC29: =+Y29*AB29*R29 -> 5486.4 | AD29: =+AC29-X29 -> 1371.6 | AE29: =IFERROR(AD29/AC29,0) -> 0.25
S30: =+Q30*R30 -> 0 | T30: 0 | U30: =S30*(1-T30) -> 0 | V30: EUR | W30: =IFERROR(VLOOKUP(V30,Curr!$B$2:$C$13,2,FALSE),0) -> 10.8 | X30: =U30*W30 -> 0 | Y30: =Q30 -> 0 | Z30: =+Y30*R30 -> 0 | AA30: EUR | AB30: =IFERROR(VLOOKUP(AA30,Curr!$B$2:$C$13,2,FALSE),0) -> 10.8 | AC30: =+Y30*AB30*R30 -> 0 | AD30: =+AC30-X30 -> 0 | AE30: =IFERROR(AD30/AC30,0) -> 0
C31: Day 6 | D31: Activity | E31: 02.07.2026 | J31: Reykjavik: FlyOver Iceland - Time: 12:30 pm - 1:30 pm - Meeting point: Fiskislóð 43 - Includes: Entry or admission fee, FlyOver Iceland Pursuit | P31: https://booknordics.com/iceland/western-iceland/reykjavik/flyover-iceland | Q31: 35 | R31: 4 | S31: =+Q31*R31 -> 140 | T31: 0.2 | U31: =S31*(1-T31) -> 112 | V31: EUR | W31: =IFERROR(VLOOKUP(V31,Curr!$B$2:$C$13,2,FALSE),0) -> 10.8 | X31: =U31*W31 -> 1209.6 | Y31: =Q31 -> 35 | Z31: =+Y31*R31 -> 140 | AA31: EUR | AB31: =IFERROR(VLOOKUP(AA31,Curr!$B$2:$C$13,2,FALSE),0) -> 10.8 | AC31: =+Y31*AB31*R31 -> 1512 | AD31: =+AC31-X31 -> 302.4 | AE31: =IFERROR(AD31/AC31,0) -> 0.2
C32: Day 6 | D32: Leisure | E32: 02.07.2026 | J32: Reykjavik: Spend time at leisure | Q32: 0 | R32: 0 | S32: =+Q32*R32 -> 0 | T32: 0 | U32: =S32*(1-T32) -> 0 | V32: EUR | W32: =IFERROR(VLOOKUP(V32,Curr!$B$2:$C$13,2,FALSE),0) -> 10.8 | X32: =U32*W32 -> 0 | Y32: =Q32 -> 0 | Z32: =+Y32*R32 -> 0 | AA32: EUR | AB32: =IFERROR(VLOOKUP(AA32,Curr!$B$2:$C$13,2,FALSE),0) -> 10.8 | AC32: =+Y32*AB32*R32 -> 0 | AD32: =+AC32-X32 -> 0 | AE32: =IFERROR(AD32/AC32,0) -> 0
C33: Day 6 | D33: Activity | E33: 02.07.2026 | J33: Reykjavik: Sky Lagoon Sér Pass with Transfer - Time: 5:00 pm - 7:30 pm - Meeting point: Hotel Pick up - Includes: Bus fare, Sky Lagoon Sér Admission, Complete Seven-step Ritual, Private Changing Facilities, Towel | P33: https://booknordics.com/iceland/western-iceland/reykjavik/sky-lagoon-sky-pass-with-transfer | Q33: 167 | R33: 4 | S33: =+Q33*R33 -> 668 | T33: 0.2 | U33: =S33*(1-T33) -> 534.4 | V33: EUR | W33: =IFERROR(VLOOKUP(V33,Curr!$B$2:$C$13,2,FALSE),0) -> 10.8 | X33: =U33*W33 -> 5771.52 | Y33: =Q33 -> 167 | Z33: =+Y33*R33 -> 668 | AA33: EUR | AB33: =IFERROR(VLOOKUP(AA33,Curr!$B$2:$C$13,2,FALSE),0) -> 10.8 | AC33: =+Y33*AB33*R33 -> 7214.4 | AD33: =+AC33-X33 -> 1442.88 | AE33: =IFERROR(AD33/AC33,0) -> 0.2
S34: =+Q34*R34 -> 0 | T34: 0 | U34: =S34*(1-T34) -> 0 | V34: EUR | W34: =IFERROR(VLOOKUP(V34,Curr!$B$2:$C$13,2,FALSE),0) -> 10.8 | X34: =U34*W34 -> 0 | Y34: =Q34 -> 0 | Z34: =+Y34*R34 -> 0 | AA34: EUR | AB34: =IFERROR(VLOOKUP(AA34,Curr!$B$2:$C$13,2,FALSE),0) -> 10.8 | AC34: =+Y34*AB34*R34 -> 0 | AD34: =+AC34-X34 -> 0 | AE34: =IFERROR(AD34/AC34,0) -> 0
C35: Day 7 | D35: Drive | E35: 03.07.2026 | J35: Reykjavik: Drive to Keflavik Airport | Q35: 0 | R35: 0 | S35: =+Q35*R35 -> 0 | T35: 0 | U35: =S35*(1-T35) -> 0 | V35: EUR | W35: =IFERROR(VLOOKUP(V35,Curr!$B$2:$C$13,2,FALSE),0) -> 10.8 | X35: =U35*W35 -> 0 | Y35: =Q35 -> 0 | Z35: =+Y35*R35 -> 0 | AA35: EUR | AB35: =IFERROR(VLOOKUP(AA35,Curr!$B$2:$C$13,2,FALSE),0) -> 10.8 | AC35: =+Y35*AB35*R35 -> 0 | AD35: =+AC35-X35 -> 0 | AE35: =IFERROR(AD35/AC35,0) -> 0
C36: Day 7 | D36: Car | E36: 03.07.2026 | J36: Keflavik: Deliver your rental car at the airport car rental office | Q36: 0 | R36: 0 | S36: =+Q36*R36 -> 0 | T36: 0 | U36: =S36*(1-T36) -> 0 | V36: EUR | W36: =IFERROR(VLOOKUP(V36,Curr!$B$2:$C$13,2,FALSE),0) -> 10.8 | X36: =U36*W36 -> 0 | Y36: =Q36 -> 0 | Z36: =+Y36*R36 -> 0 | AA36: EUR | AB36: =IFERROR(VLOOKUP(AA36,Curr!$B$2:$C$13,2,FALSE),0) -> 10.8 | AC36: =+Y36*AB36*R36 -> 0 | AD36: =+AC36-X36 -> 0 | AE36: =IFERROR(AD36/AC36,0) -> 0
C37: Day 7 | D37: Flight | E37: 03.07.2026 | J37: Keflavik: Flight to Oslo - Time: 09:10 am - 1:50 pm - Luggage included: 1 x 23 kg check in and 1 x 8 kg carry on per person | P37: https://www.sas.no/book/flights/?search=OW_KEF-OSL-20260703_a4c0i0y0&view=upsell&bookingFlow=revenue&out_flight_number=SK4788&skyscanner_redirectid=RhZvBkUmTrSXl9DScsN5CA&utm_source=skyscanner&utm_medium=metasearch&utm_campaign=skyscanner_metasearch&sortBy=rec&out_class=ECONOMY&out_sub_class=FLEX | Q37: 3747 | R37: 4 | S37: =+Q37*R37 -> 14988 | T37: 0 | U37: =S37*(1-T37) -> 14988 | V37: NOK | W37: =IFERROR(VLOOKUP(V37,Curr!$B$2:$C$13,2,FALSE),0) -> 1 | X37: =U37*W37 -> 14988 | Y37: =Q37/11/0.8 -> 425.79545 | Z37: =+Y37*R37 -> 1703.1818 | AA37: EUR | AB37: =IFERROR(VLOOKUP(AA37,Curr!$B$2:$C$13,2,FALSE),0) -> 10.8 | AC37: =+Y37*AB37*R37 -> 18394.364 | AD37: =+AC37-X37 -> 3406.3636 | AE37: =IFERROR(AD37/AC37,0) -> 0.18518519
C38: Day 7 | D38: Transfer | E38: 03.07.2026 | J38: Oslo: Private transfer to your accommodation | Q38: 1900 | R38: 1 | S38: =+Q38*R38 -> 1900 | T38: 0 | U38: =S38*(1-T38) -> 1900 | V38: NOK | W38: =IFERROR(VLOOKUP(V38,Curr!$B$2:$C$13,2,FALSE),0) -> 1 | X38: =U38*W38 -> 1900 | Y38: =Q38/11/0.8 -> 215.90909 | Z38: =+Y38*R38 -> 215.90909 | AA38: EUR | AB38: =IFERROR(VLOOKUP(AA38,Curr!$B$2:$C$13,2,FALSE),0) -> 10.8 | AC38: =+Y38*AB38*R38 -> 2331.8182 | AD38: =+AC38-X38 -> 431.81818 | AE38: =IFERROR(AD38/AC38,0) -> 0.18518519
C39: Day 7 | D39: Hotel | E39: 03.07.2026 | F39: 05.07.2026 | J39: Oslo: Check in to your accommodation for a 2 night stay - Grand Hotel Oslo by Scandic - 2 x Superior king - Breakfast included | P39: https://app.hotelbeds.com/factsheet/stay/616601?check_in=03-07-2026&check_out=05-07-2026&occupancy=2~0_2~0&packaging=true | Q39: 2014 | R39: 1 | S39: =+Q39*R39 -> 2014 | T39: 0 | U39: =S39*(1-T39) -> 2014 | V39: EUR | W39: =IFERROR(VLOOKUP(V39,Curr!$B$2:$C$13,2,FALSE),0) -> 10.8 | X39: =U39*W39 -> 21751.2 | Y39: =Q39/0.85 -> 2369.4118 | Z39: =+Y39*R39 -> 2369.4118 | AA39: EUR | AB39: =IFERROR(VLOOKUP(AA39,Curr!$B$2:$C$13,2,FALSE),0) -> 10.8 | AC39: =+Y39*AB39*R39 -> 25589.647 | AD39: =+AC39-X39 -> 3838.4471 | AE39: =IFERROR(AD39/AC39,0) -> 0.15
C40: Day 7 | D40: Leisure | E40: 03.07.2026 | J40: Oslo: Spend time at leisure | Q40: 0 | R40: 0 | S40: =+Q40*R40 -> 0 | T40: 0 | U40: =S40*(1-T40) -> 0 | V40: EUR | W40: =IFERROR(VLOOKUP(V40,Curr!$B$2:$C$13,2,FALSE),0) -> 10.8 | X40: =U40*W40 -> 0 | Y40: =Q40 -> 0 | Z40: =+Y40*R40 -> 0 | AA40: EUR | AB40: =IFERROR(VLOOKUP(AA40,Curr!$B$2:$C$13,2,FALSE),0) -> 10.8 | AC40: =+Y40*AB40*R40 -> 0 | AD40: =+AC40-X40 -> 0 | AE40: =IFERROR(AD40/AC40,0) -> 0
S41: =+Q41*R41 -> 0 | T41: 0 | U41: =S41*(1-T41) -> 0 | V41: EUR | W41: =IFERROR(VLOOKUP(V41,Curr!$B$2:$C$13,2,FALSE),0) -> 10.8 | X41: =U41*W41 -> 0 | Y41: =Q41 -> 0 | Z41: =+Y41*R41 -> 0 | AA41: EUR | AB41: =IFERROR(VLOOKUP(AA41,Curr!$B$2:$C$13,2,FALSE),0) -> 10.8 | AC41: =+Y41*AB41*R41 -> 0 | AD41: =+AC41-X41 -> 0 | AE41: =IFERROR(AD41/AC41,0) -> 0
C42: Day 8 | D42: Activity | E42: 04.07.2026 | J42: Oslo: Fjord Sightseeing Cruise by 100% Electric Boat - Time: 1:30 pm - 3:30 pm - Meeting point: Rådhusbrygge 4, Platform E - Includes: Oslo Fjord archipelago cruise by electric boat, Cafeteria with snacks and drinks for purchase, "Voice of Norway" Audio guide for download, Stop at the Bygdøy peninsula near to museums | P42: https://booknordics.com/norway/eastern-norway/oslo/oslofjord-sightseeing-cruise | Q42: 40 | R42: 4 | S42: =+Q42*R42 -> 160 | T42: 0.2 | U42: =S42*(1-T42) -> 128 | V42: EUR | W42: =IFERROR(VLOOKUP(V42,Curr!$B$2:$C$13,2,FALSE),0) -> 10.8 | X42: =U42*W42 -> 1382.4 | Y42: =Q42 -> 40 | Z42: =+Y42*R42 -> 160 | AA42: EUR | AB42: =IFERROR(VLOOKUP(AA42,Curr!$B$2:$C$13,2,FALSE),0) -> 10.8 | AC42: =+Y42*AB42*R42 -> 1728 | AD42: =+AC42-X42 -> 345.6 | AE42: =IFERROR(AD42/AC42,0) -> 0.2
C43: Day 8 | D43: Leisure | E43: 04.07.2026 | J43: Oslo: Spend time at leisure | Q43: 0 | R43: 0 | S43: =+Q43*R43 -> 0 | T43: 0 | U43: =S43*(1-T43) -> 0 | V43: EUR | W43: =IFERROR(VLOOKUP(V43,Curr!$B$2:$C$13,2,FALSE),0) -> 10.8 | X43: =U43*W43 -> 0 | Y43: =Q43 -> 0 | Z43: =+Y43*R43 -> 0 | AA43: EUR | AB43: =IFERROR(VLOOKUP(AA43,Curr!$B$2:$C$13,2,FALSE),0) -> 10.8 | AC43: =+Y43*AB43*R43 -> 0 | AD43: =+AC43-X43 -> 0 | AE43: =IFERROR(AD43/AC43,0) -> 0
S44: =+Q44*R44 -> 0 | T44: 0 | U44: =S44*(1-T44) -> 0 | V44: EUR | W44: =IFERROR(VLOOKUP(V44,Curr!$B$2:$C$13,2,FALSE),0) -> 10.8 | X44: =U44*W44 -> 0 | Y44: =Q44 -> 0 | Z44: =+Y44*R44 -> 0 | AA44: EUR | AB44: =IFERROR(VLOOKUP(AA44,Curr!$B$2:$C$13,2,FALSE),0) -> 10.8 | AC44: =+Y44*AB44*R44 -> 0 | AD44: =+AC44-X44 -> 0 | AE44: =IFERROR(AD44/AC44,0) -> 0
C45: Day 9 | D45: Transfer | E45: 05.07.2026 | J45: Oslo: Self transfer to Oslo Central Station | Q45: 0 | R45: 0 | S45: =+Q45*R45 -> 0 | T45: 0 | U45: =S45*(1-T45) -> 0 | V45: EUR | W45: =IFERROR(VLOOKUP(V45,Curr!$B$2:$C$13,2,FALSE),0) -> 10.8 | X45: =U45*W45 -> 0 | Y45: =Q45 -> 0 | Z45: =+Y45*R45 -> 0 | AA45: EUR | AB45: =IFERROR(VLOOKUP(AA45,Curr!$B$2:$C$13,2,FALSE),0) -> 10.8 | AC45: =+Y45*AB45*R45 -> 0 | AD45: =+AC45-X45 -> 0 | AE45: =IFERROR(AD45/AC45,0) -> 0
C46: Day 9 | D46: Activity | E46: 05.07.2026 | J46: Oslo: Norway in a Nutshell tour to Bergen, including Luggage transfer for 4 x luggage - Time: 08:23 am - 8:38 pm - Includes: Train tickets Oslo to Bergen, Train tickets Flåm to Myrdal, Fjord Cruisee Flåm to Gudvangen - Tour summary: 08:23 am - 1:04 pm: Train from Oslo to Myrdal. 1:24 pm - 2:22 pm: Flåmsbana to Flåm. 3:00 pm - 5:00 pm: Fjord Cruise to Gudangen. 5:25 pm - 6:25 pm: Premium Coach to Voss. 7:14 pm - 8:38 pm: Train to Bergen . | P46: https://www.fjordtours.com/en/norway/booking/tour/norway-in-a-nutshell/b1205fbc-1045-45fb-a099-1d3be8f4aa58/5c582628-ae09-482f-93bf-e41e16e39ac0 | Q46: =3474+450 -> 3924 | R46: 4 | S46: =+Q46*R46 -> 15696 | T46: 0.12 | U46: =S46*(1-T46) -> 13812.48 | V46: NOK | W46: =IFERROR(VLOOKUP(V46,Curr!$B$2:$C$13,2,FALSE),0) -> 1 | X46: =U46*W46 -> 13812.48 | Y46: =Q46/11/0.9 -> 396.36364 | Z46: =+Y46*R46 -> 1585.4545 | AA46: EUR | AB46: =IFERROR(VLOOKUP(AA46,Curr!$B$2:$C$13,2,FALSE),0) -> 10.8 | AC46: =+Y46*AB46*R46 -> 17122.909 | AD46: =+AC46-X46 -> 3310.4291 | AE46: =IFERROR(AD46/AC46,0) -> 0.19333333
C47: Day 9 | D47: Transfer | E47: 05.07.2026 | J47: Bergen: Private transfer to your accommodation | P47: https://www.btservice.no/private-cruiseport-transfer | Q47: 1690 | R47: 1 | S47: =+Q47*R47 -> 1690 | T47: 0.15 | U47: =S47*(1-T47) -> 1436.5 | V47: NOK | W47: =IFERROR(VLOOKUP(V47,Curr!$B$2:$C$13,2,FALSE),0) -> 1 | X47: =U47*W47 -> 1436.5 | Y47: =Q47/11/0.9 -> 170.70707 | Z47: =+Y47*R47 -> 170.70707 | AA47: EUR | AB47: =IFERROR(VLOOKUP(AA47,Curr!$B$2:$C$13,2,FALSE),0) -> 10.8 | AC47: =+Y47*AB47*R47 -> 1843.6364 | AD47: =+AC47-X47 -> 407.13636 | AE47: =IFERROR(AD47/AC47,0) -> 0.22083333
C48: Day 9 | D48: Hotel | E48: 05.07.2026 | F48: 07.07.2026 | J48: Bergen: Check in to your accommodation for a 2 night stay - Bergen Bors - 2 x Suite loft - breakfast included | P48: https://app.hotelbeds.com/factsheet/stay/647045?check_in=05-07-2026&check_out=07-07-2026&occupancy=2~0_2~0&packaging=true | Q48: 2662 | R48: 1 | S48: =+Q48*R48 -> 2662 | T48: 0 | U48: =S48*(1-T48) -> 2662 | V48: EUR | W48: =IFERROR(VLOOKUP(V48,Curr!$B$2:$C$13,2,FALSE),0) -> 10.8 | X48: =U48*W48 -> 28749.6 | Y48: =Q48/0.85 -> 3131.7647 | Z48: =+Y48*R48 -> 3131.7647 | AA48: EUR | AB48: =IFERROR(VLOOKUP(AA48,Curr!$B$2:$C$13,2,FALSE),0) -> 10.8 | AC48: =+Y48*AB48*R48 -> 33823.059 | AD48: =+AC48-X48 -> 5073.4588 | AE48: =IFERROR(AD48/AC48,0) -> 0.15
C49: Day 9 | D49: Leisure | E49: 05.07.2026 | J49: Bergen: Spend time at leisure | Q49: 0 | R49: 0 | S49: =+Q49*R49 -> 0 | T49: 0 | U49: =S49*(1-T49) -> 0 | V49: EUR | W49: =IFERROR(VLOOKUP(V49,Curr!$B$2:$C$13,2,FALSE),0) -> 10.8 | X49: =U49*W49 -> 0 | Y49: =Q49 -> 0 | Z49: =+Y49*R49 -> 0 | AA49: EUR | AB49: =IFERROR(VLOOKUP(AA49,Curr!$B$2:$C$13,2,FALSE),0) -> 10.8 | AC49: =+Y49*AB49*R49 -> 0 | AD49: =+AC49-X49 -> 0 | AE49: =IFERROR(AD49/AC49,0) -> 0
S50: =+Q50*R50 -> 0 | T50: 0 | U50: =S50*(1-T50) -> 0 | V50: EUR | W50: =IFERROR(VLOOKUP(V50,Curr!$B$2:$C$13,2,FALSE),0) -> 10.8 | X50: =U50*W50 -> 0 | Y50: =Q50 -> 0 | Z50: =+Y50*R50 -> 0 | AA50: EUR | AB50: =IFERROR(VLOOKUP(AA50,Curr!$B$2:$C$13,2,FALSE),0) -> 10.8 | AC50: =+Y50*AB50*R50 -> 0 | AD50: =+AC50-X50 -> 0 | AE50: =IFERROR(AD50/AC50,0) -> 0
C51: Day 10 | D51: Activity | E51: 06.07.2026 | J51: Bergen: Fløybanen Funicular Tickets - Time: Flexible - Meeting point: Fløybanen | P51: https://www.floyen.no/floibanen/kjop-billetter | Q51: 200 | R51: 4 | S51: =+Q51*R51 -> 800 | T51: 0 | U51: =S51*(1-T51) -> 800 | V51: NOK | W51: =IFERROR(VLOOKUP(V51,Curr!$B$2:$C$13,2,FALSE),0) -> 1 | X51: =U51*W51 -> 800 | Y51: =Q51/11/0.8 -> 22.727273 | Z51: =+Y51*R51 -> 90.909091 | AA51: EUR | AB51: =IFERROR(VLOOKUP(AA51,Curr!$B$2:$C$13,2,FALSE),0) -> 10.8 | AC51: =+Y51*AB51*R51 -> 981.81818 | AD51: =+AC51-X51 -> 181.81818 | AE51: =IFERROR(AD51/AC51,0) -> 0.18518519
C52: Day 10 | D52: Leisure | E52: 06.07.2026 | J52: Bergen: Spend time at leisure | Q52: 0 | R52: 0 | S52: =+Q52*R52 -> 0 | T52: 0 | U52: =S52*(1-T52) -> 0 | V52: EUR | W52: =IFERROR(VLOOKUP(V52,Curr!$B$2:$C$13,2,FALSE),0) -> 10.8 | X52: =U52*W52 -> 0 | Y52: =Q52 -> 0 | Z52: =+Y52*R52 -> 0 | AA52: EUR | AB52: =IFERROR(VLOOKUP(AA52,Curr!$B$2:$C$13,2,FALSE),0) -> 10.8 | AC52: =+Y52*AB52*R52 -> 0 | AD52: =+AC52-X52 -> 0 | AE52: =IFERROR(AD52/AC52,0) -> 0
C53: Day 10 | D53: Activity | E53: 06.07.2026 | J53: Bergen: Mostraumen Majestic Fjord & Waterfall Cruise - Time: 5:00 pm - 7:00 pm - Meeting point: Börshopen Pier, Strandkaien 13 - Round-trip criose Bergen to Mostraumen to Bergen | P53: https://booknordics.com/norway/western-fjord-norway/bergen-and-hardanger/mostraumen-fjord-waterfall-cruise | Q53: 75 | R53: 4 | S53: =+Q53*R53 -> 300 | T53: 0.2 | U53: =S53*(1-T53) -> 240 | V53: EUR | W53: =IFERROR(VLOOKUP(V53,Curr!$B$2:$C$13,2,FALSE),0) -> 10.8 | X53: =U53*W53 -> 2592 | Y53: =Q53 -> 75 | Z53: =+Y53*R53 -> 300 | AA53: EUR | AB53: =IFERROR(VLOOKUP(AA53,Curr!$B$2:$C$13,2,FALSE),0) -> 10.8 | AC53: =+Y53*AB53*R53 -> 3240 | AD53: =+AC53-X53 -> 648 | AE53: =IFERROR(AD53/AC53,0) -> 0.2
S54: =+Q54*R54 -> 0 | T54: 0 | U54: =S54*(1-T54) -> 0 | V54: EUR | W54: =IFERROR(VLOOKUP(V54,Curr!$B$2:$C$13,2,FALSE),0) -> 10.8 | X54: =U54*W54 -> 0 | Y54: =Q54 -> 0 | Z54: =+Y54*R54 -> 0 | AA54: EUR | AB54: =IFERROR(VLOOKUP(AA54,Curr!$B$2:$C$13,2,FALSE),0) -> 10.8 | AC54: =+Y54*AB54*R54 -> 0 | AD54: =+AC54-X54 -> 0 | AE54: =IFERROR(AD54/AC54,0) -> 0
C55: Day 11 | D55: Transfer | E55: 07.07.2026 | J55: Bergen: Private transfer to Bergen Airport | P55: https://www.btservice.no/private-cruiseport-transfer | Q55: 2290 | R55: 1 | S55: =+Q55*R55 -> 2290 | T55: 0.15 | U55: =S55*(1-T55) -> 1946.5 | V55: NOK | W55: =IFERROR(VLOOKUP(V55,Curr!$B$2:$C$13,2,FALSE),0) -> 1 | X55: =U55*W55 -> 1946.5 | Y55: =Q55/11/0.9 -> 231.31313 | Z55: =+Y55*R55 -> 231.31313 | AA55: EUR | AB55: =IFERROR(VLOOKUP(AA55,Curr!$B$2:$C$13,2,FALSE),0) -> 10.8 | AC55: =+Y55*AB55*R55 -> 2498.1818 | AD55: =+AC55-X55 -> 551.68182 | AE55: =IFERROR(AD55/AC55,0) -> 0.22083333
C56: Day 11 | D56: Flight | E56: 07.07.2026 | J56: Bergen: Flight to Ålesund - Time: 11:00 am - 11:50 am - Luggage included: 1 x 23 kg check in and 1 x 8 kg carry on per person | P56: https://www.wideroe.no/booking/booking#/select-flight | Q56: 1169 | R56: 4 | S56: =+Q56*R56 -> 4676 | T56: 0 | U56: =S56*(1-T56) -> 4676 | V56: NOK | W56: =IFERROR(VLOOKUP(V56,Curr!$B$2:$C$13,2,FALSE),0) -> 1 | X56: =U56*W56 -> 4676 | Y56: =Q56/11/0.8 -> 132.84091 | Z56: =+Y56*R56 -> 531.36364 | AA56: EUR | AB56: =IFERROR(VLOOKUP(AA56,Curr!$B$2:$C$13,2,FALSE),0) -> 10.8 | AC56: =+Y56*AB56*R56 -> 5738.7273 | AD56: =+AC56-X56 -> 1062.7273 | AE56: =IFERROR(AD56/AC56,0) -> 0.18518519
C57: Day 11 | D57: Car | E57: 07.07.2026 | J57: Ålesund: Pick up your rental car at the Ålesund Airport Car rental office - Car: SUZUKI S-CROSS - Office location: Flyplassvegen 27 - Includes: Collision damage waiver, Fuel information, Unlimited mileage, Theft protection, Vat, Personal accident insurance, Cancellation fee - Excludes: 1 way fee, road tax | Q57: 372 | R57: 1 | S57: =+Q57*R57 -> 372 | T57: 0 | U57: =S57*(1-T57) -> 372 | V57: EUR | W57: =IFERROR(VLOOKUP(V57,Curr!$B$2:$C$13,2,FALSE),0) -> 10.8 | X57: =U57*W57 -> 4017.6 | Y57: =Q57/0.8 -> 465 | Z57: =+Y57*R57 -> 465 | AA57: EUR | AB57: =IFERROR(VLOOKUP(AA57,Curr!$B$2:$C$13,2,FALSE),0) -> 10.8 | AC57: =+Y57*AB57*R57 -> 5022 | AD57: =+AC57-X57 -> 1004.4 | AE57: =IFERROR(AD57/AC57,0) -> 0.2
C58: Day 11 | D58: Drive | E58: 07.07.2026 | J58: Ålesund: Drive to your accommodation | Q58: 0 | R58: 0 | S58: =+Q58*R58 -> 0 | T58: 0 | U58: =S58*(1-T58) -> 0 | V58: EUR | W58: =IFERROR(VLOOKUP(V58,Curr!$B$2:$C$13,2,FALSE),0) -> 10.8 | X58: =U58*W58 -> 0 | Y58: =Q58 -> 0 | Z58: =+Y58*R58 -> 0 | AA58: EUR | AB58: =IFERROR(VLOOKUP(AA58,Curr!$B$2:$C$13,2,FALSE),0) -> 10.8 | AC58: =+Y58*AB58*R58 -> 0 | AD58: =+AC58-X58 -> 0 | AE58: =IFERROR(AD58/AC58,0) -> 0
C59: Day 11 | D59: Hotel | E59: 07.07.2026 | F59: 10.07.2026 | J59: Ålesund: Check in to your accommodation for a 3 night stay - Hotel Brosundet - 2 x Junior suite - breakfast included | P59: https://app.hotelbeds.com/factsheet/stay/70251?check_in=07-07-2026&check_out=10-07-2026&occupancy=2~0_2~0&packaging=true | Q59: 2995 | R59: 1 | S59: =+Q59*R59 -> 2995 | T59: 0 | U59: =S59*(1-T59) -> 2995 | V59: EUR | W59: =IFERROR(VLOOKUP(V59,Curr!$B$2:$C$13,2,FALSE),0) -> 10.8 | X59: =U59*W59 -> 32346 | Y59: =Q59/0.85 -> 3523.5294 | Z59: =+Y59*R59 -> 3523.5294 | AA59: EUR | AB59: =IFERROR(VLOOKUP(AA59,Curr!$B$2:$C$13,2,FALSE),0) -> 10.8 | AC59: =+Y59*AB59*R59 -> 38054.118 | AD59: =+AC59-X59 -> 5708.1176 | AE59: =IFERROR(AD59/AC59,0) -> 0.15
C60: Day 11 | D60: Leisure | E60: 07.07.2026 | J60: Ålesund: Spend time at leisure | Q60: 0 | R60: 0 | S60: =+Q60*R60 -> 0 | T60: 0 | U60: =S60*(1-T60) -> 0 | V60: EUR | W60: =IFERROR(VLOOKUP(V60,Curr!$B$2:$C$13,2,FALSE),0) -> 10.8 | X60: =U60*W60 -> 0 | Y60: =Q60 -> 0 | Z60: =+Y60*R60 -> 0 | AA60: EUR | AB60: =IFERROR(VLOOKUP(AA60,Curr!$B$2:$C$13,2,FALSE),0) -> 10.8 | AC60: =+Y60*AB60*R60 -> 0 | AD60: =+AC60-X60 -> 0 | AE60: =IFERROR(AD60/AC60,0) -> 0
S61: =+Q61*R61 -> 0 | T61: 0 | U61: =S61*(1-T61) -> 0 | V61: EUR | W61: =IFERROR(VLOOKUP(V61,Curr!$B$2:$C$13,2,FALSE),0) -> 10.8 | X61: =U61*W61 -> 0 | Y61: =Q61 -> 0 | Z61: =+Y61*R61 -> 0 | AA61: EUR | AB61: =IFERROR(VLOOKUP(AA61,Curr!$B$2:$C$13,2,FALSE),0) -> 10.8 | AC61: =+Y61*AB61*R61 -> 0 | AD61: =+AC61-X61 -> 0 | AE61: =IFERROR(AD61/AC61,0) -> 0
C62: Day 12 | D62: Drive | E62: 08.07.2026 | J62: Ålesund: Geiranger Road Trip - Drive to Hellesylt, and take the Geiranger Fjord Ferry to Geiranger at 11:00 am. Spend some time at leisuree in Geiranger, before driving back to Ålesund via Sjøholt | P62: https://www.fjordtours.com/no/norge/transport/ferge/geiranger-hellesylt | Q62: 1680 | R62: 1 | S62: =+Q62*R62 -> 1680 | T62: 0.12 | U62: =S62*(1-T62) -> 1478.4 | V62: NOK | W62: =IFERROR(VLOOKUP(V62,Curr!$B$2:$C$13,2,FALSE),0) -> 1 | X62: =U62*W62 -> 1478.4 | Y62: =Q62/11/0.8 -> 190.90909 | Z62: =+Y62*R62 -> 190.90909 | AA62: EUR | AB62: =IFERROR(VLOOKUP(AA62,Curr!$B$2:$C$13,2,FALSE),0) -> 10.8 | AC62: =+Y62*AB62*R62 -> 2061.8182 | AD62: =+AC62-X62 -> 583.41818 | AE62: =IFERROR(AD62/AC62,0) -> 0.28296296
C63: Day 12 | D63: Leisure | E63: 08.07.2026 | J63: Ålesund: Spend time at leisure | Q63: 0 | R63: 0 | S63: =+Q63*R63 -> 0 | T63: 0 | U63: =S63*(1-T63) -> 0 | V63: EUR | W63: =IFERROR(VLOOKUP(V63,Curr!$B$2:$C$13,2,FALSE),0) -> 10.8 | X63: =U63*W63 -> 0 | Y63: =Q63 -> 0 | Z63: =+Y63*R63 -> 0 | AA63: EUR | AB63: =IFERROR(VLOOKUP(AA63,Curr!$B$2:$C$13,2,FALSE),0) -> 10.8 | AC63: =+Y63*AB63*R63 -> 0 | AD63: =+AC63-X63 -> 0 | AE63: =IFERROR(AD63/AC63,0) -> 0
S64: =+Q64*R64 -> 0 | T64: 0 | U64: =S64*(1-T64) -> 0 | V64: EUR | W64: =IFERROR(VLOOKUP(V64,Curr!$B$2:$C$13,2,FALSE),0) -> 10.8 | X64: =U64*W64 -> 0 | Y64: =Q64 -> 0 | Z64: =+Y64*R64 -> 0 | AA64: EUR | AB64: =IFERROR(VLOOKUP(AA64,Curr!$B$2:$C$13,2,FALSE),0) -> 10.8 | AC64: =+Y64*AB64*R64 -> 0 | AD64: =+AC64-X64 -> 0 | AE64: =IFERROR(AD64/AC64,0) -> 0
C65: Day 13 | D65: Drive | E65: 09.07.2026 | J65: Ålesund: Atlantic Road Road Trip - Drive from your accommodation to the Atlantic Road. Head up to Kristiansund and spend some time at leisure. Drive to Molde, and head to Molde Panorama. Drive back to your accommodation in Ålesund | Q65: 0 | R65: 0 | S65: =+Q65*R65 -> 0 | T65: 0 | U65: =S65*(1-T65) -> 0 | V65: EUR | W65: =IFERROR(VLOOKUP(V65,Curr!$B$2:$C$13,2,FALSE),0) -> 10.8 | X65: =U65*W65 -> 0 | Y65: =Q65 -> 0 | Z65: =+Y65*R65 -> 0 | AA65: EUR | AB65: =IFERROR(VLOOKUP(AA65,Curr!$B$2:$C$13,2,FALSE),0) -> 10.8 | AC65: =+Y65*AB65*R65 -> 0 | AD65: =+AC65-X65 -> 0 | AE65: =IFERROR(AD65/AC65,0) -> 0
C66: Day 13 | D66: Leisure | E66: 09.07.2026 | J66: Ålesund: Spend time at leisure | Q66: 0 | R66: 0 | S66: =+Q66*R66 -> 0 | T66: 0 | U66: =S66*(1-T66) -> 0 | V66: EUR | W66: =IFERROR(VLOOKUP(V66,Curr!$B$2:$C$13,2,FALSE),0) -> 10.8 | X66: =U66*W66 -> 0 | Y66: =Q66 -> 0 | Z66: =+Y66*R66 -> 0 | AA66: EUR | AB66: =IFERROR(VLOOKUP(AA66,Curr!$B$2:$C$13,2,FALSE),0) -> 10.8 | AC66: =+Y66*AB66*R66 -> 0 | AD66: =+AC66-X66 -> 0 | AE66: =IFERROR(AD66/AC66,0) -> 0
S67: =+Q67*R67 -> 0 | T67: 0 | U67: =S67*(1-T67) -> 0 | V67: EUR | W67: =IFERROR(VLOOKUP(V67,Curr!$B$2:$C$13,2,FALSE),0) -> 10.8 | X67: =U67*W67 -> 0 | Y67: =Q67 -> 0 | Z67: =+Y67*R67 -> 0 | AA67: EUR | AB67: =IFERROR(VLOOKUP(AA67,Curr!$B$2:$C$13,2,FALSE),0) -> 10.8 | AC67: =+Y67*AB67*R67 -> 0 | AD67: =+AC67-X67 -> 0 | AE67: =IFERROR(AD67/AC67,0) -> 0
C68: Day 14 | D68: Drive | E68: 10.07.2026 | J68: Ålesund: Drive to Ålesund Airport | Q68: 0 | R68: 0 | S68: =+Q68*R68 -> 0 | T68: 0 | U68: =S68*(1-T68) -> 0 | V68: EUR | W68: =IFERROR(VLOOKUP(V68,Curr!$B$2:$C$13,2,FALSE),0) -> 10.8 | X68: =U68*W68 -> 0 | Y68: =Q68 -> 0 | Z68: =+Y68*R68 -> 0 | AA68: EUR | AB68: =IFERROR(VLOOKUP(AA68,Curr!$B$2:$C$13,2,FALSE),0) -> 10.8 | AC68: =+Y68*AB68*R68 -> 0 | AD68: =+AC68-X68 -> 0 | AE68: =IFERROR(AD68/AC68,0) -> 0
C69: Day 14 | D69: Car | E69: 10.07.2026 | J69: Ålesund: Deliver your rental car at the Ålesund Airport Car rental office | Q69: 0 | R69: 0 | S69: =+Q69*R69 -> 0 | T69: 0 | U69: =S69*(1-T69) -> 0 | V69: EUR | W69: =IFERROR(VLOOKUP(V69,Curr!$B$2:$C$13,2,FALSE),0) -> 10.8 | X69: =U69*W69 -> 0 | Y69: =Q69 -> 0 | Z69: =+Y69*R69 -> 0 | AA69: EUR | AB69: =IFERROR(VLOOKUP(AA69,Curr!$B$2:$C$13,2,FALSE),0) -> 10.8 | AC69: =+Y69*AB69*R69 -> 0 | AD69: =+AC69-X69 -> 0 | AE69: =IFERROR(AD69/AC69,0) -> 0
C70: Day 14 | D70: Flight | E70: 10.07.2026 | J70: Ålesund: Flight to Oslo - Time: 4:15 pm - 5:10 pm - Luggage included: 1 x 23 kg check in and 1 x 8 kg carry on per person | P70: https://booking.norwegian.com/booking/flight/0 | Q70: 1900 | R70: 4 | S70: =+Q70*R70 -> 7600 | T70: 0 | U70: =S70*(1-T70) -> 7600 | V70: NOK | W70: =IFERROR(VLOOKUP(V70,Curr!$B$2:$C$13,2,FALSE),0) -> 1 | X70: =U70*W70 -> 7600 | Y70: =Q70/11/0.8 -> 215.90909 | Z70: =+Y70*R70 -> 863.63636 | AA70: EUR | AB70: =IFERROR(VLOOKUP(AA70,Curr!$B$2:$C$13,2,FALSE),0) -> 10.8 | AC70: =+Y70*AB70*R70 -> 9327.2727 | AD70: =+AC70-X70 -> 1727.2727 | AE70: =IFERROR(AD70/AC70,0) -> 0.18518519
C71: Day 14 | D71: Transfer | E71: 10.07.2026 | J71: Oslo: Self transfer to your accommodation | Q71: 0 | R71: 0 | S71: =+Q71*R71 -> 0 | T71: 0 | U71: =S71*(1-T71) -> 0 | V71: EUR | W71: =IFERROR(VLOOKUP(V71,Curr!$B$2:$C$13,2,FALSE),0) -> 10.8 | X71: =U71*W71 -> 0 | Y71: =Q71 -> 0 | Z71: =+Y71*R71 -> 0 | AA71: EUR | AB71: =IFERROR(VLOOKUP(AA71,Curr!$B$2:$C$13,2,FALSE),0) -> 10.8 | AC71: =+Y71*AB71*R71 -> 0 | AD71: =+AC71-X71 -> 0 | AE71: =IFERROR(AD71/AC71,0) -> 0
C72: Day 14 | D72: Hotel | E72: 10.07.2026 | F72: 11.07.2026 | J72: Oslo: Check in to your accommodation for a 1 night stay - Scandic Oslo Airport - 2 x Superior - breakfast included | P72: https://app.hotelbeds.com/factsheet/stay/107785?check_in=10-07-2026&check_out=11-07-2026&occupancy=2~0_2~0&packaging=true | Q72: 275 | R72: 1 | S72: =+Q72*R72 -> 275 | T72: 0 | U72: =S72*(1-T72) -> 275 | V72: EUR | W72: =IFERROR(VLOOKUP(V72,Curr!$B$2:$C$13,2,FALSE),0) -> 10.8 | X72: =U72*W72 -> 2970 | Y72: =Q72/0.85 -> 323.52941 | Z72: =+Y72*R72 -> 323.52941 | AA72: EUR | AB72: =IFERROR(VLOOKUP(AA72,Curr!$B$2:$C$13,2,FALSE),0) -> 10.8 | AC72: =+Y72*AB72*R72 -> 3494.1176 | AD72: =+AC72-X72 -> 524.11765 | AE72: =IFERROR(AD72/AC72,0) -> 0.15
C73: Day 14 | D73: Leisure | E73: 10.07.2026 | J73: Oslo: Spend time at leisure | Q73: 0 | R73: 0 | S73: =+Q73*R73 -> 0 | T73: 0 | U73: =S73*(1-T73) -> 0 | V73: EUR | W73: =IFERROR(VLOOKUP(V73,Curr!$B$2:$C$13,2,FALSE),0) -> 10.8 | X73: =U73*W73 -> 0 | Y73: =Q73 -> 0 | Z73: =+Y73*R73 -> 0 | AA73: EUR | AB73: =IFERROR(VLOOKUP(AA73,Curr!$B$2:$C$13,2,FALSE),0) -> 10.8 | AC73: =+Y73*AB73*R73 -> 0 | AD73: =+AC73-X73 -> 0 | AE73: =IFERROR(AD73/AC73,0) -> 0
S74: =+Q74*R74 -> 0 | T74: 0 | U74: =S74*(1-T74) -> 0 | V74: EUR | W74: =IFERROR(VLOOKUP(V74,Curr!$B$2:$C$13,2,FALSE),0) -> 10.8 | X74: =U74*W74 -> 0 | Y74: =Q74 -> 0 | Z74: =+Y74*R74 -> 0 | AA74: EUR | AB74: =IFERROR(VLOOKUP(AA74,Curr!$B$2:$C$13,2,FALSE),0) -> 10.8 | AC74: =+Y74*AB74*R74 -> 0 | AD74: =+AC74-X74 -> 0 | AE74: =IFERROR(AD74/AC74,0) -> 0
C75: Day 15 | D75: Transfer | E75: 11.07.2026 | J75: Oslo: Self transfer to Oslo Airport | Q75: 0 | R75: 0 | S75: =+Q75*R75 -> 0 | T75: 0 | U75: =S75*(1-T75) -> 0 | V75: EUR | W75: =IFERROR(VLOOKUP(V75,Curr!$B$2:$C$13,2,FALSE),0) -> 10.8 | X75: =U75*W75 -> 0 | Y75: =Q75 -> 0 | Z75: =+Y75*R75 -> 0 | AA75: EUR | AB75: =IFERROR(VLOOKUP(AA75,Curr!$B$2:$C$13,2,FALSE),0) -> 10.8 | AC75: =+Y75*AB75*R75 -> 0 | AD75: =+AC75-X75 -> 0 | AE75: =IFERROR(AD75/AC75,0) -> 0
C76: Day 15 | D76: Departure | E76: 11.07.2026 | J76: Oslo: Departure home | Q76: 0 | R76: 0 | S76: =+Q76*R76 -> 0 | T76: 0 | U76: =S76*(1-T76) -> 0 | V76: EUR | W76: =IFERROR(VLOOKUP(V76,Curr!$B$2:$C$13,2,FALSE),0) -> 10.8 | X76: =U76*W76 -> 0 | Y76: =Q76 -> 0 | Z76: =+Y76*R76 -> 0 | AA76: EUR | AB76: =IFERROR(VLOOKUP(AA76,Curr!$B$2:$C$13,2,FALSE),0) -> 10.8 | AC76: =+Y76*AB76*R76 -> 0 | AD76: =+AC76-X76 -> 0 | AE76: =IFERROR(AD76/AC76,0) -> 0
Q77: 0 | R77: 0 | S77: =+Q77*R77 -> 0 | T77: 0 | U77: =S77*(1-T77) -> 0 | V77: EUR | W77: =IFERROR(VLOOKUP(V77,Curr!$B$2:$C$13,2,FALSE),0) -> 10.8 | X77: =U77*W77 -> 0 | Y77: =Q77 -> 0 | Z77: =+Y77*R77 -> 0 | AA77: EUR | AB77: =IFERROR(VLOOKUP(AA77,Curr!$B$2:$C$13,2,FALSE),0) -> 10.8 | AC77: =+Y77*AB77*R77 -> 0 | AD77: =+AC77-X77 -> 0 | AE77: =IFERROR(AD77/AC77,0) -> 0
Q78: 0 | R78: 0 | S78: =+Q78*R78 -> 0 | T78: 0 | U78: =S78*(1-T78) -> 0 | V78: EUR | W78: =IFERROR(VLOOKUP(V78,Curr!$B$2:$C$13,2,FALSE),0) -> 10.8 | X78: =U78*W78 -> 0 | Y78: =Q78 -> 0 | Z78: =+Y78*R78 -> 0 | AA78: EUR | AB78: =IFERROR(VLOOKUP(AA78,Curr!$B$2:$C$13,2,FALSE),0) -> 10.8 | AC78: =+Y78*AB78*R78 -> 0 | AD78: =+AC78-X78 -> 0 | AE78: =IFERROR(AD78/AC78,0) -> 0
Q79: 0 | R79: 0 | S79: =+Q79*R79 -> 0 | T79: 0 | U79: =S79*(1-T79) -> 0 | V79: EUR | W79: =IFERROR(VLOOKUP(V79,Curr!$B$2:$C$13,2,FALSE),0) -> 10.8 | X79: =U79*W79 -> 0 | Y79: =Q79 -> 0 | Z79: =+Y79*R79 -> 0 | AA79: EUR | AB79: =IFERROR(VLOOKUP(AA79,Curr!$B$2:$C$13,2,FALSE),0) -> 10.8 | AC79: =+Y79*AB79*R79 -> 0 | AD79: =+AC79-X79 -> 0 | AE79: =IFERROR(AD79/AC79,0) -> 0
Q80: 0 | R80: 0 | S80: =+Q80*R80 -> 0 | T80: 0 | U80: =S80*(1-T80) -> 0 | V80: EUR | W80: =IFERROR(VLOOKUP(V80,Curr!$B$2:$C$13,2,FALSE),0) -> 10.8 | X80: =U80*W80 -> 0 | Y80: =Q80 -> 0 | Z80: =+Y80*R80 -> 0 | AA80: EUR | AB80: =IFERROR(VLOOKUP(AA80,Curr!$B$2:$C$13,2,FALSE),0) -> 10.8 | AC80: =+Y80*AB80*R80 -> 0 | AD80: =+AC80-X80 -> 0 | AE80: =IFERROR(AD80/AC80,0) -> 0
Q81: 0 | R81: 0 | S81: =+Q81*R81 -> 0 | T81: 0 | U81: =S81*(1-T81) -> 0 | V81: EUR | W81: =IFERROR(VLOOKUP(V81,Curr!$B$2:$C$13,2,FALSE),0) -> 10.8 | X81: =U81*W81 -> 0 | Y81: =Q81 -> 0 | Z81: =+Y81*R81 -> 0 | AA81: EUR | AB81: =IFERROR(VLOOKUP(AA81,Curr!$B$2:$C$13,2,FALSE),0) -> 10.8 | AC81: =+Y81*AB81*R81 -> 0 | AD81: =+AC81-X81 -> 0 | AE81: =IFERROR(AD81/AC81,0) -> 0
Q82: 0 | R82: 0 | S82: =+Q82*R82 -> 0 | T82: 0 | U82: =S82*(1-T82) -> 0 | V82: EUR | W82: =IFERROR(VLOOKUP(V82,Curr!$B$2:$C$13,2,FALSE),0) -> 10.8 | X82: =U82*W82 -> 0 | Y82: =Q82 -> 0 | Z82: =+Y82*R82 -> 0 | AA82: EUR | AB82: =IFERROR(VLOOKUP(AA82,Curr!$B$2:$C$13,2,FALSE),0) -> 10.8 | AC82: =+Y82*AB82*R82 -> 0 | AD82: =+AC82-X82 -> 0 | AE82: =IFERROR(AD82/AC82,0) -> 0
Q83: 0 | R83: 0 | S83: =+Q83*R83 -> 0 | T83: 0 | U83: =S83*(1-T83) -> 0 | V83: EUR | W83: =IFERROR(VLOOKUP(V83,Curr!$B$2:$C$13,2,FALSE),0) -> 10.8 | X83: =U83*W83 -> 0 | Y83: =Q83 -> 0 | Z83: =+Y83*R83 -> 0 | AA83: EUR | AB83: =IFERROR(VLOOKUP(AA83,Curr!$B$2:$C$13,2,FALSE),0) -> 10.8 | AC83: =+Y83*AB83*R83 -> 0 | AD83: =+AC83-X83 -> 0 | AE83: =IFERROR(AD83/AC83,0) -> 0
B85: Totals | D85: x | E85: x | F85: x | G85: x | H85: x | I85: x | J85: x | K85: x | L85: x | M85: x | N85: x | O85: x | P85: x | Q85: x | R85: x | S85: x | T85: x | U85: x | V85: x | W85: x | X85: x | Y85: x | Z85: =SUM(Z7:Z83) -> 26205.413 | AC85: =SUM(AC7:AC83) -> 283018.46 | AD85: =SUM(AD7:AD83) -> 48635.703 | AE85: =IFERROR(AD85/AC85,0) -> 0.1718464 | AF85: =SUM(AF8:AF84) -> 0 | AG85: =SUM(AG8:AG84) -> 0 | AH85: =SUM(AH8:AH84) -> 0 | AI85: =SUM(AI8:AI84) -> 0 | AJ85: =SUM(AJ8:AJ84) -> 0
Y87: Quote | Z87: 26200
Y88: PP | Z88: =Z87/4 -> 6550
Y90: USD | Z90: 30800
Y91: PP | Z91: =Z90/4 -> 7700
Y93: NoHotel | Z93: 9840
Y94: USD | Z94: 11600
Y95: PP | Z95: =Z94/4 -> 2900

Sheet Kalk 4
B2: Dates: 27.06.2026
B3: Pax: 4
B4: Rooming: 2 x double
B6: ID | C6: Day | D6: Type | E6: From date | F6: To date | G6: From time | H6: To time | I6: Supplier | J6: Travel element | K6: Manual booking? | L6: Status | M6: Comments | N6: Non-refundable | O6: Refundable | P6: URL | Q6: Gross P per unit | R6: Units | S6: Gross P | T6: Supp Comm | U6: Net P | V6: Supp curr | W6: X-rate | X6: Net P NOK | Y6: Sales P per unit | Z6: Price | AA6: Sales curr | AB6: X-rate | AC6: Sales P NOK tot | AD6: GP NOK | AE6: GP % | AF6: VAT25 | AG6: VAT15 | AH6: VAT12 | AI6: VAT0-D | AJ6: VAT0-I
C7: Day 1 | D7: Arrival | E7: 27.06.2026 | J7: Keflavik: Welcome to Iceland | Q7: 0 | R7: 0 | S7: =+Q7*R7 -> 0 | T7: 0 | U7: =S7*(1-T7) -> 0 | V7: EUR | W7: =IFERROR(VLOOKUP(V7,Curr!$B$2:$C$13,2,FALSE),0) -> 10.8 | X7: =U7*W7 -> 0 | Y7: =Q7 -> 0 | Z7: =+Y7*R7 -> 0 | AA7: EUR | AB7: =IFERROR(VLOOKUP(AA7,Curr!$B$2:$C$13,2,FALSE),0) -> 10.8 | AC7: =+Y7*AB7*R7 -> 0 | AD7: =+AC7-X7 -> 0 | AE7: =IFERROR(AD7/AC7,0) -> 0
C8: Day 1 | D8: Tranfser | E8: 27.06.2026 | J8: Keflavik: Private transfer to your accommodation | Q8: 160 | R8: 1 | S8: =+Q8*R8 -> 160 | T8: 0.2 | U8: =S8*(1-T8) -> 128 | V8: EUR | W8: =IFERROR(VLOOKUP(V8,Curr!$B$2:$C$13,2,FALSE),0) -> 10.8 | X8: =U8*W8 -> 1382.4 | Y8: =Q8 -> 160 | Z8: =+Y8*R8 -> 160 | AA8: EUR | AB8: =IFERROR(VLOOKUP(AA8,Curr!$B$2:$C$13,2,FALSE),0) -> 10.8 | AC8: =+Y8*AB8*R8 -> 1728 | AD8: =+AC8-X8 -> 345.6 | AE8: =IFERROR(AD8/AC8,0) -> 0.2
C9: Day 1 | D9: Hotel | E9: 27.06.2026 | F9: 29.06.2026 | J9: Reykjavik: Check in to your accommodation for a 1 night stay - Borg by Keahotels - 2 x Deluxe room - breakfast included | P9: https://app.hotelbeds.com/factsheet/stay/90467?check_in=27-06-2026&check_out=29-06-2026&occupancy=2~0_2~0&packaging=true | Q9: 2075 | R9: 1 | S9: =+Q9*R9 -> 2075 | T9: 0 | U9: =S9*(1-T9) -> 2075 | V9: EUR | W9: =IFERROR(VLOOKUP(V9,Curr!$B$2:$C$13,2,FALSE),0) -> 10.8 | X9: =U9*W9 -> 22410 | Y9: =Q9/0.8 -> 2593.75 | Z9: =+Y9*R9 -> 2593.75 | AA9: EUR | AB9: =IFERROR(VLOOKUP(AA9,Curr!$B$2:$C$13,2,FALSE),0) -> 10.8 | AC9: =+Y9*AB9*R9 -> 28012.5 | AD9: =+AC9-X9 -> 5602.5 | AE9: =IFERROR(AD9/AC9,0) -> 0.2
C10: Day 1 | D10: Leisure | E10: 27.06.2026 | J10: Reykjavik: Spend time at leisure | Q10: 0 | R10: 0 | S10: =+Q10*R10 -> 0 | T10: 0 | U10: =S10*(1-T10) -> 0 | V10: EUR | W10: =IFERROR(VLOOKUP(V10,Curr!$B$2:$C$13,2,FALSE),0) -> 10.8 | X10: =U10*W10 -> 0 | Y10: =Q10 -> 0 | Z10: =+Y10*R10 -> 0 | AA10: EUR | AB10: =IFERROR(VLOOKUP(AA10,Curr!$B$2:$C$13,2,FALSE),0) -> 10.8 | AC10: =+Y10*AB10*R10 -> 0 | AD10: =+AC10-X10 -> 0 | AE10: =IFERROR(AD10/AC10,0) -> 0
S11: =+Q11*R11 -> 0 | T11: 0 | U11: =S11*(1-T11) -> 0 | V11: EUR | W11: =IFERROR(VLOOKUP(V11,Curr!$B$2:$C$13,2,FALSE),0) -> 10.8 | X11: =U11*W11 -> 0 | Y11: =Q11 -> 0 | Z11: =+Y11*R11 -> 0 | AA11: EUR | AB11: =IFERROR(VLOOKUP(AA11,Curr!$B$2:$C$13,2,FALSE),0) -> 10.8 | AC11: =+Y11*AB11*R11 -> 0 | AD11: =+AC11-X11 -> 0 | AE11: =IFERROR(AD11/AC11,0) -> 0
C12: Day 2 | D12: Activity | E12: 28.06.2026 | J12: Reykjavik: FlyOver Iceland - Time: 12:30 pm - 1:30 pm - Meeting point: Fiskislóð 43 - Includes: Entry or admission fee, FlyOver Iceland Pursuit | P12: https://booknordics.com/iceland/western-iceland/reykjavik/flyover-iceland | Q12: 35 | R12: 4 | S12: =+Q12*R12 -> 140 | T12: 0.2 | U12: =S12*(1-T12) -> 112 | V12: EUR | W12: =IFERROR(VLOOKUP(V12,Curr!$B$2:$C$13,2,FALSE),0) -> 10.8 | X12: =U12*W12 -> 1209.6 | Y12: =Q12/0.8 -> 43.75 | Z12: =+Y12*R12 -> 175 | AA12: EUR | AB12: =IFERROR(VLOOKUP(AA12,Curr!$B$2:$C$13,2,FALSE),0) -> 10.8 | AC12: =+Y12*AB12*R12 -> 1890 | AD12: =+AC12-X12 -> 680.4 | AE12: =IFERROR(AD12/AC12,0) -> 0.36
C13: Day 2 | D13: Leisure | E13: 28.06.2026 | J13: Reykjavik: Spend time at leisure | Q13: 0 | R13: 0 | S13: =+Q13*R13 -> 0 | T13: 0 | U13: =S13*(1-T13) -> 0 | V13: EUR | W13: =IFERROR(VLOOKUP(V13,Curr!$B$2:$C$13,2,FALSE),0) -> 10.8 | X13: =U13*W13 -> 0 | Y13: =Q13 -> 0 | Z13: =+Y13*R13 -> 0 | AA13: EUR | AB13: =IFERROR(VLOOKUP(AA13,Curr!$B$2:$C$13,2,FALSE),0) -> 10.8 | AC13: =+Y13*AB13*R13 -> 0 | AD13: =+AC13-X13 -> 0 | AE13: =IFERROR(AD13/AC13,0) -> 0
C14: Day 2 | D14: Activity | E14: 28.06.2026 | J14: Reykjavík: Classic Whale Watching under the Midnight Sun - Time: 8:30 pm - 11:30 pm - Meeting point: Elding ticket office, Ægisgarður 5c -Includes: 2-3,5 hours whale watching tour, Access to our Wildlife Exhibition, Excellent live commentary in English, Use of warm overalls & mellow music | P14: https://booknordics.com/iceland/western-iceland/reykjavik/reykjavik-classic-whales-in-the-midnight-sun | Q14: 127 | R14: 4 | S14: =+Q14*R14 -> 508 | T14: 0.25 | U14: =S14*(1-T14) -> 381 | V14: EUR | W14: =IFERROR(VLOOKUP(V14,Curr!$B$2:$C$13,2,FALSE),0) -> 10.8 | X14: =U14*W14 -> 4114.8 | Y14: =Q14 -> 127 | Z14: =+Y14*R14 -> 508 | AA14: EUR | AB14: =IFERROR(VLOOKUP(AA14,Curr!$B$2:$C$13,2,FALSE),0) -> 10.8 | AC14: =+Y14*AB14*R14 -> 5486.4 | AD14: =+AC14-X14 -> 1371.6 | AE14: =IFERROR(AD14/AC14,0) -> 0.25
S15: =+Q15*R15 -> 0 | T15: 0 | U15: =S15*(1-T15) -> 0 | V15: EUR | W15: =IFERROR(VLOOKUP(V15,Curr!$B$2:$C$13,2,FALSE),0) -> 10.8 | X15: =U15*W15 -> 0 | Y15: =Q15 -> 0 | Z15: =+Y15*R15 -> 0 | AA15: EUR | AB15: =IFERROR(VLOOKUP(AA15,Curr!$B$2:$C$13,2,FALSE),0) -> 10.8 | AC15: =+Y15*AB15*R15 -> 0 | AD15: =+AC15-X15 -> 0 | AE15: =IFERROR(AD15/AC15,0) -> 0
C16: Day 3 | D16: Transfer | E16: 29.06.2026 | J16: Reykjavik: Self transfer by Uber to the car rental office | Q16: 0 | R16: 0 | S16: =+Q16*R16 -> 0 | T16: 0 | U16: =S16*(1-T16) -> 0 | V16: EUR | W16: =IFERROR(VLOOKUP(V16,Curr!$B$2:$C$13,2,FALSE),0) -> 10.8 | X16: =U16*W16 -> 0 | Y16: =Q16 -> 0 | Z16: =+Y16*R16 -> 0 | AA16: EUR | AB16: =IFERROR(VLOOKUP(AA16,Curr!$B$2:$C$13,2,FALSE),0) -> 10.8 | AC16: =+Y16*AB16*R16 -> 0 | AD16: =+AC16-X16 -> 0 | AE16: =IFERROR(AD16/AC16,0) -> 0
C17: Day 3 | D17: Car | E17: 29.06.2026 | F17: 03.07.2026 | J17: Reykjavik: Pick up your rental car at the car rental office - Car: TOYOTA RAV4 2.0 4WD AUTOMATIC or similar - Office Location: Njardargata Fluggardar - Includes: Collision damage waiver, Fuel information, Unlimited mileage, Theft protection, Vat, Personal accident insurance, Cancellation fee - Excludes: 1 way fee, road tax | P17: https://app.hotelbeds.com/carhire/search?baggage=4&results=20&sortBy=LOWEST_PRICE_FIRST&field=PRICE&direction=ASCENDING&page=2&destinationTab=Reykjav%C3%ADk&pickupDate=29-06-2026&pickupTime=12:00&dropoffDate=03-07-2026&dropoffTime=12:00&sameOfficeCheckbox=false&officePickupControl=1171&officeDropoffControl=701&typeDepartureCode=airport&_timestamp=1776931327625&departureTab=Keflav%C3%ADk%20International%20Airport%20(KEF)&typeArrivalCode=city | Q17: 564 | R17: 1 | S17: =+Q17*R17 -> 564 | T17: 0 | U17: =S17*(1-T17) -> 564 | V17: EUR | W17: =IFERROR(VLOOKUP(V17,Curr!$B$2:$C$13,2,FALSE),0) -> 10.8 | X17: =U17*W17 -> 6091.2 | Y17: =Q17/0.8 -> 705 | Z17: =+Y17*R17 -> 705 | AA17: EUR | AB17: =IFERROR(VLOOKUP(AA17,Curr!$B$2:$C$13,2,FALSE),0) -> 10.8 | AC17: =+Y17*AB17*R17 -> 7614 | AD17: =+AC17-X17 -> 1522.8 | AE17: =IFERROR(AD17/AC17,0) -> 0.2
C18: Day 3 | D18: Drive | E18: 29.06.2026 | J18: Reykjavik: Drive the Golden Circle to Asborgir - Driving time: 3 hours - Things to see: Öxarárfoss, Efstidalur, Geysir Hot Springs, Gullfoss Waterfall, Friðheimar, Kerið | Q18: 0 | R18: 0 | S18: =+Q18*R18 -> 0 | T18: 0 | U18: =S18*(1-T18) -> 0 | V18: EUR | W18: =IFERROR(VLOOKUP(V18,Curr!$B$2:$C$13,2,FALSE),0) -> 10.8 | X18: =U18*W18 -> 0 | Y18: =Q18 -> 0 | Z18: =+Y18*R18 -> 0 | AA18: EUR | AB18: =IFERROR(VLOOKUP(AA18,Curr!$B$2:$C$13,2,FALSE),0) -> 10.8 | AC18: =+Y18*AB18*R18 -> 0 | AD18: =+AC18-X18 -> 0 | AE18: =IFERROR(AD18/AC18,0) -> 0
C19: Day 3 | D19: Hotel | E19: 29.06.2026 | F19: 30.07.2026 | J19: Asborgir: Check in to your accommodation for a 1 night stay - Grimsborgir by Keahotels - 2 x Superior Room - Breakfast included | P19: https://app.hotelbeds.com/factsheet/stay/257043?check_in=29-06-2026&check_out=30-06-2026&occupancy=2~0_2~0&packaging=true | Q19: 607 | R19: 1 | S19: =+Q19*R19 -> 607 | T19: 0 | U19: =S19*(1-T19) -> 607 | V19: EUR | W19: =IFERROR(VLOOKUP(V19,Curr!$B$2:$C$13,2,FALSE),0) -> 10.8 | X19: =U19*W19 -> 6555.6 | Y19: =Q19/0.8 -> 758.75 | Z19: =+Y19*R19 -> 758.75 | AA19: EUR | AB19: =IFERROR(VLOOKUP(AA19,Curr!$B$2:$C$13,2,FALSE),0) -> 10.8 | AC19: =+Y19*AB19*R19 -> 8194.5 | AD19: =+AC19-X19 -> 1638.9 | AE19: =IFERROR(AD19/AC19,0) -> 0.2
C20: Day 3 | D20: Leisure | E20: 29.06.2026 | J20: Asborgir: Spend time at leisure | Q20: 0 | R20: 0 | S20: =+Q20*R20 -> 0 | T20: 0 | U20: =S20*(1-T20) -> 0 | V20: EUR | W20: =IFERROR(VLOOKUP(V20,Curr!$B$2:$C$13,2,FALSE),0) -> 10.8 | X20: =U20*W20 -> 0 | Y20: =Q20 -> 0 | Z20: =+Y20*R20 -> 0 | AA20: EUR | AB20: =IFERROR(VLOOKUP(AA20,Curr!$B$2:$C$13,2,FALSE),0) -> 10.8 | AC20: =+Y20*AB20*R20 -> 0 | AD20: =+AC20-X20 -> 0 | AE20: =IFERROR(AD20/AC20,0) -> 0
S21: =+Q21*R21 -> 0 | T21: 0 | U21: =S21*(1-T21) -> 0 | V21: EUR | W21: =IFERROR(VLOOKUP(V21,Curr!$B$2:$C$13,2,FALSE),0) -> 10.8 | X21: =U21*W21 -> 0 | Y21: =Q21/0.8 -> 0 | Z21: =+Y21*R21 -> 0 | AA21: EUR | AB21: =IFERROR(VLOOKUP(AA21,Curr!$B$2:$C$13,2,FALSE),0) -> 10.8 | AC21: =+Y21*AB21*R21 -> 0 | AD21: =+AC21-X21 -> 0 | AE21: =IFERROR(AD21/AC21,0) -> 0
C22: Day 4 | D22: Drive | E22: 30.07.2026 | J22: Asborgir: Drive to Vik - Driving time: 2 hrs - Things to See: Selfoss, Hella, Hvolsvöllur | Q22: 0 | R22: 0 | S22: =+Q22*R22 -> 0 | T22: 0 | U22: =S22*(1-T22) -> 0 | V22: EUR | W22: =IFERROR(VLOOKUP(V22,Curr!$B$2:$C$13,2,FALSE),0) -> 10.8 | X22: =U22*W22 -> 0 | Y22: =Q22 -> 0 | Z22: =+Y22*R22 -> 0 | AA22: EUR | AB22: =IFERROR(VLOOKUP(AA22,Curr!$B$2:$C$13,2,FALSE),0) -> 10.8 | AC22: =+Y22*AB22*R22 -> 0 | AD22: =+AC22-X22 -> 0 | AE22: =IFERROR(AD22/AC22,0) -> 0
C23: Day 4 | D23: Hotel | E23: 30.07.2026 | F23: 02.07.2026 | J23: Vik: Check in to your accommodation for a 2 night stay - Hotel Katla by Keahotels - 2 x Superior Double room - breakfast included | P23: https://www.ratehawk.com/hotel/iceland/vik_i_myrdal/mid7524341/hotel_hofdabrekka_country_hotel/?q=6130429&dates=30.06.2026-02.07.2026&guests=2-2&price=one&sid=22ec769a-b117-452f-befc-9c97bff50e0a | Q23: 2976 | R23: 1 | S23: =+Q23*R23 -> 2976 | T23: 0 | U23: =S23*(1-T23) -> 2976 | V23: EUR | W23: =IFERROR(VLOOKUP(V23,Curr!$B$2:$C$13,2,FALSE),0) -> 10.8 | X23: =U23*W23 -> 32140.8 | Y23: =Q23/0.85 -> 3501.1765 | Z23: =+Y23*R23 -> 3501.1765 | AA23: EUR | AB23: =IFERROR(VLOOKUP(AA23,Curr!$B$2:$C$13,2,FALSE),0) -> 10.8 | AC23: =+Y23*AB23*R23 -> 37812.706 | AD23: =+AC23-X23 -> 5671.9059 | AE23: =IFERROR(AD23/AC23,0) -> 0.15
C24: Day 4 | D24: Leisure | E24: 30.07.2026 | J24: Vik: Spend time at leisure | Q24: 0 | R24: 0 | S24: =+Q24*R24 -> 0 | T24: 0 | U24: =S24*(1-T24) -> 0 | V24: EUR | W24: =IFERROR(VLOOKUP(V24,Curr!$B$2:$C$13,2,FALSE),0) -> 10.8 | X24: =U24*W24 -> 0 | Y24: =Q24 -> 0 | Z24: =+Y24*R24 -> 0 | AA24: EUR | AB24: =IFERROR(VLOOKUP(AA24,Curr!$B$2:$C$13,2,FALSE),0) -> 10.8 | AC24: =+Y24*AB24*R24 -> 0 | AD24: =+AC24-X24 -> 0 | AE24: =IFERROR(AD24/AC24,0) -> 0
S25: =+Q25*R25 -> 0 | T25: 0 | U25: =S25*(1-T25) -> 0 | V25: EUR | W25: =IFERROR(VLOOKUP(V25,Curr!$B$2:$C$13,2,FALSE),0) -> 10.8 | X25: =U25*W25 -> 0 | Y25: =Q25 -> 0 | Z25: =+Y25*R25 -> 0 | AA25: EUR | AB25: =IFERROR(VLOOKUP(AA25,Curr!$B$2:$C$13,2,FALSE),0) -> 10.8 | AC25: =+Y25*AB25*R25 -> 0 | AD25: =+AC25-X25 -> 0 | AE25: =IFERROR(AD25/AC25,0) -> 0
C26: Day 5 | D26: Activity | E26: 01.07.2026 | J26: Vik: Lava Show Vík - Time: 11:00 am - 12:00 pm - Meeeting point: Icelandic Lava Show, Víkurbraut 5 - Includes: A chance to get up close to real flowing lava, The only live lava show in the world, Security goggles, A live host makes the show fun and personal, A short educational video about Icelandic volcanism, A true story from the 1918 Katla eruption, A sensory loaded experience - you feel the heat from the lava, A Q&A session at the end of the show, A unique once-in-a-lifetime experience | P26: https://booknordics.com/iceland/southern-iceland/vik/lava-show-vik-the-original | Q26: 46 | R26: 4 | S26: =+Q26*R26 -> 184 | T26: 0.2 | U26: =S26*(1-T26) -> 147.2 | V26: EUR | W26: =IFERROR(VLOOKUP(V26,Curr!$B$2:$C$13,2,FALSE),0) -> 10.8 | X26: =U26*W26 -> 1589.76 | Y26: =Q26/0.8 -> 57.5 | Z26: =+Y26*R26 -> 230 | AA26: EUR | AB26: =IFERROR(VLOOKUP(AA26,Curr!$B$2:$C$13,2,FALSE),0) -> 10.8 | AC26: =+Y26*AB26*R26 -> 2484 | AD26: =+AC26-X26 -> 894.24 | AE26: =IFERROR(AD26/AC26,0) -> 0.36
C27: Day 5 | D27: Leisure | E27: 01.07.2026 | J27: Vik: Spend time at leisure | Q27: 0 | R27: 0 | S27: =+Q27*R27 -> 0 | T27: 0 | U27: =S27*(1-T27) -> 0 | V27: EUR | W27: =IFERROR(VLOOKUP(V27,Curr!$B$2:$C$13,2,FALSE),0) -> 10.8 | X27: =U27*W27 -> 0 | Y27: =Q27 -> 0 | Z27: =+Y27*R27 -> 0 | AA27: EUR | AB27: =IFERROR(VLOOKUP(AA27,Curr!$B$2:$C$13,2,FALSE),0) -> 10.8 | AC27: =+Y27*AB27*R27 -> 0 | AD27: =+AC27-X27 -> 0 | AE27: =IFERROR(AD27/AC27,0) -> 0
C28: Day 5 | D28: Activity | E28: 01.07.2026 | J28: Vik: Ice Cave Underneath Katla Volcano Super Jeep Tour - Time: 6:00 pm - 9:00 pm - Meeting point: Tröll Expeditions Katla Ice Cave, Víkubraut 26 - Includes: Stunning ride on a super jeep, Certified glacier guide, Visit to a natural ice cave, All safety ice cave equipment, Scenic landscapes viewing | P28: https://booknordics.com/iceland/southern-iceland/vik/katla-ice-cave-super-jeep-from-vik | Q28: 204 | R28: 4 | S28: =+Q28*R28 -> 816 | T28: 0.25 | U28: =S28*(1-T28) -> 612 | V28: EUR | W28: =IFERROR(VLOOKUP(V28,Curr!$B$2:$C$13,2,FALSE),0) -> 10.8 | X28: =U28*W28 -> 6609.6 | Y28: =Q28 -> 204 | Z28: =+Y28*R28 -> 816 | AA28: EUR | AB28: =IFERROR(VLOOKUP(AA28,Curr!$B$2:$C$13,2,FALSE),0) -> 10.8 | AC28: =+Y28*AB28*R28 -> 8812.8 | AD28: =+AC28-X28 -> 2203.2 | AE28: =IFERROR(AD28/AC28,0) -> 0.25
S29: =+Q29*R29 -> 0 | T29: 0 | U29: =S29*(1-T29) -> 0 | V29: EUR | W29: =IFERROR(VLOOKUP(V29,Curr!$B$2:$C$13,2,FALSE),0) -> 10.8 | X29: =U29*W29 -> 0 | Y29: =Q29 -> 0 | Z29: =+Y29*R29 -> 0 | AA29: EUR | AB29: =IFERROR(VLOOKUP(AA29,Curr!$B$2:$C$13,2,FALSE),0) -> 10.8 | AC29: =+Y29*AB29*R29 -> 0 | AD29: =+AC29-X29 -> 0 | AE29: =IFERROR(AD29/AC29,0) -> 0
C30: Day 6 | D30: Drive | E30: 02.07.2026 | J30: Vik: Drive to Reykjavik via the South Coast - Driving time: 2 hrs 30 minutes - Things to see: | Q30: 0 | R30: 0 | S30: =+Q30*R30 -> 0 | T30: 0 | U30: =S30*(1-T30) -> 0 | V30: EUR | W30: =IFERROR(VLOOKUP(V30,Curr!$B$2:$C$13,2,FALSE),0) -> 10.8 | X30: =U30*W30 -> 0 | Y30: =Q30 -> 0 | Z30: =+Y30*R30 -> 0 | AA30: EUR | AB30: =IFERROR(VLOOKUP(AA30,Curr!$B$2:$C$13,2,FALSE),0) -> 10.8 | AC30: =+Y30*AB30*R30 -> 0 | AD30: =+AC30-X30 -> 0 | AE30: =IFERROR(AD30/AC30,0) -> 0
C31: Day 6 | D31: Hotel | E31: 02.07.2026 | F31: 03.07.2026 | J31: Reykjavik: Check in to your accommodation for a 1 night stay - Borg by Keahotels - 2 x Deluxe room - breakfast included | P31: https://app.hotelbeds.com/factsheet/stay/90467?check_in=02-07-2026&check_out=03-07-2026&occupancy=2~0_2~0&packaging=true | Q31: 1091 | R31: 1 | S31: =+Q31*R31 -> 1091 | T31: 0 | U31: =S31*(1-T31) -> 1091 | V31: EUR | W31: =IFERROR(VLOOKUP(V31,Curr!$B$2:$C$13,2,FALSE),0) -> 10.8 | X31: =U31*W31 -> 11782.8 | Y31: =Q31/0.8 -> 1363.75 | Z31: =+Y31*R31 -> 1363.75 | AA31: EUR | AB31: =IFERROR(VLOOKUP(AA31,Curr!$B$2:$C$13,2,FALSE),0) -> 10.8 | AC31: =+Y31*AB31*R31 -> 14728.5 | AD31: =+AC31-X31 -> 2945.7 | AE31: =IFERROR(AD31/AC31,0) -> 0.2
C32: Day 6 | D32: Leisure | E32: 02.07.2026 | J32: Reykjavik: Spend time at leisure | Q32: 0 | R32: 0 | S32: =+Q32*R32 -> 0 | T32: 0 | U32: =S32*(1-T32) -> 0 | V32: EUR | W32: =IFERROR(VLOOKUP(V32,Curr!$B$2:$C$13,2,FALSE),0) -> 10.8 | X32: =U32*W32 -> 0 | Y32: =Q32 -> 0 | Z32: =+Y32*R32 -> 0 | AA32: EUR | AB32: =IFERROR(VLOOKUP(AA32,Curr!$B$2:$C$13,2,FALSE),0) -> 10.8 | AC32: =+Y32*AB32*R32 -> 0 | AD32: =+AC32-X32 -> 0 | AE32: =IFERROR(AD32/AC32,0) -> 0
C33: Day 6 | D33: Activity | E33: 02.07.2026 | J33: Reykjavik: Sky Lagoon Sér Pass with Transfer - Time: 5:00 pm - 7:30 pm - Meeting point: Hotel Pick up - Includes: Bus fare, Sky Lagoon Sér Admission, Complete Seven-step Ritual, Private Changing Facilities, Towel | P33: https://booknordics.com/iceland/western-iceland/reykjavik/sky-lagoon-sky-pass-with-transfer | Q33: 167 | R33: 4 | S33: =+Q33*R33 -> 668 | T33: 0.2 | U33: =S33*(1-T33) -> 534.4 | V33: EUR | W33: =IFERROR(VLOOKUP(V33,Curr!$B$2:$C$13,2,FALSE),0) -> 10.8 | X33: =U33*W33 -> 5771.52 | Y33: =Q33 -> 167 | Z33: =+Y33*R33 -> 668 | AA33: EUR | AB33: =IFERROR(VLOOKUP(AA33,Curr!$B$2:$C$13,2,FALSE),0) -> 10.8 | AC33: =+Y33*AB33*R33 -> 7214.4 | AD33: =+AC33-X33 -> 1442.88 | AE33: =IFERROR(AD33/AC33,0) -> 0.2
S34: =+Q34*R34 -> 0 | T34: 0 | U34: =S34*(1-T34) -> 0 | V34: EUR | W34: =IFERROR(VLOOKUP(V34,Curr!$B$2:$C$13,2,FALSE),0) -> 10.8 | X34: =U34*W34 -> 0 | Y34: =Q34 -> 0 | Z34: =+Y34*R34 -> 0 | AA34: EUR | AB34: =IFERROR(VLOOKUP(AA34,Curr!$B$2:$C$13,2,FALSE),0) -> 10.8 | AC34: =+Y34*AB34*R34 -> 0 | AD34: =+AC34-X34 -> 0 | AE34: =IFERROR(AD34/AC34,0) -> 0
C35: Day 7 | D35: Drive | E35: 03.07.2026 | J35: Reykjavik: Drive to Keflavik Airport | Q35: 0 | R35: 0 | S35: =+Q35*R35 -> 0 | T35: 0 | U35: =S35*(1-T35) -> 0 | V35: EUR | W35: =IFERROR(VLOOKUP(V35,Curr!$B$2:$C$13,2,FALSE),0) -> 10.8 | X35: =U35*W35 -> 0 | Y35: =Q35 -> 0 | Z35: =+Y35*R35 -> 0 | AA35: EUR | AB35: =IFERROR(VLOOKUP(AA35,Curr!$B$2:$C$13,2,FALSE),0) -> 10.8 | AC35: =+Y35*AB35*R35 -> 0 | AD35: =+AC35-X35 -> 0 | AE35: =IFERROR(AD35/AC35,0) -> 0
C36: Day 7 | D36: Car | E36: 03.07.2026 | J36: Keflavik: Deliver your rental car at the airport car rental office | Q36: 0 | R36: 0 | S36: =+Q36*R36 -> 0 | T36: 0 | U36: =S36*(1-T36) -> 0 | V36: EUR | W36: =IFERROR(VLOOKUP(V36,Curr!$B$2:$C$13,2,FALSE),0) -> 10.8 | X36: =U36*W36 -> 0 | Y36: =Q36 -> 0 | Z36: =+Y36*R36 -> 0 | AA36: EUR | AB36: =IFERROR(VLOOKUP(AA36,Curr!$B$2:$C$13,2,FALSE),0) -> 10.8 | AC36: =+Y36*AB36*R36 -> 0 | AD36: =+AC36-X36 -> 0 | AE36: =IFERROR(AD36/AC36,0) -> 0
C37: Day 7 | D37: Flight | E37: 03.07.2026 | J37: Keflavik: Flight to Oslo - Time: 09:10 am - 1:50 pm - Luggage included: 1 x 23 kg check in and 1 x 8 kg carry on per person | P37: https://www.sas.no/book/flights/?search=OW_KEF-OSL-20260703_a4c0i0y0&view=upsell&bookingFlow=revenue&out_flight_number=SK4788&skyscanner_redirectid=RhZvBkUmTrSXl9DScsN5CA&utm_source=skyscanner&utm_medium=metasearch&utm_campaign=skyscanner_metasearch&sortBy=rec&out_class=ECONOMY&out_sub_class=FLEX | Q37: 2778 | R37: 4 | S37: =+Q37*R37 -> 11112 | T37: 0 | U37: =S37*(1-T37) -> 11112 | V37: NOK | W37: =IFERROR(VLOOKUP(V37,Curr!$B$2:$C$13,2,FALSE),0) -> 1 | X37: =U37*W37 -> 11112 | Y37: =Q37/11/0.8 -> 315.68182 | Z37: =+Y37*R37 -> 1262.7273 | AA37: EUR | AB37: =IFERROR(VLOOKUP(AA37,Curr!$B$2:$C$13,2,FALSE),0) -> 10.8 | AC37: =+Y37*AB37*R37 -> 13637.455 | AD37: =+AC37-X37 -> 2525.4545 | AE37: =IFERROR(AD37/AC37,0) -> 0.18518519
C38: Day 7 | D38: Transfer | E38: 03.07.2026 | J38: Oslo: Private transfer to your accommodation | Q38: 1900 | R38: 1 | S38: =+Q38*R38 -> 1900 | T38: 0 | U38: =S38*(1-T38) -> 1900 | V38: NOK | W38: =IFERROR(VLOOKUP(V38,Curr!$B$2:$C$13,2,FALSE),0) -> 1 | X38: =U38*W38 -> 1900 | Y38: =Q38/11/0.8 -> 215.90909 | Z38: =+Y38*R38 -> 215.90909 | AA38: EUR | AB38: =IFERROR(VLOOKUP(AA38,Curr!$B$2:$C$13,2,FALSE),0) -> 10.8 | AC38: =+Y38*AB38*R38 -> 2331.8182 | AD38: =+AC38-X38 -> 431.81818 | AE38: =IFERROR(AD38/AC38,0) -> 0.18518519
C39: Day 7 | D39: Hotel | E39: 03.07.2026 | F39: 05.07.2026 | J39: Oslo: Check in to your accommodation for a 2 night stay - Grand Hotel Oslo by Scandic - 2 x Superior king - Breakfast included | P39: https://app.hotelbeds.com/factsheet/stay/616601?check_in=03-07-2026&check_out=05-07-2026&occupancy=2~0_2~0&packaging=true | Q39: 2058 | R39: 1 | S39: =+Q39*R39 -> 2058 | T39: 0 | U39: =S39*(1-T39) -> 2058 | V39: EUR | W39: =IFERROR(VLOOKUP(V39,Curr!$B$2:$C$13,2,FALSE),0) -> 10.8 | X39: =U39*W39 -> 22226.4 | Y39: =Q39/0.85 -> 2421.1765 | Z39: =+Y39*R39 -> 2421.1765 | AA39: EUR | AB39: =IFERROR(VLOOKUP(AA39,Curr!$B$2:$C$13,2,FALSE),0) -> 10.8 | AC39: =+Y39*AB39*R39 -> 26148.706 | AD39: =+AC39-X39 -> 3922.3059 | AE39: =IFERROR(AD39/AC39,0) -> 0.15
C40: Day 7 | D40: Leisure | E40: 03.07.2026 | J40: Oslo: Spend time at leisure | Q40: 0 | R40: 0 | S40: =+Q40*R40 -> 0 | T40: 0 | U40: =S40*(1-T40) -> 0 | V40: EUR | W40: =IFERROR(VLOOKUP(V40,Curr!$B$2:$C$13,2,FALSE),0) -> 10.8 | X40: =U40*W40 -> 0 | Y40: =Q40 -> 0 | Z40: =+Y40*R40 -> 0 | AA40: EUR | AB40: =IFERROR(VLOOKUP(AA40,Curr!$B$2:$C$13,2,FALSE),0) -> 10.8 | AC40: =+Y40*AB40*R40 -> 0 | AD40: =+AC40-X40 -> 0 | AE40: =IFERROR(AD40/AC40,0) -> 0
S41: =+Q41*R41 -> 0 | T41: 0 | U41: =S41*(1-T41) -> 0 | V41: EUR | W41: =IFERROR(VLOOKUP(V41,Curr!$B$2:$C$13,2,FALSE),0) -> 10.8 | X41: =U41*W41 -> 0 | Y41: =Q41 -> 0 | Z41: =+Y41*R41 -> 0 | AA41: EUR | AB41: =IFERROR(VLOOKUP(AA41,Curr!$B$2:$C$13,2,FALSE),0) -> 10.8 | AC41: =+Y41*AB41*R41 -> 0 | AD41: =+AC41-X41 -> 0 | AE41: =IFERROR(AD41/AC41,0) -> 0
C42: Day 8 | D42: Activity | E42: 04.07.2026 | J42: Oslo: Fjord Sightseeing Cruise by 100% Electric Boat - Time: 1:30 pm - 3:30 pm - Meeting point: Rådhusbrygge 4, Platform E - Includes: Oslo Fjord archipelago cruise by electric boat, Cafeteria with snacks and drinks for purchase, "Voice of Norway" Audio guide for download, Stop at the Bygdøy peninsula near to museums | P42: https://booknordics.com/norway/eastern-norway/oslo/oslofjord-sightseeing-cruise | Q42: 40 | R42: 4 | S42: =+Q42*R42 -> 160 | T42: 0.2 | U42: =S42*(1-T42) -> 128 | V42: EUR | W42: =IFERROR(VLOOKUP(V42,Curr!$B$2:$C$13,2,FALSE),0) -> 10.8 | X42: =U42*W42 -> 1382.4 | Y42: =Q42 -> 40 | Z42: =+Y42*R42 -> 160 | AA42: EUR | AB42: =IFERROR(VLOOKUP(AA42,Curr!$B$2:$C$13,2,FALSE),0) -> 10.8 | AC42: =+Y42*AB42*R42 -> 1728 | AD42: =+AC42-X42 -> 345.6 | AE42: =IFERROR(AD42/AC42,0) -> 0.2
C43: Day 8 | D43: Leisure | E43: 04.07.2026 | J43: Oslo: Spend time at leisure | Q43: 0 | R43: 0 | S43: =+Q43*R43 -> 0 | T43: 0 | U43: =S43*(1-T43) -> 0 | V43: EUR | W43: =IFERROR(VLOOKUP(V43,Curr!$B$2:$C$13,2,FALSE),0) -> 10.8 | X43: =U43*W43 -> 0 | Y43: =Q43 -> 0 | Z43: =+Y43*R43 -> 0 | AA43: EUR | AB43: =IFERROR(VLOOKUP(AA43,Curr!$B$2:$C$13,2,FALSE),0) -> 10.8 | AC43: =+Y43*AB43*R43 -> 0 | AD43: =+AC43-X43 -> 0 | AE43: =IFERROR(AD43/AC43,0) -> 0
S44: =+Q44*R44 -> 0 | T44: 0 | U44: =S44*(1-T44) -> 0 | V44: EUR | W44: =IFERROR(VLOOKUP(V44,Curr!$B$2:$C$13,2,FALSE),0) -> 10.8 | X44: =U44*W44 -> 0 | Y44: =Q44 -> 0 | Z44: =+Y44*R44 -> 0 | AA44: EUR | AB44: =IFERROR(VLOOKUP(AA44,Curr!$B$2:$C$13,2,FALSE),0) -> 10.8 | AC44: =+Y44*AB44*R44 -> 0 | AD44: =+AC44-X44 -> 0 | AE44: =IFERROR(AD44/AC44,0) -> 0
C45: Day 9 | D45: Transfer | E45: 05.07.2026 | J45: Oslo: Self transfer to Oslo Central Station | Q45: 0 | R45: 0 | S45: =+Q45*R45 -> 0 | T45: 0 | U45: =S45*(1-T45) -> 0 | V45: EUR | W45: =IFERROR(VLOOKUP(V45,Curr!$B$2:$C$13,2,FALSE),0) -> 10.8 | X45: =U45*W45 -> 0 | Y45: =Q45 -> 0 | Z45: =+Y45*R45 -> 0 | AA45: EUR | AB45: =IFERROR(VLOOKUP(AA45,Curr!$B$2:$C$13,2,FALSE),0) -> 10.8 | AC45: =+Y45*AB45*R45 -> 0 | AD45: =+AC45-X45 -> 0 | AE45: =IFERROR(AD45/AC45,0) -> 0
C46: Day 9 | D46: Activity | E46: 05.07.2026 | J46: Oslo: Norway in a Nutshell tour to Bergen, including Luggage transfer for 4 x luggage - Time: 08:23 am - 11:18 pm - Includes: Train tickets Oslo to Bergen, Train tickets Flåm to Myrdal, Fjord Cruisee Flåm to Gudvangen - Tour summary: 08:23 am - 1:04 pm: Train from Oslo to Myrdal. 1:24 pm - 2:22 pm: Flåmsbana to Flåm. 5:30 pm - 7:20 pm: Fjord Cruise to Gudangen. 7:30 pm - 8:30 pm: Premium Coach to Voss. 10:06 pm - 11:18 pm: Train to Bergen . | P46: https://www.fjordtours.com/en/norway/booking/tour/norway-in-a-nutshell/b1205fbc-1045-45fb-a099-1d3be8f4aa58/5c582628-ae09-482f-93bf-e41e16e39ac0 | Q46: =3873+450 -> 4323 | R46: 4 | S46: =+Q46*R46 -> 17292 | T46: 0.12 | U46: =S46*(1-T46) -> 15216.96 | V46: NOK | W46: =IFERROR(VLOOKUP(V46,Curr!$B$2:$C$13,2,FALSE),0) -> 1 | X46: =U46*W46 -> 15216.96 | Y46: =Q46/11/0.9 -> 436.66667 | Z46: =+Y46*R46 -> 1746.6667 | AA46: EUR | AB46: =IFERROR(VLOOKUP(AA46,Curr!$B$2:$C$13,2,FALSE),0) -> 10.8 | AC46: =+Y46*AB46*R46 -> 18864 | AD46: =+AC46-X46 -> 3647.04 | AE46: =IFERROR(AD46/AC46,0) -> 0.19333333
C47: Day 9 | D47: Transfer | E47: 05.07.2026 | J47: Bergen: Private transfer to your accommodation | P47: https://www.btservice.no/private-cruiseport-transfer | Q47: 1490 | R47: 1 | S47: =+Q47*R47 -> 1490 | T47: 0.15 | U47: =S47*(1-T47) -> 1266.5 | V47: NOK | W47: =IFERROR(VLOOKUP(V47,Curr!$B$2:$C$13,2,FALSE),0) -> 1 | X47: =U47*W47 -> 1266.5 | Y47: =Q47/11/0.9 -> 150.50505 | Z47: =+Y47*R47 -> 150.50505 | AA47: EUR | AB47: =IFERROR(VLOOKUP(AA47,Curr!$B$2:$C$13,2,FALSE),0) -> 10.8 | AC47: =+Y47*AB47*R47 -> 1625.4545 | AD47: =+AC47-X47 -> 358.95455 | AE47: =IFERROR(AD47/AC47,0) -> 0.22083333
C48: Day 9 | D48: Hotel | E48: 05.07.2026 | F48: 07.07.2026 | J48: Bergen: Check in to your accommodation for a 2 night stay - Bergen Bors - 2 x Suite loft - breakfast included | P48: https://app.hotelbeds.com/factsheet/stay/647045?check_in=05-07-2026&check_out=07-07-2026&occupancy=2~0_2~0&packaging=true | Q48: 2620 | R48: 1 | S48: =+Q48*R48 -> 2620 | T48: 0 | U48: =S48*(1-T48) -> 2620 | V48: EUR | W48: =IFERROR(VLOOKUP(V48,Curr!$B$2:$C$13,2,FALSE),0) -> 10.8 | X48: =U48*W48 -> 28296 | Y48: =Q48/0.85 -> 3082.3529 | Z48: =+Y48*R48 -> 3082.3529 | AA48: EUR | AB48: =IFERROR(VLOOKUP(AA48,Curr!$B$2:$C$13,2,FALSE),0) -> 10.8 | AC48: =+Y48*AB48*R48 -> 33289.412 | AD48: =+AC48-X48 -> 4993.4118 | AE48: =IFERROR(AD48/AC48,0) -> 0.15
C49: Day 9 | D49: Leisure | E49: 05.07.2026 | J49: Bergen: Spend time at leisure | Q49: 0 | R49: 0 | S49: =+Q49*R49 -> 0 | T49: 0 | U49: =S49*(1-T49) -> 0 | V49: EUR | W49: =IFERROR(VLOOKUP(V49,Curr!$B$2:$C$13,2,FALSE),0) -> 10.8 | X49: =U49*W49 -> 0 | Y49: =Q49 -> 0 | Z49: =+Y49*R49 -> 0 | AA49: EUR | AB49: =IFERROR(VLOOKUP(AA49,Curr!$B$2:$C$13,2,FALSE),0) -> 10.8 | AC49: =+Y49*AB49*R49 -> 0 | AD49: =+AC49-X49 -> 0 | AE49: =IFERROR(AD49/AC49,0) -> 0
S50: =+Q50*R50 -> 0 | T50: 0 | U50: =S50*(1-T50) -> 0 | V50: EUR | W50: =IFERROR(VLOOKUP(V50,Curr!$B$2:$C$13,2,FALSE),0) -> 10.8 | X50: =U50*W50 -> 0 | Y50: =Q50 -> 0 | Z50: =+Y50*R50 -> 0 | AA50: EUR | AB50: =IFERROR(VLOOKUP(AA50,Curr!$B$2:$C$13,2,FALSE),0) -> 10.8 | AC50: =+Y50*AB50*R50 -> 0 | AD50: =+AC50-X50 -> 0 | AE50: =IFERROR(AD50/AC50,0) -> 0
C51: Day 10 | D51: Activity | E51: 06.07.2026 | J51: Bergen: Fløybanen Funicular Tickets - Time: Flexible - Meeting point: Fløybanen | P51: https://www.floyen.no/floibanen/kjop-billetter | Q51: 200 | R51: 4 | S51: =+Q51*R51 -> 800 | T51: 0 | U51: =S51*(1-T51) -> 800 | V51: NOK | W51: =IFERROR(VLOOKUP(V51,Curr!$B$2:$C$13,2,FALSE),0) -> 1 | X51: =U51*W51 -> 800 | Y51: =Q51/11/0.6 -> 30.30303 | Z51: =+Y51*R51 -> 121.21212 | AA51: EUR | AB51: =IFERROR(VLOOKUP(AA51,Curr!$B$2:$C$13,2,FALSE),0) -> 10.8 | AC51: =+Y51*AB51*R51 -> 1309.0909 | AD51: =+AC51-X51 -> 509.09091 | AE51: =IFERROR(AD51/AC51,0) -> 0.38888889
C52: Day 10 | D52: Leisure | E52: 06.07.2026 | J52: Bergen: Spend time at leisure | Q52: 0 | R52: 0 | S52: =+Q52*R52 -> 0 | T52: 0 | U52: =S52*(1-T52) -> 0 | V52: EUR | W52: =IFERROR(VLOOKUP(V52,Curr!$B$2:$C$13,2,FALSE),0) -> 10.8 | X52: =U52*W52 -> 0 | Y52: =Q52 -> 0 | Z52: =+Y52*R52 -> 0 | AA52: EUR | AB52: =IFERROR(VLOOKUP(AA52,Curr!$B$2:$C$13,2,FALSE),0) -> 10.8 | AC52: =+Y52*AB52*R52 -> 0 | AD52: =+AC52-X52 -> 0 | AE52: =IFERROR(AD52/AC52,0) -> 0
C53: Day 10 | D53: Activity | E53: 06.07.2026 | J53: Bergen: Mostraumen Majestic Fjord & Waterfall Cruise - Time: 5:00 pm - 7:00 pm - Meeting point: Börshopen Pier, Strandkaien 13 - Round-trip criose Bergen to Mostraumen to Bergen | P53: https://booknordics.com/norway/western-fjord-norway/bergen-and-hardanger/mostraumen-fjord-waterfall-cruise | Q53: 75 | R53: 4 | S53: =+Q53*R53 -> 300 | T53: 0.2 | U53: =S53*(1-T53) -> 240 | V53: EUR | W53: =IFERROR(VLOOKUP(V53,Curr!$B$2:$C$13,2,FALSE),0) -> 10.8 | X53: =U53*W53 -> 2592 | Y53: =Q53/0.9 -> 83.333333 | Z53: =+Y53*R53 -> 333.33333 | AA53: EUR | AB53: =IFERROR(VLOOKUP(AA53,Curr!$B$2:$C$13,2,FALSE),0) -> 10.8 | AC53: =+Y53*AB53*R53 -> 3600 | AD53: =+AC53-X53 -> 1008 | AE53: =IFERROR(AD53/AC53,0) -> 0.28
S54: =+Q54*R54 -> 0 | T54: 0 | U54: =S54*(1-T54) -> 0 | V54: EUR | W54: =IFERROR(VLOOKUP(V54,Curr!$B$2:$C$13,2,FALSE),0) -> 10.8 | X54: =U54*W54 -> 0 | Y54: =Q54 -> 0 | Z54: =+Y54*R54 -> 0 | AA54: EUR | AB54: =IFERROR(VLOOKUP(AA54,Curr!$B$2:$C$13,2,FALSE),0) -> 10.8 | AC54: =+Y54*AB54*R54 -> 0 | AD54: =+AC54-X54 -> 0 | AE54: =IFERROR(AD54/AC54,0) -> 0
C55: Day 11 | D55: Transfer | E55: 07.07.2026 | J55: Bergen: Private transfer to Bergen Airport | P55: https://www.btservice.no/private-cruiseport-transfer | Q55: 2290 | R55: 1 | S55: =+Q55*R55 -> 2290 | T55: 0.15 | U55: =S55*(1-T55) -> 1946.5 | V55: NOK | W55: =IFERROR(VLOOKUP(V55,Curr!$B$2:$C$13,2,FALSE),0) -> 1 | X55: =U55*W55 -> 1946.5 | Y55: =Q55/11/0.9 -> 231.31313 | Z55: =+Y55*R55 -> 231.31313 | AA55: EUR | AB55: =IFERROR(VLOOKUP(AA55,Curr!$B$2:$C$13,2,FALSE),0) -> 10.8 | AC55: =+Y55*AB55*R55 -> 2498.1818 | AD55: =+AC55-X55 -> 551.68182 | AE55: =IFERROR(AD55/AC55,0) -> 0.22083333
C56: Day 11 | D56: Flight | E56: 07.07.2026 | J56: Bergen: Flight to Ålesund - Time: 11:00 am - 11:50 am - Luggage included: 1 x 23 kg check in and 1 x 8 kg carry on per person | P56: https://www.wideroe.no/booking/booking#/select-flight | Q56: 1639 | R56: 4 | S56: =+Q56*R56 -> 6556 | T56: 0 | U56: =S56*(1-T56) -> 6556 | V56: NOK | W56: =IFERROR(VLOOKUP(V56,Curr!$B$2:$C$13,2,FALSE),0) -> 1 | X56: =U56*W56 -> 6556 | Y56: =Q56/11/0.8 -> 186.25 | Z56: =+Y56*R56 -> 745 | AA56: EUR | AB56: =IFERROR(VLOOKUP(AA56,Curr!$B$2:$C$13,2,FALSE),0) -> 10.8 | AC56: =+Y56*AB56*R56 -> 8046 | AD56: =+AC56-X56 -> 1490 | AE56: =IFERROR(AD56/AC56,0) -> 0.18518519
C57: Day 11 | D57: Car | E57: 07.07.2026 | F57: 10.07.2026 | J57: Ålesund: Pick up your rental car at the Ålesund Airport Car rental office - Car: SUZUKI S-CROSS - Office location: Flyplassvegen 27 - Includes: Collision damage waiver, Fuel information, Unlimited mileage, Theft protection, Vat, Personal accident insurance, Cancellation fee - Excludes: 1 way fee, road tax | P57: https://app.hotelbeds.com/carhire/search?seat=5&results=20&sortBy=LOWEST_PRICE_FIRST&field=PRICE&direction=ASCENDING&page=1&destinationTab=Alesund%20Airport%20(AES)&pickupDate=07-07-2026&pickupTime=13:00&dropoffDate=10-07-2026&dropoffTime=13:00&sameOfficeCheckbox=true&officePickupControl=56&officeDropoffControl=56&typeDepartureCode=airport&_timestamp=1776932694225&typeArrivalCode=airport&departureTab= | Q57: 334 | R57: 1 | S57: =+Q57*R57 -> 334 | T57: 0 | U57: =S57*(1-T57) -> 334 | V57: EUR | W57: =IFERROR(VLOOKUP(V57,Curr!$B$2:$C$13,2,FALSE),0) -> 10.8 | X57: =U57*W57 -> 3607.2 | Y57: =Q57/0.8 -> 417.5 | Z57: =+Y57*R57 -> 417.5 | AA57: EUR | AB57: =IFERROR(VLOOKUP(AA57,Curr!$B$2:$C$13,2,FALSE),0) -> 10.8 | AC57: =+Y57*AB57*R57 -> 4509 | AD57: =+AC57-X57 -> 901.8 | AE57: =IFERROR(AD57/AC57,0) -> 0.2
C58: Day 11 | D58: Drive | E58: 07.07.2026 | J58: Ålesund: Drive to your accommodation | Q58: 0 | R58: 0 | S58: =+Q58*R58 -> 0 | T58: 0 | U58: =S58*(1-T58) -> 0 | V58: EUR | W58: =IFERROR(VLOOKUP(V58,Curr!$B$2:$C$13,2,FALSE),0) -> 10.8 | X58: =U58*W58 -> 0 | Y58: =Q58 -> 0 | Z58: =+Y58*R58 -> 0 | AA58: EUR | AB58: =IFERROR(VLOOKUP(AA58,Curr!$B$2:$C$13,2,FALSE),0) -> 10.8 | AC58: =+Y58*AB58*R58 -> 0 | AD58: =+AC58-X58 -> 0 | AE58: =IFERROR(AD58/AC58,0) -> 0
C59: Day 11 | D59: Hotel | E59: 07.07.2026 | F59: 10.07.2026 | J59: Ålesund: Check in to your accommodation for a 3 night stay - Hotel Brosundet - 2 x Junior suite - breakfast included | P59: https://app.hotelbeds.com/factsheet/stay/70251?check_in=07-07-2026&check_out=10-07-2026&occupancy=2~0_2~0&packaging=true | Q59: 3072 | R59: 1 | S59: =+Q59*R59 -> 3072 | T59: 0 | U59: =S59*(1-T59) -> 3072 | V59: EUR | W59: =IFERROR(VLOOKUP(V59,Curr!$B$2:$C$13,2,FALSE),0) -> 10.8 | X59: =U59*W59 -> 33177.6 | Y59: =Q59/0.8 -> 3840 | Z59: =+Y59*R59 -> 3840 | AA59: EUR | AB59: =IFERROR(VLOOKUP(AA59,Curr!$B$2:$C$13,2,FALSE),0) -> 10.8 | AC59: =+Y59*AB59*R59 -> 41472 | AD59: =+AC59-X59 -> 8294.4 | AE59: =IFERROR(AD59/AC59,0) -> 0.2
C60: Day 11 | D60: Leisure | E60: 07.07.2026 | J60: Ålesund: Spend time at leisure | Q60: 0 | R60: 0 | S60: =+Q60*R60 -> 0 | T60: 0 | U60: =S60*(1-T60) -> 0 | V60: EUR | W60: =IFERROR(VLOOKUP(V60,Curr!$B$2:$C$13,2,FALSE),0) -> 10.8 | X60: =U60*W60 -> 0 | Y60: =Q60 -> 0 | Z60: =+Y60*R60 -> 0 | AA60: EUR | AB60: =IFERROR(VLOOKUP(AA60,Curr!$B$2:$C$13,2,FALSE),0) -> 10.8 | AC60: =+Y60*AB60*R60 -> 0 | AD60: =+AC60-X60 -> 0 | AE60: =IFERROR(AD60/AC60,0) -> 0
S61: =+Q61*R61 -> 0 | T61: 0 | U61: =S61*(1-T61) -> 0 | V61: EUR | W61: =IFERROR(VLOOKUP(V61,Curr!$B$2:$C$13,2,FALSE),0) -> 10.8 | X61: =U61*W61 -> 0 | Y61: =Q61 -> 0 | Z61: =+Y61*R61 -> 0 | AA61: EUR | AB61: =IFERROR(VLOOKUP(AA61,Curr!$B$2:$C$13,2,FALSE),0) -> 10.8 | AC61: =+Y61*AB61*R61 -> 0 | AD61: =+AC61-X61 -> 0 | AE61: =IFERROR(AD61/AC61,0) -> 0
C62: Day 12 | D62: Drive | E62: 08.07.2026 | J62: Ålesund: Geiranger Road Trip - Drive to Hellesylt, and take the Geiranger Fjord Ferry to Geiranger at 11:00 am. Spend some time at leisuree in Geiranger, before driving back to Ålesund via Sjøholt | P62: https://www.fjordtours.com/no/norge/transport/ferge/geiranger-hellesylt | Q62: 1680 | R62: 1 | S62: =+Q62*R62 -> 1680 | T62: 0.12 | U62: =S62*(1-T62) -> 1478.4 | V62: NOK | W62: =IFERROR(VLOOKUP(V62,Curr!$B$2:$C$13,2,FALSE),0) -> 1 | X62: =U62*W62 -> 1478.4 | Y62: =Q62/11/0.8 -> 190.90909 | Z62: =+Y62*R62 -> 190.90909 | AA62: EUR | AB62: =IFERROR(VLOOKUP(AA62,Curr!$B$2:$C$13,2,FALSE),0) -> 10.8 | AC62: =+Y62*AB62*R62 -> 2061.8182 | AD62: =+AC62-X62 -> 583.41818 | AE62: =IFERROR(AD62/AC62,0) -> 0.28296296
C63: Day 12 | D63: Leisure | E63: 08.07.2026 | J63: Ålesund: Spend time at leisure | Q63: 0 | R63: 0 | S63: =+Q63*R63 -> 0 | T63: 0 | U63: =S63*(1-T63) -> 0 | V63: EUR | W63: =IFERROR(VLOOKUP(V63,Curr!$B$2:$C$13,2,FALSE),0) -> 10.8 | X63: =U63*W63 -> 0 | Y63: =Q63 -> 0 | Z63: =+Y63*R63 -> 0 | AA63: EUR | AB63: =IFERROR(VLOOKUP(AA63,Curr!$B$2:$C$13,2,FALSE),0) -> 10.8 | AC63: =+Y63*AB63*R63 -> 0 | AD63: =+AC63-X63 -> 0 | AE63: =IFERROR(AD63/AC63,0) -> 0
S64: =+Q64*R64 -> 0 | T64: 0 | U64: =S64*(1-T64) -> 0 | V64: EUR | W64: =IFERROR(VLOOKUP(V64,Curr!$B$2:$C$13,2,FALSE),0) -> 10.8 | X64: =U64*W64 -> 0 | Y64: =Q64 -> 0 | Z64: =+Y64*R64 -> 0 | AA64: EUR | AB64: =IFERROR(VLOOKUP(AA64,Curr!$B$2:$C$13,2,FALSE),0) -> 10.8 | AC64: =+Y64*AB64*R64 -> 0 | AD64: =+AC64-X64 -> 0 | AE64: =IFERROR(AD64/AC64,0) -> 0
C65: Day 13 | D65: Drive | E65: 09.07.2026 | J65: Ålesund: Atlantic Road Road Trip - Drive from your accommodation to the Atlantic Road. Head up to Kristiansund and spend some time at leisure. Drive to Molde, and head to Molde Panorama. Drive back to your accommodation in Ålesund | Q65: 0 | R65: 0 | S65: =+Q65*R65 -> 0 | T65: 0 | U65: =S65*(1-T65) -> 0 | V65: EUR | W65: =IFERROR(VLOOKUP(V65,Curr!$B$2:$C$13,2,FALSE),0) -> 10.8 | X65: =U65*W65 -> 0 | Y65: =Q65 -> 0 | Z65: =+Y65*R65 -> 0 | AA65: EUR | AB65: =IFERROR(VLOOKUP(AA65,Curr!$B$2:$C$13,2,FALSE),0) -> 10.8 | AC65: =+Y65*AB65*R65 -> 0 | AD65: =+AC65-X65 -> 0 | AE65: =IFERROR(AD65/AC65,0) -> 0
C66: Day 13 | D66: Leisure | E66: 09.07.2026 | J66: Ålesund: Spend time at leisure | Q66: 0 | R66: 0 | S66: =+Q66*R66 -> 0 | T66: 0 | U66: =S66*(1-T66) -> 0 | V66: EUR | W66: =IFERROR(VLOOKUP(V66,Curr!$B$2:$C$13,2,FALSE),0) -> 10.8 | X66: =U66*W66 -> 0 | Y66: =Q66 -> 0 | Z66: =+Y66*R66 -> 0 | AA66: EUR | AB66: =IFERROR(VLOOKUP(AA66,Curr!$B$2:$C$13,2,FALSE),0) -> 10.8 | AC66: =+Y66*AB66*R66 -> 0 | AD66: =+AC66-X66 -> 0 | AE66: =IFERROR(AD66/AC66,0) -> 0
S67: =+Q67*R67 -> 0 | T67: 0 | U67: =S67*(1-T67) -> 0 | V67: EUR | W67: =IFERROR(VLOOKUP(V67,Curr!$B$2:$C$13,2,FALSE),0) -> 10.8 | X67: =U67*W67 -> 0 | Y67: =Q67 -> 0 | Z67: =+Y67*R67 -> 0 | AA67: EUR | AB67: =IFERROR(VLOOKUP(AA67,Curr!$B$2:$C$13,2,FALSE),0) -> 10.8 | AC67: =+Y67*AB67*R67 -> 0 | AD67: =+AC67-X67 -> 0 | AE67: =IFERROR(AD67/AC67,0) -> 0
C68: Day 14 | D68: Drive | E68: 10.07.2026 | J68: Ålesund: Drive to Ålesund Airport | Q68: 0 | R68: 0 | S68: =+Q68*R68 -> 0 | T68: 0 | U68: =S68*(1-T68) -> 0 | V68: EUR | W68: =IFERROR(VLOOKUP(V68,Curr!$B$2:$C$13,2,FALSE),0) -> 10.8 | X68: =U68*W68 -> 0 | Y68: =Q68 -> 0 | Z68: =+Y68*R68 -> 0 | AA68: EUR | AB68: =IFERROR(VLOOKUP(AA68,Curr!$B$2:$C$13,2,FALSE),0) -> 10.8 | AC68: =+Y68*AB68*R68 -> 0 | AD68: =+AC68-X68 -> 0 | AE68: =IFERROR(AD68/AC68,0) -> 0
C69: Day 14 | D69: Car | E69: 10.07.2026 | J69: Ålesund: Deliver your rental car at the Ålesund Airport Car rental office | Q69: 0 | R69: 0 | S69: =+Q69*R69 -> 0 | T69: 0 | U69: =S69*(1-T69) -> 0 | V69: EUR | W69: =IFERROR(VLOOKUP(V69,Curr!$B$2:$C$13,2,FALSE),0) -> 10.8 | X69: =U69*W69 -> 0 | Y69: =Q69 -> 0 | Z69: =+Y69*R69 -> 0 | AA69: EUR | AB69: =IFERROR(VLOOKUP(AA69,Curr!$B$2:$C$13,2,FALSE),0) -> 10.8 | AC69: =+Y69*AB69*R69 -> 0 | AD69: =+AC69-X69 -> 0 | AE69: =IFERROR(AD69/AC69,0) -> 0
C70: Day 14 | D70: Flight | E70: 10.07.2026 | J70: Ålesund: Flight to Oslo - Time: 4:15 pm - 5:10 pm - Luggage included: 1 x 23 kg check in and 1 x 8 kg carry on per person | P70: https://booking.norwegian.com/booking/flight/0 | Q70: 1900 | R70: 4 | S70: =+Q70*R70 -> 7600 | T70: 0 | U70: =S70*(1-T70) -> 7600 | V70: NOK | W70: =IFERROR(VLOOKUP(V70,Curr!$B$2:$C$13,2,FALSE),0) -> 1 | X70: =U70*W70 -> 7600 | Y70: =Q70/11/0.75 -> 230.30303 | Z70: =+Y70*R70 -> 921.21212 | AA70: EUR | AB70: =IFERROR(VLOOKUP(AA70,Curr!$B$2:$C$13,2,FALSE),0) -> 10.8 | AC70: =+Y70*AB70*R70 -> 9949.0909 | AD70: =+AC70-X70 -> 2349.0909 | AE70: =IFERROR(AD70/AC70,0) -> 0.23611111
C71: Day 14 | D71: Transfer | E71: 10.07.2026 | J71: Oslo: Self transfer to your accommodation | Q71: 0 | R71: 0 | S71: =+Q71*R71 -> 0 | T71: 0 | U71: =S71*(1-T71) -> 0 | V71: EUR | W71: =IFERROR(VLOOKUP(V71,Curr!$B$2:$C$13,2,FALSE),0) -> 10.8 | X71: =U71*W71 -> 0 | Y71: =Q71 -> 0 | Z71: =+Y71*R71 -> 0 | AA71: EUR | AB71: =IFERROR(VLOOKUP(AA71,Curr!$B$2:$C$13,2,FALSE),0) -> 10.8 | AC71: =+Y71*AB71*R71 -> 0 | AD71: =+AC71-X71 -> 0 | AE71: =IFERROR(AD71/AC71,0) -> 0
C72: Day 14 | D72: Hotel | E72: 10.07.2026 | F72: 11.07.2026 | J72: Oslo: Check in to your accommodation for a 1 night stay - Scandic Oslo Airport - 2 x Superior - breakfast included | P72: https://app.hotelbeds.com/factsheet/stay/107785?check_in=10-07-2026&check_out=11-07-2026&occupancy=2~0_2~0&packaging=true | Q72: 197 | R72: 1 | S72: =+Q72*R72 -> 197 | T72: 0 | U72: =S72*(1-T72) -> 197 | V72: EUR | W72: =IFERROR(VLOOKUP(V72,Curr!$B$2:$C$13,2,FALSE),0) -> 10.8 | X72: =U72*W72 -> 2127.6 | Y72: =Q72/0.75 -> 262.66667 | Z72: =+Y72*R72 -> 262.66667 | AA72: EUR | AB72: =IFERROR(VLOOKUP(AA72,Curr!$B$2:$C$13,2,FALSE),0) -> 10.8 | AC72: =+Y72*AB72*R72 -> 2836.8 | AD72: =+AC72-X72 -> 709.2 | AE72: =IFERROR(AD72/AC72,0) -> 0.25
C73: Day 14 | D73: Leisure | E73: 10.07.2026 | J73: Oslo: Spend time at leisure | Q73: 0 | R73: 0 | S73: =+Q73*R73 -> 0 | T73: 0 | U73: =S73*(1-T73) -> 0 | V73: EUR | W73: =IFERROR(VLOOKUP(V73,Curr!$B$2:$C$13,2,FALSE),0) -> 10.8 | X73: =U73*W73 -> 0 | Y73: =Q73 -> 0 | Z73: =+Y73*R73 -> 0 | AA73: EUR | AB73: =IFERROR(VLOOKUP(AA73,Curr!$B$2:$C$13,2,FALSE),0) -> 10.8 | AC73: =+Y73*AB73*R73 -> 0 | AD73: =+AC73-X73 -> 0 | AE73: =IFERROR(AD73/AC73,0) -> 0
S74: =+Q74*R74 -> 0 | T74: 0 | U74: =S74*(1-T74) -> 0 | V74: EUR | W74: =IFERROR(VLOOKUP(V74,Curr!$B$2:$C$13,2,FALSE),0) -> 10.8 | X74: =U74*W74 -> 0 | Y74: =Q74 -> 0 | Z74: =+Y74*R74 -> 0 | AA74: EUR | AB74: =IFERROR(VLOOKUP(AA74,Curr!$B$2:$C$13,2,FALSE),0) -> 10.8 | AC74: =+Y74*AB74*R74 -> 0 | AD74: =+AC74-X74 -> 0 | AE74: =IFERROR(AD74/AC74,0) -> 0
C75: Day 15 | D75: Transfer | E75: 11.07.2026 | J75: Oslo: Self transfer to Oslo Airport | Q75: 0 | R75: 0 | S75: =+Q75*R75 -> 0 | T75: 0 | U75: =S75*(1-T75) -> 0 | V75: EUR | W75: =IFERROR(VLOOKUP(V75,Curr!$B$2:$C$13,2,FALSE),0) -> 10.8 | X75: =U75*W75 -> 0 | Y75: =Q75 -> 0 | Z75: =+Y75*R75 -> 0 | AA75: EUR | AB75: =IFERROR(VLOOKUP(AA75,Curr!$B$2:$C$13,2,FALSE),0) -> 10.8 | AC75: =+Y75*AB75*R75 -> 0 | AD75: =+AC75-X75 -> 0 | AE75: =IFERROR(AD75/AC75,0) -> 0
C76: Day 15 | D76: Departure | E76: 11.07.2026 | J76: Oslo: Departure home | Q76: 0 | R76: 0 | S76: =+Q76*R76 -> 0 | T76: 0 | U76: =S76*(1-T76) -> 0 | V76: EUR | W76: =IFERROR(VLOOKUP(V76,Curr!$B$2:$C$13,2,FALSE),0) -> 10.8 | X76: =U76*W76 -> 0 | Y76: =Q76 -> 0 | Z76: =+Y76*R76 -> 0 | AA76: EUR | AB76: =IFERROR(VLOOKUP(AA76,Curr!$B$2:$C$13,2,FALSE),0) -> 10.8 | AC76: =+Y76*AB76*R76 -> 0 | AD76: =+AC76-X76 -> 0 | AE76: =IFERROR(AD76/AC76,0) -> 0
S77: =+Q77*R77 -> 0 | T77: 0 | U77: =S77*(1-T77) -> 0 | V77: EUR | W77: =IFERROR(VLOOKUP(V77,Curr!$B$2:$C$13,2,FALSE),0) -> 10.8 | X77: =U77*W77 -> 0 | Y77: =Q77 -> 0 | Z77: =+Y77*R77 -> 0 | AA77: EUR | AB77: =IFERROR(VLOOKUP(AA77,Curr!$B$2:$C$13,2,FALSE),0) -> 10.8 | AC77: =+Y77*AB77*R77 -> 0 | AD77: =+AC77-X77 -> 0 | AE77: =IFERROR(AD77/AC77,0) -> 0
S78: =+Q78*R78 -> 0 | T78: 0 | U78: =S78*(1-T78) -> 0 | V78: EUR | W78: =IFERROR(VLOOKUP(V78,Curr!$B$2:$C$13,2,FALSE),0) -> 10.8 | X78: =U78*W78 -> 0 | Y78: =Q78 -> 0 | Z78: =+Y78*R78 -> 0 | AA78: EUR | AB78: =IFERROR(VLOOKUP(AA78,Curr!$B$2:$C$13,2,FALSE),0) -> 10.8 | AC78: =+Y78*AB78*R78 -> 0 | AD78: =+AC78-X78 -> 0 | AE78: =IFERROR(AD78/AC78,0) -> 0
S79: =+Q79*R79 -> 0 | T79: 0 | U79: =S79*(1-T79) -> 0 | V79: EUR | W79: =IFERROR(VLOOKUP(V79,Curr!$B$2:$C$13,2,FALSE),0) -> 10.8 | X79: =U79*W79 -> 0 | Y79: =Q79 -> 0 | Z79: =+Y79*R79 -> 0 | AA79: EUR | AB79: =IFERROR(VLOOKUP(AA79,Curr!$B$2:$C$13,2,FALSE),0) -> 10.8 | AC79: =+Y79*AB79*R79 -> 0 | AD79: =+AC79-X79 -> 0 | AE79: =IFERROR(AD79/AC79,0) -> 0
S80: =+Q80*R80 -> 0 | T80: 0 | U80: =S80*(1-T80) -> 0 | V80: EUR | W80: =IFERROR(VLOOKUP(V80,Curr!$B$2:$C$13,2,FALSE),0) -> 10.8 | X80: =U80*W80 -> 0 | Y80: =Q80 -> 0 | Z80: =+Y80*R80 -> 0 | AA80: EUR | AB80: =IFERROR(VLOOKUP(AA80,Curr!$B$2:$C$13,2,FALSE),0) -> 10.8 | AC80: =+Y80*AB80*R80 -> 0 | AD80: =+AC80-X80 -> 0 | AE80: =IFERROR(AD80/AC80,0) -> 0
S81: =+Q81*R81 -> 0 | T81: 0 | U81: =S81*(1-T81) -> 0 | V81: EUR | W81: =IFERROR(VLOOKUP(V81,Curr!$B$2:$C$13,2,FALSE),0) -> 10.8 | X81: =U81*W81 -> 0 | Y81: =Q81 -> 0 | Z81: =+Y81*R81 -> 0 | AA81: EUR | AB81: =IFERROR(VLOOKUP(AA81,Curr!$B$2:$C$13,2,FALSE),0) -> 10.8 | AC81: =+Y81*AB81*R81 -> 0 | AD81: =+AC81-X81 -> 0 | AE81: =IFERROR(AD81/AC81,0) -> 0
S82: =+Q82*R82 -> 0 | T82: 0 | U82: =S82*(1-T82) -> 0 | V82: EUR | W82: =IFERROR(VLOOKUP(V82,Curr!$B$2:$C$13,2,FALSE),0) -> 10.8 | X82: =U82*W82 -> 0 | Y82: =Q82 -> 0 | Z82: =+Y82*R82 -> 0 | AA82: EUR | AB82: =IFERROR(VLOOKUP(AA82,Curr!$B$2:$C$13,2,FALSE),0) -> 10.8 | AC82: =+Y82*AB82*R82 -> 0 | AD82: =+AC82-X82 -> 0 | AE82: =IFERROR(AD82/AC82,0) -> 0
S83: =+Q83*R83 -> 0 | T83: 0 | U83: =S83*(1-T83) -> 0 | V83: EUR | W83: =IFERROR(VLOOKUP(V83,Curr!$B$2:$C$13,2,FALSE),0) -> 10.8 | X83: =U83*W83 -> 0 | Y83: =Q83 -> 0 | Z83: =+Y83*R83 -> 0 | AA83: EUR | AB83: =IFERROR(VLOOKUP(AA83,Curr!$B$2:$C$13,2,FALSE),0) -> 10.8 | AC83: =+Y83*AB83*R83 -> 0 | AD83: =+AC83-X83 -> 0 | AE83: =IFERROR(AD83/AC83,0) -> 0
B85: Totals | D85: x | E85: x | F85: x | G85: x | H85: x | I85: x | J85: x | K85: x | L85: x | M85: x | N85: x | O85: x | P85: x | Q85: x | R85: x | S85: x | T85: x | U85: x | V85: x | W85: x | X85: x | Y85: x | Z85: =SUM(Z7:Z83) -> 27581.91 | AC85: =SUM(AC7:AC83) -> 297884.63 | AD85: =SUM(AD7:AD83) -> 56940.993 | AE85: =IFERROR(AD85/AC85,0) -> 0.19115116 | AF85: =SUM(AF8:AF84) -> 0 | AG85: =SUM(AG8:AG84) -> 0 | AH85: =SUM(AH8:AH84) -> 0 | AI85: =SUM(AI8:AI84) -> 0 | AJ85: =SUM(AJ8:AJ84) -> 0
Y87: Quote | Z87: 27600
Y88: PP | Z88: =Z87/4 -> 6900
Y90: USD | Z90: 32280
Y91: PP | Z91: =Z90/4 -> 8070
Y93: NoHotel | Z93: =Z87-Y9-Y19-Y23-Y31-Y39-Y48-Y59-Y72 -> 9776.3775
Y94: USD | Z94: =Z93*1.17 -> 11438.362
Y95: PP | Z95: =Z94/4 -> 2859.5904
Y97: Rounded | Z97: 11600
Z98: =Z97/4 -> 2900

Sheet Kalk 5
B2: Dates: 27.06.2026
B3: Pax: 4
B4: Rooming: 2 x double
B6: ID | C6: Day | D6: Type | E6: From date | F6: To date | G6: From time | H6: To time | I6: Supplier | J6: Travel element | K6: Manual booking? | L6: Status | M6: Comments | N6: Non-refundable | O6: Refundable | P6: URL | Q6: Gross P per unit | R6: Units | S6: Gross P | T6: Supp Comm | U6: Net P | V6: Supp curr | W6: X-rate | X6: Net P NOK | Y6: Sales P per unit | Z6: Price | AA6: Sales curr | AB6: X-rate | AC6: Sales P NOK tot | AD6: GP NOK | AE6: GP % | AF6: VAT25 | AG6: VAT15 | AH6: VAT12 | AI6: VAT0-D | AJ6: VAT0-I
C7: Day 1 | D7: Arrival | E7: 27.06.2026 | J7: Keflavik: Welcome to Iceland | Q7: 0 | R7: 0 | S7: =+Q7*R7 -> 0 | T7: 0 | U7: =S7*(1-T7) -> 0 | V7: EUR | W7: =IFERROR(VLOOKUP(V7,Curr!$B$2:$C$13,2,FALSE),0) -> 10.8 | X7: =U7*W7 -> 0 | Y7: =Q7 -> 0 | Z7: =+Y7*R7 -> 0 | AA7: EUR | AB7: =IFERROR(VLOOKUP(AA7,Curr!$B$2:$C$13,2,FALSE),0) -> 10.8 | AC7: =+Y7*AB7*R7 -> 0 | AD7: =+AC7-X7 -> 0 | AE7: =IFERROR(AD7/AC7,0) -> 0
C8: Day 1 | D8: Tranfser | E8: 27.06.2026 | J8: Keflavik: Private transfer to your accommodation | Q8: 160 | R8: 1 | S8: =+Q8*R8 -> 160 | T8: 0.2 | U8: =S8*(1-T8) -> 128 | V8: EUR | W8: =IFERROR(VLOOKUP(V8,Curr!$B$2:$C$13,2,FALSE),0) -> 10.8 | X8: =U8*W8 -> 1382.4 | Y8: =Q8 -> 160 | Z8: =+Y8*R8 -> 160 | AA8: EUR | AB8: =IFERROR(VLOOKUP(AA8,Curr!$B$2:$C$13,2,FALSE),0) -> 10.8 | AC8: =+Y8*AB8*R8 -> 1728 | AD8: =+AC8-X8 -> 345.6 | AE8: =IFERROR(AD8/AC8,0) -> 0.2
C9: Day 1 | D9: Hotel | E9: 27.06.2026 | F9: 29.06.2026 | J9: Reykjavik: Check in to your accommodation for a 1 night stay - Borg by Keahotels - 2 x Deluxe room - breakfast included | P9: https://app.hotelbeds.com/factsheet/stay/90467?check_in=27-06-2026&check_out=29-06-2026&occupancy=2~0_2~0&packaging=true | Q9: 2075 | R9: 1 | S9: =+Q9*R9 -> 2075 | T9: 0 | U9: =S9*(1-T9) -> 2075 | V9: EUR | W9: =IFERROR(VLOOKUP(V9,Curr!$B$2:$C$13,2,FALSE),0) -> 10.8 | X9: =U9*W9 -> 22410 | Y9: =Q9/0.8 -> 2593.75 | Z9: =+Y9*R9 -> 2593.75 | AA9: EUR | AB9: =IFERROR(VLOOKUP(AA9,Curr!$B$2:$C$13,2,FALSE),0) -> 10.8 | AC9: =+Y9*AB9*R9 -> 28012.5 | AD9: =+AC9-X9 -> 5602.5 | AE9: =IFERROR(AD9/AC9,0) -> 0.2
C10: Day 1 | D10: Leisure | E10: 27.06.2026 | J10: Reykjavik: Spend time at leisure | Q10: 0 | R10: 0 | S10: =+Q10*R10 -> 0 | T10: 0 | U10: =S10*(1-T10) -> 0 | V10: EUR | W10: =IFERROR(VLOOKUP(V10,Curr!$B$2:$C$13,2,FALSE),0) -> 10.8 | X10: =U10*W10 -> 0 | Y10: =Q10 -> 0 | Z10: =+Y10*R10 -> 0 | AA10: EUR | AB10: =IFERROR(VLOOKUP(AA10,Curr!$B$2:$C$13,2,FALSE),0) -> 10.8 | AC10: =+Y10*AB10*R10 -> 0 | AD10: =+AC10-X10 -> 0 | AE10: =IFERROR(AD10/AC10,0) -> 0
C11: Day 1 | D11: Activity | E11: 27.06.2026 | J11: Reykjavík: Classic Whale Watching under the Midnight Sun - Time: 8:30 pm - 11:30 pm - Meeting point: Elding ticket office, Ægisgarður 5c -Includes: 2-3,5 hours whale watching tour, Access to our Wildlife Exhibition, Excellent live commentary in English, Use of warm overalls & mellow music | P11: https://booknordics.com/iceland/western-iceland/reykjavik/reykjavik-classic-whales-in-the-midnight-sun | Q11: 127 | R11: 4 | S11: =+Q11*R11 -> 508 | T11: 0.25 | U11: =S11*(1-T11) -> 381 | V11: EUR | W11: =IFERROR(VLOOKUP(V11,Curr!$B$2:$C$13,2,FALSE),0) -> 10.8 | X11: =U11*W11 -> 4114.8 | Y11: =Q11 -> 127 | Z11: =+Y11*R11 -> 508 | AA11: EUR | AB11: =IFERROR(VLOOKUP(AA11,Curr!$B$2:$C$13,2,FALSE),0) -> 10.8 | AC11: =+Y11*AB11*R11 -> 5486.4 | AD11: =+AC11-X11 -> 1371.6 | AE11: =IFERROR(AD11/AC11,0) -> 0.25
S12: =+Q12*R12 -> 0 | T12: 0 | U12: =S12*(1-T12) -> 0 | V12: EUR | W12: =IFERROR(VLOOKUP(V12,Curr!$B$2:$C$13,2,FALSE),0) -> 10.8 | X12: =U12*W12 -> 0 | Y12: =Q12 -> 0 | Z12: =+Y12*R12 -> 0 | AA12: EUR | AB12: =IFERROR(VLOOKUP(AA12,Curr!$B$2:$C$13,2,FALSE),0) -> 10.8 | AC12: =+Y12*AB12*R12 -> 0 | AD12: =+AC12-X12 -> 0 | AE12: =IFERROR(AD12/AC12,0) -> 0
C13: Day 2 | D13: Activity | E13: 28.06.2026 | J13: Reykjavik: FlyOver Iceland - Time: 12:30 pm - 1:30 pm - Meeting point: Fiskislóð 43 - Includes: Entry or admission fee, FlyOver Iceland Pursuit | P13: https://booknordics.com/iceland/western-iceland/reykjavik/flyover-iceland | Q13: 35 | R13: 4 | S13: =+Q13*R13 -> 140 | T13: 0.2 | U13: =S13*(1-T13) -> 112 | V13: EUR | W13: =IFERROR(VLOOKUP(V13,Curr!$B$2:$C$13,2,FALSE),0) -> 10.8 | X13: =U13*W13 -> 1209.6 | Y13: =Q13/0.8 -> 43.75 | Z13: =+Y13*R13 -> 175 | AA13: EUR | AB13: =IFERROR(VLOOKUP(AA13,Curr!$B$2:$C$13,2,FALSE),0) -> 10.8 | AC13: =+Y13*AB13*R13 -> 1890 | AD13: =+AC13-X13 -> 680.4 | AE13: =IFERROR(AD13/AC13,0) -> 0.36
C14: Day 2 | D14: Leisure | E14: 28.06.2026 | J14: Reykjavik: Spend time at leisure | Q14: 0 | R14: 0 | S14: =+Q14*R14 -> 0 | T14: 0 | U14: =S14*(1-T14) -> 0 | V14: EUR | W14: =IFERROR(VLOOKUP(V14,Curr!$B$2:$C$13,2,FALSE),0) -> 10.8 | X14: =U14*W14 -> 0 | Y14: =Q14 -> 0 | Z14: =+Y14*R14 -> 0 | AA14: EUR | AB14: =IFERROR(VLOOKUP(AA14,Curr!$B$2:$C$13,2,FALSE),0) -> 10.8 | AC14: =+Y14*AB14*R14 -> 0 | AD14: =+AC14-X14 -> 0 | AE14: =IFERROR(AD14/AC14,0) -> 0
S15: =+Q15*R15 -> 0 | T15: 0 | U15: =S15*(1-T15) -> 0 | V15: EUR | W15: =IFERROR(VLOOKUP(V15,Curr!$B$2:$C$13,2,FALSE),0) -> 10.8 | X15: =U15*W15 -> 0 | Y15: =Q15 -> 0 | Z15: =+Y15*R15 -> 0 | AA15: EUR | AB15: =IFERROR(VLOOKUP(AA15,Curr!$B$2:$C$13,2,FALSE),0) -> 10.8 | AC15: =+Y15*AB15*R15 -> 0 | AD15: =+AC15-X15 -> 0 | AE15: =IFERROR(AD15/AC15,0) -> 0
C16: Day 3 | D16: Transfer | E16: 29.06.2026 | J16: Reykjavik: Self transfer by Uber to the car rental office | Q16: 0 | R16: 0 | S16: =+Q16*R16 -> 0 | T16: 0 | U16: =S16*(1-T16) -> 0 | V16: EUR | W16: =IFERROR(VLOOKUP(V16,Curr!$B$2:$C$13,2,FALSE),0) -> 10.8 | X16: =U16*W16 -> 0 | Y16: =Q16 -> 0 | Z16: =+Y16*R16 -> 0 | AA16: EUR | AB16: =IFERROR(VLOOKUP(AA16,Curr!$B$2:$C$13,2,FALSE),0) -> 10.8 | AC16: =+Y16*AB16*R16 -> 0 | AD16: =+AC16-X16 -> 0 | AE16: =IFERROR(AD16/AC16,0) -> 0
C17: Day 3 | D17: Car | E17: 29.06.2026 | F17: 03.07.2026 | J17: Reykjavik: Pick up your rental car at the car rental office - Car: TOYOTA RAV4 2.0 4WD AUTOMATIC or similar - Office Location: Njardargata Fluggardar - Includes: Collision damage waiver, Fuel information, Unlimited mileage, Theft protection, Vat, Personal accident insurance, Cancellation fee - Excludes: 1 way fee, road tax | P17: https://app.hotelbeds.com/carhire/search?baggage=4&results=20&sortBy=LOWEST_PRICE_FIRST&field=PRICE&direction=ASCENDING&page=2&destinationTab=Reykjav%C3%ADk&pickupDate=29-06-2026&pickupTime=12:00&dropoffDate=03-07-2026&dropoffTime=12:00&sameOfficeCheckbox=false&officePickupControl=1171&officeDropoffControl=701&typeDepartureCode=airport&_timestamp=1776931327625&departureTab=Keflav%C3%ADk%20International%20Airport%20(KEF)&typeArrivalCode=city | Q17: 564 | R17: 1 | S17: =+Q17*R17 -> 564 | T17: 0 | U17: =S17*(1-T17) -> 564 | V17: EUR | W17: =IFERROR(VLOOKUP(V17,Curr!$B$2:$C$13,2,FALSE),0) -> 10.8 | X17: =U17*W17 -> 6091.2 | Y17: =Q17/0.8 -> 705 | Z17: =+Y17*R17 -> 705 | AA17: EUR | AB17: =IFERROR(VLOOKUP(AA17,Curr!$B$2:$C$13,2,FALSE),0) -> 10.8 | AC17: =+Y17*AB17*R17 -> 7614 | AD17: =+AC17-X17 -> 1522.8 | AE17: =IFERROR(AD17/AC17,0) -> 0.2
C18: Day 3 | D18: Drive | E18: 29.06.2026 | J18: Reykjavik: Drive the Golden Circle to Asborgir - Driving time: 3 hours - Things to see: Öxarárfoss, Efstidalur, Geysir Hot Springs, Gullfoss Waterfall, Friðheimar, Kerið | Q18: 0 | R18: 0 | S18: =+Q18*R18 -> 0 | T18: 0 | U18: =S18*(1-T18) -> 0 | V18: EUR | W18: =IFERROR(VLOOKUP(V18,Curr!$B$2:$C$13,2,FALSE),0) -> 10.8 | X18: =U18*W18 -> 0 | Y18: =Q18 -> 0 | Z18: =+Y18*R18 -> 0 | AA18: EUR | AB18: =IFERROR(VLOOKUP(AA18,Curr!$B$2:$C$13,2,FALSE),0) -> 10.8 | AC18: =+Y18*AB18*R18 -> 0 | AD18: =+AC18-X18 -> 0 | AE18: =IFERROR(AD18/AC18,0) -> 0
C19: Day 3 | D19: Hotel | E19: 29.06.2026 | F19: 30.07.2026 | J19: Asborgir: Check in to your accommodation for a 1 night stay - Grimsborgir by Keahotels - 2 x Superior Room - Breakfast included | P19: https://app.hotelbeds.com/factsheet/stay/257043?check_in=29-06-2026&check_out=30-06-2026&occupancy=2~0_2~0&packaging=true | Q19: 607 | R19: 1 | S19: =+Q19*R19 -> 607 | T19: 0 | U19: =S19*(1-T19) -> 607 | V19: EUR | W19: =IFERROR(VLOOKUP(V19,Curr!$B$2:$C$13,2,FALSE),0) -> 10.8 | X19: =U19*W19 -> 6555.6 | Y19: =Q19/0.8 -> 758.75 | Z19: =+Y19*R19 -> 758.75 | AA19: EUR | AB19: =IFERROR(VLOOKUP(AA19,Curr!$B$2:$C$13,2,FALSE),0) -> 10.8 | AC19: =+Y19*AB19*R19 -> 8194.5 | AD19: =+AC19-X19 -> 1638.9 | AE19: =IFERROR(AD19/AC19,0) -> 0.2
C20: Day 3 | D20: Leisure | E20: 29.06.2026 | J20: Asborgir: Spend time at leisure | Q20: 0 | R20: 0 | S20: =+Q20*R20 -> 0 | T20: 0 | U20: =S20*(1-T20) -> 0 | V20: EUR | W20: =IFERROR(VLOOKUP(V20,Curr!$B$2:$C$13,2,FALSE),0) -> 10.8 | X20: =U20*W20 -> 0 | Y20: =Q20 -> 0 | Z20: =+Y20*R20 -> 0 | AA20: EUR | AB20: =IFERROR(VLOOKUP(AA20,Curr!$B$2:$C$13,2,FALSE),0) -> 10.8 | AC20: =+Y20*AB20*R20 -> 0 | AD20: =+AC20-X20 -> 0 | AE20: =IFERROR(AD20/AC20,0) -> 0
S21: =+Q21*R21 -> 0 | T21: 0 | U21: =S21*(1-T21) -> 0 | V21: EUR | W21: =IFERROR(VLOOKUP(V21,Curr!$B$2:$C$13,2,FALSE),0) -> 10.8 | X21: =U21*W21 -> 0 | Y21: =Q21/0.8 -> 0 | Z21: =+Y21*R21 -> 0 | AA21: EUR | AB21: =IFERROR(VLOOKUP(AA21,Curr!$B$2:$C$13,2,FALSE),0) -> 10.8 | AC21: =+Y21*AB21*R21 -> 0 | AD21: =+AC21-X21 -> 0 | AE21: =IFERROR(AD21/AC21,0) -> 0
C22: Day 4 | D22: Drive | E22: 30.07.2026 | J22: Asborgir: Drive to Vik - Driving time: 2 hrs - Things to See: Selfoss, Hella, Hvolsvöllur | Q22: 0 | R22: 0 | S22: =+Q22*R22 -> 0 | T22: 0 | U22: =S22*(1-T22) -> 0 | V22: EUR | W22: =IFERROR(VLOOKUP(V22,Curr!$B$2:$C$13,2,FALSE),0) -> 10.8 | X22: =U22*W22 -> 0 | Y22: =Q22 -> 0 | Z22: =+Y22*R22 -> 0 | AA22: EUR | AB22: =IFERROR(VLOOKUP(AA22,Curr!$B$2:$C$13,2,FALSE),0) -> 10.8 | AC22: =+Y22*AB22*R22 -> 0 | AD22: =+AC22-X22 -> 0 | AE22: =IFERROR(AD22/AC22,0) -> 0
C23: Day 4 | D23: Hotel | E23: 30.07.2026 | F23: 02.07.2026 | J23: Vik: Check in to your accommodation for a 2 night stay - Hotel Katla by Keahotels - 2 x Superior Double room - breakfast included | P23: https://www.ratehawk.com/hotel/iceland/vik_i_myrdal/mid7524341/hotel_hofdabrekka_country_hotel/?q=6130429&dates=30.06.2026-02.07.2026&guests=2-2&price=one&sid=22ec769a-b117-452f-befc-9c97bff50e0a | Q23: 2976 | R23: 1 | S23: =+Q23*R23 -> 2976 | T23: 0 | U23: =S23*(1-T23) -> 2976 | V23: EUR | W23: =IFERROR(VLOOKUP(V23,Curr!$B$2:$C$13,2,FALSE),0) -> 10.8 | X23: =U23*W23 -> 32140.8 | Y23: =Q23/0.85 -> 3501.1765 | Z23: =+Y23*R23 -> 3501.1765 | AA23: EUR | AB23: =IFERROR(VLOOKUP(AA23,Curr!$B$2:$C$13,2,FALSE),0) -> 10.8 | AC23: =+Y23*AB23*R23 -> 37812.706 | AD23: =+AC23-X23 -> 5671.9059 | AE23: =IFERROR(AD23/AC23,0) -> 0.15
C24: Day 4 | D24: Activity | E24: 30.07.2026 | J24: Vik: Lava Show Vík - Time: 11:00 am - 12:00 pm - Meeeting point: Icelandic Lava Show, Víkurbraut 5 - Includes: A chance to get up close to real flowing lava, The only live lava show in the world, Security goggles, A live host makes the show fun and personal, A short educational video about Icelandic volcanism, A true story from the 1918 Katla eruption, A sensory loaded experience - you feel the heat from the lava, A Q&A session at the end of the show, A unique once-in-a-lifetime experience | P24: https://booknordics.com/iceland/southern-iceland/vik/lava-show-vik-the-original | Q24: 46 | R24: 4 | S24: =+Q24*R24 -> 184 | T24: 0.2 | U24: =S24*(1-T24) -> 147.2 | V24: EUR | W24: =IFERROR(VLOOKUP(V24,Curr!$B$2:$C$13,2,FALSE),0) -> 10.8 | X24: =U24*W24 -> 1589.76 | Y24: =Q24/0.9 -> 51.111111 | Z24: =+Y24*R24 -> 204.44444 | AA24: EUR | AB24: =IFERROR(VLOOKUP(AA24,Curr!$B$2:$C$13,2,FALSE),0) -> 10.8 | AC24: =+Y24*AB24*R24 -> 2208 | AD24: =+AC24-X24 -> 618.24 | AE24: =IFERROR(AD24/AC24,0) -> 0.28
C25: Day 4 | D25: Leisure | E25: 30.07.2026 | J25: Vik: Spend time at leisure | Q25: 0 | R25: 0 | S25: =+Q25*R25 -> 0 | T25: 0 | U25: =S25*(1-T25) -> 0 | V25: EUR | W25: =IFERROR(VLOOKUP(V25,Curr!$B$2:$C$13,2,FALSE),0) -> 10.8 | X25: =U25*W25 -> 0 | Y25: =Q25 -> 0 | Z25: =+Y25*R25 -> 0 | AA25: EUR | AB25: =IFERROR(VLOOKUP(AA25,Curr!$B$2:$C$13,2,FALSE),0) -> 10.8 | AC25: =+Y25*AB25*R25 -> 0 | AD25: =+AC25-X25 -> 0 | AE25: =IFERROR(AD25/AC25,0) -> 0
S26: =+Q26*R26 -> 0 | T26: 0 | U26: =S26*(1-T26) -> 0 | V26: EUR | W26: =IFERROR(VLOOKUP(V26,Curr!$B$2:$C$13,2,FALSE),0) -> 10.8 | X26: =U26*W26 -> 0 | Y26: =Q26 -> 0 | Z26: =+Y26*R26 -> 0 | AA26: EUR | AB26: =IFERROR(VLOOKUP(AA26,Curr!$B$2:$C$13,2,FALSE),0) -> 10.8 | AC26: =+Y26*AB26*R26 -> 0 | AD26: =+AC26-X26 -> 0 | AE26: =IFERROR(AD26/AC26,0) -> 0
C27: Day 5 | D27: Leisure | E27: 01.07.2026 | J27: Vik: Spend time at leisure | Q27: 0 | R27: 0 | S27: =+Q27*R27 -> 0 | T27: 0 | U27: =S27*(1-T27) -> 0 | V27: EUR | W27: =IFERROR(VLOOKUP(V27,Curr!$B$2:$C$13,2,FALSE),0) -> 10.8 | X27: =U27*W27 -> 0 | Y27: =Q27 -> 0 | Z27: =+Y27*R27 -> 0 | AA27: EUR | AB27: =IFERROR(VLOOKUP(AA27,Curr!$B$2:$C$13,2,FALSE),0) -> 10.8 | AC27: =+Y27*AB27*R27 -> 0 | AD27: =+AC27-X27 -> 0 | AE27: =IFERROR(AD27/AC27,0) -> 0
C28: Day 5 | D28: Activity | E28: 01.07.2026 | J28: Vik: Ice Cave Underneath Katla Volcano Super Jeep Tour - Time: 6:00 pm - 9:00 pm - Meeting point: Tröll Expeditions Katla Ice Cave, Víkubraut 26 - Includes: Stunning ride on a super jeep, Certified glacier guide, Visit to a natural ice cave, All safety ice cave equipment, Scenic landscapes viewing | P28: https://booknordics.com/iceland/southern-iceland/vik/katla-ice-cave-super-jeep-from-vik | Q28: 204 | R28: 4 | S28: =+Q28*R28 -> 816 | T28: 0.25 | U28: =S28*(1-T28) -> 612 | V28: EUR | W28: =IFERROR(VLOOKUP(V28,Curr!$B$2:$C$13,2,FALSE),0) -> 10.8 | X28: =U28*W28 -> 6609.6 | Y28: =Q28 -> 204 | Z28: =+Y28*R28 -> 816 | AA28: EUR | AB28: =IFERROR(VLOOKUP(AA28,Curr!$B$2:$C$13,2,FALSE),0) -> 10.8 | AC28: =+Y28*AB28*R28 -> 8812.8 | AD28: =+AC28-X28 -> 2203.2 | AE28: =IFERROR(AD28/AC28,0) -> 0.25
S29: =+Q29*R29 -> 0 | T29: 0 | U29: =S29*(1-T29) -> 0 | V29: EUR | W29: =IFERROR(VLOOKUP(V29,Curr!$B$2:$C$13,2,FALSE),0) -> 10.8 | X29: =U29*W29 -> 0 | Y29: =Q29 -> 0 | Z29: =+Y29*R29 -> 0 | AA29: EUR | AB29: =IFERROR(VLOOKUP(AA29,Curr!$B$2:$C$13,2,FALSE),0) -> 10.8 | AC29: =+Y29*AB29*R29 -> 0 | AD29: =+AC29-X29 -> 0 | AE29: =IFERROR(AD29/AC29,0) -> 0
C30: Day 6 | D30: Drive | E30: 02.07.2026 | J30: Vik: Drive to Reykjavik via the South Coast - Driving time: 2 hrs 30 minutes - Things to see: | Q30: 0 | R30: 0 | S30: =+Q30*R30 -> 0 | T30: 0 | U30: =S30*(1-T30) -> 0 | V30: EUR | W30: =IFERROR(VLOOKUP(V30,Curr!$B$2:$C$13,2,FALSE),0) -> 10.8 | X30: =U30*W30 -> 0 | Y30: =Q30 -> 0 | Z30: =+Y30*R30 -> 0 | AA30: EUR | AB30: =IFERROR(VLOOKUP(AA30,Curr!$B$2:$C$13,2,FALSE),0) -> 10.8 | AC30: =+Y30*AB30*R30 -> 0 | AD30: =+AC30-X30 -> 0 | AE30: =IFERROR(AD30/AC30,0) -> 0
C31: Day 6 | D31: Hotel | E31: 02.07.2026 | F31: 03.07.2026 | J31: Reykjavik: Check in to your accommodation for a 1 night stay - Borg by Keahotels - 2 x Deluxe room - breakfast included | P31: https://app.hotelbeds.com/factsheet/stay/90467?check_in=02-07-2026&check_out=03-07-2026&occupancy=2~0_2~0&packaging=true | Q31: 1091 | R31: 1 | S31: =+Q31*R31 -> 1091 | T31: 0 | U31: =S31*(1-T31) -> 1091 | V31: EUR | W31: =IFERROR(VLOOKUP(V31,Curr!$B$2:$C$13,2,FALSE),0) -> 10.8 | X31: =U31*W31 -> 11782.8 | Y31: =Q31/0.8 -> 1363.75 | Z31: =+Y31*R31 -> 1363.75 | AA31: EUR | AB31: =IFERROR(VLOOKUP(AA31,Curr!$B$2:$C$13,2,FALSE),0) -> 10.8 | AC31: =+Y31*AB31*R31 -> 14728.5 | AD31: =+AC31-X31 -> 2945.7 | AE31: =IFERROR(AD31/AC31,0) -> 0.2
C32: Day 6 | D32: Leisure | E32: 02.07.2026 | J32: Reykjavik: Spend time at leisure | Q32: 0 | R32: 0 | S32: =+Q32*R32 -> 0 | T32: 0 | U32: =S32*(1-T32) -> 0 | V32: EUR | W32: =IFERROR(VLOOKUP(V32,Curr!$B$2:$C$13,2,FALSE),0) -> 10.8 | X32: =U32*W32 -> 0 | Y32: =Q32 -> 0 | Z32: =+Y32*R32 -> 0 | AA32: EUR | AB32: =IFERROR(VLOOKUP(AA32,Curr!$B$2:$C$13,2,FALSE),0) -> 10.8 | AC32: =+Y32*AB32*R32 -> 0 | AD32: =+AC32-X32 -> 0 | AE32: =IFERROR(AD32/AC32,0) -> 0
C33: Day 6 | D33: Activity | E33: 02.07.2026 | J33: Reykjavik: Sky Lagoon Sér Pass with Transfer - Time: 5:00 pm - 7:30 pm - Meeting point: Hotel Pick up - Includes: Bus fare, Sky Lagoon Sér Admission, Complete Seven-step Ritual, Private Changing Facilities, Towel | P33: https://booknordics.com/iceland/western-iceland/reykjavik/sky-lagoon-sky-pass-with-transfer | Q33: 167 | R33: 4 | S33: =+Q33*R33 -> 668 | T33: 0.2 | U33: =S33*(1-T33) -> 534.4 | V33: EUR | W33: =IFERROR(VLOOKUP(V33,Curr!$B$2:$C$13,2,FALSE),0) -> 10.8 | X33: =U33*W33 -> 5771.52 | Y33: =Q33 -> 167 | Z33: =+Y33*R33 -> 668 | AA33: EUR | AB33: =IFERROR(VLOOKUP(AA33,Curr!$B$2:$C$13,2,FALSE),0) -> 10.8 | AC33: =+Y33*AB33*R33 -> 7214.4 | AD33: =+AC33-X33 -> 1442.88 | AE33: =IFERROR(AD33/AC33,0) -> 0.2
S34: =+Q34*R34 -> 0 | T34: 0 | U34: =S34*(1-T34) -> 0 | V34: EUR | W34: =IFERROR(VLOOKUP(V34,Curr!$B$2:$C$13,2,FALSE),0) -> 10.8 | X34: =U34*W34 -> 0 | Y34: =Q34 -> 0 | Z34: =+Y34*R34 -> 0 | AA34: EUR | AB34: =IFERROR(VLOOKUP(AA34,Curr!$B$2:$C$13,2,FALSE),0) -> 10.8 | AC34: =+Y34*AB34*R34 -> 0 | AD34: =+AC34-X34 -> 0 | AE34: =IFERROR(AD34/AC34,0) -> 0
C35: Day 7 | D35: Drive | E35: 03.07.2026 | J35: Reykjavik: Drive to Keflavik Airport | Q35: 0 | R35: 0 | S35: =+Q35*R35 -> 0 | T35: 0 | U35: =S35*(1-T35) -> 0 | V35: EUR | W35: =IFERROR(VLOOKUP(V35,Curr!$B$2:$C$13,2,FALSE),0) -> 10.8 | X35: =U35*W35 -> 0 | Y35: =Q35 -> 0 | Z35: =+Y35*R35 -> 0 | AA35: EUR | AB35: =IFERROR(VLOOKUP(AA35,Curr!$B$2:$C$13,2,FALSE),0) -> 10.8 | AC35: =+Y35*AB35*R35 -> 0 | AD35: =+AC35-X35 -> 0 | AE35: =IFERROR(AD35/AC35,0) -> 0
C36: Day 7 | D36: Car | E36: 03.07.2026 | J36: Keflavik: Deliver your rental car at the airport car rental office | Q36: 0 | R36: 0 | S36: =+Q36*R36 -> 0 | T36: 0 | U36: =S36*(1-T36) -> 0 | V36: EUR | W36: =IFERROR(VLOOKUP(V36,Curr!$B$2:$C$13,2,FALSE),0) -> 10.8 | X36: =U36*W36 -> 0 | Y36: =Q36 -> 0 | Z36: =+Y36*R36 -> 0 | AA36: EUR | AB36: =IFERROR(VLOOKUP(AA36,Curr!$B$2:$C$13,2,FALSE),0) -> 10.8 | AC36: =+Y36*AB36*R36 -> 0 | AD36: =+AC36-X36 -> 0 | AE36: =IFERROR(AD36/AC36,0) -> 0
C37: Day 7 | D37: Flight | E37: 03.07.2026 | J37: Keflavik: Flight to Oslo - Time: 09:10 am - 1:50 pm - Luggage included: 1 x 23 kg check in and 1 x 8 kg carry on per person | P37: https://www.sas.no/book/flights/?search=OW_KEF-OSL-20260703_a4c0i0y0&view=upsell&bookingFlow=revenue&out_flight_number=SK4788&skyscanner_redirectid=RhZvBkUmTrSXl9DScsN5CA&utm_source=skyscanner&utm_medium=metasearch&utm_campaign=skyscanner_metasearch&sortBy=rec&out_class=ECONOMY&out_sub_class=FLEX | Q37: 2778 | R37: 4 | S37: =+Q37*R37 -> 11112 | T37: 0 | U37: =S37*(1-T37) -> 11112 | V37: NOK | W37: =IFERROR(VLOOKUP(V37,Curr!$B$2:$C$13,2,FALSE),0) -> 1 | X37: =U37*W37 -> 11112 | Y37: =Q37/11/0.8 -> 315.68182 | Z37: =+Y37*R37 -> 1262.7273 | AA37: EUR | AB37: =IFERROR(VLOOKUP(AA37,Curr!$B$2:$C$13,2,FALSE),0) -> 10.8 | AC37: =+Y37*AB37*R37 -> 13637.455 | AD37: =+AC37-X37 -> 2525.4545 | AE37: =IFERROR(AD37/AC37,0) -> 0.18518519
C38: Day 7 | D38: Transfer | E38: 03.07.2026 | J38: Oslo: Private transfer to your accommodation | Q38: 1900 | R38: 1 | S38: =+Q38*R38 -> 1900 | T38: 0 | U38: =S38*(1-T38) -> 1900 | V38: NOK | W38: =IFERROR(VLOOKUP(V38,Curr!$B$2:$C$13,2,FALSE),0) -> 1 | X38: =U38*W38 -> 1900 | Y38: =Q38/11/0.8 -> 215.90909 | Z38: =+Y38*R38 -> 215.90909 | AA38: EUR | AB38: =IFERROR(VLOOKUP(AA38,Curr!$B$2:$C$13,2,FALSE),0) -> 10.8 | AC38: =+Y38*AB38*R38 -> 2331.8182 | AD38: =+AC38-X38 -> 431.81818 | AE38: =IFERROR(AD38/AC38,0) -> 0.18518519
C39: Day 7 | D39: Hotel | E39: 03.07.2026 | F39: 05.07.2026 | J39: Oslo: Check in to your accommodation for a 2 night stay - Grand Hotel Oslo by Scandic - 2 x Superior king - Breakfast included | P39: https://app.hotelbeds.com/factsheet/stay/616601?check_in=03-07-2026&check_out=05-07-2026&occupancy=2~0_2~0&packaging=true | Q39: 2058 | R39: 1 | S39: =+Q39*R39 -> 2058 | T39: 0 | U39: =S39*(1-T39) -> 2058 | V39: EUR | W39: =IFERROR(VLOOKUP(V39,Curr!$B$2:$C$13,2,FALSE),0) -> 10.8 | X39: =U39*W39 -> 22226.4 | Y39: =Q39/0.85 -> 2421.1765 | Z39: =+Y39*R39 -> 2421.1765 | AA39: EUR | AB39: =IFERROR(VLOOKUP(AA39,Curr!$B$2:$C$13,2,FALSE),0) -> 10.8 | AC39: =+Y39*AB39*R39 -> 26148.706 | AD39: =+AC39-X39 -> 3922.3059 | AE39: =IFERROR(AD39/AC39,0) -> 0.15
C40: Day 7 | D40: Leisure | E40: 03.07.2026 | J40: Oslo: Spend time at leisure | Q40: 0 | R40: 0 | S40: =+Q40*R40 -> 0 | T40: 0 | U40: =S40*(1-T40) -> 0 | V40: EUR | W40: =IFERROR(VLOOKUP(V40,Curr!$B$2:$C$13,2,FALSE),0) -> 10.8 | X40: =U40*W40 -> 0 | Y40: =Q40 -> 0 | Z40: =+Y40*R40 -> 0 | AA40: EUR | AB40: =IFERROR(VLOOKUP(AA40,Curr!$B$2:$C$13,2,FALSE),0) -> 10.8 | AC40: =+Y40*AB40*R40 -> 0 | AD40: =+AC40-X40 -> 0 | AE40: =IFERROR(AD40/AC40,0) -> 0
S41: =+Q41*R41 -> 0 | T41: 0 | U41: =S41*(1-T41) -> 0 | V41: EUR | W41: =IFERROR(VLOOKUP(V41,Curr!$B$2:$C$13,2,FALSE),0) -> 10.8 | X41: =U41*W41 -> 0 | Y41: =Q41 -> 0 | Z41: =+Y41*R41 -> 0 | AA41: EUR | AB41: =IFERROR(VLOOKUP(AA41,Curr!$B$2:$C$13,2,FALSE),0) -> 10.8 | AC41: =+Y41*AB41*R41 -> 0 | AD41: =+AC41-X41 -> 0 | AE41: =IFERROR(AD41/AC41,0) -> 0
C42: Day 8 | D42: Activity | E42: 04.07.2026 | J42: Oslo: Fjord Sightseeing Cruise by 100% Electric Boat - Time: 1:30 pm - 3:30 pm - Meeting point: Rådhusbrygge 4, Platform E - Includes: Oslo Fjord archipelago cruise by electric boat, Cafeteria with snacks and drinks for purchase, "Voice of Norway" Audio guide for download, Stop at the Bygdøy peninsula near to museums | P42: https://booknordics.com/norway/eastern-norway/oslo/oslofjord-sightseeing-cruise | Q42: 40 | R42: 4 | S42: =+Q42*R42 -> 160 | T42: 0.2 | U42: =S42*(1-T42) -> 128 | V42: EUR | W42: =IFERROR(VLOOKUP(V42,Curr!$B$2:$C$13,2,FALSE),0) -> 10.8 | X42: =U42*W42 -> 1382.4 | Y42: =Q42 -> 40 | Z42: =+Y42*R42 -> 160 | AA42: EUR | AB42: =IFERROR(VLOOKUP(AA42,Curr!$B$2:$C$13,2,FALSE),0) -> 10.8 | AC42: =+Y42*AB42*R42 -> 1728 | AD42: =+AC42-X42 -> 345.6 | AE42: =IFERROR(AD42/AC42,0) -> 0.2
C43: Day 8 | D43: Leisure | E43: 04.07.2026 | J43: Oslo: Spend time at leisure | Q43: 0 | R43: 0 | S43: =+Q43*R43 -> 0 | T43: 0 | U43: =S43*(1-T43) -> 0 | V43: EUR | W43: =IFERROR(VLOOKUP(V43,Curr!$B$2:$C$13,2,FALSE),0) -> 10.8 | X43: =U43*W43 -> 0 | Y43: =Q43 -> 0 | Z43: =+Y43*R43 -> 0 | AA43: EUR | AB43: =IFERROR(VLOOKUP(AA43,Curr!$B$2:$C$13,2,FALSE),0) -> 10.8 | AC43: =+Y43*AB43*R43 -> 0 | AD43: =+AC43-X43 -> 0 | AE43: =IFERROR(AD43/AC43,0) -> 0
S44: =+Q44*R44 -> 0 | T44: 0 | U44: =S44*(1-T44) -> 0 | V44: EUR | W44: =IFERROR(VLOOKUP(V44,Curr!$B$2:$C$13,2,FALSE),0) -> 10.8 | X44: =U44*W44 -> 0 | Y44: =Q44 -> 0 | Z44: =+Y44*R44 -> 0 | AA44: EUR | AB44: =IFERROR(VLOOKUP(AA44,Curr!$B$2:$C$13,2,FALSE),0) -> 10.8 | AC44: =+Y44*AB44*R44 -> 0 | AD44: =+AC44-X44 -> 0 | AE44: =IFERROR(AD44/AC44,0) -> 0
C45: Day 9 | D45: Transfer | E45: 05.07.2026 | J45: Oslo: Self transfer to Oslo Central Station | Q45: 0 | R45: 0 | S45: =+Q45*R45 -> 0 | T45: 0 | U45: =S45*(1-T45) -> 0 | V45: EUR | W45: =IFERROR(VLOOKUP(V45,Curr!$B$2:$C$13,2,FALSE),0) -> 10.8 | X45: =U45*W45 -> 0 | Y45: =Q45 -> 0 | Z45: =+Y45*R45 -> 0 | AA45: EUR | AB45: =IFERROR(VLOOKUP(AA45,Curr!$B$2:$C$13,2,FALSE),0) -> 10.8 | AC45: =+Y45*AB45*R45 -> 0 | AD45: =+AC45-X45 -> 0 | AE45: =IFERROR(AD45/AC45,0) -> 0
C46: Day 9 | D46: Activity | E46: 05.07.2026 | J46: Oslo: Norway in a Nutshell tour to Bergen, including Luggage transfer for 4 x luggage - Time: 08:23 am - 11:18 pm - Includes: Train tickets Oslo to Bergen, Train tickets Flåm to Myrdal, Fjord Cruisee Flåm to Gudvangen - Tour summary: 08:23 am - 1:04 pm: Train from Oslo to Myrdal. 1:24 pm - 2:22 pm: Flåmsbana to Flåm. 5:30 pm - 7:20 pm: Fjord Cruise to Gudangen. 7:30 pm - 8:30 pm: Premium Coach to Voss. 10:06 pm - 11:18 pm: Train to Bergen . | P46: https://www.fjordtours.com/en/norway/booking/tour/norway-in-a-nutshell/b1205fbc-1045-45fb-a099-1d3be8f4aa58/5c582628-ae09-482f-93bf-e41e16e39ac0 | Q46: =3873+450 -> 4323 | R46: 4 | S46: =+Q46*R46 -> 17292 | T46: 0.12 | U46: =S46*(1-T46) -> 15216.96 | V46: NOK | W46: =IFERROR(VLOOKUP(V46,Curr!$B$2:$C$13,2,FALSE),0) -> 1 | X46: =U46*W46 -> 15216.96 | Y46: =Q46/11/0.9 -> 436.66667 | Z46: =+Y46*R46 -> 1746.6667 | AA46: EUR | AB46: =IFERROR(VLOOKUP(AA46,Curr!$B$2:$C$13,2,FALSE),0) -> 10.8 | AC46: =+Y46*AB46*R46 -> 18864 | AD46: =+AC46-X46 -> 3647.04 | AE46: =IFERROR(AD46/AC46,0) -> 0.19333333
C47: Day 9 | D47: Transfer | E47: 05.07.2026 | J47: Bergen: Private transfer to your accommodation | P47: https://www.btservice.no/private-cruiseport-transfer | Q47: 1490 | R47: 1 | S47: =+Q47*R47 -> 1490 | T47: 0.15 | U47: =S47*(1-T47) -> 1266.5 | V47: NOK | W47: =IFERROR(VLOOKUP(V47,Curr!$B$2:$C$13,2,FALSE),0) -> 1 | X47: =U47*W47 -> 1266.5 | Y47: =Q47/11/0.9 -> 150.50505 | Z47: =+Y47*R47 -> 150.50505 | AA47: EUR | AB47: =IFERROR(VLOOKUP(AA47,Curr!$B$2:$C$13,2,FALSE),0) -> 10.8 | AC47: =+Y47*AB47*R47 -> 1625.4545 | AD47: =+AC47-X47 -> 358.95455 | AE47: =IFERROR(AD47/AC47,0) -> 0.22083333
C48: Day 9 | D48: Hotel | E48: 05.07.2026 | F48: 07.07.2026 | J48: Bergen: Check in to your accommodation for a 2 night stay - Bergen Bors - 2 x Suite loft - breakfast included | P48: https://app.hotelbeds.com/factsheet/stay/647045?check_in=05-07-2026&check_out=07-07-2026&occupancy=2~0_2~0&packaging=true | Q48: 2620 | R48: 1 | S48: =+Q48*R48 -> 2620 | T48: 0 | U48: =S48*(1-T48) -> 2620 | V48: EUR | W48: =IFERROR(VLOOKUP(V48,Curr!$B$2:$C$13,2,FALSE),0) -> 10.8 | X48: =U48*W48 -> 28296 | Y48: =Q48/0.85 -> 3082.3529 | Z48: =+Y48*R48 -> 3082.3529 | AA48: EUR | AB48: =IFERROR(VLOOKUP(AA48,Curr!$B$2:$C$13,2,FALSE),0) -> 10.8 | AC48: =+Y48*AB48*R48 -> 33289.412 | AD48: =+AC48-X48 -> 4993.4118 | AE48: =IFERROR(AD48/AC48,0) -> 0.15
C49: Day 9 | D49: Leisure | E49: 05.07.2026 | J49: Bergen: Spend time at leisure | Q49: 0 | R49: 0 | S49: =+Q49*R49 -> 0 | T49: 0 | U49: =S49*(1-T49) -> 0 | V49: EUR | W49: =IFERROR(VLOOKUP(V49,Curr!$B$2:$C$13,2,FALSE),0) -> 10.8 | X49: =U49*W49 -> 0 | Y49: =Q49 -> 0 | Z49: =+Y49*R49 -> 0 | AA49: EUR | AB49: =IFERROR(VLOOKUP(AA49,Curr!$B$2:$C$13,2,FALSE),0) -> 10.8 | AC49: =+Y49*AB49*R49 -> 0 | AD49: =+AC49-X49 -> 0 | AE49: =IFERROR(AD49/AC49,0) -> 0
S50: =+Q50*R50 -> 0 | T50: 0 | U50: =S50*(1-T50) -> 0 | V50: EUR | W50: =IFERROR(VLOOKUP(V50,Curr!$B$2:$C$13,2,FALSE),0) -> 10.8 | X50: =U50*W50 -> 0 | Y50: =Q50 -> 0 | Z50: =+Y50*R50 -> 0 | AA50: EUR | AB50: =IFERROR(VLOOKUP(AA50,Curr!$B$2:$C$13,2,FALSE),0) -> 10.8 | AC50: =+Y50*AB50*R50 -> 0 | AD50: =+AC50-X50 -> 0 | AE50: =IFERROR(AD50/AC50,0) -> 0
C51: Day 10 | D51: Activity | E51: 06.07.2026 | J51: Bergen: Fløybanen Funicular Tickets - Time: Flexible - Meeting point: Fløybanen | P51: https://www.floyen.no/floibanen/kjop-billetter | Q51: 200 | R51: 4 | S51: =+Q51*R51 -> 800 | T51: 0 | U51: =S51*(1-T51) -> 800 | V51: NOK | W51: =IFERROR(VLOOKUP(V51,Curr!$B$2:$C$13,2,FALSE),0) -> 1 | X51: =U51*W51 -> 800 | Y51: =Q51/11/0.6 -> 30.30303 | Z51: =+Y51*R51 -> 121.21212 | AA51: EUR | AB51: =IFERROR(VLOOKUP(AA51,Curr!$B$2:$C$13,2,FALSE),0) -> 10.8 | AC51: =+Y51*AB51*R51 -> 1309.0909 | AD51: =+AC51-X51 -> 509.09091 | AE51: =IFERROR(AD51/AC51,0) -> 0.38888889
C52: Day 10 | D52: Leisure | E52: 06.07.2026 | J52: Bergen: Spend time at leisure | Q52: 0 | R52: 0 | S52: =+Q52*R52 -> 0 | T52: 0 | U52: =S52*(1-T52) -> 0 | V52: EUR | W52: =IFERROR(VLOOKUP(V52,Curr!$B$2:$C$13,2,FALSE),0) -> 10.8 | X52: =U52*W52 -> 0 | Y52: =Q52 -> 0 | Z52: =+Y52*R52 -> 0 | AA52: EUR | AB52: =IFERROR(VLOOKUP(AA52,Curr!$B$2:$C$13,2,FALSE),0) -> 10.8 | AC52: =+Y52*AB52*R52 -> 0 | AD52: =+AC52-X52 -> 0 | AE52: =IFERROR(AD52/AC52,0) -> 0
C53: Day 10 | D53: Activity | E53: 06.07.2026 | J53: Bergen: Mostraumen Majestic Fjord & Waterfall Cruise - Time: 5:00 pm - 7:00 pm - Meeting point: Börshopen Pier, Strandkaien 13 - Round-trip criose Bergen to Mostraumen to Bergen | P53: https://booknordics.com/norway/western-fjord-norway/bergen-and-hardanger/mostraumen-fjord-waterfall-cruise | Q53: 75 | R53: 4 | S53: =+Q53*R53 -> 300 | T53: 0.2 | U53: =S53*(1-T53) -> 240 | V53: EUR | W53: =IFERROR(VLOOKUP(V53,Curr!$B$2:$C$13,2,FALSE),0) -> 10.8 | X53: =U53*W53 -> 2592 | Y53: =Q53/0.9 -> 83.333333 | Z53: =+Y53*R53 -> 333.33333 | AA53: EUR | AB53: =IFERROR(VLOOKUP(AA53,Curr!$B$2:$C$13,2,FALSE),0) -> 10.8 | AC53: =+Y53*AB53*R53 -> 3600 | AD53: =+AC53-X53 -> 1008 | AE53: =IFERROR(AD53/AC53,0) -> 0.28
S54: =+Q54*R54 -> 0 | T54: 0 | U54: =S54*(1-T54) -> 0 | V54: EUR | W54: =IFERROR(VLOOKUP(V54,Curr!$B$2:$C$13,2,FALSE),0) -> 10.8 | X54: =U54*W54 -> 0 | Y54: =Q54 -> 0 | Z54: =+Y54*R54 -> 0 | AA54: EUR | AB54: =IFERROR(VLOOKUP(AA54,Curr!$B$2:$C$13,2,FALSE),0) -> 10.8 | AC54: =+Y54*AB54*R54 -> 0 | AD54: =+AC54-X54 -> 0 | AE54: =IFERROR(AD54/AC54,0) -> 0
C55: Day 11 | D55: Transfer | E55: 07.07.2026 | J55: Bergen: Private transfer to Bergen Airport | P55: https://www.btservice.no/private-cruiseport-transfer | Q55: 2290 | R55: 1 | S55: =+Q55*R55 -> 2290 | T55: 0.15 | U55: =S55*(1-T55) -> 1946.5 | V55: NOK | W55: =IFERROR(VLOOKUP(V55,Curr!$B$2:$C$13,2,FALSE),0) -> 1 | X55: =U55*W55 -> 1946.5 | Y55: =Q55/11/0.9 -> 231.31313 | Z55: =+Y55*R55 -> 231.31313 | AA55: EUR | AB55: =IFERROR(VLOOKUP(AA55,Curr!$B$2:$C$13,2,FALSE),0) -> 10.8 | AC55: =+Y55*AB55*R55 -> 2498.1818 | AD55: =+AC55-X55 -> 551.68182 | AE55: =IFERROR(AD55/AC55,0) -> 0.22083333
C56: Day 11 | D56: Flight | E56: 07.07.2026 | J56: Bergen: Flight to Ålesund - Time: 11:00 am - 11:50 am - Luggage included: 1 x 23 kg check in and 1 x 8 kg carry on per person | P56: https://www.wideroe.no/booking/booking#/select-flight | Q56: 1639 | R56: 4 | S56: =+Q56*R56 -> 6556 | T56: 0 | U56: =S56*(1-T56) -> 6556 | V56: NOK | W56: =IFERROR(VLOOKUP(V56,Curr!$B$2:$C$13,2,FALSE),0) -> 1 | X56: =U56*W56 -> 6556 | Y56: =Q56/11/0.8 -> 186.25 | Z56: =+Y56*R56 -> 745 | AA56: EUR | AB56: =IFERROR(VLOOKUP(AA56,Curr!$B$2:$C$13,2,FALSE),0) -> 10.8 | AC56: =+Y56*AB56*R56 -> 8046 | AD56: =+AC56-X56 -> 1490 | AE56: =IFERROR(AD56/AC56,0) -> 0.18518519
C57: Day 11 | D57: Car | E57: 07.07.2026 | F57: 10.07.2026 | J57: Ålesund: Pick up your rental car at the Ålesund Airport Car rental office - Car: SUZUKI S-CROSS - Office location: Flyplassvegen 27 - Includes: Collision damage waiver, Fuel information, Unlimited mileage, Theft protection, Vat, Personal accident insurance, Cancellation fee - Excludes: 1 way fee, road tax | P57: https://app.hotelbeds.com/carhire/search?seat=5&results=20&sortBy=LOWEST_PRICE_FIRST&field=PRICE&direction=ASCENDING&page=1&destinationTab=Alesund%20Airport%20(AES)&pickupDate=07-07-2026&pickupTime=13:00&dropoffDate=10-07-2026&dropoffTime=13:00&sameOfficeCheckbox=true&officePickupControl=56&officeDropoffControl=56&typeDepartureCode=airport&_timestamp=1776932694225&typeArrivalCode=airport&departureTab= | Q57: 334 | R57: 1 | S57: =+Q57*R57 -> 334 | T57: 0 | U57: =S57*(1-T57) -> 334 | V57: EUR | W57: =IFERROR(VLOOKUP(V57,Curr!$B$2:$C$13,2,FALSE),0) -> 10.8 | X57: =U57*W57 -> 3607.2 | Y57: =Q57/0.8 -> 417.5 | Z57: =+Y57*R57 -> 417.5 | AA57: EUR | AB57: =IFERROR(VLOOKUP(AA57,Curr!$B$2:$C$13,2,FALSE),0) -> 10.8 | AC57: =+Y57*AB57*R57 -> 4509 | AD57: =+AC57-X57 -> 901.8 | AE57: =IFERROR(AD57/AC57,0) -> 0.2
C58: Day 11 | D58: Drive | E58: 07.07.2026 | J58: Ålesund: Drive to your accommodation | Q58: 0 | R58: 0 | S58: =+Q58*R58 -> 0 | T58: 0 | U58: =S58*(1-T58) -> 0 | V58: EUR | W58: =IFERROR(VLOOKUP(V58,Curr!$B$2:$C$13,2,FALSE),0) -> 10.8 | X58: =U58*W58 -> 0 | Y58: =Q58 -> 0 | Z58: =+Y58*R58 -> 0 | AA58: EUR | AB58: =IFERROR(VLOOKUP(AA58,Curr!$B$2:$C$13,2,FALSE),0) -> 10.8 | AC58: =+Y58*AB58*R58 -> 0 | AD58: =+AC58-X58 -> 0 | AE58: =IFERROR(AD58/AC58,0) -> 0
C59: Day 11 | D59: Hotel | E59: 07.07.2026 | F59: 10.07.2026 | J59: Ålesund: Check in to your accommodation for a 3 night stay - Hotel Brosundet - 2 x Junior suite - breakfast included | P59: https://app.hotelbeds.com/factsheet/stay/70251?check_in=07-07-2026&check_out=10-07-2026&occupancy=2~0_2~0&packaging=true | Q59: 3072 | R59: 1 | S59: =+Q59*R59 -> 3072 | T59: 0 | U59: =S59*(1-T59) -> 3072 | V59: EUR | W59: =IFERROR(VLOOKUP(V59,Curr!$B$2:$C$13,2,FALSE),0) -> 10.8 | X59: =U59*W59 -> 33177.6 | Y59: =Q59/0.8 -> 3840 | Z59: =+Y59*R59 -> 3840 | AA59: EUR | AB59: =IFERROR(VLOOKUP(AA59,Curr!$B$2:$C$13,2,FALSE),0) -> 10.8 | AC59: =+Y59*AB59*R59 -> 41472 | AD59: =+AC59-X59 -> 8294.4 | AE59: =IFERROR(AD59/AC59,0) -> 0.2
C60: Day 11 | D60: Leisure | E60: 07.07.2026 | J60: Ålesund: Spend time at leisure | Q60: 0 | R60: 0 | S60: =+Q60*R60 -> 0 | T60: 0 | U60: =S60*(1-T60) -> 0 | V60: EUR | W60: =IFERROR(VLOOKUP(V60,Curr!$B$2:$C$13,2,FALSE),0) -> 10.8 | X60: =U60*W60 -> 0 | Y60: =Q60 -> 0 | Z60: =+Y60*R60 -> 0 | AA60: EUR | AB60: =IFERROR(VLOOKUP(AA60,Curr!$B$2:$C$13,2,FALSE),0) -> 10.8 | AC60: =+Y60*AB60*R60 -> 0 | AD60: =+AC60-X60 -> 0 | AE60: =IFERROR(AD60/AC60,0) -> 0
S61: =+Q61*R61 -> 0 | T61: 0 | U61: =S61*(1-T61) -> 0 | V61: EUR | W61: =IFERROR(VLOOKUP(V61,Curr!$B$2:$C$13,2,FALSE),0) -> 10.8 | X61: =U61*W61 -> 0 | Y61: =Q61 -> 0 | Z61: =+Y61*R61 -> 0 | AA61: EUR | AB61: =IFERROR(VLOOKUP(AA61,Curr!$B$2:$C$13,2,FALSE),0) -> 10.8 | AC61: =+Y61*AB61*R61 -> 0 | AD61: =+AC61-X61 -> 0 | AE61: =IFERROR(AD61/AC61,0) -> 0
C62: Day 12 | D62: Drive | E62: 08.07.2026 | J62: Ålesund: Geiranger Road Trip - Drive to Hellesylt, and take the Geiranger Fjord Ferry to Geiranger at 11:00 am. Spend some time at leisuree in Geiranger, before driving back to Ålesund via Sjøholt | P62: https://www.fjordtours.com/no/norge/transport/ferge/geiranger-hellesylt | Q62: 1680 | R62: 1 | S62: =+Q62*R62 -> 1680 | T62: 0.12 | U62: =S62*(1-T62) -> 1478.4 | V62: NOK | W62: =IFERROR(VLOOKUP(V62,Curr!$B$2:$C$13,2,FALSE),0) -> 1 | X62: =U62*W62 -> 1478.4 | Y62: =Q62/11/0.8 -> 190.90909 | Z62: =+Y62*R62 -> 190.90909 | AA62: EUR | AB62: =IFERROR(VLOOKUP(AA62,Curr!$B$2:$C$13,2,FALSE),0) -> 10.8 | AC62: =+Y62*AB62*R62 -> 2061.8182 | AD62: =+AC62-X62 -> 583.41818 | AE62: =IFERROR(AD62/AC62,0) -> 0.28296296
C63: Day 12 | D63: Leisure | E63: 08.07.2026 | J63: Ålesund: Spend time at leisure | Q63: 0 | R63: 0 | S63: =+Q63*R63 -> 0 | T63: 0 | U63: =S63*(1-T63) -> 0 | V63: EUR | W63: =IFERROR(VLOOKUP(V63,Curr!$B$2:$C$13,2,FALSE),0) -> 10.8 | X63: =U63*W63 -> 0 | Y63: =Q63 -> 0 | Z63: =+Y63*R63 -> 0 | AA63: EUR | AB63: =IFERROR(VLOOKUP(AA63,Curr!$B$2:$C$13,2,FALSE),0) -> 10.8 | AC63: =+Y63*AB63*R63 -> 0 | AD63: =+AC63-X63 -> 0 | AE63: =IFERROR(AD63/AC63,0) -> 0
S64: =+Q64*R64 -> 0 | T64: 0 | U64: =S64*(1-T64) -> 0 | V64: EUR | W64: =IFERROR(VLOOKUP(V64,Curr!$B$2:$C$13,2,FALSE),0) -> 10.8 | X64: =U64*W64 -> 0 | Y64: =Q64 -> 0 | Z64: =+Y64*R64 -> 0 | AA64: EUR | AB64: =IFERROR(VLOOKUP(AA64,Curr!$B$2:$C$13,2,FALSE),0) -> 10.8 | AC64: =+Y64*AB64*R64 -> 0 | AD64: =+AC64-X64 -> 0 | AE64: =IFERROR(AD64/AC64,0) -> 0
C65: Day 13 | D65: Drive | E65: 09.07.2026 | J65: Ålesund: Atlantic Road Road Trip - Drive from your accommodation to the Atlantic Road. Head up to Kristiansund and spend some time at leisure. Drive to Molde, and head to Molde Panorama. Drive back to your accommodation in Ålesund | Q65: 0 | R65: 0 | S65: =+Q65*R65 -> 0 | T65: 0 | U65: =S65*(1-T65) -> 0 | V65: EUR | W65: =IFERROR(VLOOKUP(V65,Curr!$B$2:$C$13,2,FALSE),0) -> 10.8 | X65: =U65*W65 -> 0 | Y65: =Q65 -> 0 | Z65: =+Y65*R65 -> 0 | AA65: EUR | AB65: =IFERROR(VLOOKUP(AA65,Curr!$B$2:$C$13,2,FALSE),0) -> 10.8 | AC65: =+Y65*AB65*R65 -> 0 | AD65: =+AC65-X65 -> 0 | AE65: =IFERROR(AD65/AC65,0) -> 0
