Workbook

Sheet Curr
C1: NOK
B2: EUR | C2: 11.3
B3: SEK | C3: 1.02
B4: DKK | C4: 1.5
B5: ISK | C5: 0.075
B6: NOK | C6: 1
B7: USD | C7: 10.6

Sheet Overview
A2: ITIN | B2: Cost
A3: 1201 | B3: ='1201'!Z60 -> 4380
A4: 1202 | B4: ='1202'!Z63 -> 3420
A5: 1203 | B5: ='1203'!Z72 -> 4340
A6: 1204 | B6: ='1204'!Z64 -> 4940
A7: 1205 | B7: ='1205'!Z74 -> 4560
A8: 1206 | B8: ='1206'!Z67 -> 4640
A9: 1207 | B9: ='1207'!Z65 -> 4560
A10: 1208 | B10: ='1208'!Z82 -> 5140
A11: 1209 | B11: ='1209'!Z84 -> 5160
A12: 1210 | B12: ='1210'!Z85 -> 4920
A13: 1211 | B13: ='1211'!Z71 -> 4080
A14: 1212 | B14: ='1212'!Z77 -> 5240
A15: 1213 | B15: ='1213'!Z82 -> 4760
A16: 1214 | B16: ='1214'!Z88 -> 5920
A17: 1215
A18: 1216

Sheet 1201
B1: Places: 3N Rovaniemi - 3N Tromsø
B2: Dates: Winter
B3: Pax: 2
B4: Rooming: Double
B6: ID | C6: Day | D6: Type | E6: From date | F6: To date | G6: From time | H6: To time | I6: Supplier | J6: Travel element | K6: Manual booking? | L6: Status | M6: Comments | N6: Non-refundable | O6: Refundable | P6: URL | Q6: Gross P per unit | R6: Units | S6: Gross P | T6: Supp Comm | U6: Net P | V6: Supp curr | W6: X-rate | X6: Net P NOK | Y6: Sales P per unit | Z6: Price | AA6: Sales curr | AB6: X-rate | AC6: Sales P NOK tot | AD6: GP NOK | AE6: GP % | AF6: VAT25 | AG6: VAT15 | AH6: VAT12 | AI6: VAT0-D | AJ6: VAT0-I
C7: Day 1 | D7: Arrival | J7: Rovaniemi: Welcome to Finland | Q7: 0 | R7: 0 | S7: =+Q7*R7 -> 0 | T7: 0 | U7: =S7*(1-T7) -> 0 | V7: EUR | W7: =IFERROR(VLOOKUP(V7,[1]Curr!$B$2:$C$13,2,FALSE),0) -> 11.3 | X7: =U7*W7 -> 0 | Y7: =Q7 -> 0 | Z7: =+Y7*R7 -> 0 | AA7: EUR | AB7: =IFERROR(VLOOKUP(AA7,Curr!$B$2:$C$13,2,FALSE),0) -> 11.3 | AC7: =+Y7*AB7*R7 -> 0 | AD7: =+AC7-X7 -> 0 | AE7: =IFERROR(AD7/AC7,0) -> 0
C8: Day 1 | D8: Transfer | J8: Rovaniemi: Self transfer to your accommodation | Q8: 0 | R8: 0 | S8: =+Q8*R8 -> 0 | T8: 0 | U8: =S8*(1-T8) -> 0 | V8: EUR | W8: =IFERROR(VLOOKUP(V8,[1]Curr!$B$2:$C$13,2,FALSE),0) -> 11.3 | X8: =U8*W8 -> 0 | Y8: =Q8/0.8 -> 0 | Z8: =+Y8*R8 -> 0 | AA8: EUR | AB8: =IFERROR(VLOOKUP(AA8,Curr!$B$2:$C$13,2,FALSE),0) -> 11.3 | AC8: =+Y8*AB8*R8 -> 0 | AD8: =+AC8-X8 -> 0 | AE8: =IFERROR(AD8/AC8,0) -> 0
C9: Day 1 | D9: Hotel | J9: Rovaniemi: Check in to your accommodation for a 3 night stay - Centrally Located 3/4-star Hotel - Standard Room - Breakfast included | N9: x | Q9: 850 | R9: 1 | S9: =+Q9*R9 -> 850 | T9: 0 | U9: =S9*(1-T9) -> 850 | V9: EUR | W9: =IFERROR(VLOOKUP(V9,[1]Curr!$B$2:$C$13,2,FALSE),0) -> 11.3 | X9: =U9*W9 -> 9605 | Y9: =Q9/0.8 -> 1062.5 | Z9: =+Y9*R9 -> 1062.5 | AA9: EUR | AB9: =IFERROR(VLOOKUP(AA9,Curr!$B$2:$C$13,2,FALSE),0) -> 11.3 | AC9: =+Y9*AB9*R9 -> 12006.25 | AD9: =+AC9-X9 -> 2401.25 | AE9: =IFERROR(AD9/AC9,0) -> 0.2
C10: Day 1 | D10: Leisure | J10: Rovaniemi: Spend time at leisure | Q10: 0 | R10: 0 | S10: =+Q10*R10 -> 0 | T10: 0 | U10: =S10*(1-T10) -> 0 | V10: EUR | W10: =IFERROR(VLOOKUP(V10,[1]Curr!$B$2:$C$13,2,FALSE),0) -> 11.3 | X10: =U10*W10 -> 0 | Y10: =Q10 -> 0 | Z10: =+Y10*R10 -> 0 | AA10: EUR | AB10: =IFERROR(VLOOKUP(AA10,Curr!$B$2:$C$13,2,FALSE),0) -> 11.3 | AC10: =+Y10*AB10*R10 -> 0 | AD10: =+AC10-X10 -> 0 | AE10: =IFERROR(AD10/AC10,0) -> 0
S11: =+Q11*R11 -> 0 | T11: 0 | U11: =S11*(1-T11) -> 0 | V11: EUR | W11: =IFERROR(VLOOKUP(V11,[1]Curr!$B$2:$C$13,2,FALSE),0) -> 11.3 | X11: =U11*W11 -> 0 | Y11: =Q11 -> 0 | Z11: =+Y11*R11 -> 0 | AA11: EUR | AB11: =IFERROR(VLOOKUP(AA11,Curr!$B$2:$C$13,2,FALSE),0) -> 11.3 | AC11: =+Y11*AB11*R11 -> 0 | AD11: =+AC11-X11 -> 0 | AE11: =IFERROR(AD11/AC11,0) -> 0
C12: Day 2 | D12: Activity | J12: Rovaniemi: Arctic Circle Highlights Adventure Day - Time: 08:45 am - 2:45 pm - Meeting point: Arctic Circle Snowmobile Park office - Includes: Pick-up/drop-off in central Rovaniemi, Reindeer Farm visit with sleigh ride (2-3 pers), Reindeer sledge driver’s license reward, Alaskan Husky visit with sleigh ride (4 pers), Approx. 2 hours free time in Santa Claus Village, Winter clothes (overalls, boots and gloves), Traditional salmon soup or vegetarian option | O12: x | P12: https://booknordics.com/finland/western-lapland/rovaniemi/arctic-circle-highlights-family-day-by-minibus | Q12: 188 | R12: 2 | S12: 376 | T12: 0.2 | U12: 300.8 | V12: EUR | W12: 11.3 | X12: 3399.04 | Y12: 188 | Z12: =+Y12*R12 -> 376 | AA12: EUR | AB12: =IFERROR(VLOOKUP(AA12,Curr!$B$2:$C$13,2,FALSE),0) -> 11.3 | AC12: =+Y12*AB12*R12 -> 4248.8 | AD12: =+AC12-X12 -> 849.76 | AE12: =IFERROR(AD12/AC12,0) -> 0.2
C13: Day 2 | D13: Leisure | J13: Rovaniemi: Spend time at leisure | Q13: 0 | R13: 0 | S13: =+Q13*R13 -> 0 | T13: 0 | U13: =S13*(1-T13) -> 0 | V13: EUR | W13: =IFERROR(VLOOKUP(V13,[1]Curr!$B$2:$C$13,2,FALSE),0) -> 11.3 | X13: =U13*W13 -> 0 | Y13: =Q13 -> 0 | Z13: =+Y13*R13 -> 0 | AA13: EUR | AB13: =IFERROR(VLOOKUP(AA13,Curr!$B$2:$C$13,2,FALSE),0) -> 11.3 | AC13: =+Y13*AB13*R13 -> 0 | AD13: =+AC13-X13 -> 0 | AE13: =IFERROR(AD13/AC13,0) -> 0
C14: Day 2 | D14: Activity | J14: Rovaniemi: Northern Lights Unlimited Mileage Photo Tour - Time: 08:00 pm - 01:00 am - Meeting point: Book Lapland Office - Includes: Pick-up/drop-off in central Rovaniemi, Knowledgeable, English-speaking guides, Professional DSLR photography (unlimited), Meteorological observations, Thermal winter clothing, Hot drinks & snacks or cookies | O14: x | P14: https://booknordics.com/finland/western-lapland/rovaniemi/rovaniemi-northern-lights-family-tour-by-bus-with-photos | Q14: 109 | R14: 2 | S14: =+Q14*R14 -> 218 | T14: 0.2 | U14: =S14*(1-T14) -> 174.4 | V14: EUR | W14: =IFERROR(VLOOKUP(V14,[1]Curr!$B$2:$C$13,2,FALSE),0) -> 11.3 | X14: =U14*W14 -> 1970.72 | Y14: =Q14 -> 109 | Z14: =+Y14*R14 -> 218 | AA14: EUR | AB14: =IFERROR(VLOOKUP(AA14,Curr!$B$2:$C$13,2,FALSE),0) -> 11.3 | AC14: =+Y14*AB14*R14 -> 2463.4 | AD14: =+AC14-X14 -> 492.68 | AE14: =IFERROR(AD14/AC14,0) -> 0.2
S15: =+Q15*R15 -> 0 | T15: 0 | U15: =S15*(1-T15) -> 0 | V15: EUR | W15: =IFERROR(VLOOKUP(V15,[1]Curr!$B$2:$C$13,2,FALSE),0) -> 11.3 | X15: =U15*W15 -> 0 | Y15: =Q15 -> 0 | Z15: =+Y15*R15 -> 0 | AA15: EUR | AB15: =IFERROR(VLOOKUP(AA15,Curr!$B$2:$C$13,2,FALSE),0) -> 11.3 | AC15: =+Y15*AB15*R15 -> 0 | AD15: =+AC15-X15 -> 0 | AE15: =IFERROR(AD15/AC15,0) -> 0
C16: Day 3 | D16: Activity | J16: Rovaniemi: Arctic Wildlife Adventure to Ranua Park - Time: 10:00 am - 4:00 pm - Meeting point: Lapland Royal Adventures office - Includes: Pick-up/drop-off in central Rovaniemi, Tickets to Ranua Wildlife Park, Drinks and BBQ sausages by fire | O16: x | P16: https://booknordics.com/finland/western-lapland/rovaniemi/arctic-wildlife-adventure-ranua-wildlife-park-trip | Q16: 109 | R16: 2 | S16: =+Q16*R16 -> 218 | T16: 0.2 | U16: =S16*(1-T16) -> 174.4 | V16: EUR | W16: =IFERROR(VLOOKUP(V16,[1]Curr!$B$2:$C$13,2,FALSE),0) -> 11.3 | X16: =U16*W16 -> 1970.72 | Y16: =Q16 -> 109 | Z16: =+Y16*R16 -> 218 | AA16: EUR | AB16: =IFERROR(VLOOKUP(AA16,Curr!$B$2:$C$13,2,FALSE),0) -> 11.3 | AC16: =+Y16*AB16*R16 -> 2463.4 | AD16: =+AC16-X16 -> 492.68 | AE16: =IFERROR(AD16/AC16,0) -> 0.2
C17: Day 3 | D17: Leisure | J17: Rovaniemi: Spend time at leisure | Q17: 0 | R17: 0 | S17: =+Q17*R17 -> 0 | T17: 0 | U17: =S17*(1-T17) -> 0 | V17: EUR | W17: =IFERROR(VLOOKUP(V17,[1]Curr!$B$2:$C$13,2,FALSE),0) -> 11.3 | X17: =U17*W17 -> 0 | Y17: =Q17 -> 0 | Z17: =+Y17*R17 -> 0 | AA17: EUR | AB17: =IFERROR(VLOOKUP(AA17,Curr!$B$2:$C$13,2,FALSE),0) -> 11.3 | AC17: =+Y17*AB17*R17 -> 0 | AD17: =+AC17-X17 -> 0 | AE17: =IFERROR(AD17/AC17,0) -> 0
C18: Day 3 | D18: Activity | J18: Rovaniemi: Small-Group Aurora Hunt by Minibus - Time: 7:00 pm - 10:00 pm - Meeting point: Lapland Royal Adventures Office - Includes: Pick-up/drop-off from central Rovaniemi, Knowledgeable, English-speaking guide, Dedicated Northern Lights chase by minibus, Cozy blankets, hot drinks and a snack | O18: x | P18: https://booknordics.com/finland/western-lapland/rovaniemi/aurora-quest-by-minibus | Q18: 89 | R18: 2 | S18: 178 | T18: 0.2 | U18: 142.4 | V18: EUR | W18: 11.3 | X18: 1609.12 | Y18: 89 | Z18: =+Y18*R18 -> 178 | AA18: EUR | AB18: =IFERROR(VLOOKUP(AA18,Curr!$B$2:$C$13,2,FALSE),0) -> 11.3 | AC18: =+Y18*AB18*R18 -> 2011.4 | AD18: =+AC18-X18 -> 402.28 | AE18: =IFERROR(AD18/AC18,0) -> 0.2
S19: =+Q19*R19 -> 0 | T19: 0 | U19: =S19*(1-T19) -> 0 | V19: EUR | W19: =IFERROR(VLOOKUP(V19,[1]Curr!$B$2:$C$13,2,FALSE),0) -> 11.3 | X19: =U19*W19 -> 0 | Y19: =Q19 -> 0 | Z19: =+Y19*R19 -> 0 | AA19: EUR | AB19: =IFERROR(VLOOKUP(AA19,Curr!$B$2:$C$13,2,FALSE),0) -> 11.3 | AC19: =+Y19*AB19*R19 -> 0 | AD19: =+AC19-X19 -> 0 | AE19: =IFERROR(AD19/AC19,0) -> 0
C20: Day 4 | D20: Transfer | J20: Rovaniemi: Self transfer to Rovaniemi Bus Station | Q20: 0 | R20: 0 | S20: =+Q20*R20 -> 0 | T20: 0 | U20: =S20*(1-T20) -> 0 | V20: EUR | W20: =IFERROR(VLOOKUP(V20,[1]Curr!$B$2:$C$13,2,FALSE),0) -> 11.3 | X20: =U20*W20 -> 0 | Y20: =Q20 -> 0 | Z20: =+Y20*R20 -> 0 | AA20: EUR | AB20: =IFERROR(VLOOKUP(AA20,Curr!$B$2:$C$13,2,FALSE),0) -> 11.3 | AC20: =+Y20*AB20*R20 -> 0 | AD20: =+AC20-X20 -> 0 | AE20: =IFERROR(AD20/AC20,0) -> 0
C21: Day 4 | D21: Activity | J21: Rovaniemi: Arctic Route Coach Transfer to Tromsø - Time: 11:40 am - 7:30 pm - Includes: Tickets | O21: x | P21: https://bestarctic.com/the-arctic-route/arctic-winter-routes-explore-norway-sweden-and-finland/bus-between-tromso-norway-and-rovaniemi-finland/ | Q21: 1830 | R21: 2 | S21: =+Q21*R21 -> 3660 | T21: 0.2 | U21: =S21*(1-T21) -> 2928 | V21: NOK | W21: =IFERROR(VLOOKUP(V21,[1]Curr!$B$2:$C$13,2,FALSE),0) -> 1 | X21: =U21*W21 -> 2928 | Y21: =Q21/11.3/0.9 -> 179.941 | Z21: =+Y21*R21 -> 359.88201 | AA21: EUR | AB21: =IFERROR(VLOOKUP(AA21,Curr!$B$2:$C$13,2,FALSE),0) -> 11.3 | AC21: =+Y21*AB21*R21 -> 4066.6667 | AD21: =+AC21-X21 -> 1138.6667 | AE21: =IFERROR(AD21/AC21,0) -> 0.28
C22: Day 4 | D22: Transfer | J22: Tromsø: Self transfer to your accommodation | Q22: 0 | R22: 0 | S22: =+Q22*R22 -> 0 | T22: 0 | U22: =S22*(1-T22) -> 0 | V22: EUR | W22: =IFERROR(VLOOKUP(V22,[1]Curr!$B$2:$C$13,2,FALSE),0) -> 11.3 | X22: =U22*W22 -> 0 | Y22: =Q22 -> 0 | Z22: =+Y22*R22 -> 0 | AA22: EUR | AB22: =IFERROR(VLOOKUP(AA22,Curr!$B$2:$C$13,2,FALSE),0) -> 11.3 | AC22: =+Y22*AB22*R22 -> 0 | AD22: =+AC22-X22 -> 0 | AE22: =IFERROR(AD22/AC22,0) -> 0
C23: Day 4 | D23: Hotel | J23: Tromsø: Check in to your accommodation for a 3 night stay - Centrally Located 3/4-star Hotel - Standard Room - Breakfast included | O23: x | Q23: 800 | R23: 1 | S23: =+Q23*R23 -> 800 | T23: 0 | U23: =S23*(1-T23) -> 800 | V23: EUR | W23: =IFERROR(VLOOKUP(V23,[1]Curr!$B$2:$C$13,2,FALSE),0) -> 11.3 | X23: =U23*W23 -> 9040 | Y23: =Q23/0.85 -> 941.17647 | Z23: =+Y23*R23 -> 941.17647 | AA23: EUR | AB23: =IFERROR(VLOOKUP(AA23,Curr!$B$2:$C$13,2,FALSE),0) -> 11.3 | AC23: =+Y23*AB23*R23 -> 10635.294 | AD23: =+AC23-X23 -> 1595.2941 | AE23: =IFERROR(AD23/AC23,0) -> 0.15
C24: Day 4 | D24: Leisure | J24: Tromsø: Spend time at leisure | Q24: 0 | R24: 0 | S24: =+Q24*R24 -> 0 | T24: 0 | U24: =S24*(1-T24) -> 0 | V24: EUR | W24: =IFERROR(VLOOKUP(V24,[1]Curr!$B$2:$C$13,2,FALSE),0) -> 11.3 | X24: =U24*W24 -> 0 | Y24: =Q24 -> 0 | Z24: =+Y24*R24 -> 0 | AA24: EUR | AB24: =IFERROR(VLOOKUP(AA24,Curr!$B$2:$C$13,2,FALSE),0) -> 11.3 | AC24: =+Y24*AB24*R24 -> 0 | AD24: =+AC24-X24 -> 0 | AE24: =IFERROR(AD24/AC24,0) -> 0
S25: =+Q25*R25 -> 0 | T25: 0 | U25: =S25*(1-T25) -> 0 | V25: EUR | W25: =IFERROR(VLOOKUP(V25,[1]Curr!$B$2:$C$13,2,FALSE),0) -> 11.3 | X25: =U25*W25 -> 0 | Y25: =Q25 -> 0 | Z25: =+Y25*R25 -> 0 | AA25: EUR | AB25: =IFERROR(VLOOKUP(AA25,Curr!$B$2:$C$13,2,FALSE),0) -> 11.3 | AC25: =+Y25*AB25*R25 -> 0 | AD25: =+AC25-X25 -> 0 | AE25: =IFERROR(AD25/AC25,0) -> 0
C26: Day 5 | D26: Activity | J26: Tromsø: Reindeer Feeding and Sámi Culture - Time: 09:45 am - 2:30 pm - Meeting point: Radisson Blu Hotel's main entrance (Sjøgata 7) - Includes: Scenic transfers (45 min each way), Knowledgeable English and Norwegian speaking guide, Feeding the herd at our camp, Hot beverages and hot meal (traditional Sámi stew or vegetable/lentil soup), Cultural introduction about Sámi history and daily life, A chance to see the northern lights from our camp, Thermal suit and warm snow boots | O26: x | P26: https://www.tromsolapland.no/activities/reindeer-feeding-and-sami-culture | Q26: 1695 | R26: 2 | S26: =+Q26*R26 -> 3390 | T26: 0.2 | U26: =S26*(1-T26) -> 2712 | V26: NOK | W26: =IFERROR(VLOOKUP(V26,[1]Curr!$B$2:$C$13,2,FALSE),0) -> 1 | X26: =U26*W26 -> 2712 | Y26: =Q26/11.3 -> 150 | Z26: =+Y26*R26 -> 300 | AA26: EUR | AB26: =IFERROR(VLOOKUP(AA26,Curr!$B$2:$C$13,2,FALSE),0) -> 11.3 | AC26: =+Y26*AB26*R26 -> 3390 | AD26: =+AC26-X26 -> 678 | AE26: =IFERROR(AD26/AC26,0) -> 0.2
C27: Day 5 | D27: Leisure | J27: Tromsø: Spend time at leisure | Q27: 0 | R27: 0 | S27: =+Q27*R27 -> 0 | T27: 0 | U27: =S27*(1-T27) -> 0 | V27: EUR | W27: =IFERROR(VLOOKUP(V27,[1]Curr!$B$2:$C$13,2,FALSE),0) -> 11.3 | X27: =U27*W27 -> 0 | Y27: =Q27 -> 0 | Z27: =+Y27*R27 -> 0 | AA27: EUR | AB27: =IFERROR(VLOOKUP(AA27,Curr!$B$2:$C$13,2,FALSE),0) -> 11.3 | AC27: =+Y27*AB27*R27 -> 0 | AD27: =+AC27-X27 -> 0 | AE27: =IFERROR(AD27/AC27,0) -> 0
C28: Day 5 | D28: Activity | J28: Tromsø: Northern Lights Chase with Pro Photographer - Time: 6:00 pm - 12:00 am - Meeting point: Roald Amundsens plass 1A - Includes: Professional, English-speaking Aurora photographer guides, Transportation by comfortable minibus, van or coach, Help with camera settings and Aurora Borealis photography, Hot drinks and cookies | O28: x | P28: https://booknordics.com/norway/northern-norway/tromso-region/aurora-chase-with-professional-photographers | Q28: 120 | R28: 2 | S28: =+Q28*R28 -> 240 | T28: 0.2 | U28: =S28*(1-T28) -> 192 | V28: EUR | W28: =IFERROR(VLOOKUP(V28,[2]Curr!$B$2:$C$13,2,FALSE),0) -> 11.3 | X28: =U28*W28 -> 2169.6 | Y28: =Q28 -> 120 | Z28: =+Y28*R28 -> 240 | AA28: EUR | AB28: =IFERROR(VLOOKUP(AA28,Curr!$B$2:$C$13,2,FALSE),0) -> 11.3 | AC28: =+Y28*AB28*R28 -> 2712 | AD28: =+AC28-X28 -> 542.4 | AE28: =IFERROR(AD28/AC28,0) -> 0.2
S29: =+Q29*R29 -> 0 | T29: 0 | U29: =S29*(1-T29) -> 0 | V29: EUR | W29: =IFERROR(VLOOKUP(V29,[1]Curr!$B$2:$C$13,2,FALSE),0) -> 11.3 | X29: =U29*W29 -> 0 | Y29: =Q29 -> 0 | Z29: =+Y29*R29 -> 0 | AA29: EUR | AB29: =IFERROR(VLOOKUP(AA29,Curr!$B$2:$C$13,2,FALSE),0) -> 11.3 | AC29: =+Y29*AB29*R29 -> 0 | AD29: =+AC29-X29 -> 0 | AE29: =IFERROR(AD29/AC29,0) -> 0
C30: Day 6 | D30: Activity | J30: Tromsø: Photo Tour to Arctic Landscapes and Fjords - Time: 10:00 am - 3:00 pm - Meeting point: Roald Amundsens plass 1A - Includes: Departure from central Tromsø. Drop-off to your hotel, Professional, English-speaking photo guides, Scenic fjord safari by comfortable minivan vehicle, Help with camera settings and nature photography, Usually a small-group experience with 4-8 guests, Soup or expedition food, coffee and waffles/cookies | O30: x | P30: https://booknordics.com/norway/northern-norway/tromso-region/tromso-fjord-photo-tour | Q30: 145 | R30: 2 | S30: =+Q30*R30 -> 290 | T30: 0.2 | U30: =S30*(1-T30) -> 232 | V30: EUR | W30: =IFERROR(VLOOKUP(V30,[1]Curr!$B$2:$C$13,2,FALSE),0) -> 11.3 | X30: =U30*W30 -> 2621.6 | Y30: =Q30 -> 145 | Z30: =+Y30*R30 -> 290 | AA30: EUR | AB30: =IFERROR(VLOOKUP(AA30,Curr!$B$2:$C$13,2,FALSE),0) -> 11.3 | AC30: =+Y30*AB30*R30 -> 3277 | AD30: =+AC30-X30 -> 655.4 | AE30: =IFERROR(AD30/AC30,0) -> 0.2
C31: Day 6 | D31: Leisure | J31: Tromsø: Spend time at leisure | Q31: 0 | R31: 0 | S31: =+Q31*R31 -> 0 | T31: 0 | U31: =S31*(1-T31) -> 0 | V31: EUR | W31: =IFERROR(VLOOKUP(V31,[1]Curr!$B$2:$C$13,2,FALSE),0) -> 11.3 | X31: =U31*W31 -> 0 | Y31: =Q31 -> 0 | Z31: =+Y31*R31 -> 0 | AA31: EUR | AB31: =IFERROR(VLOOKUP(AA31,Curr!$B$2:$C$13,2,FALSE),0) -> 11.3 | AC31: =+Y31*AB31*R31 -> 0 | AD31: =+AC31-X31 -> 0 | AE31: =IFERROR(AD31/AC31,0) -> 0
C32: Day 6 | D32: Activity | J32: Tromsø: Northern Lights Cruise with Silent Electric Ship - Time: 7:00 pm - 10:00 pm - Meeting point: Kaigata 6 - Includes: Departure from central Tromsø, 3-hour fjord cruise, Light meal (soup and bread) and water, English speaking guides, Warm indoor saloons, Free wifi, Toilets | O32: x | P32: https://booknordics.com/norway/northern-norway/tromso-region/northern-lights-cruise-electric-ship | Q32: 105 | R32: 2 | S32: =+Q32*R32 -> 210 | T32: 0.2 | U32: =S32*(1-T32) -> 168 | V32: EUR | W32: =IFERROR(VLOOKUP(V32,[1]Curr!$B$2:$C$13,2,FALSE),0) -> 11.3 | X32: =U32*W32 -> 1898.4 | Y32: =Q32 -> 105 | Z32: =+Y32*R32 -> 210 | AA32: EUR | AB32: =IFERROR(VLOOKUP(AA32,Curr!$B$2:$C$13,2,FALSE),0) -> 11.3 | AC32: =+Y32*AB32*R32 -> 2373 | AD32: =+AC32-X32 -> 474.6 | AE32: =IFERROR(AD32/AC32,0) -> 0.2
S33: =+Q33*R33 -> 0 | T33: 0 | U33: =S33*(1-T33) -> 0 | V33: EUR | W33: =IFERROR(VLOOKUP(V33,[1]Curr!$B$2:$C$13,2,FALSE),0) -> 11.3 | X33: =U33*W33 -> 0 | Y33: =Q33 -> 0 | Z33: =+Y33*R33 -> 0 | AA33: EUR | AB33: =IFERROR(VLOOKUP(AA33,Curr!$B$2:$C$13,2,FALSE),0) -> 11.3 | AC33: =+Y33*AB33*R33 -> 0 | AD33: =+AC33-X33 -> 0 | AE33: =IFERROR(AD33/AC33,0) -> 0
C34: Day 7 | D34: Transfer | J34: Tromsø: Self transfer to Tromsø Airport | Q34: 0 | R34: 0 | S34: =+Q34*R34 -> 0 | T34: 0 | U34: =S34*(1-T34) -> 0 | V34: EUR | W34: =IFERROR(VLOOKUP(V34,[1]Curr!$B$2:$C$13,2,FALSE),0) -> 11.3 | X34: =U34*W34 -> 0 | Y34: =Q34 -> 0 | Z34: =+Y34*R34 -> 0 | AA34: EUR | AB34: =IFERROR(VLOOKUP(AA34,Curr!$B$2:$C$13,2,FALSE),0) -> 11.3 | AC34: =+Y34*AB34*R34 -> 0 | AD34: =+AC34-X34 -> 0 | AE34: =IFERROR(AD34/AC34,0) -> 0
C35: Day 7 | D35: Departure | J35: Tromsø: Departure home | Q35: 0 | R35: 0 | S35: =+Q35*R35 -> 0 | T35: 0 | U35: =S35*(1-T35) -> 0 | V35: EUR | W35: =IFERROR(VLOOKUP(V35,[1]Curr!$B$2:$C$13,2,FALSE),0) -> 11.3 | X35: =U35*W35 -> 0 | Y35: =Q35 -> 0 | Z35: =+Y35*R35 -> 0 | AA35: EUR | AB35: =IFERROR(VLOOKUP(AA35,Curr!$B$2:$C$13,2,FALSE),0) -> 11.3 | AC35: =+Y35*AB35*R35 -> 0 | AD35: =+AC35-X35 -> 0 | AE35: =IFERROR(AD35/AC35,0) -> 0
S36: =+Q36*R36 -> 0 | T36: 0 | U36: =S36*(1-T36) -> 0 | V36: EUR | W36: =IFERROR(VLOOKUP(V36,[1]Curr!$B$2:$C$13,2,FALSE),0) -> 11.3 | X36: =U36*W36 -> 0 | Y36: =Q36 -> 0 | Z36: =+Y36*R36 -> 0 | AA36: EUR | AB36: =IFERROR(VLOOKUP(AA36,Curr!$B$2:$C$13,2,FALSE),0) -> 11.3 | AC36: =+Y36*AB36*R36 -> 0 | AD36: =+AC36-X36 -> 0 | AE36: =IFERROR(AD36/AC36,0) -> 0
S37: =+Q37*R37 -> 0 | T37: 0 | U37: =S37*(1-T37) -> 0 | V37: EUR | W37: =IFERROR(VLOOKUP(V37,[1]Curr!$B$2:$C$13,2,FALSE),0) -> 11.3 | X37: =U37*W37 -> 0 | Y37: =Q37 -> 0 | Z37: =+Y37*R37 -> 0 | AA37: EUR | AB37: =IFERROR(VLOOKUP(AA37,Curr!$B$2:$C$13,2,FALSE),0) -> 11.3 | AC37: =+Y37*AB37*R37 -> 0 | AD37: =+AC37-X37 -> 0 | AE37: =IFERROR(AD37/AC37,0) -> 0
C38: Day 1 | D38: Transfer package | J38: Rovaniemi: Private transfer to your accommodation | Q38: 40 | R38: 0 | S38: =+Q38*R38 -> 0 | T38: 0 | U38: =S38*(1-T38) -> 0 | V38: EUR | W38: =IFERROR(VLOOKUP(V38,[1]Curr!$B$2:$C$13,2,FALSE),0) -> 11.3 | X38: =U38*W38 -> 0 | Y38: =Q38/0.67 -> 59.701493 | Z38: =+Y38*R38 -> 0 | AA38: EUR | AB38: =IFERROR(VLOOKUP(AA38,Curr!$B$2:$C$13,2,FALSE),0) -> 11.3 | AC38: =+Y38*AB38*R38 -> 0 | AD38: =+AC38-X38 -> 0 | AE38: =IFERROR(AD38/AC38,0) -> 0
C39: Day 4 | D39: Transfer package | J39: Rovaniemi: Private transfer to Rovaniemi Bus Station | Q39: 40 | R39: 0 | S39: =+Q39*R39 -> 0 | T39: 0 | U39: =S39*(1-T39) -> 0 | V39: EUR | W39: =IFERROR(VLOOKUP(V39,[1]Curr!$B$2:$C$13,2,FALSE),0) -> 11.3 | X39: =U39*W39 -> 0 | Y39: =Q39/0.67 -> 59.701493 | Z39: =+Y39*R39 -> 0 | AA39: EUR | AB39: =IFERROR(VLOOKUP(AA39,Curr!$B$2:$C$13,2,FALSE),0) -> 11.3 | AC39: =+Y39*AB39*R39 -> 0 | AD39: =+AC39-X39 -> 0 | AE39: =IFERROR(AD39/AC39,0) -> 0
C40: Day 7 | D40: Transfer package | J40: Tromsø: Private transfer to Tromsø Airport | Q40: 900 | R40: 0 | S40: =+Q40*R40 -> 0 | T40: 0 | U40: =S40*(1-T40) -> 0 | V40: NOK | W40: =IFERROR(VLOOKUP(V40,[1]Curr!$B$2:$C$13,2,FALSE),0) -> 1 | X40: =U40*W40 -> 0 | Y40: =Q40/11.3/0.8 -> 99.557522 | Z40: =+Y40*R40 -> 0 | AA40: EUR | AB40: =IFERROR(VLOOKUP(AA40,Curr!$B$2:$C$13,2,FALSE),0) -> 11.3 | AC40: =+Y40*AB40*R40 -> 0 | AD40: =+AC40-X40 -> 0 | AE40: =IFERROR(AD40/AC40,0) -> 0
S41: =+Q41*R41 -> 0 | T41: 0 | U41: =S41*(1-T41) -> 0 | V41: EUR | W41: =IFERROR(VLOOKUP(V41,[1]Curr!$B$2:$C$13,2,FALSE),0) -> 11.3 | X41: =U41*W41 -> 0 | Y41: =Q41 -> 0 | Z41: =+Y41*R41 -> 0 | AA41: EUR | AB41: =IFERROR(VLOOKUP(AA41,Curr!$B$2:$C$13,2,FALSE),0) -> 11.3 | AC41: =+Y41*AB41*R41 -> 0 | AD41: =+AC41-X41 -> 0 | AE41: =IFERROR(AD41/AC41,0) -> 0
S42: =+Q42*R42 -> 0 | T42: 0 | U42: =S42*(1-T42) -> 0 | V42: EUR | W42: =IFERROR(VLOOKUP(V42,[1]Curr!$B$2:$C$13,2,FALSE),0) -> 11.3 | X42: =U42*W42 -> 0 | Y42: =Q42 -> 0 | Z42: =+Y42*R42 -> 0 | AA42: EUR | AB42: =IFERROR(VLOOKUP(AA42,Curr!$B$2:$C$13,2,FALSE),0) -> 11.3 | AC42: =+Y42*AB42*R42 -> 0 | AD42: =+AC42-X42 -> 0 | AE42: =IFERROR(AD42/AC42,0) -> 0
C43: Day 2 | D43: Activity Upgrade | J43: Rovaniemi: Snowmobiling and Sledding Arctic Circle Highlights - Time: 08:45 am - 03:45 pm - Meeting point: Arctic Circle Snowmobile Park office - Includes: Pick-up/drop-off in central Rovaniemi, Knowledgeable, English-speaking guide, 1h snowmobiling on shared snowmobile (2 pers), Reindeer experience with 500m sleigh ride, Alaskan Husky experience with 500m sleigh ride, Approx. 2 hours free time in Santa Claus Village, Winter clothes (overalls, boots and gloves), Other equipment (helmet and balaclava), Salmon soup lunch (vegetarian option available) | O43: x | P43: https://booknordics.com/finland/western-lapland/rovaniemi/family-day-snowmobile-arctic-animals-and-santa-village | Q43: 252 | R43: 0 | S43: =+Q43*R43 -> 0 | T43: 0.2 | U43: =S43*(1-T43) -> 0 | V43: EUR | W43: =IFERROR(VLOOKUP(V43,[1]Curr!$B$2:$C$13,2,FALSE),0) -> 11.3 | X43: =U43*W43 -> 0 | Y43: =Q43 -> 252 | Z43: =+Y43*R43 -> 0 | AA43: EUR | AB43: =IFERROR(VLOOKUP(AA43,Curr!$B$2:$C$13,2,FALSE),0) -> 11.3 | AC43: =+Y43*AB43*R43 -> 0 | AD43: =+AC43-X43 -> 0 | AE43: =IFERROR(AD43/AC43,0) -> 0
C44: Day 3 | D44: Activity upgrade | J44: Rovaniemi: Polar Ice Breaker Cruise - Time: 11:00 am - 7:35 pm - Meeting point: Rovaniemi Tourist Information - Includes: Lunch, transfers, 3-hour Icebreaker Cruise, Guided Icebreaker tour, Onboard Cinema, Frozen Sea Walk, Ice Swimming, Cruise and Swim Certificate | O44: x | P44: https://booknordics.com/finland/western-lapland/rovaniemi/polar-explorer-icebreaker-dancing-queen-party-cruise-and-lunch-with-shuttle-bus-transportation-from-rovaniemi | Q44: 500 | R44: 0 | S44: =+Q44*R44 -> 0 | T44: 0.12 | U44: =S44*(1-T44) -> 0 | V44: EUR | W44: =IFERROR(VLOOKUP(V44,[1]Curr!$B$2:$C$13,2,FALSE),0) -> 11.3 | X44: =U44*W44 -> 0 | Y44: =Q44/0.97 -> 515.46392 | Z44: =+Y44*R44 -> 0 | AA44: EUR | AB44: =IFERROR(VLOOKUP(AA44,Curr!$B$2:$C$13,2,FALSE),0) -> 11.3 | AC44: =+Y44*AB44*R44 -> 0 | AD44: =+AC44-X44 -> 0 | AE44: =IFERROR(AD44/AC44,0) -> 0
C45: Day 3 | D45: Activity upgrade | J45: Rovaniemi: Korouoma Frozen Waterfall + Auttiköngäs - Time: 08:00 am - 3:00 pm - Meeteing point: Hotel pick up - Includes: Tour Guiding / Transportation, Spikes if needed, Lappish BBQ & Hot Beverages, Pick/Drop within 15KM of Rovaniemi City, Goods & services tax | P45: BOKUN | Q45: 159 | R45: 0 | S45: =+Q45*R45 -> 0 | T45: 0.3 | U45: =S45*(1-T45) -> 0 | V45: EUR | W45: =IFERROR(VLOOKUP(V45,[1]Curr!$B$2:$C$13,2,FALSE),0) -> 11.3 | X45: =U45*W45 -> 0 | Y45: =Q45 -> 159 | Z45: =+Y45*R45 -> 0 | AA45: EUR | AB45: =IFERROR(VLOOKUP(AA45,Curr!$B$2:$C$13,2,FALSE),0) -> 11.3 | AC45: =+Y45*AB45*R45 -> 0 | AD45: =+AC45-X45 -> 0 | AE45: =IFERROR(AD45/AC45,0) -> 0
C46: Day 5 | D46: Activity upgrade | J46: Tromsø: Reindeer Sledding, Reindeer Feeding and Sami Culture - Time: 09:45 am - 2:30 pm - Meeting point: Radisson Blu Hotel's main entrance (Sjøgata 7) - Includes: Scenic transfers (45 min each way), Knowledgeable English- and Norwegian-speaking guide, Thermal winter suit, warm boots, Reindeer sledding (approx. 30 min, depending on weather and snow conditions), Feeding the herd on our camp, Hot traditional Sámi meal (bithos) and hot drinks. Vegetarian option available on request, Cultural introduction about Sámi history and daily life | O46: x | P46: https://booknordics.com/norway/northern-norway/tromso-region/reindeer-sledding-reindeer-feeding-and-sami-culture-3 | Q46: 2195 | R46: 0 | S46: =+Q46*R46 -> 0 | T46: 0.2 | U46: =S46*(1-T46) -> 0 | V46: NOK | W46: =IFERROR(VLOOKUP(V46,[1]Curr!$B$2:$C$13,2,FALSE),0) -> 1 | X46: =U46*W46 -> 0 | Y46: =Q46/11.3 -> 194.24779 | Z46: =+Y46*R46 -> 0 | AA46: EUR | AB46: =IFERROR(VLOOKUP(AA46,Curr!$B$2:$C$13,2,FALSE),0) -> 11.3 | AC46: =+Y46*AB46*R46 -> 0 | AD46: =+AC46-X46 -> 0 | AE46: =IFERROR(AD46/AC46,0) -> 0
S47: =+Q47*R47 -> 0 | T47: 0 | U47: =S47*(1-T47) -> 0 | V47: EUR | W47: =IFERROR(VLOOKUP(V47,[1]Curr!$B$2:$C$13,2,FALSE),0) -> 11.3 | X47: =U47*W47 -> 0 | Y47: =Q47 -> 0 | Z47: =+Y47*R47 -> 0 | AA47: EUR | AB47: =IFERROR(VLOOKUP(AA47,Curr!$B$2:$C$13,2,FALSE),0) -> 11.3 | AC47: =+Y47*AB47*R47 -> 0 | AD47: =+AC47-X47 -> 0 | AE47: =IFERROR(AD47/AC47,0) -> 0
S48: =+Q48*R48 -> 0 | T48: 0 | U48: =S48*(1-T48) -> 0 | V48: EUR | W48: =IFERROR(VLOOKUP(V48,[1]Curr!$B$2:$C$13,2,FALSE),0) -> 11.3 | X48: =U48*W48 -> 0 | Y48: =Q48 -> 0 | Z48: =+Y48*R48 -> 0 | AA48: EUR | AB48: =IFERROR(VLOOKUP(AA48,Curr!$B$2:$C$13,2,FALSE),0) -> 11.3 | AC48: =+Y48*AB48*R48 -> 0 | AD48: =+AC48-X48 -> 0 | AE48: =IFERROR(AD48/AC48,0) -> 0
S49: =+Q49*R49 -> 0 | T49: 0 | U49: =S49*(1-T49) -> 0 | V49: EUR | W49: =IFERROR(VLOOKUP(V49,[1]Curr!$B$2:$C$13,2,FALSE),0) -> 11.3 | X49: =U49*W49 -> 0 | Y49: =Q49 -> 0 | Z49: =+Y49*R49 -> 0 | AA49: EUR | AB49: =IFERROR(VLOOKUP(AA49,Curr!$B$2:$C$13,2,FALSE),0) -> 11.3 | AC49: =+Y49*AB49*R49 -> 0 | AD49: =+AC49-X49 -> 0 | AE49: =IFERROR(AD49/AC49,0) -> 0
S50: =+Q50*R50 -> 0 | T50: 0 | U50: =S50*(1-T50) -> 0 | V50: EUR | W50: =IFERROR(VLOOKUP(V50,[1]Curr!$B$2:$C$13,2,FALSE),0) -> 11.3 | X50: =U50*W50 -> 0 | Y50: =Q50 -> 0 | Z50: =+Y50*R50 -> 0 | AA50: EUR | AB50: =IFERROR(VLOOKUP(AA50,Curr!$B$2:$C$13,2,FALSE),0) -> 11.3 | AC50: =+Y50*AB50*R50 -> 0 | AD50: =+AC50-X50 -> 0 | AE50: =IFERROR(AD50/AC50,0) -> 0
S51: =+Q51*R51 -> 0 | T51: 0 | U51: =S51*(1-T51) -> 0 | V51: EUR | W51: =IFERROR(VLOOKUP(V51,[1]Curr!$B$2:$C$13,2,FALSE),0) -> 11.3 | X51: =U51*W51 -> 0 | Y51: =Q51 -> 0 | Z51: =+Y51*R51 -> 0 | AA51: EUR | AB51: =IFERROR(VLOOKUP(AA51,Curr!$B$2:$C$13,2,FALSE),0) -> 11.3 | AC51: =+Y51*AB51*R51 -> 0 | AD51: =+AC51-X51 -> 0 | AE51: =IFERROR(AD51/AC51,0) -> 0
S52: =+Q52*R52 -> 0 | T52: 0 | U52: =S52*(1-T52) -> 0 | V52: EUR | W52: =IFERROR(VLOOKUP(V52,[1]Curr!$B$2:$C$13,2,FALSE),0) -> 11.3 | X52: =U52*W52 -> 0 | Y52: =Q52 -> 0 | Z52: =+Y52*R52 -> 0 | AA52: EUR | AB52: =IFERROR(VLOOKUP(AA52,Curr!$B$2:$C$13,2,FALSE),0) -> 11.3 | AC52: =+Y52*AB52*R52 -> 0 | AD52: =+AC52-X52 -> 0 | AE52: =IFERROR(AD52/AC52,0) -> 0
S53: =+Q53*R53 -> 0 | T53: 0 | U53: =S53*(1-T53) -> 0 | V53: EUR | W53: =IFERROR(VLOOKUP(V53,[1]Curr!$B$2:$C$13,2,FALSE),0) -> 11.3 | X53: =U53*W53 -> 0 | Y53: =Q53 -> 0 | Z53: =+Y53*R53 -> 0 | AA53: EUR | AB53: =IFERROR(VLOOKUP(AA53,Curr!$B$2:$C$13,2,FALSE),0) -> 11.3 | AC53: =+Y53*AB53*R53 -> 0 | AD53: =+AC53-X53 -> 0 | AE53: =IFERROR(AD53/AC53,0) -> 0
S54: =+Q54*R54 -> 0 | T54: 0 | U54: =S54*(1-T54) -> 0 | V54: EUR | W54: =IFERROR(VLOOKUP(V54,[1]Curr!$B$2:$C$13,2,FALSE),0) -> 11.3 | X54: =U54*W54 -> 0 | Y54: =Q54 -> 0 | Z54: =+Y54*R54 -> 0 | AA54: EUR | AB54: =IFERROR(VLOOKUP(AA54,Curr!$B$2:$C$13,2,FALSE),0) -> 11.3 | AC54: =+Y54*AB54*R54 -> 0 | AD54: =+AC54-X54 -> 0 | AE54: =IFERROR(AD54/AC54,0) -> 0
B56: Totals | D56: x | E56: x | F56: x | G56: x | H56: x | I56: x | J56: x | K56: x | L56: x | M56: x | N56: x | O56: x | P56: x | Q56: x | R56: x | S56: x | T56: x | U56: x | V56: x | W56: x | X56: x | Y56: x | Z56: =SUM(Z7:Z54) -> 4393.5585 | AC56: =SUM(AC7:AC54) -> 49647.211 | AD56: =SUM(AD7:AD54) -> 9723.0108 | AE56: =IFERROR(AD56/AC56,0) -> 0.19584203 | AF56: =SUM(AF8:AF55) -> 0 | AG56: =SUM(AG8:AG55) -> 0 | AH56: =SUM(AH8:AH55) -> 0 | AI56: =SUM(AI8:AI55) -> 0 | AJ56: =SUM(AJ8:AJ55) -> 0
Y58: Fixed | Z58: =Z12+Z14+Z16+Z18+Z21+Z26+Z28+Z30+Z32 -> 2389.882
Y59: Variable | Z59: =Z9+Z23 -> 2003.6765
Y60: Total | Z60: 4380
Y61: PP | Z61: =Z60/2 -> 2190
Y64: Shoulder | Z64: =Z60 -> 4380
Y65: High | Z65: =Z64*1.18 -> 5168.4
Y66: X-mas | Z66: =Z64*1.3 -> 5694
Y67: Low | Z67: =Z64*0.85 -> 3723

Sheet 1202
B1: Places: 1N Helsinki - 1N Santa Express - 2N Rovaniemi - 2N Tromsø
B2: Dates: Winter
B3: Pax: 2
B4: Rooming: Double
B6: ID | C6: Day | D6: Type | E6: From date | F6: To date | G6: From time | H6: To time | I6: Supplier | J6: Travel element | K6: Manual booking? | L6: Status | M6: Comments | N6: Non-refundable | O6: Refundable | P6: URL | Q6: Gross P per unit | R6: Units | S6: Gross P | T6: Supp Comm | U6: Net P | V6: Supp curr | W6: X-rate | X6: Net P NOK | Y6: Sales P per unit | Z6: Price | AA6: Sales curr | AB6: X-rate | AC6: Sales P NOK tot | AD6: GP NOK | AE6: GP % | AF6: VAT25 | AG6: VAT15 | AH6: VAT12 | AI6: VAT0-D | AJ6: VAT0-I
C7: Day 1 | D7: Arrival | J7: Helsinki: Welcome to Finland | Q7: 0 | R7: 0 | S7: =+Q7*R7 -> 0 | T7: 0 | U7: =S7*(1-T7) -> 0 | V7: EUR | W7: =IFERROR(VLOOKUP(V7,[1]Curr!$B$2:$C$13,2,FALSE),0) -> 11.3 | X7: =U7*W7 -> 0 | Y7: =Q7 -> 0 | Z7: =+Y7*R7 -> 0 | AA7: EUR | AB7: =IFERROR(VLOOKUP(AA7,Curr!$B$2:$C$13,2,FALSE),0) -> 11.3 | AC7: =+Y7*AB7*R7 -> 0 | AD7: =+AC7-X7 -> 0 | AE7: =IFERROR(AD7/AC7,0) -> 0
C8: Day 1 | D8: Transfer | J8: Helsinki: Self transfer to your accommodation | Q8: 0 | R8: 0 | S8: =+Q8*R8 -> 0 | T8: 0 | U8: =S8*(1-T8) -> 0 | V8: EUR | W8: =IFERROR(VLOOKUP(V8,[1]Curr!$B$2:$C$13,2,FALSE),0) -> 11.3 | X8: =U8*W8 -> 0 | Y8: =Q8/0.8 -> 0 | Z8: =+Y8*R8 -> 0 | AA8: EUR | AB8: =IFERROR(VLOOKUP(AA8,Curr!$B$2:$C$13,2,FALSE),0) -> 11.3 | AC8: =+Y8*AB8*R8 -> 0 | AD8: =+AC8-X8 -> 0 | AE8: =IFERROR(AD8/AC8,0) -> 0
C9: Day 1 | D9: Hotel | J9: Helsinki: Check in to your accommodation for a 1 night stay - Centrally Located 3/4-star Hotel - Standard Room - Breakfast included | Q9: 150 | R9: 1 | S9: =+Q9*R9 -> 150 | T9: 0 | U9: =S9*(1-T9) -> 150 | V9: EUR | W9: =IFERROR(VLOOKUP(V9,[1]Curr!$B$2:$C$13,2,FALSE),0) -> 11.3 | X9: =U9*W9 -> 1695 | Y9: =Q9/0.85 -> 176.47059 | Z9: =+Y9*R9 -> 176.47059 | AA9: EUR | AB9: =IFERROR(VLOOKUP(AA9,Curr!$B$2:$C$13,2,FALSE),0) -> 11.3 | AC9: =+Y9*AB9*R9 -> 1994.1176 | AD9: =+AC9-X9 -> 299.11765 | AE9: =IFERROR(AD9/AC9,0) -> 0.15
C10: Day 1 | D10: Leisure | J10: Helsinki: Spend time at leisure | Q10: 0 | R10: 0 | S10: =+Q10*R10 -> 0 | T10: 0 | U10: =S10*(1-T10) -> 0 | V10: EUR | W10: =IFERROR(VLOOKUP(V10,[1]Curr!$B$2:$C$13,2,FALSE),0) -> 11.3 | X10: =U10*W10 -> 0 | Y10: =Q10 -> 0 | Z10: =+Y10*R10 -> 0 | AA10: EUR | AB10: =IFERROR(VLOOKUP(AA10,Curr!$B$2:$C$13,2,FALSE),0) -> 11.3 | AC10: =+Y10*AB10*R10 -> 0 | AD10: =+AC10-X10 -> 0 | AE10: =IFERROR(AD10/AC10,0) -> 0
S11: =+Q11*R11 -> 0 | T11: 0 | U11: =S11*(1-T11) -> 0 | V11: EUR | W11: =IFERROR(VLOOKUP(V11,[1]Curr!$B$2:$C$13,2,FALSE),0) -> 11.3 | X11: =U11*W11 -> 0 | Y11: =Q11 -> 0 | Z11: =+Y11*R11 -> 0 | AA11: EUR | AB11: =IFERROR(VLOOKUP(AA11,Curr!$B$2:$C$13,2,FALSE),0) -> 11.3 | AC11: =+Y11*AB11*R11 -> 0 | AD11: =+AC11-X11 -> 0 | AE11: =IFERROR(AD11/AC11,0) -> 0
C12: Day 2 | D12: Activity | J12: Helsinki: A Finntastic Walking Tour - Time: 10:30 am / 1:30 pm - 12:45 pm / 3:45 pm - Meeting point: Senate Square (Look for a blue and white umbrella) - End point: Helsinki Central Library Oodi - Notable Sights: Senate Square, Helsinki Cathedral, Kauppatori, Uspenski Cathedral, Esplanadi Park and more - Includes: Professional authorised Helsinki Guide, Liability Insurance | O12: x | P12: https://www.finntastictours.fi/# | Q12: 20 | R12: 2 | S12: =+Q12*R12 -> 40 | T12: 0 | U12: =S12*(1-T12) -> 40 | V12: EUR | W12: 11.3 | X12: =U12*W12 -> 452 | Y12: 35.087719 | Z12: =+Y12*R12 -> 70.175439 | AA12: EUR | AB12: =IFERROR(VLOOKUP(AA12,Curr!$B$2:$C$13,2,FALSE),0) -> 11.3 | AC12: =+Y12*AB12*R12 -> 792.98246 | AD12: =+AC12-X12 -> 340.98246 | AE12: =IFERROR(AD12/AC12,0) -> 0.43
C13: Day 2 | D13: Transfer | J13: Helsinki: Self transfer to Helsinki Central Station | Q13: 0 | R13: 0 | S13: =+Q13*R13 -> 0 | T13: 0 | U13: =S13*(1-T13) -> 0 | V13: EUR | W13: 11.3 | X13: =U13*W13 -> 0 | Y13: 0 | Z13: =+Y13*R13 -> 0 | AA13: EUR | AB13: =IFERROR(VLOOKUP(AA13,Curr!$B$2:$C$13,2,FALSE),0) -> 11.3 | AC13: =+Y13*AB13*R13 -> 0 | AD13: =+AC13-X13 -> 0 | AE13: =IFERROR(AD13/AC13,0) -> 0
C14: Day 2 | D14: Train | J14: Helsinki: Overnight Santa Claus Express Train to Rovaniemi - Time: 11:13 pm - 10:59 am - Includes: Upstairs Sleeper Cabin with Private Bathroom | N14: x | P14: https://www.vr.fi/en/santa-claus-express | Q14: 200 | R14: 1 | S14: =+Q14*R14 -> 200 | T14: 0 | U14: =S14*(1-T14) -> 200 | V14: EUR | W14: 11.3 | X14: =U14*W14 -> 2260 | Y14: =Q14/0.8 -> 250 | Z14: =+Y14*R14 -> 250 | AA14: EUR | AB14: =IFERROR(VLOOKUP(AA14,Curr!$B$2:$C$13,2,FALSE),0) -> 11.3 | AC14: =+Y14*AB14*R14 -> 2825 | AD14: =+AC14-X14 -> 565 | AE14: =IFERROR(AD14/AC14,0) -> 0.2
S15: =+Q15*R15 -> 0 | T15: 0 | U15: =S15*(1-T15) -> 0 | V15: EUR | W15: =IFERROR(VLOOKUP(V15,[1]Curr!$B$2:$C$13,2,FALSE),0) -> 11.3 | X15: =U15*W15 -> 0 | Y15: =Q15 -> 0 | Z15: =+Y15*R15 -> 0 | AA15: EUR | AB15: =IFERROR(VLOOKUP(AA15,Curr!$B$2:$C$13,2,FALSE),0) -> 11.3 | AC15: =+Y15*AB15*R15 -> 0 | AD15: =+AC15-X15 -> 0 | AE15: =IFERROR(AD15/AC15,0) -> 0
C16: Day 3 | D16: Transfer | J16: Rovaniemi: Self transfer to your accommodation | Q16: 0 | R16: 0 | S16: =+Q16*R16 -> 0 | T16: 0 | U16: =S16*(1-T16) -> 0 | V16: EUR | W16: =IFERROR(VLOOKUP(V16,[1]Curr!$B$2:$C$13,2,FALSE),0) -> 11.3 | X16: =U16*W16 -> 0 | Y16: =Q16/0.8 -> 0 | Z16: =+Y16*R16 -> 0 | AA16: EUR | AB16: =IFERROR(VLOOKUP(AA16,Curr!$B$2:$C$13,2,FALSE),0) -> 11.3 | AC16: =+Y16*AB16*R16 -> 0 | AD16: =+AC16-X16 -> 0 | AE16: =IFERROR(AD16/AC16,0) -> 0
C17: Day 3 | D17: Hotel | J17: Rovaniemi: Check in to your accommodation for a 2 night stay - Centrally Located 3/4-star Hotel - Standard Room - Breakfast included | Q17: 600 | R17: 1 | S17: =+Q17*R17 -> 600 | T17: 0 | U17: =S17*(1-T17) -> 600 | V17: EUR | W17: =IFERROR(VLOOKUP(V17,[1]Curr!$B$2:$C$13,2,FALSE),0) -> 11.3 | X17: =U17*W17 -> 6780 | Y17: =Q17/0.85 -> 705.88235 | Z17: =+Y17*R17 -> 705.88235 | AA17: EUR | AB17: =IFERROR(VLOOKUP(AA17,Curr!$B$2:$C$13,2,FALSE),0) -> 11.3 | AC17: =+Y17*AB17*R17 -> 7976.4706 | AD17: =+AC17-X17 -> 1196.4706 | AE17: =IFERROR(AD17/AC17,0) -> 0.15
C18: Day 3 | D18: Leisure | J18: Rovaniemi: Spend time at leisure | Q18: 0 | R18: 0 | S18: =+Q18*R18 -> 0 | T18: 0 | U18: =S18*(1-T18) -> 0 | V18: EUR | W18: =IFERROR(VLOOKUP(V18,[1]Curr!$B$2:$C$13,2,FALSE),0) -> 11.3 | X18: =U18*W18 -> 0 | Y18: =Q18 -> 0 | Z18: =+Y18*R18 -> 0 | AA18: EUR | AB18: =IFERROR(VLOOKUP(AA18,Curr!$B$2:$C$13,2,FALSE),0) -> 11.3 | AC18: =+Y18*AB18*R18 -> 0 | AD18: =+AC18-X18 -> 0 | AE18: =IFERROR(AD18/AC18,0) -> 0
C19: Day 3 | D19: Activity | J19: Rovaniemi: Northern Lights Unlimited Mileage Photo Tour - Time: 08:00 pm - 01:00 am - Meeting point: Book Lapland Office - Includes: Pick-up/drop-off in central Rovaniemi, Knowledgeable, English-speaking guides, Professional DSLR photography (unlimited), Meteorological observations, Thermal winter clothing, Hot drinks & snacks or cookies | O19: x | P19: https://booknordics.com/finland/western-lapland/rovaniemi/rovaniemi-northern-lights-family-tour-by-bus-with-photos | Q19: 109 | R19: 2 | S19: =+Q19*R19 -> 218 | T19: 0.2 | U19: =S19*(1-T19) -> 174.4 | V19: EUR | W19: =IFERROR(VLOOKUP(V19,[1]Curr!$B$2:$C$13,2,FALSE),0) -> 11.3 | X19: =U19*W19 -> 1970.72 | Y19: =Q19 -> 109 | Z19: =+Y19*R19 -> 218 | AA19: EUR | AB19: =IFERROR(VLOOKUP(AA19,Curr!$B$2:$C$13,2,FALSE),0) -> 11.3 | AC19: =+Y19*AB19*R19 -> 2463.4 | AD19: =+AC19-X19 -> 492.68 | AE19: =IFERROR(AD19/AC19,0) -> 0.2
S20: =+Q20*R20 -> 0 | T20: 0 | U20: =S20*(1-T20) -> 0 | V20: EUR | W20: =IFERROR(VLOOKUP(V20,[1]Curr!$B$2:$C$13,2,FALSE),0) -> 11.3 | X20: =U20*W20 -> 0 | Y20: =Q20 -> 0 | Z20: =+Y20*R20 -> 0 | AA20: EUR | AB20: =IFERROR(VLOOKUP(AA20,Curr!$B$2:$C$13,2,FALSE),0) -> 11.3 | AC20: =+Y20*AB20*R20 -> 0 | AD20: =+AC20-X20 -> 0 | AE20: =IFERROR(AD20/AC20,0) -> 0
C21: Day 4 | D21: Activity | J21: Rovaniemi: Arctic Circle Highlights Adventure Day - Time: 08:45 am - 2:45 pm - Meeting point: Arctic Circle Snowmobile Park office - Includes: Pick-up/drop-off in central Rovaniemi, Reindeer Farm visit with sleigh ride (2-3 pers), Reindeer sledge driver’s license reward, Alaskan Husky visit with sleigh ride (4 pers), Approx. 2 hours free time in Santa Claus Village, Winter clothes (overalls, boots and gloves), Traditional salmon soup or vegetarian option | O21: x | P21: https://booknordics.com/finland/western-lapland/rovaniemi/arctic-circle-highlights-family-day-by-minibus | Q21: 188 | R21: 2 | S21: =+Q21*R21 -> 376 | T21: 0.2 | U21: =S21*(1-T21) -> 300.8 | V21: EUR | W21: 11.3 | X21: =U21*W21 -> 3399.04 | Y21: =Q21 -> 188 | Z21: =+Y21*R21 -> 376 | AA21: EUR | AB21: =IFERROR(VLOOKUP(AA21,Curr!$B$2:$C$13,2,FALSE),0) -> 11.3 | AC21: =+Y21*AB21*R21 -> 4248.8 | AD21: =+AC21-X21 -> 849.76 | AE21: =IFERROR(AD21/AC21,0) -> 0.2
C22: Day 4 | D22: Leisure | J22: Rovaniemi: Spend time at leisure | Q22: 0 | R22: 0 | S22: =+Q22*R22 -> 0 | T22: 0 | U22: =S22*(1-T22) -> 0 | V22: EUR | W22: 11.3 | X22: =U22*W22 -> 0 | Y22: =Q22 -> 0 | Z22: =+Y22*R22 -> 0 | AA22: EUR | AB22: =IFERROR(VLOOKUP(AA22,Curr!$B$2:$C$13,2,FALSE),0) -> 11.3 | AC22: =+Y22*AB22*R22 -> 0 | AD22: =+AC22-X22 -> 0 | AE22: =IFERROR(AD22/AC22,0) -> 0
C23: Day 4 | D23: Activity | J23: Rovaniemi: Small-Group Aurora Hunt by Minibus - Time: 7:00 pm - 10:00 pm - Meeting point: Lapland Royal Adventures Office - Includes: Pick-up/drop-off from central Rovaniemi, Knowledgeable, English-speaking guide, Dedicated Northern Lights chase by minibus, Cozy blankets, hot drinks and a snack | O23: x | P23: https://booknordics.com/finland/western-lapland/rovaniemi/aurora-quest-by-minibus | Q23: 89 | R23: 2 | S23: =+Q23*R23 -> 178 | T23: 0.2 | U23: =S23*(1-T23) -> 142.4 | V23: EUR | W23: 11.3 | X23: =U23*W23 -> 1609.12 | Y23: =Q23 -> 89 | Z23: =+Y23*R23 -> 178 | AA23: EUR | AB23: =IFERROR(VLOOKUP(AA23,Curr!$B$2:$C$13,2,FALSE),0) -> 11.3 | AC23: =+Y23*AB23*R23 -> 2011.4 | AD23: =+AC23-X23 -> 402.28 | AE23: =IFERROR(AD23/AC23,0) -> 0.2
S24: =+Q24*R24 -> 0 | T24: 0 | U24: =S24*(1-T24) -> 0 | V24: EUR | W24: =IFERROR(VLOOKUP(V24,[1]Curr!$B$2:$C$13,2,FALSE),0) -> 11.3 | X24: =U24*W24 -> 0 | Y24: =Q24 -> 0 | Z24: =+Y24*R24 -> 0 | AA24: EUR | AB24: =IFERROR(VLOOKUP(AA24,Curr!$B$2:$C$13,2,FALSE),0) -> 11.3 | AC24: =+Y24*AB24*R24 -> 0 | AD24: =+AC24-X24 -> 0 | AE24: =IFERROR(AD24/AC24,0) -> 0
C25: Day 5 | D25: Transfer | J25: Rovaniemi: Self transfer to Rovaniemi Bus Station | Q25: 0 | R25: 0 | S25: =+Q25*R25 -> 0 | T25: 0 | U25: =S25*(1-T25) -> 0 | V25: EUR | W25: =IFERROR(VLOOKUP(V25,[1]Curr!$B$2:$C$13,2,FALSE),0) -> 11.3 | X25: =U25*W25 -> 0 | Y25: =Q25 -> 0 | Z25: =+Y25*R25 -> 0 | AA25: EUR | AB25: =IFERROR(VLOOKUP(AA25,Curr!$B$2:$C$13,2,FALSE),0) -> 11.3 | AC25: =+Y25*AB25*R25 -> 0 | AD25: =+AC25-X25 -> 0 | AE25: =IFERROR(AD25/AC25,0) -> 0
C26: Day 5 | D26: Activity | J26: Rovaniemi: Arctic Route Coach Transfer to Tromsø - Time: 11:40 am - 7:30 pm - Includes: Tickets | O26: x | P26: https://bestarctic.com/the-arctic-route/arctic-winter-routes-explore-norway-sweden-and-finland/bus-between-tromso-norway-and-rovaniemi-finland/ | Q26: 1830 | R26: 2 | S26: =+Q26*R26 -> 3660 | T26: 0.2 | U26: =S26*(1-T26) -> 2928 | V26: NOK | W26: =IFERROR(VLOOKUP(V26,[1]Curr!$B$2:$C$13,2,FALSE),0) -> 1 | X26: =U26*W26 -> 2928 | Y26: =Q26/11.3/0.9 -> 179.941 | Z26: =+Y26*R26 -> 359.88201 | AA26: EUR | AB26: =IFERROR(VLOOKUP(AA26,Curr!$B$2:$C$13,2,FALSE),0) -> 11.3 | AC26: =+Y26*AB26*R26 -> 4066.6667 | AD26: =+AC26-X26 -> 1138.6667 | AE26: =IFERROR(AD26/AC26,0) -> 0.28
C27: Day 5 | D27: Transfer | J27: Tromsø: Self transfer to your accommodation | Q27: 0 | R27: 0 | S27: =+Q27*R27 -> 0 | T27: 0 | U27: =S27*(1-T27) -> 0 | V27: EUR | W27: =IFERROR(VLOOKUP(V27,[1]Curr!$B$2:$C$13,2,FALSE),0) -> 11.3 | X27: =U27*W27 -> 0 | Y27: =Q27 -> 0 | Z27: =+Y27*R27 -> 0 | AA27: EUR | AB27: =IFERROR(VLOOKUP(AA27,Curr!$B$2:$C$13,2,FALSE),0) -> 11.3 | AC27: =+Y27*AB27*R27 -> 0 | AD27: =+AC27-X27 -> 0 | AE27: =IFERROR(AD27/AC27,0) -> 0
C28: Day 5 | D28: Hotel | J28: Tromsø: Check in to your accommodation for a 2 night stay - Centrally Located 3/4-star Hotel - Standard Room - Breakfast included | Q28: 500 | R28: 1 | S28: =+Q28*R28 -> 500 | T28: 0 | U28: =S28*(1-T28) -> 500 | V28: EUR | W28: =IFERROR(VLOOKUP(V28,[1]Curr!$B$2:$C$13,2,FALSE),0) -> 11.3 | X28: =U28*W28 -> 5650 | Y28: =Q28/0.85 -> 588.23529 | Z28: =+Y28*R28 -> 588.23529 | AA28: EUR | AB28: =IFERROR(VLOOKUP(AA28,Curr!$B$2:$C$13,2,FALSE),0) -> 11.3 | AC28: =+Y28*AB28*R28 -> 6647.0588 | AD28: =+AC28-X28 -> 997.05882 | AE28: =IFERROR(AD28/AC28,0) -> 0.15
C29: Day 5 | D29: Leisure | J29: Tromsø: Spend time at leisure | Q29: 0 | R29: 0 | S29: =+Q29*R29 -> 0 | T29: 0 | U29: =S29*(1-T29) -> 0 | V29: EUR | W29: =IFERROR(VLOOKUP(V29,[1]Curr!$B$2:$C$13,2,FALSE),0) -> 11.3 | X29: =U29*W29 -> 0 | Y29: =Q29 -> 0 | Z29: =+Y29*R29 -> 0 | AA29: EUR | AB29: =IFERROR(VLOOKUP(AA29,Curr!$B$2:$C$13,2,FALSE),0) -> 11.3 | AC29: =+Y29*AB29*R29 -> 0 | AD29: =+AC29-X29 -> 0 | AE29: =IFERROR(AD29/AC29,0) -> 0
S30: =+Q30*R30 -> 0 | T30: 0 | U30: =S30*(1-T30) -> 0 | V30: EUR | W30: =IFERROR(VLOOKUP(V30,[1]Curr!$B$2:$C$13,2,FALSE),0) -> 11.3 | X30: =U30*W30 -> 0 | Y30: =Q30 -> 0 | Z30: =+Y30*R30 -> 0 | AA30: EUR | AB30: =IFERROR(VLOOKUP(AA30,Curr!$B$2:$C$13,2,FALSE),0) -> 11.3 | AC30: =+Y30*AB30*R30 -> 0 | AD30: =+AC30-X30 -> 0 | AE30: =IFERROR(AD30/AC30,0) -> 0
C31: Day 6 | D31: Activity | J31: Tromsø: Photo Tour to Arctic Landscapes and Fjords - Time: 10:00 am - 3:00 pm - Meeting point: Roald Amundsens plass 1A - Includes: Departure from central Tromsø. Drop-off to your hotel, Professional, English-speaking photo guides, Scenic fjord safari by comfortable minivan vehicle, Help with camera settings and nature photography, Usually a small-group experience with 4-8 guests, Soup or expedition food, coffee and waffles/cookies | O31: x | P31: https://booknordics.com/norway/northern-norway/tromso-region/tromso-fjord-photo-tour | Q31: 145 | R31: 2 | S31: =+Q31*R31 -> 290 | T31: 0.2 | U31: =S31*(1-T31) -> 232 | V31: EUR | W31: =IFERROR(VLOOKUP(V31,[1]Curr!$B$2:$C$13,2,FALSE),0) -> 11.3 | X31: =U31*W31 -> 2621.6 | Y31: =Q31 -> 145 | Z31: =+Y31*R31 -> 290 | AA31: EUR | AB31: =IFERROR(VLOOKUP(AA31,Curr!$B$2:$C$13,2,FALSE),0) -> 11.3 | AC31: =+Y31*AB31*R31 -> 3277 | AD31: =+AC31-X31 -> 655.4 | AE31: =IFERROR(AD31/AC31,0) -> 0.2
C32: Day 6 | D32: Leisure | J32: Tromsø: Spend time at leisure | Q32: 0 | R32: 0 | S32: =+Q32*R32 -> 0 | T32: 0 | U32: =S32*(1-T32) -> 0 | V32: EUR | W32: =IFERROR(VLOOKUP(V32,[1]Curr!$B$2:$C$13,2,FALSE),0) -> 11.3 | X32: =U32*W32 -> 0 | Y32: =Q32 -> 0 | Z32: =+Y32*R32 -> 0 | AA32: EUR | AB32: =IFERROR(VLOOKUP(AA32,Curr!$B$2:$C$13,2,FALSE),0) -> 11.3 | AC32: =+Y32*AB32*R32 -> 0 | AD32: =+AC32-X32 -> 0 | AE32: =IFERROR(AD32/AC32,0) -> 0
C33: Day 6 | D33: Activity | J33: Tromsø: Northern Lights Cruise with Silent Electric Ship - Time: 7:00 pm - 10:00 pm - Meeting point: Kaigata 6 - Includes: Departure from central Tromsø, 3-hour fjord cruise, Light meal (soup and bread) and water, English speaking guides, Warm indoor saloons, Free wifi, Toilets | O33: x | P33: https://booknordics.com/norway/northern-norway/tromso-region/northern-lights-cruise-electric-ship | Q33: 105 | R33: 2 | S33: =+Q33*R33 -> 210 | T33: 0.2 | U33: =S33*(1-T33) -> 168 | V33: EUR | W33: =IFERROR(VLOOKUP(V33,[1]Curr!$B$2:$C$13,2,FALSE),0) -> 11.3 | X33: =U33*W33 -> 1898.4 | Y33: =Q33 -> 105 | Z33: =+Y33*R33 -> 210 | AA33: EUR | AB33: =IFERROR(VLOOKUP(AA33,Curr!$B$2:$C$13,2,FALSE),0) -> 11.3 | AC33: =+Y33*AB33*R33 -> 2373 | AD33: =+AC33-X33 -> 474.6 | AE33: =IFERROR(AD33/AC33,0) -> 0.2
S34: =+Q34*R34 -> 0 | T34: 0 | U34: =S34*(1-T34) -> 0 | V34: EUR | W34: =IFERROR(VLOOKUP(V34,[1]Curr!$B$2:$C$13,2,FALSE),0) -> 11.3 | X34: =U34*W34 -> 0 | Y34: =Q34 -> 0 | Z34: =+Y34*R34 -> 0 | AA34: EUR | AB34: =IFERROR(VLOOKUP(AA34,Curr!$B$2:$C$13,2,FALSE),0) -> 11.3 | AC34: =+Y34*AB34*R34 -> 0 | AD34: =+AC34-X34 -> 0 | AE34: =IFERROR(AD34/AC34,0) -> 0
C35: Day 7 | D35: Transfer | J35: Tromsø: Self transfer to Tromsø Airport | Q35: 0 | R35: 0 | S35: =+Q35*R35 -> 0 | T35: 0 | U35: =S35*(1-T35) -> 0 | V35: EUR | W35: =IFERROR(VLOOKUP(V35,[1]Curr!$B$2:$C$13,2,FALSE),0) -> 11.3 | X35: =U35*W35 -> 0 | Y35: =Q35 -> 0 | Z35: =+Y35*R35 -> 0 | AA35: EUR | AB35: =IFERROR(VLOOKUP(AA35,Curr!$B$2:$C$13,2,FALSE),0) -> 11.3 | AC35: =+Y35*AB35*R35 -> 0 | AD35: =+AC35-X35 -> 0 | AE35: =IFERROR(AD35/AC35,0) -> 0
C36: Day 7 | D36: Departure | J36: Tromsø: Departure home | Q36: 0 | R36: 0 | S36: =+Q36*R36 -> 0 | T36: 0 | U36: =S36*(1-T36) -> 0 | V36: EUR | W36: =IFERROR(VLOOKUP(V36,[1]Curr!$B$2:$C$13,2,FALSE),0) -> 11.3 | X36: =U36*W36 -> 0 | Y36: =Q36 -> 0 | Z36: =+Y36*R36 -> 0 | AA36: EUR | AB36: =IFERROR(VLOOKUP(AA36,Curr!$B$2:$C$13,2,FALSE),0) -> 11.3 | AC36: =+Y36*AB36*R36 -> 0 | AD36: =+AC36-X36 -> 0 | AE36: =IFERROR(AD36/AC36,0) -> 0
S37: =+Q37*R37 -> 0 | T37: 0 | U37: =S37*(1-T37) -> 0 | V37: EUR | W37: =IFERROR(VLOOKUP(V37,[1]Curr!$B$2:$C$13,2,FALSE),0) -> 11.3 | X37: =U37*W37 -> 0 | Y37: =Q37 -> 0 | Z37: =+Y37*R37 -> 0 | AA37: EUR | AB37: =IFERROR(VLOOKUP(AA37,Curr!$B$2:$C$13,2,FALSE),0) -> 11.3 | AC37: =+Y37*AB37*R37 -> 0 | AD37: =+AC37-X37 -> 0 | AE37: =IFERROR(AD37/AC37,0) -> 0
S38: =+Q38*R38 -> 0 | T38: 0 | U38: =S38*(1-T38) -> 0 | V38: EUR | W38: =IFERROR(VLOOKUP(V38,[1]Curr!$B$2:$C$13,2,FALSE),0) -> 11.3 | X38: =U38*W38 -> 0 | Y38: =Q38 -> 0 | Z38: =+Y38*R38 -> 0 | AA38: EUR | AB38: =IFERROR(VLOOKUP(AA38,Curr!$B$2:$C$13,2,FALSE),0) -> 11.3 | AC38: =+Y38*AB38*R38 -> 0 | AD38: =+AC38-X38 -> 0 | AE38: =IFERROR(AD38/AC38,0) -> 0
C39: Day 1 | D39: Transfer package | J39: Helsinki: Private transfer to your accommodation | Q39: 80 | R39: 0 | S39: =+Q39*R39 -> 0 | T39: 0 | U39: =S39*(1-T39) -> 0 | V39: EUR | W39: =IFERROR(VLOOKUP(V39,[1]Curr!$B$2:$C$13,2,FALSE),0) -> 11.3 | X39: =U39*W39 -> 0 | Y39: =Q39/0.8 -> 100 | Z39: =+Y39*R39 -> 0 | AA39: EUR | AB39: =IFERROR(VLOOKUP(AA39,Curr!$B$2:$C$13,2,FALSE),0) -> 11.3 | AC39: =+Y39*AB39*R39 -> 0 | AD39: =+AC39-X39 -> 0 | AE39: =IFERROR(AD39/AC39,0) -> 0
C40: Day 2 | D40: Transfer package | J40: Helsinki: Private transfer to Helsinki Central Station | Q40: 80 | R40: 0 | S40: =+Q40*R40 -> 0 | T40: 0 | U40: =S40*(1-T40) -> 0 | V40: EUR | W40: =IFERROR(VLOOKUP(V40,[1]Curr!$B$2:$C$13,2,FALSE),0) -> 11.3 | X40: =U40*W40 -> 0 | Y40: =Q40/0.8 -> 100 | Z40: =+Y40*R40 -> 0 | AA40: EUR | AB40: =IFERROR(VLOOKUP(AA40,Curr!$B$2:$C$13,2,FALSE),0) -> 11.3 | AC40: =+Y40*AB40*R40 -> 0 | AD40: =+AC40-X40 -> 0 | AE40: =IFERROR(AD40/AC40,0) -> 0
C41: Day 3 | D41: Transfer package | J41: Rovaniemi: Private transfer to your accommodation | Q41: 40 | R41: 0 | S41: =+Q41*R41 -> 0 | T41: 0 | U41: =S41*(1-T41) -> 0 | V41: EUR | W41: =IFERROR(VLOOKUP(V41,[1]Curr!$B$2:$C$13,2,FALSE),0) -> 11.3 | X41: =U41*W41 -> 0 | Y41: =Q41/0.67 -> 59.701493 | Z41: =+Y41*R41 -> 0 | AA41: EUR | AB41: =IFERROR(VLOOKUP(AA41,Curr!$B$2:$C$13,2,FALSE),0) -> 11.3 | AC41: =+Y41*AB41*R41 -> 0 | AD41: =+AC41-X41 -> 0 | AE41: =IFERROR(AD41/AC41,0) -> 0
C42: Day 5 | D42: Transfer package | J42: Rovaniemi: Private transfer to Rovaniemi Bus Station | Q42: 40 | R42: 0 | S42: =+Q42*R42 -> 0 | T42: 0 | U42: =S42*(1-T42) -> 0 | V42: EUR | W42: =IFERROR(VLOOKUP(V42,[1]Curr!$B$2:$C$13,2,FALSE),0) -> 11.3 | X42: =U42*W42 -> 0 | Y42: =Q42/0.67 -> 59.701493 | Z42: =+Y42*R42 -> 0 | AA42: EUR | AB42: =IFERROR(VLOOKUP(AA42,Curr!$B$2:$C$13,2,FALSE),0) -> 11.3 | AC42: =+Y42*AB42*R42 -> 0 | AD42: =+AC42-X42 -> 0 | AE42: =IFERROR(AD42/AC42,0) -> 0
C43: Day 7 | D43: Transfer package | J43: Tromsø: Private transfer to Tromsø Airport | Q43: 900 | R43: 0 | S43: =+Q43*R43 -> 0 | T43: 0 | U43: =S43*(1-T43) -> 0 | V43: NOK | W43: =IFERROR(VLOOKUP(V43,[1]Curr!$B$2:$C$13,2,FALSE),0) -> 1 | X43: =U43*W43 -> 0 | Y43: =Q43/11.3/0.8 -> 99.557522 | Z43: =+Y43*R43 -> 0 | AA43: EUR | AB43: =IFERROR(VLOOKUP(AA43,Curr!$B$2:$C$13,2,FALSE),0) -> 11.3 | AC43: =+Y43*AB43*R43 -> 0 | AD43: =+AC43-X43 -> 0 | AE43: =IFERROR(AD43/AC43,0) -> 0
S44: =+Q44*R44 -> 0 | T44: 0 | U44: =S44*(1-T44) -> 0 | V44: EUR | W44: =IFERROR(VLOOKUP(V44,[1]Curr!$B$2:$C$13,2,FALSE),0) -> 11.3 | X44: =U44*W44 -> 0 | Y44: =Q44 -> 0 | Z44: =+Y44*R44 -> 0 | AA44: EUR | AB44: =IFERROR(VLOOKUP(AA44,Curr!$B$2:$C$13,2,FALSE),0) -> 11.3 | AC44: =+Y44*AB44*R44 -> 0 | AD44: =+AC44-X44 -> 0 | AE44: =IFERROR(AD44/AC44,0) -> 0
S45: =+Q45*R45 -> 0 | T45: 0 | U45: =S45*(1-T45) -> 0 | V45: EUR | W45: =IFERROR(VLOOKUP(V45,[1]Curr!$B$2:$C$13,2,FALSE),0) -> 11.3 | X45: =U45*W45 -> 0 | Y45: =Q45 -> 0 | Z45: =+Y45*R45 -> 0 | AA45: EUR | AB45: =IFERROR(VLOOKUP(AA45,Curr!$B$2:$C$13,2,FALSE),0) -> 11.3 | AC45: =+Y45*AB45*R45 -> 0 | AD45: =+AC45-X45 -> 0 | AE45: =IFERROR(AD45/AC45,0) -> 0
C46: Day 2 | D46: Activity Upgrade | J46: Helsinki: Excurssion to Tallinn - Self Guided Experience - Departure from Helsinki: 10:30 am - Departure from Tallinn: 7:30 pm - Includes: Helsinki port transfers, Star Class Cruise Ticket | O46: x | P46: https://www.tallink.com/en | Q46: =(40+40)+(50*2) -> 180 | R46: 0 | S46: =+Q46*R46 -> 0 | T46: 0 | U46: =S46*(1-T46) -> 0 | V46: EUR | W46: =IFERROR(VLOOKUP(V46,[1]Curr!$B$2:$C$13,2,FALSE),0) -> 11.3 | X46: =U46*W46 -> 0 | Y46: =Q46/0.8 -> 225 | Z46: =+Y46*R46 -> 0 | AA46: EUR | AB46: =IFERROR(VLOOKUP(AA46,Curr!$B$2:$C$13,2,FALSE),0) -> 11.3 | AC46: =+Y46*AB46*R46 -> 0 | AD46: =+AC46-X46 -> 0 | AE46: =IFERROR(AD46/AC46,0) -> 0
C47: Day 2 | D47: Activity Upgrade | J47: Tallinn: Old Town Guided tour - Time: 1:00 pm - 3:30 pm - Meeting point: under the Town Hall clock - Notable sights: St Nickolas Church, Freedom Square, Alexander Nevsky Cathedral, St Mary's Cathedral, Danish King's Garden and more - Includes: Tour, english guide, Recommendations | O47: x | P47: https://120degrees.club/ | Q47: 25 | R47: 0 | S47: =+Q47*R47 -> 0 | T47: 0 | U47: =S47*(1-T47) -> 0 | V47: EUR | W47: =IFERROR(VLOOKUP(V47,[1]Curr!$B$2:$C$13,2,FALSE),0) -> 11.3 | X47: =U47*W47 -> 0 | Y47: =Q47/0.62 -> 40.322581 | Z47: =+Y47*R47 -> 0 | AA47: EUR | AB47: =IFERROR(VLOOKUP(AA47,Curr!$B$2:$C$13,2,FALSE),0) -> 11.3 | AC47: =+Y47*AB47*R47 -> 0 | AD47: =+AC47-X47 -> 0 | AE47: =IFERROR(AD47/AC47,0) -> 0
C48: Day 4 | D48: Activity Upgrade | J48: Rovaniemi: Snowmobiling and Sledding Arctic Circle Highlights - Time: 08:45 am - 03:45 pm - Meeting point: Arctic Circle Snowmobile Park office - Includes: Pick-up/drop-off in central Rovaniemi, Knowledgeable, English-speaking guide, 1h snowmobiling on shared snowmobile (2 pers), Reindeer experience with 500m sleigh ride, Alaskan Husky experience with 500m sleigh ride, Approx. 2 hours free time in Santa Claus Village, Winter clothes (overalls, boots and gloves), Other equipment (helmet and balaclava), Salmon soup lunch (vegetarian option available) | O48: x | P48: https://booknordics.com/finland/western-lapland/rovaniemi/family-day-snowmobile-arctic-animals-and-santa-village | Q48: 252 | R48: 0 | S48: =+Q48*R48 -> 0 | T48: 0.2 | U48: =S48*(1-T48) -> 0 | V48: EUR | W48: =IFERROR(VLOOKUP(V48,[1]Curr!$B$2:$C$13,2,FALSE),0) -> 11.3 | X48: =U48*W48 -> 0 | Y48: =Q48 -> 252 | Z48: =+Y48*R48 -> 0 | AA48: EUR | AB48: =IFERROR(VLOOKUP(AA48,Curr!$B$2:$C$13,2,FALSE),0) -> 11.3 | AC48: =+Y48*AB48*R48 -> 0 | AD48: =+AC48-X48 -> 0 | AE48: =IFERROR(AD48/AC48,0) -> 0
C49: Day 6 | D49: Activity Upgrade | J49: Tromsø: Reindeer Sledding, Reindeer Feeding and Sami Culture - Time: 09:45 am - 2:30 pm - Meeting point: Radisson Blu Hotel's main entrance (Sjøgata 7) - Includes: Scenic transfers (45 min each way), Knowledgeable English- and Norwegian-speaking guide, Thermal winter suit, warm boots, Reindeer sledding (approx. 30 min, depending on weather and snow conditions), Feeding the herd on our camp, Hot traditional Sámi meal (bithos) and hot drinks. Vegetarian option available on request, Cultural introduction about Sámi history and daily life | O49: x | P49: https://booknordics.com/norway/northern-norway/tromso-region/reindeer-sledding-reindeer-feeding-and-sami-culture-3 | Q49: 2195 | R49: 0 | S49: =+Q49*R49 -> 0 | T49: 0.2 | U49: =S49*(1-T49) -> 0 | V49: NOK | W49: =IFERROR(VLOOKUP(V49,[1]Curr!$B$2:$C$13,2,FALSE),0) -> 1 | X49: =U49*W49 -> 0 | Y49: =Q49/11.3 -> 194.24779 | Z49: =+Y49*R49 -> 0 | AA49: EUR | AB49: =IFERROR(VLOOKUP(AA49,Curr!$B$2:$C$13,2,FALSE),0) -> 11.3 | AC49: =+Y49*AB49*R49 -> 0 | AD49: =+AC49-X49 -> 0 | AE49: =IFERROR(AD49/AC49,0) -> 0
S50: =+Q50*R50 -> 0 | T50: 0 | U50: =S50*(1-T50) -> 0 | V50: EUR | W50: =IFERROR(VLOOKUP(V50,[1]Curr!$B$2:$C$13,2,FALSE),0) -> 11.3 | X50: =U50*W50 -> 0 | Y50: =Q50 -> 0 | Z50: =+Y50*R50 -> 0 | AA50: EUR | AB50: =IFERROR(VLOOKUP(AA50,Curr!$B$2:$C$13,2,FALSE),0) -> 11.3 | AC50: =+Y50*AB50*R50 -> 0 | AD50: =+AC50-X50 -> 0 | AE50: =IFERROR(AD50/AC50,0) -> 0
S51: =+Q51*R51 -> 0 | T51: 0 | U51: =S51*(1-T51) -> 0 | V51: EUR | W51: =IFERROR(VLOOKUP(V51,[1]Curr!$B$2:$C$13,2,FALSE),0) -> 11.3 | X51: =U51*W51 -> 0 | Y51: =Q51 -> 0 | Z51: =+Y51*R51 -> 0 | AA51: EUR | AB51: =IFERROR(VLOOKUP(AA51,Curr!$B$2:$C$13,2,FALSE),0) -> 11.3 | AC51: =+Y51*AB51*R51 -> 0 | AD51: =+AC51-X51 -> 0 | AE51: =IFERROR(AD51/AC51,0) -> 0
S52: =+Q52*R52 -> 0 | T52: 0 | U52: =S52*(1-T52) -> 0 | V52: EUR | W52: =IFERROR(VLOOKUP(V52,[1]Curr!$B$2:$C$13,2,FALSE),0) -> 11.3 | X52: =U52*W52 -> 0 | Y52: =Q52 -> 0 | Z52: =+Y52*R52 -> 0 | AA52: EUR | AB52: =IFERROR(VLOOKUP(AA52,Curr!$B$2:$C$13,2,FALSE),0) -> 11.3 | AC52: =+Y52*AB52*R52 -> 0 | AD52: =+AC52-X52 -> 0 | AE52: =IFERROR(AD52/AC52,0) -> 0
S53: =+Q53*R53 -> 0 | T53: 0 | U53: =S53*(1-T53) -> 0 | V53: EUR | W53: =IFERROR(VLOOKUP(V53,[1]Curr!$B$2:$C$13,2,FALSE),0) -> 11.3 | X53: =U53*W53 -> 0 | Y53: =Q53 -> 0 | Z53: =+Y53*R53 -> 0 | AA53: EUR | AB53: =IFERROR(VLOOKUP(AA53,Curr!$B$2:$C$13,2,FALSE),0) -> 11.3 | AC53: =+Y53*AB53*R53 -> 0 | AD53: =+AC53-X53 -> 0 | AE53: =IFERROR(AD53/AC53,0) -> 0
S54: =+Q54*R54 -> 0 | T54: 0 | U54: =S54*(1-T54) -> 0 | V54: EUR | W54: =IFERROR(VLOOKUP(V54,[1]Curr!$B$2:$C$13,2,FALSE),0) -> 11.3 | X54: =U54*W54 -> 0 | Y54: =Q54 -> 0 | Z54: =+Y54*R54 -> 0 | AA54: EUR | AB54: =IFERROR(VLOOKUP(AA54,Curr!$B$2:$C$13,2,FALSE),0) -> 11.3 | AC54: =+Y54*AB54*R54 -> 0 | AD54: =+AC54-X54 -> 0 | AE54: =IFERROR(AD54/AC54,0) -> 0
S55: =+Q55*R55 -> 0 | T55: 0 | U55: =S55*(1-T55) -> 0 | V55: EUR | W55: =IFERROR(VLOOKUP(V55,[1]Curr!$B$2:$C$13,2,FALSE),0) -> 11.3 | X55: =U55*W55 -> 0 | Y55: =Q55 -> 0 | Z55: =+Y55*R55 -> 0 | AA55: EUR | AB55: =IFERROR(VLOOKUP(AA55,Curr!$B$2:$C$13,2,FALSE),0) -> 11.3 | AC55: =+Y55*AB55*R55 -> 0 | AD55: =+AC55-X55 -> 0 | AE55: =IFERROR(AD55/AC55,0) -> 0
S56: =+Q56*R56 -> 0 | T56: 0 | U56: =S56*(1-T56) -> 0 | V56: EUR | W56: =IFERROR(VLOOKUP(V56,[1]Curr!$B$2:$C$13,2,FALSE),0) -> 11.3 | X56: =U56*W56 -> 0 | Y56: =Q56 -> 0 | Z56: =+Y56*R56 -> 0 | AA56: EUR | AB56: =IFERROR(VLOOKUP(AA56,Curr!$B$2:$C$13,2,FALSE),0) -> 11.3 | AC56: =+Y56*AB56*R56 -> 0 | AD56: =+AC56-X56 -> 0 | AE56: =IFERROR(AD56/AC56,0) -> 0
S57: =+Q57*R57 -> 0 | T57: 0 | U57: =S57*(1-T57) -> 0 | V57: EUR | W57: =IFERROR(VLOOKUP(V57,[1]Curr!$B$2:$C$13,2,FALSE),0) -> 11.3 | X57: =U57*W57 -> 0 | Y57: =Q57 -> 0 | Z57: =+Y57*R57 -> 0 | AA57: EUR | AB57: =IFERROR(VLOOKUP(AA57,Curr!$B$2:$C$13,2,FALSE),0) -> 11.3 | AC57: =+Y57*AB57*R57 -> 0 | AD57: =+AC57-X57 -> 0 | AE57: =IFERROR(AD57/AC57,0) -> 0
B59: Totals | D59: x | E59: x | F59: x | G59: x | H59: x | I59: x | J59: x | K59: x | L59: x | M59: x | N59: x | O59: x | P59: x | Q59: x | R59: x | S59: x | T59: x | U59: x | V59: x | W59: x | X59: x | Y59: x | Z59: =SUM(Z7:Z57) -> 3422.6457 | AC59: =SUM(AC7:AC57) -> 38675.896 | AD59: =SUM(AD7:AD57) -> 7412.0162 | AE59: =IFERROR(AD59/AC59,0) -> 0.19164433 | AF59: =SUM(AF8:AF58) -> 0 | AG59: =SUM(AG8:AG58) -> 0 | AH59: =SUM(AH8:AH58) -> 0 | AI59: =SUM(AI8:AI58) -> 0 | AJ59: =SUM(AJ8:AJ58) -> 0
Y61: Fixed | Z61: =Z12+Z19+Z21+Z23+Z26+Z31+Z33 -> 1702.0574
Y62: Variable | Z62: =Z9+Z14+Z17+Z28 -> 1720.5882
Y63: Total | Z63: 3420
Y64: PP | Z64: =Z63/2 -> 1710
Y67: Shoulder | Z67: =Z63 -> 3420
Y68: High | Z68: =Z67*1.18 -> 4035.6
Y69: X-mas | Z69: =Z67*1.3 -> 4446
Y70: Low | Z70: =Z67*0.85 -> 2907

Sheet 1203
B1: Places: 1N Helsinki - 1N Santa Express - 2N Rovaniemi - 2N Tromsø - 1N Tromsø Igloo
B2: Dates: Winter
B3: Pax: 2
B4: Rooming: Double
B6: ID | C6: Day | D6: Type | E6: From date | F6: To date | G6: From time | H6: To time | I6: Supplier | J6: Travel element | K6: Manual booking? | L6: Status | M6: Comments | N6: Non-refundable | O6: Refundable | P6: URL | Q6: Gross P per unit | R6: Units | S6: Gross P | T6: Supp Comm | U6: Net P | V6: Supp curr | W6: X-rate | X6: Net P NOK | Y6: Sales P per unit | Z6: Price | AA6: Sales curr | AB6: X-rate | AC6: Sales P NOK tot | AD6: GP NOK | AE6: GP % | AF6: VAT25 | AG6: VAT15 | AH6: VAT12 | AI6: VAT0-D | AJ6: VAT0-I
C7: Day 1 | D7: Arrival | J7: Helsinki: Welcome to Finland | Q7: 0 | R7: 0 | S7: =+Q7*R7 -> 0 | T7: 0 | U7: =S7*(1-T7) -> 0 | V7: EUR | W7: =IFERROR(VLOOKUP(V7,[1]Curr!$B$2:$C$13,2,FALSE),0) -> 11.3 | X7: =U7*W7 -> 0 | Y7: =Q7 -> 0 | Z7: =+Y7*R7 -> 0 | AA7: EUR | AB7: =IFERROR(VLOOKUP(AA7,Curr!$B$2:$C$13,2,FALSE),0) -> 11.3 | AC7: =+Y7*AB7*R7 -> 0 | AD7: =+AC7-X7 -> 0 | AE7: =IFERROR(AD7/AC7,0) -> 0
C8: Day 1 | D8: Transfer | J8: Helsinki: Self transfer to your accommodation | Q8: 0 | R8: 0 | S8: =+Q8*R8 -> 0 | T8: 0 | U8: =S8*(1-T8) -> 0 | V8: EUR | W8: =IFERROR(VLOOKUP(V8,[1]Curr!$B$2:$C$13,2,FALSE),0) -> 11.3 | X8: =U8*W8 -> 0 | Y8: =Q8/0.8 -> 0 | Z8: =+Y8*R8 -> 0 | AA8: EUR | AB8: =IFERROR(VLOOKUP(AA8,Curr!$B$2:$C$13,2,FALSE),0) -> 11.3 | AC8: =+Y8*AB8*R8 -> 0 | AD8: =+AC8-X8 -> 0 | AE8: =IFERROR(AD8/AC8,0) -> 0
C9: Day 1 | D9: Hotel | J9: Helsinki: Check in to your accommodation for a 1 night stay - Centrally Located 3/4-star Hotel - Standard Room - Breakfast included | Q9: 150 | R9: 1 | S9: =+Q9*R9 -> 150 | T9: 0 | U9: =S9*(1-T9) -> 150 | V9: EUR | W9: =IFERROR(VLOOKUP(V9,[1]Curr!$B$2:$C$13,2,FALSE),0) -> 11.3 | X9: =U9*W9 -> 1695 | Y9: =Q9/0.85 -> 176.47059 | Z9: =+Y9*R9 -> 176.47059 | AA9: EUR | AB9: =IFERROR(VLOOKUP(AA9,Curr!$B$2:$C$13,2,FALSE),0) -> 11.3 | AC9: =+Y9*AB9*R9 -> 1994.1176 | AD9: =+AC9-X9 -> 299.11765 | AE9: =IFERROR(AD9/AC9,0) -> 0.15
C10: Day 1 | D10: Leisure | J10: Helsinki: Spend time at leisure | Q10: 0 | R10: 0 | S10: =+Q10*R10 -> 0 | T10: 0 | U10: =S10*(1-T10) -> 0 | V10: EUR | W10: =IFERROR(VLOOKUP(V10,[1]Curr!$B$2:$C$13,2,FALSE),0) -> 11.3 | X10: =U10*W10 -> 0 | Y10: =Q10 -> 0 | Z10: =+Y10*R10 -> 0 | AA10: EUR | AB10: =IFERROR(VLOOKUP(AA10,Curr!$B$2:$C$13,2,FALSE),0) -> 11.3 | AC10: =+Y10*AB10*R10 -> 0 | AD10: =+AC10-X10 -> 0 | AE10: =IFERROR(AD10/AC10,0) -> 0
S11: =+Q11*R11 -> 0 | T11: 0 | U11: =S11*(1-T11) -> 0 | V11: EUR | W11: =IFERROR(VLOOKUP(V11,[1]Curr!$B$2:$C$13,2,FALSE),0) -> 11.3 | X11: =U11*W11 -> 0 | Y11: =Q11 -> 0 | Z11: =+Y11*R11 -> 0 | AA11: EUR | AB11: =IFERROR(VLOOKUP(AA11,Curr!$B$2:$C$13,2,FALSE),0) -> 11.3 | AC11: =+Y11*AB11*R11 -> 0 | AD11: =+AC11-X11 -> 0 | AE11: =IFERROR(AD11/AC11,0) -> 0
C12: Day 2 | D12: Activity | J12: Helsinki: A Finntastic Walking Tour - Time: 10:30 am / 1:30 pm - 12:45 pm / 3:45 pm - Meeting point: Senate Square (Look for a blue and white umbrella) - End point: Helsinki Central Library Oodi - Notable Sights: Senate Square, Helsinki Cathedral, Kauppatori, Uspenski Cathedral, Esplanadi Park and more - Includes: Professional authorised Helsinki Guide, Liability Insurance | O12: x | P12: https://www.finntastictours.fi/# | Q12: 20 | R12: 2 | S12: =+Q12*R12 -> 40 | T12: 0 | U12: =S12*(1-T12) -> 40 | V12: EUR | W12: 11.3 | X12: =U12*W12 -> 452 | Y12: 35.087719 | Z12: =+Y12*R12 -> 70.175439 | AA12: EUR | AB12: =IFERROR(VLOOKUP(AA12,Curr!$B$2:$C$13,2,FALSE),0) -> 11.3 | AC12: =+Y12*AB12*R12 -> 792.98246 | AD12: =+AC12-X12 -> 340.98246 | AE12: =IFERROR(AD12/AC12,0) -> 0.43
C13: Day 2 | D13: Transfer | J13: Helsinki: Self transfer to Helsinki Central Station | Q13: 0 | R13: 0 | S13: =+Q13*R13 -> 0 | T13: 0 | U13: =S13*(1-T13) -> 0 | V13: EUR | W13: 11.3 | X13: =U13*W13 -> 0 | Y13: 0 | Z13: =+Y13*R13 -> 0 | AA13: EUR | AB13: =IFERROR(VLOOKUP(AA13,Curr!$B$2:$C$13,2,FALSE),0) -> 11.3 | AC13: =+Y13*AB13*R13 -> 0 | AD13: =+AC13-X13 -> 0 | AE13: =IFERROR(AD13/AC13,0) -> 0
C14: Day 2 | D14: Train | J14: Helsinki: Overnight Santa Claus Express Train to Rovaniemi - Time: 11:13 pm - 10:59 am - Includes: Upstairs Sleeper Cabin with Private Bathroom | N14: x | P14: https://www.vr.fi/en/santa-claus-express | Q14: 200 | R14: 1 | S14: =+Q14*R14 -> 200 | T14: 0 | U14: =S14*(1-T14) -> 200 | V14: EUR | W14: 11.3 | X14: =U14*W14 -> 2260 | Y14: =Q14/0.8 -> 250 | Z14: =+Y14*R14 -> 250 | AA14: EUR | AB14: =IFERROR(VLOOKUP(AA14,Curr!$B$2:$C$13,2,FALSE),0) -> 11.3 | AC14: =+Y14*AB14*R14 -> 2825 | AD14: =+AC14-X14 -> 565 | AE14: =IFERROR(AD14/AC14,0) -> 0.2
S15: =+Q15*R15 -> 0 | T15: 0 | U15: =S15*(1-T15) -> 0 | V15: EUR | W15: =IFERROR(VLOOKUP(V15,[1]Curr!$B$2:$C$13,2,FALSE),0) -> 11.3 | X15: =U15*W15 -> 0 | Y15: =Q15 -> 0 | Z15: =+Y15*R15 -> 0 | AA15: EUR | AB15: =IFERROR(VLOOKUP(AA15,Curr!$B$2:$C$13,2,FALSE),0) -> 11.3 | AC15: =+Y15*AB15*R15 -> 0 | AD15: =+AC15-X15 -> 0 | AE15: =IFERROR(AD15/AC15,0) -> 0
C16: Day 3 | D16: Transfer | J16: Rovaniemi: Self transfer to your accommodation | Q16: 0 | R16: 0 | S16: =+Q16*R16 -> 0 | T16: 0 | U16: =S16*(1-T16) -> 0 | V16: EUR | W16: =IFERROR(VLOOKUP(V16,[1]Curr!$B$2:$C$13,2,FALSE),0) -> 11.3 | X16: =U16*W16 -> 0 | Y16: =Q16/0.8 -> 0 | Z16: =+Y16*R16 -> 0 | AA16: EUR | AB16: =IFERROR(VLOOKUP(AA16,Curr!$B$2:$C$13,2,FALSE),0) -> 11.3 | AC16: =+Y16*AB16*R16 -> 0 | AD16: =+AC16-X16 -> 0 | AE16: =IFERROR(AD16/AC16,0) -> 0
C17: Day 3 | D17: Hotel | J17: Rovaniemi: Check in to your accommodation for a 2 night stay - Centrally Located 3/4-star Hotel - Standard Room - Breakfast included | Q17: 600 | R17: 1 | S17: =+Q17*R17 -> 600 | T17: 0 | U17: =S17*(1-T17) -> 600 | V17: EUR | W17: =IFERROR(VLOOKUP(V17,[1]Curr!$B$2:$C$13,2,FALSE),0) -> 11.3 | X17: =U17*W17 -> 6780 | Y17: =Q17/0.85 -> 705.88235 | Z17: =+Y17*R17 -> 705.88235 | AA17: EUR | AB17: =IFERROR(VLOOKUP(AA17,Curr!$B$2:$C$13,2,FALSE),0) -> 11.3 | AC17: =+Y17*AB17*R17 -> 7976.4706 | AD17: =+AC17-X17 -> 1196.4706 | AE17: =IFERROR(AD17/AC17,0) -> 0.15
C18: Day 3 | D18: Leisure | J18: Rovaniemi: Spend time at leisure | Q18: 0 | R18: 0 | S18: =+Q18*R18 -> 0 | T18: 0 | U18: =S18*(1-T18) -> 0 | V18: EUR | W18: =IFERROR(VLOOKUP(V18,[1]Curr!$B$2:$C$13,2,FALSE),0) -> 11.3 | X18: =U18*W18 -> 0 | Y18: =Q18 -> 0 | Z18: =+Y18*R18 -> 0 | AA18: EUR | AB18: =IFERROR(VLOOKUP(AA18,Curr!$B$2:$C$13,2,FALSE),0) -> 11.3 | AC18: =+Y18*AB18*R18 -> 0 | AD18: =+AC18-X18 -> 0 | AE18: =IFERROR(AD18/AC18,0) -> 0
C19: Day 3 | D19: Activity | J19: Rovaniemi: Northern Lights Unlimited Mileage Photo Tour - Time: 08:00 pm - 01:00 am - Meeting point: Book Lapland Office - Includes: Pick-up/drop-off in central Rovaniemi, Knowledgeable, English-speaking guides, Professional DSLR photography (unlimited), Meteorological observations, Thermal winter clothing, Hot drinks & snacks or cookies | O19: x | P19: https://booknordics.com/finland/western-lapland/rovaniemi/rovaniemi-northern-lights-family-tour-by-bus-with-photos | Q19: 109 | R19: 2 | S19: =+Q19*R19 -> 218 | T19: 0.2 | U19: =S19*(1-T19) -> 174.4 | V19: EUR | W19: =IFERROR(VLOOKUP(V19,[1]Curr!$B$2:$C$13,2,FALSE),0) -> 11.3 | X19: =U19*W19 -> 1970.72 | Y19: =Q19 -> 109 | Z19: =+Y19*R19 -> 218 | AA19: EUR | AB19: =IFERROR(VLOOKUP(AA19,Curr!$B$2:$C$13,2,FALSE),0) -> 11.3 | AC19: =+Y19*AB19*R19 -> 2463.4 | AD19: =+AC19-X19 -> 492.68 | AE19: =IFERROR(AD19/AC19,0) -> 0.2
S20: =+Q20*R20 -> 0 | T20: 0 | U20: =S20*(1-T20) -> 0 | V20: EUR | W20: =IFERROR(VLOOKUP(V20,[1]Curr!$B$2:$C$13,2,FALSE),0) -> 11.3 | X20: =U20*W20 -> 0 | Y20: =Q20 -> 0 | Z20: =+Y20*R20 -> 0 | AA20: EUR | AB20: =IFERROR(VLOOKUP(AA20,Curr!$B$2:$C$13,2,FALSE),0) -> 11.3 | AC20: =+Y20*AB20*R20 -> 0 | AD20: =+AC20-X20 -> 0 | AE20: =IFERROR(AD20/AC20,0) -> 0
C21: Day 4 | D21: Activity | J21: Rovaniemi: Arctic Circle Highlights Adventure Day - Time: 08:45 am - 2:45 pm - Meeting point: Arctic Circle Snowmobile Park office - Includes: Pick-up/drop-off in central Rovaniemi, Reindeer Farm visit with sleigh ride (2-3 pers), Reindeer sledge driver’s license reward, Alaskan Husky visit with sleigh ride (4 pers), Approx. 2 hours free time in Santa Claus Village, Winter clothes (overalls, boots and gloves), Traditional salmon soup or vegetarian option | O21: x | P21: https://booknordics.com/finland/western-lapland/rovaniemi/arctic-circle-highlights-family-day-by-minibus | Q21: 188 | R21: 2 | S21: =+Q21*R21 -> 376 | T21: 0.2 | U21: =S21*(1-T21) -> 300.8 | V21: EUR | W21: 11.3 | X21: =U21*W21 -> 3399.04 | Y21: 188 | Z21: =+Y21*R21 -> 376 | AA21: EUR | AB21: =IFERROR(VLOOKUP(AA21,Curr!$B$2:$C$13,2,FALSE),0) -> 11.3 | AC21: =+Y21*AB21*R21 -> 4248.8 | AD21: =+AC21-X21 -> 849.76 | AE21: =IFERROR(AD21/AC21,0) -> 0.2
C22: Day 4 | D22: Leisure | J22: Rovaniemi: Spend time at leisure | Q22: 0 | R22: 0 | S22: =+Q22*R22 -> 0 | T22: 0 | U22: =S22*(1-T22) -> 0 | V22: EUR | W22: 11.3 | X22: =U22*W22 -> 0 | Y22: 0 | Z22: =+Y22*R22 -> 0 | AA22: EUR | AB22: =IFERROR(VLOOKUP(AA22,Curr!$B$2:$C$13,2,FALSE),0) -> 11.3 | AC22: =+Y22*AB22*R22 -> 0 | AD22: =+AC22-X22 -> 0 | AE22: =IFERROR(AD22/AC22,0) -> 0
C23: Day 4 | D23: Activity | J23: Rovaniemi: Small-Group Aurora Hunt by Minibus - Time: 7:00 pm - 10:00 pm - Meeting point: Lapland Royal Adventures Office - Includes: Pick-up/drop-off from central Rovaniemi, Knowledgeable, English-speaking guide, Dedicated Northern Lights chase by minibus, Cozy blankets, hot drinks and a snack | O23: x | P23: https://booknordics.com/finland/western-lapland/rovaniemi/aurora-quest-by-minibus | Q23: 89 | R23: 2 | S23: =+Q23*R23 -> 178 | T23: 0.2 | U23: =S23*(1-T23) -> 142.4 | V23: EUR | W23: 11.3 | X23: =U23*W23 -> 1609.12 | Y23: 89 | Z23: =+Y23*R23 -> 178 | AA23: EUR | AB23: =IFERROR(VLOOKUP(AA23,Curr!$B$2:$C$13,2,FALSE),0) -> 11.3 | AC23: =+Y23*AB23*R23 -> 2011.4 | AD23: =+AC23-X23 -> 402.28 | AE23: =IFERROR(AD23/AC23,0) -> 0.2
S24: =+Q24*R24 -> 0 | T24: 0 | U24: =S24*(1-T24) -> 0 | V24: EUR | W24: =IFERROR(VLOOKUP(V24,[1]Curr!$B$2:$C$13,2,FALSE),0) -> 11.3 | X24: =U24*W24 -> 0 | Y24: =Q24 -> 0 | Z24: =+Y24*R24 -> 0 | AA24: EUR | AB24: =IFERROR(VLOOKUP(AA24,Curr!$B$2:$C$13,2,FALSE),0) -> 11.3 | AC24: =+Y24*AB24*R24 -> 0 | AD24: =+AC24-X24 -> 0 | AE24: =IFERROR(AD24/AC24,0) -> 0
C25: Day 5 | D25: Transfer | J25: Rovaniemi: Self transfer to Rovaniemi Bus Station | Q25: 0 | R25: 0 | S25: =+Q25*R25 -> 0 | T25: 0 | U25: =S25*(1-T25) -> 0 | V25: EUR | W25: =IFERROR(VLOOKUP(V25,[1]Curr!$B$2:$C$13,2,FALSE),0) -> 11.3 | X25: =U25*W25 -> 0 | Y25: =Q25 -> 0 | Z25: =+Y25*R25 -> 0 | AA25: EUR | AB25: =IFERROR(VLOOKUP(AA25,Curr!$B$2:$C$13,2,FALSE),0) -> 11.3 | AC25: =+Y25*AB25*R25 -> 0 | AD25: =+AC25-X25 -> 0 | AE25: =IFERROR(AD25/AC25,0) -> 0
C26: Day 5 | D26: Activity | J26: Rovaniemi: Arctic Route Coach Transfer to Tromsø - Time: 11:40 am - 7:30 pm - Includes: Tickets | O26: x | P26: https://bestarctic.com/the-arctic-route/arctic-winter-routes-explore-norway-sweden-and-finland/bus-between-tromso-norway-and-rovaniemi-finland/ | Q26: 1830 | R26: 2 | S26: =+Q26*R26 -> 3660 | T26: 0.2 | U26: =S26*(1-T26) -> 2928 | V26: NOK | W26: =IFERROR(VLOOKUP(V26,[1]Curr!$B$2:$C$13,2,FALSE),0) -> 1 | X26: =U26*W26 -> 2928 | Y26: =Q26/11.3/0.9 -> 179.941 | Z26: =+Y26*R26 -> 359.88201 | AA26: EUR | AB26: =IFERROR(VLOOKUP(AA26,Curr!$B$2:$C$13,2,FALSE),0) -> 11.3 | AC26: =+Y26*AB26*R26 -> 4066.6667 | AD26: =+AC26-X26 -> 1138.6667 | AE26: =IFERROR(AD26/AC26,0) -> 0.28
C27: Day 5 | D27: Transfer | J27: Tromsø: Self transfer to your accommodation | Q27: 0 | R27: 0 | S27: =+Q27*R27 -> 0 | T27: 0 | U27: =S27*(1-T27) -> 0 | V27: EUR | W27: =IFERROR(VLOOKUP(V27,[1]Curr!$B$2:$C$13,2,FALSE),0) -> 11.3 | X27: =U27*W27 -> 0 | Y27: =Q27 -> 0 | Z27: =+Y27*R27 -> 0 | AA27: EUR | AB27: =IFERROR(VLOOKUP(AA27,Curr!$B$2:$C$13,2,FALSE),0) -> 11.3 | AC27: =+Y27*AB27*R27 -> 0 | AD27: =+AC27-X27 -> 0 | AE27: =IFERROR(AD27/AC27,0) -> 0
C28: Day 5 | D28: Hotel | J28: Tromsø: Check in to your accommodation for a 2 night stay - Centrally Located 3/4-star Hotel - Standard Room - Breakfast included | Q28: 500 | R28: 1 | S28: =+Q28*R28 -> 500 | T28: 0 | U28: =S28*(1-T28) -> 500 | V28: EUR | W28: =IFERROR(VLOOKUP(V28,[1]Curr!$B$2:$C$13,2,FALSE),0) -> 11.3 | X28: =U28*W28 -> 5650 | Y28: =Q28/0.85 -> 588.23529 | Z28: =+Y28*R28 -> 588.23529 | AA28: EUR | AB28: =IFERROR(VLOOKUP(AA28,Curr!$B$2:$C$13,2,FALSE),0) -> 11.3 | AC28: =+Y28*AB28*R28 -> 6647.0588 | AD28: =+AC28-X28 -> 997.05882 | AE28: =IFERROR(AD28/AC28,0) -> 0.15
C29: Day 5 | D29: Leisure | J29: Tromsø: Spend time at leisure | Q29: 0 | R29: 0 | S29: =+Q29*R29 -> 0 | T29: 0 | U29: =S29*(1-T29) -> 0 | V29: EUR | W29: =IFERROR(VLOOKUP(V29,[1]Curr!$B$2:$C$13,2,FALSE),0) -> 11.3 | X29: =U29*W29 -> 0 | Y29: =Q29 -> 0 | Z29: =+Y29*R29 -> 0 | AA29: EUR | AB29: =IFERROR(VLOOKUP(AA29,Curr!$B$2:$C$13,2,FALSE),0) -> 11.3 | AC29: =+Y29*AB29*R29 -> 0 | AD29: =+AC29-X29 -> 0 | AE29: =IFERROR(AD29/AC29,0) -> 0
S30: =+Q30*R30 -> 0 | T30: 0 | U30: =S30*(1-T30) -> 0 | V30: EUR | W30: =IFERROR(VLOOKUP(V30,[1]Curr!$B$2:$C$13,2,FALSE),0) -> 11.3 | X30: =U30*W30 -> 0 | Y30: =Q30 -> 0 | Z30: =+Y30*R30 -> 0 | AA30: EUR | AB30: =IFERROR(VLOOKUP(AA30,Curr!$B$2:$C$13,2,FALSE),0) -> 11.3 | AC30: =+Y30*AB30*R30 -> 0 | AD30: =+AC30-X30 -> 0 | AE30: =IFERROR(AD30/AC30,0) -> 0
C31: Day 6 | D31: Activity | J31: Tromsø: Photo Tour to Arctic Landscapes and Fjords - Time: 10:00 am - 3:00 pm - Meeting point: Roald Amundsens plass 1A - Includes: Departure from central Tromsø. Drop-off to your hotel, Professional, English-speaking photo guides, Scenic fjord safari by comfortable minivan vehicle, Help with camera settings and nature photography, Usually a small-group experience with 4-8 guests, Soup or expedition food, coffee and waffles/cookies | O31: x | P31: https://booknordics.com/norway/northern-norway/tromso-region/tromso-fjord-photo-tour | Q31: 145 | R31: 2 | S31: =+Q31*R31 -> 290 | T31: 0.2 | U31: =S31*(1-T31) -> 232 | V31: EUR | W31: =IFERROR(VLOOKUP(V31,[1]Curr!$B$2:$C$13,2,FALSE),0) -> 11.3 | X31: =U31*W31 -> 2621.6 | Y31: =Q31 -> 145 | Z31: =+Y31*R31 -> 290 | AA31: EUR | AB31: =IFERROR(VLOOKUP(AA31,Curr!$B$2:$C$13,2,FALSE),0) -> 11.3 | AC31: =+Y31*AB31*R31 -> 3277 | AD31: =+AC31-X31 -> 655.4 | AE31: =IFERROR(AD31/AC31,0) -> 0.2
C32: Day 6 | D32: Leisure | J32: Tromsø: Spend time at leisure | Q32: 0 | R32: 0 | S32: =+Q32*R32 -> 0 | T32: 0 | U32: =S32*(1-T32) -> 0 | V32: EUR | W32: =IFERROR(VLOOKUP(V32,[1]Curr!$B$2:$C$13,2,FALSE),0) -> 11.3 | X32: =U32*W32 -> 0 | Y32: =Q32 -> 0 | Z32: =+Y32*R32 -> 0 | AA32: EUR | AB32: =IFERROR(VLOOKUP(AA32,Curr!$B$2:$C$13,2,FALSE),0) -> 11.3 | AC32: =+Y32*AB32*R32 -> 0 | AD32: =+AC32-X32 -> 0 | AE32: =IFERROR(AD32/AC32,0) -> 0
C33: Day 6 | D33: Activity | J33: Tromsø: Northern Lights Cruise with Silent Electric Ship - Time: 7:00 pm - 10:00 pm - Meeting point: Kaigata 6 - Includes: Departure from central Tromsø, 3-hour fjord cruise, Light meal (soup and bread) and water, English speaking guides, Warm indoor saloons, Free wifi, Toilets | O33: x | P33: https://booknordics.com/norway/northern-norway/tromso-region/northern-lights-cruise-electric-ship | Q33: 105 | R33: 2 | S33: =+Q33*R33 -> 210 | T33: 0.2 | U33: =S33*(1-T33) -> 168 | V33: EUR | W33: =IFERROR(VLOOKUP(V33,[1]Curr!$B$2:$C$13,2,FALSE),0) -> 11.3 | X33: =U33*W33 -> 1898.4 | Y33: =Q33 -> 105 | Z33: =+Y33*R33 -> 210 | AA33: EUR | AB33: =IFERROR(VLOOKUP(AA33,Curr!$B$2:$C$13,2,FALSE),0) -> 11.3 | AC33: =+Y33*AB33*R33 -> 2373 | AD33: =+AC33-X33 -> 474.6 | AE33: =IFERROR(AD33/AC33,0) -> 0.2
S34: =+Q34*R34 -> 0 | T34: 0 | U34: =S34*(1-T34) -> 0 | V34: EUR | W34: =IFERROR(VLOOKUP(V34,[1]Curr!$B$2:$C$13,2,FALSE),0) -> 11.3 | X34: =U34*W34 -> 0 | Y34: =Q34 -> 0 | Z34: =+Y34*R34 -> 0 | AA34: EUR | AB34: =IFERROR(VLOOKUP(AA34,Curr!$B$2:$C$13,2,FALSE),0) -> 11.3 | AC34: =+Y34*AB34*R34 -> 0 | AD34: =+AC34-X34 -> 0 | AE34: =IFERROR(AD34/AC34,0) -> 0
C35: Day 7 | D35: Transfer | J35: Tromsø: Self transfer to Steampier Adventure Hotel | Q35: 0 | R35: 0 | S35: =+Q35*R35 -> 0 | T35: 0 | U35: =S35*(1-T35) -> 0 | V35: EUR | W35: =IFERROR(VLOOKUP(V35,[1]Curr!$B$2:$C$13,2,FALSE),0) -> 11.3 | X35: =U35*W35 -> 0 | Y35: =Q35 -> 0 | Z35: =+Y35*R35 -> 0 | AA35: EUR | AB35: =IFERROR(VLOOKUP(AA35,Curr!$B$2:$C$13,2,FALSE),0) -> 11.3 | AC35: =+Y35*AB35*R35 -> 0 | AD35: =+AC35-X35 -> 0 | AE35: =IFERROR(AD35/AC35,0) -> 0
C36: Day 7 | D36: Hotel | J36: Steampier: Check in to your accommodation for a 1 night stay - Steampier Adventure Hotel - Aurora Hut - Brekfast included | P36: https://book.steampier.no/accommodation/room-details?channelid=f7a975e2-5254-4955-9e5d-9f61036705ac&roomid=08dd5be4-4d38-4cc8-0015-5d8b242d0000&roomconfig=a2&year=2026&month=2&day=3&staylength=1 | Q36: 3900 | R36: 1 | S36: =+Q36*R36 -> 3900 | T36: 0 | U36: =S36*(1-T36) -> 3900 | V36: NOK | W36: =IFERROR(VLOOKUP(V36,[1]Curr!$B$2:$C$13,2,FALSE),0) -> 1 | X36: =U36*W36 -> 3900 | Y36: =Q36/11.3/0.75 -> 460.17699 | Z36: =+Y36*R36 -> 460.17699 | AA36: EUR | AB36: =IFERROR(VLOOKUP(AA36,Curr!$B$2:$C$13,2,FALSE),0) -> 11.3 | AC36: =+Y36*AB36*R36 -> 5200 | AD36: =+AC36-X36 -> 1300 | AE36: =IFERROR(AD36/AC36,0) -> 0.25
C37: Day 7 | D37: Leisure | J37: Steampier: Spend time at leisure | Q37: 0 | R37: 0 | S37: =+Q37*R37 -> 0 | T37: 0 | U37: =S37*(1-T37) -> 0 | V37: EUR | W37: =IFERROR(VLOOKUP(V37,[1]Curr!$B$2:$C$13,2,FALSE),0) -> 11.3 | X37: =U37*W37 -> 0 | Y37: =Q37 -> 0 | Z37: =+Y37*R37 -> 0 | AA37: EUR | AB37: =IFERROR(VLOOKUP(AA37,Curr!$B$2:$C$13,2,FALSE),0) -> 11.3 | AC37: =+Y37*AB37*R37 -> 0 | AD37: =+AC37-X37 -> 0 | AE37: =IFERROR(AD37/AC37,0) -> 0
C38: Day 7 | D38: Activity | J38: Steampier: Northern Lights Minivan Tour - Time: 6:00 pm - Durration: 6 - 9 hrs - Meeting point: Steampier Reception - Includes: Professional guide & expert photographer, Comfortable minivan transport, Help setting up your camera/phone for your own photos, Hot drinks (coffee, tea, hot chocolate), Warm soup, Bonfire (when conditions allow), Low-resolution professional photos included, Thermal suits & winter boots for warmth | P38: https://book.steampier.no/extras?channelId=f7a975e2-5254-4955-9e5d-9f61036705ac | Q38: 2100 | R38: 2 | S38: =+Q38*R38 -> 4200 | T38: 0 | U38: =S38*(1-T38) -> 4200 | V38: NOK | W38: =IFERROR(VLOOKUP(V38,[1]Curr!$B$2:$C$13,2,FALSE),0) -> 1 | X38: =U38*W38 -> 4200 | Y38: =Q38/11.3/0.8 -> 232.30088 | Z38: =+Y38*R38 -> 464.60177 | AA38: EUR | AB38: =IFERROR(VLOOKUP(AA38,Curr!$B$2:$C$13,2,FALSE),0) -> 11.3 | AC38: =+Y38*AB38*R38 -> 5250 | AD38: =+AC38-X38 -> 1050 | AE38: =IFERROR(AD38/AC38,0) -> 0.2
S39: =+Q39*R39 -> 0 | T39: 0 | U39: =S39*(1-T39) -> 0 | V39: EUR | W39: =IFERROR(VLOOKUP(V39,[1]Curr!$B$2:$C$13,2,FALSE),0) -> 11.3 | X39: =U39*W39 -> 0 | Y39: =Q39 -> 0 | Z39: =+Y39*R39 -> 0 | AA39: EUR | AB39: =IFERROR(VLOOKUP(AA39,Curr!$B$2:$C$13,2,FALSE),0) -> 11.3 | AC39: =+Y39*AB39*R39 -> 0 | AD39: =+AC39-X39 -> 0 | AE39: =IFERROR(AD39/AC39,0) -> 0
C40: Day 8 | D40: Transfer | J40: Tromsø: Self transfer to Tromsø Airport | Q40: 0 | R40: 0 | S40: =+Q40*R40 -> 0 | T40: 0 | U40: =S40*(1-T40) -> 0 | V40: EUR | W40: =IFERROR(VLOOKUP(V40,[1]Curr!$B$2:$C$13,2,FALSE),0) -> 11.3 | X40: =U40*W40 -> 0 | Y40: =Q40 -> 0 | Z40: =+Y40*R40 -> 0 | AA40: EUR | AB40: =IFERROR(VLOOKUP(AA40,Curr!$B$2:$C$13,2,FALSE),0) -> 11.3 | AC40: =+Y40*AB40*R40 -> 0 | AD40: =+AC40-X40 -> 0 | AE40: =IFERROR(AD40/AC40,0) -> 0
C41: Day 8 | D41: Departure | J41: Tromsø: Departure home | Q41: 0 | R41: 0 | S41: =+Q41*R41 -> 0 | T41: 0 | U41: =S41*(1-T41) -> 0 | V41: EUR | W41: =IFERROR(VLOOKUP(V41,[1]Curr!$B$2:$C$13,2,FALSE),0) -> 11.3 | X41: =U41*W41 -> 0 | Y41: =Q41 -> 0 | Z41: =+Y41*R41 -> 0 | AA41: EUR | AB41: =IFERROR(VLOOKUP(AA41,Curr!$B$2:$C$13,2,FALSE),0) -> 11.3 | AC41: =+Y41*AB41*R41 -> 0 | AD41: =+AC41-X41 -> 0 | AE41: =IFERROR(AD41/AC41,0) -> 0
S42: =+Q42*R42 -> 0 | T42: 0 | U42: =S42*(1-T42) -> 0 | V42: EUR | W42: =IFERROR(VLOOKUP(V42,[1]Curr!$B$2:$C$13,2,FALSE),0) -> 11.3 | X42: =U42*W42 -> 0 | Y42: =Q42 -> 0 | Z42: =+Y42*R42 -> 0 | AA42: EUR | AB42: =IFERROR(VLOOKUP(AA42,Curr!$B$2:$C$13,2,FALSE),0) -> 11.3 | AC42: =+Y42*AB42*R42 -> 0 | AD42: =+AC42-X42 -> 0 | AE42: =IFERROR(AD42/AC42,0) -> 0
S43: =+Q43*R43 -> 0 | T43: 0 | U43: =S43*(1-T43) -> 0 | V43: EUR | W43: =IFERROR(VLOOKUP(V43,[1]Curr!$B$2:$C$13,2,FALSE),0) -> 11.3 | X43: =U43*W43 -> 0 | Y43: =Q43 -> 0 | Z43: =+Y43*R43 -> 0 | AA43: EUR | AB43: =IFERROR(VLOOKUP(AA43,Curr!$B$2:$C$13,2,FALSE),0) -> 11.3 | AC43: =+Y43*AB43*R43 -> 0 | AD43: =+AC43-X43 -> 0 | AE43: =IFERROR(AD43/AC43,0) -> 0
C44: Day 1 | D44: Transfer package | J44: Helsinki: Private transfer to your accommodation | Q44: 80 | R44: 0 | S44: =+Q44*R44 -> 0 | T44: 0 | U44: =S44*(1-T44) -> 0 | V44: EUR | W44: =IFERROR(VLOOKUP(V44,[1]Curr!$B$2:$C$13,2,FALSE),0) -> 11.3 | X44: =U44*W44 -> 0 | Y44: =Q44/0.8 -> 100 | Z44: =+Y44*R44 -> 0 | AA44: EUR | AB44: =IFERROR(VLOOKUP(AA44,Curr!$B$2:$C$13,2,FALSE),0) -> 11.3 | AC44: =+Y44*AB44*R44 -> 0 | AD44: =+AC44-X44 -> 0 | AE44: =IFERROR(AD44/AC44,0) -> 0
C45: Day 2 | D45: Transfer package | J45: Helsinki: Private transfer to Helsinki Central Station | Q45: 80 | R45: 0 | S45: =+Q45*R45 -> 0 | T45: 0 | U45: =S45*(1-T45) -> 0 | V45: EUR | W45: =IFERROR(VLOOKUP(V45,[1]Curr!$B$2:$C$13,2,FALSE),0) -> 11.3 | X45: =U45*W45 -> 0 | Y45: =Q45/0.8 -> 100 | Z45: =+Y45*R45 -> 0 | AA45: EUR | AB45: =IFERROR(VLOOKUP(AA45,Curr!$B$2:$C$13,2,FALSE),0) -> 11.3 | AC45: =+Y45*AB45*R45 -> 0 | AD45: =+AC45-X45 -> 0 | AE45: =IFERROR(AD45/AC45,0) -> 0
C46: Day 3 | D46: Transfer package | J46: Rovaniemi: Private transfer to your accommodation | Q46: 40 | R46: 0 | S46: =+Q46*R46 -> 0 | T46: 0 | U46: =S46*(1-T46) -> 0 | V46: EUR | W46: =IFERROR(VLOOKUP(V46,[1]Curr!$B$2:$C$13,2,FALSE),0) -> 11.3 | X46: =U46*W46 -> 0 | Y46: =Q46/0.67 -> 59.701493 | Z46: =+Y46*R46 -> 0 | AA46: EUR | AB46: =IFERROR(VLOOKUP(AA46,Curr!$B$2:$C$13,2,FALSE),0) -> 11.3 | AC46: =+Y46*AB46*R46 -> 0 | AD46: =+AC46-X46 -> 0 | AE46: =IFERROR(AD46/AC46,0) -> 0
C47: Day 5 | D47: Transfer package | J47: Rovaniemi: Private transfer to Rovaniemi Bus Station | Q47: 40 | R47: 0 | S47: =+Q47*R47 -> 0 | T47: 0 | U47: =S47*(1-T47) -> 0 | V47: EUR | W47: =IFERROR(VLOOKUP(V47,[1]Curr!$B$2:$C$13,2,FALSE),0) -> 11.3 | X47: =U47*W47 -> 0 | Y47: =Q47/0.67 -> 59.701493 | Z47: =+Y47*R47 -> 0 | AA47: EUR | AB47: =IFERROR(VLOOKUP(AA47,Curr!$B$2:$C$13,2,FALSE),0) -> 11.3 | AC47: =+Y47*AB47*R47 -> 0 | AD47: =+AC47-X47 -> 0 | AE47: =IFERROR(AD47/AC47,0) -> 0
C48: Day 7 | D48: Transfer package | J48: Tromsø: Private transfer to Steampier Adventure Hotel | Q48: 900 | R48: 0 | S48: =+Q48*R48 -> 0 | T48: 0 | U48: =S48*(1-T48) -> 0 | V48: NOK | W48: =IFERROR(VLOOKUP(V48,[1]Curr!$B$2:$C$13,2,FALSE),0) -> 1 | X48: =U48*W48 -> 0 | Y48: =Q48/11.3/0.8 -> 99.557522 | Z48: =+Y48*R48 -> 0 | AA48: EUR | AB48: =IFERROR(VLOOKUP(AA48,Curr!$B$2:$C$13,2,FALSE),0) -> 11.3 | AC48: =+Y48*AB48*R48 -> 0 | AD48: =+AC48-X48 -> 0 | AE48: =IFERROR(AD48/AC48,0) -> 0
C49: Day 8 | D49: Transfer package | J49: Steampier: Private transfer to Tromsø Airport | Q49: 900 | R49: 0 | S49: =+Q49*R49 -> 0 | T49: 0 | U49: =S49*(1-T49) -> 0 | V49: EUR | W49: =IFERROR(VLOOKUP(V49,[1]Curr!$B$2:$C$13,2,FALSE),0) -> 11.3 | X49: =U49*W49 -> 0 | Y49: =Q49 -> 900 | Z49: =+Y49*R49 -> 0 | AA49: EUR | AB49: =IFERROR(VLOOKUP(AA49,Curr!$B$2:$C$13,2,FALSE),0) -> 11.3 | AC49: =+Y49*AB49*R49 -> 0 | AD49: =+AC49-X49 -> 0 | AE49: =IFERROR(AD49/AC49,0) -> 0
S50: =+Q50*R50 -> 0 | T50: 0 | U50: =S50*(1-T50) -> 0 | V50: EUR | W50: =IFERROR(VLOOKUP(V50,[1]Curr!$B$2:$C$13,2,FALSE),0) -> 11.3 | X50: =U50*W50 -> 0 | Y50: =Q50 -> 0 | Z50: =+Y50*R50 -> 0 | AA50: EUR | AB50: =IFERROR(VLOOKUP(AA50,Curr!$B$2:$C$13,2,FALSE),0) -> 11.3 | AC50: =+Y50*AB50*R50 -> 0 | AD50: =+AC50-X50 -> 0 | AE50: =IFERROR(AD50/AC50,0) -> 0
S51: =+Q51*R51 -> 0 | T51: 0 | U51: =S51*(1-T51) -> 0 | V51: EUR | W51: =IFERROR(VLOOKUP(V51,[1]Curr!$B$2:$C$13,2,FALSE),0) -> 11.3 | X51: =U51*W51 -> 0 | Y51: =Q51 -> 0 | Z51: =+Y51*R51 -> 0 | AA51: EUR | AB51: =IFERROR(VLOOKUP(AA51,Curr!$B$2:$C$13,2,FALSE),0) -> 11.3 | AC51: =+Y51*AB51*R51 -> 0 | AD51: =+AC51-X51 -> 0 | AE51: =IFERROR(AD51/AC51,0) -> 0
C52: Day 2 | D52: Activity Upgrade | J52: Helsinki: Excurssion to Tallinn - Self Guided Experience - Departure from Helsinki: 10:30 am - Departure from Tallinn: 7:30 pm - Includes: Helsinki port transfers, Star Class Cruise Ticket | O52: x | P52: https://www.tallink.com/en | Q52: =(40+40)+(50*2) -> 180 | R52: 0 | S52: =+Q52*R52 -> 0 | T52: 0 | U52: =S52*(1-T52) -> 0 | V52: EUR | W52: =IFERROR(VLOOKUP(V52,[1]Curr!$B$2:$C$13,2,FALSE),0) -> 11.3 | X52: =U52*W52 -> 0 | Y52: =Q52/0.8 -> 225 | Z52: =+Y52*R52 -> 0 | AA52: EUR | AB52: =IFERROR(VLOOKUP(AA52,Curr!$B$2:$C$13,2,FALSE),0) -> 11.3 | AC52: =+Y52*AB52*R52 -> 0 | AD52: =+AC52-X52 -> 0 | AE52: =IFERROR(AD52/AC52,0) -> 0
C53: Day 2 | D53: Activity Upgrade | J53: Tallinn: Old Town Guided tour - Time: 1:00 pm - 3:30 pm - Meeting point: under the Town Hall clock - Notable sights: St Nickolas Church, Freedom Square, Alexander Nevsky Cathedral, St Mary's Cathedral, Danish King's Garden and more - Includes: Tour, english guide, Recommendations | O53: x | P53: https://120degrees.club/ | Q53: 25 | R53: 0 | S53: =+Q53*R53 -> 0 | T53: 0 | U53: =S53*(1-T53) -> 0 | V53: EUR | W53: =IFERROR(VLOOKUP(V53,[1]Curr!$B$2:$C$13,2,FALSE),0) -> 11.3 | X53: =U53*W53 -> 0 | Y53: =Q53/0.62 -> 40.322581 | Z53: =+Y53*R53 -> 0 | AA53: EUR | AB53: =IFERROR(VLOOKUP(AA53,Curr!$B$2:$C$13,2,FALSE),0) -> 11.3 | AC53: =+Y53*AB53*R53 -> 0 | AD53: =+AC53-X53 -> 0 | AE53: =IFERROR(AD53/AC53,0) -> 0
C54: Day 4 | D54: Activity Upgrade | J54: Rovaniemi: Snowmobiling and Sledding Arctic Circle Highlights - Time: 08:45 am - 03:45 pm - Meeting point: Arctic Circle Snowmobile Park office - Includes: Pick-up/drop-off in central Rovaniemi, Knowledgeable, English-speaking guide, 1h snowmobiling on shared snowmobile (2 pers), Reindeer experience with 500m sleigh ride, Alaskan Husky experience with 500m sleigh ride, Approx. 2 hours free time in Santa Claus Village, Winter clothes (overalls, boots and gloves), Other equipment (helmet and balaclava), Salmon soup lunch (vegetarian option available) | O54: x | P54: https://booknordics.com/finland/western-lapland/rovaniemi/family-day-snowmobile-arctic-animals-and-santa-village | Q54: 252 | R54: 0 | S54: =+Q54*R54 -> 0 | T54: 0.2 | U54: =S54*(1-T54) -> 0 | V54: EUR | W54: =IFERROR(VLOOKUP(V54,[1]Curr!$B$2:$C$13,2,FALSE),0) -> 11.3 | X54: =U54*W54 -> 0 | Y54: =Q54 -> 252 | Z54: =+Y54*R54 -> 0 | AA54: EUR | AB54: =IFERROR(VLOOKUP(AA54,Curr!$B$2:$C$13,2,FALSE),0) -> 11.3 | AC54: =+Y54*AB54*R54 -> 0 | AD54: =+AC54-X54 -> 0 | AE54: =IFERROR(AD54/AC54,0) -> 0
C55: Day 6 | D55: Activity Upgrade | J55: Tromsø: Reindeer Sledding, Reindeer Feeding and Sami Culture - Time: 09:45 am - 2:30 pm - Meeting point: Radisson Blu Hotel's main entrance (Sjøgata 7) - Includes: Scenic transfers (45 min each way), Knowledgeable English- and Norwegian-speaking guide, Thermal winter suit, warm boots, Reindeer sledding (approx. 30 min, depending on weather and snow conditions), Feeding the herd on our camp, Hot traditional Sámi meal (bithos) and hot drinks. Vegetarian option available on request, Cultural introduction about Sámi history and daily life | O55: x | P55: https://booknordics.com/norway/northern-norway/tromso-region/reindeer-sledding-reindeer-feeding-and-sami-culture-3 | Q55: 2195 | R55: 0 | S55: =+Q55*R55 -> 0 | T55: 0.2 | U55: =S55*(1-T55) -> 0 | V55: NOK | W55: =IFERROR(VLOOKUP(V55,[1]Curr!$B$2:$C$13,2,FALSE),0) -> 1 | X55: =U55*W55 -> 0 | Y55: =Q55/11.3 -> 194.24779 | Z55: =+Y55*R55 -> 0 | AA55: EUR | AB55: =IFERROR(VLOOKUP(AA55,Curr!$B$2:$C$13,2,FALSE),0) -> 11.3 | AC55: =+Y55*AB55*R55 -> 0 | AD55: =+AC55-X55 -> 0 | AE55: =IFERROR(AD55/AC55,0) -> 0
S56: =+Q56*R56 -> 0 | T56: 0 | U56: =S56*(1-T56) -> 0 | V56: EUR | W56: =IFERROR(VLOOKUP(V56,[1]Curr!$B$2:$C$13,2,FALSE),0) -> 11.3 | X56: =U56*W56 -> 0 | Y56: =Q56 -> 0 | Z56: =+Y56*R56 -> 0 | AA56: EUR | AB56: =IFERROR(VLOOKUP(AA56,Curr!$B$2:$C$13,2,FALSE),0) -> 11.3 | AC56: =+Y56*AB56*R56 -> 0 | AD56: =+AC56-X56 -> 0 | AE56: =IFERROR(AD56/AC56,0) -> 0
S57: =+Q57*R57 -> 0 | T57: 0 | U57: =S57*(1-T57) -> 0 | V57: EUR | W57: =IFERROR(VLOOKUP(V57,[1]Curr!$B$2:$C$13,2,FALSE),0) -> 11.3 | X57: =U57*W57 -> 0 | Y57: =Q57 -> 0 | Z57: =+Y57*R57 -> 0 | AA57: EUR | AB57: =IFERROR(VLOOKUP(AA57,Curr!$B$2:$C$13,2,FALSE),0) -> 11.3 | AC57: =+Y57*AB57*R57 -> 0 | AD57: =+AC57-X57 -> 0 | AE57: =IFERROR(AD57/AC57,0) -> 0
S58: =+Q58*R58 -> 0 | T58: 0 | U58: =S58*(1-T58) -> 0 | V58: EUR | W58: =IFERROR(VLOOKUP(V58,[1]Curr!$B$2:$C$13,2,FALSE),0) -> 11.3 | X58: =U58*W58 -> 0 | Y58: =Q58 -> 0 | Z58: =+Y58*R58 -> 0 | AA58: EUR | AB58: =IFERROR(VLOOKUP(AA58,Curr!$B$2:$C$13,2,FALSE),0) -> 11.3 | AC58: =+Y58*AB58*R58 -> 0 | AD58: =+AC58-X58 -> 0 | AE58: =IFERROR(AD58/AC58,0) -> 0
S59: =+Q59*R59 -> 0 | T59: 0 | U59: =S59*(1-T59) -> 0 | V59: EUR | W59: =IFERROR(VLOOKUP(V59,[1]Curr!$B$2:$C$13,2,FALSE),0) -> 11.3 | X59: =U59*W59 -> 0 | Y59: =Q59 -> 0 | Z59: =+Y59*R59 -> 0 | AA59: EUR | AB59: =IFERROR(VLOOKUP(AA59,Curr!$B$2:$C$13,2,FALSE),0) -> 11.3 | AC59: =+Y59*AB59*R59 -> 0 | AD59: =+AC59-X59 -> 0 | AE59: =IFERROR(AD59/AC59,0) -> 0
S60: =+Q60*R60 -> 0 | T60: 0 | U60: =S60*(1-T60) -> 0 | V60: EUR | W60: =IFERROR(VLOOKUP(V60,[1]Curr!$B$2:$C$13,2,FALSE),0) -> 11.3 | X60: =U60*W60 -> 0 | Y60: =Q60 -> 0 | Z60: =+Y60*R60 -> 0 | AA60: EUR | AB60: =IFERROR(VLOOKUP(AA60,Curr!$B$2:$C$13,2,FALSE),0) -> 11.3 | AC60: =+Y60*AB60*R60 -> 0 | AD60: =+AC60-X60 -> 0 | AE60: =IFERROR(AD60/AC60,0) -> 0
S61: =+Q61*R61 -> 0 | T61: 0 | U61: =S61*(1-T61) -> 0 | V61: EUR | W61: =IFERROR(VLOOKUP(V61,[1]Curr!$B$2:$C$13,2,FALSE),0) -> 11.3 | X61: =U61*W61 -> 0 | Y61: =Q61 -> 0 | Z61: =+Y61*R61 -> 0 | AA61: EUR | AB61: =IFERROR(VLOOKUP(AA61,Curr!$B$2:$C$13,2,FALSE),0) -> 11.3 | AC61: =+Y61*AB61*R61 -> 0 | AD61: =+AC61-X61 -> 0 | AE61: =IFERROR(AD61/AC61,0) -> 0
S62: =+Q62*R62 -> 0 | T62: 0 | U62: =S62*(1-T62) -> 0 | V62: EUR | W62: =IFERROR(VLOOKUP(V62,[1]Curr!$B$2:$C$13,2,FALSE),0) -> 11.3 | X62: =U62*W62 -> 0 | Y62: =Q62 -> 0 | Z62: =+Y62*R62 -> 0 | AA62: EUR | AB62: =IFERROR(VLOOKUP(AA62,Curr!$B$2:$C$13,2,FALSE),0) -> 11.3 | AC62: =+Y62*AB62*R62 -> 0 | AD62: =+AC62-X62 -> 0 | AE62: =IFERROR(AD62/AC62,0) -> 0
S63: =+Q63*R63 -> 0 | T63: 0 | U63: =S63*(1-T63) -> 0 | V63: EUR | W63: =IFERROR(VLOOKUP(V63,[1]Curr!$B$2:$C$13,2,FALSE),0) -> 11.3 | X63: =U63*W63 -> 0 | Y63: =Q63 -> 0 | Z63: =+Y63*R63 -> 0 | AA63: EUR | AB63: =IFERROR(VLOOKUP(AA63,Curr!$B$2:$C$13,2,FALSE),0) -> 11.3 | AC63: =+Y63*AB63*R63 -> 0 | AD63: =+AC63-X63 -> 0 | AE63: =IFERROR(AD63/AC63,0) -> 0
S64: =+Q64*R64 -> 0 | T64: 0 | U64: =S64*(1-T64) -> 0 | V64: EUR | W64: =IFERROR(VLOOKUP(V64,[1]Curr!$B$2:$C$13,2,FALSE),0) -> 11.3 | X64: =U64*W64 -> 0 | Y64: =Q64 -> 0 | Z64: =+Y64*R64 -> 0 | AA64: EUR | AB64: =IFERROR(VLOOKUP(AA64,Curr!$B$2:$C$13,2,FALSE),0) -> 11.3 | AC64: =+Y64*AB64*R64 -> 0 | AD64: =+AC64-X64 -> 0 | AE64: =IFERROR(AD64/AC64,0) -> 0
S65: =+Q65*R65 -> 0 | T65: 0 | U65: =S65*(1-T65) -> 0 | V65: EUR | W65: =IFERROR(VLOOKUP(V65,[1]Curr!$B$2:$C$13,2,FALSE),0) -> 11.3 | X65: =U65*W65 -> 0 | Y65: =Q65 -> 0 | Z65: =+Y65*R65 -> 0 | AA65: EUR | AB65: =IFERROR(VLOOKUP(AA65,Curr!$B$2:$C$13,2,FALSE),0) -> 11.3 | AC65: =+Y65*AB65*R65 -> 0 | AD65: =+AC65-X65 -> 0 | AE65: =IFERROR(AD65/AC65,0) -> 0
S66: =+Q66*R66 -> 0 | T66: 0 | U66: =S66*(1-T66) -> 0 | V66: EUR | W66: =IFERROR(VLOOKUP(V66,[1]Curr!$B$2:$C$13,2,FALSE),0) -> 11.3 | X66: =U66*W66 -> 0 | Y66: =Q66 -> 0 | Z66: =+Y66*R66 -> 0 | AA66: EUR | AB66: =IFERROR(VLOOKUP(AA66,Curr!$B$2:$C$13,2,FALSE),0) -> 11.3 | AC66: =+Y66*AB66*R66 -> 0 | AD66: =+AC66-X66 -> 0 | AE66: =IFERROR(AD66/AC66,0) -> 0
B68: Totals | D68: x | E68: x | F68: x | G68: x | H68: x | I68: x | J68: x | K68: x | L68: x | M68: x | N68: x | O68: x | P68: x | Q68: x | R68: x | S68: x | T68: x | U68: x | V68: x | W68: x | X68: x | Y68: x | Z68: =SUM(Z7:Z66) -> 4347.4244 | AC68: =SUM(AC7:AC66) -> 49125.896 | AD68: =SUM(AD7:AD66) -> 9762.0162 | AE68: =IFERROR(AD68/AC68,0) -> 0.19871426 | AF68: =SUM(AF8:AF67) -> 0 | AG68: =SUM(AG8:AG67) -> 0 | AH68: =SUM(AH8:AH67) -> 0 | AI68: =SUM(AI8:AI67) -> 0 | AJ68: =SUM(AJ8:AJ67) -> 0
Y70: Fixed | Z70: =Z12+Z19+Z21+Z23+Z26+Z31+Z33+Z38+Z36 -> 2626.8362
Y71: Variable | Z71: =Z9+Z14+Z17+Z28 -> 1720.5882
Y72: Total | Z72: 4340
Y73: PP | Z73: =Z72/2 -> 2170
Y76: Shoulder | Z76: =Z72 -> 4340
Y77: High | Z77: =Z76*1.18 -> 5121.2
Y78: X-mas | Z78: =Z76*1.3 -> 5642
Y79: Low | Z79: =Z76*0.85 -> 3689

Sheet 1204
B1: Places: 3N Rovaniemi - 2N Tromsø - 1N Lyngen - 1N Tromsø
B2: Dates: Winter
B3: Pax: 2
B4: Rooming: Double
B6: ID | C6: Day | D6: Type | E6: From date | F6: To date | G6: From time | H6: To time | I6: Supplier | J6: Travel element | K6: Manual booking? | L6: Status | M6: Comments | N6: Non-refundable | O6: Refundable | P6: URL | Q6: Gross P per unit | R6: Units | S6: Gross P | T6: Supp Comm | U6: Net P | V6: Supp curr | W6: X-rate | X6: Net P NOK | Y6: Sales P per unit | Z6: Price | AA6: Sales curr | AB6: X-rate | AC6: Sales P NOK tot | AD6: GP NOK | AE6: GP % | AF6: VAT25 | AG6: VAT15 | AH6: VAT12 | AI6: VAT0-D | AJ6: VAT0-I
C7: Day 1 | D7: Arrival | J7: Rovaniemi: Welcome to Finland | Q7: 0 | R7: 0 | S7: =+Q7*R7 -> 0 | T7: 0 | U7: =S7*(1-T7) -> 0 | V7: EUR | W7: =IFERROR(VLOOKUP(V7,[1]Curr!$B$2:$C$13,2,FALSE),0) -> 11.3 | X7: =U7*W7 -> 0 | Y7: =Q7 -> 0 | Z7: =+Y7*R7 -> 0 | AA7: EUR | AB7: =IFERROR(VLOOKUP(AA7,Curr!$B$2:$C$13,2,FALSE),0) -> 11.3 | AC7: =+Y7*AB7*R7 -> 0 | AD7: =+AC7-X7 -> 0 | AE7: =IFERROR(AD7/AC7,0) -> 0
C8: Day 1 | D8: Transfer | J8: Rovaniemi: Self transfer to your accommodation | Q8: 0 | R8: 0 | S8: =+Q8*R8 -> 0 | T8: 0 | U8: =S8*(1-T8) -> 0 | V8: EUR | W8: =IFERROR(VLOOKUP(V8,[1]Curr!$B$2:$C$13,2,FALSE),0) -> 11.3 | X8: =U8*W8 -> 0 | Y8: =Q8/0.8 -> 0 | Z8: =+Y8*R8 -> 0 | AA8: EUR | AB8: =IFERROR(VLOOKUP(AA8,Curr!$B$2:$C$13,2,FALSE),0) -> 11.3 | AC8: =+Y8*AB8*R8 -> 0 | AD8: =+AC8-X8 -> 0 | AE8: =IFERROR(AD8/AC8,0) -> 0
C9: Day 1 | D9: Hotel | J9: Rovaniemi: Check in to your accommodation for a 3 night stay - Centrally Located 3/4-star Hotel - Standard Room - Breakfast included | Q9: 850 | R9: 1 | S9: =+Q9*R9 -> 850 | T9: 0 | U9: =S9*(1-T9) -> 850 | V9: EUR | W9: =IFERROR(VLOOKUP(V9,[1]Curr!$B$2:$C$13,2,FALSE),0) -> 11.3 | X9: =U9*W9 -> 9605 | Y9: =Q9/0.85 -> 1000 | Z9: =+Y9*R9 -> 1000 | AA9: EUR | AB9: =IFERROR(VLOOKUP(AA9,Curr!$B$2:$C$13,2,FALSE),0) -> 11.3 | AC9: =+Y9*AB9*R9 -> 11300 | AD9: =+AC9-X9 -> 1695 | AE9: =IFERROR(AD9/AC9,0) -> 0.15
C10: Day 1 | D10: Leisure | J10: Rovaniemi: Spend time at leisure | Q10: 0 | R10: 0 | S10: =+Q10*R10 -> 0 | T10: 0 | U10: =S10*(1-T10) -> 0 | V10: EUR | W10: =IFERROR(VLOOKUP(V10,[1]Curr!$B$2:$C$13,2,FALSE),0) -> 11.3 | X10: =U10*W10 -> 0 | Y10: =Q10 -> 0 | Z10: =+Y10*R10 -> 0 | AA10: EUR | AB10: =IFERROR(VLOOKUP(AA10,Curr!$B$2:$C$13,2,FALSE),0) -> 11.3 | AC10: =+Y10*AB10*R10 -> 0 | AD10: =+AC10-X10 -> 0 | AE10: =IFERROR(AD10/AC10,0) -> 0
S11: =+Q11*R11 -> 0 | T11: 0 | U11: =S11*(1-T11) -> 0 | V11: EUR | W11: =IFERROR(VLOOKUP(V11,[1]Curr!$B$2:$C$13,2,FALSE),0) -> 11.3 | X11: =U11*W11 -> 0 | Y11: =Q11 -> 0 | Z11: =+Y11*R11 -> 0 | AA11: EUR | AB11: =IFERROR(VLOOKUP(AA11,Curr!$B$2:$C$13,2,FALSE),0) -> 11.3 | AC11: =+Y11*AB11*R11 -> 0 | AD11: =+AC11-X11 -> 0 | AE11: =IFERROR(AD11/AC11,0) -> 0
C12: Day 2 | D12: Activity | J12: Rovaniemi: Arctic Circle Highlights Adventure Day - Time: 08:45 am - 2:45 pm - Meeting point: Arctic Circle Snowmobile Park office - Includes: Pick-up/drop-off in central Rovaniemi, Reindeer Farm visit with sleigh ride (2-3 pers), Reindeer sledge driver’s license reward, Alaskan Husky visit with sleigh ride (4 pers), Approx. 2 hours free time in Santa Claus Village, Winter clothes (overalls, boots and gloves), Traditional salmon soup or vegetarian option | O12: x | P12: https://booknordics.com/finland/western-lapland/rovaniemi/arctic-circle-highlights-family-day-by-minibus | Q12: 188 | R12: 2 | S12: =+Q12*R12 -> 376 | T12: 0.2 | U12: =S12*(1-T12) -> 300.8 | V12: EUR | W12: 11.3 | X12: =U12*W12 -> 3399.04 | Y12: 188 | Z12: =+Y12*R12 -> 376 | AA12: EUR | AB12: =IFERROR(VLOOKUP(AA12,Curr!$B$2:$C$13,2,FALSE),0) -> 11.3 | AC12: =+Y12*AB12*R12 -> 4248.8 | AD12: =+AC12-X12 -> 849.76 | AE12: =IFERROR(AD12/AC12,0) -> 0.2
C13: Day 2 | D13: Leisure | J13: Rovaniemi: Spend time at leisure | Q13: 0 | R13: 0 | S13: =+Q13*R13 -> 0 | T13: 0 | U13: =S13*(1-T13) -> 0 | V13: EUR | W13: =IFERROR(VLOOKUP(V13,[1]Curr!$B$2:$C$13,2,FALSE),0) -> 11.3 | X13: =U13*W13 -> 0 | Y13: =Q13 -> 0 | Z13: =+Y13*R13 -> 0 | AA13: EUR | AB13: =IFERROR(VLOOKUP(AA13,Curr!$B$2:$C$13,2,FALSE),0) -> 11.3 | AC13: =+Y13*AB13*R13 -> 0 | AD13: =+AC13-X13 -> 0 | AE13: =IFERROR(AD13/AC13,0) -> 0
C14: Day 2 | D14: Activity | J14: Rovaniemi: Northern Lights Unlimited Mileage Photo Tour - Time: 08:00 pm - 01:00 am - Meeting point: Book Lapland Office - Includes: Pick-up/drop-off in central Rovaniemi, Knowledgeable, English-speaking guides, Professional DSLR photography (unlimited), Meteorological observations, Thermal winter clothing, Hot drinks & snacks or cookies | O14: x | P14: https://booknordics.com/finland/western-lapland/rovaniemi/rovaniemi-northern-lights-family-tour-by-bus-with-photos | Q14: 109 | R14: 2 | S14: =+Q14*R14 -> 218 | T14: 0.2 | U14: =S14*(1-T14) -> 174.4 | V14: EUR | W14: =IFERROR(VLOOKUP(V14,[1]Curr!$B$2:$C$13,2,FALSE),0) -> 11.3 | X14: =U14*W14 -> 1970.72 | Y14: =Q14 -> 109 | Z14: =+Y14*R14 -> 218 | AA14: EUR | AB14: =IFERROR(VLOOKUP(AA14,Curr!$B$2:$C$13,2,FALSE),0) -> 11.3 | AC14: =+Y14*AB14*R14 -> 2463.4 | AD14: =+AC14-X14 -> 492.68 | AE14: =IFERROR(AD14/AC14,0) -> 0.2
S15: =+Q15*R15 -> 0 | T15: 0 | U15: =S15*(1-T15) -> 0 | V15: EUR | W15: =IFERROR(VLOOKUP(V15,[1]Curr!$B$2:$C$13,2,FALSE),0) -> 11.3 | X15: =U15*W15 -> 0 | Y15: =Q15 -> 0 | Z15: =+Y15*R15 -> 0 | AA15: EUR | AB15: =IFERROR(VLOOKUP(AA15,Curr!$B$2:$C$13,2,FALSE),0) -> 11.3 | AC15: =+Y15*AB15*R15 -> 0 | AD15: =+AC15-X15 -> 0 | AE15: =IFERROR(AD15/AC15,0) -> 0
C16: Day 3 | D16: Activity | J16: Rovaniemi: Arctic Wildlife Adventure to Ranua Park - Time: 10:00 am - 4:00 pm - Meeting point: Lapland Royal Adventures office - Includes: Pick-up/drop-off in central Rovaniemi, Tickets to Ranua Wildlife Park, Drinks and BBQ sausages by fire | O16: x | P16: https://booknordics.com/finland/western-lapland/rovaniemi/arctic-wildlife-adventure-ranua-wildlife-park-trip | Q16: 109 | R16: 2 | S16: =+Q16*R16 -> 218 | T16: 0.2 | U16: =S16*(1-T16) -> 174.4 | V16: EUR | W16: =IFERROR(VLOOKUP(V16,[1]Curr!$B$2:$C$13,2,FALSE),0) -> 11.3 | X16: =U16*W16 -> 1970.72 | Y16: =Q16 -> 109 | Z16: =+Y16*R16 -> 218 | AA16: EUR | AB16: =IFERROR(VLOOKUP(AA16,Curr!$B$2:$C$13,2,FALSE),0) -> 11.3 | AC16: =+Y16*AB16*R16 -> 2463.4 | AD16: =+AC16-X16 -> 492.68 | AE16: =IFERROR(AD16/AC16,0) -> 0.2
C17: Day 3 | D17: Leisure | J17: Rovaniemi: Spend time at leisure | Q17: 0 | R17: 0 | S17: =+Q17*R17 -> 0 | T17: 0 | U17: =S17*(1-T17) -> 0 | V17: EUR | W17: =IFERROR(VLOOKUP(V17,[1]Curr!$B$2:$C$13,2,FALSE),0) -> 11.3 | X17: =U17*W17 -> 0 | Y17: =Q17 -> 0 | Z17: =+Y17*R17 -> 0 | AA17: EUR | AB17: =IFERROR(VLOOKUP(AA17,Curr!$B$2:$C$13,2,FALSE),0) -> 11.3 | AC17: =+Y17*AB17*R17 -> 0 | AD17: =+AC17-X17 -> 0 | AE17: =IFERROR(AD17/AC17,0) -> 0
C18: Day 3 | D18: Activity | J18: Rovaniemi: Small-Group Aurora Hunt by Minibus - Time: 7:00 pm - 10:00 pm - Meeting point: Lapland Royal Adventures Office - Includes: Pick-up/drop-off from central Rovaniemi, Knowledgeable, English-speaking guide, Dedicated Northern Lights chase by minibus, Cozy blankets, hot drinks and a snack | O18: x | P18: https://booknordics.com/finland/western-lapland/rovaniemi/aurora-quest-by-minibus | Q18: 89 | R18: 2 | S18: =+Q18*R18 -> 178 | T18: 0.2 | U18: =S18*(1-T18) -> 142.4 | V18: EUR | W18: 11.3 | X18: =U18*W18 -> 1609.12 | Y18: 89 | Z18: =+Y18*R18 -> 178 | AA18: EUR | AB18: =IFERROR(VLOOKUP(AA18,Curr!$B$2:$C$13,2,FALSE),0) -> 11.3 | AC18: =+Y18*AB18*R18 -> 2011.4 | AD18: =+AC18-X18 -> 402.28 | AE18: =IFERROR(AD18/AC18,0) -> 0.2
S19: =+Q19*R19 -> 0 | T19: 0 | U19: =S19*(1-T19) -> 0 | V19: EUR | W19: =IFERROR(VLOOKUP(V19,[1]Curr!$B$2:$C$13,2,FALSE),0) -> 11.3 | X19: =U19*W19 -> 0 | Y19: =Q19 -> 0 | Z19: =+Y19*R19 -> 0 | AA19: EUR | AB19: =IFERROR(VLOOKUP(AA19,Curr!$B$2:$C$13,2,FALSE),0) -> 11.3 | AC19: =+Y19*AB19*R19 -> 0 | AD19: =+AC19-X19 -> 0 | AE19: =IFERROR(AD19/AC19,0) -> 0
C20: Day 4 | D20: Transfer | J20: Rovaniemi: Self transfer to Rovaniemi Bus Station | Q20: 0 | R20: 0 | S20: =+Q20*R20 -> 0 | T20: 0 | U20: =S20*(1-T20) -> 0 | V20: EUR | W20: =IFERROR(VLOOKUP(V20,[1]Curr!$B$2:$C$13,2,FALSE),0) -> 11.3 | X20: =U20*W20 -> 0 | Y20: =Q20 -> 0 | Z20: =+Y20*R20 -> 0 | AA20: EUR | AB20: =IFERROR(VLOOKUP(AA20,Curr!$B$2:$C$13,2,FALSE),0) -> 11.3 | AC20: =+Y20*AB20*R20 -> 0 | AD20: =+AC20-X20 -> 0 | AE20: =IFERROR(AD20/AC20,0) -> 0
C21: Day 4 | D21: Activity | J21: Rovaniemi: Arctic Route Coach Transfer to Tromsø - Time: 11:40 am - 7:30 pm - Includes: Tickets | O21: x | P21: https://bestarctic.com/the-arctic-route/arctic-winter-routes-explore-norway-sweden-and-finland/bus-between-tromso-norway-and-rovaniemi-finland/ | Q21: 1830 | R21: 2 | S21: =+Q21*R21 -> 3660 | T21: 0.2 | U21: =S21*(1-T21) -> 2928 | V21: NOK | W21: =IFERROR(VLOOKUP(V21,[1]Curr!$B$2:$C$13,2,FALSE),0) -> 1 | X21: =U21*W21 -> 2928 | Y21: =Q21/11.3/0.9 -> 179.941 | Z21: =+Y21*R21 -> 359.88201 | AA21: EUR | AB21: =IFERROR(VLOOKUP(AA21,Curr!$B$2:$C$13,2,FALSE),0) -> 11.3 | AC21: =+Y21*AB21*R21 -> 4066.6667 | AD21: =+AC21-X21 -> 1138.6667 | AE21: =IFERROR(AD21/AC21,0) -> 0.28
C22: Day 4 | D22: Transfer | J22: Tromsø: Self transfer to your accommodation | Q22: 0 | R22: 0 | S22: =+Q22*R22 -> 0 | T22: 0 | U22: =S22*(1-T22) -> 0 | V22: EUR | W22: =IFERROR(VLOOKUP(V22,[1]Curr!$B$2:$C$13,2,FALSE),0) -> 11.3 | X22: =U22*W22 -> 0 | Y22: =Q22 -> 0 | Z22: =+Y22*R22 -> 0 | AA22: EUR | AB22: =IFERROR(VLOOKUP(AA22,Curr!$B$2:$C$13,2,FALSE),0) -> 11.3 | AC22: =+Y22*AB22*R22 -> 0 | AD22: =+AC22-X22 -> 0 | AE22: =IFERROR(AD22/AC22,0) -> 0
C23: Day 4 | D23: Hotel | J23: Tromsø: Check in to your accommodation for a 2 night stay - Centrally Located 3/4-star Hotel - Standard Room - Breakfast included | Q23: 800 | R23: 1 | S23: =+Q23*R23 -> 800 | T23: 0 | U23: =S23*(1-T23) -> 800 | V23: EUR | W23: =IFERROR(VLOOKUP(V23,[1]Curr!$B$2:$C$13,2,FALSE),0) -> 11.3 | X23: =U23*W23 -> 9040 | Y23: =Q23/0.85 -> 941.17647 | Z23: =+Y23*R23 -> 941.17647 | AA23: EUR | AB23: =IFERROR(VLOOKUP(AA23,Curr!$B$2:$C$13,2,FALSE),0) -> 11.3 | AC23: =+Y23*AB23*R23 -> 10635.294 | AD23: =+AC23-X23 -> 1595.2941 | AE23: =IFERROR(AD23/AC23,0) -> 0.15
C24: Day 4 | D24: Leisure | J24: Tromsø: Spend time at leisure | Q24: 0 | R24: 0 | S24: =+Q24*R24 -> 0 | T24: 0 | U24: =S24*(1-T24) -> 0 | V24: EUR | W24: =IFERROR(VLOOKUP(V24,[1]Curr!$B$2:$C$13,2,FALSE),0) -> 11.3 | X24: =U24*W24 -> 0 | Y24: =Q24 -> 0 | Z24: =+Y24*R24 -> 0 | AA24: EUR | AB24: =IFERROR(VLOOKUP(AA24,Curr!$B$2:$C$13,2,FALSE),0) -> 11.3 | AC24: =+Y24*AB24*R24 -> 0 | AD24: =+AC24-X24 -> 0 | AE24: =IFERROR(AD24/AC24,0) -> 0
S25: =+Q25*R25 -> 0 | T25: 0 | U25: =S25*(1-T25) -> 0 | V25: EUR | W25: =IFERROR(VLOOKUP(V25,[1]Curr!$B$2:$C$13,2,FALSE),0) -> 11.3 | X25: =U25*W25 -> 0 | Y25: =Q25 -> 0 | Z25: =+Y25*R25 -> 0 | AA25: EUR | AB25: =IFERROR(VLOOKUP(AA25,Curr!$B$2:$C$13,2,FALSE),0) -> 11.3 | AC25: =+Y25*AB25*R25 -> 0 | AD25: =+AC25-X25 -> 0 | AE25: =IFERROR(AD25/AC25,0) -> 0
C26: Day 5 | D26: Activity | J26: Tromsø: Photo Tour to Arctic Landscapes and Fjords - Time: 10:00 am - 3:00 pm - Meeting point: Roald Amundsens plass 1A - Includes: Departure from central Tromsø. Drop-off to your hotel, Professional, English-speaking photo guides, Scenic fjord safari by comfortable minivan vehicle, Help with camera settings and nature photography, Usually a small-group experience with 4-8 guests, Soup or expedition food, coffee and waffles/cookies | O26: x | P26: https://booknordics.com/norway/northern-norway/tromso-region/tromso-fjord-photo-tour | Q26: 145 | R26: 2 | S26: =+Q26*R26 -> 290 | T26: 0.2 | U26: =S26*(1-T26) -> 232 | V26: EUR | W26: =IFERROR(VLOOKUP(V26,[1]Curr!$B$2:$C$13,2,FALSE),0) -> 11.3 | X26: =U26*W26 -> 2621.6 | Y26: =Q26 -> 145 | Z26: =+Y26*R26 -> 290 | AA26: EUR | AB26: =IFERROR(VLOOKUP(AA26,Curr!$B$2:$C$13,2,FALSE),0) -> 11.3 | AC26: =+Y26*AB26*R26 -> 3277 | AD26: =+AC26-X26 -> 655.4 | AE26: =IFERROR(AD26/AC26,0) -> 0.2
C27: Day 5 | D27: Leisure | J27: Tromsø: Spend time at leisure | Q27: 0 | R27: 0 | S27: =+Q27*R27 -> 0 | T27: 0 | U27: =S27*(1-T27) -> 0 | V27: EUR | W27: =IFERROR(VLOOKUP(V27,[1]Curr!$B$2:$C$13,2,FALSE),0) -> 11.3 | X27: =U27*W27 -> 0 | Y27: =Q27 -> 0 | Z27: =+Y27*R27 -> 0 | AA27: EUR | AB27: =IFERROR(VLOOKUP(AA27,Curr!$B$2:$C$13,2,FALSE),0) -> 11.3 | AC27: =+Y27*AB27*R27 -> 0 | AD27: =+AC27-X27 -> 0 | AE27: =IFERROR(AD27/AC27,0) -> 0
C28: Day 5 | D28: Activity | J28: Tromsø: Northern Lights Cruise with Silent Electric Ship - Time: 7:00 pm - 10:00 pm - Meeting point: Kaigata 6 - Includes: Departure from central Tromsø, 3-hour fjord cruise, Light meal (soup and bread) and water, English speaking guides, Warm indoor saloons, Free wifi, Toilets | O28: x | P28: https://booknordics.com/norway/northern-norway/tromso-region/northern-lights-cruise-electric-ship | Q28: 105 | R28: 2 | S28: =+Q28*R28 -> 210 | T28: 0.2 | U28: =S28*(1-T28) -> 168 | V28: EUR | W28: =IFERROR(VLOOKUP(V28,[1]Curr!$B$2:$C$13,2,FALSE),0) -> 11.3 | X28: =U28*W28 -> 1898.4 | Y28: =Q28 -> 105 | Z28: =+Y28*R28 -> 210 | AA28: EUR | AB28: =IFERROR(VLOOKUP(AA28,Curr!$B$2:$C$13,2,FALSE),0) -> 11.3 | AC28: =+Y28*AB28*R28 -> 2373 | AD28: =+AC28-X28 -> 474.6 | AE28: =IFERROR(AD28/AC28,0) -> 0.2
S29: =+Q29*R29 -> 0 | T29: 0 | U29: =S29*(1-T29) -> 0 | V29: EUR | W29: =IFERROR(VLOOKUP(V29,[1]Curr!$B$2:$C$13,2,FALSE),0) -> 11.3 | X29: =U29*W29 -> 0 | Y29: =Q29 -> 0 | Z29: =+Y29*R29 -> 0 | AA29: EUR | AB29: =IFERROR(VLOOKUP(AA29,Curr!$B$2:$C$13,2,FALSE),0) -> 11.3 | AC29: =+Y29*AB29*R29 -> 0 | AD29: =+AC29-X29 -> 0 | AE29: =IFERROR(AD29/AC29,0) -> 0
C30: Day 6 | D30: Transfer | J30: Tromsø: Self transfer to Scandic Ishavs Hotel | Q30: 0 | R30: 0 | S30: =+Q30*R30 -> 0 | T30: 0 | U30: =S30*(1-T30) -> 0 | V30: EUR | W30: =IFERROR(VLOOKUP(V30,[1]Curr!$B$2:$C$13,2,FALSE),0) -> 11.3 | X30: =U30*W30 -> 0 | Y30: =Q30 -> 0 | Z30: =+Y30*R30 -> 0 | AA30: EUR | AB30: =IFERROR(VLOOKUP(AA30,Curr!$B$2:$C$13,2,FALSE),0) -> 11.3 | AC30: =+Y30*AB30*R30 -> 0 | AD30: =+AC30-X30 -> 0 | AE30: =IFERROR(AD30/AC30,0) -> 0
C31: Day 6 | D31: Activity | J31: Tromsø: Crystal Lavvo Stay with Auroras, Meals & Activities - Time: 11:30 am - 10: 50 am (the next day) - Meeting point: Samuel Arnesens gate 5 - Includes: Pick-up/drop-off in Tromsø with scenic transfers, Comfortable overnight stay in crystal lavvo, Fireplace heating with unlimited firewood, Northern Lights hunt with photo workshop, Snowshoeing experience nearby, Lunch and dinner included on day 1, Bathroom/toilet facilities in the main house, Breakfast and return transfer included on day 2 | O31: x | P31: https://booknordics.com/norway/northern-norway/tromso-region/crystal-lavvy-stay-northern-lights-snowshoeing | Q31: 375 | R31: 2 | S31: =+Q31*R31 -> 750 | T31: 0.2 | U31: =S31*(1-T31) -> 600 | V31: EUR | W31: =IFERROR(VLOOKUP(V31,[1]Curr!$B$2:$C$13,2,FALSE),0) -> 11.3 | X31: =U31*W31 -> 6780 | Y31: =Q31 -> 375 | Z31: =+Y31*R31 -> 750 | AA31: EUR | AB31: =IFERROR(VLOOKUP(AA31,Curr!$B$2:$C$13,2,FALSE),0) -> 11.3 | AC31: =+Y31*AB31*R31 -> 8475 | AD31: =+AC31-X31 -> 1695 | AE31: =IFERROR(AD31/AC31,0) -> 0.2
S32: =+Q32*R32 -> 0 | T32: 0 | U32: =S32*(1-T32) -> 0 | V32: EUR | W32: =IFERROR(VLOOKUP(V32,[1]Curr!$B$2:$C$13,2,FALSE),0) -> 11.3 | X32: =U32*W32 -> 0 | Y32: =Q32 -> 0 | Z32: =+Y32*R32 -> 0 | AA32: EUR | AB32: =IFERROR(VLOOKUP(AA32,Curr!$B$2:$C$13,2,FALSE),0) -> 11.3 | AC32: =+Y32*AB32*R32 -> 0 | AD32: =+AC32-X32 -> 0 | AE32: =IFERROR(AD32/AC32,0) -> 0
C33: Day 7 | D33: Transfer | J33: Lyngen: Shuttle transfer back to Scandic Ishavs Hotel in Tromsø | Q33: 0 | R33: 0 | S33: =+Q33*R33 -> 0 | T33: 0 | U33: =S33*(1-T33) -> 0 | V33: EUR | W33: =IFERROR(VLOOKUP(V33,[1]Curr!$B$2:$C$13,2,FALSE),0) -> 11.3 | X33: =U33*W33 -> 0 | Y33: =Q33 -> 0 | Z33: =+Y33*R33 -> 0 | AA33: EUR | AB33: =IFERROR(VLOOKUP(AA33,Curr!$B$2:$C$13,2,FALSE),0) -> 11.3 | AC33: =+Y33*AB33*R33 -> 0 | AD33: =+AC33-X33 -> 0 | AE33: =IFERROR(AD33/AC33,0) -> 0
C34: Day 7 | D34: Transfer | J34: Tromsø: Self transfer to your accommodation | Q34: 0 | R34: 0 | S34: =+Q34*R34 -> 0 | T34: 0 | U34: =S34*(1-T34) -> 0 | V34: EUR | W34: =IFERROR(VLOOKUP(V34,[1]Curr!$B$2:$C$13,2,FALSE),0) -> 11.3 | X34: =U34*W34 -> 0 | Y34: =Q34 -> 0 | Z34: =+Y34*R34 -> 0 | AA34: EUR | AB34: =IFERROR(VLOOKUP(AA34,Curr!$B$2:$C$13,2,FALSE),0) -> 11.3 | AC34: =+Y34*AB34*R34 -> 0 | AD34: =+AC34-X34 -> 0 | AE34: =IFERROR(AD34/AC34,0) -> 0
C35: Day 7 | D35: Hotel | J35: Tromsø: Check in to your accommodation for a 1 night stay - Centrally Located 3/4-star Hotel - Standard Room - Breakfast included | Q35: 310 | R35: 1 | S35: =+Q35*R35 -> 310 | T35: 0 | U35: =S35*(1-T35) -> 310 | V35: EUR | W35: =IFERROR(VLOOKUP(V35,[1]Curr!$B$2:$C$13,2,FALSE),0) -> 11.3 | X35: =U35*W35 -> 3503 | Y35: =Q35/0.8 -> 387.5 | Z35: =+Y35*R35 -> 387.5 | AA35: EUR | AB35: =IFERROR(VLOOKUP(AA35,Curr!$B$2:$C$13,2,FALSE),0) -> 11.3 | AC35: =+Y35*AB35*R35 -> 4378.75 | AD35: =+AC35-X35 -> 875.75 | AE35: =IFERROR(AD35/AC35,0) -> 0.2
C36: Day 7 | D36: Leisure | J36: Tromsø: Spend time at leisure | Q36: 0 | R36: 0 | S36: =+Q36*R36 -> 0 | T36: 0 | U36: =S36*(1-T36) -> 0 | V36: EUR | W36: =IFERROR(VLOOKUP(V36,[1]Curr!$B$2:$C$13,2,FALSE),0) -> 11.3 | X36: =U36*W36 -> 0 | Y36: =Q36 -> 0 | Z36: =+Y36*R36 -> 0 | AA36: EUR | AB36: =IFERROR(VLOOKUP(AA36,Curr!$B$2:$C$13,2,FALSE),0) -> 11.3 | AC36: =+Y36*AB36*R36 -> 0 | AD36: =+AC36-X36 -> 0 | AE36: =IFERROR(AD36/AC36,0) -> 0
S37: =+Q37*R37 -> 0 | T37: 0 | U37: =S37*(1-T37) -> 0 | V37: EUR | W37: =IFERROR(VLOOKUP(V37,[1]Curr!$B$2:$C$13,2,FALSE),0) -> 11.3 | X37: =U37*W37 -> 0 | Y37: =Q37 -> 0 | Z37: =+Y37*R37 -> 0 | AA37: EUR | AB37: =IFERROR(VLOOKUP(AA37,Curr!$B$2:$C$13,2,FALSE),0) -> 11.3 | AC37: =+Y37*AB37*R37 -> 0 | AD37: =+AC37-X37 -> 0 | AE37: =IFERROR(AD37/AC37,0) -> 0
C38: Day 8 | D38: Transfer | J38: Tromsø: Self transfer to Tromsø Airport | Q38: 0 | R38: 0 | S38: =+Q38*R38 -> 0 | T38: 0 | U38: =S38*(1-T38) -> 0 | V38: EUR | W38: =IFERROR(VLOOKUP(V38,[1]Curr!$B$2:$C$13,2,FALSE),0) -> 11.3 | X38: =U38*W38 -> 0 | Y38: =Q38 -> 0 | Z38: =+Y38*R38 -> 0 | AA38: EUR | AB38: =IFERROR(VLOOKUP(AA38,Curr!$B$2:$C$13,2,FALSE),0) -> 11.3 | AC38: =+Y38*AB38*R38 -> 0 | AD38: =+AC38-X38 -> 0 | AE38: =IFERROR(AD38/AC38,0) -> 0
C39: Day 8 | D39: Departure | J39: Tromsø: Departure home | Q39: 0 | R39: 0 | S39: =+Q39*R39 -> 0 | T39: 0 | U39: =S39*(1-T39) -> 0 | V39: EUR | W39: =IFERROR(VLOOKUP(V39,[1]Curr!$B$2:$C$13,2,FALSE),0) -> 11.3 | X39: =U39*W39 -> 0 | Y39: =Q39 -> 0 | Z39: =+Y39*R39 -> 0 | AA39: EUR | AB39: =IFERROR(VLOOKUP(AA39,Curr!$B$2:$C$13,2,FALSE),0) -> 11.3 | AC39: =+Y39*AB39*R39 -> 0 | AD39: =+AC39-X39 -> 0 | AE39: =IFERROR(AD39/AC39,0) -> 0
S40: =+Q40*R40 -> 0 | T40: 0 | U40: =S40*(1-T40) -> 0 | V40: EUR | W40: =IFERROR(VLOOKUP(V40,[1]Curr!$B$2:$C$13,2,FALSE),0) -> 11.3 | X40: =U40*W40 -> 0 | Y40: =Q40 -> 0 | Z40: =+Y40*R40 -> 0 | AA40: EUR | AB40: =IFERROR(VLOOKUP(AA40,Curr!$B$2:$C$13,2,FALSE),0) -> 11.3 | AC40: =+Y40*AB40*R40 -> 0 | AD40: =+AC40-X40 -> 0 | AE40: =IFERROR(AD40/AC40,0) -> 0
S41: =+Q41*R41 -> 0 | T41: 0 | U41: =S41*(1-T41) -> 0 | V41: EUR | W41: =IFERROR(VLOOKUP(V41,[1]Curr!$B$2:$C$13,2,FALSE),0) -> 11.3 | X41: =U41*W41 -> 0 | Y41: =Q41 -> 0 | Z41: =+Y41*R41 -> 0 | AA41: EUR | AB41: =IFERROR(VLOOKUP(AA41,Curr!$B$2:$C$13,2,FALSE),0) -> 11.3 | AC41: =+Y41*AB41*R41 -> 0 | AD41: =+AC41-X41 -> 0 | AE41: =IFERROR(AD41/AC41,0) -> 0
C42: Day 1 | D42: Transfer package | J42: Rovaniemi: Private transfer to your accommodation | Q42: 40 | R42: 0 | S42: =+Q42*R42 -> 0 | T42: 0 | U42: =S42*(1-T42) -> 0 | V42: EUR | W42: =IFERROR(VLOOKUP(V42,[1]Curr!$B$2:$C$13,2,FALSE),0) -> 11.3 | X42: =U42*W42 -> 0 | Y42: =Q42/0.67 -> 59.701493 | Z42: =+Y42*R42 -> 0 | AA42: EUR | AB42: =IFERROR(VLOOKUP(AA42,Curr!$B$2:$C$13,2,FALSE),0) -> 11.3 | AC42: =+Y42*AB42*R42 -> 0 | AD42: =+AC42-X42 -> 0 | AE42: =IFERROR(AD42/AC42,0) -> 0
C43: Day 5 | D43: Transfer package | J43: Rovaniemi: Private transfer to Rovaniemi Bus Station | Q43: 40 | R43: 0 | S43: =+Q43*R43 -> 0 | T43: 0 | U43: =S43*(1-T43) -> 0 | V43: EUR | W43: =IFERROR(VLOOKUP(V43,[1]Curr!$B$2:$C$13,2,FALSE),0) -> 11.3 | X43: =U43*W43 -> 0 | Y43: =Q43/0.67 -> 59.701493 | Z43: =+Y43*R43 -> 0 | AA43: EUR | AB43: =IFERROR(VLOOKUP(AA43,Curr!$B$2:$C$13,2,FALSE),0) -> 11.3 | AC43: =+Y43*AB43*R43 -> 0 | AD43: =+AC43-X43 -> 0 | AE43: =IFERROR(AD43/AC43,0) -> 0
C44: Day 8 | D44: Transfer package | J44: Tromsø: Private transfer to Tromsø Airport | Q44: 900 | R44: 0 | S44: =+Q44*R44 -> 0 | T44: 0 | U44: =S44*(1-T44) -> 0 | V44: EUR | W44: =IFERROR(VLOOKUP(V44,[1]Curr!$B$2:$C$13,2,FALSE),0) -> 11.3 | X44: =U44*W44 -> 0 | Y44: =Q44 -> 900 | Z44: =+Y44*R44 -> 0 | AA44: EUR | AB44: =IFERROR(VLOOKUP(AA44,Curr!$B$2:$C$13,2,FALSE),0) -> 11.3 | AC44: =+Y44*AB44*R44 -> 0 | AD44: =+AC44-X44 -> 0 | AE44: =IFERROR(AD44/AC44,0) -> 0
S45: =+Q45*R45 -> 0 | T45: 0 | U45: =S45*(1-T45) -> 0 | V45: EUR | W45: =IFERROR(VLOOKUP(V45,[1]Curr!$B$2:$C$13,2,FALSE),0) -> 11.3 | X45: =U45*W45 -> 0 | Y45: =Q45 -> 0 | Z45: =+Y45*R45 -> 0 | AA45: EUR | AB45: =IFERROR(VLOOKUP(AA45,Curr!$B$2:$C$13,2,FALSE),0) -> 11.3 | AC45: =+Y45*AB45*R45 -> 0 | AD45: =+AC45-X45 -> 0 | AE45: =IFERROR(AD45/AC45,0) -> 0
S46: =+Q46*R46 -> 0 | T46: 0 | U46: =S46*(1-T46) -> 0 | V46: EUR | W46: =IFERROR(VLOOKUP(V46,[1]Curr!$B$2:$C$13,2,FALSE),0) -> 11.3 | X46: =U46*W46 -> 0 | Y46: =Q46 -> 0 | Z46: =+Y46*R46 -> 0 | AA46: EUR | AB46: =IFERROR(VLOOKUP(AA46,Curr!$B$2:$C$13,2,FALSE),0) -> 11.3 | AC46: =+Y46*AB46*R46 -> 0 | AD46: =+AC46-X46 -> 0 | AE46: =IFERROR(AD46/AC46,0) -> 0
C47: Day 2 | D47: Activity Upgrade | J47: Rovaniemi: Snowmobiling and Sledding Arctic Circle Highlights - Time: 08:45 am - 03:45 pm - Meeting point: Arctic Circle Snowmobile Park office - Includes: Pick-up/drop-off in central Rovaniemi, Knowledgeable, English-speaking guide, 1h snowmobiling on shared snowmobile (2 pers), Reindeer experience with 500m sleigh ride, Alaskan Husky experience with 500m sleigh ride, Approx. 2 hours free time in Santa Claus Village, Winter clothes (overalls, boots and gloves), Other equipment (helmet and balaclava), Salmon soup lunch (vegetarian option available) | O47: x | P47: https://booknordics.com/finland/western-lapland/rovaniemi/family-day-snowmobile-arctic-animals-and-santa-village | Q47: 252 | R47: 0 | S47: =+Q47*R47 -> 0 | T47: 0.2 | U47: =S47*(1-T47) -> 0 | V47: EUR | W47: =IFERROR(VLOOKUP(V47,[1]Curr!$B$2:$C$13,2,FALSE),0) -> 11.3 | X47: =U47*W47 -> 0 | Y47: =Q47 -> 252 | Z47: =+Y47*R47 -> 0 | AA47: EUR | AB47: =IFERROR(VLOOKUP(AA47,Curr!$B$2:$C$13,2,FALSE),0) -> 11.3 | AC47: =+Y47*AB47*R47 -> 0 | AD47: =+AC47-X47 -> 0 | AE47: =IFERROR(AD47/AC47,0) -> 0
C48: Day 3 | D48: Activity upgrade | J48: Rovaniemi: Polar Ice Breaker Cruise - Time: 11:00 am - 7:35 pm - Meeting point: Rovaniemi Tourist Information - Includes: Lunch, transfers, 3-hour Icebreaker Cruise, Guided Icebreaker tour, Onboard Cinema, Frozen Sea Walk, Ice Swimming, Cruise and Swim Certificate | O48: x | P48: https://booknordics.com/finland/western-lapland/rovaniemi/polar-explorer-icebreaker-dancing-queen-party-cruise-and-lunch-with-shuttle-bus-transportation-from-rovaniemi | Q48: 500 | R48: 0 | S48: =+Q48*R48 -> 0 | T48: 0.12 | U48: =S48*(1-T48) -> 0 | V48: EUR | W48: =IFERROR(VLOOKUP(V48,[1]Curr!$B$2:$C$13,2,FALSE),0) -> 11.3 | X48: =U48*W48 -> 0 | Y48: =Q48/0.97 -> 515.46392 | Z48: =+Y48*R48 -> 0 | AA48: EUR | AB48: =IFERROR(VLOOKUP(AA48,Curr!$B$2:$C$13,2,FALSE),0) -> 11.3 | AC48: =+Y48*AB48*R48 -> 0 | AD48: =+AC48-X48 -> 0 | AE48: =IFERROR(AD48/AC48,0) -> 0
C49: Day 3 | D49: Activity upgrade | J49: Rovaniemi: Korouoma Frozen Waterfall + Auttiköngäs - Time: 08:00 am - 3:00 pm - Meeteing point: Hotel pick up - Includes: Tour Guiding / Transportation, Spikes if needed, Lappish BBQ & Hot Beverages, Pick/Drop within 15KM of Rovaniemi City, Goods & services tax | P49: BOKUN | Q49: 159 | R49: 0 | S49: =+Q49*R49 -> 0 | T49: 0.3 | U49: =S49*(1-T49) -> 0 | V49: EUR | W49: =IFERROR(VLOOKUP(V49,[1]Curr!$B$2:$C$13,2,FALSE),0) -> 11.3 | X49: =U49*W49 -> 0 | Y49: =Q49 -> 159 | Z49: =+Y49*R49 -> 0 | AA49: EUR | AB49: =IFERROR(VLOOKUP(AA49,Curr!$B$2:$C$13,2,FALSE),0) -> 11.3 | AC49: =+Y49*AB49*R49 -> 0 | AD49: =+AC49-X49 -> 0 | AE49: =IFERROR(AD49/AC49,0) -> 0
C50: Day 5 | D50: Activity upgrade | J50: Tromsø: Reindeer Sledding, Reindeer Feeding and Sami Culture - Time: 09:45 am - 2:30 pm - Meeting point: Radisson Blu Hotel's main entrance (Sjøgata 7) - Includes: Scenic transfers (45 min each way), Knowledgeable English- and Norwegian-speaking guide, Thermal winter suit, warm boots, Reindeer sledding (approx. 30 min, depending on weather and snow conditions), Feeding the herd on our camp, Hot traditional Sámi meal (bithos) and hot drinks. Vegetarian option available on request, Cultural introduction about Sámi history and daily life | O50: x | P50: https://booknordics.com/norway/northern-norway/tromso-region/reindeer-sledding-reindeer-feeding-and-sami-culture-3 | Q50: 2195 | R50: 0 | S50: =+Q50*R50 -> 0 | T50: 0.2 | U50: =S50*(1-T50) -> 0 | V50: NOK | W50: =IFERROR(VLOOKUP(V50,[1]Curr!$B$2:$C$13,2,FALSE),0) -> 1 | X50: =U50*W50 -> 0 | Y50: =Q50/11.3 -> 194.24779 | Z50: =+Y50*R50 -> 0 | AA50: EUR | AB50: =IFERROR(VLOOKUP(AA50,Curr!$B$2:$C$13,2,FALSE),0) -> 11.3 | AC50: =+Y50*AB50*R50 -> 0 | AD50: =+AC50-X50 -> 0 | AE50: =IFERROR(AD50/AC50,0) -> 0
S51: =+Q51*R51 -> 0 | T51: 0 | U51: =S51*(1-T51) -> 0 | V51: EUR | W51: =IFERROR(VLOOKUP(V51,[1]Curr!$B$2:$C$13,2,FALSE),0) -> 11.3 | X51: =U51*W51 -> 0 | Y51: =Q51 -> 0 | Z51: =+Y51*R51 -> 0 | AA51: EUR | AB51: =IFERROR(VLOOKUP(AA51,Curr!$B$2:$C$13,2,FALSE),0) -> 11.3 | AC51: =+Y51*AB51*R51 -> 0 | AD51: =+AC51-X51 -> 0 | AE51: =IFERROR(AD51/AC51,0) -> 0
S52: =+Q52*R52 -> 0 | T52: 0 | U52: =S52*(1-T52) -> 0 | V52: EUR | W52: =IFERROR(VLOOKUP(V52,[1]Curr!$B$2:$C$13,2,FALSE),0) -> 11.3 | X52: =U52*W52 -> 0 | Y52: =Q52 -> 0 | Z52: =+Y52*R52 -> 0 | AA52: EUR | AB52: =IFERROR(VLOOKUP(AA52,Curr!$B$2:$C$13,2,FALSE),0) -> 11.3 | AC52: =+Y52*AB52*R52 -> 0 | AD52: =+AC52-X52 -> 0 | AE52: =IFERROR(AD52/AC52,0) -> 0
S53: =+Q53*R53 -> 0 | T53: 0 | U53: =S53*(1-T53) -> 0 | V53: EUR | W53: =IFERROR(VLOOKUP(V53,[1]Curr!$B$2:$C$13,2,FALSE),0) -> 11.3 | X53: =U53*W53 -> 0 | Y53: =Q53 -> 0 | Z53: =+Y53*R53 -> 0 | AA53: EUR | AB53: =IFERROR(VLOOKUP(AA53,Curr!$B$2:$C$13,2,FALSE),0) -> 11.3 | AC53: =+Y53*AB53*R53 -> 0 | AD53: =+AC53-X53 -> 0 | AE53: =IFERROR(AD53/AC53,0) -> 0
S54: =+Q54*R54 -> 0 | T54: 0 | U54: =S54*(1-T54) -> 0 | V54: EUR | W54: =IFERROR(VLOOKUP(V54,[1]Curr!$B$2:$C$13,2,FALSE),0) -> 11.3 | X54: =U54*W54 -> 0 | Y54: =Q54 -> 0 | Z54: =+Y54*R54 -> 0 | AA54: EUR | AB54: =IFERROR(VLOOKUP(AA54,Curr!$B$2:$C$13,2,FALSE),0) -> 11.3 | AC54: =+Y54*AB54*R54 -> 0 | AD54: =+AC54-X54 -> 0 | AE54: =IFERROR(AD54/AC54,0) -> 0
S55: =+Q55*R55 -> 0 | T55: 0 | U55: =S55*(1-T55) -> 0 | V55: EUR | W55: =IFERROR(VLOOKUP(V55,[1]Curr!$B$2:$C$13,2,FALSE),0) -> 11.3 | X55: =U55*W55 -> 0 | Y55: =Q55 -> 0 | Z55: =+Y55*R55 -> 0 | AA55: EUR | AB55: =IFERROR(VLOOKUP(AA55,Curr!$B$2:$C$13,2,FALSE),0) -> 11.3 | AC55: =+Y55*AB55*R55 -> 0 | AD55: =+AC55-X55 -> 0 | AE55: =IFERROR(AD55/AC55,0) -> 0
S56: =+Q56*R56 -> 0 | T56: 0 | U56: =S56*(1-T56) -> 0 | V56: EUR | W56: =IFERROR(VLOOKUP(V56,[1]Curr!$B$2:$C$13,2,FALSE),0) -> 11.3 | X56: =U56*W56 -> 0 | Y56: =Q56 -> 0 | Z56: =+Y56*R56 -> 0 | AA56: EUR | AB56: =IFERROR(VLOOKUP(AA56,Curr!$B$2:$C$13,2,FALSE),0) -> 11.3 | AC56: =+Y56*AB56*R56 -> 0 | AD56: =+AC56-X56 -> 0 | AE56: =IFERROR(AD56/AC56,0) -> 0
S57: =+Q57*R57 -> 0 | T57: 0 | U57: =S57*(1-T57) -> 0 | V57: EUR | W57: =IFERROR(VLOOKUP(V57,[1]Curr!$B$2:$C$13,2,FALSE),0) -> 11.3 | X57: =U57*W57 -> 0 | Y57: =Q57 -> 0 | Z57: =+Y57*R57 -> 0 | AA57: EUR | AB57: =IFERROR(VLOOKUP(AA57,Curr!$B$2:$C$13,2,FALSE),0) -> 11.3 | AC57: =+Y57*AB57*R57 -> 0 | AD57: =+AC57-X57 -> 0 | AE57: =IFERROR(AD57/AC57,0) -> 0
S58: =+Q58*R58 -> 0 | T58: 0 | U58: =S58*(1-T58) -> 0 | V58: EUR | W58: =IFERROR(VLOOKUP(V58,[1]Curr!$B$2:$C$13,2,FALSE),0) -> 11.3 | X58: =U58*W58 -> 0 | Y58: =Q58 -> 0 | Z58: =+Y58*R58 -> 0 | AA58: EUR | AB58: =IFERROR(VLOOKUP(AA58,Curr!$B$2:$C$13,2,FALSE),0) -> 11.3 | AC58: =+Y58*AB58*R58 -> 0 | AD58: =+AC58-X58 -> 0 | AE58: =IFERROR(AD58/AC58,0) -> 0
B60: Totals | D60: x | E60: x | F60: x | G60: x | H60: x | I60: x | J60: x | K60: x | L60: x | M60: x | N60: x | O60: x | P60: x | Q60: x | R60: x | S60: x | T60: x | U60: x | V60: x | W60: x | X60: x | Y60: x | Z60: =SUM(Z7:Z58) -> 4928.5585 | AC60: =SUM(AC7:AC58) -> 55692.711 | AD60: =SUM(AD7:AD58) -> 10367.111 | AE60: =IFERROR(AD60/AC60,0) -> 0.18614843 | AF60: =SUM(AF8:AF59) -> 0 | AG60: =SUM(AG8:AG59) -> 0 | AH60: =SUM(AH8:AH59) -> 0 | AI60: =SUM(AI8:AI59) -> 0 | AJ60: =SUM(AJ8:AJ59) -> 0
Y62: Fixed | Z62: =Z12+Z14+Z16+Z18+Z21+Z26+Z28+Z31 -> 2599.882
Y63: Variable | Z63: =Z9+Z23+Z35 -> 2328.6765
Y64: Total | Z64: 4940
Y65: PP | Z65: =Z64/2 -> 2470
Y68: Shoulder | Z68: =Z64 -> 4940
Y69: High | Z69: =Z68*1.18 -> 5829.2
Y70: X-mas | Z70: =Z68*1.3 -> 6422
Y71: Low | Z71: =Z68*0.85 -> 4199

Sheet 1205
B1: Places: 1N Helsinki - 1N Santa Express - 2N Rovaniemi - 2N Tromsø - 1N Lyngen - 1N Tromsø
B2: Dates: Winter
B3: Pax: 2
B4: Rooming: Double
B6: ID | C6: Day | D6: Type | E6: From date | F6: To date | G6: From time | H6: To time | I6: Supplier | J6: Travel element | K6: Manual booking? | L6: Status | M6: Comments | N6: Non-refundable | O6: Refundable | P6: URL | Q6: Gross P per unit | R6: Units | S6: Gross P | T6: Supp Comm | U6: Net P | V6: Supp curr | W6: X-rate | X6: Net P NOK | Y6: Sales P per unit | Z6: Price | AA6: Sales curr | AB6: X-rate | AC6: Sales P NOK tot | AD6: GP NOK | AE6: GP % | AF6: VAT25 | AG6: VAT15 | AH6: VAT12 | AI6: VAT0-D | AJ6: VAT0-I
C7: Day 1 | D7: Arrival | J7: Helsinki: Welcome to Finland | Q7: 0 | R7: 0 | S7: =+Q7*R7 -> 0 | T7: 0 | U7: =S7*(1-T7) -> 0 | V7: EUR | W7: =IFERROR(VLOOKUP(V7,[1]Curr!$B$2:$C$13,2,FALSE),0) -> 11.3 | X7: =U7*W7 -> 0 | Y7: =Q7 -> 0 | Z7: =+Y7*R7 -> 0 | AA7: EUR | AB7: =IFERROR(VLOOKUP(AA7,Curr!$B$2:$C$13,2,FALSE),0) -> 11.3 | AC7: =+Y7*AB7*R7 -> 0 | AD7: =+AC7-X7 -> 0 | AE7: =IFERROR(AD7/AC7,0) -> 0
C8: Day 1 | D8: Transfer | J8: Helsinki: Self transfer to your accommodation | Q8: 0 | R8: 0 | S8: =+Q8*R8 -> 0 | T8: 0 | U8: =S8*(1-T8) -> 0 | V8: EUR | W8: =IFERROR(VLOOKUP(V8,[1]Curr!$B$2:$C$13,2,FALSE),0) -> 11.3 | X8: =U8*W8 -> 0 | Y8: =Q8/0.8 -> 0 | Z8: =+Y8*R8 -> 0 | AA8: EUR | AB8: =IFERROR(VLOOKUP(AA8,Curr!$B$2:$C$13,2,FALSE),0) -> 11.3 | AC8: =+Y8*AB8*R8 -> 0 | AD8: =+AC8-X8 -> 0 | AE8: =IFERROR(AD8/AC8,0) -> 0
C9: Day 1 | D9: Hotel | J9: Helsinki: Check in to your accommodation for a 1 night stay - Centrally Located 3/4-star Hotel - Standard Room - Breakfast included | Q9: 150 | R9: 1 | S9: =+Q9*R9 -> 150 | T9: 0 | U9: =S9*(1-T9) -> 150 | V9: EUR | W9: =IFERROR(VLOOKUP(V9,[1]Curr!$B$2:$C$13,2,FALSE),0) -> 11.3 | X9: =U9*W9 -> 1695 | Y9: =Q9/0.8 -> 187.5 | Z9: =+Y9*R9 -> 187.5 | AA9: EUR | AB9: =IFERROR(VLOOKUP(AA9,Curr!$B$2:$C$13,2,FALSE),0) -> 11.3 | AC9: =+Y9*AB9*R9 -> 2118.75 | AD9: =+AC9-X9 -> 423.75 | AE9: =IFERROR(AD9/AC9,0) -> 0.2
C10: Day 1 | D10: Leisure | J10: Helsinki: Spend time at leisure | Q10: 0 | R10: 0 | S10: =+Q10*R10 -> 0 | T10: 0 | U10: =S10*(1-T10) -> 0 | V10: EUR | W10: =IFERROR(VLOOKUP(V10,[1]Curr!$B$2:$C$13,2,FALSE),0) -> 11.3 | X10: =U10*W10 -> 0 | Y10: =Q10 -> 0 | Z10: =+Y10*R10 -> 0 | AA10: EUR | AB10: =IFERROR(VLOOKUP(AA10,Curr!$B$2:$C$13,2,FALSE),0) -> 11.3 | AC10: =+Y10*AB10*R10 -> 0 | AD10: =+AC10-X10 -> 0 | AE10: =IFERROR(AD10/AC10,0) -> 0
S11: =+Q11*R11 -> 0 | T11: 0 | U11: =S11*(1-T11) -> 0 | V11: EUR | W11: =IFERROR(VLOOKUP(V11,[1]Curr!$B$2:$C$13,2,FALSE),0) -> 11.3 | X11: =U11*W11 -> 0 | Y11: =Q11 -> 0 | Z11: =+Y11*R11 -> 0 | AA11: EUR | AB11: =IFERROR(VLOOKUP(AA11,Curr!$B$2:$C$13,2,FALSE),0) -> 11.3 | AC11: =+Y11*AB11*R11 -> 0 | AD11: =+AC11-X11 -> 0 | AE11: =IFERROR(AD11/AC11,0) -> 0
C12: Day 2 | D12: Activity | J12: Helsinki: A Finntastic Walking Tour - Time: 10:30 am / 1:30 pm - 12:45 pm / 3:45 pm - Meeting point: Senate Square (Look for a blue and white umbrella) - End point: Helsinki Central Library Oodi - Notable Sights: Senate Square, Helsinki Cathedral, Kauppatori, Uspenski Cathedral, Esplanadi Park and more - Includes: Professional authorised Helsinki Guide, Liability Insurance | O12: x | P12: https://www.finntastictours.fi/# | Q12: 20 | R12: 2 | S12: =+Q12*R12 -> 40 | T12: 0 | U12: =S12*(1-T12) -> 40 | V12: EUR | W12: 11.3 | X12: =U12*W12 -> 452 | Y12: 35.087719 | Z12: =+Y12*R12 -> 70.175439 | AA12: EUR | AB12: =IFERROR(VLOOKUP(AA12,Curr!$B$2:$C$13,2,FALSE),0) -> 11.3 | AC12: =+Y12*AB12*R12 -> 792.98246 | AD12: =+AC12-X12 -> 340.98246 | AE12: =IFERROR(AD12/AC12,0) -> 0.43
C13: Day 2 | D13: Transfer | J13: Helsinki: Self transfer to Helsinki Central Station | Q13: 0 | R13: 0 | S13: =+Q13*R13 -> 0 | T13: 0 | U13: =S13*(1-T13) -> 0 | V13: EUR | W13: 11.3 | X13: =U13*W13 -> 0 | Y13: =Q13 -> 0 | Z13: =+Y13*R13 -> 0 | AA13: EUR | AB13: =IFERROR(VLOOKUP(AA13,Curr!$B$2:$C$13,2,FALSE),0) -> 11.3 | AC13: =+Y13*AB13*R13 -> 0 | AD13: =+AC13-X13 -> 0 | AE13: =IFERROR(AD13/AC13,0) -> 0
C14: Day 2 | D14: Train | J14: Helsinki: Overnight Santa Claus Express Train to Rovaniemi - Time: 11:13 pm - 10:59 am - Includes: Upstairs Sleeper Cabin with Private Bathroom | N14: x | P14: https://www.vr.fi/en/santa-claus-express | Q14: 200 | R14: 1 | S14: =+Q14*R14 -> 200 | T14: 0 | U14: =S14*(1-T14) -> 200 | V14: EUR | W14: 11.3 | X14: =U14*W14 -> 2260 | Y14: =Q14/0.8 -> 250 | Z14: =+Y14*R14 -> 250 | AA14: EUR | AB14: =IFERROR(VLOOKUP(AA14,Curr!$B$2:$C$13,2,FALSE),0) -> 11.3 | AC14: =+Y14*AB14*R14 -> 2825 | AD14: =+AC14-X14 -> 565 | AE14: =IFERROR(AD14/AC14,0) -> 0.2
S15: =+Q15*R15 -> 0 | T15: 0 | U15: =S15*(1-T15) -> 0 | V15: EUR | W15: =IFERROR(VLOOKUP(V15,[1]Curr!$B$2:$C$13,2,FALSE),0) -> 11.3 | X15: =U15*W15 -> 0 | Y15: =Q15 -> 0 | Z15: =+Y15*R15 -> 0 | AA15: EUR | AB15: =IFERROR(VLOOKUP(AA15,Curr!$B$2:$C$13,2,FALSE),0) -> 11.3 | AC15: =+Y15*AB15*R15 -> 0 | AD15: =+AC15-X15 -> 0 | AE15: =IFERROR(AD15/AC15,0) -> 0
C16: Day 3 | D16: Transfer | J16: Rovaniemi: Self transfer to your accommodation | Q16: 0 | R16: 0 | S16: =+Q16*R16 -> 0 | T16: 0 | U16: =S16*(1-T16) -> 0 | V16: EUR | W16: =IFERROR(VLOOKUP(V16,[1]Curr!$B$2:$C$13,2,FALSE),0) -> 11.3 | X16: =U16*W16 -> 0 | Y16: =Q16/0.8 -> 0 | Z16: =+Y16*R16 -> 0 | AA16: EUR | AB16: =IFERROR(VLOOKUP(AA16,Curr!$B$2:$C$13,2,FALSE),0) -> 11.3 | AC16: =+Y16*AB16*R16 -> 0 | AD16: =+AC16-X16 -> 0 | AE16: =IFERROR(AD16/AC16,0) -> 0
C17: Day 3 | D17: Hotel | J17: Rovaniemi: Check in to your accommodation for a 2 night stay - Centrally Located 3/4-star Hotel - Standard Room - Breakfast included | Q17: 600 | R17: 1 | S17: =+Q17*R17 -> 600 | T17: 0 | U17: =S17*(1-T17) -> 600 | V17: EUR | W17: =IFERROR(VLOOKUP(V17,[1]Curr!$B$2:$C$13,2,FALSE),0) -> 11.3 | X17: =U17*W17 -> 6780 | Y17: =Q17/0.85 -> 705.88235 | Z17: =+Y17*R17 -> 705.88235 | AA17: EUR | AB17: =IFERROR(VLOOKUP(AA17,Curr!$B$2:$C$13,2,FALSE),0) -> 11.3 | AC17: =+Y17*AB17*R17 -> 7976.4706 | AD17: =+AC17-X17 -> 1196.4706 | AE17: =IFERROR(AD17/AC17,0) -> 0.15
C18: Day 3 | D18: Leisure | J18: Rovaniemi: Spend time at leisure | Q18: 0 | R18: 0 | S18: =+Q18*R18 -> 0 | T18: 0 | U18: =S18*(1-T18) -> 0 | V18: EUR | W18: =IFERROR(VLOOKUP(V18,[1]Curr!$B$2:$C$13,2,FALSE),0) -> 11.3 | X18: =U18*W18 -> 0 | Y18: =Q18 -> 0 | Z18: =+Y18*R18 -> 0 | AA18: EUR | AB18: =IFERROR(VLOOKUP(AA18,Curr!$B$2:$C$13,2,FALSE),0) -> 11.3 | AC18: =+Y18*AB18*R18 -> 0 | AD18: =+AC18-X18 -> 0 | AE18: =IFERROR(AD18/AC18,0) -> 0
C19: Day 3 | D19: Activity | J19: Rovaniemi: Northern Lights Unlimited Mileage Photo Tour - Time: 08:00 pm - 01:00 am - Meeting point: Book Lapland Office - Includes: Pick-up/drop-off in central Rovaniemi, Knowledgeable, English-speaking guides, Professional DSLR photography (unlimited), Meteorological observations, Thermal winter clothing, Hot drinks & snacks or cookies | O19: x | P19: https://booknordics.com/finland/western-lapland/rovaniemi/rovaniemi-northern-lights-family-tour-by-bus-with-photos | Q19: 109 | R19: 2 | S19: =+Q19*R19 -> 218 | T19: 0.2 | U19: =S19*(1-T19) -> 174.4 | V19: EUR | W19: =IFERROR(VLOOKUP(V19,[1]Curr!$B$2:$C$13,2,FALSE),0) -> 11.3 | X19: =U19*W19 -> 1970.72 | Y19: =Q19 -> 109 | Z19: =+Y19*R19 -> 218 | AA19: EUR | AB19: =IFERROR(VLOOKUP(AA19,Curr!$B$2:$C$13,2,FALSE),0) -> 11.3 | AC19: =+Y19*AB19*R19 -> 2463.4 | AD19: =+AC19-X19 -> 492.68 | AE19: =IFERROR(AD19/AC19,0) -> 0.2
S20: =+Q20*R20 -> 0 | T20: 0 | U20: =S20*(1-T20) -> 0 | V20: EUR | W20: =IFERROR(VLOOKUP(V20,[1]Curr!$B$2:$C$13,2,FALSE),0) -> 11.3 | X20: =U20*W20 -> 0 | Y20: =Q20 -> 0 | Z20: =+Y20*R20 -> 0 | AA20: EUR | AB20: =IFERROR(VLOOKUP(AA20,Curr!$B$2:$C$13,2,FALSE),0) -> 11.3 | AC20: =+Y20*AB20*R20 -> 0 | AD20: =+AC20-X20 -> 0 | AE20: =IFERROR(AD20/AC20,0) -> 0
C21: Day 4 | D21: Activity | J21: Rovaniemi: Arctic Circle Highlights Adventure Day - Time: 08:45 am - 2:45 pm - Meeting point: Arctic Circle Snowmobile Park office - Includes: Pick-up/drop-off in central Rovaniemi, Reindeer Farm visit with sleigh ride (2-3 pers), Reindeer sledge driver’s license reward, Alaskan Husky visit with sleigh ride (4 pers), Approx. 2 hours free time in Santa Claus Village, Winter clothes (overalls, boots and gloves), Traditional salmon soup or vegetarian option | O21: x | P21: https://booknordics.com/finland/western-lapland/rovaniemi/arctic-circle-highlights-family-day-by-minibus | Q21: 188 | R21: 2 | S21: =+Q21*R21 -> 376 | T21: 0.2 | U21: =S21*(1-T21) -> 300.8 | V21: EUR | W21: 11.3 | X21: =U21*W21 -> 3399.04 | Y21: 188 | Z21: =+Y21*R21 -> 376 | AA21: EUR | AB21: =IFERROR(VLOOKUP(AA21,Curr!$B$2:$C$13,2,FALSE),0) -> 11.3 | AC21: =+Y21*AB21*R21 -> 4248.8 | AD21: =+AC21-X21 -> 849.76 | AE21: =IFERROR(AD21/AC21,0) -> 0.2
C22: Day 4 | D22: Leisure | J22: Rovaniemi: Spend time at leisure | Q22: 0 | R22: 0 | S22: =+Q22*R22 -> 0 | T22: 0 | U22: =S22*(1-T22) -> 0 | V22: EUR | W22: 11.3 | X22: =U22*W22 -> 0 | Y22: 0 | Z22: =+Y22*R22 -> 0 | AA22: EUR | AB22: =IFERROR(VLOOKUP(AA22,Curr!$B$2:$C$13,2,FALSE),0) -> 11.3 | AC22: =+Y22*AB22*R22 -> 0 | AD22: =+AC22-X22 -> 0 | AE22: =IFERROR(AD22/AC22,0) -> 0
C23: Day 4 | D23: Activity | J23: Rovaniemi: Small-Group Aurora Hunt by Minibus - Time: 7:00 pm - 10:00 pm - Meeting point: Lapland Royal Adventures Office - Includes: Pick-up/drop-off from central Rovaniemi, Knowledgeable, English-speaking guide, Dedicated Northern Lights chase by minibus, Cozy blankets, hot drinks and a snack | O23: x | P23: https://booknordics.com/finland/western-lapland/rovaniemi/aurora-quest-by-minibus | Q23: 89 | R23: 2 | S23: =+Q23*R23 -> 178 | T23: 0.2 | U23: =S23*(1-T23) -> 142.4 | V23: EUR | W23: 11.3 | X23: =U23*W23 -> 1609.12 | Y23: 89 | Z23: =+Y23*R23 -> 178 | AA23: EUR | AB23: =IFERROR(VLOOKUP(AA23,Curr!$B$2:$C$13,2,FALSE),0) -> 11.3 | AC23: =+Y23*AB23*R23 -> 2011.4 | AD23: =+AC23-X23 -> 402.28 | AE23: =IFERROR(AD23/AC23,0) -> 0.2
S24: =+Q24*R24 -> 0 | T24: 0 | U24: =S24*(1-T24) -> 0 | V24: EUR | W24: =IFERROR(VLOOKUP(V24,[1]Curr!$B$2:$C$13,2,FALSE),0) -> 11.3 | X24: =U24*W24 -> 0 | Y24: =Q24 -> 0 | Z24: =+Y24*R24 -> 0 | AA24: EUR | AB24: =IFERROR(VLOOKUP(AA24,Curr!$B$2:$C$13,2,FALSE),0) -> 11.3 | AC24: =+Y24*AB24*R24 -> 0 | AD24: =+AC24-X24 -> 0 | AE24: =IFERROR(AD24/AC24,0) -> 0
C25: Day 5 | D25: Transfer | J25: Rovaniemi: Self transfer to Rovaniemi Bus Station | Q25: 0 | R25: 0 | S25: =+Q25*R25 -> 0 | T25: 0 | U25: =S25*(1-T25) -> 0 | V25: EUR | W25: =IFERROR(VLOOKUP(V25,[1]Curr!$B$2:$C$13,2,FALSE),0) -> 11.3 | X25: =U25*W25 -> 0 | Y25: =Q25 -> 0 | Z25: =+Y25*R25 -> 0 | AA25: EUR | AB25: =IFERROR(VLOOKUP(AA25,Curr!$B$2:$C$13,2,FALSE),0) -> 11.3 | AC25: =+Y25*AB25*R25 -> 0 | AD25: =+AC25-X25 -> 0 | AE25: =IFERROR(AD25/AC25,0) -> 0
C26: Day 5 | D26: Activity | J26: Rovaniemi: Arctic Route Coach Transfer to Tromsø - Time: 11:40 am - 7:30 pm - Includes: Tickets | O26: x | P26: https://bestarctic.com/the-arctic-route/arctic-winter-routes-explore-norway-sweden-and-finland/bus-between-tromso-norway-and-rovaniemi-finland/ | Q26: 1830 | R26: 2 | S26: =+Q26*R26 -> 3660 | T26: 0.2 | U26: =S26*(1-T26) -> 2928 | V26: NOK | W26: =IFERROR(VLOOKUP(V26,[1]Curr!$B$2:$C$13,2,FALSE),0) -> 1 | X26: =U26*W26 -> 2928 | Y26: =Q26/11.3/0.9 -> 179.941 | Z26: =+Y26*R26 -> 359.88201 | AA26: EUR | AB26: =IFERROR(VLOOKUP(AA26,Curr!$B$2:$C$13,2,FALSE),0) -> 11.3 | AC26: =+Y26*AB26*R26 -> 4066.6667 | AD26: =+AC26-X26 -> 1138.6667 | AE26: =IFERROR(AD26/AC26,0) -> 0.28
C27: Day 5 | D27: Transfer | J27: Tromsø: Self transfer to your accommodation | Q27: 0 | R27: 0 | S27: =+Q27*R27 -> 0 | T27: 0 | U27: =S27*(1-T27) -> 0 | V27: EUR | W27: =IFERROR(VLOOKUP(V27,[1]Curr!$B$2:$C$13,2,FALSE),0) -> 11.3 | X27: =U27*W27 -> 0 | Y27: =Q27 -> 0 | Z27: =+Y27*R27 -> 0 | AA27: EUR | AB27: =IFERROR(VLOOKUP(AA27,Curr!$B$2:$C$13,2,FALSE),0) -> 11.3 | AC27: =+Y27*AB27*R27 -> 0 | AD27: =+AC27-X27 -> 0 | AE27: =IFERROR(AD27/AC27,0) -> 0
C28: Day 5 | D28: Hotel | J28: Tromsø: Check in to your accommodation for a 2 night stay - Centrally Located 3/4-star Hotel - Standard Room - Breakfast included | Q28: 500 | R28: 1 | S28: =+Q28*R28 -> 500 | T28: 0 | U28: =S28*(1-T28) -> 500 | V28: EUR | W28: =IFERROR(VLOOKUP(V28,[1]Curr!$B$2:$C$13,2,FALSE),0) -> 11.3 | X28: =U28*W28 -> 5650 | Y28: =Q28/0.85 -> 588.23529 | Z28: =+Y28*R28 -> 588.23529 | AA28: EUR | AB28: =IFERROR(VLOOKUP(AA28,Curr!$B$2:$C$13,2,FALSE),0) -> 11.3 | AC28: =+Y28*AB28*R28 -> 6647.0588 | AD28: =+AC28-X28 -> 997.05882 | AE28: =IFERROR(AD28/AC28,0) -> 0.15
C29: Day 5 | D29: Leisure | J29: Tromsø: Spend time at leisure | Q29: 0 | R29: 0 | S29: =+Q29*R29 -> 0 | T29: 0 | U29: =S29*(1-T29) -> 0 | V29: EUR | W29: =IFERROR(VLOOKUP(V29,[1]Curr!$B$2:$C$13,2,FALSE),0) -> 11.3 | X29: =U29*W29 -> 0 | Y29: =Q29 -> 0 | Z29: =+Y29*R29 -> 0 | AA29: EUR | AB29: =IFERROR(VLOOKUP(AA29,Curr!$B$2:$C$13,2,FALSE),0) -> 11.3 | AC29: =+Y29*AB29*R29 -> 0 | AD29: =+AC29-X29 -> 0 | AE29: =IFERROR(AD29/AC29,0) -> 0
S30: =+Q30*R30 -> 0 | T30: 0 | U30: =S30*(1-T30) -> 0 | V30: EUR | W30: =IFERROR(VLOOKUP(V30,[1]Curr!$B$2:$C$13,2,FALSE),0) -> 11.3 | X30: =U30*W30 -> 0 | Y30: =Q30 -> 0 | Z30: =+Y30*R30 -> 0 | AA30: EUR | AB30: =IFERROR(VLOOKUP(AA30,Curr!$B$2:$C$13,2,FALSE),0) -> 11.3 | AC30: =+Y30*AB30*R30 -> 0 | AD30: =+AC30-X30 -> 0 | AE30: =IFERROR(AD30/AC30,0) -> 0
C31: Day 6 | D31: Activity | J31: Tromsø: Photo Tour to Arctic Landscapes and Fjords - Time: 10:00 am - 3:00 pm - Meeting point: Roald Amundsens plass 1A - Includes: Departure from central Tromsø. Drop-off to your hotel, Professional, English-speaking photo guides, Scenic fjord safari by comfortable minivan vehicle, Help with camera settings and nature photography, Usually a small-group experience with 4-8 guests, Soup or expedition food, coffee and waffles/cookies | O31: x | P31: https://booknordics.com/norway/northern-norway/tromso-region/tromso-fjord-photo-tour | Q31: 145 | R31: 2 | S31: =+Q31*R31 -> 290 | T31: 0.2 | U31: =S31*(1-T31) -> 232 | V31: EUR | W31: =IFERROR(VLOOKUP(V31,[1]Curr!$B$2:$C$13,2,FALSE),0) -> 11.3 | X31: =U31*W31 -> 2621.6 | Y31: =Q31 -> 145 | Z31: =+Y31*R31 -> 290 | AA31: EUR | AB31: =IFERROR(VLOOKUP(AA31,Curr!$B$2:$C$13,2,FALSE),0) -> 11.3 | AC31: =+Y31*AB31*R31 -> 3277 | AD31: =+AC31-X31 -> 655.4 | AE31: =IFERROR(AD31/AC31,0) -> 0.2
C32: Day 6 | D32: Leisure | J32: Tromsø: Spend time at leisure | Q32: 0 | R32: 0 | S32: =+Q32*R32 -> 0 | T32: 0 | U32: =S32*(1-T32) -> 0 | V32: EUR | W32: =IFERROR(VLOOKUP(V32,[1]Curr!$B$2:$C$13,2,FALSE),0) -> 11.3 | X32: =U32*W32 -> 0 | Y32: =Q32 -> 0 | Z32: =+Y32*R32 -> 0 | AA32: EUR | AB32: =IFERROR(VLOOKUP(AA32,Curr!$B$2:$C$13,2,FALSE),0) -> 11.3 | AC32: =+Y32*AB32*R32 -> 0 | AD32: =+AC32-X32 -> 0 | AE32: =IFERROR(AD32/AC32,0) -> 0
C33: Day 6 | D33: Activity | J33: Tromsø: Northern Lights Cruise with Silent Electric Ship - Time: 7:00 pm - 10:00 pm - Meeting point: Kaigata 6 - Includes: Departure from central Tromsø, 3-hour fjord cruise, Light meal (soup and bread) and water, English speaking guides, Warm indoor saloons, Free wifi, Toilets | O33: x | P33: https://booknordics.com/norway/northern-norway/tromso-region/northern-lights-cruise-electric-ship | Q33: 105 | R33: 2 | S33: =+Q33*R33 -> 210 | T33: 0.2 | U33: =S33*(1-T33) -> 168 | V33: EUR | W33: =IFERROR(VLOOKUP(V33,[1]Curr!$B$2:$C$13,2,FALSE),0) -> 11.3 | X33: =U33*W33 -> 1898.4 | Y33: =Q33 -> 105 | Z33: =+Y33*R33 -> 210 | AA33: EUR | AB33: =IFERROR(VLOOKUP(AA33,Curr!$B$2:$C$13,2,FALSE),0) -> 11.3 | AC33: =+Y33*AB33*R33 -> 2373 | AD33: =+AC33-X33 -> 474.6 | AE33: =IFERROR(AD33/AC33,0) -> 0.2
S34: =+Q34*R34 -> 0 | T34: 0 | U34: =S34*(1-T34) -> 0 | V34: EUR | W34: =IFERROR(VLOOKUP(V34,[1]Curr!$B$2:$C$13,2,FALSE),0) -> 11.3 | X34: =U34*W34 -> 0 | Y34: =Q34 -> 0 | Z34: =+Y34*R34 -> 0 | AA34: EUR | AB34: =IFERROR(VLOOKUP(AA34,Curr!$B$2:$C$13,2,FALSE),0) -> 11.3 | AC34: =+Y34*AB34*R34 -> 0 | AD34: =+AC34-X34 -> 0 | AE34: =IFERROR(AD34/AC34,0) -> 0
C35: Day 7 | D35: Transfer | J35: Tromsø: Self transfer to Scandic Ishavs Hotel | Q35: 0 | R35: 0 | S35: =+Q35*R35 -> 0 | T35: 0 | U35: =S35*(1-T35) -> 0 | V35: EUR | W35: =IFERROR(VLOOKUP(V35,[1]Curr!$B$2:$C$13,2,FALSE),0) -> 11.3 | X35: =U35*W35 -> 0 | Y35: =Q35 -> 0 | Z35: =+Y35*R35 -> 0 | AA35: EUR | AB35: =IFERROR(VLOOKUP(AA35,Curr!$B$2:$C$13,2,FALSE),0) -> 11.3 | AC35: =+Y35*AB35*R35 -> 0 | AD35: =+AC35-X35 -> 0 | AE35: =IFERROR(AD35/AC35,0) -> 0
C36: Day 7 | D36: Activity | J36: Tromsø: Crystal Lavvo Stay with Auroras, Meals & Activities - Time: 11:30 am - 10: 50 am (the next day) - Meeting point: Samuel Arnesens gate 5 - Includes: Pick-up/drop-off in Tromsø with scenic transfers, Comfortable overnight stay in crystal lavvo, Fireplace heating with unlimited firewood, Northern Lights hunt with photo workshop, Snowshoeing experience nearby, Lunch and dinner included on day 1, Bathroom/toilet facilities in the main house, Breakfast and return transfer included on day 2 | O36: x | P36: https://booknordics.com/norway/northern-norway/tromso-region/crystal-lavvy-stay-northern-lights-snowshoeing | Q36: 375 | R36: 2 | S36: =+Q36*R36 -> 750 | T36: 0.2 | U36: =S36*(1-T36) -> 600 | V36: EUR | W36: =IFERROR(VLOOKUP(V36,[1]Curr!$B$2:$C$13,2,FALSE),0) -> 11.3 | X36: =U36*W36 -> 6780 | Y36: =Q36 -> 375 | Z36: =+Y36*R36 -> 750 | AA36: EUR | AB36: =IFERROR(VLOOKUP(AA36,Curr!$B$2:$C$13,2,FALSE),0) -> 11.3 | AC36: =+Y36*AB36*R36 -> 8475 | AD36: =+AC36-X36 -> 1695 | AE36: =IFERROR(AD36/AC36,0) -> 0.2
S37: =+Q37*R37 -> 0 | T37: 0 | U37: =S37*(1-T37) -> 0 | V37: EUR | W37: =IFERROR(VLOOKUP(V37,[1]Curr!$B$2:$C$13,2,FALSE),0) -> 11.3 | X37: =U37*W37 -> 0 | Y37: =Q37 -> 0 | Z37: =+Y37*R37 -> 0 | AA37: EUR | AB37: =IFERROR(VLOOKUP(AA37,Curr!$B$2:$C$13,2,FALSE),0) -> 11.3 | AC37: =+Y37*AB37*R37 -> 0 | AD37: =+AC37-X37 -> 0 | AE37: =IFERROR(AD37/AC37,0) -> 0
C38: Day 8 | D38: Transfer | J38: Lyngen: Shuttle transfer back to Scandic Ishavs Hotel in Tromsø | Q38: 0 | R38: 0 | S38: =+Q38*R38 -> 0 | T38: 0 | U38: =S38*(1-T38) -> 0 | V38: EUR | W38: =IFERROR(VLOOKUP(V38,[1]Curr!$B$2:$C$13,2,FALSE),0) -> 11.3 | X38: =U38*W38 -> 0 | Y38: =Q38 -> 0 | Z38: =+Y38*R38 -> 0 | AA38: EUR | AB38: =IFERROR(VLOOKUP(AA38,Curr!$B$2:$C$13,2,FALSE),0) -> 11.3 | AC38: =+Y38*AB38*R38 -> 0 | AD38: =+AC38-X38 -> 0 | AE38: =IFERROR(AD38/AC38,0) -> 0
C39: Day 8 | D39: Transfer | J39: Tromsø: Self transfer to your accommodation | Q39: 0 | R39: 0 | S39: =+Q39*R39 -> 0 | T39: 0 | U39: =S39*(1-T39) -> 0 | V39: EUR | W39: =IFERROR(VLOOKUP(V39,[1]Curr!$B$2:$C$13,2,FALSE),0) -> 11.3 | X39: =U39*W39 -> 0 | Y39: =Q39 -> 0 | Z39: =+Y39*R39 -> 0 | AA39: EUR | AB39: =IFERROR(VLOOKUP(AA39,Curr!$B$2:$C$13,2,FALSE),0) -> 11.3 | AC39: =+Y39*AB39*R39 -> 0 | AD39: =+AC39-X39 -> 0 | AE39: =IFERROR(AD39/AC39,0) -> 0
C40: Day 8 | D40: Hotel | J40: Tromsø: Check in to your accommodation for a 1 night stay - Centrally Located 3/4-star Hotel - Standard Room - Breakfast included | Q40: 310 | R40: 1 | S40: =+Q40*R40 -> 310 | T40: 0 | U40: =S40*(1-T40) -> 310 | V40: EUR | W40: =IFERROR(VLOOKUP(V40,[1]Curr!$B$2:$C$13,2,FALSE),0) -> 11.3 | X40: =U40*W40 -> 3503 | Y40: =Q40/0.85 -> 364.70588 | Z40: =+Y40*R40 -> 364.70588 | AA40: EUR | AB40: =IFERROR(VLOOKUP(AA40,Curr!$B$2:$C$13,2,FALSE),0) -> 11.3 | AC40: =+Y40*AB40*R40 -> 4121.1765 | AD40: =+AC40-X40 -> 618.17647 | AE40: =IFERROR(AD40/AC40,0) -> 0.15
C41: Day 8 | D41: Leisure | J41: Tromsø: Spend time at leisure | Q41: 0 | R41: 0 | S41: =+Q41*R41 -> 0 | T41: 0 | U41: =S41*(1-T41) -> 0 | V41: EUR | W41: =IFERROR(VLOOKUP(V41,[1]Curr!$B$2:$C$13,2,FALSE),0) -> 11.3 | X41: =U41*W41 -> 0 | Y41: =Q41 -> 0 | Z41: =+Y41*R41 -> 0 | AA41: EUR | AB41: =IFERROR(VLOOKUP(AA41,Curr!$B$2:$C$13,2,FALSE),0) -> 11.3 | AC41: =+Y41*AB41*R41 -> 0 | AD41: =+AC41-X41 -> 0 | AE41: =IFERROR(AD41/AC41,0) -> 0
S42: =+Q42*R42 -> 0 | T42: 0 | U42: =S42*(1-T42) -> 0 | V42: EUR | W42: =IFERROR(VLOOKUP(V42,[1]Curr!$B$2:$C$13,2,FALSE),0) -> 11.3 | X42: =U42*W42 -> 0 | Y42: =Q42 -> 0 | Z42: =+Y42*R42 -> 0 | AA42: EUR | AB42: =IFERROR(VLOOKUP(AA42,Curr!$B$2:$C$13,2,FALSE),0) -> 11.3 | AC42: =+Y42*AB42*R42 -> 0 | AD42: =+AC42-X42 -> 0 | AE42: =IFERROR(AD42/AC42,0) -> 0
C43: Day 9 | D43: Transfer | J43: Tromsø: Self transfer to Tromsø Airport | Q43: 0 | R43: 0 | S43: =+Q43*R43 -> 0 | T43: 0 | U43: =S43*(1-T43) -> 0 | V43: EUR | W43: =IFERROR(VLOOKUP(V43,[1]Curr!$B$2:$C$13,2,FALSE),0) -> 11.3 | X43: =U43*W43 -> 0 | Y43: =Q43 -> 0 | Z43: =+Y43*R43 -> 0 | AA43: EUR | AB43: =IFERROR(VLOOKUP(AA43,Curr!$B$2:$C$13,2,FALSE),0) -> 11.3 | AC43: =+Y43*AB43*R43 -> 0 | AD43: =+AC43-X43 -> 0 | AE43: =IFERROR(AD43/AC43,0) -> 0
C44: Day 9 | D44: Departure | J44: Tromsø: Departure home | Q44: 0 | R44: 0 | S44: =+Q44*R44 -> 0 | T44: 0 | U44: =S44*(1-T44) -> 0 | V44: EUR | W44: =IFERROR(VLOOKUP(V44,[1]Curr!$B$2:$C$13,2,FALSE),0) -> 11.3 | X44: =U44*W44 -> 0 | Y44: =Q44 -> 0 | Z44: =+Y44*R44 -> 0 | AA44: EUR | AB44: =IFERROR(VLOOKUP(AA44,Curr!$B$2:$C$13,2,FALSE),0) -> 11.3 | AC44: =+Y44*AB44*R44 -> 0 | AD44: =+AC44-X44 -> 0 | AE44: =IFERROR(AD44/AC44,0) -> 0
S45: =+Q45*R45 -> 0 | T45: 0 | U45: =S45*(1-T45) -> 0 | V45: EUR | W45: =IFERROR(VLOOKUP(V45,[1]Curr!$B$2:$C$13,2,FALSE),0) -> 11.3 | X45: =U45*W45 -> 0 | Y45: =Q45 -> 0 | Z45: =+Y45*R45 -> 0 | AA45: EUR | AB45: =IFERROR(VLOOKUP(AA45,Curr!$B$2:$C$13,2,FALSE),0) -> 11.3 | AC45: =+Y45*AB45*R45 -> 0 | AD45: =+AC45-X45 -> 0 | AE45: =IFERROR(AD45/AC45,0) -> 0
S46: =+Q46*R46 -> 0 | T46: 0 | U46: =S46*(1-T46) -> 0 | V46: EUR | W46: =IFERROR(VLOOKUP(V46,[1]Curr!$B$2:$C$13,2,FALSE),0) -> 11.3 | X46: =U46*W46 -> 0 | Y46: =Q46 -> 0 | Z46: =+Y46*R46 -> 0 | AA46: EUR | AB46: =IFERROR(VLOOKUP(AA46,Curr!$B$2:$C$13,2,FALSE),0) -> 11.3 | AC46: =+Y46*AB46*R46 -> 0 | AD46: =+AC46-X46 -> 0 | AE46: =IFERROR(AD46/AC46,0) -> 0
C47: Day 1 | D47: Transfer package | J47: Helsinki: Private transfer to your accommodation | Q47: 80 | R47: 0 | S47: =+Q47*R47 -> 0 | T47: 0 | U47: =S47*(1-T47) -> 0 | V47: EUR | W47: =IFERROR(VLOOKUP(V47,[1]Curr!$B$2:$C$13,2,FALSE),0) -> 11.3 | X47: =U47*W47 -> 0 | Y47: =Q47/0.8 -> 100 | Z47: =+Y47*R47 -> 0 | AA47: EUR | AB47: =IFERROR(VLOOKUP(AA47,Curr!$B$2:$C$13,2,FALSE),0) -> 11.3 | AC47: =+Y47*AB47*R47 -> 0 | AD47: =+AC47-X47 -> 0 | AE47: =IFERROR(AD47/AC47,0) -> 0
C48: Day 2 | D48: Transfer package | J48: Helsinki: Private transfer to Helsinki Central Station | Q48: 80 | R48: 0 | S48: =+Q48*R48 -> 0 | T48: 0 | U48: =S48*(1-T48) -> 0 | V48: EUR | W48: =IFERROR(VLOOKUP(V48,[1]Curr!$B$2:$C$13,2,FALSE),0) -> 11.3 | X48: =U48*W48 -> 0 | Y48: =Q48/0.8 -> 100 | Z48: =+Y48*R48 -> 0 | AA48: EUR | AB48: =IFERROR(VLOOKUP(AA48,Curr!$B$2:$C$13,2,FALSE),0) -> 11.3 | AC48: =+Y48*AB48*R48 -> 0 | AD48: =+AC48-X48 -> 0 | AE48: =IFERROR(AD48/AC48,0) -> 0
C49: Day 3 | D49: Transfer package | J49: Rovaniemi: Private transfer to your accommodation | Q49: 40 | R49: 0 | S49: =+Q49*R49 -> 0 | T49: 0 | U49: =S49*(1-T49) -> 0 | V49: EUR | W49: =IFERROR(VLOOKUP(V49,[1]Curr!$B$2:$C$13,2,FALSE),0) -> 11.3 | X49: =U49*W49 -> 0 | Y49: =Q49/0.67 -> 59.701493 | Z49: =+Y49*R49 -> 0 | AA49: EUR | AB49: =IFERROR(VLOOKUP(AA49,Curr!$B$2:$C$13,2,FALSE),0) -> 11.3 | AC49: =+Y49*AB49*R49 -> 0 | AD49: =+AC49-X49 -> 0 | AE49: =IFERROR(AD49/AC49,0) -> 0
C50: Day 5 | D50: Transfer package | J50: Rovaniemi: Private transfer to Rovaniemi Bus Station | Q50: 40 | R50: 0 | S50: =+Q50*R50 -> 0 | T50: 0 | U50: =S50*(1-T50) -> 0 | V50: EUR | W50: =IFERROR(VLOOKUP(V50,[1]Curr!$B$2:$C$13,2,FALSE),0) -> 11.3 | X50: =U50*W50 -> 0 | Y50: =Q50/0.67 -> 59.701493 | Z50: =+Y50*R50 -> 0 | AA50: EUR | AB50: =IFERROR(VLOOKUP(AA50,Curr!$B$2:$C$13,2,FALSE),0) -> 11.3 | AC50: =+Y50*AB50*R50 -> 0 | AD50: =+AC50-X50 -> 0 | AE50: =IFERROR(AD50/AC50,0) -> 0
C51: Day 9 | D51: Transfer package | J51: Tromsø: Private transfer to Tromsø Airport | Q51: 900 | R51: 0 | S51: =+Q51*R51 -> 0 | T51: 0 | U51: =S51*(1-T51) -> 0 | V51: EUR | W51: =IFERROR(VLOOKUP(V51,[1]Curr!$B$2:$C$13,2,FALSE),0) -> 11.3 | X51: =U51*W51 -> 0 | Y51: =Q51 -> 900 | Z51: =+Y51*R51 -> 0 | AA51: EUR | AB51: =IFERROR(VLOOKUP(AA51,Curr!$B$2:$C$13,2,FALSE),0) -> 11.3 | AC51: =+Y51*AB51*R51 -> 0 | AD51: =+AC51-X51 -> 0 | AE51: =IFERROR(AD51/AC51,0) -> 0
S52: =+Q52*R52 -> 0 | T52: 0 | U52: =S52*(1-T52) -> 0 | V52: EUR | W52: =IFERROR(VLOOKUP(V52,[1]Curr!$B$2:$C$13,2,FALSE),0) -> 11.3 | X52: =U52*W52 -> 0 | Y52: =Q52 -> 0 | Z52: =+Y52*R52 -> 0 | AA52: EUR | AB52: =IFERROR(VLOOKUP(AA52,Curr!$B$2:$C$13,2,FALSE),0) -> 11.3 | AC52: =+Y52*AB52*R52 -> 0 | AD52: =+AC52-X52 -> 0 | AE52: =IFERROR(AD52/AC52,0) -> 0
S53: =+Q53*R53 -> 0 | T53: 0 | U53: =S53*(1-T53) -> 0 | V53: EUR | W53: =IFERROR(VLOOKUP(V53,[1]Curr!$B$2:$C$13,2,FALSE),0) -> 11.3 | X53: =U53*W53 -> 0 | Y53: =Q53 -> 0 | Z53: =+Y53*R53 -> 0 | AA53: EUR | AB53: =IFERROR(VLOOKUP(AA53,Curr!$B$2:$C$13,2,FALSE),0) -> 11.3 | AC53: =+Y53*AB53*R53 -> 0 | AD53: =+AC53-X53 -> 0 | AE53: =IFERROR(AD53/AC53,0) -> 0
C54: Day 2 | D54: Activity Upgrade | J54: Helsinki: Excurssion to Tallinn - Self Guided Experience - Departure from Helsinki: 10:30 am - Departure from Tallinn: 7:30 pm - Includes: Helsinki port transfers, Star Class Cruise Ticket | O54: x | P54: https://www.tallink.com/en | Q54: =(40+40)+(50*2) -> 180 | R54: 0 | S54: =+Q54*R54 -> 0 | T54: 0 | U54: =S54*(1-T54) -> 0 | V54: EUR | W54: =IFERROR(VLOOKUP(V54,[1]Curr!$B$2:$C$13,2,FALSE),0) -> 11.3 | X54: =U54*W54 -> 0 | Y54: =Q54/0.8 -> 225 | Z54: =+Y54*R54 -> 0 | AA54: EUR | AB54: =IFERROR(VLOOKUP(AA54,Curr!$B$2:$C$13,2,FALSE),0) -> 11.3 | AC54: =+Y54*AB54*R54 -> 0 | AD54: =+AC54-X54 -> 0 | AE54: =IFERROR(AD54/AC54,0) -> 0
C55: Day 2 | D55: Activity Upgrade | J55: Tallinn: Old Town Guided tour - Time: 1:00 pm - 3:30 pm - Meeting point: under the Town Hall clock - Notable sights: St Nickolas Church, Freedom Square, Alexander Nevsky Cathedral, St Mary's Cathedral, Danish King's Garden and more - Includes: Tour, english guide, Recommendations | O55: x | P55: https://120degrees.club/ | Q55: 25 | R55: 0 | S55: =+Q55*R55 -> 0 | T55: 0 | U55: =S55*(1-T55) -> 0 | V55: EUR | W55: =IFERROR(VLOOKUP(V55,[1]Curr!$B$2:$C$13,2,FALSE),0) -> 11.3 | X55: =U55*W55 -> 0 | Y55: =Q55/0.62 -> 40.322581 | Z55: =+Y55*R55 -> 0 | AA55: EUR | AB55: =IFERROR(VLOOKUP(AA55,Curr!$B$2:$C$13,2,FALSE),0) -> 11.3 | AC55: =+Y55*AB55*R55 -> 0 | AD55: =+AC55-X55 -> 0 | AE55: =IFERROR(AD55/AC55,0) -> 0
C56: Day 4 | D56: Activity Upgrade | J56: Rovaniemi: Snowmobiling and Sledding Arctic Circle Highlights - Time: 08:45 am - 03:45 pm - Meeting point: Arctic Circle Snowmobile Park office - Includes: Pick-up/drop-off in central Rovaniemi, Knowledgeable, English-speaking guide, 1h snowmobiling on shared snowmobile (2 pers), Reindeer experience with 500m sleigh ride, Alaskan Husky experience with 500m sleigh ride, Approx. 2 hours free time in Santa Claus Village, Winter clothes (overalls, boots and gloves), Other equipment (helmet and balaclava), Salmon soup lunch (vegetarian option available) | O56: x | P56: https://booknordics.com/finland/western-lapland/rovaniemi/family-day-snowmobile-arctic-animals-and-santa-village | Q56: 252 | R56: 0 | S56: =+Q56*R56 -> 0 | T56: 0.2 | U56: =S56*(1-T56) -> 0 | V56: EUR | W56: =IFERROR(VLOOKUP(V56,[1]Curr!$B$2:$C$13,2,FALSE),0) -> 11.3 | X56: =U56*W56 -> 0 | Y56: =Q56 -> 252 | Z56: =+Y56*R56 -> 0 | AA56: EUR | AB56: =IFERROR(VLOOKUP(AA56,Curr!$B$2:$C$13,2,FALSE),0) -> 11.3 | AC56: =+Y56*AB56*R56 -> 0 | AD56: =+AC56-X56 -> 0 | AE56: =IFERROR(AD56/AC56,0) -> 0
C57: Day 6 | D57: Activity Upgrade | J57: Tromsø: Reindeer Sledding, Reindeer Feeding and Sami Culture - Time: 09:45 am - 2:30 pm - Meeting point: Radisson Blu Hotel's main entrance (Sjøgata 7) - Includes: Scenic transfers (45 min each way), Knowledgeable English- and Norwegian-speaking guide, Thermal winter suit, warm boots, Reindeer sledding (approx. 30 min, depending on weather and snow conditions), Feeding the herd on our camp, Hot traditional Sámi meal (bithos) and hot drinks. Vegetarian option available on request, Cultural introduction about Sámi history and daily life | O57: x | P57: https://booknordics.com/norway/northern-norway/tromso-region/reindeer-sledding-reindeer-feeding-and-sami-culture-3 | Q57: 2195 | R57: 0 | S57: =+Q57*R57 -> 0 | T57: 0.2 | U57: =S57*(1-T57) -> 0 | V57: NOK | W57: =IFERROR(VLOOKUP(V57,[1]Curr!$B$2:$C$13,2,FALSE),0) -> 1 | X57: =U57*W57 -> 0 | Y57: =Q57/11.3 -> 194.24779 | Z57: =+Y57*R57 -> 0 | AA57: EUR | AB57: =IFERROR(VLOOKUP(AA57,Curr!$B$2:$C$13,2,FALSE),0) -> 11.3 | AC57: =+Y57*AB57*R57 -> 0 | AD57: =+AC57-X57 -> 0 | AE57: =IFERROR(AD57/AC57,0) -> 0
S58: =+Q58*R58 -> 0 | T58: 0 | U58: =S58*(1-T58) -> 0 | V58: EUR | W58: =IFERROR(VLOOKUP(V58,[1]Curr!$B$2:$C$13,2,FALSE),0) -> 11.3 | X58: =U58*W58 -> 0 | Y58: =Q58 -> 0 | Z58: =+Y58*R58 -> 0 | AA58: EUR | AB58: =IFERROR(VLOOKUP(AA58,Curr!$B$2:$C$13,2,FALSE),0) -> 11.3 | AC58: =+Y58*AB58*R58 -> 0 | AD58: =+AC58-X58 -> 0 | AE58: =IFERROR(AD58/AC58,0) -> 0
S59: =+Q59*R59 -> 0 | T59: 0 | U59: =S59*(1-T59) -> 0 | V59: EUR | W59: =IFERROR(VLOOKUP(V59,[1]Curr!$B$2:$C$13,2,FALSE),0) -> 11.3 | X59: =U59*W59 -> 0 | Y59: =Q59 -> 0 | Z59: =+Y59*R59 -> 0 | AA59: EUR | AB59: =IFERROR(VLOOKUP(AA59,Curr!$B$2:$C$13,2,FALSE),0) -> 11.3 | AC59: =+Y59*AB59*R59 -> 0 | AD59: =+AC59-X59 -> 0 | AE59: =IFERROR(AD59/AC59,0) -> 0
S60: =+Q60*R60 -> 0 | T60: 0 | U60: =S60*(1-T60) -> 0 | V60: EUR | W60: =IFERROR(VLOOKUP(V60,[1]Curr!$B$2:$C$13,2,FALSE),0) -> 11.3 | X60: =U60*W60 -> 0 | Y60: =Q60 -> 0 | Z60: =+Y60*R60 -> 0 | AA60: EUR | AB60: =IFERROR(VLOOKUP(AA60,Curr!$B$2:$C$13,2,FALSE),0) -> 11.3 | AC60: =+Y60*AB60*R60 -> 0 | AD60: =+AC60-X60 -> 0 | AE60: =IFERROR(AD60/AC60,0) -> 0
S61: =+Q61*R61 -> 0 | T61: 0 | U61: =S61*(1-T61) -> 0 | V61: EUR | W61: =IFERROR(VLOOKUP(V61,[1]Curr!$B$2:$C$13,2,FALSE),0) -> 11.3 | X61: =U61*W61 -> 0 | Y61: =Q61 -> 0 | Z61: =+Y61*R61 -> 0 | AA61: EUR | AB61: =IFERROR(VLOOKUP(AA61,Curr!$B$2:$C$13,2,FALSE),0) -> 11.3 | AC61: =+Y61*AB61*R61 -> 0 | AD61: =+AC61-X61 -> 0 | AE61: =IFERROR(AD61/AC61,0) -> 0
S62: =+Q62*R62 -> 0 | T62: 0 | U62: =S62*(1-T62) -> 0 | V62: EUR | W62: =IFERROR(VLOOKUP(V62,[1]Curr!$B$2:$C$13,2,FALSE),0) -> 11.3 | X62: =U62*W62 -> 0 | Y62: =Q62 -> 0 | Z62: =+Y62*R62 -> 0 | AA62: EUR | AB62: =IFERROR(VLOOKUP(AA62,Curr!$B$2:$C$13,2,FALSE),0) -> 11.3 | AC62: =+Y62*AB62*R62 -> 0 | AD62: =+AC62-X62 -> 0 | AE62: =IFERROR(AD62/AC62,0) -> 0
S63: =+Q63*R63 -> 0 | T63: 0 | U63: =S63*(1-T63) -> 0 | V63: EUR | W63: =IFERROR(VLOOKUP(V63,[1]Curr!$B$2:$C$13,2,FALSE),0) -> 11.3 | X63: =U63*W63 -> 0 | Y63: =Q63 -> 0 | Z63: =+Y63*R63 -> 0 | AA63: EUR | AB63: =IFERROR(VLOOKUP(AA63,Curr!$B$2:$C$13,2,FALSE),0) -> 11.3 | AC63: =+Y63*AB63*R63 -> 0 | AD63: =+AC63-X63 -> 0 | AE63: =IFERROR(AD63/AC63,0) -> 0
S64: =+Q64*R64 -> 0 | T64: 0 | U64: =S64*(1-T64) -> 0 | V64: EUR | W64: =IFERROR(VLOOKUP(V64,[1]Curr!$B$2:$C$13,2,FALSE),0) -> 11.3 | X64: =U64*W64 -> 0 | Y64: =Q64 -> 0 | Z64: =+Y64*R64 -> 0 | AA64: EUR | AB64: =IFERROR(VLOOKUP(AA64,Curr!$B$2:$C$13,2,FALSE),0) -> 11.3 | AC64: =+Y64*AB64*R64 -> 0 | AD64: =+AC64-X64 -> 0 | AE64: =IFERROR(AD64/AC64,0) -> 0
S65: =+Q65*R65 -> 0 | T65: 0 | U65: =S65*(1-T65) -> 0 | V65: EUR | W65: =IFERROR(VLOOKUP(V65,[1]Curr!$B$2:$C$13,2,FALSE),0) -> 11.3 | X65: =U65*W65 -> 0 | Y65: =Q65 -> 0 | Z65: =+Y65*R65 -> 0 | AA65: EUR | AB65: =IFERROR(VLOOKUP(AA65,Curr!$B$2:$C$13,2,FALSE),0) -> 11.3 | AC65: =+Y65*AB65*R65 -> 0 | AD65: =+AC65-X65 -> 0 | AE65: =IFERROR(AD65/AC65,0) -> 0
S66: =+Q66*R66 -> 0 | T66: 0 | U66: =S66*(1-T66) -> 0 | V66: EUR | W66: =IFERROR(VLOOKUP(V66,[1]Curr!$B$2:$C$13,2,FALSE),0) -> 11.3 | X66: =U66*W66 -> 0 | Y66: =Q66 -> 0 | Z66: =+Y66*R66 -> 0 | AA66: EUR | AB66: =IFERROR(VLOOKUP(AA66,Curr!$B$2:$C$13,2,FALSE),0) -> 11.3 | AC66: =+Y66*AB66*R66 -> 0 | AD66: =+AC66-X66 -> 0 | AE66: =IFERROR(AD66/AC66,0) -> 0
S67: =+Q67*R67 -> 0 | T67: 0 | U67: =S67*(1-T67) -> 0 | V67: EUR | W67: =IFERROR(VLOOKUP(V67,[1]Curr!$B$2:$C$13,2,FALSE),0) -> 11.3 | X67: =U67*W67 -> 0 | Y67: =Q67 -> 0 | Z67: =+Y67*R67 -> 0 | AA67: EUR | AB67: =IFERROR(VLOOKUP(AA67,Curr!$B$2:$C$13,2,FALSE),0) -> 11.3 | AC67: =+Y67*AB67*R67 -> 0 | AD67: =+AC67-X67 -> 0 | AE67: =IFERROR(AD67/AC67,0) -> 0
S68: =+Q68*R68 -> 0 | T68: 0 | U68: =S68*(1-T68) -> 0 | V68: EUR | W68: =IFERROR(VLOOKUP(V68,[1]Curr!$B$2:$C$13,2,FALSE),0) -> 11.3 | X68: =U68*W68 -> 0 | Y68: =Q68 -> 0 | Z68: =+Y68*R68 -> 0 | AA68: EUR | AB68: =IFERROR(VLOOKUP(AA68,Curr!$B$2:$C$13,2,FALSE),0) -> 11.3 | AC68: =+Y68*AB68*R68 -> 0 | AD68: =+AC68-X68 -> 0 | AE68: =IFERROR(AD68/AC68,0) -> 0
B70: Totals | D70: x | E70: x | F70: x | G70: x | H70: x | I70: x | J70: x | K70: x | L70: x | M70: x | N70: x | O70: x | P70: x | Q70: x | R70: x | S70: x | T70: x | U70: x | V70: x | W70: x | X70: x | Y70: x | Z70: =SUM(Z7:Z68) -> 4548.381 | AC70: =SUM(AC7:AC68) -> 51396.705 | AD70: =SUM(AD7:AD68) -> 9849.825 | AE70: =IFERROR(AD70/AC70,0) -> 0.19164312 | AF70: =SUM(AF8:AF69) -> 0 | AG70: =SUM(AG8:AG69) -> 0 | AH70: =SUM(AH8:AH69) -> 0 | AI70: =SUM(AI8:AI69) -> 0 | AJ70: =SUM(AJ8:AJ69) -> 0
Y72: Fixed | Z72: =Z12+Z19+Z21+Z23+Z26+Z31+Z33+Z36 -> 2452.0574
Y73: Variable | Z73: =Z9+Z14+Z17+Z28+Z40 -> 2096.3235
Y74: Total | Z74: 4560
Y75: PP | Z75: =Z74/2 -> 2280
Y78: Shoulder | Z78: =Z74 -> 4560
Y79: High | Z79: =Z78*1.18 -> 5380.8
Y80: X-mas | Z80: =Z78*1.3 -> 5928
Y81: Low | Z81: =Z78*0.85 -> 3876

Sheet 1206
B1: Places: 2N Rovaniemi - 3N Tromsø - 2N Alta
B2: Dates: Winter
B3: Pax: 2
B4: Rooming: Double
B6: ID | C6: Day | D6: Type | E6: From date | F6: To date | G6: From time | H6: To time | I6: Supplier | J6: Travel element | K6: Manual booking? | L6: Status | M6: Comments | N6: Non-refundable | O6: Refundable | P6: URL | Q6: Gross P per unit | R6: Units | S6: Gross P | T6: Supp Comm | U6: Net P | V6: Supp curr | W6: X-rate | X6: Net P NOK | Y6: Sales P per unit | Z6: Price | AA6: Sales curr | AB6: X-rate | AC6: Sales P NOK tot | AD6: GP NOK | AE6: GP % | AF6: VAT25 | AG6: VAT15 | AH6: VAT12 | AI6: VAT0-D | AJ6: VAT0-I
C7: Day 1 | D7: Arrival | J7: Rovaniemi: Welcome to Finland | Q7: 0 | R7: 0 | S7: =+Q7*R7 -> 0 | T7: 0 | U7: =S7*(1-T7) -> 0 | V7: EUR | W7: =IFERROR(VLOOKUP(V7,[1]Curr!$B$2:$C$13,2,FALSE),0) -> 11.3 | X7: =U7*W7 -> 0 | Y7: =Q7 -> 0 | Z7: =+Y7*R7 -> 0 | AA7: EUR | AB7: =IFERROR(VLOOKUP(AA7,Curr!$B$2:$C$13,2,FALSE),0) -> 11.3 | AC7: =+Y7*AB7*R7 -> 0 | AD7: =+AC7-X7 -> 0 | AE7: =IFERROR(AD7/AC7,0) -> 0
C8: Day 1 | D8: Transfer | J8: Rovaniemi: Self transfer to your accommodation | Q8: 0 | R8: 0 | S8: =+Q8*R8 -> 0 | T8: 0 | U8: =S8*(1-T8) -> 0 | V8: EUR | W8: =IFERROR(VLOOKUP(V8,[1]Curr!$B$2:$C$13,2,FALSE),0) -> 11.3 | X8: =U8*W8 -> 0 | Y8: =Q8/0.8 -> 0 | Z8: =+Y8*R8 -> 0 | AA8: EUR | AB8: =IFERROR(VLOOKUP(AA8,Curr!$B$2:$C$13,2,FALSE),0) -> 11.3 | AC8: =+Y8*AB8*R8 -> 0 | AD8: =+AC8-X8 -> 0 | AE8: =IFERROR(AD8/AC8,0) -> 0
C9: Day 1 | D9: Hotel | J9: Rovaniemi: Check in to your accommodation for a 2 night stay - Centrally Located 3/4-star Hotel - Standard Room - Breakfast included | Q9: 600 | R9: 1 | S9: =+Q9*R9 -> 600 | T9: 0 | U9: =S9*(1-T9) -> 600 | V9: EUR | W9: =IFERROR(VLOOKUP(V9,[1]Curr!$B$2:$C$13,2,FALSE),0) -> 11.3 | X9: =U9*W9 -> 6780 | Y9: =Q9/0.85 -> 705.88235 | Z9: =+Y9*R9 -> 705.88235 | AA9: EUR | AB9: =IFERROR(VLOOKUP(AA9,Curr!$B$2:$C$13,2,FALSE),0) -> 11.3 | AC9: =+Y9*AB9*R9 -> 7976.4706 | AD9: =+AC9-X9 -> 1196.4706 | AE9: =IFERROR(AD9/AC9,0) -> 0.15
C10: Day 1 | D10: Leisure | J10: Rovaniemi: Spend time at leisure | Q10: 0 | R10: 0 | S10: =+Q10*R10 -> 0 | T10: 0 | U10: =S10*(1-T10) -> 0 | V10: EUR | W10: =IFERROR(VLOOKUP(V10,[1]Curr!$B$2:$C$13,2,FALSE),0) -> 11.3 | X10: =U10*W10 -> 0 | Y10: =Q10 -> 0 | Z10: =+Y10*R10 -> 0 | AA10: EUR | AB10: =IFERROR(VLOOKUP(AA10,Curr!$B$2:$C$13,2,FALSE),0) -> 11.3 | AC10: =+Y10*AB10*R10 -> 0 | AD10: =+AC10-X10 -> 0 | AE10: =IFERROR(AD10/AC10,0) -> 0
S11: =+Q11*R11 -> 0 | T11: 0 | U11: =S11*(1-T11) -> 0 | V11: EUR | W11: =IFERROR(VLOOKUP(V11,[1]Curr!$B$2:$C$13,2,FALSE),0) -> 11.3 | X11: =U11*W11 -> 0 | Y11: =Q11 -> 0 | Z11: =+Y11*R11 -> 0 | AA11: EUR | AB11: =IFERROR(VLOOKUP(AA11,Curr!$B$2:$C$13,2,FALSE),0) -> 11.3 | AC11: =+Y11*AB11*R11 -> 0 | AD11: =+AC11-X11 -> 0 | AE11: =IFERROR(AD11/AC11,0) -> 0
C12: Day 2 | D12: Activity | J12: Rovaniemi: Arctic Circle Highlights Adventure Day - Time: 08:45 am - 2:45 pm - Meeting point: Arctic Circle Snowmobile Park office - Includes: Pick-up/drop-off in central Rovaniemi, Reindeer Farm visit with sleigh ride (2-3 pers), Reindeer sledge driver’s license reward, Alaskan Husky visit with sleigh ride (4 pers), Approx. 2 hours free time in Santa Claus Village, Winter clothes (overalls, boots and gloves), Traditional salmon soup or vegetarian option | O12: x | P12: https://booknordics.com/finland/western-lapland/rovaniemi/arctic-circle-highlights-family-day-by-minibus | Q12: 188 | R12: 2 | S12: =+Q12*R12 -> 376 | T12: 0.2 | U12: =S12*(1-T12) -> 300.8 | V12: EUR | W12: 11.3 | X12: =U12*W12 -> 3399.04 | Y12: =Q12 -> 188 | Z12: =+Y12*R12 -> 376 | AA12: EUR | AB12: =IFERROR(VLOOKUP(AA12,Curr!$B$2:$C$13,2,FALSE),0) -> 11.3 | AC12: =+Y12*AB12*R12 -> 4248.8 | AD12: =+AC12-X12 -> 849.76 | AE12: =IFERROR(AD12/AC12,0) -> 0.2
C13: Day 2 | D13: Leisure | J13: Rovaniemi: Spend time at leisure | Q13: 0 | R13: 0 | S13: =+Q13*R13 -> 0 | T13: 0 | U13: =S13*(1-T13) -> 0 | V13: EUR | W13: =IFERROR(VLOOKUP(V13,[1]Curr!$B$2:$C$13,2,FALSE),0) -> 11.3 | X13: =U13*W13 -> 0 | Y13: =Q13 -> 0 | Z13: =+Y13*R13 -> 0 | AA13: EUR | AB13: =IFERROR(VLOOKUP(AA13,Curr!$B$2:$C$13,2,FALSE),0) -> 11.3 | AC13: =+Y13*AB13*R13 -> 0 | AD13: =+AC13-X13 -> 0 | AE13: =IFERROR(AD13/AC13,0) -> 0
C14: Day 2 | D14: Activity | J14: Rovaniemi: Northern Lights Unlimited Mileage Photo Tour - Time: 08:00 pm - 01:00 am - Meeting point: Book Lapland Office - Includes: Pick-up/drop-off in central Rovaniemi, Knowledgeable, English-speaking guides, Professional DSLR photography (unlimited), Meteorological observations, Thermal winter clothing, Hot drinks & snacks or cookies | O14: x | P14: https://booknordics.com/finland/western-lapland/rovaniemi/rovaniemi-northern-lights-family-tour-by-bus-with-photos | Q14: 109 | R14: 2 | S14: =+Q14*R14 -> 218 | T14: 0.2 | U14: =S14*(1-T14) -> 174.4 | V14: EUR | W14: =IFERROR(VLOOKUP(V14,[1]Curr!$B$2:$C$13,2,FALSE),0) -> 11.3 | X14: =U14*W14 -> 1970.72 | Y14: =Q14 -> 109 | Z14: =+Y14*R14 -> 218 | AA14: EUR | AB14: =IFERROR(VLOOKUP(AA14,Curr!$B$2:$C$13,2,FALSE),0) -> 11.3 | AC14: =+Y14*AB14*R14 -> 2463.4 | AD14: =+AC14-X14 -> 492.68 | AE14: =IFERROR(AD14/AC14,0) -> 0.2
Q15: 0 | R15: 0 | S15: =+Q15*R15 -> 0 | T15: 0 | U15: =S15*(1-T15) -> 0 | V15: EUR | W15: =IFERROR(VLOOKUP(V15,[1]Curr!$B$2:$C$13,2,FALSE),0) -> 11.3 | X15: =U15*W15 -> 0 | Y15: =Q15 -> 0 | Z15: =+Y15*R15 -> 0 | AA15: EUR | AB15: =IFERROR(VLOOKUP(AA15,Curr!$B$2:$C$13,2,FALSE),0) -> 11.3 | AC15: =+Y15*AB15*R15 -> 0 | AD15: =+AC15-X15 -> 0 | AE15: =IFERROR(AD15/AC15,0) -> 0
C16: Day 3 | D16: Transfer | J16: Rovaniemi: Self transfer to Rovaniemi Bus Station | Q16: 0 | R16: 0 | S16: =+Q16*R16 -> 0 | T16: 0 | U16: =S16*(1-T16) -> 0 | V16: EUR | W16: =IFERROR(VLOOKUP(V16,[1]Curr!$B$2:$C$13,2,FALSE),0) -> 11.3 | X16: =U16*W16 -> 0 | Y16: =Q16 -> 0 | Z16: =+Y16*R16 -> 0 | AA16: EUR | AB16: =IFERROR(VLOOKUP(AA16,Curr!$B$2:$C$13,2,FALSE),0) -> 11.3 | AC16: =+Y16*AB16*R16 -> 0 | AD16: =+AC16-X16 -> 0 | AE16: =IFERROR(AD16/AC16,0) -> 0
C17: Day 3 | D17: Activity | J17: Rovaniemi: Arctic Route Coach Transfer to Tromsø - Time: 11:40 am - 7:30 pm - Includes: Tickets | O17: x | P17: https://bestarctic.com/the-arctic-route/arctic-winter-routes-explore-norway-sweden-and-finland/bus-between-tromso-norway-and-rovaniemi-finland/ | Q17: 1830 | R17: 2 | S17: =+Q17*R17 -> 3660 | T17: 0.2 | U17: =S17*(1-T17) -> 2928 | V17: NOK | W17: =IFERROR(VLOOKUP(V17,[1]Curr!$B$2:$C$13,2,FALSE),0) -> 1 | X17: =U17*W17 -> 2928 | Y17: =Q17/11.3/0.9 -> 179.941 | Z17: =+Y17*R17 -> 359.88201 | AA17: EUR | AB17: =IFERROR(VLOOKUP(AA17,Curr!$B$2:$C$13,2,FALSE),0) -> 11.3 | AC17: =+Y17*AB17*R17 -> 4066.6667 | AD17: =+AC17-X17 -> 1138.6667 | AE17: =IFERROR(AD17/AC17,0) -> 0.28
C18: Day 3 | D18: Transfer | J18: Tromsø: Self transfer to your accommodation | Q18: 0 | R18: 0 | S18: =+Q18*R18 -> 0 | T18: 0 | U18: =S18*(1-T18) -> 0 | V18: EUR | W18: =IFERROR(VLOOKUP(V18,[1]Curr!$B$2:$C$13,2,FALSE),0) -> 11.3 | X18: =U18*W18 -> 0 | Y18: =Q18 -> 0 | Z18: =+Y18*R18 -> 0 | AA18: EUR | AB18: =IFERROR(VLOOKUP(AA18,Curr!$B$2:$C$13,2,FALSE),0) -> 11.3 | AC18: =+Y18*AB18*R18 -> 0 | AD18: =+AC18-X18 -> 0 | AE18: =IFERROR(AD18/AC18,0) -> 0
C19: Day 3 | D19: Hotel | J19: Tromsø: Check in to your accommodation for a 3 night stay - Centrally Located 3/4-star Hotel - Standard Room - Breakfast included | O19: x | Q19: 800 | R19: 1 | S19: =+Q19*R19 -> 800 | T19: 0 | U19: =S19*(1-T19) -> 800 | V19: EUR | W19: =IFERROR(VLOOKUP(V19,[1]Curr!$B$2:$C$13,2,FALSE),0) -> 11.3 | X19: =U19*W19 -> 9040 | Y19: =Q19/0.85 -> 941.17647 | Z19: =+Y19*R19 -> 941.17647 | AA19: EUR | AB19: =IFERROR(VLOOKUP(AA19,Curr!$B$2:$C$13,2,FALSE),0) -> 11.3 | AC19: =+Y19*AB19*R19 -> 10635.294 | AD19: =+AC19-X19 -> 1595.2941 | AE19: =IFERROR(AD19/AC19,0) -> 0.15
C20: Day 3 | D20: Leisure | J20: Tromsø: Spend time at leisure | Q20: 0 | R20: 0 | S20: =+Q20*R20 -> 0 | T20: 0 | U20: =S20*(1-T20) -> 0 | V20: EUR | W20: =IFERROR(VLOOKUP(V20,[1]Curr!$B$2:$C$13,2,FALSE),0) -> 11.3 | X20: =U20*W20 -> 0 | Y20: =Q20 -> 0 | Z20: =+Y20*R20 -> 0 | AA20: EUR | AB20: =IFERROR(VLOOKUP(AA20,Curr!$B$2:$C$13,2,FALSE),0) -> 11.3 | AC20: =+Y20*AB20*R20 -> 0 | AD20: =+AC20-X20 -> 0 | AE20: =IFERROR(AD20/AC20,0) -> 0
Q21: 0 | R21: 0 | S21: =+Q21*R21 -> 0 | T21: 0 | U21: =S21*(1-T21) -> 0 | V21: EUR | W21: =IFERROR(VLOOKUP(V21,[1]Curr!$B$2:$C$13,2,FALSE),0) -> 11.3 | X21: =U21*W21 -> 0 | Y21: =Q21 -> 0 | Z21: =+Y21*R21 -> 0 | AA21: EUR | AB21: =IFERROR(VLOOKUP(AA21,Curr!$B$2:$C$13,2,FALSE),0) -> 11.3 | AC21: =+Y21*AB21*R21 -> 0 | AD21: =+AC21-X21 -> 0 | AE21: =IFERROR(AD21/AC21,0) -> 0
C22: Day 4 | D22: Activity | J22: Tromsø: Reindeer Feeding and Sámi Culture - Time: 09:45 am - 2:30 pm - Meeting point: Radisson Blu Hotel's main entrance (Sjøgata 7) - Includes: Scenic transfers (45 min each way), Knowledgeable English and Norwegian speaking guide, Feeding the herd at our camp, Hot beverages and hot meal (traditional Sámi stew or vegetable/lentil soup), Cultural introduction about Sámi history and daily life, A chance to see the northern lights from our camp, Thermal suit and warm snow boots | O22: x | P22: https://www.tromsolapland.no/activities/reindeer-feeding-and-sami-culture | Q22: 1695 | R22: 2 | S22: =+Q22*R22 -> 3390 | T22: 0.2 | U22: =S22*(1-T22) -> 2712 | V22: NOK | W22: =IFERROR(VLOOKUP(V22,[1]Curr!$B$2:$C$13,2,FALSE),0) -> 1 | X22: =U22*W22 -> 2712 | Y22: =Q22/11.3 -> 150 | Z22: =+Y22*R22 -> 300 | AA22: EUR | AB22: =IFERROR(VLOOKUP(AA22,Curr!$B$2:$C$13,2,FALSE),0) -> 11.3 | AC22: =+Y22*AB22*R22 -> 3390 | AD22: =+AC22-X22 -> 678 | AE22: =IFERROR(AD22/AC22,0) -> 0.2
C23: Day 4 | D23: Leisure | J23: Tromsø: Spend time at leisure | Q23: 0 | R23: 0 | S23: =+Q23*R23 -> 0 | T23: 0 | U23: =S23*(1-T23) -> 0 | V23: EUR | W23: =IFERROR(VLOOKUP(V23,[1]Curr!$B$2:$C$13,2,FALSE),0) -> 11.3 | X23: =U23*W23 -> 0 | Y23: =Q23 -> 0 | Z23: =+Y23*R23 -> 0 | AA23: EUR | AB23: =IFERROR(VLOOKUP(AA23,Curr!$B$2:$C$13,2,FALSE),0) -> 11.3 | AC23: =+Y23*AB23*R23 -> 0 | AD23: =+AC23-X23 -> 0 | AE23: =IFERROR(AD23/AC23,0) -> 0
C24: Day 4 | D24: Activity | J24: Tromsø: Northern Lights Chase with authentic North Norwegian Charm - Time: 6:35 pm - Duration: 5 - 7 hrs - Meeting point: Outside Scandic ishavshotel (Fredrik Langes gate 2) Includes: Tripod for camera or phone, The Story of the Aurora – Short Film, Memorable Free Portraits, Small photo booklet showing old Tromsø, Coffee, tea, hot chocolate, buljong and chocolate cake, Warm insulated suits, Norwegian guide, but the activity is conducted in English | O24: x | P24: https://www.tromso-friluftsenter.no/activities/northern-lights-chase-with-authentic-north-norwegian-charm | Q24: 2050 | R24: 2 | S24: =+Q24*R24 -> 4100 | T24: 0.2 | U24: =S24*(1-T24) -> 3280 | V24: NOK | W24: =IFERROR(VLOOKUP(V24,[1]Curr!$B$2:$C$13,2,FALSE),0) -> 1 | X24: =U24*W24 -> 3280 | Y24: =Q24/11.3 -> 181.41593 | Z24: =+Y24*R24 -> 362.83186 | AA24: EUR | AB24: =IFERROR(VLOOKUP(AA24,Curr!$B$2:$C$13,2,FALSE),0) -> 11.3 | AC24: =+Y24*AB24*R24 -> 4100 | AD24: =+AC24-X24 -> 820 | AE24: =IFERROR(AD24/AC24,0) -> 0.2
S25: =+Q25*R25 -> 0 | T25: 0 | U25: =S25*(1-T25) -> 0 | V25: EUR | W25: =IFERROR(VLOOKUP(V25,[1]Curr!$B$2:$C$13,2,FALSE),0) -> 11.3 | X25: =U25*W25 -> 0 | Y25: =Q25 -> 0 | Z25: =+Y25*R25 -> 0 | AA25: EUR | AB25: =IFERROR(VLOOKUP(AA25,Curr!$B$2:$C$13,2,FALSE),0) -> 11.3 | AC25: =+Y25*AB25*R25 -> 0 | AD25: =+AC25-X25 -> 0 | AE25: =IFERROR(AD25/AC25,0) -> 0
C26: Day 5 | D26: Activity | J26: Tromsø: Photo Tour to Arctic Landscapes and Fjords - Time: 10:00 am - 3:00 pm - Meeting point: Roald Amundsens plass 1A - Includes: Departure from central Tromsø. Drop-off to your hotel, Professional, English-speaking photo guides, Scenic fjord safari by comfortable minivan vehicle, Help with camera settings and nature photography, Usually a small-group experience with 4-8 guests, Soup or expedition food, coffee and waffles/cookies | O26: x | P26: https://booknordics.com/norway/northern-norway/tromso-region/tromso-fjord-photo-tour | Q26: 145 | R26: 2 | S26: =+Q26*R26 -> 290 | T26: 0.2 | U26: =S26*(1-T26) -> 232 | V26: EUR | W26: =IFERROR(VLOOKUP(V26,[1]Curr!$B$2:$C$13,2,FALSE),0) -> 11.3 | X26: =U26*W26 -> 2621.6 | Y26: =Q26 -> 145 | Z26: =+Y26*R26 -> 290 | AA26: EUR | AB26: =IFERROR(VLOOKUP(AA26,Curr!$B$2:$C$13,2,FALSE),0) -> 11.3 | AC26: =+Y26*AB26*R26 -> 3277 | AD26: =+AC26-X26 -> 655.4 | AE26: =IFERROR(AD26/AC26,0) -> 0.2
C27: Day 5 | D27: Leisure | J27: Tromsø: Spend time at leisure | Q27: 0 | R27: 0 | S27: =+Q27*R27 -> 0 | T27: 0 | U27: =S27*(1-T27) -> 0 | V27: EUR | W27: =IFERROR(VLOOKUP(V27,[1]Curr!$B$2:$C$13,2,FALSE),0) -> 11.3 | X27: =U27*W27 -> 0 | Y27: =Q27 -> 0 | Z27: =+Y27*R27 -> 0 | AA27: EUR | AB27: =IFERROR(VLOOKUP(AA27,Curr!$B$2:$C$13,2,FALSE),0) -> 11.3 | AC27: =+Y27*AB27*R27 -> 0 | AD27: =+AC27-X27 -> 0 | AE27: =IFERROR(AD27/AC27,0) -> 0
C28: Day 5 | D28: Activity | J28: Tromsø: Northern Lights Cruise with Silent Electric Ship - Time: 7:00 pm - 10:00 pm - Meeting point: Kaigata 6 - Includes: Departure from central Tromsø, 3-hour fjord cruise, Light meal (soup and bread) and water, English speaking guides, Warm indoor saloons, Free wifi, Toilets | O28: x | P28: https://booknordics.com/norway/northern-norway/tromso-region/northern-lights-cruise-electric-ship | Q28: 105 | R28: 2 | S28: =+Q28*R28 -> 210 | T28: 0.2 | U28: =S28*(1-T28) -> 168 | V28: EUR | W28: =IFERROR(VLOOKUP(V28,[1]Curr!$B$2:$C$13,2,FALSE),0) -> 11.3 | X28: =U28*W28 -> 1898.4 | Y28: =Q28 -> 105 | Z28: =+Y28*R28 -> 210 | AA28: EUR | AB28: =IFERROR(VLOOKUP(AA28,Curr!$B$2:$C$13,2,FALSE),0) -> 11.3 | AC28: =+Y28*AB28*R28 -> 2373 | AD28: =+AC28-X28 -> 474.6 | AE28: =IFERROR(AD28/AC28,0) -> 0.2
S29: =+Q29*R29 -> 0 | T29: 0 | U29: =S29*(1-T29) -> 0 | V29: EUR | W29: =IFERROR(VLOOKUP(V29,[1]Curr!$B$2:$C$13,2,FALSE),0) -> 11.3 | X29: =U29*W29 -> 0 | Y29: =Q29 -> 0 | Z29: =+Y29*R29 -> 0 | AA29: EUR | AB29: =IFERROR(VLOOKUP(AA29,Curr!$B$2:$C$13,2,FALSE),0) -> 11.3 | AC29: =+Y29*AB29*R29 -> 0 | AD29: =+AC29-X29 -> 0 | AE29: =IFERROR(AD29/AC29,0) -> 0
C30: Day 6 | D30: Leisure | J30: Tromsø: Spend time at leisure | Q30: 0 | R30: 0 | S30: =+Q30*R30 -> 0 | T30: 0 | U30: =S30*(1-T30) -> 0 | V30: EUR | W30: =IFERROR(VLOOKUP(V30,[1]Curr!$B$2:$C$13,2,FALSE),0) -> 11.3 | X30: =U30*W30 -> 0 | Y30: =Q30 -> 0 | Z30: =+Y30*R30 -> 0 | AA30: EUR | AB30: =IFERROR(VLOOKUP(AA30,Curr!$B$2:$C$13,2,FALSE),0) -> 11.3 | AC30: =+Y30*AB30*R30 -> 0 | AD30: =+AC30-X30 -> 0 | AE30: =IFERROR(AD30/AC30,0) -> 0
C31: Day 6 | D31: Transfer | J31: Tromsø: Self transfer to Tromsø Bus Terminal Prostneset | Q31: 0 | R31: 0 | S31: =+Q31*R31 -> 0 | T31: 0 | U31: =S31*(1-T31) -> 0 | V31: EUR | W31: =IFERROR(VLOOKUP(V31,[1]Curr!$B$2:$C$13,2,FALSE),0) -> 11.3 | X31: =U31*W31 -> 0 | Y31: =Q31 -> 0 | Z31: =+Y31*R31 -> 0 | AA31: EUR | AB31: =IFERROR(VLOOKUP(AA31,Curr!$B$2:$C$13,2,FALSE),0) -> 11.3 | AC31: =+Y31*AB31*R31 -> 0 | AD31: =+AC31-X31 -> 0 | AE31: =IFERROR(AD31/AC31,0) -> 0
C32: Day 6 | D32: Coach | J32: Tromsø: Long distance panorama coach transfer to Alta - Bus 150 - Time: 4:00 pm - 10:20 pm - Excludes: Tickets (To be bought on site) | Q32: 0 | R32: 0 | S32: =+Q32*R32 -> 0 | T32: 0 | U32: =S32*(1-T32) -> 0 | V32: EUR | W32: =IFERROR(VLOOKUP(V32,[1]Curr!$B$2:$C$13,2,FALSE),0) -> 11.3 | X32: =U32*W32 -> 0 | Y32: =Q32 -> 0 | Z32: =+Y32*R32 -> 0 | AA32: EUR | AB32: =IFERROR(VLOOKUP(AA32,Curr!$B$2:$C$13,2,FALSE),0) -> 11.3 | AC32: =+Y32*AB32*R32 -> 0 | AD32: =+AC32-X32 -> 0 | AE32: =IFERROR(AD32/AC32,0) -> 0
C33: Day 6 | D33: Transfer | J33: Alta: Self transfer to your accommodation | Q33: 0 | R33: 0 | S33: =+Q33*R33 -> 0 | T33: 0 | U33: =S33*(1-T33) -> 0 | V33: EUR | W33: =IFERROR(VLOOKUP(V33,[1]Curr!$B$2:$C$13,2,FALSE),0) -> 11.3 | X33: =U33*W33 -> 0 | Y33: =Q33 -> 0 | Z33: =+Y33*R33 -> 0 | AA33: EUR | AB33: =IFERROR(VLOOKUP(AA33,Curr!$B$2:$C$13,2,FALSE),0) -> 11.3 | AC33: =+Y33*AB33*R33 -> 0 | AD33: =+AC33-X33 -> 0 | AE33: =IFERROR(AD33/AC33,0) -> 0
C34: Day 6 | D34: Hotel | J34: Alta: Check in to your accommodation for a 2 night stay - Centrally Located 3/4-star Hotel - Standard Room - Breakfast included | Q34: 300 | R34: 1 | S34: =+Q34*R34 -> 300 | T34: 0 | U34: =S34*(1-T34) -> 300 | V34: EUR | W34: =IFERROR(VLOOKUP(V34,[1]Curr!$B$2:$C$13,2,FALSE),0) -> 11.3 | X34: =U34*W34 -> 3390 | Y34: =Q34/0.8 -> 375 | Z34: =+Y34*R34 -> 375 | AA34: EUR | AB34: =IFERROR(VLOOKUP(AA34,Curr!$B$2:$C$13,2,FALSE),0) -> 11.3 | AC34: =+Y34*AB34*R34 -> 4237.5 | AD34: =+AC34-X34 -> 847.5 | AE34: =IFERROR(AD34/AC34,0) -> 0.2
C35: Day 6 | D35: Leisure | J35: Alta: Spend time at leisure | Q35: 0 | R35: 0 | S35: =+Q35*R35 -> 0 | T35: 0 | U35: =S35*(1-T35) -> 0 | V35: EUR | W35: =IFERROR(VLOOKUP(V35,[1]Curr!$B$2:$C$13,2,FALSE),0) -> 11.3 | X35: =U35*W35 -> 0 | Y35: =Q35 -> 0 | Z35: =+Y35*R35 -> 0 | AA35: EUR | AB35: =IFERROR(VLOOKUP(AA35,Curr!$B$2:$C$13,2,FALSE),0) -> 11.3 | AC35: =+Y35*AB35*R35 -> 0 | AD35: =+AC35-X35 -> 0 | AE35: =IFERROR(AD35/AC35,0) -> 0
S36: =+Q36*R36 -> 0 | T36: 0 | U36: =S36*(1-T36) -> 0 | V36: EUR | W36: =IFERROR(VLOOKUP(V36,[1]Curr!$B$2:$C$13,2,FALSE),0) -> 11.3 | X36: =U36*W36 -> 0 | Y36: =Q36 -> 0 | Z36: =+Y36*R36 -> 0 | AA36: EUR | AB36: =IFERROR(VLOOKUP(AA36,Curr!$B$2:$C$13,2,FALSE),0) -> 11.3 | AC36: =+Y36*AB36*R36 -> 0 | AD36: =+AC36-X36 -> 0 | AE36: =IFERROR(AD36/AC36,0) -> 0
C37: Day 7 | D37: Activity | J37: Alta: Visit to Sorrisniva Igloo Hotel - Time: Flexible - Meeting point: Sorrisniva Arctic Wilderness Lodge - Includes: Entry ticket to explore Sorrisniva Igloo Hotel | O37: x | P37: https://booknordics.com/norway/northern-norway/alta-and-north-cape/entrance-ticket-igloo-hotel | Q37: 34 | R37: 2 | S37: =+Q37*R37 -> 68 | T37: 0.15 | U37: =S37*(1-T37) -> 57.8 | V37: EUR | W37: =IFERROR(VLOOKUP(V37,[1]Curr!$B$2:$C$13,2,FALSE),0) -> 11.3 | X37: =U37*W37 -> 653.14 | Y37: =Q37/0.95 -> 35.789474 | Z37: =+Y37*R37 -> 71.578947 | AA37: EUR | AB37: =IFERROR(VLOOKUP(AA37,Curr!$B$2:$C$13,2,FALSE),0) -> 11.3 | AC37: =+Y37*AB37*R37 -> 808.84211 | AD37: =+AC37-X37 -> 155.70211 | AE37: =IFERROR(AD37/AC37,0) -> 0.1925
C38: Day 7 | D38: Leisure | J38: Alta: Spend time at leisure | Q38: 0 | R38: 0 | S38: =+Q38*R38 -> 0 | T38: 0 | U38: =S38*(1-T38) -> 0 | V38: EUR | W38: =IFERROR(VLOOKUP(V38,[1]Curr!$B$2:$C$13,2,FALSE),0) -> 11.3 | X38: =U38*W38 -> 0 | Y38: =Q38 -> 0 | Z38: =+Y38*R38 -> 0 | AA38: EUR | AB38: =IFERROR(VLOOKUP(AA38,Curr!$B$2:$C$13,2,FALSE),0) -> 11.3 | AC38: =+Y38*AB38*R38 -> 0 | AD38: =+AC38-X38 -> 0 | AE38: =IFERROR(AD38/AC38,0) -> 0
C39: Day 7 | D39: Activity | J39: Alta: Small Group Northern Lights Hunt - Time: 7:00 pm - 11:00 pm - Meeting point: Æventyr Booking Point - Includes: Professional guide, Northern Lights lectures and local history, Coffee / tea and snacks, Warm overalls for loan | O39: x | P39: https://www.aeventyr.no/activities/small-group-northern-lights-hunt | Q39: 2290 | R39: 2 | S39: =+Q39*R39 -> 4580 | T39: 0.15 | U39: =S39*(1-T39) -> 3893 | V39: NOK | W39: =IFERROR(VLOOKUP(V39,[1]Curr!$B$2:$C$13,2,FALSE),0) -> 1 | X39: =U39*W39 -> 3893 | Y39: =Q39/11 -> 208.18182 | Z39: =+Y39*R39 -> 416.36364 | AA39: EUR | AB39: =IFERROR(VLOOKUP(AA39,Curr!$B$2:$C$13,2,FALSE),0) -> 11.3 | AC39: =+Y39*AB39*R39 -> 4704.9091 | AD39: =+AC39-X39 -> 811.90909 | AE39: =IFERROR(AD39/AC39,0) -> 0.17256637
S40: =+Q40*R40 -> 0 | T40: 0 | U40: =S40*(1-T40) -> 0 | V40: EUR | W40: =IFERROR(VLOOKUP(V40,[1]Curr!$B$2:$C$13,2,FALSE),0) -> 11.3 | X40: =U40*W40 -> 0 | Y40: =Q40 -> 0 | Z40: =+Y40*R40 -> 0 | AA40: EUR | AB40: =IFERROR(VLOOKUP(AA40,Curr!$B$2:$C$13,2,FALSE),0) -> 11.3 | AC40: =+Y40*AB40*R40 -> 0 | AD40: =+AC40-X40 -> 0 | AE40: =IFERROR(AD40/AC40,0) -> 0
C41: Day 8 | D41: Transfer | J41: Alta: Self transfer to Alta Airport | Q41: 0 | R41: 0 | S41: =+Q41*R41 -> 0 | T41: 0 | U41: =S41*(1-T41) -> 0 | V41: EUR | W41: =IFERROR(VLOOKUP(V41,[1]Curr!$B$2:$C$13,2,FALSE),0) -> 11.3 | X41: =U41*W41 -> 0 | Y41: =Q41 -> 0 | Z41: =+Y41*R41 -> 0 | AA41: EUR | AB41: =IFERROR(VLOOKUP(AA41,Curr!$B$2:$C$13,2,FALSE),0) -> 11.3 | AC41: =+Y41*AB41*R41 -> 0 | AD41: =+AC41-X41 -> 0 | AE41: =IFERROR(AD41/AC41,0) -> 0
C42: Day 8 | D42: Departure | J42: Alta: Departure home | Q42: 0 | R42: 0 | S42: =+Q42*R42 -> 0 | T42: 0 | U42: =S42*(1-T42) -> 0 | V42: EUR | W42: =IFERROR(VLOOKUP(V42,[1]Curr!$B$2:$C$13,2,FALSE),0) -> 11.3 | X42: =U42*W42 -> 0 | Y42: =Q42 -> 0 | Z42: =+Y42*R42 -> 0 | AA42: EUR | AB42: =IFERROR(VLOOKUP(AA42,Curr!$B$2:$C$13,2,FALSE),0) -> 11.3 | AC42: =+Y42*AB42*R42 -> 0 | AD42: =+AC42-X42 -> 0 | AE42: =IFERROR(AD42/AC42,0) -> 0
S43: =+Q43*R43 -> 0 | T43: 0 | U43: =S43*(1-T43) -> 0 | V43: EUR | W43: =IFERROR(VLOOKUP(V43,[1]Curr!$B$2:$C$13,2,FALSE),0) -> 11.3 | X43: =U43*W43 -> 0 | Y43: =Q43 -> 0 | Z43: =+Y43*R43 -> 0 | AA43: EUR | AB43: =IFERROR(VLOOKUP(AA43,Curr!$B$2:$C$13,2,FALSE),0) -> 11.3 | AC43: =+Y43*AB43*R43 -> 0 | AD43: =+AC43-X43 -> 0 | AE43: =IFERROR(AD43/AC43,0) -> 0
S44: =+Q44*R44 -> 0 | T44: 0 | U44: =S44*(1-T44) -> 0 | V44: EUR | W44: =IFERROR(VLOOKUP(V44,[1]Curr!$B$2:$C$13,2,FALSE),0) -> 11.3 | X44: =U44*W44 -> 0 | Y44: =Q44 -> 0 | Z44: =+Y44*R44 -> 0 | AA44: EUR | AB44: =IFERROR(VLOOKUP(AA44,Curr!$B$2:$C$13,2,FALSE),0) -> 11.3 | AC44: =+Y44*AB44*R44 -> 0 | AD44: =+AC44-X44 -> 0 | AE44: =IFERROR(AD44/AC44,0) -> 0
C45: Day 1 | D45: Transfer package | J45: Rovaniemi: Private transfer to your accommodation | Q45: 40 | R45: 0 | S45: =+Q45*R45 -> 0 | T45: 0 | U45: =S45*(1-T45) -> 0 | V45: EUR | W45: =IFERROR(VLOOKUP(V45,[1]Curr!$B$2:$C$13,2,FALSE),0) -> 11.3 | X45: =U45*W45 -> 0 | Y45: =Q45/0.67 -> 59.701493 | Z45: =+Y45*R45 -> 0 | AA45: EUR | AB45: =IFERROR(VLOOKUP(AA45,Curr!$B$2:$C$13,2,FALSE),0) -> 11.3 | AC45: =+Y45*AB45*R45 -> 0 | AD45: =+AC45-X45 -> 0 | AE45: =IFERROR(AD45/AC45,0) -> 0
C46: Day 3 | D46: Transfer package | J46: Rovaniemi: Private transfer to Rovaniemi Bus Station | Q46: 40 | R46: 0 | S46: =+Q46*R46 -> 0 | T46: 0 | U46: =S46*(1-T46) -> 0 | V46: EUR | W46: =IFERROR(VLOOKUP(V46,[1]Curr!$B$2:$C$13,2,FALSE),0) -> 11.3 | X46: =U46*W46 -> 0 | Y46: =Q46/0.67 -> 59.701493 | Z46: =+Y46*R46 -> 0 | AA46: EUR | AB46: =IFERROR(VLOOKUP(AA46,Curr!$B$2:$C$13,2,FALSE),0) -> 11.3 | AC46: =+Y46*AB46*R46 -> 0 | AD46: =+AC46-X46 -> 0 | AE46: =IFERROR(AD46/AC46,0) -> 0
C47: Day 8 | D47: Transfer package | J47: Alta: Private transfer to Alta Airport | Q47: 900 | R47: 0 | S47: =+Q47*R47 -> 0 | T47: 0 | U47: =S47*(1-T47) -> 0 | V47: NOK | W47: =IFERROR(VLOOKUP(V47,[1]Curr!$B$2:$C$13,2,FALSE),0) -> 1 | X47: =U47*W47 -> 0 | Y47: =Q47/11.3/0.8 -> 99.557522 | Z47: =+Y47*R47 -> 0 | AA47: EUR | AB47: =IFERROR(VLOOKUP(AA47,Curr!$B$2:$C$13,2,FALSE),0) -> 11.3 | AC47: =+Y47*AB47*R47 -> 0 | AD47: =+AC47-X47 -> 0 | AE47: =IFERROR(AD47/AC47,0) -> 0
S48: =+Q48*R48 -> 0 | T48: 0 | U48: =S48*(1-T48) -> 0 | V48: EUR | W48: =IFERROR(VLOOKUP(V48,[1]Curr!$B$2:$C$13,2,FALSE),0) -> 11.3 | X48: =U48*W48 -> 0 | Y48: =Q48 -> 0 | Z48: =+Y48*R48 -> 0 | AA48: EUR | AB48: =IFERROR(VLOOKUP(AA48,Curr!$B$2:$C$13,2,FALSE),0) -> 11.3 | AC48: =+Y48*AB48*R48 -> 0 | AD48: =+AC48-X48 -> 0 | AE48: =IFERROR(AD48/AC48,0) -> 0
S49: =+Q49*R49 -> 0 | T49: 0 | U49: =S49*(1-T49) -> 0 | V49: EUR | W49: =IFERROR(VLOOKUP(V49,[1]Curr!$B$2:$C$13,2,FALSE),0) -> 11.3 | X49: =U49*W49 -> 0 | Y49: =Q49 -> 0 | Z49: =+Y49*R49 -> 0 | AA49: EUR | AB49: =IFERROR(VLOOKUP(AA49,Curr!$B$2:$C$13,2,FALSE),0) -> 11.3 | AC49: =+Y49*AB49*R49 -> 0 | AD49: =+AC49-X49 -> 0 | AE49: =IFERROR(AD49/AC49,0) -> 0
C50: Day 2 | D50: Activity Upgrade | J50: Rovaniemi: Snowmobiling and Sledding Arctic Circle Highlights - Time: 08:45 am - 03:45 pm - Meeting point: Arctic Circle Snowmobile Park office - Includes: Pick-up/drop-off in central Rovaniemi, Knowledgeable, English-speaking guide, 1h snowmobiling on shared snowmobile (2 pers), Reindeer experience with 500m sleigh ride, Alaskan Husky experience with 500m sleigh ride, Approx. 2 hours free time in Santa Claus Village, Winter clothes (overalls, boots and gloves), Other equipment (helmet and balaclava), Salmon soup lunch (vegetarian option available) | O50: x | P50: https://booknordics.com/finland/western-lapland/rovaniemi/family-day-snowmobile-arctic-animals-and-santa-village | Q50: 252 | R50: 0 | S50: =+Q50*R50 -> 0 | T50: 0.2 | U50: =S50*(1-T50) -> 0 | V50: EUR | W50: =IFERROR(VLOOKUP(V50,[1]Curr!$B$2:$C$13,2,FALSE),0) -> 11.3 | X50: =U50*W50 -> 0 | Y50: =Q50 -> 252 | Z50: =+Y50*R50 -> 0 | AA50: EUR | AB50: =IFERROR(VLOOKUP(AA50,Curr!$B$2:$C$13,2,FALSE),0) -> 11.3 | AC50: =+Y50*AB50*R50 -> 0 | AD50: =+AC50-X50 -> 0 | AE50: =IFERROR(AD50/AC50,0) -> 0
C51: Day 5 | D51: Activity upgrade | J51: Tromsø: Reindeer Sledding, Reindeer Feeding and Sami Culture - Time: 09:45 am - 2:30 pm - Meeting point: Radisson Blu Hotel's main entrance (Sjøgata 7) - Includes: Scenic transfers (45 min each way), Knowledgeable English- and Norwegian-speaking guide, Thermal winter suit, warm boots, Reindeer sledding (approx. 30 min, depending on weather and snow conditions), Feeding the herd on our camp, Hot traditional Sámi meal (bithos) and hot drinks. Vegetarian option available on request, Cultural introduction about Sámi history and daily life | O51: x | P51: https://booknordics.com/norway/northern-norway/tromso-region/reindeer-sledding-reindeer-feeding-and-sami-culture-3 | Q51: 2195 | R51: 0 | S51: =+Q51*R51 -> 0 | T51: 0.2 | U51: =S51*(1-T51) -> 0 | V51: NOK | W51: =IFERROR(VLOOKUP(V51,[1]Curr!$B$2:$C$13,2,FALSE),0) -> 1 | X51: =U51*W51 -> 0 | Y51: =Q51/11.3 -> 194.24779 | Z51: =+Y51*R51 -> 0 | AA51: EUR | AB51: =IFERROR(VLOOKUP(AA51,Curr!$B$2:$C$13,2,FALSE),0) -> 11.3 | AC51: =+Y51*AB51*R51 -> 0 | AD51: =+AC51-X51 -> 0 | AE51: =IFERROR(AD51/AC51,0) -> 0
C52: Day 7 | D52: Activity upgrade | J52: Alta: Northern Lights Dog Sledding Trip in Alta - Time: 6:00 pm - 10:00 pm - Meeting point: Adventure Store (inside Canyon Hotell), Markedsgata 6 - Includes: Pick-up/drop-off in central Alta, Dog Sledding training and equipment, Dressing the dogs with assistance, Approx. 50 minutes of dog sledding, History of dog sledding and Gargia, Warm clothing to stay cozy in the cold, Hot coffee and tea at mountain lodge | O52: x | P52: https://booknordics.com/norway/northern-norway/alta-and-north-cape/northern-lights-dog-sledding-trip-in-alta | Q52: 185 | R52: 0 | S52: =+Q52*R52 -> 0 | T52: 0.15 | U52: =S52*(1-T52) -> 0 | V52: EUR | W52: =IFERROR(VLOOKUP(V52,[1]Curr!$B$2:$C$13,2,FALSE),0) -> 11.3 | X52: =U52*W52 -> 0 | Y52: =Q52 -> 185 | Z52: =+Y52*R52 -> 0 | AA52: EUR | AB52: =IFERROR(VLOOKUP(AA52,Curr!$B$2:$C$13,2,FALSE),0) -> 11.3 | AC52: =+Y52*AB52*R52 -> 0 | AD52: =+AC52-X52 -> 0 | AE52: =IFERROR(AD52/AC52,0) -> 0
S53: =+Q53*R53 -> 0 | T53: 0 | U53: =S53*(1-T53) -> 0 | V53: EUR | W53: =IFERROR(VLOOKUP(V53,[1]Curr!$B$2:$C$13,2,FALSE),0) -> 11.3 | X53: =U53*W53 -> 0 | Y53: =Q53 -> 0 | Z53: =+Y53*R53 -> 0 | AA53: EUR | AB53: =IFERROR(VLOOKUP(AA53,Curr!$B$2:$C$13,2,FALSE),0) -> 11.3 | AC53: =+Y53*AB53*R53 -> 0 | AD53: =+AC53-X53 -> 0 | AE53: =IFERROR(AD53/AC53,0) -> 0
S54: =+Q54*R54 -> 0 | T54: 0 | U54: =S54*(1-T54) -> 0 | V54: EUR | W54: =IFERROR(VLOOKUP(V54,[1]Curr!$B$2:$C$13,2,FALSE),0) -> 11.3 | X54: =U54*W54 -> 0 | Y54: =Q54 -> 0 | Z54: =+Y54*R54 -> 0 | AA54: EUR | AB54: =IFERROR(VLOOKUP(AA54,Curr!$B$2:$C$13,2,FALSE),0) -> 11.3 | AC54: =+Y54*AB54*R54 -> 0 | AD54: =+AC54-X54 -> 0 | AE54: =IFERROR(AD54/AC54,0) -> 0
C55: Day 8 | D55: Extra Day | J55: Alta: Flight to Oslo - Time: Date dependant - Luggage included: 1 x 23 kg check in and 1 x 8 kg carry on per person | Q55: 0 | R55: 0 | S55: =+Q55*R55 -> 0 | T55: 0 | U55: =S55*(1-T55) -> 0 | V55: NOK | W55: =IFERROR(VLOOKUP(V55,[1]Curr!$B$2:$C$13,2,FALSE),0) -> 1 | X55: =U55*W55 -> 0 | Y55: =Q55/11.3/0.8 -> 0 | Z55: =+Y55*R55 -> 0 | AA55: EUR | AB55: =IFERROR(VLOOKUP(AA55,Curr!$B$2:$C$13,2,FALSE),0) -> 11.3 | AC55: =+Y55*AB55*R55 -> 0 | AD55: =+AC55-X55 -> 0 | AE55: =IFERROR(AD55/AC55,0) -> 0
C56: Day 8 | D56: Extra Day | J56: Oslo: Self transfer to your accommodation | Q56: 0 | R56: 0 | S56: =+Q56*R56 -> 0 | T56: 0 | U56: =S56*(1-T56) -> 0 | V56: EUR | W56: =IFERROR(VLOOKUP(V56,[1]Curr!$B$2:$C$13,2,FALSE),0) -> 11.3 | X56: =U56*W56 -> 0 | Y56: =Q56 -> 0 | Z56: =+Y56*R56 -> 0 | AA56: EUR | AB56: =IFERROR(VLOOKUP(AA56,Curr!$B$2:$C$13,2,FALSE),0) -> 11.3 | AC56: =+Y56*AB56*R56 -> 0 | AD56: =+AC56-X56 -> 0 | AE56: =IFERROR(AD56/AC56,0) -> 0
C57: Day 8 | D57: Extra Day | J57: Oslo: Check in to your accommodation for a 1 night stay - Centrally Located 3/4-star Hotel - Standard Room - Breakfast included | Q57: 175 | R57: 0 | S57: =+Q57*R57 -> 0 | T57: 0 | U57: =S57*(1-T57) -> 0 | V57: EUR | W57: =IFERROR(VLOOKUP(V57,[1]Curr!$B$2:$C$13,2,FALSE),0) -> 11.3 | X57: =U57*W57 -> 0 | Y57: =Q57/0.85 -> 205.88235 | Z57: =+Y57*R57 -> 0 | AA57: EUR | AB57: =IFERROR(VLOOKUP(AA57,Curr!$B$2:$C$13,2,FALSE),0) -> 11.3 | AC57: =+Y57*AB57*R57 -> 0 | AD57: =+AC57-X57 -> 0 | AE57: =IFERROR(AD57/AC57,0) -> 0
C58: Day 9 | D58: Extra Day | J58: Oslo: Self transfer to Oslo Airport | Q58: 0 | R58: 0 | S58: =+Q58*R58 -> 0 | T58: 0 | U58: =S58*(1-T58) -> 0 | V58: EUR | W58: =IFERROR(VLOOKUP(V58,[1]Curr!$B$2:$C$13,2,FALSE),0) -> 11.3 | X58: =U58*W58 -> 0 | Y58: =Q58 -> 0 | Z58: =+Y58*R58 -> 0 | AA58: EUR | AB58: =IFERROR(VLOOKUP(AA58,Curr!$B$2:$C$13,2,FALSE),0) -> 11.3 | AC58: =+Y58*AB58*R58 -> 0 | AD58: =+AC58-X58 -> 0 | AE58: =IFERROR(AD58/AC58,0) -> 0
C59: Day 9 | D59: Extra Day | J59: Oslo: Departure home | Q59: 0 | R59: 0 | S59: =+Q59*R59 -> 0 | T59: 0 | U59: =S59*(1-T59) -> 0 | V59: EUR | W59: =IFERROR(VLOOKUP(V59,[1]Curr!$B$2:$C$13,2,FALSE),0) -> 11.3 | X59: =U59*W59 -> 0 | Y59: =Q59 -> 0 | Z59: =+Y59*R59 -> 0 | AA59: EUR | AB59: =IFERROR(VLOOKUP(AA59,Curr!$B$2:$C$13,2,FALSE),0) -> 11.3 | AC59: =+Y59*AB59*R59 -> 0 | AD59: =+AC59-X59 -> 0 | AE59: =IFERROR(AD59/AC59,0) -> 0
S60: =+Q60*R60 -> 0 | T60: 0 | U60: =S60*(1-T60) -> 0 | V60: EUR | W60: =IFERROR(VLOOKUP(V60,[1]Curr!$B$2:$C$13,2,FALSE),0) -> 11.3 | X60: =U60*W60 -> 0 | Y60: =Q60 -> 0 | Z60: =+Y60*R60 -> 0 | AA60: EUR | AB60: =IFERROR(VLOOKUP(AA60,Curr!$B$2:$C$13,2,FALSE),0) -> 11.3 | AC60: =+Y60*AB60*R60 -> 0 | AD60: =+AC60-X60 -> 0 | AE60: =IFERROR(AD60/AC60,0) -> 0
S61: =+Q61*R61 -> 0 | T61: 0 | U61: =S61*(1-T61) -> 0 | V61: EUR | W61: =IFERROR(VLOOKUP(V61,[1]Curr!$B$2:$C$13,2,FALSE),0) -> 11.3 | X61: =U61*W61 -> 0 | Y61: =Q61 -> 0 | Z61: =+Y61*R61 -> 0 | AA61: EUR | AB61: =IFERROR(VLOOKUP(AA61,Curr!$B$2:$C$13,2,FALSE),0) -> 11.3 | AC61: =+Y61*AB61*R61 -> 0 | AD61: =+AC61-X61 -> 0 | AE61: =IFERROR(AD61/AC61,0) -> 0
B63: Totals | D63: x | E63: x | F63: x | G63: x | H63: x | I63: x | J63: x | K63: x | L63: x | M63: x | N63: x | O63: x | P63: x | Q63: x | R63: x | S63: x | T63: x | U63: x | V63: x | W63: x | X63: x | Y63: x | Z63: =SUM(Z7:Z61) -> 4626.7153 | AC63: =SUM(AC7:AC61) -> 52281.883 | AD63: =SUM(AD7:AD61) -> 9715.9826 | AE63: =IFERROR(AD63/AC63,0) -> 0.18583842 | AF63: =SUM(AF8:AF62) -> 0 | AG63: =SUM(AG8:AG62) -> 0 | AH63: =SUM(AH8:AH62) -> 0 | AI63: =SUM(AI8:AI62) -> 0 | AJ63: =SUM(AJ8:AJ62) -> 0
Y65: Fixed | Z65: =Z12+Z14+Z17+Z22+Z24+Z26+Z28+Z37+Z39 -> 2604.6564
Y66: Variable | Z66: =Z9+Z19+Z34 -> 2022.0588
Y67: Total | Z67: 4640
Y68: PP | Z68: =Z67/2 -> 2320
Y71: Shoulder | Z71: =Z67 -> 4640
Y72: High | Z72: =Z71*1.18 -> 5475.2
Y73: X-mas | Z73: =Z71*1.3 -> 6032
Y74: Low | Z74: =Z71*0.85 -> 3944

Sheet 1207
B1: Places: 2N Rovaniemi - 2N Tromsø -1N Lyngen - 2N Alta
B2: Dates: Winter
B3: Pax: 2
B4: Rooming: Double
B6: ID | C6: Day | D6: Type | E6: From date | F6: To date | G6: From time | H6: To time | I6: Supplier | J6: Travel element | K6: Manual booking? | L6: Status | M6: Comments | N6: Non-refundable | O6: Refundable | P6: URL | Q6: Gross P per unit | R6: Units | S6: Gross P | T6: Supp Comm | U6: Net P | V6: Supp curr | W6: X-rate | X6: Net P NOK | Y6: Sales P per unit | Z6: Price | AA6: Sales curr | AB6: X-rate | AC6: Sales P NOK tot | AD6: GP NOK | AE6: GP % | AF6: VAT25 | AG6: VAT15 | AH6: VAT12 | AI6: VAT0-D | AJ6: VAT0-I
C7: Day 1 | D7: Arrival | J7: Rovaniemi: Welcome to Finland | Q7: 0 | R7: 0 | S7: =+Q7*R7 -> 0 | T7: 0 | U7: =S7*(1-T7) -> 0 | V7: EUR | W7: =IFERROR(VLOOKUP(V7,[1]Curr!$B$2:$C$13,2,FALSE),0) -> 11.3 | X7: =U7*W7 -> 0 | Y7: =Q7 -> 0 | Z7: =+Y7*R7 -> 0 | AA7: EUR | AB7: =IFERROR(VLOOKUP(AA7,Curr!$B$2:$C$13,2,FALSE),0) -> 11.3 | AC7: =+Y7*AB7*R7 -> 0 | AD7: =+AC7-X7 -> 0 | AE7: =IFERROR(AD7/AC7,0) -> 0
C8: Day 1 | D8: Transfer | J8: Rovaniemi: Self transfer to your accommodation | Q8: 0 | R8: 0 | S8: =+Q8*R8 -> 0 | T8: 0 | U8: =S8*(1-T8) -> 0 | V8: EUR | W8: =IFERROR(VLOOKUP(V8,[1]Curr!$B$2:$C$13,2,FALSE),0) -> 11.3 | X8: =U8*W8 -> 0 | Y8: =Q8/0.8 -> 0 | Z8: =+Y8*R8 -> 0 | AA8: EUR | AB8: =IFERROR(VLOOKUP(AA8,Curr!$B$2:$C$13,2,FALSE),0) -> 11.3 | AC8: =+Y8*AB8*R8 -> 0 | AD8: =+AC8-X8 -> 0 | AE8: =IFERROR(AD8/AC8,0) -> 0
C9: Day 1 | D9: Hotel | J9: Rovaniemi: Check in to your accommodation for a 2 night stay - Centrally Located 3/4-star Hotel - Standard Room - Breakfast included | Q9: 600 | R9: 1 | S9: =+Q9*R9 -> 600 | T9: 0 | U9: =S9*(1-T9) -> 600 | V9: EUR | W9: =IFERROR(VLOOKUP(V9,[1]Curr!$B$2:$C$13,2,FALSE),0) -> 11.3 | X9: =U9*W9 -> 6780 | Y9: =Q9/0.8 -> 750 | Z9: =+Y9*R9 -> 750 | AA9: EUR | AB9: =IFERROR(VLOOKUP(AA9,Curr!$B$2:$C$13,2,FALSE),0) -> 11.3 | AC9: =+Y9*AB9*R9 -> 8475 | AD9: =+AC9-X9 -> 1695 | AE9: =IFERROR(AD9/AC9,0) -> 0.2
C10: Day 1 | D10: Leisure | J10: Rovaniemi: Spend time at leisure | Q10: 0 | R10: 0 | S10: =+Q10*R10 -> 0 | T10: 0 | U10: =S10*(1-T10) -> 0 | V10: EUR | W10: =IFERROR(VLOOKUP(V10,[1]Curr!$B$2:$C$13,2,FALSE),0) -> 11.3 | X10: =U10*W10 -> 0 | Y10: =Q10 -> 0 | Z10: =+Y10*R10 -> 0 | AA10: EUR | AB10: =IFERROR(VLOOKUP(AA10,Curr!$B$2:$C$13,2,FALSE),0) -> 11.3 | AC10: =+Y10*AB10*R10 -> 0 | AD10: =+AC10-X10 -> 0 | AE10: =IFERROR(AD10/AC10,0) -> 0
S11: =+Q11*R11 -> 0 | T11: 0 | U11: =S11*(1-T11) -> 0 | V11: EUR | W11: =IFERROR(VLOOKUP(V11,[1]Curr!$B$2:$C$13,2,FALSE),0) -> 11.3 | X11: =U11*W11 -> 0 | Y11: =Q11 -> 0 | Z11: =+Y11*R11 -> 0 | AA11: EUR | AB11: =IFERROR(VLOOKUP(AA11,Curr!$B$2:$C$13,2,FALSE),0) -> 11.3 | AC11: =+Y11*AB11*R11 -> 0 | AD11: =+AC11-X11 -> 0 | AE11: =IFERROR(AD11/AC11,0) -> 0
C12: Day 2 | D12: Activity | J12: Rovaniemi: Arctic Circle Highlights Adventure Day - Time: 08:45 am - 2:45 pm - Meeting point: Arctic Circle Snowmobile Park office - Includes: Pick-up/drop-off in central Rovaniemi, Reindeer Farm visit with sleigh ride (2-3 pers), Reindeer sledge driver’s license reward, Alaskan Husky visit with sleigh ride (4 pers), Approx. 2 hours free time in Santa Claus Village, Winter clothes (overalls, boots and gloves), Traditional salmon soup or vegetarian option | O12: x | P12: https://booknordics.com/finland/western-lapland/rovaniemi/arctic-circle-highlights-family-day-by-minibus | Q12: 188 | R12: 2 | S12: =+Q12*R12 -> 376 | T12: 0.2 | U12: =S12*(1-T12) -> 300.8 | V12: EUR | W12: 11.3 | X12: =U12*W12 -> 3399.04 | Y12: 188 | Z12: =+Y12*R12 -> 376 | AA12: EUR | AB12: =IFERROR(VLOOKUP(AA12,Curr!$B$2:$C$13,2,FALSE),0) -> 11.3 | AC12: =+Y12*AB12*R12 -> 4248.8 | AD12: =+AC12-X12 -> 849.76 | AE12: =IFERROR(AD12/AC12,0) -> 0.2
C13: Day 2 | D13: Leisure | J13: Rovaniemi: Spend time at leisure | Q13: 0 | R13: 0 | S13: =+Q13*R13 -> 0 | T13: 0 | U13: =S13*(1-T13) -> 0 | V13: EUR | W13: =IFERROR(VLOOKUP(V13,[1]Curr!$B$2:$C$13,2,FALSE),0) -> 11.3 | X13: =U13*W13 -> 0 | Y13: =Q13 -> 0 | Z13: =+Y13*R13 -> 0 | AA13: EUR | AB13: =IFERROR(VLOOKUP(AA13,Curr!$B$2:$C$13,2,FALSE),0) -> 11.3 | AC13: =+Y13*AB13*R13 -> 0 | AD13: =+AC13-X13 -> 0 | AE13: =IFERROR(AD13/AC13,0) -> 0
C14: Day 2 | D14: Activity | J14: Rovaniemi: Northern Lights Unlimited Mileage Photo Tour - Time: 08:00 pm - 01:00 am - Meeting point: Book Lapland Office - Includes: Pick-up/drop-off in central Rovaniemi, Knowledgeable, English-speaking guides, Professional DSLR photography (unlimited), Meteorological observations, Thermal winter clothing, Hot drinks & snacks or cookies | O14: x | P14: https://booknordics.com/finland/western-lapland/rovaniemi/rovaniemi-northern-lights-family-tour-by-bus-with-photos | Q14: 109 | R14: 2 | S14: =+Q14*R14 -> 218 | T14: 0.2 | U14: =S14*(1-T14) -> 174.4 | V14: EUR | W14: =IFERROR(VLOOKUP(V14,[1]Curr!$B$2:$C$13,2,FALSE),0) -> 11.3 | X14: =U14*W14 -> 1970.72 | Y14: =Q14 -> 109 | Z14: =+Y14*R14 -> 218 | AA14: EUR | AB14: =IFERROR(VLOOKUP(AA14,Curr!$B$2:$C$13,2,FALSE),0) -> 11.3 | AC14: =+Y14*AB14*R14 -> 2463.4 | AD14: =+AC14-X14 -> 492.68 | AE14: =IFERROR(AD14/AC14,0) -> 0.2
S15: =+Q15*R15 -> 0 | T15: 0 | U15: =S15*(1-T15) -> 0 | V15: EUR | W15: =IFERROR(VLOOKUP(V15,[1]Curr!$B$2:$C$13,2,FALSE),0) -> 11.3 | X15: =U15*W15 -> 0 | Y15: =Q15 -> 0 | Z15: =+Y15*R15 -> 0 | AA15: EUR | AB15: =IFERROR(VLOOKUP(AA15,Curr!$B$2:$C$13,2,FALSE),0) -> 11.3 | AC15: =+Y15*AB15*R15 -> 0 | AD15: =+AC15-X15 -> 0 | AE15: =IFERROR(AD15/AC15,0) -> 0
C16: Day 3 | D16: Transfer | J16: Rovaniemi: Self transfer to Rovaniemi Bus Station | Q16: 0 | R16: 0 | S16: =+Q16*R16 -> 0 | T16: 0 | U16: =S16*(1-T16) -> 0 | V16: EUR | W16: =IFERROR(VLOOKUP(V16,[1]Curr!$B$2:$C$13,2,FALSE),0) -> 11.3 | X16: =U16*W16 -> 0 | Y16: =Q16 -> 0 | Z16: =+Y16*R16 -> 0 | AA16: EUR | AB16: =IFERROR(VLOOKUP(AA16,Curr!$B$2:$C$13,2,FALSE),0) -> 11.3 | AC16: =+Y16*AB16*R16 -> 0 | AD16: =+AC16-X16 -> 0 | AE16: =IFERROR(AD16/AC16,0) -> 0
C17: Day 3 | D17: Activity | J17: Rovaniemi: Arctic Route Coach Transfer to Tromsø - Time: 11:40 am - 7:30 pm - Includes: Tickets | O17: x | P17: https://bestarctic.com/the-arctic-route/arctic-winter-routes-explore-norway-sweden-and-finland/bus-between-tromso-norway-and-rovaniemi-finland/ | Q17: 1830 | R17: 2 | S17: =+Q17*R17 -> 3660 | T17: 0.2 | U17: =S17*(1-T17) -> 2928 | V17: NOK | W17: =IFERROR(VLOOKUP(V17,[1]Curr!$B$2:$C$13,2,FALSE),0) -> 1 | X17: =U17*W17 -> 2928 | Y17: =Q17/11.3/0.9 -> 179.941 | Z17: =+Y17*R17 -> 359.88201 | AA17: EUR | AB17: =IFERROR(VLOOKUP(AA17,Curr!$B$2:$C$13,2,FALSE),0) -> 11.3 | AC17: =+Y17*AB17*R17 -> 4066.6667 | AD17: =+AC17-X17 -> 1138.6667 | AE17: =IFERROR(AD17/AC17,0) -> 0.28
C18: Day 3 | D18: Transfer | J18: Tromsø: Self transfer to your accommodation | Q18: 0 | R18: 0 | S18: =+Q18*R18 -> 0 | T18: 0 | U18: =S18*(1-T18) -> 0 | V18: EUR | W18: =IFERROR(VLOOKUP(V18,[1]Curr!$B$2:$C$13,2,FALSE),0) -> 11.3 | X18: =U18*W18 -> 0 | Y18: =Q18 -> 0 | Z18: =+Y18*R18 -> 0 | AA18: EUR | AB18: =IFERROR(VLOOKUP(AA18,Curr!$B$2:$C$13,2,FALSE),0) -> 11.3 | AC18: =+Y18*AB18*R18 -> 0 | AD18: =+AC18-X18 -> 0 | AE18: =IFERROR(AD18/AC18,0) -> 0
C19: Day 3 | D19: Hotel | J19: Tromsø: Check in to your accommodation for a 2 night stay - Centrally Located 3/4-star Hotel - Standard Room - Breakfast included | O19: x | Q19: 500 | R19: 1 | S19: =+Q19*R19 -> 500 | T19: 0 | U19: =S19*(1-T19) -> 500 | V19: EUR | W19: =IFERROR(VLOOKUP(V19,[1]Curr!$B$2:$C$13,2,FALSE),0) -> 11.3 | X19: =U19*W19 -> 5650 | Y19: =Q19/0.8 -> 625 | Z19: =+Y19*R19 -> 625 | AA19: EUR | AB19: =IFERROR(VLOOKUP(AA19,Curr!$B$2:$C$13,2,FALSE),0) -> 11.3 | AC19: =+Y19*AB19*R19 -> 7062.5 | AD19: =+AC19-X19 -> 1412.5 | AE19: =IFERROR(AD19/AC19,0) -> 0.2
C20: Day 3 | D20: Leisure | J20: Tromsø: Spend time at leisure | Q20: 0 | R20: 0 | S20: =+Q20*R20 -> 0 | T20: 0 | U20: =S20*(1-T20) -> 0 | V20: EUR | W20: =IFERROR(VLOOKUP(V20,[1]Curr!$B$2:$C$13,2,FALSE),0) -> 11.3 | X20: =U20*W20 -> 0 | Y20: =Q20 -> 0 | Z20: =+Y20*R20 -> 0 | AA20: EUR | AB20: =IFERROR(VLOOKUP(AA20,Curr!$B$2:$C$13,2,FALSE),0) -> 11.3 | AC20: =+Y20*AB20*R20 -> 0 | AD20: =+AC20-X20 -> 0 | AE20: =IFERROR(AD20/AC20,0) -> 0
S21: =+Q21*R21 -> 0 | T21: 0 | U21: =S21*(1-T21) -> 0 | V21: EUR | W21: =IFERROR(VLOOKUP(V21,[1]Curr!$B$2:$C$13,2,FALSE),0) -> 11.3 | X21: =U21*W21 -> 0 | Y21: =Q21 -> 0 | Z21: =+Y21*R21 -> 0 | AA21: EUR | AB21: =IFERROR(VLOOKUP(AA21,Curr!$B$2:$C$13,2,FALSE),0) -> 11.3 | AC21: =+Y21*AB21*R21 -> 0 | AD21: =+AC21-X21 -> 0 | AE21: =IFERROR(AD21/AC21,0) -> 0
C22: Day 4 | D22: Activity | J22: Tromsø: Reindeer Feeding and Sámi Culture - Time: 09:45 am - 2:30 pm - Meeting point: Radisson Blu Hotel's main entrance (Sjøgata 7) - Includes: Scenic transfers (45 min each way), Knowledgeable English and Norwegian speaking guide, Feeding the herd at our camp, Hot beverages and hot meal (traditional Sámi stew or vegetable/lentil soup), Cultural introduction about Sámi history and daily life, A chance to see the northern lights from our camp, Thermal suit and warm snow boots | O22: x | P22: https://www.tromsolapland.no/activities/reindeer-feeding-and-sami-culture | Q22: 1695 | R22: 2 | S22: =+Q22*R22 -> 3390 | T22: 0.2 | U22: =S22*(1-T22) -> 2712 | V22: NOK | W22: =IFERROR(VLOOKUP(V22,[1]Curr!$B$2:$C$13,2,FALSE),0) -> 1 | X22: =U22*W22 -> 2712 | Y22: =Q22/11.3 -> 150 | Z22: =+Y22*R22 -> 300 | AA22: EUR | AB22: =IFERROR(VLOOKUP(AA22,Curr!$B$2:$C$13,2,FALSE),0) -> 11.3 | AC22: =+Y22*AB22*R22 -> 3390 | AD22: =+AC22-X22 -> 678 | AE22: =IFERROR(AD22/AC22,0) -> 0.2
C23: Day 4 | D23: Leisure | J23: Tromsø: Spend time at leisure | Q23: 0 | R23: 0 | S23: =+Q23*R23 -> 0 | T23: 0 | U23: =S23*(1-T23) -> 0 | V23: EUR | W23: =IFERROR(VLOOKUP(V23,[1]Curr!$B$2:$C$13,2,FALSE),0) -> 11.3 | X23: =U23*W23 -> 0 | Y23: =Q23 -> 0 | Z23: =+Y23*R23 -> 0 | AA23: EUR | AB23: =IFERROR(VLOOKUP(AA23,Curr!$B$2:$C$13,2,FALSE),0) -> 11.3 | AC23: =+Y23*AB23*R23 -> 0 | AD23: =+AC23-X23 -> 0 | AE23: =IFERROR(AD23/AC23,0) -> 0
C24: Day 4 | D24: Activity | J24: Tromsø: Northern Lights Chase with Pro Photographer - Time: 6:00 pm - 12:00 am - Meeting point: Roald Amundsens plass 1A - Includes: Professional, English-speaking Aurora photographer guides, Transportation by comfortable minibus, van or coach, Help with camera settings and Aurora Borealis photography, Hot drinks and cookies | O24: x | P24: https://booknordics.com/norway/northern-norway/tromso-region/aurora-chase-with-professional-photographers | Q24: 120 | R24: 2 | S24: =+Q24*R24 -> 240 | T24: 0.2 | U24: =S24*(1-T24) -> 192 | V24: EUR | W24: =IFERROR(VLOOKUP(V24,[2]Curr!$B$2:$C$13,2,FALSE),0) -> 11.3 | X24: =U24*W24 -> 2169.6 | Y24: =Q24 -> 120 | Z24: =+Y24*R24 -> 240 | AA24: EUR | AB24: =IFERROR(VLOOKUP(AA24,Curr!$B$2:$C$13,2,FALSE),0) -> 11.3 | AC24: =+Y24*AB24*R24 -> 2712 | AD24: =+AC24-X24 -> 542.4 | AE24: =IFERROR(AD24/AC24,0) -> 0.2
S25: =+Q25*R25 -> 0 | T25: 0 | U25: =S25*(1-T25) -> 0 | V25: EUR | W25: =IFERROR(VLOOKUP(V25,[1]Curr!$B$2:$C$13,2,FALSE),0) -> 11.3 | X25: =U25*W25 -> 0 | Y25: =Q25 -> 0 | Z25: =+Y25*R25 -> 0 | AA25: EUR | AB25: =IFERROR(VLOOKUP(AA25,Curr!$B$2:$C$13,2,FALSE),0) -> 11.3 | AC25: =+Y25*AB25*R25 -> 0 | AD25: =+AC25-X25 -> 0 | AE25: =IFERROR(AD25/AC25,0) -> 0
C26: Day 5 | D26: Transfer | J26: Tromsø: Self transfer to Scandic Ishavs Hotel | Q26: 0 | R26: 0 | S26: =+Q26*R26 -> 0 | T26: 0 | U26: =S26*(1-T26) -> 0 | V26: EUR | W26: =IFERROR(VLOOKUP(V26,[1]Curr!$B$2:$C$13,2,FALSE),0) -> 11.3 | X26: =U26*W26 -> 0 | Y26: =Q26 -> 0 | Z26: =+Y26*R26 -> 0 | AA26: EUR | AB26: =IFERROR(VLOOKUP(AA26,Curr!$B$2:$C$13,2,FALSE),0) -> 11.3 | AC26: =+Y26*AB26*R26 -> 0 | AD26: =+AC26-X26 -> 0 | AE26: =IFERROR(AD26/AC26,0) -> 0
C27: Day 5 | D27: Activity | J27: Tromsø: Crystal Lavvo Stay with Auroras, Meals & Activities - Time: 11:30 am - 10: 50 am (the next day) - Meeting point: Samuel Arnesens gate 5 - Includes: Pick-up/drop-off in Tromsø with scenic transfers, Comfortable overnight stay in crystal lavvo, Fireplace heating with unlimited firewood, Northern Lights hunt with photo workshop, Snowshoeing experience nearby, Lunch and dinner included on day 1, Bathroom/toilet facilities in the main house, Breakfast and return transfer included on day 2 | O27: x | P27: https://booknordics.com/norway/northern-norway/tromso-region/crystal-lavvy-stay-northern-lights-snowshoeing | Q27: 375 | R27: 2 | S27: =+Q27*R27 -> 750 | T27: 0.2 | U27: =S27*(1-T27) -> 600 | V27: EUR | W27: =IFERROR(VLOOKUP(V27,[1]Curr!$B$2:$C$13,2,FALSE),0) -> 11.3 | X27: =U27*W27 -> 6780 | Y27: =Q27 -> 375 | Z27: =+Y27*R27 -> 750 | AA27: EUR | AB27: =IFERROR(VLOOKUP(AA27,Curr!$B$2:$C$13,2,FALSE),0) -> 11.3 | AC27: =+Y27*AB27*R27 -> 8475 | AD27: =+AC27-X27 -> 1695 | AE27: =IFERROR(AD27/AC27,0) -> 0.2
S28: =+Q28*R28 -> 0 | T28: 0 | U28: =S28*(1-T28) -> 0 | V28: EUR | W28: =IFERROR(VLOOKUP(V28,[1]Curr!$B$2:$C$13,2,FALSE),0) -> 11.3 | X28: =U28*W28 -> 0 | Y28: =Q28 -> 0 | Z28: =+Y28*R28 -> 0 | AA28: EUR | AB28: =IFERROR(VLOOKUP(AA28,Curr!$B$2:$C$13,2,FALSE),0) -> 11.3 | AC28: =+Y28*AB28*R28 -> 0 | AD28: =+AC28-X28 -> 0 | AE28: =IFERROR(AD28/AC28,0) -> 0
C29: Day 6 | D29: Transfer | J29: Lyngen: Shuttle transfer back to Scandic Ishavs Hotel in Tromsø | Q29: 0 | R29: 0 | S29: =+Q29*R29 -> 0 | T29: 0 | U29: =S29*(1-T29) -> 0 | V29: EUR | W29: =IFERROR(VLOOKUP(V29,[1]Curr!$B$2:$C$13,2,FALSE),0) -> 11.3 | X29: =U29*W29 -> 0 | Y29: =Q29 -> 0 | Z29: =+Y29*R29 -> 0 | AA29: EUR | AB29: =IFERROR(VLOOKUP(AA29,Curr!$B$2:$C$13,2,FALSE),0) -> 11.3 | AC29: =+Y29*AB29*R29 -> 0 | AD29: =+AC29-X29 -> 0 | AE29: =IFERROR(AD29/AC29,0) -> 0
C30: Day 6 | D30: Transfer | J30: Tromsø: Self transfer to Tromsø Bus Terminal Prostneset | Q30: 0 | R30: 0 | S30: =+Q30*R30 -> 0 | T30: 0 | U30: =S30*(1-T30) -> 0 | V30: EUR | W30: =IFERROR(VLOOKUP(V30,[1]Curr!$B$2:$C$13,2,FALSE),0) -> 11.3 | X30: =U30*W30 -> 0 | Y30: =Q30 -> 0 | Z30: =+Y30*R30 -> 0 | AA30: EUR | AB30: =IFERROR(VLOOKUP(AA30,Curr!$B$2:$C$13,2,FALSE),0) -> 11.3 | AC30: =+Y30*AB30*R30 -> 0 | AD30: =+AC30-X30 -> 0 | AE30: =IFERROR(AD30/AC30,0) -> 0
C31: Day 6 | D31: Coach | J31: Tromsø: Long distance panorama coach transfer to Alta - Bus 150 - Time: 4:00 pm - 10:20 pm - Excludes: Tickets (To be bought on site) | Q31: 0 | R31: 0 | S31: =+Q31*R31 -> 0 | T31: 0 | U31: =S31*(1-T31) -> 0 | V31: EUR | W31: =IFERROR(VLOOKUP(V31,[1]Curr!$B$2:$C$13,2,FALSE),0) -> 11.3 | X31: =U31*W31 -> 0 | Y31: =Q31 -> 0 | Z31: =+Y31*R31 -> 0 | AA31: EUR | AB31: =IFERROR(VLOOKUP(AA31,Curr!$B$2:$C$13,2,FALSE),0) -> 11.3 | AC31: =+Y31*AB31*R31 -> 0 | AD31: =+AC31-X31 -> 0 | AE31: =IFERROR(AD31/AC31,0) -> 0
C32: Day 6 | D32: Transfer | J32: Alta: Self transfer to your accommodation | Q32: 0 | R32: 0 | S32: =+Q32*R32 -> 0 | T32: 0 | U32: =S32*(1-T32) -> 0 | V32: EUR | W32: =IFERROR(VLOOKUP(V32,[1]Curr!$B$2:$C$13,2,FALSE),0) -> 11.3 | X32: =U32*W32 -> 0 | Y32: =Q32 -> 0 | Z32: =+Y32*R32 -> 0 | AA32: EUR | AB32: =IFERROR(VLOOKUP(AA32,Curr!$B$2:$C$13,2,FALSE),0) -> 11.3 | AC32: =+Y32*AB32*R32 -> 0 | AD32: =+AC32-X32 -> 0 | AE32: =IFERROR(AD32/AC32,0) -> 0
C33: Day 6 | D33: Hotel | J33: Alta: Check in to your accommodation for a 2 night stay - Centrally Located 3/4-star Hotel - Standard Room - Breakfast included | Q33: 400 | R33: 1 | S33: =+Q33*R33 -> 400 | T33: 0 | U33: =S33*(1-T33) -> 400 | V33: EUR | W33: =IFERROR(VLOOKUP(V33,[1]Curr!$B$2:$C$13,2,FALSE),0) -> 11.3 | X33: =U33*W33 -> 4520 | Y33: =Q33/0.85 -> 470.58824 | Z33: =+Y33*R33 -> 470.58824 | AA33: EUR | AB33: =IFERROR(VLOOKUP(AA33,Curr!$B$2:$C$13,2,FALSE),0) -> 11.3 | AC33: =+Y33*AB33*R33 -> 5317.6471 | AD33: =+AC33-X33 -> 797.64706 | AE33: =IFERROR(AD33/AC33,0) -> 0.15
C34: Day 6 | D34: Leisure | J34: Alta: Spend time at leisure | Q34: 0 | R34: 0 | S34: =+Q34*R34 -> 0 | T34: 0 | U34: =S34*(1-T34) -> 0 | V34: EUR | W34: =IFERROR(VLOOKUP(V34,[1]Curr!$B$2:$C$13,2,FALSE),0) -> 11.3 | X34: =U34*W34 -> 0 | Y34: =Q34 -> 0 | Z34: =+Y34*R34 -> 0 | AA34: EUR | AB34: =IFERROR(VLOOKUP(AA34,Curr!$B$2:$C$13,2,FALSE),0) -> 11.3 | AC34: =+Y34*AB34*R34 -> 0 | AD34: =+AC34-X34 -> 0 | AE34: =IFERROR(AD34/AC34,0) -> 0
S35: =+Q35*R35 -> 0 | T35: 0 | U35: =S35*(1-T35) -> 0 | V35: EUR | W35: =IFERROR(VLOOKUP(V35,[1]Curr!$B$2:$C$13,2,FALSE),0) -> 11.3 | X35: =U35*W35 -> 0 | Y35: =Q35 -> 0 | Z35: =+Y35*R35 -> 0 | AA35: EUR | AB35: =IFERROR(VLOOKUP(AA35,Curr!$B$2:$C$13,2,FALSE),0) -> 11.3 | AC35: =+Y35*AB35*R35 -> 0 | AD35: =+AC35-X35 -> 0 | AE35: =IFERROR(AD35/AC35,0) -> 0
C36: Day 7 | D36: Activity | J36: Alta: Visit to Sorrisniva Igloo Hotel - Time: Flexible - Meeting point: Sorrisniva Arctic Wilderness Lodge - Includes: Entry ticket to explore Sorrisniva Igloo Hotel | O36: x | P36: https://booknordics.com/norway/northern-norway/alta-and-north-cape/entrance-ticket-igloo-hotel | Q36: 34 | R36: 2 | S36: =+Q36*R36 -> 68 | T36: 0.15 | U36: =S36*(1-T36) -> 57.8 | V36: EUR | W36: =IFERROR(VLOOKUP(V36,[1]Curr!$B$2:$C$13,2,FALSE),0) -> 11.3 | X36: =U36*W36 -> 653.14 | Y36: =Q36 -> 34 | Z36: =+Y36*R36 -> 68 | AA36: EUR | AB36: =IFERROR(VLOOKUP(AA36,Curr!$B$2:$C$13,2,FALSE),0) -> 11.3 | AC36: =+Y36*AB36*R36 -> 768.4 | AD36: =+AC36-X36 -> 115.26 | AE36: =IFERROR(AD36/AC36,0) -> 0.15
C37: Day 7 | D37: Leisure | J37: Alta: Spend time at leisure | Q37: 0 | R37: 0 | S37: =+Q37*R37 -> 0 | T37: 0 | U37: =S37*(1-T37) -> 0 | V37: EUR | W37: =IFERROR(VLOOKUP(V37,[1]Curr!$B$2:$C$13,2,FALSE),0) -> 11.3 | X37: =U37*W37 -> 0 | Y37: =Q37 -> 0 | Z37: =+Y37*R37 -> 0 | AA37: EUR | AB37: =IFERROR(VLOOKUP(AA37,Curr!$B$2:$C$13,2,FALSE),0) -> 11.3 | AC37: =+Y37*AB37*R37 -> 0 | AD37: =+AC37-X37 -> 0 | AE37: =IFERROR(AD37/AC37,0) -> 0
C38: Day 7 | D38: Activity | J38: Alta: Small Group Northern Lights Hunt - Time: 7:00 pm - 11:00 pm - Meeting point: Æventyr Booking Point - Includes: Professional guide, Northern Lights lectures and local history, Coffee / tea and snacks, Warm overalls for loan | O38: x | P38: https://www.aeventyr.no/activities/small-group-northern-lights-hunt | Q38: 2290 | R38: 2 | S38: =+Q38*R38 -> 4580 | T38: 0.15 | U38: =S38*(1-T38) -> 3893 | V38: NOK | W38: =IFERROR(VLOOKUP(V38,[1]Curr!$B$2:$C$13,2,FALSE),0) -> 1 | X38: =U38*W38 -> 3893 | Y38: =Q38/11.3 -> 202.65487 | Z38: =+Y38*R38 -> 405.30973 | AA38: EUR | AB38: =IFERROR(VLOOKUP(AA38,Curr!$B$2:$C$13,2,FALSE),0) -> 11.3 | AC38: =+Y38*AB38*R38 -> 4580 | AD38: =+AC38-X38 -> 687 | AE38: =IFERROR(AD38/AC38,0) -> 0.15
