Workbook

Sheet Curr
C1: NOK
B2: EUR | C2: 11.2
B3: SEK | C3: 1.02
B4: DKK | C4: 1.5
B5: ISK | C5: 0.075
B6: NOK | C6: 1
B7: USD | C7: 10.6

Sheet Mal
B1: Season: Summer
B2: Places: Trondheim - Sandnessjøen - Svolvær
B3: Pax: 2
B4: Rooming: Double
B6: ID | C6: Day | D6: Type | E6: From date | F6: To date | G6: From time | H6: To time | I6: Supplier | J6: Travel element | K6: Manual booking? | L6: Status | M6: Comments | N6: Non-refundable | O6: Refundable | P6: URL | Q6: Gross P per unit | R6: Units | S6: Gross P | T6: Supp Comm | U6: Net P | V6: Supp curr | W6: X-rate | X6: Net P NOK | Y6: Sales P per unit | Z6: Price | AA6: Sales curr | AB6: X-rate | AC6: Sales P NOK tot | AD6: GP NOK | AE6: GP % | AF6: VAT25 | AG6: VAT15 | AH6: VAT12 | AI6: VAT0-D | AJ6: VAT0-I
Q7: 0 | R7: 0 | S7: =+Q7*R7 -> 0 | T7: 0 | U7: =S7*(1-T7) -> 0 | V7: EUR | W7: =IFERROR(VLOOKUP(V7,Curr!$B$2:$C$13,2,FALSE),0) -> 11.2 | X7: =U7*W7 -> 0 | Y7: =Q7 -> 0 | Z7: =+Y7*R7 -> 0 | AA7: EUR | AB7: =IFERROR(VLOOKUP(AA7,Curr!$B$2:$C$13,2,FALSE),0) -> 11.2 | AC7: =+Y7*AB7*R7 -> 0 | AD7: =+AC7-X7 -> 0 | AE7: =IFERROR(AD7/AC7,0) -> 0
Q8: 0 | R8: 0 | S8: =+Q8*R8 -> 0 | T8: 0 | U8: =S8*(1-T8) -> 0 | V8: EUR | W8: =IFERROR(VLOOKUP(V8,Curr!$B$2:$C$13,2,FALSE),0) -> 11.2 | X8: =U8*W8 -> 0 | Y8: =Q8 -> 0 | Z8: =+Y8*R8 -> 0 | AA8: EUR | AB8: =IFERROR(VLOOKUP(AA8,Curr!$B$2:$C$13,2,FALSE),0) -> 11.2 | AC8: =+Y8*AB8*R8 -> 0 | AD8: =+AC8-X8 -> 0 | AE8: =IFERROR(AD8/AC8,0) -> 0
Q9: 0 | R9: 0 | S9: =+Q9*R9 -> 0 | T9: 0 | U9: =S9*(1-T9) -> 0 | V9: EUR | W9: =IFERROR(VLOOKUP(V9,Curr!$B$2:$C$13,2,FALSE),0) -> 11.2 | X9: =U9*W9 -> 0 | Y9: =Q9 -> 0 | Z9: =+Y9*R9 -> 0 | AA9: EUR | AB9: =IFERROR(VLOOKUP(AA9,Curr!$B$2:$C$13,2,FALSE),0) -> 11.2 | AC9: =+Y9*AB9*R9 -> 0 | AD9: =+AC9-X9 -> 0 | AE9: =IFERROR(AD9/AC9,0) -> 0
Q10: 0 | R10: 0 | S10: =+Q10*R10 -> 0 | T10: 0 | U10: =S10*(1-T10) -> 0 | V10: EUR | W10: =IFERROR(VLOOKUP(V10,Curr!$B$2:$C$13,2,FALSE),0) -> 11.2 | X10: =U10*W10 -> 0 | Y10: =Q10 -> 0 | Z10: =+Y10*R10 -> 0 | AA10: EUR | AB10: =IFERROR(VLOOKUP(AA10,Curr!$B$2:$C$13,2,FALSE),0) -> 11.2 | AC10: =+Y10*AB10*R10 -> 0 | AD10: =+AC10-X10 -> 0 | AE10: =IFERROR(AD10/AC10,0) -> 0
Q11: 0 | R11: 0 | S11: =+Q11*R11 -> 0 | T11: 0 | U11: =S11*(1-T11) -> 0 | V11: EUR | W11: =IFERROR(VLOOKUP(V11,Curr!$B$2:$C$13,2,FALSE),0) -> 11.2 | X11: =U11*W11 -> 0 | Y11: =Q11 -> 0 | Z11: =+Y11*R11 -> 0 | AA11: EUR | AB11: =IFERROR(VLOOKUP(AA11,Curr!$B$2:$C$13,2,FALSE),0) -> 11.2 | AC11: =+Y11*AB11*R11 -> 0 | AD11: =+AC11-X11 -> 0 | AE11: =IFERROR(AD11/AC11,0) -> 0
Q12: 0 | R12: 0 | S12: =+Q12*R12 -> 0 | T12: 0 | U12: =S12*(1-T12) -> 0 | V12: EUR | W12: =IFERROR(VLOOKUP(V12,Curr!$B$2:$C$13,2,FALSE),0) -> 11.2 | X12: =U12*W12 -> 0 | Y12: =Q12 -> 0 | Z12: =+Y12*R12 -> 0 | AA12: EUR | AB12: =IFERROR(VLOOKUP(AA12,Curr!$B$2:$C$13,2,FALSE),0) -> 11.2 | AC12: =+Y12*AB12*R12 -> 0 | AD12: =+AC12-X12 -> 0 | AE12: =IFERROR(AD12/AC12,0) -> 0
Q13: 0 | R13: 0 | S13: =+Q13*R13 -> 0 | T13: 0 | U13: =S13*(1-T13) -> 0 | V13: EUR | W13: =IFERROR(VLOOKUP(V13,Curr!$B$2:$C$13,2,FALSE),0) -> 11.2 | X13: =U13*W13 -> 0 | Y13: =Q13 -> 0 | Z13: =+Y13*R13 -> 0 | AA13: EUR | AB13: =IFERROR(VLOOKUP(AA13,Curr!$B$2:$C$13,2,FALSE),0) -> 11.2 | AC13: =+Y13*AB13*R13 -> 0 | AD13: =+AC13-X13 -> 0 | AE13: =IFERROR(AD13/AC13,0) -> 0
Q14: 0 | R14: 0 | S14: =+Q14*R14 -> 0 | T14: 0 | U14: =S14*(1-T14) -> 0 | V14: EUR | W14: =IFERROR(VLOOKUP(V14,Curr!$B$2:$C$13,2,FALSE),0) -> 11.2 | X14: =U14*W14 -> 0 | Y14: =Q14 -> 0 | Z14: =+Y14*R14 -> 0 | AA14: EUR | AB14: =IFERROR(VLOOKUP(AA14,Curr!$B$2:$C$13,2,FALSE),0) -> 11.2 | AC14: =+Y14*AB14*R14 -> 0 | AD14: =+AC14-X14 -> 0 | AE14: =IFERROR(AD14/AC14,0) -> 0
Q15: 0 | R15: 0 | S15: =+Q15*R15 -> 0 | T15: 0 | U15: =S15*(1-T15) -> 0 | V15: EUR | W15: =IFERROR(VLOOKUP(V15,Curr!$B$2:$C$13,2,FALSE),0) -> 11.2 | X15: =U15*W15 -> 0 | Y15: =Q15 -> 0 | Z15: =+Y15*R15 -> 0 | AA15: EUR | AB15: =IFERROR(VLOOKUP(AA15,Curr!$B$2:$C$13,2,FALSE),0) -> 11.2 | AC15: =+Y15*AB15*R15 -> 0 | AD15: =+AC15-X15 -> 0 | AE15: =IFERROR(AD15/AC15,0) -> 0
Q16: 0 | R16: 0 | S16: =+Q16*R16 -> 0 | T16: 0 | U16: =S16*(1-T16) -> 0 | V16: EUR | W16: =IFERROR(VLOOKUP(V16,Curr!$B$2:$C$13,2,FALSE),0) -> 11.2 | X16: =U16*W16 -> 0 | Y16: =Q16 -> 0 | Z16: =+Y16*R16 -> 0 | AA16: EUR | AB16: =IFERROR(VLOOKUP(AA16,Curr!$B$2:$C$13,2,FALSE),0) -> 11.2 | AC16: =+Y16*AB16*R16 -> 0 | AD16: =+AC16-X16 -> 0 | AE16: =IFERROR(AD16/AC16,0) -> 0
Q17: 0 | R17: 0 | S17: =+Q17*R17 -> 0 | T17: 0 | U17: =S17*(1-T17) -> 0 | V17: EUR | W17: =IFERROR(VLOOKUP(V17,Curr!$B$2:$C$13,2,FALSE),0) -> 11.2 | X17: =U17*W17 -> 0 | Y17: =Q17 -> 0 | Z17: =+Y17*R17 -> 0 | AA17: EUR | AB17: =IFERROR(VLOOKUP(AA17,Curr!$B$2:$C$13,2,FALSE),0) -> 11.2 | AC17: =+Y17*AB17*R17 -> 0 | AD17: =+AC17-X17 -> 0 | AE17: =IFERROR(AD17/AC17,0) -> 0
Q18: 0 | R18: 0 | S18: =+Q18*R18 -> 0 | T18: 0 | U18: =S18*(1-T18) -> 0 | V18: EUR | W18: =IFERROR(VLOOKUP(V18,Curr!$B$2:$C$13,2,FALSE),0) -> 11.2 | X18: =U18*W18 -> 0 | Y18: =Q18 -> 0 | Z18: =+Y18*R18 -> 0 | AA18: EUR | AB18: =IFERROR(VLOOKUP(AA18,Curr!$B$2:$C$13,2,FALSE),0) -> 11.2 | AC18: =+Y18*AB18*R18 -> 0 | AD18: =+AC18-X18 -> 0 | AE18: =IFERROR(AD18/AC18,0) -> 0
... Q98: 0 | R98: 0 | S98: =+Q98*R98 -> 0 | T98: 0 | U98: =S98*(1-T98) -> 0 | V98: EUR | W98: =IFERROR(VLOOKUP(V98,Curr!$B$2:$C$13,2,FALSE),0) -> 11.2 | X98: =U98*W98 -> 0 | Y98: =Q98 -> 0 | Z98: =+Y98*R98 -> 0 | AA98: EUR | AB98: =IFERROR(VLOOKUP(AA98,Curr!$B$2:$C$13,2,FALSE),0) -> 11.2 | AC98: =+Y98*AB98*R98 -> 0 | AD98: =+AC98-X98 -> 0 | AE98: =IFERROR(AD98/AC98,0) -> 0
B100: Totals | D100: x | E100: x | F100: x | G100: x | H100: x | I100: x | J100: x | K100: x | L100: x | M100: x | N100: x | O100: x | P100: x | Q100: x | R100: x | S100: x | T100: x | U100: x | V100: x | W100: x | X100: x | Y100: x | Z100: =SUM(Z7:Z98) -> 0 | AC100: =SUM(AC7:AC98) -> 0 | AD100: =SUM(AD7:AD98) -> 0 | AE100: =IFERROR(AD100/AC100,0) -> 0 | AF100: =SUM(AF8:AF99) -> 0 | AG100: =SUM(AG8:AG99) -> 0 | AH100: =SUM(AH8:AH99) -> 0 | AI100: =SUM(AI8:AI99) -> 0 | AJ100: =SUM(AJ8:AJ99) -> 0
Y102: Fixed | Z102: 1290
Y103: Variable | Z103: =Z54+Z60+Z68+Z70 -> 0
Y104: Total | Z104: 2920
Y105: PP | Z105: =Z104/2 -> 1460
Y107: Ref | Z107: 2920
Y108: NoRef | Z108: 0
Y110: Deposit | Z110: 850
Y111: Rest | Z111: 1760

Sheet 201
B1: Season: Winter
B2: Places: Oslo 1N - Bergen 2N - Tromsø 2N
B3: Pax: 2
B4: Rooming: Double
B6: ID | C6: Day | D6: Type | E6: From date | F6: To date | G6: From time | H6: To time | I6: Supplier | J6: Travel element | K6: Manual booking? | L6: Status | M6: Comments | N6: Non-refundable | O6: Refundable | P6: URL | Q6: Gross P per unit | R6: Units | S6: Gross P | T6: Supp Comm | U6: Net P | V6: Supp curr | W6: X-rate | X6: Net P NOK | Y6: Sales P per unit | Z6: Price | AA6: Sales curr | AB6: X-rate | AC6: Sales P NOK tot | AD6: GP NOK | AE6: GP % | AF6: VAT25 | AG6: VAT15 | AH6: VAT12 | AI6: VAT0-D | AJ6: VAT0-I
C7: Day 1 | D7: Arrival | J7: Oslo: Welcome to Norway | Q7: 0 | R7: 0 | S7: =+Q7*R7 -> 0 | T7: 0 | U7: =S7*(1-T7) -> 0 | V7: EUR | W7: =IFERROR(VLOOKUP(V7,Curr!$B$2:$C$13,2,FALSE),0) -> 11.2 | X7: =U7*W7 -> 0 | Y7: =Q7 -> 0 | Z7: =+Y7*R7 -> 0 | AA7: EUR | AB7: =IFERROR(VLOOKUP(AA7,Curr!$B$2:$C$13,2,FALSE),0) -> 11.2 | AC7: =+Y7*AB7*R7 -> 0 | AD7: =+AC7-X7 -> 0 | AE7: =IFERROR(AD7/AC7,0) -> 0
C8: Day 1 | D8: Transfer | J8: Oslo: Self transfer to your accommodation | Q8: 0 | R8: 0 | S8: =+Q8*R8 -> 0 | T8: 0 | U8: =S8*(1-T8) -> 0 | V8: NOK | W8: =IFERROR(VLOOKUP(V8,Curr!$B$2:$C$13,2,FALSE),0) -> 1 | X8: =U8*W8 -> 0 | Y8: =Q8/11.3/0.8 -> 0 | Z8: =+Y8*R8 -> 0 | AA8: EUR | AB8: =IFERROR(VLOOKUP(AA8,Curr!$B$2:$C$13,2,FALSE),0) -> 11.2 | AC8: =+Y8*AB8*R8 -> 0 | AD8: =+AC8-X8 -> 0 | AE8: =IFERROR(AD8/AC8,0) -> 0
C9: Day 1 | D9: Hotel | J9: Oslo: Check in to your accommodation for a 1 night stay - Centrally located 3/4-star hotel - Standard Room - Breakfast included | Q9: 150 | R9: 1 | S9: =+Q9*R9 -> 150 | T9: 0 | U9: =S9*(1-T9) -> 150 | V9: EUR | W9: =IFERROR(VLOOKUP(V9,Curr!$B$2:$C$13,2,FALSE),0) -> 11.2 | X9: =U9*W9 -> 1680 | Y9: =Q9/0.85 -> 176.47059 | Z9: =+Y9*R9 -> 176.47059 | AA9: EUR | AB9: =IFERROR(VLOOKUP(AA9,Curr!$B$2:$C$13,2,FALSE),0) -> 11.2 | AC9: =+Y9*AB9*R9 -> 1976.4706 | AD9: =+AC9-X9 -> 296.47059 | AE9: =IFERROR(AD9/AC9,0) -> 0.15
C10: Day 1 | D10: Leisure | J10: Oslo: Spend time at leisure | Q10: 0 | R10: 0 | S10: =+Q10*R10 -> 0 | T10: 0 | U10: =S10*(1-T10) -> 0 | V10: EUR | W10: =IFERROR(VLOOKUP(V10,Curr!$B$2:$C$13,2,FALSE),0) -> 11.2 | X10: =U10*W10 -> 0 | Y10: =Q10 -> 0 | Z10: =+Y10*R10 -> 0 | AA10: EUR | AB10: =IFERROR(VLOOKUP(AA10,Curr!$B$2:$C$13,2,FALSE),0) -> 11.2 | AC10: =+Y10*AB10*R10 -> 0 | AD10: =+AC10-X10 -> 0 | AE10: =IFERROR(AD10/AC10,0) -> 0
S11: =+Q11*R11 -> 0 | T11: 0 | U11: =S11*(1-T11) -> 0 | V11: EUR | W11: =IFERROR(VLOOKUP(V11,Curr!$B$2:$C$13,2,FALSE),0) -> 11.2 | X11: =U11*W11 -> 0 | Y11: =Q11 -> 0 | Z11: =+Y11*R11 -> 0 | AA11: EUR | AB11: =IFERROR(VLOOKUP(AA11,Curr!$B$2:$C$13,2,FALSE),0) -> 11.2 | AC11: =+Y11*AB11*R11 -> 0 | AD11: =+AC11-X11 -> 0 | AE11: =IFERROR(AD11/AC11,0) -> 0
C12: Day 2 | D12: Transfer | J12: Oslo: Self transfer to Oslo Central Station | Q12: 0 | R12: 0 | S12: =+Q12*R12 -> 0 | T12: 0 | U12: =S12*(1-T12) -> 0 | V12: EUR | W12: =IFERROR(VLOOKUP(V12,Curr!$B$2:$C$13,2,FALSE),0) -> 11.2 | X12: =U12*W12 -> 0 | Y12: =Q12 -> 0 | Z12: =+Y12*R12 -> 0 | AA12: EUR | AB12: =IFERROR(VLOOKUP(AA12,Curr!$B$2:$C$13,2,FALSE),0) -> 11.2 | AC12: =+Y12*AB12*R12 -> 0 | AD12: =+AC12-X12 -> 0 | AE12: =IFERROR(AD12/AC12,0) -> 0
C13: Day 2 | D13: Train | J13: Oslo: Scenic Long Distance Train transfer to Bergen - Time: 08:25 am - 3:00 pm - Includes: Tickets | O13: x | P13: https://www.vy.no/#reisesok | Q13: 2400 | R13: 1 | S13: =+Q13*R13 -> 2400 | T13: 0 | U13: =S13*(1-T13) -> 2400 | V13: NOK | W13: =IFERROR(VLOOKUP(V13,Curr!$B$2:$C$13,2,FALSE),0) -> 1 | X13: =U13*W13 -> 2400 | Y13: =Q13/11.3/0.8 -> 265.48673 | Z13: =+Y13*R13 -> 265.48673 | AA13: EUR | AB13: =IFERROR(VLOOKUP(AA13,Curr!$B$2:$C$13,2,FALSE),0) -> 11.2 | AC13: =+Y13*AB13*R13 -> 2973.4513 | AD13: =+AC13-X13 -> 573.45133 | AE13: =IFERROR(AD13/AC13,0) -> 0.19285714
C14: Day 2 | D14: Transfer | J14: Bergen: Self transfer to your accommodation | Q14: 0 | R14: 0 | S14: =+Q14*R14 -> 0 | T14: 0 | U14: =S14*(1-T14) -> 0 | V14: EUR | W14: =IFERROR(VLOOKUP(V14,Curr!$B$2:$C$13,2,FALSE),0) -> 11.2 | X14: =U14*W14 -> 0 | Y14: =Q14 -> 0 | Z14: =+Y14*R14 -> 0 | AA14: EUR | AB14: =IFERROR(VLOOKUP(AA14,Curr!$B$2:$C$13,2,FALSE),0) -> 11.2 | AC14: =+Y14*AB14*R14 -> 0 | AD14: =+AC14-X14 -> 0 | AE14: =IFERROR(AD14/AC14,0) -> 0
C15: Day 2 | D15: Hotel | J15: Bergen: Check in to your accommodation for a 2 night stay - Centrally located 3/4-star hotel - Standard Room - Breakfast included | Q15: 280 | R15: 1 | S15: =+Q15*R15 -> 280 | T15: 0 | U15: =S15*(1-T15) -> 280 | V15: EUR | W15: =IFERROR(VLOOKUP(V15,Curr!$B$2:$C$13,2,FALSE),0) -> 11.2 | X15: =U15*W15 -> 3136 | Y15: =Q15/0.85 -> 329.41176 | Z15: =+Y15*R15 -> 329.41176 | AA15: EUR | AB15: =IFERROR(VLOOKUP(AA15,Curr!$B$2:$C$13,2,FALSE),0) -> 11.2 | AC15: =+Y15*AB15*R15 -> 3689.4118 | AD15: =+AC15-X15 -> 553.41176 | AE15: =IFERROR(AD15/AC15,0) -> 0.15
C16: Day 2 | D16: Leisure | J16: Bergen: Spend time at leisure | Q16: 0 | R16: 0 | S16: =+Q16*R16 -> 0 | T16: 0 | U16: =S16*(1-T16) -> 0 | V16: EUR | W16: =IFERROR(VLOOKUP(V16,Curr!$B$2:$C$13,2,FALSE),0) -> 11.2 | X16: =U16*W16 -> 0 | Y16: =Q16 -> 0 | Z16: =+Y16*R16 -> 0 | AA16: EUR | AB16: =IFERROR(VLOOKUP(AA16,Curr!$B$2:$C$13,2,FALSE),0) -> 11.2 | AC16: =+Y16*AB16*R16 -> 0 | AD16: =+AC16-X16 -> 0 | AE16: =IFERROR(AD16/AC16,0) -> 0
S17: =+Q17*R17 -> 0 | T17: 0 | U17: =S17*(1-T17) -> 0 | V17: EUR | W17: =IFERROR(VLOOKUP(V17,Curr!$B$2:$C$13,2,FALSE),0) -> 11.2 | X17: =U17*W17 -> 0 | Y17: =Q17 -> 0 | Z17: =+Y17*R17 -> 0 | AA17: EUR | AB17: =IFERROR(VLOOKUP(AA17,Curr!$B$2:$C$13,2,FALSE),0) -> 11.2 | AC17: =+Y17*AB17*R17 -> 0 | AD17: =+AC17-X17 -> 0 | AE17: =IFERROR(AD17/AC17,0) -> 0
C18: Day 3 | D18: Activity | J18: Bergen: 2 hr walk Through Bergen Past & Present - Time: 10:00 am - 12:00 pm - Meeting point: Bradbenken 1 - Includes: Profesional Guide | O18: x | P18: https://www.ilovebergen.net/tour/a-walk-through-bergen-past-present/ | Q18: 290 | R18: 2 | S18: =+Q18*R18 -> 580 | T18: 0.2 | U18: =S18*(1-T18) -> 464 | V18: NOK | W18: =IFERROR(VLOOKUP(V18,Curr!$B$2:$C$13,2,FALSE),0) -> 1 | X18: =U18*W18 -> 464 | Y18: =Q18/11.3/0.64 -> 40.099558 | Z18: =+Y18*R18 -> 80.199115 | AA18: EUR | AB18: =IFERROR(VLOOKUP(AA18,Curr!$B$2:$C$13,2,FALSE),0) -> 11.2 | AC18: =+Y18*AB18*R18 -> 898.23009 | AD18: =+AC18-X18 -> 434.23009 | AE18: =IFERROR(AD18/AC18,0) -> 0.48342857
C19: Day 3 | D19: Activity | J19: Bergen: Fløibanen Funicual - Time: Flexible - Meeting point: Vetrlidsallmenningen 23A - Includes: Tickets | O19: x | P19: https://www.floyen.no/en/floibanen/buy-tickets/ | Q19: 175 | R19: 2 | S19: =+Q19*R19 -> 350 | T19: 0 | U19: =S19*(1-T19) -> 350 | V19: NOK | W19: =IFERROR(VLOOKUP(V19,Curr!$B$2:$C$13,2,FALSE),0) -> 1 | X19: =U19*W19 -> 350 | Y19: =Q19/11.3/0.5 -> 30.973451 | Z19: =+Y19*R19 -> 61.946903 | AA19: EUR | AB19: =IFERROR(VLOOKUP(AA19,Curr!$B$2:$C$13,2,FALSE),0) -> 11.2 | AC19: =+Y19*AB19*R19 -> 693.80531 | AD19: =+AC19-X19 -> 343.80531 | AE19: =IFERROR(AD19/AC19,0) -> 0.49553571
C20: Day 3 | D20: Leisure | J20: Bergen: Spend time at leisure | Q20: 0 | R20: 0 | S20: =+Q20*R20 -> 0 | T20: 0 | U20: =S20*(1-T20) -> 0 | V20: EUR | W20: =IFERROR(VLOOKUP(V20,Curr!$B$2:$C$13,2,FALSE),0) -> 11.2 | X20: =U20*W20 -> 0 | Y20: =Q20 -> 0 | Z20: =+Y20*R20 -> 0 | AA20: EUR | AB20: =IFERROR(VLOOKUP(AA20,Curr!$B$2:$C$13,2,FALSE),0) -> 11.2 | AC20: =+Y20*AB20*R20 -> 0 | AD20: =+AC20-X20 -> 0 | AE20: =IFERROR(AD20/AC20,0) -> 0
S21: =+Q21*R21 -> 0 | T21: 0 | U21: =S21*(1-T21) -> 0 | V21: EUR | W21: =IFERROR(VLOOKUP(V21,Curr!$B$2:$C$13,2,FALSE),0) -> 11.2 | X21: =U21*W21 -> 0 | Y21: =Q21 -> 0 | Z21: =+Y21*R21 -> 0 | AA21: EUR | AB21: =IFERROR(VLOOKUP(AA21,Curr!$B$2:$C$13,2,FALSE),0) -> 11.2 | AC21: =+Y21*AB21*R21 -> 0 | AD21: =+AC21-X21 -> 0 | AE21: =IFERROR(AD21/AC21,0) -> 0
C22: Day 4 | D22: Transfer | J22: Bergen: Self transfer to Bergen Airport | Q22: 0 | R22: 0 | S22: =+Q22*R22 -> 0 | T22: 0 | U22: =S22*(1-T22) -> 0 | V22: EUR | W22: =IFERROR(VLOOKUP(V22,Curr!$B$2:$C$13,2,FALSE),0) -> 11.2 | X22: =U22*W22 -> 0 | Y22: =Q22 -> 0 | Z22: =+Y22*R22 -> 0 | AA22: EUR | AB22: =IFERROR(VLOOKUP(AA22,Curr!$B$2:$C$13,2,FALSE),0) -> 11.2 | AC22: =+Y22*AB22*R22 -> 0 | AD22: =+AC22-X22 -> 0 | AE22: =IFERROR(AD22/AC22,0) -> 0
C23: Day 4 | D23: Flight | J23: Bergen: Flight to Tromsø - Time: Date dependant - Luggage included: 1 x 23 kg check in and 1 x 8 kg carry on per person | O23: x | Q23: 1800 | R23: 2 | S23: =+Q23*R23 -> 3600 | T23: 0 | U23: =S23*(1-T23) -> 3600 | V23: NOK | W23: =IFERROR(VLOOKUP(V23,Curr!$B$2:$C$13,2,FALSE),0) -> 1 | X23: =U23*W23 -> 3600 | Y23: =Q23/11.3/0.8 -> 199.11504 | Z23: =+Y23*R23 -> 398.23009 | AA23: EUR | AB23: =IFERROR(VLOOKUP(AA23,Curr!$B$2:$C$13,2,FALSE),0) -> 11.2 | AC23: =+Y23*AB23*R23 -> 4460.177 | AD23: =+AC23-X23 -> 860.17699 | AE23: =IFERROR(AD23/AC23,0) -> 0.19285714
C24: Day 4 | D24: Transfer | J24: Tromsø: Self transfer to your accommodation | Q24: 0 | R24: 0 | S24: =+Q24*R24 -> 0 | T24: 0 | U24: =S24*(1-T24) -> 0 | V24: NOK | W24: =IFERROR(VLOOKUP(V24,Curr!$B$2:$C$13,2,FALSE),0) -> 1 | X24: =U24*W24 -> 0 | Y24: =Q24/11.3/0.8 -> 0 | Z24: =+Y24*R24 -> 0 | AA24: EUR | AB24: =IFERROR(VLOOKUP(AA24,Curr!$B$2:$C$13,2,FALSE),0) -> 11.2 | AC24: =+Y24*AB24*R24 -> 0 | AD24: =+AC24-X24 -> 0 | AE24: =IFERROR(AD24/AC24,0) -> 0
C25: Day 4 | D25: Hotel | J25: Tromsø: Check in to your accommodation for a 2 night stay - Centrally located 3/4-star hotel - Standard Room - Breakfast included | Q25: 500 | R25: 1 | S25: =+Q25*R25 -> 500 | T25: 0 | U25: =S25*(1-T25) -> 500 | V25: EUR | W25: =IFERROR(VLOOKUP(V25,Curr!$B$2:$C$13,2,FALSE),0) -> 11.2 | X25: =U25*W25 -> 5600 | Y25: =Q25/0.85 -> 588.23529 | Z25: =+Y25*R25 -> 588.23529 | AA25: EUR | AB25: =IFERROR(VLOOKUP(AA25,Curr!$B$2:$C$13,2,FALSE),0) -> 11.2 | AC25: =+Y25*AB25*R25 -> 6588.2353 | AD25: =+AC25-X25 -> 988.23529 | AE25: =IFERROR(AD25/AC25,0) -> 0.15
C26: Day 4 | D26: Leisure | J26: Tromsø: Spend time at leisure | Q26: 0 | R26: 0 | S26: =+Q26*R26 -> 0 | T26: 0 | U26: =S26*(1-T26) -> 0 | V26: EUR | W26: =IFERROR(VLOOKUP(V26,Curr!$B$2:$C$13,2,FALSE),0) -> 11.2 | X26: =U26*W26 -> 0 | Y26: =Q26 -> 0 | Z26: =+Y26*R26 -> 0 | AA26: EUR | AB26: =IFERROR(VLOOKUP(AA26,Curr!$B$2:$C$13,2,FALSE),0) -> 11.2 | AC26: =+Y26*AB26*R26 -> 0 | AD26: =+AC26-X26 -> 0 | AE26: =IFERROR(AD26/AC26,0) -> 0
C27: Day 4 | D27: Activity | J27: Tromsø: Northern Lights Cruise with Silent Electric Ship - Time: 7:00 pm - 10:00 pm - Meeting point: Kaigata 6 - Includes: Departure from central Tromsø, 3-hour fjord cruise, Light meal (soup and bread) and water, English speaking guides, Warm indoor saloons, Free wifi, Toilets | O27: x | P27: https://booknordics.com/norway/northern-norway/tromso-region/northern-lights-cruise-electric-ship | Q27: 105 | R27: 2 | S27: =+Q27*R27 -> 210 | T27: 0.2 | U27: =S27*(1-T27) -> 168 | V27: EUR | W27: =IFERROR(VLOOKUP(V27,Curr!$B$2:$C$13,2,FALSE),0) -> 11.2 | X27: =U27*W27 -> 1881.6 | Y27: =Q27 -> 105 | Z27: =+Y27*R27 -> 210 | AA27: EUR | AB27: =IFERROR(VLOOKUP(AA27,Curr!$B$2:$C$13,2,FALSE),0) -> 11.2 | AC27: =+Y27*AB27*R27 -> 2352 | AD27: =+AC27-X27 -> 470.4 | AE27: =IFERROR(AD27/AC27,0) -> 0.2
S28: =+Q28*R28 -> 0 | T28: 0 | U28: =S28*(1-T28) -> 0 | V28: EUR | W28: =IFERROR(VLOOKUP(V28,Curr!$B$2:$C$13,2,FALSE),0) -> 11.2 | X28: =U28*W28 -> 0 | Y28: =Q28 -> 0 | Z28: =+Y28*R28 -> 0 | AA28: EUR | AB28: =IFERROR(VLOOKUP(AA28,Curr!$B$2:$C$13,2,FALSE),0) -> 11.2 | AC28: =+Y28*AB28*R28 -> 0 | AD28: =+AC28-X28 -> 0 | AE28: =IFERROR(AD28/AC28,0) -> 0
C29: Day 5 | D29: Activity | J29: Tromsø: Reindeer Feeding and Sámi Culture - Time: 09:45 am - 2:30 pm - Meeting point: Radisson Blu Hotel's main entrance (Sjøgata 7) - Includes: Scenic transfers (45 min each way), Knowledgeable English and Norwegian speaking guide, Feeding the herd at our camp, Hot beverages and hot meal (traditional Sámi stew or vegetable/lentil soup), Cultural introduction about Sámi history and daily life, A chance to see the northern lights from our camp, Thermal suit and warm snow boots | O29: x | P29: https://www.tromsolapland.no/activities/reindeer-feeding-and-sami-culture | Q29: 1695 | R29: 2 | S29: =+Q29*R29 -> 3390 | T29: 0.2 | U29: =S29*(1-T29) -> 2712 | V29: NOK | W29: =IFERROR(VLOOKUP(V29,Curr!$B$2:$C$13,2,FALSE),0) -> 1 | X29: =U29*W29 -> 2712 | Y29: =Q29/11.3 -> 150 | Z29: =+Y29*R29 -> 300 | AA29: EUR | AB29: =IFERROR(VLOOKUP(AA29,Curr!$B$2:$C$13,2,FALSE),0) -> 11.2 | AC29: =+Y29*AB29*R29 -> 3360 | AD29: =+AC29-X29 -> 648 | AE29: =IFERROR(AD29/AC29,0) -> 0.19285714
C30: Day 5 | D30: Leisure | J30: Tromsø: Spend time at leisure | Q30: 0 | R30: 0 | S30: =+Q30*R30 -> 0 | T30: 0 | U30: =S30*(1-T30) -> 0 | V30: EUR | W30: =IFERROR(VLOOKUP(V30,Curr!$B$2:$C$13,2,FALSE),0) -> 11.2 | X30: =U30*W30 -> 0 | Y30: =Q30 -> 0 | Z30: =+Y30*R30 -> 0 | AA30: EUR | AB30: =IFERROR(VLOOKUP(AA30,Curr!$B$2:$C$13,2,FALSE),0) -> 11.2 | AC30: =+Y30*AB30*R30 -> 0 | AD30: =+AC30-X30 -> 0 | AE30: =IFERROR(AD30/AC30,0) -> 0
C31: Day 5 | D31: Activity | J31: Tromsø: All-Evening Northern Lights Hunt by Minibus or Bus - Time: 7:00 pm - 12:00 am - Meeting point: Kaigata 4 - Includes: Knowledgeable, English-speaking guides, Photos shared with you after the tour, Thermo clothing and warm gear, Light snacks and warm/cold beverages, Drop-off at hotel, up to 5 km from Tromsø | O31: x | P31: https://booknordics.com/norway/northern-norway/tromso-region/full-day-magic-of-the-arctic-lights-in-tromso | Q31: 120 | R31: 2 | S31: =+Q31*R31 -> 240 | T31: 0.2 | U31: =S31*(1-T31) -> 192 | V31: EUR | W31: =IFERROR(VLOOKUP(V31,Curr!$B$2:$C$13,2,FALSE),0) -> 11.2 | X31: =U31*W31 -> 2150.4 | Y31: =Q31 -> 120 | Z31: =+Y31*R31 -> 240 | AA31: EUR | AB31: =IFERROR(VLOOKUP(AA31,Curr!$B$2:$C$13,2,FALSE),0) -> 11.2 | AC31: =+Y31*AB31*R31 -> 2688 | AD31: =+AC31-X31 -> 537.6 | AE31: =IFERROR(AD31/AC31,0) -> 0.2
S32: =+Q32*R32 -> 0 | T32: 0 | U32: =S32*(1-T32) -> 0 | V32: EUR | W32: =IFERROR(VLOOKUP(V32,Curr!$B$2:$C$13,2,FALSE),0) -> 11.2 | X32: =U32*W32 -> 0 | Y32: =Q32 -> 0 | Z32: =+Y32*R32 -> 0 | AA32: EUR | AB32: =IFERROR(VLOOKUP(AA32,Curr!$B$2:$C$13,2,FALSE),0) -> 11.2 | AC32: =+Y32*AB32*R32 -> 0 | AD32: =+AC32-X32 -> 0 | AE32: =IFERROR(AD32/AC32,0) -> 0
C33: Day 6 | D33: Transfer | J33: Tromsø: Self transfer to Tromsø Airport | Q33: 0 | R33: 0 | S33: =+Q33*R33 -> 0 | T33: 0 | U33: =S33*(1-T33) -> 0 | V33: NOK | W33: =IFERROR(VLOOKUP(V33,Curr!$B$2:$C$13,2,FALSE),0) -> 1 | X33: =U33*W33 -> 0 | Y33: =Q33/11.3/0.8 -> 0 | Z33: =+Y33*R33 -> 0 | AA33: EUR | AB33: =IFERROR(VLOOKUP(AA33,Curr!$B$2:$C$13,2,FALSE),0) -> 11.2 | AC33: =+Y33*AB33*R33 -> 0 | AD33: =+AC33-X33 -> 0 | AE33: =IFERROR(AD33/AC33,0) -> 0
C34: Day 6 | D34: Departure | J34: Tromsø: Departure home | Q34: 0 | R34: 0 | S34: =+Q34*R34 -> 0 | T34: 0 | U34: =S34*(1-T34) -> 0 | V34: EUR | W34: =IFERROR(VLOOKUP(V34,Curr!$B$2:$C$13,2,FALSE),0) -> 11.2 | X34: =U34*W34 -> 0 | Y34: =Q34 -> 0 | Z34: =+Y34*R34 -> 0 | AA34: EUR | AB34: =IFERROR(VLOOKUP(AA34,Curr!$B$2:$C$13,2,FALSE),0) -> 11.2 | AC34: =+Y34*AB34*R34 -> 0 | AD34: =+AC34-X34 -> 0 | AE34: =IFERROR(AD34/AC34,0) -> 0
S35: =+Q35*R35 -> 0 | T35: 0 | U35: =S35*(1-T35) -> 0 | V35: EUR | W35: =IFERROR(VLOOKUP(V35,Curr!$B$2:$C$13,2,FALSE),0) -> 11.2 | X35: =U35*W35 -> 0 | Y35: =Q35 -> 0 | Z35: =+Y35*R35 -> 0 | AA35: EUR | AB35: =IFERROR(VLOOKUP(AA35,Curr!$B$2:$C$13,2,FALSE),0) -> 11.2 | AC35: =+Y35*AB35*R35 -> 0 | AD35: =+AC35-X35 -> 0 | AE35: =IFERROR(AD35/AC35,0) -> 0
S36: =+Q36*R36 -> 0 | T36: 0 | U36: =S36*(1-T36) -> 0 | V36: EUR | W36: =IFERROR(VLOOKUP(V36,Curr!$B$2:$C$13,2,FALSE),0) -> 11.2 | X36: =U36*W36 -> 0 | Y36: =Q36 -> 0 | Z36: =+Y36*R36 -> 0 | AA36: EUR | AB36: =IFERROR(VLOOKUP(AA36,Curr!$B$2:$C$13,2,FALSE),0) -> 11.2 | AC36: =+Y36*AB36*R36 -> 0 | AD36: =+AC36-X36 -> 0 | AE36: =IFERROR(AD36/AC36,0) -> 0
C37: Day 1 | D37: Transfer Package | J37: Oslo: Private transfer to your accommodation | Q37: 1750 | R37: 0 | S37: =+Q37*R37 -> 0 | T37: 0 | U37: =S37*(1-T37) -> 0 | V37: NOK | W37: =IFERROR(VLOOKUP(V37,Curr!$B$2:$C$13,2,FALSE),0) -> 1 | X37: =U37*W37 -> 0 | Y37: =Q37/11.3/0.8 -> 193.58407 | Z37: =+Y37*R37 -> 0 | AA37: EUR | AB37: =IFERROR(VLOOKUP(AA37,Curr!$B$2:$C$13,2,FALSE),0) -> 11.2 | AC37: =+Y37*AB37*R37 -> 0 | AD37: =+AC37-X37 -> 0 | AE37: =IFERROR(AD37/AC37,0) -> 0
C38: Day 2 | D38: Transfer Package | J38: Bergen: Private transfer to your accommodation | Q38: 1290 | R38: 0 | S38: =+Q38*R38 -> 0 | T38: 0.15 | U38: =S38*(1-T38) -> 0 | V38: NOK | W38: =IFERROR(VLOOKUP(V38,Curr!$B$2:$C$13,2,FALSE),0) -> 1 | X38: =U38*W38 -> 0 | Y38: =Q38/11.3/0.98 -> 116.48907 | Z38: =+Y38*R38 -> 0 | AA38: EUR | AB38: =IFERROR(VLOOKUP(AA38,Curr!$B$2:$C$13,2,FALSE),0) -> 11.2 | AC38: =+Y38*AB38*R38 -> 0 | AD38: =+AC38-X38 -> 0 | AE38: =IFERROR(AD38/AC38,0) -> 0
C39: Day 4 | D39: Transfer Package | J39: Bergen: Private transfer to Bergen Airport | Q39: 1690 | R39: 0 | S39: =+Q39*R39 -> 0 | T39: 0.15 | U39: =S39*(1-T39) -> 0 | V39: NOK | W39: =IFERROR(VLOOKUP(V39,Curr!$B$2:$C$13,2,FALSE),0) -> 1 | X39: =U39*W39 -> 0 | Y39: =Q39/11.3/0.98 -> 152.60972 | Z39: =+Y39*R39 -> 0 | AA39: EUR | AB39: =IFERROR(VLOOKUP(AA39,Curr!$B$2:$C$13,2,FALSE),0) -> 11.2 | AC39: =+Y39*AB39*R39 -> 0 | AD39: =+AC39-X39 -> 0 | AE39: =IFERROR(AD39/AC39,0) -> 0
C40: Day 4 | D40: Transfer Package | J40: Tromsø: Private transfer to your accommodation | Q40: 900 | R40: 0 | S40: =+Q40*R40 -> 0 | T40: 0 | U40: =S40*(1-T40) -> 0 | V40: NOK | W40: =IFERROR(VLOOKUP(V40,Curr!$B$2:$C$13,2,FALSE),0) -> 1 | X40: =U40*W40 -> 0 | Y40: =Q40/11.3/0.8 -> 99.557522 | Z40: =+Y40*R40 -> 0 | AA40: EUR | AB40: =IFERROR(VLOOKUP(AA40,Curr!$B$2:$C$13,2,FALSE),0) -> 11.2 | AC40: =+Y40*AB40*R40 -> 0 | AD40: =+AC40-X40 -> 0 | AE40: =IFERROR(AD40/AC40,0) -> 0
C41: Day 6 | D41: Transfer Package | J41: Tromsø: Private transfer to Tromsø Airport | Q41: 900 | R41: 0 | S41: =+Q41*R41 -> 0 | T41: 0 | U41: =S41*(1-T41) -> 0 | V41: NOK | W41: =IFERROR(VLOOKUP(V41,Curr!$B$2:$C$13,2,FALSE),0) -> 1 | X41: =U41*W41 -> 0 | Y41: =Q41/11.3/0.8 -> 99.557522 | Z41: =+Y41*R41 -> 0 | AA41: EUR | AB41: =IFERROR(VLOOKUP(AA41,Curr!$B$2:$C$13,2,FALSE),0) -> 11.2 | AC41: =+Y41*AB41*R41 -> 0 | AD41: =+AC41-X41 -> 0 | AE41: =IFERROR(AD41/AC41,0) -> 0
S42: =+Q42*R42 -> 0 | T42: 0 | U42: =S42*(1-T42) -> 0 | V42: EUR | W42: =IFERROR(VLOOKUP(V42,Curr!$B$2:$C$13,2,FALSE),0) -> 11.2 | X42: =U42*W42 -> 0 | Y42: =Q42 -> 0 | Z42: =+Y42*R42 -> 0 | AA42: EUR | AB42: =IFERROR(VLOOKUP(AA42,Curr!$B$2:$C$13,2,FALSE),0) -> 11.2 | AC42: =+Y42*AB42*R42 -> 0 | AD42: =+AC42-X42 -> 0 | AE42: =IFERROR(AD42/AC42,0) -> 0
S43: =+Q43*R43 -> 0 | T43: 0 | U43: =S43*(1-T43) -> 0 | V43: EUR | W43: =IFERROR(VLOOKUP(V43,Curr!$B$2:$C$13,2,FALSE),0) -> 11.2 | X43: =U43*W43 -> 0 | Y43: =Q43 -> 0 | Z43: =+Y43*R43 -> 0 | AA43: EUR | AB43: =IFERROR(VLOOKUP(AA43,Curr!$B$2:$C$13,2,FALSE),0) -> 11.2 | AC43: =+Y43*AB43*R43 -> 0 | AD43: =+AC43-X43 -> 0 | AE43: =IFERROR(AD43/AC43,0) -> 0
Q44: 0 | R44: 0 | S44: =+Q44*R44 -> 0 | T44: 0 | U44: =S44*(1-T44) -> 0 | V44: EUR | W44: =IFERROR(VLOOKUP(V44,Curr!$B$2:$C$13,2,FALSE),0) -> 11.2 | X44: =U44*W44 -> 0 | Y44: =Q44 -> 0 | Z44: =+Y44*R44 -> 0 | AA44: EUR | AB44: =IFERROR(VLOOKUP(AA44,Curr!$B$2:$C$13,2,FALSE),0) -> 11.2 | AC44: =+Y44*AB44*R44 -> 0 | AD44: =+AC44-X44 -> 0 | AE44: =IFERROR(AD44/AC44,0) -> 0
C45: Day 2 | D45: Activity Upgrade | J45: Oslo: Norway in a Nutshell to Bergen - Time: 08:00 am - 09:00 pm - Meeting point. Oslo Central Station - Includes: Train transfer Oslo to Myrdal, Train tranfser Myrdal to Flåm, Fjord Cruise Flåm to Gudvangen, Coach Transfer Gudvangen to Voss, Train transfer Voss to Bergen | O45: x | P45: https://www.fjordtours.com/en | Q45: 3250 | R45: 0 | S45: =+Q45*R45 -> 0 | T45: 0.08 | U45: =S45*(1-T45) -> 0 | V45: NOK | W45: =IFERROR(VLOOKUP(V45,Curr!$B$2:$C$13,2,FALSE),0) -> 1 | X45: =U45*W45 -> 0 | Y45: =Q45/11.3/0.9 -> 319.56735 | Z45: =+Y45*R45 -> 0 | AA45: EUR | AB45: =IFERROR(VLOOKUP(AA45,Curr!$B$2:$C$13,2,FALSE),0) -> 11.2 | AC45: =+Y45*AB45*R45 -> 0 | AD45: =+AC45-X45 -> 0 | AE45: =IFERROR(AD45/AC45,0) -> 0
C46: Day 2 | D46: Activity Upgrade | J46: Oslo: Norway in a Nutshell Porter Service - Includes: Luggage transfer from your accommodation in Oslo to your accommodaiton in Bergen | Q46: 450 | R46: 0 | S46: =+Q46*R46 -> 0 | T46: 0 | U46: =S46*(1-T46) -> 0 | V46: NOK | W46: =IFERROR(VLOOKUP(V46,Curr!$B$2:$C$13,2,FALSE),0) -> 1 | X46: =U46*W46 -> 0 | Y46: =Q46/11.3/0.8 -> 49.778761 | Z46: =+Y46*R46 -> 0 | AA46: EUR | AB46: =IFERROR(VLOOKUP(AA46,Curr!$B$2:$C$13,2,FALSE),0) -> 11.2 | AC46: =+Y46*AB46*R46 -> 0 | AD46: =+AC46-X46 -> 0 | AE46: =IFERROR(AD46/AC46,0) -> 0
C47: Day 3 | D47: Activity Upgrade | J47: Bergen: Mostraumen Majestic Fjord & Waterfall Cruise - Time: 12:00 pm - 4:00 pm - Meeting point: Strandkaien 13 - Includes: 4-hour panoramic fjord cruise, Expert captain navigating through the fjords, English-audio guide | O47: x | P47: https://booknordics.com/norway/western-fjord-norway/bergen-and-hardanger/mostraumen-fjord-waterfall-cruise | Q47: 71 | R47: 0 | S47: =+Q47*R47 -> 0 | T47: 0.2 | U47: =S47*(1-T47) -> 0 | V47: EUR | W47: =IFERROR(VLOOKUP(V47,Curr!$B$2:$C$13,2,FALSE),0) -> 11.2 | X47: =U47*W47 -> 0 | Y47: =Q47 -> 71 | Z47: =+Y47*R47 -> 0 | AA47: EUR | AB47: =IFERROR(VLOOKUP(AA47,Curr!$B$2:$C$13,2,FALSE),0) -> 11.2 | AC47: =+Y47*AB47*R47 -> 0 | AD47: =+AC47-X47 -> 0 | AE47: =IFERROR(AD47/AC47,0) -> 0
C48: Day 5 | D48: Activity Upgrade | J48: Tromsø: Reindeer Sledding, Reindeer Feeding and Sami Culture - Time: 09:45 am - 2:30 pm - Meeting point: Radisson Blu Hotel's main entrance (Sjøgata 7) - Includes: Scenic transfers (45 min each way), Knowledgeable English- and Norwegian-speaking guide, Thermal winter suit, warm boots, Reindeer sledding (approx. 30 min, depending on weather and snow conditions), Feeding the herd on our camp, Hot traditional Sámi meal (bithos) and hot drinks. Vegetarian option available on request, Cultural introduction about Sámi history and daily life | O48: x | P48: https://booknordics.com/norway/northern-norway/tromso-region/reindeer-sledding-reindeer-feeding-and-sami-culture-3 | Q48: 2195 | R48: 0 | S48: =+Q48*R48 -> 0 | T48: 0.2 | U48: =S48*(1-T48) -> 0 | V48: NOK | W48: =IFERROR(VLOOKUP(V48,Curr!$B$2:$C$13,2,FALSE),0) -> 1 | X48: =U48*W48 -> 0 | Y48: =Q48/11.3 -> 194.24779 | Z48: =+Y48*R48 -> 0 | AA48: EUR | AB48: =IFERROR(VLOOKUP(AA48,Curr!$B$2:$C$13,2,FALSE),0) -> 11.2 | AC48: =+Y48*AB48*R48 -> 0 | AD48: =+AC48-X48 -> 0 | AE48: =IFERROR(AD48/AC48,0) -> 0
S49: =+Q49*R49 -> 0 | T49: 0 | U49: =S49*(1-T49) -> 0 | V49: EUR | W49: =IFERROR(VLOOKUP(V49,Curr!$B$2:$C$13,2,FALSE),0) -> 11.2 | X49: =U49*W49 -> 0 | Y49: =Q49 -> 0 | Z49: =+Y49*R49 -> 0 | AA49: EUR | AB49: =IFERROR(VLOOKUP(AA49,Curr!$B$2:$C$13,2,FALSE),0) -> 11.2 | AC49: =+Y49*AB49*R49 -> 0 | AD49: =+AC49-X49 -> 0 | AE49: =IFERROR(AD49/AC49,0) -> 0
S50: =+Q50*R50 -> 0 | T50: 0 | U50: =S50*(1-T50) -> 0 | V50: EUR | W50: =IFERROR(VLOOKUP(V50,Curr!$B$2:$C$13,2,FALSE),0) -> 11.2 | X50: =U50*W50 -> 0 | Y50: =Q50 -> 0 | Z50: =+Y50*R50 -> 0 | AA50: EUR | AB50: =IFERROR(VLOOKUP(AA50,Curr!$B$2:$C$13,2,FALSE),0) -> 11.2 | AC50: =+Y50*AB50*R50 -> 0 | AD50: =+AC50-X50 -> 0 | AE50: =IFERROR(AD50/AC50,0) -> 0
S51: =+Q51*R51 -> 0 | T51: 0 | U51: =S51*(1-T51) -> 0 | V51: EUR | W51: =IFERROR(VLOOKUP(V51,Curr!$B$2:$C$13,2,FALSE),0) -> 11.2 | X51: =U51*W51 -> 0 | Y51: =Q51 -> 0 | Z51: =+Y51*R51 -> 0 | AA51: EUR | AB51: =IFERROR(VLOOKUP(AA51,Curr!$B$2:$C$13,2,FALSE),0) -> 11.2 | AC51: =+Y51*AB51*R51 -> 0 | AD51: =+AC51-X51 -> 0 | AE51: =IFERROR(AD51/AC51,0) -> 0
S52: =+Q52*R52 -> 0 | T52: 0 | U52: =S52*(1-T52) -> 0 | V52: EUR | W52: =IFERROR(VLOOKUP(V52,Curr!$B$2:$C$13,2,FALSE),0) -> 11.2 | X52: =U52*W52 -> 0 | Y52: =Q52 -> 0 | Z52: =+Y52*R52 -> 0 | AA52: EUR | AB52: =IFERROR(VLOOKUP(AA52,Curr!$B$2:$C$13,2,FALSE),0) -> 11.2 | AC52: =+Y52*AB52*R52 -> 0 | AD52: =+AC52-X52 -> 0 | AE52: =IFERROR(AD52/AC52,0) -> 0
S53: =+Q53*R53 -> 0 | T53: 0 | U53: =S53*(1-T53) -> 0 | V53: EUR | W53: =IFERROR(VLOOKUP(V53,Curr!$B$2:$C$13,2,FALSE),0) -> 11.2 | X53: =U53*W53 -> 0 | Y53: =Q53 -> 0 | Z53: =+Y53*R53 -> 0 | AA53: EUR | AB53: =IFERROR(VLOOKUP(AA53,Curr!$B$2:$C$13,2,FALSE),0) -> 11.2 | AC53: =+Y53*AB53*R53 -> 0 | AD53: =+AC53-X53 -> 0 | AE53: =IFERROR(AD53/AC53,0) -> 0
B55: Totals | D55: x | E55: x | F55: x | G55: x | H55: x | I55: x | J55: x | K55: x | L55: x | M55: x | N55: x | O55: x | P55: x | Q55: x | R55: x | S55: x | T55: x | U55: x | V55: x | W55: x | X55: x | Y55: x | Z55: =SUM(Z7:Z53) -> 2649.9805 | AC55: =SUM(AC7:AC53) -> 29679.781 | AD55: =SUM(AD7:AD53) -> 5705.7814 | AE55: =IFERROR(AD55/AC55,0) -> 0.19224472 | AF55: =SUM(AF8:AF54) -> 0 | AG55: =SUM(AG8:AG54) -> 0 | AH55: =SUM(AH8:AH54) -> 0 | AI55: =SUM(AI8:AI54) -> 0 | AJ55: =SUM(AJ8:AJ54) -> 0
Y57: Fixed | Z57: 1290
Y58: Variable | Z58: =Z9+Z15+Z23+Z25 -> 1492.3477
Y59: Total | Z59: 2660
Y60: PP | Z60: =Z59/2 -> 1330
Z67: Winter
Y68: Shoulder | Z68: =Z59 -> 2660
Y69: High | Z69: =Z68*1.18 -> 3138.8
Y70: Holiday | Z70: =Z68*1.25 -> 3325
Y71: Low | Z71: =Z68*0.85 -> 2261
Y72: Summer | Z72: NA

Sheet 202
B1: Season: Winter
B2: Places: Oslo 1N - Flåm 1N - Bergen 2N - Tromsø 3N
B3: Pax: 2
B4: Rooming: Double
B6: ID | C6: Day | D6: Type | E6: From date | F6: To date | G6: From time | H6: To time | I6: Supplier | J6: Travel element | K6: Manual booking? | L6: Status | M6: Comments | N6: Non-refundable | O6: Refundable | P6: URL | Q6: Gross P per unit | R6: Units | S6: Gross P | T6: Supp Comm | U6: Net P | V6: Supp curr | W6: X-rate | X6: Net P NOK | Y6: Sales P per unit | Z6: Price | AA6: Sales curr | AB6: X-rate | AC6: Sales P NOK tot | AD6: GP NOK | AE6: GP % | AF6: VAT25 | AG6: VAT15 | AH6: VAT12 | AI6: VAT0-D | AJ6: VAT0-I
C7: Day 1 | D7: Arrival | J7: Oslo: Welcome to Norway | Q7: 0 | R7: 0 | S7: =+Q7*R7 -> 0 | T7: 0 | U7: =S7*(1-T7) -> 0 | V7: EUR | W7: =IFERROR(VLOOKUP(V7,Curr!$B$2:$C$13,2,FALSE),0) -> 11.2 | X7: =U7*W7 -> 0 | Y7: =Q7 -> 0 | Z7: =+Y7*R7 -> 0 | AA7: EUR | AB7: =IFERROR(VLOOKUP(AA7,Curr!$B$2:$C$13,2,FALSE),0) -> 11.2 | AC7: =+Y7*AB7*R7 -> 0 | AD7: =+AC7-X7 -> 0 | AE7: =IFERROR(AD7/AC7,0) -> 0
C8: Day 1 | D8: Transfer | J8: Oslo: Self transfer to your accommodation | Q8: 0 | R8: 0 | S8: =+Q8*R8 -> 0 | T8: 0 | U8: =S8*(1-T8) -> 0 | V8: NOK | W8: =IFERROR(VLOOKUP(V8,Curr!$B$2:$C$13,2,FALSE),0) -> 1 | X8: =U8*W8 -> 0 | Y8: =Q8/11.3/0.8 -> 0 | Z8: =+Y8*R8 -> 0 | AA8: EUR | AB8: =IFERROR(VLOOKUP(AA8,Curr!$B$2:$C$13,2,FALSE),0) -> 11.2 | AC8: =+Y8*AB8*R8 -> 0 | AD8: =+AC8-X8 -> 0 | AE8: =IFERROR(AD8/AC8,0) -> 0
C9: Day 1 | D9: Hotel | J9: Oslo: Check in to your accommodation for a 1 night stay - Centrally located 3/4-star hotel - Standard Room - Breakfast included | Q9: 150 | R9: 1 | S9: =+Q9*R9 -> 150 | T9: 0 | U9: =S9*(1-T9) -> 150 | V9: EUR | W9: =IFERROR(VLOOKUP(V9,Curr!$B$2:$C$13,2,FALSE),0) -> 11.2 | X9: =U9*W9 -> 1680 | Y9: =Q9/0.85 -> 176.47059 | Z9: =+Y9*R9 -> 176.47059 | AA9: EUR | AB9: =IFERROR(VLOOKUP(AA9,Curr!$B$2:$C$13,2,FALSE),0) -> 11.2 | AC9: =+Y9*AB9*R9 -> 1976.4706 | AD9: =+AC9-X9 -> 296.47059 | AE9: =IFERROR(AD9/AC9,0) -> 0.15
C10: Day 1 | D10: Leisure | J10: Oslo: Spend time at leisure | Q10: 0 | R10: 0 | S10: =+Q10*R10 -> 0 | T10: 0 | U10: =S10*(1-T10) -> 0 | V10: EUR | W10: =IFERROR(VLOOKUP(V10,Curr!$B$2:$C$13,2,FALSE),0) -> 11.2 | X10: =U10*W10 -> 0 | Y10: =Q10 -> 0 | Z10: =+Y10*R10 -> 0 | AA10: EUR | AB10: =IFERROR(VLOOKUP(AA10,Curr!$B$2:$C$13,2,FALSE),0) -> 11.2 | AC10: =+Y10*AB10*R10 -> 0 | AD10: =+AC10-X10 -> 0 | AE10: =IFERROR(AD10/AC10,0) -> 0
S11: =+Q11*R11 -> 0 | T11: 0 | U11: =S11*(1-T11) -> 0 | V11: EUR | W11: =IFERROR(VLOOKUP(V11,Curr!$B$2:$C$13,2,FALSE),0) -> 11.2 | X11: =U11*W11 -> 0 | Y11: =Q11 -> 0 | Z11: =+Y11*R11 -> 0 | AA11: EUR | AB11: =IFERROR(VLOOKUP(AA11,Curr!$B$2:$C$13,2,FALSE),0) -> 11.2 | AC11: =+Y11*AB11*R11 -> 0 | AD11: =+AC11-X11 -> 0 | AE11: =IFERROR(AD11/AC11,0) -> 0
C12: Day 2 | D12: Transfer | J12: Oslo: Self transfer to Oslo Central Station | Q12: 0 | R12: 0 | S12: =+Q12*R12 -> 0 | T12: 0 | U12: =S12*(1-T12) -> 0 | V12: EUR | W12: =IFERROR(VLOOKUP(V12,Curr!$B$2:$C$13,2,FALSE),0) -> 11.2 | X12: =U12*W12 -> 0 | Y12: =Q12 -> 0 | Z12: =+Y12*R12 -> 0 | AA12: EUR | AB12: =IFERROR(VLOOKUP(AA12,Curr!$B$2:$C$13,2,FALSE),0) -> 11.2 | AC12: =+Y12*AB12*R12 -> 0 | AD12: =+AC12-X12 -> 0 | AE12: =IFERROR(AD12/AC12,0) -> 0
C13: Day 2 | D13: Activity | J13: Oslo: Norway in a Nutshell to Flåm - Time: 08:00 am - 2:00 pm - Meeting point: Oslo Central Station - Includes: Train transfer Oslo to Myrdal, Train tranfser Myrdal to Flåm | O13: x | P13: https://www.fjordtours.com/en | Q13: 3280 | R13: 2 | S13: =+Q13*R13 -> 6560 | T13: 0.08 | U13: =S13*(1-T13) -> 6035.2 | V13: NOK | W13: =IFERROR(VLOOKUP(V13,Curr!$B$2:$C$13,2,FALSE),0) -> 1 | X13: =U13*W13 -> 6035.2 | Y13: =Q13/11.3/0.9 -> 322.51721 | Z13: =+Y13*R13 -> 645.03441 | AA13: EUR | AB13: =IFERROR(VLOOKUP(AA13,Curr!$B$2:$C$13,2,FALSE),0) -> 11.2 | AC13: =+Y13*AB13*R13 -> 7224.3854 | AD13: =+AC13-X13 -> 1189.1854 | AE13: =IFERROR(AD13/AC13,0) -> 0.16460714
C14: Day 2 | D14: Transfer | J14: Flåm: Self transfer to your accommodation | Q14: 0 | R14: 0 | S14: =+Q14*R14 -> 0 | T14: 0 | U14: =S14*(1-T14) -> 0 | V14: EUR | W14: =IFERROR(VLOOKUP(V14,Curr!$B$2:$C$13,2,FALSE),0) -> 11.2 | X14: =U14*W14 -> 0 | Y14: =Q14 -> 0 | Z14: =+Y14*R14 -> 0 | AA14: EUR | AB14: =IFERROR(VLOOKUP(AA14,Curr!$B$2:$C$13,2,FALSE),0) -> 11.2 | AC14: =+Y14*AB14*R14 -> 0 | AD14: =+AC14-X14 -> 0 | AE14: =IFERROR(AD14/AC14,0) -> 0
C15: Day 2 | D15: Hotel | J15: Flåm: Check in to your accommodation for a 1 night stay - Centrally located 3/4-star hotel - Standard Room - Breakfast included | Q15: 225 | R15: 1 | S15: =+Q15*R15 -> 225 | T15: 0 | U15: =S15*(1-T15) -> 225 | V15: EUR | W15: =IFERROR(VLOOKUP(V15,Curr!$B$2:$C$13,2,FALSE),0) -> 11.2 | X15: =U15*W15 -> 2520 | Y15: =Q15/0.85 -> 264.70588 | Z15: =+Y15*R15 -> 264.70588 | AA15: EUR | AB15: =IFERROR(VLOOKUP(AA15,Curr!$B$2:$C$13,2,FALSE),0) -> 11.2 | AC15: =+Y15*AB15*R15 -> 2964.7059 | AD15: =+AC15-X15 -> 444.70588 | AE15: =IFERROR(AD15/AC15,0) -> 0.15
C16: Day 2 | D16: Leisure | J16: Flåm: Spend time at leisure | Q16: 0 | R16: 0 | S16: =+Q16*R16 -> 0 | T16: 0 | U16: =S16*(1-T16) -> 0 | V16: EUR | W16: =IFERROR(VLOOKUP(V16,Curr!$B$2:$C$13,2,FALSE),0) -> 11.2 | X16: =U16*W16 -> 0 | Y16: =Q16 -> 0 | Z16: =+Y16*R16 -> 0 | AA16: EUR | AB16: =IFERROR(VLOOKUP(AA16,Curr!$B$2:$C$13,2,FALSE),0) -> 11.2 | AC16: =+Y16*AB16*R16 -> 0 | AD16: =+AC16-X16 -> 0 | AE16: =IFERROR(AD16/AC16,0) -> 0
S17: =+Q17*R17 -> 0 | T17: 0 | U17: =S17*(1-T17) -> 0 | V17: EUR | W17: =IFERROR(VLOOKUP(V17,Curr!$B$2:$C$13,2,FALSE),0) -> 11.2 | X17: =U17*W17 -> 0 | Y17: =Q17 -> 0 | Z17: =+Y17*R17 -> 0 | AA17: EUR | AB17: =IFERROR(VLOOKUP(AA17,Curr!$B$2:$C$13,2,FALSE),0) -> 11.2 | AC17: =+Y17*AB17*R17 -> 0 | AD17: =+AC17-X17 -> 0 | AE17: =IFERROR(AD17/AC17,0) -> 0
C18: Day 3 | D18: Transfer | J18: Flåm: Self transfer to Flåm Harbor | Q18: 0 | R18: 0 | S18: =+Q18*R18 -> 0 | T18: 0 | U18: =S18*(1-T18) -> 0 | V18: EUR | W18: =IFERROR(VLOOKUP(V18,Curr!$B$2:$C$13,2,FALSE),0) -> 11.2 | X18: =U18*W18 -> 0 | Y18: =Q18 -> 0 | Z18: =+Y18*R18 -> 0 | AA18: EUR | AB18: =IFERROR(VLOOKUP(AA18,Curr!$B$2:$C$13,2,FALSE),0) -> 11.2 | AC18: =+Y18*AB18*R18 -> 0 | AD18: =+AC18-X18 -> 0 | AE18: =IFERROR(AD18/AC18,0) -> 0
C19: Day 3 | D19: Activity | J19: Flåm: Norway in a Nutshell to Bergen - Time: - Meeting point: Flåm Harbor - Includes: Fjord Cruise Flåm to Gudvangen, Coach Transfer Gudvangen to Voss, Train transfer Voss to Bergen | O19: x | P19: https://www.fjordtours.com/en | Q19: 0 | R19: 0 | S19: =+Q19*R19 -> 0 | T19: 0.08 | U19: =S19*(1-T19) -> 0 | V19: NOK | W19: =IFERROR(VLOOKUP(V19,Curr!$B$2:$C$13,2,FALSE),0) -> 1 | X19: =U19*W19 -> 0 | Y19: =Q19/11.3/0.9 -> 0 | Z19: =+Y19*R19 -> 0 | AA19: EUR | AB19: =IFERROR(VLOOKUP(AA19,Curr!$B$2:$C$13,2,FALSE),0) -> 11.2 | AC19: =+Y19*AB19*R19 -> 0 | AD19: =+AC19-X19 -> 0 | AE19: =IFERROR(AD19/AC19,0) -> 0
C20: Day 3 | D20: Transfer | J20: Bergen: Self transfer to your accommodation | Q20: 0 | R20: 0 | S20: =+Q20*R20 -> 0 | T20: 0 | U20: =S20*(1-T20) -> 0 | V20: EUR | W20: =IFERROR(VLOOKUP(V20,Curr!$B$2:$C$13,2,FALSE),0) -> 11.2 | X20: =U20*W20 -> 0 | Y20: =Q20 -> 0 | Z20: =+Y20*R20 -> 0 | AA20: EUR | AB20: =IFERROR(VLOOKUP(AA20,Curr!$B$2:$C$13,2,FALSE),0) -> 11.2 | AC20: =+Y20*AB20*R20 -> 0 | AD20: =+AC20-X20 -> 0 | AE20: =IFERROR(AD20/AC20,0) -> 0
C21: Day 3 | D21: Hotel | J21: Bergen: Check in to your accommodation for a 2 night stay - Centrally located 3/4-star hotel - Standard Room - Breakfast included | Q21: 290 | R21: 1 | S21: =+Q21*R21 -> 290 | T21: 0 | U21: =S21*(1-T21) -> 290 | V21: EUR | W21: =IFERROR(VLOOKUP(V21,Curr!$B$2:$C$13,2,FALSE),0) -> 11.2 | X21: =U21*W21 -> 3248 | Y21: =Q21/0.85 -> 341.17647 | Z21: =+Y21*R21 -> 341.17647 | AA21: EUR | AB21: =IFERROR(VLOOKUP(AA21,Curr!$B$2:$C$13,2,FALSE),0) -> 11.2 | AC21: =+Y21*AB21*R21 -> 3821.1765 | AD21: =+AC21-X21 -> 573.17647 | AE21: =IFERROR(AD21/AC21,0) -> 0.15
C22: Day 3 | D22: Leisure | J22: Bergen: Spend time at leisure | Q22: 0 | R22: 0 | S22: =+Q22*R22 -> 0 | T22: 0 | U22: =S22*(1-T22) -> 0 | V22: EUR | W22: =IFERROR(VLOOKUP(V22,Curr!$B$2:$C$13,2,FALSE),0) -> 11.2 | X22: =U22*W22 -> 0 | Y22: =Q22 -> 0 | Z22: =+Y22*R22 -> 0 | AA22: EUR | AB22: =IFERROR(VLOOKUP(AA22,Curr!$B$2:$C$13,2,FALSE),0) -> 11.2 | AC22: =+Y22*AB22*R22 -> 0 | AD22: =+AC22-X22 -> 0 | AE22: =IFERROR(AD22/AC22,0) -> 0
S23: =+Q23*R23 -> 0 | T23: 0 | U23: =S23*(1-T23) -> 0 | V23: EUR | W23: =IFERROR(VLOOKUP(V23,Curr!$B$2:$C$13,2,FALSE),0) -> 11.2 | X23: =U23*W23 -> 0 | Y23: =Q23 -> 0 | Z23: =+Y23*R23 -> 0 | AA23: EUR | AB23: =IFERROR(VLOOKUP(AA23,Curr!$B$2:$C$13,2,FALSE),0) -> 11.2 | AC23: =+Y23*AB23*R23 -> 0 | AD23: =+AC23-X23 -> 0 | AE23: =IFERROR(AD23/AC23,0) -> 0
C24: Day 4 | D24: Activity | J24: Bergen: 2 hr walk Through Bergen Past & Present - Time: 10:00 am - 12:00 pm - Meeting point: Bradbenken 1 - Includes: Profesional Guide | O24: x | P24: https://www.ilovebergen.net/tour/a-walk-through-bergen-past-present/ | Q24: 290 | R24: 2 | S24: =+Q24*R24 -> 580 | T24: 0.2 | U24: =S24*(1-T24) -> 464 | V24: NOK | W24: =IFERROR(VLOOKUP(V24,Curr!$B$2:$C$13,2,FALSE),0) -> 1 | X24: =U24*W24 -> 464 | Y24: =Q24/11.3/0.64 -> 40.099558 | Z24: =+Y24*R24 -> 80.199115 | AA24: EUR | AB24: =IFERROR(VLOOKUP(AA24,Curr!$B$2:$C$13,2,FALSE),0) -> 11.2 | AC24: =+Y24*AB24*R24 -> 898.23009 | AD24: =+AC24-X24 -> 434.23009 | AE24: =IFERROR(AD24/AC24,0) -> 0.48342857
C25: Day 4 | D25: Activity | J25: Bergen: Fløibanen Funicual - Time: Flexible - Meeting point: Vetrlidsallmenningen 23A - Includes: Tickets | O25: x | P25: https://www.floyen.no/en/floibanen/buy-tickets/ | Q25: 175 | R25: 2 | S25: =+Q25*R25 -> 350 | T25: 0 | U25: =S25*(1-T25) -> 350 | V25: NOK | W25: =IFERROR(VLOOKUP(V25,Curr!$B$2:$C$13,2,FALSE),0) -> 1 | X25: =U25*W25 -> 350 | Y25: =Q25/11.3/0.5 -> 30.973451 | Z25: =+Y25*R25 -> 61.946903 | AA25: EUR | AB25: =IFERROR(VLOOKUP(AA25,Curr!$B$2:$C$13,2,FALSE),0) -> 11.2 | AC25: =+Y25*AB25*R25 -> 693.80531 | AD25: =+AC25-X25 -> 343.80531 | AE25: =IFERROR(AD25/AC25,0) -> 0.49553571
C26: Day 4 | D26: Leisure | J26: Bergen: Spend time at leisure | Q26: 0 | R26: 0 | S26: =+Q26*R26 -> 0 | T26: 0 | U26: =S26*(1-T26) -> 0 | V26: EUR | W26: =IFERROR(VLOOKUP(V26,Curr!$B$2:$C$13,2,FALSE),0) -> 11.2 | X26: =U26*W26 -> 0 | Y26: =Q26 -> 0 | Z26: =+Y26*R26 -> 0 | AA26: EUR | AB26: =IFERROR(VLOOKUP(AA26,Curr!$B$2:$C$13,2,FALSE),0) -> 11.2 | AC26: =+Y26*AB26*R26 -> 0 | AD26: =+AC26-X26 -> 0 | AE26: =IFERROR(AD26/AC26,0) -> 0
S27: =+Q27*R27 -> 0 | T27: 0 | U27: =S27*(1-T27) -> 0 | V27: EUR | W27: =IFERROR(VLOOKUP(V27,Curr!$B$2:$C$13,2,FALSE),0) -> 11.2 | X27: =U27*W27 -> 0 | Y27: =Q27 -> 0 | Z27: =+Y27*R27 -> 0 | AA27: EUR | AB27: =IFERROR(VLOOKUP(AA27,Curr!$B$2:$C$13,2,FALSE),0) -> 11.2 | AC27: =+Y27*AB27*R27 -> 0 | AD27: =+AC27-X27 -> 0 | AE27: =IFERROR(AD27/AC27,0) -> 0
C28: Day 5 | D28: Transfer | J28: Bergen: Self transfer to Bergen Airport | Q28: 0 | R28: 0 | S28: =+Q28*R28 -> 0 | T28: 0 | U28: =S28*(1-T28) -> 0 | V28: EUR | W28: =IFERROR(VLOOKUP(V28,Curr!$B$2:$C$13,2,FALSE),0) -> 11.2 | X28: =U28*W28 -> 0 | Y28: =Q28 -> 0 | Z28: =+Y28*R28 -> 0 | AA28: EUR | AB28: =IFERROR(VLOOKUP(AA28,Curr!$B$2:$C$13,2,FALSE),0) -> 11.2 | AC28: =+Y28*AB28*R28 -> 0 | AD28: =+AC28-X28 -> 0 | AE28: =IFERROR(AD28/AC28,0) -> 0
C29: Day 5 | D29: Flight | J29: Bergen: Flight to Tromsø - Time: Date dependant - Luggage included: 1 x 23 kg check in and 1 x 8 kg carry on per person | O29: x | Q29: 1800 | R29: 2 | S29: =+Q29*R29 -> 3600 | T29: 0 | U29: =S29*(1-T29) -> 3600 | V29: NOK | W29: =IFERROR(VLOOKUP(V29,Curr!$B$2:$C$13,2,FALSE),0) -> 1 | X29: =U29*W29 -> 3600 | Y29: =Q29/11.3/0.8 -> 199.11504 | Z29: =+Y29*R29 -> 398.23009 | AA29: EUR | AB29: =IFERROR(VLOOKUP(AA29,Curr!$B$2:$C$13,2,FALSE),0) -> 11.2 | AC29: =+Y29*AB29*R29 -> 4460.177 | AD29: =+AC29-X29 -> 860.17699 | AE29: =IFERROR(AD29/AC29,0) -> 0.19285714
C30: Day 5 | D30: Transfer | J30: Tromsø: Self transfer to your accommodation | Q30: 0 | R30: 0 | S30: =+Q30*R30 -> 0 | T30: 0 | U30: =S30*(1-T30) -> 0 | V30: NOK | W30: =IFERROR(VLOOKUP(V30,Curr!$B$2:$C$13,2,FALSE),0) -> 1 | X30: =U30*W30 -> 0 | Y30: =Q30/11.3/0.8 -> 0 | Z30: =+Y30*R30 -> 0 | AA30: EUR | AB30: =IFERROR(VLOOKUP(AA30,Curr!$B$2:$C$13,2,FALSE),0) -> 11.2 | AC30: =+Y30*AB30*R30 -> 0 | AD30: =+AC30-X30 -> 0 | AE30: =IFERROR(AD30/AC30,0) -> 0
C31: Day 5 | D31: Hotel | J31: Tromsø: Check in to your accommodation for a 3 night stay - Centrally located 3/4-star hotel - Standard Room - Breakfast included | Q31: 700 | R31: 1 | S31: =+Q31*R31 -> 700 | T31: 0 | U31: =S31*(1-T31) -> 700 | V31: EUR | W31: =IFERROR(VLOOKUP(V31,Curr!$B$2:$C$13,2,FALSE),0) -> 11.2 | X31: =U31*W31 -> 7840 | Y31: =Q31/0.85 -> 823.52941 | Z31: =+Y31*R31 -> 823.52941 | AA31: EUR | AB31: =IFERROR(VLOOKUP(AA31,Curr!$B$2:$C$13,2,FALSE),0) -> 11.2 | AC31: =+Y31*AB31*R31 -> 9223.5294 | AD31: =+AC31-X31 -> 1383.5294 | AE31: =IFERROR(AD31/AC31,0) -> 0.15
C32: Day 5 | D32: Leisure | J32: Tromsø: Spend time at leisure | Q32: 0 | R32: 0 | S32: =+Q32*R32 -> 0 | T32: 0 | U32: =S32*(1-T32) -> 0 | V32: EUR | W32: =IFERROR(VLOOKUP(V32,Curr!$B$2:$C$13,2,FALSE),0) -> 11.2 | X32: =U32*W32 -> 0 | Y32: =Q32 -> 0 | Z32: =+Y32*R32 -> 0 | AA32: EUR | AB32: =IFERROR(VLOOKUP(AA32,Curr!$B$2:$C$13,2,FALSE),0) -> 11.2 | AC32: =+Y32*AB32*R32 -> 0 | AD32: =+AC32-X32 -> 0 | AE32: =IFERROR(AD32/AC32,0) -> 0
C33: Day 5 | D33: Activity | J33: Tromsø: Northern Lights Cruise with Silent Electric Ship - Time: 7:00 pm - 10:00 pm - Meeting point: Kaigata 6 - Includes: Departure from central Tromsø, 3-hour fjord cruise, Light meal (soup and bread) and water, English speaking guides, Warm indoor saloons, Free wifi, Toilets | O33: x | P33: https://booknordics.com/norway/northern-norway/tromso-region/northern-lights-cruise-electric-ship | Q33: 105 | R33: 2 | S33: =+Q33*R33 -> 210 | T33: 0.2 | U33: =S33*(1-T33) -> 168 | V33: EUR | W33: =IFERROR(VLOOKUP(V33,Curr!$B$2:$C$13,2,FALSE),0) -> 11.2 | X33: =U33*W33 -> 1881.6 | Y33: =Q33 -> 105 | Z33: =+Y33*R33 -> 210 | AA33: EUR | AB33: =IFERROR(VLOOKUP(AA33,Curr!$B$2:$C$13,2,FALSE),0) -> 11.2 | AC33: =+Y33*AB33*R33 -> 2352 | AD33: =+AC33-X33 -> 470.4 | AE33: =IFERROR(AD33/AC33,0) -> 0.2
S34: =+Q34*R34 -> 0 | T34: 0 | U34: =S34*(1-T34) -> 0 | V34: EUR | W34: =IFERROR(VLOOKUP(V34,Curr!$B$2:$C$13,2,FALSE),0) -> 11.2 | X34: =U34*W34 -> 0 | Y34: =Q34 -> 0 | Z34: =+Y34*R34 -> 0 | AA34: EUR | AB34: =IFERROR(VLOOKUP(AA34,Curr!$B$2:$C$13,2,FALSE),0) -> 11.2 | AC34: =+Y34*AB34*R34 -> 0 | AD34: =+AC34-X34 -> 0 | AE34: =IFERROR(AD34/AC34,0) -> 0
C35: Day 6 | D35: Activity | J35: Tromsø: Reindeer Feeding and Sámi Culture - Time: 09:45 am - 2:30 pm - Meeting point: Radisson Blu Hotel's main entrance (Sjøgata 7) - Includes: Scenic transfers (45 min each way), Knowledgeable English and Norwegian speaking guide, Feeding the herd at our camp, Hot beverages and hot meal (traditional Sámi stew or vegetable/lentil soup), Cultural introduction about Sámi history and daily life, A chance to see the northern lights from our camp, Thermal suit and warm snow boots | O35: x | P35: https://www.tromsolapland.no/activities/reindeer-feeding-and-sami-culture | Q35: 1695 | R35: 2 | S35: =+Q35*R35 -> 3390 | T35: 0.2 | U35: =S35*(1-T35) -> 2712 | V35: NOK | W35: =IFERROR(VLOOKUP(V35,Curr!$B$2:$C$13,2,FALSE),0) -> 1 | X35: =U35*W35 -> 2712 | Y35: =Q35/11.3 -> 150 | Z35: =+Y35*R35 -> 300 | AA35: EUR | AB35: =IFERROR(VLOOKUP(AA35,Curr!$B$2:$C$13,2,FALSE),0) -> 11.2 | AC35: =+Y35*AB35*R35 -> 3360 | AD35: =+AC35-X35 -> 648 | AE35: =IFERROR(AD35/AC35,0) -> 0.19285714
C36: Day 6 | D36: Leisure | J36: Tromsø: Spend time at leisure | Q36: 0 | R36: 0 | S36: =+Q36*R36 -> 0 | T36: 0 | U36: =S36*(1-T36) -> 0 | V36: EUR | W36: =IFERROR(VLOOKUP(V36,Curr!$B$2:$C$13,2,FALSE),0) -> 11.2 | X36: =U36*W36 -> 0 | Y36: =Q36 -> 0 | Z36: =+Y36*R36 -> 0 | AA36: EUR | AB36: =IFERROR(VLOOKUP(AA36,Curr!$B$2:$C$13,2,FALSE),0) -> 11.2 | AC36: =+Y36*AB36*R36 -> 0 | AD36: =+AC36-X36 -> 0 | AE36: =IFERROR(AD36/AC36,0) -> 0
C37: Day 6 | D37: Activity | J37: Tromsø: All-Evening Northern Lights Hunt by Minibus or Bus - Time: 7:00 pm - 12:00 am - Meeting point: Kaigata 4 - Includes: Knowledgeable, English-speaking guides, Photos shared with you after the tour, Thermo clothing and warm gear, Light snacks and warm/cold beverages, Drop-off at hotel, up to 5 km from Tromsø | O37: x | P37: https://booknordics.com/norway/northern-norway/tromso-region/full-day-magic-of-the-arctic-lights-in-tromso | Q37: 120 | R37: 2 | S37: =+Q37*R37 -> 240 | T37: 0.2 | U37: =S37*(1-T37) -> 192 | V37: EUR | W37: =IFERROR(VLOOKUP(V37,Curr!$B$2:$C$13,2,FALSE),0) -> 11.2 | X37: =U37*W37 -> 2150.4 | Y37: =Q37 -> 120 | Z37: =+Y37*R37 -> 240 | AA37: EUR | AB37: =IFERROR(VLOOKUP(AA37,Curr!$B$2:$C$13,2,FALSE),0) -> 11.2 | AC37: =+Y37*AB37*R37 -> 2688 | AD37: =+AC37-X37 -> 537.6 | AE37: =IFERROR(AD37/AC37,0) -> 0.2
S38: =+Q38*R38 -> 0 | T38: 0 | U38: =S38*(1-T38) -> 0 | V38: EUR | W38: =IFERROR(VLOOKUP(V38,Curr!$B$2:$C$13,2,FALSE),0) -> 11.2 | X38: =U38*W38 -> 0 | Y38: =Q38 -> 0 | Z38: =+Y38*R38 -> 0 | AA38: EUR | AB38: =IFERROR(VLOOKUP(AA38,Curr!$B$2:$C$13,2,FALSE),0) -> 11.2 | AC38: =+Y38*AB38*R38 -> 0 | AD38: =+AC38-X38 -> 0 | AE38: =IFERROR(AD38/AC38,0) -> 0
C39: Day 7 | D39: Activity | J39: Tromsø: Photo Tour to Arctic Landscapes and Fjords - Time: 10:00 am - 3:00 pm - Meeting point: Roald Amundsens plass 1A - Includes: Departure from central Tromsø. Drop-off to your hotel, Professional, English-speaking photo guides, Scenic fjord safari by comfortable minivan vehicle, Help with camera settings and nature photography, Usually a small-group experience with 4-8 guests, Soup or expedition food, coffee and waffles/cookies | O39: x | P39: https://booknordics.com/norway/northern-norway/tromso-region/tromso-fjord-photo-tour | Q39: 145 | R39: 2 | S39: =+Q39*R39 -> 290 | T39: 0.2 | U39: =S39*(1-T39) -> 232 | V39: EUR | W39: =IFERROR(VLOOKUP(V39,Curr!$B$2:$C$13,2,FALSE),0) -> 11.2 | X39: =U39*W39 -> 2598.4 | Y39: =Q39 -> 145 | Z39: =+Y39*R39 -> 290 | AA39: EUR | AB39: =IFERROR(VLOOKUP(AA39,Curr!$B$2:$C$13,2,FALSE),0) -> 11.2 | AC39: =+Y39*AB39*R39 -> 3248 | AD39: =+AC39-X39 -> 649.6 | AE39: =IFERROR(AD39/AC39,0) -> 0.2
C40: Day 7 | D40: Leisure | J40: Tromsø: Spend time at leisure | Q40: 0 | R40: 0 | S40: =+Q40*R40 -> 0 | T40: 0 | U40: =S40*(1-T40) -> 0 | V40: EUR | W40: =IFERROR(VLOOKUP(V40,Curr!$B$2:$C$13,2,FALSE),0) -> 11.2 | X40: =U40*W40 -> 0 | Y40: =Q40 -> 0 | Z40: =+Y40*R40 -> 0 | AA40: EUR | AB40: =IFERROR(VLOOKUP(AA40,Curr!$B$2:$C$13,2,FALSE),0) -> 11.2 | AC40: =+Y40*AB40*R40 -> 0 | AD40: =+AC40-X40 -> 0 | AE40: =IFERROR(AD40/AC40,0) -> 0
S41: =+Q41*R41 -> 0 | T41: 0 | U41: =S41*(1-T41) -> 0 | V41: EUR | W41: =IFERROR(VLOOKUP(V41,Curr!$B$2:$C$13,2,FALSE),0) -> 11.2 | X41: =U41*W41 -> 0 | Y41: =Q41 -> 0 | Z41: =+Y41*R41 -> 0 | AA41: EUR | AB41: =IFERROR(VLOOKUP(AA41,Curr!$B$2:$C$13,2,FALSE),0) -> 11.2 | AC41: =+Y41*AB41*R41 -> 0 | AD41: =+AC41-X41 -> 0 | AE41: =IFERROR(AD41/AC41,0) -> 0
C42: Day 8 | D42: Transfer | J42: Tromsø: Self transfer to Tromsø Airport | Q42: 0 | R42: 0 | S42: =+Q42*R42 -> 0 | T42: 0 | U42: =S42*(1-T42) -> 0 | V42: NOK | W42: =IFERROR(VLOOKUP(V42,Curr!$B$2:$C$13,2,FALSE),0) -> 1 | X42: =U42*W42 -> 0 | Y42: =Q42/11.3/0.8 -> 0 | Z42: =+Y42*R42 -> 0 | AA42: EUR | AB42: =IFERROR(VLOOKUP(AA42,Curr!$B$2:$C$13,2,FALSE),0) -> 11.2 | AC42: =+Y42*AB42*R42 -> 0 | AD42: =+AC42-X42 -> 0 | AE42: =IFERROR(AD42/AC42,0) -> 0
C43: Day 8 | D43: Departure | J43: Tromsø: Departure home | Q43: 0 | R43: 0 | S43: =+Q43*R43 -> 0 | T43: 0 | U43: =S43*(1-T43) -> 0 | V43: EUR | W43: =IFERROR(VLOOKUP(V43,Curr!$B$2:$C$13,2,FALSE),0) -> 11.2 | X43: =U43*W43 -> 0 | Y43: =Q43 -> 0 | Z43: =+Y43*R43 -> 0 | AA43: EUR | AB43: =IFERROR(VLOOKUP(AA43,Curr!$B$2:$C$13,2,FALSE),0) -> 11.2 | AC43: =+Y43*AB43*R43 -> 0 | AD43: =+AC43-X43 -> 0 | AE43: =IFERROR(AD43/AC43,0) -> 0
S44: =+Q44*R44 -> 0 | T44: 0 | U44: =S44*(1-T44) -> 0 | V44: EUR | W44: =IFERROR(VLOOKUP(V44,Curr!$B$2:$C$13,2,FALSE),0) -> 11.2 | X44: =U44*W44 -> 0 | Y44: =Q44 -> 0 | Z44: =+Y44*R44 -> 0 | AA44: EUR | AB44: =IFERROR(VLOOKUP(AA44,Curr!$B$2:$C$13,2,FALSE),0) -> 11.2 | AC44: =+Y44*AB44*R44 -> 0 | AD44: =+AC44-X44 -> 0 | AE44: =IFERROR(AD44/AC44,0) -> 0
S45: =+Q45*R45 -> 0 | T45: 0 | U45: =S45*(1-T45) -> 0 | V45: EUR | W45: =IFERROR(VLOOKUP(V45,Curr!$B$2:$C$13,2,FALSE),0) -> 11.2 | X45: =U45*W45 -> 0 | Y45: =Q45 -> 0 | Z45: =+Y45*R45 -> 0 | AA45: EUR | AB45: =IFERROR(VLOOKUP(AA45,Curr!$B$2:$C$13,2,FALSE),0) -> 11.2 | AC45: =+Y45*AB45*R45 -> 0 | AD45: =+AC45-X45 -> 0 | AE45: =IFERROR(AD45/AC45,0) -> 0
C46: Day 1 | D46: Transfer Package | J46: Oslo: Private transfer to your accommodation | Q46: 1750 | R46: 0 | S46: =+Q46*R46 -> 0 | T46: 0 | U46: =S46*(1-T46) -> 0 | V46: NOK | W46: =IFERROR(VLOOKUP(V46,Curr!$B$2:$C$13,2,FALSE),0) -> 1 | X46: =U46*W46 -> 0 | Y46: =Q46/11.3/0.8 -> 193.58407 | Z46: =+Y46*R46 -> 0 | AA46: EUR | AB46: =IFERROR(VLOOKUP(AA46,Curr!$B$2:$C$13,2,FALSE),0) -> 11.2 | AC46: =+Y46*AB46*R46 -> 0 | AD46: =+AC46-X46 -> 0 | AE46: =IFERROR(AD46/AC46,0) -> 0
C47: Day 3 | D47: Transfer Package | J47: Bergen: Private transfer to your accommodation | Q47: 1290 | R47: 0 | S47: =+Q47*R47 -> 0 | T47: 0.15 | U47: =S47*(1-T47) -> 0 | V47: NOK | W47: =IFERROR(VLOOKUP(V47,Curr!$B$2:$C$13,2,FALSE),0) -> 1 | X47: =U47*W47 -> 0 | Y47: =Q47/11.3/0.98 -> 116.48907 | Z47: =+Y47*R47 -> 0 | AA47: EUR | AB47: =IFERROR(VLOOKUP(AA47,Curr!$B$2:$C$13,2,FALSE),0) -> 11.2 | AC47: =+Y47*AB47*R47 -> 0 | AD47: =+AC47-X47 -> 0 | AE47: =IFERROR(AD47/AC47,0) -> 0
C48: Day 5 | D48: Transfer Package | J48: Bergen: Private transfer to Bergen Airport | Q48: 1690 | R48: 0 | S48: =+Q48*R48 -> 0 | T48: 0.15 | U48: =S48*(1-T48) -> 0 | V48: NOK | W48: =IFERROR(VLOOKUP(V48,Curr!$B$2:$C$13,2,FALSE),0) -> 1 | X48: =U48*W48 -> 0 | Y48: =Q48/11.3/0.98 -> 152.60972 | Z48: =+Y48*R48 -> 0 | AA48: EUR | AB48: =IFERROR(VLOOKUP(AA48,Curr!$B$2:$C$13,2,FALSE),0) -> 11.2 | AC48: =+Y48*AB48*R48 -> 0 | AD48: =+AC48-X48 -> 0 | AE48: =IFERROR(AD48/AC48,0) -> 0
C49: Day 5 | D49: Transfer Package | J49: Tromsø: Private transfer to your accommodation | Q49: 900 | R49: 0 | S49: =+Q49*R49 -> 0 | T49: 0 | U49: =S49*(1-T49) -> 0 | V49: NOK | W49: =IFERROR(VLOOKUP(V49,Curr!$B$2:$C$13,2,FALSE),0) -> 1 | X49: =U49*W49 -> 0 | Y49: =Q49/11.3/0.8 -> 99.557522 | Z49: =+Y49*R49 -> 0 | AA49: EUR | AB49: =IFERROR(VLOOKUP(AA49,Curr!$B$2:$C$13,2,FALSE),0) -> 11.2 | AC49: =+Y49*AB49*R49 -> 0 | AD49: =+AC49-X49 -> 0 | AE49: =IFERROR(AD49/AC49,0) -> 0
C50: Day 6 | D50: Transfer Package | J50: Tromsø: Private transfer to Tromsø Airport | Q50: 900 | R50: 0 | S50: =+Q50*R50 -> 0 | T50: 0 | U50: =S50*(1-T50) -> 0 | V50: NOK | W50: =IFERROR(VLOOKUP(V50,Curr!$B$2:$C$13,2,FALSE),0) -> 1 | X50: =U50*W50 -> 0 | Y50: =Q50/11.3/0.8 -> 99.557522 | Z50: =+Y50*R50 -> 0 | AA50: EUR | AB50: =IFERROR(VLOOKUP(AA50,Curr!$B$2:$C$13,2,FALSE),0) -> 11.2 | AC50: =+Y50*AB50*R50 -> 0 | AD50: =+AC50-X50 -> 0 | AE50: =IFERROR(AD50/AC50,0) -> 0
S51: =+Q51*R51 -> 0 | T51: 0 | U51: =S51*(1-T51) -> 0 | V51: EUR | W51: =IFERROR(VLOOKUP(V51,Curr!$B$2:$C$13,2,FALSE),0) -> 11.2 | X51: =U51*W51 -> 0 | Y51: =Q51 -> 0 | Z51: =+Y51*R51 -> 0 | AA51: EUR | AB51: =IFERROR(VLOOKUP(AA51,Curr!$B$2:$C$13,2,FALSE),0) -> 11.2 | AC51: =+Y51*AB51*R51 -> 0 | AD51: =+AC51-X51 -> 0 | AE51: =IFERROR(AD51/AC51,0) -> 0
C52: Day 2 | D52: Activity Upgrade | J52: Oslo: Norway in a Nutshell Porter Service - Includes: Luggage transfer from your accommodation in Oslo to your accommodaiton in Bergen | S52: =+Q52*R52 -> 0 | T52: 0 | U52: =S52*(1-T52) -> 0 | V52: EUR | W52: =IFERROR(VLOOKUP(V52,Curr!$B$2:$C$13,2,FALSE),0) -> 11.2 | X52: =U52*W52 -> 0 | Y52: =Q52 -> 0 | Z52: =+Y52*R52 -> 0 | AA52: EUR | AB52: =IFERROR(VLOOKUP(AA52,Curr!$B$2:$C$13,2,FALSE),0) -> 11.2 | AC52: =+Y52*AB52*R52 -> 0 | AD52: =+AC52-X52 -> 0 | AE52: =IFERROR(AD52/AC52,0) -> 0
C53: Day 2 | D53: Activity Upgrade | J53: Oslo: Norway in a Nutshell Porter Service - Includes: Luggage transfer from your accommodation in Oslo to your accommodaiton in Bergen | Q53: 450 | R53: 0 | S53: =+Q53*R53 -> 0 | T53: 0 | U53: =S53*(1-T53) -> 0 | V53: NOK | W53: =IFERROR(VLOOKUP(V53,Curr!$B$2:$C$13,2,FALSE),0) -> 1 | X53: =U53*W53 -> 0 | Y53: =Q53/11.3/0.8 -> 49.778761 | Z53: =+Y53*R53 -> 0 | AA53: EUR | AB53: =IFERROR(VLOOKUP(AA53,Curr!$B$2:$C$13,2,FALSE),0) -> 11.2 | AC53: =+Y53*AB53*R53 -> 0 | AD53: =+AC53-X53 -> 0 | AE53: =IFERROR(AD53/AC53,0) -> 0
C54: Day 4 | D54: Activity Upgrade | J54: Bergen: Mostraumen Majestic Fjord & Waterfall Cruise - Time: 12:00 pm - 4:00 pm - Meeting point: Strandkaien 13 - Includes: 4-hour panoramic fjord cruise, Expert captain navigating through the fjords, English-audio guide | O54: x | P54: https://booknordics.com/norway/western-fjord-norway/bergen-and-hardanger/mostraumen-fjord-waterfall-cruise | Q54: 71 | R54: 0 | S54: =+Q54*R54 -> 0 | T54: 0.2 | U54: =S54*(1-T54) -> 0 | V54: EUR | W54: =IFERROR(VLOOKUP(V54,Curr!$B$2:$C$13,2,FALSE),0) -> 11.2 | X54: =U54*W54 -> 0 | Y54: =Q54 -> 71 | Z54: =+Y54*R54 -> 0 | AA54: EUR | AB54: =IFERROR(VLOOKUP(AA54,Curr!$B$2:$C$13,2,FALSE),0) -> 11.2 | AC54: =+Y54*AB54*R54 -> 0 | AD54: =+AC54-X54 -> 0 | AE54: =IFERROR(AD54/AC54,0) -> 0
C55: Day 6 | D55: Activity Upgrade | J55: Tromsø: Reindeer Sledding, Reindeer Feeding and Sami Culture - Time: 09:45 am - 2:30 pm - Meeting point: Radisson Blu Hotel's main entrance (Sjøgata 7) - Includes: Scenic transfers (45 min each way), Knowledgeable English- and Norwegian-speaking guide, Thermal winter suit, warm boots, Reindeer sledding (approx. 30 min, depending on weather and snow conditions), Feeding the herd on our camp, Hot traditional Sámi meal (bithos) and hot drinks. Vegetarian option available on request, Cultural introduction about Sámi history and daily life | O55: x | P55: https://booknordics.com/norway/northern-norway/tromso-region/reindeer-sledding-reindeer-feeding-and-sami-culture-3 | Q55: 2195 | R55: 0 | S55: =+Q55*R55 -> 0 | T55: 0.2 | U55: =S55*(1-T55) -> 0 | V55: NOK | W55: =IFERROR(VLOOKUP(V55,Curr!$B$2:$C$13,2,FALSE),0) -> 1 | X55: =U55*W55 -> 0 | Y55: =Q55/11.3 -> 194.24779 | Z55: =+Y55*R55 -> 0 | AA55: EUR | AB55: =IFERROR(VLOOKUP(AA55,Curr!$B$2:$C$13,2,FALSE),0) -> 11.2 | AC55: =+Y55*AB55*R55 -> 0 | AD55: =+AC55-X55 -> 0 | AE55: =IFERROR(AD55/AC55,0) -> 0
S56: =+Q56*R56 -> 0 | T56: 0 | U56: =S56*(1-T56) -> 0 | V56: EUR | W56: =IFERROR(VLOOKUP(V56,Curr!$B$2:$C$13,2,FALSE),0) -> 11.2 | X56: =U56*W56 -> 0 | Y56: =Q56 -> 0 | Z56: =+Y56*R56 -> 0 | AA56: EUR | AB56: =IFERROR(VLOOKUP(AA56,Curr!$B$2:$C$13,2,FALSE),0) -> 11.2 | AC56: =+Y56*AB56*R56 -> 0 | AD56: =+AC56-X56 -> 0 | AE56: =IFERROR(AD56/AC56,0) -> 0
S57: =+Q57*R57 -> 0 | T57: 0 | U57: =S57*(1-T57) -> 0 | V57: EUR | W57: =IFERROR(VLOOKUP(V57,Curr!$B$2:$C$13,2,FALSE),0) -> 11.2 | X57: =U57*W57 -> 0 | Y57: =Q57 -> 0 | Z57: =+Y57*R57 -> 0 | AA57: EUR | AB57: =IFERROR(VLOOKUP(AA57,Curr!$B$2:$C$13,2,FALSE),0) -> 11.2 | AC57: =+Y57*AB57*R57 -> 0 | AD57: =+AC57-X57 -> 0 | AE57: =IFERROR(AD57/AC57,0) -> 0
S58: =+Q58*R58 -> 0 | T58: 0 | U58: =S58*(1-T58) -> 0 | V58: EUR | W58: =IFERROR(VLOOKUP(V58,Curr!$B$2:$C$13,2,FALSE),0) -> 11.2 | X58: =U58*W58 -> 0 | Y58: =Q58 -> 0 | Z58: =+Y58*R58 -> 0 | AA58: EUR | AB58: =IFERROR(VLOOKUP(AA58,Curr!$B$2:$C$13,2,FALSE),0) -> 11.2 | AC58: =+Y58*AB58*R58 -> 0 | AD58: =+AC58-X58 -> 0 | AE58: =IFERROR(AD58/AC58,0) -> 0
S59: =+Q59*R59 -> 0 | T59: 0 | U59: =S59*(1-T59) -> 0 | V59: EUR | W59: =IFERROR(VLOOKUP(V59,Curr!$B$2:$C$13,2,FALSE),0) -> 11.2 | X59: =U59*W59 -> 0 | Y59: =Q59 -> 0 | Z59: =+Y59*R59 -> 0 | AA59: EUR | AB59: =IFERROR(VLOOKUP(AA59,Curr!$B$2:$C$13,2,FALSE),0) -> 11.2 | AC59: =+Y59*AB59*R59 -> 0 | AD59: =+AC59-X59 -> 0 | AE59: =IFERROR(AD59/AC59,0) -> 0
S60: =+Q60*R60 -> 0 | T60: 0 | U60: =S60*(1-T60) -> 0 | V60: EUR | W60: =IFERROR(VLOOKUP(V60,Curr!$B$2:$C$13,2,FALSE),0) -> 11.2 | X60: =U60*W60 -> 0 | Y60: =Q60 -> 0 | Z60: =+Y60*R60 -> 0 | AA60: EUR | AB60: =IFERROR(VLOOKUP(AA60,Curr!$B$2:$C$13,2,FALSE),0) -> 11.2 | AC60: =+Y60*AB60*R60 -> 0 | AD60: =+AC60-X60 -> 0 | AE60: =IFERROR(AD60/AC60,0) -> 0
S61: =+Q61*R61 -> 0 | T61: 0 | U61: =S61*(1-T61) -> 0 | V61: EUR | W61: =IFERROR(VLOOKUP(V61,Curr!$B$2:$C$13,2,FALSE),0) -> 11.2 | X61: =U61*W61 -> 0 | Y61: =Q61 -> 0 | Z61: =+Y61*R61 -> 0 | AA61: EUR | AB61: =IFERROR(VLOOKUP(AA61,Curr!$B$2:$C$13,2,FALSE),0) -> 11.2 | AC61: =+Y61*AB61*R61 -> 0 | AD61: =+AC61-X61 -> 0 | AE61: =IFERROR(AD61/AC61,0) -> 0
B63: Totals | D63: x | E63: x | F63: x | G63: x | H63: x | I63: x | J63: x | K63: x | L63: x | M63: x | N63: x | O63: x | P63: x | Q63: x | R63: x | S63: x | T63: x | U63: x | V63: x | W63: x | X63: x | Y63: x | Z63: =SUM(Z7:Z61) -> 3831.2929 | AC63: =SUM(AC7:AC61) -> 42910.48 | AD63: =SUM(AD7:AD61) -> 7830.8802 | AE63: =IFERROR(AD63/AC63,0) -> 0.18249342 | AF63: =SUM(AF8:AF62) -> 0 | AG63: =SUM(AG8:AG62) -> 0 | AH63: =SUM(AH8:AH62) -> 0 | AI63: =SUM(AI8:AI62) -> 0 | AJ63: =SUM(AJ8:AJ62) -> 0
Y65: Fixed | Z65: 1940
Y66: Variable | Z66: =Z9+Z15+Z21+Z29+Z31 -> 2004.1124
Y67: Total | Z67: 3840
Y68: PP | Z68: =Z67/2 -> 1920
Z71: Winter
Y72: Shoulder | Z72: =Z67 -> 3840
Y73: High | Z73: =Z72*1.18 -> 4531.2
Y74: Holiday | Z74: =Z72*1.25 -> 4800
Y75: Low | Z75: =Z72*0.85 -> 3264
Y76: Summer | Z76: NA

Sheet 203
B1: Season: Winter
B2: Places: Oslo 1N - Bergen 2N - Tromsø 2N - Lyngen 1N - Tromsø 1N
B3: Pax: 2
B4: Rooming: Double
B6: ID | C6: Day | D6: Type | E6: From date | F6: To date | G6: From time | H6: To time | I6: Supplier | J6: Travel element | K6: Manual booking? | L6: Status | M6: Comments | N6: Non-refundable | O6: Refundable | P6: URL | Q6: Gross P per unit | R6: Units | S6: Gross P | T6: Supp Comm | U6: Net P | V6: Supp curr | W6: X-rate | X6: Net P NOK | Y6: Sales P per unit | Z6: Price | AA6: Sales curr | AB6: X-rate | AC6: Sales P NOK tot | AD6: GP NOK | AE6: GP % | AF6: VAT25 | AG6: VAT15 | AH6: VAT12 | AI6: VAT0-D | AJ6: VAT0-I
C7: Day 1 | D7: Arrival | J7: Oslo: Welcome to Norway | Q7: 0 | R7: 0 | S7: =+Q7*R7 -> 0 | T7: 0 | U7: =S7*(1-T7) -> 0 | V7: EUR | W7: =IFERROR(VLOOKUP(V7,Curr!$B$2:$C$13,2,FALSE),0) -> 11.2 | X7: =U7*W7 -> 0 | Y7: =Q7 -> 0 | Z7: =+Y7*R7 -> 0 | AA7: EUR | AB7: =IFERROR(VLOOKUP(AA7,Curr!$B$2:$C$13,2,FALSE),0) -> 11.2 | AC7: =+Y7*AB7*R7 -> 0 | AD7: =+AC7-X7 -> 0 | AE7: =IFERROR(AD7/AC7,0) -> 0
C8: Day 1 | D8: Transfer | J8: Oslo: Self transfer to your accommodation | Q8: 0 | R8: 0 | S8: =+Q8*R8 -> 0 | T8: 0 | U8: =S8*(1-T8) -> 0 | V8: NOK | W8: =IFERROR(VLOOKUP(V8,Curr!$B$2:$C$13,2,FALSE),0) -> 1 | X8: =U8*W8 -> 0 | Y8: =Q8/11.3/0.8 -> 0 | Z8: =+Y8*R8 -> 0 | AA8: EUR | AB8: =IFERROR(VLOOKUP(AA8,Curr!$B$2:$C$13,2,FALSE),0) -> 11.2 | AC8: =+Y8*AB8*R8 -> 0 | AD8: =+AC8-X8 -> 0 | AE8: =IFERROR(AD8/AC8,0) -> 0
C9: Day 1 | D9: Hotel | J9: Oslo: Check in to your accommodation for a 1 night stay - Centrally located 3/4-star hotel - Standard Room - Breakfast included | Q9: 150 | R9: 1 | S9: =+Q9*R9 -> 150 | T9: 0 | U9: =S9*(1-T9) -> 150 | V9: EUR | W9: =IFERROR(VLOOKUP(V9,Curr!$B$2:$C$13,2,FALSE),0) -> 11.2 | X9: =U9*W9 -> 1680 | Y9: =Q9/0.85 -> 176.47059 | Z9: =+Y9*R9 -> 176.47059 | AA9: EUR | AB9: =IFERROR(VLOOKUP(AA9,Curr!$B$2:$C$13,2,FALSE),0) -> 11.2 | AC9: =+Y9*AB9*R9 -> 1976.4706 | AD9: =+AC9-X9 -> 296.47059 | AE9: =IFERROR(AD9/AC9,0) -> 0.15
C10: Day 1 | D10: Leisure | J10: Oslo: Spend time at leisure | Q10: 0 | R10: 0 | S10: =+Q10*R10 -> 0 | T10: 0 | U10: =S10*(1-T10) -> 0 | V10: EUR | W10: =IFERROR(VLOOKUP(V10,Curr!$B$2:$C$13,2,FALSE),0) -> 11.2 | X10: =U10*W10 -> 0 | Y10: =Q10 -> 0 | Z10: =+Y10*R10 -> 0 | AA10: EUR | AB10: =IFERROR(VLOOKUP(AA10,Curr!$B$2:$C$13,2,FALSE),0) -> 11.2 | AC10: =+Y10*AB10*R10 -> 0 | AD10: =+AC10-X10 -> 0 | AE10: =IFERROR(AD10/AC10,0) -> 0
S11: =+Q11*R11 -> 0 | T11: 0 | U11: =S11*(1-T11) -> 0 | V11: EUR | W11: =IFERROR(VLOOKUP(V11,Curr!$B$2:$C$13,2,FALSE),0) -> 11.2 | X11: =U11*W11 -> 0 | Y11: =Q11 -> 0 | Z11: =+Y11*R11 -> 0 | AA11: EUR | AB11: =IFERROR(VLOOKUP(AA11,Curr!$B$2:$C$13,2,FALSE),0) -> 11.2 | AC11: =+Y11*AB11*R11 -> 0 | AD11: =+AC11-X11 -> 0 | AE11: =IFERROR(AD11/AC11,0) -> 0
C12: Day 2 | D12: Transfer | J12: Oslo: Self transfer to Oslo Central Station | Q12: 0 | R12: 0 | S12: =+Q12*R12 -> 0 | T12: 0 | U12: =S12*(1-T12) -> 0 | V12: EUR | W12: =IFERROR(VLOOKUP(V12,Curr!$B$2:$C$13,2,FALSE),0) -> 11.2 | X12: =U12*W12 -> 0 | Y12: =Q12 -> 0 | Z12: =+Y12*R12 -> 0 | AA12: EUR | AB12: =IFERROR(VLOOKUP(AA12,Curr!$B$2:$C$13,2,FALSE),0) -> 11.2 | AC12: =+Y12*AB12*R12 -> 0 | AD12: =+AC12-X12 -> 0 | AE12: =IFERROR(AD12/AC12,0) -> 0
C13: Day 2 | D13: Train | J13: Oslo: Scenic Long Distance Train transfer to Bergen - Time: 08:25 am - 3:00 pm - Includes: Tickets | O13: x | P13: https://www.vy.no/#reisesok | Q13: 2400 | R13: 1 | S13: =+Q13*R13 -> 2400 | T13: 0 | U13: =S13*(1-T13) -> 2400 | V13: NOK | W13: =IFERROR(VLOOKUP(V13,Curr!$B$2:$C$13,2,FALSE),0) -> 1 | X13: =U13*W13 -> 2400 | Y13: =Q13/11.3/0.8 -> 265.48673 | Z13: =+Y13*R13 -> 265.48673 | AA13: EUR | AB13: =IFERROR(VLOOKUP(AA13,Curr!$B$2:$C$13,2,FALSE),0) -> 11.2 | AC13: =+Y13*AB13*R13 -> 2973.4513 | AD13: =+AC13-X13 -> 573.45133 | AE13: =IFERROR(AD13/AC13,0) -> 0.19285714
C14: Day 2 | D14: Transfer | J14: Bergen: Self transfer to your accommodation | Q14: 0 | R14: 0 | S14: =+Q14*R14 -> 0 | T14: 0 | U14: =S14*(1-T14) -> 0 | V14: EUR | W14: =IFERROR(VLOOKUP(V14,Curr!$B$2:$C$13,2,FALSE),0) -> 11.2 | X14: =U14*W14 -> 0 | Y14: =Q14 -> 0 | Z14: =+Y14*R14 -> 0 | AA14: EUR | AB14: =IFERROR(VLOOKUP(AA14,Curr!$B$2:$C$13,2,FALSE),0) -> 11.2 | AC14: =+Y14*AB14*R14 -> 0 | AD14: =+AC14-X14 -> 0 | AE14: =IFERROR(AD14/AC14,0) -> 0
C15: Day 2 | D15: Hotel | J15: Bergen: Check in to your accommodation for a 2 night stay - Centrally located 3/4-star hotel - Standard Room - Breakfast included | Q15: 280 | R15: 1 | S15: =+Q15*R15 -> 280 | T15: 0 | U15: =S15*(1-T15) -> 280 | V15: EUR | W15: =IFERROR(VLOOKUP(V15,Curr!$B$2:$C$13,2,FALSE),0) -> 11.2 | X15: =U15*W15 -> 3136 | Y15: =Q15/0.85 -> 329.41176 | Z15: =+Y15*R15 -> 329.41176 | AA15: EUR | AB15: =IFERROR(VLOOKUP(AA15,Curr!$B$2:$C$13,2,FALSE),0) -> 11.2 | AC15: =+Y15*AB15*R15 -> 3689.4118 | AD15: =+AC15-X15 -> 553.41176 | AE15: =IFERROR(AD15/AC15,0) -> 0.15
C16: Day 2 | D16: Leisure | J16: Bergen: Spend time at leisure | Q16: 0 | R16: 0 | S16: =+Q16*R16 -> 0 | T16: 0 | U16: =S16*(1-T16) -> 0 | V16: EUR | W16: =IFERROR(VLOOKUP(V16,Curr!$B$2:$C$13,2,FALSE),0) -> 11.2 | X16: =U16*W16 -> 0 | Y16: =Q16 -> 0 | Z16: =+Y16*R16 -> 0 | AA16: EUR | AB16: =IFERROR(VLOOKUP(AA16,Curr!$B$2:$C$13,2,FALSE),0) -> 11.2 | AC16: =+Y16*AB16*R16 -> 0 | AD16: =+AC16-X16 -> 0 | AE16: =IFERROR(AD16/AC16,0) -> 0
S17: =+Q17*R17 -> 0 | T17: 0 | U17: =S17*(1-T17) -> 0 | V17: EUR | W17: =IFERROR(VLOOKUP(V17,Curr!$B$2:$C$13,2,FALSE),0) -> 11.2 | X17: =U17*W17 -> 0 | Y17: =Q17 -> 0 | Z17: =+Y17*R17 -> 0 | AA17: EUR | AB17: =IFERROR(VLOOKUP(AA17,Curr!$B$2:$C$13,2,FALSE),0) -> 11.2 | AC17: =+Y17*AB17*R17 -> 0 | AD17: =+AC17-X17 -> 0 | AE17: =IFERROR(AD17/AC17,0) -> 0
C18: Day 3 | D18: Activity | J18: Bergen: 2 hr walk Through Bergen Past & Present - Time: 10:00 am - 12:00 pm - Meeting point: Bradbenken 1 - Includes: Profesional Guide | O18: x | P18: https://www.ilovebergen.net/tour/a-walk-through-bergen-past-present/ | Q18: 290 | R18: 2 | S18: =+Q18*R18 -> 580 | T18: 0.2 | U18: =S18*(1-T18) -> 464 | V18: NOK | W18: =IFERROR(VLOOKUP(V18,Curr!$B$2:$C$13,2,FALSE),0) -> 1 | X18: =U18*W18 -> 464 | Y18: =Q18/11.3/0.64 -> 40.099558 | Z18: =+Y18*R18 -> 80.199115 | AA18: EUR | AB18: =IFERROR(VLOOKUP(AA18,Curr!$B$2:$C$13,2,FALSE),0) -> 11.2 | AC18: =+Y18*AB18*R18 -> 898.23009 | AD18: =+AC18-X18 -> 434.23009 | AE18: =IFERROR(AD18/AC18,0) -> 0.48342857
C19: Day 3 | D19: Activity | J19: Bergen: Fløibanen Funicual - Time: Flexible - Meeting point: Vetrlidsallmenningen 23A - Includes: Tickets | O19: x | P19: https://www.floyen.no/en/floibanen/buy-tickets/ | Q19: 175 | R19: 2 | S19: =+Q19*R19 -> 350 | T19: 0 | U19: =S19*(1-T19) -> 350 | V19: NOK | W19: =IFERROR(VLOOKUP(V19,Curr!$B$2:$C$13,2,FALSE),0) -> 1 | X19: =U19*W19 -> 350 | Y19: =Q19/11.3/0.5 -> 30.973451 | Z19: =+Y19*R19 -> 61.946903 | AA19: EUR | AB19: =IFERROR(VLOOKUP(AA19,Curr!$B$2:$C$13,2,FALSE),0) -> 11.2 | AC19: =+Y19*AB19*R19 -> 693.80531 | AD19: =+AC19-X19 -> 343.80531 | AE19: =IFERROR(AD19/AC19,0) -> 0.49553571
C20: Day 3 | D20: Leisure | J20: Bergen: Spend time at leisure | Q20: 0 | R20: 0 | S20: =+Q20*R20 -> 0 | T20: 0 | U20: =S20*(1-T20) -> 0 | V20: EUR | W20: =IFERROR(VLOOKUP(V20,Curr!$B$2:$C$13,2,FALSE),0) -> 11.2 | X20: =U20*W20 -> 0 | Y20: =Q20 -> 0 | Z20: =+Y20*R20 -> 0 | AA20: EUR | AB20: =IFERROR(VLOOKUP(AA20,Curr!$B$2:$C$13,2,FALSE),0) -> 11.2 | AC20: =+Y20*AB20*R20 -> 0 | AD20: =+AC20-X20 -> 0 | AE20: =IFERROR(AD20/AC20,0) -> 0
S21: =+Q21*R21 -> 0 | T21: 0 | U21: =S21*(1-T21) -> 0 | V21: EUR | W21: =IFERROR(VLOOKUP(V21,Curr!$B$2:$C$13,2,FALSE),0) -> 11.2 | X21: =U21*W21 -> 0 | Y21: =Q21 -> 0 | Z21: =+Y21*R21 -> 0 | AA21: EUR | AB21: =IFERROR(VLOOKUP(AA21,Curr!$B$2:$C$13,2,FALSE),0) -> 11.2 | AC21: =+Y21*AB21*R21 -> 0 | AD21: =+AC21-X21 -> 0 | AE21: =IFERROR(AD21/AC21,0) -> 0
C22: Day 4 | D22: Transfer | J22: Bergen: Self transfer to Bergen Airport | Q22: 0 | R22: 0 | S22: =+Q22*R22 -> 0 | T22: 0 | U22: =S22*(1-T22) -> 0 | V22: EUR | W22: =IFERROR(VLOOKUP(V22,Curr!$B$2:$C$13,2,FALSE),0) -> 11.2 | X22: =U22*W22 -> 0 | Y22: =Q22 -> 0 | Z22: =+Y22*R22 -> 0 | AA22: EUR | AB22: =IFERROR(VLOOKUP(AA22,Curr!$B$2:$C$13,2,FALSE),0) -> 11.2 | AC22: =+Y22*AB22*R22 -> 0 | AD22: =+AC22-X22 -> 0 | AE22: =IFERROR(AD22/AC22,0) -> 0
C23: Day 4 | D23: Flight | J23: Bergen: Flight to Tromsø - Time: Date dependant - Luggage included: 1 x 23 kg check in and 1 x 8 kg carry on per person | O23: x | Q23: 1800 | R23: 2 | S23: =+Q23*R23 -> 3600 | T23: 0 | U23: =S23*(1-T23) -> 3600 | V23: NOK | W23: =IFERROR(VLOOKUP(V23,Curr!$B$2:$C$13,2,FALSE),0) -> 1 | X23: =U23*W23 -> 3600 | Y23: =Q23/11.3/0.8 -> 199.11504 | Z23: =+Y23*R23 -> 398.23009 | AA23: EUR | AB23: =IFERROR(VLOOKUP(AA23,Curr!$B$2:$C$13,2,FALSE),0) -> 11.2 | AC23: =+Y23*AB23*R23 -> 4460.177 | AD23: =+AC23-X23 -> 860.17699 | AE23: =IFERROR(AD23/AC23,0) -> 0.19285714
C24: Day 4 | D24: Transfer | J24: Tromsø: Self transfer to your accommodation | Q24: 0 | R24: 0 | S24: =+Q24*R24 -> 0 | T24: 0 | U24: =S24*(1-T24) -> 0 | V24: NOK | W24: =IFERROR(VLOOKUP(V24,Curr!$B$2:$C$13,2,FALSE),0) -> 1 | X24: =U24*W24 -> 0 | Y24: =Q24/11.3/0.8 -> 0 | Z24: =+Y24*R24 -> 0 | AA24: EUR | AB24: =IFERROR(VLOOKUP(AA24,Curr!$B$2:$C$13,2,FALSE),0) -> 11.2 | AC24: =+Y24*AB24*R24 -> 0 | AD24: =+AC24-X24 -> 0 | AE24: =IFERROR(AD24/AC24,0) -> 0
C25: Day 4 | D25: Hotel | J25: Tromsø: Check in to your accommodation for a 2 night stay - Centrally located 3/4-star hotel - Standard Room - Breakfast included | Q25: 500 | R25: 1 | S25: =+Q25*R25 -> 500 | T25: 0 | U25: =S25*(1-T25) -> 500 | V25: EUR | W25: =IFERROR(VLOOKUP(V25,Curr!$B$2:$C$13,2,FALSE),0) -> 11.2 | X25: =U25*W25 -> 5600 | Y25: =Q25/0.85 -> 588.23529 | Z25: =+Y25*R25 -> 588.23529 | AA25: EUR | AB25: =IFERROR(VLOOKUP(AA25,Curr!$B$2:$C$13,2,FALSE),0) -> 11.2 | AC25: =+Y25*AB25*R25 -> 6588.2353 | AD25: =+AC25-X25 -> 988.23529 | AE25: =IFERROR(AD25/AC25,0) -> 0.15
C26: Day 4 | D26: Leisure | J26: Tromsø: Spend time at leisure | Q26: 0 | R26: 0 | S26: =+Q26*R26 -> 0 | T26: 0 | U26: =S26*(1-T26) -> 0 | V26: EUR | W26: =IFERROR(VLOOKUP(V26,Curr!$B$2:$C$13,2,FALSE),0) -> 11.2 | X26: =U26*W26 -> 0 | Y26: =Q26 -> 0 | Z26: =+Y26*R26 -> 0 | AA26: EUR | AB26: =IFERROR(VLOOKUP(AA26,Curr!$B$2:$C$13,2,FALSE),0) -> 11.2 | AC26: =+Y26*AB26*R26 -> 0 | AD26: =+AC26-X26 -> 0 | AE26: =IFERROR(AD26/AC26,0) -> 0
C27: Day 4 | D27: Activity | J27: Tromsø: Northern Lights Cruise with Silent Electric Ship - Time: 7:00 pm - 10:00 pm - Meeting point: Kaigata 6 - Includes: Departure from central Tromsø, 3-hour fjord cruise, Light meal (soup and bread) and water, English speaking guides, Warm indoor saloons, Free wifi, Toilets | O27: x | P27: https://booknordics.com/norway/northern-norway/tromso-region/northern-lights-cruise-electric-ship | Q27: 105 | R27: 2 | S27: =+Q27*R27 -> 210 | T27: 0.2 | U27: =S27*(1-T27) -> 168 | V27: EUR | W27: =IFERROR(VLOOKUP(V27,Curr!$B$2:$C$13,2,FALSE),0) -> 11.2 | X27: =U27*W27 -> 1881.6 | Y27: =Q27 -> 105 | Z27: =+Y27*R27 -> 210 | AA27: EUR | AB27: =IFERROR(VLOOKUP(AA27,Curr!$B$2:$C$13,2,FALSE),0) -> 11.2 | AC27: =+Y27*AB27*R27 -> 2352 | AD27: =+AC27-X27 -> 470.4 | AE27: =IFERROR(AD27/AC27,0) -> 0.2
S28: =+Q28*R28 -> 0 | T28: 0 | U28: =S28*(1-T28) -> 0 | V28: EUR | W28: =IFERROR(VLOOKUP(V28,Curr!$B$2:$C$13,2,FALSE),0) -> 11.2 | X28: =U28*W28 -> 0 | Y28: =Q28 -> 0 | Z28: =+Y28*R28 -> 0 | AA28: EUR | AB28: =IFERROR(VLOOKUP(AA28,Curr!$B$2:$C$13,2,FALSE),0) -> 11.2 | AC28: =+Y28*AB28*R28 -> 0 | AD28: =+AC28-X28 -> 0 | AE28: =IFERROR(AD28/AC28,0) -> 0
C29: Day 5 | D29: Activity | J29: Tromsø: Reindeer Feeding and Sámi Culture - Time: 09:45 am - 2:30 pm - Meeting point: Radisson Blu Hotel's main entrance (Sjøgata 7) - Includes: Scenic transfers (45 min each way), Knowledgeable English and Norwegian speaking guide, Feeding the herd at our camp, Hot beverages and hot meal (traditional Sámi stew or vegetable/lentil soup), Cultural introduction about Sámi history and daily life, A chance to see the northern lights from our camp, Thermal suit and warm snow boots | O29: x | P29: https://www.tromsolapland.no/activities/reindeer-feeding-and-sami-culture | Q29: 1695 | R29: 2 | S29: =+Q29*R29 -> 3390 | T29: 0.2 | U29: =S29*(1-T29) -> 2712 | V29: NOK | W29: =IFERROR(VLOOKUP(V29,Curr!$B$2:$C$13,2,FALSE),0) -> 1 | X29: =U29*W29 -> 2712 | Y29: =Q29/11.3 -> 150 | Z29: =+Y29*R29 -> 300 | AA29: EUR | AB29: =IFERROR(VLOOKUP(AA29,Curr!$B$2:$C$13,2,FALSE),0) -> 11.2 | AC29: =+Y29*AB29*R29 -> 3360 | AD29: =+AC29-X29 -> 648 | AE29: =IFERROR(AD29/AC29,0) -> 0.19285714
C30: Day 5 | D30: Leisure | J30: Tromsø: Spend time at leisure | Q30: 0 | R30: 0 | S30: =+Q30*R30 -> 0 | T30: 0 | U30: =S30*(1-T30) -> 0 | V30: EUR | W30: =IFERROR(VLOOKUP(V30,Curr!$B$2:$C$13,2,FALSE),0) -> 11.2 | X30: =U30*W30 -> 0 | Y30: =Q30 -> 0 | Z30: =+Y30*R30 -> 0 | AA30: EUR | AB30: =IFERROR(VLOOKUP(AA30,Curr!$B$2:$C$13,2,FALSE),0) -> 11.2 | AC30: =+Y30*AB30*R30 -> 0 | AD30: =+AC30-X30 -> 0 | AE30: =IFERROR(AD30/AC30,0) -> 0
C31: Day 5 | D31: Activity | J31: Tromsø: All-Evening Northern Lights Hunt by Minibus or Bus - Time: 7:00 pm - 12:00 am - Meeting point: Kaigata 4 - Includes: Knowledgeable, English-speaking guides, Photos shared with you after the tour, Thermo clothing and warm gear, Light snacks and warm/cold beverages, Drop-off at hotel, up to 5 km from Tromsø | O31: x | P31: https://booknordics.com/norway/northern-norway/tromso-region/full-day-magic-of-the-arctic-lights-in-tromso | Q31: 120 | R31: 2 | S31: =+Q31*R31 -> 240 | T31: 0.2 | U31: =S31*(1-T31) -> 192 | V31: EUR | W31: =IFERROR(VLOOKUP(V31,Curr!$B$2:$C$13,2,FALSE),0) -> 11.2 | X31: =U31*W31 -> 2150.4 | Y31: =Q31 -> 120 | Z31: =+Y31*R31 -> 240 | AA31: EUR | AB31: =IFERROR(VLOOKUP(AA31,Curr!$B$2:$C$13,2,FALSE),0) -> 11.2 | AC31: =+Y31*AB31*R31 -> 2688 | AD31: =+AC31-X31 -> 537.6 | AE31: =IFERROR(AD31/AC31,0) -> 0.2
S32: =+Q32*R32 -> 0 | T32: 0 | U32: =S32*(1-T32) -> 0 | V32: EUR | W32: =IFERROR(VLOOKUP(V32,Curr!$B$2:$C$13,2,FALSE),0) -> 11.2 | X32: =U32*W32 -> 0 | Y32: =Q32 -> 0 | Z32: =+Y32*R32 -> 0 | AA32: EUR | AB32: =IFERROR(VLOOKUP(AA32,Curr!$B$2:$C$13,2,FALSE),0) -> 11.2 | AC32: =+Y32*AB32*R32 -> 0 | AD32: =+AC32-X32 -> 0 | AE32: =IFERROR(AD32/AC32,0) -> 0
C33: Day 6 | D33: Transfer | J33: Tromsø: Self transfer to Scandic Ishavs Hotel | Q33: 0 | R33: 0 | S33: =+Q33*R33 -> 0 | T33: 0 | U33: =S33*(1-T33) -> 0 | V33: EUR | W33: =IFERROR(VLOOKUP(V33,Curr!$B$2:$C$13,2,FALSE),0) -> 11.2 | X33: =U33*W33 -> 0 | Y33: =Q33 -> 0 | Z33: =+Y33*R33 -> 0 | AA33: EUR | AB33: =IFERROR(VLOOKUP(AA33,Curr!$B$2:$C$13,2,FALSE),0) -> 11.2 | AC33: =+Y33*AB33*R33 -> 0 | AD33: =+AC33-X33 -> 0 | AE33: =IFERROR(AD33/AC33,0) -> 0
C34: Day 6 | D34: Activity | J34: Tromsø: Crystal Lavvo Stay with Auroras, Meals & Activities - Time: 11:30 am - 10: 50 am (the next day) - Meeting point: Samuel Arnesens gate 5 - Includes: Pick-up/drop-off in Tromsø with scenic transfers, Comfortable overnight stay in crystal lavvo, Fireplace heating with unlimited firewood, Northern Lights hunt with photo workshop, Snowshoeing experience nearby, Lunch and dinner included on day 1, Bathroom/toilet facilities in the main house, Breakfast and return transfer included on day 2 | O34: x | P34: https://booknordics.com/norway/northern-norway/tromso-region/crystal-lavvy-stay-northern-lights-snowshoeing | Q34: 375 | R34: 2 | S34: =+Q34*R34 -> 750 | T34: 0.2 | U34: =S34*(1-T34) -> 600 | V34: EUR | W34: =IFERROR(VLOOKUP(V34,Curr!$B$2:$C$13,2,FALSE),0) -> 11.2 | X34: =U34*W34 -> 6720 | Y34: =Q34 -> 375 | Z34: =+Y34*R34 -> 750 | AA34: EUR | AB34: =IFERROR(VLOOKUP(AA34,Curr!$B$2:$C$13,2,FALSE),0) -> 11.2 | AC34: =+Y34*AB34*R34 -> 8400 | AD34: =+AC34-X34 -> 1680 | AE34: =IFERROR(AD34/AC34,0) -> 0.2
S35: =+Q35*R35 -> 0 | T35: 0 | U35: =S35*(1-T35) -> 0 | V35: EUR | W35: =IFERROR(VLOOKUP(V35,Curr!$B$2:$C$13,2,FALSE),0) -> 11.2 | X35: =U35*W35 -> 0 | Y35: =Q35 -> 0 | Z35: =+Y35*R35 -> 0 | AA35: EUR | AB35: =IFERROR(VLOOKUP(AA35,Curr!$B$2:$C$13,2,FALSE),0) -> 11.2 | AC35: =+Y35*AB35*R35 -> 0 | AD35: =+AC35-X35 -> 0 | AE35: =IFERROR(AD35/AC35,0) -> 0
C36: Day 7 | D36: Transfer | J36: Lyngen: Included transfer back to Central Tromsø | Q36: 0 | R36: 0 | S36: =+Q36*R36 -> 0 | T36: 0 | U36: =S36*(1-T36) -> 0 | V36: EUR | W36: =IFERROR(VLOOKUP(V36,Curr!$B$2:$C$13,2,FALSE),0) -> 11.2 | X36: =U36*W36 -> 0 | Y36: =Q36 -> 0 | Z36: =+Y36*R36 -> 0 | AA36: EUR | AB36: =IFERROR(VLOOKUP(AA36,Curr!$B$2:$C$13,2,FALSE),0) -> 11.2 | AC36: =+Y36*AB36*R36 -> 0 | AD36: =+AC36-X36 -> 0 | AE36: =IFERROR(AD36/AC36,0) -> 0
C37: Day 7 | D37: Transfer | J37: Tromsø: Check in to your accommodation for a 1 night stay - Centrally located 3/4-star hotel - Standard Room - Breakfast included | Q37: 250 | R37: 1 | S37: =+Q37*R37 -> 250 | T37: 0 | U37: =S37*(1-T37) -> 250 | V37: EUR | W37: =IFERROR(VLOOKUP(V37,Curr!$B$2:$C$13,2,FALSE),0) -> 11.2 | X37: =U37*W37 -> 2800 | Y37: =Q37/0.85 -> 294.11765 | Z37: =+Y37*R37 -> 294.11765 | AA37: EUR | AB37: =IFERROR(VLOOKUP(AA37,Curr!$B$2:$C$13,2,FALSE),0) -> 11.2 | AC37: =+Y37*AB37*R37 -> 3294.1176 | AD37: =+AC37-X37 -> 494.11765 | AE37: =IFERROR(AD37/AC37,0) -> 0.15
C38: Day 7 | D38: Leisure | J38: Tromsø: Spend time at leisure | Q38: 0 | R38: 0 | S38: =+Q38*R38 -> 0 | T38: 0 | U38: =S38*(1-T38) -> 0 | V38: EUR | W38: =IFERROR(VLOOKUP(V38,Curr!$B$2:$C$13,2,FALSE),0) -> 11.2 | X38: =U38*W38 -> 0 | Y38: =Q38 -> 0 | Z38: =+Y38*R38 -> 0 | AA38: EUR | AB38: =IFERROR(VLOOKUP(AA38,Curr!$B$2:$C$13,2,FALSE),0) -> 11.2 | AC38: =+Y38*AB38*R38 -> 0 | AD38: =+AC38-X38 -> 0 | AE38: =IFERROR(AD38/AC38,0) -> 0
S39: =+Q39*R39 -> 0 | T39: 0 | U39: =S39*(1-T39) -> 0 | V39: EUR | W39: =IFERROR(VLOOKUP(V39,Curr!$B$2:$C$13,2,FALSE),0) -> 11.2 | X39: =U39*W39 -> 0 | Y39: =Q39 -> 0 | Z39: =+Y39*R39 -> 0 | AA39: EUR | AB39: =IFERROR(VLOOKUP(AA39,Curr!$B$2:$C$13,2,FALSE),0) -> 11.2 | AC39: =+Y39*AB39*R39 -> 0 | AD39: =+AC39-X39 -> 0 | AE39: =IFERROR(AD39/AC39,0) -> 0
C40: Day 8 | D40: Transfer | J40: Tromsø: Self transfer to Tromsø Airport | Q40: 0 | R40: 0 | S40: =+Q40*R40 -> 0 | T40: 0 | U40: =S40*(1-T40) -> 0 | V40: NOK | W40: =IFERROR(VLOOKUP(V40,Curr!$B$2:$C$13,2,FALSE),0) -> 1 | X40: =U40*W40 -> 0 | Y40: =Q40/11.3/0.8 -> 0 | Z40: =+Y40*R40 -> 0 | AA40: EUR | AB40: =IFERROR(VLOOKUP(AA40,Curr!$B$2:$C$13,2,FALSE),0) -> 11.2 | AC40: =+Y40*AB40*R40 -> 0 | AD40: =+AC40-X40 -> 0 | AE40: =IFERROR(AD40/AC40,0) -> 0
C41: Day 8 | D41: Departure | J41: Tromsø: Departure home | Q41: 0 | R41: 0 | S41: =+Q41*R41 -> 0 | T41: 0 | U41: =S41*(1-T41) -> 0 | V41: EUR | W41: =IFERROR(VLOOKUP(V41,Curr!$B$2:$C$13,2,FALSE),0) -> 11.2 | X41: =U41*W41 -> 0 | Y41: =Q41 -> 0 | Z41: =+Y41*R41 -> 0 | AA41: EUR | AB41: =IFERROR(VLOOKUP(AA41,Curr!$B$2:$C$13,2,FALSE),0) -> 11.2 | AC41: =+Y41*AB41*R41 -> 0 | AD41: =+AC41-X41 -> 0 | AE41: =IFERROR(AD41/AC41,0) -> 0
S42: =+Q42*R42 -> 0 | T42: 0 | U42: =S42*(1-T42) -> 0 | V42: EUR | W42: =IFERROR(VLOOKUP(V42,Curr!$B$2:$C$13,2,FALSE),0) -> 11.2 | X42: =U42*W42 -> 0 | Y42: =Q42 -> 0 | Z42: =+Y42*R42 -> 0 | AA42: EUR | AB42: =IFERROR(VLOOKUP(AA42,Curr!$B$2:$C$13,2,FALSE),0) -> 11.2 | AC42: =+Y42*AB42*R42 -> 0 | AD42: =+AC42-X42 -> 0 | AE42: =IFERROR(AD42/AC42,0) -> 0
S43: =+Q43*R43 -> 0 | T43: 0 | U43: =S43*(1-T43) -> 0 | V43: EUR | W43: =IFERROR(VLOOKUP(V43,Curr!$B$2:$C$13,2,FALSE),0) -> 11.2 | X43: =U43*W43 -> 0 | Y43: =Q43 -> 0 | Z43: =+Y43*R43 -> 0 | AA43: EUR | AB43: =IFERROR(VLOOKUP(AA43,Curr!$B$2:$C$13,2,FALSE),0) -> 11.2 | AC43: =+Y43*AB43*R43 -> 0 | AD43: =+AC43-X43 -> 0 | AE43: =IFERROR(AD43/AC43,0) -> 0
C44: Day 1 | D44: Transfer Package | J44: Oslo: Private transfer to your accommodation | Q44: 1750 | R44: 0 | S44: =+Q44*R44 -> 0 | T44: 0 | U44: =S44*(1-T44) -> 0 | V44: NOK | W44: =IFERROR(VLOOKUP(V44,Curr!$B$2:$C$13,2,FALSE),0) -> 1 | X44: =U44*W44 -> 0 | Y44: =Q44/11.3/0.8 -> 193.58407 | Z44: =+Y44*R44 -> 0 | AA44: EUR | AB44: =IFERROR(VLOOKUP(AA44,Curr!$B$2:$C$13,2,FALSE),0) -> 11.2 | AC44: =+Y44*AB44*R44 -> 0 | AD44: =+AC44-X44 -> 0 | AE44: =IFERROR(AD44/AC44,0) -> 0
C45: Day 2 | D45: Transfer Package | J45: Bergen: Private transfer to your accommodation | Q45: 1290 | R45: 0 | S45: =+Q45*R45 -> 0 | T45: 0.15 | U45: =S45*(1-T45) -> 0 | V45: NOK | W45: =IFERROR(VLOOKUP(V45,Curr!$B$2:$C$13,2,FALSE),0) -> 1 | X45: =U45*W45 -> 0 | Y45: =Q45/11.3/0.98 -> 116.48907 | Z45: =+Y45*R45 -> 0 | AA45: EUR | AB45: =IFERROR(VLOOKUP(AA45,Curr!$B$2:$C$13,2,FALSE),0) -> 11.2 | AC45: =+Y45*AB45*R45 -> 0 | AD45: =+AC45-X45 -> 0 | AE45: =IFERROR(AD45/AC45,0) -> 0
C46: Day 4 | D46: Transfer Package | J46: Bergen: Private transfer to Bergen Airport | Q46: 1690 | R46: 0 | S46: =+Q46*R46 -> 0 | T46: 0.15 | U46: =S46*(1-T46) -> 0 | V46: NOK | W46: =IFERROR(VLOOKUP(V46,Curr!$B$2:$C$13,2,FALSE),0) -> 1 | X46: =U46*W46 -> 0 | Y46: =Q46/11.3/0.98 -> 152.60972 | Z46: =+Y46*R46 -> 0 | AA46: EUR | AB46: =IFERROR(VLOOKUP(AA46,Curr!$B$2:$C$13,2,FALSE),0) -> 11.2 | AC46: =+Y46*AB46*R46 -> 0 | AD46: =+AC46-X46 -> 0 | AE46: =IFERROR(AD46/AC46,0) -> 0
C47: Day 4 | D47: Transfer Package | J47: Tromsø: Private transfer to your accommodation | Q47: 900 | R47: 0 | S47: =+Q47*R47 -> 0 | T47: 0 | U47: =S47*(1-T47) -> 0 | V47: NOK | W47: =IFERROR(VLOOKUP(V47,Curr!$B$2:$C$13,2,FALSE),0) -> 1 | X47: =U47*W47 -> 0 | Y47: =Q47/11.3/0.8 -> 99.557522 | Z47: =+Y47*R47 -> 0 | AA47: EUR | AB47: =IFERROR(VLOOKUP(AA47,Curr!$B$2:$C$13,2,FALSE),0) -> 11.2 | AC47: =+Y47*AB47*R47 -> 0 | AD47: =+AC47-X47 -> 0 | AE47: =IFERROR(AD47/AC47,0) -> 0
C48: Day 8 | D48: Transfer Package | J48: Tromsø: Private transfer to Tromsø Airport | Q48: 900 | R48: 0 | S48: =+Q48*R48 -> 0 | T48: 0 | U48: =S48*(1-T48) -> 0 | V48: NOK | W48: =IFERROR(VLOOKUP(V48,Curr!$B$2:$C$13,2,FALSE),0) -> 1 | X48: =U48*W48 -> 0 | Y48: =Q48/11.3/0.8 -> 99.557522 | Z48: =+Y48*R48 -> 0 | AA48: EUR | AB48: =IFERROR(VLOOKUP(AA48,Curr!$B$2:$C$13,2,FALSE),0) -> 11.2 | AC48: =+Y48*AB48*R48 -> 0 | AD48: =+AC48-X48 -> 0 | AE48: =IFERROR(AD48/AC48,0) -> 0
S49: =+Q49*R49 -> 0 | T49: 0 | U49: =S49*(1-T49) -> 0 | V49: EUR | W49: =IFERROR(VLOOKUP(V49,Curr!$B$2:$C$13,2,FALSE),0) -> 11.2 | X49: =U49*W49 -> 0 | Y49: =Q49 -> 0 | Z49: =+Y49*R49 -> 0 | AA49: EUR | AB49: =IFERROR(VLOOKUP(AA49,Curr!$B$2:$C$13,2,FALSE),0) -> 11.2 | AC49: =+Y49*AB49*R49 -> 0 | AD49: =+AC49-X49 -> 0 | AE49: =IFERROR(AD49/AC49,0) -> 0
S50: =+Q50*R50 -> 0 | T50: 0 | U50: =S50*(1-T50) -> 0 | V50: EUR | W50: =IFERROR(VLOOKUP(V50,Curr!$B$2:$C$13,2,FALSE),0) -> 11.2 | X50: =U50*W50 -> 0 | Y50: =Q50 -> 0 | Z50: =+Y50*R50 -> 0 | AA50: EUR | AB50: =IFERROR(VLOOKUP(AA50,Curr!$B$2:$C$13,2,FALSE),0) -> 11.2 | AC50: =+Y50*AB50*R50 -> 0 | AD50: =+AC50-X50 -> 0 | AE50: =IFERROR(AD50/AC50,0) -> 0
C51: Day 2 | D51: Activity Upgrade | J51: Oslo: Norway in a Nutshell to Bergen - Time: 08:00 am - 09:00 pm - Meeting point. Oslo Central Station - Includes: Train transfer Oslo to Myrdal, Train tranfser Myrdal to Flåm, Fjord Cruise Flåm to Gudvangen, Coach Transfer Gudvangen to Voss, Train transfer Voss to Bergen | O51: x | P51: https://www.fjordtours.com/en | Q51: 3250 | R51: 0 | S51: =+Q51*R51 -> 0 | T51: 0.08 | U51: =S51*(1-T51) -> 0 | V51: NOK | W51: =IFERROR(VLOOKUP(V51,Curr!$B$2:$C$13,2,FALSE),0) -> 1 | X51: =U51*W51 -> 0 | Y51: =Q51/11.3/0.9 -> 319.56735 | Z51: =+Y51*R51 -> 0 | AA51: EUR | AB51: =IFERROR(VLOOKUP(AA51,Curr!$B$2:$C$13,2,FALSE),0) -> 11.2 | AC51: =+Y51*AB51*R51 -> 0 | AD51: =+AC51-X51 -> 0 | AE51: =IFERROR(AD51/AC51,0) -> 0
C52: Day 2 | D52: Activity Upgrade | J52: Oslo: Norway in a Nutshell Porter Service - Includes: Luggage transfer from your accommodation in Oslo to your accommodaiton in Bergen | Q52: 450 | R52: 0 | S52: =+Q52*R52 -> 0 | T52: 0 | U52: =S52*(1-T52) -> 0 | V52: NOK | W52: =IFERROR(VLOOKUP(V52,Curr!$B$2:$C$13,2,FALSE),0) -> 1 | X52: =U52*W52 -> 0 | Y52: =Q52/11.3/0.8 -> 49.778761 | Z52: =+Y52*R52 -> 0 | AA52: EUR | AB52: =IFERROR(VLOOKUP(AA52,Curr!$B$2:$C$13,2,FALSE),0) -> 11.2 | AC52: =+Y52*AB52*R52 -> 0 | AD52: =+AC52-X52 -> 0 | AE52: =IFERROR(AD52/AC52,0) -> 0
C53: Day 3 | D53: Activity Upgrade | J53: Bergen: Mostraumen Majestic Fjord & Waterfall Cruise - Time: 12:00 pm - 4:00 pm - Meeting point: Strandkaien 13 - Includes: 4-hour panoramic fjord cruise, Expert captain navigating through the fjords, English-audio guide | O53: x | P53: https://booknordics.com/norway/western-fjord-norway/bergen-and-hardanger/mostraumen-fjord-waterfall-cruise | Q53: 71 | R53: 0 | S53: =+Q53*R53 -> 0 | T53: 0.2 | U53: =S53*(1-T53) -> 0 | V53: EUR | W53: =IFERROR(VLOOKUP(V53,Curr!$B$2:$C$13,2,FALSE),0) -> 11.2 | X53: =U53*W53 -> 0 | Y53: =Q53 -> 71 | Z53: =+Y53*R53 -> 0 | AA53: EUR | AB53: =IFERROR(VLOOKUP(AA53,Curr!$B$2:$C$13,2,FALSE),0) -> 11.2 | AC53: =+Y53*AB53*R53 -> 0 | AD53: =+AC53-X53 -> 0 | AE53: =IFERROR(AD53/AC53,0) -> 0
C54: Day 5 | D54: Activity Upgrade | J54: Tromsø: Reindeer Sledding, Reindeer Feeding and Sami Culture - Time: 09:45 am - 2:30 pm - Meeting point: Radisson Blu Hotel's main entrance (Sjøgata 7) - Includes: Scenic transfers (45 min each way), Knowledgeable English- and Norwegian-speaking guide, Thermal winter suit, warm boots, Reindeer sledding (approx. 30 min, depending on weather and snow conditions), Feeding the herd on our camp, Hot traditional Sámi meal (bithos) and hot drinks. Vegetarian option available on request, Cultural introduction about Sámi history and daily life | O54: x | P54: https://booknordics.com/norway/northern-norway/tromso-region/reindeer-sledding-reindeer-feeding-and-sami-culture-3 | Q54: 2195 | R54: 0 | S54: =+Q54*R54 -> 0 | T54: 0.2 | U54: =S54*(1-T54) -> 0 | V54: NOK | W54: =IFERROR(VLOOKUP(V54,Curr!$B$2:$C$13,2,FALSE),0) -> 1 | X54: =U54*W54 -> 0 | Y54: =Q54/11.3 -> 194.24779 | Z54: =+Y54*R54 -> 0 | AA54: EUR | AB54: =IFERROR(VLOOKUP(AA54,Curr!$B$2:$C$13,2,FALSE),0) -> 11.2 | AC54: =+Y54*AB54*R54 -> 0 | AD54: =+AC54-X54 -> 0 | AE54: =IFERROR(AD54/AC54,0) -> 0
C55: Day 7 | D55: Activity Upgrade | J55: Tromsø: Midnight Concert in Tromsø Cathedral - Time: 10:45 pm - 11:45 pm - Meeteing point: Tromsø Cathedral - Includes: Admission to Tromsø Cathedral (Northern Europe's largest wooden cathedral), Evening concert with professional musicians (30 minutes) | O55: x | P55: https://booknordics.com/norway/northern-norway/tromso-region/midnight-concert-in-tromso-cathedral | Q55: 25 | R55: 0 | S55: =+Q55*R55 -> 0 | T55: 0.2 | U55: =S55*(1-T55) -> 0 | V55: EUR | W55: =IFERROR(VLOOKUP(V55,Curr!$B$2:$C$13,2,FALSE),0) -> 11.2 | X55: =U55*W55 -> 0 | Y55: =Q55 -> 25 | Z55: =+Y55*R55 -> 0 | AA55: EUR | AB55: =IFERROR(VLOOKUP(AA55,Curr!$B$2:$C$13,2,FALSE),0) -> 11.2 | AC55: =+Y55*AB55*R55 -> 0 | AD55: =+AC55-X55 -> 0 | AE55: =IFERROR(AD55/AC55,0) -> 0
C56: Day 7 | D56: Activity Upgrade | J56: Tromsø: Magic Ice Bar - Time: Flexible - Meeting point: Kaigata 4 - Includes: Entry to the ice bar & gallery, Gloves and winter poncho, Our signature drink | O56: x | P56: https://booknordics.com/norway/northern-norway/tromso-region/tromso-norway | Q56: 30 | R56: 0 | S56: =+Q56*R56 -> 0 | T56: 0.2 | U56: =S56*(1-T56) -> 0 | V56: EUR | W56: =IFERROR(VLOOKUP(V56,Curr!$B$2:$C$13,2,FALSE),0) -> 11.2 | X56: =U56*W56 -> 0 | Y56: =Q56 -> 30 | Z56: =+Y56*R56 -> 0 | AA56: EUR | AB56: =IFERROR(VLOOKUP(AA56,Curr!$B$2:$C$13,2,FALSE),0) -> 11.2 | AC56: =+Y56*AB56*R56 -> 0 | AD56: =+AC56-X56 -> 0 | AE56: =IFERROR(AD56/AC56,0) -> 0
S57: =+Q57*R57 -> 0 | T57: 0 | U57: =S57*(1-T57) -> 0 | V57: EUR | W57: =IFERROR(VLOOKUP(V57,Curr!$B$2:$C$13,2,FALSE),0) -> 11.2 | X57: =U57*W57 -> 0 | Y57: =Q57 -> 0 | Z57: =+Y57*R57 -> 0 | AA57: EUR | AB57: =IFERROR(VLOOKUP(AA57,Curr!$B$2:$C$13,2,FALSE),0) -> 11.2 | AC57: =+Y57*AB57*R57 -> 0 | AD57: =+AC57-X57 -> 0 | AE57: =IFERROR(AD57/AC57,0) -> 0
S58: =+Q58*R58 -> 0 | T58: 0 | U58: =S58*(1-T58) -> 0 | V58: EUR | W58: =IFERROR(VLOOKUP(V58,Curr!$B$2:$C$13,2,FALSE),0) -> 11.2 | X58: =U58*W58 -> 0 | Y58: =Q58 -> 0 | Z58: =+Y58*R58 -> 0 | AA58: EUR | AB58: =IFERROR(VLOOKUP(AA58,Curr!$B$2:$C$13,2,FALSE),0) -> 11.2 | AC58: =+Y58*AB58*R58 -> 0 | AD58: =+AC58-X58 -> 0 | AE58: =IFERROR(AD58/AC58,0) -> 0
S59: =+Q59*R59 -> 0 | T59: 0 | U59: =S59*(1-T59) -> 0 | V59: EUR | W59: =IFERROR(VLOOKUP(V59,Curr!$B$2:$C$13,2,FALSE),0) -> 11.2 | X59: =U59*W59 -> 0 | Y59: =Q59 -> 0 | Z59: =+Y59*R59 -> 0 | AA59: EUR | AB59: =IFERROR(VLOOKUP(AA59,Curr!$B$2:$C$13,2,FALSE),0) -> 11.2 | AC59: =+Y59*AB59*R59 -> 0 | AD59: =+AC59-X59 -> 0 | AE59: =IFERROR(AD59/AC59,0) -> 0
S60: =+Q60*R60 -> 0 | T60: 0 | U60: =S60*(1-T60) -> 0 | V60: EUR | W60: =IFERROR(VLOOKUP(V60,Curr!$B$2:$C$13,2,FALSE),0) -> 11.2 | X60: =U60*W60 -> 0 | Y60: =Q60 -> 0 | Z60: =+Y60*R60 -> 0 | AA60: EUR | AB60: =IFERROR(VLOOKUP(AA60,Curr!$B$2:$C$13,2,FALSE),0) -> 11.2 | AC60: =+Y60*AB60*R60 -> 0 | AD60: =+AC60-X60 -> 0 | AE60: =IFERROR(AD60/AC60,0) -> 0
S61: =+Q61*R61 -> 0 | T61: 0 | U61: =S61*(1-T61) -> 0 | V61: EUR | W61: =IFERROR(VLOOKUP(V61,Curr!$B$2:$C$13,2,FALSE),0) -> 11.2 | X61: =U61*W61 -> 0 | Y61: =Q61 -> 0 | Z61: =+Y61*R61 -> 0 | AA61: EUR | AB61: =IFERROR(VLOOKUP(AA61,Curr!$B$2:$C$13,2,FALSE),0) -> 11.2 | AC61: =+Y61*AB61*R61 -> 0 | AD61: =+AC61-X61 -> 0 | AE61: =IFERROR(AD61/AC61,0) -> 0
S62: =+Q62*R62 -> 0 | T62: 0 | U62: =S62*(1-T62) -> 0 | V62: EUR | W62: =IFERROR(VLOOKUP(V62,Curr!$B$2:$C$13,2,FALSE),0) -> 11.2 | X62: =U62*W62 -> 0 | Y62: =Q62 -> 0 | Z62: =+Y62*R62 -> 0 | AA62: EUR | AB62: =IFERROR(VLOOKUP(AA62,Curr!$B$2:$C$13,2,FALSE),0) -> 11.2 | AC62: =+Y62*AB62*R62 -> 0 | AD62: =+AC62-X62 -> 0 | AE62: =IFERROR(AD62/AC62,0) -> 0
S63: =+Q63*R63 -> 0 | T63: 0 | U63: =S63*(1-T63) -> 0 | V63: EUR | W63: =IFERROR(VLOOKUP(V63,Curr!$B$2:$C$13,2,FALSE),0) -> 11.2 | X63: =U63*W63 -> 0 | Y63: =Q63 -> 0 | Z63: =+Y63*R63 -> 0 | AA63: EUR | AB63: =IFERROR(VLOOKUP(AA63,Curr!$B$2:$C$13,2,FALSE),0) -> 11.2 | AC63: =+Y63*AB63*R63 -> 0 | AD63: =+AC63-X63 -> 0 | AE63: =IFERROR(AD63/AC63,0) -> 0
B65: Totals | D65: x | E65: x | F65: x | G65: x | H65: x | I65: x | J65: x | K65: x | L65: x | M65: x | N65: x | O65: x | P65: x | Q65: x | R65: x | S65: x | T65: x | U65: x | V65: x | W65: x | X65: x | Y65: x | Z65: =SUM(Z7:Z63) -> 3694.0981 | AC65: =SUM(AC7:AC63) -> 41373.899 | AD65: =SUM(AD7:AD63) -> 7879.899 | AE65: =IFERROR(AD65/AC65,0) -> 0.1904558 | AF65: =SUM(AF8:AF64) -> 0 | AG65: =SUM(AG8:AG64) -> 0 | AH65: =SUM(AH8:AH64) -> 0 | AI65: =SUM(AI8:AI64) -> 0 | AJ65: =SUM(AJ8:AJ64) -> 0
Y67: Fixed | Z67: 2040
Y68: Variable | Z68: =Z9+Z15+Z23+Z25+Z37 -> 1786.4654
Y69: Total | Z69: 3720
Y70: PP | Z70: =Z69/2 -> 1860
Z73: Winter
Y74: Shoulder | Z74: =Z69 -> 3720
Y75: High | Z75: =Z74*1.18 -> 4389.6
Y76: Holiday | Z76: =Z74*1.25 -> 4650
Y77: Low | Z77: =Z74*0.85 -> 3162
Y78: Summer | Z78: NA

Sheet 204
B1: Season: Winter
B2: Places: Oslo 1N - Bergen 2N - Tromsø 2N - Lyngen 1N - Alta 2N
B3: Pax: 2
B4: Rooming: Double
B6: ID | C6: Day | D6: Type | E6: From date | F6: To date | G6: From time | H6: To time | I6: Supplier | J6: Travel element | K6: Manual booking? | L6: Status | M6: Comments | N6: Non-refundable | O6: Refundable | P6: URL | Q6: Gross P per unit | R6: Units | S6: Gross P | T6: Supp Comm | U6: Net P | V6: Supp curr | W6: X-rate | X6: Net P NOK | Y6: Sales P per unit | Z6: Price | AA6: Sales curr | AB6: X-rate | AC6: Sales P NOK tot | AD6: GP NOK | AE6: GP % | AF6: VAT25 | AG6: VAT15 | AH6: VAT12 | AI6: VAT0-D | AJ6: VAT0-I
C7: Day 1 | D7: Arrival | J7: Oslo: Welcome to Norway | Q7: 0 | R7: 0 | S7: =+Q7*R7 -> 0 | T7: 0 | U7: =S7*(1-T7) -> 0 | V7: EUR | W7: =IFERROR(VLOOKUP(V7,Curr!$B$2:$C$13,2,FALSE),0) -> 11.2 | X7: =U7*W7 -> 0 | Y7: =Q7 -> 0 | Z7: =+Y7*R7 -> 0 | AA7: EUR | AB7: =IFERROR(VLOOKUP(AA7,Curr!$B$2:$C$13,2,FALSE),0) -> 11.2 | AC7: =+Y7*AB7*R7 -> 0 | AD7: =+AC7-X7 -> 0 | AE7: =IFERROR(AD7/AC7,0) -> 0
C8: Day 1 | D8: Transfer | J8: Oslo: Self transfer to your accommodation | Q8: 0 | R8: 0 | S8: =+Q8*R8 -> 0 | T8: 0 | U8: =S8*(1-T8) -> 0 | V8: NOK | W8: =IFERROR(VLOOKUP(V8,Curr!$B$2:$C$13,2,FALSE),0) -> 1 | X8: =U8*W8 -> 0 | Y8: =Q8/11.3/0.8 -> 0 | Z8: =+Y8*R8 -> 0 | AA8: EUR | AB8: =IFERROR(VLOOKUP(AA8,Curr!$B$2:$C$13,2,FALSE),0) -> 11.2 | AC8: =+Y8*AB8*R8 -> 0 | AD8: =+AC8-X8 -> 0 | AE8: =IFERROR(AD8/AC8,0) -> 0
C9: Day 1 | D9: Hotel | J9: Oslo: Check in to your accommodation for a 1 night stay - Centrally located 3/4-star hotel - Standard Room - Breakfast included | Q9: 150 | R9: 1 | S9: =+Q9*R9 -> 150 | T9: 0 | U9: =S9*(1-T9) -> 150 | V9: EUR | W9: =IFERROR(VLOOKUP(V9,Curr!$B$2:$C$13,2,FALSE),0) -> 11.2 | X9: =U9*W9 -> 1680 | Y9: =Q9/0.85 -> 176.47059 | Z9: =+Y9*R9 -> 176.47059 | AA9: EUR | AB9: =IFERROR(VLOOKUP(AA9,Curr!$B$2:$C$13,2,FALSE),0) -> 11.2 | AC9: =+Y9*AB9*R9 -> 1976.4706 | AD9: =+AC9-X9 -> 296.47059 | AE9: =IFERROR(AD9/AC9,0) -> 0.15
C10: Day 1 | D10: Leisure | J10: Oslo: Spend time at leisure | Q10: 0 | R10: 0 | S10: =+Q10*R10 -> 0 | T10: 0 | U10: =S10*(1-T10) -> 0 | V10: EUR | W10: =IFERROR(VLOOKUP(V10,Curr!$B$2:$C$13,2,FALSE),0) -> 11.2 | X10: =U10*W10 -> 0 | Y10: =Q10 -> 0 | Z10: =+Y10*R10 -> 0 | AA10: EUR | AB10: =IFERROR(VLOOKUP(AA10,Curr!$B$2:$C$13,2,FALSE),0) -> 11.2 | AC10: =+Y10*AB10*R10 -> 0 | AD10: =+AC10-X10 -> 0 | AE10: =IFERROR(AD10/AC10,0) -> 0
S11: =+Q11*R11 -> 0 | T11: 0 | U11: =S11*(1-T11) -> 0 | V11: EUR | W11: =IFERROR(VLOOKUP(V11,Curr!$B$2:$C$13,2,FALSE),0) -> 11.2 | X11: =U11*W11 -> 0 | Y11: =Q11 -> 0 | Z11: =+Y11*R11 -> 0 | AA11: EUR | AB11: =IFERROR(VLOOKUP(AA11,Curr!$B$2:$C$13,2,FALSE),0) -> 11.2 | AC11: =+Y11*AB11*R11 -> 0 | AD11: =+AC11-X11 -> 0 | AE11: =IFERROR(AD11/AC11,0) -> 0
C12: Day 2 | D12: Transfer | J12: Oslo: Self transfer to Oslo Central Station | Q12: 0 | R12: 0 | S12: =+Q12*R12 -> 0 | T12: 0 | U12: =S12*(1-T12) -> 0 | V12: EUR | W12: =IFERROR(VLOOKUP(V12,Curr!$B$2:$C$13,2,FALSE),0) -> 11.2 | X12: =U12*W12 -> 0 | Y12: =Q12 -> 0 | Z12: =+Y12*R12 -> 0 | AA12: EUR | AB12: =IFERROR(VLOOKUP(AA12,Curr!$B$2:$C$13,2,FALSE),0) -> 11.2 | AC12: =+Y12*AB12*R12 -> 0 | AD12: =+AC12-X12 -> 0 | AE12: =IFERROR(AD12/AC12,0) -> 0
C13: Day 2 | D13: Train | J13: Oslo: Scenic Long Distance Train transfer to Bergen - Time: 08:25 am - 3:00 pm - Includes: Tickets | O13: x | P13: https://www.vy.no/#reisesok | Q13: 2400 | R13: 1 | S13: =+Q13*R13 -> 2400 | T13: 0 | U13: =S13*(1-T13) -> 2400 | V13: NOK | W13: =IFERROR(VLOOKUP(V13,Curr!$B$2:$C$13,2,FALSE),0) -> 1 | X13: =U13*W13 -> 2400 | Y13: =Q13/11.3/0.8 -> 265.48673 | Z13: =+Y13*R13 -> 265.48673 | AA13: EUR | AB13: =IFERROR(VLOOKUP(AA13,Curr!$B$2:$C$13,2,FALSE),0) -> 11.2 | AC13: =+Y13*AB13*R13 -> 2973.4513 | AD13: =+AC13-X13 -> 573.45133 | AE13: =IFERROR(AD13/AC13,0) -> 0.19285714
C14: Day 2 | D14: Transfer | J14: Bergen: Self transfer to your accommodation | Q14: 0 | R14: 0 | S14: =+Q14*R14 -> 0 | T14: 0 | U14: =S14*(1-T14) -> 0 | V14: EUR | W14: =IFERROR(VLOOKUP(V14,Curr!$B$2:$C$13,2,FALSE),0) -> 11.2 | X14: =U14*W14 -> 0 | Y14: =Q14 -> 0 | Z14: =+Y14*R14 -> 0 | AA14: EUR | AB14: =IFERROR(VLOOKUP(AA14,Curr!$B$2:$C$13,2,FALSE),0) -> 11.2 | AC14: =+Y14*AB14*R14 -> 0 | AD14: =+AC14-X14 -> 0 | AE14: =IFERROR(AD14/AC14,0) -> 0
C15: Day 2 | D15: Hotel | J15: Bergen: Check in to your accommodation for a 2 night stay - Centrally located 3/4-star hotel - Standard Room - Breakfast included | Q15: 280 | R15: 1 | S15: =+Q15*R15 -> 280 | T15: 0 | U15: =S15*(1-T15) -> 280 | V15: EUR | W15: =IFERROR(VLOOKUP(V15,Curr!$B$2:$C$13,2,FALSE),0) -> 11.2 | X15: =U15*W15 -> 3136 | Y15: =Q15/0.85 -> 329.41176 | Z15: =+Y15*R15 -> 329.41176 | AA15: EUR | AB15: =IFERROR(VLOOKUP(AA15,Curr!$B$2:$C$13,2,FALSE),0) -> 11.2 | AC15: =+Y15*AB15*R15 -> 3689.4118 | AD15: =+AC15-X15 -> 553.41176 | AE15: =IFERROR(AD15/AC15,0) -> 0.15
C16: Day 2 | D16: Leisure | J16: Bergen: Spend time at leisure | Q16: 0 | R16: 0 | S16: =+Q16*R16 -> 0 | T16: 0 | U16: =S16*(1-T16) -> 0 | V16: EUR | W16: =IFERROR(VLOOKUP(V16,Curr!$B$2:$C$13,2,FALSE),0) -> 11.2 | X16: =U16*W16 -> 0 | Y16: =Q16 -> 0 | Z16: =+Y16*R16 -> 0 | AA16: EUR | AB16: =IFERROR(VLOOKUP(AA16,Curr!$B$2:$C$13,2,FALSE),0) -> 11.2 | AC16: =+Y16*AB16*R16 -> 0 | AD16: =+AC16-X16 -> 0 | AE16: =IFERROR(AD16/AC16,0) -> 0
S17: =+Q17*R17 -> 0 | T17: 0 | U17: =S17*(1-T17) -> 0 | V17: EUR | W17: =IFERROR(VLOOKUP(V17,Curr!$B$2:$C$13,2,FALSE),0) -> 11.2 | X17: =U17*W17 -> 0 | Y17: =Q17 -> 0 | Z17: =+Y17*R17 -> 0 | AA17: EUR | AB17: =IFERROR(VLOOKUP(AA17,Curr!$B$2:$C$13,2,FALSE),0) -> 11.2 | AC17: =+Y17*AB17*R17 -> 0 | AD17: =+AC17-X17 -> 0 | AE17: =IFERROR(AD17/AC17,0) -> 0
C18: Day 3 | D18: Activity | J18: Bergen: 2 hr walk Through Bergen Past & Present - Time: 10:00 am - 12:00 pm - Meeting point: Bradbenken 1 - Includes: Profesional Guide | O18: x | P18: https://www.ilovebergen.net/tour/a-walk-through-bergen-past-present/ | Q18: 290 | R18: 2 | S18: =+Q18*R18 -> 580 | T18: 0.2 | U18: =S18*(1-T18) -> 464 | V18: NOK | W18: =IFERROR(VLOOKUP(V18,Curr!$B$2:$C$13,2,FALSE),0) -> 1 | X18: =U18*W18 -> 464 | Y18: =Q18/11.3/0.64 -> 40.099558 | Z18: =+Y18*R18 -> 80.199115 | AA18: EUR | AB18: =IFERROR(VLOOKUP(AA18,Curr!$B$2:$C$13,2,FALSE),0) -> 11.2 | AC18: =+Y18*AB18*R18 -> 898.23009 | AD18: =+AC18-X18 -> 434.23009 | AE18: =IFERROR(AD18/AC18,0) -> 0.48342857
C19: Day 3 | D19: Activity | J19: Bergen: Fløibanen Funicual - Time: Flexible - Meeting point: Vetrlidsallmenningen 23A - Includes: Tickets | O19: x | P19: https://www.floyen.no/en/floibanen/buy-tickets/ | Q19: 175 | R19: 2 | S19: =+Q19*R19 -> 350 | T19: 0 | U19: =S19*(1-T19) -> 350 | V19: NOK | W19: =IFERROR(VLOOKUP(V19,Curr!$B$2:$C$13,2,FALSE),0) -> 1 | X19: =U19*W19 -> 350 | Y19: =Q19/11.3/0.5 -> 30.973451 | Z19: =+Y19*R19 -> 61.946903 | AA19: EUR | AB19: =IFERROR(VLOOKUP(AA19,Curr!$B$2:$C$13,2,FALSE),0) -> 11.2 | AC19: =+Y19*AB19*R19 -> 693.80531 | AD19: =+AC19-X19 -> 343.80531 | AE19: =IFERROR(AD19/AC19,0) -> 0.49553571
C20: Day 3 | D20: Leisure | J20: Bergen: Spend time at leisure | Q20: 0 | R20: 0 | S20: =+Q20*R20 -> 0 | T20: 0 | U20: =S20*(1-T20) -> 0 | V20: EUR | W20: =IFERROR(VLOOKUP(V20,Curr!$B$2:$C$13,2,FALSE),0) -> 11.2 | X20: =U20*W20 -> 0 | Y20: =Q20 -> 0 | Z20: =+Y20*R20 -> 0 | AA20: EUR | AB20: =IFERROR(VLOOKUP(AA20,Curr!$B$2:$C$13,2,FALSE),0) -> 11.2 | AC20: =+Y20*AB20*R20 -> 0 | AD20: =+AC20-X20 -> 0 | AE20: =IFERROR(AD20/AC20,0) -> 0
S21: =+Q21*R21 -> 0 | T21: 0 | U21: =S21*(1-T21) -> 0 | V21: EUR | W21: =IFERROR(VLOOKUP(V21,Curr!$B$2:$C$13,2,FALSE),0) -> 11.2 | X21: =U21*W21 -> 0 | Y21: =Q21 -> 0 | Z21: =+Y21*R21 -> 0 | AA21: EUR | AB21: =IFERROR(VLOOKUP(AA21,Curr!$B$2:$C$13,2,FALSE),0) -> 11.2 | AC21: =+Y21*AB21*R21 -> 0 | AD21: =+AC21-X21 -> 0 | AE21: =IFERROR(AD21/AC21,0) -> 0
C22: Day 4 | D22: Transfer | J22: Bergen: Self transfer to Bergen Airport | Q22: 0 | R22: 0 | S22: =+Q22*R22 -> 0 | T22: 0 | U22: =S22*(1-T22) -> 0 | V22: EUR | W22: =IFERROR(VLOOKUP(V22,Curr!$B$2:$C$13,2,FALSE),0) -> 11.2 | X22: =U22*W22 -> 0 | Y22: =Q22 -> 0 | Z22: =+Y22*R22 -> 0 | AA22: EUR | AB22: =IFERROR(VLOOKUP(AA22,Curr!$B$2:$C$13,2,FALSE),0) -> 11.2 | AC22: =+Y22*AB22*R22 -> 0 | AD22: =+AC22-X22 -> 0 | AE22: =IFERROR(AD22/AC22,0) -> 0
C23: Day 4 | D23: Flight | J23: Bergen: Flight to Tromsø - Time: Date dependant - Luggage included: 1 x 23 kg check in and 1 x 8 kg carry on per person | O23: x | Q23: 1800 | R23: 2 | S23: =+Q23*R23 -> 3600 | T23: 0 | U23: =S23*(1-T23) -> 3600 | V23: NOK | W23: =IFERROR(VLOOKUP(V23,Curr!$B$2:$C$13,2,FALSE),0) -> 1 | X23: =U23*W23 -> 3600 | Y23: =Q23/11.3/0.8 -> 199.11504 | Z23: =+Y23*R23 -> 398.23009 | AA23: EUR | AB23: =IFERROR(VLOOKUP(AA23,Curr!$B$2:$C$13,2,FALSE),0) -> 11.2 | AC23: =+Y23*AB23*R23 -> 4460.177 | AD23: =+AC23-X23 -> 860.17699 | AE23: =IFERROR(AD23/AC23,0) -> 0.19285714
C24: Day 4 | D24: Transfer | J24: Tromsø: Self transfer to your accommodation | Q24: 0 | R24: 0 | S24: =+Q24*R24 -> 0 | T24: 0 | U24: =S24*(1-T24) -> 0 | V24: NOK | W24: =IFERROR(VLOOKUP(V24,Curr!$B$2:$C$13,2,FALSE),0) -> 1 | X24: =U24*W24 -> 0 | Y24: =Q24/11.3/0.8 -> 0 | Z24: =+Y24*R24 -> 0 | AA24: EUR | AB24: =IFERROR(VLOOKUP(AA24,Curr!$B$2:$C$13,2,FALSE),0) -> 11.2 | AC24: =+Y24*AB24*R24 -> 0 | AD24: =+AC24-X24 -> 0 | AE24: =IFERROR(AD24/AC24,0) -> 0
C25: Day 4 | D25: Hotel | J25: Tromsø: Check in to your accommodation for a 2 night stay - Centrally located 3/4-star hotel - Standard Room - Breakfast included | Q25: 500 | R25: 1 | S25: =+Q25*R25 -> 500 | T25: 0 | U25: =S25*(1-T25) -> 500 | V25: EUR | W25: =IFERROR(VLOOKUP(V25,Curr!$B$2:$C$13,2,FALSE),0) -> 11.2 | X25: =U25*W25 -> 5600 | Y25: =Q25/0.85 -> 588.23529 | Z25: =+Y25*R25 -> 588.23529 | AA25: EUR | AB25: =IFERROR(VLOOKUP(AA25,Curr!$B$2:$C$13,2,FALSE),0) -> 11.2 | AC25: =+Y25*AB25*R25 -> 6588.2353 | AD25: =+AC25-X25 -> 988.23529 | AE25: =IFERROR(AD25/AC25,0) -> 0.15
C26: Day 4 | D26: Leisure | J26: Tromsø: Spend time at leisure | Q26: 0 | R26: 0 | S26: =+Q26*R26 -> 0 | T26: 0 | U26: =S26*(1-T26) -> 0 | V26: EUR | W26: =IFERROR(VLOOKUP(V26,Curr!$B$2:$C$13,2,FALSE),0) -> 11.2 | X26: =U26*W26 -> 0 | Y26: =Q26 -> 0 | Z26: =+Y26*R26 -> 0 | AA26: EUR | AB26: =IFERROR(VLOOKUP(AA26,Curr!$B$2:$C$13,2,FALSE),0) -> 11.2 | AC26: =+Y26*AB26*R26 -> 0 | AD26: =+AC26-X26 -> 0 | AE26: =IFERROR(AD26/AC26,0) -> 0
C27: Day 4 | D27: Activity | J27: Tromsø: Northern Lights Cruise with Silent Electric Ship - Time: 7:00 pm - 10:00 pm - Meeting point: Kaigata 6 - Includes: Departure from central Tromsø, 3-hour fjord cruise, Light meal (soup and bread) and water, English speaking guides, Warm indoor saloons, Free wifi, Toilets | O27: x | P27: https://booknordics.com/norway/northern-norway/tromso-region/northern-lights-cruise-electric-ship | Q27: 105 | R27: 2 | S27: =+Q27*R27 -> 210 | T27: 0.2 | U27: =S27*(1-T27) -> 168 | V27: EUR | W27: =IFERROR(VLOOKUP(V27,Curr!$B$2:$C$13,2,FALSE),0) -> 11.2 | X27: =U27*W27 -> 1881.6 | Y27: =Q27 -> 105 | Z27: =+Y27*R27 -> 210 | AA27: EUR | AB27: =IFERROR(VLOOKUP(AA27,Curr!$B$2:$C$13,2,FALSE),0) -> 11.2 | AC27: =+Y27*AB27*R27 -> 2352 | AD27: =+AC27-X27 -> 470.4 | AE27: =IFERROR(AD27/AC27,0) -> 0.2
S28: =+Q28*R28 -> 0 | T28: 0 | U28: =S28*(1-T28) -> 0 | V28: EUR | W28: =IFERROR(VLOOKUP(V28,Curr!$B$2:$C$13,2,FALSE),0) -> 11.2 | X28: =U28*W28 -> 0 | Y28: =Q28 -> 0 | Z28: =+Y28*R28 -> 0 | AA28: EUR | AB28: =IFERROR(VLOOKUP(AA28,Curr!$B$2:$C$13,2,FALSE),0) -> 11.2 | AC28: =+Y28*AB28*R28 -> 0 | AD28: =+AC28-X28 -> 0 | AE28: =IFERROR(AD28/AC28,0) -> 0
C29: Day 5 | D29: Activity | J29: Tromsø: Reindeer Feeding and Sámi Culture - Time: 09:45 am - 2:30 pm - Meeting point: Radisson Blu Hotel's main entrance (Sjøgata 7) - Includes: Scenic transfers (45 min each way), Knowledgeable English and Norwegian speaking guide, Feeding the herd at our camp, Hot beverages and hot meal (traditional Sámi stew or vegetable/lentil soup), Cultural introduction about Sámi history and daily life, A chance to see the northern lights from our camp, Thermal suit and warm snow boots | O29: x | P29: https://www.tromsolapland.no/activities/reindeer-feeding-and-sami-culture | Q29: 1695 | R29: 2 | S29: =+Q29*R29 -> 3390 | T29: 0.2 | U29: =S29*(1-T29) -> 2712 | V29: NOK | W29: =IFERROR(VLOOKUP(V29,Curr!$B$2:$C$13,2,FALSE),0) -> 1 | X29: =U29*W29 -> 2712 | Y29: =Q29/11.3 -> 150 | Z29: =+Y29*R29 -> 300 | AA29: EUR | AB29: =IFERROR(VLOOKUP(AA29,Curr!$B$2:$C$13,2,FALSE),0) -> 11.2 | AC29: =+Y29*AB29*R29 -> 3360 | AD29: =+AC29-X29 -> 648 | AE29: =IFERROR(AD29/AC29,0) -> 0.19285714
C30: Day 5 | D30: Leisure | J30: Tromsø: Spend time at leisure | Q30: 0 | R30: 0 | S30: =+Q30*R30 -> 0 | T30: 0 | U30: =S30*(1-T30) -> 0 | V30: EUR | W30: =IFERROR(VLOOKUP(V30,Curr!$B$2:$C$13,2,FALSE),0) -> 11.2 | X30: =U30*W30 -> 0 | Y30: =Q30 -> 0 | Z30: =+Y30*R30 -> 0 | AA30: EUR | AB30: =IFERROR(VLOOKUP(AA30,Curr!$B$2:$C$13,2,FALSE),0) -> 11.2 | AC30: =+Y30*AB30*R30 -> 0 | AD30: =+AC30-X30 -> 0 | AE30: =IFERROR(AD30/AC30,0) -> 0
C31: Day 5 | D31: Activity | J31: Tromsø: All-Evening Northern Lights Hunt by Minibus or Bus - Time: 7:00 pm - 12:00 am - Meeting point: Kaigata 4 - Includes: Knowledgeable, English-speaking guides, Photos shared with you after the tour, Thermo clothing and warm gear, Light snacks and warm/cold beverages, Drop-off at hotel, up to 5 km from Tromsø | O31: x | P31: https://booknordics.com/norway/northern-norway/tromso-region/full-day-magic-of-the-arctic-lights-in-tromso | Q31: 120 | R31: 2 | S31: =+Q31*R31 -> 240 | T31: 0.2 | U31: =S31*(1-T31) -> 192 | V31: EUR | W31: =IFERROR(VLOOKUP(V31,Curr!$B$2:$C$13,2,FALSE),0) -> 11.2 | X31: =U31*W31 -> 2150.4 | Y31: =Q31 -> 120 | Z31: =+Y31*R31 -> 240 | AA31: EUR | AB31: =IFERROR(VLOOKUP(AA31,Curr!$B$2:$C$13,2,FALSE),0) -> 11.2 | AC31: =+Y31*AB31*R31 -> 2688 | AD31: =+AC31-X31 -> 537.6 | AE31: =IFERROR(AD31/AC31,0) -> 0.2
S32: =+Q32*R32 -> 0 | T32: 0 | U32: =S32*(1-T32) -> 0 | V32: EUR | W32: =IFERROR(VLOOKUP(V32,Curr!$B$2:$C$13,2,FALSE),0) -> 11.2 | X32: =U32*W32 -> 0 | Y32: =Q32 -> 0 | Z32: =+Y32*R32 -> 0 | AA32: EUR | AB32: =IFERROR(VLOOKUP(AA32,Curr!$B$2:$C$13,2,FALSE),0) -> 11.2 | AC32: =+Y32*AB32*R32 -> 0 | AD32: =+AC32-X32 -> 0 | AE32: =IFERROR(AD32/AC32,0) -> 0
C33: Day 6 | D33: Transfer | J33: Tromsø: Self transfer to Scandic Ishavs Hotel | Q33: 0 | R33: 0 | S33: =+Q33*R33 -> 0 | T33: 0 | U33: =S33*(1-T33) -> 0 | V33: EUR | W33: =IFERROR(VLOOKUP(V33,Curr!$B$2:$C$13,2,FALSE),0) -> 11.2 | X33: =U33*W33 -> 0 | Y33: =Q33 -> 0 | Z33: =+Y33*R33 -> 0 | AA33: EUR | AB33: =IFERROR(VLOOKUP(AA33,Curr!$B$2:$C$13,2,FALSE),0) -> 11.2 | AC33: =+Y33*AB33*R33 -> 0 | AD33: =+AC33-X33 -> 0 | AE33: =IFERROR(AD33/AC33,0) -> 0
C34: Day 6 | D34: Activity | J34: Tromsø: Crystal Lavvo Stay with Auroras, Meals & Activities - Time: 11:30 am - 10: 50 am (the next day) - Meeting point: Samuel Arnesens gate 5 - Includes: Pick-up/drop-off in Tromsø with scenic transfers, Comfortable overnight stay in crystal lavvo, Fireplace heating with unlimited firewood, Northern Lights hunt with photo workshop, Snowshoeing experience nearby, Lunch and dinner included on day 1, Bathroom/toilet facilities in the main house, Breakfast and return transfer included on day 2 | O34: x | P34: https://booknordics.com/norway/northern-norway/tromso-region/crystal-lavvy-stay-northern-lights-snowshoeing | Q34: 375 | R34: 2 | S34: =+Q34*R34 -> 750 | T34: 0.2 | U34: =S34*(1-T34) -> 600 | V34: EUR | W34: =IFERROR(VLOOKUP(V34,Curr!$B$2:$C$13,2,FALSE),0) -> 11.2 | X34: =U34*W34 -> 6720 | Y34: =Q34 -> 375 | Z34: =+Y34*R34 -> 750 | AA34: EUR | AB34: =IFERROR(VLOOKUP(AA34,Curr!$B$2:$C$13,2,FALSE),0) -> 11.2 | AC34: =+Y34*AB34*R34 -> 8400 | AD34: =+AC34-X34 -> 1680 | AE34: =IFERROR(AD34/AC34,0) -> 0.2
S35: =+Q35*R35 -> 0 | T35: 0 | U35: =S35*(1-T35) -> 0 | V35: EUR | W35: =IFERROR(VLOOKUP(V35,Curr!$B$2:$C$13,2,FALSE),0) -> 11.2 | X35: =U35*W35 -> 0 | Y35: =Q35 -> 0 | Z35: =+Y35*R35 -> 0 | AA35: EUR | AB35: =IFERROR(VLOOKUP(AA35,Curr!$B$2:$C$13,2,FALSE),0) -> 11.2 | AC35: =+Y35*AB35*R35 -> 0 | AD35: =+AC35-X35 -> 0 | AE35: =IFERROR(AD35/AC35,0) -> 0
C36: Day 7 | D36: Transfer | J36: Lyngen: Included transfer back to Central Tromsø | Q36: 0 | R36: 0 | S36: =+Q36*R36 -> 0 | T36: 0 | U36: =S36*(1-T36) -> 0 | V36: EUR | W36: =IFERROR(VLOOKUP(V36,Curr!$B$2:$C$13,2,FALSE),0) -> 11.2 | X36: =U36*W36 -> 0 | Y36: =Q36 -> 0 | Z36: =+Y36*R36 -> 0 | AA36: EUR | AB36: =IFERROR(VLOOKUP(AA36,Curr!$B$2:$C$13,2,FALSE),0) -> 11.2 | AC36: =+Y36*AB36*R36 -> 0 | AD36: =+AC36-X36 -> 0 | AE36: =IFERROR(AD36/AC36,0) -> 0
C37: Day 7 | D37: Leisure | J37: Tromsø: Spend time at leisure | Q37: 0 | R37: 0 | S37: =+Q37*R37 -> 0 | T37: 0 | U37: =S37*(1-T37) -> 0 | V37: EUR | W37: =IFERROR(VLOOKUP(V37,Curr!$B$2:$C$13,2,FALSE),0) -> 11.2 | X37: =U37*W37 -> 0 | Y37: =Q37 -> 0 | Z37: =+Y37*R37 -> 0 | AA37: EUR | AB37: =IFERROR(VLOOKUP(AA37,Curr!$B$2:$C$13,2,FALSE),0) -> 11.2 | AC37: =+Y37*AB37*R37 -> 0 | AD37: =+AC37-X37 -> 0 | AE37: =IFERROR(AD37/AC37,0) -> 0
C38: Day 7 | D38: Coach | J38: Tromsø: Long distance panorama coach transfer to Alta - Bus 150 - Time: 4:00 pm - 10:20 pm - Excludes: Tickets (To be bought on site) | Q38: 0 | R38: 0 | S38: =+Q38*R38 -> 0 | T38: 0 | U38: =S38*(1-T38) -> 0 | V38: EUR | W38: =IFERROR(VLOOKUP(V38,Curr!$B$2:$C$13,2,FALSE),0) -> 11.2 | X38: =U38*W38 -> 0 | Y38: =Q38 -> 0 | Z38: =+Y38*R38 -> 0 | AA38: EUR | AB38: =IFERROR(VLOOKUP(AA38,Curr!$B$2:$C$13,2,FALSE),0) -> 11.2 | AC38: =+Y38*AB38*R38 -> 0 | AD38: =+AC38-X38 -> 0 | AE38: =IFERROR(AD38/AC38,0) -> 0
C39: Day 7 | D39: Transfer | J39: Alta: Self transfer to your accommodation | Q39: 0 | R39: 0 | S39: =+Q39*R39 -> 0 | T39: 0 | U39: =S39*(1-T39) -> 0 | V39: EUR | W39: =IFERROR(VLOOKUP(V39,Curr!$B$2:$C$13,2,FALSE),0) -> 11.2 | X39: =U39*W39 -> 0 | Y39: =Q39 -> 0 | Z39: =+Y39*R39 -> 0 | AA39: EUR | AB39: =IFERROR(VLOOKUP(AA39,Curr!$B$2:$C$13,2,FALSE),0) -> 11.2 | AC39: =+Y39*AB39*R39 -> 0 | AD39: =+AC39-X39 -> 0 | AE39: =IFERROR(AD39/AC39,0) -> 0
C40: Day 7 | D40: Hotel | J40: Alta: Check in to your accommodation for a 2 night stay - Centrally located 3/4-star hotel - Standard Room - Breakfast included | Q40: 280 | R40: 1 | S40: =+Q40*R40 -> 280 | T40: 0 | U40: =S40*(1-T40) -> 280 | V40: EUR | W40: =IFERROR(VLOOKUP(V40,Curr!$B$2:$C$13,2,FALSE),0) -> 11.2 | X40: =U40*W40 -> 3136 | Y40: =Q40/0.85 -> 329.41176 | Z40: =+Y40*R40 -> 329.41176 | AA40: EUR | AB40: =IFERROR(VLOOKUP(AA40,Curr!$B$2:$C$13,2,FALSE),0) -> 11.2 | AC40: =+Y40*AB40*R40 -> 3689.4118 | AD40: =+AC40-X40 -> 553.41176 | AE40: =IFERROR(AD40/AC40,0) -> 0.15
C41: Day 7 | D41: Leisure | J41: Alta: Spend time at leisure | Q41: 0 | R41: 0 | S41: =+Q41*R41 -> 0 | T41: 0 | U41: =S41*(1-T41) -> 0 | V41: EUR | W41: =IFERROR(VLOOKUP(V41,Curr!$B$2:$C$13,2,FALSE),0) -> 11.2 | X41: =U41*W41 -> 0 | Y41: =Q41 -> 0 | Z41: =+Y41*R41 -> 0 | AA41: EUR | AB41: =IFERROR(VLOOKUP(AA41,Curr!$B$2:$C$13,2,FALSE),0) -> 11.2 | AC41: =+Y41*AB41*R41 -> 0 | AD41: =+AC41-X41 -> 0 | AE41: =IFERROR(AD41/AC41,0) -> 0
S42: =+Q42*R42 -> 0 | T42: 0 | U42: =S42*(1-T42) -> 0 | V42: EUR | W42: =IFERROR(VLOOKUP(V42,Curr!$B$2:$C$13,2,FALSE),0) -> 11.2 | X42: =U42*W42 -> 0 | Y42: =Q42 -> 0 | Z42: =+Y42*R42 -> 0 | AA42: EUR | AB42: =IFERROR(VLOOKUP(AA42,Curr!$B$2:$C$13,2,FALSE),0) -> 11.2 | AC42: =+Y42*AB42*R42 -> 0 | AD42: =+AC42-X42 -> 0 | AE42: =IFERROR(AD42/AC42,0) -> 0
C43: Day 8 | D43: Activity | J43: Alta: Visit to Sorrisniva Igloo Hotel - Time: Flexible - Meeting point: Sorrisniva Arctic Wilderness Lodge - Includes: Entry ticket to explore Sorrisniva Igloo Hotel | O43: x | P43: https://booknordics.com/norway/northern-norway/alta-and-north-cape/entrance-ticket-igloo-hotel | Q43: 34 | R43: 2 | S43: =+Q43*R43 -> 68 | T43: 0.15 | U43: =S43*(1-T43) -> 57.8 | V43: EUR | W43: =IFERROR(VLOOKUP(V43,Curr!$B$2:$C$13,2,FALSE),0) -> 11.2 | X43: =U43*W43 -> 647.36 | Y43: =Q43 -> 34 | Z43: =+Y43*R43 -> 68 | AA43: EUR | AB43: =IFERROR(VLOOKUP(AA43,Curr!$B$2:$C$13,2,FALSE),0) -> 11.2 | AC43: =+Y43*AB43*R43 -> 761.6 | AD43: =+AC43-X43 -> 114.24 | AE43: =IFERROR(AD43/AC43,0) -> 0.15
C44: Day 8 | D44: Leisure | J44: Alta: Spend time at leisure | Q44: 0 | R44: 0 | S44: =+Q44*R44 -> 0 | T44: 0 | U44: =S44*(1-T44) -> 0 | V44: EUR | W44: =IFERROR(VLOOKUP(V44,Curr!$B$2:$C$13,2,FALSE),0) -> 11.2 | X44: =U44*W44 -> 0 | Y44: =Q44 -> 0 | Z44: =+Y44*R44 -> 0 | AA44: EUR | AB44: =IFERROR(VLOOKUP(AA44,Curr!$B$2:$C$13,2,FALSE),0) -> 11.2 | AC44: =+Y44*AB44*R44 -> 0 | AD44: =+AC44-X44 -> 0 | AE44: =IFERROR(AD44/AC44,0) -> 0
C45: Day 8 | D45: Activity | J45: Alta: Small Group Northern Lights Hunt - Time: 7:00 pm - 11:00 pm - Meeting point: Æventyr Booking Point - Includes: Professional guide, Northern Lights lectures and local history, Coffee / tea and snacks, Warm overalls for loan | O45: x | P45: https://www.aeventyr.no/activities/small-group-northern-lights-hunt | Q45: 2290 | R45: 2 | S45: =+Q45*R45 -> 4580 | T45: 0.15 | U45: =S45*(1-T45) -> 3893 | V45: NOK | W45: =IFERROR(VLOOKUP(V45,Curr!$B$2:$C$13,2,FALSE),0) -> 1 | X45: =U45*W45 -> 3893 | Y45: =Q45/11.3 -> 202.65487 | Z45: =+Y45*R45 -> 405.30973 | AA45: EUR | AB45: =IFERROR(VLOOKUP(AA45,Curr!$B$2:$C$13,2,FALSE),0) -> 11.2 | AC45: =+Y45*AB45*R45 -> 4539.469 | AD45: =+AC45-X45 -> 646.46903 | AE45: =IFERROR(AD45/AC45,0) -> 0.14241071
S46: =+Q46*R46 -> 0 | T46: 0 | U46: =S46*(1-T46) -> 0 | V46: EUR | W46: =IFERROR(VLOOKUP(V46,Curr!$B$2:$C$13,2,FALSE),0) -> 11.2 | X46: =U46*W46 -> 0 | Y46: =Q46 -> 0 | Z46: =+Y46*R46 -> 0 | AA46: EUR | AB46: =IFERROR(VLOOKUP(AA46,Curr!$B$2:$C$13,2,FALSE),0) -> 11.2 | AC46: =+Y46*AB46*R46 -> 0 | AD46: =+AC46-X46 -> 0 | AE46: =IFERROR(AD46/AC46,0) -> 0
C47: Day 9 | D47: Transfer | J47: Alta: Self transfer to Alta Airport | Q47: 0 | R47: 0 | S47: =+Q47*R47 -> 0 | T47: 0 | U47: =S47*(1-T47) -> 0 | V47: EUR | W47: =IFERROR(VLOOKUP(V47,Curr!$B$2:$C$13,2,FALSE),0) -> 11.2 | X47: =U47*W47 -> 0 | Y47: =Q47 -> 0 | Z47: =+Y47*R47 -> 0 | AA47: EUR | AB47: =IFERROR(VLOOKUP(AA47,Curr!$B$2:$C$13,2,FALSE),0) -> 11.2 | AC47: =+Y47*AB47*R47 -> 0 | AD47: =+AC47-X47 -> 0 | AE47: =IFERROR(AD47/AC47,0) -> 0
C48: Day 9 | D48: Departure | J48: Alta: Departure home | Q48: 0 | R48: 0 | S48: =+Q48*R48 -> 0 | T48: 0 | U48: =S48*(1-T48) -> 0 | V48: EUR | W48: =IFERROR(VLOOKUP(V48,Curr!$B$2:$C$13,2,FALSE),0) -> 11.2 | X48: =U48*W48 -> 0 | Y48: =Q48 -> 0 | Z48: =+Y48*R48 -> 0 | AA48: EUR | AB48: =IFERROR(VLOOKUP(AA48,Curr!$B$2:$C$13,2,FALSE),0) -> 11.2 | AC48: =+Y48*AB48*R48 -> 0 | AD48: =+AC48-X48 -> 0 | AE48: =IFERROR(AD48/AC48,0) -> 0
S49: =+Q49*R49 -> 0 | T49: 0 | U49: =S49*(1-T49) -> 0 | V49: EUR | W49: =IFERROR(VLOOKUP(V49,Curr!$B$2:$C$13,2,FALSE),0) -> 11.2 | X49: =U49*W49 -> 0 | Y49: =Q49 -> 0 | Z49: =+Y49*R49 -> 0 | AA49: EUR | AB49: =IFERROR(VLOOKUP(AA49,Curr!$B$2:$C$13,2,FALSE),0) -> 11.2 | AC49: =+Y49*AB49*R49 -> 0 | AD49: =+AC49-X49 -> 0 | AE49: =IFERROR(AD49/AC49,0) -> 0
S50: =+Q50*R50 -> 0 | T50: 0 | U50: =S50*(1-T50) -> 0 | V50: EUR | W50: =IFERROR(VLOOKUP(V50,Curr!$B$2:$C$13,2,FALSE),0) -> 11.2 | X50: =U50*W50 -> 0 | Y50: =Q50 -> 0 | Z50: =+Y50*R50 -> 0 | AA50: EUR | AB50: =IFERROR(VLOOKUP(AA50,Curr!$B$2:$C$13,2,FALSE),0) -> 11.2 | AC50: =+Y50*AB50*R50 -> 0 | AD50: =+AC50-X50 -> 0 | AE50: =IFERROR(AD50/AC50,0) -> 0
C51: Day 1 | D51: Transfer Package | J51: Oslo: Private transfer to your accommodation | Q51: 1750 | R51: 0 | S51: =+Q51*R51 -> 0 | T51: 0 | U51: =S51*(1-T51) -> 0 | V51: NOK | W51: =IFERROR(VLOOKUP(V51,Curr!$B$2:$C$13,2,FALSE),0) -> 1 | X51: =U51*W51 -> 0 | Y51: =Q51/11.3/0.8 -> 193.58407 | Z51: =+Y51*R51 -> 0 | AA51: EUR | AB51: =IFERROR(VLOOKUP(AA51,Curr!$B$2:$C$13,2,FALSE),0) -> 11.2 | AC51: =+Y51*AB51*R51 -> 0 | AD51: =+AC51-X51 -> 0 | AE51: =IFERROR(AD51/AC51,0) -> 0
C52: Day 2 | D52: Transfer Package | J52: Bergen: Private transfer to your accommodation | Q52: 1290 | R52: 0 | S52: =+Q52*R52 -> 0 | T52: 0.15 | U52: =S52*(1-T52) -> 0 | V52: NOK | W52: =IFERROR(VLOOKUP(V52,Curr!$B$2:$C$13,2,FALSE),0) -> 1 | X52: =U52*W52 -> 0 | Y52: =Q52/11.3/0.98 -> 116.48907 | Z52: =+Y52*R52 -> 0 | AA52: EUR | AB52: =IFERROR(VLOOKUP(AA52,Curr!$B$2:$C$13,2,FALSE),0) -> 11.2 | AC52: =+Y52*AB52*R52 -> 0 | AD52: =+AC52-X52 -> 0 | AE52: =IFERROR(AD52/AC52,0) -> 0
C53: Day 4 | D53: Transfer Package | J53: Bergen: Private transfer to Bergen Airport | Q53: 1690 | R53: 0 | S53: =+Q53*R53 -> 0 | T53: 0.15 | U53: =S53*(1-T53) -> 0 | V53: NOK | W53: =IFERROR(VLOOKUP(V53,Curr!$B$2:$C$13,2,FALSE),0) -> 1 | X53: =U53*W53 -> 0 | Y53: =Q53/11.3/0.98 -> 152.60972 | Z53: =+Y53*R53 -> 0 | AA53: EUR | AB53: =IFERROR(VLOOKUP(AA53,Curr!$B$2:$C$13,2,FALSE),0) -> 11.2 | AC53: =+Y53*AB53*R53 -> 0 | AD53: =+AC53-X53 -> 0 | AE53: =IFERROR(AD53/AC53,0) -> 0
C54: Day 4 | D54: Transfer Package | J54: Tromsø: Private transfer to your accommodation | Q54: 900 | R54: 0 | S54: =+Q54*R54 -> 0 | T54: 0 | U54: =S54*(1-T54) -> 0 | V54: NOK | W54: =IFERROR(VLOOKUP(V54,Curr!$B$2:$C$13,2,FALSE),0) -> 1 | X54: =U54*W54 -> 0 | Y54: =Q54/11.3/0.8 -> 99.557522 | Z54: =+Y54*R54 -> 0 | AA54: EUR | AB54: =IFERROR(VLOOKUP(AA54,Curr!$B$2:$C$13,2,FALSE),0) -> 11.2 | AC54: =+Y54*AB54*R54 -> 0 | AD54: =+AC54-X54 -> 0 | AE54: =IFERROR(AD54/AC54,0) -> 0
C55: Day 9 | D55: Transfer Package | J55: Alta: Private transfer to Alta Airport | Q55: 900 | R55: 0 | S55: =+Q55*R55 -> 0 | T55: 0 | U55: =S55*(1-T55) -> 0 | V55: NOK | W55: =IFERROR(VLOOKUP(V55,Curr!$B$2:$C$13,2,FALSE),0) -> 1 | X55: =U55*W55 -> 0 | Y55: =Q55/11.3/0.8 -> 99.557522 | Z55: =+Y55*R55 -> 0 | AA55: EUR | AB55: =IFERROR(VLOOKUP(AA55,Curr!$B$2:$C$13,2,FALSE),0) -> 11.2 | AC55: =+Y55*AB55*R55 -> 0 | AD55: =+AC55-X55 -> 0 | AE55: =IFERROR(AD55/AC55,0) -> 0
S56: =+Q56*R56 -> 0 | T56: 0 | U56: =S56*(1-T56) -> 0 | V56: EUR | W56: =IFERROR(VLOOKUP(V56,Curr!$B$2:$C$13,2,FALSE),0) -> 11.2 | X56: =U56*W56 -> 0 | Y56: =Q56 -> 0 | Z56: =+Y56*R56 -> 0 | AA56: EUR | AB56: =IFERROR(VLOOKUP(AA56,Curr!$B$2:$C$13,2,FALSE),0) -> 11.2 | AC56: =+Y56*AB56*R56 -> 0 | AD56: =+AC56-X56 -> 0 | AE56: =IFERROR(AD56/AC56,0) -> 0
S57: =+Q57*R57 -> 0 | T57: 0 | U57: =S57*(1-T57) -> 0 | V57: EUR | W57: =IFERROR(VLOOKUP(V57,Curr!$B$2:$C$13,2,FALSE),0) -> 11.2 | X57: =U57*W57 -> 0 | Y57: =Q57 -> 0 | Z57: =+Y57*R57 -> 0 | AA57: EUR | AB57: =IFERROR(VLOOKUP(AA57,Curr!$B$2:$C$13,2,FALSE),0) -> 11.2 | AC57: =+Y57*AB57*R57 -> 0 | AD57: =+AC57-X57 -> 0 | AE57: =IFERROR(AD57/AC57,0) -> 0
C58: Day 2 | D58: Activity Upgrade | J58: Oslo: Norway in a Nutshell to Bergen - Time: 08:00 am - 09:00 pm - Meeting point. Oslo Central Station - Includes: Train transfer Oslo to Myrdal, Train tranfser Myrdal to Flåm, Fjord Cruise Flåm to Gudvangen, Coach Transfer Gudvangen to Voss, Train transfer Voss to Bergen | O58: x | P58: https://www.fjordtours.com/en | Q58: 3250 | R58: 0 | S58: =+Q58*R58 -> 0 | T58: 0.08 | U58: =S58*(1-T58) -> 0 | V58: NOK | W58: =IFERROR(VLOOKUP(V58,Curr!$B$2:$C$13,2,FALSE),0) -> 1 | X58: =U58*W58 -> 0 | Y58: =Q58/11.3/0.9 -> 319.56735 | Z58: =+Y58*R58 -> 0 | AA58: EUR | AB58: =IFERROR(VLOOKUP(AA58,Curr!$B$2:$C$13,2,FALSE),0) -> 11.2 | AC58: =+Y58*AB58*R58 -> 0 | AD58: =+AC58-X58 -> 0 | AE58: =IFERROR(AD58/AC58,0) -> 0
C59: Day 2 | D59: Activity Upgrade | J59: Oslo: Norway in a Nutshell Porter Service - Includes: Luggage transfer from your accommodation in Oslo to your accommodaiton in Bergen | Q59: 450 | R59: 0 | S59: =+Q59*R59 -> 0 | T59: 0 | U59: =S59*(1-T59) -> 0 | V59: NOK | W59: =IFERROR(VLOOKUP(V59,Curr!$B$2:$C$13,2,FALSE),0) -> 1 | X59: =U59*W59 -> 0 | Y59: =Q59/11.3/0.8 -> 49.778761 | Z59: =+Y59*R59 -> 0 | AA59: EUR | AB59: =IFERROR(VLOOKUP(AA59,Curr!$B$2:$C$13,2,FALSE),0) -> 11.2 | AC59: =+Y59*AB59*R59 -> 0 | AD59: =+AC59-X59 -> 0 | AE59: =IFERROR(AD59/AC59,0) -> 0
C60: Day 3 | D60: Activity Upgrade | J60: Bergen: Mostraumen Majestic Fjord & Waterfall Cruise - Time: 12:00 pm - 4:00 pm - Meeting point: Strandkaien 13 - Includes: 4-hour panoramic fjord cruise, Expert captain navigating through the fjords, English-audio guide | O60: x | P60: https://booknordics.com/norway/western-fjord-norway/bergen-and-hardanger/mostraumen-fjord-waterfall-cruise | Q60: 71 | R60: 0 | S60: =+Q60*R60 -> 0 | T60: 0.2 | U60: =S60*(1-T60) -> 0 | V60: EUR | W60: =IFERROR(VLOOKUP(V60,Curr!$B$2:$C$13,2,FALSE),0) -> 11.2 | X60: =U60*W60 -> 0 | Y60: =Q60 -> 71 | Z60: =+Y60*R60 -> 0 | AA60: EUR | AB60: =IFERROR(VLOOKUP(AA60,Curr!$B$2:$C$13,2,FALSE),0) -> 11.2 | AC60: =+Y60*AB60*R60 -> 0 | AD60: =+AC60-X60 -> 0 | AE60: =IFERROR(AD60/AC60,0) -> 0
C61: Day 5 | D61: Activity Upgrade | J61: Tromsø: Reindeer Sledding, Reindeer Feeding and Sami Culture - Time: 09:45 am - 2:30 pm - Meeting point: Radisson Blu Hotel's main entrance (Sjøgata 7) - Includes: Scenic transfers (45 min each way), Knowledgeable English- and Norwegian-speaking guide, Thermal winter suit, warm boots, Reindeer sledding (approx. 30 min, depending on weather and snow conditions), Feeding the herd on our camp, Hot traditional Sámi meal (bithos) and hot drinks. Vegetarian option available on request, Cultural introduction about Sámi history and daily life | O61: x | P61: https://booknordics.com/norway/northern-norway/tromso-region/reindeer-sledding-reindeer-feeding-and-sami-culture-3 | Q61: 2195 | R61: 0 | S61: =+Q61*R61 -> 0 | T61: 0.2 | U61: =S61*(1-T61) -> 0 | V61: NOK | W61: =IFERROR(VLOOKUP(V61,Curr!$B$2:$C$13,2,FALSE),0) -> 1 | X61: =U61*W61 -> 0 | Y61: =Q61/11.3 -> 194.24779 | Z61: =+Y61*R61 -> 0 | AA61: EUR | AB61: =IFERROR(VLOOKUP(AA61,Curr!$B$2:$C$13,2,FALSE),0) -> 11.2 | AC61: =+Y61*AB61*R61 -> 0 | AD61: =+AC61-X61 -> 0 | AE61: =IFERROR(AD61/AC61,0) -> 0
C62: Day 8 | D62: Activity Upgrade | J62: Alta: Dog Sledding in Alta - Time: 10:00 am - 2:00 pm - Meeting point: Æventyr Booking Point - Includes: Dog Sledding: Approximately 50 minutes on the trail, Transport: From Alta to Gargia and back (approximately 30 minutes each way), Dog Sledding Training and Equipment: Learn the basics of dog sledding and get equipped with the necessary gear, Warm Clothing: Stay cozy in the Arctic cold, Coffee & Tea, Storytelling: Discover the history of dog sledding and Gargia, Assistance with Dressing/Undressing the Dogs, Meet the Huskies | O62: x | P62: https://www.aeventyr.no/activities/embark-on-an-arctic-adventure-dog-sledding-in-alta | Q62: 2990 | R62: 0 | S62: =+Q62*R62 -> 0 | T62: 0.15 | U62: =S62*(1-T62) -> 0 | V62: NOK | W62: =IFERROR(VLOOKUP(V62,Curr!$B$2:$C$13,2,FALSE),0) -> 1 | X62: =U62*W62 -> 0 | Y62: =Q62/11.3 -> 264.60177 | Z62: =+Y62*R62 -> 0 | AA62: EUR | AB62: =IFERROR(VLOOKUP(AA62,Curr!$B$2:$C$13,2,FALSE),0) -> 11.2 | AC62: =+Y62*AB62*R62 -> 0 | AD62: =+AC62-X62 -> 0 | AE62: =IFERROR(AD62/AC62,0) -> 0
C63: Day 8 | D63: Activity Upgrade | J63: Alta: Northern Lights Dog Sledding - Time: 7:00 pm - 11:00 pm - Meeting point: Æventyr Booking Point - Includes: Dog Sledding: Approximately 50 minutes on the trail, Transport: From Alta to Gargia and back (approximately 30 minutes each way), Dog Sledding Training and Equipment: Learn the basics of dog sledding and get equipped with the necessary gear, Warm Clothing: Stay cozy in the Arctic cold, Coffee & Tea, Storytelling: Discover the history of dog sledding and Gargia, Assistance with Dressing/Undressing the Dogs | O63: x | P63: https://www.aeventyr.no/activities/northern-lights-dog-sledding-trip-in-alta | Q63: 3390 | R63: 0 | S63: =+Q63*R63 -> 0 | T63: 0.15 | U63: =S63*(1-T63) -> 0 | V63: NOK | W63: =IFERROR(VLOOKUP(V63,Curr!$B$2:$C$13,2,FALSE),0) -> 1 | X63: =U63*W63 -> 0 | Y63: =Q63/11.3 -> 300 | Z63: =+Y63*R63 -> 0 | AA63: EUR | AB63: =IFERROR(VLOOKUP(AA63,Curr!$B$2:$C$13,2,FALSE),0) -> 11.2 | AC63: =+Y63*AB63*R63 -> 0 | AD63: =+AC63-X63 -> 0 | AE63: =IFERROR(AD63/AC63,0) -> 0
S64: =+Q64*R64 -> 0 | T64: 0 | U64: =S64*(1-T64) -> 0 | V64: EUR | W64: =IFERROR(VLOOKUP(V64,Curr!$B$2:$C$13,2,FALSE),0) -> 11.2 | X64: =U64*W64 -> 0 | Y64: =Q64 -> 0 | Z64: =+Y64*R64 -> 0 | AA64: EUR | AB64: =IFERROR(VLOOKUP(AA64,Curr!$B$2:$C$13,2,FALSE),0) -> 11.2 | AC64: =+Y64*AB64*R64 -> 0 | AD64: =+AC64-X64 -> 0 | AE64: =IFERROR(AD64/AC64,0) -> 0
S65: =+Q65*R65 -> 0 | T65: 0 | U65: =S65*(1-T65) -> 0 | V65: EUR | W65: =IFERROR(VLOOKUP(V65,Curr!$B$2:$C$13,2,FALSE),0) -> 11.2 | X65: =U65*W65 -> 0 | Y65: =Q65 -> 0 | Z65: =+Y65*R65 -> 0 | AA65: EUR | AB65: =IFERROR(VLOOKUP(AA65,Curr!$B$2:$C$13,2,FALSE),0) -> 11.2 | AC65: =+Y65*AB65*R65 -> 0 | AD65: =+AC65-X65 -> 0 | AE65: =IFERROR(AD65/AC65,0) -> 0
S66: =+Q66*R66 -> 0 | T66: 0 | U66: =S66*(1-T66) -> 0 | V66: EUR | W66: =IFERROR(VLOOKUP(V66,Curr!$B$2:$C$13,2,FALSE),0) -> 11.2 | X66: =U66*W66 -> 0 | Y66: =Q66 -> 0 | Z66: =+Y66*R66 -> 0 | AA66: EUR | AB66: =IFERROR(VLOOKUP(AA66,Curr!$B$2:$C$13,2,FALSE),0) -> 11.2 | AC66: =+Y66*AB66*R66 -> 0 | AD66: =+AC66-X66 -> 0 | AE66: =IFERROR(AD66/AC66,0) -> 0
S67: =+Q67*R67 -> 0 | T67: 0 | U67: =S67*(1-T67) -> 0 | V67: EUR | W67: =IFERROR(VLOOKUP(V67,Curr!$B$2:$C$13,2,FALSE),0) -> 11.2 | X67: =U67*W67 -> 0 | Y67: =Q67 -> 0 | Z67: =+Y67*R67 -> 0 | AA67: EUR | AB67: =IFERROR(VLOOKUP(AA67,Curr!$B$2:$C$13,2,FALSE),0) -> 11.2 | AC67: =+Y67*AB67*R67 -> 0 | AD67: =+AC67-X67 -> 0 | AE67: =IFERROR(AD67/AC67,0) -> 0
S68: =+Q68*R68 -> 0 | T68: 0 | U68: =S68*(1-T68) -> 0 | V68: EUR | W68: =IFERROR(VLOOKUP(V68,Curr!$B$2:$C$13,2,FALSE),0) -> 11.2 | X68: =U68*W68 -> 0 | Y68: =Q68 -> 0 | Z68: =+Y68*R68 -> 0 | AA68: EUR | AB68: =IFERROR(VLOOKUP(AA68,Curr!$B$2:$C$13,2,FALSE),0) -> 11.2 | AC68: =+Y68*AB68*R68 -> 0 | AD68: =+AC68-X68 -> 0 | AE68: =IFERROR(AD68/AC68,0) -> 0
S69: =+Q69*R69 -> 0 | T69: 0 | U69: =S69*(1-T69) -> 0 | V69: EUR | W69: =IFERROR(VLOOKUP(V69,Curr!$B$2:$C$13,2,FALSE),0) -> 11.2 | X69: =U69*W69 -> 0 | Y69: =Q69 -> 0 | Z69: =+Y69*R69 -> 0 | AA69: EUR | AB69: =IFERROR(VLOOKUP(AA69,Curr!$B$2:$C$13,2,FALSE),0) -> 11.2 | AC69: =+Y69*AB69*R69 -> 0 | AD69: =+AC69-X69 -> 0 | AE69: =IFERROR(AD69/AC69,0) -> 0
S70: =+Q70*R70 -> 0 | T70: 0 | U70: =S70*(1-T70) -> 0 | V70: EUR | W70: =IFERROR(VLOOKUP(V70,Curr!$B$2:$C$13,2,FALSE),0) -> 11.2 | X70: =U70*W70 -> 0 | Y70: =Q70 -> 0 | Z70: =+Y70*R70 -> 0 | AA70: EUR | AB70: =IFERROR(VLOOKUP(AA70,Curr!$B$2:$C$13,2,FALSE),0) -> 11.2 | AC70: =+Y70*AB70*R70 -> 0 | AD70: =+AC70-X70 -> 0 | AE70: =IFERROR(AD70/AC70,0) -> 0
S71: =+Q71*R71 -> 0 | T71: 0 | U71: =S71*(1-T71) -> 0 | V71: EUR | W71: =IFERROR(VLOOKUP(V71,Curr!$B$2:$C$13,2,FALSE),0) -> 11.2 | X71: =U71*W71 -> 0 | Y71: =Q71 -> 0 | Z71: =+Y71*R71 -> 0 | AA71: EUR | AB71: =IFERROR(VLOOKUP(AA71,Curr!$B$2:$C$13,2,FALSE),0) -> 11.2 | AC71: =+Y71*AB71*R71 -> 0 | AD71: =+AC71-X71 -> 0 | AE71: =IFERROR(AD71/AC71,0) -> 0
B73: Totals | D73: x | E73: x | F73: x | G73: x | H73: x | I73: x | J73: x | K73: x | L73: x | M73: x | N73: x | O73: x | P73: x | Q73: x | R73: x | S73: x | T73: x | U73: x | V73: x | W73: x | X73: x | Y73: x | Z73: =SUM(Z7:Z71) -> 4202.702 | AC73: =SUM(AC7:AC71) -> 47070.262 | AD73: =SUM(AD7:AD71) -> 8699.9022 | AE73: =IFERROR(AD73/AC73,0) -> 0.18482799 | AF73: =SUM(AF8:AF72) -> 0 | AG73: =SUM(AG8:AG72) -> 0 | AH73: =SUM(AH8:AH72) -> 0 | AI73: =SUM(AI8:AI72) -> 0 | AJ73: =SUM(AJ8:AJ72) -> 0
Y75: Fixed | Z75: 2520
Y76: Variable | Z76: =Z9+Z15+Z23+Z25+Z40 -> 1821.7595
Y77: Total | Z77: 4220
Y78: PP | Z78: =Z77/2 -> 2110
Z81: Winter
Y82: Shoulder | Z82: =Z77 -> 4220
Y83: High | Z83: =Z82*1.18 -> 4979.6
Y84: Holiday | Z84: =Z82*1.25 -> 5275
Y85: Low | Z85: =Z82*0.85 -> 3587
Y86: Summer | Z86: NA

Sheet 205
B1: Season: Winter
B2: Places: Oslo 1N - Bergen 2N - Tromsø 2N - Alta 2N
B3: Pax: 2
B4: Rooming: Double
B6: ID | C6: Day | D6: Type | E6: From date | F6: To date | G6: From time | H6: To time | I6: Supplier | J6: Travel element | K6: Manual booking? | L6: Status | M6: Comments | N6: Non-refundable | O6: Refundable | P6: URL | Q6: Gross P per unit | R6: Units | S6: Gross P | T6: Supp Comm | U6: Net P | V6: Supp curr | W6: X-rate | X6: Net P NOK | Y6: Sales P per unit | Z6: Price | AA6: Sales curr | AB6: X-rate | AC6: Sales P NOK tot | AD6: GP NOK | AE6: GP % | AF6: VAT25 | AG6: VAT15 | AH6: VAT12 | AI6: VAT0-D | AJ6: VAT0-I
C7: Day 1 | D7: Arrival | J7: Oslo: Welcome to Norway | Q7: 0 | R7: 0 | S7: =+Q7*R7 -> 0 | T7: 0 | U7: =S7*(1-T7) -> 0 | V7: EUR | W7: =IFERROR(VLOOKUP(V7,Curr!$B$2:$C$13,2,FALSE),0) -> 11.2 | X7: =U7*W7 -> 0 | Y7: =Q7 -> 0 | Z7: =+Y7*R7 -> 0 | AA7: EUR | AB7: =IFERROR(VLOOKUP(AA7,Curr!$B$2:$C$13,2,FALSE),0) -> 11.2 | AC7: =+Y7*AB7*R7 -> 0 | AD7: =+AC7-X7 -> 0 | AE7: =IFERROR(AD7/AC7,0) -> 0
C8: Day 1 | D8: Transfer | J8: Oslo: Self transfer to your accommodation | Q8: 0 | R8: 0 | S8: =+Q8*R8 -> 0 | T8: 0 | U8: =S8*(1-T8) -> 0 | V8: NOK | W8: =IFERROR(VLOOKUP(V8,Curr!$B$2:$C$13,2,FALSE),0) -> 1 | X8: =U8*W8 -> 0 | Y8: =Q8/11.3/0.8 -> 0 | Z8: =+Y8*R8 -> 0 | AA8: EUR | AB8: =IFERROR(VLOOKUP(AA8,Curr!$B$2:$C$13,2,FALSE),0) -> 11.2 | AC8: =+Y8*AB8*R8 -> 0 | AD8: =+AC8-X8 -> 0 | AE8: =IFERROR(AD8/AC8,0) -> 0
C9: Day 1 | D9: Hotel | J9: Oslo: Check in to your accommodation for a 1 night stay - Centrally located 3/4-star hotel - Standard Room - Breakfast included | Q9: 150 | R9: 1 | S9: =+Q9*R9 -> 150 | T9: 0 | U9: =S9*(1-T9) -> 150 | V9: EUR | W9: =IFERROR(VLOOKUP(V9,Curr!$B$2:$C$13,2,FALSE),0) -> 11.2 | X9: =U9*W9 -> 1680 | Y9: =Q9/0.85 -> 176.47059 | Z9: =+Y9*R9 -> 176.47059 | AA9: EUR | AB9: =IFERROR(VLOOKUP(AA9,Curr!$B$2:$C$13,2,FALSE),0) -> 11.2 | AC9: =+Y9*AB9*R9 -> 1976.4706 | AD9: =+AC9-X9 -> 296.47059 | AE9: =IFERROR(AD9/AC9,0) -> 0.15
C10: Day 1 | D10: Leisure | J10: Oslo: Spend time at leisure | Q10: 0 | R10: 0 | S10: =+Q10*R10 -> 0 | T10: 0 | U10: =S10*(1-T10) -> 0 | V10: EUR | W10: =IFERROR(VLOOKUP(V10,Curr!$B$2:$C$13,2,FALSE),0) -> 11.2 | X10: =U10*W10 -> 0 | Y10: =Q10 -> 0 | Z10: =+Y10*R10 -> 0 | AA10: EUR | AB10: =IFERROR(VLOOKUP(AA10,Curr!$B$2:$C$13,2,FALSE),0) -> 11.2 | AC10: =+Y10*AB10*R10 -> 0 | AD10: =+AC10-X10 -> 0 | AE10: =IFERROR(AD10/AC10,0) -> 0
S11: =+Q11*R11 -> 0 | T11: 0 | U11: =S11*(1-T11) -> 0 | V11: EUR | W11: =IFERROR(VLOOKUP(V11,Curr!$B$2:$C$13,2,FALSE),0) -> 11.2 | X11: =U11*W11 -> 0 | Y11: =Q11 -> 0 | Z11: =+Y11*R11 -> 0 | AA11: EUR | AB11: =IFERROR(VLOOKUP(AA11,Curr!$B$2:$C$13,2,FALSE),0) -> 11.2 | AC11: =+Y11*AB11*R11 -> 0 | AD11: =+AC11-X11 -> 0 | AE11: =IFERROR(AD11/AC11,0) -> 0
C12: Day 2 | D12: Transfer | J12: Oslo: Self transfer to Oslo Central Station | Q12: 0 | R12: 0 | S12: =+Q12*R12 -> 0 | T12: 0 | U12: =S12*(1-T12) -> 0 | V12: EUR | W12: =IFERROR(VLOOKUP(V12,Curr!$B$2:$C$13,2,FALSE),0) -> 11.2 | X12: =U12*W12 -> 0 | Y12: =Q12 -> 0 | Z12: =+Y12*R12 -> 0 | AA12: EUR | AB12: =IFERROR(VLOOKUP(AA12,Curr!$B$2:$C$13,2,FALSE),0) -> 11.2 | AC12: =+Y12*AB12*R12 -> 0 | AD12: =+AC12-X12 -> 0 | AE12: =IFERROR(AD12/AC12,0) -> 0
C13: Day 2 | D13: Train | J13: Oslo: Scenic Long Distance Train transfer to Bergen - Time: 08:25 am - 3:00 pm - Includes: Tickets | O13: x | P13: https://www.vy.no/#reisesok | Q13: 2400 | R13: 1 | S13: =+Q13*R13 -> 2400 | T13: 0 | U13: =S13*(1-T13) -> 2400 | V13: NOK | W13: =IFERROR(VLOOKUP(V13,Curr!$B$2:$C$13,2,FALSE),0) -> 1 | X13: =U13*W13 -> 2400 | Y13: =Q13/11.3/0.8 -> 265.48673 | Z13: =+Y13*R13 -> 265.48673 | AA13: EUR | AB13: =IFERROR(VLOOKUP(AA13,Curr!$B$2:$C$13,2,FALSE),0) -> 11.2 | AC13: =+Y13*AB13*R13 -> 2973.4513 | AD13: =+AC13-X13 -> 573.45133 | AE13: =IFERROR(AD13/AC13,0) -> 0.19285714
C14: Day 2 | D14: Transfer | J14: Bergen: Self transfer to your accommodation | Q14: 0 | R14: 0 | S14: =+Q14*R14 -> 0 | T14: 0 | U14: =S14*(1-T14) -> 0 | V14: EUR | W14: =IFERROR(VLOOKUP(V14,Curr!$B$2:$C$13,2,FALSE),0) -> 11.2 | X14: =U14*W14 -> 0 | Y14: =Q14 -> 0 | Z14: =+Y14*R14 -> 0 | AA14: EUR | AB14: =IFERROR(VLOOKUP(AA14,Curr!$B$2:$C$13,2,FALSE),0) -> 11.2 | AC14: =+Y14*AB14*R14 -> 0 | AD14: =+AC14-X14 -> 0 | AE14: =IFERROR(AD14/AC14,0) -> 0
C15: Day 2 | D15: Hotel | J15: Bergen: Check in to your accommodation for a 2 night stay - Centrally located 3/4-star hotel - Standard Room - Breakfast included | Q15: 280 | R15: 1 | S15: =+Q15*R15 -> 280 | T15: 0 | U15: =S15*(1-T15) -> 280 | V15: EUR | W15: =IFERROR(VLOOKUP(V15,Curr!$B$2:$C$13,2,FALSE),0) -> 11.2 | X15: =U15*W15 -> 3136 | Y15: =Q15/0.85 -> 329.41176 | Z15: =+Y15*R15 -> 329.41176 | AA15: EUR | AB15: =IFERROR(VLOOKUP(AA15,Curr!$B$2:$C$13,2,FALSE),0) -> 11.2 | AC15: =+Y15*AB15*R15 -> 3689.4118 | AD15: =+AC15-X15 -> 553.41176 | AE15: =IFERROR(AD15/AC15,0) -> 0.15
C16: Day 2 | D16: Leisure | J16: Bergen: Spend time at leisure | Q16: 0 | R16: 0 | S16: =+Q16*R16 -> 0 | T16: 0 | U16: =S16*(1-T16) -> 0 | V16: EUR | W16: =IFERROR(VLOOKUP(V16,Curr!$B$2:$C$13,2,FALSE),0) -> 11.2 | X16: =U16*W16 -> 0 | Y16: =Q16 -> 0 | Z16: =+Y16*R16 -> 0 | AA16: EUR | AB16: =IFERROR(VLOOKUP(AA16,Curr!$B$2:$C$13,2,FALSE),0) -> 11.2 | AC16: =+Y16*AB16*R16 -> 0 | AD16: =+AC16-X16 -> 0 | AE16: =IFERROR(AD16/AC16,0) -> 0
S17: =+Q17*R17 -> 0 | T17: 0 | U17: =S17*(1-T17) -> 0 | V17: EUR | W17: =IFERROR(VLOOKUP(V17,Curr!$B$2:$C$13,2,FALSE),0) -> 11.2 | X17: =U17*W17 -> 0 | Y17: =Q17 -> 0 | Z17: =+Y17*R17 -> 0 | AA17: EUR | AB17: =IFERROR(VLOOKUP(AA17,Curr!$B$2:$C$13,2,FALSE),0) -> 11.2 | AC17: =+Y17*AB17*R17 -> 0 | AD17: =+AC17-X17 -> 0 | AE17: =IFERROR(AD17/AC17,0) -> 0
C18: Day 3 | D18: Activity | J18: Bergen: 2 hr walk Through Bergen Past & Present - Time: 10:00 am - 12:00 pm - Meeting point: Bradbenken 1 - Includes: Profesional Guide | O18: x | P18: https://www.ilovebergen.net/tour/a-walk-through-bergen-past-present/ | Q18: 290 | R18: 2 | S18: =+Q18*R18 -> 580 | T18: 0.2 | U18: =S18*(1-T18) -> 464 | V18: NOK | W18: =IFERROR(VLOOKUP(V18,Curr!$B$2:$C$13,2,FALSE),0) -> 1 | X18: =U18*W18 -> 464 | Y18: =Q18/11.3/0.64 -> 40.099558 | Z18: =+Y18*R18 -> 80.199115 | AA18: EUR | AB18: =IFERROR(VLOOKUP(AA18,Curr!$B$2:$C$13,2,FALSE),0) -> 11.2 | AC18: =+Y18*AB18*R18 -> 898.23009 | AD18: =+AC18-X18 -> 434.23009 | AE18: =IFERROR(AD18/AC18,0) -> 0.48342857
C19: Day 3 | D19: Activity | J19: Bergen: Fløibanen Funicual - Time: Flexible - Meeting point: Vetrlidsallmenningen 23A - Includes: Tickets | O19: x | P19: https://www.floyen.no/en/floibanen/buy-tickets/ | Q19: 175 | R19: 2 | S19: =+Q19*R19 -> 350 | T19: 0 | U19: =S19*(1-T19) -> 350 | V19: NOK | W19: =IFERROR(VLOOKUP(V19,Curr!$B$2:$C$13,2,FALSE),0) -> 1 | X19: =U19*W19 -> 350 | Y19: =Q19/11.3/0.5 -> 30.973451 | Z19: =+Y19*R19 -> 61.946903 | AA19: EUR | AB19: =IFERROR(VLOOKUP(AA19,Curr!$B$2:$C$13,2,FALSE),0) -> 11.2 | AC19: =+Y19*AB19*R19 -> 693.80531 | AD19: =+AC19-X19 -> 343.80531 | AE19: =IFERROR(AD19/AC19,0) -> 0.49553571
C20: Day 3 | D20: Leisure | J20: Bergen: Spend time at leisure | Q20: 0 | R20: 0 | S20: =+Q20*R20 -> 0 | T20: 0 | U20: =S20*(1-T20) -> 0 | V20: EUR | W20: =IFERROR(VLOOKUP(V20,Curr!$B$2:$C$13,2,FALSE),0) -> 11.2 | X20: =U20*W20 -> 0 | Y20: =Q20 -> 0 | Z20: =+Y20*R20 -> 0 | AA20: EUR | AB20: =IFERROR(VLOOKUP(AA20,Curr!$B$2:$C$13,2,FALSE),0) -> 11.2 | AC20: =+Y20*AB20*R20 -> 0 | AD20: =+AC20-X20 -> 0 | AE20: =IFERROR(AD20/AC20,0) -> 0
S21: =+Q21*R21 -> 0 | T21: 0 | U21: =S21*(1-T21) -> 0 | V21: EUR | W21: =IFERROR(VLOOKUP(V21,Curr!$B$2:$C$13,2,FALSE),0) -> 11.2 | X21: =U21*W21 -> 0 | Y21: =Q21 -> 0 | Z21: =+Y21*R21 -> 0 | AA21: EUR | AB21: =IFERROR(VLOOKUP(AA21,Curr!$B$2:$C$13,2,FALSE),0) -> 11.2 | AC21: =+Y21*AB21*R21 -> 0 | AD21: =+AC21-X21 -> 0 | AE21: =IFERROR(AD21/AC21,0) -> 0
C22: Day 4 | D22: Transfer | J22: Bergen: Self transfer to Bergen Airport | Q22: 0 | R22: 0 | S22: =+Q22*R22 -> 0 | T22: 0 | U22: =S22*(1-T22) -> 0 | V22: EUR | W22: =IFERROR(VLOOKUP(V22,Curr!$B$2:$C$13,2,FALSE),0) -> 11.2 | X22: =U22*W22 -> 0 | Y22: =Q22 -> 0 | Z22: =+Y22*R22 -> 0 | AA22: EUR | AB22: =IFERROR(VLOOKUP(AA22,Curr!$B$2:$C$13,2,FALSE),0) -> 11.2 | AC22: =+Y22*AB22*R22 -> 0 | AD22: =+AC22-X22 -> 0 | AE22: =IFERROR(AD22/AC22,0) -> 0
C23: Day 4 | D23: Flight | J23: Bergen: Flight to Tromsø - Time: Date dependant - Luggage included: 1 x 23 kg check in and 1 x 8 kg carry on per person | O23: x | Q23: 1800 | R23: 2 | S23: =+Q23*R23 -> 3600 | T23: 0 | U23: =S23*(1-T23) -> 3600 | V23: NOK | W23: =IFERROR(VLOOKUP(V23,Curr!$B$2:$C$13,2,FALSE),0) -> 1 | X23: =U23*W23 -> 3600 | Y23: =Q23/11.3/0.8 -> 199.11504 | Z23: =+Y23*R23 -> 398.23009 | AA23: EUR | AB23: =IFERROR(VLOOKUP(AA23,Curr!$B$2:$C$13,2,FALSE),0) -> 11.2 | AC23: =+Y23*AB23*R23 -> 4460.177 | AD23: =+AC23-X23 -> 860.17699 | AE23: =IFERROR(AD23/AC23,0) -> 0.19285714
C24: Day 4 | D24: Transfer | J24: Tromsø: Self transfer to your accommodation | Q24: 0 | R24: 0 | S24: =+Q24*R24 -> 0 | T24: 0 | U24: =S24*(1-T24) -> 0 | V24: NOK | W24: =IFERROR(VLOOKUP(V24,Curr!$B$2:$C$13,2,FALSE),0) -> 1 | X24: =U24*W24 -> 0 | Y24: =Q24/11.3/0.8 -> 0 | Z24: =+Y24*R24 -> 0 | AA24: EUR | AB24: =IFERROR(VLOOKUP(AA24,Curr!$B$2:$C$13,2,FALSE),0) -> 11.2 | AC24: =+Y24*AB24*R24 -> 0 | AD24: =+AC24-X24 -> 0 | AE24: =IFERROR(AD24/AC24,0) -> 0
C25: Day 4 | D25: Hotel | J25: Tromsø: Check in to your accommodation for a 2 night stay - Centrally located 3/4-star hotel - Standard Room - Breakfast included | Q25: 500 | R25: 1 | S25: =+Q25*R25 -> 500 | T25: 0 | U25: =S25*(1-T25) -> 500 | V25: EUR | W25: =IFERROR(VLOOKUP(V25,Curr!$B$2:$C$13,2,FALSE),0) -> 11.2 | X25: =U25*W25 -> 5600 | Y25: =Q25/0.85 -> 588.23529 | Z25: =+Y25*R25 -> 588.23529 | AA25: EUR | AB25: =IFERROR(VLOOKUP(AA25,Curr!$B$2:$C$13,2,FALSE),0) -> 11.2 | AC25: =+Y25*AB25*R25 -> 6588.2353 | AD25: =+AC25-X25 -> 988.23529 | AE25: =IFERROR(AD25/AC25,0) -> 0.15
C26: Day 4 | D26: Leisure | J26: Tromsø: Spend time at leisure | Q26: 0 | R26: 0 | S26: =+Q26*R26 -> 0 | T26: 0 | U26: =S26*(1-T26) -> 0 | V26: EUR | W26: =IFERROR(VLOOKUP(V26,Curr!$B$2:$C$13,2,FALSE),0) -> 11.2 | X26: =U26*W26 -> 0 | Y26: =Q26 -> 0 | Z26: =+Y26*R26 -> 0 | AA26: EUR | AB26: =IFERROR(VLOOKUP(AA26,Curr!$B$2:$C$13,2,FALSE),0) -> 11.2 | AC26: =+Y26*AB26*R26 -> 0 | AD26: =+AC26-X26 -> 0 | AE26: =IFERROR(AD26/AC26,0) -> 0
C27: Day 4 | D27: Activity | J27: Tromsø: Northern Lights Cruise with Silent Electric Ship - Time: 7:00 pm - 10:00 pm - Meeting point: Kaigata 6 - Includes: Departure from central Tromsø, 3-hour fjord cruise, Light meal (soup and bread) and water, English speaking guides, Warm indoor saloons, Free wifi, Toilets | O27: x | P27: https://booknordics.com/norway/northern-norway/tromso-region/northern-lights-cruise-electric-ship | Q27: 105 | R27: 2 | S27: =+Q27*R27 -> 210 | T27: 0.2 | U27: =S27*(1-T27) -> 168 | V27: EUR | W27: =IFERROR(VLOOKUP(V27,Curr!$B$2:$C$13,2,FALSE),0) -> 11.2 | X27: =U27*W27 -> 1881.6 | Y27: =Q27 -> 105 | Z27: =+Y27*R27 -> 210 | AA27: EUR | AB27: =IFERROR(VLOOKUP(AA27,Curr!$B$2:$C$13,2,FALSE),0) -> 11.2 | AC27: =+Y27*AB27*R27 -> 2352 | AD27: =+AC27-X27 -> 470.4 | AE27: =IFERROR(AD27/AC27,0) -> 0.2
S28: =+Q28*R28 -> 0 | T28: 0 | U28: =S28*(1-T28) -> 0 | V28: EUR | W28: =IFERROR(VLOOKUP(V28,Curr!$B$2:$C$13,2,FALSE),0) -> 11.2 | X28: =U28*W28 -> 0 | Y28: =Q28 -> 0 | Z28: =+Y28*R28 -> 0 | AA28: EUR | AB28: =IFERROR(VLOOKUP(AA28,Curr!$B$2:$C$13,2,FALSE),0) -> 11.2 | AC28: =+Y28*AB28*R28 -> 0 | AD28: =+AC28-X28 -> 0 | AE28: =IFERROR(AD28/AC28,0) -> 0
C29: Day 5 | D29: Activity | J29: Tromsø: Reindeer Feeding and Sámi Culture - Time: 09:45 am - 2:30 pm - Meeting point: Radisson Blu Hotel's main entrance (Sjøgata 7) - Includes: Scenic transfers (45 min each way), Knowledgeable English and Norwegian speaking guide, Feeding the herd at our camp, Hot beverages and hot meal (traditional Sámi stew or vegetable/lentil soup), Cultural introduction about Sámi history and daily life, A chance to see the northern lights from our camp, Thermal suit and warm snow boots | O29: x | P29: https://www.tromsolapland.no/activities/reindeer-feeding-and-sami-culture | Q29: 1695 | R29: 2 | S29: =+Q29*R29 -> 3390 | T29: 0.2 | U29: =S29*(1-T29) -> 2712 | V29: NOK | W29: =IFERROR(VLOOKUP(V29,Curr!$B$2:$C$13,2,FALSE),0) -> 1 | X29: =U29*W29 -> 2712 | Y29: =Q29/11.3 -> 150 | Z29: =+Y29*R29 -> 300 | AA29: EUR | AB29: =IFERROR(VLOOKUP(AA29,Curr!$B$2:$C$13,2,FALSE),0) -> 11.2 | AC29: =+Y29*AB29*R29 -> 3360 | AD29: =+AC29-X29 -> 648 | AE29: =IFERROR(AD29/AC29,0) -> 0.19285714
C30: Day 5 | D30: Leisure | J30: Tromsø: Spend time at leisure | Q30: 0 | R30: 0 | S30: =+Q30*R30 -> 0 | T30: 0 | U30: =S30*(1-T30) -> 0 | V30: EUR | W30: =IFERROR(VLOOKUP(V30,Curr!$B$2:$C$13,2,FALSE),0) -> 11.2 | X30: =U30*W30 -> 0 | Y30: =Q30 -> 0 | Z30: =+Y30*R30 -> 0 | AA30: EUR | AB30: =IFERROR(VLOOKUP(AA30,Curr!$B$2:$C$13,2,FALSE),0) -> 11.2 | AC30: =+Y30*AB30*R30 -> 0 | AD30: =+AC30-X30 -> 0 | AE30: =IFERROR(AD30/AC30,0) -> 0
C31: Day 5 | D31: Activity | J31: Tromsø: All-Evening Northern Lights Hunt by Minibus or Bus - Time: 7:00 pm - 12:00 am - Meeting point: Kaigata 4 - Includes: Knowledgeable, English-speaking guides, Photos shared with you after the tour, Thermo clothing and warm gear, Light snacks and warm/cold beverages, Drop-off at hotel, up to 5 km from Tromsø | O31: x | P31: https://booknordics.com/norway/northern-norway/tromso-region/full-day-magic-of-the-arctic-lights-in-tromso | Q31: 120 | R31: 2 | S31: =+Q31*R31 -> 240 | T31: 0.2 | U31: =S31*(1-T31) -> 192 | V31: EUR | W31: =IFERROR(VLOOKUP(V31,Curr!$B$2:$C$13,2,FALSE),0) -> 11.2 | X31: =U31*W31 -> 2150.4 | Y31: =Q31 -> 120 | Z31: =+Y31*R31 -> 240 | AA31: EUR | AB31: =IFERROR(VLOOKUP(AA31,Curr!$B$2:$C$13,2,FALSE),0) -> 11.2 | AC31: =+Y31*AB31*R31 -> 2688 | AD31: =+AC31-X31 -> 537.6 | AE31: =IFERROR(AD31/AC31,0) -> 0.2
S32: =+Q32*R32 -> 0 | T32: 0 | U32: =S32*(1-T32) -> 0 | V32: EUR | W32: =IFERROR(VLOOKUP(V32,Curr!$B$2:$C$13,2,FALSE),0) -> 11.2 | X32: =U32*W32 -> 0 | Y32: =Q32 -> 0 | Z32: =+Y32*R32 -> 0 | AA32: EUR | AB32: =IFERROR(VLOOKUP(AA32,Curr!$B$2:$C$13,2,FALSE),0) -> 11.2 | AC32: =+Y32*AB32*R32 -> 0 | AD32: =+AC32-X32 -> 0 | AE32: =IFERROR(AD32/AC32,0) -> 0
C33: Day 6 | D33: Leisure | J33: Tromsø: Spend time at leisure | Q33: 0 | R33: 0 | S33: =+Q33*R33 -> 0 | T33: 0 | U33: =S33*(1-T33) -> 0 | V33: EUR | W33: =IFERROR(VLOOKUP(V33,Curr!$B$2:$C$13,2,FALSE),0) -> 11.2 | X33: =U33*W33 -> 0 | Y33: =Q33 -> 0 | Z33: =+Y33*R33 -> 0 | AA33: EUR | AB33: =IFERROR(VLOOKUP(AA33,Curr!$B$2:$C$13,2,FALSE),0) -> 11.2 | AC33: =+Y33*AB33*R33 -> 0 | AD33: =+AC33-X33 -> 0 | AE33: =IFERROR(AD33/AC33,0) -> 0
C34: Day 6 | D34: Transfer | J34: Tromsø: Self transfer to Tromsø Bus Terminal Prostneset | Q34: 0 | R34: 0 | S34: =+Q34*R34 -> 0 | T34: 0 | U34: =S34*(1-T34) -> 0 | V34: EUR | W34: =IFERROR(VLOOKUP(V34,Curr!$B$2:$C$13,2,FALSE),0) -> 11.2 | X34: =U34*W34 -> 0 | Y34: =Q34 -> 0 | Z34: =+Y34*R34 -> 0 | AA34: EUR | AB34: =IFERROR(VLOOKUP(AA34,Curr!$B$2:$C$13,2,FALSE),0) -> 11.2 | AC34: =+Y34*AB34*R34 -> 0 | AD34: =+AC34-X34 -> 0 | AE34: =IFERROR(AD34/AC34,0) -> 0
C35: Day 6 | D35: Coach | J35: Tromsø: Long distance panorama coach transfer to Alta - Bus 150 - Time: 4:00 pm - 10:20 pm - Excludes: Tickets (To be bought on site) | Q35: 0 | R35: 0 | S35: =+Q35*R35 -> 0 | T35: 0 | U35: =S35*(1-T35) -> 0 | V35: EUR | W35: =IFERROR(VLOOKUP(V35,Curr!$B$2:$C$13,2,FALSE),0) -> 11.2 | X35: =U35*W35 -> 0 | Y35: =Q35 -> 0 | Z35: =+Y35*R35 -> 0 | AA35: EUR | AB35: =IFERROR(VLOOKUP(AA35,Curr!$B$2:$C$13,2,FALSE),0) -> 11.2 | AC35: =+Y35*AB35*R35 -> 0 | AD35: =+AC35-X35 -> 0 | AE35: =IFERROR(AD35/AC35,0) -> 0
C36: Day 6 | D36: Transfer | J36: Alta: Self transfer to your accommodation | Q36: 0 | R36: 0 | S36: =+Q36*R36 -> 0 | T36: 0 | U36: =S36*(1-T36) -> 0 | V36: EUR | W36: =IFERROR(VLOOKUP(V36,Curr!$B$2:$C$13,2,FALSE),0) -> 11.2 | X36: =U36*W36 -> 0 | Y36: =Q36 -> 0 | Z36: =+Y36*R36 -> 0 | AA36: EUR | AB36: =IFERROR(VLOOKUP(AA36,Curr!$B$2:$C$13,2,FALSE),0) -> 11.2 | AC36: =+Y36*AB36*R36 -> 0 | AD36: =+AC36-X36 -> 0 | AE36: =IFERROR(AD36/AC36,0) -> 0
C37: Day 6 | D37: Hotel | J37: Alta: Check in to your accommodation for a 2 night stay - Centrally located 3/4-star hotel - Standard Room - Breakfast included | Q37: 280 | R37: 1 | S37: =+Q37*R37 -> 280 | T37: 0 | U37: =S37*(1-T37) -> 280 | V37: EUR | W37: =IFERROR(VLOOKUP(V37,Curr!$B$2:$C$13,2,FALSE),0) -> 11.2 | X37: =U37*W37 -> 3136 | Y37: =Q37/0.85 -> 329.41176 | Z37: =+Y37*R37 -> 329.41176 | AA37: EUR | AB37: =IFERROR(VLOOKUP(AA37,Curr!$B$2:$C$13,2,FALSE),0) -> 11.2 | AC37: =+Y37*AB37*R37 -> 3689.4118 | AD37: =+AC37-X37 -> 553.41176 | AE37: =IFERROR(AD37/AC37,0) -> 0.15
C38: Day 6 | D38: Leisure | J38: Alta: Spend time at leisure | Q38: 0 | R38: 0 | S38: =+Q38*R38 -> 0 | T38: 0 | U38: =S38*(1-T38) -> 0 | V38: EUR | W38: =IFERROR(VLOOKUP(V38,Curr!$B$2:$C$13,2,FALSE),0) -> 11.2 | X38: =U38*W38 -> 0 | Y38: =Q38 -> 0 | Z38: =+Y38*R38 -> 0 | AA38: EUR | AB38: =IFERROR(VLOOKUP(AA38,Curr!$B$2:$C$13,2,FALSE),0) -> 11.2 | AC38: =+Y38*AB38*R38 -> 0 | AD38: =+AC38-X38 -> 0 | AE38: =IFERROR(AD38/AC38,0) -> 0
S39: =+Q39*R39 -> 0 | T39: 0 | U39: =S39*(1-T39) -> 0 | V39: EUR | W39: =IFERROR(VLOOKUP(V39,Curr!$B$2:$C$13,2,FALSE),0) -> 11.2 | X39: =U39*W39 -> 0 | Y39: =Q39 -> 0 | Z39: =+Y39*R39 -> 0 | AA39: EUR | AB39: =IFERROR(VLOOKUP(AA39,Curr!$B$2:$C$13,2,FALSE),0) -> 11.2 | AC39: =+Y39*AB39*R39 -> 0 | AD39: =+AC39-X39 -> 0 | AE39: =IFERROR(AD39/AC39,0) -> 0
C40: Day 7 | D40: Activity | J40: Alta: Visit to Sorrisniva Igloo Hotel - Time: Flexible - Meeting point: Sorrisniva Arctic Wilderness Lodge - Includes: Entry ticket to explore Sorrisniva Igloo Hotel | O40: x | P40: https://booknordics.com/norway/northern-norway/alta-and-north-cape/entrance-ticket-igloo-hotel | Q40: 34 | R40: 2 | S40: =+Q40*R40 -> 68 | T40: 0.15 | U40: =S40*(1-T40) -> 57.8 | V40: EUR | W40: =IFERROR(VLOOKUP(V40,Curr!$B$2:$C$13,2,FALSE),0) -> 11.2 | X40: =U40*W40 -> 647.36 | Y40: =Q40 -> 34 | Z40: =+Y40*R40 -> 68 | AA40: EUR | AB40: =IFERROR(VLOOKUP(AA40,Curr!$B$2:$C$13,2,FALSE),0) -> 11.2 | AC40: =+Y40*AB40*R40 -> 761.6 | AD40: =+AC40-X40 -> 114.24 | AE40: =IFERROR(AD40/AC40,0) -> 0.15
C41: Day 7 | D41: Leisure | J41: Alta: Spend time at leisure | Q41: 0 | R41: 0 | S41: =+Q41*R41 -> 0 | T41: 0 | U41: =S41*(1-T41) -> 0 | V41: EUR | W41: =IFERROR(VLOOKUP(V41,Curr!$B$2:$C$13,2,FALSE),0) -> 11.2 | X41: =U41*W41 -> 0 | Y41: =Q41 -> 0 | Z41: =+Y41*R41 -> 0 | AA41: EUR | AB41: =IFERROR(VLOOKUP(AA41,Curr!$B$2:$C$13,2,FALSE),0) -> 11.2 | AC41: =+Y41*AB41*R41 -> 0 | AD41: =+AC41-X41 -> 0 | AE41: =IFERROR(AD41/AC41,0) -> 0
C42: Day 7 | D42: Activity | J42: Alta: Small Group Northern Lights Hunt - Time: 7:00 pm - 11:00 pm - Meeting point: Æventyr Booking Point - Includes: Professional guide, Northern Lights lectures and local history, Coffee / tea and snacks, Warm overalls for loan | O42: x | P42: https://www.aeventyr.no/activities/small-group-northern-lights-hunt | Q42: 2290 | R42: 2 | S42: =+Q42*R42 -> 4580 | T42: 0.15 | U42: =S42*(1-T42) -> 3893 | V42: NOK | W42: =IFERROR(VLOOKUP(V42,Curr!$B$2:$C$13,2,FALSE),0) -> 1 | X42: =U42*W42 -> 3893 | Y42: =Q42/11.3 -> 202.65487 | Z42: =+Y42*R42 -> 405.30973 | AA42: EUR | AB42: =IFERROR(VLOOKUP(AA42,Curr!$B$2:$C$13,2,FALSE),0) -> 11.2 | AC42: =+Y42*AB42*R42 -> 4539.469 | AD42: =+AC42-X42 -> 646.46903 | AE42: =IFERROR(AD42/AC42,0) -> 0.14241071
S43: =+Q43*R43 -> 0 | T43: 0 | U43: =S43*(1-T43) -> 0 | V43: EUR | W43: =IFERROR(VLOOKUP(V43,Curr!$B$2:$C$13,2,FALSE),0) -> 11.2 | X43: =U43*W43 -> 0 | Y43: =Q43 -> 0 | Z43: =+Y43*R43 -> 0 | AA43: EUR | AB43: =IFERROR(VLOOKUP(AA43,Curr!$B$2:$C$13,2,FALSE),0) -> 11.2 | AC43: =+Y43*AB43*R43 -> 0 | AD43: =+AC43-X43 -> 0 | AE43: =IFERROR(AD43/AC43,0) -> 0
C44: Day 8 | D44: Transfer | J44: Alta: Self transfer to Alta Airport | Q44: 0 | R44: 0 | S44: =+Q44*R44 -> 0 | T44: 0 | U44: =S44*(1-T44) -> 0 | V44: EUR | W44: =IFERROR(VLOOKUP(V44,Curr!$B$2:$C$13,2,FALSE),0) -> 11.2 | X44: =U44*W44 -> 0 | Y44: =Q44 -> 0 | Z44: =+Y44*R44 -> 0 | AA44: EUR | AB44: =IFERROR(VLOOKUP(AA44,Curr!$B$2:$C$13,2,FALSE),0) -> 11.2 | AC44: =+Y44*AB44*R44 -> 0 | AD44: =+AC44-X44 -> 0 | AE44: =IFERROR(AD44/AC44,0) -> 0
C45: Day 8 | D45: Departure | J45: Alta: Departure home | Q45: 0 | R45: 0 | S45: =+Q45*R45 -> 0 | T45: 0 | U45: =S45*(1-T45) -> 0 | V45: EUR | W45: =IFERROR(VLOOKUP(V45,Curr!$B$2:$C$13,2,FALSE),0) -> 11.2 | X45: =U45*W45 -> 0 | Y45: =Q45 -> 0 | Z45: =+Y45*R45 -> 0 | AA45: EUR | AB45: =IFERROR(VLOOKUP(AA45,Curr!$B$2:$C$13,2,FALSE),0) -> 11.2 | AC45: =+Y45*AB45*R45 -> 0 | AD45: =+AC45-X45 -> 0 | AE45: =IFERROR(AD45/AC45,0) -> 0
S46: =+Q46*R46 -> 0 | T46: 0 | U46: =S46*(1-T46) -> 0 | V46: EUR | W46: =IFERROR(VLOOKUP(V46,Curr!$B$2:$C$13,2,FALSE),0) -> 11.2 | X46: =U46*W46 -> 0 | Y46: =Q46 -> 0 | Z46: =+Y46*R46 -> 0 | AA46: EUR | AB46: =IFERROR(VLOOKUP(AA46,Curr!$B$2:$C$13,2,FALSE),0) -> 11.2 | AC46: =+Y46*AB46*R46 -> 0 | AD46: =+AC46-X46 -> 0 | AE46: =IFERROR(AD46/AC46,0) -> 0
S47: =+Q47*R47 -> 0 | T47: 0 | U47: =S47*(1-T47) -> 0 | V47: EUR | W47: =IFERROR(VLOOKUP(V47,Curr!$B$2:$C$13,2,FALSE),0) -> 11.2 | X47: =U47*W47 -> 0 | Y47: =Q47 -> 0 | Z47: =+Y47*R47 -> 0 | AA47: EUR | AB47: =IFERROR(VLOOKUP(AA47,Curr!$B$2:$C$13,2,FALSE),0) -> 11.2 | AC47: =+Y47*AB47*R47 -> 0 | AD47: =+AC47-X47 -> 0 | AE47: =IFERROR(AD47/AC47,0) -> 0
C48: Day 1 | D48: Transfer Package | J48: Oslo: Private transfer to your accommodation | Q48: 1750 | R48: 0 | S48: =+Q48*R48 -> 0 | T48: 0 | U48: =S48*(1-T48) -> 0 | V48: NOK | W48: =IFERROR(VLOOKUP(V48,Curr!$B$2:$C$13,2,FALSE),0) -> 1 | X48: =U48*W48 -> 0 | Y48: =Q48/11.3/0.8 -> 193.58407 | Z48: =+Y48*R48 -> 0 | AA48: EUR | AB48: =IFERROR(VLOOKUP(AA48,Curr!$B$2:$C$13,2,FALSE),0) -> 11.2 | AC48: =+Y48*AB48*R48 -> 0 | AD48: =+AC48-X48 -> 0 | AE48: =IFERROR(AD48/AC48,0) -> 0
C49: Day 2 | D49: Transfer Package | J49: Bergen: Private transfer to your accommodation | Q49: 1290 | R49: 0 | S49: =+Q49*R49 -> 0 | T49: 0.15 | U49: =S49*(1-T49) -> 0 | V49: NOK | W49: =IFERROR(VLOOKUP(V49,Curr!$B$2:$C$13,2,FALSE),0) -> 1 | X49: =U49*W49 -> 0 | Y49: =Q49/11.3/0.98 -> 116.48907 | Z49: =+Y49*R49 -> 0 | AA49: EUR | AB49: =IFERROR(VLOOKUP(AA49,Curr!$B$2:$C$13,2,FALSE),0) -> 11.2 | AC49: =+Y49*AB49*R49 -> 0 | AD49: =+AC49-X49 -> 0 | AE49: =IFERROR(AD49/AC49,0) -> 0
C50: Day 4 | D50: Transfer Package | J50: Bergen: Private transfer to Bergen Airport | Q50: 1690 | R50: 0 | S50: =+Q50*R50 -> 0 | T50: 0.15 | U50: =S50*(1-T50) -> 0 | V50: NOK | W50: =IFERROR(VLOOKUP(V50,Curr!$B$2:$C$13,2,FALSE),0) -> 1 | X50: =U50*W50 -> 0 | Y50: =Q50/11.3/0.98 -> 152.60972 | Z50: =+Y50*R50 -> 0 | AA50: EUR | AB50: =IFERROR(VLOOKUP(AA50,Curr!$B$2:$C$13,2,FALSE),0) -> 11.2 | AC50: =+Y50*AB50*R50 -> 0 | AD50: =+AC50-X50 -> 0 | AE50: =IFERROR(AD50/AC50,0) -> 0
C51: Day 4 | D51: Transfer Package | J51: Tromsø: Private transfer to your accommodation | Q51: 900 | R51: 0 | S51: =+Q51*R51 -> 0 | T51: 0 | U51: =S51*(1-T51) -> 0 | V51: NOK | W51: =IFERROR(VLOOKUP(V51,Curr!$B$2:$C$13,2,FALSE),0) -> 1 | X51: =U51*W51 -> 0 | Y51: =Q51/11.3/0.8 -> 99.557522 | Z51: =+Y51*R51 -> 0 | AA51: EUR | AB51: =IFERROR(VLOOKUP(AA51,Curr!$B$2:$C$13,2,FALSE),0) -> 11.2 | AC51: =+Y51*AB51*R51 -> 0 | AD51: =+AC51-X51 -> 0 | AE51: =IFERROR(AD51/AC51,0) -> 0
C52: Day 8 | D52: Transfer Package | J52: Alta: Private transfer to Alta Airport | Q52: 900 | R52: 0 | S52: =+Q52*R52 -> 0 | T52: 0 | U52: =S52*(1-T52) -> 0 | V52: NOK | W52: =IFERROR(VLOOKUP(V52,Curr!$B$2:$C$13,2,FALSE),0) -> 1 | X52: =U52*W52 -> 0 | Y52: =Q52/11.3/0.8 -> 99.557522 | Z52: =+Y52*R52 -> 0 | AA52: EUR | AB52: =IFERROR(VLOOKUP(AA52,Curr!$B$2:$C$13,2,FALSE),0) -> 11.2 | AC52: =+Y52*AB52*R52 -> 0 | AD52: =+AC52-X52 -> 0 | AE52: =IFERROR(AD52/AC52,0) -> 0
S53: =+Q53*R53 -> 0 | T53: 0 | U53: =S53*(1-T53) -> 0 | V53: EUR | W53: =IFERROR(VLOOKUP(V53,Curr!$B$2:$C$13,2,FALSE),0) -> 11.2 | X53: =U53*W53 -> 0 | Y53: =Q53 -> 0 | Z53: =+Y53*R53 -> 0 | AA53: EUR | AB53: =IFERROR(VLOOKUP(AA53,Curr!$B$2:$C$13,2,FALSE),0) -> 11.2 | AC53: =+Y53*AB53*R53 -> 0 | AD53: =+AC53-X53 -> 0 | AE53: =IFERROR(AD53/AC53,0) -> 0
S54: =+Q54*R54 -> 0 | T54: 0 | U54: =S54*(1-T54) -> 0 | V54: EUR | W54: =IFERROR(VLOOKUP(V54,Curr!$B$2:$C$13,2,FALSE),0) -> 11.2 | X54: =U54*W54 -> 0 | Y54: =Q54 -> 0 | Z54: =+Y54*R54 -> 0 | AA54: EUR | AB54: =IFERROR(VLOOKUP(AA54,Curr!$B$2:$C$13,2,FALSE),0) -> 11.2 | AC54: =+Y54*AB54*R54 -> 0 | AD54: =+AC54-X54 -> 0 | AE54: =IFERROR(AD54/AC54,0) -> 0
C55: Day 2 | D55: Activity Upgrade | J55: Oslo: Norway in a Nutshell to Bergen - Time: 08:00 am - 09:00 pm - Meeting point. Oslo Central Station - Includes: Train transfer Oslo to Myrdal, Train tranfser Myrdal to Flåm, Fjord Cruise Flåm to Gudvangen, Coach Transfer Gudvangen to Voss, Train transfer Voss to Bergen | O55: x | P55: https://www.fjordtours.com/en | Q55: 3250 | R55: 0 | S55: =+Q55*R55 -> 0 | T55: 0.08 | U55: =S55*(1-T55) -> 0 | V55: NOK | W55: =IFERROR(VLOOKUP(V55,Curr!$B$2:$C$13,2,FALSE),0) -> 1 | X55: =U55*W55 -> 0 | Y55: =Q55/11.3/0.9 -> 319.56735 | Z55: =+Y55*R55 -> 0 | AA55: EUR | AB55: =IFERROR(VLOOKUP(AA55,Curr!$B$2:$C$13,2,FALSE),0) -> 11.2 | AC55: =+Y55*AB55*R55 -> 0 | AD55: =+AC55-X55 -> 0 | AE55: =IFERROR(AD55/AC55,0) -> 0
C56: Day 2 | D56: Activity Upgrade | J56: Oslo: Norway in a Nutshell Porter Service - Includes: Luggage transfer from your accommodation in Oslo to your accommodaiton in Bergen | Q56: 450 | R56: 0 | S56: =+Q56*R56 -> 0 | T56: 0 | U56: =S56*(1-T56) -> 0 | V56: NOK | W56: =IFERROR(VLOOKUP(V56,Curr!$B$2:$C$13,2,FALSE),0) -> 1 | X56: =U56*W56 -> 0 | Y56: =Q56/11.3/0.8 -> 49.778761 | Z56: =+Y56*R56 -> 0 | AA56: EUR | AB56: =IFERROR(VLOOKUP(AA56,Curr!$B$2:$C$13,2,FALSE),0) -> 11.2 | AC56: =+Y56*AB56*R56 -> 0 | AD56: =+AC56-X56 -> 0 | AE56: =IFERROR(AD56/AC56,0) -> 0
C57: Day 3 | D57: Activity Upgrade | J57: Bergen: Mostraumen Majestic Fjord & Waterfall Cruise - Time: 12:00 pm - 4:00 pm - Meeting point: Strandkaien 13 - Includes: 4-hour panoramic fjord cruise, Expert captain navigating through the fjords, English-audio guide | O57: x | P57: https://booknordics.com/norway/western-fjord-norway/bergen-and-hardanger/mostraumen-fjord-waterfall-cruise | Q57: 71 | R57: 0 | S57: =+Q57*R57 -> 0 | T57: 0.2 | U57: =S57*(1-T57) -> 0 | V57: EUR | W57: =IFERROR(VLOOKUP(V57,Curr!$B$2:$C$13,2,FALSE),0) -> 11.2 | X57: =U57*W57 -> 0 | Y57: =Q57 -> 71 | Z57: =+Y57*R57 -> 0 | AA57: EUR | AB57: =IFERROR(VLOOKUP(AA57,Curr!$B$2:$C$13,2,FALSE),0) -> 11.2 | AC57: =+Y57*AB57*R57 -> 0 | AD57: =+AC57-X57 -> 0 | AE57: =IFERROR(AD57/AC57,0) -> 0
C58: Day 5 | D58: Activity Upgrade | J58: Tromsø: Reindeer Sledding, Reindeer Feeding and Sami Culture - Time: 09:45 am - 2:30 pm - Meeting point: Radisson Blu Hotel's main entrance (Sjøgata 7) - Includes: Scenic transfers (45 min each way), Knowledgeable English- and Norwegian-speaking guide, Thermal winter suit, warm boots, Reindeer sledding (approx. 30 min, depending on weather and snow conditions), Feeding the herd on our camp, Hot traditional Sámi meal (bithos) and hot drinks. Vegetarian option available on request, Cultural introduction about Sámi history and daily life | O58: x | P58: https://booknordics.com/norway/northern-norway/tromso-region/reindeer-sledding-reindeer-feeding-and-sami-culture-3 | Q58: 2195 | R58: 0 | S58: =+Q58*R58 -> 0 | T58: 0.2 | U58: =S58*(1-T58) -> 0 | V58: NOK | W58: =IFERROR(VLOOKUP(V58,Curr!$B$2:$C$13,2,FALSE),0) -> 1 | X58: =U58*W58 -> 0 | Y58: =Q58/11.3 -> 194.24779 | Z58: =+Y58*R58 -> 0 | AA58: EUR | AB58: =IFERROR(VLOOKUP(AA58,Curr!$B$2:$C$13,2,FALSE),0) -> 11.2 | AC58: =+Y58*AB58*R58 -> 0 | AD58: =+AC58-X58 -> 0 | AE58: =IFERROR(AD58/AC58,0) -> 0
C59: Day 7 | D59: Activity Upgrade | J59: Alta: Dog Sledding in Alta - Time: 10:00 am - 2:00 pm - Meeting point: Æventyr Booking Point - Includes: Dog Sledding: Approximately 50 minutes on the trail, Transport: From Alta to Gargia and back (approximately 30 minutes each way), Dog Sledding Training and Equipment: Learn the basics of dog sledding and get equipped with the necessary gear, Warm Clothing: Stay cozy in the Arctic cold, Coffee & Tea, Storytelling: Discover the history of dog sledding and Gargia, Assistance with Dressing/Undressing the Dogs, Meet the Huskies | O59: x | P59: https://www.aeventyr.no/activities/embark-on-an-arctic-adventure-dog-sledding-in-alta | Q59: 2990 | R59: 0 | S59: =+Q59*R59 -> 0 | T59: 0.15 | U59: =S59*(1-T59) -> 0 | V59: NOK | W59: =IFERROR(VLOOKUP(V59,Curr!$B$2:$C$13,2,FALSE),0) -> 1 | X59: =U59*W59 -> 0 | Y59: =Q59/11.3 -> 264.60177 | Z59: =+Y59*R59 -> 0 | AA59: EUR | AB59: =IFERROR(VLOOKUP(AA59,Curr!$B$2:$C$13,2,FALSE),0) -> 11.2 | AC59: =+Y59*AB59*R59 -> 0 | AD59: =+AC59-X59 -> 0 | AE59: =IFERROR(AD59/AC59,0) -> 0
C60: Day 7 | D60: Activity Upgrade | J60: Alta: Northern Lights Dog Sledding - Time: 7:00 pm - 11:00 pm - Meeting point: Æventyr Booking Point - Includes: Dog Sledding: Approximately 50 minutes on the trail, Transport: From Alta to Gargia and back (approximately 30 minutes each way), Dog Sledding Training and Equipment: Learn the basics of dog sledding and get equipped with the necessary gear, Warm Clothing: Stay cozy in the Arctic cold, Coffee & Tea, Storytelling: Discover the history of dog sledding and Gargia, Assistance with Dressing/Undressing the Dogs | O60: x | P60: https://www.aeventyr.no/activities/northern-lights-dog-sledding-trip-in-alta | Q60: 3390 | R60: 0 | S60: =+Q60*R60 -> 0 | T60: 0.15 | U60: =S60*(1-T60) -> 0 | V60: NOK | W60: =IFERROR(VLOOKUP(V60,Curr!$B$2:$C$13,2,FALSE),0) -> 1 | X60: =U60*W60 -> 0 | Y60: =Q60/11.3 -> 300 | Z60: =+Y60*R60 -> 0 | AA60: EUR | AB60: =IFERROR(VLOOKUP(AA60,Curr!$B$2:$C$13,2,FALSE),0) -> 11.2 | AC60: =+Y60*AB60*R60 -> 0 | AD60: =+AC60-X60 -> 0 | AE60: =IFERROR(AD60/AC60,0) -> 0
S61: =+Q61*R61 -> 0 | T61: 0 | U61: =S61*(1-T61) -> 0 | V61: EUR | W61: =IFERROR(VLOOKUP(V61,Curr!$B$2:$C$13,2,FALSE),0) -> 11.2 | X61: =U61*W61 -> 0 | Y61: =Q61 -> 0 | Z61: =+Y61*R61 -> 0 | AA61: EUR | AB61: =IFERROR(VLOOKUP(AA61,Curr!$B$2:$C$13,2,FALSE),0) -> 11.2 | AC61: =+Y61*AB61*R61 -> 0 | AD61: =+AC61-X61 -> 0 | AE61: =IFERROR(AD61/AC61,0) -> 0
S62: =+Q62*R62 -> 0 | T62: 0 | U62: =S62*(1-T62) -> 0 | V62: EUR | W62: =IFERROR(VLOOKUP(V62,Curr!$B$2:$C$13,2,FALSE),0) -> 11.2 | X62: =U62*W62 -> 0 | Y62: =Q62 -> 0 | Z62: =+Y62*R62 -> 0 | AA62: EUR | AB62: =IFERROR(VLOOKUP(AA62,Curr!$B$2:$C$13,2,FALSE),0) -> 11.2 | AC62: =+Y62*AB62*R62 -> 0 | AD62: =+AC62-X62 -> 0 | AE62: =IFERROR(AD62/AC62,0) -> 0
S63: =+Q63*R63 -> 0 | T63: 0 | U63: =S63*(1-T63) -> 0 | V63: EUR | W63: =IFERROR(VLOOKUP(V63,Curr!$B$2:$C$13,2,FALSE),0) -> 11.2 | X63: =U63*W63 -> 0 | Y63: =Q63 -> 0 | Z63: =+Y63*R63 -> 0 | AA63: EUR | AB63: =IFERROR(VLOOKUP(AA63,Curr!$B$2:$C$13,2,FALSE),0) -> 11.2 | AC63: =+Y63*AB63*R63 -> 0 | AD63: =+AC63-X63 -> 0 | AE63: =IFERROR(AD63/AC63,0) -> 0
S64: =+Q64*R64 -> 0 | T64: 0 | U64: =S64*(1-T64) -> 0 | V64: EUR | W64: =IFERROR(VLOOKUP(V64,Curr!$B$2:$C$13,2,FALSE),0) -> 11.2 | X64: =U64*W64 -> 0 | Y64: =Q64 -> 0 | Z64: =+Y64*R64 -> 0 | AA64: EUR | AB64: =IFERROR(VLOOKUP(AA64,Curr!$B$2:$C$13,2,FALSE),0) -> 11.2 | AC64: =+Y64*AB64*R64 -> 0 | AD64: =+AC64-X64 -> 0 | AE64: =IFERROR(AD64/AC64,0) -> 0
S65: =+Q65*R65 -> 0 | T65: 0 | U65: =S65*(1-T65) -> 0 | V65: EUR | W65: =IFERROR(VLOOKUP(V65,Curr!$B$2:$C$13,2,FALSE),0) -> 11.2 | X65: =U65*W65 -> 0 | Y65: =Q65 -> 0 | Z65: =+Y65*R65 -> 0 | AA65: EUR | AB65: =IFERROR(VLOOKUP(AA65,Curr!$B$2:$C$13,2,FALSE),0) -> 11.2 | AC65: =+Y65*AB65*R65 -> 0 | AD65: =+AC65-X65 -> 0 | AE65: =IFERROR(AD65/AC65,0) -> 0
S66: =+Q66*R66 -> 0 | T66: 0 | U66: =S66*(1-T66) -> 0 | V66: EUR | W66: =IFERROR(VLOOKUP(V66,Curr!$B$2:$C$13,2,FALSE),0) -> 11.2 | X66: =U66*W66 -> 0 | Y66: =Q66 -> 0 | Z66: =+Y66*R66 -> 0 | AA66: EUR | AB66: =IFERROR(VLOOKUP(AA66,Curr!$B$2:$C$13,2,FALSE),0) -> 11.2 | AC66: =+Y66*AB66*R66 -> 0 | AD66: =+AC66-X66 -> 0 | AE66: =IFERROR(AD66/AC66,0) -> 0
S67: =+Q67*R67 -> 0 | T67: 0 | U67: =S67*(1-T67) -> 0 | V67: EUR | W67: =IFERROR(VLOOKUP(V67,Curr!$B$2:$C$13,2,FALSE),0) -> 11.2 | X67: =U67*W67 -> 0 | Y67: =Q67 -> 0 | Z67: =+Y67*R67 -> 0 | AA67: EUR | AB67: =IFERROR(VLOOKUP(AA67,Curr!$B$2:$C$13,2,FALSE),0) -> 11.2 | AC67: =+Y67*AB67*R67 -> 0 | AD67: =+AC67-X67 -> 0 | AE67: =IFERROR(AD67/AC67,0) -> 0
S68: =+Q68*R68 -> 0 | T68: 0 | U68: =S68*(1-T68) -> 0 | V68: EUR | W68: =IFERROR(VLOOKUP(V68,Curr!$B$2:$C$13,2,FALSE),0) -> 11.2 | X68: =U68*W68 -> 0 | Y68: =Q68 -> 0 | Z68: =+Y68*R68 -> 0 | AA68: EUR | AB68: =IFERROR(VLOOKUP(AA68,Curr!$B$2:$C$13,2,FALSE),0) -> 11.2 | AC68: =+Y68*AB68*R68 -> 0 | AD68: =+AC68-X68 -> 0 | AE68: =IFERROR(AD68/AC68,0) -> 0
B70: Totals | D70: x | E70: x | F70: x | G70: x | H70: x | I70: x | J70: x | K70: x | L70: x | M70: x | N70: x | O70: x | P70: x | Q70: x | R70: x | S70: x | T70: x | U70: x | V70: x | W70: x | X70: x | Y70: x | Z70: =SUM(Z7:Z68) -> 3452.702 | AC70: =SUM(AC7:AC68) -> 38670.262 | AD70: =SUM(AD7:AD68) -> 7019.9022 | AE70: =IFERROR(AD70/AC70,0) -> 0.18153231 | AF70: =SUM(AF8:AF69) -> 0 | AG70: =SUM(AG8:AG69) -> 0 | AH70: =SUM(AH8:AH69) -> 0 | AI70: =SUM(AI8:AI69) -> 0 | AJ70: =SUM(AJ8:AJ69) -> 0
Y72: Fixed | Z72: 1760
Y73: Variable | Z73: =Z9+Z15+Z23+Z25+Z37 -> 1821.7595
Y74: Total | Z74: 3460
Y75: PP | Z75: =Z74/2 -> 1730
Z78: Winter
Y79: Shoulder | Z79: =Z74 -> 3460
Y80: High | Z80: =Z79*1.18 -> 4082.8
Y81: Holiday | Z81: =Z79*1.25 -> 4325
Y82: Low | Z82: =Z79*0.85 -> 2941
Y83: Summer | Z83: NA

Sheet 206
B1: Season: Winter
B2: Places: Oslo 1N - Bergen 2N - Bodø 2N
B3: Pax: 2
B4: Rooming: Double
B6: ID | C6: Day | D6: Type | E6: From date | F6: To date | G6: From time | H6: To time | I6: Supplier | J6: Travel element | K6: Manual booking? | L6: Status | M6: Comments | N6: Non-refundable | O6: Refundable | P6: URL | Q6: Gross P per unit | R6: Units | S6: Gross P | T6: Supp Comm | U6: Net P | V6: Supp curr | W6: X-rate | X6: Net P NOK | Y6: Sales P per unit | Z6: Price | AA6: Sales curr | AB6: X-rate | AC6: Sales P NOK tot | AD6: GP NOK | AE6: GP % | AF6: VAT25 | AG6: VAT15 | AH6: VAT12 | AI6: VAT0-D | AJ6: VAT0-I
C7: Day 1 | D7: Arrival | J7: Oslo: Welcome to Norway | Q7: 0 | R7: 0 | S7: =+Q7*R7 -> 0 | T7: 0 | U7: =S7*(1-T7) -> 0 | V7: EUR | W7: =IFERROR(VLOOKUP(V7,Curr!$B$2:$C$13,2,FALSE),0) -> 11.2 | X7: =U7*W7 -> 0 | Y7: =Q7 -> 0 | Z7: =+Y7*R7 -> 0 | AA7: EUR | AB7: =IFERROR(VLOOKUP(AA7,Curr!$B$2:$C$13,2,FALSE),0) -> 11.2 | AC7: =+Y7*AB7*R7 -> 0 | AD7: =+AC7-X7 -> 0 | AE7: =IFERROR(AD7/AC7,0) -> 0
C8: Day 1 | D8: Transfer | J8: Oslo: Self transfer to your accommodation | Q8: 0 | R8: 0 | S8: =+Q8*R8 -> 0 | T8: 0 | U8: =S8*(1-T8) -> 0 | V8: NOK | W8: =IFERROR(VLOOKUP(V8,Curr!$B$2:$C$13,2,FALSE),0) -> 1 | X8: =U8*W8 -> 0 | Y8: =Q8/11.3/0.8 -> 0 | Z8: =+Y8*R8 -> 0 | AA8: EUR | AB8: =IFERROR(VLOOKUP(AA8,Curr!$B$2:$C$13,2,FALSE),0) -> 11.2 | AC8: =+Y8*AB8*R8 -> 0 | AD8: =+AC8-X8 -> 0 | AE8: =IFERROR(AD8/AC8,0) -> 0
C9: Day 1 | D9: Hotel | J9: Oslo: Check in to your accommodation for a 1 night stay - Centrally located 3/4-star hotel - Standard Room - Breakfast included | Q9: 150 | R9: 1 | S9: =+Q9*R9 -> 150 | T9: 0 | U9: =S9*(1-T9) -> 150 | V9: EUR | W9: =IFERROR(VLOOKUP(V9,Curr!$B$2:$C$13,2,FALSE),0) -> 11.2 | X9: =U9*W9 -> 1680 | Y9: =Q9/0.85 -> 176.47059 | Z9: =+Y9*R9 -> 176.47059 | AA9: EUR | AB9: =IFERROR(VLOOKUP(AA9,Curr!$B$2:$C$13,2,FALSE),0) -> 11.2 | AC9: =+Y9*AB9*R9 -> 1976.4706 | AD9: =+AC9-X9 -> 296.47059 | AE9: =IFERROR(AD9/AC9,0) -> 0.15
C10: Day 1 | D10: Leisure | J10: Oslo: Spend time at leisure | Q10: 0 | R10: 0 | S10: =+Q10*R10 -> 0 | T10: 0 | U10: =S10*(1-T10) -> 0 | V10: EUR | W10: =IFERROR(VLOOKUP(V10,Curr!$B$2:$C$13,2,FALSE),0) -> 11.2 | X10: =U10*W10 -> 0 | Y10: =Q10 -> 0 | Z10: =+Y10*R10 -> 0 | AA10: EUR | AB10: =IFERROR(VLOOKUP(AA10,Curr!$B$2:$C$13,2,FALSE),0) -> 11.2 | AC10: =+Y10*AB10*R10 -> 0 | AD10: =+AC10-X10 -> 0 | AE10: =IFERROR(AD10/AC10,0) -> 0
S11: =+Q11*R11 -> 0 | T11: 0 | U11: =S11*(1-T11) -> 0 | V11: EUR | W11: =IFERROR(VLOOKUP(V11,Curr!$B$2:$C$13,2,FALSE),0) -> 11.2 | X11: =U11*W11 -> 0 | Y11: =Q11 -> 0 | Z11: =+Y11*R11 -> 0 | AA11: EUR | AB11: =IFERROR(VLOOKUP(AA11,Curr!$B$2:$C$13,2,FALSE),0) -> 11.2 | AC11: =+Y11*AB11*R11 -> 0 | AD11: =+AC11-X11 -> 0 | AE11: =IFERROR(AD11/AC11,0) -> 0
C12: Day 2 | D12: Transfer | J12: Oslo: Self transfer to Oslo Central Station | Q12: 0 | R12: 0 | S12: =+Q12*R12 -> 0 | T12: 0 | U12: =S12*(1-T12) -> 0 | V12: EUR | W12: =IFERROR(VLOOKUP(V12,Curr!$B$2:$C$13,2,FALSE),0) -> 11.2 | X12: =U12*W12 -> 0 | Y12: =Q12 -> 0 | Z12: =+Y12*R12 -> 0 | AA12: EUR | AB12: =IFERROR(VLOOKUP(AA12,Curr!$B$2:$C$13,2,FALSE),0) -> 11.2 | AC12: =+Y12*AB12*R12 -> 0 | AD12: =+AC12-X12 -> 0 | AE12: =IFERROR(AD12/AC12,0) -> 0
C13: Day 2 | D13: Train | J13: Oslo: Scenic Long Distance Train transfer to Bergen - Time: 08:25 am - 3:00 pm - Includes: Tickets | O13: x | P13: https://www.vy.no/#reisesok | Q13: 2400 | R13: 1 | S13: =+Q13*R13 -> 2400 | T13: 0 | U13: =S13*(1-T13) -> 2400 | V13: NOK | W13: =IFERROR(VLOOKUP(V13,Curr!$B$2:$C$13,2,FALSE),0) -> 1 | X13: =U13*W13 -> 2400 | Y13: =Q13/11.3/0.8 -> 265.48673 | Z13: =+Y13*R13 -> 265.48673 | AA13: EUR | AB13: =IFERROR(VLOOKUP(AA13,Curr!$B$2:$C$13,2,FALSE),0) -> 11.2 | AC13: =+Y13*AB13*R13 -> 2973.4513 | AD13: =+AC13-X13 -> 573.45133 | AE13: =IFERROR(AD13/AC13,0) -> 0.19285714
C14: Day 2 | D14: Transfer | J14: Bergen: Self transfer to your accommodation | Q14: 0 | R14: 0 | S14: =+Q14*R14 -> 0 | T14: 0 | U14: =S14*(1-T14) -> 0 | V14: EUR | W14: =IFERROR(VLOOKUP(V14,Curr!$B$2:$C$13,2,FALSE),0) -> 11.2 | X14: =U14*W14 -> 0 | Y14: =Q14 -> 0 | Z14: =+Y14*R14 -> 0 | AA14: EUR | AB14: =IFERROR(VLOOKUP(AA14,Curr!$B$2:$C$13,2,FALSE),0) -> 11.2 | AC14: =+Y14*AB14*R14 -> 0 | AD14: =+AC14-X14 -> 0 | AE14: =IFERROR(AD14/AC14,0) -> 0
C15: Day 2 | D15: Hotel | J15: Bergen: Check in to your accommodation for a 2 night stay - Centrally located 3/4-star hotel - Standard Room - Breakfast included | Q15: 280 | R15: 1 | S15: =+Q15*R15 -> 280 | T15: 0 | U15: =S15*(1-T15) -> 280 | V15: EUR | W15: =IFERROR(VLOOKUP(V15,Curr!$B$2:$C$13,2,FALSE),0) -> 11.2 | X15: =U15*W15 -> 3136 | Y15: =Q15/0.85 -> 329.41176 | Z15: =+Y15*R15 -> 329.41176 | AA15: EUR | AB15: =IFERROR(VLOOKUP(AA15,Curr!$B$2:$C$13,2,FALSE),0) -> 11.2 | AC15: =+Y15*AB15*R15 -> 3689.4118 | AD15: =+AC15-X15 -> 553.41176 | AE15: =IFERROR(AD15/AC15,0) -> 0.15
C16: Day 2 | D16: Leisure | J16: Bergen: Spend time at leisure | Q16: 0 | R16: 0 | S16: =+Q16*R16 -> 0 | T16: 0 | U16: =S16*(1-T16) -> 0 | V16: EUR | W16: =IFERROR(VLOOKUP(V16,Curr!$B$2:$C$13,2,FALSE),0) -> 11.2 | X16: =U16*W16 -> 0 | Y16: =Q16 -> 0 | Z16: =+Y16*R16 -> 0 | AA16: EUR | AB16: =IFERROR(VLOOKUP(AA16,Curr!$B$2:$C$13,2,FALSE),0) -> 11.2 | AC16: =+Y16*AB16*R16 -> 0 | AD16: =+AC16-X16 -> 0 | AE16: =IFERROR(AD16/AC16,0) -> 0
S17: =+Q17*R17 -> 0 | T17: 0 | U17: =S17*(1-T17) -> 0 | V17: EUR | W17: =IFERROR(VLOOKUP(V17,Curr!$B$2:$C$13,2,FALSE),0) -> 11.2 | X17: =U17*W17 -> 0 | Y17: =Q17 -> 0 | Z17: =+Y17*R17 -> 0 | AA17: EUR | AB17: =IFERROR(VLOOKUP(AA17,Curr!$B$2:$C$13,2,FALSE),0) -> 11.2 | AC17: =+Y17*AB17*R17 -> 0 | AD17: =+AC17-X17 -> 0 | AE17: =IFERROR(AD17/AC17,0) -> 0
C18: Day 3 | D18: Activity | J18: Bergen: 2 hr walk Through Bergen Past & Present - Time: 10:00 am - 12:00 pm - Meeting point: Bradbenken 1 - Includes: Profesional Guide | O18: x | P18: https://www.ilovebergen.net/tour/a-walk-through-bergen-past-present/ | Q18: 290 | R18: 2 | S18: =+Q18*R18 -> 580 | T18: 0.2 | U18: =S18*(1-T18) -> 464 | V18: NOK | W18: =IFERROR(VLOOKUP(V18,Curr!$B$2:$C$13,2,FALSE),0) -> 1 | X18: =U18*W18 -> 464 | Y18: =Q18/11.3/0.64 -> 40.099558 | Z18: =+Y18*R18 -> 80.199115 | AA18: EUR | AB18: =IFERROR(VLOOKUP(AA18,Curr!$B$2:$C$13,2,FALSE),0) -> 11.2 | AC18: =+Y18*AB18*R18 -> 898.23009 | AD18: =+AC18-X18 -> 434.23009 | AE18: =IFERROR(AD18/AC18,0) -> 0.48342857
C19: Day 3 | D19: Activity | J19: Bergen: Fløibanen Funicual - Time: Flexible - Meeting point: Vetrlidsallmenningen 23A - Includes: Tickets | O19: x | P19: https://www.floyen.no/en/floibanen/buy-tickets/ | Q19: 175 | R19: 2 | S19: =+Q19*R19 -> 350 | T19: 0 | U19: =S19*(1-T19) -> 350 | V19: NOK | W19: =IFERROR(VLOOKUP(V19,Curr!$B$2:$C$13,2,FALSE),0) -> 1 | X19: =U19*W19 -> 350 | Y19: =Q19/11.3/0.5 -> 30.973451 | Z19: =+Y19*R19 -> 61.946903 | AA19: EUR | AB19: =IFERROR(VLOOKUP(AA19,Curr!$B$2:$C$13,2,FALSE),0) -> 11.2 | AC19: =+Y19*AB19*R19 -> 693.80531 | AD19: =+AC19-X19 -> 343.80531 | AE19: =IFERROR(AD19/AC19,0) -> 0.49553571
C20: Day 3 | D20: Leisure | J20: Bergen: Spend time at leisure | Q20: 0 | R20: 0 | S20: =+Q20*R20 -> 0 | T20: 0 | U20: =S20*(1-T20) -> 0 | V20: EUR | W20: =IFERROR(VLOOKUP(V20,Curr!$B$2:$C$13,2,FALSE),0) -> 11.2 | X20: =U20*W20 -> 0 | Y20: =Q20 -> 0 | Z20: =+Y20*R20 -> 0 | AA20: EUR | AB20: =IFERROR(VLOOKUP(AA20,Curr!$B$2:$C$13,2,FALSE),0) -> 11.2 | AC20: =+Y20*AB20*R20 -> 0 | AD20: =+AC20-X20 -> 0 | AE20: =IFERROR(AD20/AC20,0) -> 0
S21: =+Q21*R21 -> 0 | T21: 0 | U21: =S21*(1-T21) -> 0 | V21: EUR | W21: =IFERROR(VLOOKUP(V21,Curr!$B$2:$C$13,2,FALSE),0) -> 11.2 | X21: =U21*W21 -> 0 | Y21: =Q21 -> 0 | Z21: =+Y21*R21 -> 0 | AA21: EUR | AB21: =IFERROR(VLOOKUP(AA21,Curr!$B$2:$C$13,2,FALSE),0) -> 11.2 | AC21: =+Y21*AB21*R21 -> 0 | AD21: =+AC21-X21 -> 0 | AE21: =IFERROR(AD21/AC21,0) -> 0
C22: Day 4 | D22: Transfer | J22: Bergen: Self transfer to Bergen Airport | Q22: 0 | R22: 0 | S22: =+Q22*R22 -> 0 | T22: 0 | U22: =S22*(1-T22) -> 0 | V22: EUR | W22: =IFERROR(VLOOKUP(V22,Curr!$B$2:$C$13,2,FALSE),0) -> 11.2 | X22: =U22*W22 -> 0 | Y22: =Q22 -> 0 | Z22: =+Y22*R22 -> 0 | AA22: EUR | AB22: =IFERROR(VLOOKUP(AA22,Curr!$B$2:$C$13,2,FALSE),0) -> 11.2 | AC22: =+Y22*AB22*R22 -> 0 | AD22: =+AC22-X22 -> 0 | AE22: =IFERROR(AD22/AC22,0) -> 0
C23: Day 4 | D23: Flight | J23: Bergen: Flight to Bodø - Time: Date dependant - Luggage included: 1 x 23 kg check in and 1 x 8 kg carry on per person | O23: x | Q23: 1800 | R23: 2 | S23: =+Q23*R23 -> 3600 | T23: 0 | U23: =S23*(1-T23) -> 3600 | V23: NOK | W23: =IFERROR(VLOOKUP(V23,Curr!$B$2:$C$13,2,FALSE),0) -> 1 | X23: =U23*W23 -> 3600 | Y23: =Q23/11.3/0.8 -> 199.11504 | Z23: =+Y23*R23 -> 398.23009 | AA23: EUR | AB23: =IFERROR(VLOOKUP(AA23,Curr!$B$2:$C$13,2,FALSE),0) -> 11.2 | AC23: =+Y23*AB23*R23 -> 4460.177 | AD23: =+AC23-X23 -> 860.17699 | AE23: =IFERROR(AD23/AC23,0) -> 0.19285714
C24: Day 4 | D24: Transfer | J24: Bodø: Self transfer to your accommodation | Q24: 0 | R24: 0 | S24: =+Q24*R24 -> 0 | T24: 0 | U24: =S24*(1-T24) -> 0 | V24: EUR | W24: =IFERROR(VLOOKUP(V24,Curr!$B$2:$C$13,2,FALSE),0) -> 11.2 | X24: =U24*W24 -> 0 | Y24: =Q24 -> 0 | Z24: =+Y24*R24 -> 0 | AA24: EUR | AB24: =IFERROR(VLOOKUP(AA24,Curr!$B$2:$C$13,2,FALSE),0) -> 11.2 | AC24: =+Y24*AB24*R24 -> 0 | AD24: =+AC24-X24 -> 0 | AE24: =IFERROR(AD24/AC24,0) -> 0
C25: Day 4 | D25: Hotel | J25: Bodø: Check in to your accommodation for a 2 night stay - Centrally located 3/4-star hotel - Standard Room - Breakfast included | Q25: 250 | R25: 1 | S25: =+Q25*R25 -> 250 | T25: 0 | U25: =S25*(1-T25) -> 250 | V25: EUR | W25: =IFERROR(VLOOKUP(V25,Curr!$B$2:$C$13,2,FALSE),0) -> 11.2 | X25: =U25*W25 -> 2800 | Y25: =Q25/0.85 -> 294.11765 | Z25: =+Y25*R25 -> 294.11765 | AA25: EUR | AB25: =IFERROR(VLOOKUP(AA25,Curr!$B$2:$C$13,2,FALSE),0) -> 11.2 | AC25: =+Y25*AB25*R25 -> 3294.1176 | AD25: =+AC25-X25 -> 494.11765 | AE25: =IFERROR(AD25/AC25,0) -> 0.15
C26: Day 4 | D26: Leisure | J26: Bodø: Spend time at leisure | Q26: 0 | R26: 0 | S26: =+Q26*R26 -> 0 | T26: 0 | U26: =S26*(1-T26) -> 0 | V26: EUR | W26: =IFERROR(VLOOKUP(V26,Curr!$B$2:$C$13,2,FALSE),0) -> 11.2 | X26: =U26*W26 -> 0 | Y26: =Q26 -> 0 | Z26: =+Y26*R26 -> 0 | AA26: EUR | AB26: =IFERROR(VLOOKUP(AA26,Curr!$B$2:$C$13,2,FALSE),0) -> 11.2 | AC26: =+Y26*AB26*R26 -> 0 | AD26: =+AC26-X26 -> 0 | AE26: =IFERROR(AD26/AC26,0) -> 0
C27: Day 4 | D27: Activity | J27: Bodø: The hunt for the northern lights - Time: 7:00 pm - 10:30 pm - Meeting point: Rampen Adventure Hub - Includes: Transportation, guide, hot drink | Q27: 1950 | R27: 2 | S27: =+Q27*R27 -> 3900 | T27: 0 | U27: =S27*(1-T27) -> 3900 | V27: NOK | W27: =IFERROR(VLOOKUP(V27,Curr!$B$2:$C$13,2,FALSE),0) -> 1 | X27: =U27*W27 -> 3900 | Y27: =Q27/11.3/0.85 -> 203.01926 | Z27: =+Y27*R27 -> 406.03852 | AA27: EUR | AB27: =IFERROR(VLOOKUP(AA27,Curr!$B$2:$C$13,2,FALSE),0) -> 11.2 | AC27: =+Y27*AB27*R27 -> 4547.6314 | AD27: =+AC27-X27 -> 647.63144 | AE27: =IFERROR(AD27/AC27,0) -> 0.14241071
S28: =+Q28*R28 -> 0 | T28: 0 | U28: =S28*(1-T28) -> 0 | V28: EUR | W28: =IFERROR(VLOOKUP(V28,Curr!$B$2:$C$13,2,FALSE),0) -> 11.2 | X28: =U28*W28 -> 0 | Y28: =Q28 -> 0 | Z28: =+Y28*R28 -> 0 | AA28: EUR | AB28: =IFERROR(VLOOKUP(AA28,Curr!$B$2:$C$13,2,FALSE),0) -> 11.2 | AC28: =+Y28*AB28*R28 -> 0 | AD28: =+AC28-X28 -> 0 | AE28: =IFERROR(AD28/AC28,0) -> 0
C29: Day 5 | D29: Activity | J29: Bodø: Scenic Walk on Arctic Sandy Beaches - Time: 12:45 pm - 2:45 pm - Meeting point: The Hurtigruten Quay - Includes: Knowledgeable, English-speaking guide, Coastal hike on sandy beaches, Spikes for shoes during the winter | P29: https://booknordics.com/norway/northern-norway/bodo-and-helgeland-coast/arctic-coastal-walk | Q29: 55 | R29: 2 | S29: =+Q29*R29 -> 110 | T29: 0.2 | U29: =S29*(1-T29) -> 88 | V29: EUR | W29: =IFERROR(VLOOKUP(V29,Curr!$B$2:$C$13,2,FALSE),0) -> 11.2 | X29: =U29*W29 -> 985.6 | Y29: =Q29 -> 55 | Z29: =+Y29*R29 -> 110 | AA29: EUR | AB29: =IFERROR(VLOOKUP(AA29,Curr!$B$2:$C$13,2,FALSE),0) -> 11.2 | AC29: =+Y29*AB29*R29 -> 1232 | AD29: =+AC29-X29 -> 246.4 | AE29: =IFERROR(AD29/AC29,0) -> 0.2
C30: Day 5 | D30: Leisure | J30: Bodø: Spend time at leisure | Q30: 0 | R30: 0 | S30: =+Q30*R30 -> 0 | T30: 0 | U30: =S30*(1-T30) -> 0 | V30: EUR | W30: =IFERROR(VLOOKUP(V30,Curr!$B$2:$C$13,2,FALSE),0) -> 11.2 | X30: =U30*W30 -> 0 | Y30: =Q30 -> 0 | Z30: =+Y30*R30 -> 0 | AA30: EUR | AB30: =IFERROR(VLOOKUP(AA30,Curr!$B$2:$C$13,2,FALSE),0) -> 11.2 | AC30: =+Y30*AB30*R30 -> 0 | AD30: =+AC30-X30 -> 0 | AE30: =IFERROR(AD30/AC30,0) -> 0
C31: Day 5 | D31: Activity | J31: Bodø: Northern Lights Tour by Minivan with Panoramic Roof - Time: 7:00 pm - 2:00 am - Meeting point: Hotel pick up - Includes: Pick-up/drop-off in central Tromsø, Knowledgeable, English-speaking guide, Winter clothes, headlamp, tripod & hot drink | P31: https://booknordics.com/norway/northern-norway/bodo-and-helgeland-coast/northern-lights-tours-bodo-norway | Q31: 2150 | R31: 2 | S31: =+Q31*R31 -> 4300 | T31: 0.2 | U31: =S31*(1-T31) -> 3440 | V31: NOK | W31: =IFERROR(VLOOKUP(V31,Curr!$B$2:$C$13,2,FALSE),0) -> 1 | X31: =U31*W31 -> 3440 | Y31: =Q31/11.3 -> 190.26549 | Z31: =+Y31*R31 -> 380.53097 | AA31: EUR | AB31: =IFERROR(VLOOKUP(AA31,Curr!$B$2:$C$13,2,FALSE),0) -> 11.2 | AC31: =+Y31*AB31*R31 -> 4261.9469 | AD31: =+AC31-X31 -> 821.9469 | AE31: =IFERROR(AD31/AC31,0) -> 0.19285714
S32: =+Q32*R32 -> 0 | T32: 0 | U32: =S32*(1-T32) -> 0 | V32: EUR | W32: =IFERROR(VLOOKUP(V32,Curr!$B$2:$C$13,2,FALSE),0) -> 11.2 | X32: =U32*W32 -> 0 | Y32: =Q32 -> 0 | Z32: =+Y32*R32 -> 0 | AA32: EUR | AB32: =IFERROR(VLOOKUP(AA32,Curr!$B$2:$C$13,2,FALSE),0) -> 11.2 | AC32: =+Y32*AB32*R32 -> 0 | AD32: =+AC32-X32 -> 0 | AE32: =IFERROR(AD32/AC32,0) -> 0
C33: Day 6 | D33: Transfer | J33: Bodø: Self transfer to Bodø Airport | Q33: 0 | R33: 0 | S33: =+Q33*R33 -> 0 | T33: 0 | U33: =S33*(1-T33) -> 0 | V33: EUR | W33: =IFERROR(VLOOKUP(V33,Curr!$B$2:$C$13,2,FALSE),0) -> 11.2 | X33: =U33*W33 -> 0 | Y33: =Q33 -> 0 | Z33: =+Y33*R33 -> 0 | AA33: EUR | AB33: =IFERROR(VLOOKUP(AA33,Curr!$B$2:$C$13,2,FALSE),0) -> 11.2 | AC33: =+Y33*AB33*R33 -> 0 | AD33: =+AC33-X33 -> 0 | AE33: =IFERROR(AD33/AC33,0) -> 0
C34: Day 6 | D34: Departure | J34: Bodø: Departure home | Q34: 0 | R34: 0 | S34: =+Q34*R34 -> 0 | T34: 0 | U34: =S34*(1-T34) -> 0 | V34: EUR | W34: =IFERROR(VLOOKUP(V34,Curr!$B$2:$C$13,2,FALSE),0) -> 11.2 | X34: =U34*W34 -> 0 | Y34: =Q34 -> 0 | Z34: =+Y34*R34 -> 0 | AA34: EUR | AB34: =IFERROR(VLOOKUP(AA34,Curr!$B$2:$C$13,2,FALSE),0) -> 11.2 | AC34: =+Y34*AB34*R34 -> 0 | AD34: =+AC34-X34 -> 0 | AE34: =IFERROR(AD34/AC34,0) -> 0
S35: =+Q35*R35 -> 0 | T35: 0 | U35: =S35*(1-T35) -> 0 | V35: EUR | W35: =IFERROR(VLOOKUP(V35,Curr!$B$2:$C$13,2,FALSE),0) -> 11.2 | X35: =U35*W35 -> 0 | Y35: =Q35 -> 0 | Z35: =+Y35*R35 -> 0 | AA35: EUR | AB35: =IFERROR(VLOOKUP(AA35,Curr!$B$2:$C$13,2,FALSE),0) -> 11.2 | AC35: =+Y35*AB35*R35 -> 0 | AD35: =+AC35-X35 -> 0 | AE35: =IFERROR(AD35/AC35,0) -> 0
S36: =+Q36*R36 -> 0 | T36: 0 | U36: =S36*(1-T36) -> 0 | V36: EUR | W36: =IFERROR(VLOOKUP(V36,Curr!$B$2:$C$13,2,FALSE),0) -> 11.2 | X36: =U36*W36 -> 0 | Y36: =Q36 -> 0 | Z36: =+Y36*R36 -> 0 | AA36: EUR | AB36: =IFERROR(VLOOKUP(AA36,Curr!$B$2:$C$13,2,FALSE),0) -> 11.2 | AC36: =+Y36*AB36*R36 -> 0 | AD36: =+AC36-X36 -> 0 | AE36: =IFERROR(AD36/AC36,0) -> 0
C37: Day 1 | D37: Transfer Package | J37: Oslo: Private transfer to your accommodation | Q37: 1750 | R37: 0 | S37: =+Q37*R37 -> 0 | T37: 0 | U37: =S37*(1-T37) -> 0 | V37: NOK | W37: =IFERROR(VLOOKUP(V37,Curr!$B$2:$C$13,2,FALSE),0) -> 1 | X37: =U37*W37 -> 0 | Y37: =Q37/11.3/0.8 -> 193.58407 | Z37: =+Y37*R37 -> 0 | AA37: EUR | AB37: =IFERROR(VLOOKUP(AA37,Curr!$B$2:$C$13,2,FALSE),0) -> 11.2 | AC37: =+Y37*AB37*R37 -> 0 | AD37: =+AC37-X37 -> 0 | AE37: =IFERROR(AD37/AC37,0) -> 0
C38: Day 2 | D38: Transfer Package | J38: Bergen: Private transfer to your accommodation | Q38: 1290 | R38: 0 | S38: =+Q38*R38 -> 0 | T38: 0.15 | U38: =S38*(1-T38) -> 0 | V38: NOK | W38: =IFERROR(VLOOKUP(V38,Curr!$B$2:$C$13,2,FALSE),0) -> 1 | X38: =U38*W38 -> 0 | Y38: =Q38/11.3/0.98 -> 116.48907 | Z38: =+Y38*R38 -> 0 | AA38: EUR | AB38: =IFERROR(VLOOKUP(AA38,Curr!$B$2:$C$13,2,FALSE),0) -> 11.2 | AC38: =+Y38*AB38*R38 -> 0 | AD38: =+AC38-X38 -> 0 | AE38: =IFERROR(AD38/AC38,0) -> 0
C39: Day 4 | D39: Transfer Package | J39: Bergen: Private transfer to Bergen Airport | Q39: 1690 | R39: 0 | S39: =+Q39*R39 -> 0 | T39: 0.15 | U39: =S39*(1-T39) -> 0 | V39: NOK | W39: =IFERROR(VLOOKUP(V39,Curr!$B$2:$C$13,2,FALSE),0) -> 1 | X39: =U39*W39 -> 0 | Y39: =Q39/11.3/0.98 -> 152.60972 | Z39: =+Y39*R39 -> 0 | AA39: EUR | AB39: =IFERROR(VLOOKUP(AA39,Curr!$B$2:$C$13,2,FALSE),0) -> 11.2 | AC39: =+Y39*AB39*R39 -> 0 | AD39: =+AC39-X39 -> 0 | AE39: =IFERROR(AD39/AC39,0) -> 0
C40: Day 4 | D40: Transfer Package | J40: Bodø: Private transfer to your accommodation | Q40: 900 | R40: 0 | S40: =+Q40*R40 -> 0 | T40: 0 | U40: =S40*(1-T40) -> 0 | V40: NOK | W40: =IFERROR(VLOOKUP(V40,Curr!$B$2:$C$13,2,FALSE),0) -> 1 | X40: =U40*W40 -> 0 | Y40: =Q40/11.3/0.8 -> 99.557522 | Z40: =+Y40*R40 -> 0 | AA40: EUR | AB40: =IFERROR(VLOOKUP(AA40,Curr!$B$2:$C$13,2,FALSE),0) -> 11.2 | AC40: =+Y40*AB40*R40 -> 0 | AD40: =+AC40-X40 -> 0 | AE40: =IFERROR(AD40/AC40,0) -> 0
C41: Day 6 | D41: Transfer Package | J41: Bodø: Private transfer to Bodø Airport | Q41: 900 | R41: 0 | S41: =+Q41*R41 -> 0 | T41: 0 | U41: =S41*(1-T41) -> 0 | V41: NOK | W41: =IFERROR(VLOOKUP(V41,Curr!$B$2:$C$13,2,FALSE),0) -> 1 | X41: =U41*W41 -> 0 | Y41: =Q41/11.3/0.8 -> 99.557522 | Z41: =+Y41*R41 -> 0 | AA41: EUR | AB41: =IFERROR(VLOOKUP(AA41,Curr!$B$2:$C$13,2,FALSE),0) -> 11.2 | AC41: =+Y41*AB41*R41 -> 0 | AD41: =+AC41-X41 -> 0 | AE41: =IFERROR(AD41/AC41,0) -> 0
S42: =+Q42*R42 -> 0 | T42: 0 | U42: =S42*(1-T42) -> 0 | V42: EUR | W42: =IFERROR(VLOOKUP(V42,Curr!$B$2:$C$13,2,FALSE),0) -> 11.2 | X42: =U42*W42 -> 0 | Y42: =Q42 -> 0 | Z42: =+Y42*R42 -> 0 | AA42: EUR | AB42: =IFERROR(VLOOKUP(AA42,Curr!$B$2:$C$13,2,FALSE),0) -> 11.2 | AC42: =+Y42*AB42*R42 -> 0 | AD42: =+AC42-X42 -> 0 | AE42: =IFERROR(AD42/AC42,0) -> 0
S43: =+Q43*R43 -> 0 | T43: 0 | U43: =S43*(1-T43) -> 0 | V43: EUR | W43: =IFERROR(VLOOKUP(V43,Curr!$B$2:$C$13,2,FALSE),0) -> 11.2 | X43: =U43*W43 -> 0 | Y43: =Q43 -> 0 | Z43: =+Y43*R43 -> 0 | AA43: EUR | AB43: =IFERROR(VLOOKUP(AA43,Curr!$B$2:$C$13,2,FALSE),0) -> 11.2 | AC43: =+Y43*AB43*R43 -> 0 | AD43: =+AC43-X43 -> 0 | AE43: =IFERROR(AD43/AC43,0) -> 0
C44: Day 2 | D44: Activity Upgrade | J44: Oslo: Norway in a Nutshell to Bergen - Time: 08:00 am - 09:00 pm - Meeting point. Oslo Central Station - Includes: Train transfer Oslo to Myrdal, Train tranfser Myrdal to Flåm, Fjord Cruise Flåm to Gudvangen, Coach Transfer Gudvangen to Voss, Train transfer Voss to Bergen | O44: x | P44: https://www.fjordtours.com/en | Q44: 3250 | R44: 0 | S44: =+Q44*R44 -> 0 | T44: 0.08 | U44: =S44*(1-T44) -> 0 | V44: NOK | W44: =IFERROR(VLOOKUP(V44,Curr!$B$2:$C$13,2,FALSE),0) -> 1 | X44: =U44*W44 -> 0 | Y44: =Q44/11.3/0.9 -> 319.56735 | Z44: =+Y44*R44 -> 0 | AA44: EUR | AB44: =IFERROR(VLOOKUP(AA44,Curr!$B$2:$C$13,2,FALSE),0) -> 11.2 | AC44: =+Y44*AB44*R44 -> 0 | AD44: =+AC44-X44 -> 0 | AE44: =IFERROR(AD44/AC44,0) -> 0
C45: Day 2 | D45: Activity Upgrade | J45: Oslo: Norway in a Nutshell Porter Service - Includes: Luggage transfer from your accommodation in Oslo to your accommodaiton in Bergen | Q45: 450 | R45: 0 | S45: =+Q45*R45 -> 0 | T45: 0 | U45: =S45*(1-T45) -> 0 | V45: NOK | W45: =IFERROR(VLOOKUP(V45,Curr!$B$2:$C$13,2,FALSE),0) -> 1 | X45: =U45*W45 -> 0 | Y45: =Q45/11.3/0.8 -> 49.778761 | Z45: =+Y45*R45 -> 0 | AA45: EUR | AB45: =IFERROR(VLOOKUP(AA45,Curr!$B$2:$C$13,2,FALSE),0) -> 11.2 | AC45: =+Y45*AB45*R45 -> 0 | AD45: =+AC45-X45 -> 0 | AE45: =IFERROR(AD45/AC45,0) -> 0
C46: Day 3 | D46: Activity Upgrade | J46: Bergen: Mostraumen Majestic Fjord & Waterfall Cruise - Time: 12:00 pm - 4:00 pm - Meeting point: Strandkaien 13 - Includes: 4-hour panoramic fjord cruise, Expert captain navigating through the fjords, English-audio guide | O46: x | P46: https://booknordics.com/norway/western-fjord-norway/bergen-and-hardanger/mostraumen-fjord-waterfall-cruise | Q46: 71 | R46: 0 | S46: =+Q46*R46 -> 0 | T46: 0.2 | U46: =S46*(1-T46) -> 0 | V46: EUR | W46: =IFERROR(VLOOKUP(V46,Curr!$B$2:$C$13,2,FALSE),0) -> 11.2 | X46: =U46*W46 -> 0 | Y46: =Q46 -> 71 | Z46: =+Y46*R46 -> 0 | AA46: EUR | AB46: =IFERROR(VLOOKUP(AA46,Curr!$B$2:$C$13,2,FALSE),0) -> 11.2 | AC46: =+Y46*AB46*R46 -> 0 | AD46: =+AC46-X46 -> 0 | AE46: =IFERROR(AD46/AC46,0) -> 0
O47: x | Q47: 0 | R47: 0 | S47: =+Q47*R47 -> 0 | T47: 0.2 | U47: =S47*(1-T47) -> 0 | V47: NOK | W47: =IFERROR(VLOOKUP(V47,Curr!$B$2:$C$13,2,FALSE),0) -> 1 | X47: =U47*W47 -> 0 | Y47: =Q47/11.3 -> 0 | Z47: =+Y47*R47 -> 0 | AA47: EUR | AB47: =IFERROR(VLOOKUP(AA47,Curr!$B$2:$C$13,2,FALSE),0) -> 11.2 | AC47: =+Y47*AB47*R47 -> 0 | AD47: =+AC47-X47 -> 0 | AE47: =IFERROR(AD47/AC47,0) -> 0
S48: =+Q48*R48 -> 0 | T48: 0 | U48: =S48*(1-T48) -> 0 | V48: EUR | W48: =IFERROR(VLOOKUP(V48,Curr!$B$2:$C$13,2,FALSE),0) -> 11.2 | X48: =U48*W48 -> 0 | Y48: =Q48 -> 0 | Z48: =+Y48*R48 -> 0 | AA48: EUR | AB48: =IFERROR(VLOOKUP(AA48,Curr!$B$2:$C$13,2,FALSE),0) -> 11.2 | AC48: =+Y48*AB48*R48 -> 0 | AD48: =+AC48-X48 -> 0 | AE48: =IFERROR(AD48/AC48,0) -> 0
S49: =+Q49*R49 -> 0 | T49: 0 | U49: =S49*(1-T49) -> 0 | V49: EUR | W49: =IFERROR(VLOOKUP(V49,Curr!$B$2:$C$13,2,FALSE),0) -> 11.2 | X49: =U49*W49 -> 0 | Y49: =Q49 -> 0 | Z49: =+Y49*R49 -> 0 | AA49: EUR | AB49: =IFERROR(VLOOKUP(AA49,Curr!$B$2:$C$13,2,FALSE),0) -> 11.2 | AC49: =+Y49*AB49*R49 -> 0 | AD49: =+AC49-X49 -> 0 | AE49: =IFERROR(AD49/AC49,0) -> 0
S50: =+Q50*R50 -> 0 | T50: 0 | U50: =S50*(1-T50) -> 0 | V50: EUR | W50: =IFERROR(VLOOKUP(V50,Curr!$B$2:$C$13,2,FALSE),0) -> 11.2 | X50: =U50*W50 -> 0 | Y50: =Q50 -> 0 | Z50: =+Y50*R50 -> 0 | AA50: EUR | AB50: =IFERROR(VLOOKUP(AA50,Curr!$B$2:$C$13,2,FALSE),0) -> 11.2 | AC50: =+Y50*AB50*R50 -> 0 | AD50: =+AC50-X50 -> 0 | AE50: =IFERROR(AD50/AC50,0) -> 0
S51: =+Q51*R51 -> 0 | T51: 0 | U51: =S51*(1-T51) -> 0 | V51: EUR | W51: =IFERROR(VLOOKUP(V51,Curr!$B$2:$C$13,2,FALSE),0) -> 11.2 | X51: =U51*W51 -> 0 | Y51: =Q51 -> 0 | Z51: =+Y51*R51 -> 0 | AA51: EUR | AB51: =IFERROR(VLOOKUP(AA51,Curr!$B$2:$C$13,2,FALSE),0) -> 11.2 | AC51: =+Y51*AB51*R51 -> 0 | AD51: =+AC51-X51 -> 0 | AE51: =IFERROR(AD51/AC51,0) -> 0
S52: =+Q52*R52 -> 0 | T52: 0 | U52: =S52*(1-T52) -> 0 | V52: EUR | W52: =IFERROR(VLOOKUP(V52,Curr!$B$2:$C$13,2,FALSE),0) -> 11.2 | X52: =U52*W52 -> 0 | Y52: =Q52 -> 0 | Z52: =+Y52*R52 -> 0 | AA52: EUR | AB52: =IFERROR(VLOOKUP(AA52,Curr!$B$2:$C$13,2,FALSE),0) -> 11.2 | AC52: =+Y52*AB52*R52 -> 0 | AD52: =+AC52-X52 -> 0 | AE52: =IFERROR(AD52/AC52,0) -> 0
S53: =+Q53*R53 -> 0 | T53: 0 | U53: =S53*(1-T53) -> 0 | V53: EUR | W53: =IFERROR(VLOOKUP(V53,Curr!$B$2:$C$13,2,FALSE),0) -> 11.2 | X53: =U53*W53 -> 0 | Y53: =Q53 -> 0 | Z53: =+Y53*R53 -> 0 | AA53: EUR | AB53: =IFERROR(VLOOKUP(AA53,Curr!$B$2:$C$13,2,FALSE),0) -> 11.2 | AC53: =+Y53*AB53*R53 -> 0 | AD53: =+AC53-X53 -> 0 | AE53: =IFERROR(AD53/AC53,0) -> 0
B55: Totals | D55: x | E55: x | F55: x | G55: x | H55: x | I55: x | J55: x | K55: x | L55: x | M55: x | N55: x | O55: x | P55: x | Q55: x | R55: x | S55: x | T55: x | U55: x | V55: x | W55: x | X55: x | Y55: x | Z55: =SUM(Z7:Z53) -> 2502.4323 | AC55: =SUM(AC7:AC53) -> 28027.242 | AD55: =SUM(AD7:AD53) -> 5271.6421 | AE55: =IFERROR(AD55/AC55,0) -> 0.18808993 | AF55: =SUM(AF8:AF54) -> 0 | AG55: =SUM(AG8:AG54) -> 0 | AH55: =SUM(AH8:AH54) -> 0 | AI55: =SUM(AI8:AI54) -> 0 | AJ55: =SUM(AJ8:AJ54) -> 0
Y57: Fixed | Z57: 1310
Y58: Variable | Z58: =Z9+Z15+Z23+Z25 -> 1198.2301
Y59: Total | Z59: 2520
Y60: PP | Z60: =Z59/2 -> 1260
Z63: Winter
Y64: Shoulder | Z64: =Z59 -> 2520
Y65: High | Z65: =Z64*1.18 -> 2973.6
Y66: Holiday | Z66: =Z64*1.25 -> 3150
Y67: Low | Z67: =Z64*0.85 -> 2142
Y68: Summer | Z68: NA

Sheet 207
B1: Season: Summer
B2: Places: Oslo 1N - Bergen 2N - Bodø 2N - Svolvær 3N
B3: Pax: 2
B4: Rooming: Double
B6: ID | C6: Day | D6: Type | E6: From date | F6: To date | G6: From time | H6: To time | I6: Supplier | J6: Travel element | K6: Manual booking? | L6: Status | M6: Comments | N6: Non-refundable | O6: Refundable | P6: URL | Q6: Gross P per unit | R6: Units | S6: Gross P | T6: Supp Comm | U6: Net P | V6: Supp curr | W6: X-rate | X6: Net P NOK | Y6: Sales P per unit | Z6: Price | AA6: Sales curr | AB6: X-rate | AC6: Sales P NOK tot | AD6: GP NOK | AE6: GP % | AF6: VAT25 | AG6: VAT15 | AH6: VAT12 | AI6: VAT0-D | AJ6: VAT0-I
C7: Day 1 | D7: Arrival | J7: Oslo: Welcome to Norway | Q7: 0 | R7: 0 | S7: =+Q7*R7 -> 0 | T7: 0 | U7: =S7*(1-T7) -> 0 | V7: EUR | W7: =IFERROR(VLOOKUP(V7,Curr!$B$2:$C$13,2,FALSE),0) -> 11.2 | X7: =U7*W7 -> 0 | Y7: =Q7 -> 0 | Z7: =+Y7*R7 -> 0 | AA7: EUR | AB7: =IFERROR(VLOOKUP(AA7,Curr!$B$2:$C$13,2,FALSE),0) -> 11.2 | AC7: =+Y7*AB7*R7 -> 0 | AD7: =+AC7-X7 -> 0 | AE7: =IFERROR(AD7/AC7,0) -> 0
C8: Day 1 | D8: Transfer | J8: Oslo: Self transfer to your accommodation | Q8: 0 | R8: 0 | S8: =+Q8*R8 -> 0 | T8: 0 | U8: =S8*(1-T8) -> 0 | V8: NOK | W8: =IFERROR(VLOOKUP(V8,Curr!$B$2:$C$13,2,FALSE),0) -> 1 | X8: =U8*W8 -> 0 | Y8: =Q8/11.3/0.8 -> 0 | Z8: =+Y8*R8 -> 0 | AA8: EUR | AB8: =IFERROR(VLOOKUP(AA8,Curr!$B$2:$C$13,2,FALSE),0) -> 11.2 | AC8: =+Y8*AB8*R8 -> 0 | AD8: =+AC8-X8 -> 0 | AE8: =IFERROR(AD8/AC8,0) -> 0
C9: Day 1 | D9: Hotel | J9: Oslo: Check in to your accommodation for a 1 night stay - Centrally located 3/4-star hotel - Standard Room - Breakfast included | Q9: 200 | R9: 1 | S9: =+Q9*R9 -> 200 | T9: 0 | U9: =S9*(1-T9) -> 200 | V9: EUR | W9: =IFERROR(VLOOKUP(V9,Curr!$B$2:$C$13,2,FALSE),0) -> 11.2 | X9: =U9*W9 -> 2240 | Y9: =Q9/0.85 -> 235.29412 | Z9: =+Y9*R9 -> 235.29412 | AA9: EUR | AB9: =IFERROR(VLOOKUP(AA9,Curr!$B$2:$C$13,2,FALSE),0) -> 11.2 | AC9: =+Y9*AB9*R9 -> 2635.2941 | AD9: =+AC9-X9 -> 395.29412 | AE9: =IFERROR(AD9/AC9,0) -> 0.15
C10: Day 1 | D10: Leisure | J10: Oslo: Spend time at leisure | Q10: 0 | R10: 0 | S10: =+Q10*R10 -> 0 | T10: 0 | U10: =S10*(1-T10) -> 0 | V10: EUR | W10: =IFERROR(VLOOKUP(V10,Curr!$B$2:$C$13,2,FALSE),0) -> 11.2 | X10: =U10*W10 -> 0 | Y10: =Q10 -> 0 | Z10: =+Y10*R10 -> 0 | AA10: EUR | AB10: =IFERROR(VLOOKUP(AA10,Curr!$B$2:$C$13,2,FALSE),0) -> 11.2 | AC10: =+Y10*AB10*R10 -> 0 | AD10: =+AC10-X10 -> 0 | AE10: =IFERROR(AD10/AC10,0) -> 0
S11: =+Q11*R11 -> 0 | T11: 0 | U11: =S11*(1-T11) -> 0 | V11: EUR | W11: =IFERROR(VLOOKUP(V11,Curr!$B$2:$C$13,2,FALSE),0) -> 11.2 | X11: =U11*W11 -> 0 | Y11: =Q11 -> 0 | Z11: =+Y11*R11 -> 0 | AA11: EUR | AB11: =IFERROR(VLOOKUP(AA11,Curr!$B$2:$C$13,2,FALSE),0) -> 11.2 | AC11: =+Y11*AB11*R11 -> 0 | AD11: =+AC11-X11 -> 0 | AE11: =IFERROR(AD11/AC11,0) -> 0
C12: Day 2 | D12: Transfer | J12: Oslo: Self transfer to Oslo Central Station | Q12: 0 | R12: 0 | S12: =+Q12*R12 -> 0 | T12: 0 | U12: =S12*(1-T12) -> 0 | V12: EUR | W12: =IFERROR(VLOOKUP(V12,Curr!$B$2:$C$13,2,FALSE),0) -> 11.2 | X12: =U12*W12 -> 0 | Y12: =Q12 -> 0 | Z12: =+Y12*R12 -> 0 | AA12: EUR | AB12: =IFERROR(VLOOKUP(AA12,Curr!$B$2:$C$13,2,FALSE),0) -> 11.2 | AC12: =+Y12*AB12*R12 -> 0 | AD12: =+AC12-X12 -> 0 | AE12: =IFERROR(AD12/AC12,0) -> 0
C13: Day 2 | D13: Train | J13: Oslo: Scenic Long Distance Train transfer to Bergen - Time: 08:25 am - 3:00 pm - Includes: Tickets | O13: x | P13: https://www.vy.no/#reisesok | Q13: 2400 | R13: 1 | S13: =+Q13*R13 -> 2400 | T13: 0 | U13: =S13*(1-T13) -> 2400 | V13: NOK | W13: =IFERROR(VLOOKUP(V13,Curr!$B$2:$C$13,2,FALSE),0) -> 1 | X13: =U13*W13 -> 2400 | Y13: =Q13/11.3/0.8 -> 265.48673 | Z13: =+Y13*R13 -> 265.48673 | AA13: EUR | AB13: =IFERROR(VLOOKUP(AA13,Curr!$B$2:$C$13,2,FALSE),0) -> 11.2 | AC13: =+Y13*AB13*R13 -> 2973.4513 | AD13: =+AC13-X13 -> 573.45133 | AE13: =IFERROR(AD13/AC13,0) -> 0.19285714
C14: Day 2 | D14: Transfer | J14: Bergen: Self transfer to your accommodation | Q14: 0 | R14: 0 | S14: =+Q14*R14 -> 0 | T14: 0 | U14: =S14*(1-T14) -> 0 | V14: EUR | W14: =IFERROR(VLOOKUP(V14,Curr!$B$2:$C$13,2,FALSE),0) -> 11.2 | X14: =U14*W14 -> 0 | Y14: =Q14 -> 0 | Z14: =+Y14*R14 -> 0 | AA14: EUR | AB14: =IFERROR(VLOOKUP(AA14,Curr!$B$2:$C$13,2,FALSE),0) -> 11.2 | AC14: =+Y14*AB14*R14 -> 0 | AD14: =+AC14-X14 -> 0 | AE14: =IFERROR(AD14/AC14,0) -> 0
C15: Day 2 | D15: Hotel | J15: Bergen: Check in to your accommodation for a 2 night stay - Centrally located 3/4-star hotel - Standard Room - Breakfast included | Q15: 400 | R15: 1 | S15: =+Q15*R15 -> 400 | T15: 0 | U15: =S15*(1-T15) -> 400 | V15: EUR | W15: =IFERROR(VLOOKUP(V15,Curr!$B$2:$C$13,2,FALSE),0) -> 11.2 | X15: =U15*W15 -> 4480 | Y15: =Q15/0.85 -> 470.58824 | Z15: =+Y15*R15 -> 470.58824 | AA15: EUR | AB15: =IFERROR(VLOOKUP(AA15,Curr!$B$2:$C$13,2,FALSE),0) -> 11.2 | AC15: =+Y15*AB15*R15 -> 5270.5882 | AD15: =+AC15-X15 -> 790.58824 | AE15: =IFERROR(AD15/AC15,0) -> 0.15
C16: Day 2 | D16: Leisure | J16: Bergen: Spend time at leisure | Q16: 0 | R16: 0 | S16: =+Q16*R16 -> 0 | T16: 0 | U16: =S16*(1-T16) -> 0 | V16: EUR | W16: =IFERROR(VLOOKUP(V16,Curr!$B$2:$C$13,2,FALSE),0) -> 11.2 | X16: =U16*W16 -> 0 | Y16: =Q16 -> 0 | Z16: =+Y16*R16 -> 0 | AA16: EUR | AB16: =IFERROR(VLOOKUP(AA16,Curr!$B$2:$C$13,2,FALSE),0) -> 11.2 | AC16: =+Y16*AB16*R16 -> 0 | AD16: =+AC16-X16 -> 0 | AE16: =IFERROR(AD16/AC16,0) -> 0
S17: =+Q17*R17 -> 0 | T17: 0 | U17: =S17*(1-T17) -> 0 | V17: EUR | W17: =IFERROR(VLOOKUP(V17,Curr!$B$2:$C$13,2,FALSE),0) -> 11.2 | X17: =U17*W17 -> 0 | Y17: =Q17 -> 0 | Z17: =+Y17*R17 -> 0 | AA17: EUR | AB17: =IFERROR(VLOOKUP(AA17,Curr!$B$2:$C$13,2,FALSE),0) -> 11.2 | AC17: =+Y17*AB17*R17 -> 0 | AD17: =+AC17-X17 -> 0 | AE17: =IFERROR(AD17/AC17,0) -> 0
C18: Day 3 | D18: Activity | J18: Bergen: 2 hr walk Through Bergen Past & Present - Time: 10:00 am - 12:00 pm - Meeting point: Bradbenken 1 - Includes: Profesional Guide | O18: x | P18: https://www.ilovebergen.net/tour/a-walk-through-bergen-past-present/ | Q18: 290 | R18: 2 | S18: =+Q18*R18 -> 580 | T18: 0.2 | U18: =S18*(1-T18) -> 464 | V18: NOK | W18: =IFERROR(VLOOKUP(V18,Curr!$B$2:$C$13,2,FALSE),0) -> 1 | X18: =U18*W18 -> 464 | Y18: =Q18/11.3/0.64 -> 40.099558 | Z18: =+Y18*R18 -> 80.199115 | AA18: EUR | AB18: =IFERROR(VLOOKUP(AA18,Curr!$B$2:$C$13,2,FALSE),0) -> 11.2 | AC18: =+Y18*AB18*R18 -> 898.23009 | AD18: =+AC18-X18 -> 434.23009 | AE18: =IFERROR(AD18/AC18,0) -> 0.48342857
C19: Day 3 | D19: Activity | J19: Bergen: Fløibanen Funicual - Time: Flexible - Meeting point: Vetrlidsallmenningen 23A - Includes: Tickets | O19: x | P19: https://www.floyen.no/en/floibanen/buy-tickets/ | Q19: 175 | R19: 2 | S19: =+Q19*R19 -> 350 | T19: 0 | U19: =S19*(1-T19) -> 350 | V19: NOK | W19: =IFERROR(VLOOKUP(V19,Curr!$B$2:$C$13,2,FALSE),0) -> 1 | X19: =U19*W19 -> 350 | Y19: =Q19/11.3/0.5 -> 30.973451 | Z19: =+Y19*R19 -> 61.946903 | AA19: EUR | AB19: =IFERROR(VLOOKUP(AA19,Curr!$B$2:$C$13,2,FALSE),0) -> 11.2 | AC19: =+Y19*AB19*R19 -> 693.80531 | AD19: =+AC19-X19 -> 343.80531 | AE19: =IFERROR(AD19/AC19,0) -> 0.49553571
C20: Day 3 | D20: Leisure | J20: Bergen: Spend time at leisure | Q20: 0 | R20: 0 | S20: =+Q20*R20 -> 0 | T20: 0 | U20: =S20*(1-T20) -> 0 | V20: EUR | W20: =IFERROR(VLOOKUP(V20,Curr!$B$2:$C$13,2,FALSE),0) -> 11.2 | X20: =U20*W20 -> 0 | Y20: =Q20 -> 0 | Z20: =+Y20*R20 -> 0 | AA20: EUR | AB20: =IFERROR(VLOOKUP(AA20,Curr!$B$2:$C$13,2,FALSE),0) -> 11.2 | AC20: =+Y20*AB20*R20 -> 0 | AD20: =+AC20-X20 -> 0 | AE20: =IFERROR(AD20/AC20,0) -> 0
S21: =+Q21*R21 -> 0 | T21: 0 | U21: =S21*(1-T21) -> 0 | V21: EUR | W21: =IFERROR(VLOOKUP(V21,Curr!$B$2:$C$13,2,FALSE),0) -> 11.2 | X21: =U21*W21 -> 0 | Y21: =Q21 -> 0 | Z21: =+Y21*R21 -> 0 | AA21: EUR | AB21: =IFERROR(VLOOKUP(AA21,Curr!$B$2:$C$13,2,FALSE),0) -> 11.2 | AC21: =+Y21*AB21*R21 -> 0 | AD21: =+AC21-X21 -> 0 | AE21: =IFERROR(AD21/AC21,0) -> 0
C22: Day 4 | D22: Transfer | J22: Bergen: Self transfer to Bergen Airport | Q22: 0 | R22: 0 | S22: =+Q22*R22 -> 0 | T22: 0 | U22: =S22*(1-T22) -> 0 | V22: EUR | W22: =IFERROR(VLOOKUP(V22,Curr!$B$2:$C$13,2,FALSE),0) -> 11.2 | X22: =U22*W22 -> 0 | Y22: =Q22 -> 0 | Z22: =+Y22*R22 -> 0 | AA22: EUR | AB22: =IFERROR(VLOOKUP(AA22,Curr!$B$2:$C$13,2,FALSE),0) -> 11.2 | AC22: =+Y22*AB22*R22 -> 0 | AD22: =+AC22-X22 -> 0 | AE22: =IFERROR(AD22/AC22,0) -> 0
C23: Day 4 | D23: Flight | J23: Bergen: Flight to Bodø - Time: Date dependandt - Luggage included: 1 x 23 kg check in and 1 x 8 kg carry on per person | O23: x | Q23: 2000 | R23: 2 | S23: =+Q23*R23 -> 4000 | T23: 0 | U23: =S23*(1-T23) -> 4000 | V23: NOK | W23: =IFERROR(VLOOKUP(V23,Curr!$B$2:$C$13,2,FALSE),0) -> 1 | X23: =U23*W23 -> 4000 | Y23: =Q23/11.3/0.8 -> 221.23894 | Z23: =+Y23*R23 -> 442.47788 | AA23: EUR | AB23: =IFERROR(VLOOKUP(AA23,Curr!$B$2:$C$13,2,FALSE),0) -> 11.2 | AC23: =+Y23*AB23*R23 -> 4955.7522 | AD23: =+AC23-X23 -> 955.75221 | AE23: =IFERROR(AD23/AC23,0) -> 0.19285714
C24: Day 4 | D24: Transfer | J24: Bodø: Self transfer to your accommodation | Q24: 0 | R24: 0 | S24: =+Q24*R24 -> 0 | T24: 0 | U24: =S24*(1-T24) -> 0 | V24: EUR | W24: =IFERROR(VLOOKUP(V24,Curr!$B$2:$C$13,2,FALSE),0) -> 11.2 | X24: =U24*W24 -> 0 | Y24: =Q24 -> 0 | Z24: =+Y24*R24 -> 0 | AA24: EUR | AB24: =IFERROR(VLOOKUP(AA24,Curr!$B$2:$C$13,2,FALSE),0) -> 11.2 | AC24: =+Y24*AB24*R24 -> 0 | AD24: =+AC24-X24 -> 0 | AE24: =IFERROR(AD24/AC24,0) -> 0
C25: Day 4 | D25: Hotel | J25: Bodø: Check in to your accommodation for a 2 night stay - Centrally located 3/4-star hotel - Standard Room - Breakfast included | Q25: 200 | R25: 1 | S25: =+Q25*R25 -> 200 | T25: 0 | U25: =S25*(1-T25) -> 200 | V25: EUR | W25: =IFERROR(VLOOKUP(V25,Curr!$B$2:$C$13,2,FALSE),0) -> 11.2 | X25: =U25*W25 -> 2240 | Y25: =Q25/0.85 -> 235.29412 | Z25: =+Y25*R25 -> 235.29412 | AA25: EUR | AB25: =IFERROR(VLOOKUP(AA25,Curr!$B$2:$C$13,2,FALSE),0) -> 11.2 | AC25: =+Y25*AB25*R25 -> 2635.2941 | AD25: =+AC25-X25 -> 395.29412 | AE25: =IFERROR(AD25/AC25,0) -> 0.15
C26: Day 4 | D26: Leisure | J26: Bodø: Spend time at leisure | Q26: 0 | R26: 0 | S26: =+Q26*R26 -> 0 | T26: 0 | U26: =S26*(1-T26) -> 0 | V26: EUR | W26: =IFERROR(VLOOKUP(V26,Curr!$B$2:$C$13,2,FALSE),0) -> 11.2 | X26: =U26*W26 -> 0 | Y26: =Q26 -> 0 | Z26: =+Y26*R26 -> 0 | AA26: EUR | AB26: =IFERROR(VLOOKUP(AA26,Curr!$B$2:$C$13,2,FALSE),0) -> 11.2 | AC26: =+Y26*AB26*R26 -> 0 | AD26: =+AC26-X26 -> 0 | AE26: =IFERROR(AD26/AC26,0) -> 0
S27: =+Q27*R27 -> 0 | T27: 0 | U27: =S27*(1-T27) -> 0 | V27: EUR | W27: =IFERROR(VLOOKUP(V27,Curr!$B$2:$C$13,2,FALSE),0) -> 11.2 | X27: =U27*W27 -> 0 | Y27: =Q27 -> 0 | Z27: =+Y27*R27 -> 0 | AA27: EUR | AB27: =IFERROR(VLOOKUP(AA27,Curr!$B$2:$C$13,2,FALSE),0) -> 11.2 | AC27: =+Y27*AB27*R27 -> 0 | AD27: =+AC27-X27 -> 0 | AE27: =IFERROR(AD27/AC27,0) -> 0
C28: Day 5 | D28: Activity | J28: Bodø: Cruise to Kjerringøy by Silent Electric Ship - Time: 09:00 am - 1:00 pm - Meeting point: Quality Hotel Ramsalt - Includes: Knowledgeable, English-speaking guide, Fully licensed bar with drinks for sale, Cafe with food & beverages for purchase, Warm indoor saloons, toilets & free wifi | P28: https://booknordics.com/norway/northern-norway/bodo-and-helgeland-coast/bodo-kjerringoy-nordfjord-cruise | Q28: 1290 | R28: 2 | S28: =+Q28*R28 -> 2580 | T28: 0.2 | U28: =S28*(1-T28) -> 2064 | V28: NOK | W28: =IFERROR(VLOOKUP(V28,Curr!$B$2:$C$13,2,FALSE),0) -> 1 | X28: =U28*W28 -> 2064 | Y28: =Q28/11.3 -> 114.15929 | Z28: =+Y28*R28 -> 228.31858 | AA28: EUR | AB28: =IFERROR(VLOOKUP(AA28,Curr!$B$2:$C$13,2,FALSE),0) -> 11.2 | AC28: =+Y28*AB28*R28 -> 2557.1681 | AD28: =+AC28-X28 -> 493.16814 | AE28: =IFERROR(AD28/AC28,0) -> 0.19285714
C29: Day 5 | D29: Leisure | J29: Bodø: Spend time at leisure | Q29: 0 | R29: 0 | S29: =+Q29*R29 -> 0 | T29: 0 | U29: =S29*(1-T29) -> 0 | V29: EUR | W29: =IFERROR(VLOOKUP(V29,Curr!$B$2:$C$13,2,FALSE),0) -> 11.2 | X29: =U29*W29 -> 0 | Y29: =Q29 -> 0 | Z29: =+Y29*R29 -> 0 | AA29: EUR | AB29: =IFERROR(VLOOKUP(AA29,Curr!$B$2:$C$13,2,FALSE),0) -> 11.2 | AC29: =+Y29*AB29*R29 -> 0 | AD29: =+AC29-X29 -> 0 | AE29: =IFERROR(AD29/AC29,0) -> 0
S30: =+Q30*R30 -> 0 | T30: 0 | U30: =S30*(1-T30) -> 0 | V30: EUR | W30: =IFERROR(VLOOKUP(V30,Curr!$B$2:$C$13,2,FALSE),0) -> 11.2 | X30: =U30*W30 -> 0 | Y30: =Q30 -> 0 | Z30: =+Y30*R30 -> 0 | AA30: EUR | AB30: =IFERROR(VLOOKUP(AA30,Curr!$B$2:$C$13,2,FALSE),0) -> 11.2 | AC30: =+Y30*AB30*R30 -> 0 | AD30: =+AC30-X30 -> 0 | AE30: =IFERROR(AD30/AC30,0) -> 0
C31: Day 6 | D31: Transfer | J31: Bodø: Self transfer to Bodø Airport | Q31: 0 | R31: 0 | S31: =+Q31*R31 -> 0 | T31: 0 | U31: =S31*(1-T31) -> 0 | V31: EUR | W31: =IFERROR(VLOOKUP(V31,Curr!$B$2:$C$13,2,FALSE),0) -> 11.2 | X31: =U31*W31 -> 0 | Y31: =Q31 -> 0 | Z31: =+Y31*R31 -> 0 | AA31: EUR | AB31: =IFERROR(VLOOKUP(AA31,Curr!$B$2:$C$13,2,FALSE),0) -> 11.2 | AC31: =+Y31*AB31*R31 -> 0 | AD31: =+AC31-X31 -> 0 | AE31: =IFERROR(AD31/AC31,0) -> 0
C32: Day 6 | D32: Flight | J32: Bodø: Flight to Svolvær - Time: Date dependant - Luggage included: 1 x 23 kg check in and 1 x 8 kg carry on per person | Q32: 1000 | R32: 2 | S32: =+Q32*R32 -> 2000 | T32: 0 | U32: =S32*(1-T32) -> 2000 | V32: NOK | W32: =IFERROR(VLOOKUP(V32,Curr!$B$2:$C$13,2,FALSE),0) -> 1 | X32: =U32*W32 -> 2000 | Y32: =Q32/11.3/0.8 -> 110.61947 | Z32: =+Y32*R32 -> 221.23894 | AA32: EUR | AB32: =IFERROR(VLOOKUP(AA32,Curr!$B$2:$C$13,2,FALSE),0) -> 11.2 | AC32: =+Y32*AB32*R32 -> 2477.8761 | AD32: =+AC32-X32 -> 477.87611 | AE32: =IFERROR(AD32/AC32,0) -> 0.19285714
C33: Day 6 | D33: Transfer | J33: Svolvær: Self transfer to your accommodation | Q33: 0 | R33: 0 | S33: =+Q33*R33 -> 0 | T33: 0 | U33: =S33*(1-T33) -> 0 | V33: EUR | W33: =IFERROR(VLOOKUP(V33,Curr!$B$2:$C$13,2,FALSE),0) -> 11.2 | X33: =U33*W33 -> 0 | Y33: =Q33 -> 0 | Z33: =+Y33*R33 -> 0 | AA33: EUR | AB33: =IFERROR(VLOOKUP(AA33,Curr!$B$2:$C$13,2,FALSE),0) -> 11.2 | AC33: =+Y33*AB33*R33 -> 0 | AD33: =+AC33-X33 -> 0 | AE33: =IFERROR(AD33/AC33,0) -> 0
C34: Day 6 | D34: Hotel | J34: Svolvær: Check in to your accommodation for a 3 night stay - Centrally located 3/4-star hotel - Standard Room - Breakfast included | Q34: 550 | R34: 1 | S34: =+Q34*R34 -> 550 | T34: 0 | U34: =S34*(1-T34) -> 550 | V34: EUR | W34: =IFERROR(VLOOKUP(V34,Curr!$B$2:$C$13,2,FALSE),0) -> 11.2 | X34: =U34*W34 -> 6160 | Y34: =Q34/0.85 -> 647.05882 | Z34: =+Y34*R34 -> 647.05882 | AA34: EUR | AB34: =IFERROR(VLOOKUP(AA34,Curr!$B$2:$C$13,2,FALSE),0) -> 11.2 | AC34: =+Y34*AB34*R34 -> 7247.0588 | AD34: =+AC34-X34 -> 1087.0588 | AE34: =IFERROR(AD34/AC34,0) -> 0.15
C35: Day 6 | D35: Leisure | J35: Svolvær: Spend time at leisure | Q35: 0 | R35: 0 | S35: =+Q35*R35 -> 0 | T35: 0 | U35: =S35*(1-T35) -> 0 | V35: EUR | W35: =IFERROR(VLOOKUP(V35,Curr!$B$2:$C$13,2,FALSE),0) -> 11.2 | X35: =U35*W35 -> 0 | Y35: =Q35 -> 0 | Z35: =+Y35*R35 -> 0 | AA35: EUR | AB35: =IFERROR(VLOOKUP(AA35,Curr!$B$2:$C$13,2,FALSE),0) -> 11.2 | AC35: =+Y35*AB35*R35 -> 0 | AD35: =+AC35-X35 -> 0 | AE35: =IFERROR(AD35/AC35,0) -> 0
C36: Day 6 | D36: Activity | J36: Svolvær: Sail to Skrova, Lofoten’s Secret Paradise Awaits - Time: 2:00 pm - 5:00 pm - Meeting point: Svolvær Harbor - Includes: Knowledgeable, English-speaking guide, 1-hour island visit at Skrova with storytelling, Comfortable thermal suits and lifejackets, Unique piece of digital art as a memory, Warm coffee, tea, and light snacks | P36: https://booknordics.com/norway/northern-norway/lofoten-and-vesteralen/sail-to-skrova-lofotens-secret-paradise-awaits | Q36: 135 | R36: 2 | S36: =+Q36*R36 -> 270 | T36: 0.2 | U36: =S36*(1-T36) -> 216 | V36: EUR | W36: =IFERROR(VLOOKUP(V36,Curr!$B$2:$C$13,2,FALSE),0) -> 11.2 | X36: =U36*W36 -> 2419.2 | Y36: =Q36 -> 135 | Z36: =+Y36*R36 -> 270 | AA36: EUR | AB36: =IFERROR(VLOOKUP(AA36,Curr!$B$2:$C$13,2,FALSE),0) -> 11.2 | AC36: =+Y36*AB36*R36 -> 3024 | AD36: =+AC36-X36 -> 604.8 | AE36: =IFERROR(AD36/AC36,0) -> 0.2
S37: =+Q37*R37 -> 0 | T37: 0 | U37: =S37*(1-T37) -> 0 | V37: EUR | W37: =IFERROR(VLOOKUP(V37,Curr!$B$2:$C$13,2,FALSE),0) -> 11.2 | X37: =U37*W37 -> 0 | Y37: =Q37 -> 0 | Z37: =+Y37*R37 -> 0 | AA37: EUR | AB37: =IFERROR(VLOOKUP(AA37,Curr!$B$2:$C$13,2,FALSE),0) -> 11.2 | AC37: =+Y37*AB37*R37 -> 0 | AD37: =+AC37-X37 -> 0 | AE37: =IFERROR(AD37/AC37,0) -> 0
