Workbook

Sheet Curr
C1: NOK
B2: EUR | C2: 11
B3: SEK | C3: 1.02
B4: DKK | C4: 1.5
B5: ISK | C5: 0.075
B6: NOK | C6: 1
B7: USD | C7: 10.6

Sheet Oversikt
B3: D | C3: Day | F3: ITIN | G3: Page | H3: Cost | I3: Margin
B4: SD | C4: Self Drive | F4: 301 | G4: 5D SD | H4: ='5D SD'!Z51 -> 1468.75 | I4: ='5D SD'!AE51 -> 0.2
B5: GTS | C5: Group Tour Summer | F5: 302 | G5: 6D SD | H5: ='6D SD'!Z51 -> 1875 | I5: ='6D SD'!AE51 -> 0.2
B6: GTW | C6: Group Tour Winter | F6: 303 | G6: 7D SD | H6: ='7D SD'!Z51 -> 2312.5 | I6: ='7D SD'!AE51 -> 0.2
B7: RS | C7: Reykjavik Summer | F7: 304 | G7: 8D SD | H7: ='8D SD'!Z58 -> 2812.5 | I7: ='8D SD'!AE58 -> 0.2
B8: RW | C8: Reykjavik Winter | F8: 305 | G8: 10D SD | H8: ='10D SD'!Z66 -> 3500 | I8: ='10D SD'!AE66 -> 0.2
F9: 306 | G9: 5D GTS | H9: ='5D GTS'!Z43 -> 2190.0882 | I9: ='5D GTS'!AE43 -> 0.15619838
F10: 307 | G10: 6D GTS | H10: ='6D GTS'!Z52 -> 2798.0882 | I10: ='6D GTS'!AE52 -> 0.15656698
F11: 308 | G11: 7D GTS | H11: ='7D GTS'!Z57 -> 3339.5882 | I11: ='7D GTS'!AE57 -> 0.15678227
F12: 309 | G12: 8D GTS | H12: ='8D GTS'!Z59 -> 4223.0882 | I12: ='8D GTS'!AE59 -> 0.15701501
F13: 310 | G13: 10D GTS | H13: ='10D GTS'!Z62 -> 5159.7882 | I13: ='10D GTS'!AE62 -> 0.15717471
F14: 311 | G14: 5D GTW | H14: ='5D GTW'!Z47 -> 2133.0882 | I14: ='5D GTW'!AE47 -> 0.15615305
F15: 312 | G15: 6D GTW | H15: ='6D GTW'!Z50 -> 2581.4882 | I15: ='6D GTW'!AE50 -> 0.15645558
F16: 313 | G16: 7D GTW | H16: ='7D GTW'!Z51 -> 3339.5882 | I16: ='7D GTW'!AE51 -> 0.15678227
F17: 314 | G17: 8D GTW | H17: ='8D GTW'!Z58 -> 4213.5882 | I17: ='8D GTW'!AE58 -> 0.15701303
F18: 315 | G18: 10D GTW | H18: ='10D GTW'!Z62 -> 4878.5882 | I18: ='10D GTW'!AE62 -> 0.15713321
F19: 316 | G19: 5D RS | H19: ='5D RS'!Z45 -> 2130.4706 | I19: ='5D RS'!AE45 -> 0.18712795
F20: 317 | G20: 6D RS | H20: ='6D RS'!Z48 -> 2461.7647 | I20: ='6D RS'!AE48 -> 0.18448746
F21: 318 | G21: 7D RS | H21: ='7D RS'!Z53 -> 2937.0588 | I21: ='7D RS'!AE53 -> 0.18707791
F22: 319 | G22: 8D RS | H22: ='8D RS'!Z53 -> 3376.3529 | I22: ='8D RS'!AE53 -> 0.18829576
F23: 320 | G23: 5D RW | H23: ='5D RW'!Z44 -> 1797.5294 | I23: ='5D RW'!AE44 -> 0.19511748
F24: 321 | G24: 6D RW | H24: ='6D RW'!Z52 -> 2108.8235 | I24: ='6D RW'!AE52 -> 0.19025941
F25: 322 | G25: 7D RW | H25: ='7D RW'!Z55 -> 2584.1176 | I25: ='7D RW'!AE55 -> 0.19214204
F26: 323 | G26: 8D RW | H26: ='8D RW'!Z52 -> 3023.4118 | I26: ='8D RW'!AE52 -> 0.19276626

Sheet 5D SD
B1: Season: All
B2: Places: Reykjavik 1N - Vik I Myrdal 1N - Hofn 1N - Selfoss 1N
B3: Pax: 2
B4: Rooming: Double
B6: ID | C6: Day | D6: Type | E6: From date | F6: To date | G6: From time | H6: To time | I6: Supplier | J6: Travel element | K6: Manual booking? | L6: Status | M6: Comments | N6: Non-refundable | O6: Refundable | P6: URL | Q6: Gross P per unit | R6: Units | S6: Gross P | T6: Supp Comm | U6: Net P | V6: Supp curr | W6: X-rate | X6: Net P NOK | Y6: Sales P per unit | Z6: Price | AA6: Sales curr | AB6: X-rate | AC6: Sales P NOK tot | AD6: GP NOK | AE6: GP % | AF6: VAT25 | AG6: VAT15 | AH6: VAT12 | AI6: VAT0-D | AJ6: VAT0-I
C7: Day 1 | D7: Arrival | J7: Keflavik: Welcome to Iceland | Q7: 0 | R7: 0 | S7: =+Q7*R7 -> 0 | T7: 0 | U7: =S7*(1-T7) -> 0 | V7: EUR | W7: =IFERROR(VLOOKUP(V7,Curr!$B$2:$C$13,2,FALSE),0) -> 11 | X7: =U7*W7 -> 0 | Y7: =Q7 -> 0 | Z7: =+Y7*R7 -> 0 | AA7: EUR | AB7: =IFERROR(VLOOKUP(AA7,Curr!$B$2:$C$13,2,FALSE),0) -> 11 | AC7: =+Y7*AB7*R7 -> 0 | AD7: =+AC7-X7 -> 0 | AE7: =IFERROR(AD7/AC7,0) -> 0
C8: Day 1 | D8: Car | J8: Keflavik: Pick up your rental car at the car rental office - A 4x4 will with room for 4 luggages will be provided - Includes: Basic Insuarance - Excludes: Deposit | P8: https://www.ratehawk.com/cars/?route=965846080%2C965846080&date=2026-06-14T09%3A00%2C2026-06-18T18%3A00&age=26%2C69&sid=c2238b01-0af9-4e1e-b966-e14d15ef26da | Q8: 300 | R8: 1 | S8: =+Q8*R8 -> 300 | T8: 0 | U8: =S8*(1-T8) -> 300 | V8: EUR | W8: =IFERROR(VLOOKUP(V8,Curr!$B$2:$C$13,2,FALSE),0) -> 11 | X8: =U8*W8 -> 3300 | Y8: =Q8/0.8 -> 375 | Z8: =+Y8*R8 -> 375 | AA8: EUR | AB8: =IFERROR(VLOOKUP(AA8,Curr!$B$2:$C$13,2,FALSE),0) -> 11 | AC8: =+Y8*AB8*R8 -> 4125 | AD8: =+AC8-X8 -> 825 | AE8: =IFERROR(AD8/AC8,0) -> 0.2
C9: Day 1 | D9: Drive | J9: Keflavik: Drive to Reykjavik - Driving time: 45 min - 1 hr - Optional Stops: Reykjanes lava fields, Coastal views along Route 41, Faxaflói Bay viewpoints (weather permitting) - Hidden Gems: Small roadside lava formations, Quiet pull-offs with ocean views, Reykjanes Peninsula backroad detours (only if not rushing) | Q9: 0 | R9: 0 | S9: =+Q9*R9 -> 0 | T9: 0 | U9: =S9*(1-T9) -> 0 | V9: EUR | W9: =IFERROR(VLOOKUP(V9,Curr!$B$2:$C$13,2,FALSE),0) -> 11 | X9: =U9*W9 -> 0 | Y9: =Q9 -> 0 | Z9: =+Y9*R9 -> 0 | AA9: EUR | AB9: =IFERROR(VLOOKUP(AA9,Curr!$B$2:$C$13,2,FALSE),0) -> 11 | AC9: =+Y9*AB9*R9 -> 0 | AD9: =+AC9-X9 -> 0 | AE9: =IFERROR(AD9/AC9,0) -> 0
C10: Day 1 | D10: Hotel | J10: Reykjavik: Check in to your accommodation for a 1 night stay - Cenrally located 3/4-star hotel - Standard room - breakfast included | P10: https://www.ratehawk.com/?sid=5c11424c-1694-4e32-9a64-786852f88adb | Q10: 200 | R10: 1 | S10: =+Q10*R10 -> 200 | T10: 0 | U10: =S10*(1-T10) -> 200 | V10: EUR | W10: =IFERROR(VLOOKUP(V10,Curr!$B$2:$C$13,2,FALSE),0) -> 11 | X10: =U10*W10 -> 2200 | Y10: =Q10/0.8 -> 250 | Z10: =+Y10*R10 -> 250 | AA10: EUR | AB10: =IFERROR(VLOOKUP(AA10,Curr!$B$2:$C$13,2,FALSE),0) -> 11 | AC10: =+Y10*AB10*R10 -> 2750 | AD10: =+AC10-X10 -> 550 | AE10: =IFERROR(AD10/AC10,0) -> 0.2
C11: Day 1 | D11: Leisure | J11: Reykjavik: Spend time at leisure | Q11: 0 | R11: 0 | S11: =+Q11*R11 -> 0 | T11: 0 | U11: =S11*(1-T11) -> 0 | V11: EUR | W11: =IFERROR(VLOOKUP(V11,Curr!$B$2:$C$13,2,FALSE),0) -> 11 | X11: =U11*W11 -> 0 | Y11: =Q11 -> 0 | Z11: =+Y11*R11 -> 0 | AA11: EUR | AB11: =IFERROR(VLOOKUP(AA11,Curr!$B$2:$C$13,2,FALSE),0) -> 11 | AC11: =+Y11*AB11*R11 -> 0 | AD11: =+AC11-X11 -> 0 | AE11: =IFERROR(AD11/AC11,0) -> 0
S12: =+Q12*R12 -> 0 | T12: 0 | U12: =S12*(1-T12) -> 0 | V12: EUR | W12: =IFERROR(VLOOKUP(V12,Curr!$B$2:$C$13,2,FALSE),0) -> 11 | X12: =U12*W12 -> 0 | Y12: =Q12 -> 0 | Z12: =+Y12*R12 -> 0 | AA12: EUR | AB12: =IFERROR(VLOOKUP(AA12,Curr!$B$2:$C$13,2,FALSE),0) -> 11 | AC12: =+Y12*AB12*R12 -> 0 | AD12: =+AC12-X12 -> 0 | AE12: =IFERROR(AD12/AC12,0) -> 0
C13: Day 2 | D13: Drive | J13: Reykjavik: Drive to Vik I Myrdal via the Golden Circle - Driving time: 5.5hrs - 6.5hrs - Highlights: Þingvellir National Park, Geysir (Strokkur), Gullfoss, Seljalandsfoss, Skógafoss, Reynisfjara - Hidden Gems: Kerið, Gljúfrabúi, Dyrhólaey coastal viewpoints (weather permitting) | Q13: 0 | R13: 0 | S13: =+Q13*R13 -> 0 | T13: 0 | U13: =S13*(1-T13) -> 0 | V13: EUR | W13: =IFERROR(VLOOKUP(V13,Curr!$B$2:$C$13,2,FALSE),0) -> 11 | X13: =U13*W13 -> 0 | Y13: =Q13 -> 0 | Z13: =+Y13*R13 -> 0 | AA13: EUR | AB13: =IFERROR(VLOOKUP(AA13,Curr!$B$2:$C$13,2,FALSE),0) -> 11 | AC13: =+Y13*AB13*R13 -> 0 | AD13: =+AC13-X13 -> 0 | AE13: =IFERROR(AD13/AC13,0) -> 0
C14: Day 2 | D14: Hotel | J14: Vik i Myrdal: Check in to your accommodation for a 1 night stay - Cenrally located 3/4-star hotel - Standard room - breakfast included | Q14: 250 | R14: 1 | S14: =+Q14*R14 -> 250 | T14: 0 | U14: =S14*(1-T14) -> 250 | V14: EUR | W14: =IFERROR(VLOOKUP(V14,Curr!$B$2:$C$13,2,FALSE),0) -> 11 | X14: =U14*W14 -> 2750 | Y14: =Q14/0.8 -> 312.5 | Z14: =+Y14*R14 -> 312.5 | AA14: EUR | AB14: =IFERROR(VLOOKUP(AA14,Curr!$B$2:$C$13,2,FALSE),0) -> 11 | AC14: =+Y14*AB14*R14 -> 3437.5 | AD14: =+AC14-X14 -> 687.5 | AE14: =IFERROR(AD14/AC14,0) -> 0.2
C15: Day 2 | D15: Leisure | J15: Vik i Myrdal: Spend time at leisure | Q15: 0 | R15: 0 | S15: =+Q15*R15 -> 0 | T15: 0 | U15: =S15*(1-T15) -> 0 | V15: EUR | W15: =IFERROR(VLOOKUP(V15,Curr!$B$2:$C$13,2,FALSE),0) -> 11 | X15: =U15*W15 -> 0 | Y15: =Q15 -> 0 | Z15: =+Y15*R15 -> 0 | AA15: EUR | AB15: =IFERROR(VLOOKUP(AA15,Curr!$B$2:$C$13,2,FALSE),0) -> 11 | AC15: =+Y15*AB15*R15 -> 0 | AD15: =+AC15-X15 -> 0 | AE15: =IFERROR(AD15/AC15,0) -> 0
S16: =+Q16*R16 -> 0 | T16: 0 | U16: =S16*(1-T16) -> 0 | V16: EUR | W16: =IFERROR(VLOOKUP(V16,Curr!$B$2:$C$13,2,FALSE),0) -> 11 | X16: =U16*W16 -> 0 | Y16: =Q16 -> 0 | Z16: =+Y16*R16 -> 0 | AA16: EUR | AB16: =IFERROR(VLOOKUP(AA16,Curr!$B$2:$C$13,2,FALSE),0) -> 11 | AC16: =+Y16*AB16*R16 -> 0 | AD16: =+AC16-X16 -> 0 | AE16: =IFERROR(AD16/AC16,0) -> 0
C17: Day 3 | D17: Drive | J17: Vik i Myrdal: Drive to Höfn - Driving time: 4.5hrs - 5.5 hrs - Highlights: Fjaðrárgljúfur, Skaftafell, Svartifoss, Jökulsárlón, Diamond Beach - Hidden Gems: Moss-covered lava fields of Eldhraun, Svínafellsjökull, Quiet pull-offs along Skeiðarársandur outwash plain | Q17: 0 | R17: 0 | S17: =+Q17*R17 -> 0 | T17: 0 | U17: =S17*(1-T17) -> 0 | V17: EUR | W17: =IFERROR(VLOOKUP(V17,Curr!$B$2:$C$13,2,FALSE),0) -> 11 | X17: =U17*W17 -> 0 | Y17: =Q17 -> 0 | Z17: =+Y17*R17 -> 0 | AA17: EUR | AB17: =IFERROR(VLOOKUP(AA17,Curr!$B$2:$C$13,2,FALSE),0) -> 11 | AC17: =+Y17*AB17*R17 -> 0 | AD17: =+AC17-X17 -> 0 | AE17: =IFERROR(AD17/AC17,0) -> 0
C18: Day 3 | D18: Hotel | J18: Höfn: Check in to your accommodation for a 1 night stay - Cenrally located 3/4-star hotel - Standard room - breakfast included | Q18: 200 | R18: 1 | S18: =+Q18*R18 -> 200 | T18: 0 | U18: =S18*(1-T18) -> 200 | V18: EUR | W18: =IFERROR(VLOOKUP(V18,Curr!$B$2:$C$13,2,FALSE),0) -> 11 | X18: =U18*W18 -> 2200 | Y18: =Q18/0.8 -> 250 | Z18: =+Y18*R18 -> 250 | AA18: EUR | AB18: =IFERROR(VLOOKUP(AA18,Curr!$B$2:$C$13,2,FALSE),0) -> 11 | AC18: =+Y18*AB18*R18 -> 2750 | AD18: =+AC18-X18 -> 550 | AE18: =IFERROR(AD18/AC18,0) -> 0.2
C19: Day 3 | D19: Leisure | J19: Höfn: Spend time at leisure | Q19: 0 | R19: 0 | S19: =+Q19*R19 -> 0 | T19: 0 | U19: =S19*(1-T19) -> 0 | V19: EUR | W19: =IFERROR(VLOOKUP(V19,Curr!$B$2:$C$13,2,FALSE),0) -> 11 | X19: =U19*W19 -> 0 | Y19: =Q19 -> 0 | Z19: =+Y19*R19 -> 0 | AA19: EUR | AB19: =IFERROR(VLOOKUP(AA19,Curr!$B$2:$C$13,2,FALSE),0) -> 11 | AC19: =+Y19*AB19*R19 -> 0 | AD19: =+AC19-X19 -> 0 | AE19: =IFERROR(AD19/AC19,0) -> 0
S20: =+Q20*R20 -> 0 | T20: 0 | U20: =S20*(1-T20) -> 0 | V20: EUR | W20: =IFERROR(VLOOKUP(V20,Curr!$B$2:$C$13,2,FALSE),0) -> 11 | X20: =U20*W20 -> 0 | Y20: =Q20 -> 0 | Z20: =+Y20*R20 -> 0 | AA20: EUR | AB20: =IFERROR(VLOOKUP(AA20,Curr!$B$2:$C$13,2,FALSE),0) -> 11 | AC20: =+Y20*AB20*R20 -> 0 | AD20: =+AC20-X20 -> 0 | AE20: =IFERROR(AD20/AC20,0) -> 0
C21: Day 4 | D21: Drive | J21: Höfn: Drive to Selfoss - Driving time: 6hrs - 7hrs - Highlights: Vatnajökull views, Skaftafell, Eldhraun, Skógafoss, Seljalandsfoss - Hidden Gems: Svínafellsjökull, Gljúfrabúi, Quiet stretches of Skeiðarársandur outwash plains | Q21: 0 | R21: 0 | S21: =+Q21*R21 -> 0 | T21: 0 | U21: =S21*(1-T21) -> 0 | V21: EUR | W21: =IFERROR(VLOOKUP(V21,Curr!$B$2:$C$13,2,FALSE),0) -> 11 | X21: =U21*W21 -> 0 | Y21: =Q21 -> 0 | Z21: =+Y21*R21 -> 0 | AA21: EUR | AB21: =IFERROR(VLOOKUP(AA21,Curr!$B$2:$C$13,2,FALSE),0) -> 11 | AC21: =+Y21*AB21*R21 -> 0 | AD21: =+AC21-X21 -> 0 | AE21: =IFERROR(AD21/AC21,0) -> 0
C22: Day 4 | D22: Hotel | J22: Selfoss: Check in to your accommodation for a 1 night stay - Cenrally located 3/4-star hotel - Standard room - breakfast included | Q22: 225 | R22: 1 | S22: =+Q22*R22 -> 225 | T22: 0 | U22: =S22*(1-T22) -> 225 | V22: EUR | W22: =IFERROR(VLOOKUP(V22,Curr!$B$2:$C$13,2,FALSE),0) -> 11 | X22: =U22*W22 -> 2475 | Y22: =Q22/0.8 -> 281.25 | Z22: =+Y22*R22 -> 281.25 | AA22: EUR | AB22: =IFERROR(VLOOKUP(AA22,Curr!$B$2:$C$13,2,FALSE),0) -> 11 | AC22: =+Y22*AB22*R22 -> 3093.75 | AD22: =+AC22-X22 -> 618.75 | AE22: =IFERROR(AD22/AC22,0) -> 0.2
C23: Day 4 | D23: Leisure | J23: Selfoss: Spend time at leisure | Q23: 0 | R23: 0 | S23: =+Q23*R23 -> 0 | T23: 0 | U23: =S23*(1-T23) -> 0 | V23: EUR | W23: =IFERROR(VLOOKUP(V23,Curr!$B$2:$C$13,2,FALSE),0) -> 11 | X23: =U23*W23 -> 0 | Y23: =Q23 -> 0 | Z23: =+Y23*R23 -> 0 | AA23: EUR | AB23: =IFERROR(VLOOKUP(AA23,Curr!$B$2:$C$13,2,FALSE),0) -> 11 | AC23: =+Y23*AB23*R23 -> 0 | AD23: =+AC23-X23 -> 0 | AE23: =IFERROR(AD23/AC23,0) -> 0
S24: =+Q24*R24 -> 0 | T24: 0 | U24: =S24*(1-T24) -> 0 | V24: EUR | W24: =IFERROR(VLOOKUP(V24,Curr!$B$2:$C$13,2,FALSE),0) -> 11 | X24: =U24*W24 -> 0 | Y24: =Q24 -> 0 | Z24: =+Y24*R24 -> 0 | AA24: EUR | AB24: =IFERROR(VLOOKUP(AA24,Curr!$B$2:$C$13,2,FALSE),0) -> 11 | AC24: =+Y24*AB24*R24 -> 0 | AD24: =+AC24-X24 -> 0 | AE24: =IFERROR(AD24/AC24,0) -> 0
C25: Day 5 | D25: Drive | J25: Selfoss: Drive to Keflavik Airport - Driving time: 1.5hrs - 2hrs - Highlights: Reykjanes lava landscapes, Reykjanes Peninsula scenery, Coastal views approaching Keflavík - Hidden Gems: Bridge Between Continents, Gunnuhver, Reykjanesviti | Q25: 0 | R25: 0 | S25: =+Q25*R25 -> 0 | T25: 0 | U25: =S25*(1-T25) -> 0 | V25: EUR | W25: =IFERROR(VLOOKUP(V25,Curr!$B$2:$C$13,2,FALSE),0) -> 11 | X25: =U25*W25 -> 0 | Y25: =Q25 -> 0 | Z25: =+Y25*R25 -> 0 | AA25: EUR | AB25: =IFERROR(VLOOKUP(AA25,Curr!$B$2:$C$13,2,FALSE),0) -> 11 | AC25: =+Y25*AB25*R25 -> 0 | AD25: =+AC25-X25 -> 0 | AE25: =IFERROR(AD25/AC25,0) -> 0
C26: Day 5 | D26: Car | J26: Keflavik: Deliver your car at the car rental office | Q26: 0 | R26: 0 | S26: =+Q26*R26 -> 0 | T26: 0 | U26: =S26*(1-T26) -> 0 | V26: EUR | W26: =IFERROR(VLOOKUP(V26,Curr!$B$2:$C$13,2,FALSE),0) -> 11 | X26: =U26*W26 -> 0 | Y26: =Q26 -> 0 | Z26: =+Y26*R26 -> 0 | AA26: EUR | AB26: =IFERROR(VLOOKUP(AA26,Curr!$B$2:$C$13,2,FALSE),0) -> 11 | AC26: =+Y26*AB26*R26 -> 0 | AD26: =+AC26-X26 -> 0 | AE26: =IFERROR(AD26/AC26,0) -> 0
C27: Day 5 | D27: Departure | J27: Keflavik: Departure home | Q27: 0 | R27: 0 | S27: =+Q27*R27 -> 0 | T27: 0 | U27: =S27*(1-T27) -> 0 | V27: EUR | W27: =IFERROR(VLOOKUP(V27,Curr!$B$2:$C$13,2,FALSE),0) -> 11 | X27: =U27*W27 -> 0 | Y27: =Q27 -> 0 | Z27: =+Y27*R27 -> 0 | AA27: EUR | AB27: =IFERROR(VLOOKUP(AA27,Curr!$B$2:$C$13,2,FALSE),0) -> 11 | AC27: =+Y27*AB27*R27 -> 0 | AD27: =+AC27-X27 -> 0 | AE27: =IFERROR(AD27/AC27,0) -> 0
S28: =+Q28*R28 -> 0 | T28: 0 | U28: =S28*(1-T28) -> 0 | V28: EUR | W28: =IFERROR(VLOOKUP(V28,Curr!$B$2:$C$13,2,FALSE),0) -> 11 | X28: =U28*W28 -> 0 | Y28: =Q28 -> 0 | Z28: =+Y28*R28 -> 0 | AA28: EUR | AB28: =IFERROR(VLOOKUP(AA28,Curr!$B$2:$C$13,2,FALSE),0) -> 11 | AC28: =+Y28*AB28*R28 -> 0 | AD28: =+AC28-X28 -> 0 | AE28: =IFERROR(AD28/AC28,0) -> 0
S29: =+Q29*R29 -> 0 | T29: 0 | U29: =S29*(1-T29) -> 0 | V29: EUR | W29: =IFERROR(VLOOKUP(V29,Curr!$B$2:$C$13,2,FALSE),0) -> 11 | X29: =U29*W29 -> 0 | Y29: =Q29 -> 0 | Z29: =+Y29*R29 -> 0 | AA29: EUR | AB29: =IFERROR(VLOOKUP(AA29,Curr!$B$2:$C$13,2,FALSE),0) -> 11 | AC29: =+Y29*AB29*R29 -> 0 | AD29: =+AC29-X29 -> 0 | AE29: =IFERROR(AD29/AC29,0) -> 0
C30: Day 1 | D30: Activity Upgrade | J30: Reykjavík: City Walking Tour - Time: 2:00 pm - 5:00 pm - Meeting point: Hallgrímskirkja, Hallgrimstorgi 1 - Includes: Professional, English-speaking guide - Highlights: Hallgrímskirkja, All the major landmarks, Hidden street art & local corners, Iceland in a nutshell | P30: https://booknordics.com/iceland/western-iceland/reykjavik/reykjavik-walking-tour-small-group-citywalk | Q30: 37 | R30: 0 | S30: =+Q30*R30 -> 0 | T30: 0.2 | U30: =S30*(1-T30) -> 0 | V30: EUR | W30: =IFERROR(VLOOKUP(V30,Curr!$B$2:$C$13,2,FALSE),0) -> 11 | X30: =U30*W30 -> 0 | Y30: =Q30 -> 37 | Z30: =+Y30*R30 -> 0 | AA30: EUR | AB30: =IFERROR(VLOOKUP(AA30,Curr!$B$2:$C$13,2,FALSE),0) -> 11 | AC30: =+Y30*AB30*R30 -> 0 | AD30: =+AC30-X30 -> 0 | AE30: =IFERROR(AD30/AC30,0) -> 0
C31: Day 1 | D31: Activity Upgrade | J31: Reykjavík: Northern Lights Minibus Tour - Small Group - Time: 8:30 pm - 12:30 am - Meeting point: Hotel pick up - Includes: Pick-up/drop-off in central Reykjavik, Professional, English-speaking guide, Northern lights tour in a small group, Ticket to Aurora Museum Reykjavik, Free Wi-Fi onboard the vehicle, Hot chocolate and refreshments | P31: https://booknordics.com/iceland/western-iceland/reykjavik/northern-lights-small-group-minibus-tour | Q31: 89 | R31: 0 | S31: =+Q31*R31 -> 0 | T31: 0.25 | U31: =S31*(1-T31) -> 0 | V31: EUR | W31: =IFERROR(VLOOKUP(V31,Curr!$B$2:$C$13,2,FALSE),0) -> 11 | X31: =U31*W31 -> 0 | Y31: =Q31 -> 89 | Z31: =+Y31*R31 -> 0 | AA31: EUR | AB31: =IFERROR(VLOOKUP(AA31,Curr!$B$2:$C$13,2,FALSE),0) -> 11 | AC31: =+Y31*AB31*R31 -> 0 | AD31: =+AC31-X31 -> 0 | AE31: =IFERROR(AD31/AC31,0) -> 0
C32: Day 3 | D32: Activity Upgrade | J32: Vik: Katla Ice Cave Super Jeep Tour - Time: 09:30 am - 12:30 pm - Meeting point: Tröll Expeditions Katla Ice Cave - Includes: Super Jeep excursion to Katla Ice Cave, Certified glacier guide and glacier hike, Experienced off-road driver, Ice cave gear: crampons, and helmet | P32: https://booknordics.com/iceland/southern-iceland/vik/katla-ice-cave-super-jeep-from-vik | Q32: 205 | R32: 0 | S32: =+Q32*R32 -> 0 | T32: 0 | U32: =S32*(1-T32) -> 0 | V32: EUR | W32: =IFERROR(VLOOKUP(V32,Curr!$B$2:$C$13,2,FALSE),0) -> 11 | X32: =U32*W32 -> 0 | Y32: =Q32 -> 205 | Z32: =+Y32*R32 -> 0 | AA32: EUR | AB32: =IFERROR(VLOOKUP(AA32,Curr!$B$2:$C$13,2,FALSE),0) -> 11 | AC32: =+Y32*AB32*R32 -> 0 | AD32: =+AC32-X32 -> 0 | AE32: =IFERROR(AD32/AC32,0) -> 0
C33: Day 5 | D33: Activity Upgrade | J33: Reykjavik: Blue Lagoon Comfort Package - Time: 09:00 am - 1:00 pm - Meeting point: Hotel Pick up - Includes: Return transfer, Entrance to the Blue Lagoon, Silica mud mask at the Mask Bar, Use of towel, shampoo, conditioner, and moisturizer, Private locker, Non-alcoholic drink at the in-water bar | P33: https://booknordics.com/iceland/western-iceland/reykjavik/reykjavik-blue-lagoon-comfort-including-admission | Q33: 163 | R33: 0 | S33: =+Q33*R33 -> 0 | T33: 0.2 | U33: =S33*(1-T33) -> 0 | V33: EUR | W33: =IFERROR(VLOOKUP(V33,Curr!$B$2:$C$13,2,FALSE),0) -> 11 | X33: =U33*W33 -> 0 | Y33: =Q33 -> 163 | Z33: =+Y33*R33 -> 0 | AA33: EUR | AB33: =IFERROR(VLOOKUP(AA33,Curr!$B$2:$C$13,2,FALSE),0) -> 11 | AC33: =+Y33*AB33*R33 -> 0 | AD33: =+AC33-X33 -> 0 | AE33: =IFERROR(AD33/AC33,0) -> 0
S34: =+Q34*R34 -> 0 | T34: 0 | U34: =S34*(1-T34) -> 0 | V34: EUR | W34: =IFERROR(VLOOKUP(V34,Curr!$B$2:$C$13,2,FALSE),0) -> 11 | X34: =U34*W34 -> 0 | Y34: =Q34 -> 0 | Z34: =+Y34*R34 -> 0 | AA34: EUR | AB34: =IFERROR(VLOOKUP(AA34,Curr!$B$2:$C$13,2,FALSE),0) -> 11 | AC34: =+Y34*AB34*R34 -> 0 | AD34: =+AC34-X34 -> 0 | AE34: =IFERROR(AD34/AC34,0) -> 0
S35: =+Q35*R35 -> 0 | T35: 0 | U35: =S35*(1-T35) -> 0 | V35: EUR | W35: =IFERROR(VLOOKUP(V35,Curr!$B$2:$C$13,2,FALSE),0) -> 11 | X35: =U35*W35 -> 0 | Y35: =Q35 -> 0 | Z35: =+Y35*R35 -> 0 | AA35: EUR | AB35: =IFERROR(VLOOKUP(AA35,Curr!$B$2:$C$13,2,FALSE),0) -> 11 | AC35: =+Y35*AB35*R35 -> 0 | AD35: =+AC35-X35 -> 0 | AE35: =IFERROR(AD35/AC35,0) -> 0
C36: Day 1 | D36: Extra Hotel Night | J36: Reykjavik: Add on an extra night in Reykjavik | Q36: 225 | R36: 0 | S36: =+Q36*R36 -> 0 | T36: 0 | U36: =S36*(1-T36) -> 0 | V36: EUR | W36: =IFERROR(VLOOKUP(V36,Curr!$B$2:$C$13,2,FALSE),0) -> 11 | X36: =U36*W36 -> 0 | Y36: =Q36/0.85 -> 264.70588 | Z36: =+Y36*R36 -> 0 | AA36: EUR | AB36: =IFERROR(VLOOKUP(AA36,Curr!$B$2:$C$13,2,FALSE),0) -> 11 | AC36: =+Y36*AB36*R36 -> 0 | AD36: =+AC36-X36 -> 0 | AE36: =IFERROR(AD36/AC36,0) -> 0
C37: Day 5 | D37: Extra Hotel Night | J37: Reykjavik: Add on an extra night in Reykjavik | Q37: 225 | R37: 0 | S37: =+Q37*R37 -> 0 | T37: 0 | U37: =S37*(1-T37) -> 0 | V37: EUR | W37: =IFERROR(VLOOKUP(V37,Curr!$B$2:$C$13,2,FALSE),0) -> 11 | X37: =U37*W37 -> 0 | Y37: =Q37/0.85 -> 264.70588 | Z37: =+Y37*R37 -> 0 | AA37: EUR | AB37: =IFERROR(VLOOKUP(AA37,Curr!$B$2:$C$13,2,FALSE),0) -> 11 | AC37: =+Y37*AB37*R37 -> 0 | AD37: =+AC37-X37 -> 0 | AE37: =IFERROR(AD37/AC37,0) -> 0
S38: =+Q38*R38 -> 0 | T38: 0 | U38: =S38*(1-T38) -> 0 | V38: EUR | W38: =IFERROR(VLOOKUP(V38,Curr!$B$2:$C$13,2,FALSE),0) -> 11 | X38: =U38*W38 -> 0 | Y38: =Q38 -> 0 | Z38: =+Y38*R38 -> 0 | AA38: EUR | AB38: =IFERROR(VLOOKUP(AA38,Curr!$B$2:$C$13,2,FALSE),0) -> 11 | AC38: =+Y38*AB38*R38 -> 0 | AD38: =+AC38-X38 -> 0 | AE38: =IFERROR(AD38/AC38,0) -> 0
S39: =+Q39*R39 -> 0 | T39: 0 | U39: =S39*(1-T39) -> 0 | V39: EUR | W39: =IFERROR(VLOOKUP(V39,Curr!$B$2:$C$13,2,FALSE),0) -> 11 | X39: =U39*W39 -> 0 | Y39: =Q39 -> 0 | Z39: =+Y39*R39 -> 0 | AA39: EUR | AB39: =IFERROR(VLOOKUP(AA39,Curr!$B$2:$C$13,2,FALSE),0) -> 11 | AC39: =+Y39*AB39*R39 -> 0 | AD39: =+AC39-X39 -> 0 | AE39: =IFERROR(AD39/AC39,0) -> 0
S40: =+Q40*R40 -> 0 | T40: 0 | U40: =S40*(1-T40) -> 0 | V40: EUR | W40: =IFERROR(VLOOKUP(V40,Curr!$B$2:$C$13,2,FALSE),0) -> 11 | X40: =U40*W40 -> 0 | Y40: =Q40 -> 0 | Z40: =+Y40*R40 -> 0 | AA40: EUR | AB40: =IFERROR(VLOOKUP(AA40,Curr!$B$2:$C$13,2,FALSE),0) -> 11 | AC40: =+Y40*AB40*R40 -> 0 | AD40: =+AC40-X40 -> 0 | AE40: =IFERROR(AD40/AC40,0) -> 0
S41: =+Q41*R41 -> 0 | T41: 0 | U41: =S41*(1-T41) -> 0 | V41: EUR | W41: =IFERROR(VLOOKUP(V41,Curr!$B$2:$C$13,2,FALSE),0) -> 11 | X41: =U41*W41 -> 0 | Y41: =Q41 -> 0 | Z41: =+Y41*R41 -> 0 | AA41: EUR | AB41: =IFERROR(VLOOKUP(AA41,Curr!$B$2:$C$13,2,FALSE),0) -> 11 | AC41: =+Y41*AB41*R41 -> 0 | AD41: =+AC41-X41 -> 0 | AE41: =IFERROR(AD41/AC41,0) -> 0
S42: =+Q42*R42 -> 0 | T42: 0 | U42: =S42*(1-T42) -> 0 | V42: EUR | W42: =IFERROR(VLOOKUP(V42,Curr!$B$2:$C$13,2,FALSE),0) -> 11 | X42: =U42*W42 -> 0 | Y42: =Q42 -> 0 | Z42: =+Y42*R42 -> 0 | AA42: EUR | AB42: =IFERROR(VLOOKUP(AA42,Curr!$B$2:$C$13,2,FALSE),0) -> 11 | AC42: =+Y42*AB42*R42 -> 0 | AD42: =+AC42-X42 -> 0 | AE42: =IFERROR(AD42/AC42,0) -> 0
S43: =+Q43*R43 -> 0 | T43: 0 | U43: =S43*(1-T43) -> 0 | V43: EUR | W43: =IFERROR(VLOOKUP(V43,Curr!$B$2:$C$13,2,FALSE),0) -> 11 | X43: =U43*W43 -> 0 | Y43: =Q43 -> 0 | Z43: =+Y43*R43 -> 0 | AA43: EUR | AB43: =IFERROR(VLOOKUP(AA43,Curr!$B$2:$C$13,2,FALSE),0) -> 11 | AC43: =+Y43*AB43*R43 -> 0 | AD43: =+AC43-X43 -> 0 | AE43: =IFERROR(AD43/AC43,0) -> 0
S44: =+Q44*R44 -> 0 | T44: 0 | U44: =S44*(1-T44) -> 0 | V44: EUR | W44: =IFERROR(VLOOKUP(V44,Curr!$B$2:$C$13,2,FALSE),0) -> 11 | X44: =U44*W44 -> 0 | Y44: =Q44 -> 0 | Z44: =+Y44*R44 -> 0 | AA44: EUR | AB44: =IFERROR(VLOOKUP(AA44,Curr!$B$2:$C$13,2,FALSE),0) -> 11 | AC44: =+Y44*AB44*R44 -> 0 | AD44: =+AC44-X44 -> 0 | AE44: =IFERROR(AD44/AC44,0) -> 0
S45: =+Q45*R45 -> 0 | T45: 0 | U45: =S45*(1-T45) -> 0 | V45: EUR | W45: =IFERROR(VLOOKUP(V45,Curr!$B$2:$C$13,2,FALSE),0) -> 11 | X45: =U45*W45 -> 0 | Y45: =Q45 -> 0 | Z45: =+Y45*R45 -> 0 | AA45: EUR | AB45: =IFERROR(VLOOKUP(AA45,Curr!$B$2:$C$13,2,FALSE),0) -> 11 | AC45: =+Y45*AB45*R45 -> 0 | AD45: =+AC45-X45 -> 0 | AE45: =IFERROR(AD45/AC45,0) -> 0
S46: =+Q46*R46 -> 0 | T46: 0 | U46: =S46*(1-T46) -> 0 | V46: EUR | W46: =IFERROR(VLOOKUP(V46,Curr!$B$2:$C$13,2,FALSE),0) -> 11 | X46: =U46*W46 -> 0 | Y46: =Q46 -> 0 | Z46: =+Y46*R46 -> 0 | AA46: EUR | AB46: =IFERROR(VLOOKUP(AA46,Curr!$B$2:$C$13,2,FALSE),0) -> 11 | AC46: =+Y46*AB46*R46 -> 0 | AD46: =+AC46-X46 -> 0 | AE46: =IFERROR(AD46/AC46,0) -> 0
S47: =+Q47*R47 -> 0 | T47: 0 | U47: =S47*(1-T47) -> 0 | V47: EUR | W47: =IFERROR(VLOOKUP(V47,Curr!$B$2:$C$13,2,FALSE),0) -> 11 | X47: =U47*W47 -> 0 | Y47: =Q47 -> 0 | Z47: =+Y47*R47 -> 0 | AA47: EUR | AB47: =IFERROR(VLOOKUP(AA47,Curr!$B$2:$C$13,2,FALSE),0) -> 11 | AC47: =+Y47*AB47*R47 -> 0 | AD47: =+AC47-X47 -> 0 | AE47: =IFERROR(AD47/AC47,0) -> 0
S48: =+Q48*R48 -> 0 | T48: 0 | U48: =S48*(1-T48) -> 0 | V48: EUR | W48: =IFERROR(VLOOKUP(V48,Curr!$B$2:$C$13,2,FALSE),0) -> 11 | X48: =U48*W48 -> 0 | Y48: =Q48 -> 0 | Z48: =+Y48*R48 -> 0 | AA48: EUR | AB48: =IFERROR(VLOOKUP(AA48,Curr!$B$2:$C$13,2,FALSE),0) -> 11 | AC48: =+Y48*AB48*R48 -> 0 | AD48: =+AC48-X48 -> 0 | AE48: =IFERROR(AD48/AC48,0) -> 0
S49: =+Q49*R49 -> 0 | T49: 0 | U49: =S49*(1-T49) -> 0 | V49: EUR | W49: =IFERROR(VLOOKUP(V49,Curr!$B$2:$C$13,2,FALSE),0) -> 11 | X49: =U49*W49 -> 0 | Y49: =Q49 -> 0 | Z49: =+Y49*R49 -> 0 | AA49: EUR | AB49: =IFERROR(VLOOKUP(AA49,Curr!$B$2:$C$13,2,FALSE),0) -> 11 | AC49: =+Y49*AB49*R49 -> 0 | AD49: =+AC49-X49 -> 0 | AE49: =IFERROR(AD49/AC49,0) -> 0
B51: Totals | D51: x | E51: x | F51: x | G51: x | H51: x | I51: x | J51: x | K51: x | L51: x | M51: x | N51: x | O51: x | P51: x | Q51: x | R51: x | S51: x | T51: x | U51: x | V51: x | W51: x | X51: x | Y51: x | Z51: =SUM(Z7:Z49) -> 1468.75 | AC51: =SUM(AC7:AC49) -> 16156.25 | AD51: =SUM(AD7:AD49) -> 3231.25 | AE51: =IFERROR(AD51/AC51,0) -> 0.2 | AF51: =SUM(AF8:AF50) -> 0 | AG51: =SUM(AG8:AG50) -> 0 | AH51: =SUM(AH8:AH50) -> 0 | AI51: =SUM(AI8:AI50) -> 0 | AJ51: =SUM(AJ8:AJ50) -> 0
Y53: Fixed | Z53: 0
Y54: Variable | Z54: =Z8+Z10+Z14+Z18+Z22 -> 1468.75
Y55: Total | Z55: 1480
Y56: PP | Z56: =Z55/2 -> 740
Y59: Shoulder | Z59: =Z55 -> 1480
Y60: High | Z60: =Z59*1.2 -> 1776
Y61: Peak | Z61: =Z59*1.4 -> 2072
Y62: Low | Z62: =Z59*0.7 -> 1036

Sheet 6D SD
B1: Season: All
B2: Places: Reykjavik 1N - Vik I Myrdal 1N - Hofn 1N - Myvatn 1N - Borgarnes 1N
B3: Pax: 2
B4: Rooming: Double
B6: ID | C6: Day | D6: Type | E6: From date | F6: To date | G6: From time | H6: To time | I6: Supplier | J6: Travel element | K6: Manual booking? | L6: Status | M6: Comments | N6: Non-refundable | O6: Refundable | P6: URL | Q6: Gross P per unit | R6: Units | S6: Gross P | T6: Supp Comm | U6: Net P | V6: Supp curr | W6: X-rate | X6: Net P NOK | Y6: Sales P per unit | Z6: Price | AA6: Sales curr | AB6: X-rate | AC6: Sales P NOK tot | AD6: GP NOK | AE6: GP % | AF6: VAT25 | AG6: VAT15 | AH6: VAT12 | AI6: VAT0-D | AJ6: VAT0-I
C7: Day 1 | D7: Arrival | J7: Keflavik: Welcome to Iceland | Q7: 0 | R7: 0 | S7: =+Q7*R7 -> 0 | T7: 0 | U7: =S7*(1-T7) -> 0 | V7: EUR | W7: =IFERROR(VLOOKUP(V7,Curr!$B$2:$C$13,2,FALSE),0) -> 11 | X7: =U7*W7 -> 0 | Y7: =Q7 -> 0 | Z7: =+Y7*R7 -> 0 | AA7: EUR | AB7: =IFERROR(VLOOKUP(AA7,Curr!$B$2:$C$13,2,FALSE),0) -> 11 | AC7: =+Y7*AB7*R7 -> 0 | AD7: =+AC7-X7 -> 0 | AE7: =IFERROR(AD7/AC7,0) -> 0
C8: Day 1 | D8: Car | J8: Keflavik: Pick up your rental car at the car rental office - A 4x4 will with room for 4 luggages will be provided - Includes: Basic Insuarance - Excludes: Deposit | Q8: 450 | R8: 1 | S8: =+Q8*R8 -> 450 | T8: 0 | U8: =S8*(1-T8) -> 450 | V8: EUR | W8: =IFERROR(VLOOKUP(V8,Curr!$B$2:$C$13,2,FALSE),0) -> 11 | X8: =U8*W8 -> 4950 | Y8: =Q8/0.8 -> 562.5 | Z8: =+Y8*R8 -> 562.5 | AA8: EUR | AB8: =IFERROR(VLOOKUP(AA8,Curr!$B$2:$C$13,2,FALSE),0) -> 11 | AC8: =+Y8*AB8*R8 -> 6187.5 | AD8: =+AC8-X8 -> 1237.5 | AE8: =IFERROR(AD8/AC8,0) -> 0.2
C9: Day 1 | D9: Drive | J9: Keflavik: Drive to Reykjavik - Driving time: 45 min - 1 hr - Optional Stops: Reykjanes lava fields, Coastal views along Route 41, Faxaflói Bay viewpoints (weather permitting) - Hidden Gems: Small roadside lava formations, Quiet pull-offs with ocean views, Reykjanes Peninsula backroad detours (only if not rushing) | Q9: 0 | R9: 0 | S9: =+Q9*R9 -> 0 | T9: 0 | U9: =S9*(1-T9) -> 0 | V9: EUR | W9: =IFERROR(VLOOKUP(V9,Curr!$B$2:$C$13,2,FALSE),0) -> 11 | X9: =U9*W9 -> 0 | Y9: =Q9 -> 0 | Z9: =+Y9*R9 -> 0 | AA9: EUR | AB9: =IFERROR(VLOOKUP(AA9,Curr!$B$2:$C$13,2,FALSE),0) -> 11 | AC9: =+Y9*AB9*R9 -> 0 | AD9: =+AC9-X9 -> 0 | AE9: =IFERROR(AD9/AC9,0) -> 0
C10: Day 1 | D10: Hotel | J10: Reykjavik: Check in to your accommodation for a 1 night stay - Cenrally located 3/4-star hotel - Standard room - breakfast included | P10: https://www.ratehawk.com/?sid=5c11424c-1694-4e32-9a64-786852f88adb | Q10: 200 | R10: 1 | S10: =+Q10*R10 -> 200 | T10: 0 | U10: =S10*(1-T10) -> 200 | V10: EUR | W10: =IFERROR(VLOOKUP(V10,Curr!$B$2:$C$13,2,FALSE),0) -> 11 | X10: =U10*W10 -> 2200 | Y10: =Q10/0.8 -> 250 | Z10: =+Y10*R10 -> 250 | AA10: EUR | AB10: =IFERROR(VLOOKUP(AA10,Curr!$B$2:$C$13,2,FALSE),0) -> 11 | AC10: =+Y10*AB10*R10 -> 2750 | AD10: =+AC10-X10 -> 550 | AE10: =IFERROR(AD10/AC10,0) -> 0.2
C11: Day 1 | D11: Leisure | J11: Reykjavik: Spend time at leisure | Q11: 0 | R11: 0 | S11: =+Q11*R11 -> 0 | T11: 0 | U11: =S11*(1-T11) -> 0 | V11: EUR | W11: =IFERROR(VLOOKUP(V11,Curr!$B$2:$C$13,2,FALSE),0) -> 11 | X11: =U11*W11 -> 0 | Y11: =Q11 -> 0 | Z11: =+Y11*R11 -> 0 | AA11: EUR | AB11: =IFERROR(VLOOKUP(AA11,Curr!$B$2:$C$13,2,FALSE),0) -> 11 | AC11: =+Y11*AB11*R11 -> 0 | AD11: =+AC11-X11 -> 0 | AE11: =IFERROR(AD11/AC11,0) -> 0
S12: =+Q12*R12 -> 0 | T12: 0 | U12: =S12*(1-T12) -> 0 | V12: EUR | W12: =IFERROR(VLOOKUP(V12,Curr!$B$2:$C$13,2,FALSE),0) -> 11 | X12: =U12*W12 -> 0 | Y12: =Q12 -> 0 | Z12: =+Y12*R12 -> 0 | AA12: EUR | AB12: =IFERROR(VLOOKUP(AA12,Curr!$B$2:$C$13,2,FALSE),0) -> 11 | AC12: =+Y12*AB12*R12 -> 0 | AD12: =+AC12-X12 -> 0 | AE12: =IFERROR(AD12/AC12,0) -> 0
C13: Day 2 | D13: Drive | J13: Reykjavik: Drive to Vik I Myrdal via the Golden Circle - Driving time: 5.5hrs - 6.5hrs - Highlights: Þingvellir National Park, Geysir (Strokkur), Gullfoss, Seljalandsfoss, Skógafoss, Reynisfjara - Hidden Gems: Kerið, Gljúfrabúi, Dyrhólaey coastal viewpoints (weather permitting) | Q13: 0 | R13: 0 | S13: =+Q13*R13 -> 0 | T13: 0 | U13: =S13*(1-T13) -> 0 | V13: EUR | W13: =IFERROR(VLOOKUP(V13,Curr!$B$2:$C$13,2,FALSE),0) -> 11 | X13: =U13*W13 -> 0 | Y13: =Q13 -> 0 | Z13: =+Y13*R13 -> 0 | AA13: EUR | AB13: =IFERROR(VLOOKUP(AA13,Curr!$B$2:$C$13,2,FALSE),0) -> 11 | AC13: =+Y13*AB13*R13 -> 0 | AD13: =+AC13-X13 -> 0 | AE13: =IFERROR(AD13/AC13,0) -> 0
C14: Day 2 | D14: Hotel | J14: Vik i Myrdal: Check in to your accommodation for a 1 night stay - Cenrally located 3/4-star hotel - Standard room - breakfast included | Q14: 250 | R14: 1 | S14: =+Q14*R14 -> 250 | T14: 0 | U14: =S14*(1-T14) -> 250 | V14: EUR | W14: =IFERROR(VLOOKUP(V14,Curr!$B$2:$C$13,2,FALSE),0) -> 11 | X14: =U14*W14 -> 2750 | Y14: =Q14/0.8 -> 312.5 | Z14: =+Y14*R14 -> 312.5 | AA14: EUR | AB14: =IFERROR(VLOOKUP(AA14,Curr!$B$2:$C$13,2,FALSE),0) -> 11 | AC14: =+Y14*AB14*R14 -> 3437.5 | AD14: =+AC14-X14 -> 687.5 | AE14: =IFERROR(AD14/AC14,0) -> 0.2
C15: Day 2 | D15: Leisure | J15: Vik i Myrdal: Spend time at leisure | Q15: 0 | R15: 0 | S15: =+Q15*R15 -> 0 | T15: 0 | U15: =S15*(1-T15) -> 0 | V15: EUR | W15: =IFERROR(VLOOKUP(V15,Curr!$B$2:$C$13,2,FALSE),0) -> 11 | X15: =U15*W15 -> 0 | Y15: =Q15 -> 0 | Z15: =+Y15*R15 -> 0 | AA15: EUR | AB15: =IFERROR(VLOOKUP(AA15,Curr!$B$2:$C$13,2,FALSE),0) -> 11 | AC15: =+Y15*AB15*R15 -> 0 | AD15: =+AC15-X15 -> 0 | AE15: =IFERROR(AD15/AC15,0) -> 0
S16: =+Q16*R16 -> 0 | T16: 0 | U16: =S16*(1-T16) -> 0 | V16: EUR | W16: =IFERROR(VLOOKUP(V16,Curr!$B$2:$C$13,2,FALSE),0) -> 11 | X16: =U16*W16 -> 0 | Y16: =Q16 -> 0 | Z16: =+Y16*R16 -> 0 | AA16: EUR | AB16: =IFERROR(VLOOKUP(AA16,Curr!$B$2:$C$13,2,FALSE),0) -> 11 | AC16: =+Y16*AB16*R16 -> 0 | AD16: =+AC16-X16 -> 0 | AE16: =IFERROR(AD16/AC16,0) -> 0
C17: Day 3 | D17: Drive | J17: Vik i Myrdal: Drive to Höfn - Driving time: 4.5hrs - 5.5 hrs - Highlights: Fjaðrárgljúfur, Skaftafell, Svartifoss, Jökulsárlón, Diamond Beach - Hidden Gems: Moss-covered lava fields of Eldhraun, Svínafellsjökull, Quiet pull-offs along Skeiðarársandur outwash plain | Q17: 0 | R17: 0 | S17: =+Q17*R17 -> 0 | T17: 0 | U17: =S17*(1-T17) -> 0 | V17: EUR | W17: =IFERROR(VLOOKUP(V17,Curr!$B$2:$C$13,2,FALSE),0) -> 11 | X17: =U17*W17 -> 0 | Y17: =Q17 -> 0 | Z17: =+Y17*R17 -> 0 | AA17: EUR | AB17: =IFERROR(VLOOKUP(AA17,Curr!$B$2:$C$13,2,FALSE),0) -> 11 | AC17: =+Y17*AB17*R17 -> 0 | AD17: =+AC17-X17 -> 0 | AE17: =IFERROR(AD17/AC17,0) -> 0
C18: Day 3 | D18: Hotel | J18: Höfn: Check in to your accommodation for a 1 night stay - Cenrally located 3/4-star hotel - Standard room - breakfast included | Q18: 200 | R18: 1 | S18: =+Q18*R18 -> 200 | T18: 0 | U18: =S18*(1-T18) -> 200 | V18: EUR | W18: =IFERROR(VLOOKUP(V18,Curr!$B$2:$C$13,2,FALSE),0) -> 11 | X18: =U18*W18 -> 2200 | Y18: =Q18/0.8 -> 250 | Z18: =+Y18*R18 -> 250 | AA18: EUR | AB18: =IFERROR(VLOOKUP(AA18,Curr!$B$2:$C$13,2,FALSE),0) -> 11 | AC18: =+Y18*AB18*R18 -> 2750 | AD18: =+AC18-X18 -> 550 | AE18: =IFERROR(AD18/AC18,0) -> 0.2
C19: Day 3 | D19: Leisure | J19: Höfn: Spend time at leisure | Q19: 0 | R19: 0 | S19: =+Q19*R19 -> 0 | T19: 0 | U19: =S19*(1-T19) -> 0 | V19: EUR | W19: =IFERROR(VLOOKUP(V19,Curr!$B$2:$C$13,2,FALSE),0) -> 11 | X19: =U19*W19 -> 0 | Y19: =Q19 -> 0 | Z19: =+Y19*R19 -> 0 | AA19: EUR | AB19: =IFERROR(VLOOKUP(AA19,Curr!$B$2:$C$13,2,FALSE),0) -> 11 | AC19: =+Y19*AB19*R19 -> 0 | AD19: =+AC19-X19 -> 0 | AE19: =IFERROR(AD19/AC19,0) -> 0
S20: =+Q20*R20 -> 0 | T20: 0 | U20: =S20*(1-T20) -> 0 | V20: EUR | W20: =IFERROR(VLOOKUP(V20,Curr!$B$2:$C$13,2,FALSE),0) -> 11 | X20: =U20*W20 -> 0 | Y20: =Q20 -> 0 | Z20: =+Y20*R20 -> 0 | AA20: EUR | AB20: =IFERROR(VLOOKUP(AA20,Curr!$B$2:$C$13,2,FALSE),0) -> 11 | AC20: =+Y20*AB20*R20 -> 0 | AD20: =+AC20-X20 -> 0 | AE20: =IFERROR(AD20/AC20,0) -> 0
C21: Day 4 | D21: Drive | J21: Höfn: Drive to Myvatn - Driving time: 6.5hrs - 7.5hrs - Highlights: Djúpivogur coastal scenery, Eastfjords mountain passes & fjords, Dettifoss, Lake Mývatn area - Hidden Gems: Eggin í Gleðivík, Stuðlagil Canyon, Hverir | Q21: 0 | R21: 0 | S21: =+Q21*R21 -> 0 | T21: 0 | U21: =S21*(1-T21) -> 0 | V21: EUR | W21: =IFERROR(VLOOKUP(V21,Curr!$B$2:$C$13,2,FALSE),0) -> 11 | X21: =U21*W21 -> 0 | Y21: =Q21 -> 0 | Z21: =+Y21*R21 -> 0 | AA21: EUR | AB21: =IFERROR(VLOOKUP(AA21,Curr!$B$2:$C$13,2,FALSE),0) -> 11 | AC21: =+Y21*AB21*R21 -> 0 | AD21: =+AC21-X21 -> 0 | AE21: =IFERROR(AD21/AC21,0) -> 0
C22: Day 4 | D22: Hotel | J22: Myvatn: Check in to your accommodation for a 1 night stay - Cenrally located 3/4-star hotel - Standard room - breakfast included | Q22: 225 | R22: 1 | S22: =+Q22*R22 -> 225 | T22: 0 | U22: =S22*(1-T22) -> 225 | V22: EUR | W22: =IFERROR(VLOOKUP(V22,Curr!$B$2:$C$13,2,FALSE),0) -> 11 | X22: =U22*W22 -> 2475 | Y22: =Q22/0.8 -> 281.25 | Z22: =+Y22*R22 -> 281.25 | AA22: EUR | AB22: =IFERROR(VLOOKUP(AA22,Curr!$B$2:$C$13,2,FALSE),0) -> 11 | AC22: =+Y22*AB22*R22 -> 3093.75 | AD22: =+AC22-X22 -> 618.75 | AE22: =IFERROR(AD22/AC22,0) -> 0.2
C23: Day 4 | D23: Leisure | J23: Myvatn: Spend time at leisure | Q23: 0 | R23: 0 | S23: =+Q23*R23 -> 0 | T23: 0 | U23: =S23*(1-T23) -> 0 | V23: EUR | W23: =IFERROR(VLOOKUP(V23,Curr!$B$2:$C$13,2,FALSE),0) -> 11 | X23: =U23*W23 -> 0 | Y23: =Q23 -> 0 | Z23: =+Y23*R23 -> 0 | AA23: EUR | AB23: =IFERROR(VLOOKUP(AA23,Curr!$B$2:$C$13,2,FALSE),0) -> 11 | AC23: =+Y23*AB23*R23 -> 0 | AD23: =+AC23-X23 -> 0 | AE23: =IFERROR(AD23/AC23,0) -> 0
S24: =+Q24*R24 -> 0 | T24: 0 | U24: =S24*(1-T24) -> 0 | V24: EUR | W24: =IFERROR(VLOOKUP(V24,Curr!$B$2:$C$13,2,FALSE),0) -> 11 | X24: =U24*W24 -> 0 | Y24: =Q24 -> 0 | Z24: =+Y24*R24 -> 0 | AA24: EUR | AB24: =IFERROR(VLOOKUP(AA24,Curr!$B$2:$C$13,2,FALSE),0) -> 11 | AC24: =+Y24*AB24*R24 -> 0 | AD24: =+AC24-X24 -> 0 | AE24: =IFERROR(AD24/AC24,0) -> 0
C25: Day 5 | D25: Drive | J25: Myvatn: Drive to Borgarnes via the Diamond Circle - Driving time: 3.5hrs - 4.5hrs - Highlights: Dettifoss, Ásbyrgi, Húsavík, Goðafoss, Hraunfossar, Barnafoss - Hidden Gems: Grjótagjá, Hljóðaklettar, Quiet stretches along Skagafjörður farmland | Q25: 0 | R25: 0 | S25: =+Q25*R25 -> 0 | T25: 0 | U25: =S25*(1-T25) -> 0 | V25: EUR | W25: =IFERROR(VLOOKUP(V25,Curr!$B$2:$C$13,2,FALSE),0) -> 11 | X25: =U25*W25 -> 0 | Y25: =Q25 -> 0 | Z25: =+Y25*R25 -> 0 | AA25: EUR | AB25: =IFERROR(VLOOKUP(AA25,Curr!$B$2:$C$13,2,FALSE),0) -> 11 | AC25: =+Y25*AB25*R25 -> 0 | AD25: =+AC25-X25 -> 0 | AE25: =IFERROR(AD25/AC25,0) -> 0
C26: Day 5 | D26: Hotel | J26: Borgarnes: Check in to your accommodation for a 1 night stay - Cenrally located 3/4-star hotel - Standard room - breakfast included | Q26: 175 | R26: 1 | S26: =+Q26*R26 -> 175 | T26: 0 | U26: =S26*(1-T26) -> 175 | V26: EUR | W26: =IFERROR(VLOOKUP(V26,Curr!$B$2:$C$13,2,FALSE),0) -> 11 | X26: =U26*W26 -> 1925 | Y26: =Q26/0.8 -> 218.75 | Z26: =+Y26*R26 -> 218.75 | AA26: EUR | AB26: =IFERROR(VLOOKUP(AA26,Curr!$B$2:$C$13,2,FALSE),0) -> 11 | AC26: =+Y26*AB26*R26 -> 2406.25 | AD26: =+AC26-X26 -> 481.25 | AE26: =IFERROR(AD26/AC26,0) -> 0.2
C27: Day 5 | D27: Leisure | J27: Borgarnes: Spend time at leisure | Q27: 0 | R27: 0 | S27: =+Q27*R27 -> 0 | T27: 0 | U27: =S27*(1-T27) -> 0 | V27: EUR | W27: =IFERROR(VLOOKUP(V27,Curr!$B$2:$C$13,2,FALSE),0) -> 11 | X27: =U27*W27 -> 0 | Y27: =Q27 -> 0 | Z27: =+Y27*R27 -> 0 | AA27: EUR | AB27: =IFERROR(VLOOKUP(AA27,Curr!$B$2:$C$13,2,FALSE),0) -> 11 | AC27: =+Y27*AB27*R27 -> 0 | AD27: =+AC27-X27 -> 0 | AE27: =IFERROR(AD27/AC27,0) -> 0
S28: =+Q28*R28 -> 0 | T28: 0 | U28: =S28*(1-T28) -> 0 | V28: EUR | W28: =IFERROR(VLOOKUP(V28,Curr!$B$2:$C$13,2,FALSE),0) -> 11 | X28: =U28*W28 -> 0 | Y28: =Q28 -> 0 | Z28: =+Y28*R28 -> 0 | AA28: EUR | AB28: =IFERROR(VLOOKUP(AA28,Curr!$B$2:$C$13,2,FALSE),0) -> 11 | AC28: =+Y28*AB28*R28 -> 0 | AD28: =+AC28-X28 -> 0 | AE28: =IFERROR(AD28/AC28,0) -> 0
C29: Day 6 | D29: Drive | J29: Borgarnes: Drive to Keflavik Airport - Driving time: 1.5hrs - 2hrs - Highlights: Hvalfjörður coastal drive (Route 47), Mountain and fjord scenery in West Iceland, Reykjanes lava landscapes near Keflavík - Hidden Gems: Glymur (short hike), Quiet pull-offs along Hvalfjörður, Small geothermal areas on the Reykjanes Peninsula | Q29: 0 | R29: 0 | S29: =+Q29*R29 -> 0 | T29: 0 | U29: =S29*(1-T29) -> 0 | V29: EUR | W29: =IFERROR(VLOOKUP(V29,Curr!$B$2:$C$13,2,FALSE),0) -> 11 | X29: =U29*W29 -> 0 | Y29: =Q29 -> 0 | Z29: =+Y29*R29 -> 0 | AA29: EUR | AB29: =IFERROR(VLOOKUP(AA29,Curr!$B$2:$C$13,2,FALSE),0) -> 11 | AC29: =+Y29*AB29*R29 -> 0 | AD29: =+AC29-X29 -> 0 | AE29: =IFERROR(AD29/AC29,0) -> 0
C30: Day 6 | D30: Car | J30: Keflavik: Deliver your car at the car rental office | Q30: 0 | R30: 0 | S30: =+Q30*R30 -> 0 | T30: 0 | U30: =S30*(1-T30) -> 0 | V30: EUR | W30: =IFERROR(VLOOKUP(V30,Curr!$B$2:$C$13,2,FALSE),0) -> 11 | X30: =U30*W30 -> 0 | Y30: =Q30 -> 0 | Z30: =+Y30*R30 -> 0 | AA30: EUR | AB30: =IFERROR(VLOOKUP(AA30,Curr!$B$2:$C$13,2,FALSE),0) -> 11 | AC30: =+Y30*AB30*R30 -> 0 | AD30: =+AC30-X30 -> 0 | AE30: =IFERROR(AD30/AC30,0) -> 0
C31: Day 6 | D31: Departure | J31: Keflavik: Departure home | Q31: 0 | R31: 0 | S31: =+Q31*R31 -> 0 | T31: 0 | U31: =S31*(1-T31) -> 0 | V31: EUR | W31: =IFERROR(VLOOKUP(V31,Curr!$B$2:$C$13,2,FALSE),0) -> 11 | X31: =U31*W31 -> 0 | Y31: =Q31 -> 0 | Z31: =+Y31*R31 -> 0 | AA31: EUR | AB31: =IFERROR(VLOOKUP(AA31,Curr!$B$2:$C$13,2,FALSE),0) -> 11 | AC31: =+Y31*AB31*R31 -> 0 | AD31: =+AC31-X31 -> 0 | AE31: =IFERROR(AD31/AC31,0) -> 0
S32: =+Q32*R32 -> 0 | T32: 0 | U32: =S32*(1-T32) -> 0 | V32: EUR | W32: =IFERROR(VLOOKUP(V32,Curr!$B$2:$C$13,2,FALSE),0) -> 11 | X32: =U32*W32 -> 0 | Y32: =Q32 -> 0 | Z32: =+Y32*R32 -> 0 | AA32: EUR | AB32: =IFERROR(VLOOKUP(AA32,Curr!$B$2:$C$13,2,FALSE),0) -> 11 | AC32: =+Y32*AB32*R32 -> 0 | AD32: =+AC32-X32 -> 0 | AE32: =IFERROR(AD32/AC32,0) -> 0
S33: =+Q33*R33 -> 0 | T33: 0 | U33: =S33*(1-T33) -> 0 | V33: EUR | W33: =IFERROR(VLOOKUP(V33,Curr!$B$2:$C$13,2,FALSE),0) -> 11 | X33: =U33*W33 -> 0 | Y33: =Q33 -> 0 | Z33: =+Y33*R33 -> 0 | AA33: EUR | AB33: =IFERROR(VLOOKUP(AA33,Curr!$B$2:$C$13,2,FALSE),0) -> 11 | AC33: =+Y33*AB33*R33 -> 0 | AD33: =+AC33-X33 -> 0 | AE33: =IFERROR(AD33/AC33,0) -> 0
C34: Day 1 | D34: Activity Upgrade | J34: Reykjavík: City Walking Tour - Time: 2:00 pm - 5:00 pm - Meeting point: Hallgrímskirkja, Hallgrimstorgi 1 - Includes: Professional, English-speaking guide - Highlights: Hallgrímskirkja, All the major landmarks, Hidden street art & local corners, Iceland in a nutshell | P34: https://booknordics.com/iceland/western-iceland/reykjavik/reykjavik-walking-tour-small-group-citywalk | Q34: 37 | R34: 0 | S34: =+Q34*R34 -> 0 | T34: 0.2 | U34: =S34*(1-T34) -> 0 | V34: EUR | W34: =IFERROR(VLOOKUP(V34,Curr!$B$2:$C$13,2,FALSE),0) -> 11 | X34: =U34*W34 -> 0 | Y34: =Q34 -> 37 | Z34: =+Y34*R34 -> 0 | AA34: EUR | AB34: =IFERROR(VLOOKUP(AA34,Curr!$B$2:$C$13,2,FALSE),0) -> 11 | AC34: =+Y34*AB34*R34 -> 0 | AD34: =+AC34-X34 -> 0 | AE34: =IFERROR(AD34/AC34,0) -> 0
C35: Day 1 | D35: Activity Upgrade | J35: Reykjavík: Northern Lights Minibus Tour - Small Group - Time: 8:30 pm - 12:30 am - Meeting point: Hotel pick up - Includes: Pick-up/drop-off in central Reykjavik, Professional, English-speaking guide, Northern lights tour in a small group, Ticket to Aurora Museum Reykjavik, Free Wi-Fi onboard the vehicle, Hot chocolate and refreshments | P35: https://booknordics.com/iceland/western-iceland/reykjavik/northern-lights-small-group-minibus-tour | Q35: 89 | R35: 0 | S35: =+Q35*R35 -> 0 | T35: 0.25 | U35: =S35*(1-T35) -> 0 | V35: EUR | W35: =IFERROR(VLOOKUP(V35,Curr!$B$2:$C$13,2,FALSE),0) -> 11 | X35: =U35*W35 -> 0 | Y35: =Q35 -> 89 | Z35: =+Y35*R35 -> 0 | AA35: EUR | AB35: =IFERROR(VLOOKUP(AA35,Curr!$B$2:$C$13,2,FALSE),0) -> 11 | AC35: =+Y35*AB35*R35 -> 0 | AD35: =+AC35-X35 -> 0 | AE35: =IFERROR(AD35/AC35,0) -> 0
C36: Day 3 | D36: Activity Upgrade | J36: Vik: Katla Ice Cave Super Jeep Tour - Time: 09:30 am - 12:30 pm - Meeting point: Tröll Expeditions Katla Ice Cave - Includes: Super Jeep excursion to Katla Ice Cave, Certified glacier guide and glacier hike, Experienced off-road driver, Ice cave gear: crampons, and helmet | P36: https://booknordics.com/iceland/southern-iceland/vik/katla-ice-cave-super-jeep-from-vik | Q36: 205 | R36: 0 | S36: =+Q36*R36 -> 0 | T36: 0 | U36: =S36*(1-T36) -> 0 | V36: EUR | W36: =IFERROR(VLOOKUP(V36,Curr!$B$2:$C$13,2,FALSE),0) -> 11 | X36: =U36*W36 -> 0 | Y36: =Q36 -> 205 | Z36: =+Y36*R36 -> 0 | AA36: EUR | AB36: =IFERROR(VLOOKUP(AA36,Curr!$B$2:$C$13,2,FALSE),0) -> 11 | AC36: =+Y36*AB36*R36 -> 0 | AD36: =+AC36-X36 -> 0 | AE36: =IFERROR(AD36/AC36,0) -> 0
C37: Day 5 | D37: Activity Upgrade | J37: Akureyri: Whale Watching Tour - Time: 11:00 am - 1:30 pm - Meeting point: Oddeyrarbót 2, next to the cultural centre HOF in Akureyri - Includes: Whale watching tour approx. 2,5-3 hrs, Knowledgeable, English-speaking guides, Use of warm overalls and blankets, Warm indoor saloom and Free WiFi, Panoramic viewing windows | P37: https://booknordics.com/iceland/northern-iceland/akureyri/akureyri-classic-whale-watching | Q37: 99 | R37: 0 | S37: =+Q37*R37 -> 0 | T37: 0.25 | U37: =S37*(1-T37) -> 0 | V37: EUR | W37: =IFERROR(VLOOKUP(V37,Curr!$B$2:$C$13,2,FALSE),0) -> 11 | X37: =U37*W37 -> 0 | Y37: =Q37 -> 99 | Z37: =+Y37*R37 -> 0 | AA37: EUR | AB37: =IFERROR(VLOOKUP(AA37,Curr!$B$2:$C$13,2,FALSE),0) -> 11 | AC37: =+Y37*AB37*R37 -> 0 | AD37: =+AC37-X37 -> 0 | AE37: =IFERROR(AD37/AC37,0) -> 0
C38: Day 6 | D38: Activity Upgrade | J38: Reykjavik: Blue Lagoon Comfort Package - Time: 09:00 am - 1:00 pm - Meeting point: Hotel Pick up - Includes: Return transfer, Entrance to the Blue Lagoon, Silica mud mask at the Mask Bar, Use of towel, shampoo, conditioner, and moisturizer, Private locker, Non-alcoholic drink at the in-water bar | P38: https://booknordics.com/iceland/western-iceland/reykjavik/reykjavik-blue-lagoon-comfort-including-admission | Q38: 163 | R38: 0 | S38: =+Q38*R38 -> 0 | T38: 0.2 | U38: =S38*(1-T38) -> 0 | V38: EUR | W38: =IFERROR(VLOOKUP(V38,Curr!$B$2:$C$13,2,FALSE),0) -> 11 | X38: =U38*W38 -> 0 | Y38: =Q38 -> 163 | Z38: =+Y38*R38 -> 0 | AA38: EUR | AB38: =IFERROR(VLOOKUP(AA38,Curr!$B$2:$C$13,2,FALSE),0) -> 11 | AC38: =+Y38*AB38*R38 -> 0 | AD38: =+AC38-X38 -> 0 | AE38: =IFERROR(AD38/AC38,0) -> 0
S39: =+Q39*R39 -> 0 | T39: 0 | U39: =S39*(1-T39) -> 0 | V39: EUR | W39: =IFERROR(VLOOKUP(V39,Curr!$B$2:$C$13,2,FALSE),0) -> 11 | X39: =U39*W39 -> 0 | Y39: =Q39 -> 0 | Z39: =+Y39*R39 -> 0 | AA39: EUR | AB39: =IFERROR(VLOOKUP(AA39,Curr!$B$2:$C$13,2,FALSE),0) -> 11 | AC39: =+Y39*AB39*R39 -> 0 | AD39: =+AC39-X39 -> 0 | AE39: =IFERROR(AD39/AC39,0) -> 0
S40: =+Q40*R40 -> 0 | T40: 0 | U40: =S40*(1-T40) -> 0 | V40: EUR | W40: =IFERROR(VLOOKUP(V40,Curr!$B$2:$C$13,2,FALSE),0) -> 11 | X40: =U40*W40 -> 0 | Y40: =Q40 -> 0 | Z40: =+Y40*R40 -> 0 | AA40: EUR | AB40: =IFERROR(VLOOKUP(AA40,Curr!$B$2:$C$13,2,FALSE),0) -> 11 | AC40: =+Y40*AB40*R40 -> 0 | AD40: =+AC40-X40 -> 0 | AE40: =IFERROR(AD40/AC40,0) -> 0
C41: Day 1 | D41: Extra Hotel Night | J41: Reykjavik: Add on an extra night in Reykjavik | Q41: 225 | R41: 0 | S41: =+Q41*R41 -> 0 | T41: 0 | U41: =S41*(1-T41) -> 0 | V41: EUR | W41: =IFERROR(VLOOKUP(V41,Curr!$B$2:$C$13,2,FALSE),0) -> 11 | X41: =U41*W41 -> 0 | Y41: =Q41/0.85 -> 264.70588 | Z41: =+Y41*R41 -> 0 | AA41: EUR | AB41: =IFERROR(VLOOKUP(AA41,Curr!$B$2:$C$13,2,FALSE),0) -> 11 | AC41: =+Y41*AB41*R41 -> 0 | AD41: =+AC41-X41 -> 0 | AE41: =IFERROR(AD41/AC41,0) -> 0
C42: Day 6 | D42: Extra Hotel Night | J42: Reykjavik: Add on an extra night in Reykjavik | Q42: 225 | R42: 0 | S42: =+Q42*R42 -> 0 | T42: 0 | U42: =S42*(1-T42) -> 0 | V42: EUR | W42: =IFERROR(VLOOKUP(V42,Curr!$B$2:$C$13,2,FALSE),0) -> 11 | X42: =U42*W42 -> 0 | Y42: =Q42/0.85 -> 264.70588 | Z42: =+Y42*R42 -> 0 | AA42: EUR | AB42: =IFERROR(VLOOKUP(AA42,Curr!$B$2:$C$13,2,FALSE),0) -> 11 | AC42: =+Y42*AB42*R42 -> 0 | AD42: =+AC42-X42 -> 0 | AE42: =IFERROR(AD42/AC42,0) -> 0
S43: =+Q43*R43 -> 0 | T43: 0 | U43: =S43*(1-T43) -> 0 | V43: EUR | W43: =IFERROR(VLOOKUP(V43,Curr!$B$2:$C$13,2,FALSE),0) -> 11 | X43: =U43*W43 -> 0 | Y43: =Q43 -> 0 | Z43: =+Y43*R43 -> 0 | AA43: EUR | AB43: =IFERROR(VLOOKUP(AA43,Curr!$B$2:$C$13,2,FALSE),0) -> 11 | AC43: =+Y43*AB43*R43 -> 0 | AD43: =+AC43-X43 -> 0 | AE43: =IFERROR(AD43/AC43,0) -> 0
S44: =+Q44*R44 -> 0 | T44: 0 | U44: =S44*(1-T44) -> 0 | V44: EUR | W44: =IFERROR(VLOOKUP(V44,Curr!$B$2:$C$13,2,FALSE),0) -> 11 | X44: =U44*W44 -> 0 | Y44: =Q44 -> 0 | Z44: =+Y44*R44 -> 0 | AA44: EUR | AB44: =IFERROR(VLOOKUP(AA44,Curr!$B$2:$C$13,2,FALSE),0) -> 11 | AC44: =+Y44*AB44*R44 -> 0 | AD44: =+AC44-X44 -> 0 | AE44: =IFERROR(AD44/AC44,0) -> 0
S45: =+Q45*R45 -> 0 | T45: 0 | U45: =S45*(1-T45) -> 0 | V45: EUR | W45: =IFERROR(VLOOKUP(V45,Curr!$B$2:$C$13,2,FALSE),0) -> 11 | X45: =U45*W45 -> 0 | Y45: =Q45 -> 0 | Z45: =+Y45*R45 -> 0 | AA45: EUR | AB45: =IFERROR(VLOOKUP(AA45,Curr!$B$2:$C$13,2,FALSE),0) -> 11 | AC45: =+Y45*AB45*R45 -> 0 | AD45: =+AC45-X45 -> 0 | AE45: =IFERROR(AD45/AC45,0) -> 0
S46: =+Q46*R46 -> 0 | T46: 0 | U46: =S46*(1-T46) -> 0 | V46: EUR | W46: =IFERROR(VLOOKUP(V46,Curr!$B$2:$C$13,2,FALSE),0) -> 11 | X46: =U46*W46 -> 0 | Y46: =Q46 -> 0 | Z46: =+Y46*R46 -> 0 | AA46: EUR | AB46: =IFERROR(VLOOKUP(AA46,Curr!$B$2:$C$13,2,FALSE),0) -> 11 | AC46: =+Y46*AB46*R46 -> 0 | AD46: =+AC46-X46 -> 0 | AE46: =IFERROR(AD46/AC46,0) -> 0
S47: =+Q47*R47 -> 0 | T47: 0 | U47: =S47*(1-T47) -> 0 | V47: EUR | W47: =IFERROR(VLOOKUP(V47,Curr!$B$2:$C$13,2,FALSE),0) -> 11 | X47: =U47*W47 -> 0 | Y47: =Q47 -> 0 | Z47: =+Y47*R47 -> 0 | AA47: EUR | AB47: =IFERROR(VLOOKUP(AA47,Curr!$B$2:$C$13,2,FALSE),0) -> 11 | AC47: =+Y47*AB47*R47 -> 0 | AD47: =+AC47-X47 -> 0 | AE47: =IFERROR(AD47/AC47,0) -> 0
S48: =+Q48*R48 -> 0 | T48: 0 | U48: =S48*(1-T48) -> 0 | V48: EUR | W48: =IFERROR(VLOOKUP(V48,Curr!$B$2:$C$13,2,FALSE),0) -> 11 | X48: =U48*W48 -> 0 | Y48: =Q48 -> 0 | Z48: =+Y48*R48 -> 0 | AA48: EUR | AB48: =IFERROR(VLOOKUP(AA48,Curr!$B$2:$C$13,2,FALSE),0) -> 11 | AC48: =+Y48*AB48*R48 -> 0 | AD48: =+AC48-X48 -> 0 | AE48: =IFERROR(AD48/AC48,0) -> 0
S49: =+Q49*R49 -> 0 | T49: 0 | U49: =S49*(1-T49) -> 0 | V49: EUR | W49: =IFERROR(VLOOKUP(V49,Curr!$B$2:$C$13,2,FALSE),0) -> 11 | X49: =U49*W49 -> 0 | Y49: =Q49 -> 0 | Z49: =+Y49*R49 -> 0 | AA49: EUR | AB49: =IFERROR(VLOOKUP(AA49,Curr!$B$2:$C$13,2,FALSE),0) -> 11 | AC49: =+Y49*AB49*R49 -> 0 | AD49: =+AC49-X49 -> 0 | AE49: =IFERROR(AD49/AC49,0) -> 0
B51: Totals | D51: x | E51: x | F51: x | G51: x | H51: x | I51: x | J51: x | K51: x | L51: x | M51: x | N51: x | O51: x | P51: x | Q51: x | R51: x | S51: x | T51: x | U51: x | V51: x | W51: x | X51: x | Y51: x | Z51: =SUM(Z7:Z49) -> 1875 | AC51: =SUM(AC7:AC49) -> 20625 | AD51: =SUM(AD7:AD49) -> 4125 | AE51: =IFERROR(AD51/AC51,0) -> 0.2 | AF51: =SUM(AF8:AF50) -> 0 | AG51: =SUM(AG8:AG50) -> 0 | AH51: =SUM(AH8:AH50) -> 0 | AI51: =SUM(AI8:AI50) -> 0 | AJ51: =SUM(AJ8:AJ50) -> 0
Y53: Fixed | Z53: 0
Y54: Variable | Z54: =Z8+Z10+Z14+Z18+Z22+Z26 -> 1875
Y55: Total | Z55: 1880
Y56: PP | Z56: =Z55/2 -> 940
Y59: Shoulder | Z59: =Z55 -> 1880
Y60: High | Z60: =Z59*1.2 -> 2256
Y61: Peak | Z61: =Z59*1.4 -> 2632
Y62: Low | Z62: =Z59*0.7 -> 1316

Sheet 7D SD
B1: Season: All
B2: Places: Reykjavik 1N - Vik I Myrdal 1N - Hofn 1N - Egilsstadir 1N - Akureyri 1N - Reykjavik 1N
B3: Pax: 2
B4: Rooming: Double
B6: ID | C6: Day | D6: Type | E6: From date | F6: To date | G6: From time | H6: To time | I6: Supplier | J6: Travel element | K6: Manual booking? | L6: Status | M6: Comments | N6: Non-refundable | O6: Refundable | P6: URL | Q6: Gross P per unit | R6: Units | S6: Gross P | T6: Supp Comm | U6: Net P | V6: Supp curr | W6: X-rate | X6: Net P NOK | Y6: Sales P per unit | Z6: Price | AA6: Sales curr | AB6: X-rate | AC6: Sales P NOK tot | AD6: GP NOK | AE6: GP % | AF6: VAT25 | AG6: VAT15 | AH6: VAT12 | AI6: VAT0-D | AJ6: VAT0-I
C7: Day 1 | D7: Arrival | J7: Keflavik: Welcome to Iceland | Q7: 0 | R7: 0 | S7: =+Q7*R7 -> 0 | T7: 0 | U7: =S7*(1-T7) -> 0 | V7: EUR | W7: =IFERROR(VLOOKUP(V7,Curr!$B$2:$C$13,2,FALSE),0) -> 11 | X7: =U7*W7 -> 0 | Y7: =Q7 -> 0 | Z7: =+Y7*R7 -> 0 | AA7: EUR | AB7: =IFERROR(VLOOKUP(AA7,Curr!$B$2:$C$13,2,FALSE),0) -> 11 | AC7: =+Y7*AB7*R7 -> 0 | AD7: =+AC7-X7 -> 0 | AE7: =IFERROR(AD7/AC7,0) -> 0
C8: Day 1 | D8: Car | J8: Keflavik: Pick up your rental car at the car rental office - A 4x4 will with room for 4 luggages will be provided - Includes: Basic Insuarance - Excludes: Deposit | Q8: 550 | R8: 1 | S8: =+Q8*R8 -> 550 | T8: 0 | U8: =S8*(1-T8) -> 550 | V8: EUR | W8: =IFERROR(VLOOKUP(V8,Curr!$B$2:$C$13,2,FALSE),0) -> 11 | X8: =U8*W8 -> 6050 | Y8: =Q8/0.8 -> 687.5 | Z8: =+Y8*R8 -> 687.5 | AA8: EUR | AB8: =IFERROR(VLOOKUP(AA8,Curr!$B$2:$C$13,2,FALSE),0) -> 11 | AC8: =+Y8*AB8*R8 -> 7562.5 | AD8: =+AC8-X8 -> 1512.5 | AE8: =IFERROR(AD8/AC8,0) -> 0.2
C9: Day 1 | D9: Drive | J9: Keflavik: Drive to Reykjavik - Driving time: 45 min - 1 hr - Optional Stops: Reykjanes lava fields, Coastal views along Route 41, Faxaflói Bay viewpoints (weather permitting) - Hidden Gems: Small roadside lava formations, Quiet pull-offs with ocean views, Reykjanes Peninsula backroad detours (only if not rushing) | Q9: 0 | R9: 0 | S9: =+Q9*R9 -> 0 | T9: 0 | U9: =S9*(1-T9) -> 0 | V9: EUR | W9: =IFERROR(VLOOKUP(V9,Curr!$B$2:$C$13,2,FALSE),0) -> 11 | X9: =U9*W9 -> 0 | Y9: =Q9 -> 0 | Z9: =+Y9*R9 -> 0 | AA9: EUR | AB9: =IFERROR(VLOOKUP(AA9,Curr!$B$2:$C$13,2,FALSE),0) -> 11 | AC9: =+Y9*AB9*R9 -> 0 | AD9: =+AC9-X9 -> 0 | AE9: =IFERROR(AD9/AC9,0) -> 0
C10: Day 1 | D10: Hotel | J10: Reykjavik: Check in to your accommodation for a 1 night stay - Cenrally located 3/4-star hotel - Standard room - breakfast included | P10: https://www.ratehawk.com/?sid=5c11424c-1694-4e32-9a64-786852f88adb | Q10: 200 | R10: 1 | S10: =+Q10*R10 -> 200 | T10: 0 | U10: =S10*(1-T10) -> 200 | V10: EUR | W10: =IFERROR(VLOOKUP(V10,Curr!$B$2:$C$13,2,FALSE),0) -> 11 | X10: =U10*W10 -> 2200 | Y10: =Q10/0.8 -> 250 | Z10: =+Y10*R10 -> 250 | AA10: EUR | AB10: =IFERROR(VLOOKUP(AA10,Curr!$B$2:$C$13,2,FALSE),0) -> 11 | AC10: =+Y10*AB10*R10 -> 2750 | AD10: =+AC10-X10 -> 550 | AE10: =IFERROR(AD10/AC10,0) -> 0.2
C11: Day 1 | D11: Leisure | J11: Reykjavik: Spend time at leisure | Q11: 0 | R11: 0 | S11: =+Q11*R11 -> 0 | T11: 0 | U11: =S11*(1-T11) -> 0 | V11: EUR | W11: =IFERROR(VLOOKUP(V11,Curr!$B$2:$C$13,2,FALSE),0) -> 11 | X11: =U11*W11 -> 0 | Y11: =Q11 -> 0 | Z11: =+Y11*R11 -> 0 | AA11: EUR | AB11: =IFERROR(VLOOKUP(AA11,Curr!$B$2:$C$13,2,FALSE),0) -> 11 | AC11: =+Y11*AB11*R11 -> 0 | AD11: =+AC11-X11 -> 0 | AE11: =IFERROR(AD11/AC11,0) -> 0
S12: =+Q12*R12 -> 0 | T12: 0 | U12: =S12*(1-T12) -> 0 | V12: EUR | W12: =IFERROR(VLOOKUP(V12,Curr!$B$2:$C$13,2,FALSE),0) -> 11 | X12: =U12*W12 -> 0 | Y12: =Q12 -> 0 | Z12: =+Y12*R12 -> 0 | AA12: EUR | AB12: =IFERROR(VLOOKUP(AA12,Curr!$B$2:$C$13,2,FALSE),0) -> 11 | AC12: =+Y12*AB12*R12 -> 0 | AD12: =+AC12-X12 -> 0 | AE12: =IFERROR(AD12/AC12,0) -> 0
C13: Day 2 | D13: Drive | J13: Reykjavik: Drive to Vik I Myrdal via the Golden Circle - Driving time: 5.5hrs - 6.5hrs - Highlights: Þingvellir National Park, Geysir (Strokkur), Gullfoss, Seljalandsfoss, Skógafoss, Reynisfjara - Hidden Gems: Kerið, Gljúfrabúi, Dyrhólaey coastal viewpoints (weather permitting) | Q13: 0 | R13: 0 | S13: =+Q13*R13 -> 0 | T13: 0 | U13: =S13*(1-T13) -> 0 | V13: EUR | W13: =IFERROR(VLOOKUP(V13,Curr!$B$2:$C$13,2,FALSE),0) -> 11 | X13: =U13*W13 -> 0 | Y13: =Q13 -> 0 | Z13: =+Y13*R13 -> 0 | AA13: EUR | AB13: =IFERROR(VLOOKUP(AA13,Curr!$B$2:$C$13,2,FALSE),0) -> 11 | AC13: =+Y13*AB13*R13 -> 0 | AD13: =+AC13-X13 -> 0 | AE13: =IFERROR(AD13/AC13,0) -> 0
C14: Day 2 | D14: Hotel | J14: Vik i Myrdal: Check in to your accommodation for a 1 night stay - Cenrally located 3/4-star hotel - Standard room - breakfast included | Q14: 250 | R14: 1 | S14: =+Q14*R14 -> 250 | T14: 0 | U14: =S14*(1-T14) -> 250 | V14: EUR | W14: =IFERROR(VLOOKUP(V14,Curr!$B$2:$C$13,2,FALSE),0) -> 11 | X14: =U14*W14 -> 2750 | Y14: =Q14/0.8 -> 312.5 | Z14: =+Y14*R14 -> 312.5 | AA14: EUR | AB14: =IFERROR(VLOOKUP(AA14,Curr!$B$2:$C$13,2,FALSE),0) -> 11 | AC14: =+Y14*AB14*R14 -> 3437.5 | AD14: =+AC14-X14 -> 687.5 | AE14: =IFERROR(AD14/AC14,0) -> 0.2
C15: Day 2 | D15: Leisure | J15: Vik i Myrdal: Spend time at leisure | Q15: 0 | R15: 0 | S15: =+Q15*R15 -> 0 | T15: 0 | U15: =S15*(1-T15) -> 0 | V15: EUR | W15: =IFERROR(VLOOKUP(V15,Curr!$B$2:$C$13,2,FALSE),0) -> 11 | X15: =U15*W15 -> 0 | Y15: =Q15 -> 0 | Z15: =+Y15*R15 -> 0 | AA15: EUR | AB15: =IFERROR(VLOOKUP(AA15,Curr!$B$2:$C$13,2,FALSE),0) -> 11 | AC15: =+Y15*AB15*R15 -> 0 | AD15: =+AC15-X15 -> 0 | AE15: =IFERROR(AD15/AC15,0) -> 0
S16: =+Q16*R16 -> 0 | T16: 0 | U16: =S16*(1-T16) -> 0 | V16: EUR | W16: =IFERROR(VLOOKUP(V16,Curr!$B$2:$C$13,2,FALSE),0) -> 11 | X16: =U16*W16 -> 0 | Y16: =Q16 -> 0 | Z16: =+Y16*R16 -> 0 | AA16: EUR | AB16: =IFERROR(VLOOKUP(AA16,Curr!$B$2:$C$13,2,FALSE),0) -> 11 | AC16: =+Y16*AB16*R16 -> 0 | AD16: =+AC16-X16 -> 0 | AE16: =IFERROR(AD16/AC16,0) -> 0
C17: Day 3 | D17: Drive | J17: Vik i Myrdal: Drive to Höfn - Driving time: 4.5hrs - 5.5 hrs - Highlights: Fjaðrárgljúfur, Skaftafell, Svartifoss, Jökulsárlón, Diamond Beach - Hidden Gems: Moss-covered lava fields of Eldhraun, Svínafellsjökull, Quiet pull-offs along Skeiðarársandur outwash plain | Q17: 0 | R17: 0 | S17: =+Q17*R17 -> 0 | T17: 0 | U17: =S17*(1-T17) -> 0 | V17: EUR | W17: =IFERROR(VLOOKUP(V17,Curr!$B$2:$C$13,2,FALSE),0) -> 11 | X17: =U17*W17 -> 0 | Y17: =Q17 -> 0 | Z17: =+Y17*R17 -> 0 | AA17: EUR | AB17: =IFERROR(VLOOKUP(AA17,Curr!$B$2:$C$13,2,FALSE),0) -> 11 | AC17: =+Y17*AB17*R17 -> 0 | AD17: =+AC17-X17 -> 0 | AE17: =IFERROR(AD17/AC17,0) -> 0
C18: Day 3 | D18: Hotel | J18: Höfn: Check in to your accommodation for a 1 night stay - Cenrally located 3/4-star hotel - Standard room - breakfast included | Q18: 200 | R18: 1 | S18: =+Q18*R18 -> 200 | T18: 0 | U18: =S18*(1-T18) -> 200 | V18: EUR | W18: =IFERROR(VLOOKUP(V18,Curr!$B$2:$C$13,2,FALSE),0) -> 11 | X18: =U18*W18 -> 2200 | Y18: =Q18/0.8 -> 250 | Z18: =+Y18*R18 -> 250 | AA18: EUR | AB18: =IFERROR(VLOOKUP(AA18,Curr!$B$2:$C$13,2,FALSE),0) -> 11 | AC18: =+Y18*AB18*R18 -> 2750 | AD18: =+AC18-X18 -> 550 | AE18: =IFERROR(AD18/AC18,0) -> 0.2
C19: Day 3 | D19: Leisure | J19: Höfn: Spend time at leisure | Q19: 0 | R19: 0 | S19: =+Q19*R19 -> 0 | T19: 0 | U19: =S19*(1-T19) -> 0 | V19: EUR | W19: =IFERROR(VLOOKUP(V19,Curr!$B$2:$C$13,2,FALSE),0) -> 11 | X19: =U19*W19 -> 0 | Y19: =Q19 -> 0 | Z19: =+Y19*R19 -> 0 | AA19: EUR | AB19: =IFERROR(VLOOKUP(AA19,Curr!$B$2:$C$13,2,FALSE),0) -> 11 | AC19: =+Y19*AB19*R19 -> 0 | AD19: =+AC19-X19 -> 0 | AE19: =IFERROR(AD19/AC19,0) -> 0
S20: =+Q20*R20 -> 0 | T20: 0 | U20: =S20*(1-T20) -> 0 | V20: EUR | W20: =IFERROR(VLOOKUP(V20,Curr!$B$2:$C$13,2,FALSE),0) -> 11 | X20: =U20*W20 -> 0 | Y20: =Q20 -> 0 | Z20: =+Y20*R20 -> 0 | AA20: EUR | AB20: =IFERROR(VLOOKUP(AA20,Curr!$B$2:$C$13,2,FALSE),0) -> 11 | AC20: =+Y20*AB20*R20 -> 0 | AD20: =+AC20-X20 -> 0 | AE20: =IFERROR(AD20/AC20,0) -> 0
C21: Day 4 | D21: Drive | J21: Höfn: Drive to Egilsstaðir - Driving time: 3.5hrs - 4-5hrs - Highlights: Eastfjords coastal & mountain scenery, Djúpivogur, Fjord crossings and dramatic mountain passes, Lagarfljót - Hidden Gems: Eggin í Gleðivík, Remote Eastfjords viewpoints, Small roadside waterfalls along Route 1 | Q21: 0 | R21: 0 | S21: =+Q21*R21 -> 0 | T21: 0 | U21: =S21*(1-T21) -> 0 | V21: EUR | W21: =IFERROR(VLOOKUP(V21,Curr!$B$2:$C$13,2,FALSE),0) -> 11 | X21: =U21*W21 -> 0 | Y21: =Q21 -> 0 | Z21: =+Y21*R21 -> 0 | AA21: EUR | AB21: =IFERROR(VLOOKUP(AA21,Curr!$B$2:$C$13,2,FALSE),0) -> 11 | AC21: =+Y21*AB21*R21 -> 0 | AD21: =+AC21-X21 -> 0 | AE21: =IFERROR(AD21/AC21,0) -> 0
C22: Day 4 | D22: Hotel | J22: Egilsstaðir: Check in to your accommodation for a 1 night stay - Cenrally located 3/4-star hotel - Standard room - breakfast included | Q22: 250 | R22: 1 | S22: =+Q22*R22 -> 250 | T22: 0 | U22: =S22*(1-T22) -> 250 | V22: EUR | W22: =IFERROR(VLOOKUP(V22,Curr!$B$2:$C$13,2,FALSE),0) -> 11 | X22: =U22*W22 -> 2750 | Y22: =Q22/0.8 -> 312.5 | Z22: =+Y22*R22 -> 312.5 | AA22: EUR | AB22: =IFERROR(VLOOKUP(AA22,Curr!$B$2:$C$13,2,FALSE),0) -> 11 | AC22: =+Y22*AB22*R22 -> 3437.5 | AD22: =+AC22-X22 -> 687.5 | AE22: =IFERROR(AD22/AC22,0) -> 0.2
C23: Day 4 | D23: Leisure | J23: Egilsstaðir: Spend time at leisure | Q23: 0 | R23: 0 | S23: =+Q23*R23 -> 0 | T23: 0 | U23: =S23*(1-T23) -> 0 | V23: EUR | W23: =IFERROR(VLOOKUP(V23,Curr!$B$2:$C$13,2,FALSE),0) -> 11 | X23: =U23*W23 -> 0 | Y23: =Q23 -> 0 | Z23: =+Y23*R23 -> 0 | AA23: EUR | AB23: =IFERROR(VLOOKUP(AA23,Curr!$B$2:$C$13,2,FALSE),0) -> 11 | AC23: =+Y23*AB23*R23 -> 0 | AD23: =+AC23-X23 -> 0 | AE23: =IFERROR(AD23/AC23,0) -> 0
S24: =+Q24*R24 -> 0 | T24: 0 | U24: =S24*(1-T24) -> 0 | V24: EUR | W24: =IFERROR(VLOOKUP(V24,Curr!$B$2:$C$13,2,FALSE),0) -> 11 | X24: =U24*W24 -> 0 | Y24: =Q24 -> 0 | Z24: =+Y24*R24 -> 0 | AA24: EUR | AB24: =IFERROR(VLOOKUP(AA24,Curr!$B$2:$C$13,2,FALSE),0) -> 11 | AC24: =+Y24*AB24*R24 -> 0 | AD24: =+AC24-X24 -> 0 | AE24: =IFERROR(AD24/AC24,0) -> 0
C25: Day 5 | D25: Drive | J25: Egilsstaðir: Drive to Akureyri, via the Diamond Circle - Driving time: 4.5hrs - 5.5hrs - Highlights: Stuðlagil Canyon, Dettifoss, Ásbyrgi, Goðafoss - Hidden Gems: Hljóðaklettar, Jökulsárgljúfur canyon viewpoints, Quiet stretches near Lake Mývatn | Q25: 0 | R25: 0 | S25: =+Q25*R25 -> 0 | T25: 0 | U25: =S25*(1-T25) -> 0 | V25: EUR | W25: =IFERROR(VLOOKUP(V25,Curr!$B$2:$C$13,2,FALSE),0) -> 11 | X25: =U25*W25 -> 0 | Y25: =Q25 -> 0 | Z25: =+Y25*R25 -> 0 | AA25: EUR | AB25: =IFERROR(VLOOKUP(AA25,Curr!$B$2:$C$13,2,FALSE),0) -> 11 | AC25: =+Y25*AB25*R25 -> 0 | AD25: =+AC25-X25 -> 0 | AE25: =IFERROR(AD25/AC25,0) -> 0
C26: Day 5 | D26: Hotel | J26: Akureyri: Check in to your accommodation for a 1 night stay - Cenrally located 3/4-star hotel - Standard room - breakfast included | Q26: 200 | R26: 1 | S26: =+Q26*R26 -> 200 | T26: 0 | U26: =S26*(1-T26) -> 200 | V26: EUR | W26: =IFERROR(VLOOKUP(V26,Curr!$B$2:$C$13,2,FALSE),0) -> 11 | X26: =U26*W26 -> 2200 | Y26: =Q26/0.8 -> 250 | Z26: =+Y26*R26 -> 250 | AA26: EUR | AB26: =IFERROR(VLOOKUP(AA26,Curr!$B$2:$C$13,2,FALSE),0) -> 11 | AC26: =+Y26*AB26*R26 -> 2750 | AD26: =+AC26-X26 -> 550 | AE26: =IFERROR(AD26/AC26,0) -> 0.2
C27: Day 5 | D27: Leisure | J27: Akureyri: Spend time at leisure | Q27: 0 | R27: 0 | S27: =+Q27*R27 -> 0 | T27: 0 | U27: =S27*(1-T27) -> 0 | V27: EUR | W27: =IFERROR(VLOOKUP(V27,Curr!$B$2:$C$13,2,FALSE),0) -> 11 | X27: =U27*W27 -> 0 | Y27: =Q27 -> 0 | Z27: =+Y27*R27 -> 0 | AA27: EUR | AB27: =IFERROR(VLOOKUP(AA27,Curr!$B$2:$C$13,2,FALSE),0) -> 11 | AC27: =+Y27*AB27*R27 -> 0 | AD27: =+AC27-X27 -> 0 | AE27: =IFERROR(AD27/AC27,0) -> 0
S28: =+Q28*R28 -> 0 | T28: 0 | U28: =S28*(1-T28) -> 0 | V28: EUR | W28: =IFERROR(VLOOKUP(V28,Curr!$B$2:$C$13,2,FALSE),0) -> 11 | X28: =U28*W28 -> 0 | Y28: =Q28 -> 0 | Z28: =+Y28*R28 -> 0 | AA28: EUR | AB28: =IFERROR(VLOOKUP(AA28,Curr!$B$2:$C$13,2,FALSE),0) -> 11 | AC28: =+Y28*AB28*R28 -> 0 | AD28: =+AC28-X28 -> 0 | AE28: =IFERROR(AD28/AC28,0) -> 0
C29: Day 6 | D29: Drive | J29: Akureyri: Drive to Reykjavik - Driving time: 4.5hrs - 5.5hrs - Highlights: Goðafoss, Skagafjörður valley scenery, Borgarnes, Reykjavík arrival - Hidden Gems: Hraunfossar, Barnafoss, Hvalfjörður scenic coastal route (Route 47) | Q29: 0 | R29: 0 | S29: =+Q29*R29 -> 0 | T29: 0 | U29: =S29*(1-T29) -> 0 | V29: EUR | W29: =IFERROR(VLOOKUP(V29,Curr!$B$2:$C$13,2,FALSE),0) -> 11 | X29: =U29*W29 -> 0 | Y29: =Q29 -> 0 | Z29: =+Y29*R29 -> 0 | AA29: EUR | AB29: =IFERROR(VLOOKUP(AA29,Curr!$B$2:$C$13,2,FALSE),0) -> 11 | AC29: =+Y29*AB29*R29 -> 0 | AD29: =+AC29-X29 -> 0 | AE29: =IFERROR(AD29/AC29,0) -> 0
C30: Day 6 | D30: Hotel | J30: Reykjavik: Check in to your accommodation for a 1 night stay - Cenrally located 3/4-star hotel - Standard room - breakfast included | Q30: 200 | R30: 1 | S30: =+Q30*R30 -> 200 | T30: 0 | U30: =S30*(1-T30) -> 200 | V30: EUR | W30: =IFERROR(VLOOKUP(V30,Curr!$B$2:$C$13,2,FALSE),0) -> 11 | X30: =U30*W30 -> 2200 | Y30: =Q30/0.8 -> 250 | Z30: =+Y30*R30 -> 250 | AA30: EUR | AB30: =IFERROR(VLOOKUP(AA30,Curr!$B$2:$C$13,2,FALSE),0) -> 11 | AC30: =+Y30*AB30*R30 -> 2750 | AD30: =+AC30-X30 -> 550 | AE30: =IFERROR(AD30/AC30,0) -> 0.2
C31: Day 6 | D31: Leisure | J31: Reykjavik: Spend time at leisure | Q31: 0 | R31: 0 | S31: =+Q31*R31 -> 0 | T31: 0 | U31: =S31*(1-T31) -> 0 | V31: EUR | W31: =IFERROR(VLOOKUP(V31,Curr!$B$2:$C$13,2,FALSE),0) -> 11 | X31: =U31*W31 -> 0 | Y31: =Q31 -> 0 | Z31: =+Y31*R31 -> 0 | AA31: EUR | AB31: =IFERROR(VLOOKUP(AA31,Curr!$B$2:$C$13,2,FALSE),0) -> 11 | AC31: =+Y31*AB31*R31 -> 0 | AD31: =+AC31-X31 -> 0 | AE31: =IFERROR(AD31/AC31,0) -> 0
S32: =+Q32*R32 -> 0 | T32: 0 | U32: =S32*(1-T32) -> 0 | V32: EUR | W32: =IFERROR(VLOOKUP(V32,Curr!$B$2:$C$13,2,FALSE),0) -> 11 | X32: =U32*W32 -> 0 | Y32: =Q32 -> 0 | Z32: =+Y32*R32 -> 0 | AA32: EUR | AB32: =IFERROR(VLOOKUP(AA32,Curr!$B$2:$C$13,2,FALSE),0) -> 11 | AC32: =+Y32*AB32*R32 -> 0 | AD32: =+AC32-X32 -> 0 | AE32: =IFERROR(AD32/AC32,0) -> 0
C33: Day 7 | D33: Drive | J33: Reykjavik: Drive to Keflavik Airport - Driving time: 45min - 1hrs - Highlights: Reykjanes lava fields, Coastal views toward Faxaflói Bay - Hidden Gems: Small pull-offs with ocean views, Short detours on the Reykjanes Peninsula | Q33: 0 | R33: 0 | S33: =+Q33*R33 -> 0 | T33: 0 | U33: =S33*(1-T33) -> 0 | V33: EUR | W33: =IFERROR(VLOOKUP(V33,Curr!$B$2:$C$13,2,FALSE),0) -> 11 | X33: =U33*W33 -> 0 | Y33: =Q33 -> 0 | Z33: =+Y33*R33 -> 0 | AA33: EUR | AB33: =IFERROR(VLOOKUP(AA33,Curr!$B$2:$C$13,2,FALSE),0) -> 11 | AC33: =+Y33*AB33*R33 -> 0 | AD33: =+AC33-X33 -> 0 | AE33: =IFERROR(AD33/AC33,0) -> 0
C34: Day 7 | D34: Car | J34: Keflavik: Deliver your car at the car rental office | Q34: 0 | R34: 0 | S34: =+Q34*R34 -> 0 | T34: 0 | U34: =S34*(1-T34) -> 0 | V34: EUR | W34: =IFERROR(VLOOKUP(V34,Curr!$B$2:$C$13,2,FALSE),0) -> 11 | X34: =U34*W34 -> 0 | Y34: =Q34 -> 0 | Z34: =+Y34*R34 -> 0 | AA34: EUR | AB34: =IFERROR(VLOOKUP(AA34,Curr!$B$2:$C$13,2,FALSE),0) -> 11 | AC34: =+Y34*AB34*R34 -> 0 | AD34: =+AC34-X34 -> 0 | AE34: =IFERROR(AD34/AC34,0) -> 0
C35: Day 7 | D35: Departure | J35: Keflavik: Departure home | Q35: 0 | R35: 0 | S35: =+Q35*R35 -> 0 | T35: 0 | U35: =S35*(1-T35) -> 0 | V35: EUR | W35: =IFERROR(VLOOKUP(V35,Curr!$B$2:$C$13,2,FALSE),0) -> 11 | X35: =U35*W35 -> 0 | Y35: =Q35 -> 0 | Z35: =+Y35*R35 -> 0 | AA35: EUR | AB35: =IFERROR(VLOOKUP(AA35,Curr!$B$2:$C$13,2,FALSE),0) -> 11 | AC35: =+Y35*AB35*R35 -> 0 | AD35: =+AC35-X35 -> 0 | AE35: =IFERROR(AD35/AC35,0) -> 0
S36: =+Q36*R36 -> 0 | T36: 0 | U36: =S36*(1-T36) -> 0 | V36: EUR | W36: =IFERROR(VLOOKUP(V36,Curr!$B$2:$C$13,2,FALSE),0) -> 11 | X36: =U36*W36 -> 0 | Y36: =Q36 -> 0 | Z36: =+Y36*R36 -> 0 | AA36: EUR | AB36: =IFERROR(VLOOKUP(AA36,Curr!$B$2:$C$13,2,FALSE),0) -> 11 | AC36: =+Y36*AB36*R36 -> 0 | AD36: =+AC36-X36 -> 0 | AE36: =IFERROR(AD36/AC36,0) -> 0
S37: =+Q37*R37 -> 0 | T37: 0 | U37: =S37*(1-T37) -> 0 | V37: EUR | W37: =IFERROR(VLOOKUP(V37,Curr!$B$2:$C$13,2,FALSE),0) -> 11 | X37: =U37*W37 -> 0 | Y37: =Q37 -> 0 | Z37: =+Y37*R37 -> 0 | AA37: EUR | AB37: =IFERROR(VLOOKUP(AA37,Curr!$B$2:$C$13,2,FALSE),0) -> 11 | AC37: =+Y37*AB37*R37 -> 0 | AD37: =+AC37-X37 -> 0 | AE37: =IFERROR(AD37/AC37,0) -> 0
C38: Day 1 | D38: Activity Upgrade | J38: Reykjavík: City Walking Tour - Time: 2:00 pm - 5:00 pm - Meeting point: Hallgrímskirkja, Hallgrimstorgi 1 - Includes: Professional, English-speaking guide - Highlights: Hallgrímskirkja, All the major landmarks, Hidden street art & local corners, Iceland in a nutshell | P38: https://booknordics.com/iceland/western-iceland/reykjavik/reykjavik-walking-tour-small-group-citywalk | Q38: 37 | R38: 0 | S38: =+Q38*R38 -> 0 | T38: 0.2 | U38: =S38*(1-T38) -> 0 | V38: EUR | W38: =IFERROR(VLOOKUP(V38,Curr!$B$2:$C$13,2,FALSE),0) -> 11 | X38: =U38*W38 -> 0 | Y38: =Q38 -> 37 | Z38: =+Y38*R38 -> 0 | AA38: EUR | AB38: =IFERROR(VLOOKUP(AA38,Curr!$B$2:$C$13,2,FALSE),0) -> 11 | AC38: =+Y38*AB38*R38 -> 0 | AD38: =+AC38-X38 -> 0 | AE38: =IFERROR(AD38/AC38,0) -> 0
C39: Day 1 | D39: Activity Upgrade | J39: Reykjavík: Northern Lights Minibus Tour - Small Group - Time: 8:30 pm - 12:30 am - Meeting point: Hotel pick up - Includes: Pick-up/drop-off in central Reykjavik, Professional, English-speaking guide, Northern lights tour in a small group, Ticket to Aurora Museum Reykjavik, Free Wi-Fi onboard the vehicle, Hot chocolate and refreshments | P39: https://booknordics.com/iceland/western-iceland/reykjavik/northern-lights-small-group-minibus-tour | Q39: 89 | R39: 0 | S39: =+Q39*R39 -> 0 | T39: 0.25 | U39: =S39*(1-T39) -> 0 | V39: EUR | W39: =IFERROR(VLOOKUP(V39,Curr!$B$2:$C$13,2,FALSE),0) -> 11 | X39: =U39*W39 -> 0 | Y39: =Q39 -> 89 | Z39: =+Y39*R39 -> 0 | AA39: EUR | AB39: =IFERROR(VLOOKUP(AA39,Curr!$B$2:$C$13,2,FALSE),0) -> 11 | AC39: =+Y39*AB39*R39 -> 0 | AD39: =+AC39-X39 -> 0 | AE39: =IFERROR(AD39/AC39,0) -> 0
C40: Day 3 | D40: Activity Upgrade | J40: Vik: Katla Ice Cave Super Jeep Tour - Time: 09:30 am - 12:30 pm - Meeting point: Tröll Expeditions Katla Ice Cave - Includes: Super Jeep excursion to Katla Ice Cave, Certified glacier guide and glacier hike, Experienced off-road driver, Ice cave gear: crampons, and helmet | P40: https://booknordics.com/iceland/southern-iceland/vik/katla-ice-cave-super-jeep-from-vik | Q40: 205 | R40: 0 | S40: =+Q40*R40 -> 0 | T40: 0 | U40: =S40*(1-T40) -> 0 | V40: EUR | W40: =IFERROR(VLOOKUP(V40,Curr!$B$2:$C$13,2,FALSE),0) -> 11 | X40: =U40*W40 -> 0 | Y40: =Q40 -> 205 | Z40: =+Y40*R40 -> 0 | AA40: EUR | AB40: =IFERROR(VLOOKUP(AA40,Curr!$B$2:$C$13,2,FALSE),0) -> 11 | AC40: =+Y40*AB40*R40 -> 0 | AD40: =+AC40-X40 -> 0 | AE40: =IFERROR(AD40/AC40,0) -> 0
C41: Day 6 | D41: Activity Upgrade | J41: Akureyri: Whale Watching Tour - Time: 11:00 am - 1:30 pm - Meeting point: Oddeyrarbót 2, next to the cultural centre HOF in Akureyri - Includes: Whale watching tour approx. 2,5-3 hrs, Knowledgeable, English-speaking guides, Use of warm overalls and blankets, Warm indoor saloom and Free WiFi, Panoramic viewing windows | P41: https://booknordics.com/iceland/northern-iceland/akureyri/akureyri-classic-whale-watching | Q41: 99 | R41: 0 | S41: =+Q41*R41 -> 0 | T41: 0.25 | U41: =S41*(1-T41) -> 0 | V41: EUR | W41: =IFERROR(VLOOKUP(V41,Curr!$B$2:$C$13,2,FALSE),0) -> 11 | X41: =U41*W41 -> 0 | Y41: =Q41 -> 99 | Z41: =+Y41*R41 -> 0 | AA41: EUR | AB41: =IFERROR(VLOOKUP(AA41,Curr!$B$2:$C$13,2,FALSE),0) -> 11 | AC41: =+Y41*AB41*R41 -> 0 | AD41: =+AC41-X41 -> 0 | AE41: =IFERROR(AD41/AC41,0) -> 0
C42: Day 7 | D42: Activity Upgrade | J42: Reykjavik: Blue Lagoon Comfort Package - Time: 09:00 am - 1:00 pm - Meeting point: Hotel Pick up - Includes: Return transfer, Entrance to the Blue Lagoon, Silica mud mask at the Mask Bar, Use of towel, shampoo, conditioner, and moisturizer, Private locker, Non-alcoholic drink at the in-water bar | P42: https://booknordics.com/iceland/western-iceland/reykjavik/reykjavik-blue-lagoon-comfort-including-admission | Q42: 163 | R42: 0 | S42: =+Q42*R42 -> 0 | T42: 0.2 | U42: =S42*(1-T42) -> 0 | V42: EUR | W42: =IFERROR(VLOOKUP(V42,Curr!$B$2:$C$13,2,FALSE),0) -> 11 | X42: =U42*W42 -> 0 | Y42: =Q42 -> 163 | Z42: =+Y42*R42 -> 0 | AA42: EUR | AB42: =IFERROR(VLOOKUP(AA42,Curr!$B$2:$C$13,2,FALSE),0) -> 11 | AC42: =+Y42*AB42*R42 -> 0 | AD42: =+AC42-X42 -> 0 | AE42: =IFERROR(AD42/AC42,0) -> 0
S43: =+Q43*R43 -> 0 | T43: 0 | U43: =S43*(1-T43) -> 0 | V43: EUR | W43: =IFERROR(VLOOKUP(V43,Curr!$B$2:$C$13,2,FALSE),0) -> 11 | X43: =U43*W43 -> 0 | Y43: =Q43 -> 0 | Z43: =+Y43*R43 -> 0 | AA43: EUR | AB43: =IFERROR(VLOOKUP(AA43,Curr!$B$2:$C$13,2,FALSE),0) -> 11 | AC43: =+Y43*AB43*R43 -> 0 | AD43: =+AC43-X43 -> 0 | AE43: =IFERROR(AD43/AC43,0) -> 0
S44: =+Q44*R44 -> 0 | T44: 0 | U44: =S44*(1-T44) -> 0 | V44: EUR | W44: =IFERROR(VLOOKUP(V44,Curr!$B$2:$C$13,2,FALSE),0) -> 11 | X44: =U44*W44 -> 0 | Y44: =Q44 -> 0 | Z44: =+Y44*R44 -> 0 | AA44: EUR | AB44: =IFERROR(VLOOKUP(AA44,Curr!$B$2:$C$13,2,FALSE),0) -> 11 | AC44: =+Y44*AB44*R44 -> 0 | AD44: =+AC44-X44 -> 0 | AE44: =IFERROR(AD44/AC44,0) -> 0
C45: Day 1 | D45: Extra Hotel Night | J45: Reykjavik: Add on an extra night in Reykjavik | Q45: 225 | R45: 0 | S45: =+Q45*R45 -> 0 | T45: 0 | U45: =S45*(1-T45) -> 0 | V45: EUR | W45: =IFERROR(VLOOKUP(V45,Curr!$B$2:$C$13,2,FALSE),0) -> 11 | X45: =U45*W45 -> 0 | Y45: =Q45/0.85 -> 264.70588 | Z45: =+Y45*R45 -> 0 | AA45: EUR | AB45: =IFERROR(VLOOKUP(AA45,Curr!$B$2:$C$13,2,FALSE),0) -> 11 | AC45: =+Y45*AB45*R45 -> 0 | AD45: =+AC45-X45 -> 0 | AE45: =IFERROR(AD45/AC45,0) -> 0
C46: Day 7 | D46: Extra Hotel Night | J46: Reykjavik: Add on an extra night in Reykjavik | Q46: 225 | R46: 0 | S46: =+Q46*R46 -> 0 | T46: 0 | U46: =S46*(1-T46) -> 0 | V46: EUR | W46: =IFERROR(VLOOKUP(V46,Curr!$B$2:$C$13,2,FALSE),0) -> 11 | X46: =U46*W46 -> 0 | Y46: =Q46/0.85 -> 264.70588 | Z46: =+Y46*R46 -> 0 | AA46: EUR | AB46: =IFERROR(VLOOKUP(AA46,Curr!$B$2:$C$13,2,FALSE),0) -> 11 | AC46: =+Y46*AB46*R46 -> 0 | AD46: =+AC46-X46 -> 0 | AE46: =IFERROR(AD46/AC46,0) -> 0
S47: =+Q47*R47 -> 0 | T47: 0 | U47: =S47*(1-T47) -> 0 | V47: EUR | W47: =IFERROR(VLOOKUP(V47,Curr!$B$2:$C$13,2,FALSE),0) -> 11 | X47: =U47*W47 -> 0 | Y47: =Q47 -> 0 | Z47: =+Y47*R47 -> 0 | AA47: EUR | AB47: =IFERROR(VLOOKUP(AA47,Curr!$B$2:$C$13,2,FALSE),0) -> 11 | AC47: =+Y47*AB47*R47 -> 0 | AD47: =+AC47-X47 -> 0 | AE47: =IFERROR(AD47/AC47,0) -> 0
S48: =+Q48*R48 -> 0 | T48: 0 | U48: =S48*(1-T48) -> 0 | V48: EUR | W48: =IFERROR(VLOOKUP(V48,Curr!$B$2:$C$13,2,FALSE),0) -> 11 | X48: =U48*W48 -> 0 | Y48: =Q48 -> 0 | Z48: =+Y48*R48 -> 0 | AA48: EUR | AB48: =IFERROR(VLOOKUP(AA48,Curr!$B$2:$C$13,2,FALSE),0) -> 11 | AC48: =+Y48*AB48*R48 -> 0 | AD48: =+AC48-X48 -> 0 | AE48: =IFERROR(AD48/AC48,0) -> 0
S49: =+Q49*R49 -> 0 | T49: 0 | U49: =S49*(1-T49) -> 0 | V49: EUR | W49: =IFERROR(VLOOKUP(V49,Curr!$B$2:$C$13,2,FALSE),0) -> 11 | X49: =U49*W49 -> 0 | Y49: =Q49 -> 0 | Z49: =+Y49*R49 -> 0 | AA49: EUR | AB49: =IFERROR(VLOOKUP(AA49,Curr!$B$2:$C$13,2,FALSE),0) -> 11 | AC49: =+Y49*AB49*R49 -> 0 | AD49: =+AC49-X49 -> 0 | AE49: =IFERROR(AD49/AC49,0) -> 0
B51: Totals | D51: x | E51: x | F51: x | G51: x | H51: x | I51: x | J51: x | K51: x | L51: x | M51: x | N51: x | O51: x | P51: x | Q51: x | R51: x | S51: x | T51: x | U51: x | V51: x | W51: x | X51: x | Y51: x | Z51: =SUM(Z7:Z49) -> 2312.5 | AC51: =SUM(AC7:AC49) -> 25437.5 | AD51: =SUM(AD7:AD49) -> 5087.5 | AE51: =IFERROR(AD51/AC51,0) -> 0.2 | AF51: =SUM(AF8:AF50) -> 0 | AG51: =SUM(AG8:AG50) -> 0 | AH51: =SUM(AH8:AH50) -> 0 | AI51: =SUM(AI8:AI50) -> 0 | AJ51: =SUM(AJ8:AJ50) -> 0
Y53: Fixed | Z53: 0
Y54: Variable | Z54: =Z8+Z10+Z14+Z18+Z22+Z26+Z30 -> 2312.5
Y55: Total | Z55: 2320
Y56: PP | Z56: =Z55/2 -> 1160
Y59: Shoulder | Z59: =Z55 -> 2320
Y60: High | Z60: =Z59*1.2 -> 2784
Y61: Peak | Z61: =Z59*1.4 -> 3248
Y62: Low | Z62: =Z59*0.7 -> 1624

Sheet 8D SD
B1: Season: All
B2: Places: Reykjavik 1N - Vik I Myrdal 1N - Hofn 1N - Egilsstadir 1N - Akureyri 1N - Snæfellsnes Pininsula 1N - Reykjavik 1N
B3: Pax: 2
B4: Rooming: Double
B6: ID | C6: Day | D6: Type | E6: From date | F6: To date | G6: From time | H6: To time | I6: Supplier | J6: Travel element | K6: Manual booking? | L6: Status | M6: Comments | N6: Non-refundable | O6: Refundable | P6: URL | Q6: Gross P per unit | R6: Units | S6: Gross P | T6: Supp Comm | U6: Net P | V6: Supp curr | W6: X-rate | X6: Net P NOK | Y6: Sales P per unit | Z6: Price | AA6: Sales curr | AB6: X-rate | AC6: Sales P NOK tot | AD6: GP NOK | AE6: GP % | AF6: VAT25 | AG6: VAT15 | AH6: VAT12 | AI6: VAT0-D | AJ6: VAT0-I
C7: Day 1 | D7: Arrival | J7: Keflavik: Welcome to Iceland | Q7: 0 | R7: 0 | S7: =+Q7*R7 -> 0 | T7: 0 | U7: =S7*(1-T7) -> 0 | V7: EUR | W7: =IFERROR(VLOOKUP(V7,Curr!$B$2:$C$13,2,FALSE),0) -> 11 | X7: =U7*W7 -> 0 | Y7: =Q7 -> 0 | Z7: =+Y7*R7 -> 0 | AA7: EUR | AB7: =IFERROR(VLOOKUP(AA7,Curr!$B$2:$C$13,2,FALSE),0) -> 11 | AC7: =+Y7*AB7*R7 -> 0 | AD7: =+AC7-X7 -> 0 | AE7: =IFERROR(AD7/AC7,0) -> 0
C8: Day 1 | D8: Car | J8: Keflavik: Pick up your rental car at the car rental office - A 4x4 will with room for 4 luggages will be provided | Q8: 650 | R8: 1 | S8: =+Q8*R8 -> 650 | T8: 0 | U8: =S8*(1-T8) -> 650 | V8: EUR | W8: =IFERROR(VLOOKUP(V8,Curr!$B$2:$C$13,2,FALSE),0) -> 11 | X8: =U8*W8 -> 7150 | Y8: =Q8/0.8 -> 812.5 | Z8: =+Y8*R8 -> 812.5 | AA8: EUR | AB8: =IFERROR(VLOOKUP(AA8,Curr!$B$2:$C$13,2,FALSE),0) -> 11 | AC8: =+Y8*AB8*R8 -> 8937.5 | AD8: =+AC8-X8 -> 1787.5 | AE8: =IFERROR(AD8/AC8,0) -> 0.2
C9: Day 1 | D9: Drive | J9: Keflavik: Drive to Reykjavik - Driving time: 45 min - 1 hr - Optional Stops: Reykjanes lava fields, Coastal views along Route 41, Faxaflói Bay viewpoints (weather permitting) - Hidden Gems: Small roadside lava formations, Quiet pull-offs with ocean views, Reykjanes Peninsula backroad detours (only if not rushing) | Q9: 0 | R9: 0 | S9: =+Q9*R9 -> 0 | T9: 0 | U9: =S9*(1-T9) -> 0 | V9: EUR | W9: =IFERROR(VLOOKUP(V9,Curr!$B$2:$C$13,2,FALSE),0) -> 11 | X9: =U9*W9 -> 0 | Y9: =Q9 -> 0 | Z9: =+Y9*R9 -> 0 | AA9: EUR | AB9: =IFERROR(VLOOKUP(AA9,Curr!$B$2:$C$13,2,FALSE),0) -> 11 | AC9: =+Y9*AB9*R9 -> 0 | AD9: =+AC9-X9 -> 0 | AE9: =IFERROR(AD9/AC9,0) -> 0
C10: Day 1 | D10: Hotel | J10: Reykjavik: Check in to your accommodation for a 1 night stay - Cenrally located 3/4-star hotel - Standard room - breakfast included | P10: https://www.ratehawk.com/?sid=5c11424c-1694-4e32-9a64-786852f88adb | Q10: 200 | R10: 1 | S10: =+Q10*R10 -> 200 | T10: 0 | U10: =S10*(1-T10) -> 200 | V10: EUR | W10: =IFERROR(VLOOKUP(V10,Curr!$B$2:$C$13,2,FALSE),0) -> 11 | X10: =U10*W10 -> 2200 | Y10: =Q10/0.8 -> 250 | Z10: =+Y10*R10 -> 250 | AA10: EUR | AB10: =IFERROR(VLOOKUP(AA10,Curr!$B$2:$C$13,2,FALSE),0) -> 11 | AC10: =+Y10*AB10*R10 -> 2750 | AD10: =+AC10-X10 -> 550 | AE10: =IFERROR(AD10/AC10,0) -> 0.2
C11: Day 1 | D11: Leisure | J11: Reykjavik: Spend time at leisure | Q11: 0 | R11: 0 | S11: =+Q11*R11 -> 0 | T11: 0 | U11: =S11*(1-T11) -> 0 | V11: EUR | W11: =IFERROR(VLOOKUP(V11,Curr!$B$2:$C$13,2,FALSE),0) -> 11 | X11: =U11*W11 -> 0 | Y11: =Q11 -> 0 | Z11: =+Y11*R11 -> 0 | AA11: EUR | AB11: =IFERROR(VLOOKUP(AA11,Curr!$B$2:$C$13,2,FALSE),0) -> 11 | AC11: =+Y11*AB11*R11 -> 0 | AD11: =+AC11-X11 -> 0 | AE11: =IFERROR(AD11/AC11,0) -> 0
S12: =+Q12*R12 -> 0 | T12: 0 | U12: =S12*(1-T12) -> 0 | V12: EUR | W12: =IFERROR(VLOOKUP(V12,Curr!$B$2:$C$13,2,FALSE),0) -> 11 | X12: =U12*W12 -> 0 | Y12: =Q12 -> 0 | Z12: =+Y12*R12 -> 0 | AA12: EUR | AB12: =IFERROR(VLOOKUP(AA12,Curr!$B$2:$C$13,2,FALSE),0) -> 11 | AC12: =+Y12*AB12*R12 -> 0 | AD12: =+AC12-X12 -> 0 | AE12: =IFERROR(AD12/AC12,0) -> 0
C13: Day 2 | D13: Drive | J13: Reykjavik: Drive to Vik I Myrdal via the Golden Circle - Driving time: 5.5hrs - 6.5hrs - Highlights: Þingvellir National Park, Geysir (Strokkur), Gullfoss, Seljalandsfoss, Skógafoss, Reynisfjara - Hidden Gems: Kerið, Gljúfrabúi, Dyrhólaey coastal viewpoints (weather permitting) | Q13: 0 | R13: 0 | S13: =+Q13*R13 -> 0 | T13: 0 | U13: =S13*(1-T13) -> 0 | V13: EUR | W13: =IFERROR(VLOOKUP(V13,Curr!$B$2:$C$13,2,FALSE),0) -> 11 | X13: =U13*W13 -> 0 | Y13: =Q13 -> 0 | Z13: =+Y13*R13 -> 0 | AA13: EUR | AB13: =IFERROR(VLOOKUP(AA13,Curr!$B$2:$C$13,2,FALSE),0) -> 11 | AC13: =+Y13*AB13*R13 -> 0 | AD13: =+AC13-X13 -> 0 | AE13: =IFERROR(AD13/AC13,0) -> 0
C14: Day 2 | D14: Hotel | J14: Vik i Myrdal: Check in to your accommodation for a 1 night stay - Cenrally located 3/4-star hotel - Standard room - breakfast included | Q14: 250 | R14: 1 | S14: =+Q14*R14 -> 250 | T14: 0 | U14: =S14*(1-T14) -> 250 | V14: EUR | W14: =IFERROR(VLOOKUP(V14,Curr!$B$2:$C$13,2,FALSE),0) -> 11 | X14: =U14*W14 -> 2750 | Y14: =Q14/0.8 -> 312.5 | Z14: =+Y14*R14 -> 312.5 | AA14: EUR | AB14: =IFERROR(VLOOKUP(AA14,Curr!$B$2:$C$13,2,FALSE),0) -> 11 | AC14: =+Y14*AB14*R14 -> 3437.5 | AD14: =+AC14-X14 -> 687.5 | AE14: =IFERROR(AD14/AC14,0) -> 0.2
C15: Day 2 | D15: Leisure | J15: Vik i Myrdal: Spend time at leisure | Q15: 0 | R15: 0 | S15: =+Q15*R15 -> 0 | T15: 0 | U15: =S15*(1-T15) -> 0 | V15: EUR | W15: =IFERROR(VLOOKUP(V15,Curr!$B$2:$C$13,2,FALSE),0) -> 11 | X15: =U15*W15 -> 0 | Y15: =Q15 -> 0 | Z15: =+Y15*R15 -> 0 | AA15: EUR | AB15: =IFERROR(VLOOKUP(AA15,Curr!$B$2:$C$13,2,FALSE),0) -> 11 | AC15: =+Y15*AB15*R15 -> 0 | AD15: =+AC15-X15 -> 0 | AE15: =IFERROR(AD15/AC15,0) -> 0
S16: =+Q16*R16 -> 0 | T16: 0 | U16: =S16*(1-T16) -> 0 | V16: EUR | W16: =IFERROR(VLOOKUP(V16,Curr!$B$2:$C$13,2,FALSE),0) -> 11 | X16: =U16*W16 -> 0 | Y16: =Q16 -> 0 | Z16: =+Y16*R16 -> 0 | AA16: EUR | AB16: =IFERROR(VLOOKUP(AA16,Curr!$B$2:$C$13,2,FALSE),0) -> 11 | AC16: =+Y16*AB16*R16 -> 0 | AD16: =+AC16-X16 -> 0 | AE16: =IFERROR(AD16/AC16,0) -> 0
C17: Day 3 | D17: Drive | J17: Vik i Myrdal: Drive to Höfn - Driving time: 4.5hrs - 5.5 hrs - Highlights: Fjaðrárgljúfur, Skaftafell, Svartifoss, Jökulsárlón, Diamond Beach - Hidden Gems: Moss-covered lava fields of Eldhraun, Svínafellsjökull, Quiet pull-offs along Skeiðarársandur outwash plain | Q17: 0 | R17: 0 | S17: =+Q17*R17 -> 0 | T17: 0 | U17: =S17*(1-T17) -> 0 | V17: EUR | W17: =IFERROR(VLOOKUP(V17,Curr!$B$2:$C$13,2,FALSE),0) -> 11 | X17: =U17*W17 -> 0 | Y17: =Q17 -> 0 | Z17: =+Y17*R17 -> 0 | AA17: EUR | AB17: =IFERROR(VLOOKUP(AA17,Curr!$B$2:$C$13,2,FALSE),0) -> 11 | AC17: =+Y17*AB17*R17 -> 0 | AD17: =+AC17-X17 -> 0 | AE17: =IFERROR(AD17/AC17,0) -> 0
C18: Day 3 | D18: Hotel | J18: Höfn: Check in to your accommodation for a 1 night stay - Cenrally located 3/4-star hotel - Standard room - breakfast included | Q18: 200 | R18: 1 | S18: =+Q18*R18 -> 200 | T18: 0 | U18: =S18*(1-T18) -> 200 | V18: EUR | W18: =IFERROR(VLOOKUP(V18,Curr!$B$2:$C$13,2,FALSE),0) -> 11 | X18: =U18*W18 -> 2200 | Y18: =Q18/0.8 -> 250 | Z18: =+Y18*R18 -> 250 | AA18: EUR | AB18: =IFERROR(VLOOKUP(AA18,Curr!$B$2:$C$13,2,FALSE),0) -> 11 | AC18: =+Y18*AB18*R18 -> 2750 | AD18: =+AC18-X18 -> 550 | AE18: =IFERROR(AD18/AC18,0) -> 0.2
C19: Day 3 | D19: Leisure | J19: Höfn: Spend time at leisure | Q19: 0 | R19: 0 | S19: =+Q19*R19 -> 0 | T19: 0 | U19: =S19*(1-T19) -> 0 | V19: EUR | W19: =IFERROR(VLOOKUP(V19,Curr!$B$2:$C$13,2,FALSE),0) -> 11 | X19: =U19*W19 -> 0 | Y19: =Q19 -> 0 | Z19: =+Y19*R19 -> 0 | AA19: EUR | AB19: =IFERROR(VLOOKUP(AA19,Curr!$B$2:$C$13,2,FALSE),0) -> 11 | AC19: =+Y19*AB19*R19 -> 0 | AD19: =+AC19-X19 -> 0 | AE19: =IFERROR(AD19/AC19,0) -> 0
S20: =+Q20*R20 -> 0 | T20: 0 | U20: =S20*(1-T20) -> 0 | V20: EUR | W20: =IFERROR(VLOOKUP(V20,Curr!$B$2:$C$13,2,FALSE),0) -> 11 | X20: =U20*W20 -> 0 | Y20: =Q20 -> 0 | Z20: =+Y20*R20 -> 0 | AA20: EUR | AB20: =IFERROR(VLOOKUP(AA20,Curr!$B$2:$C$13,2,FALSE),0) -> 11 | AC20: =+Y20*AB20*R20 -> 0 | AD20: =+AC20-X20 -> 0 | AE20: =IFERROR(AD20/AC20,0) -> 0
C21: Day 4 | D21: Drive | J21: Höfn: Drive to Egilsstaðir - Driving time: 3.5hrs - 4-5hrs - Highlights: Eastfjords coastal & mountain scenery, Djúpivogur, Fjord crossings and dramatic mountain passes, Lagarfljót - Hidden Gems: Eggin í Gleðivík, Remote Eastfjords viewpoints, Small roadside waterfalls along Route 1 | Q21: 0 | R21: 0 | S21: =+Q21*R21 -> 0 | T21: 0 | U21: =S21*(1-T21) -> 0 | V21: EUR | W21: =IFERROR(VLOOKUP(V21,Curr!$B$2:$C$13,2,FALSE),0) -> 11 | X21: =U21*W21 -> 0 | Y21: =Q21 -> 0 | Z21: =+Y21*R21 -> 0 | AA21: EUR | AB21: =IFERROR(VLOOKUP(AA21,Curr!$B$2:$C$13,2,FALSE),0) -> 11 | AC21: =+Y21*AB21*R21 -> 0 | AD21: =+AC21-X21 -> 0 | AE21: =IFERROR(AD21/AC21,0) -> 0
C22: Day 4 | D22: Hotel | J22: Egilsstaðir: Check in to your accommodation for a 1 night stay - Cenrally located 3/4-star hotel - Standard room - breakfast included | Q22: 250 | R22: 1 | S22: =+Q22*R22 -> 250 | T22: 0 | U22: =S22*(1-T22) -> 250 | V22: EUR | W22: =IFERROR(VLOOKUP(V22,Curr!$B$2:$C$13,2,FALSE),0) -> 11 | X22: =U22*W22 -> 2750 | Y22: =Q22/0.8 -> 312.5 | Z22: =+Y22*R22 -> 312.5 | AA22: EUR | AB22: =IFERROR(VLOOKUP(AA22,Curr!$B$2:$C$13,2,FALSE),0) -> 11 | AC22: =+Y22*AB22*R22 -> 3437.5 | AD22: =+AC22-X22 -> 687.5 | AE22: =IFERROR(AD22/AC22,0) -> 0.2
C23: Day 4 | D23: Leisure | J23: Egilsstaðir: Spend time at leisure | Q23: 0 | R23: 0 | S23: =+Q23*R23 -> 0 | T23: 0 | U23: =S23*(1-T23) -> 0 | V23: EUR | W23: =IFERROR(VLOOKUP(V23,Curr!$B$2:$C$13,2,FALSE),0) -> 11 | X23: =U23*W23 -> 0 | Y23: =Q23 -> 0 | Z23: =+Y23*R23 -> 0 | AA23: EUR | AB23: =IFERROR(VLOOKUP(AA23,Curr!$B$2:$C$13,2,FALSE),0) -> 11 | AC23: =+Y23*AB23*R23 -> 0 | AD23: =+AC23-X23 -> 0 | AE23: =IFERROR(AD23/AC23,0) -> 0
S24: =+Q24*R24 -> 0 | T24: 0 | U24: =S24*(1-T24) -> 0 | V24: EUR | W24: =IFERROR(VLOOKUP(V24,Curr!$B$2:$C$13,2,FALSE),0) -> 11 | X24: =U24*W24 -> 0 | Y24: =Q24 -> 0 | Z24: =+Y24*R24 -> 0 | AA24: EUR | AB24: =IFERROR(VLOOKUP(AA24,Curr!$B$2:$C$13,2,FALSE),0) -> 11 | AC24: =+Y24*AB24*R24 -> 0 | AD24: =+AC24-X24 -> 0 | AE24: =IFERROR(AD24/AC24,0) -> 0
C25: Day 5 | D25: Drive | J25: Egilsstaðir: Drive to Akureyri, via the Diamond Circle - Driving time: 4.5hrs - 5.5hrs - Highlights: Stuðlagil Canyon, Dettifoss, Ásbyrgi, Goðafoss - Hidden Gems: Hljóðaklettar, Jökulsárgljúfur canyon viewpoints, Quiet stretches near Lake Mývatn | Q25: 0 | R25: 0 | S25: =+Q25*R25 -> 0 | T25: 0 | U25: =S25*(1-T25) -> 0 | V25: EUR | W25: =IFERROR(VLOOKUP(V25,Curr!$B$2:$C$13,2,FALSE),0) -> 11 | X25: =U25*W25 -> 0 | Y25: =Q25 -> 0 | Z25: =+Y25*R25 -> 0 | AA25: EUR | AB25: =IFERROR(VLOOKUP(AA25,Curr!$B$2:$C$13,2,FALSE),0) -> 11 | AC25: =+Y25*AB25*R25 -> 0 | AD25: =+AC25-X25 -> 0 | AE25: =IFERROR(AD25/AC25,0) -> 0
C26: Day 5 | D26: Hotel | J26: Akureyri: Check in to your accommodation for a 1 night stay - Cenrally located 3/4-star hotel - Standard room - breakfast included | Q26: 200 | R26: 1 | S26: =+Q26*R26 -> 200 | T26: 0 | U26: =S26*(1-T26) -> 200 | V26: EUR | W26: =IFERROR(VLOOKUP(V26,Curr!$B$2:$C$13,2,FALSE),0) -> 11 | X26: =U26*W26 -> 2200 | Y26: =Q26/0.8 -> 250 | Z26: =+Y26*R26 -> 250 | AA26: EUR | AB26: =IFERROR(VLOOKUP(AA26,Curr!$B$2:$C$13,2,FALSE),0) -> 11 | AC26: =+Y26*AB26*R26 -> 2750 | AD26: =+AC26-X26 -> 550 | AE26: =IFERROR(AD26/AC26,0) -> 0.2
C27: Day 5 | D27: Leisure | J27: Akureyri: Spend time at leisure | Q27: 0 | R27: 0 | S27: =+Q27*R27 -> 0 | T27: 0 | U27: =S27*(1-T27) -> 0 | V27: EUR | W27: =IFERROR(VLOOKUP(V27,Curr!$B$2:$C$13,2,FALSE),0) -> 11 | X27: =U27*W27 -> 0 | Y27: =Q27 -> 0 | Z27: =+Y27*R27 -> 0 | AA27: EUR | AB27: =IFERROR(VLOOKUP(AA27,Curr!$B$2:$C$13,2,FALSE),0) -> 11 | AC27: =+Y27*AB27*R27 -> 0 | AD27: =+AC27-X27 -> 0 | AE27: =IFERROR(AD27/AC27,0) -> 0
S28: =+Q28*R28 -> 0 | T28: 0 | U28: =S28*(1-T28) -> 0 | V28: EUR | W28: =IFERROR(VLOOKUP(V28,Curr!$B$2:$C$13,2,FALSE),0) -> 11 | X28: =U28*W28 -> 0 | Y28: =Q28 -> 0 | Z28: =+Y28*R28 -> 0 | AA28: EUR | AB28: =IFERROR(VLOOKUP(AA28,Curr!$B$2:$C$13,2,FALSE),0) -> 11 | AC28: =+Y28*AB28*R28 -> 0 | AD28: =+AC28-X28 -> 0 | AE28: =IFERROR(AD28/AC28,0) -> 0
C29: Day 6 | D29: Drive | J29: Akureyri: Drive to Snæfellsnes Peninsula - Driving time: 6hrs - 7hrs - Highlights: Skagafjörður valley landscapes, Hvítserkur, Snæfellsjökull National Park, Kirkjufell - Hidden Gems: Arnarstapi cliffs, Lóndrangar, Quiet black-sand beaches on Snæfellsnes’ north coast | Q29: 0 | R29: 0 | S29: =+Q29*R29 -> 0 | T29: 0 | U29: =S29*(1-T29) -> 0 | V29: EUR | W29: =IFERROR(VLOOKUP(V29,Curr!$B$2:$C$13,2,FALSE),0) -> 11 | X29: =U29*W29 -> 0 | Y29: =Q29 -> 0 | Z29: =+Y29*R29 -> 0 | AA29: EUR | AB29: =IFERROR(VLOOKUP(AA29,Curr!$B$2:$C$13,2,FALSE),0) -> 11 | AC29: =+Y29*AB29*R29 -> 0 | AD29: =+AC29-X29 -> 0 | AE29: =IFERROR(AD29/AC29,0) -> 0
C30: Day 6 | D30: Hotel | J30: Snæfellsnes Peninsula: Check in to your accommodation for a 1 night stay - Cenrally located 3/4-star hotel - Standard room - breakfast included | Q30: 300 | R30: 1 | S30: =+Q30*R30 -> 300 | T30: 0 | U30: =S30*(1-T30) -> 300 | V30: EUR | W30: =IFERROR(VLOOKUP(V30,Curr!$B$2:$C$13,2,FALSE),0) -> 11 | X30: =U30*W30 -> 3300 | Y30: =Q30/0.8 -> 375 | Z30: =+Y30*R30 -> 375 | AA30: EUR | AB30: =IFERROR(VLOOKUP(AA30,Curr!$B$2:$C$13,2,FALSE),0) -> 11 | AC30: =+Y30*AB30*R30 -> 4125 | AD30: =+AC30-X30 -> 825 | AE30: =IFERROR(AD30/AC30,0) -> 0.2
C31: Day 6 | D31: Leisure | J31: Snæfellsnes Peninsula: Spend the evening at leisure | Q31: 0 | R31: 0 | S31: =+Q31*R31 -> 0 | T31: 0 | U31: =S31*(1-T31) -> 0 | V31: EUR | W31: =IFERROR(VLOOKUP(V31,Curr!$B$2:$C$13,2,FALSE),0) -> 11 | X31: =U31*W31 -> 0 | Y31: =Q31 -> 0 | Z31: =+Y31*R31 -> 0 | AA31: EUR | AB31: =IFERROR(VLOOKUP(AA31,Curr!$B$2:$C$13,2,FALSE),0) -> 11 | AC31: =+Y31*AB31*R31 -> 0 | AD31: =+AC31-X31 -> 0 | AE31: =IFERROR(AD31/AC31,0) -> 0
S32: =+Q32*R32 -> 0 | T32: 0 | U32: =S32*(1-T32) -> 0 | V32: EUR | W32: =IFERROR(VLOOKUP(V32,Curr!$B$2:$C$13,2,FALSE),0) -> 11 | X32: =U32*W32 -> 0 | Y32: =Q32 -> 0 | Z32: =+Y32*R32 -> 0 | AA32: EUR | AB32: =IFERROR(VLOOKUP(AA32,Curr!$B$2:$C$13,2,FALSE),0) -> 11 | AC32: =+Y32*AB32*R32 -> 0 | AD32: =+AC32-X32 -> 0 | AE32: =IFERROR(AD32/AC32,0) -> 0
C33: Day 7 | D33: Drive | J33: Snæfellsnes Peninsula: Drive to Reykjavik - Driving time: 2.5hrs - 3.5hrs - Highlights: Kirkjufell, Arnarstapi, Snæfellsnes coastal scenery, Borgarnes - Hidden Gems: Búðir, Ytri Tunga, Scenic pull-offs along Hvalfjörður (Route 47) | Q33: 0 | R33: 0 | S33: =+Q33*R33 -> 0 | T33: 0 | U33: =S33*(1-T33) -> 0 | V33: EUR | W33: =IFERROR(VLOOKUP(V33,Curr!$B$2:$C$13,2,FALSE),0) -> 11 | X33: =U33*W33 -> 0 | Y33: =Q33 -> 0 | Z33: =+Y33*R33 -> 0 | AA33: EUR | AB33: =IFERROR(VLOOKUP(AA33,Curr!$B$2:$C$13,2,FALSE),0) -> 11 | AC33: =+Y33*AB33*R33 -> 0 | AD33: =+AC33-X33 -> 0 | AE33: =IFERROR(AD33/AC33,0) -> 0
C34: Day 7 | D34: Hotel | J34: Reykjavik: Check in to your accommodation for a 1 night stay - Cenrally located 3/4-star hotel - Standard room - breakfast included | Q34: 200 | R34: 1 | S34: =+Q34*R34 -> 200 | T34: 0 | U34: =S34*(1-T34) -> 200 | V34: EUR | W34: =IFERROR(VLOOKUP(V34,Curr!$B$2:$C$13,2,FALSE),0) -> 11 | X34: =U34*W34 -> 2200 | Y34: =Q34/0.8 -> 250 | Z34: =+Y34*R34 -> 250 | AA34: EUR | AB34: =IFERROR(VLOOKUP(AA34,Curr!$B$2:$C$13,2,FALSE),0) -> 11 | AC34: =+Y34*AB34*R34 -> 2750 | AD34: =+AC34-X34 -> 550 | AE34: =IFERROR(AD34/AC34,0) -> 0.2
C35: Day 7 | D35: Leisure | J35: Reykjavik: Spend time at leisure | Q35: 0 | R35: 0 | S35: =+Q35*R35 -> 0 | T35: 0 | U35: =S35*(1-T35) -> 0 | V35: EUR | W35: =IFERROR(VLOOKUP(V35,Curr!$B$2:$C$13,2,FALSE),0) -> 11 | X35: =U35*W35 -> 0 | Y35: =Q35 -> 0 | Z35: =+Y35*R35 -> 0 | AA35: EUR | AB35: =IFERROR(VLOOKUP(AA35,Curr!$B$2:$C$13,2,FALSE),0) -> 11 | AC35: =+Y35*AB35*R35 -> 0 | AD35: =+AC35-X35 -> 0 | AE35: =IFERROR(AD35/AC35,0) -> 0
S36: =+Q36*R36 -> 0 | T36: 0 | U36: =S36*(1-T36) -> 0 | V36: EUR | W36: =IFERROR(VLOOKUP(V36,Curr!$B$2:$C$13,2,FALSE),0) -> 11 | X36: =U36*W36 -> 0 | Y36: =Q36 -> 0 | Z36: =+Y36*R36 -> 0 | AA36: EUR | AB36: =IFERROR(VLOOKUP(AA36,Curr!$B$2:$C$13,2,FALSE),0) -> 11 | AC36: =+Y36*AB36*R36 -> 0 | AD36: =+AC36-X36 -> 0 | AE36: =IFERROR(AD36/AC36,0) -> 0
C37: Day 8 | D37: Drive | J37: Reykjavik: Drive to Keflavik Airport - Driving time: 45min - 1hrs - Highlights: Reykjanes lava fields, Coastal views toward Faxaflói Bay - Hidden Gems: Small pull-offs with ocean views, Short detours on the Reykjanes Peninsula | Q37: 0 | R37: 0 | S37: =+Q37*R37 -> 0 | T37: 0 | U37: =S37*(1-T37) -> 0 | V37: EUR | W37: =IFERROR(VLOOKUP(V37,Curr!$B$2:$C$13,2,FALSE),0) -> 11 | X37: =U37*W37 -> 0 | Y37: =Q37 -> 0 | Z37: =+Y37*R37 -> 0 | AA37: EUR | AB37: =IFERROR(VLOOKUP(AA37,Curr!$B$2:$C$13,2,FALSE),0) -> 11 | AC37: =+Y37*AB37*R37 -> 0 | AD37: =+AC37-X37 -> 0 | AE37: =IFERROR(AD37/AC37,0) -> 0
C38: Day 8 | D38: Car | J38: Keflavik: Deliver your car at the car rental office | Q38: 0 | R38: 0 | S38: =+Q38*R38 -> 0 | T38: 0 | U38: =S38*(1-T38) -> 0 | V38: EUR | W38: =IFERROR(VLOOKUP(V38,Curr!$B$2:$C$13,2,FALSE),0) -> 11 | X38: =U38*W38 -> 0 | Y38: =Q38 -> 0 | Z38: =+Y38*R38 -> 0 | AA38: EUR | AB38: =IFERROR(VLOOKUP(AA38,Curr!$B$2:$C$13,2,FALSE),0) -> 11 | AC38: =+Y38*AB38*R38 -> 0 | AD38: =+AC38-X38 -> 0 | AE38: =IFERROR(AD38/AC38,0) -> 0
C39: Day 8 | D39: Departure | J39: Keflavik: Departure home | Q39: 0 | R39: 0 | S39: =+Q39*R39 -> 0 | T39: 0 | U39: =S39*(1-T39) -> 0 | V39: EUR | W39: =IFERROR(VLOOKUP(V39,Curr!$B$2:$C$13,2,FALSE),0) -> 11 | X39: =U39*W39 -> 0 | Y39: =Q39 -> 0 | Z39: =+Y39*R39 -> 0 | AA39: EUR | AB39: =IFERROR(VLOOKUP(AA39,Curr!$B$2:$C$13,2,FALSE),0) -> 11 | AC39: =+Y39*AB39*R39 -> 0 | AD39: =+AC39-X39 -> 0 | AE39: =IFERROR(AD39/AC39,0) -> 0
S40: =+Q40*R40 -> 0 | T40: 0 | U40: =S40*(1-T40) -> 0 | V40: EUR | W40: =IFERROR(VLOOKUP(V40,Curr!$B$2:$C$13,2,FALSE),0) -> 11 | X40: =U40*W40 -> 0 | Y40: =Q40 -> 0 | Z40: =+Y40*R40 -> 0 | AA40: EUR | AB40: =IFERROR(VLOOKUP(AA40,Curr!$B$2:$C$13,2,FALSE),0) -> 11 | AC40: =+Y40*AB40*R40 -> 0 | AD40: =+AC40-X40 -> 0 | AE40: =IFERROR(AD40/AC40,0) -> 0
S41: =+Q41*R41 -> 0 | T41: 0 | U41: =S41*(1-T41) -> 0 | V41: EUR | W41: =IFERROR(VLOOKUP(V41,Curr!$B$2:$C$13,2,FALSE),0) -> 11 | X41: =U41*W41 -> 0 | Y41: =Q41 -> 0 | Z41: =+Y41*R41 -> 0 | AA41: EUR | AB41: =IFERROR(VLOOKUP(AA41,Curr!$B$2:$C$13,2,FALSE),0) -> 11 | AC41: =+Y41*AB41*R41 -> 0 | AD41: =+AC41-X41 -> 0 | AE41: =IFERROR(AD41/AC41,0) -> 0
C42: Day 1 | D42: Activity Upgrade | J42: Reykjavík: City Walking Tour - Time: 2:00 pm - 5:00 pm - Meeting point: Hallgrímskirkja, Hallgrimstorgi 1 - Includes: Professional, English-speaking guide - Highlights: Hallgrímskirkja, All the major landmarks, Hidden street art & local corners, Iceland in a nutshell | P42: https://booknordics.com/iceland/western-iceland/reykjavik/reykjavik-walking-tour-small-group-citywalk | Q42: 37 | R42: 0 | S42: =+Q42*R42 -> 0 | T42: 0.2 | U42: =S42*(1-T42) -> 0 | V42: EUR | W42: =IFERROR(VLOOKUP(V42,Curr!$B$2:$C$13,2,FALSE),0) -> 11 | X42: =U42*W42 -> 0 | Y42: =Q42 -> 37 | Z42: =+Y42*R42 -> 0 | AA42: EUR | AB42: =IFERROR(VLOOKUP(AA42,Curr!$B$2:$C$13,2,FALSE),0) -> 11 | AC42: =+Y42*AB42*R42 -> 0 | AD42: =+AC42-X42 -> 0 | AE42: =IFERROR(AD42/AC42,0) -> 0
C43: Day 1 | D43: Activity Upgrade | J43: Reykjavík: Northern Lights Minibus Tour - Small Group - Time: 8:30 pm - 12:30 am - Meeting point: Hotel pick up - Includes: Pick-up/drop-off in central Reykjavik, Professional, English-speaking guide, Northern lights tour in a small group, Ticket to Aurora Museum Reykjavik, Free Wi-Fi onboard the vehicle, Hot chocolate and refreshments | P43: https://booknordics.com/iceland/western-iceland/reykjavik/northern-lights-small-group-minibus-tour | Q43: 89 | R43: 0 | S43: =+Q43*R43 -> 0 | T43: 0.25 | U43: =S43*(1-T43) -> 0 | V43: EUR | W43: =IFERROR(VLOOKUP(V43,Curr!$B$2:$C$13,2,FALSE),0) -> 11 | X43: =U43*W43 -> 0 | Y43: =Q43 -> 89 | Z43: =+Y43*R43 -> 0 | AA43: EUR | AB43: =IFERROR(VLOOKUP(AA43,Curr!$B$2:$C$13,2,FALSE),0) -> 11 | AC43: =+Y43*AB43*R43 -> 0 | AD43: =+AC43-X43 -> 0 | AE43: =IFERROR(AD43/AC43,0) -> 0
C44: Day 3 | D44: Activity Upgrade | J44: Vik: Katla Ice Cave Super Jeep Tour - Time: 09:30 am - 12:30 pm - Meeting point: Tröll Expeditions Katla Ice Cave - Includes: Super Jeep excursion to Katla Ice Cave, Certified glacier guide and glacier hike, Experienced off-road driver, Ice cave gear: crampons, and helmet | P44: https://booknordics.com/iceland/southern-iceland/vik/katla-ice-cave-super-jeep-from-vik | Q44: 205 | R44: 0 | S44: =+Q44*R44 -> 0 | T44: 0 | U44: =S44*(1-T44) -> 0 | V44: EUR | W44: =IFERROR(VLOOKUP(V44,Curr!$B$2:$C$13,2,FALSE),0) -> 11 | X44: =U44*W44 -> 0 | Y44: =Q44 -> 205 | Z44: =+Y44*R44 -> 0 | AA44: EUR | AB44: =IFERROR(VLOOKUP(AA44,Curr!$B$2:$C$13,2,FALSE),0) -> 11 | AC44: =+Y44*AB44*R44 -> 0 | AD44: =+AC44-X44 -> 0 | AE44: =IFERROR(AD44/AC44,0) -> 0
C45: Day 6 | D45: Activity Upgrade | J45: Akureyri: Whale Watching Tour - Time: 11:00 am - 1:30 pm - Meeting point: Oddeyrarbót 2, next to the cultural centre HOF in Akureyri - Includes: Whale watching tour approx. 2,5-3 hrs, Knowledgeable, English-speaking guides, Use of warm overalls and blankets, Warm indoor saloom and Free WiFi, Panoramic viewing windows | P45: https://booknordics.com/iceland/northern-iceland/akureyri/akureyri-classic-whale-watching | Q45: 99 | R45: 0 | S45: =+Q45*R45 -> 0 | T45: 0.25 | U45: =S45*(1-T45) -> 0 | V45: EUR | W45: =IFERROR(VLOOKUP(V45,Curr!$B$2:$C$13,2,FALSE),0) -> 11 | X45: =U45*W45 -> 0 | Y45: =Q45 -> 99 | Z45: =+Y45*R45 -> 0 | AA45: EUR | AB45: =IFERROR(VLOOKUP(AA45,Curr!$B$2:$C$13,2,FALSE),0) -> 11 | AC45: =+Y45*AB45*R45 -> 0 | AD45: =+AC45-X45 -> 0 | AE45: =IFERROR(AD45/AC45,0) -> 0
C46: Day 8 | D46: Activity Upgrade | J46: Reykjavik: Blue Lagoon Comfort Package - Time: 09:00 am - 1:00 pm - Meeting point: Hotel Pick up - Includes: Return transfer, Entrance to the Blue Lagoon, Silica mud mask at the Mask Bar, Use of towel, shampoo, conditioner, and moisturizer, Private locker, Non-alcoholic drink at the in-water bar | P46: https://booknordics.com/iceland/western-iceland/reykjavik/reykjavik-blue-lagoon-comfort-including-admission | Q46: 163 | R46: 0 | S46: =+Q46*R46 -> 0 | T46: 0.2 | U46: =S46*(1-T46) -> 0 | V46: EUR | W46: =IFERROR(VLOOKUP(V46,Curr!$B$2:$C$13,2,FALSE),0) -> 11 | X46: =U46*W46 -> 0 | Y46: =Q46 -> 163 | Z46: =+Y46*R46 -> 0 | AA46: EUR | AB46: =IFERROR(VLOOKUP(AA46,Curr!$B$2:$C$13,2,FALSE),0) -> 11 | AC46: =+Y46*AB46*R46 -> 0 | AD46: =+AC46-X46 -> 0 | AE46: =IFERROR(AD46/AC46,0) -> 0
S47: =+Q47*R47 -> 0 | T47: 0 | U47: =S47*(1-T47) -> 0 | V47: EUR | W47: =IFERROR(VLOOKUP(V47,Curr!$B$2:$C$13,2,FALSE),0) -> 11 | X47: =U47*W47 -> 0 | Y47: =Q47 -> 0 | Z47: =+Y47*R47 -> 0 | AA47: EUR | AB47: =IFERROR(VLOOKUP(AA47,Curr!$B$2:$C$13,2,FALSE),0) -> 11 | AC47: =+Y47*AB47*R47 -> 0 | AD47: =+AC47-X47 -> 0 | AE47: =IFERROR(AD47/AC47,0) -> 0
S48: =+Q48*R48 -> 0 | T48: 0 | U48: =S48*(1-T48) -> 0 | V48: EUR | W48: =IFERROR(VLOOKUP(V48,Curr!$B$2:$C$13,2,FALSE),0) -> 11 | X48: =U48*W48 -> 0 | Y48: =Q48 -> 0 | Z48: =+Y48*R48 -> 0 | AA48: EUR | AB48: =IFERROR(VLOOKUP(AA48,Curr!$B$2:$C$13,2,FALSE),0) -> 11 | AC48: =+Y48*AB48*R48 -> 0 | AD48: =+AC48-X48 -> 0 | AE48: =IFERROR(AD48/AC48,0) -> 0
C49: Day 1 | D49: Extra Hotel Night | J49: Reykjavik: Add on an extra night in Reykjavik | Q49: 225 | R49: 0 | S49: =+Q49*R49 -> 0 | T49: 0 | U49: =S49*(1-T49) -> 0 | V49: EUR | W49: =IFERROR(VLOOKUP(V49,Curr!$B$2:$C$13,2,FALSE),0) -> 11 | X49: =U49*W49 -> 0 | Y49: =Q49/0.85 -> 264.70588 | Z49: =+Y49*R49 -> 0 | AA49: EUR | AB49: =IFERROR(VLOOKUP(AA49,Curr!$B$2:$C$13,2,FALSE),0) -> 11 | AC49: =+Y49*AB49*R49 -> 0 | AD49: =+AC49-X49 -> 0 | AE49: =IFERROR(AD49/AC49,0) -> 0
C50: Day 8 | D50: Extra Hotel Night | J50: Reykjavik: Add on an extra night in Reykjavik | Q50: 225 | R50: 0 | S50: =+Q50*R50 -> 0 | T50: 0 | U50: =S50*(1-T50) -> 0 | V50: EUR | W50: =IFERROR(VLOOKUP(V50,Curr!$B$2:$C$13,2,FALSE),0) -> 11 | X50: =U50*W50 -> 0 | Y50: =Q50/0.85 -> 264.70588 | Z50: =+Y50*R50 -> 0 | AA50: EUR | AB50: =IFERROR(VLOOKUP(AA50,Curr!$B$2:$C$13,2,FALSE),0) -> 11 | AC50: =+Y50*AB50*R50 -> 0 | AD50: =+AC50-X50 -> 0 | AE50: =IFERROR(AD50/AC50,0) -> 0
S51: =+Q51*R51 -> 0 | T51: 0 | U51: =S51*(1-T51) -> 0 | V51: EUR | W51: =IFERROR(VLOOKUP(V51,Curr!$B$2:$C$13,2,FALSE),0) -> 11 | X51: =U51*W51 -> 0 | Y51: =Q51 -> 0 | Z51: =+Y51*R51 -> 0 | AA51: EUR | AB51: =IFERROR(VLOOKUP(AA51,Curr!$B$2:$C$13,2,FALSE),0) -> 11 | AC51: =+Y51*AB51*R51 -> 0 | AD51: =+AC51-X51 -> 0 | AE51: =IFERROR(AD51/AC51,0) -> 0
S52: =+Q52*R52 -> 0 | T52: 0 | U52: =S52*(1-T52) -> 0 | V52: EUR | W52: =IFERROR(VLOOKUP(V52,Curr!$B$2:$C$13,2,FALSE),0) -> 11 | X52: =U52*W52 -> 0 | Y52: =Q52 -> 0 | Z52: =+Y52*R52 -> 0 | AA52: EUR | AB52: =IFERROR(VLOOKUP(AA52,Curr!$B$2:$C$13,2,FALSE),0) -> 11 | AC52: =+Y52*AB52*R52 -> 0 | AD52: =+AC52-X52 -> 0 | AE52: =IFERROR(AD52/AC52,0) -> 0
S53: =+Q53*R53 -> 0 | T53: 0 | U53: =S53*(1-T53) -> 0 | V53: EUR | W53: =IFERROR(VLOOKUP(V53,Curr!$B$2:$C$13,2,FALSE),0) -> 11 | X53: =U53*W53 -> 0 | Y53: =Q53 -> 0 | Z53: =+Y53*R53 -> 0 | AA53: EUR | AB53: =IFERROR(VLOOKUP(AA53,Curr!$B$2:$C$13,2,FALSE),0) -> 11 | AC53: =+Y53*AB53*R53 -> 0 | AD53: =+AC53-X53 -> 0 | AE53: =IFERROR(AD53/AC53,0) -> 0
S54: =+Q54*R54 -> 0 | T54: 0 | U54: =S54*(1-T54) -> 0 | V54: EUR | W54: =IFERROR(VLOOKUP(V54,Curr!$B$2:$C$13,2,FALSE),0) -> 11 | X54: =U54*W54 -> 0 | Y54: =Q54 -> 0 | Z54: =+Y54*R54 -> 0 | AA54: EUR | AB54: =IFERROR(VLOOKUP(AA54,Curr!$B$2:$C$13,2,FALSE),0) -> 11 | AC54: =+Y54*AB54*R54 -> 0 | AD54: =+AC54-X54 -> 0 | AE54: =IFERROR(AD54/AC54,0) -> 0
S55: =+Q55*R55 -> 0 | T55: 0 | U55: =S55*(1-T55) -> 0 | V55: EUR | W55: =IFERROR(VLOOKUP(V55,Curr!$B$2:$C$13,2,FALSE),0) -> 11 | X55: =U55*W55 -> 0 | Y55: =Q55 -> 0 | Z55: =+Y55*R55 -> 0 | AA55: EUR | AB55: =IFERROR(VLOOKUP(AA55,Curr!$B$2:$C$13,2,FALSE),0) -> 11 | AC55: =+Y55*AB55*R55 -> 0 | AD55: =+AC55-X55 -> 0 | AE55: =IFERROR(AD55/AC55,0) -> 0
S56: =+Q56*R56 -> 0 | T56: 0 | U56: =S56*(1-T56) -> 0 | V56: EUR | W56: =IFERROR(VLOOKUP(V56,Curr!$B$2:$C$13,2,FALSE),0) -> 11 | X56: =U56*W56 -> 0 | Y56: =Q56 -> 0 | Z56: =+Y56*R56 -> 0 | AA56: EUR | AB56: =IFERROR(VLOOKUP(AA56,Curr!$B$2:$C$13,2,FALSE),0) -> 11 | AC56: =+Y56*AB56*R56 -> 0 | AD56: =+AC56-X56 -> 0 | AE56: =IFERROR(AD56/AC56,0) -> 0
B58: Totals | D58: x | E58: x | F58: x | G58: x | H58: x | I58: x | J58: x | K58: x | L58: x | M58: x | N58: x | O58: x | P58: x | Q58: x | R58: x | S58: x | T58: x | U58: x | V58: x | W58: x | X58: x | Y58: x | Z58: =SUM(Z7:Z56) -> 2812.5 | AC58: =SUM(AC7:AC56) -> 30937.5 | AD58: =SUM(AD7:AD56) -> 6187.5 | AE58: =IFERROR(AD58/AC58,0) -> 0.2 | AF58: =SUM(AF8:AF57) -> 0 | AG58: =SUM(AG8:AG57) -> 0 | AH58: =SUM(AH8:AH57) -> 0 | AI58: =SUM(AI8:AI57) -> 0 | AJ58: =SUM(AJ8:AJ57) -> 0
Y60: Fixed | Z60: 0
Y61: Variable | Z61: =Z8+Z10+Z14+Z18+Z22+Z26+Z30+Z34 -> 2812.5
Y62: Total | Z62: 2820
Y63: PP | Z63: =Z62/2 -> 1410
Y66: Shoulder | Z66: =Z62 -> 2820
Y67: High | Z67: =Z66*1.2 -> 3384
Y68: Peak | Z68: =Z66*1.4 -> 3948
Y69: Low | Z69: =Z66*0.7 -> 1974

Sheet 10D SD
B1: Season: All
B2: Places: Reykjavik 1N - Vik I Myrdal 1N - Hofn 1N - Egilsstadir 1N - Myvatn 1N - Akureyri 1N - Borgarnes 1N - Snæfellsnes Pininsula 1N - Reykjavik 1N
B3: Pax: 2
B4: Rooming: Double
B6: ID | C6: Day | D6: Type | E6: From date | F6: To date | G6: From time | H6: To time | I6: Supplier | J6: Travel element | K6: Manual booking? | L6: Status | M6: Comments | N6: Non-refundable | O6: Refundable | P6: URL | Q6: Gross P per unit | R6: Units | S6: Gross P | T6: Supp Comm | U6: Net P | V6: Supp curr | W6: X-rate | X6: Net P NOK | Y6: Sales P per unit | Z6: Price | AA6: Sales curr | AB6: X-rate | AC6: Sales P NOK tot | AD6: GP NOK | AE6: GP % | AF6: VAT25 | AG6: VAT15 | AH6: VAT12 | AI6: VAT0-D | AJ6: VAT0-I
C7: Day 1 | D7: Arrival | J7: Keflavik: Welcome to Iceland | Q7: 0 | R7: 0 | S7: =+Q7*R7 -> 0 | T7: 0 | U7: =S7*(1-T7) -> 0 | V7: EUR | W7: =IFERROR(VLOOKUP(V7,Curr!$B$2:$C$13,2,FALSE),0) -> 11 | X7: =U7*W7 -> 0 | Y7: =Q7 -> 0 | Z7: =+Y7*R7 -> 0 | AA7: EUR | AB7: =IFERROR(VLOOKUP(AA7,Curr!$B$2:$C$13,2,FALSE),0) -> 11 | AC7: =+Y7*AB7*R7 -> 0 | AD7: =+AC7-X7 -> 0 | AE7: =IFERROR(AD7/AC7,0) -> 0
C8: Day 1 | D8: Car | J8: Keflavik: Pick up your rental car at the car rental office - A 4x4 will with room for 4 luggages will be provided - Includes: Unlimited milage, Supplementary liability insurance, Cancellation fee, Collision damage waiver, Fuel information, Theft protection - Fuel Information: The vehicle should be returned with the same amount of fuel as delivered - Deposit not included | Q8: 800 | R8: 1 | S8: =+Q8*R8 -> 800 | T8: 0 | U8: =S8*(1-T8) -> 800 | V8: EUR | W8: =IFERROR(VLOOKUP(V8,Curr!$B$2:$C$13,2,FALSE),0) -> 11 | X8: =U8*W8 -> 8800 | Y8: =Q8/0.8 -> 1000 | Z8: =+Y8*R8 -> 1000 | AA8: EUR | AB8: =IFERROR(VLOOKUP(AA8,Curr!$B$2:$C$13,2,FALSE),0) -> 11 | AC8: =+Y8*AB8*R8 -> 11000 | AD8: =+AC8-X8 -> 2200 | AE8: =IFERROR(AD8/AC8,0) -> 0.2
C9: Day 1 | D9: Drive | J9: Keflavik: Drive to Reykjavik - Driving time: 45 min - 1 hr - Optional Stops: Reykjanes lava fields, Coastal views along Route 41, Faxaflói Bay viewpoints (weather permitting) - Hidden Gems: Small roadside lava formations, Quiet pull-offs with ocean views, Reykjanes Peninsula backroad detours (only if not rushing) | Q9: 0 | R9: 0 | S9: =+Q9*R9 -> 0 | T9: 0 | U9: =S9*(1-T9) -> 0 | V9: EUR | W9: =IFERROR(VLOOKUP(V9,Curr!$B$2:$C$13,2,FALSE),0) -> 11 | X9: =U9*W9 -> 0 | Y9: =Q9 -> 0 | Z9: =+Y9*R9 -> 0 | AA9: EUR | AB9: =IFERROR(VLOOKUP(AA9,Curr!$B$2:$C$13,2,FALSE),0) -> 11 | AC9: =+Y9*AB9*R9 -> 0 | AD9: =+AC9-X9 -> 0 | AE9: =IFERROR(AD9/AC9,0) -> 0
C10: Day 1 | D10: Hotel | J10: Reykjavik: Check in to your accommodation for a 1 night stay - Cenrally located 3/4-star hotel - Standard room - breakfast included | P10: https://www.ratehawk.com/?sid=5c11424c-1694-4e32-9a64-786852f88adb | Q10: 200 | R10: 1 | S10: =+Q10*R10 -> 200 | T10: 0 | U10: =S10*(1-T10) -> 200 | V10: EUR | W10: =IFERROR(VLOOKUP(V10,Curr!$B$2:$C$13,2,FALSE),0) -> 11 | X10: =U10*W10 -> 2200 | Y10: =Q10/0.8 -> 250 | Z10: =+Y10*R10 -> 250 | AA10: EUR | AB10: =IFERROR(VLOOKUP(AA10,Curr!$B$2:$C$13,2,FALSE),0) -> 11 | AC10: =+Y10*AB10*R10 -> 2750 | AD10: =+AC10-X10 -> 550 | AE10: =IFERROR(AD10/AC10,0) -> 0.2
C11: Day 1 | D11: Leisure | J11: Reykjavik: Spend time at leisure | Q11: 0 | R11: 0 | S11: =+Q11*R11 -> 0 | T11: 0 | U11: =S11*(1-T11) -> 0 | V11: EUR | W11: =IFERROR(VLOOKUP(V11,Curr!$B$2:$C$13,2,FALSE),0) -> 11 | X11: =U11*W11 -> 0 | Y11: =Q11 -> 0 | Z11: =+Y11*R11 -> 0 | AA11: EUR | AB11: =IFERROR(VLOOKUP(AA11,Curr!$B$2:$C$13,2,FALSE),0) -> 11 | AC11: =+Y11*AB11*R11 -> 0 | AD11: =+AC11-X11 -> 0 | AE11: =IFERROR(AD11/AC11,0) -> 0
S12: =+Q12*R12 -> 0 | T12: 0 | U12: =S12*(1-T12) -> 0 | V12: EUR | W12: =IFERROR(VLOOKUP(V12,Curr!$B$2:$C$13,2,FALSE),0) -> 11 | X12: =U12*W12 -> 0 | Y12: =Q12 -> 0 | Z12: =+Y12*R12 -> 0 | AA12: EUR | AB12: =IFERROR(VLOOKUP(AA12,Curr!$B$2:$C$13,2,FALSE),0) -> 11 | AC12: =+Y12*AB12*R12 -> 0 | AD12: =+AC12-X12 -> 0 | AE12: =IFERROR(AD12/AC12,0) -> 0
C13: Day 2 | D13: Drive | J13: Reykjavik: Drive to Vik I Myrdal via the Golden Circle - Driving time: 5.5hrs - 6.5hrs - Highlights: Þingvellir National Park, Geysir (Strokkur), Gullfoss, Seljalandsfoss, Skógafoss, Reynisfjara - Hidden Gems: Kerið, Gljúfrabúi, Dyrhólaey coastal viewpoints (weather permitting) | Q13: 0 | R13: 0 | S13: =+Q13*R13 -> 0 | T13: 0 | U13: =S13*(1-T13) -> 0 | V13: EUR | W13: =IFERROR(VLOOKUP(V13,Curr!$B$2:$C$13,2,FALSE),0) -> 11 | X13: =U13*W13 -> 0 | Y13: =Q13 -> 0 | Z13: =+Y13*R13 -> 0 | AA13: EUR | AB13: =IFERROR(VLOOKUP(AA13,Curr!$B$2:$C$13,2,FALSE),0) -> 11 | AC13: =+Y13*AB13*R13 -> 0 | AD13: =+AC13-X13 -> 0 | AE13: =IFERROR(AD13/AC13,0) -> 0
C14: Day 2 | D14: Hotel | J14: Vik i Myrdal: Check in to your accommodation for a 1 night stay - Cenrally located 3/4-star hotel - Standard room - breakfast included | Q14: 250 | R14: 1 | S14: =+Q14*R14 -> 250 | T14: 0 | U14: =S14*(1-T14) -> 250 | V14: EUR | W14: =IFERROR(VLOOKUP(V14,Curr!$B$2:$C$13,2,FALSE),0) -> 11 | X14: =U14*W14 -> 2750 | Y14: =Q14/0.8 -> 312.5 | Z14: =+Y14*R14 -> 312.5 | AA14: EUR | AB14: =IFERROR(VLOOKUP(AA14,Curr!$B$2:$C$13,2,FALSE),0) -> 11 | AC14: =+Y14*AB14*R14 -> 3437.5 | AD14: =+AC14-X14 -> 687.5 | AE14: =IFERROR(AD14/AC14,0) -> 0.2
C15: Day 2 | D15: Leisure | J15: Vik i Myrdal: Spend time at leisure | Q15: 0 | R15: 0 | S15: =+Q15*R15 -> 0 | T15: 0 | U15: =S15*(1-T15) -> 0 | V15: EUR | W15: =IFERROR(VLOOKUP(V15,Curr!$B$2:$C$13,2,FALSE),0) -> 11 | X15: =U15*W15 -> 0 | Y15: =Q15 -> 0 | Z15: =+Y15*R15 -> 0 | AA15: EUR | AB15: =IFERROR(VLOOKUP(AA15,Curr!$B$2:$C$13,2,FALSE),0) -> 11 | AC15: =+Y15*AB15*R15 -> 0 | AD15: =+AC15-X15 -> 0 | AE15: =IFERROR(AD15/AC15,0) -> 0
S16: =+Q16*R16 -> 0 | T16: 0 | U16: =S16*(1-T16) -> 0 | V16: EUR | W16: =IFERROR(VLOOKUP(V16,Curr!$B$2:$C$13,2,FALSE),0) -> 11 | X16: =U16*W16 -> 0 | Y16: =Q16 -> 0 | Z16: =+Y16*R16 -> 0 | AA16: EUR | AB16: =IFERROR(VLOOKUP(AA16,Curr!$B$2:$C$13,2,FALSE),0) -> 11 | AC16: =+Y16*AB16*R16 -> 0 | AD16: =+AC16-X16 -> 0 | AE16: =IFERROR(AD16/AC16,0) -> 0
C17: Day 3 | D17: Drive | J17: Vik i Myrdal: Drive to Höfn - Driving time: 4.5hrs - 5.5 hrs - Highlights: Fjaðrárgljúfur, Skaftafell, Svartifoss, Jökulsárlón, Diamond Beach - Hidden Gems: Moss-covered lava fields of Eldhraun, Svínafellsjökull, Quiet pull-offs along Skeiðarársandur outwash plain | Q17: 0 | R17: 0 | S17: =+Q17*R17 -> 0 | T17: 0 | U17: =S17*(1-T17) -> 0 | V17: EUR | W17: =IFERROR(VLOOKUP(V17,Curr!$B$2:$C$13,2,FALSE),0) -> 11 | X17: =U17*W17 -> 0 | Y17: =Q17 -> 0 | Z17: =+Y17*R17 -> 0 | AA17: EUR | AB17: =IFERROR(VLOOKUP(AA17,Curr!$B$2:$C$13,2,FALSE),0) -> 11 | AC17: =+Y17*AB17*R17 -> 0 | AD17: =+AC17-X17 -> 0 | AE17: =IFERROR(AD17/AC17,0) -> 0
C18: Day 3 | D18: Hotel | J18: Höfn: Check in to your accommodation for a 1 night stay - Cenrally located 3/4-star hotel - Standard room - breakfast included | Q18: 200 | R18: 1 | S18: =+Q18*R18 -> 200 | T18: 0 | U18: =S18*(1-T18) -> 200 | V18: EUR | W18: =IFERROR(VLOOKUP(V18,Curr!$B$2:$C$13,2,FALSE),0) -> 11 | X18: =U18*W18 -> 2200 | Y18: =Q18/0.8 -> 250 | Z18: =+Y18*R18 -> 250 | AA18: EUR | AB18: =IFERROR(VLOOKUP(AA18,Curr!$B$2:$C$13,2,FALSE),0) -> 11 | AC18: =+Y18*AB18*R18 -> 2750 | AD18: =+AC18-X18 -> 550 | AE18: =IFERROR(AD18/AC18,0) -> 0.2
C19: Day 3 | D19: Leisure | J19: Höfn: Spend time at leisure | Q19: 0 | R19: 0 | S19: =+Q19*R19 -> 0 | T19: 0 | U19: =S19*(1-T19) -> 0 | V19: EUR | W19: =IFERROR(VLOOKUP(V19,Curr!$B$2:$C$13,2,FALSE),0) -> 11 | X19: =U19*W19 -> 0 | Y19: =Q19 -> 0 | Z19: =+Y19*R19 -> 0 | AA19: EUR | AB19: =IFERROR(VLOOKUP(AA19,Curr!$B$2:$C$13,2,FALSE),0) -> 11 | AC19: =+Y19*AB19*R19 -> 0 | AD19: =+AC19-X19 -> 0 | AE19: =IFERROR(AD19/AC19,0) -> 0
S20: =+Q20*R20 -> 0 | T20: 0 | U20: =S20*(1-T20) -> 0 | V20: EUR | W20: =IFERROR(VLOOKUP(V20,Curr!$B$2:$C$13,2,FALSE),0) -> 11 | X20: =U20*W20 -> 0 | Y20: =Q20 -> 0 | Z20: =+Y20*R20 -> 0 | AA20: EUR | AB20: =IFERROR(VLOOKUP(AA20,Curr!$B$2:$C$13,2,FALSE),0) -> 11 | AC20: =+Y20*AB20*R20 -> 0 | AD20: =+AC20-X20 -> 0 | AE20: =IFERROR(AD20/AC20,0) -> 0
C21: Day 4 | D21: Drive | J21: Höfn: Drive to Egilsstaðir - Driving time: 3.5hrs - 4-5hrs - Highlights: Eastfjords coastal & mountain scenery, Djúpivogur, Fjord crossings and dramatic mountain passes, Lagarfljót - Hidden Gems: Eggin í Gleðivík, Remote Eastfjords viewpoints, Small roadside waterfalls along Route 1 | Q21: 0 | R21: 0 | S21: =+Q21*R21 -> 0 | T21: 0 | U21: =S21*(1-T21) -> 0 | V21: EUR | W21: =IFERROR(VLOOKUP(V21,Curr!$B$2:$C$13,2,FALSE),0) -> 11 | X21: =U21*W21 -> 0 | Y21: =Q21 -> 0 | Z21: =+Y21*R21 -> 0 | AA21: EUR | AB21: =IFERROR(VLOOKUP(AA21,Curr!$B$2:$C$13,2,FALSE),0) -> 11 | AC21: =+Y21*AB21*R21 -> 0 | AD21: =+AC21-X21 -> 0 | AE21: =IFERROR(AD21/AC21,0) -> 0
C22: Day 4 | D22: Hotel | J22: Egilsstaðir: Check in to your accommodation for a 1 night stay - Cenrally located 3/4-star hotel - Standard room - breakfast included | Q22: 250 | R22: 1 | S22: =+Q22*R22 -> 250 | T22: 0 | U22: =S22*(1-T22) -> 250 | V22: EUR | W22: =IFERROR(VLOOKUP(V22,Curr!$B$2:$C$13,2,FALSE),0) -> 11 | X22: =U22*W22 -> 2750 | Y22: =Q22/0.8 -> 312.5 | Z22: =+Y22*R22 -> 312.5 | AA22: EUR | AB22: =IFERROR(VLOOKUP(AA22,Curr!$B$2:$C$13,2,FALSE),0) -> 11 | AC22: =+Y22*AB22*R22 -> 3437.5 | AD22: =+AC22-X22 -> 687.5 | AE22: =IFERROR(AD22/AC22,0) -> 0.2
C23: Day 4 | D23: Leisure | J23: Egilsstaðir: Spend time at leisure | Q23: 0 | R23: 0 | S23: =+Q23*R23 -> 0 | T23: 0 | U23: =S23*(1-T23) -> 0 | V23: EUR | W23: =IFERROR(VLOOKUP(V23,Curr!$B$2:$C$13,2,FALSE),0) -> 11 | X23: =U23*W23 -> 0 | Y23: =Q23 -> 0 | Z23: =+Y23*R23 -> 0 | AA23: EUR | AB23: =IFERROR(VLOOKUP(AA23,Curr!$B$2:$C$13,2,FALSE),0) -> 11 | AC23: =+Y23*AB23*R23 -> 0 | AD23: =+AC23-X23 -> 0 | AE23: =IFERROR(AD23/AC23,0) -> 0
S24: =+Q24*R24 -> 0 | T24: 0 | U24: =S24*(1-T24) -> 0 | V24: EUR | W24: =IFERROR(VLOOKUP(V24,Curr!$B$2:$C$13,2,FALSE),0) -> 11 | X24: =U24*W24 -> 0 | Y24: =Q24 -> 0 | Z24: =+Y24*R24 -> 0 | AA24: EUR | AB24: =IFERROR(VLOOKUP(AA24,Curr!$B$2:$C$13,2,FALSE),0) -> 11 | AC24: =+Y24*AB24*R24 -> 0 | AD24: =+AC24-X24 -> 0 | AE24: =IFERROR(AD24/AC24,0) -> 0
C25: Day 5 | D25: Drive | J25: Egilsstaðir: Drive to Myvatn - Driving time: 3.5hrs - 4.5hrs - Highlights: Möðrudalsöræfi scenery, Dettifoss (west side recommended), Lake Mývatn area - Hidden Gems: Stuðlagil Canyon, Grjótagjá, Hverir | Q25: 0 | R25: 0 | S25: =+Q25*R25 -> 0 | T25: 0 | U25: =S25*(1-T25) -> 0 | V25: EUR | W25: =IFERROR(VLOOKUP(V25,Curr!$B$2:$C$13,2,FALSE),0) -> 11 | X25: =U25*W25 -> 0 | Y25: =Q25 -> 0 | Z25: =+Y25*R25 -> 0 | AA25: EUR | AB25: =IFERROR(VLOOKUP(AA25,Curr!$B$2:$C$13,2,FALSE),0) -> 11 | AC25: =+Y25*AB25*R25 -> 0 | AD25: =+AC25-X25 -> 0 | AE25: =IFERROR(AD25/AC25,0) -> 0
C26: Day 5 | D26: Hotel | J26: Myvatn: Check in to your accommodation for a 1 night stay - Cenrally located 3/4-star hotel - Standard room - breakfast included | Q26: 225 | R26: 1 | S26: =+Q26*R26 -> 225 | T26: 0 | U26: =S26*(1-T26) -> 225 | V26: EUR | W26: =IFERROR(VLOOKUP(V26,Curr!$B$2:$C$13,2,FALSE),0) -> 11 | X26: =U26*W26 -> 2475 | Y26: =Q26/0.8 -> 281.25 | Z26: =+Y26*R26 -> 281.25 | AA26: EUR | AB26: =IFERROR(VLOOKUP(AA26,Curr!$B$2:$C$13,2,FALSE),0) -> 11 | AC26: =+Y26*AB26*R26 -> 3093.75 | AD26: =+AC26-X26 -> 618.75 | AE26: =IFERROR(AD26/AC26,0) -> 0.2
C27: Day 5 | D27: Leisure | J27: Myvatn: Spend time at leisure | Q27: 0 | R27: 0 | S27: =+Q27*R27 -> 0 | T27: 0 | U27: =S27*(1-T27) -> 0 | V27: EUR | W27: =IFERROR(VLOOKUP(V27,Curr!$B$2:$C$13,2,FALSE),0) -> 11 | X27: =U27*W27 -> 0 | Y27: =Q27 -> 0 | Z27: =+Y27*R27 -> 0 | AA27: EUR | AB27: =IFERROR(VLOOKUP(AA27,Curr!$B$2:$C$13,2,FALSE),0) -> 11 | AC27: =+Y27*AB27*R27 -> 0 | AD27: =+AC27-X27 -> 0 | AE27: =IFERROR(AD27/AC27,0) -> 0
S28: =+Q28*R28 -> 0 | T28: 0 | U28: =S28*(1-T28) -> 0 | V28: EUR | W28: =IFERROR(VLOOKUP(V28,Curr!$B$2:$C$13,2,FALSE),0) -> 11 | X28: =U28*W28 -> 0 | Y28: =Q28 -> 0 | Z28: =+Y28*R28 -> 0 | AA28: EUR | AB28: =IFERROR(VLOOKUP(AA28,Curr!$B$2:$C$13,2,FALSE),0) -> 11 | AC28: =+Y28*AB28*R28 -> 0 | AD28: =+AC28-X28 -> 0 | AE28: =IFERROR(AD28/AC28,0) -> 0
C29: Day 6 | D29: Drive | J29: Myvatn: Drive to Akureyri - Driving time: 3.5hrs - 4.5hrs - Highlights: Dettifoss, Ásbyrgi, Húsavík, Goðafoss - Hidden Gems: Grjótagjá, Hljóðaklettar, Krafla | Q29: 0 | R29: 0 | S29: =+Q29*R29 -> 0 | T29: 0 | U29: =S29*(1-T29) -> 0 | V29: EUR | W29: =IFERROR(VLOOKUP(V29,Curr!$B$2:$C$13,2,FALSE),0) -> 11 | X29: =U29*W29 -> 0 | Y29: =Q29 -> 0 | Z29: =+Y29*R29 -> 0 | AA29: EUR | AB29: =IFERROR(VLOOKUP(AA29,Curr!$B$2:$C$13,2,FALSE),0) -> 11 | AC29: =+Y29*AB29*R29 -> 0 | AD29: =+AC29-X29 -> 0 | AE29: =IFERROR(AD29/AC29,0) -> 0
C30: Day 6 | D30: Hotel | J30: Akureyri: Check in to your accommodation for a 1 night stay - Cenrally located 3/4-star hotel - Standard room - breakfast included | Q30: 200 | R30: 1 | S30: =+Q30*R30 -> 200 | T30: 0 | U30: =S30*(1-T30) -> 200 | V30: EUR | W30: =IFERROR(VLOOKUP(V30,Curr!$B$2:$C$13,2,FALSE),0) -> 11 | X30: =U30*W30 -> 2200 | Y30: =Q30/0.8 -> 250 | Z30: =+Y30*R30 -> 250 | AA30: EUR | AB30: =IFERROR(VLOOKUP(AA30,Curr!$B$2:$C$13,2,FALSE),0) -> 11 | AC30: =+Y30*AB30*R30 -> 2750 | AD30: =+AC30-X30 -> 550 | AE30: =IFERROR(AD30/AC30,0) -> 0.2
C31: Day 6 | D31: Leisure | J31: Akureyri: Spend time at leisure | Q31: 0 | R31: 0 | S31: =+Q31*R31 -> 0 | T31: 0 | U31: =S31*(1-T31) -> 0 | V31: EUR | W31: =IFERROR(VLOOKUP(V31,Curr!$B$2:$C$13,2,FALSE),0) -> 11 | X31: =U31*W31 -> 0 | Y31: =Q31 -> 0 | Z31: =+Y31*R31 -> 0 | AA31: EUR | AB31: =IFERROR(VLOOKUP(AA31,Curr!$B$2:$C$13,2,FALSE),0) -> 11 | AC31: =+Y31*AB31*R31 -> 0 | AD31: =+AC31-X31 -> 0 | AE31: =IFERROR(AD31/AC31,0) -> 0
S32: =+Q32*R32 -> 0 | T32: 0 | U32: =S32*(1-T32) -> 0 | V32: EUR | W32: =IFERROR(VLOOKUP(V32,Curr!$B$2:$C$13,2,FALSE),0) -> 11 | X32: =U32*W32 -> 0 | Y32: =Q32 -> 0 | Z32: =+Y32*R32 -> 0 | AA32: EUR | AB32: =IFERROR(VLOOKUP(AA32,Curr!$B$2:$C$13,2,FALSE),0) -> 11 | AC32: =+Y32*AB32*R32 -> 0 | AD32: =+AC32-X32 -> 0 | AE32: =IFERROR(AD32/AC32,0) -> 0
C33: Day 7 | D33: Drive | J33: Akureyri: Drive to Borgarnes - Driving time: 4.5hrs - 5.5hrs - Highlights: Skagafjörður valley scenery, Blönduós, Hraunfossar, Barnafoss - Hidden Gems: Hvitserkur (minor detour north), Quiet farmland viewpoints in Skagafjörður, Scenic pull-offs approaching Borgarfjörður | Q33: 0 | R33: 0 | S33: =+Q33*R33 -> 0 | T33: 0 | U33: =S33*(1-T33) -> 0 | V33: EUR | W33: =IFERROR(VLOOKUP(V33,Curr!$B$2:$C$13,2,FALSE),0) -> 11 | X33: =U33*W33 -> 0 | Y33: =Q33 -> 0 | Z33: =+Y33*R33 -> 0 | AA33: EUR | AB33: =IFERROR(VLOOKUP(AA33,Curr!$B$2:$C$13,2,FALSE),0) -> 11 | AC33: =+Y33*AB33*R33 -> 0 | AD33: =+AC33-X33 -> 0 | AE33: =IFERROR(AD33/AC33,0) -> 0
C34: Day 7 | D34: Hotel | J34: Borgarnes: Check in to your accommodation for a 1 night stay - Cenrally located 3/4-star hotel - Standard room - breakfast included | Q34: 175 | R34: 1 | S34: =+Q34*R34 -> 175 | T34: 0 | U34: =S34*(1-T34) -> 175 | V34: EUR | W34: =IFERROR(VLOOKUP(V34,Curr!$B$2:$C$13,2,FALSE),0) -> 11 | X34: =U34*W34 -> 1925 | Y34: =Q34/0.8 -> 218.75 | Z34: =+Y34*R34 -> 218.75 | AA34: EUR | AB34: =IFERROR(VLOOKUP(AA34,Curr!$B$2:$C$13,2,FALSE),0) -> 11 | AC34: =+Y34*AB34*R34 -> 2406.25 | AD34: =+AC34-X34 -> 481.25 | AE34: =IFERROR(AD34/AC34,0) -> 0.2
C35: Day 7 | D35: Leisure | J35: Borgarnes: Spend time at leisure | Q35: 0 | R35: 0 | S35: =+Q35*R35 -> 0 | T35: 0 | U35: =S35*(1-T35) -> 0 | V35: EUR | W35: =IFERROR(VLOOKUP(V35,Curr!$B$2:$C$13,2,FALSE),0) -> 11 | X35: =U35*W35 -> 0 | Y35: =Q35 -> 0 | Z35: =+Y35*R35 -> 0 | AA35: EUR | AB35: =IFERROR(VLOOKUP(AA35,Curr!$B$2:$C$13,2,FALSE),0) -> 11 | AC35: =+Y35*AB35*R35 -> 0 | AD35: =+AC35-X35 -> 0 | AE35: =IFERROR(AD35/AC35,0) -> 0
S36: =+Q36*R36 -> 0 | T36: 0 | U36: =S36*(1-T36) -> 0 | V36: EUR | W36: =IFERROR(VLOOKUP(V36,Curr!$B$2:$C$13,2,FALSE),0) -> 11 | X36: =U36*W36 -> 0 | Y36: =Q36 -> 0 | Z36: =+Y36*R36 -> 0 | AA36: EUR | AB36: =IFERROR(VLOOKUP(AA36,Curr!$B$2:$C$13,2,FALSE),0) -> 11 | AC36: =+Y36*AB36*R36 -> 0 | AD36: =+AC36-X36 -> 0 | AE36: =IFERROR(AD36/AC36,0) -> 0
C37: Day 8 | D37: Drive | J37: Borgarnes: Drive to Snæfellsnes Peninsula - Driving time: 1.5hrs - 2hrs - Highlights: Ytri Tunga, Búðir, Arnarstapi, Kirkjufell - Hidden Gems: Lóndrangar, Quiet coves along the north coast of Snæfellsnes, Small roadside lava fields and viewpoints | Q37: 0 | R37: 0 | S37: =+Q37*R37 -> 0 | T37: 0 | U37: =S37*(1-T37) -> 0 | V37: EUR | W37: =IFERROR(VLOOKUP(V37,Curr!$B$2:$C$13,2,FALSE),0) -> 11 | X37: =U37*W37 -> 0 | Y37: =Q37 -> 0 | Z37: =+Y37*R37 -> 0 | AA37: EUR | AB37: =IFERROR(VLOOKUP(AA37,Curr!$B$2:$C$13,2,FALSE),0) -> 11 | AC37: =+Y37*AB37*R37 -> 0 | AD37: =+AC37-X37 -> 0 | AE37: =IFERROR(AD37/AC37,0) -> 0
C38: Day 8 | D38: Hotel | J38: Snæfellsnes Peninsula: Check in to your accommodation for a 1 night stay - Cenrally located 3/4-star hotel - Standard room - breakfast included | Q38: 300 | R38: 1 | S38: =+Q38*R38 -> 300 | T38: 0 | U38: =S38*(1-T38) -> 300 | V38: EUR | W38: =IFERROR(VLOOKUP(V38,Curr!$B$2:$C$13,2,FALSE),0) -> 11 | X38: =U38*W38 -> 3300 | Y38: =Q38/0.8 -> 375 | Z38: =+Y38*R38 -> 375 | AA38: EUR | AB38: =IFERROR(VLOOKUP(AA38,Curr!$B$2:$C$13,2,FALSE),0) -> 11 | AC38: =+Y38*AB38*R38 -> 4125 | AD38: =+AC38-X38 -> 825 | AE38: =IFERROR(AD38/AC38,0) -> 0.2
C39: Day 8 | D39: Leisure | J39: Snæfellsnes Peninsula: Spend the evening at leisure | Q39: 0 | R39: 0 | S39: =+Q39*R39 -> 0 | T39: 0 | U39: =S39*(1-T39) -> 0 | V39: EUR | W39: =IFERROR(VLOOKUP(V39,Curr!$B$2:$C$13,2,FALSE),0) -> 11 | X39: =U39*W39 -> 0 | Y39: =Q39 -> 0 | Z39: =+Y39*R39 -> 0 | AA39: EUR | AB39: =IFERROR(VLOOKUP(AA39,Curr!$B$2:$C$13,2,FALSE),0) -> 11 | AC39: =+Y39*AB39*R39 -> 0 | AD39: =+AC39-X39 -> 0 | AE39: =IFERROR(AD39/AC39,0) -> 0
S40: =+Q40*R40 -> 0 | T40: 0 | U40: =S40*(1-T40) -> 0 | V40: EUR | W40: =IFERROR(VLOOKUP(V40,Curr!$B$2:$C$13,2,FALSE),0) -> 11 | X40: =U40*W40 -> 0 | Y40: =Q40 -> 0 | Z40: =+Y40*R40 -> 0 | AA40: EUR | AB40: =IFERROR(VLOOKUP(AA40,Curr!$B$2:$C$13,2,FALSE),0) -> 11 | AC40: =+Y40*AB40*R40 -> 0 | AD40: =+AC40-X40 -> 0 | AE40: =IFERROR(AD40/AC40,0) -> 0
C41: Day 9 | D41: Drive | J41: Snæfellsnes Peninsula: Drive to Reykjavik - Driving time: 2.5hrs - 3.5hrs - Highlights: Kirkjufell, Arnarstapi, Snæfellsnes coastal scenery, Borgarnes - Hidden Gems: Búðir, Ytri Tunga, Scenic pull-offs along Hvalfjörður (Route 47) | Q41: 0 | R41: 0 | S41: =+Q41*R41 -> 0 | T41: 0 | U41: =S41*(1-T41) -> 0 | V41: EUR | W41: =IFERROR(VLOOKUP(V41,Curr!$B$2:$C$13,2,FALSE),0) -> 11 | X41: =U41*W41 -> 0 | Y41: =Q41 -> 0 | Z41: =+Y41*R41 -> 0 | AA41: EUR | AB41: =IFERROR(VLOOKUP(AA41,Curr!$B$2:$C$13,2,FALSE),0) -> 11 | AC41: =+Y41*AB41*R41 -> 0 | AD41: =+AC41-X41 -> 0 | AE41: =IFERROR(AD41/AC41,0) -> 0
C42: Day 9 | D42: Hotel | J42: Reykjavik: Check in to your accommodation for a 1 night stay - Cenrally located 3/4-star hotel - Standard room - breakfast included | Q42: 200 | R42: 1 | S42: =+Q42*R42 -> 200 | T42: 0 | U42: =S42*(1-T42) -> 200 | V42: EUR | W42: =IFERROR(VLOOKUP(V42,Curr!$B$2:$C$13,2,FALSE),0) -> 11 | X42: =U42*W42 -> 2200 | Y42: =Q42/0.8 -> 250 | Z42: =+Y42*R42 -> 250 | AA42: EUR | AB42: =IFERROR(VLOOKUP(AA42,Curr!$B$2:$C$13,2,FALSE),0) -> 11 | AC42: =+Y42*AB42*R42 -> 2750 | AD42: =+AC42-X42 -> 550 | AE42: =IFERROR(AD42/AC42,0) -> 0.2
C43: Day 9 | D43: Leisure | J43: Reykjavik: Spend time at leisure | Q43: 0 | R43: 0 | S43: =+Q43*R43 -> 0 | T43: 0 | U43: =S43*(1-T43) -> 0 | V43: EUR | W43: =IFERROR(VLOOKUP(V43,Curr!$B$2:$C$13,2,FALSE),0) -> 11 | X43: =U43*W43 -> 0 | Y43: =Q43 -> 0 | Z43: =+Y43*R43 -> 0 | AA43: EUR | AB43: =IFERROR(VLOOKUP(AA43,Curr!$B$2:$C$13,2,FALSE),0) -> 11 | AC43: =+Y43*AB43*R43 -> 0 | AD43: =+AC43-X43 -> 0 | AE43: =IFERROR(AD43/AC43,0) -> 0
S44: =+Q44*R44 -> 0 | T44: 0 | U44: =S44*(1-T44) -> 0 | V44: EUR | W44: =IFERROR(VLOOKUP(V44,Curr!$B$2:$C$13,2,FALSE),0) -> 11 | X44: =U44*W44 -> 0 | Y44: =Q44 -> 0 | Z44: =+Y44*R44 -> 0 | AA44: EUR | AB44: =IFERROR(VLOOKUP(AA44,Curr!$B$2:$C$13,2,FALSE),0) -> 11 | AC44: =+Y44*AB44*R44 -> 0 | AD44: =+AC44-X44 -> 0 | AE44: =IFERROR(AD44/AC44,0) -> 0
C45: Day 10 | D45: Drive | J45: Reykjavik: Drive to Keflavik Airport - Driving time: 45min - 1hrs - Highlights: Reykjanes lava fields, Coastal views toward Faxaflói Bay - Hidden Gems: Small pull-offs with ocean views, Short detours on the Reykjanes Peninsula | Q45: 0 | R45: 0 | S45: =+Q45*R45 -> 0 | T45: 0 | U45: =S45*(1-T45) -> 0 | V45: EUR | W45: =IFERROR(VLOOKUP(V45,Curr!$B$2:$C$13,2,FALSE),0) -> 11 | X45: =U45*W45 -> 0 | Y45: =Q45 -> 0 | Z45: =+Y45*R45 -> 0 | AA45: EUR | AB45: =IFERROR(VLOOKUP(AA45,Curr!$B$2:$C$13,2,FALSE),0) -> 11 | AC45: =+Y45*AB45*R45 -> 0 | AD45: =+AC45-X45 -> 0 | AE45: =IFERROR(AD45/AC45,0) -> 0
C46: Day 10 | D46: Car | J46: Keflavik: Deliver your car at the car rental office | Q46: 0 | R46: 0 | S46: =+Q46*R46 -> 0 | T46: 0 | U46: =S46*(1-T46) -> 0 | V46: EUR | W46: =IFERROR(VLOOKUP(V46,Curr!$B$2:$C$13,2,FALSE),0) -> 11 | X46: =U46*W46 -> 0 | Y46: =Q46 -> 0 | Z46: =+Y46*R46 -> 0 | AA46: EUR | AB46: =IFERROR(VLOOKUP(AA46,Curr!$B$2:$C$13,2,FALSE),0) -> 11 | AC46: =+Y46*AB46*R46 -> 0 | AD46: =+AC46-X46 -> 0 | AE46: =IFERROR(AD46/AC46,0) -> 0
C47: Day 10 | D47: Departure | J47: Keflavik: Departure home | Q47: 0 | R47: 0 | S47: =+Q47*R47 -> 0 | T47: 0 | U47: =S47*(1-T47) -> 0 | V47: EUR | W47: =IFERROR(VLOOKUP(V47,Curr!$B$2:$C$13,2,FALSE),0) -> 11 | X47: =U47*W47 -> 0 | Y47: =Q47 -> 0 | Z47: =+Y47*R47 -> 0 | AA47: EUR | AB47: =IFERROR(VLOOKUP(AA47,Curr!$B$2:$C$13,2,FALSE),0) -> 11 | AC47: =+Y47*AB47*R47 -> 0 | AD47: =+AC47-X47 -> 0 | AE47: =IFERROR(AD47/AC47,0) -> 0
S48: =+Q48*R48 -> 0 | T48: 0 | U48: =S48*(1-T48) -> 0 | V48: EUR | W48: =IFERROR(VLOOKUP(V48,Curr!$B$2:$C$13,2,FALSE),0) -> 11 | X48: =U48*W48 -> 0 | Y48: =Q48 -> 0 | Z48: =+Y48*R48 -> 0 | AA48: EUR | AB48: =IFERROR(VLOOKUP(AA48,Curr!$B$2:$C$13,2,FALSE),0) -> 11 | AC48: =+Y48*AB48*R48 -> 0 | AD48: =+AC48-X48 -> 0 | AE48: =IFERROR(AD48/AC48,0) -> 0
S49: =+Q49*R49 -> 0 | T49: 0 | U49: =S49*(1-T49) -> 0 | V49: EUR | W49: =IFERROR(VLOOKUP(V49,Curr!$B$2:$C$13,2,FALSE),0) -> 11 | X49: =U49*W49 -> 0 | Y49: =Q49 -> 0 | Z49: =+Y49*R49 -> 0 | AA49: EUR | AB49: =IFERROR(VLOOKUP(AA49,Curr!$B$2:$C$13,2,FALSE),0) -> 11 | AC49: =+Y49*AB49*R49 -> 0 | AD49: =+AC49-X49 -> 0 | AE49: =IFERROR(AD49/AC49,0) -> 0
C50: Day 1 | D50: Activity Upgrade | J50: Reykjavík: City Walking Tour - Time: 2:00 pm - 5:00 pm - Meeting point: Hallgrímskirkja, Hallgrimstorgi 1 - Includes: Professional, English-speaking guide - Highlights: Hallgrímskirkja, All the major landmarks, Hidden street art & local corners, Iceland in a nutshell | P50: https://booknordics.com/iceland/western-iceland/reykjavik/reykjavik-walking-tour-small-group-citywalk | Q50: 37 | R50: 0 | S50: =+Q50*R50 -> 0 | T50: 0.2 | U50: =S50*(1-T50) -> 0 | V50: EUR | W50: =IFERROR(VLOOKUP(V50,Curr!$B$2:$C$13,2,FALSE),0) -> 11 | X50: =U50*W50 -> 0 | Y50: =Q50 -> 37 | Z50: =+Y50*R50 -> 0 | AA50: EUR | AB50: =IFERROR(VLOOKUP(AA50,Curr!$B$2:$C$13,2,FALSE),0) -> 11 | AC50: =+Y50*AB50*R50 -> 0 | AD50: =+AC50-X50 -> 0 | AE50: =IFERROR(AD50/AC50,0) -> 0
C51: Day 1 | D51: Activity Upgrade | J51: Reykjavík: Northern Lights Minibus Tour - Small Group - Time: 8:30 pm - 12:30 am - Meeting point: Hotel pick up - Includes: Pick-up/drop-off in central Reykjavik, Professional, English-speaking guide, Northern lights tour in a small group, Ticket to Aurora Museum Reykjavik, Free Wi-Fi onboard the vehicle, Hot chocolate and refreshments | P51: https://booknordics.com/iceland/western-iceland/reykjavik/northern-lights-small-group-minibus-tour | Q51: 89 | R51: 0 | S51: =+Q51*R51 -> 0 | T51: 0.25 | U51: =S51*(1-T51) -> 0 | V51: EUR | W51: =IFERROR(VLOOKUP(V51,Curr!$B$2:$C$13,2,FALSE),0) -> 11 | X51: =U51*W51 -> 0 | Y51: =Q51 -> 89 | Z51: =+Y51*R51 -> 0 | AA51: EUR | AB51: =IFERROR(VLOOKUP(AA51,Curr!$B$2:$C$13,2,FALSE),0) -> 11 | AC51: =+Y51*AB51*R51 -> 0 | AD51: =+AC51-X51 -> 0 | AE51: =IFERROR(AD51/AC51,0) -> 0
C52: Day 3 | D52: Activity Upgrade | J52: Vik: Katla Ice Cave Super Jeep Tour - Time: 09:30 am - 12:30 pm - Meeting point: Tröll Expeditions Katla Ice Cave - Includes: Super Jeep excursion to Katla Ice Cave, Certified glacier guide and glacier hike, Experienced off-road driver, Ice cave gear: crampons, and helmet | P52: https://booknordics.com/iceland/southern-iceland/vik/katla-ice-cave-super-jeep-from-vik | Q52: 205 | R52: 0 | S52: =+Q52*R52 -> 0 | T52: 0 | U52: =S52*(1-T52) -> 0 | V52: EUR | W52: =IFERROR(VLOOKUP(V52,Curr!$B$2:$C$13,2,FALSE),0) -> 11 | X52: =U52*W52 -> 0 | Y52: =Q52 -> 205 | Z52: =+Y52*R52 -> 0 | AA52: EUR | AB52: =IFERROR(VLOOKUP(AA52,Curr!$B$2:$C$13,2,FALSE),0) -> 11 | AC52: =+Y52*AB52*R52 -> 0 | AD52: =+AC52-X52 -> 0 | AE52: =IFERROR(AD52/AC52,0) -> 0
C53: Day 6 | D53: Activity Upgrade | J53: Akureyri: Whale Watching Tour - Time: 11:00 am - 1:30 pm - Meeting point: Oddeyrarbót 2, next to the cultural centre HOF in Akureyri - Includes: Whale watching tour approx. 2,5-3 hrs, Knowledgeable, English-speaking guides, Use of warm overalls and blankets, Warm indoor saloom and Free WiFi, Panoramic viewing windows | P53: https://booknordics.com/iceland/northern-iceland/akureyri/akureyri-classic-whale-watching | Q53: 99 | R53: 0 | S53: =+Q53*R53 -> 0 | T53: 0.25 | U53: =S53*(1-T53) -> 0 | V53: EUR | W53: =IFERROR(VLOOKUP(V53,Curr!$B$2:$C$13,2,FALSE),0) -> 11 | X53: =U53*W53 -> 0 | Y53: =Q53 -> 99 | Z53: =+Y53*R53 -> 0 | AA53: EUR | AB53: =IFERROR(VLOOKUP(AA53,Curr!$B$2:$C$13,2,FALSE),0) -> 11 | AC53: =+Y53*AB53*R53 -> 0 | AD53: =+AC53-X53 -> 0 | AE53: =IFERROR(AD53/AC53,0) -> 0
C54: Day 10 | D54: Activity Upgrade | J54: Reykjavik: Blue Lagoon Comfort Package - Time: 09:00 am - 1:00 pm - Meeting point: Hotel Pick up - Includes: Return transfer, Entrance to the Blue Lagoon, Silica mud mask at the Mask Bar, Use of towel, shampoo, conditioner, and moisturizer, Private locker, Non-alcoholic drink at the in-water bar | P54: https://booknordics.com/iceland/western-iceland/reykjavik/reykjavik-blue-lagoon-comfort-including-admission | Q54: 163 | R54: 0 | S54: =+Q54*R54 -> 0 | T54: 0.2 | U54: =S54*(1-T54) -> 0 | V54: EUR | W54: =IFERROR(VLOOKUP(V54,Curr!$B$2:$C$13,2,FALSE),0) -> 11 | X54: =U54*W54 -> 0 | Y54: =Q54 -> 163 | Z54: =+Y54*R54 -> 0 | AA54: EUR | AB54: =IFERROR(VLOOKUP(AA54,Curr!$B$2:$C$13,2,FALSE),0) -> 11 | AC54: =+Y54*AB54*R54 -> 0 | AD54: =+AC54-X54 -> 0 | AE54: =IFERROR(AD54/AC54,0) -> 0
S55: =+Q55*R55 -> 0 | T55: 0 | U55: =S55*(1-T55) -> 0 | V55: EUR | W55: =IFERROR(VLOOKUP(V55,Curr!$B$2:$C$13,2,FALSE),0) -> 11 | X55: =U55*W55 -> 0 | Y55: =Q55 -> 0 | Z55: =+Y55*R55 -> 0 | AA55: EUR | AB55: =IFERROR(VLOOKUP(AA55,Curr!$B$2:$C$13,2,FALSE),0) -> 11 | AC55: =+Y55*AB55*R55 -> 0 | AD55: =+AC55-X55 -> 0 | AE55: =IFERROR(AD55/AC55,0) -> 0
S56: =+Q56*R56 -> 0 | T56: 0 | U56: =S56*(1-T56) -> 0 | V56: EUR | W56: =IFERROR(VLOOKUP(V56,Curr!$B$2:$C$13,2,FALSE),0) -> 11 | X56: =U56*W56 -> 0 | Y56: =Q56 -> 0 | Z56: =+Y56*R56 -> 0 | AA56: EUR | AB56: =IFERROR(VLOOKUP(AA56,Curr!$B$2:$C$13,2,FALSE),0) -> 11 | AC56: =+Y56*AB56*R56 -> 0 | AD56: =+AC56-X56 -> 0 | AE56: =IFERROR(AD56/AC56,0) -> 0
C57: Day 1 | D57: Extra Hotel Night | J57: Reykjavik: Add on an extra night in Reykjavik | Q57: 225 | R57: 0 | S57: =+Q57*R57 -> 0 | T57: 0 | U57: =S57*(1-T57) -> 0 | V57: EUR | W57: =IFERROR(VLOOKUP(V57,Curr!$B$2:$C$13,2,FALSE),0) -> 11 | X57: =U57*W57 -> 0 | Y57: =Q57/0.85 -> 264.70588 | Z57: =+Y57*R57 -> 0 | AA57: EUR | AB57: =IFERROR(VLOOKUP(AA57,Curr!$B$2:$C$13,2,FALSE),0) -> 11 | AC57: =+Y57*AB57*R57 -> 0 | AD57: =+AC57-X57 -> 0 | AE57: =IFERROR(AD57/AC57,0) -> 0
C58: Day 10 | D58: Extra Hotel Night | J58: Reykjavik: Add on an extra night in Reykjavik | Q58: 225 | R58: 0 | S58: =+Q58*R58 -> 0 | T58: 0 | U58: =S58*(1-T58) -> 0 | V58: EUR | W58: =IFERROR(VLOOKUP(V58,Curr!$B$2:$C$13,2,FALSE),0) -> 11 | X58: =U58*W58 -> 0 | Y58: =Q58/0.85 -> 264.70588 | Z58: =+Y58*R58 -> 0 | AA58: EUR | AB58: =IFERROR(VLOOKUP(AA58,Curr!$B$2:$C$13,2,FALSE),0) -> 11 | AC58: =+Y58*AB58*R58 -> 0 | AD58: =+AC58-X58 -> 0 | AE58: =IFERROR(AD58/AC58,0) -> 0
S59: =+Q59*R59 -> 0 | T59: 0 | U59: =S59*(1-T59) -> 0 | V59: EUR | W59: =IFERROR(VLOOKUP(V59,Curr!$B$2:$C$13,2,FALSE),0) -> 11 | X59: =U59*W59 -> 0 | Y59: =Q59 -> 0 | Z59: =+Y59*R59 -> 0 | AA59: EUR | AB59: =IFERROR(VLOOKUP(AA59,Curr!$B$2:$C$13,2,FALSE),0) -> 11 | AC59: =+Y59*AB59*R59 -> 0 | AD59: =+AC59-X59 -> 0 | AE59: =IFERROR(AD59/AC59,0) -> 0
S60: =+Q60*R60 -> 0 | T60: 0 | U60: =S60*(1-T60) -> 0 | V60: EUR | W60: =IFERROR(VLOOKUP(V60,Curr!$B$2:$C$13,2,FALSE),0) -> 11 | X60: =U60*W60 -> 0 | Y60: =Q60 -> 0 | Z60: =+Y60*R60 -> 0 | AA60: EUR | AB60: =IFERROR(VLOOKUP(AA60,Curr!$B$2:$C$13,2,FALSE),0) -> 11 | AC60: =+Y60*AB60*R60 -> 0 | AD60: =+AC60-X60 -> 0 | AE60: =IFERROR(AD60/AC60,0) -> 0
S61: =+Q61*R61 -> 0 | T61: 0 | U61: =S61*(1-T61) -> 0 | V61: EUR | W61: =IFERROR(VLOOKUP(V61,Curr!$B$2:$C$13,2,FALSE),0) -> 11 | X61: =U61*W61 -> 0 | Y61: =Q61 -> 0 | Z61: =+Y61*R61 -> 0 | AA61: EUR | AB61: =IFERROR(VLOOKUP(AA61,Curr!$B$2:$C$13,2,FALSE),0) -> 11 | AC61: =+Y61*AB61*R61 -> 0 | AD61: =+AC61-X61 -> 0 | AE61: =IFERROR(AD61/AC61,0) -> 0
S62: =+Q62*R62 -> 0 | T62: 0 | U62: =S62*(1-T62) -> 0 | V62: EUR | W62: =IFERROR(VLOOKUP(V62,Curr!$B$2:$C$13,2,FALSE),0) -> 11 | X62: =U62*W62 -> 0 | Y62: =Q62 -> 0 | Z62: =+Y62*R62 -> 0 | AA62: EUR | AB62: =IFERROR(VLOOKUP(AA62,Curr!$B$2:$C$13,2,FALSE),0) -> 11 | AC62: =+Y62*AB62*R62 -> 0 | AD62: =+AC62-X62 -> 0 | AE62: =IFERROR(AD62/AC62,0) -> 0
S63: =+Q63*R63 -> 0 | T63: 0 | U63: =S63*(1-T63) -> 0 | V63: EUR | W63: =IFERROR(VLOOKUP(V63,Curr!$B$2:$C$13,2,FALSE),0) -> 11 | X63: =U63*W63 -> 0 | Y63: =Q63 -> 0 | Z63: =+Y63*R63 -> 0 | AA63: EUR | AB63: =IFERROR(VLOOKUP(AA63,Curr!$B$2:$C$13,2,FALSE),0) -> 11 | AC63: =+Y63*AB63*R63 -> 0 | AD63: =+AC63-X63 -> 0 | AE63: =IFERROR(AD63/AC63,0) -> 0
S64: =+Q64*R64 -> 0 | T64: 0 | U64: =S64*(1-T64) -> 0 | V64: EUR | W64: =IFERROR(VLOOKUP(V64,Curr!$B$2:$C$13,2,FALSE),0) -> 11 | X64: =U64*W64 -> 0 | Y64: =Q64 -> 0 | Z64: =+Y64*R64 -> 0 | AA64: EUR | AB64: =IFERROR(VLOOKUP(AA64,Curr!$B$2:$C$13,2,FALSE),0) -> 11 | AC64: =+Y64*AB64*R64 -> 0 | AD64: =+AC64-X64 -> 0 | AE64: =IFERROR(AD64/AC64,0) -> 0
B66: Totals | D66: x | E66: x | F66: x | G66: x | H66: x | I66: x | J66: x | K66: x | L66: x | M66: x | N66: x | O66: x | P66: x | Q66: x | R66: x | S66: x | T66: x | U66: x | V66: x | W66: x | X66: x | Y66: x | Z66: =SUM(Z7:Z64) -> 3500 | AC66: =SUM(AC7:AC64) -> 38500 | AD66: =SUM(AD7:AD64) -> 7700 | AE66: =IFERROR(AD66/AC66,0) -> 0.2 | AF66: =SUM(AF8:AF65) -> 0 | AG66: =SUM(AG8:AG65) -> 0 | AH66: =SUM(AH8:AH65) -> 0 | AI66: =SUM(AI8:AI65) -> 0 | AJ66: =SUM(AJ8:AJ65) -> 0
Y68: Fixed | Z68: 0
Y69: Variable | Z69: =Z8+Z10+Z14+Z18+Z22+Z26+Z30+Z34+Z38+Z42 -> 3500
Y70: Total | Z70: 3520
Y71: PP | Z71: =Z70/2 -> 1760
Y74: Shoulder | Z74: =Z70 -> 3520
Y75: High | Z75: =Z74*1.2 -> 4224
Y76: Peak | Z76: =Z74*1.4 -> 4928
Y77: Low | Z77: =Z74*0.7 -> 2464

Sheet 5D GTS
B1: Season: Summer
B2: Tour: https://booknordics.com/iceland/western-iceland/reykjavik/3-day-summer-minibus-tour-south-coast-glacier-hike-and-golden-circle
B3: Pax: 2
B4: Rooming: Double
B6: ID | C6: Day | D6: Type | E6: From date | F6: To date | G6: From time | H6: To time | I6: Supplier | J6: Travel element | K6: Manual booking? | L6: Status | M6: Comments | N6: Non-refundable | O6: Refundable | P6: URL | Q6: Gross P per unit | R6: Units | S6: Gross P | T6: Supp Comm | U6: Net P | V6: Supp curr | W6: X-rate | X6: Net P NOK | Y6: Sales P per unit | Z6: Price | AA6: Sales curr | AB6: X-rate | AC6: Sales P NOK tot | AD6: GP NOK | AE6: GP % | AF6: VAT25 | AG6: VAT15 | AH6: VAT12 | AI6: VAT0-D | AJ6: VAT0-I
C7: Day 1 | D7: Arrival | J7: Keflavik: Welcome to Iceland | Q7: 0 | R7: 0 | S7: =+Q7*R7 -> 0 | T7: 0 | U7: =S7*(1-T7) -> 0 | V7: EUR | W7: =IFERROR(VLOOKUP(V7,Curr!$B$2:$C$13,2,FALSE),0) -> 11 | X7: =U7*W7 -> 0 | Y7: =Q7 -> 0 | Z7: =+Y7*R7 -> 0 | AA7: EUR | AB7: =IFERROR(VLOOKUP(AA7,Curr!$B$2:$C$13,2,FALSE),0) -> 11 | AC7: =+Y7*AB7*R7 -> 0 | AD7: =+AC7-X7 -> 0 | AE7: =IFERROR(AD7/AC7,0) -> 0
C8: Day 1 | D8: Transfer | J8: Keflavik: Self transfer to your accommodaiton | Q8: 0 | R8: 0 | S8: =+Q8*R8 -> 0 | T8: 0 | U8: =S8*(1-T8) -> 0 | V8: EUR | W8: =IFERROR(VLOOKUP(V8,Curr!$B$2:$C$13,2,FALSE),0) -> 11 | X8: =U8*W8 -> 0 | Y8: =Q8 -> 0 | Z8: =+Y8*R8 -> 0 | AA8: EUR | AB8: =IFERROR(VLOOKUP(AA8,Curr!$B$2:$C$13,2,FALSE),0) -> 11 | AC8: =+Y8*AB8*R8 -> 0 | AD8: =+AC8-X8 -> 0 | AE8: =IFERROR(AD8/AC8,0) -> 0
C9: Day 1 | D9: Hotel | J9: Reykjavik: Check in to your accommodation for a 1 night stay - Centraly Located 3/4-star hotel - Standard room - breakfast included | Q9: 200 | R9: 1 | S9: =+Q9*R9 -> 200 | T9: 0 | U9: =S9*(1-T9) -> 200 | V9: EUR | W9: =IFERROR(VLOOKUP(V9,Curr!$B$2:$C$13,2,FALSE),0) -> 11 | X9: =U9*W9 -> 2200 | Y9: =Q9/0.85 -> 235.29412 | Z9: =+Y9*R9 -> 235.29412 | AA9: EUR | AB9: =IFERROR(VLOOKUP(AA9,Curr!$B$2:$C$13,2,FALSE),0) -> 11 | AC9: =+Y9*AB9*R9 -> 2588.2353 | AD9: =+AC9-X9 -> 388.23529 | AE9: =IFERROR(AD9/AC9,0) -> 0.15
C10: Day 1 | D10: Leisure | J10: Reykjavik: Spend the evening at leisure | Q10: 0 | R10: 0 | S10: =+Q10*R10 -> 0 | T10: 0 | U10: =S10*(1-T10) -> 0 | V10: EUR | W10: =IFERROR(VLOOKUP(V10,Curr!$B$2:$C$13,2,FALSE),0) -> 11 | X10: =U10*W10 -> 0 | Y10: =Q10 -> 0 | Z10: =+Y10*R10 -> 0 | AA10: EUR | AB10: =IFERROR(VLOOKUP(AA10,Curr!$B$2:$C$13,2,FALSE),0) -> 11 | AC10: =+Y10*AB10*R10 -> 0 | AD10: =+AC10-X10 -> 0 | AE10: =IFERROR(AD10/AC10,0) -> 0
S11: =+Q11*R11 -> 0 | T11: 0 | U11: =S11*(1-T11) -> 0 | V11: EUR | W11: =IFERROR(VLOOKUP(V11,Curr!$B$2:$C$13,2,FALSE),0) -> 11 | X11: =U11*W11 -> 0 | Y11: =Q11 -> 0 | Z11: =+Y11*R11 -> 0 | AA11: EUR | AB11: =IFERROR(VLOOKUP(AA11,Curr!$B$2:$C$13,2,FALSE),0) -> 11 | AC11: =+Y11*AB11*R11 -> 0 | AD11: =+AC11-X11 -> 0 | AE11: =IFERROR(AD11/AC11,0) -> 0
C12: Day 2 | D12: Activity | J12: Reykjavik: 3-Day Summer Minibus Tour | South Coast, Glacier Hike & Golden Circle - Meeting point: Hotel pick-up - Time: Between 08:00 am and 8:30 am - Witness the best of Iceland's natural beauty, geological wonders, and the warmth of Icelandic culture. Hike on top of a glacier, see powerful waterfalls, join a boat tour in Glacier Lagoon, admire Diamond Beach, and be amazed by basalt-rock formations on the Reynisfjara Black Sand Beach. Includes: Pick-up/drop off in central Reykjavik, Professional, English-speaking guide, Hotel stays with breakfast and private bathroom, Travel in premum vehicle with WiFi on board, Small-group, local Iceland experience, Day 1: Visit to Thingvellir National Park, Day 1: Visit to the Geysir geothermal area, Day 1: Visit to Gullfoss waterfall, Day 2: Visit to Seljalandsfoss waterfall, Day 2: Visit to Skogafoss waterfall, Day 2: 3-hr glacier hike with a certified guide, Day 2: Helmet, harness, crampons, ice axe, Day 3: Jökulsárlón Amphibian boat ride, Day 3: Visit to Diamond Beach, Day 3: Visit to Reynisfjara Black Sand Beach, All taxes and fees included | P12: https://booknordics.com/iceland/western-iceland/reykjavik/3-day-summer-minibus-tour-south-coast-glacier-hike-and-golden-circle | Q12: 905 | R12: 2 | S12: =+Q12*R12 -> 1810 | T12: 0.2 | U12: =S12*(1-T12) -> 1448 | V12: EUR | W12: =IFERROR(VLOOKUP(V12,Curr!$B$2:$C$13,2,FALSE),0) -> 11 | X12: =U12*W12 -> 15928 | Y12: =Q12*0.95 -> 859.75 | Z12: =+Y12*R12 -> 1719.5 | AA12: EUR | AB12: =IFERROR(VLOOKUP(AA12,Curr!$B$2:$C$13,2,FALSE),0) -> 11 | AC12: =+Y12*AB12*R12 -> 18914.5 | AD12: =+AC12-X12 -> 2986.5 | AE12: =IFERROR(AD12/AC12,0) -> 0.15789474
C13: Day 2 | D13: Group Tour | J13: Day 1: The Golden Circle - Thingvellir National Park: visit the place where the two tectonic plates, the North American and the Eurasian plate, are moving away from each other. Few places in the world offer a better and clearer view of this massive geographic activity. Not only is this vast park beautiful to look at, but it is also remarkable geographically, as the ridge that runs through it is comprised of two exposed tectonic plates: the Eurasian and North American plates pull apart here, giving you the unique opportunity to walk between continents.The biggest natural lake in Iceland is also located at Thingvellir National Park and hosts a great variety of fish and bird life. Thingvellir is also an important place for Icelandic national history. At Thingvellir Icelanders founded their parliament in 930 a.d. where the chieftains had their annual meeting every summer. The name “Thingvellir” translates to “Parliament Plains”. The Geysir geothermal area: it hosts hundreds of colorful hot springs and two geysers hot springs: one is dormant and it's called “Geysir”, that named all the geysers in the world after its name; the other one is called “Strokkur”, which erupts every 5 minutes up to 40 meters. Gullfoss Waterfall: the melting water from Iceland´s second biggest glacier, Langjökull, falls into a deep canyon forming the majestic “Golden Falls”. On a sunny day, you can see the glacier Langjökull in the distance and enjoy a rainbow in the mist of the waterfall, an Instagram blockbuster waiting to happen! Spend your night in a cozy countryside hotel or guesthouse in a room with a private bathroom and breakfast included the next morning. This is included in the price. | Q13: 0 | R13: 0 | S13: =+Q13*R13 -> 0 | T13: 0 | U13: =S13*(1-T13) -> 0 | V13: EUR | W13: =IFERROR(VLOOKUP(V13,Curr!$B$2:$C$13,2,FALSE),0) -> 11 | X13: =U13*W13 -> 0 | Y13: =Q13 -> 0 | Z13: =+Y13*R13 -> 0 | AA13: EUR | AB13: =IFERROR(VLOOKUP(AA13,Curr!$B$2:$C$13,2,FALSE),0) -> 11 | AC13: =+Y13*AB13*R13 -> 0 | AD13: =+AC13-X13 -> 0 | AE13: =IFERROR(AD13/AC13,0) -> 0
S14: =+Q14*R14 -> 0 | T14: 0 | U14: =S14*(1-T14) -> 0 | V14: EUR | W14: =IFERROR(VLOOKUP(V14,Curr!$B$2:$C$13,2,FALSE),0) -> 11 | X14: =U14*W14 -> 0 | Y14: =Q14 -> 0 | Z14: =+Y14*R14 -> 0 | AA14: EUR | AB14: =IFERROR(VLOOKUP(AA14,Curr!$B$2:$C$13,2,FALSE),0) -> 11 | AC14: =+Y14*AB14*R14 -> 0 | AD14: =+AC14-X14 -> 0 | AE14: =IFERROR(AD14/AC14,0) -> 0
C15: Day 3 | D15: Group Tour | J15: Day 2: The South Coast - Seljalandsfoss: the adventure begins with the powerful theatrics of Seljalandsfoss. Bring a raincoat and you’ll be able to make the short hike behind the falls. The scene behind the fall and the trembling ground from the power of the falling water makes for an automatic Instagram blockbuster! Skógafoss waterfall: further east along the coast is Skógafoss waterfall. Skógafoss is an incredibly picturesque sight. Tucked in a little gorge, the river Skógá tumbles down a 60 meter cliff before continuing down the landscape towards the Atlantic Ocean. Alongside the gorge a staircase can take you to the shelf above the waterfall for stunning views. See if you can count your steps on your way up. Glacier Hike: We will hike an outlet glacier spawning from one of the largest glaciers in the country. After meeting our highly trained glacier guides and strapping on our safety and glacier equipment, including helmets, harnesses, crampons and ice axes we hike on the ice for an hour and a half. A spectacular experience and opportunity to learn more about this breathtaking and increasingly rare natural phenomena. Spend your night in a cozy countryside hotel or guesthouse in a room with a private bathroom and breakfast included the next morning. This is included in the price. | Q15: 0 | R15: 0 | S15: =+Q15*R15 -> 0 | T15: 0 | U15: =S15*(1-T15) -> 0 | V15: EUR | W15: =IFERROR(VLOOKUP(V15,Curr!$B$2:$C$13,2,FALSE),0) -> 11 | X15: =U15*W15 -> 0 | Y15: =Q15 -> 0 | Z15: =+Y15*R15 -> 0 | AA15: EUR | AB15: =IFERROR(VLOOKUP(AA15,Curr!$B$2:$C$13,2,FALSE),0) -> 11 | AC15: =+Y15*AB15*R15 -> 0 | AD15: =+AC15-X15 -> 0 | AE15: =IFERROR(AD15/AC15,0) -> 0
S16: =+Q16*R16 -> 0 | T16: 0 | U16: =S16*(1-T16) -> 0 | V16: EUR | W16: =IFERROR(VLOOKUP(V16,Curr!$B$2:$C$13,2,FALSE),0) -> 11 | X16: =U16*W16 -> 0 | Y16: =Q16 -> 0 | Z16: =+Y16*R16 -> 0 | AA16: EUR | AB16: =IFERROR(VLOOKUP(AA16,Curr!$B$2:$C$13,2,FALSE),0) -> 11 | AC16: =+Y16*AB16*R16 -> 0 | AD16: =+AC16-X16 -> 0 | AE16: =IFERROR(AD16/AC16,0) -> 0
C17: Day 4 | D17: Group Tour | J17: Day 3: Boat ride in The Glacier Lagoon - Jökulsárlón: the Glacier Lagoon is a 200m deep glacial lagoon fed by Breiðamerkurjökull, an outlet glacier of Europe’s largest glacier. Enormous icebergs come from Breiðamerkurjökull all year round so the lagoon is usually filled with ice that floats south. We will bring you on a boat ride (inclided in the price) among the icebergs to explore the lake and maybe spot some seals, sunbathing on the icechunks. Try walking alongside the glacier lagoon enjoying the magnificent views and dead silence of Icelandic nature. The Diamond Beach: on the other side of the road the icebergs from Jökulsárlón glacier lagoon float into the Atlantic Ocean where they are quickly thrown back to shore by the tide and winds. This black sand beach is full of smaller ice rocks in all shapes and sizes, sparkling like diamonds in the daylight. The ice itself comes in all shades of white and blue forming beautiful contrasts, guaranteed to make your Instagram account pop! Reynisfjara, the Black Sand Beach: later, we visit the black sand beach of Reynisfjara where the Atlantic coastline presents massive waves hitting the unique basalt columns in the cliffs above the sand. Rock pillars in the water and the cliffs of Dýrhólaey are seen in the distance. This area of the south is also a paradise for bird lovers, as puffins and dozens of other unique species nest on top of these cliffs in the summertime from June to August. Return to Reykjavik - You can expect to arrive back in Reykjavik around 7.00 pm on day 3, depending on traffic and roads | Q17: 0 | R17: 0 | S17: =+Q17*R17 -> 0 | T17: 0 | U17: =S17*(1-T17) -> 0 | V17: EUR | W17: =IFERROR(VLOOKUP(V17,Curr!$B$2:$C$13,2,FALSE),0) -> 11 | X17: =U17*W17 -> 0 | Y17: =Q17 -> 0 | Z17: =+Y17*R17 -> 0 | AA17: EUR | AB17: =IFERROR(VLOOKUP(AA17,Curr!$B$2:$C$13,2,FALSE),0) -> 11 | AC17: =+Y17*AB17*R17 -> 0 | AD17: =+AC17-X17 -> 0 | AE17: =IFERROR(AD17/AC17,0) -> 0
C18: Day 4 | D18: Hotel | J18: Reykjavik: Check in to your accommodation for a 1 night stay - Centraly Located 3/4-star hotel - Standard room - breakfast included | Q18: 200 | R18: 1 | S18: =+Q18*R18 -> 200 | T18: 0 | U18: =S18*(1-T18) -> 200 | V18: EUR | W18: =IFERROR(VLOOKUP(V18,Curr!$B$2:$C$13,2,FALSE),0) -> 11 | X18: =U18*W18 -> 2200 | Y18: =Q18/0.85 -> 235.29412 | Z18: =+Y18*R18 -> 235.29412 | AA18: EUR | AB18: =IFERROR(VLOOKUP(AA18,Curr!$B$2:$C$13,2,FALSE),0) -> 11 | AC18: =+Y18*AB18*R18 -> 2588.2353 | AD18: =+AC18-X18 -> 388.23529 | AE18: =IFERROR(AD18/AC18,0) -> 0.15
C19: Day 4 | D19: Leisure | J19: Reykjavik: Spend the evening at leisure | Q19: 0 | R19: 0 | S19: =+Q19*R19 -> 0 | T19: 0 | U19: =S19*(1-T19) -> 0 | V19: EUR | W19: =IFERROR(VLOOKUP(V19,Curr!$B$2:$C$13,2,FALSE),0) -> 11 | X19: =U19*W19 -> 0 | Y19: =Q19 -> 0 | Z19: =+Y19*R19 -> 0 | AA19: EUR | AB19: =IFERROR(VLOOKUP(AA19,Curr!$B$2:$C$13,2,FALSE),0) -> 11 | AC19: =+Y19*AB19*R19 -> 0 | AD19: =+AC19-X19 -> 0 | AE19: =IFERROR(AD19/AC19,0) -> 0
S20: =+Q20*R20 -> 0 | T20: 0 | U20: =S20*(1-T20) -> 0 | V20: EUR | W20: =IFERROR(VLOOKUP(V20,Curr!$B$2:$C$13,2,FALSE),0) -> 11 | X20: =U20*W20 -> 0 | Y20: =Q20 -> 0 | Z20: =+Y20*R20 -> 0 | AA20: EUR | AB20: =IFERROR(VLOOKUP(AA20,Curr!$B$2:$C$13,2,FALSE),0) -> 11 | AC20: =+Y20*AB20*R20 -> 0 | AD20: =+AC20-X20 -> 0 | AE20: =IFERROR(AD20/AC20,0) -> 0
C21: Day 5 | D21: Transfer | J21: Reykjavik: Self transfer to Keflavik Airport | Q21: 0 | R21: 0 | S21: =+Q21*R21 -> 0 | T21: 0 | U21: =S21*(1-T21) -> 0 | V21: EUR | W21: =IFERROR(VLOOKUP(V21,Curr!$B$2:$C$13,2,FALSE),0) -> 11 | X21: =U21*W21 -> 0 | Y21: =Q21 -> 0 | Z21: =+Y21*R21 -> 0 | AA21: EUR | AB21: =IFERROR(VLOOKUP(AA21,Curr!$B$2:$C$13,2,FALSE),0) -> 11 | AC21: =+Y21*AB21*R21 -> 0 | AD21: =+AC21-X21 -> 0 | AE21: =IFERROR(AD21/AC21,0) -> 0
C22: Day 5 | D22: Departure | J22: Keflavik: Departure home | Q22: 0 | R22: 0 | S22: =+Q22*R22 -> 0 | T22: 0 | U22: =S22*(1-T22) -> 0 | V22: EUR | W22: =IFERROR(VLOOKUP(V22,Curr!$B$2:$C$13,2,FALSE),0) -> 11 | X22: =U22*W22 -> 0 | Y22: =Q22 -> 0 | Z22: =+Y22*R22 -> 0 | AA22: EUR | AB22: =IFERROR(VLOOKUP(AA22,Curr!$B$2:$C$13,2,FALSE),0) -> 11 | AC22: =+Y22*AB22*R22 -> 0 | AD22: =+AC22-X22 -> 0 | AE22: =IFERROR(AD22/AC22,0) -> 0
S23: =+Q23*R23 -> 0 | T23: 0 | U23: =S23*(1-T23) -> 0 | V23: EUR | W23: =IFERROR(VLOOKUP(V23,Curr!$B$2:$C$13,2,FALSE),0) -> 11 | X23: =U23*W23 -> 0 | Y23: =Q23 -> 0 | Z23: =+Y23*R23 -> 0 | AA23: EUR | AB23: =IFERROR(VLOOKUP(AA23,Curr!$B$2:$C$13,2,FALSE),0) -> 11 | AC23: =+Y23*AB23*R23 -> 0 | AD23: =+AC23-X23 -> 0 | AE23: =IFERROR(AD23/AC23,0) -> 0
S24: =+Q24*R24 -> 0 | T24: 0 | U24: =S24*(1-T24) -> 0 | V24: EUR | W24: =IFERROR(VLOOKUP(V24,Curr!$B$2:$C$13,2,FALSE),0) -> 11 | X24: =U24*W24 -> 0 | Y24: =Q24 -> 0 | Z24: =+Y24*R24 -> 0 | AA24: EUR | AB24: =IFERROR(VLOOKUP(AA24,Curr!$B$2:$C$13,2,FALSE),0) -> 11 | AC24: =+Y24*AB24*R24 -> 0 | AD24: =+AC24-X24 -> 0 | AE24: =IFERROR(AD24/AC24,0) -> 0
C25: Day 1 | D25: Transfer package | J25: Keflavik: Private transfer to your accommodaiton | Q25: 160 | R25: 0 | S25: =+Q25*R25 -> 0 | T25: 0.2 | U25: =S25*(1-T25) -> 0 | V25: EUR | W25: =IFERROR(VLOOKUP(V25,Curr!$B$2:$C$13,2,FALSE),0) -> 11 | X25: =U25*W25 -> 0 | Y25: =Q25 -> 160 | Z25: =+Y25*R25 -> 0 | AA25: EUR | AB25: =IFERROR(VLOOKUP(AA25,Curr!$B$2:$C$13,2,FALSE),0) -> 11 | AC25: =+Y25*AB25*R25 -> 0 | AD25: =+AC25-X25 -> 0 | AE25: =IFERROR(AD25/AC25,0) -> 0
C26: Day 1 | D26: Transfer package | J26: Keflavik: Airport Shuttle Bus transfer to your accommodaiton | Q26: 39 | R26: 0 | S26: =+Q26*R26 -> 0 | T26: 0.2 | U26: =S26*(1-T26) -> 0 | V26: EUR | W26: =IFERROR(VLOOKUP(V26,Curr!$B$2:$C$13,2,FALSE),0) -> 11 | X26: =U26*W26 -> 0 | Y26: =Q26 -> 39 | Z26: =+Y26*R26 -> 0 | AA26: EUR | AB26: =IFERROR(VLOOKUP(AA26,Curr!$B$2:$C$13,2,FALSE),0) -> 11 | AC26: =+Y26*AB26*R26 -> 0 | AD26: =+AC26-X26 -> 0 | AE26: =IFERROR(AD26/AC26,0) -> 0
C27: Day 5 | D27: Transfer package | J27: Reykjavik: Private transfer to Keflavik Airport | Q27: 160 | R27: 0 | S27: =+Q27*R27 -> 0 | T27: 0.2 | U27: =S27*(1-T27) -> 0 | V27: EUR | W27: =IFERROR(VLOOKUP(V27,Curr!$B$2:$C$13,2,FALSE),0) -> 11 | X27: =U27*W27 -> 0 | Y27: =Q27 -> 160 | Z27: =+Y27*R27 -> 0 | AA27: EUR | AB27: =IFERROR(VLOOKUP(AA27,Curr!$B$2:$C$13,2,FALSE),0) -> 11 | AC27: =+Y27*AB27*R27 -> 0 | AD27: =+AC27-X27 -> 0 | AE27: =IFERROR(AD27/AC27,0) -> 0
C28: Day 5 | D28: Transfer package | J28: Reykjavik: Airport Shuttle Bus transfer to Keflavik Airport | Q28: 39 | R28: 0 | S28: =+Q28*R28 -> 0 | T28: 0.2 | U28: =S28*(1-T28) -> 0 | V28: EUR | W28: =IFERROR(VLOOKUP(V28,Curr!$B$2:$C$13,2,FALSE),0) -> 11 | X28: =U28*W28 -> 0 | Y28: =Q28 -> 39 | Z28: =+Y28*R28 -> 0 | AA28: EUR | AB28: =IFERROR(VLOOKUP(AA28,Curr!$B$2:$C$13,2,FALSE),0) -> 11 | AC28: =+Y28*AB28*R28 -> 0 | AD28: =+AC28-X28 -> 0 | AE28: =IFERROR(AD28/AC28,0) -> 0
S29: =+Q29*R29 -> 0 | T29: 0 | U29: =S29*(1-T29) -> 0 | V29: EUR | W29: =IFERROR(VLOOKUP(V29,Curr!$B$2:$C$13,2,FALSE),0) -> 11 | X29: =U29*W29 -> 0 | Y29: =Q29 -> 0 | Z29: =+Y29*R29 -> 0 | AA29: EUR | AB29: =IFERROR(VLOOKUP(AA29,Curr!$B$2:$C$13,2,FALSE),0) -> 11 | AC29: =+Y29*AB29*R29 -> 0 | AD29: =+AC29-X29 -> 0 | AE29: =IFERROR(AD29/AC29,0) -> 0
S30: =+Q30*R30 -> 0 | T30: 0 | U30: =S30*(1-T30) -> 0 | V30: EUR | W30: =IFERROR(VLOOKUP(V30,Curr!$B$2:$C$13,2,FALSE),0) -> 11 | X30: =U30*W30 -> 0 | Y30: =Q30 -> 0 | Z30: =+Y30*R30 -> 0 | AA30: EUR | AB30: =IFERROR(VLOOKUP(AA30,Curr!$B$2:$C$13,2,FALSE),0) -> 11 | AC30: =+Y30*AB30*R30 -> 0 | AD30: =+AC30-X30 -> 0 | AE30: =IFERROR(AD30/AC30,0) -> 0
C31: Day 1 | D31: Activity Upgrade | J31: Reykjavík: City Walking Tour - Time: 2:00 pm - 5:00 pm - Meeting point: Hallgrímskirkja, Hallgrimstorgi 1 - Includes: Professional, English-speaking guide - Highlights: Hallgrímskirkja, All the major landmarks, Hidden street art & local corners, Iceland in a nutshell | P31: https://booknordics.com/iceland/western-iceland/reykjavik/reykjavik-walking-tour-small-group-citywalk | Q31: 37 | R31: 0 | S31: =+Q31*R31 -> 0 | T31: 0.2 | U31: =S31*(1-T31) -> 0 | V31: EUR | W31: =IFERROR(VLOOKUP(V31,Curr!$B$2:$C$13,2,FALSE),0) -> 11 | X31: =U31*W31 -> 0 | Y31: =Q31 -> 37 | Z31: =+Y31*R31 -> 0 | AA31: EUR | AB31: =IFERROR(VLOOKUP(AA31,Curr!$B$2:$C$13,2,FALSE),0) -> 11 | AC31: =+Y31*AB31*R31 -> 0 | AD31: =+AC31-X31 -> 0 | AE31: =IFERROR(AD31/AC31,0) -> 0
C32: Day 3 | D32: Activity Upgrade | J32: Day 3: Boat Ride at Jökulsárlón | Q32: 50 | R32: 0 | S32: =+Q32*R32 -> 0 | T32: 0 | U32: =S32*(1-T32) -> 0 | V32: EUR | W32: =IFERROR(VLOOKUP(V32,Curr!$B$2:$C$13,2,FALSE),0) -> 11 | X32: =U32*W32 -> 0 | Y32: =Q32/0.8 -> 62.5 | Z32: =+Y32*R32 -> 0 | AA32: EUR | AB32: =IFERROR(VLOOKUP(AA32,Curr!$B$2:$C$13,2,FALSE),0) -> 11 | AC32: =+Y32*AB32*R32 -> 0 | AD32: =+AC32-X32 -> 0 | AE32: =IFERROR(AD32/AC32,0) -> 0
C33: Day 5 | D33: Activity Upgrade | J33: Reykjavik: Blue Lagoon Comfort Package - Time: 09:00 am - 1:00 pm - Meeting point: Hotel Pick up - Includes: Return transfer, Entrance to the Blue Lagoon, Silica mud mask at the Mask Bar, Use of towel, shampoo, conditioner, and moisturizer, Private locker, Non-alcoholic drink at the in-water bar | P33: https://booknordics.com/iceland/western-iceland/reykjavik/reykjavik-blue-lagoon-comfort-including-admission | Q33: 163 | R33: 0 | S33: =+Q33*R33 -> 0 | T33: 0.2 | U33: =S33*(1-T33) -> 0 | V33: EUR | W33: =IFERROR(VLOOKUP(V33,Curr!$B$2:$C$13,2,FALSE),0) -> 11 | X33: =U33*W33 -> 0 | Y33: =Q33 -> 163 | Z33: =+Y33*R33 -> 0 | AA33: EUR | AB33: =IFERROR(VLOOKUP(AA33,Curr!$B$2:$C$13,2,FALSE),0) -> 11 | AC33: =+Y33*AB33*R33 -> 0 | AD33: =+AC33-X33 -> 0 | AE33: =IFERROR(AD33/AC33,0) -> 0
S34: =+Q34*R34 -> 0 | T34: 0 | U34: =S34*(1-T34) -> 0 | V34: EUR | W34: =IFERROR(VLOOKUP(V34,Curr!$B$2:$C$13,2,FALSE),0) -> 11 | X34: =U34*W34 -> 0 | Y34: =Q34 -> 0 | Z34: =+Y34*R34 -> 0 | AA34: EUR | AB34: =IFERROR(VLOOKUP(AA34,Curr!$B$2:$C$13,2,FALSE),0) -> 11 | AC34: =+Y34*AB34*R34 -> 0 | AD34: =+AC34-X34 -> 0 | AE34: =IFERROR(AD34/AC34,0) -> 0
S35: =+Q35*R35 -> 0 | T35: 0 | U35: =S35*(1-T35) -> 0 | V35: EUR | W35: =IFERROR(VLOOKUP(V35,Curr!$B$2:$C$13,2,FALSE),0) -> 11 | X35: =U35*W35 -> 0 | Y35: =Q35 -> 0 | Z35: =+Y35*R35 -> 0 | AA35: EUR | AB35: =IFERROR(VLOOKUP(AA35,Curr!$B$2:$C$13,2,FALSE),0) -> 11 | AC35: =+Y35*AB35*R35 -> 0 | AD35: =+AC35-X35 -> 0 | AE35: =IFERROR(AD35/AC35,0) -> 0
C36: Day 2 | D36: Single Supplement Fee | J36: Group Tour: Single Supplement Fee (Mandatory for Solo Travelers) | Q36: 153 | R36: 0 | S36: =+Q36*R36 -> 0 | T36: 0 | U36: =S36*(1-T36) -> 0 | V36: EUR | W36: =IFERROR(VLOOKUP(V36,Curr!$B$2:$C$13,2,FALSE),0) -> 11 | X36: =U36*W36 -> 0 | Y36: =Q36/0.8 -> 191.25 | Z36: =+Y36*R36 -> 0 | AA36: EUR | AB36: =IFERROR(VLOOKUP(AA36,Curr!$B$2:$C$13,2,FALSE),0) -> 11 | AC36: =+Y36*AB36*R36 -> 0 | AD36: =+AC36-X36 -> 0 | AE36: =IFERROR(AD36/AC36,0) -> 0
S37: =+Q37*R37 -> 0 | T37: 0 | U37: =S37*(1-T37) -> 0 | V37: EUR | W37: =IFERROR(VLOOKUP(V37,Curr!$B$2:$C$13,2,FALSE),0) -> 11 | X37: =U37*W37 -> 0 | Y37: =Q37 -> 0 | Z37: =+Y37*R37 -> 0 | AA37: EUR | AB37: =IFERROR(VLOOKUP(AA37,Curr!$B$2:$C$13,2,FALSE),0) -> 11 | AC37: =+Y37*AB37*R37 -> 0 | AD37: =+AC37-X37 -> 0 | AE37: =IFERROR(AD37/AC37,0) -> 0
S38: =+Q38*R38 -> 0 | T38: 0 | U38: =S38*(1-T38) -> 0 | V38: EUR | W38: =IFERROR(VLOOKUP(V38,Curr!$B$2:$C$13,2,FALSE),0) -> 11 | X38: =U38*W38 -> 0 | Y38: =Q38 -> 0 | Z38: =+Y38*R38 -> 0 | AA38: EUR | AB38: =IFERROR(VLOOKUP(AA38,Curr!$B$2:$C$13,2,FALSE),0) -> 11 | AC38: =+Y38*AB38*R38 -> 0 | AD38: =+AC38-X38 -> 0 | AE38: =IFERROR(AD38/AC38,0) -> 0
C39: Day 5 | D39: Extra Hotel Night | J39: Reykjavik: Add on an extra night in Reykjavik | Q39: 225 | R39: 0 | S39: =+Q39*R39 -> 0 | T39: 0 | U39: =S39*(1-T39) -> 0 | V39: EUR | W39: =IFERROR(VLOOKUP(V39,Curr!$B$2:$C$13,2,FALSE),0) -> 11 | X39: =U39*W39 -> 0 | Y39: =Q39/0.85 -> 264.70588 | Z39: =+Y39*R39 -> 0 | AA39: EUR | AB39: =IFERROR(VLOOKUP(AA39,Curr!$B$2:$C$13,2,FALSE),0) -> 11 | AC39: =+Y39*AB39*R39 -> 0 | AD39: =+AC39-X39 -> 0 | AE39: =IFERROR(AD39/AC39,0) -> 0
S40: =+Q40*R40 -> 0 | T40: 0 | U40: =S40*(1-T40) -> 0 | V40: EUR | W40: =IFERROR(VLOOKUP(V40,Curr!$B$2:$C$13,2,FALSE),0) -> 11 | X40: =U40*W40 -> 0 | Y40: =Q40 -> 0 | Z40: =+Y40*R40 -> 0 | AA40: EUR | AB40: =IFERROR(VLOOKUP(AA40,Curr!$B$2:$C$13,2,FALSE),0) -> 11 | AC40: =+Y40*AB40*R40 -> 0 | AD40: =+AC40-X40 -> 0 | AE40: =IFERROR(AD40/AC40,0) -> 0
S41: =+Q41*R41 -> 0 | T41: 0 | U41: =S41*(1-T41) -> 0 | V41: EUR | W41: =IFERROR(VLOOKUP(V41,Curr!$B$2:$C$13,2,FALSE),0) -> 11 | X41: =U41*W41 -> 0 | Y41: =Q41 -> 0 | Z41: =+Y41*R41 -> 0 | AA41: EUR | AB41: =IFERROR(VLOOKUP(AA41,Curr!$B$2:$C$13,2,FALSE),0) -> 11 | AC41: =+Y41*AB41*R41 -> 0 | AD41: =+AC41-X41 -> 0 | AE41: =IFERROR(AD41/AC41,0) -> 0
B43: Totals | D43: x | E43: x | F43: x | G43: x | H43: x | I43: x | J43: x | K43: x | L43: x | M43: x | N43: x | O43: x | P43: x | Q43: x | R43: x | S43: x | T43: x | U43: x | V43: x | W43: x | X43: x | Y43: x | Z43: =SUM(Z7:Z41) -> 2190.0882 | AC43: =SUM(AC7:AC41) -> 24090.971 | AD43: =SUM(AD7:AD41) -> 3762.9706 | AE43: =IFERROR(AD43/AC43,0) -> 0.15619838 | AF43: =SUM(AF8:AF42) -> 0 | AG43: =SUM(AG8:AG42) -> 0 | AH43: =SUM(AH8:AH42) -> 0 | AI43: =SUM(AI8:AI42) -> 0 | AJ43: =SUM(AJ8:AJ42) -> 0
Y45: Fixed | Z45: =Z12 -> 1719.5
Y46: Variable | Z46: =Z9+Z18 -> 470.58824
Y47: Total | Z47: 2160
Y48: PP | Z48: =Z47/2 -> 1080
Y50: Ref | Z50: =Z47-Z51 -> 2160
Y51: NoRef | Z51: 0
Y53: Deposit | Z53: =Z47*0.3 -> 648
Y54: Rest | Z54: =Z47-Z53 -> 1512

Sheet 6D GTS
B1: Season: Summer
B2: Tour: https://booknordics.com/iceland/western-iceland/reykjavik/4-day-summer-minibus-tour-south-coast-golden-circle-snaefellsnes-and-jokulsarlon
B3: Pax: 2
B4: Rooming: Double
B6: ID | C6: Day | D6: Type | E6: From date | F6: To date | G6: From time | H6: To time | I6: Supplier | J6: Travel element | K6: Manual booking? | L6: Status | M6: Comments | N6: Non-refundable | O6: Refundable | P6: URL | Q6: Gross P per unit | R6: Units | S6: Gross P | T6: Supp Comm | U6: Net P | V6: Supp curr | W6: X-rate | X6: Net P NOK | Y6: Sales P per unit | Z6: Price | AA6: Sales curr | AB6: X-rate | AC6: Sales P NOK tot | AD6: GP NOK | AE6: GP % | AF6: VAT25 | AG6: VAT15 | AH6: VAT12 | AI6: VAT0-D | AJ6: VAT0-I
C7: Day 1 | D7: Arrival | J7: Keflavik: Welcome to Iceland | Q7: 0 | R7: 0 | S7: =+Q7*R7 -> 0 | T7: 0 | U7: =S7*(1-T7) -> 0 | V7: EUR | W7: =IFERROR(VLOOKUP(V7,Curr!$B$2:$C$13,2,FALSE),0) -> 11 | X7: =U7*W7 -> 0 | Y7: =Q7 -> 0 | Z7: =+Y7*R7 -> 0 | AA7: EUR | AB7: =IFERROR(VLOOKUP(AA7,Curr!$B$2:$C$13,2,FALSE),0) -> 11 | AC7: =+Y7*AB7*R7 -> 0 | AD7: =+AC7-X7 -> 0 | AE7: =IFERROR(AD7/AC7,0) -> 0
C8: Day 1 | D8: Transfer | J8: Keflavik: Self transfer to your accommodaiton | Q8: 0 | R8: 0 | S8: =+Q8*R8 -> 0 | T8: 0 | U8: =S8*(1-T8) -> 0 | V8: EUR | W8: =IFERROR(VLOOKUP(V8,Curr!$B$2:$C$13,2,FALSE),0) -> 11 | X8: =U8*W8 -> 0 | Y8: =Q8 -> 0 | Z8: =+Y8*R8 -> 0 | AA8: EUR | AB8: =IFERROR(VLOOKUP(AA8,Curr!$B$2:$C$13,2,FALSE),0) -> 11 | AC8: =+Y8*AB8*R8 -> 0 | AD8: =+AC8-X8 -> 0 | AE8: =IFERROR(AD8/AC8,0) -> 0
C9: Day 1 | D9: Hotel | J9: Reykjavik: Check in to your accommodation for a 1 night stay - Centraly Located 3/4-star hotel - Standard room - breakfast included | Q9: 200 | R9: 1 | S9: =+Q9*R9 -> 200 | T9: 0 | U9: =S9*(1-T9) -> 200 | V9: EUR | W9: =IFERROR(VLOOKUP(V9,Curr!$B$2:$C$13,2,FALSE),0) -> 11 | X9: =U9*W9 -> 2200 | Y9: =Q9/0.85 -> 235.29412 | Z9: =+Y9*R9 -> 235.29412 | AA9: EUR | AB9: =IFERROR(VLOOKUP(AA9,Curr!$B$2:$C$13,2,FALSE),0) -> 11 | AC9: =+Y9*AB9*R9 -> 2588.2353 | AD9: =+AC9-X9 -> 388.23529 | AE9: =IFERROR(AD9/AC9,0) -> 0.15
C10: Day 1 | D10: Leisure | J10: Reykjavik: Spend the evening at leisure | Q10: 0 | R10: 0 | S10: =+Q10*R10 -> 0 | T10: 0 | U10: =S10*(1-T10) -> 0 | V10: EUR | W10: =IFERROR(VLOOKUP(V10,Curr!$B$2:$C$13,2,FALSE),0) -> 11 | X10: =U10*W10 -> 0 | Y10: =Q10 -> 0 | Z10: =+Y10*R10 -> 0 | AA10: EUR | AB10: =IFERROR(VLOOKUP(AA10,Curr!$B$2:$C$13,2,FALSE),0) -> 11 | AC10: =+Y10*AB10*R10 -> 0 | AD10: =+AC10-X10 -> 0 | AE10: =IFERROR(AD10/AC10,0) -> 0
Q11: 0 | R11: 0 | S11: =+Q11*R11 -> 0 | T11: 0 | U11: =S11*(1-T11) -> 0 | V11: EUR | W11: =IFERROR(VLOOKUP(V11,Curr!$B$2:$C$13,2,FALSE),0) -> 11 | X11: =U11*W11 -> 0 | Y11: =Q11 -> 0 | Z11: =+Y11*R11 -> 0 | AA11: EUR | AB11: =IFERROR(VLOOKUP(AA11,Curr!$B$2:$C$13,2,FALSE),0) -> 11 | AC11: =+Y11*AB11*R11 -> 0 | AD11: =+AC11-X11 -> 0 | AE11: =IFERROR(AD11/AC11,0) -> 0
C12: Day 2 | D12: Activity | J12: Reykjavik: 4-Day Summer Minibus Tour | South Coast, Snæfellsnes & Golden Circle - Meeting point: Hotel Pick up - Time: Between 08:00 am and 8:30 am - Embark on a 4-day tour that combines many of the most essential Icelandic sightseeing tours: the classic Golden Circle, the famous South Coast including Jökulsarlon glacier lagoon and amphibian boat ride, and the mystical Snæfellsnes peninsula. Includes: Pick-up/drop off in central Reykjavik, Professional, English-speaking guide, Hotel stays with breakfast and private bathroom, Travel in premum vehicle with WiFi on board, Small-group, local Iceland experience, Day 1: Visit to Thingvellir National Park, Day 1: Visit to the Geysir geothermal area, Day 1: Visit to Gullfoss waterfall, Day 2: Visit to Seljalandsfoss waterfall, Day 2: Visit to Skogafoss waterfall, Day 2: 3-hr glacier hike with a certified guide, Day 2: Helmet, harness, crampons, ice axe, Day 3: Jökulsárlón Amphibian boat ride, Day 3: Visit to Diamond Beach, Day 3: Visit to Reynisfjara Black Sand Beach, Day 4: Round trip to Snæfelsness peninsula, Day 4: Visit to seal colony and iconic Kirkjufell, Day 4: Visit to Arnarstapi fishing village, All taxes and fees included | P12: https://booknordics.com/iceland/western-iceland/reykjavik/4-day-summer-minibus-tour-south-coast-golden-circle-snaefellsnes-and-jokulsarlon | Q12: 1225 | R12: 2 | S12: =+Q12*R12 -> 2450 | T12: 0.2 | U12: =S12*(1-T12) -> 1960 | V12: EUR | W12: =IFERROR(VLOOKUP(V12,Curr!$B$2:$C$13,2,FALSE),0) -> 11 | X12: =U12*W12 -> 21560 | Y12: =Q12*0.95 -> 1163.75 | Z12: =+Y12*R12 -> 2327.5 | AA12: EUR | AB12: =IFERROR(VLOOKUP(AA12,Curr!$B$2:$C$13,2,FALSE),0) -> 11 | AC12: =+Y12*AB12*R12 -> 25602.5 | AD12: =+AC12-X12 -> 4042.5 | AE12: =IFERROR(AD12/AC12,0) -> 0.15789474
C13: Day 2 | D13: Group Tour | J13: Day 1: You will be picked up from Reykjavík, between 8am and 8.30. After pick up is completed, off we go for our adventure! After pick up, you will head right away to Iceland’s most famous route: The Golden Circle. You’ll get the chance to experience everything that the area has to offer, including geothermal areas, waterfalls, and our favorite locals. Thingvellir National Park: visit the place where the two tectonic plates, the North American and the Eurasian plate, are moving away from each other. Few places in the world offer a better and clearer view of this massive geographic activity. Not only is this vast park beautiful to look at, but it is also remarkable geographically, as the ridge that runs through it is comprised of two exposed tectonic plates: the Eurasian and North American plates pull apart here, giving you the unique opportunity to walk between continents. The biggest natural lake in Iceland is also located at Thingvellir National Park and hosts a great variety of fish and bird life. Thingvellir is also an important place for Icelandic national history. At Thingvellir Icelanders founded their parliament in 930 a.d. where the chieftains had their annual meeting every summer. The name “Thingvellir” translates to “Parliament Plains”. The Geysir geothermal area: it hosts hundreds of colorful hot springs and two geysers hot springs: one is dormant and it's called “Geysir”, that named all the geysers in the world after its name; the other one is called “Strokkur”, which erupts every 5 minutes up to 40 meters. Gullfoss Waterfall: the melting water from Iceland´s second biggest glacier, Langjökull, falls into a deep canyon forming the majestic “Golden Falls”. On a sunny day, you can see the glacier Langjökull in the distance and enjoy a rainbow in the mist of the waterfall, an Instagram blockbuster waiting to happen! Spend your night in a cozy countryside hotel or guesthouse in a room with a private bathroom and breakfast included the next morning. This is included in the price. | Q13: 0 | R13: 0 | S13: =+Q13*R13 -> 0 | T13: 0 | U13: =S13*(1-T13) -> 0 | V13: EUR | W13: =IFERROR(VLOOKUP(V13,Curr!$B$2:$C$13,2,FALSE),0) -> 11 | X13: =U13*W13 -> 0 | Y13: =Q13 -> 0 | Z13: =+Y13*R13 -> 0 | AA13: EUR | AB13: =IFERROR(VLOOKUP(AA13,Curr!$B$2:$C$13,2,FALSE),0) -> 11 | AC13: =+Y13*AB13*R13 -> 0 | AD13: =+AC13-X13 -> 0 | AE13: =IFERROR(AD13/AC13,0) -> 0
S14: =+Q14*R14 -> 0 | T14: 0 | U14: =S14*(1-T14) -> 0 | V14: EUR | W14: =IFERROR(VLOOKUP(V14,Curr!$B$2:$C$13,2,FALSE),0) -> 11 | X14: =U14*W14 -> 0 | Y14: =Q14 -> 0 | Z14: =+Y14*R14 -> 0 | AA14: EUR | AB14: =IFERROR(VLOOKUP(AA14,Curr!$B$2:$C$13,2,FALSE),0) -> 11 | AC14: =+Y14*AB14*R14 -> 0 | AD14: =+AC14-X14 -> 0 | AE14: =IFERROR(AD14/AC14,0) -> 0
C15: Day 3 | D15: Group Tour | J15: Day 2: On the second day you will head towards the South Coast. Seljalandsfoss: the adventure begins with the powerful theatrics of Seljalandsfoss. Bring a raincoat and you’ll be able to make the short hike behind the falls. The scene behind the fall and the trembling ground from the power of the falling water makes for an automatic Instagram blockbuster! Skógafoss waterfall: further east along the coast is Skógafoss waterfall. Skógafoss is an incredibly picturesque sight. Tucked in a little gorge, the river Skógá tumbles down a 60 meter cliff before continuing down the landscape towards the Atlantic Ocean. Alongside the gorge a staircase can take you to the shelf above the waterfall for stunning views. See if you can count your steps on your way up. Glacier Hike: We will hike an outlet glacier spawning from one of the largest glaciers in the country. After meeting our highly trained glacier guides and strapping on our safety and glacier equipment, including helmets, harnesses, crampons and ice axes we hike on the ice for an hour and a half. A spectacular experience and opportunity to learn more about this breathtaking and increasingly rare natural phenomena. Spend your night in a cozy countryside hotel or guesthouse in a room with a private bathroom and breakfast included the next morning. This is included in the price. | Q15: 0 | R15: 0 | S15: =+Q15*R15 -> 0 | T15: 0 | U15: =S15*(1-T15) -> 0 | V15: EUR | W15: =IFERROR(VLOOKUP(V15,Curr!$B$2:$C$13,2,FALSE),0) -> 11 | X15: =U15*W15 -> 0 | Y15: =Q15 -> 0 | Z15: =+Y15*R15 -> 0 | AA15: EUR | AB15: =IFERROR(VLOOKUP(AA15,Curr!$B$2:$C$13,2,FALSE),0) -> 11 | AC15: =+Y15*AB15*R15 -> 0 | AD15: =+AC15-X15 -> 0 | AE15: =IFERROR(AD15/AC15,0) -> 0
S16: =+Q16*R16 -> 0 | T16: 0 | U16: =S16*(1-T16) -> 0 | V16: EUR | W16: =IFERROR(VLOOKUP(V16,Curr!$B$2:$C$13,2,FALSE),0) -> 11 | X16: =U16*W16 -> 0 | Y16: =Q16 -> 0 | Z16: =+Y16*R16 -> 0 | AA16: EUR | AB16: =IFERROR(VLOOKUP(AA16,Curr!$B$2:$C$13,2,FALSE),0) -> 11 | AC16: =+Y16*AB16*R16 -> 0 | AD16: =+AC16-X16 -> 0 | AE16: =IFERROR(AD16/AC16,0) -> 0
C17: Day 4 | D17: Group Tour | J17: Day 3: Boat ride in The Glacier Lagoon. Jökulsárlón: the Glacier Lagoon is a 200m deep glacial lagoon fed by Breiðamerkurjökull, an outlet glacier of Europe’s largest glacier. Enormous icebergs come from Breiðamerkurjökull all year round so the lagoon is usually filled with ice that floats south. We will bring you on a boat ride (inclided in the price) among the icebergs to explore the lake and maybe spot some seals, sunbathing on the icechunks. Try walking alongside the glacier lagoon enjoying the magnificent views and dead silence of Icelandic nature. The Diamond Beach: on the other side of the road the icebergs from Jökulsárlón glacier lagoon float into the Atlantic Ocean where they are quickly thrown back to shore by the tide and winds. This black sand beach is full of smaller ice rocks in all shapes and sizes, sparkling like diamonds in the daylight. The ice itself comes in all shades of white and blue forming beautiful contrasts, guaranteed to make your Instagram account pop! Reynisfjara Black Sand Beach: later, we visit the black sand beach of Reynisfjara where the Atlantic coastline presents massive waves hitting the unique basalt columns in the cliffs above the sand. Rock pillars in the water and the cliffs of Dýrhólaey are seen in the distance. This area of the south is also a paradise for bird lovers, as puffins and dozens of other unique species nest on top of these cliffs in the summertime from June to August. Spend your night in a cozy countryside hotel or guesthouse in a room with a private bathroom and breakfast included the next morning. This is included in the price. | Q17: 0 | R17: 0 | S17: =+Q17*R17 -> 0 | T17: 0 | U17: =S17*(1-T17) -> 0 | V17: EUR | W17: =IFERROR(VLOOKUP(V17,Curr!$B$2:$C$13,2,FALSE),0) -> 11 | X17: =U17*W17 -> 0 | Y17: =Q17 -> 0 | Z17: =+Y17*R17 -> 0 | AA17: EUR | AB17: =IFERROR(VLOOKUP(AA17,Curr!$B$2:$C$13,2,FALSE),0) -> 11 | AC17: =+Y17*AB17*R17 -> 0 | AD17: =+AC17-X17 -> 0 | AE17: =IFERROR(AD17/AC17,0) -> 0
S18: =+Q18*R18 -> 0 | T18: 0 | U18: =S18*(1-T18) -> 0 | V18: EUR | W18: =IFERROR(VLOOKUP(V18,Curr!$B$2:$C$13,2,FALSE),0) -> 11 | X18: =U18*W18 -> 0 | Y18: =Q18 -> 0 | Z18: =+Y18*R18 -> 0 | AA18: EUR | AB18: =IFERROR(VLOOKUP(AA18,Curr!$B$2:$C$13,2,FALSE),0) -> 11 | AC18: =+Y18*AB18*R18 -> 0 | AD18: =+AC18-X18 -> 0 | AE18: =IFERROR(AD18/AC18,0) -> 0
C19: Day 5 | D19: Group Tour | J19: Day 4: Visit the Snæfelsness peninsula. See Borgarnes, the Ytri Tunga Beach and a Seal Colony, Búðir, Arnarstapi: Fishing Village, Djúpalónssandur, Lóndrangar Basalt Cliffs and of course the iconic Kirkjufell! Ytri Tunga Beach and Seal Colony: Spot-friendly seals on the beautiful sandy beach. Búðakirkja: Visit the picturesque Black Church of Búdir with its historic charm. Arnarstapi Fishing Village: Explore the coastal cliffs and hear tales of Bárður, the half-man half-troll. Lóndrangar and Basalt Cliffs: Marvel at the towering rock pinnacles and seabirds. Djúpalónssandur: Discover the black volcanic sand beach, lifting stones, and shipwreck remains. Kirkjufell and Kirkjufellsfoss Waterfall: Capture the iconic mountain and waterfall in a perfect shot. Return to Reykjavik. You can expect to arrive back in Reykjavik around 19.00 on day 3, depending on traffic and roads | Q19: 0 | R19: 0 | S19: =+Q19*R19 -> 0 | T19: 0 | U19: =S19*(1-T19) -> 0 | V19: EUR | W19: =IFERROR(VLOOKUP(V19,Curr!$B$2:$C$13,2,FALSE),0) -> 11 | X19: =U19*W19 -> 0 | Y19: =Q19 -> 0 | Z19: =+Y19*R19 -> 0 | AA19: EUR | AB19: =IFERROR(VLOOKUP(AA19,Curr!$B$2:$C$13,2,FALSE),0) -> 11 | AC19: =+Y19*AB19*R19 -> 0 | AD19: =+AC19-X19 -> 0 | AE19: =IFERROR(AD19/AC19,0) -> 0
C20: Day 5 | D20: Hotel | J20: Reykjavik: Check in to your accommodation for a 1 night stay - Centraly Located 3/4-star hotel - Standard room - breakfast included | Q20: 200 | R20: 1 | S20: =+Q20*R20 -> 200 | T20: 0 | U20: =S20*(1-T20) -> 200 | V20: EUR | W20: =IFERROR(VLOOKUP(V20,Curr!$B$2:$C$13,2,FALSE),0) -> 11 | X20: =U20*W20 -> 2200 | Y20: =Q20/0.85 -> 235.29412 | Z20: =+Y20*R20 -> 235.29412 | AA20: EUR | AB20: =IFERROR(VLOOKUP(AA20,Curr!$B$2:$C$13,2,FALSE),0) -> 11 | AC20: =+Y20*AB20*R20 -> 2588.2353 | AD20: =+AC20-X20 -> 388.23529 | AE20: =IFERROR(AD20/AC20,0) -> 0.15
C21: Day 5 | D21: Leisure | J21: Reykjavik: Spend the evening at leisure | Q21: 0 | R21: 0 | S21: =+Q21*R21 -> 0 | T21: 0 | U21: =S21*(1-T21) -> 0 | V21: EUR | W21: =IFERROR(VLOOKUP(V21,Curr!$B$2:$C$13,2,FALSE),0) -> 11 | X21: =U21*W21 -> 0 | Y21: =Q21 -> 0 | Z21: =+Y21*R21 -> 0 | AA21: EUR | AB21: =IFERROR(VLOOKUP(AA21,Curr!$B$2:$C$13,2,FALSE),0) -> 11 | AC21: =+Y21*AB21*R21 -> 0 | AD21: =+AC21-X21 -> 0 | AE21: =IFERROR(AD21/AC21,0) -> 0
S22: =+Q22*R22 -> 0 | T22: 0 | U22: =S22*(1-T22) -> 0 | V22: EUR | W22: =IFERROR(VLOOKUP(V22,Curr!$B$2:$C$13,2,FALSE),0) -> 11 | X22: =U22*W22 -> 0 | Y22: =Q22 -> 0 | Z22: =+Y22*R22 -> 0 | AA22: EUR | AB22: =IFERROR(VLOOKUP(AA22,Curr!$B$2:$C$13,2,FALSE),0) -> 11 | AC22: =+Y22*AB22*R22 -> 0 | AD22: =+AC22-X22 -> 0 | AE22: =IFERROR(AD22/AC22,0) -> 0
C23: Day 6 | D23: Transfer | J23: Reykjavik: Self transfer to Keflavik Airport | Q23: 0 | R23: 0 | S23: =+Q23*R23 -> 0 | T23: 0 | U23: =S23*(1-T23) -> 0 | V23: EUR | W23: =IFERROR(VLOOKUP(V23,Curr!$B$2:$C$13,2,FALSE),0) -> 11 | X23: =U23*W23 -> 0 | Y23: =Q23 -> 0 | Z23: =+Y23*R23 -> 0 | AA23: EUR | AB23: =IFERROR(VLOOKUP(AA23,Curr!$B$2:$C$13,2,FALSE),0) -> 11 | AC23: =+Y23*AB23*R23 -> 0 | AD23: =+AC23-X23 -> 0 | AE23: =IFERROR(AD23/AC23,0) -> 0
C24: Day 6 | D24: Departure | J24: Keflavik: Departure home | Q24: 0 | R24: 0 | S24: =+Q24*R24 -> 0 | T24: 0 | U24: =S24*(1-T24) -> 0 | V24: EUR | W24: =IFERROR(VLOOKUP(V24,Curr!$B$2:$C$13,2,FALSE),0) -> 11 | X24: =U24*W24 -> 0 | Y24: =Q24 -> 0 | Z24: =+Y24*R24 -> 0 | AA24: EUR | AB24: =IFERROR(VLOOKUP(AA24,Curr!$B$2:$C$13,2,FALSE),0) -> 11 | AC24: =+Y24*AB24*R24 -> 0 | AD24: =+AC24-X24 -> 0 | AE24: =IFERROR(AD24/AC24,0) -> 0
S25: =+Q25*R25 -> 0 | T25: 0 | U25: =S25*(1-T25) -> 0 | V25: EUR | W25: =IFERROR(VLOOKUP(V25,Curr!$B$2:$C$13,2,FALSE),0) -> 11 | X25: =U25*W25 -> 0 | Y25: =Q25 -> 0 | Z25: =+Y25*R25 -> 0 | AA25: EUR | AB25: =IFERROR(VLOOKUP(AA25,Curr!$B$2:$C$13,2,FALSE),0) -> 11 | AC25: =+Y25*AB25*R25 -> 0 | AD25: =+AC25-X25 -> 0 | AE25: =IFERROR(AD25/AC25,0) -> 0
S26: =+Q26*R26 -> 0 | T26: 0 | U26: =S26*(1-T26) -> 0 | V26: EUR | W26: =IFERROR(VLOOKUP(V26,Curr!$B$2:$C$13,2,FALSE),0) -> 11 | X26: =U26*W26 -> 0 | Y26: =Q26 -> 0 | Z26: =+Y26*R26 -> 0 | AA26: EUR | AB26: =IFERROR(VLOOKUP(AA26,Curr!$B$2:$C$13,2,FALSE),0) -> 11 | AC26: =+Y26*AB26*R26 -> 0 | AD26: =+AC26-X26 -> 0 | AE26: =IFERROR(AD26/AC26,0) -> 0
C27: Day 1 | D27: Transfer package | J27: Keflavik: Private transfer to your accommodaiton | Q27: 160 | R27: 0 | S27: =+Q27*R27 -> 0 | T27: 0.2 | U27: =S27*(1-T27) -> 0 | V27: EUR | W27: =IFERROR(VLOOKUP(V27,Curr!$B$2:$C$13,2,FALSE),0) -> 11 | X27: =U27*W27 -> 0 | Y27: =Q27 -> 160 | Z27: =+Y27*R27 -> 0 | AA27: EUR | AB27: =IFERROR(VLOOKUP(AA27,Curr!$B$2:$C$13,2,FALSE),0) -> 11 | AC27: =+Y27*AB27*R27 -> 0 | AD27: =+AC27-X27 -> 0 | AE27: =IFERROR(AD27/AC27,0) -> 0
C28: Day 1 | D28: Transfer package | J28: Keflavik: Airport Shuttle Bus transfer to your accommodaiton | Q28: 39 | R28: 0 | S28: =+Q28*R28 -> 0 | T28: 0.2 | U28: =S28*(1-T28) -> 0 | V28: EUR | W28: =IFERROR(VLOOKUP(V28,Curr!$B$2:$C$13,2,FALSE),0) -> 11 | X28: =U28*W28 -> 0 | Y28: =Q28 -> 39 | Z28: =+Y28*R28 -> 0 | AA28: EUR | AB28: =IFERROR(VLOOKUP(AA28,Curr!$B$2:$C$13,2,FALSE),0) -> 11 | AC28: =+Y28*AB28*R28 -> 0 | AD28: =+AC28-X28 -> 0 | AE28: =IFERROR(AD28/AC28,0) -> 0
C29: Day 6 | D29: Transfer package | J29: Reykjavik: Private transfer to Keflavik Airport | Q29: 160 | R29: 0 | S29: =+Q29*R29 -> 0 | T29: 0.2 | U29: =S29*(1-T29) -> 0 | V29: EUR | W29: =IFERROR(VLOOKUP(V29,Curr!$B$2:$C$13,2,FALSE),0) -> 11 | X29: =U29*W29 -> 0 | Y29: =Q29 -> 160 | Z29: =+Y29*R29 -> 0 | AA29: EUR | AB29: =IFERROR(VLOOKUP(AA29,Curr!$B$2:$C$13,2,FALSE),0) -> 11 | AC29: =+Y29*AB29*R29 -> 0 | AD29: =+AC29-X29 -> 0 | AE29: =IFERROR(AD29/AC29,0) -> 0
C30: Day 6 | D30: Transfer package | J30: Reykjavik: Airport Shuttle Bus transfer to Keflavik Airport | Q30: 39 | R30: 0 | S30: =+Q30*R30 -> 0 | T30: 0.2 | U30: =S30*(1-T30) -> 0 | V30: EUR | W30: =IFERROR(VLOOKUP(V30,Curr!$B$2:$C$13,2,FALSE),0) -> 11 | X30: =U30*W30 -> 0 | Y30: =Q30 -> 39 | Z30: =+Y30*R30 -> 0 | AA30: EUR | AB30: =IFERROR(VLOOKUP(AA30,Curr!$B$2:$C$13,2,FALSE),0) -> 11 | AC30: =+Y30*AB30*R30 -> 0 | AD30: =+AC30-X30 -> 0 | AE30: =IFERROR(AD30/AC30,0) -> 0
S31: =+Q31*R31 -> 0 | T31: 0 | U31: =S31*(1-T31) -> 0 | V31: EUR | W31: =IFERROR(VLOOKUP(V31,Curr!$B$2:$C$13,2,FALSE),0) -> 11 | X31: =U31*W31 -> 0 | Y31: =Q31 -> 0 | Z31: =+Y31*R31 -> 0 | AA31: EUR | AB31: =IFERROR(VLOOKUP(AA31,Curr!$B$2:$C$13,2,FALSE),0) -> 11 | AC31: =+Y31*AB31*R31 -> 0 | AD31: =+AC31-X31 -> 0 | AE31: =IFERROR(AD31/AC31,0) -> 0
S32: =+Q32*R32 -> 0 | T32: 0 | U32: =S32*(1-T32) -> 0 | V32: EUR | W32: =IFERROR(VLOOKUP(V32,Curr!$B$2:$C$13,2,FALSE),0) -> 11 | X32: =U32*W32 -> 0 | Y32: =Q32 -> 0 | Z32: =+Y32*R32 -> 0 | AA32: EUR | AB32: =IFERROR(VLOOKUP(AA32,Curr!$B$2:$C$13,2,FALSE),0) -> 11 | AC32: =+Y32*AB32*R32 -> 0 | AD32: =+AC32-X32 -> 0 | AE32: =IFERROR(AD32/AC32,0) -> 0
C33: Day 1 | D33: Activity Upgrade | J33: Reykjavík: City Walking Tour - Time: 2:00 pm - 5:00 pm - Meeting point: Hallgrímskirkja, Hallgrimstorgi 1 - Includes: Professional, English-speaking guide - Highlights: Hallgrímskirkja, All the major landmarks, Hidden street art & local corners, Iceland in a nutshell | P33: https://booknordics.com/iceland/western-iceland/reykjavik/reykjavik-walking-tour-small-group-citywalk | Q33: 37 | R33: 0 | S33: =+Q33*R33 -> 0 | T33: 0.2 | U33: =S33*(1-T33) -> 0 | V33: EUR | W33: =IFERROR(VLOOKUP(V33,Curr!$B$2:$C$13,2,FALSE),0) -> 11 | X33: =U33*W33 -> 0 | Y33: =Q33 -> 37 | Z33: =+Y33*R33 -> 0 | AA33: EUR | AB33: =IFERROR(VLOOKUP(AA33,Curr!$B$2:$C$13,2,FALSE),0) -> 11 | AC33: =+Y33*AB33*R33 -> 0 | AD33: =+AC33-X33 -> 0 | AE33: =IFERROR(AD33/AC33,0) -> 0
C34: Day 3 | D34: Activity Upgrade | J34: Day 3: Boat Ride at Jökulsárlón | Q34: 50 | R34: 0 | S34: =+Q34*R34 -> 0 | T34: 0 | U34: =S34*(1-T34) -> 0 | V34: EUR | W34: =IFERROR(VLOOKUP(V34,Curr!$B$2:$C$13,2,FALSE),0) -> 11 | X34: =U34*W34 -> 0 | Y34: =Q34/0.8 -> 62.5 | Z34: =+Y34*R34 -> 0 | AA34: EUR | AB34: =IFERROR(VLOOKUP(AA34,Curr!$B$2:$C$13,2,FALSE),0) -> 11 | AC34: =+Y34*AB34*R34 -> 0 | AD34: =+AC34-X34 -> 0 | AE34: =IFERROR(AD34/AC34,0) -> 0
C35: Day 6 | D35: Activity Upgrade | J35: Reykjavik: Blue Lagoon Comfort Package - Time: 09:00 am - 1:00 pm - Meeting point: Hotel Pick up - Includes: Return transfer, Entrance to the Blue Lagoon, Silica mud mask at the Mask Bar, Use of towel, shampoo, conditioner, and moisturizer, Private locker, Non-alcoholic drink at the in-water bar | P35: https://booknordics.com/iceland/western-iceland/reykjavik/reykjavik-blue-lagoon-comfort-including-admission | Q35: 163 | R35: 0 | S35: =+Q35*R35 -> 0 | T35: 0.2 | U35: =S35*(1-T35) -> 0 | V35: EUR | W35: =IFERROR(VLOOKUP(V35,Curr!$B$2:$C$13,2,FALSE),0) -> 11 | X35: =U35*W35 -> 0 | Y35: =Q35 -> 163 | Z35: =+Y35*R35 -> 0 | AA35: EUR | AB35: =IFERROR(VLOOKUP(AA35,Curr!$B$2:$C$13,2,FALSE),0) -> 11 | AC35: =+Y35*AB35*R35 -> 0 | AD35: =+AC35-X35 -> 0 | AE35: =IFERROR(AD35/AC35,0) -> 0
S36: =+Q36*R36 -> 0 | T36: 0 | U36: =S36*(1-T36) -> 0 | V36: EUR | W36: =IFERROR(VLOOKUP(V36,Curr!$B$2:$C$13,2,FALSE),0) -> 11 | X36: =U36*W36 -> 0 | Y36: =Q36 -> 0 | Z36: =+Y36*R36 -> 0 | AA36: EUR | AB36: =IFERROR(VLOOKUP(AA36,Curr!$B$2:$C$13,2,FALSE),0) -> 11 | AC36: =+Y36*AB36*R36 -> 0 | AD36: =+AC36-X36 -> 0 | AE36: =IFERROR(AD36/AC36,0) -> 0
S37: =+Q37*R37 -> 0 | T37: 0 | U37: =S37*(1-T37) -> 0 | V37: EUR | W37: =IFERROR(VLOOKUP(V37,Curr!$B$2:$C$13,2,FALSE),0) -> 11 | X37: =U37*W37 -> 0 | Y37: =Q37 -> 0 | Z37: =+Y37*R37 -> 0 | AA37: EUR | AB37: =IFERROR(VLOOKUP(AA37,Curr!$B$2:$C$13,2,FALSE),0) -> 11 | AC37: =+Y37*AB37*R37 -> 0 | AD37: =+AC37-X37 -> 0 | AE37: =IFERROR(AD37/AC37,0) -> 0
C38: Day 2 | D38: Single Supplement Fee | J38: Group Tour: Single Supplement Fee (Mandatory for Solo Travelers) | Q38: 230 | R38: 0 | S38: =+Q38*R38 -> 0 | T38: 0 | U38: =S38*(1-T38) -> 0 | V38: EUR | W38: =IFERROR(VLOOKUP(V38,Curr!$B$2:$C$13,2,FALSE),0) -> 11 | X38: =U38*W38 -> 0 | Y38: =Q38/0.8 -> 287.5 | Z38: =+Y38*R38 -> 0 | AA38: EUR | AB38: =IFERROR(VLOOKUP(AA38,Curr!$B$2:$C$13,2,FALSE),0) -> 11 | AC38: =+Y38*AB38*R38 -> 0 | AD38: =+AC38-X38 -> 0 | AE38: =IFERROR(AD38/AC38,0) -> 0
S39: =+Q39*R39 -> 0 | T39: 0 | U39: =S39*(1-T39) -> 0 | V39: EUR | W39: =IFERROR(VLOOKUP(V39,Curr!$B$2:$C$13,2,FALSE),0) -> 11 | X39: =U39*W39 -> 0 | Y39: =Q39 -> 0 | Z39: =+Y39*R39 -> 0 | AA39: EUR | AB39: =IFERROR(VLOOKUP(AA39,Curr!$B$2:$C$13,2,FALSE),0) -> 11 | AC39: =+Y39*AB39*R39 -> 0 | AD39: =+AC39-X39 -> 0 | AE39: =IFERROR(AD39/AC39,0) -> 0
S40: =+Q40*R40 -> 0 | T40: 0 | U40: =S40*(1-T40) -> 0 | V40: EUR | W40: =IFERROR(VLOOKUP(V40,Curr!$B$2:$C$13,2,FALSE),0) -> 11 | X40: =U40*W40 -> 0 | Y40: =Q40 -> 0 | Z40: =+Y40*R40 -> 0 | AA40: EUR | AB40: =IFERROR(VLOOKUP(AA40,Curr!$B$2:$C$13,2,FALSE),0) -> 11 | AC40: =+Y40*AB40*R40 -> 0 | AD40: =+AC40-X40 -> 0 | AE40: =IFERROR(AD40/AC40,0) -> 0
C41: Day 6 | D41: Extra Hotel Night | J41: Reykjavik: Add on an extra night in Reykjavik | Q41: 225 | R41: 0 | S41: =+Q41*R41 -> 0 | T41: 0 | U41: =S41*(1-T41) -> 0 | V41: EUR | W41: =IFERROR(VLOOKUP(V41,Curr!$B$2:$C$13,2,FALSE),0) -> 11 | X41: =U41*W41 -> 0 | Y41: =Q41/0.85 -> 264.70588 | Z41: =+Y41*R41 -> 0 | AA41: EUR | AB41: =IFERROR(VLOOKUP(AA41,Curr!$B$2:$C$13,2,FALSE),0) -> 11 | AC41: =+Y41*AB41*R41 -> 0 | AD41: =+AC41-X41 -> 0 | AE41: =IFERROR(AD41/AC41,0) -> 0
S42: =+Q42*R42 -> 0 | T42: 0 | U42: =S42*(1-T42) -> 0 | V42: EUR | W42: =IFERROR(VLOOKUP(V42,Curr!$B$2:$C$13,2,FALSE),0) -> 11 | X42: =U42*W42 -> 0 | Y42: =Q42 -> 0 | Z42: =+Y42*R42 -> 0 | AA42: EUR | AB42: =IFERROR(VLOOKUP(AA42,Curr!$B$2:$C$13,2,FALSE),0) -> 11 | AC42: =+Y42*AB42*R42 -> 0 | AD42: =+AC42-X42 -> 0 | AE42: =IFERROR(AD42/AC42,0) -> 0
S43: =+Q43*R43 -> 0 | T43: 0 | U43: =S43*(1-T43) -> 0 | V43: EUR | W43: =IFERROR(VLOOKUP(V43,Curr!$B$2:$C$13,2,FALSE),0) -> 11 | X43: =U43*W43 -> 0 | Y43: =Q43 -> 0 | Z43: =+Y43*R43 -> 0 | AA43: EUR | AB43: =IFERROR(VLOOKUP(AA43,Curr!$B$2:$C$13,2,FALSE),0) -> 11 | AC43: =+Y43*AB43*R43 -> 0 | AD43: =+AC43-X43 -> 0 | AE43: =IFERROR(AD43/AC43,0) -> 0
S44: =+Q44*R44 -> 0 | T44: 0 | U44: =S44*(1-T44) -> 0 | V44: EUR | W44: =IFERROR(VLOOKUP(V44,Curr!$B$2:$C$13,2,FALSE),0) -> 11 | X44: =U44*W44 -> 0 | Y44: =Q44 -> 0 | Z44: =+Y44*R44 -> 0 | AA44: EUR | AB44: =IFERROR(VLOOKUP(AA44,Curr!$B$2:$C$13,2,FALSE),0) -> 11 | AC44: =+Y44*AB44*R44 -> 0 | AD44: =+AC44-X44 -> 0 | AE44: =IFERROR(AD44/AC44,0) -> 0
S45: =+Q45*R45 -> 0 | T45: 0 | U45: =S45*(1-T45) -> 0 | V45: EUR | W45: =IFERROR(VLOOKUP(V45,Curr!$B$2:$C$13,2,FALSE),0) -> 11 | X45: =U45*W45 -> 0 | Y45: =Q45 -> 0 | Z45: =+Y45*R45 -> 0 | AA45: EUR | AB45: =IFERROR(VLOOKUP(AA45,Curr!$B$2:$C$13,2,FALSE),0) -> 11 | AC45: =+Y45*AB45*R45 -> 0 | AD45: =+AC45-X45 -> 0 | AE45: =IFERROR(AD45/AC45,0) -> 0
S46: =+Q46*R46 -> 0 | T46: 0 | U46: =S46*(1-T46) -> 0 | V46: EUR | W46: =IFERROR(VLOOKUP(V46,Curr!$B$2:$C$13,2,FALSE),0) -> 11 | X46: =U46*W46 -> 0 | Y46: =Q46 -> 0 | Z46: =+Y46*R46 -> 0 | AA46: EUR | AB46: =IFERROR(VLOOKUP(AA46,Curr!$B$2:$C$13,2,FALSE),0) -> 11 | AC46: =+Y46*AB46*R46 -> 0 | AD46: =+AC46-X46 -> 0 | AE46: =IFERROR(AD46/AC46,0) -> 0
S47: =+Q47*R47 -> 0 | T47: 0 | U47: =S47*(1-T47) -> 0 | V47: EUR | W47: =IFERROR(VLOOKUP(V47,Curr!$B$2:$C$13,2,FALSE),0) -> 11 | X47: =U47*W47 -> 0 | Y47: =Q47 -> 0 | Z47: =+Y47*R47 -> 0 | AA47: EUR | AB47: =IFERROR(VLOOKUP(AA47,Curr!$B$2:$C$13,2,FALSE),0) -> 11 | AC47: =+Y47*AB47*R47 -> 0 | AD47: =+AC47-X47 -> 0 | AE47: =IFERROR(AD47/AC47,0) -> 0
S48: =+Q48*R48 -> 0 | T48: 0 | U48: =S48*(1-T48) -> 0 | V48: EUR | W48: =IFERROR(VLOOKUP(V48,Curr!$B$2:$C$13,2,FALSE),0) -> 11 | X48: =U48*W48 -> 0 | Y48: =Q48 -> 0 | Z48: =+Y48*R48 -> 0 | AA48: EUR | AB48: =IFERROR(VLOOKUP(AA48,Curr!$B$2:$C$13,2,FALSE),0) -> 11 | AC48: =+Y48*AB48*R48 -> 0 | AD48: =+AC48-X48 -> 0 | AE48: =IFERROR(AD48/AC48,0) -> 0
S49: =+Q49*R49 -> 0 | T49: 0 | U49: =S49*(1-T49) -> 0 | V49: EUR | W49: =IFERROR(VLOOKUP(V49,Curr!$B$2:$C$13,2,FALSE),0) -> 11 | X49: =U49*W49 -> 0 | Y49: =Q49 -> 0 | Z49: =+Y49*R49 -> 0 | AA49: EUR | AB49: =IFERROR(VLOOKUP(AA49,Curr!$B$2:$C$13,2,FALSE),0) -> 11 | AC49: =+Y49*AB49*R49 -> 0 | AD49: =+AC49-X49 -> 0 | AE49: =IFERROR(AD49/AC49,0) -> 0
S50: =+Q50*R50 -> 0 | T50: 0 | U50: =S50*(1-T50) -> 0 | V50: EUR | W50: =IFERROR(VLOOKUP(V50,Curr!$B$2:$C$13,2,FALSE),0) -> 11 | X50: =U50*W50 -> 0 | Y50: =Q50 -> 0 | Z50: =+Y50*R50 -> 0 | AA50: EUR | AB50: =IFERROR(VLOOKUP(AA50,Curr!$B$2:$C$13,2,FALSE),0) -> 11 | AC50: =+Y50*AB50*R50 -> 0 | AD50: =+AC50-X50 -> 0 | AE50: =IFERROR(AD50/AC50,0) -> 0
B52: Totals | D52: x | E52: x | F52: x | G52: x | H52: x | I52: x | J52: x | K52: x | L52: x | M52: x | N52: x | O52: x | P52: x | Q52: x | R52: x | S52: x | T52: x | U52: x | V52: x | W52: x | X52: x | Y52: x | Z52: =SUM(Z7:Z50) -> 2798.0882 | AC52: =SUM(AC7:AC50) -> 30778.971 | AD52: =SUM(AD7:AD50) -> 4818.9706 | AE52: =IFERROR(AD52/AC52,0) -> 0.15656698 | AF52: =SUM(AF8:AF51) -> 0 | AG52: =SUM(AG8:AG51) -> 0 | AH52: =SUM(AH8:AH51) -> 0 | AI52: =SUM(AI8:AI51) -> 0 | AJ52: =SUM(AJ8:AJ51) -> 0
Y54: Fixed | Z54: =Z12 -> 2327.5
Y55: Variable | Z55: =Z9+Z20 -> 470.58824
Y56: Total | Z56: 2780
Y57: PP | Z57: =Z56/2 -> 1390
Y59: Ref | Z59: =Z56-Z60 -> 2780
Y60: NoRef | Z60: 0
Y62: Deposit | Z62: =Z56*0.3 -> 834
Y63: Rest | Z63: =Z56-Z62 -> 1946

Sheet 7D GTS
B1: Season: Summer
B2: Tour: https://booknordics.com/iceland/western-iceland/reykjavik/5-day-winter-minibus-tour-blue-ice-cave-snaefellsnes-golden-circle-south-coast-northern-lights
B3: Pax: 2
B4: Rooming: Double
B6: ID | C6: Day | D6: Type | E6: From date | F6: To date | G6: From time | H6: To time | I6: Supplier | J6: Travel element | K6: Manual booking? | L6: Status | M6: Comments | N6: Non-refundable | O6: Refundable | P6: URL | Q6: Gross P per unit | R6: Units | S6: Gross P | T6: Supp Comm | U6: Net P | V6: Supp curr | W6: X-rate | X6: Net P NOK | Y6: Sales P per unit | Z6: Price | AA6: Sales curr | AB6: X-rate | AC6: Sales P NOK tot | AD6: GP NOK | AE6: GP % | AF6: VAT25 | AG6: VAT15 | AH6: VAT12 | AI6: VAT0-D | AJ6: VAT0-I
C7: Day 1 | D7: Arrival | J7: Keflavik: Welcome to Iceland | Q7: 0 | R7: 0 | S7: =+Q7*R7 -> 0 | T7: 0 | U7: =S7*(1-T7) -> 0 | V7: EUR | W7: =IFERROR(VLOOKUP(V7,Curr!$B$2:$C$13,2,FALSE),0) -> 11 | X7: =U7*W7 -> 0 | Y7: =Q7 -> 0 | Z7: =+Y7*R7 -> 0 | AA7: EUR | AB7: =IFERROR(VLOOKUP(AA7,Curr!$B$2:$C$13,2,FALSE),0) -> 11 | AC7: =+Y7*AB7*R7 -> 0 | AD7: =+AC7-X7 -> 0 | AE7: =IFERROR(AD7/AC7,0) -> 0
C8: Day 1 | D8: Transfer | J8: Keflavik: Self transfer to your accommodaiton | Q8: 0 | R8: 0 | S8: =+Q8*R8 -> 0 | T8: 0 | U8: =S8*(1-T8) -> 0 | V8: EUR | W8: =IFERROR(VLOOKUP(V8,Curr!$B$2:$C$13,2,FALSE),0) -> 11 | X8: =U8*W8 -> 0 | Y8: =Q8 -> 0 | Z8: =+Y8*R8 -> 0 | AA8: EUR | AB8: =IFERROR(VLOOKUP(AA8,Curr!$B$2:$C$13,2,FALSE),0) -> 11 | AC8: =+Y8*AB8*R8 -> 0 | AD8: =+AC8-X8 -> 0 | AE8: =IFERROR(AD8/AC8,0) -> 0
C9: Day 1 | D9: Hotel | J9: Reykjavik: Check in to your accommodation for a 1 night stay - Centraly Located 3/4-star hotel - Standard room - breakfast included | Q9: 200 | R9: 1 | S9: =+Q9*R9 -> 200 | T9: 0 | U9: =S9*(1-T9) -> 200 | V9: EUR | W9: =IFERROR(VLOOKUP(V9,Curr!$B$2:$C$13,2,FALSE),0) -> 11 | X9: =U9*W9 -> 2200 | Y9: =Q9/0.85 -> 235.29412 | Z9: =+Y9*R9 -> 235.29412 | AA9: EUR | AB9: =IFERROR(VLOOKUP(AA9,Curr!$B$2:$C$13,2,FALSE),0) -> 11 | AC9: =+Y9*AB9*R9 -> 2588.2353 | AD9: =+AC9-X9 -> 388.23529 | AE9: =IFERROR(AD9/AC9,0) -> 0.15
C10: Day 1 | D10: Leisure | J10: Reykjavik: Spend the evening at leisure | Q10: 0 | R10: 0 | S10: =+Q10*R10 -> 0 | T10: 0 | U10: =S10*(1-T10) -> 0 | V10: EUR | W10: =IFERROR(VLOOKUP(V10,Curr!$B$2:$C$13,2,FALSE),0) -> 11 | X10: =U10*W10 -> 0 | Y10: =Q10 -> 0 | Z10: =+Y10*R10 -> 0 | AA10: EUR | AB10: =IFERROR(VLOOKUP(AA10,Curr!$B$2:$C$13,2,FALSE),0) -> 11 | AC10: =+Y10*AB10*R10 -> 0 | AD10: =+AC10-X10 -> 0 | AE10: =IFERROR(AD10/AC10,0) -> 0
S11: =+Q11*R11 -> 0 | T11: 0 | U11: =S11*(1-T11) -> 0 | V11: EUR | W11: =IFERROR(VLOOKUP(V11,Curr!$B$2:$C$13,2,FALSE),0) -> 11 | X11: =U11*W11 -> 0 | Y11: =Q11 -> 0 | Z11: =+Y11*R11 -> 0 | AA11: EUR | AB11: =IFERROR(VLOOKUP(AA11,Curr!$B$2:$C$13,2,FALSE),0) -> 11 | AC11: =+Y11*AB11*R11 -> 0 | AD11: =+AC11-X11 -> 0 | AE11: =IFERROR(AD11/AC11,0) -> 0
C12: Day 2 | D12: Activity | J12: Reykjavik: 5-Day Winter Minibus Tour | South Coast, Snæfellsnes, Golden Circle & More - Meeting point: Hotel Pick up - Time: Between 08:00 am and 8:30 am - On this 5-day tour, expore Borgarfjörður Valley, waterfalls, and Viking heritage sites. Discover the wonders of the Snæfellsnes Peninsula, with its lava fields, beaches, and the iconic Snæfellsjökull Glacier. Experience the Golden Circle's famous landmarks, such as Thingvellir National Park, Gullfoss Waterfall, and Geysir. Embark on thrilling adventures along the South Coast, including glacier hikes and visits to Jökulsárlón and the Blue Ice Cave. Includes: Pick-up/drop off in central Reykjavik, Professional, English-speaking guide, Hotel stays with breakfast and private bathroom, Travel in premum vehicle with WiFi on board, Northern Lights Hunt along the way, Small-group, local Iceland experience, Day 1: Borgarfjörður Valley and Waterfalls, Day 1: Viking Heritage of Western Iceland, Day 2: Explore Snaefellsnes Peninsula, Day 3: Iceland's famous Golden Circle, Day 4: South Coast & 3h Glacier Hike, Day 4: Helmet, harness, crampons, ice axe, Day 5: Explore Jökulsárlón & a Blue Ice Cave | P12: https://booknordics.com/iceland/western-iceland/reykjavik/5-day-winter-minibus-tour-blue-ice-cave-snaefellsnes-golden-circle-south-coast-northern-lights | Q12: 1510 | R12: 2 | S12: =+Q12*R12 -> 3020 | T12: 0.2 | U12: =S12*(1-T12) -> 2416 | V12: EUR | W12: =IFERROR(VLOOKUP(V12,Curr!$B$2:$C$13,2,FALSE),0) -> 11 | X12: =U12*W12 -> 26576 | Y12: =Q12*0.95 -> 1434.5 | Z12: =+Y12*R12 -> 2869 | AA12: EUR | AB12: =IFERROR(VLOOKUP(AA12,Curr!$B$2:$C$13,2,FALSE),0) -> 11 | AC12: =+Y12*AB12*R12 -> 31559 | AD12: =+AC12-X12 -> 4983 | AE12: =IFERROR(AD12/AC12,0) -> 0.15789474
C13: Day 2 | D13: Group Tour | J13: Day 1 - Borgarfjörður Valley, Waterfalls, and Viking Heritage - We start the tour in West Iceland. You will be picked up in the morning by a guide and a driver and you will be heading straight towards the mountain Esja, which overlooks Reykjavík. Driving along side it you will reach Hvalfjörður fjords, the name of it translates to “whale fjord”. You will enjoy the features of the area, towering snow capped mountains and open fields. You will be able to see an old abandoned naval base, which was occupied by the British during WWII. After Hvalfjörður you will head on to Borgarfjörður, a region filled with historical heritage, Viking sailors reached land and settled there after leaving their homeland.Reykholtsdalur valley is your next location, there you can learn all about the forces of Deildartunguhver, Europe’s most powerful hot spring. From there you will journey to the village of Reykholt, where Snorri Sturluson, the poet, lawmaker and historian used to live during the Middle ages. Snorri wrote many codices that are invaluable records of mythology and the Old Norse language. Not far from there are you will find two very different but equally beautiful waterfalls, Hraunsfossar and Barnafoss. Hraunfossar are a series of streams rushing through dark lava fields and Barnafoss, a bright blue stream speeding through a narrow ravine.You will then head to your accommodation for a restful sleep. Keep an eye out for the magical Aurora at night, especially if the sky is starry and clear. | Q13: 0 | R13: 0 | S13: =+Q13*R13 -> 0 | T13: 0 | U13: =S13*(1-T13) -> 0 | V13: EUR | W13: =IFERROR(VLOOKUP(V13,Curr!$B$2:$C$13,2,FALSE),0) -> 11 | X13: =U13*W13 -> 0 | Y13: =Q13 -> 0 | Z13: =+Y13*R13 -> 0 | AA13: EUR | AB13: =IFERROR(VLOOKUP(AA13,Curr!$B$2:$C$13,2,FALSE),0) -> 11 | AC13: =+Y13*AB13*R13 -> 0 | AD13: =+AC13-X13 -> 0 | AE13: =IFERROR(AD13/AC13,0) -> 0
S14: =+Q14*R14 -> 0 | T14: 0 | U14: =S14*(1-T14) -> 0 | V14: EUR | W14: =IFERROR(VLOOKUP(V14,Curr!$B$2:$C$13,2,FALSE),0) -> 11 | X14: =U14*W14 -> 0 | Y14: =Q14 -> 0 | Z14: =+Y14*R14 -> 0 | AA14: EUR | AB14: =IFERROR(VLOOKUP(AA14,Curr!$B$2:$C$13,2,FALSE),0) -> 11 | AC14: =+Y14*AB14*R14 -> 0 | AD14: =+AC14-X14 -> 0 | AE14: =IFERROR(AD14/AC14,0) -> 0
C15: Day 3 | D15: Group Tour | J15: Day 2 - Snaefellsnes Peninsula - Prepare to explore amazing things like, lava fields, dreamy waterfalls, dark caves, black and white beaches, historical locations and the mighty Snæfellsjökull Glacier of the west. The glacier played an important role in the novel Journey to the Centre of the Earth, by Jules Verne, where it was the opening point to a great underground journey. You will have a nice breakfast and then head out for an adventure where you will be exploring the underground. Once you have reached the Snæfellsnes Peninsula you will visit Gerðuberg Cliff, a large basalt column wall. Next you will be able to explore a white sand beach at Ytri-Tunga, which is unusual for Icelandic beaches, most of them have black sand. The sand in Ytri-Tunga is golden and the location is great for spotting seals.The village of Arnarstapi is your next destination, a small fishing village surrounded by basalt ravines and lava pillars. You can see old fisherman landing spots and you can follow a path leading you along the coast with the Atlantic Ocean waves crushing against Gatklettur arch rock. You will head to Djúpalónssandur, a black pebble beach, to get there you will trek through a unique field of lava pillars and rocks, a very special location, unlike anything else. When you reach the beach you can walk on the pebble shore and take in all the incredible features of the location.Afterwards, the iconic Kirkjufell mountain will welcome you with all of its unique features. As you may know, the mountain was featured in the popular series, Game of Thrones and has become one of Icelands most popular sites. On your way back to the capital, you will past Hraunsfjörður, a beautiful fjords surrounded by mountains covered in snow you will be able to see the dark lava field of Berserkjahraun, and your guide will give you some knowledge about the road’s construction.Remember to keep a look out for the magical sight in the sky when it gets dark, the Northern Lights with their unbelievable colours cant wait to put on a show for you. You then will reach your accommodation in Reykjavík in the evening where you can relax, that concludes your journey to West Iceland. | Q15: 0 | R15: 0 | S15: =+Q15*R15 -> 0 | T15: 0 | U15: =S15*(1-T15) -> 0 | V15: EUR | W15: =IFERROR(VLOOKUP(V15,Curr!$B$2:$C$13,2,FALSE),0) -> 11 | X15: =U15*W15 -> 0 | Y15: =Q15 -> 0 | Z15: =+Y15*R15 -> 0 | AA15: EUR | AB15: =IFERROR(VLOOKUP(AA15,Curr!$B$2:$C$13,2,FALSE),0) -> 11 | AC15: =+Y15*AB15*R15 -> 0 | AD15: =+AC15-X15 -> 0 | AE15: =IFERROR(AD15/AC15,0) -> 0
S16: =+Q16*R16 -> 0 | T16: 0 | U16: =S16*(1-T16) -> 0 | V16: EUR | W16: =IFERROR(VLOOKUP(V16,Curr!$B$2:$C$13,2,FALSE),0) -> 11 | X16: =U16*W16 -> 0 | Y16: =Q16 -> 0 | Z16: =+Y16*R16 -> 0 | AA16: EUR | AB16: =IFERROR(VLOOKUP(AA16,Curr!$B$2:$C$13,2,FALSE),0) -> 11 | AC16: =+Y16*AB16*R16 -> 0 | AD16: =+AC16-X16 -> 0 | AE16: =IFERROR(AD16/AC16,0) -> 0
C17: Day 4 | D17: Group Tour | J17: Day 3 - The Golden Circle - You will visit the famous Thingvellir National Park, Gullfoss Waterfall, Geysir and the surrounding Geothermal Area. In Thingvellir, Iceland’s first parliament was founded in the year 930 AD. Also, Thingvellir is a UNESCO World Heritage due to its visible tectonic plates on the surface. At Haukadalur Geothermal Area you'll see Strokkur erupting every five to ten minutes, and the original Geysir that has named all geysers worldwide. The Golden Circle has its name from Gullfoss, which means "The Golden Waterfall". Its water from the glacial river Hvítá, rushes down two tiers of a 32 meters fall. | Q17: 0 | R17: 0 | S17: =+Q17*R17 -> 0 | T17: 0 | U17: =S17*(1-T17) -> 0 | V17: EUR | W17: =IFERROR(VLOOKUP(V17,Curr!$B$2:$C$13,2,FALSE),0) -> 11 | X17: =U17*W17 -> 0 | Y17: =Q17 -> 0 | Z17: =+Y17*R17 -> 0 | AA17: EUR | AB17: =IFERROR(VLOOKUP(AA17,Curr!$B$2:$C$13,2,FALSE),0) -> 11 | AC17: =+Y17*AB17*R17 -> 0 | AD17: =+AC17-X17 -> 0 | AE17: =IFERROR(AD17/AC17,0) -> 0
S18: =+Q18*R18 -> 0 | T18: 0 | U18: =S18*(1-T18) -> 0 | V18: EUR | W18: =IFERROR(VLOOKUP(V18,Curr!$B$2:$C$13,2,FALSE),0) -> 11 | X18: =U18*W18 -> 0 | Y18: =Q18 -> 0 | Z18: =+Y18*R18 -> 0 | AA18: EUR | AB18: =IFERROR(VLOOKUP(AA18,Curr!$B$2:$C$13,2,FALSE),0) -> 11 | AC18: =+Y18*AB18*R18 -> 0 | AD18: =+AC18-X18 -> 0 | AE18: =IFERROR(AD18/AC18,0) -> 0
C19: Day 5 | D19: Group Tour | J19: Day 4- South Coast & Glacier Hike - The first stop is at Seljalandsfoss waterfall where you can walk behind the tumbling water flow and feel the vibrations of the water hitting the ground. Thirsty? Just open your mouth. Right next to it is the waterfall Gljúfrabúi which snugly tucked in a gorge hidden from most. Gljúfrabúi actually means Canyon Dweller in English. To reach the waterfall, you must first test your balance by bouncing on rocks lying in the river bed. A failure means instant foot wetness and a good laugh by your co-travellers. Skógafoss Prepare to meet the pearl of the South Coast, Skógafoss waterfall. Majestically tucked in a wide gorge, the waterfall tumbles down 60 metres from up above a cliff into a small river, producing a cloud of mist and spray that rainbows like to dance in during sunshine. Try to warm up for the glacier by running up the 527 steps to the top... Your guide will be timing you! Reynisfjara - Black Sand Beach. Heading further east, we visit the black sand beach of Reynisfjara where the Atlantic coastline presents massive waves hitting the unique basalt columns in the cliffs above the sand. Rock pillars in the water and the cliffs of Dýrhólaey are seen in the distance. Glacier Hike complete our perfect adventure we will hike an outlet glacier spawning from the one of the largest glaciers in the country. After meeting our highly trained glacier guides and strapping on our safety and glacier equipment, including helmets, harnesses, crampons and ice axes we hike on the ice for an hour and a half. A spectacular experience and opportunity to learn more about this breathtaking and increasingly rare natural phenomena. | Q19: 0 | R19: 0 | S19: =+Q19*R19 -> 0 | T19: 0 | U19: =S19*(1-T19) -> 0 | V19: EUR | W19: =IFERROR(VLOOKUP(V19,Curr!$B$2:$C$13,2,FALSE),0) -> 11 | X19: =U19*W19 -> 0 | Y19: =Q19 -> 0 | Z19: =+Y19*R19 -> 0 | AA19: EUR | AB19: =IFERROR(VLOOKUP(AA19,Curr!$B$2:$C$13,2,FALSE),0) -> 11 | AC19: =+Y19*AB19*R19 -> 0 | AD19: =+AC19-X19 -> 0 | AE19: =IFERROR(AD19/AC19,0) -> 0
S20: =+Q20*R20 -> 0 | T20: 0 | U20: =S20*(1-T20) -> 0 | V20: EUR | W20: =IFERROR(VLOOKUP(V20,Curr!$B$2:$C$13,2,FALSE),0) -> 11 | X20: =U20*W20 -> 0 | Y20: =Q20 -> 0 | Z20: =+Y20*R20 -> 0 | AA20: EUR | AB20: =IFERROR(VLOOKUP(AA20,Curr!$B$2:$C$13,2,FALSE),0) -> 11 | AC20: =+Y20*AB20*R20 -> 0 | AD20: =+AC20-X20 -> 0 | AE20: =IFERROR(AD20/AC20,0) -> 0
C21: Day 6 | D21: Group Tour | J21: Day 5 - Jökulsárlón & Blue Ice Cave - A 200m deep glacial lake fed by Breiðamerkurjökull, an outlet glacier of Europe’s largest glacier. Fed enormous icebergs all year round the lagoon is usually filled with ice that floats south. We walk alongside the glacier lagoon enjoying the magnificent views and dead silence of Icelandic nature. Diamond Beach On the other side of the road the icebergs from Jökulsárlón glacier lagoon float into the Atlantic Ocean where they are quickly thrown back to shore by the tide and winds. This black sand beach is full of smaller ice rocks in all shapes and sizes, sparkling like diamonds in the daylight. The ice itself comes in all shades of white and blue forming beautiful contrasts, guaranteed to make your Instagram account pop! And to make the experience even better we end with an Ice cave tour from Jökulsárlón, where you'll meet our guides, hop into our super jeep and take on an amazing journey up the glacier where the blue ice caves are. There you'll enter the unique phenomena which is the blue ice cave. What are you waiting for? Come and join us to check all the fun stuff we can do in the southern region, including glacier hiking! | Q21: 0 | R21: 0 | S21: =+Q21*R21 -> 0 | T21: 0 | U21: =S21*(1-T21) -> 0 | V21: EUR | W21: =IFERROR(VLOOKUP(V21,Curr!$B$2:$C$13,2,FALSE),0) -> 11 | X21: =U21*W21 -> 0 | Y21: =Q21 -> 0 | Z21: =+Y21*R21 -> 0 | AA21: EUR | AB21: =IFERROR(VLOOKUP(AA21,Curr!$B$2:$C$13,2,FALSE),0) -> 11 | AC21: =+Y21*AB21*R21 -> 0 | AD21: =+AC21-X21 -> 0 | AE21: =IFERROR(AD21/AC21,0) -> 0
C22: Day 6 | D22: Hotel | J22: Reykjavik: Check in to your accommodation for a 1 night stay - Centraly Located 3/4-star hotel - Standard room - breakfast included | Q22: 200 | R22: 1 | S22: =+Q22*R22 -> 200 | T22: 0 | U22: =S22*(1-T22) -> 200 | V22: EUR | W22: =IFERROR(VLOOKUP(V22,Curr!$B$2:$C$13,2,FALSE),0) -> 11 | X22: =U22*W22 -> 2200 | Y22: =Q22/0.85 -> 235.29412 | Z22: =+Y22*R22 -> 235.29412 | AA22: EUR | AB22: =IFERROR(VLOOKUP(AA22,Curr!$B$2:$C$13,2,FALSE),0) -> 11 | AC22: =+Y22*AB22*R22 -> 2588.2353 | AD22: =+AC22-X22 -> 388.23529 | AE22: =IFERROR(AD22/AC22,0) -> 0.15
C23: Day 6 | D23: Leisure | J23: Reykjavik: Spend the evening at leisure | Q23: 0 | R23: 0 | S23: =+Q23*R23 -> 0 | T23: 0 | U23: =S23*(1-T23) -> 0 | V23: EUR | W23: =IFERROR(VLOOKUP(V23,Curr!$B$2:$C$13,2,FALSE),0) -> 11 | X23: =U23*W23 -> 0 | Y23: =Q23 -> 0 | Z23: =+Y23*R23 -> 0 | AA23: EUR | AB23: =IFERROR(VLOOKUP(AA23,Curr!$B$2:$C$13,2,FALSE),0) -> 11 | AC23: =+Y23*AB23*R23 -> 0 | AD23: =+AC23-X23 -> 0 | AE23: =IFERROR(AD23/AC23,0) -> 0
S24: =+Q24*R24 -> 0 | T24: 0 | U24: =S24*(1-T24) -> 0 | V24: EUR | W24: =IFERROR(VLOOKUP(V24,Curr!$B$2:$C$13,2,FALSE),0) -> 11 | X24: =U24*W24 -> 0 | Y24: =Q24 -> 0 | Z24: =+Y24*R24 -> 0 | AA24: EUR | AB24: =IFERROR(VLOOKUP(AA24,Curr!$B$2:$C$13,2,FALSE),0) -> 11 | AC24: =+Y24*AB24*R24 -> 0 | AD24: =+AC24-X24 -> 0 | AE24: =IFERROR(AD24/AC24,0) -> 0
C25: Day 7 | D25: Transfer | J25: Reykjavik: Self transfer to Keflavik Airport | Q25: 0 | R25: 0 | S25: =+Q25*R25 -> 0 | T25: 0 | U25: =S25*(1-T25) -> 0 | V25: EUR | W25: =IFERROR(VLOOKUP(V25,Curr!$B$2:$C$13,2,FALSE),0) -> 11 | X25: =U25*W25 -> 0 | Y25: =Q25 -> 0 | Z25: =+Y25*R25 -> 0 | AA25: EUR | AB25: =IFERROR(VLOOKUP(AA25,Curr!$B$2:$C$13,2,FALSE),0) -> 11 | AC25: =+Y25*AB25*R25 -> 0 | AD25: =+AC25-X25 -> 0 | AE25: =IFERROR(AD25/AC25,0) -> 0
C26: Day 7 | D26: Departure | J26: Keflavik: Departure home | Q26: 0 | R26: 0 | S26: =+Q26*R26 -> 0 | T26: 0 | U26: =S26*(1-T26) -> 0 | V26: EUR | W26: =IFERROR(VLOOKUP(V26,Curr!$B$2:$C$13,2,FALSE),0) -> 11 | X26: =U26*W26 -> 0 | Y26: =Q26 -> 0 | Z26: =+Y26*R26 -> 0 | AA26: EUR | AB26: =IFERROR(VLOOKUP(AA26,Curr!$B$2:$C$13,2,FALSE),0) -> 11 | AC26: =+Y26*AB26*R26 -> 0 | AD26: =+AC26-X26 -> 0 | AE26: =IFERROR(AD26/AC26,0) -> 0
Q27: 0 | R27: 0 | S27: =+Q27*R27 -> 0 | T27: 0 | U27: =S27*(1-T27) -> 0 | V27: EUR | W27: =IFERROR(VLOOKUP(V27,Curr!$B$2:$C$13,2,FALSE),0) -> 11 | X27: =U27*W27 -> 0 | Y27: =Q27 -> 0 | Z27: =+Y27*R27 -> 0 | AA27: EUR | AB27: =IFERROR(VLOOKUP(AA27,Curr!$B$2:$C$13,2,FALSE),0) -> 11 | AC27: =+Y27*AB27*R27 -> 0 | AD27: =+AC27-X27 -> 0 | AE27: =IFERROR(AD27/AC27,0) -> 0
Q28: 0 | R28: 0 | S28: =+Q28*R28 -> 0 | T28: 0 | U28: =S28*(1-T28) -> 0 | V28: EUR | W28: =IFERROR(VLOOKUP(V28,Curr!$B$2:$C$13,2,FALSE),0) -> 11 | X28: =U28*W28 -> 0 | Y28: =Q28 -> 0 | Z28: =+Y28*R28 -> 0 | AA28: EUR | AB28: =IFERROR(VLOOKUP(AA28,Curr!$B$2:$C$13,2,FALSE),0) -> 11 | AC28: =+Y28*AB28*R28 -> 0 | AD28: =+AC28-X28 -> 0 | AE28: =IFERROR(AD28/AC28,0) -> 0
C29: Day 1 | D29: Transfer package | J29: Keflavik: Private transfer to your accommodaiton | Q29: 160 | R29: 0 | S29: =+Q29*R29 -> 0 | T29: 0.2 | U29: =S29*(1-T29) -> 0 | V29: EUR | W29: =IFERROR(VLOOKUP(V29,Curr!$B$2:$C$13,2,FALSE),0) -> 11 | X29: =U29*W29 -> 0 | Y29: =Q29 -> 160 | Z29: =+Y29*R29 -> 0 | AA29: EUR | AB29: =IFERROR(VLOOKUP(AA29,Curr!$B$2:$C$13,2,FALSE),0) -> 11 | AC29: =+Y29*AB29*R29 -> 0 | AD29: =+AC29-X29 -> 0 | AE29: =IFERROR(AD29/AC29,0) -> 0
C30: Day 1 | D30: Transfer package | J30: Keflavik: Airport Shuttle Bus transfer to your accommodaiton | Q30: 39 | R30: 0 | S30: =+Q30*R30 -> 0 | T30: 0.2 | U30: =S30*(1-T30) -> 0 | V30: EUR | W30: =IFERROR(VLOOKUP(V30,Curr!$B$2:$C$13,2,FALSE),0) -> 11 | X30: =U30*W30 -> 0 | Y30: =Q30 -> 39 | Z30: =+Y30*R30 -> 0 | AA30: EUR | AB30: =IFERROR(VLOOKUP(AA30,Curr!$B$2:$C$13,2,FALSE),0) -> 11 | AC30: =+Y30*AB30*R30 -> 0 | AD30: =+AC30-X30 -> 0 | AE30: =IFERROR(AD30/AC30,0) -> 0
C31: Day 7 | D31: Transfer package | J31: Reykjavik: Private transfer to Keflavik Airport | Q31: 160 | R31: 0 | S31: =+Q31*R31 -> 0 | T31: 0.2 | U31: =S31*(1-T31) -> 0 | V31: EUR | W31: =IFERROR(VLOOKUP(V31,Curr!$B$2:$C$13,2,FALSE),0) -> 11 | X31: =U31*W31 -> 0 | Y31: =Q31 -> 160 | Z31: =+Y31*R31 -> 0 | AA31: EUR | AB31: =IFERROR(VLOOKUP(AA31,Curr!$B$2:$C$13,2,FALSE),0) -> 11 | AC31: =+Y31*AB31*R31 -> 0 | AD31: =+AC31-X31 -> 0 | AE31: =IFERROR(AD31/AC31,0) -> 0
C32: Day 7 | D32: Transfer package | J32: Reykjavik: Airport Shuttle Bus transfer to Keflavik Airport | Q32: 39 | R32: 0 | S32: =+Q32*R32 -> 0 | T32: 0.2 | U32: =S32*(1-T32) -> 0 | V32: EUR | W32: =IFERROR(VLOOKUP(V32,Curr!$B$2:$C$13,2,FALSE),0) -> 11 | X32: =U32*W32 -> 0 | Y32: =Q32 -> 39 | Z32: =+Y32*R32 -> 0 | AA32: EUR | AB32: =IFERROR(VLOOKUP(AA32,Curr!$B$2:$C$13,2,FALSE),0) -> 11 | AC32: =+Y32*AB32*R32 -> 0 | AD32: =+AC32-X32 -> 0 | AE32: =IFERROR(AD32/AC32,0) -> 0
S33: =+Q33*R33 -> 0 | T33: 0 | U33: =S33*(1-T33) -> 0 | V33: EUR | W33: =IFERROR(VLOOKUP(V33,Curr!$B$2:$C$13,2,FALSE),0) -> 11 | X33: =U33*W33 -> 0 | Y33: =Q33 -> 0 | Z33: =+Y33*R33 -> 0 | AA33: EUR | AB33: =IFERROR(VLOOKUP(AA33,Curr!$B$2:$C$13,2,FALSE),0) -> 11 | AC33: =+Y33*AB33*R33 -> 0 | AD33: =+AC33-X33 -> 0 | AE33: =IFERROR(AD33/AC33,0) -> 0
S34: =+Q34*R34 -> 0 | T34: 0 | U34: =S34*(1-T34) -> 0 | V34: EUR | W34: =IFERROR(VLOOKUP(V34,Curr!$B$2:$C$13,2,FALSE),0) -> 11 | X34: =U34*W34 -> 0 | Y34: =Q34 -> 0 | Z34: =+Y34*R34 -> 0 | AA34: EUR | AB34: =IFERROR(VLOOKUP(AA34,Curr!$B$2:$C$13,2,FALSE),0) -> 11 | AC34: =+Y34*AB34*R34 -> 0 | AD34: =+AC34-X34 -> 0 | AE34: =IFERROR(AD34/AC34,0) -> 0
C35: Day 1 | D35: Activity Upgrade | J35: Reykjavík: City Walking Tour - Time: 2:00 pm - 5:00 pm - Meeting point: Hallgrímskirkja, Hallgrimstorgi 1 - Includes: Professional, English-speaking guide - Highlights: Hallgrímskirkja, All the major landmarks, Hidden street art & local corners, Iceland in a nutshell | P35: https://booknordics.com/iceland/western-iceland/reykjavik/reykjavik-walking-tour-small-group-citywalk | Q35: 37 | R35: 0 | S35: =+Q35*R35 -> 0 | T35: 0.2 | U35: =S35*(1-T35) -> 0 | V35: EUR | W35: =IFERROR(VLOOKUP(V35,Curr!$B$2:$C$13,2,FALSE),0) -> 11 | X35: =U35*W35 -> 0 | Y35: =Q35 -> 37 | Z35: =+Y35*R35 -> 0 | AA35: EUR | AB35: =IFERROR(VLOOKUP(AA35,Curr!$B$2:$C$13,2,FALSE),0) -> 11 | AC35: =+Y35*AB35*R35 -> 0 | AD35: =+AC35-X35 -> 0 | AE35: =IFERROR(AD35/AC35,0) -> 0
C36: Day 3 | D36: Activity Upgrade | J36: Day 5: Boat Ride at Jökulsárlón | Q36: 50 | R36: 0 | S36: =+Q36*R36 -> 0 | T36: 0 | U36: =S36*(1-T36) -> 0 | V36: EUR | W36: =IFERROR(VLOOKUP(V36,Curr!$B$2:$C$13,2,FALSE),0) -> 11 | X36: =U36*W36 -> 0 | Y36: =Q36/0.8 -> 62.5 | Z36: =+Y36*R36 -> 0 | AA36: EUR | AB36: =IFERROR(VLOOKUP(AA36,Curr!$B$2:$C$13,2,FALSE),0) -> 11 | AC36: =+Y36*AB36*R36 -> 0 | AD36: =+AC36-X36 -> 0 | AE36: =IFERROR(AD36/AC36,0) -> 0
