Workbook

Sheet Curr
C1: NOK
B2: EUR | C2: 11
B3: SEK | C3: 1.02
B4: DKK | C4: 1.5
B5: ISK | C5: 0.075
B6: NOK | C6: 1
B7: USD | C7: 10.6

Sheet General
B2: Dates:
B3: Pax:
B4: Rooming:
B6: ID | C6: Day | D6: Type | E6: From date | F6: To date | G6: From time | H6: To time | I6: Supplier | J6: Travel element | K6: Manual booking? | L6: Status | M6: Comments | N6: Non-refundable | O6: Refundable | P6: URL | Q6: Gross P per unit | R6: Units | S6: Gross P | T6: Supp Comm | U6: Net P | V6: Supp curr | W6: X-rate | X6: Net P NOK | Y6: Sales P per unit | Z6: Price | AA6: Sales curr | AB6: X-rate2 | AC6: Sales P NOK tot | AD6: GP NOK | AE6: GP % | AF6: VAT25 | AG6: VAT15 | AH6: VAT12 | AI6: VAT0-D | AJ6: VAT0-I
B7: FI | D7: Arrival | J7: Helsinki: Welcome to Finland | Q7: 0 | R7: 0 | S7: =+Q7*R7 -> 0 | T7: 0 | U7: =S7*(1-T7) -> 0 | V7: EUR | W7: =IFERROR(VLOOKUP(V7,Curr!$B$2:$C$13,2,FALSE),0) -> 11 | X7: =U7*W7 -> 0 | Y7: =Q7 -> 0 | Z7: =+Y7*R7 -> 0 | AA7: EUR | AB7: =IFERROR(VLOOKUP(AA7,Curr!$B$2:$C$13,2,FALSE),0) -> 11 | AC7: =+Y7*AB7*R7 -> 0 | AD7: =+AC7-X7 -> 0 | AE7: =IFERROR(AD7/AC7,0) -> 0
B8: FI | D8: Departure | J8: Helsinki: Departure home | Q8: 0 | R8: 0 | S8: =+Q8*R8 -> 0 | T8: 0 | U8: =S8*(1-T8) -> 0 | V8: EUR | W8: =IFERROR(VLOOKUP(V8,Curr!$B$2:$C$13,2,FALSE),0) -> 11 | X8: =U8*W8 -> 0 | Y8: =Q8 -> 0 | Z8: =+Y8*R8 -> 0 | AA8: EUR | AB8: =IFERROR(VLOOKUP(AA8,Curr!$B$2:$C$13,2,FALSE),0) -> 11 | AC8: =+Y8*AB8*R8 -> 0 | AD8: =+AC8-X8 -> 0 | AE8: =IFERROR(AD8/AC8,0) -> 0
B9: FI | D9: Leisure | J9: Helsinki: Spend time at leisure | Q9: 0 | R9: 0 | S9: =+Q9*R9 -> 0 | T9: 0 | U9: =S9*(1-T9) -> 0 | V9: EUR | W9: =IFERROR(VLOOKUP(V9,Curr!$B$2:$C$13,2,FALSE),0) -> 11 | X9: =U9*W9 -> 0 | Y9: =Q9 -> 0 | Z9: =+Y9*R9 -> 0 | AA9: EUR | AB9: =IFERROR(VLOOKUP(AA9,Curr!$B$2:$C$13,2,FALSE),0) -> 11 | AC9: =+Y9*AB9*R9 -> 0 | AD9: =+AC9-X9 -> 0 | AE9: =IFERROR(AD9/AC9,0) -> 0
B10: FI | D10: Arrival | J10: Rovaniemi: Welcome to Finland | Q10: 0 | R10: 0 | S10: =+Q10*R10 -> 0 | T10: 0 | U10: =S10*(1-T10) -> 0 | V10: EUR | W10: =IFERROR(VLOOKUP(V10,Curr!$B$2:$C$13,2,FALSE),0) -> 11 | X10: =U10*W10 -> 0 | Y10: =Q10 -> 0 | Z10: =+Y10*R10 -> 0 | AA10: EUR | AB10: =IFERROR(VLOOKUP(AA10,Curr!$B$2:$C$13,2,FALSE),0) -> 11 | AC10: =+Y10*AB10*R10 -> 0 | AD10: =+AC10-X10 -> 0 | AE10: =IFERROR(AD10/AC10,0) -> 0
B11: FI | D11: Departure | J11: Rovaniemi: Departure home | Q11: 0 | R11: 0 | S11: =+Q11*R11 -> 0 | T11: 0 | U11: =S11*(1-T11) -> 0 | V11: EUR | W11: =IFERROR(VLOOKUP(V11,Curr!$B$2:$C$13,2,FALSE),0) -> 11 | X11: =U11*W11 -> 0 | Y11: =Q11 -> 0 | Z11: =+Y11*R11 -> 0 | AA11: EUR | AB11: =IFERROR(VLOOKUP(AA11,Curr!$B$2:$C$13,2,FALSE),0) -> 11 | AC11: =+Y11*AB11*R11 -> 0 | AD11: =+AC11-X11 -> 0 | AE11: =IFERROR(AD11/AC11,0) -> 0
B12: FI | D12: Leisure | J12: Rovaniemi: Spend time at leisure | Q12: 0 | R12: 0 | S12: =+Q12*R12 -> 0 | T12: 0 | U12: =S12*(1-T12) -> 0 | V12: EUR | W12: =IFERROR(VLOOKUP(V12,Curr!$B$2:$C$13,2,FALSE),0) -> 11 | X12: =U12*W12 -> 0 | Y12: =Q12 -> 0 | Z12: =+Y12*R12 -> 0 | AA12: EUR | AB12: =IFERROR(VLOOKUP(AA12,Curr!$B$2:$C$13,2,FALSE),0) -> 11 | AC12: =+Y12*AB12*R12 -> 0 | AD12: =+AC12-X12 -> 0 | AE12: =IFERROR(AD12/AC12,0) -> 0
B13: FI | D13: Arrival | J13: Turku: Welcome to Finland | Q13: 0 | R13: 0 | S13: =+Q13*R13 -> 0 | T13: 0 | U13: =S13*(1-T13) -> 0 | V13: EUR | W13: =IFERROR(VLOOKUP(V13,Curr!$B$2:$C$13,2,FALSE),0) -> 11 | X13: =U13*W13 -> 0 | Y13: =Q13 -> 0 | Z13: =+Y13*R13 -> 0 | AA13: EUR | AB13: =IFERROR(VLOOKUP(AA13,Curr!$B$2:$C$13,2,FALSE),0) -> 11 | AC13: =+Y13*AB13*R13 -> 0 | AD13: =+AC13-X13 -> 0 | AE13: =IFERROR(AD13/AC13,0) -> 0
B14: FI | D14: Departure | J14: Turku: Departure home | Q14: 0 | R14: 0 | S14: =+Q14*R14 -> 0 | T14: 0 | U14: =S14*(1-T14) -> 0 | V14: EUR | W14: =IFERROR(VLOOKUP(V14,Curr!$B$2:$C$13,2,FALSE),0) -> 11 | X14: =U14*W14 -> 0 | Y14: =Q14 -> 0 | Z14: =+Y14*R14 -> 0 | AA14: EUR | AB14: =IFERROR(VLOOKUP(AA14,Curr!$B$2:$C$13,2,FALSE),0) -> 11 | AC14: =+Y14*AB14*R14 -> 0 | AD14: =+AC14-X14 -> 0 | AE14: =IFERROR(AD14/AC14,0) -> 0
B15: FI | D15: Leisure | J15: Turku: Spend time at leisure | Q15: 0 | R15: 0 | S15: =+Q15*R15 -> 0 | T15: 0 | U15: =S15*(1-T15) -> 0 | V15: EUR | W15: =IFERROR(VLOOKUP(V15,Curr!$B$2:$C$13,2,FALSE),0) -> 11 | X15: =U15*W15 -> 0 | Y15: =Q15 -> 0 | Z15: =+Y15*R15 -> 0 | AA15: EUR | AB15: =IFERROR(VLOOKUP(AA15,Curr!$B$2:$C$13,2,FALSE),0) -> 11 | AC15: =+Y15*AB15*R15 -> 0 | AD15: =+AC15-X15 -> 0 | AE15: =IFERROR(AD15/AC15,0) -> 0
B16: FI | D16: Arrival | J16: Tampere: Welcome to Finland | Q16: 0 | R16: 0 | S16: =+Q16*R16 -> 0 | T16: 0 | U16: =S16*(1-T16) -> 0 | V16: EUR | W16: =IFERROR(VLOOKUP(V16,Curr!$B$2:$C$13,2,FALSE),0) -> 11 | X16: =U16*W16 -> 0 | Y16: =Q16 -> 0 | Z16: =+Y16*R16 -> 0 | AA16: EUR | AB16: =IFERROR(VLOOKUP(AA16,Curr!$B$2:$C$13,2,FALSE),0) -> 11 | AC16: =+Y16*AB16*R16 -> 0 | AD16: =+AC16-X16 -> 0 | AE16: =IFERROR(AD16/AC16,0) -> 0
B17: FI | D17: Departure | J17: Tampere: Departure home | Q17: 0 | R17: 0 | S17: =+Q17*R17 -> 0 | T17: 0 | U17: =S17*(1-T17) -> 0 | V17: EUR | W17: =IFERROR(VLOOKUP(V17,Curr!$B$2:$C$13,2,FALSE),0) -> 11 | X17: =U17*W17 -> 0 | Y17: =Q17 -> 0 | Z17: =+Y17*R17 -> 0 | AA17: EUR | AB17: =IFERROR(VLOOKUP(AA17,Curr!$B$2:$C$13,2,FALSE),0) -> 11 | AC17: =+Y17*AB17*R17 -> 0 | AD17: =+AC17-X17 -> 0 | AE17: =IFERROR(AD17/AC17,0) -> 0
B18: FI | D18: Leisure | J18: Tampere: Spend time at leisure | Q18: 0 | R18: 0 | S18: =+Q18*R18 -> 0 | T18: 0 | U18: =S18*(1-T18) -> 0 | V18: EUR | W18: =IFERROR(VLOOKUP(V18,Curr!$B$2:$C$13,2,FALSE),0) -> 11 | X18: =U18*W18 -> 0 | Y18: =Q18 -> 0 | Z18: =+Y18*R18 -> 0 | AA18: EUR | AB18: =IFERROR(VLOOKUP(AA18,Curr!$B$2:$C$13,2,FALSE),0) -> 11 | AC18: =+Y18*AB18*R18 -> 0 | AD18: =+AC18-X18 -> 0 | AE18: =IFERROR(AD18/AC18,0) -> 0
... B1254: DK | D1254: Leisure | J1254: Aakirkeby: Spend time at leisure | Q1254: 0 | R1254: 0 | S1254: =+Q1254*R1254 -> 0 | T1254: 0 | U1254: =S1254*(1-T1254) -> 0 | V1254: EUR | W1254: =IFERROR(VLOOKUP(V1254,Curr!$B$2:$C$13,2,FALSE),0) -> 11 | X1254: =U1254*W1254 -> 0 | Y1254: =Q1254 -> 0 | Z1254: =+Y1254*R1254 -> 0 | AA1254: EUR | AB1254: =IFERROR(VLOOKUP(AA1254,Curr!$B$2:$C$13,2,FALSE),0) -> 11 | AC1254: =+Y1254*AB1254*R1254 -> 0 | AD1254: =+AC1254-X1254 -> 0 | AE1254: =IFERROR(AD1254/AC1254,0) -> 0

Sheet Hotels
B2: Dates:
B3: Pax:
B4: Rooming:
B6: ID | C6: Day | D6: Type | E6: From date | F6: To date | G6: From time | H6: To time | I6: Supplier | J6: Travel element | K6: Manual booking? | L6: Status | M6: Comments | N6: Non-refundable | O6: Refundable | P6: URL | Q6: Gross P per unit | R6: Units | S6: Gross P | T6: Supp Comm | U6: Net P | V6: Supp curr | W6: X-rate | X6: Net P NOK | Y6: Sales P per unit | Z6: Price | AA6: Sales curr | AB6: X-rate2 | AC6: Sales P NOK tot | AD6: GP NOK | AE6: GP % | AF6: VAT25 | AG6: VAT15 | AH6: VAT12 | AI6: VAT0-D | AJ6: VAT0-I
B7: FI | D7: Hotel | J7: Helsinki: Check in to your accommodation for a X night stay - Hotel - Room - Bed - Breakfast included | Q7: 0 | R7: 0 | S7: =+Q7*R7 -> 0 | T7: 0 | U7: =S7*(1-T7) -> 0 | V7: EUR | W7: =IFERROR(VLOOKUP(V7,Curr!$B$2:$C$13,2,FALSE),0) -> 11 | X7: =U7*W7 -> 0 | Y7: =Q7/0.8 -> 0 | Z7: =+Y7*R7 -> 0 | AA7: EUR | AB7: =IFERROR(VLOOKUP(AA7,Curr!$B$2:$C$13,2,FALSE),0) -> 11 | AC7: =+Y7*AB7*R7 -> 0 | AD7: =+AC7-X7 -> 0 | AE7: =IFERROR(AD7/AC7,0) -> 0
B8: FI | D8: Hotel | J8: Helsinki: Check in to your accommodation for a X night stay - Hotel Arthur - Standard Room - Double/Twin Bed - Breakfast included | P8: https://www.ratehawk.com/hotel/finland/helsinki/mid7593355/hotel_arthur/?q=1443&dates=18.12.2026-19.12.2026&guests=1and14&meal_types=breakfast.halfBoard.fullBoard.allInclusive&payment=freecancellation&price=one&room=s-4c978903-d37c-5b78-8635-e8e17aeaccb6&serp_price=hotel_arthur.103.EUR.sr-019f85ad-99c9-75bd-97e1-20ea862313f2 | Q8: 110 | R8: 0 | S8: =+Q8*R8 -> 0 | T8: 0 | U8: =S8*(1-T8) -> 0 | V8: EUR | W8: =IFERROR(VLOOKUP(V8,Curr!$B$2:$C$13,2,FALSE),0) -> 11 | X8: =U8*W8 -> 0 | Y8: =Q8/0.8 -> 137.5 | Z8: =+Y8*R8 -> 0 | AA8: EUR | AB8: =IFERROR(VLOOKUP(AA8,Curr!$B$2:$C$13,2,FALSE),0) -> 11 | AC8: =+Y8*AB8*R8 -> 0 | AD8: =+AC8-X8 -> 0 | AE8: =IFERROR(AD8/AC8,0) -> 0
B9: FI | D9: Hotel | J9: Helsinki: Check in to your accommodation for a X night stay - Scandic Grand Marina Hotel - Standard Room - Double/Twin Bed - Breakfast included | P9: https://www.ratehawk.com/hotel/finland/helsinki/mid7594190/scandic_grand_marina/?dates=18.12.2026-19.12.2026&guests=1and14&meal_types=breakfast.halfBoard.fullBoard.allInclusive&payment=freecancellation&price=one&q=1443&room=s-ae0e9f27-be6c-50c5-a5fb-5c8d4489da01&serp_price=scandic_grand_marina.117.EUR.sr-019f85ad-9a17-74a4-af52-f491a6422915 | Q9: 130 | R9: 0 | S9: =+Q9*R9 -> 0 | T9: 0 | U9: =S9*(1-T9) -> 0 | V9: EUR | W9: =IFERROR(VLOOKUP(V9,Curr!$B$2:$C$13,2,FALSE),0) -> 11 | X9: =U9*W9 -> 0 | Y9: =Q9/0.8 -> 162.5 | Z9: =+Y9*R9 -> 0 | AA9: EUR | AB9: =IFERROR(VLOOKUP(AA9,Curr!$B$2:$C$13,2,FALSE),0) -> 11 | AC9: =+Y9*AB9*R9 -> 0 | AD9: =+AC9-X9 -> 0 | AE9: =IFERROR(AD9/AC9,0) -> 0
B10: FI | D10: Hotel | J10: Helsinki: Check in to your accommodation for a X night stay - Radisson Blu Royal - Standard Room - Double/Twin Bed - Breakfast included | P10: https://www.ratehawk.com/hotel/finland/helsinki/mid7593528/radisson_blu_royal_hotel_2/?q=1443&dates=18.12.2026-19.12.2026&guests=1and14&meal_types=breakfast.halfBoard.fullBoard.allInclusive&payment=freecancellation&price=one&room=s-6357a1f9-2246-5e2d-8197-57a7b4758b56&serp_price=radisson_blu_royal_hotel_2.127.EUR.sr-019f85ad-999d-737c-a93e-76852575a6d0 | Q10: 150 | R10: 0 | S10: =+Q10*R10 -> 0 | T10: 0 | U10: =S10*(1-T10) -> 0 | V10: EUR | W10: =IFERROR(VLOOKUP(V10,Curr!$B$2:$C$13,2,FALSE),0) -> 11 | X10: =U10*W10 -> 0 | Y10: =Q10/0.8 -> 187.5 | Z10: =+Y10*R10 -> 0 | AA10: EUR | AB10: =IFERROR(VLOOKUP(AA10,Curr!$B$2:$C$13,2,FALSE),0) -> 11 | AC10: =+Y10*AB10*R10 -> 0 | AD10: =+AC10-X10 -> 0 | AE10: =IFERROR(AD10/AC10,0) -> 0
B11: FI | D11: Hotel | J11: Helsinki: Check in to your accommodation for a X night stay - Lapland Hotels Bulevardi - Standard Room - Double/Twin Bed - Breakfast included | P11: https://www.ratehawk.com/hotel/finland/helsinki/mid8922586/lapland_hotels_bulevardi/?q=1443&dates=18.12.2026-19.12.2026&guests=1and14&meal_types=breakfast.halfBoard.fullBoard.allInclusive&payment=freecancellation&price=one&room=s-59505059-71d0-5e15-86cb-f22a7c7af008&serp_price=lapland_hotels_bulevardi.195.EUR.sr-019f85ad-95da-7247-993e-14193d9e981d&stars=5 | Q11: 220 | R11: 0 | S11: =+Q11*R11 -> 0 | T11: 0 | U11: =S11*(1-T11) -> 0 | V11: EUR | W11: =IFERROR(VLOOKUP(V11,Curr!$B$2:$C$13,2,FALSE),0) -> 11 | X11: =U11*W11 -> 0 | Y11: =Q11/0.8 -> 275 | Z11: =+Y11*R11 -> 0 | AA11: EUR | AB11: =IFERROR(VLOOKUP(AA11,Curr!$B$2:$C$13,2,FALSE),0) -> 11 | AC11: =+Y11*AB11*R11 -> 0 | AD11: =+AC11-X11 -> 0 | AE11: =IFERROR(AD11/AC11,0) -> 0
B12: FI | D12: Hotel | J12: Rovaniemi: Check in to your accommodation for a X night stay - Hotel - Room - Bed - Breakfast included | Q12: 0 | R12: 0 | S12: =+Q12*R12 -> 0 | T12: 0 | U12: =S12*(1-T12) -> 0 | V12: EUR | W12: =IFERROR(VLOOKUP(V12,Curr!$B$2:$C$13,2,FALSE),0) -> 11 | X12: =U12*W12 -> 0 | Y12: =Q12/0.8 -> 0 | Z12: =+Y12*R12 -> 0 | AA12: EUR | AB12: =IFERROR(VLOOKUP(AA12,Curr!$B$2:$C$13,2,FALSE),0) -> 11 | AC12: =+Y12*AB12*R12 -> 0 | AD12: =+AC12-X12 -> 0 | AE12: =IFERROR(AD12/AC12,0) -> 0
B13: FI | D13: Hotel | J13: Rovaniemi: Check in to your accommodation for a X night stay - Arctic City Hotel - Standard Room - Double/Twin Bed - Breakfast included | Q13: =166+166 -> 332 | R13: 0 | S13: =+Q13*R13 -> 0 | T13: 0 | U13: =S13*(1-T13) -> 0 | V13: EUR | W13: =IFERROR(VLOOKUP(V13,Curr!$B$2:$C$13,2,FALSE),0) -> 11 | X13: =U13*W13 -> 0 | Y13: =Q13/0.8 -> 415 | Z13: =+Y13*R13 -> 0 | AA13: EUR | AB13: =IFERROR(VLOOKUP(AA13,Curr!$B$2:$C$13,2,FALSE),0) -> 11 | AC13: =+Y13*AB13*R13 -> 0 | AD13: =+AC13-X13 -> 0 | AE13: =IFERROR(AD13/AC13,0) -> 0
B14: FI | D14: Hotel | J14: Rovaniemi: Check in to your accommodation for a X night stay - Arctic Light Hotel - Arctic Room -Double/Twin Bed - Breakfast included | Q14: =218+218 -> 436 | R14: 0 | S14: =+Q14*R14 -> 0 | T14: 0 | U14: =S14*(1-T14) -> 0 | V14: EUR | W14: =IFERROR(VLOOKUP(V14,Curr!$B$2:$C$13,2,FALSE),0) -> 11 | X14: =U14*W14 -> 0 | Y14: =Q14/0.8 -> 545 | Z14: =+Y14*R14 -> 0 | AA14: EUR | AB14: =IFERROR(VLOOKUP(AA14,Curr!$B$2:$C$13,2,FALSE),0) -> 11 | AC14: =+Y14*AB14*R14 -> 0 | AD14: =+AC14-X14 -> 0 | AE14: =IFERROR(AD14/AC14,0) -> 0
B15: FI | D15: Hotel | J15: Rovaniemi: Check in to your accommodation for a X night stay - Hotel - Room - Bed - Breakfast included | Q15: 0 | R15: 0 | S15: =+Q15*R15 -> 0 | T15: 0 | U15: =S15*(1-T15) -> 0 | V15: EUR | W15: =IFERROR(VLOOKUP(V15,Curr!$B$2:$C$13,2,FALSE),0) -> 11 | X15: =U15*W15 -> 0 | Y15: =Q15/0.8 -> 0 | Z15: =+Y15*R15 -> 0 | AA15: EUR | AB15: =IFERROR(VLOOKUP(AA15,Curr!$B$2:$C$13,2,FALSE),0) -> 11 | AC15: =+Y15*AB15*R15 -> 0 | AD15: =+AC15-X15 -> 0 | AE15: =IFERROR(AD15/AC15,0) -> 0
B16: FI | D16: Hotel | J16: Rovaniemi: Check in to your accommodation for a X night stay - Hotel - Room - Bed - Breakfast included | Q16: 0 | R16: 0 | S16: =+Q16*R16 -> 0 | T16: 0 | U16: =S16*(1-T16) -> 0 | V16: EUR | W16: =IFERROR(VLOOKUP(V16,Curr!$B$2:$C$13,2,FALSE),0) -> 11 | X16: =U16*W16 -> 0 | Y16: =Q16/0.8 -> 0 | Z16: =+Y16*R16 -> 0 | AA16: EUR | AB16: =IFERROR(VLOOKUP(AA16,Curr!$B$2:$C$13,2,FALSE),0) -> 11 | AC16: =+Y16*AB16*R16 -> 0 | AD16: =+AC16-X16 -> 0 | AE16: =IFERROR(AD16/AC16,0) -> 0
B17: FI | D17: Hotel | J17: Turku: Check in to your accommodation for a X night stay - Hotel - Room - Bed - Breakfast included | Q17: 0 | R17: 0 | S17: =+Q17*R17 -> 0 | T17: 0 | U17: =S17*(1-T17) -> 0 | V17: EUR | W17: =IFERROR(VLOOKUP(V17,Curr!$B$2:$C$13,2,FALSE),0) -> 11 | X17: =U17*W17 -> 0 | Y17: =Q17/0.8 -> 0 | Z17: =+Y17*R17 -> 0 | AA17: EUR | AB17: =IFERROR(VLOOKUP(AA17,Curr!$B$2:$C$13,2,FALSE),0) -> 11 | AC17: =+Y17*AB17*R17 -> 0 | AD17: =+AC17-X17 -> 0 | AE17: =IFERROR(AD17/AC17,0) -> 0
B18: FI | D18: Hotel | J18: Tampere: Check in to your accommodation for a X night stay - Hotel - Room - Bed - Breakfast included | Q18: 0 | R18: 0 | S18: =+Q18*R18 -> 0 | T18: 0 | U18: =S18*(1-T18) -> 0 | V18: EUR | W18: =IFERROR(VLOOKUP(V18,Curr!$B$2:$C$13,2,FALSE),0) -> 11 | X18: =U18*W18 -> 0 | Y18: =Q18/0.8 -> 0 | Z18: =+Y18*R18 -> 0 | AA18: EUR | AB18: =IFERROR(VLOOKUP(AA18,Curr!$B$2:$C$13,2,FALSE),0) -> 11 | AC18: =+Y18*AB18*R18 -> 0 | AD18: =+AC18-X18 -> 0 | AE18: =IFERROR(AD18/AC18,0) -> 0
B19: FI | D19: Hotel | J19: Porvoo: Check in to your accommodation for a X night stay - Hotel - Room - Bed - Breakfast included | Q19: 0 | R19: 0 | S19: =+Q19*R19 -> 0 | T19: 0 | U19: =S19*(1-T19) -> 0 | V19: EUR | W19: =IFERROR(VLOOKUP(V19,Curr!$B$2:$C$13,2,FALSE),0) -> 11 | X19: =U19*W19 -> 0 | Y19: =Q19/0.8 -> 0 | Z19: =+Y19*R19 -> 0 | AA19: EUR | AB19: =IFERROR(VLOOKUP(AA19,Curr!$B$2:$C$13,2,FALSE),0) -> 11 | AC19: =+Y19*AB19*R19 -> 0 | AD19: =+AC19-X19 -> 0 | AE19: =IFERROR(AD19/AC19,0) -> 0
B20: FI | D20: Hotel | J20: Savonlinna: Check in to your accommodation for a X night stay - Hotel - Room - Bed - Breakfast included | Q20: 0 | R20: 0 | S20: =+Q20*R20 -> 0 | T20: 0 | U20: =S20*(1-T20) -> 0 | V20: EUR | W20: =IFERROR(VLOOKUP(V20,Curr!$B$2:$C$13,2,FALSE),0) -> 11 | X20: =U20*W20 -> 0 | Y20: =Q20/0.8 -> 0 | Z20: =+Y20*R20 -> 0 | AA20: EUR | AB20: =IFERROR(VLOOKUP(AA20,Curr!$B$2:$C$13,2,FALSE),0) -> 11 | AC20: =+Y20*AB20*R20 -> 0 | AD20: =+AC20-X20 -> 0 | AE20: =IFERROR(AD20/AC20,0) -> 0
B21: FI | D21: Hotel | J21: Kuopio: Check in to your accommodation for a X night stay - Hotel - Room - Bed - Breakfast included | Q21: 0 | R21: 0 | S21: =+Q21*R21 -> 0 | T21: 0 | U21: =S21*(1-T21) -> 0 | V21: EUR | W21: =IFERROR(VLOOKUP(V21,Curr!$B$2:$C$13,2,FALSE),0) -> 11 | X21: =U21*W21 -> 0 | Y21: =Q21/0.8 -> 0 | Z21: =+Y21*R21 -> 0 | AA21: EUR | AB21: =IFERROR(VLOOKUP(AA21,Curr!$B$2:$C$13,2,FALSE),0) -> 11 | AC21: =+Y21*AB21*R21 -> 0 | AD21: =+AC21-X21 -> 0 | AE21: =IFERROR(AD21/AC21,0) -> 0
B22: FI | D22: Hotel | J22: Oulu: Check in to your accommodation for a X night stay - Hotel - Room - Bed - Breakfast included | Q22: 0 | R22: 0 | S22: =+Q22*R22 -> 0 | T22: 0 | U22: =S22*(1-T22) -> 0 | V22: EUR | W22: =IFERROR(VLOOKUP(V22,Curr!$B$2:$C$13,2,FALSE),0) -> 11 | X22: =U22*W22 -> 0 | Y22: =Q22/0.8 -> 0 | Z22: =+Y22*R22 -> 0 | AA22: EUR | AB22: =IFERROR(VLOOKUP(AA22,Curr!$B$2:$C$13,2,FALSE),0) -> 11 | AC22: =+Y22*AB22*R22 -> 0 | AD22: =+AC22-X22 -> 0 | AE22: =IFERROR(AD22/AC22,0) -> 0
B23: FI | D23: Hotel | J23: Jyväskylä: Check in to your accommodation for a X night stay - Hotel - Room - Bed - Breakfast included | Q23: 0 | R23: 0 | S23: =+Q23*R23 -> 0 | T23: 0 | U23: =S23*(1-T23) -> 0 | V23: EUR | W23: =IFERROR(VLOOKUP(V23,Curr!$B$2:$C$13,2,FALSE),0) -> 11 | X23: =U23*W23 -> 0 | Y23: =Q23/0.8 -> 0 | Z23: =+Y23*R23 -> 0 | AA23: EUR | AB23: =IFERROR(VLOOKUP(AA23,Curr!$B$2:$C$13,2,FALSE),0) -> 11 | AC23: =+Y23*AB23*R23 -> 0 | AD23: =+AC23-X23 -> 0 | AE23: =IFERROR(AD23/AC23,0) -> 0
B24: FI | D24: Hotel | J24: Vaasa: Check in to your accommodation for a X night stay - Hotel - Room - Bed - Breakfast included | Q24: 0 | R24: 0 | S24: =+Q24*R24 -> 0 | T24: 0 | U24: =S24*(1-T24) -> 0 | V24: EUR | W24: =IFERROR(VLOOKUP(V24,Curr!$B$2:$C$13,2,FALSE),0) -> 11 | X24: =U24*W24 -> 0 | Y24: =Q24/0.8 -> 0 | Z24: =+Y24*R24 -> 0 | AA24: EUR | AB24: =IFERROR(VLOOKUP(AA24,Curr!$B$2:$C$13,2,FALSE),0) -> 11 | AC24: =+Y24*AB24*R24 -> 0 | AD24: =+AC24-X24 -> 0 | AE24: =IFERROR(AD24/AC24,0) -> 0
B25: FI | D25: Hotel | J25: Mariehamn: Check in to your accommodation for a X night stay - Hotel - Room - Bed - Breakfast included | Q25: 0 | R25: 0 | S25: =+Q25*R25 -> 0 | T25: 0 | U25: =S25*(1-T25) -> 0 | V25: EUR | W25: =IFERROR(VLOOKUP(V25,Curr!$B$2:$C$13,2,FALSE),0) -> 11 | X25: =U25*W25 -> 0 | Y25: =Q25/0.8 -> 0 | Z25: =+Y25*R25 -> 0 | AA25: EUR | AB25: =IFERROR(VLOOKUP(AA25,Curr!$B$2:$C$13,2,FALSE),0) -> 11 | AC25: =+Y25*AB25*R25 -> 0 | AD25: =+AC25-X25 -> 0 | AE25: =IFERROR(AD25/AC25,0) -> 0
B26: FI | D26: Hotel | J26: Långnäs: Check in to your accommodation for a X night stay - Hotel - Room - Bed - Breakfast included | Q26: 0 | R26: 0 | S26: =+Q26*R26 -> 0 | T26: 0 | U26: =S26*(1-T26) -> 0 | V26: EUR | W26: =IFERROR(VLOOKUP(V26,Curr!$B$2:$C$13,2,FALSE),0) -> 11 | X26: =U26*W26 -> 0 | Y26: =Q26/0.8 -> 0 | Z26: =+Y26*R26 -> 0 | AA26: EUR | AB26: =IFERROR(VLOOKUP(AA26,Curr!$B$2:$C$13,2,FALSE),0) -> 11 | AC26: =+Y26*AB26*R26 -> 0 | AD26: =+AC26-X26 -> 0 | AE26: =IFERROR(AD26/AC26,0) -> 0
... B494: DK | D494: Hotel | J494: Aakirkeby: Check in to your accommodation for a X night stay - Hotel - Room - Bed - Breakfast included | Q494: 0 | R494: 0 | S494: =+Q494*R494 -> 0 | T494: 0 | U494: =S494*(1-T494) -> 0 | V494: EUR | W494: =IFERROR(VLOOKUP(V494,Curr!$B$2:$C$13,2,FALSE),0) -> 11 | X494: =U494*W494 -> 0 | Y494: =Q494/0.8 -> 0 | Z494: =+Y494*R494 -> 0 | AA494: EUR | AB494: =IFERROR(VLOOKUP(AA494,Curr!$B$2:$C$13,2,FALSE),0) -> 11 | AC494: =+Y494*AB494*R494 -> 0 | AD494: =+AC494-X494 -> 0 | AE494: =IFERROR(AD494/AC494,0) -> 0

Sheet Transfers
B2: Dates:
B3: Pax:
B4: Rooming:
B6: ID | C6: Day | D6: Type | E6: From date | F6: To date | G6: From time | H6: To time | I6: Supplier | J6: Travel element | K6: Manual booking? | L6: Status | M6: Comments | N6: Non-refundable | O6: Refundable | P6: URL | Q6: Gross P per unit | R6: Units | S6: Gross P | T6: Supp Comm | U6: Net P | V6: Supp curr | W6: X-rate | X6: Net P NOK | Y6: Sales P per unit | Z6: Price | AA6: Sales curr | AB6: X-rate2 | AC6: Sales P NOK tot | AD6: GP NOK | AE6: GP % | AF6: VAT25 | AG6: VAT15 | AH6: VAT12 | AI6: VAT0-D | AJ6: VAT0-I
B7: FI | D7: Transfer | J7: Helsinki: Self transfer to your accommodation | Q7: 0 | R7: 0 | S7: =+Q7*R7 -> 0 | T7: 0 | U7: =S7*(1-T7) -> 0 | V7: EUR | W7: =IFERROR(VLOOKUP(V7,Curr!$B$2:$C$13,2,FALSE),0) -> 11 | X7: =U7*W7 -> 0 | Y7: =Q7 -> 0 | Z7: =+Y7*R7 -> 0 | AA7: EUR | AB7: =IFERROR(VLOOKUP(AA7,Curr!$B$2:$C$13,2,FALSE),0) -> 11 | AC7: =+Y7*AB7*R7 -> 0 | AD7: =+AC7-X7 -> 0 | AE7: =IFERROR(AD7/AC7,0) -> 0
B8: FI | D8: Transfer | J8: Helsinki: Private transfer to your accommodation | Q8: 80 | R8: 1 | S8: =+Q8*R8 -> 80 | T8: 0 | U8: =S8*(1-T8) -> 80 | V8: EUR | W8: =IFERROR(VLOOKUP(V8,Curr!$B$2:$C$13,2,FALSE),0) -> 11 | X8: =U8*W8 -> 880 | Y8: =Q8/0.8 -> 100 | Z8: =+Y8*R8 -> 100 | AA8: EUR | AB8: =IFERROR(VLOOKUP(AA8,Curr!$B$2:$C$13,2,FALSE),0) -> 11 | AC8: =+Y8*AB8*R8 -> 1100 | AD8: =+AC8-X8 -> 220 | AE8: =IFERROR(AD8/AC8,0) -> 0.2
B9: FI | D9: Transfer | J9: Helsinki: Self transfer to Helsinki Airport | Q9: 0 | R9: 0 | S9: =+Q9*R9 -> 0 | T9: 0 | U9: =S9*(1-T9) -> 0 | V9: EUR | W9: =IFERROR(VLOOKUP(V9,Curr!$B$2:$C$13,2,FALSE),0) -> 11 | X9: =U9*W9 -> 0 | Y9: =Q9 -> 0 | Z9: =+Y9*R9 -> 0 | AA9: EUR | AB9: =IFERROR(VLOOKUP(AA9,Curr!$B$2:$C$13,2,FALSE),0) -> 11 | AC9: =+Y9*AB9*R9 -> 0 | AD9: =+AC9-X9 -> 0 | AE9: =IFERROR(AD9/AC9,0) -> 0
B10: FI | D10: Transfer | J10: Helsinki: Private transfer to Helsinki Airport | Q10: 80 | R10: 1 | S10: =+Q10*R10 -> 80 | T10: 0 | U10: =S10*(1-T10) -> 80 | V10: EUR | W10: =IFERROR(VLOOKUP(V10,Curr!$B$2:$C$13,2,FALSE),0) -> 11 | X10: =U10*W10 -> 880 | Y10: =Q10/0.8 -> 100 | Z10: =+Y10*R10 -> 100 | AA10: EUR | AB10: =IFERROR(VLOOKUP(AA10,Curr!$B$2:$C$13,2,FALSE),0) -> 11 | AC10: =+Y10*AB10*R10 -> 1100 | AD10: =+AC10-X10 -> 220 | AE10: =IFERROR(AD10/AC10,0) -> 0.2
B11: FI | D11: Transfer | J11: Helsinki: Self transfer to Helsinki Central Railway Station | Q11: 0 | R11: 0 | S11: =+Q11*R11 -> 0 | T11: 0 | U11: =S11*(1-T11) -> 0 | V11: EUR | W11: =IFERROR(VLOOKUP(V11,Curr!$B$2:$C$13,2,FALSE),0) -> 11 | X11: =U11*W11 -> 0 | Y11: =Q11 -> 0 | Z11: =+Y11*R11 -> 0 | AA11: EUR | AB11: =IFERROR(VLOOKUP(AA11,Curr!$B$2:$C$13,2,FALSE),0) -> 11 | AC11: =+Y11*AB11*R11 -> 0 | AD11: =+AC11-X11 -> 0 | AE11: =IFERROR(AD11/AC11,0) -> 0
B12: FI | D12: Transfer | J12: Helsinki: Private transfer to Helsinki Central Railway Station | Q12: 40 | R12: 1 | S12: =+Q12*R12 -> 40 | T12: 0 | U12: =S12*(1-T12) -> 40 | V12: EUR | W12: =IFERROR(VLOOKUP(V12,Curr!$B$2:$C$13,2,FALSE),0) -> 11 | X12: =U12*W12 -> 440 | Y12: =Q12/0.8 -> 50 | Z12: =+Y12*R12 -> 50 | AA12: EUR | AB12: =IFERROR(VLOOKUP(AA12,Curr!$B$2:$C$13,2,FALSE),0) -> 11 | AC12: =+Y12*AB12*R12 -> 550 | AD12: =+AC12-X12 -> 110 | AE12: =IFERROR(AD12/AC12,0) -> 0.2
B13: FI | D13: Transfer | J13: Helsinki: Self transfer to Kamppi Bus Station | Q13: 0 | R13: 0 | S13: =+Q13*R13 -> 0 | T13: 0 | U13: =S13*(1-T13) -> 0 | V13: EUR | W13: =IFERROR(VLOOKUP(V13,Curr!$B$2:$C$13,2,FALSE),0) -> 11 | X13: =U13*W13 -> 0 | Y13: =Q13 -> 0 | Z13: =+Y13*R13 -> 0 | AA13: EUR | AB13: =IFERROR(VLOOKUP(AA13,Curr!$B$2:$C$13,2,FALSE),0) -> 11 | AC13: =+Y13*AB13*R13 -> 0 | AD13: =+AC13-X13 -> 0 | AE13: =IFERROR(AD13/AC13,0) -> 0
B14: FI | D14: Transfer | J14: Helsinki: Private transfer to Kamppi Bus Station | Q14: 40 | R14: 1 | S14: =+Q14*R14 -> 40 | T14: 0 | U14: =S14*(1-T14) -> 40 | V14: EUR | W14: =IFERROR(VLOOKUP(V14,Curr!$B$2:$C$13,2,FALSE),0) -> 11 | X14: =U14*W14 -> 440 | Y14: =Q14/0.8 -> 50 | Z14: =+Y14*R14 -> 50 | AA14: EUR | AB14: =IFERROR(VLOOKUP(AA14,Curr!$B$2:$C$13,2,FALSE),0) -> 11 | AC14: =+Y14*AB14*R14 -> 550 | AD14: =+AC14-X14 -> 110 | AE14: =IFERROR(AD14/AC14,0) -> 0.2
B15: FI | D15: Transfer | J15: Helsinki: Self transfer to Helsinki ferry terminal | Q15: 0 | R15: 0 | S15: =+Q15*R15 -> 0 | T15: 0 | U15: =S15*(1-T15) -> 0 | V15: EUR | W15: =IFERROR(VLOOKUP(V15,Curr!$B$2:$C$13,2,FALSE),0) -> 11 | X15: =U15*W15 -> 0 | Y15: =Q15 -> 0 | Z15: =+Y15*R15 -> 0 | AA15: EUR | AB15: =IFERROR(VLOOKUP(AA15,Curr!$B$2:$C$13,2,FALSE),0) -> 11 | AC15: =+Y15*AB15*R15 -> 0 | AD15: =+AC15-X15 -> 0 | AE15: =IFERROR(AD15/AC15,0) -> 0
B16: FI | D16: Transfer | J16: Helsinki: Private transfer to Helsinki ferry terminal | Q16: 40 | R16: 1 | S16: =+Q16*R16 -> 40 | T16: 0 | U16: =S16*(1-T16) -> 40 | V16: EUR | W16: =IFERROR(VLOOKUP(V16,Curr!$B$2:$C$13,2,FALSE),0) -> 11 | X16: =U16*W16 -> 440 | Y16: =Q16/0.8 -> 50 | Z16: =+Y16*R16 -> 50 | AA16: EUR | AB16: =IFERROR(VLOOKUP(AA16,Curr!$B$2:$C$13,2,FALSE),0) -> 11 | AC16: =+Y16*AB16*R16 -> 550 | AD16: =+AC16-X16 -> 110 | AE16: =IFERROR(AD16/AC16,0) -> 0.2
B17: FI | D17: Transfer | J17: Helsinki: Self transfer to Helsinki cruise port | Q17: 0 | R17: 0 | S17: =+Q17*R17 -> 0 | T17: 0 | U17: =S17*(1-T17) -> 0 | V17: EUR | W17: =IFERROR(VLOOKUP(V17,Curr!$B$2:$C$13,2,FALSE),0) -> 11 | X17: =U17*W17 -> 0 | Y17: =Q17 -> 0 | Z17: =+Y17*R17 -> 0 | AA17: EUR | AB17: =IFERROR(VLOOKUP(AA17,Curr!$B$2:$C$13,2,FALSE),0) -> 11 | AC17: =+Y17*AB17*R17 -> 0 | AD17: =+AC17-X17 -> 0 | AE17: =IFERROR(AD17/AC17,0) -> 0
B18: FI | D18: Transfer | J18: Helsinki: Private transfer to Helsinki cruise port | Q18: 40 | R18: 1 | S18: =+Q18*R18 -> 40 | T18: 0 | U18: =S18*(1-T18) -> 40 | V18: EUR | W18: =IFERROR(VLOOKUP(V18,Curr!$B$2:$C$13,2,FALSE),0) -> 11 | X18: =U18*W18 -> 440 | Y18: =Q18/0.8 -> 50 | Z18: =+Y18*R18 -> 50 | AA18: EUR | AB18: =IFERROR(VLOOKUP(AA18,Curr!$B$2:$C$13,2,FALSE),0) -> 11 | AC18: =+Y18*AB18*R18 -> 550 | AD18: =+AC18-X18 -> 110 | AE18: =IFERROR(AD18/AC18,0) -> 0.2
B19: FI | D19: Transfer | J19: Rovaniemi: Self transfer to your accommodation | Q19: 0 | R19: 0 | S19: =+Q19*R19 -> 0 | T19: 0 | U19: =S19*(1-T19) -> 0 | V19: EUR | W19: =IFERROR(VLOOKUP(V19,Curr!$B$2:$C$13,2,FALSE),0) -> 11 | X19: =U19*W19 -> 0 | Y19: =Q19 -> 0 | Z19: =+Y19*R19 -> 0 | AA19: EUR | AB19: =IFERROR(VLOOKUP(AA19,Curr!$B$2:$C$13,2,FALSE),0) -> 11 | AC19: =+Y19*AB19*R19 -> 0 | AD19: =+AC19-X19 -> 0 | AE19: =IFERROR(AD19/AC19,0) -> 0
B20: FI | D20: Transfer | J20: Rovaniemi: Private transfer to your accommodation | Q20: 40 | R20: 1 | S20: =+Q20*R20 -> 40 | T20: 0 | U20: =S20*(1-T20) -> 40 | V20: EUR | W20: =IFERROR(VLOOKUP(V20,Curr!$B$2:$C$13,2,FALSE),0) -> 11 | X20: =U20*W20 -> 440 | Y20: =Q20/0.7 -> 57.142857 | Z20: =+Y20*R20 -> 57.142857 | AA20: EUR | AB20: =IFERROR(VLOOKUP(AA20,Curr!$B$2:$C$13,2,FALSE),0) -> 11 | AC20: =+Y20*AB20*R20 -> 628.57143 | AD20: =+AC20-X20 -> 188.57143 | AE20: =IFERROR(AD20/AC20,0) -> 0.3
B21: FI | D21: Transfer | J21: Rovaniemi: Self transfer to Rovaniemi Airport | Q21: 0 | R21: 0 | S21: =+Q21*R21 -> 0 | T21: 0 | U21: =S21*(1-T21) -> 0 | V21: EUR | W21: =IFERROR(VLOOKUP(V21,Curr!$B$2:$C$13,2,FALSE),0) -> 11 | X21: =U21*W21 -> 0 | Y21: =Q21 -> 0 | Z21: =+Y21*R21 -> 0 | AA21: EUR | AB21: =IFERROR(VLOOKUP(AA21,Curr!$B$2:$C$13,2,FALSE),0) -> 11 | AC21: =+Y21*AB21*R21 -> 0 | AD21: =+AC21-X21 -> 0 | AE21: =IFERROR(AD21/AC21,0) -> 0
B22: FI | D22: Transfer | J22: Rovaniemi: Private transfer to Rovaniemi Airport | Q22: 40 | R22: 1 | S22: =+Q22*R22 -> 40 | T22: 0 | U22: =S22*(1-T22) -> 40 | V22: EUR | W22: =IFERROR(VLOOKUP(V22,Curr!$B$2:$C$13,2,FALSE),0) -> 11 | X22: =U22*W22 -> 440 | Y22: =Q22/0.7 -> 57.142857 | Z22: =+Y22*R22 -> 57.142857 | AA22: EUR | AB22: =IFERROR(VLOOKUP(AA22,Curr!$B$2:$C$13,2,FALSE),0) -> 11 | AC22: =+Y22*AB22*R22 -> 628.57143 | AD22: =+AC22-X22 -> 188.57143 | AE22: =IFERROR(AD22/AC22,0) -> 0.3
B23: FI | D23: Transfer | J23: Rovaniemi: Self transfer to Rovaniemi railway station | Q23: 0 | R23: 0 | S23: =+Q23*R23 -> 0 | T23: 0 | U23: =S23*(1-T23) -> 0 | V23: EUR | W23: =IFERROR(VLOOKUP(V23,Curr!$B$2:$C$13,2,FALSE),0) -> 11 | X23: =U23*W23 -> 0 | Y23: =Q23 -> 0 | Z23: =+Y23*R23 -> 0 | AA23: EUR | AB23: =IFERROR(VLOOKUP(AA23,Curr!$B$2:$C$13,2,FALSE),0) -> 11 | AC23: =+Y23*AB23*R23 -> 0 | AD23: =+AC23-X23 -> 0 | AE23: =IFERROR(AD23/AC23,0) -> 0
B24: FI | D24: Transfer | J24: Rovaniemi: Private transfer to Rovaniemi railway station | Q24: 40 | R24: 1 | S24: =+Q24*R24 -> 40 | T24: 0 | U24: =S24*(1-T24) -> 40 | V24: EUR | W24: =IFERROR(VLOOKUP(V24,Curr!$B$2:$C$13,2,FALSE),0) -> 11 | X24: =U24*W24 -> 440 | Y24: =Q24/0.7 -> 57.142857 | Z24: =+Y24*R24 -> 57.142857 | AA24: EUR | AB24: =IFERROR(VLOOKUP(AA24,Curr!$B$2:$C$13,2,FALSE),0) -> 11 | AC24: =+Y24*AB24*R24 -> 628.57143 | AD24: =+AC24-X24 -> 188.57143 | AE24: =IFERROR(AD24/AC24,0) -> 0.3
B25: FI | D25: Transfer | J25: Rovaniemi: Self transfer to Rovaniemi Bus Station | Q25: 0 | R25: 0 | S25: =+Q25*R25 -> 0 | T25: 0 | U25: =S25*(1-T25) -> 0 | V25: EUR | W25: =IFERROR(VLOOKUP(V25,Curr!$B$2:$C$13,2,FALSE),0) -> 11 | X25: =U25*W25 -> 0 | Y25: =Q25 -> 0 | Z25: =+Y25*R25 -> 0 | AA25: EUR | AB25: =IFERROR(VLOOKUP(AA25,Curr!$B$2:$C$13,2,FALSE),0) -> 11 | AC25: =+Y25*AB25*R25 -> 0 | AD25: =+AC25-X25 -> 0 | AE25: =IFERROR(AD25/AC25,0) -> 0
B26: FI | D26: Transfer | J26: Rovaniemi: Private transfer to Rovaniemi Bus Station | Q26: 40 | R26: 1 | S26: =+Q26*R26 -> 40 | T26: 0 | U26: =S26*(1-T26) -> 40 | V26: EUR | W26: =IFERROR(VLOOKUP(V26,Curr!$B$2:$C$13,2,FALSE),0) -> 11 | X26: =U26*W26 -> 440 | Y26: =Q26/0.7 -> 57.142857 | Z26: =+Y26*R26 -> 57.142857 | AA26: EUR | AB26: =IFERROR(VLOOKUP(AA26,Curr!$B$2:$C$13,2,FALSE),0) -> 11 | AC26: =+Y26*AB26*R26 -> 628.57143 | AD26: =+AC26-X26 -> 188.57143 | AE26: =IFERROR(AD26/AC26,0) -> 0.3
B27: FI | D27: Transfer | J27: Turku: Self transfer to your accommodation | Q27: 0 | R27: 0 | S27: =+Q27*R27 -> 0 | T27: 0 | U27: =S27*(1-T27) -> 0 | V27: EUR | W27: =IFERROR(VLOOKUP(V27,Curr!$B$2:$C$13,2,FALSE),0) -> 11 | X27: =U27*W27 -> 0 | Y27: =Q27 -> 0 | Z27: =+Y27*R27 -> 0 | AA27: EUR | AB27: =IFERROR(VLOOKUP(AA27,Curr!$B$2:$C$13,2,FALSE),0) -> 11 | AC27: =+Y27*AB27*R27 -> 0 | AD27: =+AC27-X27 -> 0 | AE27: =IFERROR(AD27/AC27,0) -> 0
B28: FI | D28: Transfer | J28: Turku: Private transfer to your accommodation | Q28: 0 | R28: 0 | S28: =+Q28*R28 -> 0 | T28: 0 | U28: =S28*(1-T28) -> 0 | V28: EUR | W28: =IFERROR(VLOOKUP(V28,Curr!$B$2:$C$13,2,FALSE),0) -> 11 | X28: =U28*W28 -> 0 | Y28: =Q28 -> 0 | Z28: =+Y28*R28 -> 0 | AA28: EUR | AB28: =IFERROR(VLOOKUP(AA28,Curr!$B$2:$C$13,2,FALSE),0) -> 11 | AC28: =+Y28*AB28*R28 -> 0 | AD28: =+AC28-X28 -> 0 | AE28: =IFERROR(AD28/AC28,0) -> 0
B29: FI | D29: Transfer | J29: Turku: Self transfer to Turku Airport | Q29: 0 | R29: 0 | S29: =+Q29*R29 -> 0 | T29: 0 | U29: =S29*(1-T29) -> 0 | V29: EUR | W29: =IFERROR(VLOOKUP(V29,Curr!$B$2:$C$13,2,FALSE),0) -> 11 | X29: =U29*W29 -> 0 | Y29: =Q29 -> 0 | Z29: =+Y29*R29 -> 0 | AA29: EUR | AB29: =IFERROR(VLOOKUP(AA29,Curr!$B$2:$C$13,2,FALSE),0) -> 11 | AC29: =+Y29*AB29*R29 -> 0 | AD29: =+AC29-X29 -> 0 | AE29: =IFERROR(AD29/AC29,0) -> 0
B30: FI | D30: Transfer | J30: Turku: Private transfer to Turku Airport | Q30: 0 | R30: 0 | S30: =+Q30*R30 -> 0 | T30: 0 | U30: =S30*(1-T30) -> 0 | V30: EUR | W30: =IFERROR(VLOOKUP(V30,Curr!$B$2:$C$13,2,FALSE),0) -> 11 | X30: =U30*W30 -> 0 | Y30: =Q30 -> 0 | Z30: =+Y30*R30 -> 0 | AA30: EUR | AB30: =IFERROR(VLOOKUP(AA30,Curr!$B$2:$C$13,2,FALSE),0) -> 11 | AC30: =+Y30*AB30*R30 -> 0 | AD30: =+AC30-X30 -> 0 | AE30: =IFERROR(AD30/AC30,0) -> 0
B31: FI | D31: Transfer | J31: Turku: Self transfer to Turku railway station | Q31: 0 | R31: 0 | S31: =+Q31*R31 -> 0 | T31: 0 | U31: =S31*(1-T31) -> 0 | V31: EUR | W31: =IFERROR(VLOOKUP(V31,Curr!$B$2:$C$13,2,FALSE),0) -> 11 | X31: =U31*W31 -> 0 | Y31: =Q31 -> 0 | Z31: =+Y31*R31 -> 0 | AA31: EUR | AB31: =IFERROR(VLOOKUP(AA31,Curr!$B$2:$C$13,2,FALSE),0) -> 11 | AC31: =+Y31*AB31*R31 -> 0 | AD31: =+AC31-X31 -> 0 | AE31: =IFERROR(AD31/AC31,0) -> 0
B32: FI | D32: Transfer | J32: Turku: Private transfer to Turku railway station | Q32: 0 | R32: 0 | S32: =+Q32*R32 -> 0 | T32: 0 | U32: =S32*(1-T32) -> 0 | V32: EUR | W32: =IFERROR(VLOOKUP(V32,Curr!$B$2:$C$13,2,FALSE),0) -> 11 | X32: =U32*W32 -> 0 | Y32: =Q32 -> 0 | Z32: =+Y32*R32 -> 0 | AA32: EUR | AB32: =IFERROR(VLOOKUP(AA32,Curr!$B$2:$C$13,2,FALSE),0) -> 11 | AC32: =+Y32*AB32*R32 -> 0 | AD32: =+AC32-X32 -> 0 | AE32: =IFERROR(AD32/AC32,0) -> 0
B33: FI | D33: Transfer | J33: Turku: Self transfer to Turku Bus Station | Q33: 0 | R33: 0 | S33: =+Q33*R33 -> 0 | T33: 0 | U33: =S33*(1-T33) -> 0 | V33: EUR | W33: =IFERROR(VLOOKUP(V33,Curr!$B$2:$C$13,2,FALSE),0) -> 11 | X33: =U33*W33 -> 0 | Y33: =Q33 -> 0 | Z33: =+Y33*R33 -> 0 | AA33: EUR | AB33: =IFERROR(VLOOKUP(AA33,Curr!$B$2:$C$13,2,FALSE),0) -> 11 | AC33: =+Y33*AB33*R33 -> 0 | AD33: =+AC33-X33 -> 0 | AE33: =IFERROR(AD33/AC33,0) -> 0
B34: FI | D34: Transfer | J34: Turku: Private transfer to Turku Bus Station | Q34: 0 | R34: 0 | S34: =+Q34*R34 -> 0 | T34: 0 | U34: =S34*(1-T34) -> 0 | V34: EUR | W34: =IFERROR(VLOOKUP(V34,Curr!$B$2:$C$13,2,FALSE),0) -> 11 | X34: =U34*W34 -> 0 | Y34: =Q34 -> 0 | Z34: =+Y34*R34 -> 0 | AA34: EUR | AB34: =IFERROR(VLOOKUP(AA34,Curr!$B$2:$C$13,2,FALSE),0) -> 11 | AC34: =+Y34*AB34*R34 -> 0 | AD34: =+AC34-X34 -> 0 | AE34: =IFERROR(AD34/AC34,0) -> 0
B35: FI | D35: Transfer | J35: Turku: Self transfer to Port of Turku ferry terminal | Q35: 0 | R35: 0 | S35: =+Q35*R35 -> 0 | T35: 0 | U35: =S35*(1-T35) -> 0 | V35: EUR | W35: =IFERROR(VLOOKUP(V35,Curr!$B$2:$C$13,2,FALSE),0) -> 11 | X35: =U35*W35 -> 0 | Y35: =Q35 -> 0 | Z35: =+Y35*R35 -> 0 | AA35: EUR | AB35: =IFERROR(VLOOKUP(AA35,Curr!$B$2:$C$13,2,FALSE),0) -> 11 | AC35: =+Y35*AB35*R35 -> 0 | AD35: =+AC35-X35 -> 0 | AE35: =IFERROR(AD35/AC35,0) -> 0
B36: FI | D36: Transfer | J36: Turku: Private transfer to Port of Turku ferry terminal | Q36: 0 | R36: 0 | S36: =+Q36*R36 -> 0 | T36: 0 | U36: =S36*(1-T36) -> 0 | V36: EUR | W36: =IFERROR(VLOOKUP(V36,Curr!$B$2:$C$13,2,FALSE),0) -> 11 | X36: =U36*W36 -> 0 | Y36: =Q36 -> 0 | Z36: =+Y36*R36 -> 0 | AA36: EUR | AB36: =IFERROR(VLOOKUP(AA36,Curr!$B$2:$C$13,2,FALSE),0) -> 11 | AC36: =+Y36*AB36*R36 -> 0 | AD36: =+AC36-X36 -> 0 | AE36: =IFERROR(AD36/AC36,0) -> 0
B37: FI | D37: Transfer | J37: Turku: Self transfer to Turku cruise port | Q37: 0 | R37: 0 | S37: =+Q37*R37 -> 0 | T37: 0 | U37: =S37*(1-T37) -> 0 | V37: EUR | W37: =IFERROR(VLOOKUP(V37,Curr!$B$2:$C$13,2,FALSE),0) -> 11 | X37: =U37*W37 -> 0 | Y37: =Q37 -> 0 | Z37: =+Y37*R37 -> 0 | AA37: EUR | AB37: =IFERROR(VLOOKUP(AA37,Curr!$B$2:$C$13,2,FALSE),0) -> 11 | AC37: =+Y37*AB37*R37 -> 0 | AD37: =+AC37-X37 -> 0 | AE37: =IFERROR(AD37/AC37,0) -> 0
B38: FI | D38: Transfer | J38: Turku: Private transfer to Turku cruise port | Q38: 0 | R38: 0 | S38: =+Q38*R38 -> 0 | T38: 0 | U38: =S38*(1-T38) -> 0 | V38: EUR | W38: =IFERROR(VLOOKUP(V38,Curr!$B$2:$C$13,2,FALSE),0) -> 11 | X38: =U38*W38 -> 0 | Y38: =Q38 -> 0 | Z38: =+Y38*R38 -> 0 | AA38: EUR | AB38: =IFERROR(VLOOKUP(AA38,Curr!$B$2:$C$13,2,FALSE),0) -> 11 | AC38: =+Y38*AB38*R38 -> 0 | AD38: =+AC38-X38 -> 0 | AE38: =IFERROR(AD38/AC38,0) -> 0
... B287: FI | D287: Transfer | J287: Ivalo: Self transfer to Ivalo Bus Station | Q287: 0 | R287: 0 | S287: =+Q287*R287 -> 0 | T287: 0 | U287: =S287*(1-T287) -> 0 | V287: EUR | W287: =IFERROR(VLOOKUP(V287,Curr!$B$2:$C$13,2,FALSE),0) -> 11 | X287: =U287*W287 -> 0 | Y287: =Q287 -> 0 | Z287: =+Y287*R287 -> 0 | AA287: EUR | AB287: =IFERROR(VLOOKUP(AA287,Curr!$B$2:$C$13,2,FALSE),0) -> 11 | AC287: =+Y287*AB287*R287 -> 0 | AD287: =+AC287-X287 -> 0 | AE287: =IFERROR(AD287/AC287,0) -> 0
B288: FI | D288: Transfer | J288: Ivalo: Shuttle transfer to Kakslauttanen Arctic Resort | Q288: 49 | R288: 0 | S288: =+Q288*R288 -> 0 | T288: 0 | U288: =S288*(1-T288) -> 0 | V288: EUR | W288: =IFERROR(VLOOKUP(V288,Curr!$B$2:$C$13,2,FALSE),0) -> 11 | X288: =U288*W288 -> 0 | Y288: =Q288/0.8 -> 61.25 | Z288: =+Y288*R288 -> 0 | AA288: EUR | AB288: =IFERROR(VLOOKUP(AA288,Curr!$B$2:$C$13,2,FALSE),0) -> 11 | AC288: =+Y288*AB288*R288 -> 0 | AD288: =+AC288-X288 -> 0 | AE288: =IFERROR(AD288/AC288,0) -> 0
B289: FI | D289: Transfer | J289: Ivalo: Private transfer to Ivalo Bus Station | Q289: 0 | R289: 0 | S289: =+Q289*R289 -> 0 | T289: 0 | U289: =S289*(1-T289) -> 0 | V289: EUR | W289: =IFERROR(VLOOKUP(V289,Curr!$B$2:$C$13,2,FALSE),0) -> 11 | X289: =U289*W289 -> 0 | Y289: =Q289 -> 0 | Z289: =+Y289*R289 -> 0 | AA289: EUR | AB289: =IFERROR(VLOOKUP(AA289,Curr!$B$2:$C$13,2,FALSE),0) -> 11 | AC289: =+Y289*AB289*R289 -> 0 | AD289: =+AC289-X289 -> 0 | AE289: =IFERROR(AD289/AC289,0) -> 0
B290: FI | D290: Transfer | J290: Kemi: Self transfer to your accommodation | Q290: 0 | R290: 0 | S290: =+Q290*R290 -> 0 | T290: 0 | U290: =S290*(1-T290) -> 0 | V290: EUR | W290: =IFERROR(VLOOKUP(V290,Curr!$B$2:$C$13,2,FALSE),0) -> 11 | X290: =U290*W290 -> 0 | Y290: =Q290 -> 0 | Z290: =+Y290*R290 -> 0 | AA290: EUR | AB290: =IFERROR(VLOOKUP(AA290,Curr!$B$2:$C$13,2,FALSE),0) -> 11 | AC290: =+Y290*AB290*R290 -> 0 | AD290: =+AC290-X290 -> 0 | AE290: =IFERROR(AD290/AC290,0) -> 0
B291: FI | D291: Transfer | J291: Kemi: Private transfer to your accommodation | Q291: 0 | R291: 0 | S291: =+Q291*R291 -> 0 | T291: 0 | U291: =S291*(1-T291) -> 0 | V291: EUR | W291: =IFERROR(VLOOKUP(V291,Curr!$B$2:$C$13,2,FALSE),0) -> 11 | X291: =U291*W291 -> 0 | Y291: =Q291 -> 0 | Z291: =+Y291*R291 -> 0 | AA291: EUR | AB291: =IFERROR(VLOOKUP(AA291,Curr!$B$2:$C$13,2,FALSE),0) -> 11 | AC291: =+Y291*AB291*R291 -> 0 | AD291: =+AC291-X291 -> 0 | AE291: =IFERROR(AD291/AC291,0) -> 0
B292: FI | D292: Transfer | J292: Kemi: Self transfer to Kemi-Tornio Airport | Q292: 0 | R292: 0 | S292: =+Q292*R292 -> 0 | T292: 0 | U292: =S292*(1-T292) -> 0 | V292: EUR | W292: =IFERROR(VLOOKUP(V292,Curr!$B$2:$C$13,2,FALSE),0) -> 11 | X292: =U292*W292 -> 0 | Y292: =Q292 -> 0 | Z292: =+Y292*R292 -> 0 | AA292: EUR | AB292: =IFERROR(VLOOKUP(AA292,Curr!$B$2:$C$13,2,FALSE),0) -> 11 | AC292: =+Y292*AB292*R292 -> 0 | AD292: =+AC292-X292 -> 0 | AE292: =IFERROR(AD292/AC292,0) -> 0
B293: FI | D293: Transfer | J293: Kemi: Private transfer to Kemi-Tornio Airport | Q293: 0 | R293: 0 | S293: =+Q293*R293 -> 0 | T293: 0 | U293: =S293*(1-T293) -> 0 | V293: EUR | W293: =IFERROR(VLOOKUP(V293,Curr!$B$2:$C$13,2,FALSE),0) -> 11 | X293: =U293*W293 -> 0 | Y293: =Q293 -> 0 | Z293: =+Y293*R293 -> 0 | AA293: EUR | AB293: =IFERROR(VLOOKUP(AA293,Curr!$B$2:$C$13,2,FALSE),0) -> 11 | AC293: =+Y293*AB293*R293 -> 0 | AD293: =+AC293-X293 -> 0 | AE293: =IFERROR(AD293/AC293,0) -> 0
B294: FI | D294: Transfer | J294: Kemi: Self transfer to Kemi railway station | Q294: 0 | R294: 0 | S294: =+Q294*R294 -> 0 | T294: 0 | U294: =S294*(1-T294) -> 0 | V294: EUR | W294: =IFERROR(VLOOKUP(V294,Curr!$B$2:$C$13,2,FALSE),0) -> 11 | X294: =U294*W294 -> 0 | Y294: =Q294 -> 0 | Z294: =+Y294*R294 -> 0 | AA294: EUR | AB294: =IFERROR(VLOOKUP(AA294,Curr!$B$2:$C$13,2,FALSE),0) -> 11 | AC294: =+Y294*AB294*R294 -> 0 | AD294: =+AC294-X294 -> 0 | AE294: =IFERROR(AD294/AC294,0) -> 0
B295: FI | D295: Transfer | J295: Kemi: Private transfer to Kemi railway station | Q295: 0 | R295: 0 | S295: =+Q295*R295 -> 0 | T295: 0 | U295: =S295*(1-T295) -> 0 | V295: EUR | W295: =IFERROR(VLOOKUP(V295,Curr!$B$2:$C$13,2,FALSE),0) -> 11 | X295: =U295*W295 -> 0 | Y295: =Q295 -> 0 | Z295: =+Y295*R295 -> 0 | AA295: EUR | AB295: =IFERROR(VLOOKUP(AA295,Curr!$B$2:$C$13,2,FALSE),0) -> 11 | AC295: =+Y295*AB295*R295 -> 0 | AD295: =+AC295-X295 -> 0 | AE295: =IFERROR(AD295/AC295,0) -> 0
B296: FI | D296: Transfer | J296: Kemi: Self transfer to Kemi Bus Station | Q296: 0 | R296: 0 | S296: =+Q296*R296 -> 0 | T296: 0 | U296: =S296*(1-T296) -> 0 | V296: EUR | W296: =IFERROR(VLOOKUP(V296,Curr!$B$2:$C$13,2,FALSE),0) -> 11 | X296: =U296*W296 -> 0 | Y296: =Q296 -> 0 | Z296: =+Y296*R296 -> 0 | AA296: EUR | AB296: =IFERROR(VLOOKUP(AA296,Curr!$B$2:$C$13,2,FALSE),0) -> 11 | AC296: =+Y296*AB296*R296 -> 0 | AD296: =+AC296-X296 -> 0 | AE296: =IFERROR(AD296/AC296,0) -> 0
B297: FI | D297: Transfer | J297: Kemi: Private transfer to Kemi Bus Station | Q297: 0 | R297: 0 | S297: =+Q297*R297 -> 0 | T297: 0 | U297: =S297*(1-T297) -> 0 | V297: EUR | W297: =IFERROR(VLOOKUP(V297,Curr!$B$2:$C$13,2,FALSE),0) -> 11 | X297: =U297*W297 -> 0 | Y297: =Q297 -> 0 | Z297: =+Y297*R297 -> 0 | AA297: EUR | AB297: =IFERROR(VLOOKUP(AA297,Curr!$B$2:$C$13,2,FALSE),0) -> 11 | AC297: =+Y297*AB297*R297 -> 0 | AD297: =+AC297-X297 -> 0 | AE297: =IFERROR(AD297/AC297,0) -> 0
B298: FI | D298: Transfer | J298: Kemi: Self transfer to Kemi cruise port | Q298: 0 | R298: 0 | S298: =+Q298*R298 -> 0 | T298: 0 | U298: =S298*(1-T298) -> 0 | V298: EUR | W298: =IFERROR(VLOOKUP(V298,Curr!$B$2:$C$13,2,FALSE),0) -> 11 | X298: =U298*W298 -> 0 | Y298: =Q298 -> 0 | Z298: =+Y298*R298 -> 0 | AA298: EUR | AB298: =IFERROR(VLOOKUP(AA298,Curr!$B$2:$C$13,2,FALSE),0) -> 11 | AC298: =+Y298*AB298*R298 -> 0 | AD298: =+AC298-X298 -> 0 | AE298: =IFERROR(AD298/AC298,0) -> 0
B299: FI | D299: Transfer | J299: Kemi: Private transfer to Kemi cruise port | Q299: 0 | R299: 0 | S299: =+Q299*R299 -> 0 | T299: 0 | U299: =S299*(1-T299) -> 0 | V299: EUR | W299: =IFERROR(VLOOKUP(V299,Curr!$B$2:$C$13,2,FALSE),0) -> 11 | X299: =U299*W299 -> 0 | Y299: =Q299 -> 0 | Z299: =+Y299*R299 -> 0 | AA299: EUR | AB299: =IFERROR(VLOOKUP(AA299,Curr!$B$2:$C$13,2,FALSE),0) -> 11 | AC299: =+Y299*AB299*R299 -> 0 | AD299: =+AC299-X299 -> 0 | AE299: =IFERROR(AD299/AC299,0) -> 0
B300: FI | D300: Transfer | J300: Kemijärvi: Self transfer to your accommodation | Q300: 0 | R300: 0 | S300: =+Q300*R300 -> 0 | T300: 0 | U300: =S300*(1-T300) -> 0 | V300: EUR | W300: =IFERROR(VLOOKUP(V300,Curr!$B$2:$C$13,2,FALSE),0) -> 11 | X300: =U300*W300 -> 0 | Y300: =Q300 -> 0 | Z300: =+Y300*R300 -> 0 | AA300: EUR | AB300: =IFERROR(VLOOKUP(AA300,Curr!$B$2:$C$13,2,FALSE),0) -> 11 | AC300: =+Y300*AB300*R300 -> 0 | AD300: =+AC300-X300 -> 0 | AE300: =IFERROR(AD300/AC300,0) -> 0
... B435: FI | D435: Transfer | J435: Kakslauttanen: Self transfer to Ivalo Airport | Q435: 0 | R435: 0 | S435: =+Q435*R435 -> 0 | T435: 0 | U435: =S435*(1-T435) -> 0 | V435: EUR | W435: =IFERROR(VLOOKUP(V435,Curr!$B$2:$C$13,2,FALSE),0) -> 11 | X435: =U435*W435 -> 0 | Y435: =Q435 -> 0 | Z435: =+Y435*R435 -> 0 | AA435: EUR | AB435: =IFERROR(VLOOKUP(AA435,Curr!$B$2:$C$13,2,FALSE),0) -> 11 | AC435: =+Y435*AB435*R435 -> 0 | AD435: =+AC435-X435 -> 0 | AE435: =IFERROR(AD435/AC435,0) -> 0
B436: FI | D436: Transfer | J436: Kakslauttanen: Shuttle transfer to Ivalo Airport | Q436: 49 | R436: 0 | S436: =+Q436*R436 -> 0 | T436: 0 | U436: =S436*(1-T436) -> 0 | V436: EUR | W436: =IFERROR(VLOOKUP(V436,Curr!$B$2:$C$13,2,FALSE),0) -> 11 | X436: =U436*W436 -> 0 | Y436: =Q436/0.8 -> 61.25 | Z436: =+Y436*R436 -> 0 | AA436: EUR | AB436: =IFERROR(VLOOKUP(AA436,Curr!$B$2:$C$13,2,FALSE),0) -> 11 | AC436: =+Y436*AB436*R436 -> 0 | AD436: =+AC436-X436 -> 0 | AE436: =IFERROR(AD436/AC436,0) -> 0
B437: FI | D437: Transfer | J437: Kakslauttanen: Self transfer to Kakslauttanen bus stop | Q437: 0 | R437: 0 | S437: =+Q437*R437 -> 0 | T437: 0 | U437: =S437*(1-T437) -> 0 | V437: EUR | W437: =IFERROR(VLOOKUP(V437,Curr!$B$2:$C$13,2,FALSE),0) -> 11 | X437: =U437*W437 -> 0 | Y437: =Q437 -> 0 | Z437: =+Y437*R437 -> 0 | AA437: EUR | AB437: =IFERROR(VLOOKUP(AA437,Curr!$B$2:$C$13,2,FALSE),0) -> 11 | AC437: =+Y437*AB437*R437 -> 0 | AD437: =+AC437-X437 -> 0 | AE437: =IFERROR(AD437/AC437,0) -> 0
B438: NO | D438: Transfer | J438: Oslo: Self transfer to your accommodation | Q438: 0 | R438: 0 | S438: =+Q438*R438 -> 0 | T438: 0 | U438: =S438*(1-T438) -> 0 | V438: NOK | W438: =IFERROR(VLOOKUP(V438,Curr!$B$2:$C$13,2,FALSE),0) -> 1 | X438: =U438*W438 -> 0 | Y438: =Q438 -> 0 | Z438: =+Y438*R438 -> 0 | AA438: EUR | AB438: =IFERROR(VLOOKUP(AA438,Curr!$B$2:$C$13,2,FALSE),0) -> 11 | AC438: =+Y438*AB438*R438 -> 0 | AD438: =+AC438-X438 -> 0 | AE438: =IFERROR(AD438/AC438,0) -> 0
B439: NO | D439: Transfer | J439: Oslo: Private transfer to your accommodation | Q439: 2200 | R439: 1 | S439: =+Q439*R439 -> 2200 | T439: 0 | U439: =S439*(1-T439) -> 2200 | V439: NOK | W439: =IFERROR(VLOOKUP(V439,Curr!$B$2:$C$13,2,FALSE),0) -> 1 | X439: =U439*W439 -> 2200 | Y439: =Q439/11/0.8 -> 250 | Z439: =+Y439*R439 -> 250 | AA439: EUR | AB439: =IFERROR(VLOOKUP(AA439,Curr!$B$2:$C$13,2,FALSE),0) -> 11 | AC439: =+Y439*AB439*R439 -> 2750 | AD439: =+AC439-X439 -> 550 | AE439: =IFERROR(AD439/AC439,0) -> 0.2
B440: NO | D440: Transfer | J440: Oslo: Self transfer to Oslo Airport | Q440: 0 | R440: 0 | S440: =+Q440*R440 -> 0 | T440: 0 | U440: =S440*(1-T440) -> 0 | V440: NOK | W440: =IFERROR(VLOOKUP(V440,Curr!$B$2:$C$13,2,FALSE),0) -> 1 | X440: =U440*W440 -> 0 | Y440: =Q440 -> 0 | Z440: =+Y440*R440 -> 0 | AA440: EUR | AB440: =IFERROR(VLOOKUP(AA440,Curr!$B$2:$C$13,2,FALSE),0) -> 11 | AC440: =+Y440*AB440*R440 -> 0 | AD440: =+AC440-X440 -> 0 | AE440: =IFERROR(AD440/AC440,0) -> 0
B441: NO | D441: Transfer | J441: Oslo: Private transfer to Oslo Airport | Q441: 2200 | R441: 1 | S441: =+Q441*R441 -> 2200 | T441: 0 | U441: =S441*(1-T441) -> 2200 | V441: NOK | W441: =IFERROR(VLOOKUP(V441,Curr!$B$2:$C$13,2,FALSE),0) -> 1 | X441: =U441*W441 -> 2200 | Y441: =Q441/11/0.8 -> 250 | Z441: =+Y441*R441 -> 250 | AA441: EUR | AB441: =IFERROR(VLOOKUP(AA441,Curr!$B$2:$C$13,2,FALSE),0) -> 11 | AC441: =+Y441*AB441*R441 -> 2750 | AD441: =+AC441-X441 -> 550 | AE441: =IFERROR(AD441/AC441,0) -> 0.2
B442: NO | D442: Transfer | J442: Oslo: Self transfer to Oslo Central Station | Q442: 0 | R442: 0 | S442: =+Q442*R442 -> 0 | T442: 0 | U442: =S442*(1-T442) -> 0 | V442: NOK | W442: =IFERROR(VLOOKUP(V442,Curr!$B$2:$C$13,2,FALSE),0) -> 1 | X442: =U442*W442 -> 0 | Y442: =Q442 -> 0 | Z442: =+Y442*R442 -> 0 | AA442: EUR | AB442: =IFERROR(VLOOKUP(AA442,Curr!$B$2:$C$13,2,FALSE),0) -> 11 | AC442: =+Y442*AB442*R442 -> 0 | AD442: =+AC442-X442 -> 0 | AE442: =IFERROR(AD442/AC442,0) -> 0
B443: NO | D443: Transfer | J443: Oslo: Private transfer to Oslo Central Station | Q443: 1200 | R443: 1 | S443: =+Q443*R443 -> 1200 | T443: 0 | U443: =S443*(1-T443) -> 1200 | V443: NOK | W443: =IFERROR(VLOOKUP(V443,Curr!$B$2:$C$13,2,FALSE),0) -> 1 | X443: =U443*W443 -> 1200 | Y443: =Q443/11/0.8 -> 136.36364 | Z443: =+Y443*R443 -> 136.36364 | AA443: EUR | AB443: =IFERROR(VLOOKUP(AA443,Curr!$B$2:$C$13,2,FALSE),0) -> 11 | AC443: =+Y443*AB443*R443 -> 1500 | AD443: =+AC443-X443 -> 300 | AE443: =IFERROR(AD443/AC443,0) -> 0.2
B444: NO | D444: Transfer | J444: Oslo: Self transfer to Oslo Bus Terminal | Q444: 0 | R444: 0 | S444: =+Q444*R444 -> 0 | T444: 0 | U444: =S444*(1-T444) -> 0 | V444: NOK | W444: =IFERROR(VLOOKUP(V444,Curr!$B$2:$C$13,2,FALSE),0) -> 1 | X444: =U444*W444 -> 0 | Y444: =Q444 -> 0 | Z444: =+Y444*R444 -> 0 | AA444: EUR | AB444: =IFERROR(VLOOKUP(AA444,Curr!$B$2:$C$13,2,FALSE),0) -> 11 | AC444: =+Y444*AB444*R444 -> 0 | AD444: =+AC444-X444 -> 0 | AE444: =IFERROR(AD444/AC444,0) -> 0
B445: NO | D445: Transfer | J445: Oslo: Private transfer to Oslo Bus Terminal | Q445: 1200 | R445: 1 | S445: =+Q445*R445 -> 1200 | T445: 0 | U445: =S445*(1-T445) -> 1200 | V445: NOK | W445: =IFERROR(VLOOKUP(V445,Curr!$B$2:$C$13,2,FALSE),0) -> 1 | X445: =U445*W445 -> 1200 | Y445: =Q445/11/0.8 -> 136.36364 | Z445: =+Y445*R445 -> 136.36364 | AA445: EUR | AB445: =IFERROR(VLOOKUP(AA445,Curr!$B$2:$C$13,2,FALSE),0) -> 11 | AC445: =+Y445*AB445*R445 -> 1500 | AD445: =+AC445-X445 -> 300 | AE445: =IFERROR(AD445/AC445,0) -> 0.2
B446: NO | D446: Transfer | J446: Oslo: Self transfer to Oslo ferry terminal | Q446: 0 | R446: 0 | S446: =+Q446*R446 -> 0 | T446: 0 | U446: =S446*(1-T446) -> 0 | V446: NOK | W446: =IFERROR(VLOOKUP(V446,Curr!$B$2:$C$13,2,FALSE),0) -> 1 | X446: =U446*W446 -> 0 | Y446: =Q446 -> 0 | Z446: =+Y446*R446 -> 0 | AA446: EUR | AB446: =IFERROR(VLOOKUP(AA446,Curr!$B$2:$C$13,2,FALSE),0) -> 11 | AC446: =+Y446*AB446*R446 -> 0 | AD446: =+AC446-X446 -> 0 | AE446: =IFERROR(AD446/AC446,0) -> 0
B447: NO | D447: Transfer | J447: Oslo: Private transfer to Oslo ferry terminal | Q447: 1200 | R447: 1 | S447: =+Q447*R447 -> 1200 | T447: 0 | U447: =S447*(1-T447) -> 1200 | V447: NOK | W447: =IFERROR(VLOOKUP(V447,Curr!$B$2:$C$13,2,FALSE),0) -> 1 | X447: =U447*W447 -> 1200 | Y447: =Q447/11/0.8 -> 136.36364 | Z447: =+Y447*R447 -> 136.36364 | AA447: EUR | AB447: =IFERROR(VLOOKUP(AA447,Curr!$B$2:$C$13,2,FALSE),0) -> 11 | AC447: =+Y447*AB447*R447 -> 1500 | AD447: =+AC447-X447 -> 300 | AE447: =IFERROR(AD447/AC447,0) -> 0.2
B448: NO | D448: Transfer | J448: Oslo: Self transfer to Oslo cruise port | Q448: 0 | R448: 0 | S448: =+Q448*R448 -> 0 | T448: 0 | U448: =S448*(1-T448) -> 0 | V448: NOK | W448: =IFERROR(VLOOKUP(V448,Curr!$B$2:$C$13,2,FALSE),0) -> 1 | X448: =U448*W448 -> 0 | Y448: =Q448 -> 0 | Z448: =+Y448*R448 -> 0 | AA448: EUR | AB448: =IFERROR(VLOOKUP(AA448,Curr!$B$2:$C$13,2,FALSE),0) -> 11 | AC448: =+Y448*AB448*R448 -> 0 | AD448: =+AC448-X448 -> 0 | AE448: =IFERROR(AD448/AC448,0) -> 0
B449: NO | D449: Transfer | J449: Oslo: Private transfer to Oslo cruise port | Q449: 1200 | R449: 1 | S449: =+Q449*R449 -> 1200 | T449: 0 | U449: =S449*(1-T449) -> 1200 | V449: NOK | W449: =IFERROR(VLOOKUP(V449,Curr!$B$2:$C$13,2,FALSE),0) -> 1 | X449: =U449*W449 -> 1200 | Y449: =Q449/11/0.8 -> 136.36364 | Z449: =+Y449*R449 -> 136.36364 | AA449: EUR | AB449: =IFERROR(VLOOKUP(AA449,Curr!$B$2:$C$13,2,FALSE),0) -> 11 | AC449: =+Y449*AB449*R449 -> 1500 | AD449: =+AC449-X449 -> 300 | AE449: =IFERROR(AD449/AC449,0) -> 0.2
B450: NO | D450: Transfer | J450: Bergen: Self transfer to your accommodation | Q450: 0 | R450: 0 | S450: =+Q450*R450 -> 0 | T450: 0 | U450: =S450*(1-T450) -> 0 | V450: NOK | W450: =IFERROR(VLOOKUP(V450,Curr!$B$2:$C$13,2,FALSE),0) -> 1 | X450: =U450*W450 -> 0 | Y450: =Q450 -> 0 | Z450: =+Y450*R450 -> 0 | AA450: EUR | AB450: =IFERROR(VLOOKUP(AA450,Curr!$B$2:$C$13,2,FALSE),0) -> 11 | AC450: =+Y450*AB450*R450 -> 0 | AD450: =+AC450-X450 -> 0 | AE450: =IFERROR(AD450/AC450,0) -> 0
B451: NO | D451: Transfer | J451: Bergen: Private transfer to your accommodation | Q451: 1890 | R451: 1 | S451: =+Q451*R451 -> 1890 | T451: 0.15 | U451: =S451*(1-T451) -> 1606.5 | V451: NOK | W451: =IFERROR(VLOOKUP(V451,Curr!$B$2:$C$13,2,FALSE),0) -> 1 | X451: =U451*W451 -> 1606.5 | Y451: =Q451/11/0.85 -> 202.13904 | Z451: =+Y451*R451 -> 202.13904 | AA451: EUR | AB451: =IFERROR(VLOOKUP(AA451,Curr!$B$2:$C$13,2,FALSE),0) -> 11 | AC451: =+Y451*AB451*R451 -> 2223.5294 | AD451: =+AC451-X451 -> 617.02941 | AE451: =IFERROR(AD451/AC451,0) -> 0.2775
B452: NO | D452: Transfer | J452: Bergen: Self transfer to Bergen Airport | Q452: 0 | R452: 0 | S452: =+Q452*R452 -> 0 | T452: 0 | U452: =S452*(1-T452) -> 0 | V452: NOK | W452: =IFERROR(VLOOKUP(V452,Curr!$B$2:$C$13,2,FALSE),0) -> 1 | X452: =U452*W452 -> 0 | Y452: =Q452 -> 0 | Z452: =+Y452*R452 -> 0 | AA452: EUR | AB452: =IFERROR(VLOOKUP(AA452,Curr!$B$2:$C$13,2,FALSE),0) -> 11 | AC452: =+Y452*AB452*R452 -> 0 | AD452: =+AC452-X452 -> 0 | AE452: =IFERROR(AD452/AC452,0) -> 0
B453: NO | D453: Transfer | J453: Bergen: Private transfer to Bergen Airport | Q453: 1890 | R453: 1 | S453: =+Q453*R453 -> 1890 | T453: 0.15 | U453: =S453*(1-T453) -> 1606.5 | V453: NOK | W453: =IFERROR(VLOOKUP(V453,Curr!$B$2:$C$13,2,FALSE),0) -> 1 | X453: =U453*W453 -> 1606.5 | Y453: =Q453/11/0.85 -> 202.13904 | Z453: =+Y453*R453 -> 202.13904 | AA453: EUR | AB453: =IFERROR(VLOOKUP(AA453,Curr!$B$2:$C$13,2,FALSE),0) -> 11 | AC453: =+Y453*AB453*R453 -> 2223.5294 | AD453: =+AC453-X453 -> 617.02941 | AE453: =IFERROR(AD453/AC453,0) -> 0.2775
B454: NO | D454: Transfer | J454: Bergen: Self transfer to Bergen railway station | Q454: 0 | R454: 0 | S454: =+Q454*R454 -> 0 | T454: 0 | U454: =S454*(1-T454) -> 0 | V454: NOK | W454: =IFERROR(VLOOKUP(V454,Curr!$B$2:$C$13,2,FALSE),0) -> 1 | X454: =U454*W454 -> 0 | Y454: =Q454 -> 0 | Z454: =+Y454*R454 -> 0 | AA454: EUR | AB454: =IFERROR(VLOOKUP(AA454,Curr!$B$2:$C$13,2,FALSE),0) -> 11 | AC454: =+Y454*AB454*R454 -> 0 | AD454: =+AC454-X454 -> 0 | AE454: =IFERROR(AD454/AC454,0) -> 0
B455: NO | D455: Transfer | J455: Bergen: Private transfer to Bergen railway station | Q455: 1290 | R455: 1 | S455: =+Q455*R455 -> 1290 | T455: 0.15 | U455: =S455*(1-T455) -> 1096.5 | V455: NOK | W455: =IFERROR(VLOOKUP(V455,Curr!$B$2:$C$13,2,FALSE),0) -> 1 | X455: =U455*W455 -> 1096.5 | Y455: =Q455/11/0.85 -> 137.96791 | Z455: =+Y455*R455 -> 137.96791 | AA455: EUR | AB455: =IFERROR(VLOOKUP(AA455,Curr!$B$2:$C$13,2,FALSE),0) -> 11 | AC455: =+Y455*AB455*R455 -> 1517.6471 | AD455: =+AC455-X455 -> 421.14706 | AE455: =IFERROR(AD455/AC455,0) -> 0.2775
B456: NO | D456: Transfer | J456: Bergen: Self transfer to Bergen Bus Station | Q456: 0 | R456: 0 | S456: =+Q456*R456 -> 0 | T456: 0 | U456: =S456*(1-T456) -> 0 | V456: NOK | W456: =IFERROR(VLOOKUP(V456,Curr!$B$2:$C$13,2,FALSE),0) -> 1 | X456: =U456*W456 -> 0 | Y456: =Q456 -> 0 | Z456: =+Y456*R456 -> 0 | AA456: EUR | AB456: =IFERROR(VLOOKUP(AA456,Curr!$B$2:$C$13,2,FALSE),0) -> 11 | AC456: =+Y456*AB456*R456 -> 0 | AD456: =+AC456-X456 -> 0 | AE456: =IFERROR(AD456/AC456,0) -> 0
B457: NO | D457: Transfer | J457: Bergen: Private transfer to Bergen Bus Station | Q457: 1290 | R457: 1 | S457: =+Q457*R457 -> 1290 | T457: 0.15 | U457: =S457*(1-T457) -> 1096.5 | V457: NOK | W457: =IFERROR(VLOOKUP(V457,Curr!$B$2:$C$13,2,FALSE),0) -> 1 | X457: =U457*W457 -> 1096.5 | Y457: =Q457/11/0.85 -> 137.96791 | Z457: =+Y457*R457 -> 137.96791 | AA457: EUR | AB457: =IFERROR(VLOOKUP(AA457,Curr!$B$2:$C$13,2,FALSE),0) -> 11 | AC457: =+Y457*AB457*R457 -> 1517.6471 | AD457: =+AC457-X457 -> 421.14706 | AE457: =IFERROR(AD457/AC457,0) -> 0.2775
B458: NO | D458: Transfer | J458: Bergen: Self transfer to Bergen ferry terminal | Q458: 0 | R458: 0 | S458: =+Q458*R458 -> 0 | T458: 0 | U458: =S458*(1-T458) -> 0 | V458: NOK | W458: =IFERROR(VLOOKUP(V458,Curr!$B$2:$C$13,2,FALSE),0) -> 1 | X458: =U458*W458 -> 0 | Y458: =Q458 -> 0 | Z458: =+Y458*R458 -> 0 | AA458: EUR | AB458: =IFERROR(VLOOKUP(AA458,Curr!$B$2:$C$13,2,FALSE),0) -> 11 | AC458: =+Y458*AB458*R458 -> 0 | AD458: =+AC458-X458 -> 0 | AE458: =IFERROR(AD458/AC458,0) -> 0
B459: NO | D459: Transfer | J459: Bergen: Private transfer to Bergen ferry terminal | Q459: 1290 | R459: 1 | S459: =+Q459*R459 -> 1290 | T459: 0.15 | U459: =S459*(1-T459) -> 1096.5 | V459: NOK | W459: =IFERROR(VLOOKUP(V459,Curr!$B$2:$C$13,2,FALSE),0) -> 1 | X459: =U459*W459 -> 1096.5 | Y459: =Q459/11/0.85 -> 137.96791 | Z459: =+Y459*R459 -> 137.96791 | AA459: EUR | AB459: =IFERROR(VLOOKUP(AA459,Curr!$B$2:$C$13,2,FALSE),0) -> 11 | AC459: =+Y459*AB459*R459 -> 1517.6471 | AD459: =+AC459-X459 -> 421.14706 | AE459: =IFERROR(AD459/AC459,0) -> 0.2775
B460: NO | D460: Transfer | J460: Bergen: Self transfer to Bergen cruise port | Q460: 0 | R460: 0 | S460: =+Q460*R460 -> 0 | T460: 0 | U460: =S460*(1-T460) -> 0 | V460: NOK | W460: =IFERROR(VLOOKUP(V460,Curr!$B$2:$C$13,2,FALSE),0) -> 1 | X460: =U460*W460 -> 0 | Y460: =Q460 -> 0 | Z460: =+Y460*R460 -> 0 | AA460: EUR | AB460: =IFERROR(VLOOKUP(AA460,Curr!$B$2:$C$13,2,FALSE),0) -> 11 | AC460: =+Y460*AB460*R460 -> 0 | AD460: =+AC460-X460 -> 0 | AE460: =IFERROR(AD460/AC460,0) -> 0
B461: NO | D461: Transfer | J461: Bergen: Private transfer to Bergen cruise port | Q461: 1290 | R461: 1 | S461: =+Q461*R461 -> 1290 | T461: 0.15 | U461: =S461*(1-T461) -> 1096.5 | V461: NOK | W461: =IFERROR(VLOOKUP(V461,Curr!$B$2:$C$13,2,FALSE),0) -> 1 | X461: =U461*W461 -> 1096.5 | Y461: =Q461/11/0.85 -> 137.96791 | Z461: =+Y461*R461 -> 137.96791 | AA461: EUR | AB461: =IFERROR(VLOOKUP(AA461,Curr!$B$2:$C$13,2,FALSE),0) -> 11 | AC461: =+Y461*AB461*R461 -> 1517.6471 | AD461: =+AC461-X461 -> 421.14706 | AE461: =IFERROR(AD461/AC461,0) -> 0.2775
B462: NO | D462: Transfer | J462: Bergen: Self transfer to Hurtigruten terminal | Q462: 0 | R462: 0 | S462: =+Q462*R462 -> 0 | T462: 0 | U462: =S462*(1-T462) -> 0 | V462: NOK | W462: =IFERROR(VLOOKUP(V462,Curr!$B$2:$C$13,2,FALSE),0) -> 1 | X462: =U462*W462 -> 0 | Y462: =Q462 -> 0 | Z462: =+Y462*R462 -> 0 | AA462: EUR | AB462: =IFERROR(VLOOKUP(AA462,Curr!$B$2:$C$13,2,FALSE),0) -> 11 | AC462: =+Y462*AB462*R462 -> 0 | AD462: =+AC462-X462 -> 0 | AE462: =IFERROR(AD462/AC462,0) -> 0
B463: NO | D463: Transfer | J463: Bergen: Private transfer to Hurtigruten terminal | Q463: 1290 | R463: 1 | S463: =+Q463*R463 -> 1290 | T463: 0.15 | U463: =S463*(1-T463) -> 1096.5 | V463: NOK | W463: =IFERROR(VLOOKUP(V463,Curr!$B$2:$C$13,2,FALSE),0) -> 1 | X463: =U463*W463 -> 1096.5 | Y463: =Q463/11/0.85 -> 137.96791 | Z463: =+Y463*R463 -> 137.96791 | AA463: EUR | AB463: =IFERROR(VLOOKUP(AA463,Curr!$B$2:$C$13,2,FALSE),0) -> 11 | AC463: =+Y463*AB463*R463 -> 1517.6471 | AD463: =+AC463-X463 -> 421.14706 | AE463: =IFERROR(AD463/AC463,0) -> 0.2775
B464: NO | D464: Transfer | J464: Tromsø: Self transfer to your accommodation | Q464: 0 | R464: 0 | S464: =+Q464*R464 -> 0 | T464: 0 | U464: =S464*(1-T464) -> 0 | V464: NOK | W464: =IFERROR(VLOOKUP(V464,Curr!$B$2:$C$13,2,FALSE),0) -> 1 | X464: =U464*W464 -> 0 | Y464: =Q464 -> 0 | Z464: =+Y464*R464 -> 0 | AA464: EUR | AB464: =IFERROR(VLOOKUP(AA464,Curr!$B$2:$C$13,2,FALSE),0) -> 11 | AC464: =+Y464*AB464*R464 -> 0 | AD464: =+AC464-X464 -> 0 | AE464: =IFERROR(AD464/AC464,0) -> 0
B465: NO | D465: Transfer | J465: Tromsø: Private transfer to your accommodation | Q465: 1800 | R465: 1 | S465: =+Q465*R465 -> 1800 | T465: 0 | U465: =S465*(1-T465) -> 1800 | V465: NOK | W465: =IFERROR(VLOOKUP(V465,Curr!$B$2:$C$13,2,FALSE),0) -> 1 | X465: =U465*W465 -> 1800 | Y465: =Q465/11/0.8 -> 204.54545 | Z465: =+Y465*R465 -> 204.54545 | AA465: EUR | AB465: =IFERROR(VLOOKUP(AA465,Curr!$B$2:$C$13,2,FALSE),0) -> 11 | AC465: =+Y465*AB465*R465 -> 2250 | AD465: =+AC465-X465 -> 450 | AE465: =IFERROR(AD465/AC465,0) -> 0.2
B466: NO | D466: Transfer | J466: Tromsø: Self transfer to Tromsø Airport | Q466: 0 | R466: 0 | S466: =+Q466*R466 -> 0 | T466: 0 | U466: =S466*(1-T466) -> 0 | V466: NOK | W466: =IFERROR(VLOOKUP(V466,Curr!$B$2:$C$13,2,FALSE),0) -> 1 | X466: =U466*W466 -> 0 | Y466: =Q466 -> 0 | Z466: =+Y466*R466 -> 0 | AA466: EUR | AB466: =IFERROR(VLOOKUP(AA466,Curr!$B$2:$C$13,2,FALSE),0) -> 11 | AC466: =+Y466*AB466*R466 -> 0 | AD466: =+AC466-X466 -> 0 | AE466: =IFERROR(AD466/AC466,0) -> 0
B467: NO | D467: Transfer | J467: Tromsø: Private transfer to Tromsø Airport | Q467: 1800 | R467: 1 | S467: =+Q467*R467 -> 1800 | T467: 0 | U467: =S467*(1-T467) -> 1800 | V467: NOK | W467: =IFERROR(VLOOKUP(V467,Curr!$B$2:$C$13,2,FALSE),0) -> 1 | X467: =U467*W467 -> 1800 | Y467: =Q467/11/0.8 -> 204.54545 | Z467: =+Y467*R467 -> 204.54545 | AA467: EUR | AB467: =IFERROR(VLOOKUP(AA467,Curr!$B$2:$C$13,2,FALSE),0) -> 11 | AC467: =+Y467*AB467*R467 -> 2250 | AD467: =+AC467-X467 -> 450 | AE467: =IFERROR(AD467/AC467,0) -> 0.2
B468: NO | D468: Transfer | J468: Tromsø: Self transfer to Prostneset Bus and Ferry Terminal | Q468: 0 | R468: 0 | S468: =+Q468*R468 -> 0 | T468: 0 | U468: =S468*(1-T468) -> 0 | V468: NOK | W468: =IFERROR(VLOOKUP(V468,Curr!$B$2:$C$13,2,FALSE),0) -> 1 | X468: =U468*W468 -> 0 | Y468: =Q468 -> 0 | Z468: =+Y468*R468 -> 0 | AA468: EUR | AB468: =IFERROR(VLOOKUP(AA468,Curr!$B$2:$C$13,2,FALSE),0) -> 11 | AC468: =+Y468*AB468*R468 -> 0 | AD468: =+AC468-X468 -> 0 | AE468: =IFERROR(AD468/AC468,0) -> 0
B469: NO | D469: Transfer | J469: Tromsø: Private transfer to Prostneset Bus and Ferry Terminal | Q469: 800 | R469: 1 | S469: =+Q469*R469 -> 800 | T469: 0 | U469: =S469*(1-T469) -> 800 | V469: NOK | W469: =IFERROR(VLOOKUP(V469,Curr!$B$2:$C$13,2,FALSE),0) -> 1 | X469: =U469*W469 -> 800 | Y469: =Q469/11/0.8 -> 90.909091 | Z469: =+Y469*R469 -> 90.909091 | AA469: EUR | AB469: =IFERROR(VLOOKUP(AA469,Curr!$B$2:$C$13,2,FALSE),0) -> 11 | AC469: =+Y469*AB469*R469 -> 1000 | AD469: =+AC469-X469 -> 200 | AE469: =IFERROR(AD469/AC469,0) -> 0.2
B470: NO | D470: Transfer | J470: Tromsø: Self transfer to Tromsø cruise port | Q470: 0 | R470: 0 | S470: =+Q470*R470 -> 0 | T470: 0 | U470: =S470*(1-T470) -> 0 | V470: NOK | W470: =IFERROR(VLOOKUP(V470,Curr!$B$2:$C$13,2,FALSE),0) -> 1 | X470: =U470*W470 -> 0 | Y470: =Q470 -> 0 | Z470: =+Y470*R470 -> 0 | AA470: EUR | AB470: =IFERROR(VLOOKUP(AA470,Curr!$B$2:$C$13,2,FALSE),0) -> 11 | AC470: =+Y470*AB470*R470 -> 0 | AD470: =+AC470-X470 -> 0 | AE470: =IFERROR(AD470/AC470,0) -> 0
B471: NO | D471: Transfer | J471: Tromsø: Private transfer to Tromsø cruise port | Q471: 800 | R471: 1 | S471: =+Q471*R471 -> 800 | T471: 0 | U471: =S471*(1-T471) -> 800 | V471: NOK | W471: =IFERROR(VLOOKUP(V471,Curr!$B$2:$C$13,2,FALSE),0) -> 1 | X471: =U471*W471 -> 800 | Y471: =Q471/11/0.8 -> 90.909091 | Z471: =+Y471*R471 -> 90.909091 | AA471: EUR | AB471: =IFERROR(VLOOKUP(AA471,Curr!$B$2:$C$13,2,FALSE),0) -> 11 | AC471: =+Y471*AB471*R471 -> 1000 | AD471: =+AC471-X471 -> 200 | AE471: =IFERROR(AD471/AC471,0) -> 0.2
B472: NO | D472: Transfer | J472: Tromsø: Self transfer to Hurtigruten terminal | Q472: 0 | R472: 0 | S472: =+Q472*R472 -> 0 | T472: 0 | U472: =S472*(1-T472) -> 0 | V472: NOK | W472: =IFERROR(VLOOKUP(V472,Curr!$B$2:$C$13,2,FALSE),0) -> 1 | X472: =U472*W472 -> 0 | Y472: =Q472 -> 0 | Z472: =+Y472*R472 -> 0 | AA472: EUR | AB472: =IFERROR(VLOOKUP(AA472,Curr!$B$2:$C$13,2,FALSE),0) -> 11 | AC472: =+Y472*AB472*R472 -> 0 | AD472: =+AC472-X472 -> 0 | AE472: =IFERROR(AD472/AC472,0) -> 0
B473: NO | D473: Transfer | J473: Tromsø: Private transfer to Hurtigruten terminal | Q473: 800 | R473: 1 | S473: =+Q473*R473 -> 800 | T473: 0 | U473: =S473*(1-T473) -> 800 | V473: NOK | W473: =IFERROR(VLOOKUP(V473,Curr!$B$2:$C$13,2,FALSE),0) -> 1 | X473: =U473*W473 -> 800 | Y473: =Q473/11/0.8 -> 90.909091 | Z473: =+Y473*R473 -> 90.909091 | AA473: EUR | AB473: =IFERROR(VLOOKUP(AA473,Curr!$B$2:$C$13,2,FALSE),0) -> 11 | AC473: =+Y473*AB473*R473 -> 1000 | AD473: =+AC473-X473 -> 200 | AE473: =IFERROR(AD473/AC473,0) -> 0.2
B474: NO | D474: Transfer | J474: Stavanger: Self transfer to your accommodation | Q474: 0 | R474: 0 | S474: =+Q474*R474 -> 0 | T474: 0 | U474: =S474*(1-T474) -> 0 | V474: NOK | W474: =IFERROR(VLOOKUP(V474,Curr!$B$2:$C$13,2,FALSE),0) -> 1 | X474: =U474*W474 -> 0 | Y474: =Q474 -> 0 | Z474: =+Y474*R474 -> 0 | AA474: EUR | AB474: =IFERROR(VLOOKUP(AA474,Curr!$B$2:$C$13,2,FALSE),0) -> 11 | AC474: =+Y474*AB474*R474 -> 0 | AD474: =+AC474-X474 -> 0 | AE474: =IFERROR(AD474/AC474,0) -> 0
B475: NO | D475: Transfer | J475: Stavanger: Private transfer to your accommodation | Q475: 2200 | R475: 1 | S475: =+Q475*R475 -> 2200 | T475: 0 | U475: =S475*(1-T475) -> 2200 | V475: NOK | W475: =IFERROR(VLOOKUP(V475,Curr!$B$2:$C$13,2,FALSE),0) -> 1 | X475: =U475*W475 -> 2200 | Y475: =Q475/11/0.8 -> 250 | Z475: =+Y475*R475 -> 250 | AA475: EUR | AB475: =IFERROR(VLOOKUP(AA475,Curr!$B$2:$C$13,2,FALSE),0) -> 11 | AC475: =+Y475*AB475*R475 -> 2750 | AD475: =+AC475-X475 -> 550 | AE475: =IFERROR(AD475/AC475,0) -> 0.2
B476: NO | D476: Transfer | J476: Stavanger: Self transfer to Stavanger Airport | Q476: 0 | R476: 0 | S476: =+Q476*R476 -> 0 | T476: 0 | U476: =S476*(1-T476) -> 0 | V476: NOK | W476: =IFERROR(VLOOKUP(V476,Curr!$B$2:$C$13,2,FALSE),0) -> 1 | X476: =U476*W476 -> 0 | Y476: =Q476 -> 0 | Z476: =+Y476*R476 -> 0 | AA476: EUR | AB476: =IFERROR(VLOOKUP(AA476,Curr!$B$2:$C$13,2,FALSE),0) -> 11 | AC476: =+Y476*AB476*R476 -> 0 | AD476: =+AC476-X476 -> 0 | AE476: =IFERROR(AD476/AC476,0) -> 0
B477: NO | D477: Transfer | J477: Stavanger: Private transfer to Stavanger Airport | Q477: 2200 | R477: 1 | S477: =+Q477*R477 -> 2200 | T477: 0 | U477: =S477*(1-T477) -> 2200 | V477: NOK | W477: =IFERROR(VLOOKUP(V477,Curr!$B$2:$C$13,2,FALSE),0) -> 1 | X477: =U477*W477 -> 2200 | Y477: =Q477/11/0.8 -> 250 | Z477: =+Y477*R477 -> 250 | AA477: EUR | AB477: =IFERROR(VLOOKUP(AA477,Curr!$B$2:$C$13,2,FALSE),0) -> 11 | AC477: =+Y477*AB477*R477 -> 2750 | AD477: =+AC477-X477 -> 550 | AE477: =IFERROR(AD477/AC477,0) -> 0.2
B478: NO | D478: Transfer | J478: Stavanger: Self transfer to Stavanger railway station | Q478: 0 | R478: 0 | S478: =+Q478*R478 -> 0 | T478: 0 | U478: =S478*(1-T478) -> 0 | V478: NOK | W478: =IFERROR(VLOOKUP(V478,Curr!$B$2:$C$13,2,FALSE),0) -> 1 | X478: =U478*W478 -> 0 | Y478: =Q478 -> 0 | Z478: =+Y478*R478 -> 0 | AA478: EUR | AB478: =IFERROR(VLOOKUP(AA478,Curr!$B$2:$C$13,2,FALSE),0) -> 11 | AC478: =+Y478*AB478*R478 -> 0 | AD478: =+AC478-X478 -> 0 | AE478: =IFERROR(AD478/AC478,0) -> 0
B479: NO | D479: Transfer | J479: Stavanger: Private transfer to Stavanger railway station | Q479: 1200 | R479: 1 | S479: =+Q479*R479 -> 1200 | T479: 0 | U479: =S479*(1-T479) -> 1200 | V479: NOK | W479: =IFERROR(VLOOKUP(V479,Curr!$B$2:$C$13,2,FALSE),0) -> 1 | X479: =U479*W479 -> 1200 | Y479: =Q479/11/0.8 -> 136.36364 | Z479: =+Y479*R479 -> 136.36364 | AA479: EUR | AB479: =IFERROR(VLOOKUP(AA479,Curr!$B$2:$C$13,2,FALSE),0) -> 11 | AC479: =+Y479*AB479*R479 -> 1500 | AD479: =+AC479-X479 -> 300 | AE479: =IFERROR(AD479/AC479,0) -> 0.2
B480: NO | D480: Transfer | J480: Stavanger: Self transfer to Stavanger Bus Terminal | Q480: 0 | R480: 0 | S480: =+Q480*R480 -> 0 | T480: 0 | U480: =S480*(1-T480) -> 0 | V480: NOK | W480: =IFERROR(VLOOKUP(V480,Curr!$B$2:$C$13,2,FALSE),0) -> 1 | X480: =U480*W480 -> 0 | Y480: =Q480 -> 0 | Z480: =+Y480*R480 -> 0 | AA480: EUR | AB480: =IFERROR(VLOOKUP(AA480,Curr!$B$2:$C$13,2,FALSE),0) -> 11 | AC480: =+Y480*AB480*R480 -> 0 | AD480: =+AC480-X480 -> 0 | AE480: =IFERROR(AD480/AC480,0) -> 0
B481: NO | D481: Transfer | J481: Stavanger: Private transfer to Stavanger Bus Terminal | Q481: 1200 | R481: 1 | S481: =+Q481*R481 -> 1200 | T481: 0 | U481: =S481*(1-T481) -> 1200 | V481: NOK | W481: =IFERROR(VLOOKUP(V481,Curr!$B$2:$C$13,2,FALSE),0) -> 1 | X481: =U481*W481 -> 1200 | Y481: =Q481/11/0.8 -> 136.36364 | Z481: =+Y481*R481 -> 136.36364 | AA481: EUR | AB481: =IFERROR(VLOOKUP(AA481,Curr!$B$2:$C$13,2,FALSE),0) -> 11 | AC481: =+Y481*AB481*R481 -> 1500 | AD481: =+AC481-X481 -> 300 | AE481: =IFERROR(AD481/AC481,0) -> 0.2
B482: NO | D482: Transfer | J482: Stavanger: Self transfer to Stavanger ferry terminal | Q482: 0 | R482: 0 | S482: =+Q482*R482 -> 0 | T482: 0 | U482: =S482*(1-T482) -> 0 | V482: NOK | W482: =IFERROR(VLOOKUP(V482,Curr!$B$2:$C$13,2,FALSE),0) -> 1 | X482: =U482*W482 -> 0 | Y482: =Q482 -> 0 | Z482: =+Y482*R482 -> 0 | AA482: EUR | AB482: =IFERROR(VLOOKUP(AA482,Curr!$B$2:$C$13,2,FALSE),0) -> 11 | AC482: =+Y482*AB482*R482 -> 0 | AD482: =+AC482-X482 -> 0 | AE482: =IFERROR(AD482/AC482,0) -> 0
B483: NO | D483: Transfer | J483: Stavanger: Private transfer to Stavanger ferry terminal | Q483: 1200 | R483: 1 | S483: =+Q483*R483 -> 1200 | T483: 0 | U483: =S483*(1-T483) -> 1200 | V483: NOK | W483: =IFERROR(VLOOKUP(V483,Curr!$B$2:$C$13,2,FALSE),0) -> 1 | X483: =U483*W483 -> 1200 | Y483: =Q483/11/0.8 -> 136.36364 | Z483: =+Y483*R483 -> 136.36364 | AA483: EUR | AB483: =IFERROR(VLOOKUP(AA483,Curr!$B$2:$C$13,2,FALSE),0) -> 11 | AC483: =+Y483*AB483*R483 -> 1500 | AD483: =+AC483-X483 -> 300 | AE483: =IFERROR(AD483/AC483,0) -> 0.2
B484: NO | D484: Transfer | J484: Stavanger: Self transfer to Stavanger cruise port | Q484: 0 | R484: 0 | S484: =+Q484*R484 -> 0 | T484: 0 | U484: =S484*(1-T484) -> 0 | V484: NOK | W484: =IFERROR(VLOOKUP(V484,Curr!$B$2:$C$13,2,FALSE),0) -> 1 | X484: =U484*W484 -> 0 | Y484: =Q484 -> 0 | Z484: =+Y484*R484 -> 0 | AA484: EUR | AB484: =IFERROR(VLOOKUP(AA484,Curr!$B$2:$C$13,2,FALSE),0) -> 11 | AC484: =+Y484*AB484*R484 -> 0 | AD484: =+AC484-X484 -> 0 | AE484: =IFERROR(AD484/AC484,0) -> 0
...

Sheet Transport
B2: Dates:
B3: Pax:
B4: Rooming:
B6: ID | C6: Day | D6: Type | E6: From date | F6: To date | G6: From time | H6: To time | I6: Supplier | J6: Travel element | K6: Manual booking? | L6: Status | M6: Comments | N6: Non-refundable | O6: Refundable | P6: URL | Q6: Gross P per unit | R6: Units | S6: Gross P | T6: Supp Comm | U6: Net P | V6: Supp curr | W6: X-rate | X6: Net P NOK | Y6: Sales P per unit | Z6: Price | AA6: Sales curr | AB6: X-rate2 | AC6: Sales P NOK tot | AD6: GP NOK | AE6: GP % | AF6: VAT25 | AG6: VAT15 | AH6: VAT12 | AI6: VAT0-D | AJ6: VAT0-I
B7: NO | D7: Activity | J7: Oslo: Norway in a Nutshell to Bergen - Time: TBD - Meeting point: Oslo Central Station - Route: Train transfer Oslo to Myrdal, Train tranfser Myrdal to Flåm, Fjord Cruise Flåm to Gudvangen, Coach Transfer Gudvangen to Voss, Train transfer Voss to Bergen - Includes: Tickets | P7: https://www.fjordtours.com/en | Q7: 3500 | R7: 0 | S7: =+Q7*R7 -> 0 | T7: 0.08 | U7: =S7*(1-T7) -> 0 | V7: NOK | W7: =IFERROR(VLOOKUP(V7,Curr!$B$2:$C$13,2,FALSE),0) -> 1 | X7: =U7*W7 -> 0 | Y7: =Q7/11/0.9 -> 353.53535 | Z7: =+Y7*R7 -> 0 | AA7: EUR | AB7: =IFERROR(VLOOKUP(AA7,Curr!$B$2:$C$13,2,FALSE),0) -> 11 | AC7: =+Y7*AB7*R7 -> 0 | AD7: =+AC7-X7 -> 0 | AE7: =IFERROR(AD7/AC7,0) -> 0
B8: NO | D8: Activity | J8: Oslo: Norway in a Nutshell to Flåm - Time: TBD - Meeting point: Oslo Central Station - Route: Train transfer Oslo to Myrdal, Train tranfser Myrdal to Flåm - Includes: Tickets | P8: https://www.fjordtours.com/en | Q8: 3500 | R8: 0 | S8: =+Q8*R8 -> 0 | T8: 0.08 | U8: =S8*(1-T8) -> 0 | V8: NOK | W8: =IFERROR(VLOOKUP(V8,Curr!$B$2:$C$13,2,FALSE),0) -> 1 | X8: =U8*W8 -> 0 | Y8: =Q8/11/0.9 -> 353.53535 | Z8: =+Y8*R8 -> 0 | AA8: EUR | AB8: =IFERROR(VLOOKUP(AA8,Curr!$B$2:$C$13,2,FALSE),0) -> 11 | AC8: =+Y8*AB8*R8 -> 0 | AD8: =+AC8-X8 -> 0 | AE8: =IFERROR(AD8/AC8,0) -> 0
B9: NO | D9: Activity | J9: Flåm: Norway in a Nutshell to Bergen - Time: TBD - Meeting point: Flåm Harbor - Route: Fjord Cruise Flåm to Gudvangen, Coach Transfer Gudvangen to Voss, Train transfer Voss to Bergen - Includes: Tickets | P9: https://www.fjordtours.com/en | Q9: 0 | R9: 0 | S9: =+Q9*R9 -> 0 | T9: 0 | U9: =S9*(1-T9) -> 0 | V9: NOK | W9: =IFERROR(VLOOKUP(V9,Curr!$B$2:$C$13,2,FALSE),0) -> 1 | X9: =U9*W9 -> 0 | Y9: =Q9 -> 0 | Z9: =+Y9*R9 -> 0 | AA9: EUR | AB9: =IFERROR(VLOOKUP(AA9,Curr!$B$2:$C$13,2,FALSE),0) -> 11 | AC9: =+Y9*AB9*R9 -> 0 | AD9: =+AC9-X9 -> 0 | AE9: =IFERROR(AD9/AC9,0) -> 0
B10: NO | D10: Activity | J10: Bergen: Norway in a Nutshell to Oslo - Time: TBD - Meeting point: Bergen Train Station - Route: Train transfer Bergen to Voss, Coach transfer Voss to Gudvangen, Fjord Cruise Gudvangen to Flåm, Train transfer Flåm to Myrdal, Train Transfer Myrdal to Oslo - Includes: Tickets | O10: x | P10: https://www.fjordtours.com/en | Q10: 3500 | R10: 0 | S10: =+Q10*R10 -> 0 | T10: 0.08 | U10: =S10*(1-T10) -> 0 | V10: NOK | W10: =IFERROR(VLOOKUP(V10,Curr!$B$2:$C$13,2,FALSE),0) -> 1 | X10: =U10*W10 -> 0 | Y10: =Q10/11/0.9 -> 353.53535 | Z10: =+Y10*R10 -> 0 | AA10: EUR | AB10: =IFERROR(VLOOKUP(AA10,Curr!$B$2:$C$13,2,FALSE),0) -> 11 | AC10: =+Y10*AB10*R10 -> 0 | AD10: =+AC10-X10 -> 0 | AE10: =IFERROR(AD10/AC10,0) -> 0
B11: NO | D11: Activity | J11: Bergen: Norway in a Nutshell to Flåm - Time: TBD - Meeting point: Bergen Train Station - Route: Train transfer Bergen to Voss, Coach transfer Voss to Gudvangen, Fjord Cruise Gudvangen to Flåm - Includes: Tickets | O11: x | P11: https://www.fjordtours.com/en | Q11: 3500 | R11: 0 | S11: =+Q11*R11 -> 0 | T11: 0.08 | U11: =S11*(1-T11) -> 0 | V11: NOK | W11: =IFERROR(VLOOKUP(V11,Curr!$B$2:$C$13,2,FALSE),0) -> 1 | X11: =U11*W11 -> 0 | Y11: =Q11/11/0.9 -> 353.53535 | Z11: =+Y11*R11 -> 0 | AA11: EUR | AB11: =IFERROR(VLOOKUP(AA11,Curr!$B$2:$C$13,2,FALSE),0) -> 11 | AC11: =+Y11*AB11*R11 -> 0 | AD11: =+AC11-X11 -> 0 | AE11: =IFERROR(AD11/AC11,0) -> 0
B12: NO | D12: Activity | J12: Flåm: Norway in a Nutshell to Oslo - Time: TBD - Meeting point: Flåm Train Station - Route: Train transfer Flåm to Myrdal, Train Transfer Myrdal to Oslo - Includes: Tickets | O12: x | P12: https://www.fjordtours.com/en | Q12: 0 | R12: 0 | S12: =+Q12*R12 -> 0 | T12: 0 | U12: =S12*(1-T12) -> 0 | V12: NOK | W12: =IFERROR(VLOOKUP(V12,Curr!$B$2:$C$13,2,FALSE),0) -> 1 | X12: =U12*W12 -> 0 | Y12: =Q12 -> 0 | Z12: =+Y12*R12 -> 0 | AA12: EUR | AB12: =IFERROR(VLOOKUP(AA12,Curr!$B$2:$C$13,2,FALSE),0) -> 11 | AC12: =+Y12*AB12*R12 -> 0 | AD12: =+AC12-X12 -> 0 | AE12: =IFERROR(AD12/AC12,0) -> 0
B13: NO | D13: Activity | J13: Bergen: Norway in a Nutshell Bergen to Bergen - Time: TBD - Route: Route: Train transfer Bergen to Voss, Coach transfer Voss to Gudvangen, Fjord Cruise Gudvangen to Flåm, Train transfer Flåm to Myrdal, Train Transfer Myrdal to Bergen - Includes: Tickets | P13: https://www.fjordtours.com/en | Q13: 3000 | R13: 0 | S13: =+Q13*R13 -> 0 | T13: 0.08 | U13: =S13*(1-T13) -> 0 | V13: NOK | W13: =IFERROR(VLOOKUP(V13,Curr!$B$2:$C$13,2,FALSE),0) -> 1 | X13: =U13*W13 -> 0 | Y13: =Q13/11/0.9 -> 303.0303 | Z13: =+Y13*R13 -> 0 | AA13: EUR | AB13: =IFERROR(VLOOKUP(AA13,Curr!$B$2:$C$13,2,FALSE),0) -> 11 | AC13: =+Y13*AB13*R13 -> 0 | AD13: =+AC13-X13 -> 0 | AE13: =IFERROR(AD13/AC13,0) -> 0
B14: FI | D14: Coach | J14: Helsinki: Coach transfer to Porvoo - Time: TBD - Includes: Tickets | Q14: 0 | R14: 0 | S14: =+Q14*R14 -> 0 | T14: 0 | U14: =S14*(1-T14) -> 0 | V14: EUR | W14: =IFERROR(VLOOKUP(V14,Curr!$B$2:$C$13,2,FALSE),0) -> 11 | X14: =U14*W14 -> 0 | Y14: =Q14/0.8 -> 0 | Z14: =+Y14*R14 -> 0 | AA14: EUR | AB14: =IFERROR(VLOOKUP(AA14,Curr!$B$2:$C$13,2,FALSE),0) -> 11 | AC14: =+Y14*AB14*R14 -> 0 | AD14: =+AC14-X14 -> 0 | AE14: =IFERROR(AD14/AC14,0) -> 0
B15: FI | D15: Coach | J15: Helsinki: Coach transfer to Hanko - Time: TBD - Includes: Tickets | Q15: 0 | R15: 0 | S15: =+Q15*R15 -> 0 | T15: 0 | U15: =S15*(1-T15) -> 0 | V15: EUR | W15: =IFERROR(VLOOKUP(V15,Curr!$B$2:$C$13,2,FALSE),0) -> 11 | X15: =U15*W15 -> 0 | Y15: =Q15/0.8 -> 0 | Z15: =+Y15*R15 -> 0 | AA15: EUR | AB15: =IFERROR(VLOOKUP(AA15,Curr!$B$2:$C$13,2,FALSE),0) -> 11 | AC15: =+Y15*AB15*R15 -> 0 | AD15: =+AC15-X15 -> 0 | AE15: =IFERROR(AD15/AC15,0) -> 0
B16: FI | D16: Coach | J16: Helsinki: Coach transfer to Turku - Time: TBD - Includes: Tickets | Q16: 0 | R16: 0 | S16: =+Q16*R16 -> 0 | T16: 0 | U16: =S16*(1-T16) -> 0 | V16: EUR | W16: =IFERROR(VLOOKUP(V16,Curr!$B$2:$C$13,2,FALSE),0) -> 11 | X16: =U16*W16 -> 0 | Y16: =Q16/0.8 -> 0 | Z16: =+Y16*R16 -> 0 | AA16: EUR | AB16: =IFERROR(VLOOKUP(AA16,Curr!$B$2:$C$13,2,FALSE),0) -> 11 | AC16: =+Y16*AB16*R16 -> 0 | AD16: =+AC16-X16 -> 0 | AE16: =IFERROR(AD16/AC16,0) -> 0
B17: FI | D17: Coach | J17: Helsinki: Coach transfer to Tampere - Time: TBD - Includes: Tickets | Q17: 0 | R17: 0 | S17: =+Q17*R17 -> 0 | T17: 0 | U17: =S17*(1-T17) -> 0 | V17: EUR | W17: =IFERROR(VLOOKUP(V17,Curr!$B$2:$C$13,2,FALSE),0) -> 11 | X17: =U17*W17 -> 0 | Y17: =Q17/0.8 -> 0 | Z17: =+Y17*R17 -> 0 | AA17: EUR | AB17: =IFERROR(VLOOKUP(AA17,Curr!$B$2:$C$13,2,FALSE),0) -> 11 | AC17: =+Y17*AB17*R17 -> 0 | AD17: =+AC17-X17 -> 0 | AE17: =IFERROR(AD17/AC17,0) -> 0
B18: FI | D18: Coach | J18: Helsinki: Coach transfer to Oulu - Time: TBD - Includes: Tickets | Q18: 0 | R18: 0 | S18: =+Q18*R18 -> 0 | T18: 0 | U18: =S18*(1-T18) -> 0 | V18: EUR | W18: =IFERROR(VLOOKUP(V18,Curr!$B$2:$C$13,2,FALSE),0) -> 11 | X18: =U18*W18 -> 0 | Y18: =Q18/0.8 -> 0 | Z18: =+Y18*R18 -> 0 | AA18: EUR | AB18: =IFERROR(VLOOKUP(AA18,Curr!$B$2:$C$13,2,FALSE),0) -> 11 | AC18: =+Y18*AB18*R18 -> 0 | AD18: =+AC18-X18 -> 0 | AE18: =IFERROR(AD18/AC18,0) -> 0
B19: FI | D19: Coach | J19: Helsinki: Coach transfer to Kuopio - Time: TBD - Includes: Tickets | Q19: 0 | R19: 0 | S19: =+Q19*R19 -> 0 | T19: 0 | U19: =S19*(1-T19) -> 0 | V19: EUR | W19: =IFERROR(VLOOKUP(V19,Curr!$B$2:$C$13,2,FALSE),0) -> 11 | X19: =U19*W19 -> 0 | Y19: =Q19/0.8 -> 0 | Z19: =+Y19*R19 -> 0 | AA19: EUR | AB19: =IFERROR(VLOOKUP(AA19,Curr!$B$2:$C$13,2,FALSE),0) -> 11 | AC19: =+Y19*AB19*R19 -> 0 | AD19: =+AC19-X19 -> 0 | AE19: =IFERROR(AD19/AC19,0) -> 0
B20: FI | D20: Coach | J20: Helsinki: Coach transfer to Lappeenranta - Time: TBD - Includes: Tickets | Q20: 0 | R20: 0 | S20: =+Q20*R20 -> 0 | T20: 0 | U20: =S20*(1-T20) -> 0 | V20: EUR | W20: =IFERROR(VLOOKUP(V20,Curr!$B$2:$C$13,2,FALSE),0) -> 11 | X20: =U20*W20 -> 0 | Y20: =Q20/0.8 -> 0 | Z20: =+Y20*R20 -> 0 | AA20: EUR | AB20: =IFERROR(VLOOKUP(AA20,Curr!$B$2:$C$13,2,FALSE),0) -> 11 | AC20: =+Y20*AB20*R20 -> 0 | AD20: =+AC20-X20 -> 0 | AE20: =IFERROR(AD20/AC20,0) -> 0
B21: FI | D21: Coach | J21: Helsinki: Coach transfer to Savonlinna - Time: TBD - Includes: Tickets | Q21: 0 | R21: 0 | S21: =+Q21*R21 -> 0 | T21: 0 | U21: =S21*(1-T21) -> 0 | V21: EUR | W21: =IFERROR(VLOOKUP(V21,Curr!$B$2:$C$13,2,FALSE),0) -> 11 | X21: =U21*W21 -> 0 | Y21: =Q21/0.8 -> 0 | Z21: =+Y21*R21 -> 0 | AA21: EUR | AB21: =IFERROR(VLOOKUP(AA21,Curr!$B$2:$C$13,2,FALSE),0) -> 11 | AC21: =+Y21*AB21*R21 -> 0 | AD21: =+AC21-X21 -> 0 | AE21: =IFERROR(AD21/AC21,0) -> 0
B22: FI | D22: Coach | J22: Rovaniemi: Coach transfer to Oulu - Time: TBD - Includes: Tickets | Q22: 0 | R22: 0 | S22: =+Q22*R22 -> 0 | T22: 0 | U22: =S22*(1-T22) -> 0 | V22: EUR | W22: =IFERROR(VLOOKUP(V22,Curr!$B$2:$C$13,2,FALSE),0) -> 11 | X22: =U22*W22 -> 0 | Y22: =Q22 -> 0 | Z22: =+Y22*R22 -> 0 | AA22: EUR | AB22: =IFERROR(VLOOKUP(AA22,Curr!$B$2:$C$13,2,FALSE),0) -> 11 | AC22: =+Y22*AB22*R22 -> 0 | AD22: =+AC22-X22 -> 0 | AE22: =IFERROR(AD22/AC22,0) -> 0
B23: FI | D23: Coach | J23: Rovaniemi: Coach transfer to Ranua - Time: TBD - Includes: Tickets | Q23: 0 | R23: 0 | S23: =+Q23*R23 -> 0 | T23: 0 | U23: =S23*(1-T23) -> 0 | V23: EUR | W23: =IFERROR(VLOOKUP(V23,Curr!$B$2:$C$13,2,FALSE),0) -> 11 | X23: =U23*W23 -> 0 | Y23: =Q23 -> 0 | Z23: =+Y23*R23 -> 0 | AA23: EUR | AB23: =IFERROR(VLOOKUP(AA23,Curr!$B$2:$C$13,2,FALSE),0) -> 11 | AC23: =+Y23*AB23*R23 -> 0 | AD23: =+AC23-X23 -> 0 | AE23: =IFERROR(AD23/AC23,0) -> 0
B24: FI | D24: Coach | J24: Rovaniemi: Coach transfer to Pyhä - Time: TBD - Includes: Tickets | Q24: 0 | R24: 0 | S24: =+Q24*R24 -> 0 | T24: 0 | U24: =S24*(1-T24) -> 0 | V24: EUR | W24: =IFERROR(VLOOKUP(V24,Curr!$B$2:$C$13,2,FALSE),0) -> 11 | X24: =U24*W24 -> 0 | Y24: =Q24 -> 0 | Z24: =+Y24*R24 -> 0 | AA24: EUR | AB24: =IFERROR(VLOOKUP(AA24,Curr!$B$2:$C$13,2,FALSE),0) -> 11 | AC24: =+Y24*AB24*R24 -> 0 | AD24: =+AC24-X24 -> 0 | AE24: =IFERROR(AD24/AC24,0) -> 0
B25: FI | D25: Coach | J25: Rovaniemi: Coach transfer to Luosto - Time: TBD - Includes: Tickets | Q25: 0 | R25: 0 | S25: =+Q25*R25 -> 0 | T25: 0 | U25: =S25*(1-T25) -> 0 | V25: EUR | W25: =IFERROR(VLOOKUP(V25,Curr!$B$2:$C$13,2,FALSE),0) -> 11 | X25: =U25*W25 -> 0 | Y25: =Q25 -> 0 | Z25: =+Y25*R25 -> 0 | AA25: EUR | AB25: =IFERROR(VLOOKUP(AA25,Curr!$B$2:$C$13,2,FALSE),0) -> 11 | AC25: =+Y25*AB25*R25 -> 0 | AD25: =+AC25-X25 -> 0 | AE25: =IFERROR(AD25/AC25,0) -> 0
B26: FI | D26: Coach | J26: Rovaniemi: Coach transfer to Kakslauttanen - Time: TBD - Includes: Tickets | Q26: 49 | R26: 0 | S26: =+Q26*R26 -> 0 | T26: 0 | U26: =S26*(1-T26) -> 0 | V26: EUR | W26: =IFERROR(VLOOKUP(V26,Curr!$B$2:$C$13,2,FALSE),0) -> 11 | X26: =U26*W26 -> 0 | Y26: =Q26/0.8 -> 61.25 | Z26: =+Y26*R26 -> 0 | AA26: EUR | AB26: =IFERROR(VLOOKUP(AA26,Curr!$B$2:$C$13,2,FALSE),0) -> 11 | AC26: =+Y26*AB26*R26 -> 0 | AD26: =+AC26-X26 -> 0 | AE26: =IFERROR(AD26/AC26,0) -> 0
B27: FI | D27: Coach | J27: Rovaniemi: Arctic Coach transfer on The Arctic Route to Levi - Time: TBD - Includes: Tickets | Q27: 0 | R27: 0 | S27: =+Q27*R27 -> 0 | T27: 0 | U27: =S27*(1-T27) -> 0 | V27: EUR | W27: =IFERROR(VLOOKUP(V27,Curr!$B$2:$C$13,2,FALSE),0) -> 11 | X27: =U27*W27 -> 0 | Y27: =Q27 -> 0 | Z27: =+Y27*R27 -> 0 | AA27: EUR | AB27: =IFERROR(VLOOKUP(AA27,Curr!$B$2:$C$13,2,FALSE),0) -> 11 | AC27: =+Y27*AB27*R27 -> 0 | AD27: =+AC27-X27 -> 0 | AE27: =IFERROR(AD27/AC27,0) -> 0
B28: FI | D28: Coach | J28: Rovaniemi: Overnight Arctic Coach transfer on the Aurora Express to Levi - Time: TBD - Includes: Tickets | Q28: 0 | R28: 0 | S28: =+Q28*R28 -> 0 | T28: 0 | U28: =S28*(1-T28) -> 0 | V28: EUR | W28: =IFERROR(VLOOKUP(V28,Curr!$B$2:$C$13,2,FALSE),0) -> 11 | X28: =U28*W28 -> 0 | Y28: =Q28 -> 0 | Z28: =+Y28*R28 -> 0 | AA28: EUR | AB28: =IFERROR(VLOOKUP(AA28,Curr!$B$2:$C$13,2,FALSE),0) -> 11 | AC28: =+Y28*AB28*R28 -> 0 | AD28: =+AC28-X28 -> 0 | AE28: =IFERROR(AD28/AC28,0) -> 0
B29: FI | D29: Coach | J29: Rovaniemi: Arctic Coach transfer on The Arctic Route to Kilpisjärvi - Time: TBD - Includes: Tickets | Q29: 0 | R29: 0 | S29: =+Q29*R29 -> 0 | T29: 0 | U29: =S29*(1-T29) -> 0 | V29: EUR | W29: =IFERROR(VLOOKUP(V29,Curr!$B$2:$C$13,2,FALSE),0) -> 11 | X29: =U29*W29 -> 0 | Y29: =Q29 -> 0 | Z29: =+Y29*R29 -> 0 | AA29: EUR | AB29: =IFERROR(VLOOKUP(AA29,Curr!$B$2:$C$13,2,FALSE),0) -> 11 | AC29: =+Y29*AB29*R29 -> 0 | AD29: =+AC29-X29 -> 0 | AE29: =IFERROR(AD29/AC29,0) -> 0
B30: FI | D30: Coach | J30: Rovaniemi: Overnight Arctic Coach transfer on the Aurora Express to Kilpisjärvi - Time: TBD - Includes: Tickets | Q30: 0 | R30: 0 | S30: =+Q30*R30 -> 0 | T30: 0 | U30: =S30*(1-T30) -> 0 | V30: EUR | W30: =IFERROR(VLOOKUP(V30,Curr!$B$2:$C$13,2,FALSE),0) -> 11 | X30: =U30*W30 -> 0 | Y30: =Q30 -> 0 | Z30: =+Y30*R30 -> 0 | AA30: EUR | AB30: =IFERROR(VLOOKUP(AA30,Curr!$B$2:$C$13,2,FALSE),0) -> 11 | AC30: =+Y30*AB30*R30 -> 0 | AD30: =+AC30-X30 -> 0 | AE30: =IFERROR(AD30/AC30,0) -> 0
B31: FI | D31: Coach | J31: Rovaniemi: Arctic Coach transfer on The Arctic Route to Tromsø - Time: TBD - Includes: Tickets | Q31: 0 | R31: 0 | S31: =+Q31*R31 -> 0 | T31: 0.2 | U31: =S31*(1-T31) -> 0 | V31: EUR | W31: =IFERROR(VLOOKUP(V31,Curr!$B$2:$C$13,2,FALSE),0) -> 11 | X31: =U31*W31 -> 0 | Y31: =Q31 -> 0 | Z31: =+Y31*R31 -> 0 | AA31: EUR | AB31: =IFERROR(VLOOKUP(AA31,Curr!$B$2:$C$13,2,FALSE),0) -> 11 | AC31: =+Y31*AB31*R31 -> 0 | AD31: =+AC31-X31 -> 0 | AE31: =IFERROR(AD31/AC31,0) -> 0
B32: FI | D32: Coach | J32: Rovaniemi: Overnight Arctic Coach transfer on the Aurora Express to Tromsø - Time: TBD - Includes: Tickets | Q32: 0 | R32: 0 | S32: =+Q32*R32 -> 0 | T32: 0.2 | U32: =S32*(1-T32) -> 0 | V32: EUR | W32: =IFERROR(VLOOKUP(V32,Curr!$B$2:$C$13,2,FALSE),0) -> 11 | X32: =U32*W32 -> 0 | Y32: =Q32 -> 0 | Z32: =+Y32*R32 -> 0 | AA32: EUR | AB32: =IFERROR(VLOOKUP(AA32,Curr!$B$2:$C$13,2,FALSE),0) -> 11 | AC32: =+Y32*AB32*R32 -> 0 | AD32: =+AC32-X32 -> 0 | AE32: =IFERROR(AD32/AC32,0) -> 0
B33: FI | D33: Coach | J33: Turku: Coach transfer to Helsinki - Time: TBD - Includes: Tickets | Q33: 0 | R33: 0 | S33: =+Q33*R33 -> 0 | T33: 0 | U33: =S33*(1-T33) -> 0 | V33: EUR | W33: =IFERROR(VLOOKUP(V33,Curr!$B$2:$C$13,2,FALSE),0) -> 11 | X33: =U33*W33 -> 0 | Y33: =Q33 -> 0 | Z33: =+Y33*R33 -> 0 | AA33: EUR | AB33: =IFERROR(VLOOKUP(AA33,Curr!$B$2:$C$13,2,FALSE),0) -> 11 | AC33: =+Y33*AB33*R33 -> 0 | AD33: =+AC33-X33 -> 0 | AE33: =IFERROR(AD33/AC33,0) -> 0
B34: FI | D34: Coach | J34: Turku: Coach transfer to Naantali - Time: TBD - Includes: Tickets | Q34: 0 | R34: 0 | S34: =+Q34*R34 -> 0 | T34: 0 | U34: =S34*(1-T34) -> 0 | V34: EUR | W34: =IFERROR(VLOOKUP(V34,Curr!$B$2:$C$13,2,FALSE),0) -> 11 | X34: =U34*W34 -> 0 | Y34: =Q34 -> 0 | Z34: =+Y34*R34 -> 0 | AA34: EUR | AB34: =IFERROR(VLOOKUP(AA34,Curr!$B$2:$C$13,2,FALSE),0) -> 11 | AC34: =+Y34*AB34*R34 -> 0 | AD34: =+AC34-X34 -> 0 | AE34: =IFERROR(AD34/AC34,0) -> 0
B35: FI | D35: Coach | J35: Tampere: Coach transfer to Helsinki - Time: TBD - Includes: Tickets | Q35: 0 | R35: 0 | S35: =+Q35*R35 -> 0 | T35: 0 | U35: =S35*(1-T35) -> 0 | V35: EUR | W35: =IFERROR(VLOOKUP(V35,Curr!$B$2:$C$13,2,FALSE),0) -> 11 | X35: =U35*W35 -> 0 | Y35: =Q35 -> 0 | Z35: =+Y35*R35 -> 0 | AA35: EUR | AB35: =IFERROR(VLOOKUP(AA35,Curr!$B$2:$C$13,2,FALSE),0) -> 11 | AC35: =+Y35*AB35*R35 -> 0 | AD35: =+AC35-X35 -> 0 | AE35: =IFERROR(AD35/AC35,0) -> 0
B36: FI | D36: Coach | J36: Porvoo: Coach transfer to Helsinki - Time: TBD - Includes: Tickets | Q36: 0 | R36: 0 | S36: =+Q36*R36 -> 0 | T36: 0 | U36: =S36*(1-T36) -> 0 | V36: EUR | W36: =IFERROR(VLOOKUP(V36,Curr!$B$2:$C$13,2,FALSE),0) -> 11 | X36: =U36*W36 -> 0 | Y36: =Q36 -> 0 | Z36: =+Y36*R36 -> 0 | AA36: EUR | AB36: =IFERROR(VLOOKUP(AA36,Curr!$B$2:$C$13,2,FALSE),0) -> 11 | AC36: =+Y36*AB36*R36 -> 0 | AD36: =+AC36-X36 -> 0 | AE36: =IFERROR(AD36/AC36,0) -> 0
B37: FI | D37: Coach | J37: Savonlinna: Coach transfer to Helsinki - Time: TBD - Includes: Tickets | Q37: 0 | R37: 0 | S37: =+Q37*R37 -> 0 | T37: 0 | U37: =S37*(1-T37) -> 0 | V37: EUR | W37: =IFERROR(VLOOKUP(V37,Curr!$B$2:$C$13,2,FALSE),0) -> 11 | X37: =U37*W37 -> 0 | Y37: =Q37 -> 0 | Z37: =+Y37*R37 -> 0 | AA37: EUR | AB37: =IFERROR(VLOOKUP(AA37,Curr!$B$2:$C$13,2,FALSE),0) -> 11 | AC37: =+Y37*AB37*R37 -> 0 | AD37: =+AC37-X37 -> 0 | AE37: =IFERROR(AD37/AC37,0) -> 0
B38: FI | D38: Coach | J38: Savonlinna: Coach transfer to Punkaharju - Time: TBD - Includes: Tickets | Q38: 0 | R38: 0 | S38: =+Q38*R38 -> 0 | T38: 0 | U38: =S38*(1-T38) -> 0 | V38: EUR | W38: =IFERROR(VLOOKUP(V38,Curr!$B$2:$C$13,2,FALSE),0) -> 11 | X38: =U38*W38 -> 0 | Y38: =Q38 -> 0 | Z38: =+Y38*R38 -> 0 | AA38: EUR | AB38: =IFERROR(VLOOKUP(AA38,Curr!$B$2:$C$13,2,FALSE),0) -> 11 | AC38: =+Y38*AB38*R38 -> 0 | AD38: =+AC38-X38 -> 0 | AE38: =IFERROR(AD38/AC38,0) -> 0
... B106: FI | D106: Coach | J106: Kakslauttanen: Coach transfer to Saariselkä - Time: TBD - Includes: Tickets | Q106: 0 | R106: 0 | S106: =+Q106*R106 -> 0 | T106: 0 | U106: =S106*(1-T106) -> 0 | V106: EUR | W106: =IFERROR(VLOOKUP(V106,Curr!$B$2:$C$13,2,FALSE),0) -> 11 | X106: =U106*W106 -> 0 | Y106: =Q106 -> 0 | Z106: =+Y106*R106 -> 0 | AA106: EUR | AB106: =IFERROR(VLOOKUP(AA106,Curr!$B$2:$C$13,2,FALSE),0) -> 11 | AC106: =+Y106*AB106*R106 -> 0 | AD106: =+AC106-X106 -> 0 | AE106: =IFERROR(AD106/AC106,0) -> 0
B107: FI | D107: Coach | J107: Kakslauttanen: Coach transfer to Rovaniemi - Time: TBD - Includes: Tickets | Q107: 49 | R107: 0 | S107: =+Q107*R107 -> 0 | T107: 0 | U107: =S107*(1-T107) -> 0 | V107: EUR | W107: =IFERROR(VLOOKUP(V107,Curr!$B$2:$C$13,2,FALSE),0) -> 11 | X107: =U107*W107 -> 0 | Y107: =Q107/0.8 -> 61.25 | Z107: =+Y107*R107 -> 0 | AA107: EUR | AB107: =IFERROR(VLOOKUP(AA107,Curr!$B$2:$C$13,2,FALSE),0) -> 11 | AC107: =+Y107*AB107*R107 -> 0 | AD107: =+AC107-X107 -> 0 | AE107: =IFERROR(AD107/AC107,0) -> 0
B108: NO | D108: Coach | J108: Oslo: Coach transfer to Kristiansand - Time: TBD - Includes: Tickets | Q108: 0 | R108: 0 | S108: =+Q108*R108 -> 0 | T108: 0 | U108: =S108*(1-T108) -> 0 | V108: EUR | W108: =IFERROR(VLOOKUP(V108,Curr!$B$2:$C$13,2,FALSE),0) -> 11 | X108: =U108*W108 -> 0 | Y108: =Q108 -> 0 | Z108: =+Y108*R108 -> 0 | AA108: EUR | AB108: =IFERROR(VLOOKUP(AA108,Curr!$B$2:$C$13,2,FALSE),0) -> 11 | AC108: =+Y108*AB108*R108 -> 0 | AD108: =+AC108-X108 -> 0 | AE108: =IFERROR(AD108/AC108,0) -> 0
B109: NO | D109: Coach | J109: Oslo: Coach transfer to Stavanger - Time: TBD - Includes: Tickets | Q109: 0 | R109: 0 | S109: =+Q109*R109 -> 0 | T109: 0 | U109: =S109*(1-T109) -> 0 | V109: EUR | W109: =IFERROR(VLOOKUP(V109,Curr!$B$2:$C$13,2,FALSE),0) -> 11 | X109: =U109*W109 -> 0 | Y109: =Q109 -> 0 | Z109: =+Y109*R109 -> 0 | AA109: EUR | AB109: =IFERROR(VLOOKUP(AA109,Curr!$B$2:$C$13,2,FALSE),0) -> 11 | AC109: =+Y109*AB109*R109 -> 0 | AD109: =+AC109-X109 -> 0 | AE109: =IFERROR(AD109/AC109,0) -> 0
B110: NO | D110: Coach | J110: Oslo: Coach transfer to Haugesund - Time: TBD - Includes: Tickets | Q110: 0 | R110: 0 | S110: =+Q110*R110 -> 0 | T110: 0 | U110: =S110*(1-T110) -> 0 | V110: EUR | W110: =IFERROR(VLOOKUP(V110,Curr!$B$2:$C$13,2,FALSE),0) -> 11 | X110: =U110*W110 -> 0 | Y110: =Q110 -> 0 | Z110: =+Y110*R110 -> 0 | AA110: EUR | AB110: =IFERROR(VLOOKUP(AA110,Curr!$B$2:$C$13,2,FALSE),0) -> 11 | AC110: =+Y110*AB110*R110 -> 0 | AD110: =+AC110-X110 -> 0 | AE110: =IFERROR(AD110/AC110,0) -> 0
B111: NO | D111: Coach | J111: Oslo: Coach transfer to Bergen - Time: TBD - Includes: Tickets | Q111: 0 | R111: 0 | S111: =+Q111*R111 -> 0 | T111: 0 | U111: =S111*(1-T111) -> 0 | V111: EUR | W111: =IFERROR(VLOOKUP(V111,Curr!$B$2:$C$13,2,FALSE),0) -> 11 | X111: =U111*W111 -> 0 | Y111: =Q111 -> 0 | Z111: =+Y111*R111 -> 0 | AA111: EUR | AB111: =IFERROR(VLOOKUP(AA111,Curr!$B$2:$C$13,2,FALSE),0) -> 11 | AC111: =+Y111*AB111*R111 -> 0 | AD111: =+AC111-X111 -> 0 | AE111: =IFERROR(AD111/AC111,0) -> 0
B112: NO | D112: Coach | J112: Oslo: Overnight coach transfer to Trondheim - Time: TBD - Includes: Tickets | Q112: 0 | R112: 0 | S112: =+Q112*R112 -> 0 | T112: 0 | U112: =S112*(1-T112) -> 0 | V112: EUR | W112: =IFERROR(VLOOKUP(V112,Curr!$B$2:$C$13,2,FALSE),0) -> 11 | X112: =U112*W112 -> 0 | Y112: =Q112 -> 0 | Z112: =+Y112*R112 -> 0 | AA112: EUR | AB112: =IFERROR(VLOOKUP(AA112,Curr!$B$2:$C$13,2,FALSE),0) -> 11 | AC112: =+Y112*AB112*R112 -> 0 | AD112: =+AC112-X112 -> 0 | AE112: =IFERROR(AD112/AC112,0) -> 0
B113: NO | D113: Coach | J113: Bergen: Coach transfer to Oslo - Time: TBD - Includes: Tickets | Q113: 0 | R113: 0 | S113: =+Q113*R113 -> 0 | T113: 0 | U113: =S113*(1-T113) -> 0 | V113: EUR | W113: =IFERROR(VLOOKUP(V113,Curr!$B$2:$C$13,2,FALSE),0) -> 11 | X113: =U113*W113 -> 0 | Y113: =Q113 -> 0 | Z113: =+Y113*R113 -> 0 | AA113: EUR | AB113: =IFERROR(VLOOKUP(AA113,Curr!$B$2:$C$13,2,FALSE),0) -> 11 | AC113: =+Y113*AB113*R113 -> 0 | AD113: =+AC113-X113 -> 0 | AE113: =IFERROR(AD113/AC113,0) -> 0
B114: NO | D114: Coach | J114: Bergen: Coach transfer to Kristiansand - Time: TBD - Includes: Tickets | Q114: 0 | R114: 0 | S114: =+Q114*R114 -> 0 | T114: 0 | U114: =S114*(1-T114) -> 0 | V114: EUR | W114: =IFERROR(VLOOKUP(V114,Curr!$B$2:$C$13,2,FALSE),0) -> 11 | X114: =U114*W114 -> 0 | Y114: =Q114 -> 0 | Z114: =+Y114*R114 -> 0 | AA114: EUR | AB114: =IFERROR(VLOOKUP(AA114,Curr!$B$2:$C$13,2,FALSE),0) -> 11 | AC114: =+Y114*AB114*R114 -> 0 | AD114: =+AC114-X114 -> 0 | AE114: =IFERROR(AD114/AC114,0) -> 0
B115: NO | D115: Coach | J115: Bergen: Coach transfer on Kystbussen to Stavanger - Time: TBD - Includes: Tickets | Q115: 0 | R115: 0 | S115: =+Q115*R115 -> 0 | T115: 0 | U115: =S115*(1-T115) -> 0 | V115: EUR | W115: =IFERROR(VLOOKUP(V115,Curr!$B$2:$C$13,2,FALSE),0) -> 11 | X115: =U115*W115 -> 0 | Y115: =Q115 -> 0 | Z115: =+Y115*R115 -> 0 | AA115: EUR | AB115: =IFERROR(VLOOKUP(AA115,Curr!$B$2:$C$13,2,FALSE),0) -> 11 | AC115: =+Y115*AB115*R115 -> 0 | AD115: =+AC115-X115 -> 0 | AE115: =IFERROR(AD115/AC115,0) -> 0
B116: NO | D116: Coach | J116: Bergen: Coach transfer on Kystbussen to Haugesund - Time: TBD - Includes: Tickets | Q116: 0 | R116: 0 | S116: =+Q116*R116 -> 0 | T116: 0 | U116: =S116*(1-T116) -> 0 | V116: EUR | W116: =IFERROR(VLOOKUP(V116,Curr!$B$2:$C$13,2,FALSE),0) -> 11 | X116: =U116*W116 -> 0 | Y116: =Q116 -> 0 | Z116: =+Y116*R116 -> 0 | AA116: EUR | AB116: =IFERROR(VLOOKUP(AA116,Curr!$B$2:$C$13,2,FALSE),0) -> 11 | AC116: =+Y116*AB116*R116 -> 0 | AD116: =+AC116-X116 -> 0 | AE116: =IFERROR(AD116/AC116,0) -> 0
B117: NO | D117: Coach | J117: Bergen: Coach transfer on Sognefjordekspressen to Voss - Time: TBD - Includes: Tickets | Q117: 0 | R117: 0 | S117: =+Q117*R117 -> 0 | T117: 0 | U117: =S117*(1-T117) -> 0 | V117: EUR | W117: =IFERROR(VLOOKUP(V117,Curr!$B$2:$C$13,2,FALSE),0) -> 11 | X117: =U117*W117 -> 0 | Y117: =Q117 -> 0 | Z117: =+Y117*R117 -> 0 | AA117: EUR | AB117: =IFERROR(VLOOKUP(AA117,Curr!$B$2:$C$13,2,FALSE),0) -> 11 | AC117: =+Y117*AB117*R117 -> 0 | AD117: =+AC117-X117 -> 0 | AE117: =IFERROR(AD117/AC117,0) -> 0
B118: NO | D118: Coach | J118: Bergen: Coach transfer on Sognefjordekspressen to Flåm - Time: TBD - Includes: Tickets | Q118: 0 | R118: 0 | S118: =+Q118*R118 -> 0 | T118: 0 | U118: =S118*(1-T118) -> 0 | V118: EUR | W118: =IFERROR(VLOOKUP(V118,Curr!$B$2:$C$13,2,FALSE),0) -> 11 | X118: =U118*W118 -> 0 | Y118: =Q118 -> 0 | Z118: =+Y118*R118 -> 0 | AA118: EUR | AB118: =IFERROR(VLOOKUP(AA118,Curr!$B$2:$C$13,2,FALSE),0) -> 11 | AC118: =+Y118*AB118*R118 -> 0 | AD118: =+AC118-X118 -> 0 | AE118: =IFERROR(AD118/AC118,0) -> 0
B119: NO | D119: Coach | J119: Bergen: Coach transfer on Sognefjordekspressen to Sogndal - Time: TBD - Includes: Tickets | Q119: 0 | R119: 0 | S119: =+Q119*R119 -> 0 | T119: 0 | U119: =S119*(1-T119) -> 0 | V119: EUR | W119: =IFERROR(VLOOKUP(V119,Curr!$B$2:$C$13,2,FALSE),0) -> 11 | X119: =U119*W119 -> 0 | Y119: =Q119 -> 0 | Z119: =+Y119*R119 -> 0 | AA119: EUR | AB119: =IFERROR(VLOOKUP(AA119,Curr!$B$2:$C$13,2,FALSE),0) -> 11 | AC119: =+Y119*AB119*R119 -> 0 | AD119: =+AC119-X119 -> 0 | AE119: =IFERROR(AD119/AC119,0) -> 0
... B352: NO | D352: Cruise | J352: Stavanger: Overnight cruise on Fjord Line to Hirtshals - Time: TBD - Includes: Tickets, Interior/Exterior cabin | Q352: 0 | R352: 0 | S352: =+Q352*R352 -> 0 | T352: 0 | U352: =S352*(1-T352) -> 0 | V352: EUR | W352: =IFERROR(VLOOKUP(V352,Curr!$B$2:$C$13,2,FALSE),0) -> 11 | X352: =U352*W352 -> 0 | Y352: =Q352 -> 0 | Z352: =+Y352*R352 -> 0 | AA352: EUR | AB352: =IFERROR(VLOOKUP(AA352,Curr!$B$2:$C$13,2,FALSE),0) -> 11 | AC352: =+Y352*AB352*R352 -> 0 | AD352: =+AC352-X352 -> 0 | AE352: =IFERROR(AD352/AC352,0) -> 0
B353: NO | D353: Cruise | J353: Stavanger: Cruise transfer on Fjord Line to Bergen - Time: 07:30 am - 1:00 pm - Meeting point: Stavanger Port, Kontinentalvegen 31 - Includes: Tickets, Fjord Lounge | P353: https://bookingv3.fjordline.com/en/departures | Q353: 62 | R353: 0 | S353: =+Q353*R353 -> 0 | T353: 0 | U353: =S353*(1-T353) -> 0 | V353: EUR | W353: =IFERROR(VLOOKUP(V353,Curr!$B$2:$C$13,2,FALSE),0) -> 11 | X353: =U353*W353 -> 0 | Y353: =Q353/0.7 -> 88.571429 | Z353: =+Y353*R353 -> 0 | AA353: EUR | AB353: =IFERROR(VLOOKUP(AA353,Curr!$B$2:$C$13,2,FALSE),0) -> 11 | AC353: =+Y353*AB353*R353 -> 0 | AD353: =+AC353-X353 -> 0 | AE353: =IFERROR(AD353/AC353,0) -> 0
B354: NO | D354: Cruise | J354: Trondheim: Overnight Norwegian Sea Coastal Cruise to Bergen - Time: TBD - Includes: Tickets, Interior/Exterior cabin | Q354: 0 | R354: 0 | S354: =+Q354*R354 -> 0 | T354: 0 | U354: =S354*(1-T354) -> 0 | V354: EUR | W354: =IFERROR(VLOOKUP(V354,Curr!$B$2:$C$13,2,FALSE),0) -> 11 | X354: =U354*W354 -> 0 | Y354: =Q354 -> 0 | Z354: =+Y354*R354 -> 0 | AA354: EUR | AB354: =IFERROR(VLOOKUP(AA354,Curr!$B$2:$C$13,2,FALSE),0) -> 11 | AC354: =+Y354*AB354*R354 -> 0 | AD354: =+AC354-X354 -> 0 | AE354: =IFERROR(AD354/AC354,0) -> 0
B355: NO | D355: Cruise | J355: Trondheim: Overnight Norwegian Sea Coastal Cruise to Bodø - Time: TBD - Includes: Tickets, Interior/Exterior cabin | Q355: 0 | R355: 0 | S355: =+Q355*R355 -> 0 | T355: 0 | U355: =S355*(1-T355) -> 0 | V355: EUR | W355: =IFERROR(VLOOKUP(V355,Curr!$B$2:$C$13,2,FALSE),0) -> 11 | X355: =U355*W355 -> 0 | Y355: =Q355 -> 0 | Z355: =+Y355*R355 -> 0 | AA355: EUR | AB355: =IFERROR(VLOOKUP(AA355,Curr!$B$2:$C$13,2,FALSE),0) -> 11 | AC355: =+Y355*AB355*R355 -> 0 | AD355: =+AC355-X355 -> 0 | AE355: =IFERROR(AD355/AC355,0) -> 0
B356: NO | D356: Cruise | J356: Trondheim: Overnight Norwegian Sea Coastal Cruise to Svolvær - Time: TBD - Includes: Tickets, Interior/Exterior cabin | Q356: 0 | R356: 0 | S356: =+Q356*R356 -> 0 | T356: 0 | U356: =S356*(1-T356) -> 0 | V356: EUR | W356: =IFERROR(VLOOKUP(V356,Curr!$B$2:$C$13,2,FALSE),0) -> 11 | X356: =U356*W356 -> 0 | Y356: =Q356 -> 0 | Z356: =+Y356*R356 -> 0 | AA356: EUR | AB356: =IFERROR(VLOOKUP(AA356,Curr!$B$2:$C$13,2,FALSE),0) -> 11 | AC356: =+Y356*AB356*R356 -> 0 | AD356: =+AC356-X356 -> 0 | AE356: =IFERROR(AD356/AC356,0) -> 0
B357: NO | D357: Cruise | J357: Trondheim: Overnight Norwegian Sea Coastal Cruise to Tromsø - Time: TBD - Includes: Tickets, Interior/Exterior cabin | Q357: 0 | R357: 0 | S357: =+Q357*R357 -> 0 | T357: 0 | U357: =S357*(1-T357) -> 0 | V357: EUR | W357: =IFERROR(VLOOKUP(V357,Curr!$B$2:$C$13,2,FALSE),0) -> 11 | X357: =U357*W357 -> 0 | Y357: =Q357 -> 0 | Z357: =+Y357*R357 -> 0 | AA357: EUR | AB357: =IFERROR(VLOOKUP(AA357,Curr!$B$2:$C$13,2,FALSE),0) -> 11 | AC357: =+Y357*AB357*R357 -> 0 | AD357: =+AC357-X357 -> 0 | AE357: =IFERROR(AD357/AC357,0) -> 0
B358: NO | D358: Cruise | J358: Kristiansand: Cruise transfer on Color Line to Hirtshals - Time: TBD - Includes: Tickets | Q358: 0 | R358: 0 | S358: =+Q358*R358 -> 0 | T358: 0 | U358: =S358*(1-T358) -> 0 | V358: EUR | W358: =IFERROR(VLOOKUP(V358,Curr!$B$2:$C$13,2,FALSE),0) -> 11 | X358: =U358*W358 -> 0 | Y358: =Q358 -> 0 | Z358: =+Y358*R358 -> 0 | AA358: EUR | AB358: =IFERROR(VLOOKUP(AA358,Curr!$B$2:$C$13,2,FALSE),0) -> 11 | AC358: =+Y358*AB358*R358 -> 0 | AD358: =+AC358-X358 -> 0 | AE358: =IFERROR(AD358/AC358,0) -> 0
B359: NO | D359: Cruise | J359: Ålesund: Overnight Norwegian Sea Coastal Cruise to Bergen - Time: TBD - Includes: Tickets, Interior/Exterior cabin | Q359: 0 | R359: 0 | S359: =+Q359*R359 -> 0 | T359: 0 | U359: =S359*(1-T359) -> 0 | V359: EUR | W359: =IFERROR(VLOOKUP(V359,Curr!$B$2:$C$13,2,FALSE),0) -> 11 | X359: =U359*W359 -> 0 | Y359: =Q359 -> 0 | Z359: =+Y359*R359 -> 0 | AA359: EUR | AB359: =IFERROR(VLOOKUP(AA359,Curr!$B$2:$C$13,2,FALSE),0) -> 11 | AC359: =+Y359*AB359*R359 -> 0 | AD359: =+AC359-X359 -> 0 | AE359: =IFERROR(AD359/AC359,0) -> 0
B360: NO | D360: Cruise | J360: Bodø: Cruise transfer on Torghatten to Moskenes - Time: TBD - Includes: Tickets | Q360: 0 | R360: 0 | S360: =+Q360*R360 -> 0 | T360: 0 | U360: =S360*(1-T360) -> 0 | V360: EUR | W360: =IFERROR(VLOOKUP(V360,Curr!$B$2:$C$13,2,FALSE),0) -> 11 | X360: =U360*W360 -> 0 | Y360: =Q360 -> 0 | Z360: =+Y360*R360 -> 0 | AA360: EUR | AB360: =IFERROR(VLOOKUP(AA360,Curr!$B$2:$C$13,2,FALSE),0) -> 11 | AC360: =+Y360*AB360*R360 -> 0 | AD360: =+AC360-X360 -> 0 | AE360: =IFERROR(AD360/AC360,0) -> 0
B361: NO | D361: Cruise | J361: Bodø: Overnight Norwegian Sea Coastal Cruise to Bergen - Time: TBD - Includes: Tickets, Interior/Exterior cabin | Q361: 0 | R361: 0 | S361: =+Q361*R361 -> 0 | T361: 0 | U361: =S361*(1-T361) -> 0 | V361: EUR | W361: =IFERROR(VLOOKUP(V361,Curr!$B$2:$C$13,2,FALSE),0) -> 11 | X361: =U361*W361 -> 0 | Y361: =Q361 -> 0 | Z361: =+Y361*R361 -> 0 | AA361: EUR | AB361: =IFERROR(VLOOKUP(AA361,Curr!$B$2:$C$13,2,FALSE),0) -> 11 | AC361: =+Y361*AB361*R361 -> 0 | AD361: =+AC361-X361 -> 0 | AE361: =IFERROR(AD361/AC361,0) -> 0
B362: NO | D362: Cruise | J362: Bodø: Overnight Norwegian Sea Coastal Cruise to Trondheim - Time: TBD - Includes: Tickets, Interior/Exterior cabin | Q362: 0 | R362: 0 | S362: =+Q362*R362 -> 0 | T362: 0 | U362: =S362*(1-T362) -> 0 | V362: EUR | W362: =IFERROR(VLOOKUP(V362,Curr!$B$2:$C$13,2,FALSE),0) -> 11 | X362: =U362*W362 -> 0 | Y362: =Q362 -> 0 | Z362: =+Y362*R362 -> 0 | AA362: EUR | AB362: =IFERROR(VLOOKUP(AA362,Curr!$B$2:$C$13,2,FALSE),0) -> 11 | AC362: =+Y362*AB362*R362 -> 0 | AD362: =+AC362-X362 -> 0 | AE362: =IFERROR(AD362/AC362,0) -> 0
B363: NO | D363: Cruise | J363: Bodø: Norwegian Sea Coastal Cruise transfer to Svolvær - Time: TBD - Includes: Tickets | Q363: 0 | R363: 0 | S363: =+Q363*R363 -> 0 | T363: 0 | U363: =S363*(1-T363) -> 0 | V363: EUR | W363: =IFERROR(VLOOKUP(V363,Curr!$B$2:$C$13,2,FALSE),0) -> 11 | X363: =U363*W363 -> 0 | Y363: =Q363 -> 0 | Z363: =+Y363*R363 -> 0 | AA363: EUR | AB363: =IFERROR(VLOOKUP(AA363,Curr!$B$2:$C$13,2,FALSE),0) -> 11 | AC363: =+Y363*AB363*R363 -> 0 | AD363: =+AC363-X363 -> 0 | AE363: =IFERROR(AD363/AC363,0) -> 0
B364: NO | D364: Cruise | J364: Bodø: Overnight Norwegian Sea Coastal Cruise to Tromsø - Time: TBD - Includes: Tickets, Interior/Exterior cabin | Q364: 0 | R364: 0 | S364: =+Q364*R364 -> 0 | T364: 0 | U364: =S364*(1-T364) -> 0 | V364: EUR | W364: =IFERROR(VLOOKUP(V364,Curr!$B$2:$C$13,2,FALSE),0) -> 11 | X364: =U364*W364 -> 0 | Y364: =Q364 -> 0 | Z364: =+Y364*R364 -> 0 | AA364: EUR | AB364: =IFERROR(VLOOKUP(AA364,Curr!$B$2:$C$13,2,FALSE),0) -> 11 | AC364: =+Y364*AB364*R364 -> 0 | AD364: =+AC364-X364 -> 0 | AE364: =IFERROR(AD364/AC364,0) -> 0
B365: NO | D365: Cruise | J365: Sandefjord: Cruise transfer on Color Line to Strömstad - Time: TBD - Includes: Tickets | Q365: 0 | R365: 0 | S365: =+Q365*R365 -> 0 | T365: 0 | U365: =S365*(1-T365) -> 0 | V365: EUR | W365: =IFERROR(VLOOKUP(V365,Curr!$B$2:$C$13,2,FALSE),0) -> 11 | X365: =U365*W365 -> 0 | Y365: =Q365 -> 0 | Z365: =+Y365*R365 -> 0 | AA365: EUR | AB365: =IFERROR(VLOOKUP(AA365,Curr!$B$2:$C$13,2,FALSE),0) -> 11 | AC365: =+Y365*AB365*R365 -> 0 | AD365: =+AC365-X365 -> 0 | AE365: =IFERROR(AD365/AC365,0) -> 0
... B503: DK | D503: Flight | J503: Rønne: Flight to DESTINATION - Time: TBD - Includes: Tickets and luggage allowance of 1 x 23 kg checked bag and 1 x 8 kg carry-on bag per person | Q503: 0 | R503: 0 | S503: =+Q503*R503 -> 0 | T503: 0 | U503: =S503*(1-T503) -> 0 | V503: EUR | W503: =IFERROR(VLOOKUP(V503,Curr!$B$2:$C$13,2,FALSE),0) -> 11 | X503: =U503*W503 -> 0 | Y503: =Q503 -> 0 | Z503: =+Y503*R503 -> 0 | AA503: EUR | AB503: =IFERROR(VLOOKUP(AA503,Curr!$B$2:$C$13,2,FALSE),0) -> 11 | AC503: =+Y503*AB503*R503 -> 0 | AD503: =+AC503-X503 -> 0 | AE503: =IFERROR(AD503/AC503,0) -> 0
B504: FI | D504: Train | J504: Helsinki: Train transfer to Turku - Time: TBD - Includes: Tickets | Q504: 0 | R504: 0 | S504: =+Q504*R504 -> 0 | T504: 0 | U504: =S504*(1-T504) -> 0 | V504: EUR | W504: =IFERROR(VLOOKUP(V504,Curr!$B$2:$C$13,2,FALSE),0) -> 11 | X504: =U504*W504 -> 0 | Y504: =Q504/0.8 -> 0 | Z504: =+Y504*R504 -> 0 | AA504: EUR | AB504: =IFERROR(VLOOKUP(AA504,Curr!$B$2:$C$13,2,FALSE),0) -> 11 | AC504: =+Y504*AB504*R504 -> 0 | AD504: =+AC504-X504 -> 0 | AE504: =IFERROR(AD504/AC504,0) -> 0
B505: FI | D505: Train | J505: Helsinki: Train transfer to Tampere - Time: TBD - Includes: Tickets | Q505: 0 | R505: 0 | S505: =+Q505*R505 -> 0 | T505: 0 | U505: =S505*(1-T505) -> 0 | V505: EUR | W505: =IFERROR(VLOOKUP(V505,Curr!$B$2:$C$13,2,FALSE),0) -> 11 | X505: =U505*W505 -> 0 | Y505: =Q505/0.8 -> 0 | Z505: =+Y505*R505 -> 0 | AA505: EUR | AB505: =IFERROR(VLOOKUP(AA505,Curr!$B$2:$C$13,2,FALSE),0) -> 11 | AC505: =+Y505*AB505*R505 -> 0 | AD505: =+AC505-X505 -> 0 | AE505: =IFERROR(AD505/AC505,0) -> 0
B506: FI | D506: Train | J506: Helsinki: Train transfer to Lappeenranta - Time: TBD - Includes: Tickets | Q506: 0 | R506: 0 | S506: =+Q506*R506 -> 0 | T506: 0 | U506: =S506*(1-T506) -> 0 | V506: EUR | W506: =IFERROR(VLOOKUP(V506,Curr!$B$2:$C$13,2,FALSE),0) -> 11 | X506: =U506*W506 -> 0 | Y506: =Q506/0.8 -> 0 | Z506: =+Y506*R506 -> 0 | AA506: EUR | AB506: =IFERROR(VLOOKUP(AA506,Curr!$B$2:$C$13,2,FALSE),0) -> 11 | AC506: =+Y506*AB506*R506 -> 0 | AD506: =+AC506-X506 -> 0 | AE506: =IFERROR(AD506/AC506,0) -> 0
B507: FI | D507: Train | J507: Helsinki: Train transfer to Imatra - Time: TBD - Includes: Tickets | Q507: 0 | R507: 0 | S507: =+Q507*R507 -> 0 | T507: 0 | U507: =S507*(1-T507) -> 0 | V507: EUR | W507: =IFERROR(VLOOKUP(V507,Curr!$B$2:$C$13,2,FALSE),0) -> 11 | X507: =U507*W507 -> 0 | Y507: =Q507/0.8 -> 0 | Z507: =+Y507*R507 -> 0 | AA507: EUR | AB507: =IFERROR(VLOOKUP(AA507,Curr!$B$2:$C$13,2,FALSE),0) -> 11 | AC507: =+Y507*AB507*R507 -> 0 | AD507: =+AC507-X507 -> 0 | AE507: =IFERROR(AD507/AC507,0) -> 0
B508: FI | D508: Train | J508: Helsinki: Train transfer to Kuopio - Time: TBD - Includes: Tickets | Q508: 0 | R508: 0 | S508: =+Q508*R508 -> 0 | T508: 0 | U508: =S508*(1-T508) -> 0 | V508: EUR | W508: =IFERROR(VLOOKUP(V508,Curr!$B$2:$C$13,2,FALSE),0) -> 11 | X508: =U508*W508 -> 0 | Y508: =Q508/0.8 -> 0 | Z508: =+Y508*R508 -> 0 | AA508: EUR | AB508: =IFERROR(VLOOKUP(AA508,Curr!$B$2:$C$13,2,FALSE),0) -> 11 | AC508: =+Y508*AB508*R508 -> 0 | AD508: =+AC508-X508 -> 0 | AE508: =IFERROR(AD508/AC508,0) -> 0
B509: FI | D509: Train | J509: Helsinki: Train transfer with connection to Savonlinna - Time: TBD - Includes: Tickets | Q509: 0 | R509: 0 | S509: =+Q509*R509 -> 0 | T509: 0 | U509: =S509*(1-T509) -> 0 | V509: EUR | W509: =IFERROR(VLOOKUP(V509,Curr!$B$2:$C$13,2,FALSE),0) -> 11 | X509: =U509*W509 -> 0 | Y509: =Q509/0.8 -> 0 | Z509: =+Y509*R509 -> 0 | AA509: EUR | AB509: =IFERROR(VLOOKUP(AA509,Curr!$B$2:$C$13,2,FALSE),0) -> 11 | AC509: =+Y509*AB509*R509 -> 0 | AD509: =+AC509-X509 -> 0 | AE509: =IFERROR(AD509/AC509,0) -> 0
B510: FI | D510: Train | J510: Helsinki: Train transfer with connection to Punkaharju - Time: TBD - Includes: Tickets | Q510: 0 | R510: 0 | S510: =+Q510*R510 -> 0 | T510: 0 | U510: =S510*(1-T510) -> 0 | V510: EUR | W510: =IFERROR(VLOOKUP(V510,Curr!$B$2:$C$13,2,FALSE),0) -> 11 | X510: =U510*W510 -> 0 | Y510: =Q510/0.8 -> 0 | Z510: =+Y510*R510 -> 0 | AA510: EUR | AB510: =IFERROR(VLOOKUP(AA510,Curr!$B$2:$C$13,2,FALSE),0) -> 11 | AC510: =+Y510*AB510*R510 -> 0 | AD510: =+AC510-X510 -> 0 | AE510: =IFERROR(AD510/AC510,0) -> 0
B511: FI | D511: Train | J511: Helsinki: Train transfer to Vaasa - Time: TBD - Includes: Tickets | Q511: 0 | R511: 0 | S511: =+Q511*R511 -> 0 | T511: 0 | U511: =S511*(1-T511) -> 0 | V511: EUR | W511: =IFERROR(VLOOKUP(V511,Curr!$B$2:$C$13,2,FALSE),0) -> 11 | X511: =U511*W511 -> 0 | Y511: =Q511/0.8 -> 0 | Z511: =+Y511*R511 -> 0 | AA511: EUR | AB511: =IFERROR(VLOOKUP(AA511,Curr!$B$2:$C$13,2,FALSE),0) -> 11 | AC511: =+Y511*AB511*R511 -> 0 | AD511: =+AC511-X511 -> 0 | AE511: =IFERROR(AD511/AC511,0) -> 0
B512: FI | D512: Train | J512: Helsinki: Train transfer to Oulu - Time: TBD - Includes: Tickets | Q512: 0 | R512: 0 | S512: =+Q512*R512 -> 0 | T512: 0 | U512: =S512*(1-T512) -> 0 | V512: EUR | W512: =IFERROR(VLOOKUP(V512,Curr!$B$2:$C$13,2,FALSE),0) -> 11 | X512: =U512*W512 -> 0 | Y512: =Q512/0.8 -> 0 | Z512: =+Y512*R512 -> 0 | AA512: EUR | AB512: =IFERROR(VLOOKUP(AA512,Curr!$B$2:$C$13,2,FALSE),0) -> 11 | AC512: =+Y512*AB512*R512 -> 0 | AD512: =+AC512-X512 -> 0 | AE512: =IFERROR(AD512/AC512,0) -> 0
B513: FI | D513: Train | J513: Helsinki: Train transfer to Kemi - Time: TBD - Includes: Tickets | Q513: 0 | R513: 0 | S513: =+Q513*R513 -> 0 | T513: 0 | U513: =S513*(1-T513) -> 0 | V513: EUR | W513: =IFERROR(VLOOKUP(V513,Curr!$B$2:$C$13,2,FALSE),0) -> 11 | X513: =U513*W513 -> 0 | Y513: =Q513/0.8 -> 0 | Z513: =+Y513*R513 -> 0 | AA513: EUR | AB513: =IFERROR(VLOOKUP(AA513,Curr!$B$2:$C$13,2,FALSE),0) -> 11 | AC513: =+Y513*AB513*R513 -> 0 | AD513: =+AC513-X513 -> 0 | AE513: =IFERROR(AD513/AC513,0) -> 0
B514: FI | D514: Train | J514: Helsinki: Train transfer to Rovaniemi - Time: TBD - Includes: Tickets | Q514: 0 | R514: 0 | S514: =+Q514*R514 -> 0 | T514: 0 | U514: =S514*(1-T514) -> 0 | V514: EUR | W514: =IFERROR(VLOOKUP(V514,Curr!$B$2:$C$13,2,FALSE),0) -> 11 | X514: =U514*W514 -> 0 | Y514: =Q514/0.8 -> 0 | Z514: =+Y514*R514 -> 0 | AA514: EUR | AB514: =IFERROR(VLOOKUP(AA514,Curr!$B$2:$C$13,2,FALSE),0) -> 11 | AC514: =+Y514*AB514*R514 -> 0 | AD514: =+AC514-X514 -> 0 | AE514: =IFERROR(AD514/AC514,0) -> 0
B515: FI | D515: Train | J515: Helsinki: Train transfer with connection to Hanko - Time: TBD - Includes: Tickets | Q515: 0 | R515: 0 | S515: =+Q515*R515 -> 0 | T515: 0 | U515: =S515*(1-T515) -> 0 | V515: EUR | W515: =IFERROR(VLOOKUP(V515,Curr!$B$2:$C$13,2,FALSE),0) -> 11 | X515: =U515*W515 -> 0 | Y515: =Q515/0.8 -> 0 | Z515: =+Y515*R515 -> 0 | AA515: EUR | AB515: =IFERROR(VLOOKUP(AA515,Curr!$B$2:$C$13,2,FALSE),0) -> 11 | AC515: =+Y515*AB515*R515 -> 0 | AD515: =+AC515-X515 -> 0 | AE515: =IFERROR(AD515/AC515,0) -> 0
... B526: FI | D526: Train | J526: Helsinki: Overnight train transfer on the Santa Claus Express to Kemijärvi - Time: TBD - Includes: Downstairs sleeper cabin with shared bathroom, Tickets | Q526: 0 | R526: 0 | S526: =+Q526*R526 -> 0 | T526: 0 | U526: =S526*(1-T526) -> 0 | V526: EUR | W526: =IFERROR(VLOOKUP(V526,Curr!$B$2:$C$13,2,FALSE),0) -> 11 | X526: =U526*W526 -> 0 | Y526: =Q526/0.8 -> 0 | Z526: =+Y526*R526 -> 0 | AA526: EUR | AB526: =IFERROR(VLOOKUP(AA526,Curr!$B$2:$C$13,2,FALSE),0) -> 11 | AC526: =+Y526*AB526*R526 -> 0 | AD526: =+AC526-X526 -> 0 | AE526: =IFERROR(AD526/AC526,0) -> 0
B527: FI | D527: Train | J527: Rovaniemi: Train transfer to Helsinki - Time: TBD - Includes: Tickets | Q527: 0 | R527: 0 | S527: =+Q527*R527 -> 0 | T527: 0 | U527: =S527*(1-T527) -> 0 | V527: EUR | W527: =IFERROR(VLOOKUP(V527,Curr!$B$2:$C$13,2,FALSE),0) -> 11 | X527: =U527*W527 -> 0 | Y527: =Q527 -> 0 | Z527: =+Y527*R527 -> 0 | AA527: EUR | AB527: =IFERROR(VLOOKUP(AA527,Curr!$B$2:$C$13,2,FALSE),0) -> 11 | AC527: =+Y527*AB527*R527 -> 0 | AD527: =+AC527-X527 -> 0 | AE527: =IFERROR(AD527/AC527,0) -> 0
B528: FI | D528: Train | J528: Rovaniemi: Train transfer to Tampere - Time: TBD - Includes: Tickets | Q528: 0 | R528: 0 | S528: =+Q528*R528 -> 0 | T528: 0 | U528: =S528*(1-T528) -> 0 | V528: EUR | W528: =IFERROR(VLOOKUP(V528,Curr!$B$2:$C$13,2,FALSE),0) -> 11 | X528: =U528*W528 -> 0 | Y528: =Q528 -> 0 | Z528: =+Y528*R528 -> 0 | AA528: EUR | AB528: =IFERROR(VLOOKUP(AA528,Curr!$B$2:$C$13,2,FALSE),0) -> 11 | AC528: =+Y528*AB528*R528 -> 0 | AD528: =+AC528-X528 -> 0 | AE528: =IFERROR(AD528/AC528,0) -> 0
B529: FI | D529: Train | J529: Rovaniemi: Train transfer to Oulu - Time: TBD - Includes: Tickets | Q529: 0 | R529: 0 | S529: =+Q529*R529 -> 0 | T529: 0 | U529: =S529*(1-T529) -> 0 | V529: EUR | W529: =IFERROR(VLOOKUP(V529,Curr!$B$2:$C$13,2,FALSE),0) -> 11 | X529: =U529*W529 -> 0 | Y529: =Q529 -> 0 | Z529: =+Y529*R529 -> 0 | AA529: EUR | AB529: =IFERROR(VLOOKUP(AA529,Curr!$B$2:$C$13,2,FALSE),0) -> 11 | AC529: =+Y529*AB529*R529 -> 0 | AD529: =+AC529-X529 -> 0 | AE529: =IFERROR(AD529/AC529,0) -> 0
B530: FI | D530: Train | J530: Rovaniemi: Overnight train transfer on the Santa Claus Express to Helsinki - Time: TBD - Includes: Upstairs sleeper cabin with private bathroom, Tickets | Q530: 0 | R530: 0 | S530: =+Q530*R530 -> 0 | T530: 0 | U530: =S530*(1-T530) -> 0 | V530: EUR | W530: =IFERROR(VLOOKUP(V530,Curr!$B$2:$C$13,2,FALSE),0) -> 11 | X530: =U530*W530 -> 0 | Y530: =Q530 -> 0 | Z530: =+Y530*R530 -> 0 | AA530: EUR | AB530: =IFERROR(VLOOKUP(AA530,Curr!$B$2:$C$13,2,FALSE),0) -> 11 | AC530: =+Y530*AB530*R530 -> 0 | AD530: =+AC530-X530 -> 0 | AE530: =IFERROR(AD530/AC530,0) -> 0
B531: FI | D531: Train | J531: Rovaniemi: Overnight train transfer on the Santa Claus Express to Helsinki - Time: TBD - Includes: Downstairs sleeper cabin with shared bathroom, Tickets | Q531: 0 | R531: 0 | S531: =+Q531*R531 -> 0 | T531: 0 | U531: =S531*(1-T531) -> 0 | V531: EUR | W531: =IFERROR(VLOOKUP(V531,Curr!$B$2:$C$13,2,FALSE),0) -> 11 | X531: =U531*W531 -> 0 | Y531: =Q531 -> 0 | Z531: =+Y531*R531 -> 0 | AA531: EUR | AB531: =IFERROR(VLOOKUP(AA531,Curr!$B$2:$C$13,2,FALSE),0) -> 11 | AC531: =+Y531*AB531*R531 -> 0 | AD531: =+AC531-X531 -> 0 | AE531: =IFERROR(AD531/AC531,0) -> 0
B532: FI | D532: Train | J532: Rovaniemi: Overnight train transfer on the Santa Claus Express to Turku - Time: TBD - Includes: Upstairs sleeper cabin with private bathroom, Tickets | Q532: 0 | R532: 0 | S532: =+Q532*R532 -> 0 | T532: 0 | U532: =S532*(1-T532) -> 0 | V532: EUR | W532: =IFERROR(VLOOKUP(V532,Curr!$B$2:$C$13,2,FALSE),0) -> 11 | X532: =U532*W532 -> 0 | Y532: =Q532 -> 0 | Z532: =+Y532*R532 -> 0 | AA532: EUR | AB532: =IFERROR(VLOOKUP(AA532,Curr!$B$2:$C$13,2,FALSE),0) -> 11 | AC532: =+Y532*AB532*R532 -> 0 | AD532: =+AC532-X532 -> 0 | AE532: =IFERROR(AD532/AC532,0) -> 0
B533: FI | D533: Train | J533: Rovaniemi: Overnight train transfer on the Santa Claus Express to Turku - Time: TBD - Includes: Downstairs sleeper cabin with shared bathroom, Tickets | Q533: 0 | R533: 0 | S533: =+Q533*R533 -> 0 | T533: 0 | U533: =S533*(1-T533) -> 0 | V533: EUR | W533: =IFERROR(VLOOKUP(V533,Curr!$B$2:$C$13,2,FALSE),0) -> 11 | X533: =U533*W533 -> 0 | Y533: =Q533 -> 0 | Z533: =+Y533*R533 -> 0 | AA533: EUR | AB533: =IFERROR(VLOOKUP(AA533,Curr!$B$2:$C$13,2,FALSE),0) -> 11 | AC533: =+Y533*AB533*R533 -> 0 | AD533: =+AC533-X533 -> 0 | AE533: =IFERROR(AD533/AC533,0) -> 0
B534: FI | D534: Train | J534: Rovaniemi: Overnight train transfer on the Santa Claus Express to Tampere - Time: TBD - Includes: Upstairs sleeper cabin with private bathroom, Tickets | Q534: 0 | R534: 0 | S534: =+Q534*R534 -> 0 | T534: 0 | U534: =S534*(1-T534) -> 0 | V534: EUR | W534: =IFERROR(VLOOKUP(V534,Curr!$B$2:$C$13,2,FALSE),0) -> 11 | X534: =U534*W534 -> 0 | Y534: =Q534 -> 0 | Z534: =+Y534*R534 -> 0 | AA534: EUR | AB534: =IFERROR(VLOOKUP(AA534,Curr!$B$2:$C$13,2,FALSE),0) -> 11 | AC534: =+Y534*AB534*R534 -> 0 | AD534: =+AC534-X534 -> 0 | AE534: =IFERROR(AD534/AC534,0) -> 0
B535: FI | D535: Train | J535: Rovaniemi: Overnight train transfer on the Santa Claus Express to Tampere - Time: TBD - Includes: Downstairs sleeper cabin with shared bathroom, Tickets | Q535: 0 | R535: 0 | S535: =+Q535*R535 -> 0 | T535: 0 | U535: =S535*(1-T535) -> 0 | V535: EUR | W535: =IFERROR(VLOOKUP(V535,Curr!$B$2:$C$13,2,FALSE),0) -> 11 | X535: =U535*W535 -> 0 | Y535: =Q535 -> 0 | Z535: =+Y535*R535 -> 0 | AA535: EUR | AB535: =IFERROR(VLOOKUP(AA535,Curr!$B$2:$C$13,2,FALSE),0) -> 11 | AC535: =+Y535*AB535*R535 -> 0 | AD535: =+AC535-X535 -> 0 | AE535: =IFERROR(AD535/AC535,0) -> 0
B536: FI | D536: Train | J536: Turku: Train transfer to Helsinki - Time: TBD - Includes: Tickets | Q536: 0 | R536: 0 | S536: =+Q536*R536 -> 0 | T536: 0 | U536: =S536*(1-T536) -> 0 | V536: EUR | W536: =IFERROR(VLOOKUP(V536,Curr!$B$2:$C$13,2,FALSE),0) -> 11 | X536: =U536*W536 -> 0 | Y536: =Q536 -> 0 | Z536: =+Y536*R536 -> 0 | AA536: EUR | AB536: =IFERROR(VLOOKUP(AA536,Curr!$B$2:$C$13,2,FALSE),0) -> 11 | AC536: =+Y536*AB536*R536 -> 0 | AD536: =+AC536-X536 -> 0 | AE536: =IFERROR(AD536/AC536,0) -> 0
B537: FI | D537: Train | J537: Turku: Train transfer to Tampere - Time: TBD - Includes: Tickets | Q537: 0 | R537: 0 | S537: =+Q537*R537 -> 0 | T537: 0 | U537: =S537*(1-T537) -> 0 | V537: EUR | W537: =IFERROR(VLOOKUP(V537,Curr!$B$2:$C$13,2,FALSE),0) -> 11 | X537: =U537*W537 -> 0 | Y537: =Q537 -> 0 | Z537: =+Y537*R537 -> 0 | AA537: EUR | AB537: =IFERROR(VLOOKUP(AA537,Curr!$B$2:$C$13,2,FALSE),0) -> 11 | AC537: =+Y537*AB537*R537 -> 0 | AD537: =+AC537-X537 -> 0 | AE537: =IFERROR(AD537/AC537,0) -> 0
B538: FI | D538: Train | J538: Turku: Overnight train transfer on the Santa Claus Express to Oulu - Time: TBD - Includes: Upstairs sleeper cabin with private bathroom, Tickets | Q538: 0 | R538: 0 | S538: =+Q538*R538 -> 0 | T538: 0 | U538: =S538*(1-T538) -> 0 | V538: EUR | W538: =IFERROR(VLOOKUP(V538,Curr!$B$2:$C$13,2,FALSE),0) -> 11 | X538: =U538*W538 -> 0 | Y538: =Q538 -> 0 | Z538: =+Y538*R538 -> 0 | AA538: EUR | AB538: =IFERROR(VLOOKUP(AA538,Curr!$B$2:$C$13,2,FALSE),0) -> 11 | AC538: =+Y538*AB538*R538 -> 0 | AD538: =+AC538-X538 -> 0 | AE538: =IFERROR(AD538/AC538,0) -> 0
... B841: DK | D841: Train | J841: Ringsted: Train transfer to Copenhagen - Time: TBD - Includes: Tickets | Q841: 0 | R841: 0 | S841: =+Q841*R841 -> 0 | T841: 0 | U841: =S841*(1-T841) -> 0 | V841: EUR | W841: =IFERROR(VLOOKUP(V841,Curr!$B$2:$C$13,2,FALSE),0) -> 11 | X841: =U841*W841 -> 0 | Y841: =Q841 -> 0 | Z841: =+Y841*R841 -> 0 | AA841: EUR | AB841: =IFERROR(VLOOKUP(AA841,Curr!$B$2:$C$13,2,FALSE),0) -> 11 | AC841: =+Y841*AB841*R841 -> 0 | AD841: =+AC841-X841 -> 0 | AE841: =IFERROR(AD841/AC841,0) -> 0

Sheet Activities
B2: Dates:
B3: Pax:
B4: Rooming:
B6: ID | C6: Day | D6: Type | E6: From date | F6: To date | G6: From time | H6: To time | I6: Supplier | J6: Travel element | K6: Manual booking? | L6: Status | M6: Comments | N6: Non-refundable | O6: Refundable | P6: URL | Q6: Gross P per unit | R6: Units | S6: Gross P | T6: Supp Comm | U6: Net P | V6: Supp curr | W6: X-rate | X6: Net P NOK | Y6: Sales P per unit | Z6: Price | AA6: Sales curr | AB6: X-rate2 | AC6: Sales P NOK tot | AD6: GP NOK | AE6: GP % | AF6: VAT25 | AG6: VAT15 | AH6: VAT12 | AI6: VAT0-D | AJ6: VAT0-I
B7: DK | D7: Activity | J7: Copenhagen: City Walking & Harbour Ferry Tour with Changing of the Guard - Time: 9:00 am - 12:00 pm - Meeting point: Copenhagen Central Station, beneath the large clock beside 7-Eleven - Includes: Small-group walking tour with local host, harbour ferry ride and Changing of the Guard - Description: Discover Copenhagen on foot and from the water, passing historic landmarks, hidden corners, Kastellet and the Little Mermaid before finishing at Amalienborg Palace for the Changing of the Guard. | P7: =HYPERLINK("https://booknordics.com/denmark/eastern-denmark/copenhagen/walk-ferry-copenhagen-highlights-change-of-guards-finale","https://booknordics.com/denmark/eastern-denmark/copenhagen/walk-ferry-copenhagen-highlights-change-of-guards-finale") -> https://booknordics.com/denmark/eastern-denmark/copenhagen/walk-ferry-copenhagen-highlights-change-of-guards-finale | Q7: 55 | R7: 0 | S7: =+Q7*R7 -> 0 | T7: 0.2 | U7: =S7*(1-T7) -> 0 | V7: EUR | W7: =IFERROR(VLOOKUP(V7,Curr!$B$2:$C$13,2,FALSE),0) -> 11 | X7: =U7*W7 -> 0 | Y7: =Q7 -> 55 | Z7: =+Y7*R7 -> 0 | AA7: EUR | AB7: =IFERROR(VLOOKUP(AA7,Curr!$B$2:$C$13,2,FALSE),0) -> 11 | AC7: =+Y7*AB7*R7 -> 0 | AD7: =+AC7-X7 -> 0 | AE7: =IFERROR(AD7/AC7,0) -> 0
B8: DK | D8: Activity | J8: Copenhagen: Forest Tower & Forgotten Giants Day Tour - Time: 10:00 am - 3:30 pm - Meeting point: CPH Tours & Tickets, Colbjørnsensgade 15 - Includes: Central Copenhagen pickup and drop-off, air-conditioned minibus transportation, guided Forest Tower and Forgotten Giants visits and Forest Tower admission - Description: Walk through the treetops to the 45-metre Forest Tower for sweeping countryside views, then discover two enormous recycled-wood sculptures from Thomas Dambo’s celebrated Forgotten Giants project. | P8: =HYPERLINK("https://booknordics.com/denmark/eastern-denmark/copenhagen/forest-tower-and-forgotten-giants-a-day-tour-from-copenhagen","https://booknordics.com/denmark/eastern-denmark/copenhagen/forest-tower-and-forgotten-giants-a-day-tour-from-copenhagen") -> https://booknordics.com/denmark/eastern-denmark/copenhagen/forest-tower-and-forgotten-giants-a-day-tour-from-copenhagen | Q8: 110 | R8: 0 | S8: =+Q8*R8 -> 0 | T8: 0.2 | U8: =S8*(1-T8) -> 0 | V8: EUR | W8: =IFERROR(VLOOKUP(V8,Curr!$B$2:$C$13,2,FALSE),0) -> 11 | X8: =U8*W8 -> 0 | Y8: =Q8 -> 110 | Z8: =+Y8*R8 -> 0 | AA8: EUR | AB8: =IFERROR(VLOOKUP(AA8,Curr!$B$2:$C$13,2,FALSE),0) -> 11 | AC8: =+Y8*AB8*R8 -> 0 | AD8: =+AC8-X8 -> 0 | AE8: =IFERROR(AD8/AC8,0) -> 0
B9: FI | D9: Activity | J9: Helsinki: A Finntastic Walking Tour in Helsinki - Time: 10:30 am - 12:30 pm - Meeting point: Senate Square - Includes: Professional authorised Helsinki guide, liability insurance - Description: Explore Helsinki’s historic centre with a local guide, taking in Senate Square, Helsinki Cathedral, Market Square and Central Library Oodi while discovering Finnish history, culture and everyday life. | P9: https://www.finntastictours.fi/tours/ | Q9: 20 | R9: 0 | S9: =+Q9*R9 -> 0 | T9: 0 | U9: =S9*(1-T9) -> 0 | V9: EUR | W9: =IFERROR(VLOOKUP(V9,Curr!$B$2:$C$13,2,FALSE),0) -> 11 | X9: =U9*W9 -> 0 | Y9: =Q9/0.5 -> 40 | Z9: =+Y9*R9 -> 0 | AA9: EUR | AB9: =IFERROR(VLOOKUP(AA9,Curr!$B$2:$C$13,2,FALSE),0) -> 11 | AC9: =+Y9*AB9*R9 -> 0 | AD9: =+AC9-X9 -> 0 | AE9: =IFERROR(AD9/AC9,0) -> 0
B10: FI | D10: Activity | J10: Helsinki: Archipelago Excursion - Time: 9:00 am - 2:00 pm - Meeting point: Helsinki Central, Mannerheiminaukio 1H - Includes: Round-trip transfers from Helsinki, knowledgeable English-speaking guide, rain jackets if required, Finnish-style lunch with dessert and coffee or tea - Description: Escape the city for a walk through coastal forests and along rocky Baltic shores. Enjoy peaceful nature, fresh sea air and beautiful views across the Helsinki archipelago. | P10: https://booknordics.com/finland/southern-finland/helsinki/archipelago-excursion | Q10: 115 | R10: 0 | S10: =+Q10*R10 -> 0 | T10: 0.2 | U10: =S10*(1-T10) -> 0 | V10: EUR | W10: =IFERROR(VLOOKUP(V10,Curr!$B$2:$C$13,2,FALSE),0) -> 11 | X10: =U10*W10 -> 0 | Y10: =Q10 -> 115 | Z10: =+Y10*R10 -> 0 | AA10: EUR | AB10: =IFERROR(VLOOKUP(AA10,Curr!$B$2:$C$13,2,FALSE),0) -> 11 | AC10: =+Y10*AB10*R10 -> 0 | AD10: =+AC10-X10 -> 0 | AE10: =IFERROR(AD10/AC10,0) -> 0
B11: FI | D11: Activity | J11: Helsinki: City Highlights & Suomenlinna Day Tour - Time: 10:00 am - 3:00 pm - Meeting point: Central Helsinki - Includes: Pickup from selected hotels, transportation by air-conditioned coach or minivan, professional English-speaking guide, round-trip ferry tickets - Description: Discover Helsinki’s best-known landmarks before taking the ferry to Suomenlinna. Explore the historic sea fortress, including its church, Great Courtyard and dry dock, while hearing stories of the city and islands. | P11: https://booknordics.com/finland/southern-finland/helsinki/helsinki-and-suomenlinna-day-sightseeing-tour | Q11: 150 | R11: 0 | S11: =+Q11*R11 -> 0 | T11: 0.2 | U11: =S11*(1-T11) -> 0 | V11: EUR | W11: =IFERROR(VLOOKUP(V11,Curr!$B$2:$C$13,2,FALSE),0) -> 11 | X11: =U11*W11 -> 0 | Y11: =Q11 -> 150 | Z11: =+Y11*R11 -> 0 | AA11: EUR | AB11: =IFERROR(VLOOKUP(AA11,Curr!$B$2:$C$13,2,FALSE),0) -> 11 | AC11: =+Y11*AB11*R11 -> 0 | AD11: =+AC11-X11 -> 0 | AE11: =IFERROR(AD11/AC11,0) -> 0
B12: FI | D12: Activity | J12: Helsinki: Tallinn Day Trip – Self-Guided Experience - Meeting point: Hotel pickup - Departure from Helsinki: 10:30 am - Departure from Tallinn: 7:30 pm - Includes: Helsinki port transfers, Star Class ferry ticket - Description: Sail across the Gulf of Finland to Tallinn and explore the city at your own pace. Wander through the medieval Old Town, historic streets and lively squares before returning to Helsinki in the evening. | O12: x | P12: https://www.tallink.com/en | Q12: =(40+40)+(50*2) -> 180 | R12: 0 | S12: =+Q12*R12 -> 0 | T12: 0 | U12: =S12*(1-T12) -> 0 | V12: EUR | W12: =IFERROR(VLOOKUP(V12,Curr!$B$2:$C$13,2,FALSE),0) -> 11 | X12: =U12*W12 -> 0 | Y12: =Q12/0.8 -> 225 | Z12: =+Y12*R12 -> 0 | AA12: EUR | AB12: =IFERROR(VLOOKUP(AA12,Curr!$B$2:$C$13,2,FALSE),0) -> 11 | AC12: =+Y12*AB12*R12 -> 0 | AD12: =+AC12-X12 -> 0 | AE12: =IFERROR(AD12/AC12,0) -> 0
B13: FI | D13: Activity | J13: Helsinki: Tallinn Day Trip – Guided Experience - Meeting point: Hotel pickup - Departure from Helsinki: 10:30 am - Departure from Tallinn: 7:30 pm - Includes: Helsinki port transfers, Star Class ferry ticket, guided tour of Tallinn Old Town - Description: Travel by ferry from Helsinki to Tallinn and discover Estonia’s capital. Explore the medieval Old Town with a local guide, then enjoy free time in the city before returning to Helsinki. | O13: x | P13: https://www.tallink.com/en | Q13: =(40+40)+(50*2) -> 180 | R13: 0 | S13: =+Q13*R13 -> 0 | T13: 0 | U13: =S13*(1-T13) -> 0 | V13: EUR | W13: =IFERROR(VLOOKUP(V13,Curr!$B$2:$C$13,2,FALSE),0) -> 11 | X13: =U13*W13 -> 0 | Y13: =Q13 -> 180 | Z13: =+Y13*R13 -> 0 | AA13: EUR | AB13: =IFERROR(VLOOKUP(AA13,Curr!$B$2:$C$13,2,FALSE),0) -> 11 | AC13: =+Y13*AB13*R13 -> 0 | AD13: =+AC13-X13 -> 0 | AE13: =IFERROR(AD13/AC13,0) -> 0
B14: FI | D14: Activity | J14: Tallinn: Old Town Guided Walking Tour - Time: 1:00 pm - 3:30 pm - Meeting point: Under the Town Hall clock - Highlights: St. Nicholas’ Church, Freedom Square, Alexander Nevsky Cathedral, St. Mary’s Cathedral, Danish King’s Garden and more - Includes: English-speaking guide, local recommendations - Description: Explore Tallinn’s medieval Old Town with a local guide, visiting historic squares, impressive churches and charming streets while learning about the city’s history and culture. | O14: x | P14: https://120degrees.club/ | Q14: 30 | R14: 0 | S14: =+Q14*R14 -> 0 | T14: 0 | U14: =S14*(1-T14) -> 0 | V14: EUR | W14: =IFERROR(VLOOKUP(V14,Curr!$B$2:$C$13,2,FALSE),0) -> 11 | X14: =U14*W14 -> 0 | Y14: =Q14 -> 30 | Z14: =+Y14*R14 -> 0 | AA14: EUR | AB14: =IFERROR(VLOOKUP(AA14,Curr!$B$2:$C$13,2,FALSE),0) -> 11 | AC14: =+Y14*AB14*R14 -> 0 | AD14: =+AC14-X14 -> 0 | AE14: =IFERROR(AD14/AC14,0) -> 0
B15: FI | D15: Activity | J15: Rovaniemi: Santa Claus Village Self-Guided Christmas Experience - Time: 10:30 am - 12:30 pm - Meeting point: Lapland Royal Adventures Office, Koskikatu 24 - Includes: Central Rovaniemi pickup and drop-off, round-trip transportation, brief guided introduction, self-guided visit - Description: Explore Santa Claus Village at your own pace. Meet Santa, visit the Main Post Office and cross the Arctic Circle before returning to Rovaniemi. | P15: https://booknordics.com/finland/western-lapland/rovaniemi/santa-claus-village-visit | Q15: 20 | R15: 0 | S15: =+Q15*R15 -> 0 | T15: 0.2 | U15: =S15*(1-T15) -> 0 | V15: EUR | W15: =IFERROR(VLOOKUP(V15,Curr!$B$2:$C$13,2,FALSE),0) -> 11 | X15: =U15*W15 -> 0 | Y15: =Q15/0.5 -> 40 | Z15: =+Y15*R15 -> 0 | AA15: EUR | AB15: =IFERROR(VLOOKUP(AA15,Curr!$B$2:$C$13,2,FALSE),0) -> 11 | AC15: =+Y15*AB15*R15 -> 0 | AD15: =+AC15-X15 -> 0 | AE15: =IFERROR(AD15/AC15,0) -> 0
B16: FI | D16: Activity | J16: Rovaniemi: Guided Santa Claus Village Experience - Time: 10:00 am - 2:00 pm - Meeting point: Nordic Unique Travels Office, Maakuntakatu 29 - Includes: Pickup and drop-off from selected locations, English-speaking guide, other languages on request, meeting with Santa Claus, Arctic Circle certificate, buffet lunch - Description: Discover the magic of Santa Claus Village with a local guide. Meet Santa, cross the Arctic Circle and visit the Main Post Office before enjoying a traditional buffet lunch. | P16: https://booknordics.com/finland/western-lapland/rovaniemi/trip-to-santa-claus-village | Q16: 99 | R16: 0 | S16: =+Q16*R16 -> 0 | T16: 0.2 | U16: =S16*(1-T16) -> 0 | V16: EUR | W16: =IFERROR(VLOOKUP(V16,Curr!$B$2:$C$13,2,FALSE),0) -> 11 | X16: =U16*W16 -> 0 | Y16: =Q16 -> 99 | Z16: =+Y16*R16 -> 0 | AA16: EUR | AB16: =IFERROR(VLOOKUP(AA16,Curr!$B$2:$C$13,2,FALSE),0) -> 11 | AC16: =+Y16*AB16*R16 -> 0 | AD16: =+AC16-X16 -> 0 | AE16: =IFERROR(AD16/AC16,0) -> 0
B17: FI | D17: Activity | J17: Rovaniemi: Reindeer & Husky Sleigh Rides with Santa Claus Village - Time: 9:00 am - 3:00 pm - Meeting point: Arctic Circle Snowmobile Park Office, Koskikatu 8 - Includes: Central Rovaniemi pickup and drop-off, reindeer farm visit with a shared sleigh ride, reindeer driver’s licence, Alaskan husky visit with a shared sleigh ride, approximately two hours at Santa Claus Village, winter clothing, traditional salmon soup or vegetarian alternative - Description: Experience a memorable day of Lapland traditions with reindeer and husky sleigh rides, fascinating encounters with Arctic animals and time to explore the festive surroundings of Santa Claus Village. | P17: https://booknordics.com/finland/western-lapland/rovaniemi/arctic-circle-highlights-family-day-by-minibus | Q17: 188 | R17: 0 | S17: =+Q17*R17 -> 0 | T17: 0.2 | U17: =S17*(1-T17) -> 0 | V17: EUR | W17: =IFERROR(VLOOKUP(V17,Curr!$B$2:$C$13,2,FALSE),0) -> 11 | X17: =U17*W17 -> 0 | Y17: =Q17 -> 188 | Z17: =+Y17*R17 -> 0 | AA17: EUR | AB17: =IFERROR(VLOOKUP(AA17,Curr!$B$2:$C$13,2,FALSE),0) -> 11 | AC17: =+Y17*AB17*R17 -> 0 | AD17: =+AC17-X17 -> 0 | AE17: =IFERROR(AD17/AC17,0) -> 0
B18: FI | D18: Activity | J18: Rovaniemi: Small-Group Northern Lights Hunt by Minibus - Time: 7:00 pm - 10:00 pm - Meeting point: Lapland Royal Adventures Office, Maakuntakatu 31 - Includes: Central Rovaniemi pickup and drop-off, knowledgeable English-speaking guide, dedicated Northern Lights chase by minibus, warm blankets, hot drinks and a snack - Description: Leave the city lights behind and follow the evening conditions to promising viewing locations around Rovaniemi. Enjoy a relaxed journey beneath the Arctic sky while searching for the Northern Lights. | P18: https://booknordics.com/finland/western-lapland/rovaniemi/aurora-quest-by-minibus | Q18: 89 | R18: 0 | S18: =+Q18*R18 -> 0 | T18: 0.2 | U18: =S18*(1-T18) -> 0 | V18: EUR | W18: =IFERROR(VLOOKUP(V18,Curr!$B$2:$C$13,2,FALSE),0) -> 11 | X18: =U18*W18 -> 0 | Y18: =Q18 -> 89 | Z18: =+Y18*R18 -> 0 | AA18: EUR | AB18: =IFERROR(VLOOKUP(AA18,Curr!$B$2:$C$13,2,FALSE),0) -> 11 | AC18: =+Y18*AB18*R18 -> 0 | AD18: =+AC18-X18 -> 0 | AE18: =IFERROR(AD18/AC18,0) -> 0
B19: FI | D19: Activity | J19: Rovaniemi: Unlimited Mileage Northern Lights Hunt - Time: Evening departure; return time varies according to conditions - Meeting point: Central Rovaniemi - Includes: Central Rovaniemi pickup and drop-off, knowledgeable English-speaking guide, dedicated Northern Lights chase, hot beverages and a light snack - Description: Follow the clearest skies far beyond Rovaniemi on an unlimited-mileage search for the Northern Lights. Travel to promising viewing locations and experience the excitement of hunting for the aurora beneath the Arctic sky. | P19: https://booknordics.com/finland/western-lapland/rovaniemi/rovaniemi-northern-lights-family-tour-by-bus-with-photos | Q19: 109 | R19: 0 | S19: =+Q19*R19 -> 0 | T19: 0.2 | U19: =S19*(1-T19) -> 0 | V19: EUR | W19: =IFERROR(VLOOKUP(V19,Curr!$B$2:$C$13,2,FALSE),0) -> 11 | X19: =U19*W19 -> 0 | Y19: =Q19 -> 109 | Z19: =+Y19*R19 -> 0 | AA19: EUR | AB19: =IFERROR(VLOOKUP(AA19,Curr!$B$2:$C$13,2,FALSE),0) -> 11 | AC19: =+Y19*AB19*R19 -> 0 | AD19: =+AC19-X19 -> 0 | AE19: =IFERROR(AD19/AC19,0) -> 0
B20: FI | D20: Activity | J20: Rovaniemi: Unlimited Mileage Northern Lights Hunt - Time: Evening departure; return time varies according to conditions - Meeting point: Central Rovaniemi - Includes: Central Rovaniemi pickup and drop-off, knowledgeable English-speaking guide, dedicated Northern Lights chase, hot beverages and a light snack - Description: Follow the clearest skies far beyond Rovaniemi on an unlimited-mileage search for the Northern Lights. Travel to promising viewing locations and experience the excitement of hunting for the aurora beneath the Arctic sky. | P20: https://booknordics.com/finland/western-lapland/rovaniemi/northern-lights-trip-no-kilometres-or-time-limit | Q20: 109 | R20: 0 | S20: =+Q20*R20 -> 0 | T20: 0.2 | U20: =S20*(1-T20) -> 0 | V20: EUR | W20: =IFERROR(VLOOKUP(V20,Curr!$B$2:$C$13,2,FALSE),0) -> 11 | X20: =U20*W20 -> 0 | Y20: =Q20 -> 109 | Z20: =+Y20*R20 -> 0 | AA20: EUR | AB20: =IFERROR(VLOOKUP(AA20,Curr!$B$2:$C$13,2,FALSE),0) -> 11 | AC20: =+Y20*AB20*R20 -> 0 | AD20: =+AC20-X20 -> 0 | AE20: =IFERROR(AD20/AC20,0) -> 0
B21: FI | D21: Activity | J21: Rovaniemi: Husky Sledding under the Northern Lights - Time: 6:15 pm - 10:15 pm - Meeting point: Nordic Unique Travels Office, Maakuntakatu 29 - Includes: Central Rovaniemi pickup and drop-off, knowledgeable English-speaking guide, husky sleigh ride through the Arctic forest, forest or lakeside Northern Lights search, winter clothing, hot blueberry juice - Description: Glide through the snowy Arctic forest behind a team of eager huskies, then continue to a peaceful forest or lakeside location to search for the Northern Lights beneath the winter sky. | P21: =HYPERLINK("https://booknordics.com/finland/western-lapland/rovaniemi/hunting-northern-lights-with-husky","https://booknordics.com/finland/western-lapland/rovaniemi/hunting-northern-lights-with-husky") -> https://booknordics.com/finland/western-lapland/rovaniemi/hunting-northern-lights-with-husky | Q21: 189 | R21: 0 | S21: =+Q21*R21 -> 0 | T21: 0.2 | U21: =S21*(1-T21) -> 0 | V21: EUR | W21: =IFERROR(VLOOKUP(V21,Curr!$B$2:$C$13,2,FALSE),0) -> 11 | X21: =U21*W21 -> 0 | Y21: =Q21 -> 189 | Z21: =+Y21*R21 -> 0 | AA21: EUR | AB21: =IFERROR(VLOOKUP(AA21,Curr!$B$2:$C$13,2,FALSE),0) -> 11 | AC21: =+Y21*AB21*R21 -> 0 | AD21: =+AC21-X21 -> 0 | AE21: =IFERROR(AD21/AC21,0) -> 0
B22: FI | D22: Activity | J22: Rovaniemi: Reindeer Farm Experience & Sleigh Ride - Time: 10:30 am - 12:30 pm - Meeting point: Nordic Unique Travels Office, Maakuntakatu 29 - Includes: Knowledgeable English-speaking guide, other languages on request, reindeer farm visit, short reindeer sleigh ride, Finnish snacks and hot blueberry juice - Description: Meet Lapland’s reindeer at a traditional farm and learn about their care and the life of local herders. Then enjoy a peaceful sleigh ride through the snowy forest. | P22: =HYPERLINK("https://booknordics.com/finland/western-lapland/rovaniemi/reindeer-farm-experience-reindeer-sledding","https://booknordics.com/finland/western-lapland/rovaniemi/reindeer-farm-experience-reindeer-sledding") -> https://booknordics.com/finland/western-lapland/rovaniemi/reindeer-farm-experience-reindeer-sledding | Q22: 119 | R22: 0 | S22: =+Q22*R22 -> 0 | T22: 0.2 | U22: =S22*(1-T22) -> 0 | V22: EUR | W22: =IFERROR(VLOOKUP(V22,Curr!$B$2:$C$13,2,FALSE),0) -> 11 | X22: =U22*W22 -> 0 | Y22: =Q22 -> 119 | Z22: =+Y22*R22 -> 0 | AA22: EUR | AB22: =IFERROR(VLOOKUP(AA22,Curr!$B$2:$C$13,2,FALSE),0) -> 11 | AC22: =+Y22*AB22*R22 -> 0 | AD22: =+AC22-X22 -> 0 | AE22: =IFERROR(AD22/AC22,0) -> 0
B23: FI | D23: Activity | J23: Rovaniemi: 2.5 km Husky Ride at Santa Claus Village - Time: Flexible start time; duration approximately 1 hour - Meeting point: Santa’s Husky Rides, Joulumaantie 3 - Includes: Pickup and transfer service, 2.5 km husky sleigh ride, Arctic outer clothing, hot juice and cookies - Description: Enjoy a lively husky sleigh ride through the snowy surroundings of Santa Claus Village. Afterwards, meet the friendly dogs and warm up with refreshments in a traditional kota. | P23: =HYPERLINK("https://booknordics.com/finland/western-lapland/rovaniemi/santas-25-km-husky-ride-at-santa-claus-village","https://booknordics.com/finland/western-lapland/rovaniemi/santas-25-km-husky-ride-at-santa-claus-village") -> https://booknordics.com/finland/western-lapland/rovaniemi/santas-25-km-husky-ride-at-santa-claus-village | Q23: 63 | R23: 0 | S23: =+Q23*R23 -> 0 | T23: 0.2 | U23: =S23*(1-T23) -> 0 | V23: EUR | W23: =IFERROR(VLOOKUP(V23,Curr!$B$2:$C$13,2,FALSE),0) -> 11 | X23: =U23*W23 -> 0 | Y23: =Q23 -> 63 | Z23: =+Y23*R23 -> 0 | AA23: EUR | AB23: =IFERROR(VLOOKUP(AA23,Curr!$B$2:$C$13,2,FALSE),0) -> 11 | AC23: =+Y23*AB23*R23 -> 0 | AD23: =+AC23-X23 -> 0 | AE23: =IFERROR(AD23/AC23,0) -> 0
B24: FI | D24: Activity | J24: Rovaniemi: Snowmobiling, Husky Sledding & Reindeer Farm Experience - Time: 09:00 am - 5:00 pm - Meeting point: Arctic Lifestyle Safaris Office, Pirkkakatu 2 - Includes: Central Rovaniemi pickup and drop-off, knowledgeable English-speaking guide, snowmobile safari, reindeer farm visit with a 500–700 m sleigh ride, 10–12 km husky safari, winter clothing, helmet and light soup lunch - Description: Experience three classic Lapland adventures in one memorable day. Travel by snowmobile through snowy landscapes, meet reindeer at a local farm and set out on an exciting husky safari through the wilderness. | P24: =HYPERLINK("https://booknordics.com/finland/western-lapland/rovaniemi/snowmobiling-husky-dog-sledding-reindeer-farm-visit","https://booknordics.com/finland/western-lapland/rovaniemi/snowmobiling-husky-dog-sledding-reindeer-farm-visit") -> https://booknordics.com/finland/western-lapland/rovaniemi/snowmobiling-husky-dog-sledding-reindeer-farm-visit | Q24: 339 | R24: 0 | S24: =+Q24*R24 -> 0 | T24: 0.2 | U24: =S24*(1-T24) -> 0 | V24: EUR | W24: =IFERROR(VLOOKUP(V24,Curr!$B$2:$C$13,2,FALSE),0) -> 11 | X24: =U24*W24 -> 0 | Y24: =Q24 -> 339 | Z24: =+Y24*R24 -> 0 | AA24: EUR | AB24: =IFERROR(VLOOKUP(AA24,Curr!$B$2:$C$13,2,FALSE),0) -> 11 | AC24: =+Y24*AB24*R24 -> 0 | AD24: =+AC24-X24 -> 0 | AE24: =IFERROR(AD24/AC24,0) -> 0
B25: FI | D25: Activity | J25: Rovaniemi: 20 km Snowy Trails Husky Adventure - Time: 12:00 pm - 7:00 pm - Meeting point: Nordic Unique Travels Office, Maakuntakatu 29 - Includes: Knowledgeable English-speaking guide, other languages on request, husky farm visit, approximately 20 km husky sleigh ride, winter clothing, Finnish snacks and hot juice - Description: Set out on an exhilarating husky sleigh ride through pristine forest trails. Afterwards, meet the dogs and learn about their training, care and role in Lapland’s traditions. | P25: =HYPERLINK("https://booknordics.com/finland/western-lapland/rovaniemi/snowy-trails-husky-adventure-20-km","https://booknordics.com/finland/western-lapland/rovaniemi/snowy-trails-husky-adventure-20-km") -> https://booknordics.com/finland/western-lapland/rovaniemi/snowy-trails-husky-adventure-20-km | Q25: 259 | R25: 0 | S25: =+Q25*R25 -> 0 | T25: 0.2 | U25: =S25*(1-T25) -> 0 | V25: EUR | W25: =IFERROR(VLOOKUP(V25,Curr!$B$2:$C$13,2,FALSE),0) -> 11 | X25: =U25*W25 -> 0 | Y25: =Q25 -> 259 | Z25: =+Y25*R25 -> 0 | AA25: EUR | AB25: =IFERROR(VLOOKUP(AA25,Curr!$B$2:$C$13,2,FALSE),0) -> 11 | AC25: =+Y25*AB25*R25 -> 0 | AD25: =+AC25-X25 -> 0 | AE25: =IFERROR(AD25/AC25,0) -> 0
B26: FI | D26: Activity | J26: Rovaniemi: One-Hour Arctic Circle Snowmobile Safari - Time: 0845 am - 10:45 am - Meeting point: Arctic Circle Snowmobile Park, Joulumaantie 5 - Includes: Professional English-speaking guide, one-hour shared snowmobile ride, thermal overalls, boots, socks, gloves and balaclava, helmet and snowmobile equipment - Description: Learn to handle a snowmobile before riding through snowy forests and frozen landscapes around Santa Claus Village. The route and pace are adapted to the group, making this an enjoyable introduction to Arctic snowmobiling. | P26: =HYPERLINK("https://booknordics.com/finland/western-lapland/rovaniemi/arctic-circle-snowmobile-safari-1h","https://booknordics.com/finland/western-lapland/rovaniemi/arctic-circle-snowmobile-safari-1h") -> https://booknordics.com/finland/western-lapland/rovaniemi/arctic-circle-snowmobile-safari-1h | Q26: 100 | R26: 0 | S26: =+Q26*R26 -> 0 | T26: 0.2 | U26: =S26*(1-T26) -> 0 | V26: EUR | W26: =IFERROR(VLOOKUP(V26,Curr!$B$2:$C$13,2,FALSE),0) -> 11 | X26: =U26*W26 -> 0 | Y26: =Q26 -> 100 | Z26: =+Y26*R26 -> 0 | AA26: EUR | AB26: =IFERROR(VLOOKUP(AA26,Curr!$B$2:$C$13,2,FALSE),0) -> 11 | AC26: =+Y26*AB26*R26 -> 0 | AD26: =+AC26-X26 -> 0 | AE26: =IFERROR(AD26/AC26,0) -> 0
B27: FI | D27: Activity | J27: Rovaniemi: Snowmobile Adventure in Lapland - Time: 8:00 am - 12:00 pm - Meeting point: Wild About Lapland Office, Rovakatu 24 - Includes: Central Rovaniemi pickup and drop-off, knowledgeable English-speaking guide, shared snowmobile ride, driving and safety instructions, thermal overalls, boots, gloves, helmet and balaclava, hot drinks - Description: Ride through snow-covered taiga forests and across frozen landscapes, pausing along the way to enjoy the peaceful scenery and a warm drink before continuing through the Arctic wilderness. | P27: =HYPERLINK("https://booknordics.com/finland/western-lapland/rovaniemi/snowmobile-adventure-in-lapland","https://booknordics.com/finland/western-lapland/rovaniemi/snowmobile-adventure-in-lapland") -> https://booknordics.com/finland/western-lapland/rovaniemi/snowmobile-adventure-in-lapland | Q27: 165 | R27: 0 | S27: =+Q27*R27 -> 0 | T27: 0.2 | U27: =S27*(1-T27) -> 0 | V27: EUR | W27: =IFERROR(VLOOKUP(V27,Curr!$B$2:$C$13,2,FALSE),0) -> 11 | X27: =U27*W27 -> 0 | Y27: =Q27 -> 165 | Z27: =+Y27*R27 -> 0 | AA27: EUR | AB27: =IFERROR(VLOOKUP(AA27,Curr!$B$2:$C$13,2,FALSE),0) -> 11 | AC27: =+Y27*AB27*R27 -> 0 | AD27: =+AC27-X27 -> 0 | AE27: =IFERROR(AD27/AC27,0) -> 0
B28: FI | D28: Activity | J28: Rovaniemi: Korouoma Canyon Frozen Waterfalls Tour - Time: 8:30 am - 3:30 pm - Meeting point: Central Rovaniemi - Includes: Central Rovaniemi pickup and drop-off, round-trip transportation, expert English-speaking guide, approximately 5 km guided hike, ice cleats, wilderness barbecue lunch and hot drinks - Description: Hike through snow-covered pine forests into Korouoma Canyon, where towering frozen waterfalls line the cliffs. Enjoy dramatic winter scenery and a fireside lunch during this rewarding Arctic nature adventure. | P28: =HYPERLINK("https://booknordics.com/finland/western-lapland/rovaniemi/korouoma-canyon-frozen-waterfalls-4","https://booknordics.com/finland/western-lapland/rovaniemi/korouoma-canyon-frozen-waterfalls-4") -> https://booknordics.com/finland/western-lapland/rovaniemi/korouoma-canyon-frozen-waterfalls-4 | Q28: 140 | R28: 0 | S28: =+Q28*R28 -> 0 | T28: 0.2 | U28: =S28*(1-T28) -> 0 | V28: EUR | W28: =IFERROR(VLOOKUP(V28,Curr!$B$2:$C$13,2,FALSE),0) -> 11 | X28: =U28*W28 -> 0 | Y28: =Q28 -> 140 | Z28: =+Y28*R28 -> 0 | AA28: EUR | AB28: =IFERROR(VLOOKUP(AA28,Curr!$B$2:$C$13,2,FALSE),0) -> 11 | AC28: =+Y28*AB28*R28 -> 0 | AD28: =+AC28-X28 -> 0 | AE28: =IFERROR(AD28/AC28,0) -> 0
B29: FI | D29: Activity | J29: Rovaniemi: Arctic Wildlife Adventure to Ranua Wildlife Park - Time: 10:00 am - 4:00 pm - Meeting point: Lapland Royal Adventures Office, Maakuntakatu 31 - Includes: Central Rovaniemi pickup and drop-off, round-trip minivan transportation, knowledgeable English-speaking guide, Ranua Wildlife Park entrance ticket, BBQ sausages and hot drinks by the campfire, stop at the Fazer outlet - Description: Discover polar bears and around 50 other Arctic and northern animal species in Ranua Wildlife Park’s peaceful forest setting. Enjoy an informative guided visit and a warming campfire break before returning to Rovaniemi. | P29: =HYPERLINK("https://booknordics.com/finland/western-lapland/rovaniemi/arctic-wildlife-adventure-ranua-wildlife-park-trip","https://booknordics.com/finland/western-lapland/rovaniemi/arctic-wildlife-adventure-ranua-wildlife-park-trip") -> https://booknordics.com/finland/western-lapland/rovaniemi/arctic-wildlife-adventure-ranua-wildlife-park-trip | Q29: 109 | R29: 0 | S29: =+Q29*R29 -> 0 | T29: 0 | U29: =S29*(1-T29) -> 0 | V29: EUR | W29: =IFERROR(VLOOKUP(V29,Curr!$B$2:$C$13,2,FALSE),0) -> 11 | X29: =U29*W29 -> 0 | Y29: =Q29 -> 109 | Z29: =+Y29*R29 -> 0 | AA29: EUR | AB29: =IFERROR(VLOOKUP(AA29,Curr!$B$2:$C$13,2,FALSE),0) -> 11 | AC29: =+Y29*AB29*R29 -> 0 | AD29: =+AC29-X29 -> 0 | AE29: =IFERROR(AD29/AC29,0) -> 0
B30: FI | D30: Activity | J30: Rovaniemi: Polar Explorer Icebreaker Party Cruise & Lunch - Time: 8:00 am - 4:35 pm - Meeting point: Rovaniemi Tourist Information, Koskikatu 12 - Includes: Round-trip shuttle transportation from Rovaniemi city centre, three-hour icebreaker cruise, guided tour across seven decks, audio guide, icebreaker film, walk on the frozen sea, optional ice swimming in a survival suit, ABBA-inspired music party, two-course lunch, hot drink and cruise certificate - Description: Cruise through the frozen Bothnian Sea aboard the Polar Explorer and enjoy lunch and music on board. Step onto the sea ice and, if you wish, float safely in the icy water. | P30: =HYPERLINK("https://booknordics.com/finland/western-lapland/rovaniemi/polar-explorer-icebreaker-dancing-queen-party-cruise-and-lunch-with-shuttle-bus-transportation-from-rovaniemi","https://booknordics.com/finland/western-lapland/rovaniemi/polar-explorer-icebreaker-dancing-queen-party-cruise-and-lunch-with-shuttle-bus-transportation-from-rovaniemi") -> https://booknordics.com/finland/western-lapland/rovaniemi/polar-explorer-icebreaker-dancing-queen-party-cruise-and-lunch-with-shuttle-bus-transportation-from-rovaniemi | Q30: 425 | R30: 0 | S30: =+Q30*R30 -> 0 | T30: 0.12 | U30: =S30*(1-T30) -> 0 | V30: EUR | W30: =IFERROR(VLOOKUP(V30,Curr!$B$2:$C$13,2,FALSE),0) -> 11 | X30: =U30*W30 -> 0 | Y30: =Q30 -> 425 | Z30: =+Y30*R30 -> 0 | AA30: EUR | AB30: =IFERROR(VLOOKUP(AA30,Curr!$B$2:$C$13,2,FALSE),0) -> 11 | AC30: =+Y30*AB30*R30 -> 0 | AD30: =+AC30-X30 -> 0 | AE30: =IFERROR(AD30/AC30,0) -> 0
B31: FI | D31: Activity | J31: Kakslauttanen: Planetarium Experience - Time: Daytime visit; duration approximately 30 minutes - Meeting point: Kakslauttanen Planetarium - Includes: Planetarium show, entry to the glass-roof restaurant and access to its local art, design and brewery displays - Description: Journey through the Arctic night sky in Scandinavia’s largest planetarium, then explore a distinctive glass-roof venue celebrating Lapland’s creativity and culture. | Q31: 35 | R31: 0 | S31: =+Q31*R31 -> 0 | T31: 0 | U31: =S31*(1-T31) -> 0 | V31: EUR | W31: =IFERROR(VLOOKUP(V31,Curr!$B$2:$C$13,2,FALSE),0) -> 11 | X31: =U31*W31 -> 0 | Y31: =Q31/0.8 -> 43.75 | Z31: =+Y31*R31 -> 0 | AA31: EUR | AB31: =IFERROR(VLOOKUP(AA31,Curr!$B$2:$C$13,2,FALSE),0) -> 11 | AC31: =+Y31*AB31*R31 -> 0 | AD31: =+AC31-X31 -> 0 | AE31: =IFERROR(AD31/AC31,0) -> 0
B32: FI | D32: Activity | J32: Kakslauttanen: Visit to Santa’s Home - Time: Afternoon visit; duration approximately 1.5 hours - Meeting point: Santa’s Home, Kakslauttanen Arctic Resort - Includes: Personal meeting with Santa Claus - Description: Step into Santa’s enchanting home for a personal encounter filled with festive stories and Christmas magic in the heart of Finnish Lapland. | Q32: 79 | R32: 0 | S32: =+Q32*R32 -> 0 | T32: 0 | U32: =S32*(1-T32) -> 0 | V32: EUR | W32: =IFERROR(VLOOKUP(V32,Curr!$B$2:$C$13,2,FALSE),0) -> 11 | X32: =U32*W32 -> 0 | Y32: =Q32/0.8 -> 98.75 | Z32: =+Y32*R32 -> 0 | AA32: EUR | AB32: =IFERROR(VLOOKUP(AA32,Curr!$B$2:$C$13,2,FALSE),0) -> 11 | AC32: =+Y32*AB32*R32 -> 0 | AD32: =+AC32-X32 -> 0 | AE32: =IFERROR(AD32/AC32,0) -> 0
B33: FI | D33: Activity | J33: Kakslauttanen: Nordic Skiing Lesson - Time: Daytime session; duration approximately 1 hour - Meeting point: Kakslauttanen Arctic Resort reception - Includes: Professional Nordic skiing instructor - Description: Learn the fundamentals of Nordic skiing and practise gliding through the peaceful, snow-covered surroundings of Kakslauttanen with guidance from an experienced instructor. | Q33: 71 | R33: 0 | S33: =+Q33*R33 -> 0 | T33: 0 | U33: =S33*(1-T33) -> 0 | V33: EUR | W33: =IFERROR(VLOOKUP(V33,Curr!$B$2:$C$13,2,FALSE),0) -> 11 | X33: =U33*W33 -> 0 | Y33: =Q33/0.8 -> 88.75 | Z33: =+Y33*R33 -> 0 | AA33: EUR | AB33: =IFERROR(VLOOKUP(AA33,Curr!$B$2:$C$13,2,FALSE),0) -> 11 | AC33: =+Y33*AB33*R33 -> 0 | AD33: =+AC33-X33 -> 0 | AE33: =IFERROR(AD33/AC33,0) -> 0
B34: FI | D34: Activity | J34: Kakslauttanen: Ice Karting Experience - Time: Daytime departure; duration approximately 2 hours - Meeting point: Kakslauttanen Arctic Resort reception - Includes: Resort transfers, thermal clothing, required karting equipment and a hot drink - Description: Race across a frozen track in specially designed karts, combining speed, skill and winter fun in an exciting Arctic setting. | Q34: 145 | R34: 0 | S34: =+Q34*R34 -> 0 | T34: 0 | U34: =S34*(1-T34) -> 0 | V34: EUR | W34: =IFERROR(VLOOKUP(V34,Curr!$B$2:$C$13,2,FALSE),0) -> 11 | X34: =U34*W34 -> 0 | Y34: =Q34/0.8 -> 181.25 | Z34: =+Y34*R34 -> 0 | AA34: EUR | AB34: =IFERROR(VLOOKUP(AA34,Curr!$B$2:$C$13,2,FALSE),0) -> 11 | AC34: =+Y34*AB34*R34 -> 0 | AD34: =+AC34-X34 -> 0 | AE34: =IFERROR(AD34/AC34,0) -> 0
B35: FI | D35: Activity | J35: Kakslauttanen: 2-Hour Husky Safari – Shared Sleigh - Time: Daytime departure; duration approximately 2 hours - Meeting point: Kakslauttanen Arctic Resort reception - Includes: Resort transfers, shared husky sleigh, thermal clothing, winter boots, gloves and a hot drink - Description: Meet an energetic team of huskies and take turns driving a shared sleigh through snowy forest trails before warming up with a hot drink. | Q35: 157 | R35: 0 | S35: =+Q35*R35 -> 0 | T35: 0 | U35: =S35*(1-T35) -> 0 | V35: EUR | W35: =IFERROR(VLOOKUP(V35,Curr!$B$2:$C$13,2,FALSE),0) -> 11 | X35: =U35*W35 -> 0 | Y35: =Q35/0.8 -> 196.25 | Z35: =+Y35*R35 -> 0 | AA35: EUR | AB35: =IFERROR(VLOOKUP(AA35,Curr!$B$2:$C$13,2,FALSE),0) -> 11 | AC35: =+Y35*AB35*R35 -> 0 | AD35: =+AC35-X35 -> 0 | AE35: =IFERROR(AD35/AC35,0) -> 0
B36: FI | D36: Activity | J36: Kakslauttanen: 2-Hour Husky Safari – Private Sleigh - Time: Daytime departure; duration approximately 2 hours - Meeting point: Kakslauttanen Arctic Resort reception - Includes: Resort transfers, private husky sleigh, thermal clothing, winter boots, gloves and a hot drink - Description: Take control of your own husky sleigh and travel through peaceful snow-covered forests, enjoying the energy of the dogs and the beauty of Lapland. | Q36: 225 | R36: 0 | S36: =+Q36*R36 -> 0 | T36: 0 | U36: =S36*(1-T36) -> 0 | V36: EUR | W36: =IFERROR(VLOOKUP(V36,Curr!$B$2:$C$13,2,FALSE),0) -> 11 | X36: =U36*W36 -> 0 | Y36: =Q36/0.8 -> 281.25 | Z36: =+Y36*R36 -> 0 | AA36: EUR | AB36: =IFERROR(VLOOKUP(AA36,Curr!$B$2:$C$13,2,FALSE),0) -> 11 | AC36: =+Y36*AB36*R36 -> 0 | AD36: =+AC36-X36 -> 0 | AE36: =IFERROR(AD36/AC36,0) -> 0
B37: FI | D37: Activity | J37: Kakslauttanen: 4-Hour Husky Safari – Shared Sleigh - Time: Daytime departure; duration approximately 4 hours - Meeting point: Kakslauttanen Arctic Resort reception - Includes: Resort transfers, shared husky sleigh, thermal clothing, winter boots, gloves and lunch - Description: Venture deeper into the wilderness on an extended husky safari, taking turns driving through snowy forests before pausing for a warming lunch. | Q37: 223 | R37: 0 | S37: =+Q37*R37 -> 0 | T37: 0 | U37: =S37*(1-T37) -> 0 | V37: EUR | W37: =IFERROR(VLOOKUP(V37,Curr!$B$2:$C$13,2,FALSE),0) -> 11 | X37: =U37*W37 -> 0 | Y37: =Q37/0.8 -> 278.75 | Z37: =+Y37*R37 -> 0 | AA37: EUR | AB37: =IFERROR(VLOOKUP(AA37,Curr!$B$2:$C$13,2,FALSE),0) -> 11 | AC37: =+Y37*AB37*R37 -> 0 | AD37: =+AC37-X37 -> 0 | AE37: =IFERROR(AD37/AC37,0) -> 0
B38: FI | D38: Activity | J38: Kakslauttanen: 4-Hour Husky Safari – Private Sleigh - Time: Daytime departure; duration approximately 4 hours - Meeting point: Kakslauttanen Arctic Resort reception - Includes: Resort transfers, private husky sleigh, thermal clothing, winter boots, gloves and lunch - Description: Guide your own husky team through the quiet Lapland wilderness on an extended safari, with time to enjoy the scenery and a warming lunch. | Q38: 276 | R38: 0 | S38: =+Q38*R38 -> 0 | T38: 0 | U38: =S38*(1-T38) -> 0 | V38: EUR | W38: =IFERROR(VLOOKUP(V38,Curr!$B$2:$C$13,2,FALSE),0) -> 11 | X38: =U38*W38 -> 0 | Y38: =Q38/0.8 -> 345 | Z38: =+Y38*R38 -> 0 | AA38: EUR | AB38: =IFERROR(VLOOKUP(AA38,Curr!$B$2:$C$13,2,FALSE),0) -> 11 | AC38: =+Y38*AB38*R38 -> 0 | AD38: =+AC38-X38 -> 0 | AE38: =IFERROR(AD38/AC38,0) -> 0
B39: FI | D39: Activity | J39: Kakslauttanen: Northern Lights Hunt with Huskies - Time: Evening departure; duration approximately 2 hours - Meeting point: Kakslauttanen Arctic Resort reception - Includes: Resort transfers, shared husky sleigh, thermal clothing, winter boots, gloves and a hot drink - Description: Glide through the dark Arctic wilderness by husky sleigh while searching the night sky for the Northern Lights, followed by a warming drink. | Q39: 189 | R39: 0 | S39: =+Q39*R39 -> 0 | T39: 0 | U39: =S39*(1-T39) -> 0 | V39: EUR | W39: =IFERROR(VLOOKUP(V39,Curr!$B$2:$C$13,2,FALSE),0) -> 11 | X39: =U39*W39 -> 0 | Y39: =Q39/0.8 -> 236.25 | Z39: =+Y39*R39 -> 0 | AA39: EUR | AB39: =IFERROR(VLOOKUP(AA39,Curr!$B$2:$C$13,2,FALSE),0) -> 11 | AC39: =+Y39*AB39*R39 -> 0 | AD39: =+AC39-X39 -> 0 | AE39: =IFERROR(AD39/AC39,0) -> 0
B40: FI | D40: Activity | J40: Kakslauttanen: Overnight Husky Safari in the Wilderness - Time: Morning departure; duration approximately 2 days - Meeting point: Kakslauttanen Arctic Resort reception - Includes: Resort transfers, private husky sleigh, thermal clothing, winter boots, gloves, full board and wilderness lodging - Description: Journey by husky sleigh into remote Lapland, spend the night in peaceful wilderness surroundings and enjoy an unforgettable two-day Arctic adventure. | Q40: 835 | R40: 0 | S40: =+Q40*R40 -> 0 | T40: 0 | U40: =S40*(1-T40) -> 0 | V40: EUR | W40: =IFERROR(VLOOKUP(V40,Curr!$B$2:$C$13,2,FALSE),0) -> 11 | X40: =U40*W40 -> 0 | Y40: =Q40/0.8 -> 1043.75 | Z40: =+Y40*R40 -> 0 | AA40: EUR | AB40: =IFERROR(VLOOKUP(AA40,Curr!$B$2:$C$13,2,FALSE),0) -> 11 | AC40: =+Y40*AB40*R40 -> 0 | AD40: =+AC40-X40 -> 0 | AE40: =IFERROR(AD40/AC40,0) -> 0
B41: FI | D41: Activity | J41: Kakslauttanen: 2-Hour Reindeer Safari – Shared Sleigh - Time: Daytime departure; duration approximately 2 hours - Meeting point: Kakslauttanen Arctic Resort reception - Includes: Resort transfers, shared reindeer sleigh, thermal clothing, winter boots, gloves and a hot drink - Description: Travel quietly through the snowy landscape in a traditional reindeer sleigh and experience the gentle pace and timeless atmosphere of Lapland. | Q41: 100 | R41: 0 | S41: =+Q41*R41 -> 0 | T41: 0 | U41: =S41*(1-T41) -> 0 | V41: EUR | W41: =IFERROR(VLOOKUP(V41,Curr!$B$2:$C$13,2,FALSE),0) -> 11 | X41: =U41*W41 -> 0 | Y41: =Q41/0.8 -> 125 | Z41: =+Y41*R41 -> 0 | AA41: EUR | AB41: =IFERROR(VLOOKUP(AA41,Curr!$B$2:$C$13,2,FALSE),0) -> 11 | AC41: =+Y41*AB41*R41 -> 0 | AD41: =+AC41-X41 -> 0 | AE41: =IFERROR(AD41/AC41,0) -> 0
B42: FI | D42: Activity | J42: Kakslauttanen: 2-Hour Reindeer Safari – Private Sleigh - Time: Daytime departure; duration approximately 2 hours - Meeting point: Kakslauttanen Arctic Resort reception - Includes: Resort transfers, private reindeer sleigh, thermal clothing, winter boots, gloves and a hot drink - Description: Enjoy a private reindeer sleigh journey through peaceful winter scenery, experiencing one of Lapland’s most traditional and tranquil ways to travel. | Q42: 145 | R42: 0 | S42: =+Q42*R42 -> 0 | T42: 0 | U42: =S42*(1-T42) -> 0 | V42: EUR | W42: =IFERROR(VLOOKUP(V42,Curr!$B$2:$C$13,2,FALSE),0) -> 11 | X42: =U42*W42 -> 0 | Y42: =Q42/0.8 -> 181.25 | Z42: =+Y42*R42 -> 0 | AA42: EUR | AB42: =IFERROR(VLOOKUP(AA42,Curr!$B$2:$C$13,2,FALSE),0) -> 11 | AC42: =+Y42*AB42*R42 -> 0 | AD42: =+AC42-X42 -> 0 | AE42: =IFERROR(AD42/AC42,0) -> 0
... B54: FI | D54: Activity | J54: Kakslauttanen: Northern Lights Hunt by Snowmobile Sleigh - Time: Evening departure; duration approximately 2.5 hours - Meeting point: Kakslauttanen Arctic Resort reception - Includes: Guided snowmobile sleigh ride, thermal clothing, winter boots, gloves, balaclava, helmet and a hot drink - Description: Travel comfortably by snowmobile sleigh into the quiet Arctic night and search for the Northern Lights beneath the open sky. | Q54: 94 | R54: 0 | S54: =+Q54*R54 -> 0 | T54: 0 | U54: =S54*(1-T54) -> 0 | V54: EUR | W54: =IFERROR(VLOOKUP(V54,Curr!$B$2:$C$13,2,FALSE),0) -> 11 | X54: =U54*W54 -> 0 | Y54: =Q54/0.8 -> 117.5 | Z54: =+Y54*R54 -> 0 | AA54: EUR | AB54: =IFERROR(VLOOKUP(AA54,Curr!$B$2:$C$13,2,FALSE),0) -> 11 | AC54: =+Y54*AB54*R54 -> 0 | AD54: =+AC54-X54 -> 0 | AE54: =IFERROR(AD54/AC54,0) -> 0
B55: FI | D55: Activity | J55: Kemi: Icebreaker Arktis Morning Cruise - Time: Morning departure; duration approximately 3 hours - Meeting point: SnowCastle of Kemi, Lumilinnankatu 15A - Includes: Three-hour icebreaker cruise, ice floating, sea-ice walk and diploma - Description: Sail through the frozen Gulf of Bothnia aboard Icebreaker Arktis, walk on the sea ice and float safely among the ice in a protective survival suit. | P55: =HYPERLINK("https://www.icebreaking.com/icebreaker-arktis-cruise/","https://www.icebreaking.com/icebreaker-arktis-cruise/") -> https://www.icebreaking.com/icebreaker-arktis-cruise/ | Q55: 278 | R55: 0 | S55: =+Q55*R55 -> 0 | T55: 0 | U55: =S55*(1-T55) -> 0 | V55: EUR | W55: =IFERROR(VLOOKUP(V55,Curr!$B$2:$C$13,2,FALSE),0) -> 11 | X55: =U55*W55 -> 0 | Y55: =Q55/0.8 -> 347.5 | Z55: =+Y55*R55 -> 0 | AA55: EUR | AB55: =IFERROR(VLOOKUP(AA55,Curr!$B$2:$C$13,2,FALSE),0) -> 11 | AC55: =+Y55*AB55*R55 -> 0 | AD55: =+AC55-X55 -> 0 | AE55: =IFERROR(AD55/AC55,0) -> 0
B56: FI | D56: Activity | J56: Kemi: Icebreaker Arktis Afternoon Cruise - Time: Afternoon departure; duration approximately 3 hours - Meeting point: SnowCastle of Kemi, Lumilinnankatu 15A - Includes: Three-hour icebreaker cruise, ice floating, sea-ice walk and diploma - Description: Sail through the frozen Gulf of Bothnia aboard Icebreaker Arktis, walk on the sea ice and float safely among the ice in a protective survival suit. | P56: =HYPERLINK("https://www.icebreaking.com/icebreaker-arktis-cruise/","https://www.icebreaking.com/icebreaker-arktis-cruise/") -> https://www.icebreaking.com/icebreaker-arktis-cruise/ | Q56: 278 | R56: 0 | S56: =+Q56*R56 -> 0 | T56: 0 | U56: =S56*(1-T56) -> 0 | V56: EUR | W56: =IFERROR(VLOOKUP(V56,Curr!$B$2:$C$13,2,FALSE),0) -> 11 | X56: =U56*W56 -> 0 | Y56: =Q56/0.8 -> 347.5 | Z56: =+Y56*R56 -> 0 | AA56: EUR | AB56: =IFERROR(VLOOKUP(AA56,Curr!$B$2:$C$13,2,FALSE),0) -> 11 | AC56: =+Y56*AB56*R56 -> 0 | AD56: =+AC56-X56 -> 0 | AE56: =IFERROR(AD56/AC56,0) -> 0
B57: FI | D57: Activity | J57: Kemi: Icebreaker Arktis Morning Cruise with Transfers - Time: Morning departure; duration approximately 4-5 hours - Meeting point: Selected Kemi or SnowCastle pickup point - Includes: Return shuttle transportation, three-hour icebreaker cruise, ice floating, sea-ice walk and diploma - Description: Travel from Kemi to the frozen Gulf of Bothnia for an Icebreaker Arktis cruise, with a sea-ice walk and memorable floating experience in a protective survival suit. | P57: =HYPERLINK("https://www.icebreaking.com/icebreaker-arktis-cruise/","https://www.icebreaking.com/icebreaker-arktis-cruise/") -> https://www.icebreaking.com/icebreaker-arktis-cruise/ | Q57: 315 | R57: 0 | S57: =+Q57*R57 -> 0 | T57: 0 | U57: =S57*(1-T57) -> 0 | V57: EUR | W57: =IFERROR(VLOOKUP(V57,Curr!$B$2:$C$13,2,FALSE),0) -> 11 | X57: =U57*W57 -> 0 | Y57: =Q57/0.8 -> 393.75 | Z57: =+Y57*R57 -> 0 | AA57: EUR | AB57: =IFERROR(VLOOKUP(AA57,Curr!$B$2:$C$13,2,FALSE),0) -> 11 | AC57: =+Y57*AB57*R57 -> 0 | AD57: =+AC57-X57 -> 0 | AE57: =IFERROR(AD57/AC57,0) -> 0
B58: FI | D58: Activity | J58: Kemi: Icebreaker Arktis Afternoon Cruise with Transfers - Time: Afternoon departure; duration approximately 4-5 hours - Meeting point: Selected Kemi or SnowCastle pickup point - Includes: Return shuttle transportation, three-hour icebreaker cruise, ice floating, sea-ice walk and diploma - Description: Travel from Kemi to the frozen Gulf of Bothnia for an Icebreaker Arktis cruise, with a sea-ice walk and memorable floating experience in a protective survival suit. | P58: =HYPERLINK("https://www.icebreaking.com/icebreaker-arktis-cruise/","https://www.icebreaking.com/icebreaker-arktis-cruise/") -> https://www.icebreaking.com/icebreaker-arktis-cruise/ | Q58: 315 | R58: 0 | S58: =+Q58*R58 -> 0 | T58: 0 | U58: =S58*(1-T58) -> 0 | V58: EUR | W58: =IFERROR(VLOOKUP(V58,Curr!$B$2:$C$13,2,FALSE),0) -> 11 | X58: =U58*W58 -> 0 | Y58: =Q58/0.8 -> 393.75 | Z58: =+Y58*R58 -> 0 | AA58: EUR | AB58: =IFERROR(VLOOKUP(AA58,Curr!$B$2:$C$13,2,FALSE),0) -> 11 | AC58: =+Y58*AB58*R58 -> 0 | AD58: =+AC58-X58 -> 0 | AE58: =IFERROR(AD58/AC58,0) -> 0
B59: FI | D59: Activity | J59: Haparanda–Tornio: Icebreaker Arktis Morning Cruise - Time: Morning departure; duration approximately 6-7 hours - Meeting point: Selected Haparanda or Tornio pickup point - Includes: Return shuttle transportation, three-hour icebreaker cruise, ice floating, sea-ice walk and diploma - Description: Journey from Haparanda or Tornio to the frozen Gulf of Bothnia for an Icebreaker Arktis cruise, sea-ice walk and memorable floating experience among the Arctic ice. | P59: =HYPERLINK("https://www.icebreaking.com/icebreaker-arktis-cruise/","https://www.icebreaking.com/icebreaker-arktis-cruise/") -> https://www.icebreaking.com/icebreaker-arktis-cruise/ | Q59: 351 | R59: 0 | S59: =+Q59*R59 -> 0 | T59: 0 | U59: =S59*(1-T59) -> 0 | V59: EUR | W59: =IFERROR(VLOOKUP(V59,Curr!$B$2:$C$13,2,FALSE),0) -> 11 | X59: =U59*W59 -> 0 | Y59: =Q59/0.8 -> 438.75 | Z59: =+Y59*R59 -> 0 | AA59: EUR | AB59: =IFERROR(VLOOKUP(AA59,Curr!$B$2:$C$13,2,FALSE),0) -> 11 | AC59: =+Y59*AB59*R59 -> 0 | AD59: =+AC59-X59 -> 0 | AE59: =IFERROR(AD59/AC59,0) -> 0
B60: FI | D60: Activity | J60: Haparanda–Tornio: Icebreaker Arktis Afternoon Cruise - Time: Afternoon departure; duration approximately 6-7 hours - Meeting point: Selected Haparanda or Tornio pickup point - Includes: Return shuttle transportation, three-hour icebreaker cruise, ice floating, sea-ice walk and diploma - Description: Journey from Haparanda or Tornio to the frozen Gulf of Bothnia for an Icebreaker Arktis cruise, sea-ice walk and memorable floating experience among the Arctic ice. | P60: =HYPERLINK("https://www.icebreaking.com/icebreaker-arktis-cruise/","https://www.icebreaking.com/icebreaker-arktis-cruise/") -> https://www.icebreaking.com/icebreaker-arktis-cruise/ | Q60: 351 | R60: 0 | S60: =+Q60*R60 -> 0 | T60: 0 | U60: =S60*(1-T60) -> 0 | V60: EUR | W60: =IFERROR(VLOOKUP(V60,Curr!$B$2:$C$13,2,FALSE),0) -> 11 | X60: =U60*W60 -> 0 | Y60: =Q60/0.8 -> 438.75 | Z60: =+Y60*R60 -> 0 | AA60: EUR | AB60: =IFERROR(VLOOKUP(AA60,Curr!$B$2:$C$13,2,FALSE),0) -> 11 | AC60: =+Y60*AB60*R60 -> 0 | AD60: =+AC60-X60 -> 0 | AE60: =IFERROR(AD60/AC60,0) -> 0
B61: FI | D61: Activity | J61: Rovaniemi: Icebreaker Arktis Morning Cruise Day Tour - Time: Early morning departure; duration approximately 9-11 hours - Meeting point: Selected Rovaniemi pickup point - Includes: Return shuttle transportation, three-hour icebreaker cruise, ice floating, sea-ice walk and diploma - Description: Travel from Rovaniemi to the frozen Gulf of Bothnia for an Icebreaker Arktis cruise, with time to walk on the sea ice and float safely in a survival suit. | P61: =HYPERLINK("https://www.icebreaking.com/icebreaker-arktis-cruise/","https://www.icebreaking.com/icebreaker-arktis-cruise/") -> https://www.icebreaking.com/icebreaker-arktis-cruise/ | Q61: 388 | R61: 0 | S61: =+Q61*R61 -> 0 | T61: 0 | U61: =S61*(1-T61) -> 0 | V61: EUR | W61: =IFERROR(VLOOKUP(V61,Curr!$B$2:$C$13,2,FALSE),0) -> 11 | X61: =U61*W61 -> 0 | Y61: =Q61/0.8 -> 485 | Z61: =+Y61*R61 -> 0 | AA61: EUR | AB61: =IFERROR(VLOOKUP(AA61,Curr!$B$2:$C$13,2,FALSE),0) -> 11 | AC61: =+Y61*AB61*R61 -> 0 | AD61: =+AC61-X61 -> 0 | AE61: =IFERROR(AD61/AC61,0) -> 0
B62: FI | D62: Activity | J62: Rovaniemi: Icebreaker Arktis Afternoon Cruise Day Tour - Time: Morning departure; duration approximately 9-11 hours - Meeting point: Selected Rovaniemi pickup point - Includes: Return shuttle transportation, three-hour icebreaker cruise, ice floating, sea-ice walk and diploma - Description: Travel from Rovaniemi for an afternoon Icebreaker Arktis cruise, with time to walk on the frozen sea and float safely among the ice in a survival suit. | P62: =HYPERLINK("https://www.icebreaking.com/icebreaker-arktis-cruise/","https://www.icebreaking.com/icebreaker-arktis-cruise/") -> https://www.icebreaking.com/icebreaker-arktis-cruise/ | Q62: 388 | R62: 0 | S62: =+Q62*R62 -> 0 | T62: 0 | U62: =S62*(1-T62) -> 0 | V62: EUR | W62: =IFERROR(VLOOKUP(V62,Curr!$B$2:$C$13,2,FALSE),0) -> 11 | X62: =U62*W62 -> 0 | Y62: =Q62/0.8 -> 485 | Z62: =+Y62*R62 -> 0 | AA62: EUR | AB62: =IFERROR(VLOOKUP(AA62,Curr!$B$2:$C$13,2,FALSE),0) -> 11 | AC62: =+Y62*AB62*R62 -> 0 | AD62: =+AC62-X62 -> 0 | AE62: =IFERROR(AD62/AC62,0) -> 0
B63: FI | D63: Activity | J63: Kemi: Icebreaker Sampo Sunrise Cruise - Time: Morning departure; duration approximately 3.5 hours - Meeting point: SnowCastle of Kemi, Lumilinnankatu 15A - Includes: Icebreaker cruise, welcome drink, guided vessel tour, ice floating, sea-ice walk, diploma and SnowCastle area exhibition admission - Description: Cruise across the frozen Gulf of Bothnia aboard legendary Icebreaker Sampo. Explore the vessel, walk on the sea ice and float safely beneath the Arctic morning light. | P63: =HYPERLINK("https://www.icebreaking.com/icebreaker-sampo-cruise/","https://www.icebreaking.com/icebreaker-sampo-cruise/") -> https://www.icebreaking.com/icebreaker-sampo-cruise/ | Q63: 360 | R63: 0 | S63: =+Q63*R63 -> 0 | T63: 0 | U63: =S63*(1-T63) -> 0 | V63: EUR | W63: =IFERROR(VLOOKUP(V63,Curr!$B$2:$C$13,2,FALSE),0) -> 11 | X63: =U63*W63 -> 0 | Y63: =Q63/0.8 -> 450 | Z63: =+Y63*R63 -> 0 | AA63: EUR | AB63: =IFERROR(VLOOKUP(AA63,Curr!$B$2:$C$13,2,FALSE),0) -> 11 | AC63: =+Y63*AB63*R63 -> 0 | AD63: =+AC63-X63 -> 0 | AE63: =IFERROR(AD63/AC63,0) -> 0
B64: FI | D64: Activity | J64: Kemi: Icebreaker Sampo Sunrise Cruise with Transfers - Time: Morning departure; duration approximately 6-7 hours - Meeting point: Selected Kemi or SnowCastle pickup point - Includes: Return shuttle transportation, welcome drink, guided vessel tour, ice floating, sea-ice walk, diploma and SnowCastle area exhibition admission - Description: Travel from Kemi to legendary Icebreaker Sampo for a morning cruise across the frozen Gulf of Bothnia, including a vessel tour, sea-ice walk and ice-floating experience. | P64: =HYPERLINK("https://www.icebreaking.com/icebreaker-sampo-cruise/","https://www.icebreaking.com/icebreaker-sampo-cruise/") -> https://www.icebreaking.com/icebreaker-sampo-cruise/ | Q64: 376 | R64: 0 | S64: =+Q64*R64 -> 0 | T64: 0 | U64: =S64*(1-T64) -> 0 | V64: EUR | W64: =IFERROR(VLOOKUP(V64,Curr!$B$2:$C$13,2,FALSE),0) -> 11 | X64: =U64*W64 -> 0 | Y64: =Q64/0.8 -> 470 | Z64: =+Y64*R64 -> 0 | AA64: EUR | AB64: =IFERROR(VLOOKUP(AA64,Curr!$B$2:$C$13,2,FALSE),0) -> 11 | AC64: =+Y64*AB64*R64 -> 0 | AD64: =+AC64-X64 -> 0 | AE64: =IFERROR(AD64/AC64,0) -> 0
B65: FI | D65: Activity | J65: Haparanda–Tornio: Icebreaker Sampo Sunrise Cruise - Time: Morning departure; duration approximately 7-8 hours - Meeting point: Selected Haparanda or Tornio pickup point - Includes: Return shuttle transportation, welcome drink, guided vessel tour, ice floating, sea-ice walk, diploma and SnowCastle area exhibition admission - Description: Journey from Haparanda or Tornio to legendary Icebreaker Sampo for a morning cruise, guided vessel tour, walk on the frozen sea and memorable ice-floating experience. | P65: =HYPERLINK("https://www.icebreaking.com/icebreaker-sampo-cruise/","https://www.icebreaking.com/icebreaker-sampo-cruise/") -> https://www.icebreaking.com/icebreaker-sampo-cruise/ | Q65: 406 | R65: 0 | S65: =+Q65*R65 -> 0 | T65: 0 | U65: =S65*(1-T65) -> 0 | V65: EUR | W65: =IFERROR(VLOOKUP(V65,Curr!$B$2:$C$13,2,FALSE),0) -> 11 | X65: =U65*W65 -> 0 | Y65: =Q65/0.8 -> 507.5 | Z65: =+Y65*R65 -> 0 | AA65: EUR | AB65: =IFERROR(VLOOKUP(AA65,Curr!$B$2:$C$13,2,FALSE),0) -> 11 | AC65: =+Y65*AB65*R65 -> 0 | AD65: =+AC65-X65 -> 0 | AE65: =IFERROR(AD65/AC65,0) -> 0
B66: FI | D66: Activity | J66: Rovaniemi: Icebreaker Sampo Sunrise Cruise Day Tour - Time: Early morning departure; duration approximately 9-11 hours - Meeting point: Selected Rovaniemi pickup point - Includes: Return shuttle transportation, welcome drink, guided vessel tour, ice floating, sea-ice walk, diploma and SnowCastle area exhibition admission - Description: Travel from Rovaniemi to legendary Icebreaker Sampo for a morning cruise across the frozen Gulf of Bothnia, including a vessel tour, sea-ice walk and ice-floating experience. | P66: =HYPERLINK("https://www.icebreaking.com/icebreaker-sampo-cruise/","https://www.icebreaking.com/icebreaker-sampo-cruise/") -> https://www.icebreaking.com/icebreaker-sampo-cruise/ | Q66: 470 | R66: 0 | S66: =+Q66*R66 -> 0 | T66: 0 | U66: =S66*(1-T66) -> 0 | V66: EUR | W66: =IFERROR(VLOOKUP(V66,Curr!$B$2:$C$13,2,FALSE),0) -> 11 | X66: =U66*W66 -> 0 | Y66: =Q66/0.8 -> 587.5 | Z66: =+Y66*R66 -> 0 | AA66: EUR | AB66: =IFERROR(VLOOKUP(AA66,Curr!$B$2:$C$13,2,FALSE),0) -> 11 | AC66: =+Y66*AB66*R66 -> 0 | AD66: =+AC66-X66 -> 0 | AE66: =IFERROR(AD66/AC66,0) -> 0
B67: FI | D67: Activity | J67: Kemi: Icebreaker Sampo Blue Moment Afternoon Cruise - Time: Afternoon departure; duration approximately 4 hours - Meeting point: SnowCastle of Kemi, Lumilinnankatu 15A - Includes: Icebreaker cruise, welcome drink, guided vessel tour, lunch buffet, ice floating, sea-ice walk, diploma and SnowCastle area exhibition admission - Description: Experience the frozen Gulf of Bothnia aboard legendary Icebreaker Sampo. Tour the vessel, enjoy a buffet lunch, walk on the sea ice and float safely in a survival suit. | P67: =HYPERLINK("https://www.icebreaking.com/icebreaker-sampo-cruise/","https://www.icebreaking.com/icebreaker-sampo-cruise/") -> https://www.icebreaking.com/icebreaker-sampo-cruise/ | Q67: 387 | R67: 0 | S67: =+Q67*R67 -> 0 | T67: 0 | U67: =S67*(1-T67) -> 0 | V67: EUR | W67: =IFERROR(VLOOKUP(V67,Curr!$B$2:$C$13,2,FALSE),0) -> 11 | X67: =U67*W67 -> 0 | Y67: =Q67/0.8 -> 483.75 | Z67: =+Y67*R67 -> 0 | AA67: EUR | AB67: =IFERROR(VLOOKUP(AA67,Curr!$B$2:$C$13,2,FALSE),0) -> 11 | AC67: =+Y67*AB67*R67 -> 0 | AD67: =+AC67-X67 -> 0 | AE67: =IFERROR(AD67/AC67,0) -> 0
B68: FI | D68: Activity | J68: Kemi: Icebreaker Sampo Blue Moment Afternoon Cruise with Transfers - Time: Late morning departure; duration approximately 6-7 hours - Meeting point: Selected Kemi or SnowCastle pickup point - Includes: Return shuttle transportation, welcome drink, guided vessel tour, lunch buffet, ice floating, sea-ice walk, diploma and SnowCastle area exhibition admission - Description: Travel from Kemi for an afternoon cruise aboard Icebreaker Sampo. Enjoy a vessel tour and buffet lunch before walking on the frozen sea and trying ice floating. | P68: =HYPERLINK("https://www.icebreaking.com/icebreaker-sampo-cruise/","https://www.icebreaking.com/icebreaker-sampo-cruise/") -> https://www.icebreaking.com/icebreaker-sampo-cruise/ | Q68: 403 | R68: 0 | S68: =+Q68*R68 -> 0 | T68: 0 | U68: =S68*(1-T68) -> 0 | V68: EUR | W68: =IFERROR(VLOOKUP(V68,Curr!$B$2:$C$13,2,FALSE),0) -> 11 | X68: =U68*W68 -> 0 | Y68: =Q68/0.8 -> 503.75 | Z68: =+Y68*R68 -> 0 | AA68: EUR | AB68: =IFERROR(VLOOKUP(AA68,Curr!$B$2:$C$13,2,FALSE),0) -> 11 | AC68: =+Y68*AB68*R68 -> 0 | AD68: =+AC68-X68 -> 0 | AE68: =IFERROR(AD68/AC68,0) -> 0
B69: FI | D69: Activity | J69: Haparanda–Tornio: Icebreaker Sampo Blue Moment Afternoon Cruise - Time: Morning departure; duration approximately 7-8 hours - Meeting point: Selected Haparanda or Tornio pickup point - Includes: Return shuttle transportation, welcome drink, guided vessel tour, lunch buffet, ice floating, sea-ice walk, diploma and SnowCastle area exhibition admission - Description: Journey from Haparanda or Tornio for an Icebreaker Sampo cruise with a guided vessel tour and buffet lunch, followed by a sea-ice walk and ice-floating experience. | P69: =HYPERLINK("https://www.icebreaking.com/icebreaker-sampo-cruise/","https://www.icebreaking.com/icebreaker-sampo-cruise/") -> https://www.icebreaking.com/icebreaker-sampo-cruise/ | Q69: 433 | R69: 0 | S69: =+Q69*R69 -> 0 | T69: 0 | U69: =S69*(1-T69) -> 0 | V69: EUR | W69: =IFERROR(VLOOKUP(V69,Curr!$B$2:$C$13,2,FALSE),0) -> 11 | X69: =U69*W69 -> 0 | Y69: =Q69/0.8 -> 541.25 | Z69: =+Y69*R69 -> 0 | AA69: EUR | AB69: =IFERROR(VLOOKUP(AA69,Curr!$B$2:$C$13,2,FALSE),0) -> 11 | AC69: =+Y69*AB69*R69 -> 0 | AD69: =+AC69-X69 -> 0 | AE69: =IFERROR(AD69/AC69,0) -> 0
B70: FI | D70: Activity | J70: Rovaniemi: Icebreaker Sampo Blue Moment Afternoon Cruise Day Tour - Time: Morning departure; duration approximately 9-11 hours - Meeting point: Selected Rovaniemi pickup point - Includes: Return shuttle transportation, welcome drink, guided vessel tour, lunch buffet, ice floating, sea-ice walk, diploma and SnowCastle area exhibition admission - Description: Travel from Rovaniemi for an Icebreaker Sampo cruise with a guided vessel tour and buffet lunch, followed by a walk on the frozen sea and ice floating. | P70: =HYPERLINK("https://www.icebreaking.com/icebreaker-sampo-cruise/","https://www.icebreaking.com/icebreaker-sampo-cruise/") -> https://www.icebreaking.com/icebreaker-sampo-cruise/ | Q70: 497 | R70: 0 | S70: =+Q70*R70 -> 0 | T70: 0 | U70: =S70*(1-T70) -> 0 | V70: EUR | W70: =IFERROR(VLOOKUP(V70,Curr!$B$2:$C$13,2,FALSE),0) -> 11 | X70: =U70*W70 -> 0 | Y70: =Q70/0.8 -> 621.25 | Z70: =+Y70*R70 -> 0 | AA70: EUR | AB70: =IFERROR(VLOOKUP(AA70,Curr!$B$2:$C$13,2,FALSE),0) -> 11 | AC70: =+Y70*AB70*R70 -> 0 | AD70: =+AC70-X70 -> 0 | AE70: =IFERROR(AD70/AC70,0) -> 0
B71: FI | D71: Activity | J71: Levi: Northern Lights Tour by Minivan & Campfire - Time: By arrangement; duration approximately 2.5 hours - Meeting point: Arctic Circle Snowmobile Park Levi, Levintie 1585, Kittilä - Includes: Central Levi pickup and drop-off, professional English-speaking guide, winter overalls, boots, gloves and warm juice - Description: Leave Levi’s village lights behind and travel by minivan to promising viewing locations in the surrounding wilderness. Enjoy the quiet Arctic night while searching for the Northern Lights with an experienced local guide. | P71: =HYPERLINK("https://booknordics.com/finland/western-lapland/levi-and-kittilae/northern-lights-by-minivan-and-campfire-levi","https://booknordics.com/finland/western-lapland/levi-and-kittilae/northern-lights-by-minivan-and-campfire-levi") -> https://booknordics.com/finland/western-lapland/levi-and-kittilae/northern-lights-by-minivan-and-campfire-levi | Q71: 99 | R71: 0 | S71: =+Q71*R71 -> 0 | T71: 0.2 | U71: =S71*(1-T71) -> 0 | V71: EUR | W71: =IFERROR(VLOOKUP(V71,Curr!$B$2:$C$13,2,FALSE),0) -> 11 | X71: =U71*W71 -> 0 | Y71: =Q71 -> 99 | Z71: =+Y71*R71 -> 0 | AA71: EUR | AB71: =IFERROR(VLOOKUP(AA71,Curr!$B$2:$C$13,2,FALSE),0) -> 11 | AC71: =+Y71*AB71*R71 -> 0 | AD71: =+AC71-X71 -> 0 | AE71: =IFERROR(AD71/AC71,0) -> 0
B72: FI | D72: Activity | J72: Levi: Snowmobiling Adventure - Time: By arrangement; duration approximately 1 hour - Meeting point: Arctic Circle Snowmobile Park Levi, Levintie 1585, Kittilä - Includes: Central Levi pickup and drop-off, professional English-speaking guide, shared snowmobile for two adults, winter overalls, boots, gloves, helmet and balaclava - Description: Learn the basics of snowmobile driving before following snowy trails through Levi’s Arctic forests. Share the snowmobile with another adult and pause during the journey to switch drivers and enjoy the scenery. | P72: =HYPERLINK("https://booknordics.com/finland/western-lapland/levi-and-kittilae/snowmobiling-adventure-levi","https://booknordics.com/finland/western-lapland/levi-and-kittilae/snowmobiling-adventure-levi") -> https://booknordics.com/finland/western-lapland/levi-and-kittilae/snowmobiling-adventure-levi | Q72: 109 | R72: 0 | S72: =+Q72*R72 -> 0 | T72: 0.2 | U72: =S72*(1-T72) -> 0 | V72: EUR | W72: =IFERROR(VLOOKUP(V72,Curr!$B$2:$C$13,2,FALSE),0) -> 11 | X72: =U72*W72 -> 0 | Y72: =Q72 -> 109 | Z72: =+Y72*R72 -> 0 | AA72: EUR | AB72: =IFERROR(VLOOKUP(AA72,Curr!$B$2:$C$13,2,FALSE),0) -> 11 | AC72: =+Y72*AB72*R72 -> 0 | AD72: =+AC72-X72 -> 0 | AE72: =IFERROR(AD72/AC72,0) -> 0
B73: FI | D73: Activity | J73: Levi: Arctic Ice Floating - Time: 1:00 pm - 5:00 pm - Meeting point: Safartica Office, Hiihtäjänkuja 10, Sirkka - Includes: Central Levi pickup and drop-off, professional English-speaking guide, flotation suit, winter clothing and hot drinks - Description: Step into an opening in a frozen wilderness lake wearing a warm, waterproof flotation suit. Relax as the calm Arctic water carries you beneath snow-covered trees, with no swimming experience required. | P73: =HYPERLINK("https://booknordics.com/finland/western-lapland/levi-and-kittilae/arctic-ice-floating-arktinen-jaakellunta","https://booknordics.com/finland/western-lapland/levi-and-kittilae/arctic-ice-floating-arktinen-jaakellunta") -> https://booknordics.com/finland/western-lapland/levi-and-kittilae/arctic-ice-floating-arktinen-jaakellunta | Q73: 132 | R73: 0 | S73: =+Q73*R73 -> 0 | T73: 0.2 | U73: =S73*(1-T73) -> 0 | V73: EUR | W73: =IFERROR(VLOOKUP(V73,Curr!$B$2:$C$13,2,FALSE),0) -> 11 | X73: =U73*W73 -> 0 | Y73: =Q73 -> 132 | Z73: =+Y73*R73 -> 0 | AA73: EUR | AB73: =IFERROR(VLOOKUP(AA73,Curr!$B$2:$C$13,2,FALSE),0) -> 11 | AC73: =+Y73*AB73*R73 -> 0 | AD73: =+AC73-X73 -> 0 | AE73: =IFERROR(AD73/AC73,0) -> 0
B74: FI | D74: Activity | J74: Levi: Ice Floating beneath the Northern Lights - Time: 7:30 pm - 11:30 pm - Meeting point: Safartica Office, Hiihtäjänkuja 10, Sirkka - Includes: Central Levi pickup and drop-off, English-speaking guide, flotation suit, winter clothing and hot drinks - Description: Float peacefully in a frozen wilderness lake while remaining warm and dry inside a protective rescue suit. Gaze at the stars and search for the Northern Lights reflected across the dark Arctic water. | P74: =HYPERLINK("https://booknordics.com/finland/western-lapland/levi-and-kittilae/northern-lights-ice-floating-revontulten-jaakellunta","https://booknordics.com/finland/western-lapland/levi-and-kittilae/northern-lights-ice-floating-revontulten-jaakellunta") -> https://booknordics.com/finland/western-lapland/levi-and-kittilae/northern-lights-ice-floating-revontulten-jaakellunta | Q74: 138 | R74: 0 | S74: =+Q74*R74 -> 0 | T74: 0.2 | U74: =S74*(1-T74) -> 0 | V74: EUR | W74: =IFERROR(VLOOKUP(V74,Curr!$B$2:$C$13,2,FALSE),0) -> 11 | X74: =U74*W74 -> 0 | Y74: =Q74 -> 138 | Z74: =+Y74*R74 -> 0 | AA74: EUR | AB74: =IFERROR(VLOOKUP(AA74,Curr!$B$2:$C$13,2,FALSE),0) -> 11 | AC74: =+Y74*AB74*R74 -> 0 | AD74: =+AC74-X74 -> 0 | AE74: =IFERROR(AD74/AC74,0) -> 0
B75: FI | D75: Activity | J75: Levi: SnowVillage Experience with Lunch - Time: By arrangement; duration approximately 4 hours - Meeting point: Arctic Circle Snowmobile Park Levi, Levintie 1585, Kittilä - Includes: Central Levi pickup and drop-off, professional English-speaking guide, SnowVillage admission, winter overalls, boots, gloves and warm soup lunch - Description: Explore an extraordinary village sculpted from millions of kilograms of snow and natural ice. Wander through decorated rooms, icy corridors and imaginative sculptures before enjoying a warming soup lunch. | P75: =HYPERLINK("https://booknordics.com/finland/western-lapland/levi-and-kittilae/snow-castle-experience-in-levi","https://booknordics.com/finland/western-lapland/levi-and-kittilae/snow-castle-experience-in-levi") -> https://booknordics.com/finland/western-lapland/levi-and-kittilae/snow-castle-experience-in-levi | Q75: 159 | R75: 0 | S75: =+Q75*R75 -> 0 | T75: 0.2 | U75: =S75*(1-T75) -> 0 | V75: EUR | W75: =IFERROR(VLOOKUP(V75,Curr!$B$2:$C$13,2,FALSE),0) -> 11 | X75: =U75*W75 -> 0 | Y75: =Q75 -> 159 | Z75: =+Y75*R75 -> 0 | AA75: EUR | AB75: =IFERROR(VLOOKUP(AA75,Curr!$B$2:$C$13,2,FALSE),0) -> 11 | AC75: =+Y75*AB75*R75 -> 0 | AD75: =+AC75-X75 -> 0 | AE75: =IFERROR(AD75/AC75,0) -> 0
B76: FI | D76: Activity | J76: Levi: Dinner at SnowVillage - Time: 6:00 pm - 10:00 pm - Meeting point: Lapland Safaris Levi, Leviraitti 26, Kittilä - Includes: Central Levi pickup and drop-off, professional English-speaking guide, thermal outfit, SnowVillage admission, ice-bar drink and three-course dinner in the ice restaurant - Description: Discover SnowVillage’s decorated rooms, frozen sculptures and atmospheric ice bar before sitting at tables carved from ice for a memorable three-course dinner inside the enchanting ice restaurant. | P76: =HYPERLINK("https://booknordics.com/finland/western-lapland/levi-and-kittilae/dinner-at-snowvillage-levi","https://booknordics.com/finland/western-lapland/levi-and-kittilae/dinner-at-snowvillage-levi") -> https://booknordics.com/finland/western-lapland/levi-and-kittilae/dinner-at-snowvillage-levi | Q76: 183 | R76: 0 | S76: =+Q76*R76 -> 0 | T76: 0.2 | U76: =S76*(1-T76) -> 0 | V76: EUR | W76: =IFERROR(VLOOKUP(V76,Curr!$B$2:$C$13,2,FALSE),0) -> 11 | X76: =U76*W76 -> 0 | Y76: =Q76 -> 183 | Z76: =+Y76*R76 -> 0 | AA76: EUR | AB76: =IFERROR(VLOOKUP(AA76,Curr!$B$2:$C$13,2,FALSE),0) -> 11 | AC76: =+Y76*AB76*R76 -> 0 | AD76: =+AC76-X76 -> 0 | AE76: =IFERROR(AD76/AC76,0) -> 0
B77: FI | D77: Activity | J77: Levi: Family Day with Huskies, Reindeer & Sledding - Time: 10:00 am - 2:00 pm - Meeting point: Arctic Circle Snowmobile Park Levi, Levintie 1585, Kittilä - Includes: Central Levi pickup and drop-off, professional English-speaking guide, winter clothing, husky and reindeer farm visits, 500-metre sleigh rides, children’s mini-snowmobiling, soup lunch and hot juice - Description: Meet friendly huskies and reindeer before enjoying short sleigh rides through the snowy surroundings. Children can try mini-snowmobiling, while the whole family shares a warming traditional soup lunch. | P77: =HYPERLINK("https://booknordics.com/finland/western-lapland/levi-and-kittilae/family-day-winter-highlights-by-minivan-levi","https://booknordics.com/finland/western-lapland/levi-and-kittilae/family-day-winter-highlights-by-minivan-levi") -> https://booknordics.com/finland/western-lapland/levi-and-kittilae/family-day-winter-highlights-by-minivan-levi | Q77: 199 | R77: 0 | S77: =+Q77*R77 -> 0 | T77: 0.2 | U77: =S77*(1-T77) -> 0 | V77: EUR | W77: =IFERROR(VLOOKUP(V77,Curr!$B$2:$C$13,2,FALSE),0) -> 11 | X77: =U77*W77 -> 0 | Y77: =Q77 -> 199 | Z77: =+Y77*R77 -> 0 | AA77: EUR | AB77: =IFERROR(VLOOKUP(AA77,Curr!$B$2:$C$13,2,FALSE),0) -> 11 | AC77: =+Y77*AB77*R77 -> 0 | AD77: =+AC77-X77 -> 0 | AE77: =IFERROR(AD77/AC77,0) -> 0
B78: FI | D78: Activity | J78: Levi: Private Shamanic Evening with Lappish Dinner - Time: 6:00 pm - 11:30 pm - Meeting point: Visit Levi, Myllyjoentie 2, Sirkka - Includes: Return transportation, private shaman host, Arctic Shaman Village admission, symbolic water-blessing ritual, fireside stargazing, three-course Lappish dinner and wine or water - Description: Spend an intimate evening with a personal shaman host, experiencing a symbolic blessing, traditional drum ceremony and fireside stories before enjoying a handcrafted dinner featuring seasonal ingredients from Lapland. | P78: =HYPERLINK("https://booknordics.com/finland/western-lapland/levi-and-kittilae/shamanic-evening-vip","https://booknordics.com/finland/western-lapland/levi-and-kittilae/shamanic-evening-vip") -> https://booknordics.com/finland/western-lapland/levi-and-kittilae/shamanic-evening-vip | Q78: 225 | R78: 0 | S78: =+Q78*R78 -> 0 | T78: 0.2 | U78: =S78*(1-T78) -> 0 | V78: EUR | W78: =IFERROR(VLOOKUP(V78,Curr!$B$2:$C$13,2,FALSE),0) -> 11 | X78: =U78*W78 -> 0 | Y78: =Q78 -> 225 | Z78: =+Y78*R78 -> 0 | AA78: EUR | AB78: =IFERROR(VLOOKUP(AA78,Curr!$B$2:$C$13,2,FALSE),0) -> 11 | AC78: =+Y78*AB78*R78 -> 0 | AD78: =+AC78-X78 -> 0 | AE78: =IFERROR(AD78/AC78,0) -> 0
B79: FI | D79: Activity | J79: Levi: Private Traditional Sauna & Wilderness Dinner - Time: By arrangement; duration approximately 5 hours - Meeting point: Selected Levi hotel pickup point - Includes: Private Levi pickup and drop-off, professional English-speaking guide, traditional sauna, towel, foot bath, sauna whisk, seasonal ice dip or snow roll, three-course dinner and soft drinks - Description: Travel to a secluded wilderness cabin for a traditional wood-fired Finnish sauna, with the option to cool down in snow or an ice hole before enjoying a three-course Lappish dinner. | P79: =HYPERLINK("https://booknordics.com/finland/western-lapland/levi-and-kittilae/private-sauna-experience-dinner-and-northern-lights-in-the-wilderness","https://booknordics.com/finland/western-lapland/levi-and-kittilae/private-sauna-experience-dinner-and-northern-lights-in-the-wilderness") -> https://booknordics.com/finland/western-lapland/levi-and-kittilae/private-sauna-experience-dinner-and-northern-lights-in-the-wilderness | Q79: 359 | R79: 0 | S79: =+Q79*R79 -> 0 | T79: 0.2 | U79: =S79*(1-T79) -> 0 | V79: EUR | W79: =IFERROR(VLOOKUP(V79,Curr!$B$2:$C$13,2,FALSE),0) -> 11 | X79: =U79*W79 -> 0 | Y79: =Q79 -> 359 | Z79: =+Y79*R79 -> 0 | AA79: EUR | AB79: =IFERROR(VLOOKUP(AA79,Curr!$B$2:$C$13,2,FALSE),0) -> 11 | AC79: =+Y79*AB79*R79 -> 0 | AD79: =+AC79-X79 -> 0 | AE79: =IFERROR(AD79/AC79,0) -> 0
B80: FI | D80: Activity | J80: Saariselkä: Northern Lights Hunting Photo Tour by Bus - Time: 7:30 pm - 10:30 pm - Meeting point: Safartica Office, Lutontie 16 - Includes: Central Saariselkä pickup and drop-off, knowledgeable English-speaking guide, aurora hunt of up to 150 kilometres, professional photos, gingerbread cookies and hot drinks - Description: Travel beyond Saariselkä in search of clearer skies and promising aurora conditions. Enjoy warm refreshments while your guide captures professional photographs beneath the Arctic night sky. | P80: =HYPERLINK("https://booknordics.com/finland/northern-lapland/saariselkae/aurora-photo-tour-by-car","https://booknordics.com/finland/northern-lapland/saariselkae/aurora-photo-tour-by-car") -> https://booknordics.com/finland/northern-lapland/saariselkae/aurora-photo-tour-by-car | Q80: 119 | R80: 0 | S80: =+Q80*R80 -> 0 | T80: 0.2 | U80: =S80*(1-T80) -> 0 | V80: EUR | W80: =IFERROR(VLOOKUP(V80,Curr!$B$2:$C$13,2,FALSE),0) -> 11 | X80: =U80*W80 -> 0 | Y80: =Q80 -> 119 | Z80: =+Y80*R80 -> 0 | AA80: EUR | AB80: =IFERROR(VLOOKUP(AA80,Curr!$B$2:$C$13,2,FALSE),0) -> 11 | AC80: =+Y80*AB80*R80 -> 0 | AD80: =+AC80-X80 -> 0 | AE80: =IFERROR(AD80/AC80,0) -> 0
B81: FI | D81: Activity | J81: Saariselkä: Two-Hour Snowmobile Safari through the Arctic Landscape - Time: 10:00 am - 12:00 pm - Meeting point: Safartica Office, Lutontie 16 - Includes: Central Saariselkä pickup and drop-off, professional English-speaking guide, driving instruction, shared snowmobile for two adults, winter clothing, approximately 1.5 hours of driving and hot drinks with biscuits - Description: Learn to handle a snowmobile before riding across snowy hills and fells around Saariselkä. Pause in the Arctic wilderness for hot drinks while taking in the quiet winter landscape. | P81: =HYPERLINK("https://booknordics.com/finland/northern-lapland/saariselkae/scenic-snowmobile-safari-2h-snowmobile-experience","https://booknordics.com/finland/northern-lapland/saariselkae/scenic-snowmobile-safari-2h-snowmobile-experience") -> https://booknordics.com/finland/northern-lapland/saariselkae/scenic-snowmobile-safari-2h-snowmobile-experience | Q81: 129 | R81: 0 | S81: =+Q81*R81 -> 0 | T81: 0.2 | U81: =S81*(1-T81) -> 0 | V81: EUR | W81: =IFERROR(VLOOKUP(V81,Curr!$B$2:$C$13,2,FALSE),0) -> 11 | X81: =U81*W81 -> 0 | Y81: =Q81 -> 129 | Z81: =+Y81*R81 -> 0 | AA81: EUR | AB81: =IFERROR(VLOOKUP(AA81,Curr!$B$2:$C$13,2,FALSE),0) -> 11 | AC81: =+Y81*AB81*R81 -> 0 | AD81: =+AC81-X81 -> 0 | AE81: =IFERROR(AD81/AC81,0) -> 0
B82: FI | D82: Activity | J82: Saariselkä: Traditional Reindeer Safari through the Snowy Forest - Time: 10:50 am - 1:20 pm - Meeting point: Safartica Office, Lutontie 16 - Includes: Central Saariselkä pickup and drop-off, knowledgeable English-speaking guide, traditional reindeer farm visit, 45-minute reindeer sleigh ride, warm winter clothing and hot drinks - Description: Visit a traditional reindeer farm and glide through snow-covered forest on a peaceful sleigh ride. Afterwards, hear stories of reindeer herding while enjoying a warming drink. | P82: =HYPERLINK("https://booknordics.com/finland/northern-lapland/saariselkae/traditional-reindeer-safari","https://booknordics.com/finland/northern-lapland/saariselkae/traditional-reindeer-safari") -> https://booknordics.com/finland/northern-lapland/saariselkae/traditional-reindeer-safari | Q82: 166 | R82: 0 | S82: =+Q82*R82 -> 0 | T82: 0.2 | U82: =S82*(1-T82) -> 0 | V82: EUR | W82: =IFERROR(VLOOKUP(V82,Curr!$B$2:$C$13,2,FALSE),0) -> 11 | X82: =U82*W82 -> 0 | Y82: =Q82 -> 166 | Z82: =+Y82*R82 -> 0 | AA82: EUR | AB82: =IFERROR(VLOOKUP(AA82,Curr!$B$2:$C$13,2,FALSE),0) -> 11 | AC82: =+Y82*AB82*R82 -> 0 | AD82: =+AC82-X82 -> 0 | AE82: =IFERROR(AD82/AC82,0) -> 0
B83: IS | D83: Activity | J83: Reykjavík: Grand Golden Circle Full-Day Tour - Time: 8:00 am - 5:00 pm - Meeting point: Bus Stop 12 Höfðatorg, Þórunnartún 6 - Includes: Round-trip coach or minivan transportation, knowledgeable English-speaking guide, Kerið admission, Golden Circle sightseeing and Wi-Fi - Description: Travel Iceland’s classic Golden Circle, visiting Þingvellir National Park, erupting Strokkur, powerful Gullfoss and colourful Kerið crater while experiencing dramatic geology, geothermal activity and historic landscapes. | P83: =HYPERLINK("https://booknordics.com/iceland/western-iceland/reykjavik/grand-golden-circle-tour","https://booknordics.com/iceland/western-iceland/reykjavik/grand-golden-circle-tour") -> https://booknordics.com/iceland/western-iceland/reykjavik/grand-golden-circle-tour | Q83: 84 | R83: 0 | S83: =+Q83*R83 -> 0 | T83: 0.25 | U83: =S83*(1-T83) -> 0 | V83: EUR | W83: =IFERROR(VLOOKUP(V83,Curr!$B$2:$C$13,2,FALSE),0) -> 11 | X83: =U83*W83 -> 0 | Y83: =Q83 -> 84 | Z83: =+Y83*R83 -> 0 | AA83: EUR | AB83: =IFERROR(VLOOKUP(AA83,Curr!$B$2:$C$13,2,FALSE),0) -> 11 | AC83: =+Y83*AB83*R83 -> 0 | AD83: =+AC83-X83 -> 0 | AE83: =IFERROR(AD83/AC83,0) -> 0
B84: IS | D84: Activity | J84: Reykjavík: Golden Circle, Kerið Crater & Friðheimar Farm - Time: 8:30 am - 5:30 pm - Meeting point: Selected central Reykjavík pickup point - Includes: Central Reykjavík pickup and drop-off, knowledgeable English-speaking guide and minivan or minibus transportation with Wi-Fi - Description: Explore the Golden Circle’s waterfalls, geysers and volcanic landscapes, with stops at Efstidalur dairy farm and Friðheimar’s tomato greenhouse before visiting Þingvellir, Gullfoss, Strokkur and Kerið crater. | P84: =HYPERLINK("https://booknordics.com/iceland/western-iceland/reykjavik/golden-circle-and-waterfalls-with-fridheimar-farm-and-kerid-in-small-group","https://booknordics.com/iceland/western-iceland/reykjavik/golden-circle-and-waterfalls-with-fridheimar-farm-and-kerid-in-small-group") -> https://booknordics.com/iceland/western-iceland/reykjavik/golden-circle-and-waterfalls-with-fridheimar-farm-and-kerid-in-small-group | Q84: 133 | R84: 0 | S84: =+Q84*R84 -> 0 | T84: 0.25 | U84: =S84*(1-T84) -> 0 | V84: EUR | W84: =IFERROR(VLOOKUP(V84,Curr!$B$2:$C$13,2,FALSE),0) -> 11 | X84: =U84*W84 -> 0 | Y84: =Q84 -> 133 | Z84: =+Y84*R84 -> 0 | AA84: EUR | AB84: =IFERROR(VLOOKUP(AA84,Curr!$B$2:$C$13,2,FALSE),0) -> 11 | AC84: =+Y84*AB84*R84 -> 0 | AD84: =+AC84-X84 -> 0 | AE84: =IFERROR(AD84/AC84,0) -> 0
B85: IS | D85: Activity | J85: Reykjavík: Golden Circle & Blue Lagoon Combo Tour - Time: 8:00 am - 6:15 pm - Meeting point: BSÍ Bus Terminal, Vatnsmýrarvegur 10 - Includes: Guided Golden Circle tour, Blue Lagoon return transfers with Wi-Fi, Comfort admission, silica mud mask, towel, drink and national park fee - Description: Experience Þingvellir, erupting Strokkur and Gullfoss before unwinding in the Blue Lagoon’s mineral-rich geothermal waters, combining Iceland’s celebrated natural landmarks with its signature spa experience. | P85: =HYPERLINK("https://booknordics.com/iceland/western-iceland/reykjavik/golden-circle-blue-lagoon","https://booknordics.com/iceland/western-iceland/reykjavik/golden-circle-blue-lagoon") -> https://booknordics.com/iceland/western-iceland/reykjavik/golden-circle-blue-lagoon | Q85: 244 | R85: 0 | S85: =+Q85*R85 -> 0 | T85: 0.1 | U85: =S85*(1-T85) -> 0 | V85: EUR | W85: =IFERROR(VLOOKUP(V85,Curr!$B$2:$C$13,2,FALSE),0) -> 11 | X85: =U85*W85 -> 0 | Y85: =Q85 -> 244 | Z85: =+Y85*R85 -> 0 | AA85: EUR | AB85: =IFERROR(VLOOKUP(AA85,Curr!$B$2:$C$13,2,FALSE),0) -> 11 | AC85: =+Y85*AB85*R85 -> 0 | AD85: =+AC85-X85 -> 0 | AE85: =IFERROR(AD85/AC85,0) -> 0
B86: IS | D86: Activity | J86: Reykjavík: South Coast, Glacier & Black Sand Beach Tour - Time: 8:00 am - 6:00 pm - Meeting point: Selected central Reykjavík pickup point - Includes: Central Reykjavík pickup and drop-off, knowledgeable English-speaking guide, transportation, Wi-Fi and visits to South Coast highlights - Description: Journey to Seljalandsfoss and Skógafoss waterfalls, Sólheimajökull glacier and Reynisfjara’s black sands. Visit coastal Vík while discovering landscapes shaped by volcanoes, glaciers and the Atlantic Ocean. | P86: =HYPERLINK("https://booknordics.com/iceland/western-iceland/reykjavik/south-coast-waterfalls-glacier-black-sand-beach-tour","https://booknordics.com/iceland/western-iceland/reykjavik/south-coast-waterfalls-glacier-black-sand-beach-tour") -> https://booknordics.com/iceland/western-iceland/reykjavik/south-coast-waterfalls-glacier-black-sand-beach-tour | Q86: 112 | R86: 0 | S86: =+Q86*R86 -> 0 | T86: 0.25 | U86: =S86*(1-T86) -> 0 | V86: EUR | W86: =IFERROR(VLOOKUP(V86,Curr!$B$2:$C$13,2,FALSE),0) -> 11 | X86: =U86*W86 -> 0 | Y86: =Q86 -> 112 | Z86: =+Y86*R86 -> 0 | AA86: EUR | AB86: =IFERROR(VLOOKUP(AA86,Curr!$B$2:$C$13,2,FALSE),0) -> 11 | AC86: =+Y86*AB86*R86 -> 0 | AD86: =+AC86-X86 -> 0 | AE86: =IFERROR(AD86/AC86,0) -> 0
B87: IS | D87: Activity | J87: Reykjavík: South Coast & Viking Sagas Small-Group Tour - Time: 8:30 am - 6:30 pm - Meeting point: Selected central Reykjavík pickup point - Includes: Central Reykjavík pickup and drop-off, knowledgeable English-speaking guide and small-group minibus transportation with Wi-Fi - Description: Explore the South Coast’s waterfalls, glacier and black-sand shoreline. Visit Seljalandsfoss, Skógafoss, Sólheimajökull and Reynisfjara while hearing stories of Iceland’s Viking heritage and dramatic geology. | P87: =HYPERLINK("https://booknordics.com/iceland/western-iceland/reykjavik/south-coast-day-tour-in-a-small-group","https://booknordics.com/iceland/western-iceland/reykjavik/south-coast-day-tour-in-a-small-group") -> https://booknordics.com/iceland/western-iceland/reykjavik/south-coast-day-tour-in-a-small-group | Q87: 147 | R87: 0 | S87: =+Q87*R87 -> 0 | T87: 0.25 | U87: =S87*(1-T87) -> 0 | V87: EUR | W87: =IFERROR(VLOOKUP(V87,Curr!$B$2:$C$13,2,FALSE),0) -> 11 | X87: =U87*W87 -> 0 | Y87: =Q87 -> 147 | Z87: =+Y87*R87 -> 0 | AA87: EUR | AB87: =IFERROR(VLOOKUP(AA87,Curr!$B$2:$C$13,2,FALSE),0) -> 11 | AC87: =+Y87*AB87*R87 -> 0 | AD87: =+AC87-X87 -> 0 | AE87: =IFERROR(AD87/AC87,0) -> 0
B88: IS | D88: Activity | J88: Reykjavík: Katla Ice Cave, South Coast & Black Beach Tour - Time: 9:00 am - 7:00 pm - Meeting point: Selected central Reykjavík pickup point - Includes: Central Reykjavík pickup and drop-off, knowledgeable English-speaking guide, minivan transportation, Wi-Fi, ice-cave visit, helmet and crampons - Description: Discover South Coast waterfalls and black-sand shores before venturing beneath Katla glacier. Explore a naturally changing ice cave and see striking layers of volcanic ash and ancient glacial ice. | P88: =HYPERLINK("https://booknordics.com/iceland/western-iceland/reykjavik/south-coast-katla-ice-cave-from-reykjavik","https://booknordics.com/iceland/western-iceland/reykjavik/south-coast-katla-ice-cave-from-reykjavik") -> https://booknordics.com/iceland/western-iceland/reykjavik/south-coast-katla-ice-cave-from-reykjavik | Q88: 248 | R88: 0 | S88: =+Q88*R88 -> 0 | T88: 0.25 | U88: =S88*(1-T88) -> 0 | V88: EUR | W88: =IFERROR(VLOOKUP(V88,Curr!$B$2:$C$13,2,FALSE),0) -> 11 | X88: =U88*W88 -> 0 | Y88: =Q88 -> 248 | Z88: =+Y88*R88 -> 0 | AA88: EUR | AB88: =IFERROR(VLOOKUP(AA88,Curr!$B$2:$C$13,2,FALSE),0) -> 11 | AC88: =+Y88*AB88*R88 -> 0 | AD88: =+AC88-X88 -> 0 | AE88: =IFERROR(AD88/AC88,0) -> 0
B89: IS | D89: Activity | J89: Reykjavík: Small-Group Snæfellsnes Peninsula Tour - Time: 8:00 am - 8:00 pm - Meeting point: Selected central Reykjavík pickup point - Includes: Central Reykjavík pickup and drop-off, professional English-speaking guide, small-group minibus transportation and Wi-Fi - Description: Discover Snæfellsnes, from Kirkjufell and Búðakirkja to Arnarstapi’s cliffs and Djúpalónssandur. Travel through volcanic scenery, fishing villages and coastal landscapes while watching for seals at Ytri-Tunga. | P89: =HYPERLINK("https://booknordics.com/iceland/western-iceland/reykjavik/snaefellsnes-peninsula-minibus-tour","https://booknordics.com/iceland/western-iceland/reykjavik/snaefellsnes-peninsula-minibus-tour") -> https://booknordics.com/iceland/western-iceland/reykjavik/snaefellsnes-peninsula-minibus-tour | Q89: 123 | R89: 0 | S89: =+Q89*R89 -> 0 | T89: 0.25 | U89: =S89*(1-T89) -> 0 | V89: EUR | W89: =IFERROR(VLOOKUP(V89,Curr!$B$2:$C$13,2,FALSE),0) -> 11 | X89: =U89*W89 -> 0 | Y89: =Q89 -> 123 | Z89: =+Y89*R89 -> 0 | AA89: EUR | AB89: =IFERROR(VLOOKUP(AA89,Curr!$B$2:$C$13,2,FALSE),0) -> 11 | AC89: =+Y89*AB89*R89 -> 0 | AD89: =+AC89-X89 -> 0 | AE89: =IFERROR(AD89/AC89,0) -> 0
B90: IS | D90: Activity | J90: Reykjavík: Blue Lagoon Comfort Admission & Return Transfer - Time: 9:00 am - 1:15 pm - Meeting point: BSÍ Bus Terminal, Vatnsmýrarvegur 10 - Includes: Return bus transportation, Blue Lagoon Comfort admission, silica mud mask, towel and drink - Description: Relax in the Blue Lagoon’s warm, mineral-rich waters amid a dramatic lava field. Enjoy the Comfort experience with a silica mud mask and drink before returning comfortably to Reykjavík. | P90: =HYPERLINK("https://booknordics.com/iceland/western-iceland/reykjavik/reykjavik-blue-lagoon-comfort-including-admission","https://booknordics.com/iceland/western-iceland/reykjavik/reykjavik-blue-lagoon-comfort-including-admission") -> https://booknordics.com/iceland/western-iceland/reykjavik/reykjavik-blue-lagoon-comfort-including-admission | Q90: 168 | R90: 0 | S90: =+Q90*R90 -> 0 | T90: 0.1 | U90: =S90*(1-T90) -> 0 | V90: EUR | W90: =IFERROR(VLOOKUP(V90,Curr!$B$2:$C$13,2,FALSE),0) -> 11 | X90: =U90*W90 -> 0 | Y90: =Q90 -> 168 | Z90: =+Y90*R90 -> 0 | AA90: EUR | AB90: =IFERROR(VLOOKUP(AA90,Curr!$B$2:$C$13,2,FALSE),0) -> 11 | AC90: =+Y90*AB90*R90 -> 0 | AD90: =+AC90-X90 -> 0 | AE90: =IFERROR(AD90/AC90,0) -> 0
B91: IS | D91: Activity | J91: Reykjavík: Blue Lagoon Premium Admission & Return Transfer - Time: 9:00 am - 1:15 pm - Meeting point: BSÍ Bus Terminal, Vatnsmýrarvegur 10 - Includes: Central Reykjavík pickup, return transportation, Premium admission, silica mud mask, towel, toiletries, drink, private locker and Wi-Fi - Description: Unwind in the Blue Lagoon’s milky geothermal waters surrounded by moss-covered lava. Enjoy an enhanced spa visit with skincare, towel, toiletries, a drink and convenient return transportation from Reykjavík. | P91: =HYPERLINK("https://booknordics.com/iceland/western-iceland/reykjavik/reykjavik-blue-lagoon-premium-including-admission","https://booknordics.com/iceland/western-iceland/reykjavik/reykjavik-blue-lagoon-premium-including-admission") -> https://booknordics.com/iceland/western-iceland/reykjavik/reykjavik-blue-lagoon-premium-including-admission | Q91: 189 | R91: 0 | S91: =+Q91*R91 -> 0 | T91: 0.1 | U91: =S91*(1-T91) -> 0 | V91: EUR | W91: =IFERROR(VLOOKUP(V91,Curr!$B$2:$C$13,2,FALSE),0) -> 11 | X91: =U91*W91 -> 0 | Y91: =Q91 -> 189 | Z91: =+Y91*R91 -> 0 | AA91: EUR | AB91: =IFERROR(VLOOKUP(AA91,Curr!$B$2:$C$13,2,FALSE),0) -> 11 | AC91: =+Y91*AB91*R91 -> 0 | AD91: =+AC91-X91 -> 0 | AE91: =IFERROR(AD91/AC91,0) -> 0
B92: IS | D92: Activity | J92: Reykjavík: Sky Lagoon Saman Pass with Return Transfer - Time: 11:00 am - 1:30 pm - Meeting point: BSÍ Bus Terminal, Vatnsmýrarvegur 10 - Includes: Return bus transportation with Wi-Fi, Sky Lagoon admission, complete seven-step ritual, shared changing facilities and towel - Description: Immerse yourself in Sky Lagoon’s oceanfront geothermal waters and follow the seven-step Icelandic bathing ritual while enjoying sweeping North Atlantic views and convenient return transportation from Reykjavík. | P92: =HYPERLINK("https://booknordics.com/iceland/western-iceland/reykjavik/sky-lagoon-pure-pass-with-transfer","https://booknordics.com/iceland/western-iceland/reykjavik/sky-lagoon-pure-pass-with-transfer") -> https://booknordics.com/iceland/western-iceland/reykjavik/sky-lagoon-pure-pass-with-transfer | Q92: 134 | R92: 0 | S92: =+Q92*R92 -> 0 | T92: 0.1 | U92: =S92*(1-T92) -> 0 | V92: EUR | W92: =IFERROR(VLOOKUP(V92,Curr!$B$2:$C$13,2,FALSE),0) -> 11 | X92: =U92*W92 -> 0 | Y92: =Q92 -> 134 | Z92: =+Y92*R92 -> 0 | AA92: EUR | AB92: =IFERROR(VLOOKUP(AA92,Curr!$B$2:$C$13,2,FALSE),0) -> 11 | AC92: =+Y92*AB92*R92 -> 0 | AD92: =+AC92-X92 -> 0 | AE92: =IFERROR(AD92/AC92,0) -> 0
B93: IS | D93: Activity | J93: Reykjavík: Whale Watching in Faxaflói Bay - Time: 9:00 am - 12:30 pm - Meeting point: Special Tours, Geirsgata 11 - Includes: Experienced professional guides, warm flotation overalls, Wi-Fi, heated indoor cabins, toilets and seasickness tablets - Description: Sail into Faxaflói Bay while watching for minke and humpback whales, dolphins and harbour porpoises. Enjoy Reykjavík’s mountain and island views from heated cabins or open viewing decks. | P93: =HYPERLINK("https://booknordics.com/iceland/western-iceland/reykjavik/whale-watching-tour-from-reykjavik","https://booknordics.com/iceland/western-iceland/reykjavik/whale-watching-tour-from-reykjavik") -> https://booknordics.com/iceland/western-iceland/reykjavik/whale-watching-tour-from-reykjavik | Q93: 94 | R93: 0 | S93: =+Q93*R93 -> 0 | T93: 0.25 | U93: =S93*(1-T93) -> 0 | V93: EUR | W93: =IFERROR(VLOOKUP(V93,Curr!$B$2:$C$13,2,FALSE),0) -> 11 | X93: =U93*W93 -> 0 | Y93: =Q93 -> 94 | Z93: =+Y93*R93 -> 0 | AA93: EUR | AB93: =IFERROR(VLOOKUP(AA93,Curr!$B$2:$C$13,2,FALSE),0) -> 11 | AC93: =+Y93*AB93*R93 -> 0 | AD93: =+AC93-X93 -> 0 | AE93: =IFERROR(AD93/AC93,0) -> 0
B94: IS | D94: Activity | J94: Reykjavík: Whale Watching Tour - Time: 9:00 am - 1:00 pm - Meeting point: Special Tours Office, Geirsgata 11 - Includes: Professional English-speaking guide, warm flotation overalls, heated indoor cabins, toilets and seasickness tablets - Description: Cruise from Reykjavík’s Old Harbour into Faxaflói Bay, searching for whales, dolphins and porpoises with an experienced guide while staying comfortable in warm overalls and heated indoor cabins. | P94: =HYPERLINK("https://booknordics.com/iceland/western-iceland/reykjavik/best-value-whale-watching-tour-from-reykjavik","https://booknordics.com/iceland/western-iceland/reykjavik/best-value-whale-watching-tour-from-reykjavik") -> https://booknordics.com/iceland/western-iceland/reykjavik/best-value-whale-watching-tour-from-reykjavik | Q94: 94 | R94: 0 | S94: =+Q94*R94 -> 0 | T94: 0.25 | U94: =S94*(1-T94) -> 0 | V94: EUR | W94: =IFERROR(VLOOKUP(V94,Curr!$B$2:$C$13,2,FALSE),0) -> 11 | X94: =U94*W94 -> 0 | Y94: =Q94 -> 94 | Z94: =+Y94*R94 -> 0 | AA94: EUR | AB94: =IFERROR(VLOOKUP(AA94,Curr!$B$2:$C$13,2,FALSE),0) -> 11 | AC94: =+Y94*AB94*R94 -> 0 | AD94: =+AC94-X94 -> 0 | AE94: =IFERROR(AD94/AC94,0) -> 0
B95: NO | D95: Activity | J95: Oslo: Essential City Centre Guided Walking Tour - Time: 10:00 am - 12:00 pm - Meeting point: Aula of the University of Oslo, Universitetsplassen, beside the P.A. Munch statue - Includes: Two-hour guided city-centre walk, knowledgeable English-speaking guide - Description: Discover Oslo’s essential landmarks on foot, from the Opera House and Karl Johans gate to the Royal Palace and City Hall, while hearing stories that bring the Norwegian capital to life. | P95: =HYPERLINK("https://booknordics.com/norway/eastern-norway/oslo/essential-oslo-city-center-guided-walking-tour-2","https://booknordics.com/norway/eastern-norway/oslo/essential-oslo-city-center-guided-walking-tour-2") -> https://booknordics.com/norway/eastern-norway/oslo/essential-oslo-city-center-guided-walking-tour-2 | Q95: 29 | R95: 0 | S95: =+Q95*R95 -> 0 | T95: 0.2 | U95: =S95*(1-T95) -> 0 | V95: EUR | W95: =IFERROR(VLOOKUP(V95,Curr!$B$2:$C$13,2,FALSE),0) -> 11 | X95: =U95*W95 -> 0 | Y95: =Q95/0.7 -> 41.428571 | Z95: =+Y95*R95 -> 0 | AA95: EUR | AB95: =IFERROR(VLOOKUP(AA95,Curr!$B$2:$C$13,2,FALSE),0) -> 11 | AC95: =+Y95*AB95*R95 -> 0 | AD95: =+AC95-X95 -> 0 | AE95: =IFERROR(AD95/AC95,0) -> 0
